{
  "type": "Feature",
  "properties": {
    "gn:admin1_code":"3.0",
    "gn:asciiname":"Batela",
    "gn:country_code":"PK",
    "gn:dem":1322,
    "gn:feature_class":"P",
    "gn:feature_code":"PPL",
    "gn:name":"Batela",
    "gn:population":0,
    "gn:timezone":"Asia/Karachi",
    "iso:country":"PK",
    "wof:name":"Batela",
    "wof:placetype":"locality"
},
  "geometry": {"coordinates":[72.8428,34.60589],"type":"Point"}
}