{
  "type": "Feature",
  "properties": {
    "gn:admin1_code":"4.0",
    "gn:asciiname":"Joian de Bhaini",
    "gn:country_code":"PK",
    "gn:dem":147,
    "gn:feature_class":"P",
    "gn:feature_code":"PPL",
    "gn:name":"Joian de Bhaini",
    "gn:population":0,
    "gn:timezone":"Asia/Karachi",
    "iso:country":"PK",
    "wof:name":"Joian de Bhaini",
    "wof:placetype":"locality"
},
  "geometry": {"coordinates":[72.78104,29.99307],"type":"Point"}
}