{
  "type": "Feature",
  "properties": {
    "gn:admin1_code":"3.0",
    "gn:asciiname":"Abdul Khel",
    "gn:country_code":"PK",
    "gn:dem":436,
    "gn:feature_class":"P",
    "gn:feature_code":"PPL",
    "gn:name":"Abdul Khel",
    "gn:population":0,
    "gn:timezone":"Asia/Karachi",
    "iso:country":"PK",
    "name:fas_x_preferred":[
        "\u0639\u0628\u062f\u0648\u0644\u200c\u0627\u0644\u062e\u0644"
    ],
    "name:und_x_variant":[
        "B\u0101nda Kh\u0101n Muhammad",
        "Wanda Kh\u0101n Muhammad"
    ],
    "name:urd_x_preferred":[
        "\u0639\u0628\u062f\u0648\u0644 \u062e\u06cc\u0644"
    ],
    "wof:name":"Abdul Khel",
    "wof:placetype":"locality"
},
  "geometry": {"coordinates":[70.97605,32.31460999999999],"type":"Point"}
}