{
  "type": "Feature",
  "properties": {
    "gn:admin1_code":"2.0",
    "gn:asciiname":"Basti Abdul Karim Khan",
    "gn:country_code":"PK",
    "gn:dem":57,
    "gn:feature_class":"P",
    "gn:feature_code":"PPL",
    "gn:name":"Basti Abdul Karim Khan",
    "gn:population":0,
    "gn:timezone":"Asia/Karachi",
    "iso:country":"PK",
    "wof:name":"Basti Abdul Karim Khan",
    "wof:placetype":"locality"
},
  "geometry": {"coordinates":[68.53825999999999,28.53839],"type":"Point"}
}