{
  "type": "Feature",
  "properties": {
    "gn:admin1_code":"4",
    "gn:asciiname":"Nawan",
    "gn:country_code":"PK",
    "gn:dem":172,
    "gn:feature_class":"P",
    "gn:feature_code":"PPL",
    "gn:name":"Nawan",
    "gn:population":0,
    "gn:timezone":"Asia/Karachi",
    "iso:country":"PK",
    "name:fas_x_preferred":[
        "\u0646\u0648\u0627\u0646"
    ],
    "name:hin_x_preferred":[
        "\u0928\u094c\u0935\u093e\u0901"
    ],
    "name:urd_x_preferred":[
        "\u0646\u0648\u0627\u06ba"
    ],
    "wof:name":"Nawan",
    "wof:placetype":"locality"
},
  "geometry": {"coordinates":[71.19583,31.68056],"type":"Point"}
}