{
  "type": "Feature",
  "properties": {
    "gn:admin1_code":"3.0",
    "gn:asciiname":"Bhagai Banda",
    "gn:country_code":"PK",
    "gn:dem":2324,
    "gn:feature_class":"P",
    "gn:feature_code":"PPL",
    "gn:name":"Bhagai Banda",
    "gn:population":0,
    "gn:timezone":"Asia/Karachi",
    "iso:country":"PK",
    "wof:name":"Bhagai Banda",
    "wof:placetype":"locality"
},
  "geometry": {"coordinates":[73.0163,35.1448],"type":"Point"}
}