{
  "type": "Feature",
  "properties": {
    "gn:admin1_code":"4.0",
    "gn:asciiname":"Babrian",
    "gn:country_code":"PK",
    "gn:dem":252,
    "gn:feature_class":"P",
    "gn:feature_code":"PPL",
    "gn:name":"Babrian",
    "gn:population":0,
    "gn:timezone":"Asia/Karachi",
    "iso:country":"PK",
    "name:und_x_variant":[
        "Babaryan",
        "Babrian"
    ],
    "wof:name":"Babrian",
    "wof:placetype":"locality"
},
  "geometry": {"coordinates":[75.0979,32.17959],"type":"Point"}
}