{
  "type": "Feature",
  "properties": {
    "gn:admin1_code":"5.0",
    "gn:asciiname":"Goth Nasir Khan Mashori",
    "gn:country_code":"PK",
    "gn:dem":44,
    "gn:feature_class":"P",
    "gn:feature_code":"PPL",
    "gn:name":"Goth Nasir Khan Mashori",
    "gn:population":0,
    "gn:timezone":"Asia/Karachi",
    "iso:country":"PK",
    "name:und_x_variant":[
        "Goth N\u0101sir Kh\u0101n Mashari"
    ],
    "wof:name":"Goth Nasir Khan Mashori",
    "wof:placetype":"locality"
},
  "geometry": {"coordinates":[68.43063000000001,26.86091],"type":"Point"}
}