{
  "type": "Feature",
  "properties": {
    "gn:admin1_code":"5.0",
    "gn:asciiname":"Sona Jat",
    "gn:country_code":"PK",
    "gn:dem":7,
    "gn:feature_class":"P",
    "gn:feature_code":"PPL",
    "gn:name":"Sona Jat",
    "gn:population":0,
    "gn:timezone":"Asia/Karachi",
    "iso:country":"PK",
    "name:eng_x_preferred":[
        "Sana Jat"
    ],
    "wof:name":"Sona Jat",
    "wof:placetype":"locality"
},
  "geometry": {"coordinates":[68.30582,24.62068],"type":"Point"}
}