{
  "type": "Feature",
  "properties": {
    "gn:admin1_code":"4",
    "gn:asciiname":"Rampur",
    "gn:country_code":"PK",
    "gn:dem":224,
    "gn:feature_class":"P",
    "gn:feature_code":"PPL",
    "gn:name":"Rampur",
    "gn:population":0,
    "gn:timezone":"Asia/Karachi",
    "iso:country":"PK",
    "wof:name":"Rampur",
    "wof:placetype":"locality"
},
  "geometry": {"coordinates":[73.50239999999999,32.58615],"type":"Point"}
}