{
  "type": "Feature",
  "properties": {
    "gn:admin1_code":"4.0",
    "gn:asciiname":"Nai Abadi",
    "gn:country_code":"PK",
    "gn:dem":166,
    "gn:feature_class":"P",
    "gn:feature_code":"PPL",
    "gn:name":"Nai Abadi",
    "gn:population":0,
    "gn:timezone":"Asia/Karachi",
    "iso:country":"PK",
    "name:eng_x_preferred":[
        "Nai Abadi"
    ],
    "name:snd_x_preferred":[
        "\u0646\u0626\u064a \u0622\u0628\u0627\u062f\u064a"
    ],
    "name:urd_x_preferred":[
        "\u0646\u0626\u06cc \u0622\u0628\u0627\u062f\u06cc"
    ],
    "wof:name":"Nai Abadi",
    "wof:placetype":"locality"
},
  "geometry": {"coordinates":[73.65427,30.15332],"type":"Point"}
}