{
  "type": "Feature",
  "properties": {
    "gn:admin1_code":"2.0",
    "gn:asciiname":"Az Murgha",
    "gn:country_code":"PK",
    "gn:dem":1650,
    "gn:feature_class":"P",
    "gn:feature_code":"PPL",
    "gn:name":"Az Murgha",
    "gn:population":0,
    "gn:timezone":"Asia/Karachi",
    "iso:country":"PK",
    "name:eng_x_preferred":[
        "Az Murgo"
    ],
    "wof:name":"Az Murgha",
    "wof:placetype":"locality"
},
  "geometry": {"coordinates":[67.49224,30.30448],"type":"Point"}
}