{
  "type": "Feature",
  "properties": {
    "gn:admin1_code":"6",
    "gn:asciiname":"Barala",
    "gn:country_code":"PK",
    "gn:dem":429,
    "gn:feature_class":"P",
    "gn:feature_code":"PPL",
    "gn:name":"Barala",
    "gn:population":0,
    "gn:timezone":"Asia/Karachi",
    "iso:country":"PK",
    "name:und_x_variant":[
        "Bar\u0101la"
    ],
    "wof:name":"Barala",
    "wof:placetype":"locality"
},
  "geometry": {"coordinates":[74.3034,32.96804],"type":"Point"}
}