{
  "type": "Feature",
  "properties": {
    "gn:admin1_code":"1.0",
    "gn:asciiname":"Dhok Bago",
    "gn:country_code":"PK",
    "gn:dem":335,
    "gn:feature_class":"P",
    "gn:feature_code":"PPL",
    "gn:name":"Dhok Bago",
    "gn:population":0,
    "gn:timezone":"Asia/Karachi",
    "iso:country":"PK",
    "wof:name":"Dhok Bago",
    "wof:placetype":"locality"
},
  "geometry": {"coordinates":[73.71935999999999,33.11455],"type":"Point"}
}