{
  "type": "Feature",
  "properties": {
    "gn:admin1_code":"4.0",
    "gn:asciiname":"Tahirpura",
    "gn:country_code":"PK",
    "gn:dem":180,
    "gn:feature_class":"P",
    "gn:feature_code":"PPL",
    "gn:name":"Tahirpura",
    "gn:population":0,
    "gn:timezone":"Asia/Karachi",
    "iso:country":"PK",
    "name:und_x_variant":[
        "Tahira Abad"
    ],
    "wof:name":"Tahirpura",
    "wof:placetype":"locality"
},
  "geometry": {"coordinates":[72.97369999999999,31.38451],"type":"Point"}
}