{
  "type": "Feature",
  "properties": {
    "gn:admin1_code":"4.0",
    "gn:asciiname":"Chak Two Hundred Seventy-one",
    "gn:country_code":"PK",
    "gn:dem":160,
    "gn:feature_class":"P",
    "gn:feature_code":"PPL",
    "gn:name":"Chak Two Hundred Seventy-one",
    "gn:population":0,
    "gn:timezone":"Asia/Karachi",
    "iso:country":"PK",
    "name:und_x_variant":[
        "Jhok Ahmad Mangla",
        "Mangl\u012banw\u0101la",
        "Mangli\u0101nw\u0101la"
    ],
    "wof:name":"Chak Two Hundred Seventy-one",
    "wof:placetype":"locality"
},
  "geometry": {"coordinates":[72.63611,30.78331],"type":"Point"}
}