{
  "type": "Feature",
  "properties": {
    "gn:admin1_code":"05",
    "gn:asciiname":"Okrara",
    "gn:country_code":"PK",
    "gn:dem":68,
    "gn:feature_class":"P",
    "gn:feature_code":"PPL",
    "gn:name":"Okrara",
    "gn:population":0,
    "gn:timezone":"Asia/Karachi",
    "iso:country":"PK",
    "name:und_x_variant":[
        "Ukraro",
        "Okrara"
    ],
    "wof:name":"Okrara",
    "wof:placetype":"locality"
},
  "geometry": {"coordinates":[70.21125000000001,25.31153],"type":"Point"}
}