{
  "type": "Feature",
  "properties": {
    "gn:admin1_code":"5.0",
    "gn:asciiname":"Goth Ghazi Khan",
    "gn:country_code":"PK",
    "gn:dem":23,
    "gn:feature_class":"P",
    "gn:feature_code":"PPL",
    "gn:name":"Goth Ghazi Khan",
    "gn:population":0,
    "gn:timezone":"Asia/Karachi",
    "iso:country":"PK",
    "wof:name":"Goth Ghazi Khan",
    "wof:placetype":"locality"
},
  "geometry": {"coordinates":[67.71460999999999,24.83285],"type":"Point"}
}