{
  "type": "Feature",
  "properties": {
    "gn:admin1_code":"3",
    "gn:asciiname":"Manna",
    "gn:country_code":"PK",
    "gn:dem":2349,
    "gn:feature_class":"P",
    "gn:feature_code":"PPL",
    "gn:name":"Manna",
    "gn:population":0,
    "gn:timezone":"Asia/Karachi",
    "iso:country":"PK",
    "wof:name":"Manna",
    "wof:placetype":"locality"
},
  "geometry": {"coordinates":[73.30360999999998,34.70907],"type":"Point"}
}