{
  "type": "Feature",
  "properties": {
    "gn:admin1_code":"6",
    "gn:asciiname":"Daleri",
    "gn:country_code":"PK",
    "gn:dem":684,
    "gn:feature_class":"P",
    "gn:feature_code":"PPL",
    "gn:name":"Daleri",
    "gn:population":0,
    "gn:timezone":"Asia/Karachi",
    "iso:country":"PK",
    "wof:name":"Daleri",
    "wof:placetype":"locality"
},
  "geometry": {"coordinates":[73.96239,33.62325999999999],"type":"Point"}
}