{
  "type": "Feature",
  "properties": {
    "gn:admin1_code":"03",
    "gn:asciiname":"Ziam",
    "gn:country_code":"PK",
    "gn:dem":1488,
    "gn:feature_class":"P",
    "gn:feature_code":"PPL",
    "gn:name":"Ziam",
    "gn:population":0,
    "gn:timezone":"Asia/Karachi",
    "iso:country":"PK",
    "name:eng_x_preferred":[
        "Ziam"
    ],
    "wof:name":"Ziam",
    "wof:placetype":"locality"
},
  "geometry": {"coordinates":[71.92768000000002,34.81771],"type":"Point"}
}