{
  "type": "Feature",
  "properties": {
    "gn:admin1_code":"4.0",
    "gn:asciiname":"Terkrah",
    "gn:country_code":"PK",
    "gn:dem":775,
    "gn:feature_class":"P",
    "gn:feature_code":"PPL",
    "gn:name":"Terkrah",
    "gn:population":0,
    "gn:timezone":"Asia/Karachi",
    "iso:country":"PK",
    "wof:name":"Terkrah",
    "wof:placetype":"locality"
},
  "geometry": {"coordinates":[73.53891,33.78113],"type":"Point"}
}