{
  "type": "Feature",
  "properties": {
    "gn:admin1_code":"4.0",
    "gn:asciiname":"Dheri Nasib",
    "gn:country_code":"PK",
    "gn:dem":663,
    "gn:feature_class":"P",
    "gn:feature_code":"PPL",
    "gn:name":"Dheri Nasib",
    "gn:population":0,
    "gn:timezone":"Asia/Karachi",
    "iso:country":"PK",
    "name:und_x_variant":[
        "Bh\u016bra Nasib"
    ],
    "wof:name":"Dheri Nasib",
    "wof:placetype":"locality"
},
  "geometry": {"coordinates":[73.40154,33.50313],"type":"Point"}
}