{
  "type": "Feature",
  "properties": {
    "gn:admin1_code":"4.0",
    "gn:asciiname":"Chak One Hundred Sixty-one",
    "gn:country_code":"PK",
    "gn:dem":165,
    "gn:feature_class":"P",
    "gn:feature_code":"PPL",
    "gn:name":"Chak One Hundred Sixty-one",
    "gn:population":0,
    "gn:timezone":"Asia/Karachi",
    "iso:country":"PK",
    "name:und_x_variant":[
        "Nal \u0100b\u0101di",
        "Chak One Hundred Sixty-one",
        "Nai \u0100b\u0101di"
    ],
    "wof:name":"Chak One Hundred Sixty-one",
    "wof:placetype":"locality"
},
  "geometry": {"coordinates":[72.68871999999998,31.01899],"type":"Point"}
}