{
  "type": "Feature",
  "properties": {
    "gn:admin1_code":"4",
    "gn:asciiname":"Kund Ahmad Hasan",
    "gn:country_code":"PK",
    "gn:dem":130,
    "gn:feature_class":"P",
    "gn:feature_code":"PPL",
    "gn:name":"Kund Ahmad Hasan",
    "gn:population":0,
    "gn:timezone":"Asia/Karachi",
    "iso:country":"PK",
    "name:und_x_variant":[
        "Kund Ahmad Asar"
    ],
    "wof:name":"Kund Ahmad Hasan",
    "wof:placetype":"locality"
},
  "geometry": {"coordinates":[72.11272,29.59632],"type":"Point"}
}