{
  "type": "Feature",
  "properties": {
    "gn:admin1_code":"4",
    "gn:asciiname":"Dittawala",
    "gn:country_code":"PK",
    "gn:dem":178,
    "gn:feature_class":"P",
    "gn:feature_code":"PPL",
    "gn:name":"Dittawala",
    "gn:population":0,
    "gn:timezone":"Asia/Karachi",
    "iso:country":"PK",
    "wof:name":"Dittawala",
    "wof:placetype":"locality"
},
  "geometry": {"coordinates":[72.96666999999999,31.68472],"type":"Point"}
}