{
  "type": "Feature",
  "properties": {
    "gn:admin1_code":"4.0",
    "gn:asciiname":"Dhasian",
    "gn:country_code":"PK",
    "gn:dem":256,
    "gn:feature_class":"P",
    "gn:feature_code":"PPL",
    "gn:name":"Dhasian",
    "gn:population":0,
    "gn:timezone":"Asia/Karachi",
    "iso:country":"PK",
    "name:und_x_variant":[
        "Dhesi\u0101n"
    ],
    "wof:name":"Dhasian",
    "wof:placetype":"locality"
},
  "geometry": {"coordinates":[74.64015000000001,32.48464],"type":"Point"}
}