{
  "type": "Feature",
  "properties": {
    "gn:admin1_code":"4.0",
    "gn:asciiname":"Membarwali Bhaini",
    "gn:country_code":"PK",
    "gn:dem":169,
    "gn:feature_class":"P",
    "gn:feature_code":"PPL",
    "gn:name":"Membarwali Bhaini",
    "gn:population":0,
    "gn:timezone":"Asia/Karachi",
    "iso:country":"PK",
    "wof:name":"Membarwali Bhaini",
    "wof:placetype":"locality"
},
  "geometry": {"coordinates":[73.46415999999998,30.00614],"type":"Point"}
}