{
  "type": "Feature",
  "properties": {
    "gn:admin1_code":"4.0",
    "gn:asciiname":"Sheru",
    "gn:country_code":"PK",
    "gn:dem":1168,
    "gn:feature_class":"P",
    "gn:feature_code":"PPL",
    "gn:name":"Sheru",
    "gn:population":0,
    "gn:timezone":"Asia/Karachi",
    "iso:country":"PK",
    "wof:name":"Sheru",
    "wof:placetype":"locality"
},
  "geometry": {"coordinates":[70.13426,30.45364],"type":"Point"}
}