{
  "type": "Feature",
  "properties": {
    "gn:admin1_code":"2.0",
    "gn:asciiname":"Drachko",
    "gn:country_code":"PK",
    "gn:dem":60,
    "gn:feature_class":"P",
    "gn:feature_code":"PPL",
    "gn:name":"Drachko",
    "gn:population":0,
    "gn:timezone":"Asia/Karachi",
    "iso:country":"PK",
    "name:und_x_variant":[
        "Darachkoh",
        "Drajko",
        "Krajko",
        "Drachko"
    ],
    "wof:name":"Drachko",
    "wof:placetype":"locality"
},
  "geometry": {"coordinates":[62.38836,25.88088],"type":"Point"}
}