{
  "type": "Feature",
  "properties": {
    "gn:admin1_code":"04",
    "gn:asciiname":"Kotli Ali Ahmad",
    "gn:country_code":"PK",
    "gn:dem":190,
    "gn:feature_class":"P",
    "gn:feature_code":"PPL",
    "gn:name":"Kotli Ali Ahmad",
    "gn:population":0,
    "gn:timezone":"Asia/Karachi",
    "iso:country":"PK",
    "name:und_x_variant":[
        "Kotli"
    ],
    "wof:name":"Kotli Ali Ahmad",
    "wof:placetype":"locality"
},
  "geometry": {"coordinates":[72.72438000000002,32.40863],"type":"Point"}
}