{
  "type": "Feature",
  "properties": {
    "gn:admin1_code":"4.0",
    "gn:asciiname":"Muhallah Manzur Abad",
    "gn:country_code":"PK",
    "gn:dem":114,
    "gn:feature_class":"P",
    "gn:feature_code":"PPL",
    "gn:name":"Muhallah Manzur Abad",
    "gn:population":0,
    "gn:timezone":"Asia/Karachi",
    "iso:country":"PK",
    "name:und_x_variant":[
        "Wish\u0101n D\u0101sw\u0101la",
        "Basti Manz\u016br\u0101b\u0101d"
    ],
    "wof:name":"Muhallah Manzur Abad",
    "wof:placetype":"locality"
},
  "geometry": {"coordinates":[71.32533000000002,29.86292000000001],"type":"Point"}
}