{
  "type": "Feature",
  "properties": {
    "gn:admin1_code":"4.0",
    "gn:asciiname":"Choran",
    "gn:country_code":"PK",
    "gn:dem":207,
    "gn:feature_class":"P",
    "gn:feature_code":"PPL",
    "gn:name":"Choran",
    "gn:population":0,
    "gn:timezone":"Asia/Karachi",
    "iso:country":"PK",
    "name:fas_x_preferred":[
        "\u0686\u0648\u0631\u0627\u0646"
    ],
    "name:und_x_variant":[
        "Churan",
        "Chaur\u0101n",
        "Choran"
    ],
    "name:urd_x_preferred":[
        "\u0686\u0648\u0631\u0627\u0646"
    ],
    "wof:name":"Choran",
    "wof:placetype":"locality"
},
  "geometry": {"coordinates":[72.95288000000002,32.59803],"type":"Point"}
}