{
  "type": "Feature",
  "properties": {
    "gn:admin1_code":"4",
    "gn:asciiname":"Dera Watli",
    "gn:country_code":"PK",
    "gn:dem":290,
    "gn:feature_class":"P",
    "gn:feature_code":"PPL",
    "gn:name":"Dera Watli",
    "gn:population":0,
    "gn:timezone":"Asia/Karachi",
    "iso:country":"PK",
    "wof:name":"Dera Watli",
    "wof:placetype":"locality"
},
  "geometry": {"coordinates":[73.51711999999998,32.86324],"type":"Point"}
}