{
  "type": "Feature",
  "properties": {
    "gn:admin1_code":"4.0",
    "gn:asciiname":"Chhale",
    "gn:country_code":"PK",
    "gn:dem":276,
    "gn:feature_class":"P",
    "gn:feature_code":"PPL",
    "gn:name":"Chhale",
    "gn:population":0,
    "gn:timezone":"Asia/Karachi",
    "iso:country":"PK",
    "name:und_x_variant":[
        "Chhala",
        "Chh\u0101le",
        "Chhale"
    ],
    "wof:name":"Chhale",
    "wof:placetype":"locality"
},
  "geometry": {"coordinates":[75.24261,32.26807],"type":"Point"}
}