{
  "type": "Feature",
  "properties": {
    "gn:admin1_code":"5",
    "gn:asciiname":"Goth Haji Saro Rajar",
    "gn:country_code":"PK",
    "gn:dem":18,
    "gn:feature_class":"P",
    "gn:feature_code":"PPL",
    "gn:name":"Goth Haji Saro Rajar",
    "gn:population":0,
    "gn:timezone":"Asia/Karachi",
    "iso:country":"PK",
    "name:und_x_variant":[
        "S\u0101ro R\u0101jar"
    ],
    "wof:name":"Goth Haji Saro Rajar",
    "wof:placetype":"locality"
},
  "geometry": {"coordinates":[69.12764,25.76345],"type":"Point"}
}