{
  "type": "Feature",
  "properties": {
    "gn:admin1_code":"4.0",
    "gn:asciiname":"Basti Matila",
    "gn:country_code":"PK",
    "gn:dem":101,
    "gn:feature_class":"P",
    "gn:feature_code":"PPL",
    "gn:name":"Basti Matila",
    "gn:population":0,
    "gn:timezone":"Asia/Karachi",
    "iso:country":"PK",
    "name:und_x_variant":[
        "Basti Matla"
    ],
    "wof:name":"Basti Matila",
    "wof:placetype":"locality"
},
  "geometry": {"coordinates":[71.02433000000001,29.22115],"type":"Point"}
}