{
  "type": "Feature",
  "properties": {
    "gn:admin1_code":"1.0",
    "gn:asciiname":"Anir Khel",
    "gn:country_code":"PK",
    "gn:dem":630,
    "gn:feature_class":"P",
    "gn:feature_code":"PPL",
    "gn:name":"Anir Khel",
    "gn:population":0,
    "gn:timezone":"Asia/Karachi",
    "iso:country":"PK",
    "wof:name":"Anir Khel",
    "wof:placetype":"locality"
},
  "geometry": {"coordinates":[70.49091,33.23947],"type":"Point"}
}