{
  "type": "Feature",
  "properties": {
    "gn:admin1_code":"4.0",
    "gn:asciiname":"Banaoti",
    "gn:country_code":"PK",
    "gn:dem":468,
    "gn:feature_class":"P",
    "gn:feature_code":"PPL",
    "gn:name":"Banaoti",
    "gn:population":0,
    "gn:timezone":"Asia/Karachi",
    "iso:country":"PK",
    "wof:name":"Banaoti",
    "wof:placetype":"locality"
},
  "geometry": {"coordinates":[72.93474000000001,33.25722],"type":"Point"}
}