{
  "type": "Feature",
  "properties": {
    "gn:admin1_code":"3.0",
    "gn:asciiname":"Dherai",
    "gn:country_code":"PK",
    "gn:dem":2350,
    "gn:feature_class":"P",
    "gn:feature_code":"PPL",
    "gn:name":"Dherai",
    "gn:population":0,
    "gn:timezone":"Asia/Karachi",
    "iso:country":"PK",
    "wof:name":"Dherai",
    "wof:placetype":"locality"
},
  "geometry": {"coordinates":[73.19651,34.82057],"type":"Point"}
}