{
  "type": "Feature",
  "properties": {
    "gn:admin1_code":"4",
    "gn:asciiname":"Thalwali",
    "gn:country_code":"PK",
    "gn:dem":176,
    "gn:feature_class":"P",
    "gn:feature_code":"PPL",
    "gn:name":"Thalwali",
    "gn:population":0,
    "gn:timezone":"Asia/Karachi",
    "iso:country":"PK",
    "name:eng_x_preferred":[
        "Thalwali Basti"
    ],
    "name:und_x_variant":[
        "Basti Thalmazar",
        "Thalwali"
    ],
    "wof:name":"Thalwali",
    "wof:placetype":"locality"
},
  "geometry": {"coordinates":[70.4645,30.09628],"type":"Point"}
}