{
  "type": "Feature",
  "properties": {
    "gn:admin1_code":"1",
    "gn:asciiname":"Partigai",
    "gn:country_code":"PK",
    "gn:dem":1395,
    "gn:feature_class":"P",
    "gn:feature_code":"PPL",
    "gn:name":"Partigai",
    "gn:population":0,
    "gn:timezone":"Asia/Karachi",
    "iso:country":"PK",
    "wof:name":"Partigai",
    "wof:placetype":"locality"
},
  "geometry": {"coordinates":[69.96679,32.5557],"type":"Point"}
}