{
  "type": "Feature",
  "properties": {
    "gn:admin1_code":"1.0",
    "gn:asciiname":"Okshin",
    "gn:country_code":"PK",
    "gn:dem":1279,
    "gn:feature_class":"P",
    "gn:feature_code":"PPL",
    "gn:name":"Okshin",
    "gn:population":0,
    "gn:timezone":"Asia/Karachi",
    "iso:country":"PK",
    "name:und_x_variant":[
        "Okash\u012bn"
    ],
    "wof:name":"Okshin",
    "wof:placetype":"locality"
},
  "geometry": {"coordinates":[71.461,34.90459],"type":"Point"}
}