{
  "type": "Feature",
  "properties": {
    "gn:admin1_code":"3.0",
    "gn:asciiname":"Barari",
    "gn:country_code":"PK",
    "gn:dem":2088,
    "gn:feature_class":"P",
    "gn:feature_code":"PPL",
    "gn:name":"Barari",
    "gn:population":0,
    "gn:timezone":"Asia/Karachi",
    "iso:country":"PK",
    "wof:name":"Barari",
    "wof:placetype":"locality"
},
  "geometry": {"coordinates":[71.66639000000001,35.74232],"type":"Point"}
}