{
  "type": "Feature",
  "properties": {
    "gn:admin1_code":"5.0",
    "gn:asciiname":"Goth Haji Nur Muhammad",
    "gn:country_code":"PK",
    "gn:dem":15,
    "gn:feature_class":"P",
    "gn:feature_code":"PPL",
    "gn:name":"Goth Haji Nur Muhammad",
    "gn:population":0,
    "gn:timezone":"Asia/Karachi",
    "iso:country":"PK",
    "name:und_x_variant":[
        "Goth H\u0101ji S\u0101hib Kh\u0101n",
        "Goth Haji Nur Muhammad"
    ],
    "wof:name":"Goth Haji Nur Muhammad",
    "wof:placetype":"locality"
},
  "geometry": {"coordinates":[66.74118,24.89748],"type":"Point"}
}