{
  "type": "Feature",
  "properties": {
    "gn:admin1_code":"3",
    "gn:asciiname":"Kol",
    "gn:country_code":"PK",
    "gn:dem":1257,
    "gn:feature_class":"P",
    "gn:feature_code":"PPL",
    "gn:name":"Kol",
    "gn:population":0,
    "gn:timezone":"Asia/Karachi",
    "iso:country":"PK",
    "name:cat_x_preferred":[
        "Kol"
    ],
    "name:ceb_x_preferred":[
        "Kol"
    ],
    "name:fra_x_preferred":[
        "Kol"
    ],
    "name:nld_x_preferred":[
        "Kol"
    ],
    "name:por_x_preferred":[
        "Kol"
    ],
    "name:swe_x_preferred":[
        "Kol"
    ],
    "name:tur_x_preferred":[
        "Kol"
    ],
    "name:und_x_variant":[
        "Qul"
    ],
    "wof:name":"Kol",
    "wof:placetype":"locality"
},
  "geometry": {"coordinates":[72.00745999999999,34.96937],"type":"Point"}
}