{
  "type": "Feature",
  "properties": {
    "gn:admin1_code":"2",
    "gn:asciiname":"Pitaogai Kili",
    "gn:country_code":"PK",
    "gn:dem":1504,
    "gn:feature_class":"P",
    "gn:feature_code":"PPL",
    "gn:name":"Pitaogai Kili",
    "gn:population":0,
    "gn:timezone":"Asia/Karachi",
    "iso:country":"PK",
    "wof:name":"Pitaogai Kili",
    "wof:placetype":"locality"
},
  "geometry": {"coordinates":[68.78916,30.72099],"type":"Point"}
}