{
  "type": "Feature",
  "properties": {
    "gn:admin1_code":"7.0",
    "gn:asciiname":"Khun",
    "gn:country_code":"PK",
    "gn:dem":1475,
    "gn:feature_class":"P",
    "gn:feature_code":"PPL",
    "gn:name":"Khun",
    "gn:population":0,
    "gn:timezone":"Asia/Karachi",
    "iso:country":"PK",
    "wof:name":"Khun",
    "wof:placetype":"locality"
},
  "geometry": {"coordinates":[74.14832,35.46907],"type":"Point"}
}