{
  "type": "Feature",
  "properties": {
    "gn:admin1_code":"4.0",
    "gn:asciiname":"Basti Mehdi Shah",
    "gn:country_code":"PK",
    "gn:dem":84,
    "gn:feature_class":"P",
    "gn:feature_code":"PPL",
    "gn:name":"Basti Mehdi Shah",
    "gn:population":0,
    "gn:timezone":"Asia/Karachi",
    "iso:country":"PK",
    "name:und_x_variant":[
        "Kot Mahdi Sh\u0101h"
    ],
    "wof:name":"Basti Mehdi Shah",
    "wof:placetype":"locality"
},
  "geometry": {"coordinates":[70.23902,28.55225],"type":"Point"}
}