{
  "type": "Feature",
  "properties": {
    "gn:admin1_code":"3",
    "gn:asciiname":"Nur Mong",
    "gn:country_code":"PK",
    "gn:dem":1623,
    "gn:feature_class":"P",
    "gn:feature_code":"PPL",
    "gn:name":"Nur Mong",
    "gn:population":0,
    "gn:timezone":"Asia/Karachi",
    "iso:country":"PK",
    "name:und_x_variant":[
        "Jhutmang"
    ],
    "wof:name":"Nur Mong",
    "wof:placetype":"locality"
},
  "geometry": {"coordinates":[73.35732,34.13479],"type":"Point"}
}