{
  "type": "Feature",
  "properties": {
    "gn:admin1_code":"4",
    "gn:asciiname":"Rauza Nadir Shah",
    "gn:country_code":"PK",
    "gn:dem":159,
    "gn:feature_class":"P",
    "gn:feature_code":"PPL",
    "gn:name":"Rauza Nadir Shah",
    "gn:population":0,
    "gn:timezone":"Asia/Karachi",
    "iso:country":"PK",
    "wof:name":"Rauza Nadir Shah",
    "wof:placetype":"locality"
},
  "geometry": {"coordinates":[72.63582,30.64772],"type":"Point"}
}