{
  "type": "Feature",
  "properties": {
    "gn:admin1_code":"6",
    "gn:asciiname":"Qurashi",
    "gn:country_code":"PK",
    "gn:dem":1689,
    "gn:feature_class":"P",
    "gn:feature_code":"PPL",
    "gn:name":"Qurashi",
    "gn:population":0,
    "gn:timezone":"Asia/Karachi",
    "iso:country":"PK",
    "name:und_x_variant":[
        "Khaur\u0101ji"
    ],
    "wof:name":"Qurashi",
    "wof:placetype":"locality"
},
  "geometry": {"coordinates":[73.92789,34.62362],"type":"Point"}
}