{
  "type": "Feature",
  "properties": {
    "gn:admin1_code":"3",
    "gn:asciiname":"Kuz Meanar",
    "gn:country_code":"PK",
    "gn:dem":1734,
    "gn:feature_class":"P",
    "gn:feature_code":"PPL",
    "gn:name":"Kuz Meanar",
    "gn:population":0,
    "gn:timezone":"Asia/Karachi",
    "iso:country":"PK",
    "name:und_x_variant":[
        "K\u016bz M\u0101ch\u0101r"
    ],
    "wof:name":"Kuz Meanar",
    "wof:placetype":"locality"
},
  "geometry": {"coordinates":[72.63084000000001,34.91122],"type":"Point"}
}