{
  "type": "Feature",
  "properties": {
    "gn:admin1_code":"3.0",
    "gn:asciiname":"Parpuni",
    "gn:country_code":"PK",
    "gn:dem":2637,
    "gn:feature_class":"P",
    "gn:feature_code":"PPL",
    "gn:name":"Parpuni",
    "gn:population":0,
    "gn:timezone":"Asia/Karachi",
    "iso:country":"PK",
    "wof:name":"Parpuni",
    "wof:placetype":"locality"
},
  "geometry": {"coordinates":[71.6771,36.19871],"type":"Point"}
}