{
  "type": "Feature",
  "properties": {
    "gn:admin1_code":"4.0",
    "gn:asciiname":"Dhok Mian Pathan",
    "gn:country_code":"PK",
    "gn:dem":525,
    "gn:feature_class":"P",
    "gn:feature_code":"PPL",
    "gn:name":"Dhok Mian Pathan",
    "gn:population":0,
    "gn:timezone":"Asia/Karachi",
    "iso:country":"PK",
    "wof:name":"Dhok Mian Pathan",
    "wof:placetype":"locality"
},
  "geometry": {"coordinates":[73.14690999999998,33.29940999999999],"type":"Point"}
}