{
  "type": "Feature",
  "properties": {
    "gn:admin1_code":"4",
    "gn:asciiname":"Basti Mahiwal Sauntra",
    "gn:country_code":"PK",
    "gn:dem":101,
    "gn:feature_class":"P",
    "gn:feature_code":"PPL",
    "gn:name":"Basti Mahiwal Sauntra",
    "gn:population":0,
    "gn:timezone":"Asia/Karachi",
    "iso:country":"PK",
    "wof:name":"Basti Mahiwal Sauntra",
    "wof:placetype":"locality"
},
  "geometry": {"coordinates":[70.58608000000002,29.38562],"type":"Point"}
}