{
  "type": "Feature",
  "properties": {
    "gn:admin1_code":"5",
    "gn:asciiname":"Sulaiman Khatian",
    "gn:country_code":"PK",
    "gn:dem":26,
    "gn:feature_class":"P",
    "gn:feature_code":"PPL",
    "gn:name":"Sulaiman Khatian",
    "gn:population":0,
    "gn:timezone":"Asia/Karachi",
    "iso:country":"PK",
    "wof:name":"Sulaiman Khatian",
    "wof:placetype":"locality"
},
  "geometry": {"coordinates":[68.53938000000001,25.47329],"type":"Point"}
}