{
  "type": "Feature",
  "properties": {
    "gn:admin1_code":"5",
    "gn:asciiname":"Ellahi Bakhsh Eri",
    "gn:country_code":"PK",
    "gn:dem":52,
    "gn:feature_class":"P",
    "gn:feature_code":"PPL",
    "gn:name":"Ellahi Bakhsh Eri",
    "gn:population":0,
    "gn:timezone":"Asia/Karachi",
    "iso:country":"PK",
    "name:und_x_variant":[
        "Sulem\u0101n"
    ],
    "wof:name":"Ellahi Bakhsh Eri",
    "wof:placetype":"locality"
},
  "geometry": {"coordinates":[68.13944000000001,28.06479],"type":"Point"}
}