{
  "type": "Feature",
  "properties": {
    "gn:admin1_code":"1.0",
    "gn:asciiname":"Hasan Khel",
    "gn:country_code":"PK",
    "gn:dem":594,
    "gn:feature_class":"P",
    "gn:feature_code":"PPL",
    "gn:name":"Hasan Khel",
    "gn:population":0,
    "gn:timezone":"Asia/Karachi",
    "iso:country":"PK",
    "wof:name":"Hasan Khel",
    "wof:placetype":"locality"
},
  "geometry": {"coordinates":[70.35103000000001,32.93336],"type":"Point"}
}