{
  "type": "Feature",
  "properties": {
    "gn:admin1_code":"4.0",
    "gn:asciiname":"Jalalpur Saiyedan",
    "gn:country_code":"PK",
    "gn:dem":186,
    "gn:feature_class":"P",
    "gn:feature_code":"PPL",
    "gn:name":"Jalalpur Saiyedan",
    "gn:population":0,
    "gn:timezone":"Asia/Karachi",
    "iso:country":"PK",
    "name:und_x_variant":[
        "Jal\u0101lpur"
    ],
    "wof:name":"Jalalpur Saiyedan",
    "wof:placetype":"locality"
},
  "geometry": {"coordinates":[72.2954,32.2186],"type":"Point"}
}