{
  "type": "Feature",
  "properties": {
    "gn:admin1_code":"3.0",
    "gn:asciiname":"Jingeret Kuh",
    "gn:country_code":"PK",
    "gn:dem":2022,
    "gn:feature_class":"P",
    "gn:feature_code":"PPL",
    "gn:name":"Jingeret Kuh",
    "gn:population":0,
    "gn:timezone":"Asia/Karachi",
    "iso:country":"PK",
    "name:eng_x_preferred":[
        "Jingeret Kuh"
    ],
    "name:und_x_variant":[
        "Jingerat Kuh"
    ],
    "wof:name":"Jingeret Kuh",
    "wof:placetype":"locality"
},
  "geometry": {"coordinates":[71.71063000000002,35.57781],"type":"Point"}
}