{
  "type": "Feature",
  "properties": {
    "gn:admin1_code":"04",
    "gn:asciiname":"Ratti Kassi",
    "gn:country_code":"PK",
    "gn:dem":446,
    "gn:feature_class":"P",
    "gn:feature_code":"PPL",
    "gn:name":"Ratti Kassi",
    "gn:population":0,
    "gn:timezone":"Asia/Karachi",
    "iso:country":"PK",
    "wof:name":"Ratti Kassi",
    "wof:placetype":"locality"
},
  "geometry": {"coordinates":[72.37354000000001,33.55699],"type":"Point"}
}