{
  "type": "Feature",
  "properties": {
    "gn:admin1_code":"6",
    "gn:asciiname":"Chaksawari",
    "gn:country_code":"PK",
    "gn:dem":406,
    "gn:feature_class":"P",
    "gn:feature_code":"PPL",
    "gn:name":"Chaksaw\u0101ri",
    "gn:population":0,
    "gn:timezone":"Asia/Karachi",
    "iso:country":"PK",
    "wof:name":"Chaksawari",
    "wof:placetype":"locality"
},
  "geometry": {"coordinates":[73.78412,33.24635],"type":"Point"}
}