{
  "type": "Feature",
  "properties": {
    "gn:admin1_code":"4.0",
    "gn:asciiname":"Chak One Hundred Seventeen Desert Branch Shimali",
    "gn:country_code":"PK",
    "gn:dem":117,
    "gn:feature_class":"P",
    "gn:feature_code":"PPL",
    "gn:name":"Chak One Hundred Seventeen Desert Branch Shimali",
    "gn:population":0,
    "gn:timezone":"Asia/Karachi",
    "iso:country":"PK",
    "name:eng_x_preferred":[
        "Chak One Hundred Seventeen DB Shum\u0101li"
    ],
    "wof:name":"Chak One Hundred Seventeen Desert Branch Shimali",
    "wof:placetype":"locality"
},
  "geometry": {"coordinates":[71.61895,29.09665],"type":"Point"}
}