{
  "type": "Feature",
  "properties": {
    "gn:admin1_code":"3.0",
    "gn:asciiname":"Dab Banda",
    "gn:country_code":"PK",
    "gn:dem":2672,
    "gn:feature_class":"P",
    "gn:feature_code":"PPL",
    "gn:name":"Dab Banda",
    "gn:population":0,
    "gn:timezone":"Asia/Karachi",
    "iso:country":"PK",
    "name:eng_x_preferred":[
        "Dab Banda"
    ],
    "wof:name":"Dab Banda",
    "wof:placetype":"locality"
},
  "geometry": {"coordinates":[72.40661,35.61816],"type":"Point"}
}