{
  "type": "Feature",
  "properties": {
    "gn:admin1_code":"1.0",
    "gn:asciiname":"Karezgai",
    "gn:country_code":"PK",
    "gn:dem":1971,
    "gn:feature_class":"P",
    "gn:feature_code":"PPL",
    "gn:name":"Karezgai",
    "gn:population":0,
    "gn:timezone":"Asia/Karachi",
    "iso:country":"PK",
    "name:und_x_variant":[
        "K\u0101rezgal",
        "Karezgai"
    ],
    "wof:name":"Karezgai",
    "wof:placetype":"locality"
},
  "geometry": {"coordinates":[70.07393,33.93738],"type":"Point"}
}