{
  "type": "Feature",
  "properties": {
    "gn:admin1_code":"04",
    "gn:asciiname":"Rakh Thaung",
    "gn:country_code":"PK",
    "gn:dem":94,
    "gn:feature_class":"P",
    "gn:feature_code":"PPL",
    "gn:name":"Rakh Thaung",
    "gn:population":0,
    "gn:timezone":"Asia/Karachi",
    "iso:country":"PK",
    "name:und_x_variant":[
        "Rakh Taung",
        "Rakh Thoung",
        "Rakh Thaung"
    ],
    "wof:name":"Rakh Thaung",
    "wof:placetype":"locality"
},
  "geometry": {"coordinates":[70.46708000000002,29.03414],"type":"Point"}
}