{
  "type": "Feature",
  "properties": {
    "gn:admin1_code":"6",
    "gn:asciiname":"Tarkanna",
    "gn:country_code":"PK",
    "gn:dem":2979,
    "gn:feature_class":"P",
    "gn:feature_code":"PPL",
    "gn:name":"Tarkanna",
    "gn:population":0,
    "gn:timezone":"Asia/Karachi",
    "iso:country":"PK",
    "name:und_x_variant":[
        "Trakanaz",
        "Trekanna"
    ],
    "wof:name":"Tarkanna",
    "wof:placetype":"locality"
},
  "geometry": {"coordinates":[74.01031999999999,33.96663],"type":"Point"}
}