{
  "type": "Feature",
  "properties": {
    "gn:admin1_code":"4.0",
    "gn:asciiname":"Chak Ninety-six Jhang Branch",
    "gn:country_code":"PK",
    "gn:dem":174,
    "gn:feature_class":"P",
    "gn:feature_code":"PPL",
    "gn:name":"Chak Ninety-six Jhang Branch",
    "gn:population":0,
    "gn:timezone":"Asia/Karachi",
    "iso:country":"PK",
    "name:und_x_variant":[
        "Gil Sibhu",
        "Gil S\u0101hbu",
        "Chak Ninety-six Jhang Branch",
        "Gil S\u0101ju"
    ],
    "wof:name":"Chak Ninety-six Jhang Branch",
    "wof:placetype":"locality"
},
  "geometry": {"coordinates":[72.76648,31.21819],"type":"Point"}
}