{
  "type": "Feature",
  "properties": {
    "gn:admin1_code":"3",
    "gn:asciiname":"Naborai",
    "gn:country_code":"PK",
    "gn:dem":1274,
    "gn:feature_class":"P",
    "gn:feature_code":"PPL",
    "gn:name":"Naborai",
    "gn:population":0,
    "gn:timezone":"Asia/Karachi",
    "iso:country":"PK",
    "wof:name":"Naborai",
    "wof:placetype":"locality"
},
  "geometry": {"coordinates":[72.48472,35.07222],"type":"Point"}
}