{
  "type": "Feature",
  "properties": {
    "gn:admin1_code":"4",
    "gn:asciiname":"Ladhewala Goraya",
    "gn:country_code":"PK",
    "gn:dem":227,
    "gn:feature_class":"P",
    "gn:feature_code":"PPL",
    "gn:name":"Ladhewala Goraya",
    "gn:population":0,
    "gn:timezone":"Asia/Karachi",
    "iso:country":"PK",
    "name:und_x_variant":[
        "Ladhew\u0101la Juraya"
    ],
    "wof:name":"Ladhewala Goraya",
    "wof:placetype":"locality"
},
  "geometry": {"coordinates":[74.30394,32.09961],"type":"Point"}
}