{
  "type": "Feature",
  "properties": {
    "gn:admin1_code":"03",
    "gn:asciiname":"Sark",
    "gn:country_code":"PK",
    "gn:dem":1417,
    "gn:feature_class":"P",
    "gn:feature_code":"PPL",
    "gn:name":"Sark",
    "gn:population":0,
    "gn:timezone":"Asia/Karachi",
    "iso:country":"PK",
    "name:eng_x_preferred":[
        "Sarkai"
    ],
    "wof:name":"Sark",
    "wof:placetype":"locality"
},
  "geometry": {"coordinates":[71.99814000000001,34.95925],"type":"Point"}
}