{
  "type": "Feature",
  "properties": {
    "gn:admin1_code":"2",
    "gn:asciiname":"Markhush Karez",
    "gn:country_code":"PK",
    "gn:dem":2249,
    "gn:feature_class":"P",
    "gn:feature_code":"PPL",
    "gn:name":"Markhush Karez",
    "gn:population":0,
    "gn:timezone":"Asia/Karachi",
    "iso:country":"PK",
    "wof:name":"Markhush Karez",
    "wof:placetype":"locality"
},
  "geometry": {"coordinates":[67.07389999999999,31.08222],"type":"Point"}
}