{
  "type": "Feature",
  "properties": {
    "gn:admin1_code":"04",
    "gn:asciiname":"Chak One Hundred Forty-nine",
    "gn:country_code":"PK",
    "gn:dem":184,
    "gn:feature_class":"P",
    "gn:feature_code":"PPL",
    "gn:name":"Chak One Hundred Forty-nine",
    "gn:population":0,
    "gn:timezone":"Asia/Karachi",
    "iso:country":"PK",
    "name:und_x_variant":[
        "Bholu\u0101na",
        "Chak One Hundred Forty-nine",
        "Mona",
        "Nama"
    ],
    "wof:name":"Chak One Hundred Forty-nine",
    "wof:placetype":"locality"
},
  "geometry": {"coordinates":[72.88706999999999,31.5309],"type":"Point"}
}