{
  "type": "Feature",
  "properties": {
    "gn:admin1_code":"5",
    "gn:asciiname":"Goth Yar Muhammad Marri",
    "gn:country_code":"PK",
    "gn:dem":22,
    "gn:feature_class":"P",
    "gn:feature_code":"PPL",
    "gn:name":"Goth Y\u0101r Muhammad Marri",
    "gn:population":0,
    "gn:timezone":"Asia/Karachi",
    "iso:country":"PK",
    "wof:name":"Goth Yar Muhammad Marri",
    "wof:placetype":"locality"
},
  "geometry": {"coordinates":[68.925,25.67361],"type":"Point"}
}