{
  "type": "Feature",
  "properties": {
    "gn:admin1_code":"4.0",
    "gn:asciiname":"Mihal Mea",
    "gn:country_code":"PK",
    "gn:dem":896,
    "gn:feature_class":"P",
    "gn:feature_code":"PPL",
    "gn:name":"Mihal Mea",
    "gn:population":0,
    "gn:timezone":"Asia/Karachi",
    "iso:country":"PK",
    "name:eng_x_preferred":[
        "Mihal Mea"
    ],
    "wof:name":"Mihal Mea",
    "wof:placetype":"locality"
},
  "geometry": {"coordinates":[70.13181,30.06056],"type":"Point"}
}