{
  "type": "Feature",
  "properties": {
    "gn:admin1_code":"03",
    "gn:asciiname":"Sherbai",
    "gn:country_code":"PK",
    "gn:dem":962,
    "gn:feature_class":"P",
    "gn:feature_code":"PPL",
    "gn:name":"Sherbai",
    "gn:population":0,
    "gn:timezone":"Asia/Karachi",
    "iso:country":"PK",
    "wof:name":"Sherbai",
    "wof:placetype":"locality"
},
  "geometry": {"coordinates":[73.11721999999997,34.23486],"type":"Point"}
}