{
  "type": "Feature",
  "properties": {
    "gn:admin1_code":"5",
    "gn:asciiname":"Goth Nadu Khoso",
    "gn:country_code":"PK",
    "gn:dem":17,
    "gn:feature_class":"P",
    "gn:feature_code":"PPL",
    "gn:name":"Goth Nadu Khoso",
    "gn:population":0,
    "gn:timezone":"Asia/Karachi",
    "iso:country":"PK",
    "name:und_x_variant":[
        "Goth Nanda Khoso"
    ],
    "wof:name":"Goth Nadu Khoso",
    "wof:placetype":"locality"
},
  "geometry": {"coordinates":[68.98843000000001,25.06125],"type":"Point"}
}