{
  "type": "Feature",
  "properties": {
    "gn:admin1_code":"6",
    "gn:asciiname":"Kaniar",
    "gn:country_code":"PK",
    "gn:dem":1367,
    "gn:feature_class":"P",
    "gn:feature_code":"PPL",
    "gn:name":"Kaniar",
    "gn:population":0,
    "gn:timezone":"Asia/Karachi",
    "iso:country":"PK",
    "name:und_x_variant":[
        "Kaniat",
        "Kaniar"
    ],
    "wof:name":"Kaniar",
    "wof:placetype":"locality"
},
  "geometry": {"coordinates":[74.07778,33.56528],"type":"Point"}
}