{
  "type": "Feature",
  "properties": {
    "gn:admin1_code":"2.0",
    "gn:asciiname":"Urmazai",
    "gn:country_code":"PK",
    "gn:dem":2455,
    "gn:feature_class":"P",
    "gn:feature_code":"PPL",
    "gn:name":"Urmazai",
    "gn:population":0,
    "gn:timezone":"Asia/Karachi",
    "iso:country":"PK",
    "name:eng_x_preferred":[
        "Urmazai"
    ],
    "wof:name":"Urmazai",
    "wof:placetype":"locality"
},
  "geometry": {"coordinates":[67.28731999999999,30.95277],"type":"Point"}
}