{
  "type": "Feature",
  "properties": {
    "gn:admin1_code":"5",
    "gn:asciiname":"Goth Haidar Shah",
    "gn:country_code":"PK",
    "gn:dem":28,
    "gn:feature_class":"P",
    "gn:feature_code":"PPL",
    "gn:name":"Goth Haidar Shah",
    "gn:population":0,
    "gn:timezone":"Asia/Karachi",
    "iso:country":"PK",
    "name:und_x_variant":[
        "Haidar Sh\u0101h"
    ],
    "wof:name":"Goth Haidar Shah",
    "wof:placetype":"locality"
},
  "geometry": {"coordinates":[68.50299,25.72621],"type":"Point"}
}