{
  "type": "Feature",
  "properties": {
    "gn:admin1_code":"7.0",
    "gn:asciiname":"Askor Brak",
    "gn:country_code":"PK",
    "gn:dem":2551,
    "gn:feature_class":"P",
    "gn:feature_code":"PPL",
    "gn:name":"Askor Brak",
    "gn:population":0,
    "gn:timezone":"Asia/Karachi",
    "iso:country":"PK",
    "wof:name":"Askor Brak",
    "wof:placetype":"locality"
},
  "geometry": {"coordinates":[75.07726,35.65051],"type":"Point"}
}