{
  "type": "Feature",
  "properties": {
    "gn:admin1_code":"3",
    "gn:asciiname":"Gujar Gali",
    "gn:country_code":"PK",
    "gn:dem":1156,
    "gn:feature_class":"P",
    "gn:feature_code":"PPL",
    "gn:name":"Gujar Gali",
    "gn:population":0,
    "gn:timezone":"Asia/Karachi",
    "iso:country":"PK",
    "name:und_x_variant":[
        "Gujargali"
    ],
    "wof:name":"Gujar Gali",
    "wof:placetype":"locality"
},
  "geometry": {"coordinates":[73.00569,34.30968],"type":"Point"}
}