{
  "type": "Feature",
  "properties": {
    "gn:admin1_code":"4.0",
    "gn:asciiname":"Adhi Kot",
    "gn:country_code":"PK",
    "gn:dem":191,
    "gn:feature_class":"P",
    "gn:feature_code":"PPL",
    "gn:name":"Adhi Kot",
    "gn:population":0,
    "gn:timezone":"Asia/Karachi",
    "iso:country":"PK",
    "name:fas_x_preferred":[
        "\u0627\u062f\u0647\u06cc \u06a9\u0648\u062a"
    ],
    "name:urd_x_preferred":[
        "\u0627\u062f\u06be\u06cc \u06a9\u0648\u0679"
    ],
    "wof:name":"Adhi Kot",
    "wof:placetype":"locality"
},
  "geometry": {"coordinates":[71.80603000000001,32.10543],"type":"Point"}
}