{
  "type": "Feature",
  "properties": {
    "gn:admin1_code":"2.0",
    "gn:asciiname":"Gorangai",
    "gn:country_code":"PK",
    "gn:dem":2588,
    "gn:feature_class":"P",
    "gn:feature_code":"PPL",
    "gn:name":"Gorangai",
    "gn:population":0,
    "gn:timezone":"Asia/Karachi",
    "iso:country":"PK",
    "wof:name":"Gorangai",
    "wof:placetype":"locality"
},
  "geometry": {"coordinates":[66.99129000000001,30.94962],"type":"Point"}
}