{
  "type": "Feature",
  "properties": {
    "gn:admin1_code":"7.0",
    "gn:asciiname":"Karalda",
    "gn:country_code":"PK",
    "gn:dem":2777,
    "gn:feature_class":"P",
    "gn:feature_code":"PPL",
    "gn:name":"Karalda",
    "gn:population":0,
    "gn:timezone":"Asia/Karachi",
    "iso:country":"PK",
    "wof:name":"Karalda",
    "wof:placetype":"locality"
},
  "geometry": {"coordinates":[75.49825,35.3075],"type":"Point"}
}