{
  "type": "Feature",
  "properties": {
    "gn:admin1_code":"4",
    "gn:asciiname":"Jhok Qadirwali",
    "gn:country_code":"PK",
    "gn:dem":168,
    "gn:feature_class":"P",
    "gn:feature_code":"PPL",
    "gn:name":"Jhok Qadirwali",
    "gn:population":0,
    "gn:timezone":"Asia/Karachi",
    "iso:country":"PK",
    "name:und_x_variant":[
        "Jhok Kh\u0101du",
        "Jhok Q\u0101dar",
        "Jhok Qadirwali"
    ],
    "wof:name":"Jhok Qadirwali",
    "wof:placetype":"locality"
},
  "geometry": {"coordinates":[70.98151999999997,31.69317],"type":"Point"}
}