{
  "type": "Feature",
  "properties": {
    "gn:admin1_code":"01",
    "gn:asciiname":"Shingas Banda",
    "gn:country_code":"PK",
    "gn:dem":830,
    "gn:feature_class":"P",
    "gn:feature_code":"PPL",
    "gn:name":"Shingas Banda",
    "gn:population":0,
    "gn:timezone":"Asia/Karachi",
    "iso:country":"PK",
    "name:eng_x_preferred":[
        "Chingas B\u0101nda"
    ],
    "wof:name":"Shingas Banda",
    "wof:placetype":"locality"
},
  "geometry": {"coordinates":[71.60949000000002,34.79145],"type":"Point"}
}