{
  "type": "Feature",
  "properties": {
    "gn:admin1_code":"7.0",
    "gn:asciiname":"Spor Kot",
    "gn:country_code":"PK",
    "gn:dem":3562,
    "gn:feature_class":"P",
    "gn:feature_code":"PPL",
    "gn:name":"Spor Kot",
    "gn:population":0,
    "gn:timezone":"Asia/Karachi",
    "iso:country":"PK",
    "wof:name":"Spor Kot",
    "wof:placetype":"locality"
},
  "geometry": {"coordinates":[74.25135,36.83761],"type":"Point"}
}