{
  "type": "Feature",
  "properties": {
    "gn:admin1_code":"03",
    "gn:asciiname":"Kurd",
    "gn:country_code":"PK",
    "gn:dem":912,
    "gn:feature_class":"P",
    "gn:feature_code":"PPL",
    "gn:name":"Kurd",
    "gn:population":0,
    "gn:timezone":"Asia/Karachi",
    "iso:country":"PK",
    "wof:name":"Kurd",
    "wof:placetype":"locality"
},
  "geometry": {"coordinates":[71.34886,33.01706],"type":"Point"}
}