{
  "type": "Feature",
  "properties": {
    "gn:admin1_code":"4.0",
    "gn:asciiname":"Basti Waswana",
    "gn:country_code":"PK",
    "gn:dem":136,
    "gn:feature_class":"P",
    "gn:feature_code":"PPL",
    "gn:name":"Basti Waswana",
    "gn:population":0,
    "gn:timezone":"Asia/Karachi",
    "iso:country":"PK",
    "name:und_x_variant":[
        "Basti W\u0101sw\u0101s\u0101i"
    ],
    "wof:name":"Basti Waswana",
    "wof:placetype":"locality"
},
  "geometry": {"coordinates":[70.2413,29.53667],"type":"Point"}
}