{
  "type": "Feature",
  "properties": {
    "gn:admin1_code":"1.0",
    "gn:asciiname":"Ghanhal",
    "gn:country_code":"PK",
    "gn:dem":1468,
    "gn:feature_class":"P",
    "gn:feature_code":"PPL",
    "gn:name":"Ghanhal",
    "gn:population":0,
    "gn:timezone":"Asia/Karachi",
    "iso:country":"PK",
    "name:und_x_variant":[
        "Gh\u0101khai"
    ],
    "wof:name":"Ghanhal",
    "wof:placetype":"locality"
},
  "geometry": {"coordinates":[70.90376999999999,33.58463],"type":"Point"}
}