{
  "type": "Feature",
  "properties": {
    "gn:admin1_code":"4.0",
    "gn:asciiname":"Bulhe Shah",
    "gn:country_code":"PK",
    "gn:dem":163,
    "gn:feature_class":"P",
    "gn:feature_code":"PPL",
    "gn:name":"Bulhe Shah",
    "gn:population":0,
    "gn:timezone":"Asia/Karachi",
    "iso:country":"PK",
    "name:und_x_variant":[
        "Bule Shah",
        "Bullhe Sh\u0101h",
        "Bulhe Shah"
    ],
    "wof:name":"Bulhe Shah",
    "wof:placetype":"locality"
},
  "geometry": {"coordinates":[72.81663,30.73503],"type":"Point"}
}