{
  "type": "Feature",
  "properties": {
    "gn:admin1_code":"1.0",
    "gn:asciiname":"Khan Beg Khel Mela",
    "gn:country_code":"PK",
    "gn:dem":821,
    "gn:feature_class":"P",
    "gn:feature_code":"PPL",
    "gn:name":"Khan Beg Khel Mela",
    "gn:population":0,
    "gn:timezone":"Asia/Karachi",
    "iso:country":"PK",
    "name:und_x_variant":[
        "Kh\u0101n Beg Khel",
        "Khan Bi Khelo Mela"
    ],
    "wof:name":"Khan Beg Khel Mela",
    "wof:placetype":"locality"
},
  "geometry": {"coordinates":[71.28568,33.92194],"type":"Point"}
}