{
  "type": "Feature",
  "properties": {
    "gn:admin1_code":"4.0",
    "gn:asciiname":"Chah Inayatwala",
    "gn:country_code":"PK",
    "gn:dem":153,
    "gn:feature_class":"P",
    "gn:feature_code":"PPL",
    "gn:name":"Chah Inayatwala",
    "gn:population":0,
    "gn:timezone":"Asia/Karachi",
    "iso:country":"PK",
    "wof:name":"Chah Inayatwala",
    "wof:placetype":"locality"
},
  "geometry": {"coordinates":[72.33436999999998,31.09957],"type":"Point"}
}