{
  "type": "Feature",
  "properties": {
    "gn:admin1_code":"1.0",
    "gn:asciiname":"Baro Khel",
    "gn:country_code":"PK",
    "gn:dem":653,
    "gn:feature_class":"P",
    "gn:feature_code":"PPL",
    "gn:name":"Baro Khel",
    "gn:population":0,
    "gn:timezone":"Asia/Karachi",
    "iso:country":"PK",
    "name:und_x_variant":[
        "Barru Khel"
    ],
    "wof:name":"Baro Khel",
    "wof:placetype":"locality"
},
  "geometry": {"coordinates":[70.27786999999999,32.93475],"type":"Point"}
}