{
  "type": "Feature",
  "properties": {
    "gn:admin1_code":"4.0",
    "gn:asciiname":"Jam Rahim Bakhsh",
    "gn:country_code":"PK",
    "gn:dem":80,
    "gn:feature_class":"P",
    "gn:feature_code":"PPL",
    "gn:name":"Jam Rahim Bakhsh",
    "gn:population":0,
    "gn:timezone":"Asia/Karachi",
    "iso:country":"PK",
    "name:und_x_variant":[
        "J\u0101m Rahim Bukhsh"
    ],
    "wof:name":"Jam Rahim Bakhsh",
    "wof:placetype":"locality"
},
  "geometry": {"coordinates":[69.80948000000001,28.55201],"type":"Point"}
}