{
  "type": "Feature",
  "properties": {
    "gn:admin1_code":"6.0",
    "gn:asciiname":"Jandi Chauntra",
    "gn:country_code":"PK",
    "gn:dem":632,
    "gn:feature_class":"P",
    "gn:feature_code":"PPL",
    "gn:name":"Jandi Chauntra",
    "gn:population":0,
    "gn:timezone":"Asia/Karachi",
    "iso:country":"PK",
    "wof:name":"Jandi Chauntra",
    "wof:placetype":"locality"
},
  "geometry": {"coordinates":[74.12755,33.05556],"type":"Point"}
}