{
  "type": "Feature",
  "properties": {
    "gn:admin1_code":"4.0",
    "gn:asciiname":"Basti Munshi",
    "gn:country_code":"PK",
    "gn:dem":115,
    "gn:feature_class":"P",
    "gn:feature_code":"PPL",
    "gn:name":"Basti Munshi",
    "gn:population":0,
    "gn:timezone":"Asia/Karachi",
    "iso:country":"PK",
    "name:und_x_variant":[
        "Basti She"
    ],
    "wof:name":"Basti Munshi",
    "wof:placetype":"locality"
},
  "geometry": {"coordinates":[71.51231999999997,29.55141],"type":"Point"}
}