{
  "type": "Feature",
  "properties": {
    "gn:admin1_code":"01",
    "gn:asciiname":"Piazha Band Khel",
    "gn:country_code":"PK",
    "gn:dem":1517,
    "gn:feature_class":"P",
    "gn:feature_code":"PPL",
    "gn:name":"Piazha Band Khel",
    "gn:population":0,
    "gn:timezone":"Asia/Karachi",
    "iso:country":"PK",
    "name:und_x_variant":[
        "P\u012bazha",
        "Pi\u0101zha Kili",
        "Piazha Band Khel"
    ],
    "wof:name":"Piazha Band Khel",
    "wof:placetype":"locality"
},
  "geometry": {"coordinates":[69.93018000000001,32.60128],"type":"Point"}
}