{
  "type": "Feature",
  "properties": {
    "gn:admin1_code":"4",
    "gn:asciiname":"Wahi Bhoja",
    "gn:country_code":"PK",
    "gn:dem":102,
    "gn:feature_class":"P",
    "gn:feature_code":"PPL",
    "gn:name":"Wahi Bhoja",
    "gn:population":0,
    "gn:timezone":"Asia/Karachi",
    "iso:country":"PK",
    "wof:name":"Wahi Bhoja",
    "wof:placetype":"locality"
},
  "geometry": {"coordinates":[71.08027,29.09793],"type":"Point"}
}