{
  "type": "Feature",
  "properties": {
    "gn:admin1_code":"7.0",
    "gn:asciiname":"Azrangbai Basti",
    "gn:country_code":"PK",
    "gn:dem":3415,
    "gn:feature_class":"P",
    "gn:feature_code":"PPL",
    "gn:name":"Azrangbai Basti",
    "gn:population":0,
    "gn:timezone":"Asia/Karachi",
    "iso:country":"PK",
    "wof:name":"Azrangbai Basti",
    "wof:placetype":"locality"
},
  "geometry": {"coordinates":[74.17591999999998,35.14026],"type":"Point"}
}