{
  "type": "Feature",
  "properties": {
    "gn:admin1_code":"4.0",
    "gn:asciiname":"Mopal di Basti",
    "gn:country_code":"PK",
    "gn:dem":108,
    "gn:feature_class":"P",
    "gn:feature_code":"PPL",
    "gn:name":"Mopal di Basti",
    "gn:population":0,
    "gn:timezone":"Asia/Karachi",
    "iso:country":"PK",
    "name:und_x_variant":[
        "Basti H\u0101ji Jhabbil",
        "Basti Moo\u0101l"
    ],
    "wof:name":"Mopal di Basti",
    "wof:placetype":"locality"
},
  "geometry": {"coordinates":[71.21183000000001,29.34905],"type":"Point"}
}