{
  "type": "Feature",
  "properties": {
    "gn:admin1_code":"4.0",
    "gn:asciiname":"Dhalla",
    "gn:country_code":"PK",
    "gn:dem":1268,
    "gn:feature_class":"P",
    "gn:feature_code":"PPL",
    "gn:name":"Dhalla",
    "gn:population":0,
    "gn:timezone":"Asia/Karachi",
    "iso:country":"PK",
    "name:eng_x_preferred":[
        "Dehla"
    ],
    "name:fas_x_preferred":[
        "\u062f\u0647\u0627\u0644\u0647"
    ],
    "name:urd_x_preferred":[
        "\u0688\u06be\u0644\u06c1"
    ],
    "wof:name":"Dhalla",
    "wof:placetype":"locality"
},
  "geometry": {"coordinates":[73.49405,33.97436],"type":"Point"}
}