{
  "type": "Feature",
  "properties": {
    "gn:admin1_code":"3.0",
    "gn:asciiname":"Banda Mausim Khan",
    "gn:country_code":"PK",
    "gn:dem":433,
    "gn:feature_class":"P",
    "gn:feature_code":"PPL",
    "gn:name":"Banda Mausim Khan",
    "gn:population":0,
    "gn:timezone":"Asia/Karachi",
    "iso:country":"PK",
    "name:und_x_variant":[
        "Banda Musam Khan",
        "Banda Mausim Khan"
    ],
    "wof:name":"Banda Mausim Khan",
    "wof:placetype":"locality"
},
  "geometry": {"coordinates":[71.47248,33.47156],"type":"Point"}
}