{
  "type": "Feature",
  "properties": {
    "gn:admin1_code":"2",
    "gn:asciiname":"Azadzai",
    "gn:country_code":"PK",
    "gn:dem":1787,
    "gn:feature_class":"P",
    "gn:feature_code":"PPL",
    "gn:name":"Azadzai",
    "gn:population":0,
    "gn:timezone":"Asia/Karachi",
    "iso:country":"PK",
    "name:und_x_variant":[
        "Az\u0101dzai"
    ],
    "wof:name":"Azadzai",
    "wof:placetype":"locality"
},
  "geometry": {"coordinates":[66.84515999999999,31.19967],"type":"Point"}
}