{
  "type": "Feature",
  "properties": {
    "gn:admin1_code":"4",
    "gn:asciiname":"Bet Saban",
    "gn:country_code":"PK",
    "gn:dem":123,
    "gn:feature_class":"P",
    "gn:feature_code":"PPL",
    "gn:name":"Bet S\u0101ban",
    "gn:population":0,
    "gn:timezone":"Asia/Karachi",
    "iso:country":"PK",
    "name:eng_x_preferred":[
        "Bet S\u0101ban"
    ],
    "wof:name":"Bet Saban",
    "wof:placetype":"locality"
},
  "geometry": {"coordinates":[70.79862,30.29788],"type":"Point"}
}