{
  "type": "Feature",
  "properties": {
    "gn:admin1_code":"4",
    "gn:asciiname":"Chak Seven / Four Right",
    "gn:country_code":"PK",
    "gn:dem":130,
    "gn:feature_class":"P",
    "gn:feature_code":"PPL",
    "gn:name":"Chak Seven / Four Right",
    "gn:population":0,
    "gn:timezone":"Asia/Karachi",
    "iso:country":"PK",
    "name:und_x_variant":[
        "Chak Seven-Four R"
    ],
    "wof:name":"Chak Seven / Four Right",
    "wof:placetype":"locality"
},
  "geometry": {"coordinates":[71.57433,30.56969],"type":"Point"}
}