{
  "type": "Feature",
  "properties": {
    "gn:admin1_code":"4.0",
    "gn:asciiname":"Ghulam Hyder Shah da Banhar",
    "gn:country_code":"PK",
    "gn:dem":186,
    "gn:feature_class":"P",
    "gn:feature_code":"PPL",
    "gn:name":"Ghulam Hyder Shah da Banhar",
    "gn:population":0,
    "gn:timezone":"Asia/Karachi",
    "iso:country":"PK",
    "wof:name":"Ghulam Hyder Shah da Banhar",
    "wof:placetype":"locality"
},
  "geometry": {"coordinates":[71.22988000000002,32.2435],"type":"Point"}
}