{
  "type": "Feature",
  "properties": {
    "gn:admin1_code":"2",
    "gn:asciiname":"Laiq",
    "gn:country_code":"PK",
    "gn:dem":1309,
    "gn:feature_class":"P",
    "gn:feature_code":"PPL",
    "gn:name":"Laiq",
    "gn:population":0,
    "gn:timezone":"Asia/Karachi",
    "iso:country":"PK",
    "wof:name":"Laiq",
    "wof:placetype":"locality"
},
  "geometry": {"coordinates":[68.77651,30.33767000000001],"type":"Point"}
}