{
  "type": "Feature",
  "properties": {
    "gn:admin1_code":"4",
    "gn:asciiname":"Ochhri",
    "gn:country_code":"PK",
    "gn:dem":907,
    "gn:feature_class":"P",
    "gn:feature_code":"PPL",
    "gn:name":"Ochhri",
    "gn:population":0,
    "gn:timezone":"Asia/Karachi",
    "iso:country":"PK",
    "wof:name":"Ochhri",
    "wof:placetype":"locality"
},
  "geometry": {"coordinates":[71.95278,32.49167],"type":"Point"}
}