{
  "type": "Feature",
  "properties": {
    "gn:admin1_code":"3.0",
    "gn:asciiname":"Fatima Khel",
    "gn:country_code":"PK",
    "gn:dem":377,
    "gn:feature_class":"P",
    "gn:feature_code":"PPL",
    "gn:name":"Fatima Khel",
    "gn:population":0,
    "gn:timezone":"Asia/Karachi",
    "iso:country":"PK",
    "wof:name":"Fatima Khel",
    "wof:placetype":"neighbourhood"
},
  "geometry": {"coordinates":[70.61837,32.98852],"type":"Point"}
}