{
  "type": "Feature",
  "properties": {
    "gn:admin1_code":"4.0",
    "gn:asciiname":"Dariwala",
    "gn:country_code":"PK",
    "gn:dem":91,
    "gn:feature_class":"P",
    "gn:feature_code":"PPL",
    "gn:name":"Dariwala",
    "gn:population":0,
    "gn:timezone":"Asia/Karachi",
    "iso:country":"PK",
    "name:und_x_variant":[
        "Dhariw\u0101la"
    ],
    "wof:name":"Dariwala",
    "wof:placetype":"locality"
},
  "geometry": {"coordinates":[70.25603000000001,28.92785],"type":"Point"}
}