{
  "type": "Feature",
  "properties": {
    "gn:admin1_code":"4.0",
    "gn:asciiname":"Ghulain Nabiwala",
    "gn:country_code":"PK",
    "gn:dem":113,
    "gn:feature_class":"P",
    "gn:feature_code":"PPL",
    "gn:name":"Ghulain Nabiwala",
    "gn:population":0,
    "gn:timezone":"Asia/Karachi",
    "iso:country":"PK",
    "wof:name":"Ghulain Nabiwala",
    "wof:placetype":"locality"
},
  "geometry": {"coordinates":[71.11119000000002,29.93559],"type":"Point"}
}