{
  "type": "Feature",
  "properties": {
    "gn:admin1_code":"3",
    "gn:asciiname":"Dheri Baihk",
    "gn:country_code":"PK",
    "gn:dem":3170,
    "gn:feature_class":"P",
    "gn:feature_code":"PPL",
    "gn:name":"Dheri Baihk",
    "gn:population":0,
    "gn:timezone":"Asia/Karachi",
    "iso:country":"PK",
    "name:und_x_variant":[
        "Dheri"
    ],
    "wof:name":"Dheri Baihk",
    "wof:placetype":"locality"
},
  "geometry": {"coordinates":[73.56362,34.89609],"type":"Point"}
}