{
  "type": "Feature",
  "properties": {
    "gn:admin1_code":"2.0",
    "gn:asciiname":"Taj Muhammad",
    "gn:country_code":"PK",
    "gn:dem":1085,
    "gn:feature_class":"P",
    "gn:feature_code":"PPL",
    "gn:name":"Taj Muhammad",
    "gn:population":0,
    "gn:timezone":"Asia/Karachi",
    "iso:country":"PK",
    "wof:name":"Taj Muhammad",
    "wof:placetype":"locality"
},
  "geometry": {"coordinates":[63.71399,29.10355],"type":"Point"}
}