{
  "type": "Feature",
  "properties": {
    "gn:admin1_code":"6",
    "gn:asciiname":"Garh",
    "gn:country_code":"PK",
    "gn:dem":1597,
    "gn:feature_class":"P",
    "gn:feature_code":"PPL",
    "gn:name":"Garh",
    "gn:population":0,
    "gn:timezone":"Asia/Karachi",
    "iso:country":"PK",
    "wof:name":"Garh",
    "wof:placetype":"locality"
},
  "geometry": {"coordinates":[73.53849,34.15215],"type":"Point"}
}