{
  "type": "Feature",
  "properties": {
    "gn:admin1_code":"4.0",
    "gn:asciiname":"Dhok Hazali",
    "gn:country_code":"PK",
    "gn:dem":396,
    "gn:feature_class":"P",
    "gn:feature_code":"PPL",
    "gn:name":"Dhok Hazali",
    "gn:population":0,
    "gn:timezone":"Asia/Karachi",
    "iso:country":"PK",
    "wof:name":"Dhok Hazali",
    "wof:placetype":"locality"
},
  "geometry": {"coordinates":[71.98259,32.91929],"type":"Point"}
}