{
  "type": "Feature",
  "properties": {
    "gn:admin1_code":"5.0",
    "gn:asciiname":"Ishaque Bhonirio",
    "gn:country_code":"PK",
    "gn:dem":8,
    "gn:feature_class":"P",
    "gn:feature_code":"PPL",
    "gn:name":"Ishaque Bhonirio",
    "gn:population":0,
    "gn:timezone":"Asia/Karachi",
    "iso:country":"PK",
    "wof:name":"Ishaque Bhonirio",
    "wof:placetype":"locality"
},
  "geometry": {"coordinates":[69.16955,24.75611],"type":"Point"}
}