{
  "type": "Feature",
  "properties": {
    "gn:admin1_code":"1",
    "gn:asciiname":"Kikarai",
    "gn:country_code":"PK",
    "gn:dem":1983,
    "gn:feature_class":"P",
    "gn:feature_code":"PPL",
    "gn:name":"Kikarai",
    "gn:population":0,
    "gn:timezone":"Asia/Karachi",
    "iso:country":"PK",
    "wof:name":"Kikarai",
    "wof:placetype":"locality"
},
  "geometry": {"coordinates":[69.77287,32.52407],"type":"Point"}
}