{
  "type": "Feature",
  "properties": {
    "gn:admin1_code":"2",
    "gn:asciiname":"Hadira Kach",
    "gn:country_code":"PK",
    "gn:dem":2192,
    "gn:feature_class":"P",
    "gn:feature_code":"PPL",
    "gn:name":"Hadira Kach",
    "gn:population":0,
    "gn:timezone":"Asia/Karachi",
    "iso:country":"PK",
    "wof:name":"Hadira Kach",
    "wof:placetype":"locality"
},
  "geometry": {"coordinates":[66.7859,31.02965],"type":"Point"}
}