{
  "type": "Feature",
  "properties": {
    "gn:admin1_code":"2.0",
    "gn:asciiname":"Chur Masezai",
    "gn:country_code":"PK",
    "gn:dem":1491,
    "gn:feature_class":"P",
    "gn:feature_code":"PPL",
    "gn:name":"Chur Masezai",
    "gn:population":0,
    "gn:timezone":"Asia/Karachi",
    "iso:country":"PK",
    "wof:name":"Chur Masezai",
    "wof:placetype":"locality"
},
  "geometry": {"coordinates":[66.727,30.68463],"type":"Point"}
}