{
  "type": "Feature",
  "properties": {
    "gn:admin1_code":"1.0",
    "gn:asciiname":"Laman",
    "gn:country_code":"PK",
    "gn:dem":1971,
    "gn:feature_class":"P",
    "gn:feature_code":"PPL",
    "gn:name":"Laman",
    "gn:population":0,
    "gn:timezone":"Asia/Karachi",
    "iso:country":"PK",
    "wof:name":"Laman",
    "wof:placetype":"locality"
},
  "geometry": {"coordinates":[69.52070000000001,32.94483],"type":"Point"}
}