{
  "type": "Feature",
  "properties": {
    "gn:admin1_code":"4",
    "gn:asciiname":"Barewala",
    "gn:country_code":"PK",
    "gn:dem":136,
    "gn:feature_class":"P",
    "gn:feature_code":"PPL",
    "gn:name":"B\u0101rew\u0101la",
    "gn:population":0,
    "gn:timezone":"Asia/Karachi",
    "iso:country":"PK",
    "wof:name":"Barewala",
    "wof:placetype":"locality"
},
  "geometry": {"coordinates":[71.45278,30.63194],"type":"Point"}
}