{
  "type": "Feature",
  "properties": {
    "gn:admin1_code":"3.0",
    "gn:asciiname":"Bara Charai",
    "gn:country_code":"PK",
    "gn:dem":2665,
    "gn:feature_class":"P",
    "gn:feature_code":"PPL",
    "gn:name":"Bara Charai",
    "gn:population":0,
    "gn:timezone":"Asia/Karachi",
    "iso:country":"PK",
    "wof:name":"Bara Charai",
    "wof:placetype":"locality"
},
  "geometry": {"coordinates":[72.65969,35.05104],"type":"Point"}
}