{
  "type": "Feature",
  "properties": {
    "gn:admin1_code":"4.0",
    "gn:asciiname":"Mad Bakhsh",
    "gn:country_code":"PK",
    "gn:dem":83,
    "gn:feature_class":"P",
    "gn:feature_code":"PPL",
    "gn:name":"Mad Bakhsh",
    "gn:population":0,
    "gn:timezone":"Asia/Karachi",
    "iso:country":"PK",
    "name:und_x_variant":[
        "Mad Bakhsh\u0101n"
    ],
    "wof:name":"Mad Bakhsh",
    "wof:placetype":"locality"
},
  "geometry": {"coordinates":[70.41283,28.4322],"type":"Point"}
}