{
  "type": "Feature",
  "properties": {
    "gn:admin1_code":"4",
    "gn:asciiname":"Chak B",
    "gn:country_code":"PK",
    "gn:dem":211,
    "gn:feature_class":"P",
    "gn:feature_code":"PPL",
    "gn:name":"Chak B",
    "gn:population":0,
    "gn:timezone":"Asia/Karachi",
    "iso:country":"PK",
    "name:und_x_variant":[
        "Chak B Y\u016bnus\u0101b\u0101d",
        "Y\u016bnus\u0101b\u0101d",
        "Chak B",
        "Younsab\u0101d"
    ],
    "wof:name":"Chak B",
    "wof:placetype":"locality"
},
  "geometry": {"coordinates":[73.24095,32.52952],"type":"Point"}
}