{
  "type": "Feature",
  "properties": {
    "gn:admin1_code":"4",
    "gn:asciiname":"Nawanpur",
    "gn:country_code":"PK",
    "gn:dem":252,
    "gn:feature_class":"P",
    "gn:feature_code":"PPL",
    "gn:name":"Nawanpur",
    "gn:population":0,
    "gn:timezone":"Asia/Karachi",
    "iso:country":"PK",
    "name:und_x_variant":[
        "Seri Yan",
        "Naw\u0101npur"
    ],
    "wof:name":"Nawanpur",
    "wof:placetype":"locality"
},
  "geometry": {"coordinates":[74.56952,32.54246],"type":"Point"}
}