{
  "type": "Feature",
  "properties": {
    "gn:admin1_code":"04",
    "gn:asciiname":"Chak Fifty-six -Four Right",
    "gn:country_code":"PK",
    "gn:dem":179,
    "gn:feature_class":"P",
    "gn:feature_code":"PPL",
    "gn:name":"Chak Fifty-six -Four Right",
    "gn:population":0,
    "gn:timezone":"Asia/Karachi",
    "iso:country":"PK",
    "name:und_x_variant":[
        "Kul\u0101njw\u0101la",
        "Qulanjw\u0101la"
    ],
    "wof:name":"Chak Fifty-six -Four Right",
    "wof:placetype":"locality"
},
  "geometry": {"coordinates":[73.28138,30.78654],"type":"Point"}
}