{
  "type": "Feature",
  "properties": {
    "gn:admin1_code":"5.0",
    "gn:asciiname":"Bhu",
    "gn:country_code":"PK",
    "gn:dem":26,
    "gn:feature_class":"P",
    "gn:feature_code":"PPL",
    "gn:name":"Bhu",
    "gn:population":0,
    "gn:timezone":"Asia/Karachi",
    "iso:country":"PK",
    "wof:name":"Bhu",
    "wof:placetype":"locality"
},
  "geometry": {"coordinates":[69.93791,24.48576],"type":"Point"}
}