{
  "type": "Feature",
  "properties": {
    "gn:admin1_code":"4",
    "gn:asciiname":"Umarwala",
    "gn:country_code":"PK",
    "gn:dem":172,
    "gn:feature_class":"P",
    "gn:feature_code":"PPL",
    "gn:name":"Umarwala",
    "gn:population":0,
    "gn:timezone":"Asia/Karachi",
    "iso:country":"PK",
    "wof:name":"Umarwala",
    "wof:placetype":"locality"
},
  "geometry": {"coordinates":[71.18940000000001,31.67905],"type":"Point"}
}