{
  "type": "Feature",
  "properties": {
    "gn:admin1_code":"1",
    "gn:asciiname":"Sherash Pal",
    "gn:country_code":"PK",
    "gn:dem":1190,
    "gn:feature_class":"P",
    "gn:feature_code":"PPL",
    "gn:name":"Sherash Pal",
    "gn:population":0,
    "gn:timezone":"Asia/Karachi",
    "iso:country":"PK",
    "wof:name":"Sherash Pal",
    "wof:placetype":"locality"
},
  "geometry": {"coordinates":[69.96193000000001,32.43071],"type":"Point"}
}