{
  "type": "Feature",
  "properties": {
    "gn:admin1_code":"5",
    "gn:asciiname":"Goth Ali Khan",
    "gn:country_code":"PK",
    "gn:dem":53,
    "gn:feature_class":"P",
    "gn:feature_code":"PPL",
    "gn:name":"Goth Ali Khan",
    "gn:population":0,
    "gn:timezone":"Asia/Karachi",
    "iso:country":"PK",
    "name:und_x_variant":[
        "Gath Ali Nawaz"
    ],
    "wof:name":"Goth Ali Khan",
    "wof:placetype":"locality"
},
  "geometry": {"coordinates":[68.50374000000001,26.96328],"type":"Point"}
}