{
  "type": "Feature",
  "properties": {
    "gn:admin1_code":"2.0",
    "gn:asciiname":"Zargan Ka Jovandan",
    "gn:country_code":"PK",
    "gn:dem":1577,
    "gn:feature_class":"P",
    "gn:feature_code":"PPL",
    "gn:name":"Zargan Ka Jovandan",
    "gn:population":0,
    "gn:timezone":"Asia/Karachi",
    "iso:country":"PK",
    "wof:name":"Zargan Ka Jovandan",
    "wof:placetype":"locality"
},
  "geometry": {"coordinates":[64.96680000000001,27.52987000000001],"type":"Point"}
}