{
  "type": "Feature",
  "properties": {
    "gn:admin1_code":"3.0",
    "gn:asciiname":"Satura",
    "gn:country_code":"PK",
    "gn:dem":1115,
    "gn:feature_class":"P",
    "gn:feature_code":"PPL",
    "gn:name":"Satura",
    "gn:population":0,
    "gn:timezone":"Asia/Karachi",
    "iso:country":"PK",
    "name:eng_x_preferred":[
        "Sataura"
    ],
    "wof:name":"Satura",
    "wof:placetype":"locality"
},
  "geometry": {"coordinates":[73.24305,33.9567],"type":"Point"}
}