{
  "type": "Feature",
  "properties": {
    "gn:admin1_code":"2.0",
    "gn:asciiname":"Tasppari",
    "gn:country_code":"PK",
    "gn:dem":2149,
    "gn:feature_class":"P",
    "gn:feature_code":"PPL",
    "gn:name":"Tasppari",
    "gn:population":0,
    "gn:timezone":"Asia/Karachi",
    "iso:country":"PK",
    "wof:name":"Tasppari",
    "wof:placetype":"locality"
},
  "geometry": {"coordinates":[68.08795000000001,30.3947],"type":"Point"}
}