{
  "type": "Feature",
  "properties": {
    "gn:admin1_code":"3.0",
    "gn:asciiname":"Khwaja Khizar",
    "gn:country_code":"PK",
    "gn:dem":703,
    "gn:feature_class":"P",
    "gn:feature_code":"PPL",
    "gn:name":"Khwaja Khizar",
    "gn:population":0,
    "gn:timezone":"Asia/Karachi",
    "iso:country":"PK",
    "wof:name":"Khwaja Khizar",
    "wof:placetype":"locality"
},
  "geometry": {"coordinates":[71.21341,33.58332],"type":"Point"}
}