{
  "type": "Feature",
  "properties": {
    "gn:admin1_code":"5.0",
    "gn:asciiname":"Chazi Khan Bagrani",
    "gn:country_code":"PK",
    "gn:dem":16,
    "gn:feature_class":"P",
    "gn:feature_code":"PPL",
    "gn:name":"Chazi Khan Bagrani",
    "gn:population":0,
    "gn:timezone":"Asia/Karachi",
    "iso:country":"PK",
    "wof:name":"Chazi Khan Bagrani",
    "wof:placetype":"locality"
},
  "geometry": {"coordinates":[68.56484,24.9381],"type":"Point"}
}