{
  "type": "Feature",
  "properties": {
    "gn:admin1_code":"2.0",
    "gn:asciiname":"Akhmadkhan",
    "gn:country_code":"PK",
    "gn:dem":2049,
    "gn:feature_class":"P",
    "gn:feature_code":"PPL",
    "gn:name":"Akhmadkhan",
    "gn:population":0,
    "gn:timezone":"Asia/Karachi",
    "iso:country":"PK",
    "wof:name":"Akhmadkhan",
    "wof:placetype":"locality"
},
  "geometry": {"coordinates":[67.88472,31.62833],"type":"Point"}
}