{
  "type": "Feature",
  "properties": {
    "gn:admin1_code":"3.0",
    "gn:asciiname":"Mandgan",
    "gn:country_code":"PK",
    "gn:dem":524,
    "gn:feature_class":"P",
    "gn:feature_code":"PPL",
    "gn:name":"Mandgan",
    "gn:population":0,
    "gn:timezone":"Asia/Karachi",
    "iso:country":"PK",
    "wof:name":"Mandgan",
    "wof:placetype":"locality"
},
  "geometry": {"coordinates":[72.80471,34.68122],"type":"Point"}
}