{
  "type": "Feature",
  "properties": {
    "gn:admin1_code":"05",
    "gn:asciiname":"Goth Ahmad Khan Khaskheli",
    "gn:country_code":"PK",
    "gn:dem":4,
    "gn:feature_class":"P",
    "gn:feature_code":"PPL",
    "gn:name":"Goth Ahmad Khan Khaskheli",
    "gn:population":0,
    "gn:timezone":"Asia/Karachi",
    "iso:country":"PK",
    "name:und_x_variant":[
        "Goth Ahmad Kh\u0101n Kh\u0101shkheli"
    ],
    "wof:name":"Goth Ahmad Khan Khaskheli",
    "wof:placetype":"locality"
},
  "geometry": {"coordinates":[67.58863000000001,24.47635],"type":"Point"}
}