{
  "type": "Feature",
  "properties": {
    "gn:admin1_code":"2.0",
    "gn:asciiname":"Mozas-i-bund",
    "gn:country_code":"PK",
    "gn:dem":57,
    "gn:feature_class":"P",
    "gn:feature_code":"PPL",
    "gn:name":"Mozas-i-bund",
    "gn:population":0,
    "gn:timezone":"Asia/Karachi",
    "iso:country":"PK",
    "wof:name":"Mozas-i-bund",
    "wof:placetype":"locality"
},
  "geometry": {"coordinates":[62.49092,25.88834],"type":"Point"}
}