{
  "type": "Feature",
  "properties": {
    "gn:admin1_code":"05",
    "gn:asciiname":"Goth Kamal",
    "gn:country_code":"PK",
    "gn:dem":349,
    "gn:feature_class":"P",
    "gn:feature_code":"PPL",
    "gn:name":"Goth Kamal",
    "gn:population":0,
    "gn:timezone":"Asia/Karachi",
    "iso:country":"PK",
    "wof:name":"Goth Kamal",
    "wof:placetype":"locality"
},
  "geometry": {"coordinates":[67.46186999999999,25.4614],"type":"Point"}
}