{
  "type": "Feature",
  "properties": {
    "gn:admin1_code":"3",
    "gn:asciiname":"Sawai",
    "gn:country_code":"PK",
    "gn:dem":1070,
    "gn:feature_class":"P",
    "gn:feature_code":"PPL",
    "gn:name":"Sawai",
    "gn:population":0,
    "gn:timezone":"Asia/Karachi",
    "iso:country":"PK",
    "name:deu_x_preferred":[
        "Sawai"
    ],
    "wof:name":"Sawai",
    "wof:placetype":"locality"
},
  "geometry": {"coordinates":[72.77403000000002,34.28870999999999],"type":"Point"}
}