{
  "type": "Feature",
  "properties": {
    "gn:admin1_code":"4",
    "gn:asciiname":"Dhok Mehr Ali",
    "gn:country_code":"PK",
    "gn:dem":517,
    "gn:feature_class":"P",
    "gn:feature_code":"PPL",
    "gn:name":"Dhok Mehr Ali",
    "gn:population":0,
    "gn:timezone":"Asia/Karachi",
    "iso:country":"PK",
    "name:und_x_variant":[
        "Dhok Husang"
    ],
    "wof:name":"Dhok Mehr Ali",
    "wof:placetype":"locality"
},
  "geometry": {"coordinates":[73.20853000000002,33.14727],"type":"Point"}
}