{
  "type": "Feature",
  "properties": {
    "gn:admin1_code":"4",
    "gn:asciiname":"Toungarh",
    "gn:country_code":"PK",
    "gn:dem":259,
    "gn:feature_class":"P",
    "gn:feature_code":"PPL",
    "gn:name":"Toungarh",
    "gn:population":0,
    "gn:timezone":"Asia/Karachi",
    "iso:country":"PK",
    "name:und_x_variant":[
        "Taungarh"
    ],
    "wof:name":"Toungarh",
    "wof:placetype":"locality"
},
  "geometry": {"coordinates":[74.66542,32.49791],"type":"Point"}
}