{
  "type": "Feature",
  "properties": {
    "gn:admin1_code":"4.0",
    "gn:asciiname":"Dar Mallanwala",
    "gn:country_code":"PK",
    "gn:dem":259,
    "gn:feature_class":"P",
    "gn:feature_code":"PPL",
    "gn:name":"Dar Mallanwala",
    "gn:population":0,
    "gn:timezone":"Asia/Karachi",
    "iso:country":"PK",
    "wof:name":"Dar Mallanwala",
    "wof:placetype":"locality"
},
  "geometry": {"coordinates":[71.72265,32.61657],"type":"Point"}
}