{
  "type": "Feature",
  "properties": {
    "gn:admin1_code":"3",
    "gn:asciiname":"Pani",
    "gn:country_code":"PK",
    "gn:dem":1215,
    "gn:feature_class":"P",
    "gn:feature_code":"PPL",
    "gn:name":"Pani",
    "gn:population":0,
    "gn:timezone":"Asia/Karachi",
    "iso:country":"PK",
    "name:und_x_variant":[
        "Bani"
    ],
    "wof:name":"Pani",
    "wof:placetype":"locality"
},
  "geometry": {"coordinates":[73.36995999999998,34.38081],"type":"Point"}
}