{
  "type": "Feature",
  "properties": {
    "gn:admin1_code":"2.0",
    "gn:asciiname":"Jalaugil",
    "gn:country_code":"PK",
    "gn:dem":1524,
    "gn:feature_class":"P",
    "gn:feature_code":"PPL",
    "gn:name":"Jalaugil",
    "gn:population":0,
    "gn:timezone":"Asia/Karachi",
    "iso:country":"PK",
    "wof:name":"Jalaugil",
    "wof:placetype":"locality"
},
  "geometry": {"coordinates":[66.93279,30.42271],"type":"Point"}
}