{
  "type": "Feature",
  "properties": {
    "gn:admin1_code":"4",
    "gn:asciiname":"Kheranwala",
    "gn:country_code":"PK",
    "gn:dem":122,
    "gn:feature_class":"P",
    "gn:feature_code":"PPL",
    "gn:name":"Kheranwala",
    "gn:population":0,
    "gn:timezone":"Asia/Karachi",
    "iso:country":"PK",
    "name:und_x_variant":[
        "Kharew\u0101la"
    ],
    "wof:name":"Kheranwala",
    "wof:placetype":"locality"
},
  "geometry": {"coordinates":[71.84174,29.68768],"type":"Point"}
}