{
  "type": "Feature",
  "properties": {
    "gn:admin1_code":"6",
    "gn:asciiname":"Kelan",
    "gn:country_code":"PK",
    "gn:dem":1177,
    "gn:feature_class":"P",
    "gn:feature_code":"PPL",
    "gn:name":"Kelan",
    "gn:population":0,
    "gn:timezone":"Asia/Karachi",
    "iso:country":"PK",
    "name:und_x_variant":[
        "Kailan"
    ],
    "wof:name":"Kelan",
    "wof:placetype":"locality"
},
  "geometry": {"coordinates":[73.77153,34.16173],"type":"Point"}
}