{
  "type": "Feature",
  "properties": {
    "gn:admin1_code":"2.0",
    "gn:asciiname":"Kazha",
    "gn:country_code":"PK",
    "gn:dem":1871,
    "gn:feature_class":"P",
    "gn:feature_code":"PPL",
    "gn:name":"Kazha",
    "gn:population":0,
    "gn:timezone":"Asia/Karachi",
    "iso:country":"PK",
    "name:jpn_x_preferred":[
        "Kazha"
    ],
    "wof:name":"Kazha",
    "wof:placetype":"locality"
},
  "geometry": {"coordinates":[69.95997,31.02727],"type":"Point"}
}