{
  "type": "Feature",
  "properties": {
    "gn:admin1_code":"5",
    "gn:asciiname":"Allah Wasayo Khan Shar",
    "gn:country_code":"PK",
    "gn:dem":17,
    "gn:feature_class":"P",
    "gn:feature_code":"PPL",
    "gn:name":"Allah Wasayo Khan Shar",
    "gn:population":0,
    "gn:timezone":"Asia/Karachi",
    "iso:country":"PK",
    "name:und_x_variant":[
        "Goth M\u012br Sh\u0101h Naw\u0101z L\u0101ndi",
        "Goth Allah Was\u0101yo Kh\u0101n Shar Baloch"
    ],
    "wof:name":"Allah Wasayo Khan Shar",
    "wof:placetype":"locality"
},
  "geometry": {"coordinates":[69.20411999999999,25.41162000000001],"type":"Point"}
}