{
  "type": "Feature",
  "properties": {
    "gn:admin1_code":"4",
    "gn:asciiname":"Dhok Marh",
    "gn:country_code":"PK",
    "gn:dem":278,
    "gn:feature_class":"P",
    "gn:feature_code":"PPL",
    "gn:name":"Dhok Marh",
    "gn:population":0,
    "gn:timezone":"Asia/Karachi",
    "iso:country":"PK",
    "name:und_x_variant":[
        "Marh"
    ],
    "wof:name":"Dhok Marh",
    "wof:placetype":"locality"
},
  "geometry": {"coordinates":[73.44665999999999,32.95539],"type":"Point"}
}