{
  "type": "Feature",
  "properties": {
    "gn:admin1_code":"1.0",
    "gn:asciiname":"Zaibogai",
    "gn:country_code":"PK",
    "gn:dem":2465,
    "gn:feature_class":"P",
    "gn:feature_code":"PPL",
    "gn:name":"Zaibogai",
    "gn:population":0,
    "gn:timezone":"Asia/Karachi",
    "iso:country":"PK",
    "name:und_x_variant":[
        "Zabo Gai"
    ],
    "wof:name":"Zaibogai",
    "wof:placetype":"locality"
},
  "geometry": {"coordinates":[69.59747,33.07752],"type":"Point"}
}