{
  "type": "Feature",
  "properties": {
    "gn:admin1_code":"1.0",
    "gn:asciiname":"Shina Kaza",
    "gn:country_code":"PK",
    "gn:dem":1038,
    "gn:feature_class":"P",
    "gn:feature_code":"PPL",
    "gn:name":"Shina Kaza",
    "gn:population":0,
    "gn:timezone":"Asia/Karachi",
    "iso:country":"PK",
    "wof:name":"Shina Kaza",
    "wof:placetype":"locality"
},
  "geometry": {"coordinates":[70.04864000000001,31.53361],"type":"Point"}
}