{
  "type": "Feature",
  "properties": {
    "gn:admin1_code":"4",
    "gn:asciiname":"Chunianwala",
    "gn:country_code":"PK",
    "gn:dem":112,
    "gn:feature_class":"P",
    "gn:feature_code":"PPL",
    "gn:name":"Chunianwala",
    "gn:population":0,
    "gn:timezone":"Asia/Karachi",
    "iso:country":"PK",
    "name:und_x_variant":[
        "Ch\u016bnew\u0101li"
    ],
    "wof:name":"Chunianwala",
    "wof:placetype":"locality"
},
  "geometry": {"coordinates":[71.50078000000001,29.58454],"type":"Point"}
}