{
  "type": "Feature",
  "properties": {
    "gn:admin1_code":"4",
    "gn:asciiname":"Panja Sharif",
    "gn:country_code":"PK",
    "gn:dem":190,
    "gn:feature_class":"P",
    "gn:feature_code":"PPL",
    "gn:name":"Panja Sharif",
    "gn:population":0,
    "gn:timezone":"Asia/Karachi",
    "iso:country":"PK",
    "name:und_x_variant":[
        "Panja"
    ],
    "wof:name":"Panja Sharif",
    "wof:placetype":"locality"
},
  "geometry": {"coordinates":[72.05632,32.22809],"type":"Point"}
}