{
  "type": "Feature",
  "properties": {
    "gn:admin1_code":"6",
    "gn:asciiname":"Battal",
    "gn:country_code":"PK",
    "gn:dem":788,
    "gn:feature_class":"P",
    "gn:feature_code":"PPL",
    "gn:name":"Battal",
    "gn:population":0,
    "gn:timezone":"Asia/Karachi",
    "iso:country":"PK",
    "name:fas_x_preferred":[
        "\u0628\u062a\u0644"
    ],
    "name:urd_x_preferred":[
        "\u0628\u0679\u0644"
    ],
    "wof:name":"Battal",
    "wof:placetype":"locality"
},
  "geometry": {"coordinates":[73.97306999999998,33.68819000000001],"type":"Point"}
}