{
  "type": "Feature",
  "properties": {
    "gn:admin1_code":"4.0",
    "gn:asciiname":"Chak Two Hundred Sixty-nine",
    "gn:country_code":"PK",
    "gn:dem":159,
    "gn:feature_class":"P",
    "gn:feature_code":"PPL",
    "gn:name":"Chak Two Hundred Sixty-nine",
    "gn:population":0,
    "gn:timezone":"Asia/Karachi",
    "iso:country":"PK",
    "name:und_x_variant":[
        "Jhok Khatran",
        "Jhok Khetr\u0101n",
        "Chak Two Hundred Sixty-nine",
        "Kat Khutran",
        "Kot Khetr\u0101n"
    ],
    "wof:name":"Chak Two Hundred Sixty-nine",
    "wof:placetype":"locality"
},
  "geometry": {"coordinates":[72.59424,30.77652],"type":"Point"}
}