{
  "type": "Feature",
  "properties": {
    "gn:admin1_code":"2.0",
    "gn:asciiname":"Gwal Idarzai",
    "gn:country_code":"PK",
    "gn:dem":1495,
    "gn:feature_class":"P",
    "gn:feature_code":"PPL",
    "gn:name":"Gwal Idarzai",
    "gn:population":0,
    "gn:timezone":"Asia/Karachi",
    "iso:country":"PK",
    "name:und_x_variant":[
        "Gw\u0101l Haidarzai"
    ],
    "wof:name":"Gwal Idarzai",
    "wof:placetype":"locality"
},
  "geometry": {"coordinates":[68.79765999999999,30.72806],"type":"Point"}
}