{
  "type": "Feature",
  "properties": {
    "gn:admin1_code":"6",
    "gn:asciiname":"Pujwalianwaladanna",
    "gn:country_code":"PK",
    "gn:dem":3101,
    "gn:feature_class":"P",
    "gn:feature_code":"PPL",
    "gn:name":"Pujwalianwaladanna",
    "gn:population":0,
    "gn:timezone":"Asia/Karachi",
    "iso:country":"PK",
    "wof:name":"Pujwalianwaladanna",
    "wof:placetype":"locality"
},
  "geometry": {"coordinates":[73.44896999999997,34.55706],"type":"Point"}
}