{
  "type": "Feature",
  "properties": {
    "gn:admin1_code":"6",
    "gn:asciiname":"Gura Balial",
    "gn:country_code":"PK",
    "gn:dem":826,
    "gn:feature_class":"P",
    "gn:feature_code":"PPL",
    "gn:name":"Gura Balial",
    "gn:population":0,
    "gn:timezone":"Asia/Karachi",
    "iso:country":"PK",
    "wof:name":"Gura Balial",
    "wof:placetype":"locality"
},
  "geometry": {"coordinates":[74.06643000000003,33.32775],"type":"Point"}
}