{
  "type": "Feature",
  "properties": {
    "gn:admin1_code":"4.0",
    "gn:asciiname":"Jhuggian Changran",
    "gn:country_code":"PK",
    "gn:dem":212,
    "gn:feature_class":"P",
    "gn:feature_code":"PPL",
    "gn:name":"Jhuggi\u0101n Changr\u0101n",
    "gn:population":0,
    "gn:timezone":"Asia/Karachi",
    "iso:country":"PK",
    "wof:name":"Jhuggian Changran",
    "wof:placetype":"locality"
},
  "geometry": {"coordinates":[74.05360999999998,31.79028],"type":"Point"}
}