{
  "type": "Feature",
  "properties": {
    "gn:admin1_code":"4.0",
    "gn:asciiname":"Kanganwala",
    "gn:country_code":"PK",
    "gn:dem":108,
    "gn:feature_class":"P",
    "gn:feature_code":"PPL",
    "gn:name":"Kanganwala",
    "gn:population":0,
    "gn:timezone":"Asia/Karachi",
    "iso:country":"PK",
    "name:und_x_variant":[
        "Kawganw\u0101la",
        "Kanganwala",
        "Kanganw\u0101la Inspection Bungalow",
        "Kanganw\u0101la Canal Lodge"
    ],
    "wof:name":"Kanganwala",
    "wof:placetype":"locality"
},
  "geometry": {"coordinates":[71.37673000000002,28.89988],"type":"Point"}
}