{
  "type": "Feature",
  "properties": {
    "gn:admin1_code":"5",
    "gn:asciiname":"Goth Marlo",
    "gn:country_code":"PK",
    "gn:dem":42,
    "gn:feature_class":"P",
    "gn:feature_code":"PPL",
    "gn:name":"Goth Marlo",
    "gn:population":0,
    "gn:timezone":"Asia/Karachi",
    "iso:country":"PK",
    "name:und_x_variant":[
        "Maro"
    ],
    "wof:name":"Goth Marlo",
    "wof:placetype":"locality"
},
  "geometry": {"coordinates":[67.73692,26.83094],"type":"Point"}
}