{
  "type": "Feature",
  "properties": {
    "gn:admin1_code":"4",
    "gn:asciiname":"Chak Forty-four Western Branch",
    "gn:country_code":"PK",
    "gn:dem":138,
    "gn:feature_class":"P",
    "gn:feature_code":"PPL",
    "gn:name":"Chak Forty-four Western Branch",
    "gn:population":0,
    "gn:timezone":"Asia/Karachi",
    "iso:country":"PK",
    "name:und_x_variant":[
        "Push\u0101nw\u0101li"
    ],
    "wof:name":"Chak Forty-four Western Branch",
    "wof:placetype":"locality"
},
  "geometry": {"coordinates":[72.24120000000001,30.108],"type":"Point"}
}