{
  "type": "Feature",
  "properties": {
    "gn:admin1_code":"01",
    "gn:asciiname":"Wau",
    "gn:country_code":"PK",
    "gn:dem":1449,
    "gn:feature_class":"P",
    "gn:feature_code":"PPL",
    "gn:name":"Wau",
    "gn:population":0,
    "gn:timezone":"Asia/Karachi",
    "iso:country":"PK",
    "name:ceb_x_preferred":[
        "Wau"
    ],
    "name:deu_x_preferred":[
        "Wau"
    ],
    "name:ell_x_preferred":[
        "\u0392\u03ac\u03bf\u03c5"
    ],
    "name:fas_x_preferred":[
        "\u0648\u0648"
    ],
    "name:fin_x_preferred":[
        "Wau"
    ],
    "name:fra_x_preferred":[
        "Wau"
    ],
    "name:hun_x_preferred":[
        "Wau"
    ],
    "name:nld_x_preferred":[
        "Wau"
    ],
    "name:pol_x_preferred":[
        "Wau"
    ],
    "name:swe_x_preferred":[
        "Wau"
    ],
    "name:und_x_variant":[
        "Waid\u0101nai",
        "Weedana"
    ],
    "wof:name":"Wau",
    "wof:placetype":"locality"
},
  "geometry": {"coordinates":[69.69698,32.97583],"type":"Point"}
}