{
  "type": "Feature",
  "properties": {
    "gn:admin1_code":"3.0",
    "gn:asciiname":"Gehal",
    "gn:country_code":"PK",
    "gn:dem":1201,
    "gn:feature_class":"P",
    "gn:feature_code":"PPL",
    "gn:name":"Gehal",
    "gn:population":0,
    "gn:timezone":"Asia/Karachi",
    "iso:country":"PK",
    "name:eng_x_preferred":[
        "Goh\u0101l"
    ],
    "wof:name":"Gehal",
    "wof:placetype":"locality"
},
  "geometry": {"coordinates":[73.26553,33.9681],"type":"Point"}
}