{
  "type": "Feature",
  "properties": {
    "gn:admin1_code":"7.0",
    "gn:asciiname":"Ling",
    "gn:country_code":"PK",
    "gn:dem":3259,
    "gn:feature_class":"P",
    "gn:feature_code":"PPL",
    "gn:name":"Ling",
    "gn:population":0,
    "gn:timezone":"Asia/Karachi",
    "iso:country":"PK",
    "name:deu_x_preferred":[
        "Ling"
    ],
    "name:fra_x_preferred":[
        "Ling"
    ],
    "name:nld_x_preferred":[
        "Ling"
    ],
    "name:por_x_preferred":[
        "Ling"
    ],
    "name:rus_x_preferred":[
        "\u041b\u0438\u043d\u0433"
    ],
    "name:swe_x_preferred":[
        "Ling"
    ],
    "wof:name":"Ling",
    "wof:placetype":"locality"
},
  "geometry": {"coordinates":[74.12293000000003,35.9502],"type":"Point"}
}