{
  "type": "Feature",
  "properties": {
    "gn:admin1_code":"2.0",
    "gn:asciiname":"Gawal Bagh",
    "gn:country_code":"PK",
    "gn:dem":2247,
    "gn:feature_class":"P",
    "gn:feature_code":"PPL",
    "gn:name":"Gawal Bagh",
    "gn:population":0,
    "gn:timezone":"Asia/Karachi",
    "iso:country":"PK",
    "name:und_x_variant":[
        "Gw\u0101l B\u0101gh"
    ],
    "wof:name":"Gawal Bagh",
    "wof:placetype":"locality"
},
  "geometry": {"coordinates":[66.83293,30.95565],"type":"Point"}
}