{
  "type": "Feature",
  "properties": {
    "gn:admin1_code":"08",
    "gn:asciiname":"Shiekhpur",
    "gn:country_code":"PK",
    "gn:dem":534,
    "gn:feature_class":"P",
    "gn:feature_code":"PPL",
    "gn:name":"Shiekhpur",
    "gn:population":0,
    "gn:timezone":"Asia/Karachi",
    "iso:country":"PK",
    "name:eng_x_preferred":[
        "Shekhpur"
    ],
    "name:eng_x_variant":[
        "Sheikhpur"
    ],
    "wof:name":"Shiekhpur",
    "wof:placetype":"locality"
},
  "geometry": {"coordinates":[72.95333000000002,33.59569],"type":"Point"}
}