{
  "type": "Feature",
  "properties": {
    "gn:admin1_code":"3",
    "gn:asciiname":"Balhag Bala",
    "gn:country_code":"PK",
    "gn:dem":1034,
    "gn:feature_class":"P",
    "gn:feature_code":"PPL",
    "gn:name":"Balhag Bala",
    "gn:population":0,
    "gn:timezone":"Asia/Karachi",
    "iso:country":"PK",
    "name:und_x_variant":[
        "Balhag Utli"
    ],
    "wof:name":"Balhag Bala",
    "wof:placetype":"locality"
},
  "geometry": {"coordinates":[73.11646999999998,34.27569],"type":"Point"}
}