{
  "type": "Feature",
  "properties": {
    "gn:admin1_code":"04",
    "gn:asciiname":"Chak Thirty-four -Twelve Left",
    "gn:country_code":"PK",
    "gn:dem":159,
    "gn:feature_class":"P",
    "gn:feature_code":"PPL",
    "gn:name":"Chak Thirty-four -Twelve Left",
    "gn:population":0,
    "gn:timezone":"Asia/Karachi",
    "iso:country":"PK",
    "name:und_x_variant":[
        "Kot Muhammad"
    ],
    "wof:name":"Chak Thirty-four -Twelve Left",
    "wof:placetype":"locality"
},
  "geometry": {"coordinates":[72.6546,30.46322],"type":"Point"}
}