{
  "type": "Feature",
  "properties": {
    "gn:admin1_code":"4.0",
    "gn:asciiname":"Garata Saiyidan",
    "gn:country_code":"PK",
    "gn:dem":560,
    "gn:feature_class":"P",
    "gn:feature_code":"PPL",
    "gn:name":"Garata Saiyidan",
    "gn:population":0,
    "gn:timezone":"Asia/Karachi",
    "iso:country":"PK",
    "name:und_x_variant":[
        "Garatah Saidan",
        "Gar\u0101ta Saiyid\u0101n",
        "Garata Saiyidan"
    ],
    "wof:name":"Garata Saiyidan",
    "wof:placetype":"locality"
},
  "geometry": {"coordinates":[73.28903000000003,33.4865],"type":"Point"}
}