{
  "type": "Feature",
  "properties": {
    "gn:admin1_code":"5.0",
    "gn:asciiname":"Karachat",
    "gn:country_code":"PK",
    "gn:dem":200,
    "gn:feature_class":"P",
    "gn:feature_code":"PPL",
    "gn:name":"Karachat",
    "gn:population":0,
    "gn:timezone":"Asia/Karachi",
    "iso:country":"PK",
    "name:und_x_variant":[
        "Karch\u0101t"
    ],
    "wof:name":"Karachat",
    "wof:placetype":"locality"
},
  "geometry": {"coordinates":[67.7372,25.75501],"type":"Point"}
}