{
  "type": "Feature",
  "properties": {
    "gn:admin1_code":"2.0",
    "gn:asciiname":"Goth Muhammad Panah",
    "gn:country_code":"PK",
    "gn:dem":62,
    "gn:feature_class":"P",
    "gn:feature_code":"PPL",
    "gn:name":"Goth Muhammad Panah",
    "gn:population":0,
    "gn:timezone":"Asia/Karachi",
    "iso:country":"PK",
    "wof:name":"Goth Muhammad Panah",
    "wof:placetype":"locality"
},
  "geometry": {"coordinates":[68.06901999999999,28.4274],"type":"Point"}
}