{
  "type": "Feature",
  "properties": {
    "gn:admin1_code":"3",
    "gn:asciiname":"Gidan",
    "gn:country_code":"PK",
    "gn:dem":1883,
    "gn:feature_class":"P",
    "gn:feature_code":"PPL",
    "gn:name":"Gidan",
    "gn:population":0,
    "gn:timezone":"Asia/Karachi",
    "iso:country":"PK",
    "name:amh_x_preferred":[
        "\u130a\u12f3\u1295"
    ],
    "name:eng_x_preferred":[
        "Gidan"
    ],
    "name:fra_x_preferred":[
        "Gidan"
    ],
    "name:und_x_variant":[
        "G\u012bdai"
    ],
    "wof:name":"Gidan",
    "wof:placetype":"locality"
},
  "geometry": {"coordinates":[72.60821999999997,35.34374000000001],"type":"Point"}
}