{
  "type": "Feature",
  "properties": {
    "gn:admin1_code":"6.0",
    "gn:asciiname":"Jang",
    "gn:country_code":"PK",
    "gn:dem":390,
    "gn:feature_class":"P",
    "gn:feature_code":"PPL",
    "gn:name":"Jang",
    "gn:population":0,
    "gn:timezone":"Asia/Karachi",
    "iso:country":"PK",
    "wof:name":"Jang",
    "wof:placetype":"locality"
},
  "geometry": {"coordinates":[73.58139,33.21955999999999],"type":"Point"}
}