{
  "type": "Feature",
  "properties": {
    "gn:admin1_code":"8.0",
    "gn:asciiname":"Kangota Komeran",
    "gn:country_code":"PK",
    "gn:dem":489,
    "gn:feature_class":"P",
    "gn:feature_code":"PPL",
    "gn:name":"Kangota Komeran",
    "gn:population":0,
    "gn:timezone":"Asia/Karachi",
    "iso:country":"PK",
    "name:und_x_variant":[
        "Kangota Gujran",
        "Kangota Gujar\u0101n",
        "Kangota Komeran"
    ],
    "wof:name":"Kangota Komeran",
    "wof:placetype":"locality"
},
  "geometry": {"coordinates":[73.22748,33.54991],"type":"Point"}
}