{
  "type": "Feature",
  "properties": {
    "gn:admin1_code":"4.0",
    "gn:asciiname":"Pia Mehr Ali",
    "gn:country_code":"PK",
    "gn:dem":603,
    "gn:feature_class":"P",
    "gn:feature_code":"PPL",
    "gn:name":"Pia Mehr Ali",
    "gn:population":0,
    "gn:timezone":"Asia/Karachi",
    "iso:country":"PK",
    "name:und_x_variant":[
        "Bh\u0101i Mehr Ali"
    ],
    "wof:name":"Pia Mehr Ali",
    "wof:placetype":"locality"
},
  "geometry": {"coordinates":[73.46087,33.45064],"type":"Point"}
}