{
  "type": "Feature",
  "properties": {
    "gn:admin1_code":"2.0",
    "gn:asciiname":"Psha Sra",
    "gn:country_code":"PK",
    "gn:dem":2081,
    "gn:feature_class":"P",
    "gn:feature_code":"PPL",
    "gn:name":"Psha Sra",
    "gn:population":0,
    "gn:timezone":"Asia/Karachi",
    "iso:country":"PK",
    "name:und_x_variant":[
        "Psha"
    ],
    "wof:name":"Psha Sra",
    "wof:placetype":"locality"
},
  "geometry": {"coordinates":[67.62220000000001,30.82519000000001],"type":"Point"}
}