{
  "type": "Feature",
  "properties": {
    "gn:admin1_code":"5.0",
    "gn:asciiname":"Band Virah",
    "gn:country_code":"PK",
    "gn:dem":97,
    "gn:feature_class":"P",
    "gn:feature_code":"PPL",
    "gn:name":"Band Virah",
    "gn:population":0,
    "gn:timezone":"Asia/Karachi",
    "iso:country":"PK",
    "name:eng_x_preferred":[
        "Band V\u012br\u0101h"
    ],
    "wof:name":"Band Virah",
    "wof:placetype":"locality"
},
  "geometry": {"coordinates":[68.07156999999999,25.58071],"type":"Point"}
}