{
  "type": "Feature",
  "properties": {
    "gn:admin1_code":"4.0",
    "gn:asciiname":"Mahdipur",
    "gn:country_code":"PK",
    "gn:dem":121,
    "gn:feature_class":"P",
    "gn:feature_code":"PPL",
    "gn:name":"Mahdipur",
    "gn:population":0,
    "gn:timezone":"Asia/Karachi",
    "iso:country":"PK",
    "name:und_x_variant":[
        "J\u0101lw\u0101la",
        "Mahdipur",
        "Mehdipur"
    ],
    "wof:name":"Mahdipur",
    "wof:placetype":"locality"
},
  "geometry": {"coordinates":[71.38195,30.13117],"type":"Point"}
}