{
  "type": "Feature",
  "properties": {
    "gn:admin1_code":"3.0",
    "gn:asciiname":"Shidak Gali",
    "gn:country_code":"PK",
    "gn:dem":3721,
    "gn:feature_class":"P",
    "gn:feature_code":"PPL",
    "gn:name":"Shidak Gali",
    "gn:population":0,
    "gn:timezone":"Asia/Karachi",
    "iso:country":"PK",
    "wof:name":"Shidak Gali",
    "wof:placetype":"locality"
},
  "geometry": {"coordinates":[73.60813,35.28137],"type":"Point"}
}