{
  "type": "Feature",
  "properties": {
    "gn:admin1_code":"1.0",
    "gn:asciiname":"Gund Seri",
    "gn:country_code":"PK",
    "gn:dem":1424,
    "gn:feature_class":"P",
    "gn:feature_code":"PPL",
    "gn:name":"Gund Seri",
    "gn:population":0,
    "gn:timezone":"Asia/Karachi",
    "iso:country":"PK",
    "wof:name":"Gund Seri",
    "wof:placetype":"locality"
},
  "geometry": {"coordinates":[70.77225,33.63249],"type":"Point"}
}