{
  "type": "Feature",
  "properties": {
    "gn:admin1_code":"1.0",
    "gn:asciiname":"Dago Kalle",
    "gn:country_code":"PK",
    "gn:dem":1866,
    "gn:feature_class":"P",
    "gn:feature_code":"PPL",
    "gn:name":"Dago Kalle",
    "gn:population":0,
    "gn:timezone":"Asia/Karachi",
    "iso:country":"PK",
    "name:und_x_variant":[
        "D\u0101goi Kili",
        "D\u0101go Kili",
        "Dago Kalle"
    ],
    "wof:name":"Dago Kalle",
    "wof:placetype":"locality"
},
  "geometry": {"coordinates":[70.00703,33.92554000000001],"type":"Point"}
}