{
  "type": "Feature",
  "properties": {
    "gn:admin1_code":"3",
    "gn:asciiname":"Kund",
    "gn:country_code":"PK",
    "gn:dem":2182,
    "gn:feature_class":"P",
    "gn:feature_code":"PPL",
    "gn:name":"Kund",
    "gn:population":0,
    "gn:timezone":"Asia/Karachi",
    "iso:country":"PK",
    "name:und_x_variant":[
        "Kand"
    ],
    "wof:name":"Kund",
    "wof:placetype":"locality"
},
  "geometry": {"coordinates":[72.36854,35.08586],"type":"Point"}
}