{
  "type": "Feature",
  "properties": {
    "gn:admin1_code":"4.0",
    "gn:asciiname":"Mohra Bagh",
    "gn:country_code":"PK",
    "gn:dem":562,
    "gn:feature_class":"P",
    "gn:feature_code":"PPL",
    "gn:name":"Mohra Bagh",
    "gn:population":0,
    "gn:timezone":"Asia/Karachi",
    "iso:country":"PK",
    "wof:name":"Mohra Bagh",
    "wof:placetype":"locality"
},
  "geometry": {"coordinates":[73.3458,33.42809],"type":"Point"}
}