{
  "type": "Feature",
  "properties": {
    "gn:admin1_code":"04",
    "gn:asciiname":"Miana Mohra",
    "gn:country_code":"PK",
    "gn:dem":461,
    "gn:feature_class":"P",
    "gn:feature_code":"PPL",
    "gn:name":"Miana Mohra",
    "gn:population":0,
    "gn:timezone":"Asia/Karachi",
    "iso:country":"PK",
    "name:eng_x_preferred":[
        "Miana Mohra"
    ],
    "wof:name":"Miana Mohra",
    "wof:placetype":"locality"
},
  "geometry": {"coordinates":[72.85836,33.1979],"type":"Point"}
}