{
  "type": "Feature",
  "properties": {
    "gn:admin1_code":"4.0",
    "gn:asciiname":"Cherewan",
    "gn:country_code":"PK",
    "gn:dem":209,
    "gn:feature_class":"P",
    "gn:feature_code":"PPL",
    "gn:name":"Cherewan",
    "gn:population":0,
    "gn:timezone":"Asia/Karachi",
    "iso:country":"PK",
    "name:und_x_variant":[
        "Charewan"
    ],
    "wof:name":"Cherewan",
    "wof:placetype":"locality"
},
  "geometry": {"coordinates":[74.40683,31.19654],"type":"Point"}
}