{
  "type": "Feature",
  "properties": {
    "gn:admin1_code":"6.0",
    "gn:asciiname":"Baindar",
    "gn:country_code":"PK",
    "gn:dem":1609,
    "gn:feature_class":"P",
    "gn:feature_code":"PPL",
    "gn:name":"Baindar",
    "gn:population":0,
    "gn:timezone":"Asia/Karachi",
    "iso:country":"PK",
    "name:und_x_variant":[
        "Bendh\u0101r"
    ],
    "wof:name":"Baindar",
    "wof:placetype":"locality"
},
  "geometry": {"coordinates":[73.69943000000001,33.82965],"type":"Point"}
}