{
  "type": "Feature",
  "properties": {
    "gn:admin1_code":"2",
    "gn:asciiname":"Dalgi Basti",
    "gn:country_code":"PK",
    "gn:dem":837,
    "gn:feature_class":"P",
    "gn:feature_code":"PPL",
    "gn:name":"Dalgi Basti",
    "gn:population":0,
    "gn:timezone":"Asia/Karachi",
    "iso:country":"PK",
    "wof:name":"Dalgi Basti",
    "wof:placetype":"locality"
},
  "geometry": {"coordinates":[65.59275,29.12176],"type":"Point"}
}