{
  "type": "Feature",
  "properties": {
    "gn:admin1_code":"4.0",
    "gn:asciiname":"Agharabad",
    "gn:country_code":"PK",
    "gn:dem":163,
    "gn:feature_class":"P",
    "gn:feature_code":"PPL",
    "gn:name":"Agharabad",
    "gn:population":0,
    "gn:timezone":"Asia/Karachi",
    "iso:country":"PK",
    "name:und_x_variant":[
        "Faiz Muhammad Khokhar"
    ],
    "wof:name":"Agharabad",
    "wof:placetype":"locality"
},
  "geometry": {"coordinates":[73.52936,30.16382],"type":"Point"}
}