{
  "type": "Feature",
  "properties": {
    "gn:admin1_code":"4",
    "gn:asciiname":"Rehlian",
    "gn:country_code":"PK",
    "gn:dem":149,
    "gn:feature_class":"P",
    "gn:feature_code":"PPL",
    "gn:name":"Rehlian",
    "gn:population":0,
    "gn:timezone":"Asia/Karachi",
    "iso:country":"PK",
    "name:und_x_variant":[
        "Rehla"
    ],
    "wof:name":"Rehlian",
    "wof:placetype":"locality"
},
  "geometry": {"coordinates":[70.73163000000002,30.92027],"type":"Point"}
}