{
  "type": "Feature",
  "properties": {
    "gn:admin1_code":"4",
    "gn:asciiname":"Alipur Asar",
    "gn:country_code":"PK",
    "gn:dem":110,
    "gn:feature_class":"P",
    "gn:feature_code":"PPL",
    "gn:name":"Alipur Asar",
    "gn:population":0,
    "gn:timezone":"Asia/Karachi",
    "iso:country":"PK",
    "wof:name":"Alipur Asar",
    "wof:placetype":"locality"
},
  "geometry": {"coordinates":[71.41884,29.45639000000001],"type":"Point"}
}