{
  "type": "Feature",
  "properties": {
    "gn:admin1_code":"4.0",
    "gn:asciiname":"Jatwal Gujran",
    "gn:country_code":"PK",
    "gn:dem":271,
    "gn:feature_class":"P",
    "gn:feature_code":"PPL",
    "gn:name":"Jatwal Gujran",
    "gn:population":0,
    "gn:timezone":"Asia/Karachi",
    "iso:country":"PK",
    "wof:name":"Jatwal Gujran",
    "wof:placetype":"locality"
},
  "geometry": {"coordinates":[75.14180999999998,32.30507],"type":"Point"}
}