{
  "type": "Feature",
  "properties": {
    "gn:admin1_code":"1.0",
    "gn:asciiname":"Gobazana",
    "gn:country_code":"PK",
    "gn:dem":2148,
    "gn:feature_class":"P",
    "gn:feature_code":"PPL",
    "gn:name":"Gobazana",
    "gn:population":0,
    "gn:timezone":"Asia/Karachi",
    "iso:country":"PK",
    "wof:name":"Gobazana",
    "wof:placetype":"locality"
},
  "geometry": {"coordinates":[69.90706,33.95947],"type":"Point"}
}