{
  "type": "Feature",
  "properties": {
    "gn:admin1_code":"1.0",
    "gn:asciiname":"Chana",
    "gn:country_code":"PK",
    "gn:dem":390,
    "gn:feature_class":"P",
    "gn:feature_code":"PPL",
    "gn:name":"Chana",
    "gn:population":0,
    "gn:timezone":"Asia/Karachi",
    "iso:country":"PK",
    "name:ceb_x_preferred":[
        "Chana"
    ],
    "name:ces_x_preferred":[
        "Chana"
    ],
    "name:deu_x_preferred":[
        "Chana"
    ],
    "name:por_x_preferred":[
        "Chana"
    ],
    "name:spa_x_preferred":[
        "Chana"
    ],
    "name:swe_x_preferred":[
        "Chana"
    ],
    "wof:name":"Chana",
    "wof:placetype":"locality"
},
  "geometry": {"coordinates":[73.66479,33.21533],"type":"Point"}
}