{
  "type": "Feature",
  "properties": {
    "gn:admin1_code":"5",
    "gn:asciiname":"Goth Chungal",
    "gn:country_code":"PK",
    "gn:dem":55,
    "gn:feature_class":"P",
    "gn:feature_code":"PPL",
    "gn:name":"Goth Chungal",
    "gn:population":0,
    "gn:timezone":"Asia/Karachi",
    "iso:country":"PK",
    "name:und_x_variant":[
        "Chungal"
    ],
    "wof:name":"Goth Chungal",
    "wof:placetype":"locality"
},
  "geometry": {"coordinates":[68.24289,27.79249],"type":"Point"}
}