{
  "type": "Feature",
  "properties": {
    "gn:admin1_code":"2.0",
    "gn:asciiname":"Pasta Khawasa Kili",
    "gn:country_code":"PK",
    "gn:dem":1222,
    "gn:feature_class":"P",
    "gn:feature_code":"PPL",
    "gn:name":"Pasta Khawasa Kili",
    "gn:population":0,
    "gn:timezone":"Asia/Karachi",
    "iso:country":"PK",
    "name:und_x_variant":[
        "Pasta Khowasa Kili"
    ],
    "wof:name":"Pasta Khawasa Kili",
    "wof:placetype":"locality"
},
  "geometry": {"coordinates":[68.44058000000001,30.15734],"type":"Point"}
}