{
  "type": "Feature",
  "properties": {
    "gn:admin1_code":"4.0",
    "gn:asciiname":"Chak Eighty-eight ML",
    "gn:country_code":"PK",
    "gn:dem":161,
    "gn:feature_class":"P",
    "gn:feature_code":"PPL",
    "gn:name":"Chak Eighty-eight ML",
    "gn:population":0,
    "gn:timezone":"Asia/Karachi",
    "iso:country":"PK",
    "name:und_x_variant":[
        "Chak 88 ML"
    ],
    "wof:name":"Chak Eighty-eight ML",
    "wof:placetype":"locality"
},
  "geometry": {"coordinates":[71.03394,31.30303],"type":"Point"}
}