{
  "type": "Feature",
  "properties": {
    "gn:admin1_code":"4.0",
    "gn:asciiname":"Chah Nurewala",
    "gn:country_code":"PK",
    "gn:dem":89,
    "gn:feature_class":"P",
    "gn:feature_code":"PPL",
    "gn:name":"Ch\u0101h Nurew\u0101la",
    "gn:population":0,
    "gn:timezone":"Asia/Karachi",
    "iso:country":"PK",
    "wof:name":"Chah Nurewala",
    "wof:placetype":"locality"
},
  "geometry": {"coordinates":[70.49444,28.60417],"type":"Point"}
}