{
  "type": "Feature",
  "properties": {
    "gn:admin1_code":"1.0",
    "gn:asciiname":"Jarubai",
    "gn:country_code":"PK",
    "gn:dem":1668,
    "gn:feature_class":"P",
    "gn:feature_code":"PPL",
    "gn:name":"Jarubai",
    "gn:population":0,
    "gn:timezone":"Asia/Karachi",
    "iso:country":"PK",
    "name:und_x_variant":[
        "Jarobai"
    ],
    "wof:name":"Jarubai",
    "wof:placetype":"locality"
},
  "geometry": {"coordinates":[70.87963000000001,33.8683],"type":"Point"}
}