{
  "type": "Feature",
  "properties": {
    "gn:admin1_code":"3.0",
    "gn:asciiname":"Golash",
    "gn:country_code":"PK",
    "gn:dem":3385,
    "gn:feature_class":"P",
    "gn:feature_code":"PPL",
    "gn:name":"Golash",
    "gn:population":0,
    "gn:timezone":"Asia/Karachi",
    "iso:country":"PK",
    "wof:name":"Golash",
    "wof:placetype":"locality"
},
  "geometry": {"coordinates":[72.98801999999998,36.61236],"type":"Point"}
}