{
  "type": "Feature",
  "properties": {
    "gn:admin1_code":"3.0",
    "gn:asciiname":"Katakot Mashriqi",
    "gn:country_code":"PK",
    "gn:dem":673,
    "gn:feature_class":"P",
    "gn:feature_code":"PPL",
    "gn:name":"Katakot Mashriqi",
    "gn:population":0,
    "gn:timezone":"Asia/Karachi",
    "iso:country":"PK",
    "wof:name":"Katakot Mashriqi",
    "wof:placetype":"locality"
},
  "geometry": {"coordinates":[72.60372,34.41517],"type":"Point"}
}