{
  "type": "Feature",
  "properties": {
    "gn:admin1_code":"4.0",
    "gn:asciiname":"Dhok Bandial",
    "gn:country_code":"PK",
    "gn:dem":550,
    "gn:feature_class":"P",
    "gn:feature_code":"PPL",
    "gn:name":"Dhok Bandial",
    "gn:population":0,
    "gn:timezone":"Asia/Karachi",
    "iso:country":"PK",
    "name:und_x_variant":[
        "Dhok Bandhy\u0101l"
    ],
    "wof:name":"Dhok Bandial",
    "wof:placetype":"locality"
},
  "geometry": {"coordinates":[72.69786999999999,33.45489],"type":"Point"}
}