{
  "type": "Feature",
  "properties": {
    "gn:admin1_code":"2.0",
    "gn:asciiname":"Aorak Kachi",
    "gn:country_code":"PK",
    "gn:dem":1510,
    "gn:feature_class":"P",
    "gn:feature_code":"PPL",
    "gn:name":"Aorak Kachi",
    "gn:population":0,
    "gn:timezone":"Asia/Karachi",
    "iso:country":"PK",
    "wof:name":"Aorak Kachi",
    "wof:placetype":"locality"
},
  "geometry": {"coordinates":[68.04500999999999,30.2101],"type":"Point"}
}