{
  "type": "Feature",
  "properties": {
    "gn:admin1_code":"5",
    "gn:asciiname":"Goth Mir Muhammad Rajar",
    "gn:country_code":"PK",
    "gn:dem":10,
    "gn:feature_class":"P",
    "gn:feature_code":"PPL",
    "gn:name":"Goth Mir Muhammad Rajar",
    "gn:population":0,
    "gn:timezone":"Asia/Karachi",
    "iso:country":"PK",
    "name:und_x_variant":[
        "M\u012br Muhammad P\u0101tho"
    ],
    "wof:name":"Goth Mir Muhammad Rajar",
    "wof:placetype":"locality"
},
  "geometry": {"coordinates":[69.71651,25.46093],"type":"Point"}
}