{
  "type": "Feature",
  "properties": {
    "gn:admin1_code":"3.0",
    "gn:asciiname":"Jajute",
    "gn:country_code":"PK",
    "gn:dem":3403,
    "gn:feature_class":"P",
    "gn:feature_code":"PPL",
    "gn:name":"Jajute",
    "gn:population":0,
    "gn:timezone":"Asia/Karachi",
    "iso:country":"PK",
    "name:eng_x_preferred":[
        "Jaija"
    ],
    "wof:name":"Jajute",
    "wof:placetype":"locality"
},
  "geometry": {"coordinates":[72.06988,35.66978],"type":"Point"}
}