{
  "type": "Feature",
  "properties": {
    "gn:admin1_code":"01",
    "gn:asciiname":"Dandu",
    "gn:country_code":"PK",
    "gn:dem":683,
    "gn:feature_class":"P",
    "gn:feature_code":"PPL",
    "gn:name":"Dandu",
    "gn:population":0,
    "gn:timezone":"Asia/Karachi",
    "iso:country":"PK",
    "name:und_x_variant":[
        "Dand\u0101o"
    ],
    "wof:name":"Dandu",
    "wof:placetype":"locality"
},
  "geometry": {"coordinates":[71.37586999999998,34.57969],"type":"Point"}
}