{
  "type": "Feature",
  "properties": {
    "gn:admin1_code":"5",
    "gn:asciiname":"Jumman Mangrio",
    "gn:country_code":"PK",
    "gn:dem":44,
    "gn:feature_class":"P",
    "gn:feature_code":"PPL",
    "gn:name":"Jumman Mangrio",
    "gn:population":0,
    "gn:timezone":"Asia/Karachi",
    "iso:country":"PK",
    "name:und_x_variant":[
        "Magria"
    ],
    "wof:name":"Jumman Mangrio",
    "wof:placetype":"locality"
},
  "geometry": {"coordinates":[68.12478,26.87629],"type":"Point"}
}