{
  "type": "Feature",
  "properties": {
    "gn:admin1_code":"8.0",
    "gn:asciiname":"Padu",
    "gn:country_code":"PK",
    "gn:dem":1163,
    "gn:feature_class":"P",
    "gn:feature_code":"PPL",
    "gn:name":"Padu",
    "gn:population":0,
    "gn:timezone":"Asia/Karachi",
    "iso:country":"PK",
    "name:eng_x_preferred":[
        "Budha"
    ],
    "wof:name":"Padu",
    "wof:placetype":"locality"
},
  "geometry": {"coordinates":[73.1541,33.80511],"type":"Point"}
}