{
  "type": "Feature",
  "properties": {
    "gn:admin1_code":"2.0",
    "gn:asciiname":"Argock",
    "gn:country_code":"PK",
    "gn:dem":1593,
    "gn:feature_class":"P",
    "gn:feature_code":"PPL",
    "gn:name":"Argock",
    "gn:population":0,
    "gn:timezone":"Asia/Karachi",
    "iso:country":"PK",
    "wof:name":"Argock",
    "wof:placetype":"locality"
},
  "geometry": {"coordinates":[66.00085,28.21582],"type":"Point"}
}