{
  "type": "Feature",
  "properties": {
    "gn:admin1_code":"4",
    "gn:asciiname":"Chak Ninety-seven Eastern Bar",
    "gn:country_code":"PK",
    "gn:dem":156,
    "gn:feature_class":"P",
    "gn:feature_code":"PPL",
    "gn:name":"Chak Ninety-seven Eastern Bar",
    "gn:population":0,
    "gn:timezone":"Asia/Karachi",
    "iso:country":"PK",
    "name:und_x_variant":[
        "Shekh\u016bpura"
    ],
    "wof:name":"Chak Ninety-seven Eastern Bar",
    "wof:placetype":"locality"
},
  "geometry": {"coordinates":[72.98178,30.20607],"type":"Point"}
}