{
  "type": "Feature",
  "properties": {
    "gn:admin1_code":"3",
    "gn:asciiname":"Pashta",
    "gn:country_code":"PK",
    "gn:dem":1461,
    "gn:feature_class":"P",
    "gn:feature_code":"PPL",
    "gn:name":"Pashta",
    "gn:population":0,
    "gn:timezone":"Asia/Karachi",
    "iso:country":"PK",
    "name:deu_x_preferred":[
        "Paschta"
    ],
    "wof:name":"Pashta",
    "wof:placetype":"locality"
},
  "geometry": {"coordinates":[72.11438000000003,34.95143],"type":"Point"}
}