{
  "type": "Feature",
  "properties": {
    "gn:admin1_code":"4.0",
    "gn:asciiname":"Kotli Salharian",
    "gn:country_code":"PK",
    "gn:dem":260,
    "gn:feature_class":"P",
    "gn:feature_code":"PPL",
    "gn:name":"Kotli Salharian",
    "gn:population":0,
    "gn:timezone":"Asia/Karachi",
    "iso:country":"PK",
    "name:und_x_variant":[
        "Kotli"
    ],
    "wof:name":"Kotli Salharian",
    "wof:placetype":"locality"
},
  "geometry": {"coordinates":[74.77136999999998,32.40324],"type":"Point"}
}