{
  "type": "Feature",
  "properties": {
    "gn:admin1_code":"4.0",
    "gn:asciiname":"Dhidianwala",
    "gn:country_code":"PK",
    "gn:dem":266,
    "gn:feature_class":"P",
    "gn:feature_code":"PPL",
    "gn:name":"Dhidianwala",
    "gn:population":0,
    "gn:timezone":"Asia/Karachi",
    "iso:country":"PK",
    "wof:name":"Dhidianwala",
    "wof:placetype":"locality"
},
  "geometry": {"coordinates":[71.74276,32.61027],"type":"Point"}
}