{
  "type": "Feature",
  "properties": {
    "gn:admin1_code":"4.0",
    "gn:asciiname":"Hussain Khanwala",
    "gn:country_code":"PK",
    "gn:dem":196,
    "gn:feature_class":"P",
    "gn:feature_code":"PPL",
    "gn:name":"Hussain Khanwala",
    "gn:population":0,
    "gn:timezone":"Asia/Karachi",
    "iso:country":"PK",
    "name:und_x_variant":[
        "Husian Kh\u0101nw\u0101la"
    ],
    "wof:name":"Hussain Khanwala",
    "wof:placetype":"locality"
},
  "geometry": {"coordinates":[74.41288,31.00982],"type":"Point"}
}