{
  "type": "Feature",
  "properties": {
    "gn:admin1_code":"6",
    "gn:asciiname":"Khakhial Dhara",
    "gn:country_code":"PK",
    "gn:dem":1302,
    "gn:feature_class":"P",
    "gn:feature_code":"PPL",
    "gn:name":"Khakhial Dhara",
    "gn:population":0,
    "gn:timezone":"Asia/Karachi",
    "iso:country":"PK",
    "wof:name":"Khakhial Dhara",
    "wof:placetype":"locality"
},
  "geometry": {"coordinates":[73.95198000000001,33.77156],"type":"Point"}
}