{
  "type": "Feature",
  "properties": {
    "gn:admin1_code":"2.0",
    "gn:asciiname":"Ziarat Isa",
    "gn:country_code":"PK",
    "gn:dem":1175,
    "gn:feature_class":"P",
    "gn:feature_code":"PPL",
    "gn:name":"Ziarat Isa",
    "gn:population":0,
    "gn:timezone":"Asia/Karachi",
    "iso:country":"PK",
    "wof:name":"Ziarat Isa",
    "wof:placetype":"locality"
},
  "geometry": {"coordinates":[65.74366999999999,27.39839000000001],"type":"Point"}
}