{
  "type": "Feature",
  "properties": {
    "gn:admin1_code":"4",
    "gn:asciiname":"Dhok Mian Jiwan",
    "gn:country_code":"PK",
    "gn:dem":506,
    "gn:feature_class":"P",
    "gn:feature_code":"PPL",
    "gn:name":"Dhok Mian Jiwan",
    "gn:population":0,
    "gn:timezone":"Asia/Karachi",
    "iso:country":"PK",
    "name:und_x_variant":[
        "Dhok Jewin"
    ],
    "wof:name":"Dhok Mian Jiwan",
    "wof:placetype":"locality"
},
  "geometry": {"coordinates":[73.37546999999998,33.10035999999999],"type":"Point"}
}