{
  "type": "Feature",
  "properties": {
    "gn:admin1_code":"5.0",
    "gn:asciiname":"Jummon Hajano",
    "gn:country_code":"PK",
    "gn:dem":29,
    "gn:feature_class":"P",
    "gn:feature_code":"PPL",
    "gn:name":"Jummon Hajano",
    "gn:population":0,
    "gn:timezone":"Asia/Karachi",
    "iso:country":"PK",
    "wof:name":"Jummon Hajano",
    "wof:placetype":"locality"
},
  "geometry": {"coordinates":[68.35386,26.07183],"type":"Point"}
}