{
  "type": "Feature",
  "properties": {
    "gn:admin1_code":"4.0",
    "gn:asciiname":"Gufa",
    "gn:country_code":"PK",
    "gn:dem":208,
    "gn:feature_class":"P",
    "gn:feature_code":"PPL",
    "gn:name":"Gufa",
    "gn:population":0,
    "gn:timezone":"Asia/Karachi",
    "iso:country":"PK",
    "wof:name":"Gufa",
    "wof:placetype":"locality"
},
  "geometry": {"coordinates":[74.37306,31.27667000000001],"type":"Point"}
}