{
  "type": "Feature",
  "properties": {
    "gn:admin1_code":"5.0",
    "gn:asciiname":"Yari Muhammas Bhambro",
    "gn:country_code":"PK",
    "gn:dem":12,
    "gn:feature_class":"P",
    "gn:feature_code":"PPL",
    "gn:name":"Yari Muhammas Bhambro",
    "gn:population":0,
    "gn:timezone":"Asia/Karachi",
    "iso:country":"PK",
    "wof:name":"Yari Muhammas Bhambro",
    "wof:placetype":"locality"
},
  "geometry": {"coordinates":[69.33844999999999,25.64917],"type":"Point"}
}