{
  "type": "Feature",
  "properties": {
    "gn:admin1_code":"4.0",
    "gn:asciiname":"Chak Seventy North",
    "gn:country_code":"PK",
    "gn:dem":193,
    "gn:feature_class":"P",
    "gn:feature_code":"PPL",
    "gn:name":"Chak Seventy North",
    "gn:population":0,
    "gn:timezone":"Asia/Karachi",
    "iso:country":"PK",
    "name:eng_x_preferred":[
        "Chak Seventy North"
    ],
    "wof:name":"Chak Seventy North",
    "wof:placetype":"locality"
},
  "geometry": {"coordinates":[72.64948000000003,32.12687],"type":"Point"}
}