{
  "type": "Feature",
  "properties": {
    "gn:admin1_code":"5.0",
    "gn:asciiname":"Goth Saiyid Khadanu Shah",
    "gn:country_code":"PK",
    "gn:dem":16,
    "gn:feature_class":"P",
    "gn:feature_code":"PPL",
    "gn:name":"Goth Saiyid Khadanu Shah",
    "gn:population":0,
    "gn:timezone":"Asia/Karachi",
    "iso:country":"PK",
    "name:und_x_variant":[
        "Goth Saiyed Khond\u0101nu Sh\u0101h"
    ],
    "wof:name":"Goth Saiyid Khadanu Shah",
    "wof:placetype":"locality"
},
  "geometry": {"coordinates":[68.34699000000001,24.92353],"type":"Point"}
}