{
  "type": "Feature",
  "properties": {
    "gn:admin1_code":"2.0",
    "gn:asciiname":"Shero",
    "gn:country_code":"PK",
    "gn:dem":1551,
    "gn:feature_class":"P",
    "gn:feature_code":"PPL",
    "gn:name":"Shero",
    "gn:population":0,
    "gn:timezone":"Asia/Karachi",
    "iso:country":"PK",
    "wof:name":"Shero",
    "wof:placetype":"locality"
},
  "geometry": {"coordinates":[66.98416,30.73818],"type":"Point"}
}