{
  "type": "Feature",
  "properties": {
    "gn:admin1_code":"4",
    "gn:asciiname":"Basti Shakhani Chota",
    "gn:country_code":"PK",
    "gn:dem":80,
    "gn:feature_class":"P",
    "gn:feature_code":"PPL",
    "gn:name":"Basti Shakhani Chota",
    "gn:population":0,
    "gn:timezone":"Asia/Karachi",
    "iso:country":"PK",
    "name:und_x_variant":[
        "Shaikh\u0101ni Khurd"
    ],
    "wof:name":"Basti Shakhani Chota",
    "wof:placetype":"locality"
},
  "geometry": {"coordinates":[69.87188,28.39553],"type":"Point"}
}