{
  "type": "Feature",
  "properties": {
    "gn:admin1_code":"4",
    "gn:asciiname":"Basti Bhattian",
    "gn:country_code":"PK",
    "gn:dem":94,
    "gn:feature_class":"P",
    "gn:feature_code":"PPL",
    "gn:name":"Basti Bhattian",
    "gn:population":0,
    "gn:timezone":"Asia/Karachi",
    "iso:country":"PK",
    "name:und_x_variant":[
        "Bhatti"
    ],
    "wof:name":"Basti Bhattian",
    "wof:placetype":"locality"
},
  "geometry": {"coordinates":[70.84484999999999,28.87289],"type":"Point"}
}