{
  "type": "Feature",
  "properties": {
    "gn:admin1_code":"7.0",
    "gn:asciiname":"Thurtonas",
    "gn:country_code":"PK",
    "gn:dem":2848,
    "gn:feature_class":"P",
    "gn:feature_code":"PPL",
    "gn:name":"Thurtonas",
    "gn:population":0,
    "gn:timezone":"Asia/Karachi",
    "iso:country":"PK",
    "wof:name":"Thurtonas",
    "wof:placetype":"locality"
},
  "geometry": {"coordinates":[72.99809999999999,36.1016],"type":"Point"}
}