{
  "type": "Feature",
  "properties": {
    "iso:country":"PK",
    "name:ara_x_preferred":[
        "\u0644\u0646\u062f\u064a \u0643\u0648\u062a\u0627\u0644"
    ],
    "name:ceb_x_preferred":[
        "Landi Kotal"
    ],
    "name:deu_x_preferred":[
        "Landi Kotal"
    ],
    "name:eng_x_preferred":[
        "Landi Kotal"
    ],
    "name:fas_x_preferred":[
        "\u0644\u0646\u062f\u06cc \u06a9\u0648\u062a\u0644"
    ],
    "name:fra_x_preferred":[
        "Landi Kotal"
    ],
    "name:jpn_x_preferred":[
        "\u30e9\u30f3\u30c7\u30a3\u30fb\u30b3\u30bf\u30eb"
    ],
    "name:nld_x_preferred":[
        "Landi Kotal"
    ],
    "name:pan_x_preferred":[
        "\u0a32\u0a70\u0a21\u0a40 \u0a15\u0a4b\u0a24\u0a32"
    ],
    "name:pnb_x_preferred":[
        "\u0644\u0646\u0688\u06cc \u06a9\u0648\u062a\u0644"
    ],
    "name:pol_x_preferred":[
        "Landi Kotal"
    ],
    "name:rus_x_preferred":[
        "\u041b\u0430\u043d\u0434\u0438-\u041a\u043e\u0442\u0430\u043b"
    ],
    "name:spa_x_preferred":[
        "Landi Kotal"
    ],
    "name:swe_x_preferred":[
        "Landi Kotal"
    ],
    "name:und_x_variant":[
        "Landlandi Kotal"
    ],
    "name:urd_x_preferred":[
        "\u0644\u0646\u0688\u06cc \u06a9\u0648\u062a\u0644"
    ],
    "qs:gn_country":"PK",
    "qs:gn_fcode":"PPL",
    "qs:gn_pop":2223,
    "qs:name":"Landi Kotal",
    "qs:name_adm0":"Pakistan",
    "qs:name_adm1":"Federally Administered Tribal Areas",
    "qs:photos":66,
    "qs:photos_1k":13,
    "qs:photos_9k":1,
    "qs:photos_9r":2,
    "qs:photos_all":66,
    "qs:photos_sr":2,
    "qs:placetype":"Town",
    "qs:pop_sr":"4",
    "qs:woe_adm0":23424922,
    "wof:name":"Landi Kotal",
    "wof:placetype":"locality",
    "wof:population":2223
},
  "geometry": {"coordinates":[71.14667,34.10167],"type":"Point"}
}