{
  "type": "Feature",
  "properties": {
    "gn:admin1_code":"4.0",
    "gn:asciiname":"Mazar Baba Kalim-ullah Shah",
    "gn:country_code":"PK",
    "gn:dem":145,
    "gn:feature_class":"P",
    "gn:feature_code":"PPL",
    "gn:name":"Mazar Baba Kalim-ullah Shah",
    "gn:population":0,
    "gn:timezone":"Asia/Karachi",
    "iso:country":"PK",
    "wof:name":"Mazar Baba Kalim-ullah Shah",
    "wof:placetype":"locality"
},
  "geometry": {"coordinates":[72.68422,29.47643],"type":"Point"}
}