{
  "type": "Feature",
  "properties": {
    "gn:admin1_code":"6.0",
    "gn:asciiname":"Darat",
    "gn:country_code":"PK",
    "gn:dem":415,
    "gn:feature_class":"P",
    "gn:feature_code":"PPL",
    "gn:name":"Darat",
    "gn:population":0,
    "gn:timezone":"Asia/Karachi",
    "iso:country":"PK",
    "wof:name":"Darat",
    "wof:placetype":"locality"
},
  "geometry": {"coordinates":[73.56234000000001,33.12956],"type":"Point"}
}