{
  "type": "Feature",
  "properties": {
    "gn:admin1_code":"4.0",
    "gn:asciiname":"Jhatla",
    "gn:country_code":"PK",
    "gn:dem":581,
    "gn:feature_class":"P",
    "gn:feature_code":"PPL",
    "gn:name":"Jhatla",
    "gn:population":0,
    "gn:timezone":"Asia/Karachi",
    "iso:country":"PK",
    "name:fas_x_preferred":[
        "\u0647\u0627\u062a\u0644\u0647"
    ],
    "name:hin_x_preferred":[
        "\u091c\u091f\u093f\u092f\u093c\u093e\u0932\u093e"
    ],
    "name:urd_x_preferred":[
        "\u062c\u0679\u06cc\u0627\u0644\u06c1"
    ],
    "wof:name":"Jhatla",
    "wof:placetype":"locality"
},
  "geometry": {"coordinates":[72.38363000000003,32.82565],"type":"Point"}
}