{
  "type": "Feature",
  "properties": {
    "gn:admin1_code":"6",
    "gn:asciiname":"Ambriala",
    "gn:country_code":"PK",
    "gn:dem":413,
    "gn:feature_class":"P",
    "gn:feature_code":"PPL",
    "gn:name":"Ambriala",
    "gn:population":0,
    "gn:timezone":"Asia/Karachi",
    "iso:country":"PK",
    "name:und_x_variant":[
        "Ambre\u0101l"
    ],
    "wof:name":"Ambriala",
    "wof:placetype":"locality"
},
  "geometry": {"coordinates":[74.21810000000001,32.91397],"type":"Point"}
}