{
  "type": "Feature",
  "properties": {
    "gn:admin1_code":"2",
    "gn:asciiname":"Loe Aghbarg",
    "gn:country_code":"PK",
    "gn:dem":2424,
    "gn:feature_class":"P",
    "gn:feature_code":"PPL",
    "gn:name":"Loe Aghbarg",
    "gn:population":0,
    "gn:timezone":"Asia/Karachi",
    "iso:country":"PK",
    "name:und_x_variant":[
        "Loe Aghbang",
        "Loe Aghbarg"
    ],
    "wof:name":"Loe Aghbarg",
    "wof:placetype":"locality"
},
  "geometry": {"coordinates":[67.78301,31.106],"type":"Point"}
}