{
  "type": "Feature",
  "properties": {
    "gn:admin1_code":"2.0",
    "gn:asciiname":"Goth Dhani Bukhsh",
    "gn:country_code":"PK",
    "gn:dem":531,
    "gn:feature_class":"P",
    "gn:feature_code":"PPL",
    "gn:name":"Goth Dhani Bukhsh",
    "gn:population":0,
    "gn:timezone":"Asia/Karachi",
    "iso:country":"PK",
    "wof:name":"Goth Dhani Bukhsh",
    "wof:placetype":"locality"
},
  "geometry": {"coordinates":[66.59118000000001,26.34572],"type":"Point"}
}