{
  "type": "Feature",
  "properties": {
    "gn:admin1_code":"5.0",
    "gn:asciiname":"Arif Abasi",
    "gn:country_code":"PK",
    "gn:dem":8,
    "gn:feature_class":"P",
    "gn:feature_code":"PPL",
    "gn:name":"Arif Abasi",
    "gn:population":0,
    "gn:timezone":"Asia/Karachi",
    "iso:country":"PK",
    "name:und_x_variant":[
        "\u0100rif Abb\u0101si"
    ],
    "wof:name":"Arif Abasi",
    "wof:placetype":"locality"
},
  "geometry": {"coordinates":[68.14497,24.38802],"type":"Point"}
}