{
  "type": "Feature",
  "properties": {
    "gn:admin1_code":"4",
    "gn:asciiname":"Ismailwala",
    "gn:country_code":"PK",
    "gn:dem":171,
    "gn:feature_class":"P",
    "gn:feature_code":"PPL",
    "gn:name":"Ismailwala",
    "gn:population":0,
    "gn:timezone":"Asia/Karachi",
    "iso:country":"PK",
    "name:und_x_variant":[
        "Samilw\u0101la"
    ],
    "wof:name":"Ismailwala",
    "wof:placetype":"locality"
},
  "geometry": {"coordinates":[71.08254000000002,31.60608],"type":"Point"}
}