{
  "type": "Feature",
  "properties": {
    "gn:admin1_code":"04",
    "gn:asciiname":"Pirah Fatehal",
    "gn:country_code":"PK",
    "gn:dem":512,
    "gn:feature_class":"P",
    "gn:feature_code":"PPL",
    "gn:name":"Pirah Fatehal",
    "gn:population":0,
    "gn:timezone":"Asia/Karachi",
    "iso:country":"PK",
    "name:und_x_variant":[
        "Pira Fattial",
        "P\u012bra Feteh\u0101l",
        "Pirah Fatehal"
    ],
    "wof:name":"Pirah Fatehal",
    "wof:placetype":"locality"
},
  "geometry": {"coordinates":[72.32449,32.86597],"type":"Point"}
}