{
  "type": "Feature",
  "properties": {
    "gn:admin1_code":"4.0",
    "gn:asciiname":"Chak One Hundred Seventy-one Gugera Branch",
    "gn:country_code":"PK",
    "gn:dem":180,
    "gn:feature_class":"P",
    "gn:feature_code":"PPL",
    "gn:name":"Chak One Hundred Seventy-one Gugera Branch",
    "gn:population":0,
    "gn:timezone":"Asia/Karachi",
    "iso:country":"PK",
    "name:und_x_variant":[
        "Bamboh",
        "Bamboo"
    ],
    "wof:name":"Chak One Hundred Seventy-one Gugera Branch",
    "wof:placetype":"locality"
},
  "geometry": {"coordinates":[73.16410999999999,31.14294000000001],"type":"Point"}
}