{
  "type": "Feature",
  "properties": {
    "gn:admin1_code":"04",
    "gn:asciiname":"Shakrila Sharif",
    "gn:country_code":"PK",
    "gn:dem":248,
    "gn:feature_class":"P",
    "gn:feature_code":"PPL",
    "gn:name":"Shakrila Sharif",
    "gn:population":0,
    "gn:timezone":"Asia/Karachi",
    "iso:country":"PK",
    "name:und_x_variant":[
        "Shakrila"
    ],
    "wof:name":"Shakrila Sharif",
    "wof:placetype":"locality"
},
  "geometry": {"coordinates":[73.83722,32.98316],"type":"Point"}
}