{
  "type": "Feature",
  "properties": {
    "gn:admin1_code":"7.0",
    "gn:asciiname":"Kachori Haroi",
    "gn:country_code":"PK",
    "gn:dem":3036,
    "gn:feature_class":"P",
    "gn:feature_code":"PPL",
    "gn:name":"Kachori Haroi",
    "gn:population":0,
    "gn:timezone":"Asia/Karachi",
    "iso:country":"PK",
    "wof:name":"Kachori Haroi",
    "wof:placetype":"locality"
},
  "geometry": {"coordinates":[73.72075,35.32593],"type":"Point"}
}