{
  "type": "Feature",
  "properties": {
    "gn:admin1_code":"4.0",
    "gn:asciiname":"Gudduwala",
    "gn:country_code":"PK",
    "gn:dem":163,
    "gn:feature_class":"P",
    "gn:feature_code":"PPL",
    "gn:name":"Gudduwala",
    "gn:population":0,
    "gn:timezone":"Asia/Karachi",
    "iso:country":"PK",
    "name:und_x_variant":[
        "Gudd\u016bw\u0101la"
    ],
    "wof:name":"Gudduwala",
    "wof:placetype":"locality"
},
  "geometry": {"coordinates":[71.76841999999998,31.34012],"type":"Point"}
}