{
  "type": "Feature",
  "properties": {
    "gn:admin1_code":"3.0",
    "gn:asciiname":"Abdul Rahman",
    "gn:country_code":"PK",
    "gn:dem":394,
    "gn:feature_class":"P",
    "gn:feature_code":"PPL",
    "gn:name":"Abdul Rahman",
    "gn:population":0,
    "gn:timezone":"Asia/Karachi",
    "iso:country":"PK",
    "name:und_x_variant":[
        "Abdur Rahm\u0101n",
        "Abdul Rahman"
    ],
    "wof:name":"Abdul Rahman",
    "wof:placetype":"locality"
},
  "geometry": {"coordinates":[70.55798,32.98303],"type":"Point"}
}