{
  "type": "Feature",
  "properties": {
    "gn:admin1_code":"2.0",
    "gn:asciiname":"Trangru",
    "gn:country_code":"PK",
    "gn:dem":978,
    "gn:feature_class":"P",
    "gn:feature_code":"PPL",
    "gn:name":"Trangru",
    "gn:population":0,
    "gn:timezone":"Asia/Karachi",
    "iso:country":"PK",
    "wof:name":"Trangru",
    "wof:placetype":"locality"
},
  "geometry": {"coordinates":[66.81956,27.56165],"type":"Point"}
}