{
  "type": "Feature",
  "properties": {
    "gn:admin1_code":"5",
    "gn:asciiname":"Gapang",
    "gn:country_code":"PK",
    "gn:dem":59,
    "gn:feature_class":"P",
    "gn:feature_code":"PPL",
    "gn:name":"Gapang",
    "gn:population":0,
    "gn:timezone":"Asia/Karachi",
    "iso:country":"PK",
    "name:und_x_variant":[
        "Gagahg"
    ],
    "wof:name":"Gapang",
    "wof:placetype":"locality"
},
  "geometry": {"coordinates":[68.75293000000001,27.48887],"type":"Point"}
}