{
  "type": "Feature",
  "properties": {
    "gn:admin1_code":"04",
    "gn:asciiname":"Shaikhpur",
    "gn:cc2":"PK",
    "gn:country_code":"PK",
    "gn:dem":117,
    "gn:feature_class":"P",
    "gn:feature_code":"PPL",
    "gn:name":"Shaikhpur",
    "gn:population":0,
    "gn:timezone":"Asia/Karachi",
    "iso:country":"PK",
    "name:und_x_variant":[
        "Sheikhpur",
        "Shaikhpur"
    ],
    "wof:name":"Shaikhpur",
    "wof:placetype":"locality"
},
  "geometry": {"coordinates":[71.53333000000001,29.98333],"type":"Point"}
}