{
  "type": "Feature",
  "properties": {
    "gn:admin1_code":"4",
    "gn:asciiname":"Mad Fazal Khan Gabol",
    "gn:country_code":"PK",
    "gn:dem":101,
    "gn:feature_class":"P",
    "gn:feature_code":"PPL",
    "gn:name":"Mad Fazal Khan Gabol",
    "gn:population":0,
    "gn:timezone":"Asia/Karachi",
    "iso:country":"PK",
    "wof:name":"Mad Fazal Khan Gabol",
    "wof:placetype":"locality"
},
  "geometry": {"coordinates":[70.27198,29.21195],"type":"Point"}
}