{
  "type": "Feature",
  "properties": {
    "gn:admin1_code":"4.0",
    "gn:asciiname":"Falakwali Bhaini",
    "gn:country_code":"PK",
    "gn:dem":181,
    "gn:feature_class":"P",
    "gn:feature_code":"PPL",
    "gn:name":"Falakwali Bhaini",
    "gn:population":0,
    "gn:timezone":"Asia/Karachi",
    "iso:country":"PK",
    "wof:name":"Falakwali Bhaini",
    "wof:placetype":"locality"
},
  "geometry": {"coordinates":[74.06983000000002,30.58467000000001],"type":"Point"}
}