{
  "type": "Feature",
  "properties": {
    "gn:admin1_code":"3.0",
    "gn:asciiname":"Chaniar",
    "gn:country_code":"PK",
    "gn:dem":1380,
    "gn:feature_class":"P",
    "gn:feature_code":"PPL",
    "gn:name":"Chaniar",
    "gn:population":0,
    "gn:timezone":"Asia/Karachi",
    "iso:country":"PK",
    "name:eng_x_preferred":[
        "Chini\u0101r"
    ],
    "wof:name":"Chaniar",
    "wof:placetype":"locality"
},
  "geometry": {"coordinates":[73.32668000000002,33.94591],"type":"Point"}
}