{
  "type": "Feature",
  "properties": {
    "gn:admin1_code":"4",
    "gn:asciiname":"Basti Tarkhanwala",
    "gn:country_code":"PK",
    "gn:dem":133,
    "gn:feature_class":"P",
    "gn:feature_code":"PPL",
    "gn:name":"Basti Tarkhanwala",
    "gn:population":0,
    "gn:timezone":"Asia/Karachi",
    "iso:country":"PK",
    "name:und_x_variant":[
        "Basti Thakr\u0101l"
    ],
    "wof:name":"Basti Tarkhanwala",
    "wof:placetype":"locality"
},
  "geometry": {"coordinates":[71.76823,30.4499],"type":"Point"}
}