{
  "type": "Feature",
  "properties": {
    "gn:admin1_code":"3.0",
    "gn:asciiname":"Dam Colony",
    "gn:country_code":"PK",
    "gn:dem":566,
    "gn:feature_class":"P",
    "gn:feature_code":"PPL",
    "gn:name":"Dam Colony",
    "gn:population":0,
    "gn:timezone":"Asia/Karachi",
    "iso:country":"PK",
    "wof:name":"Dam Colony",
    "wof:placetype":"locality"
},
  "geometry": {"coordinates":[71.4126,33.58416],"type":"Point"}
}