{
  "type": "Feature",
  "properties": {
    "gn:admin1_code":"4.0",
    "gn:asciiname":"Thekariyan Khurd",
    "gn:country_code":"PK",
    "gn:dem":277,
    "gn:feature_class":"P",
    "gn:feature_code":"PPL",
    "gn:name":"Thekariyan Khurd",
    "gn:population":0,
    "gn:timezone":"Asia/Karachi",
    "iso:country":"PK",
    "wof:name":"Thekariyan Khurd",
    "wof:placetype":"locality"
},
  "geometry": {"coordinates":[75.06544,32.3254],"type":"Point"}
}