{
  "type": "Feature",
  "properties": {
    "gn:admin1_code":"4",
    "gn:asciiname":"Chhani Mahram",
    "gn:country_code":"PK",
    "gn:dem":211,
    "gn:feature_class":"P",
    "gn:feature_code":"PPL",
    "gn:name":"Chhani Mahram",
    "gn:population":0,
    "gn:timezone":"Asia/Karachi",
    "iso:country":"PK",
    "name:und_x_variant":[
        "Chhanni Mehr\u0101n",
        "Thatta Chen",
        "Chhani Mahram"
    ],
    "wof:name":"Chhani Mahram",
    "wof:placetype":"locality"
},
  "geometry": {"coordinates":[73.76534000000002,32.39656],"type":"Point"}
}