{
  "type": "Feature",
  "properties": {
    "gn:admin1_code":"4",
    "gn:asciiname":"Chak One Hundred Thirty-three",
    "gn:country_code":"PK",
    "gn:dem":150,
    "gn:feature_class":"P",
    "gn:feature_code":"PPL",
    "gn:name":"Chak One Hundred Thirty-three",
    "gn:population":0,
    "gn:timezone":"Asia/Karachi",
    "iso:country":"PK",
    "name:und_x_variant":[
        "Semm\u012bpur",
        "Chak One Hundred Thirty-three"
    ],
    "wof:name":"Chak One Hundred Thirty-three",
    "wof:placetype":"locality"
},
  "geometry": {"coordinates":[71.08839,30.95897],"type":"Point"}
}