{
  "type": "Feature",
  "properties": {
    "gn:admin1_code":"4.0",
    "gn:asciiname":"Gidpur",
    "gn:country_code":"PK",
    "gn:dem":423,
    "gn:feature_class":"P",
    "gn:feature_code":"PPL",
    "gn:name":"Gidpur",
    "gn:population":0,
    "gn:timezone":"Asia/Karachi",
    "iso:country":"PK",
    "wof:name":"Gidpur",
    "wof:placetype":"locality"
},
  "geometry": {"coordinates":[73.03301,33.44552],"type":"Point"}
}