{
  "type": "Feature",
  "properties": {
    "gn:admin1_code":"4.0",
    "gn:asciiname":"Nathuwala",
    "gn:country_code":"PK",
    "gn:dem":605,
    "gn:feature_class":"P",
    "gn:feature_code":"PPL",
    "gn:name":"Nathuwala",
    "gn:population":0,
    "gn:timezone":"Asia/Karachi",
    "iso:country":"PK",
    "name:und_x_variant":[
        "Nat\u0101l\u0101w\u0101la Kah\u0101r"
    ],
    "wof:name":"Nathuwala",
    "wof:placetype":"locality"
},
  "geometry": {"coordinates":[72.60998000000002,32.81361],"type":"Point"}
}