{
  "type": "Feature",
  "properties": {
    "gn:admin1_code":"4.0",
    "gn:asciiname":"Kohra",
    "gn:country_code":"PK",
    "gn:dem":346,
    "gn:feature_class":"P",
    "gn:feature_code":"PPL",
    "gn:name":"Kohra",
    "gn:population":0,
    "gn:timezone":"Asia/Karachi",
    "iso:country":"PK",
    "wof:name":"Kohra",
    "wof:placetype":"locality"
},
  "geometry": {"coordinates":[72.02055,33.34491],"type":"Point"}
}