{
  "type": "Feature",
  "properties": {
    "gn:admin1_code":"5",
    "gn:asciiname":"Goth Mangna",
    "gn:country_code":"PK",
    "gn:dem":58,
    "gn:feature_class":"P",
    "gn:feature_code":"PPL",
    "gn:name":"Goth Mangna",
    "gn:population":0,
    "gn:timezone":"Asia/Karachi",
    "iso:country":"PK",
    "name:und_x_variant":[
        "Mangna"
    ],
    "wof:name":"Goth Mangna",
    "wof:placetype":"locality"
},
  "geometry": {"coordinates":[68.33029999999999,27.65344],"type":"Point"}
}