{
  "type": "Feature",
  "properties": {
    "gn:admin1_code":"03",
    "gn:asciiname":"Salim Khan",
    "gn:country_code":"PK",
    "gn:dem":349,
    "gn:feature_class":"P",
    "gn:feature_code":"PPL",
    "gn:name":"Salim Khan",
    "gn:population":0,
    "gn:timezone":"Asia/Karachi",
    "iso:country":"PK",
    "name:eng_x_preferred":[
        "Sal\u012bm Kh\u0101n"
    ],
    "wof:name":"Salim Khan",
    "wof:placetype":"locality"
},
  "geometry": {"coordinates":[72.46120000000001,34.16576],"type":"Point"}
}