{
  "type": "Feature",
  "properties": {
    "gn:admin1_code":"03",
    "gn:asciiname":"Salim Khan",
    "gn:country_code":"PK",
    "gn:dem":349,
    "gn:feature_class":"P",
    "gn:feature_code":"PPL",
    "gn:name":"Salim Khan",
    "gn:population":0,
    "gn:timezone":"Asia/Karachi",
    "iso:country":"PK",
    "name:ara_x_preferred":[
        "\u0633\u0644\u064a\u0645 \u062e\u0627\u0646"
    ],
    "name:ben_x_preferred":[
        "\u09b8\u09c7\u09b2\u09bf\u09ae \u0996\u09be\u09a8"
    ],
    "name:eng_x_preferred":[
        "Sal\u012bm Kh\u0101n"
    ],
    "name:fas_x_preferred":[
        "\u0633\u0644\u06cc\u0645 \u062e\u0627\u0646"
    ],
    "name:hin_x_preferred":[
        "\u0938\u0932\u0940\u092e \u0916\u093c\u093e\u0928"
    ],
    "name:mai_x_preferred":[
        "\u0938\u0932\u0940\u092e \u0916\u093e\u0928"
    ],
    "name:urd_x_preferred":[
        "\u0633\u0644\u06cc\u0645 \u062e\u0627\u0646"
    ],
    "wof:name":"Salim Khan",
    "wof:placetype":"locality"
},
  "geometry": {"coordinates":[72.46120000000001,34.16576],"type":"Point"}
}