{
  "type": "Feature",
  "properties": {
    "gn:admin1_code":"3.0",
    "gn:asciiname":"Kotka Khali Khel",
    "gn:country_code":"PK",
    "gn:dem":283,
    "gn:feature_class":"P",
    "gn:feature_code":"PPL",
    "gn:name":"Kotka Khali Khel",
    "gn:population":0,
    "gn:timezone":"Asia/Karachi",
    "iso:country":"PK",
    "name:und_x_variant":[
        "Naurang",
        "Kotka Khall Khel",
        "Kotka Khali Khel"
    ],
    "wof:name":"Kotka Khali Khel",
    "wof:placetype":"locality"
},
  "geometry": {"coordinates":[70.75323,32.73856],"type":"Point"}
}