{
  "type": "Feature",
  "properties": {
    "gn:admin1_code":"3.0",
    "gn:asciiname":"Shaingare",
    "gn:country_code":"PK",
    "gn:dem":403,
    "gn:feature_class":"P",
    "gn:feature_code":"PPL",
    "gn:name":"Shaingare",
    "gn:population":0,
    "gn:timezone":"Asia/Karachi",
    "iso:country":"PK",
    "name:eng_x_preferred":[
        "Shngari"
    ],
    "name:und_x_variant":[
        "Shingari",
        "Shaingare"
    ],
    "wof:name":"Shaingare",
    "wof:placetype":"locality"
},
  "geometry": {"coordinates":[71.88311999999998,34.40957],"type":"Point"}
}