{
  "type": "Feature",
  "properties": {
    "gn:admin1_code":"4",
    "gn:asciiname":"Basti Halimpur",
    "gn:country_code":"PK",
    "gn:dem":103,
    "gn:feature_class":"P",
    "gn:feature_code":"PPL",
    "gn:name":"Basti Halimpur",
    "gn:population":0,
    "gn:timezone":"Asia/Karachi",
    "iso:country":"PK",
    "name:und_x_variant":[
        "Hal\u012bmpur"
    ],
    "wof:name":"Basti Halimpur",
    "wof:placetype":"locality"
},
  "geometry": {"coordinates":[71.09328000000002,29.29287],"type":"Point"}
}