{
  "type": "Feature",
  "properties": {
    "gn:admin1_code":"3.0",
    "gn:asciiname":"Masti Khel",
    "gn:country_code":"PK",
    "gn:dem":415,
    "gn:feature_class":"P",
    "gn:feature_code":"PPL",
    "gn:name":"Masti Khel",
    "gn:population":0,
    "gn:timezone":"Asia/Karachi",
    "iso:country":"PK",
    "name:und_x_variant":[
        "Mesti Khel"
    ],
    "wof:name":"Masti Khel",
    "wof:placetype":"locality"
},
  "geometry": {"coordinates":[70.5433,33.00891],"type":"Point"}
}