{
  "type": "Feature",
  "properties": {
    "gn:admin1_code":"3.0",
    "gn:asciiname":"Kit",
    "gn:country_code":"PK",
    "gn:dem":2057,
    "gn:feature_class":"P",
    "gn:feature_code":"PPL",
    "gn:name":"Kit",
    "gn:population":0,
    "gn:timezone":"Asia/Karachi",
    "iso:country":"PK",
    "wof:name":"Kit",
    "wof:placetype":"locality"
},
  "geometry": {"coordinates":[73.0363,35.09607],"type":"Point"}
}