{
  "type": "Feature",
  "properties": {
    "gn:admin1_code":"4",
    "gn:asciiname":"Chak Forty-four Eastern Bar",
    "gn:country_code":"PK",
    "gn:dem":156,
    "gn:feature_class":"P",
    "gn:feature_code":"PPL",
    "gn:name":"Chak Forty-four Eastern Bar",
    "gn:population":0,
    "gn:timezone":"Asia/Karachi",
    "iso:country":"PK",
    "name:und_x_variant":[
        "Chak Forty-four"
    ],
    "wof:name":"Chak Forty-four Eastern Bar",
    "wof:placetype":"locality"
},
  "geometry": {"coordinates":[72.97346999999998,30.35908],"type":"Point"}
}