{
  "type": "Feature",
  "properties": {
    "gn:admin1_code":"4",
    "gn:asciiname":"Kaluwala",
    "gn:country_code":"PK",
    "gn:dem":156,
    "gn:feature_class":"P",
    "gn:feature_code":"PPL",
    "gn:name":"Kaluwala",
    "gn:population":0,
    "gn:timezone":"Asia/Karachi",
    "iso:country":"PK",
    "name:und_x_variant":[
        "K\u0101l\u016bw\u0101la"
    ],
    "wof:name":"Kaluwala",
    "wof:placetype":"locality"
},
  "geometry": {"coordinates":[71.43720999999999,31.26044000000001],"type":"Point"}
}