{
  "type": "Feature",
  "properties": {
    "gn:admin1_code":"5",
    "gn:asciiname":"Allah Jurio Lashari",
    "gn:country_code":"PK",
    "gn:dem":42,
    "gn:feature_class":"P",
    "gn:feature_code":"PPL",
    "gn:name":"Allah Jurio Lashari",
    "gn:population":0,
    "gn:timezone":"Asia/Karachi",
    "iso:country":"PK",
    "name:und_x_variant":[
        "All\u0101h Juria Lash\u0101ri"
    ],
    "wof:name":"Allah Jurio Lashari",
    "wof:placetype":"locality"
},
  "geometry": {"coordinates":[68.06730999999999,26.69579],"type":"Point"}
}