{
  "type": "Feature",
  "properties": {
    "gn:admin1_code":"3.0",
    "gn:asciiname":"Mohalla Dangdang",
    "gn:country_code":"PK",
    "gn:dem":313,
    "gn:feature_class":"P",
    "gn:feature_code":"PPL",
    "gn:name":"Mohalla Dangdang",
    "gn:population":0,
    "gn:timezone":"Asia/Karachi",
    "iso:country":"PK",
    "wof:name":"Mohalla Dangdang",
    "wof:placetype":"locality"
},
  "geometry": {"coordinates":[72.09118000000002,34.03357],"type":"Point"}
}