{
  "type": "Feature",
  "properties": {
    "gn:admin1_code":"1.0",
    "gn:asciiname":"Piran",
    "gn:country_code":"PK",
    "gn:dem":1056,
    "gn:feature_class":"P",
    "gn:feature_code":"PPL",
    "gn:name":"Piran",
    "gn:population":0,
    "gn:timezone":"Asia/Karachi",
    "iso:country":"PK",
    "wof:name":"Piran",
    "wof:placetype":"locality"
},
  "geometry": {"coordinates":[71.59439,34.58226],"type":"Point"}
}