{
  "type": "Feature",
  "properties": {
    "gn:admin1_code":"5.0",
    "gn:asciiname":"Goth Firoz Khan Chairman",
    "gn:country_code":"PK",
    "gn:dem":10,
    "gn:feature_class":"P",
    "gn:feature_code":"PPL",
    "gn:name":"Goth Firoz Khan Chairman",
    "gn:population":0,
    "gn:timezone":"Asia/Karachi",
    "iso:country":"PK",
    "wof:name":"Goth Firoz Khan Chairman",
    "wof:placetype":"locality"
},
  "geometry": {"coordinates":[67.87871,24.56447],"type":"Point"}
}