{
  "type": "Feature",
  "properties": {
    "gn:admin1_code":"2.0",
    "gn:asciiname":"Kharaba",
    "gn:country_code":"PK",
    "gn:dem":1901,
    "gn:feature_class":"P",
    "gn:feature_code":"PPL",
    "gn:name":"Kharaba",
    "gn:population":0,
    "gn:timezone":"Asia/Karachi",
    "iso:country":"PK",
    "name:ara_x_preferred":[
        "\u062e\u0631\u0628\u0627"
    ],
    "name:pol_x_preferred":[
        "Charaba"
    ],
    "name:ukr_x_preferred":[
        "\u0425\u0430\u0440\u0430\u0431\u0430"
    ],
    "name:vie_x_preferred":[
        "Kharaba"
    ],
    "wof:name":"Kharaba",
    "wof:placetype":"locality"
},
  "geometry": {"coordinates":[67.86306,30.76639],"type":"Point"}
}