{
  "type": "Feature",
  "properties": {
    "gn:admin1_code":"4",
    "gn:asciiname":"Motuwala Khu",
    "gn:country_code":"PK",
    "gn:dem":97,
    "gn:feature_class":"P",
    "gn:feature_code":"PPL",
    "gn:name":"Motuwala Khu",
    "gn:population":0,
    "gn:timezone":"Asia/Karachi",
    "iso:country":"PK",
    "name:und_x_variant":[
        "Mot\u016bw\u0101la Khu",
        "Motuwala Khu",
        "Masuw\u0101la",
        "Masuw\u0101la Khu"
    ],
    "wof:name":"Motuwala Khu",
    "wof:placetype":"locality"
},
  "geometry": {"coordinates":[70.36578,29.20873],"type":"Point"}
}