{
  "type": "Feature",
  "properties": {
    "gn:admin1_code":"5.0",
    "gn:asciiname":"Goth Murad Khoso",
    "gn:country_code":"PK",
    "gn:dem":16,
    "gn:feature_class":"P",
    "gn:feature_code":"PPL",
    "gn:name":"Goth Murad Khoso",
    "gn:population":0,
    "gn:timezone":"Asia/Karachi",
    "iso:country":"PK",
    "name:und_x_variant":[
        "Goth Mur\u0101d Khosa"
    ],
    "wof:name":"Goth Murad Khoso",
    "wof:placetype":"locality"
},
  "geometry": {"coordinates":[68.41585000000001,24.9427],"type":"Point"}
}