{
  "type": "Feature",
  "properties": {
    "gn:admin1_code":"4.0",
    "gn:asciiname":"Dhok Sarobah",
    "gn:country_code":"PK",
    "gn:dem":449,
    "gn:feature_class":"P",
    "gn:feature_code":"PPL",
    "gn:name":"Dhok Sarobah",
    "gn:population":0,
    "gn:timezone":"Asia/Karachi",
    "iso:country":"PK",
    "wof:name":"Dhok Sarobah",
    "wof:placetype":"locality"
},
  "geometry": {"coordinates":[72.35661999999998,33.61036],"type":"Point"}
}