{
  "type": "Feature",
  "properties": {
    "gn:admin1_code":"5.0",
    "gn:asciiname":"Haji Ali Sumro",
    "gn:country_code":"PK",
    "gn:dem":13,
    "gn:feature_class":"P",
    "gn:feature_code":"PPL",
    "gn:name":"Haji Ali Sumro",
    "gn:population":0,
    "gn:timezone":"Asia/Karachi",
    "iso:country":"PK",
    "wof:name":"Haji Ali Sumro",
    "wof:placetype":"locality"
},
  "geometry": {"coordinates":[68.20075,24.81577],"type":"Point"}
}