{
  "type": "Feature",
  "properties": {
    "gn:admin1_code":"03",
    "gn:asciiname":"Rustam",
    "gn:country_code":"PK",
    "gn:dem":383,
    "gn:feature_class":"P",
    "gn:feature_code":"PPL",
    "gn:name":"Rustam",
    "gn:population":0,
    "gn:timezone":"Asia/Karachi",
    "iso:country":"PK",
    "name:eng_x_preferred":[
        "Rustam"
    ],
    "name:urd_x_preferred":[
        "\u0631\u0633\u062a\u0645"
    ],
    "wof:name":"Rustam",
    "wof:placetype":"locality"
},
  "geometry": {"coordinates":[72.27891,34.34639],"type":"Point"}
}