{
  "type": "Feature",
  "properties": {
    "gn:admin1_code":"2.0",
    "gn:asciiname":"Arohi",
    "gn:country_code":"PK",
    "gn:dem":1258,
    "gn:feature_class":"P",
    "gn:feature_code":"PPL",
    "gn:name":"Arohi",
    "gn:population":0,
    "gn:timezone":"Asia/Karachi",
    "iso:country":"PK",
    "wof:name":"Arohi",
    "wof:placetype":"locality"
},
  "geometry": {"coordinates":[66.25898000000001,27.22567],"type":"Point"}
}