{
  "type": "Feature",
  "properties": {
    "gn:admin1_code":"3.0",
    "gn:asciiname":"Chargali",
    "gn:country_code":"PK",
    "gn:dem":1777,
    "gn:feature_class":"P",
    "gn:feature_code":"PPL",
    "gn:name":"Chargali",
    "gn:population":0,
    "gn:timezone":"Asia/Karachi",
    "iso:country":"PK",
    "wof:name":"Chargali",
    "wof:placetype":"locality"
},
  "geometry": {"coordinates":[71.70645,35.35897999999999],"type":"Point"}
}