{
  "type": "Feature",
  "properties": {
    "gn:admin1_code":"1.0",
    "gn:asciiname":"Razam Dherai",
    "gn:country_code":"PK",
    "gn:dem":492,
    "gn:feature_class":"P",
    "gn:feature_code":"PPL",
    "gn:name":"R\u0101zam Dherai",
    "gn:population":0,
    "gn:timezone":"Asia/Karachi",
    "iso:country":"PK",
    "wof:name":"Razam Dherai",
    "wof:placetype":"locality"
},
  "geometry": {"coordinates":[71.66139,34.42556],"type":"Point"}
}