{
  "type": "Feature",
  "properties": {
    "gn:admin1_code":"4",
    "gn:asciiname":"Nazra Gondalwala",
    "gn:country_code":"PK",
    "gn:dem":169,
    "gn:feature_class":"P",
    "gn:feature_code":"PPL",
    "gn:name":"Nazra Gondalwala",
    "gn:population":0,
    "gn:timezone":"Asia/Karachi",
    "iso:country":"PK",
    "name:und_x_variant":[
        "Dera Gondl\u0101n"
    ],
    "wof:name":"Nazra Gondalwala",
    "wof:placetype":"locality"
},
  "geometry": {"coordinates":[71.46233000000002,31.46357],"type":"Point"}
}