{
  "type": "Feature",
  "properties": {
    "gn:admin1_code":"3",
    "gn:asciiname":"Markhano",
    "gn:country_code":"PK",
    "gn:dem":1526,
    "gn:feature_class":"P",
    "gn:feature_code":"PPL",
    "gn:name":"Markhano",
    "gn:population":0,
    "gn:timezone":"Asia/Karachi",
    "iso:country":"PK",
    "name:und_x_variant":[
        "M\u0101rkh\u0101ron",
        "Markhano"
    ],
    "wof:name":"Markhano",
    "wof:placetype":"locality"
},
  "geometry": {"coordinates":[72.12182,34.9481],"type":"Point"}
}