{
  "type": "Feature",
  "properties": {
    "gn:admin1_code":"2.0",
    "gn:asciiname":"Lal Bakhsh",
    "gn:country_code":"PK",
    "gn:dem":443,
    "gn:feature_class":"P",
    "gn:feature_code":"PPL",
    "gn:name":"Lal Bakhsh",
    "gn:population":0,
    "gn:timezone":"Asia/Karachi",
    "iso:country":"PK",
    "name:por_x_preferred":[
        "Lal Bakhsh"
    ],
    "wof:name":"Lal Bakhsh",
    "wof:placetype":"locality"
},
  "geometry": {"coordinates":[65.38596,26.24127],"type":"Point"}
}