{
  "type": "Feature",
  "properties": {
    "gn:admin1_code":"4.0",
    "gn:asciiname":"Dhat Bat",
    "gn:country_code":"PK",
    "gn:dem":532,
    "gn:feature_class":"P",
    "gn:feature_code":"PPL",
    "gn:name":"Dhat Bat",
    "gn:population":0,
    "gn:timezone":"Asia/Karachi",
    "iso:country":"PK",
    "name:und_x_variant":[
        "D\u0101ta Bhat"
    ],
    "wof:name":"Dhat Bat",
    "wof:placetype":"locality"
},
  "geometry": {"coordinates":[73.10499,33.25432],"type":"Point"}
}