{
  "type": "Feature",
  "properties": {
    "gn:admin1_code":"01",
    "gn:asciiname":"Bado",
    "gn:country_code":"PK",
    "gn:dem":1126,
    "gn:feature_class":"P",
    "gn:feature_code":"PPL",
    "gn:name":"Bado",
    "gn:population":0,
    "gn:timezone":"Asia/Karachi",
    "iso:country":"PK",
    "name:eng_x_preferred":[
        "Bado"
    ],
    "name:und_x_variant":[
        "Bado Barang"
    ],
    "wof:name":"Bado",
    "wof:placetype":"locality"
},
  "geometry": {"coordinates":[71.62878000000001,34.71632],"type":"Point"}
}