{
  "type": "Feature",
  "properties": {
    "gn:admin1_code":"4.0",
    "gn:asciiname":"Khano Harni",
    "gn:country_code":"PK",
    "gn:dem":208,
    "gn:feature_class":"P",
    "gn:feature_code":"PPL",
    "gn:name":"Khano Harni",
    "gn:population":0,
    "gn:timezone":"Asia/Karachi",
    "iso:country":"PK",
    "name:und_x_variant":[
        "Khano Harne",
        "Khano Harni"
    ],
    "wof:name":"Khano Harni",
    "wof:placetype":"locality"
},
  "geometry": {"coordinates":[74.41278,31.31815],"type":"Point"}
}