{
  "type": "Feature",
  "properties": {
    "gn:admin1_code":"3.0",
    "gn:asciiname":"Didiali",
    "gn:country_code":"PK",
    "gn:dem":933,
    "gn:feature_class":"P",
    "gn:feature_code":"PPL",
    "gn:name":"Didiali",
    "gn:population":0,
    "gn:timezone":"Asia/Karachi",
    "iso:country":"PK",
    "wof:name":"Didiali",
    "wof:placetype":"locality"
},
  "geometry": {"coordinates":[73.05126,34.38124000000001],"type":"Point"}
}