{
  "type": "Feature",
  "properties": {
    "gn:admin1_code":"2.0",
    "gn:asciiname":"Goth Ali Muhammad",
    "gn:country_code":"PK",
    "gn:dem":24,
    "gn:feature_class":"P",
    "gn:feature_code":"PPL",
    "gn:name":"Goth Ali Muhammad",
    "gn:population":0,
    "gn:timezone":"Asia/Karachi",
    "iso:country":"PK",
    "name:eng_x_preferred":[
        "Goth Ay\u016bb"
    ],
    "wof:name":"Goth Ali Muhammad",
    "wof:placetype":"locality"
},
  "geometry": {"coordinates":[66.60172,25.71462],"type":"Point"}
}