{
  "type": "Feature",
  "properties": {
    "gn:admin1_code":"2.0",
    "gn:asciiname":"Barat Khel",
    "gn:country_code":"PK",
    "gn:dem":1629,
    "gn:feature_class":"P",
    "gn:feature_code":"PPL",
    "gn:name":"Barat Khel",
    "gn:population":0,
    "gn:timezone":"Asia/Karachi",
    "iso:country":"PK",
    "name:und_x_variant":[
        "Baratkhel",
        "Barat Khel Kili",
        "Barat Khel"
    ],
    "wof:name":"Barat Khel",
    "wof:placetype":"locality"
},
  "geometry": {"coordinates":[68.81815999999999,30.63455],"type":"Point"}
}