{
  "type": "Feature",
  "properties": {
    "gn:admin1_code":"5.0",
    "gn:asciiname":"Goth Isa",
    "gn:country_code":"PK",
    "gn:dem":103,
    "gn:feature_class":"P",
    "gn:feature_code":"PPL",
    "gn:name":"Goth Isa",
    "gn:population":0,
    "gn:timezone":"Asia/Karachi",
    "iso:country":"PK",
    "name:und_x_variant":[
        "Goth \u012assa"
    ],
    "wof:name":"Goth Isa",
    "wof:placetype":"locality"
},
  "geometry": {"coordinates":[67.34695000000001,25.03034],"type":"Point"}
}