{
  "type": "Feature",
  "properties": {
    "gn:admin1_code":"2.0",
    "gn:asciiname":"Sode Kili",
    "gn:country_code":"PK",
    "gn:dem":1575,
    "gn:feature_class":"P",
    "gn:feature_code":"PPL",
    "gn:name":"Sode Kili",
    "gn:population":0,
    "gn:timezone":"Asia/Karachi",
    "iso:country":"PK",
    "wof:name":"Sode Kili",
    "wof:placetype":"locality"
},
  "geometry": {"coordinates":[69.74630999999999,31.69148],"type":"Point"}
}