{
  "type": "Feature",
  "properties": {
    "gn:admin1_code":"2.0",
    "gn:asciiname":"Palwan Mena",
    "gn:country_code":"PK",
    "gn:dem":600,
    "gn:feature_class":"P",
    "gn:feature_code":"PPL",
    "gn:name":"Palwan Mena",
    "gn:population":0,
    "gn:timezone":"Asia/Karachi",
    "iso:country":"PK",
    "name:und_x_variant":[
        "Plaw\u0101n"
    ],
    "wof:name":"Palwan Mena",
    "wof:placetype":"locality"
},
  "geometry": {"coordinates":[70.20376,31.09473],"type":"Point"}
}