{
  "type": "Feature",
  "properties": {
    "gn:admin1_code":"3",
    "gn:asciiname":"Ahl",
    "gn:country_code":"PK",
    "gn:dem":1833,
    "gn:feature_class":"P",
    "gn:feature_code":"PPL",
    "gn:name":"Ahl",
    "gn:population":0,
    "gn:timezone":"Asia/Karachi",
    "iso:country":"PK",
    "wof:name":"Ahl",
    "wof:placetype":"locality"
},
  "geometry": {"coordinates":[73.20928000000001,34.61709],"type":"Point"}
}