{
  "type": "Feature",
  "properties": {
    "gn:admin1_code":"4.0",
    "gn:asciiname":"Chak Five Hundred Thirty-three Thal Development Authority",
    "gn:country_code":"PK",
    "gn:dem":142,
    "gn:feature_class":"P",
    "gn:feature_code":"PPL",
    "gn:name":"Chak Five Hundred Thirty-three Thal Development Authority",
    "gn:population":0,
    "gn:timezone":"Asia/Karachi",
    "iso:country":"PK",
    "name:und_x_variant":[
        "Chak Five Hundred Thirty-Three TDA"
    ],
    "wof:name":"Chak Five Hundred Thirty-three Thal Development Authority",
    "wof:placetype":"locality"
},
  "geometry": {"coordinates":[71.20805,30.74173],"type":"Point"}
}