{
  "type": "Feature",
  "properties": {
    "gn:admin1_code":"4",
    "gn:asciiname":"Chak Eleven SP",
    "gn:country_code":"PK",
    "gn:dem":171,
    "gn:feature_class":"P",
    "gn:feature_code":"PPL",
    "gn:name":"Chak Eleven SP",
    "gn:population":0,
    "gn:timezone":"Asia/Karachi",
    "iso:country":"PK",
    "name:und_x_variant":[
        "Khotew\u0101la",
        "K\u0101lew\u0101la"
    ],
    "wof:name":"Chak Eleven SP",
    "wof:placetype":"locality"
},
  "geometry": {"coordinates":[73.47544000000001,30.41696],"type":"Point"}
}