{
  "type": "Feature",
  "properties": {
    "gn:admin1_code":"5.0",
    "gn:asciiname":"Haji Dost Muhammad Bhatti",
    "gn:country_code":"PK",
    "gn:dem":50,
    "gn:feature_class":"P",
    "gn:feature_code":"PPL",
    "gn:name":"Haji Dost Muhammad Bhatti",
    "gn:population":0,
    "gn:timezone":"Asia/Karachi",
    "iso:country":"PK",
    "wof:name":"Haji Dost Muhammad Bhatti",
    "wof:placetype":"locality"
},
  "geometry": {"coordinates":[68.06265,27.86331],"type":"Point"}
}