{
  "type": "Feature",
  "properties": {
    "gn:admin1_code":"03",
    "gn:asciiname":"Thatha",
    "gn:country_code":"PK",
    "gn:dem":178,
    "gn:feature_class":"P",
    "gn:feature_code":"PPL",
    "gn:name":"Thatha",
    "gn:population":0,
    "gn:timezone":"Asia/Karachi",
    "iso:country":"PK",
    "name:und_x_variant":[
        "Thotha",
        "Thatha"
    ],
    "wof:name":"Thatha",
    "wof:placetype":"locality"
},
  "geometry": {"coordinates":[70.93778,31.99732],"type":"Point"}
}