{
  "type": "Feature",
  "properties": {
    "gn:admin1_code":"4.0",
    "gn:asciiname":"Saiyed Shaukat Ali Kazim",
    "gn:country_code":"PK",
    "gn:dem":137,
    "gn:feature_class":"P",
    "gn:feature_code":"PPL",
    "gn:name":"Saiyed Shaukat Ali Kazim",
    "gn:population":0,
    "gn:timezone":"Asia/Karachi",
    "iso:country":"PK",
    "wof:name":"Saiyed Shaukat Ali Kazim",
    "wof:placetype":"locality"
},
  "geometry": {"coordinates":[71.94356999999999,30.3545],"type":"Point"}
}