{
  "type": "Feature",
  "properties": {
    "gn:admin1_code":"3.0",
    "gn:asciiname":"Gul Bagh",
    "gn:country_code":"PK",
    "gn:dem":381,
    "gn:feature_class":"P",
    "gn:feature_code":"PPL",
    "gn:name":"Gul Bagh",
    "gn:population":0,
    "gn:timezone":"Asia/Karachi",
    "iso:country":"PK",
    "name:eng_x_preferred":[
        "S\u0101z Gul"
    ],
    "wof:name":"Gul Bagh",
    "wof:placetype":"locality"
},
  "geometry": {"coordinates":[71.72187,34.33413],"type":"Point"}
}