{
  "type": "Feature",
  "properties": {
    "gn:admin1_code":"4.0",
    "gn:asciiname":"Colony Two Hundred Fifty-three",
    "gn:country_code":"PK",
    "gn:dem":238,
    "gn:feature_class":"P",
    "gn:feature_code":"PPL",
    "gn:name":"Colony Two Hundred Fifty-three",
    "gn:population":0,
    "gn:timezone":"Asia/Karachi",
    "iso:country":"PK",
    "wof:name":"Colony Two Hundred Fifty-three",
    "wof:placetype":"locality"
},
  "geometry": {"coordinates":[71.61927,32.788],"type":"Point"}
}