{
  "type": "Feature",
  "properties": {
    "gn:admin1_code":"2.0",
    "gn:asciiname":"Chaghardi",
    "gn:country_code":"PK",
    "gn:dem":123,
    "gn:feature_class":"P",
    "gn:feature_code":"PPL",
    "gn:name":"Chaghardi",
    "gn:population":0,
    "gn:timezone":"Asia/Karachi",
    "iso:country":"PK",
    "name:und_x_variant":[
        "Chighirdi",
        "Goth Chaghardi",
        "Chaghardi"
    ],
    "wof:name":"Chaghardi",
    "wof:placetype":"locality"
},
  "geometry": {"coordinates":[67.61041999999999,29.20813],"type":"Point"}
}