{
  "type": "Feature",
  "properties": {
    "gn:admin1_code":"2.0",
    "gn:asciiname":"Karam Dani",
    "gn:country_code":"PK",
    "gn:dem":1300,
    "gn:feature_class":"P",
    "gn:feature_code":"PPL",
    "gn:name":"Karam Dani",
    "gn:population":0,
    "gn:timezone":"Asia/Karachi",
    "iso:country":"PK",
    "wof:name":"Karam Dani",
    "wof:placetype":"locality"
},
  "geometry": {"coordinates":[69.78579000000001,30.13796],"type":"Point"}
}