{
  "type": "Feature",
  "properties": {
    "gn:admin1_code":"01",
    "gn:asciiname":"Sai Kili",
    "gn:country_code":"PK",
    "gn:dem":2052,
    "gn:feature_class":"P",
    "gn:feature_code":"PPL",
    "gn:name":"Sai Kili",
    "gn:population":0,
    "gn:timezone":"Asia/Karachi",
    "iso:country":"PK",
    "name:und_x_variant":[
        "Soi Garhi",
        "Soi Kili"
    ],
    "wof:name":"Sai Kili",
    "wof:placetype":"locality"
},
  "geometry": {"coordinates":[70.63009,33.77269],"type":"Point"}
}