{
  "type": "Feature",
  "properties": {
    "gn:admin1_code":"4",
    "gn:asciiname":"Masum Shahwali",
    "gn:country_code":"PK",
    "gn:dem":169,
    "gn:feature_class":"P",
    "gn:feature_code":"PPL",
    "gn:name":"Masum Shahwali",
    "gn:population":0,
    "gn:timezone":"Asia/Karachi",
    "iso:country":"PK",
    "wof:name":"Masum Shahwali",
    "wof:placetype":"locality"
},
  "geometry": {"coordinates":[73.57080000000001,30.34152000000001],"type":"Point"}
}