{
  "type": "Feature",
  "properties": {
    "gn:admin1_code":"6",
    "gn:asciiname":"Tara Kals",
    "gn:country_code":"PK",
    "gn:dem":1551,
    "gn:feature_class":"P",
    "gn:feature_code":"PPL",
    "gn:name":"Tara Kals",
    "gn:population":0,
    "gn:timezone":"Asia/Karachi",
    "iso:country":"PK",
    "name:und_x_variant":[
        "T\u0101ra Kallas"
    ],
    "wof:name":"Tara Kals",
    "wof:placetype":"locality"
},
  "geometry": {"coordinates":[73.61525,34.26609000000001],"type":"Point"}
}