{
  "type": "Feature",
  "properties": {
    "gn:admin1_code":"4.0",
    "gn:asciiname":"Shah Muhammad",
    "gn:country_code":"PK",
    "gn:dem":159,
    "gn:feature_class":"P",
    "gn:feature_code":"PPL",
    "gn:name":"Shah Muhammad",
    "gn:population":0,
    "gn:timezone":"Asia/Karachi",
    "iso:country":"PK",
    "wof:name":"Shah Muhammad",
    "wof:placetype":"locality"
},
  "geometry": {"coordinates":[70.64114000000002,30.454],"type":"Point"}
}