{
  "type": "Feature",
  "properties": {
    "gn:admin1_code":"4",
    "gn:asciiname":"Rode",
    "gn:country_code":"PK",
    "gn:dem":196,
    "gn:feature_class":"P",
    "gn:feature_code":"PPL",
    "gn:name":"Rode",
    "gn:population":0,
    "gn:timezone":"Asia/Karachi",
    "iso:country":"PK",
    "name:und_x_variant":[
        "Rore"
    ],
    "wof:name":"Rode",
    "wof:placetype":"locality"
},
  "geometry": {"coordinates":[73.83695999999998,31.12206],"type":"Point"}
}