{
  "type": "Feature",
  "properties": {
    "gn:admin1_code":"4",
    "gn:asciiname":"Rode",
    "gn:country_code":"PK",
    "gn:dem":196,
    "gn:feature_class":"P",
    "gn:feature_code":"PPL",
    "gn:name":"Rode",
    "gn:population":0,
    "gn:timezone":"Asia/Karachi",
    "iso:country":"PK",
    "name:cat_x_preferred":[
        "Rode"
    ],
    "name:ceb_x_preferred":[
        "Rode"
    ],
    "name:dan_x_preferred":[
        "Rode"
    ],
    "name:deu_x_preferred":[
        "Rode"
    ],
    "name:fra_x_preferred":[
        "Rode"
    ],
    "name:ita_x_preferred":[
        "Rode"
    ],
    "name:lav_x_preferred":[
        "Rode"
    ],
    "name:nld_x_preferred":[
        "Rode"
    ],
    "name:pol_x_preferred":[
        "Rode"
    ],
    "name:por_x_preferred":[
        "Rode"
    ],
    "name:rus_x_preferred":[
        "\u0420\u043e\u0434\u0435"
    ],
    "name:swe_x_preferred":[
        "Rode"
    ],
    "name:ukr_x_preferred":[
        "\u0420\u043e\u0434\u0435"
    ],
    "name:und_x_variant":[
        "Rore"
    ],
    "wof:name":"Rode",
    "wof:placetype":"locality"
},
  "geometry": {"coordinates":[73.83695999999998,31.12206],"type":"Point"}
}