{
  "type": "Feature",
  "properties": {
    "gn:admin1_code":"5",
    "gn:asciiname":"Imam Bukhsh",
    "gn:country_code":"PK",
    "gn:dem":29,
    "gn:feature_class":"P",
    "gn:feature_code":"PPL",
    "gn:name":"Imam Bukhsh",
    "gn:population":0,
    "gn:timezone":"Asia/Karachi",
    "iso:country":"PK",
    "name:und_x_variant":[
        "Im\u0101m Bakhsh"
    ],
    "wof:name":"Imam Bukhsh",
    "wof:placetype":"locality"
},
  "geometry": {"coordinates":[68.62118000000001,26.25296],"type":"Point"}
}