{
  "type": "Feature",
  "properties": {
    "gn:admin1_code":"4",
    "gn:asciiname":"Hussainwala",
    "gn:country_code":"PK",
    "gn:dem":127,
    "gn:feature_class":"P",
    "gn:feature_code":"PPL",
    "gn:name":"Hussainwala",
    "gn:population":0,
    "gn:timezone":"Asia/Karachi",
    "iso:country":"PK",
    "name:eng_x_preferred":[
        "Husainw\u0101la"
    ],
    "wof:name":"Hussainwala",
    "wof:placetype":"locality"
},
  "geometry": {"coordinates":[70.6733,30.25592],"type":"Point"}
}