{
  "type": "Feature",
  "properties": {
    "gn:admin1_code":"3.0",
    "gn:asciiname":"Gidar Kalle",
    "gn:country_code":"PK",
    "gn:dem":356,
    "gn:feature_class":"P",
    "gn:feature_code":"PPL",
    "gn:name":"Gidar Kalle",
    "gn:population":0,
    "gn:timezone":"Asia/Karachi",
    "iso:country":"PK",
    "name:und_x_variant":[
        "Gidar"
    ],
    "wof:name":"Gidar Kalle",
    "wof:placetype":"locality"
},
  "geometry": {"coordinates":[70.59331,32.92075],"type":"Point"}
}