{
  "type": "Feature",
  "properties": {
    "gn:admin1_code":"3",
    "gn:asciiname":"Chohanwala Khu",
    "gn:country_code":"PK",
    "gn:dem":184,
    "gn:feature_class":"P",
    "gn:feature_code":"PPL",
    "gn:name":"Chohanwala Khu",
    "gn:population":0,
    "gn:timezone":"Asia/Karachi",
    "iso:country":"PK",
    "name:und_x_variant":[
        "Chhouw\u0101la Kh\u016bh"
    ],
    "wof:name":"Chohanwala Khu",
    "wof:placetype":"locality"
},
  "geometry": {"coordinates":[71.02239,32.18512],"type":"Point"}
}