{
  "type": "Feature",
  "properties": {
    "gn:admin1_code":"5",
    "gn:asciiname":"Goth Sardar Khan Laghari",
    "gn:country_code":"PK",
    "gn:dem":13,
    "gn:feature_class":"P",
    "gn:feature_code":"PPL",
    "gn:name":"Goth Sardar Khan Laghari",
    "gn:population":0,
    "gn:timezone":"Asia/Karachi",
    "iso:country":"PK",
    "wof:name":"Goth Sardar Khan Laghari",
    "wof:placetype":"locality"
},
  "geometry": {"coordinates":[68.84385999999999,25.13992],"type":"Point"}
}