{
  "type": "Feature",
  "properties": {
    "gn:admin1_code":"4",
    "gn:asciiname":"Chak Two Hundred Seventy Thal Development Authority",
    "gn:country_code":"PK",
    "gn:dem":155,
    "gn:feature_class":"P",
    "gn:feature_code":"PPL",
    "gn:name":"Chak Two Hundred Seventy Thal Development Authority",
    "gn:population":0,
    "gn:timezone":"Asia/Karachi",
    "iso:country":"PK",
    "name:und_x_variant":[
        "Chak 207 TDA",
        "Chak Two Hundred Seventy TDA",
        "Chak Two Hundred Seventy Thal Development Authority"
    ],
    "wof:name":"Chak Two Hundred Seventy Thal Development Authority",
    "wof:placetype":"locality"
},
  "geometry": {"coordinates":[71.11775,31.07097000000001],"type":"Point"}
}