{
  "type": "Feature",
  "properties": {
    "gn:admin1_code":"2.0",
    "gn:asciiname":"Ghulam Rasul",
    "gn:country_code":"PK",
    "gn:dem":984,
    "gn:feature_class":"P",
    "gn:feature_code":"PPL",
    "gn:name":"Ghulam Rasul",
    "gn:population":0,
    "gn:timezone":"Asia/Karachi",
    "iso:country":"PK",
    "name:deu_x_preferred":[
        "Ghulam Rasul"
    ],
    "name:urd_x_preferred":[
        "\u063a\u0644\u0627\u0645 \u0631\u0633\u0648\u0644"
    ],
    "wof:name":"Ghulam Rasul",
    "wof:placetype":"locality"
},
  "geometry": {"coordinates":[63.98589000000001,29.00651],"type":"Point"}
}