{
  "type": "Feature",
  "properties": {
    "gn:admin1_code":"5",
    "gn:asciiname":"Khangarh",
    "gn:country_code":"PK",
    "gn:dem":68,
    "gn:feature_class":"P",
    "gn:feature_code":"PPL",
    "gn:name":"Khangarh",
    "gn:population":0,
    "gn:timezone":"Asia/Karachi",
    "iso:country":"PK",
    "wof:name":"Khangarh",
    "wof:placetype":"locality"
},
  "geometry": {"coordinates":[69.42180999999999,27.8691],"type":"Point"}
}