{
  "type": "Feature",
  "properties": {
    "gn:admin1_code":"5.0",
    "gn:asciiname":"Goth Shafia Muhammad Arain",
    "gn:country_code":"PK",
    "gn:dem":43,
    "gn:feature_class":"P",
    "gn:feature_code":"PPL",
    "gn:name":"Goth Shafia Muhammad Arain",
    "gn:population":0,
    "gn:timezone":"Asia/Karachi",
    "iso:country":"PK",
    "wof:name":"Goth Shafia Muhammad Arain",
    "wof:placetype":"locality"
},
  "geometry": {"coordinates":[68.37940999999999,26.6777],"type":"Point"}
}