{
  "type": "Feature",
  "properties": {
    "gn:admin1_code":"3.0",
    "gn:asciiname":"Jabrai",
    "gn:country_code":"PK",
    "gn:dem":2287,
    "gn:feature_class":"P",
    "gn:feature_code":"PPL",
    "gn:name":"Jabrai",
    "gn:population":0,
    "gn:timezone":"Asia/Karachi",
    "iso:country":"PK",
    "name:eng_x_preferred":[
        "Jabrai"
    ],
    "wof:name":"Jabrai",
    "wof:placetype":"locality"
},
  "geometry": {"coordinates":[72.17379,35.35707],"type":"Point"}
}