{
  "type": "Feature",
  "properties": {
    "gn:admin1_code":"4.0",
    "gn:asciiname":"Dhok Chatha",
    "gn:country_code":"PK",
    "gn:dem":508,
    "gn:feature_class":"P",
    "gn:feature_code":"PPL",
    "gn:name":"Dhok Chatha",
    "gn:population":0,
    "gn:timezone":"Asia/Karachi",
    "iso:country":"PK",
    "name:und_x_variant":[
        "Dhok Chathi\u0101nw\u0101li"
    ],
    "wof:name":"Dhok Chatha",
    "wof:placetype":"locality"
},
  "geometry": {"coordinates":[72.94014,33.51602],"type":"Point"}
}