{
  "type": "Feature",
  "properties": {
    "gn:admin1_code":"4.0",
    "gn:asciiname":"Ismailbur",
    "gn:country_code":"PK",
    "gn:dem":171,
    "gn:feature_class":"P",
    "gn:feature_code":"PPL",
    "gn:name":"Ismailbur",
    "gn:population":0,
    "gn:timezone":"Asia/Karachi",
    "iso:country":"PK",
    "name:und_x_variant":[
        "R\u0101tteka"
    ],
    "wof:name":"Ismailbur",
    "wof:placetype":"locality"
},
  "geometry": {"coordinates":[73.67799000000002,30.23517],"type":"Point"}
}