{
  "type": "Feature",
  "properties": {
    "gn:admin1_code":"3.0",
    "gn:asciiname":"Mashomit",
    "gn:country_code":"PK",
    "gn:dem":2329,
    "gn:feature_class":"P",
    "gn:feature_code":"PPL",
    "gn:name":"Mashomit",
    "gn:population":0,
    "gn:timezone":"Asia/Karachi",
    "iso:country":"PK",
    "wof:name":"Mashomit",
    "wof:placetype":"locality"
},
  "geometry": {"coordinates":[72.29399000000002,36.30819],"type":"Point"}
}