{
  "type": "Feature",
  "properties": {
    "gn:admin1_code":"5.0",
    "gn:asciiname":"Sardar Ghazi Khan Channa",
    "gn:country_code":"PK",
    "gn:dem":69,
    "gn:feature_class":"P",
    "gn:feature_code":"PPL",
    "gn:name":"Sardar Ghazi Khan Channa",
    "gn:population":0,
    "gn:timezone":"Asia/Karachi",
    "iso:country":"PK",
    "name:und_x_variant":[
        "Chana"
    ],
    "wof:name":"Sardar Ghazi Khan Channa",
    "wof:placetype":"locality"
},
  "geometry": {"coordinates":[68.70789000000001,28.14011],"type":"Point"}
}