{
  "type": "Feature",
  "properties": {
    "gn:admin1_code":"4.0",
    "gn:asciiname":"Basti Asawali",
    "gn:country_code":"PK",
    "gn:dem":133,
    "gn:feature_class":"P",
    "gn:feature_code":"PPL",
    "gn:name":"Basti Asawali",
    "gn:population":0,
    "gn:timezone":"Asia/Karachi",
    "iso:country":"PK",
    "name:und_x_variant":[
        "\u012asa"
    ],
    "wof:name":"Basti Asawali",
    "wof:placetype":"locality"
},
  "geometry": {"coordinates":[72.31392,29.67046],"type":"Point"}
}