{
  "type": "Feature",
  "properties": {
    "gn:admin1_code":"04",
    "gn:asciiname":"Kotla Saiyidan",
    "gn:country_code":"PK",
    "gn:dem":214,
    "gn:feature_class":"P",
    "gn:feature_code":"PPL",
    "gn:name":"Kotla Saiyidan",
    "gn:population":0,
    "gn:timezone":"Asia/Karachi",
    "iso:country":"PK",
    "name:und_x_variant":[
        "Kuthala Saidan",
        "Koth\u0101ia Saiyid\u0101n",
        "Koth\u0101la Saiyid\u0101n",
        "Kotla Saiyidan"
    ],
    "wof:name":"Kotla Saiyidan",
    "wof:placetype":"neighbourhood"
},
  "geometry": {"coordinates":[73.46046,32.59018],"type":"Point"}
}