{
  "type": "Feature",
  "properties": {
    "gn:admin1_code":"4",
    "gn:asciiname":"Basti Usman Kosh",
    "gn:country_code":"PK",
    "gn:dem":76,
    "gn:feature_class":"P",
    "gn:feature_code":"PPL",
    "gn:name":"Basti Usman Kosh",
    "gn:population":0,
    "gn:timezone":"Asia/Karachi",
    "iso:country":"PK",
    "wof:name":"Basti Usman Kosh",
    "wof:placetype":"locality"
},
  "geometry": {"coordinates":[69.91171999999999,28.29558],"type":"Point"}
}