{
  "type": "Feature",
  "properties": {
    "gn:admin1_code":"4",
    "gn:asciiname":"Jhok Ladhicha",
    "gn:country_code":"PK",
    "gn:dem":208,
    "gn:feature_class":"P",
    "gn:feature_code":"PPL",
    "gn:name":"Jhok Ladhicha",
    "gn:population":0,
    "gn:timezone":"Asia/Karachi",
    "iso:country":"PK",
    "name:und_x_variant":[
        "Ladhich",
        "Jhok Ladhicha"
    ],
    "wof:name":"Jhok Ladhicha",
    "wof:placetype":"locality"
},
  "geometry": {"coordinates":[70.55766,31.01071],"type":"Point"}
}