{
  "type": "Feature",
  "properties": {
    "gn:admin1_code":"2",
    "gn:asciiname":"Kakazai",
    "gn:country_code":"PK",
    "gn:dem":1500,
    "gn:feature_class":"P",
    "gn:feature_code":"PPL",
    "gn:name":"Kakazai",
    "gn:population":0,
    "gn:timezone":"Asia/Karachi",
    "iso:country":"PK",
    "name:und_x_variant":[
        "Kakaza"
    ],
    "wof:name":"Kakazai",
    "wof:placetype":"locality"
},
  "geometry": {"coordinates":[66.89801999999999,30.72941],"type":"Point"}
}