{
  "type": "Feature",
  "properties": {
    "gn:admin1_code":"3",
    "gn:asciiname":"Nara Dheri",
    "gn:country_code":"PK",
    "gn:dem":347,
    "gn:feature_class":"P",
    "gn:feature_code":"PPL",
    "gn:name":"Nara Dheri",
    "gn:population":0,
    "gn:timezone":"Asia/Karachi",
    "iso:country":"PK",
    "name:eng_x_preferred":[
        "N\u0101ro Dheri"
    ],
    "wof:name":"Nara Dheri",
    "wof:placetype":"locality"
},
  "geometry": {"coordinates":[72.42764,34.14822],"type":"Point"}
}