{
  "type": "Feature",
  "properties": {
    "gn:admin1_code":"2.0",
    "gn:asciiname":"Muhammad Karim",
    "gn:country_code":"PK",
    "gn:dem":1731,
    "gn:feature_class":"P",
    "gn:feature_code":"PPL",
    "gn:name":"Muhammad Karim",
    "gn:population":0,
    "gn:timezone":"Asia/Karachi",
    "iso:country":"PK",
    "wof:name":"Muhammad Karim",
    "wof:placetype":"locality"
},
  "geometry": {"coordinates":[65.62806999999999,26.94532],"type":"Point"}
}