{
  "type": "Feature",
  "properties": {
    "gn:admin1_code":"1",
    "gn:asciiname":"Said Ali Mela",
    "gn:country_code":"PK",
    "gn:dem":847,
    "gn:feature_class":"P",
    "gn:feature_code":"PPL",
    "gn:name":"Said Ali Mela",
    "gn:population":0,
    "gn:timezone":"Asia/Karachi",
    "iso:country":"PK",
    "wof:name":"Said Ali Mela",
    "wof:placetype":"locality"
},
  "geometry": {"coordinates":[71.26352,34.02494],"type":"Point"}
}