{
  "type": "Feature",
  "properties": {
    "gn:admin1_code":"3.0",
    "gn:asciiname":"Maulyano Kalle",
    "gn:country_code":"PK",
    "gn:dem":408,
    "gn:feature_class":"P",
    "gn:feature_code":"PPL",
    "gn:name":"Maulyano Kalle",
    "gn:population":0,
    "gn:timezone":"Asia/Karachi",
    "iso:country":"PK",
    "name:eng_x_preferred":[
        "Malle\u0101no Kalle"
    ],
    "wof:name":"Maulyano Kalle",
    "wof:placetype":"locality"
},
  "geometry": {"coordinates":[71.63011999999998,34.35194],"type":"Point"}
}