{
  "type": "Feature",
  "properties": {
    "gn:admin1_code":"3",
    "gn:asciiname":"Kanei",
    "gn:country_code":"PK",
    "gn:dem":969,
    "gn:feature_class":"P",
    "gn:feature_code":"PPL",
    "gn:name":"Kanei",
    "gn:population":0,
    "gn:timezone":"Asia/Karachi",
    "iso:country":"PK",
    "wof:name":"Kanei",
    "wof:placetype":"locality"
},
  "geometry": {"coordinates":[72.9918,34.79986],"type":"Point"}
}