{
  "type": "Feature",
  "properties": {
    "gn:admin1_code":"4",
    "gn:asciiname":"Kakkah",
    "gn:country_code":"PK",
    "gn:dem":207,
    "gn:feature_class":"P",
    "gn:feature_code":"PPL",
    "gn:name":"Kakkah",
    "gn:population":0,
    "gn:timezone":"Asia/Karachi",
    "iso:country":"PK",
    "name:und_x_variant":[
        "Kakka"
    ],
    "wof:name":"Kakkah",
    "wof:placetype":"locality"
},
  "geometry": {"coordinates":[73.49124999999999,32.40547],"type":"Point"}
}