{
  "type": "Feature",
  "properties": {
    "gn:admin1_code":"7.0",
    "gn:asciiname":"Khesey",
    "gn:country_code":"PK",
    "gn:dem":3106,
    "gn:feature_class":"P",
    "gn:feature_code":"PPL",
    "gn:name":"Khesey",
    "gn:population":0,
    "gn:timezone":"Asia/Karachi",
    "iso:country":"PK",
    "wof:name":"Khesey",
    "wof:placetype":"locality"
},
  "geometry": {"coordinates":[74.9696,35.37548],"type":"Point"}
}