{
  "type": "Feature",
  "properties": {
    "gn:admin1_code":"4",
    "gn:asciiname":"Chaukui",
    "gn:country_code":"PK",
    "gn:dem":93,
    "gn:feature_class":"P",
    "gn:feature_code":"PPL",
    "gn:name":"Chaukui",
    "gn:population":0,
    "gn:timezone":"Asia/Karachi",
    "iso:country":"PK",
    "wof:name":"Chaukui",
    "wof:placetype":"locality"
},
  "geometry": {"coordinates":[70.43271999999997,29.0897],"type":"Point"}
}