{
  "type": "Feature",
  "properties": {
    "gn:admin1_code":"4.0",
    "gn:asciiname":"Khanke Mor",
    "gn:country_code":"PK",
    "gn:dem":197,
    "gn:feature_class":"P",
    "gn:feature_code":"PPL",
    "gn:name":"Khanke Mor",
    "gn:population":0,
    "gn:timezone":"Asia/Karachi",
    "iso:country":"PK",
    "name:und_x_variant":[
        "Kh\u0101nki Maur"
    ],
    "wof:name":"Khanke Mor",
    "wof:placetype":"locality"
},
  "geometry": {"coordinates":[73.90334,31.16527],"type":"Point"}
}