{
  "type": "Feature",
  "properties": {
    "gn:admin1_code":"5.0",
    "gn:asciiname":"Bacho Sehta",
    "gn:country_code":"PK",
    "gn:dem":9,
    "gn:feature_class":"P",
    "gn:feature_code":"PPL",
    "gn:name":"Bacho Sehta",
    "gn:population":0,
    "gn:timezone":"Asia/Karachi",
    "iso:country":"PK",
    "name:eng_x_preferred":[
        "Bachchu Sehta"
    ],
    "wof:name":"Bacho Sehta",
    "wof:placetype":"locality"
},
  "geometry": {"coordinates":[68.09628000000001,24.6617],"type":"Point"}
}