{
  "type": "Feature",
  "properties": {
    "gn:admin1_code":"5",
    "gn:asciiname":"Goth Dosu Chachar",
    "gn:country_code":"PK",
    "gn:dem":9,
    "gn:feature_class":"P",
    "gn:feature_code":"PPL",
    "gn:name":"Goth Dosu Chachar",
    "gn:population":0,
    "gn:timezone":"Asia/Karachi",
    "iso:country":"PK",
    "name:und_x_variant":[
        "Dosu Ch\u0101char"
    ],
    "wof:name":"Goth Dosu Chachar",
    "wof:placetype":"locality"
},
  "geometry": {"coordinates":[69.63793000000001,25.24159],"type":"Point"}
}