{
  "type": "Feature",
  "properties": {
    "gn:admin1_code":"4",
    "gn:asciiname":"Machhiwala",
    "gn:country_code":"PK",
    "gn:dem":107,
    "gn:feature_class":"P",
    "gn:feature_code":"PPL",
    "gn:name":"Machhiwala",
    "gn:population":0,
    "gn:timezone":"Asia/Karachi",
    "iso:country":"PK",
    "name:und_x_variant":[
        "Lakhiw\u0101la"
    ],
    "wof:name":"Machhiwala",
    "wof:placetype":"locality"
},
  "geometry": {"coordinates":[70.62886,29.66276],"type":"Point"}
}