{
  "type": "Feature",
  "properties": {
    "gn:admin1_code":"4",
    "gn:asciiname":"Taja Berwala",
    "gn:country_code":"PK",
    "gn:dem":170,
    "gn:feature_class":"P",
    "gn:feature_code":"PPL",
    "gn:name":"Taja Berwala",
    "gn:population":0,
    "gn:timezone":"Asia/Karachi",
    "iso:country":"PK",
    "name:fas_x_preferred":[
        "\u062a\u0627\u062c\u0627 \u0628\u0631\u0648\u0627\u0644\u0627"
    ],
    "name:und_x_variant":[
        "T\u0101ja Berw\u0101la Inspection Bungalow"
    ],
    "name:urd_x_preferred":[
        "\u062a\u0627\u062c\u0627 \u0628\u0631\u0648\u0627\u0644\u0627"
    ],
    "wof:name":"Taja Berwala",
    "wof:placetype":"locality"
},
  "geometry": {"coordinates":[72.6443,31.59233],"type":"Point"}
}