{
  "type": "Feature",
  "properties": {
    "gn:admin1_code":"3.0",
    "gn:asciiname":"Gagoaj",
    "gn:country_code":"PK",
    "gn:dem":2082,
    "gn:feature_class":"P",
    "gn:feature_code":"PPL",
    "gn:name":"Gagoaj",
    "gn:population":0,
    "gn:timezone":"Asia/Karachi",
    "iso:country":"PK",
    "wof:name":"Gagoaj",
    "wof:placetype":"locality"
},
  "geometry": {"coordinates":[73.36628,35.21339000000001],"type":"Point"}
}