{
  "type": "Feature",
  "properties": {
    "gn:admin1_code":"03",
    "gn:asciiname":"Naurang Utra",
    "gn:country_code":"PK",
    "gn:dem":194,
    "gn:feature_class":"P",
    "gn:feature_code":"PPL",
    "gn:name":"Naurang Utra",
    "gn:population":0,
    "gn:timezone":"Asia/Karachi",
    "iso:country":"PK",
    "name:und_x_variant":[
        "Naurang Uttera",
        "Naurang Utra"
    ],
    "wof:name":"Naurang Utra",
    "wof:placetype":"locality"
},
  "geometry": {"coordinates":[70.66521,31.75163],"type":"Point"}
}