{
  "type": "Feature",
  "properties": {
    "gn:admin1_code":"3.0",
    "gn:asciiname":"Ibrahimzai",
    "gn:country_code":"PK",
    "gn:dem":309,
    "gn:feature_class":"P",
    "gn:feature_code":"PPL",
    "gn:name":"Ibrahimzai",
    "gn:population":0,
    "gn:timezone":"Asia/Karachi",
    "iso:country":"PK",
    "name:eng_x_preferred":[
        "Ibrahimzai"
    ],
    "wof:name":"Ibrahimzai",
    "wof:placetype":"locality"
},
  "geometry": {"coordinates":[71.85556,34.14154],"type":"Point"}
}