{
  "type": "Feature",
  "properties": {
    "gn:admin1_code":"3.0",
    "gn:asciiname":"Kiala Pain",
    "gn:country_code":"PK",
    "gn:dem":1056,
    "gn:feature_class":"P",
    "gn:feature_code":"PPL",
    "gn:name":"Kiala Pain",
    "gn:population":0,
    "gn:timezone":"Asia/Karachi",
    "iso:country":"PK",
    "wof:name":"Kiala Pain",
    "wof:placetype":"locality"
},
  "geometry": {"coordinates":[73.17716999999998,33.95851],"type":"Point"}
}