{
  "type": "Feature",
  "properties": {
    "gn:admin1_code":"4.0",
    "gn:asciiname":"Guliana",
    "gn:country_code":"PK",
    "gn:dem":275,
    "gn:feature_class":"P",
    "gn:feature_code":"PPL",
    "gn:name":"Guliana",
    "gn:population":0,
    "gn:timezone":"Asia/Karachi",
    "iso:country":"PK",
    "name:und_x_variant":[
        "Galiana",
        "Guliana"
    ],
    "wof:name":"Guliana",
    "wof:placetype":"locality"
},
  "geometry": {"coordinates":[73.96143000000002,32.80154],"type":"Point"}
}