{
  "type": "Feature",
  "properties": {
    "gn:admin1_code":"4.0",
    "gn:asciiname":"Ahata Hakim Ali",
    "gn:country_code":"PK",
    "gn:dem":154,
    "gn:feature_class":"P",
    "gn:feature_code":"PPL",
    "gn:name":"Ahata Hakim Ali",
    "gn:population":0,
    "gn:timezone":"Asia/Karachi",
    "iso:country":"PK",
    "wof:name":"Ahata Hakim Ali",
    "wof:placetype":"locality"
},
  "geometry": {"coordinates":[73.05301999999998,29.62936],"type":"Point"}
}