{
  "type": "Feature",
  "properties": {
    "gn:admin1_code":"5.0",
    "gn:asciiname":"Goth Shafqat Shah",
    "gn:country_code":"PK",
    "gn:dem":12,
    "gn:feature_class":"P",
    "gn:feature_code":"PPL",
    "gn:name":"Goth Shafqat Shah",
    "gn:population":0,
    "gn:timezone":"Asia/Karachi",
    "iso:country":"PK",
    "name:eng_x_preferred":[
        "Shafqat Sh\u0101h"
    ],
    "wof:name":"Goth Shafqat Shah",
    "wof:placetype":"locality"
},
  "geometry": {"coordinates":[68.03631,24.59046],"type":"Point"}
}