{
  "type": "Feature",
  "properties": {
    "gn:admin1_code":"2",
    "gn:asciiname":"Walang",
    "gn:country_code":"PK",
    "gn:dem":1964,
    "gn:feature_class":"P",
    "gn:feature_code":"PPL",
    "gn:name":"Walang",
    "gn:population":0,
    "gn:timezone":"Asia/Karachi",
    "iso:country":"PK",
    "name:eng_x_preferred":[
        "Wal\u0101ng"
    ],
    "wof:name":"Walang",
    "wof:placetype":"locality"
},
  "geometry": {"coordinates":[67.31579000000001,30.74227],"type":"Point"}
}