{
  "type": "Feature",
  "properties": {
    "gn:admin1_code":"04",
    "gn:asciiname":"Basti Nekukara",
    "gn:country_code":"PK",
    "gn:dem":145,
    "gn:feature_class":"P",
    "gn:feature_code":"PPL",
    "gn:name":"Basti Nekukara",
    "gn:population":0,
    "gn:timezone":"Asia/Karachi",
    "iso:country":"PK",
    "name:und_x_variant":[
        "Nekok\u0101ra"
    ],
    "wof:name":"Basti Nekukara",
    "wof:placetype":"locality"
},
  "geometry": {"coordinates":[72.02759,30.95989],"type":"Point"}
}