{
  "type": "Feature",
  "properties": {
    "iso:country":"PK",
    "name:ara_x_preferred":[
        "\u062d\u0635\u0646 \u0631\u0648\u0647\u062a\u0627\u0633"
    ],
    "name:bel_x_preferred":[
        "\u0420\u043e\u0445\u0442\u0430\u0441"
    ],
    "name:ben_x_preferred":[
        "\u09b0\u09cb\u09b9\u09a4\u09be\u09b8 \u0995\u09c7\u09b2\u09cd\u09b2\u09be"
    ],
    "name:cat_x_preferred":[
        "Rohtas"
    ],
    "name:ces_x_preferred":[
        "Pevnost Rohtas"
    ],
    "name:deu_x_preferred":[
        "Rohtas"
    ],
    "name:eng_x_preferred":[
        "Rohtas Fort"
    ],
    "name:fin_x_preferred":[
        "Rohtasin linnoitus"
    ],
    "name:heb_x_preferred":[
        "\u05de\u05e6\u05d5\u05d3\u05ea \u05e8\u05d5\u05d4\u05d8\u05d0\u05e1"
    ],
    "name:hrv_x_preferred":[
        "Rohtas"
    ],
    "name:ita_x_preferred":[
        "Forte Rohtas"
    ],
    "name:jpn_x_preferred":[
        "\u30ed\u30fc\u30bf\u30b9\u30fb\u30d5\u30a9\u30fc\u30c8"
    ],
    "name:kat_x_preferred":[
        "\u10e0\u10dd\u10f0\u10e2\u10d0\u10e1\u10d8\u10e1 \u10ea\u10d8\u10ee\u10d4\u10e1\u10d8\u10db\u10d0\u10d2\u10e0\u10d4"
    ],
    "name:lit_x_preferred":[
        "Rohtaso tvirtov\u0117"
    ],
    "name:mai_x_preferred":[
        "\u0930\u094b\u0939\u0924\u093e\u0938 \u0915\u093f\u0932\u093e"
    ],
    "name:mal_x_preferred":[
        "\u0d31\u0d4b\u0d39\u0d4d\u0d24\u0d4d\u0d24\u0d3e\u0d38\u0d4d \u0d15\u0d4b\u0d1f\u0d4d\u0d1f"
    ],
    "name:nep_x_preferred":[
        "\u0930\u094b\u0939\u0924\u093e\u0938 \u0915\u093f\u0932\u094d\u0932\u093e"
    ],
    "name:nld_x_preferred":[
        "Fort Rohtas"
    ],
    "name:pan_x_preferred":[
        "\u0a30\u0a4b\u0a39\u0a24\u0a3e\u0a38 \u0a15\u0a3f\u0a32\u0a4d\u0a39\u0a3e"
    ],
    "name:pnb_x_preferred":[
        "\u0642\u0644\u0639\u06c1 \u0631\u0648\u06c1\u062a\u0627\u0633"
    ],
    "name:pus_x_preferred":[
        "\u0631\u0648\u0647\u062a\u0627\u0633"
    ],
    "name:rus_x_preferred":[
        "\u0420\u043e\u0445\u0442\u0430\u0441"
    ],
    "name:slk_x_preferred":[
        "Kil\u02bca R\u00f3ht\u00e1s"
    ],
    "name:swe_x_preferred":[
        "Rohtas fort"
    ],
    "name:tam_x_preferred":[
        "\u0bb0\u0bcb\u0b9f\u0bbe\u0b9a\u0bc1 \u0b95\u0bcb\u0b9f\u0bcd\u0b9f\u0bc8"
    ],
    "name:tur_x_preferred":[
        "Rohtas Kalesi"
    ],
    "name:ukr_x_preferred":[
        "\u0420\u043e\u0445\u0442\u0430\u0441"
    ],
    "name:unk_x_variant":[
        "Roht\u0101s"
    ],
    "name:urd_x_preferred":[
        "\u0642\u0644\u0639\u06c1 \u0631\u0648\u06c1\u062a\u0627\u0633"
    ],
    "name:vie_x_preferred":[
        "Ph\u00e1o \u0111\u00e0i Rohtas"
    ],
    "name:zho_x_preferred":[
        "\u7f85\u8d6b\u9054\u65af\u8981\u585e"
    ],
    "qs:gn_country":"PK",
    "qs:gn_fcode":"PPL",
    "qs:gn_pop":0,
    "qs:name":"Rakh Rohtas",
    "qs:name_adm0":"Pakistan",
    "qs:name_adm1":"Punjab",
    "qs:photos":426,
    "qs:photos_1k":86,
    "qs:photos_9k":2,
    "qs:photos_9r":5,
    "qs:photos_all":426,
    "qs:photos_sr":6,
    "qs:placetype":"Town",
    "qs:pop_sr":"0",
    "qs:woe_adm0":23424922,
    "wof:name":"Rakh Rohtas",
    "wof:placetype":"locality"
},
  "geometry": {"coordinates":[73.5787,32.96691],"type":"Point"}
}