{
  "type": "Feature",
  "properties": {
    "iso:country":"PK",
    "name:unk_x_variant":[
        "Roht\u0101s"
    ],
    "qs:gn_country":"PK",
    "qs:gn_fcode":"PPL",
    "qs:gn_pop":0,
    "qs:name":"Rakh Rohtas",
    "qs:name_adm0":"Pakistan",
    "qs:name_adm1":"Punjab",
    "qs:photos":426,
    "qs:photos_1k":86,
    "qs:photos_9k":2,
    "qs:photos_9r":5,
    "qs:photos_all":426,
    "qs:photos_sr":6,
    "qs:placetype":"Town",
    "qs:pop_sr":"0",
    "qs:woe_adm0":23424922,
    "wof:name":"Rakh Rohtas",
    "wof:placetype":"locality"
},
  "geometry": {"coordinates":[73.5787,32.96691],"type":"Point"}
}