{
  "type": "Feature",
  "properties": {
    "gn:admin1_code":"4.0",
    "gn:asciiname":"Dezard",
    "gn:country_code":"PK",
    "gn:dem":1208,
    "gn:feature_class":"P",
    "gn:feature_code":"PPL",
    "gn:name":"Dezard",
    "gn:population":0,
    "gn:timezone":"Asia/Karachi",
    "iso:country":"PK",
    "wof:name":"Dezard",
    "wof:placetype":"locality"
},
  "geometry": {"coordinates":[70.12785,30.70114],"type":"Point"}
}