{
  "type": "Feature",
  "properties": {
    "gn:admin1_code":"5",
    "gn:asciiname":"Goth Haider Chana",
    "gn:country_code":"PK",
    "gn:dem":27,
    "gn:feature_class":"P",
    "gn:feature_code":"PPL",
    "gn:name":"Goth Haider Chana",
    "gn:population":0,
    "gn:timezone":"Asia/Karachi",
    "iso:country":"PK",
    "name:und_x_variant":[
        "Goth Muhammad Kh\u0101n"
    ],
    "wof:name":"Goth Haider Chana",
    "wof:placetype":"locality"
},
  "geometry": {"coordinates":[68.52750999999999,25.80637],"type":"Point"}
}