{
  "type": "Feature",
  "properties": {
    "gn:admin1_code":"2.0",
    "gn:asciiname":"Kora Allahabad",
    "gn:country_code":"PK",
    "gn:dem":92,
    "gn:feature_class":"P",
    "gn:feature_code":"PPL",
    "gn:name":"Kora Allahabad",
    "gn:population":0,
    "gn:timezone":"Asia/Karachi",
    "iso:country":"PK",
    "name:und_x_variant":[
        "Korani"
    ],
    "wof:name":"Kora Allahabad",
    "wof:placetype":"locality"
},
  "geometry": {"coordinates":[67.8254,28.9052],"type":"Point"}
}