{
  "type": "Feature",
  "properties": {
    "gn:admin1_code":"5.0",
    "gn:asciiname":"Goth Sattar Khan",
    "gn:country_code":"PK",
    "gn:dem":51,
    "gn:feature_class":"P",
    "gn:feature_code":"PPL",
    "gn:name":"Goth Sattar Khan",
    "gn:population":0,
    "gn:timezone":"Asia/Karachi",
    "iso:country":"PK",
    "name:eng_x_preferred":[
        "Sathi Kh\u0101n"
    ],
    "name:und_x_variant":[
        "Gulan Hingora"
    ],
    "wof:name":"Goth Sattar Khan",
    "wof:placetype":"locality"
},
  "geometry": {"coordinates":[68.55179,27.25649],"type":"Point"}
}