{
  "type": "Feature",
  "properties": {
    "gn:admin1_code":"4",
    "gn:asciiname":"Chak One Hundred Eleven Dara Nawab Branch",
    "gn:country_code":"PK",
    "gn:dem":113,
    "gn:feature_class":"P",
    "gn:feature_code":"PPL",
    "gn:name":"Chak One Hundred Eleven Dara Nawab Branch",
    "gn:population":0,
    "gn:timezone":"Asia/Karachi",
    "iso:country":"PK",
    "name:und_x_variant":[
        "Chak 111 D N B"
    ],
    "wof:name":"Chak One Hundred Eleven Dara Nawab Branch",
    "wof:placetype":"locality"
},
  "geometry": {"coordinates":[71.40834,29.07588],"type":"Point"}
}