{
  "type": "Feature",
  "properties": {
    "gn:admin1_code":"3.0",
    "gn:asciiname":"Khoidaj",
    "gn:country_code":"PK",
    "gn:dem":1373,
    "gn:feature_class":"P",
    "gn:feature_code":"PPL",
    "gn:name":"Khoidaj",
    "gn:population":0,
    "gn:timezone":"Asia/Karachi",
    "iso:country":"PK",
    "wof:name":"Khoidaj",
    "wof:placetype":"locality"
},
  "geometry": {"coordinates":[71.92538,35.13923],"type":"Point"}
}