{
  "type": "Feature",
  "properties": {
    "gn:admin1_code":"3.0",
    "gn:asciiname":"Dubandal",
    "gn:country_code":"PK",
    "gn:dem":2614,
    "gn:feature_class":"P",
    "gn:feature_code":"PPL",
    "gn:name":"Dubandal",
    "gn:population":0,
    "gn:timezone":"Asia/Karachi",
    "iso:country":"PK",
    "name:und_x_variant":[
        "D\u016bbandai"
    ],
    "wof:name":"Dubandal",
    "wof:placetype":"locality"
},
  "geometry": {"coordinates":[72.65094999999999,35.11872],"type":"Point"}
}