{
  "type": "Feature",
  "properties": {
    "gn:admin1_code":"5.0",
    "gn:asciiname":"Jamal Sohal Mill",
    "gn:country_code":"PK",
    "gn:dem":58,
    "gn:feature_class":"P",
    "gn:feature_code":"PPL",
    "gn:name":"Jamal Sohal Mill",
    "gn:population":0,
    "gn:timezone":"Asia/Karachi",
    "iso:country":"PK",
    "wof:name":"Jamal Sohal Mill",
    "wof:placetype":"locality"
},
  "geometry": {"coordinates":[68.42093,28.25754],"type":"Point"}
}