{
  "type": "Feature",
  "properties": {
    "gn:admin1_code":"01",
    "gn:asciiname":"Dherai",
    "gn:country_code":"PK",
    "gn:dem":1239,
    "gn:feature_class":"P",
    "gn:feature_code":"PPL",
    "gn:name":"Dherai",
    "gn:population":0,
    "gn:timezone":"Asia/Karachi",
    "iso:country":"PK",
    "name:eng_x_preferred":[
        "Dheri"
    ],
    "wof:name":"Dherai",
    "wof:placetype":"locality"
},
  "geometry": {"coordinates":[71.51918000000001,34.66817],"type":"Point"}
}