{
  "type": "Feature",
  "properties": {
    "gn:admin1_code":"2.0",
    "gn:asciiname":"Kili Ahmad Khan",
    "gn:country_code":"PK",
    "gn:dem":138,
    "gn:feature_class":"P",
    "gn:feature_code":"PPL",
    "gn:name":"Kili Ahmad Khan",
    "gn:population":0,
    "gn:timezone":"Asia/Karachi",
    "iso:country":"PK",
    "name:und_x_variant":[
        "Naun\u012bh\u0101l"
    ],
    "wof:name":"Kili Ahmad Khan",
    "wof:placetype":"locality"
},
  "geometry": {"coordinates":[67.87745,29.56592],"type":"Point"}
}