{
  "type": "Feature",
  "properties": {
    "gn:admin1_code":"4.0",
    "gn:asciiname":"Chak Eighty-two Eastern Bar",
    "gn:country_code":"PK",
    "gn:dem":153,
    "gn:feature_class":"P",
    "gn:feature_code":"PPL",
    "gn:name":"Chak Eighty-two Eastern Bar",
    "gn:population":0,
    "gn:timezone":"Asia/Karachi",
    "iso:country":"PK",
    "name:und_x_variant":[
        "Gh\u0101ngra"
    ],
    "wof:name":"Chak Eighty-two Eastern Bar",
    "wof:placetype":"locality"
},
  "geometry": {"coordinates":[72.87470999999999,30.3849],"type":"Point"}
}