{
  "type": "Feature",
  "properties": {
    "gn:admin1_code":"3.0",
    "gn:asciiname":"Gat Seri",
    "gn:country_code":"PK",
    "gn:dem":1824,
    "gn:feature_class":"P",
    "gn:feature_code":"PPL",
    "gn:name":"Gat Seri",
    "gn:population":0,
    "gn:timezone":"Asia/Karachi",
    "iso:country":"PK",
    "wof:name":"Gat Seri",
    "wof:placetype":"locality"
},
  "geometry": {"coordinates":[73.08855,34.72786],"type":"Point"}
}