{
  "type": "Feature",
  "properties": {
    "gn:admin1_code":"4.0",
    "gn:asciiname":"Kalas Goraye",
    "gn:country_code":"PK",
    "gn:dem":231,
    "gn:feature_class":"P",
    "gn:feature_code":"PPL",
    "gn:name":"Kalas Goraye",
    "gn:population":0,
    "gn:timezone":"Asia/Karachi",
    "iso:country":"PK",
    "wof:name":"Kalas Goraye",
    "wof:placetype":"locality"
},
  "geometry": {"coordinates":[74.83194,32.07333],"type":"Point"}
}