{
  "type": "Feature",
  "properties": {
    "gn:admin1_code":"01",
    "gn:asciiname":"Sursara",
    "gn:country_code":"PK",
    "gn:dem":1942,
    "gn:feature_class":"P",
    "gn:feature_code":"PPL",
    "gn:name":"Sursara",
    "gn:population":0,
    "gn:timezone":"Asia/Karachi",
    "iso:country":"PK",
    "wof:name":"Sursara",
    "wof:placetype":"locality"
},
  "geometry": {"coordinates":[70.56219,33.73888],"type":"Point"}
}