{
  "type": "Feature",
  "properties": {
    "gn:admin1_code":"3",
    "gn:asciiname":"Ghuzano Cham",
    "gn:country_code":"PK",
    "gn:dem":1246,
    "gn:feature_class":"P",
    "gn:feature_code":"PPL",
    "gn:name":"Ghuzano Cham",
    "gn:population":0,
    "gn:timezone":"Asia/Karachi",
    "iso:country":"PK",
    "name:und_x_variant":[
        "Gh\u016bz\u0101 Cham",
        "Ghuzano Cham"
    ],
    "wof:name":"Ghuzano Cham",
    "wof:placetype":"locality"
},
  "geometry": {"coordinates":[72.35160999999999,34.95318],"type":"Point"}
}