{
  "type": "Feature",
  "properties": {
    "gn:admin1_code":"5",
    "gn:asciiname":"Goth Abdul Aziz",
    "gn:country_code":"PK",
    "gn:dem":25,
    "gn:feature_class":"P",
    "gn:feature_code":"PPL",
    "gn:name":"Goth Abdul Aziz",
    "gn:population":0,
    "gn:timezone":"Asia/Karachi",
    "iso:country":"PK",
    "name:und_x_variant":[
        "Goth Ehs\u0101n Ch\u0101ndio"
    ],
    "wof:name":"Goth Abdul Aziz",
    "wof:placetype":"locality"
},
  "geometry": {"coordinates":[68.62371,25.80228],"type":"Point"}
}