{
  "type": "Feature",
  "properties": {
    "gn:admin1_code":"6",
    "gn:asciiname":"Charakki",
    "gn:country_code":"PK",
    "gn:dem":387,
    "gn:feature_class":"P",
    "gn:feature_code":"PPL",
    "gn:name":"Charakki",
    "gn:population":0,
    "gn:timezone":"Asia/Karachi",
    "iso:country":"PK",
    "wof:name":"Charakki",
    "wof:placetype":"locality"
},
  "geometry": {"coordinates":[74.27324,32.89771],"type":"Point"}
}