{
  "type": "Feature",
  "properties": {
    "gn:admin1_code":"03",
    "gn:asciiname":"Saiyeduwali",
    "gn:country_code":"PK",
    "gn:dem":185,
    "gn:feature_class":"P",
    "gn:feature_code":"PPL",
    "gn:name":"Saiyeduwali",
    "gn:population":0,
    "gn:timezone":"Asia/Karachi",
    "iso:country":"PK",
    "name:und_x_variant":[
        "Sajuwala",
        "Saidu Wali",
        "Saiyeduwali",
        "Saiyiduw\u0101li"
    ],
    "wof:name":"Saiyeduwali",
    "wof:placetype":"locality"
},
  "geometry": {"coordinates":[71.03506999999998,32.19231],"type":"Point"}
}