{
  "type": "Feature",
  "properties": {
    "gn:admin1_code":"4.0",
    "gn:asciiname":"Jaidke",
    "gn:country_code":"PK",
    "gn:dem":213,
    "gn:feature_class":"P",
    "gn:feature_code":"PPL",
    "gn:name":"Jaidke",
    "gn:population":0,
    "gn:timezone":"Asia/Karachi",
    "iso:country":"PK",
    "wof:name":"Jaidke",
    "wof:placetype":"locality"
},
  "geometry": {"coordinates":[73.76464,32.06283],"type":"Point"}
}