{
  "type": "Feature",
  "properties": {
    "gn:admin1_code":"3.0",
    "gn:asciiname":"Dupar Banda",
    "gn:country_code":"PK",
    "gn:dem":372,
    "gn:feature_class":"P",
    "gn:feature_code":"PPL",
    "gn:name":"Dupar Banda",
    "gn:population":0,
    "gn:timezone":"Asia/Karachi",
    "iso:country":"PK",
    "wof:name":"Dupar Banda",
    "wof:placetype":"locality"
},
  "geometry": {"coordinates":[71.67125,33.31816],"type":"Point"}
}