{
  "type": "Feature",
  "properties": {
    "gn:admin1_code":"5",
    "gn:asciiname":"Goth Muhammad Ramzan",
    "gn:country_code":"PK",
    "gn:dem":13,
    "gn:feature_class":"P",
    "gn:feature_code":"PPL",
    "gn:name":"Goth Muhammad Ramzan",
    "gn:population":0,
    "gn:timezone":"Asia/Karachi",
    "iso:country":"PK",
    "name:und_x_variant":[
        "Goth Punj\u0101bi"
    ],
    "wof:name":"Goth Muhammad Ramzan",
    "wof:placetype":"locality"
},
  "geometry": {"coordinates":[69.16048000000001,25.2515],"type":"Point"}
}