{
  "type": "Feature",
  "properties": {
    "gn:admin1_code":"3",
    "gn:asciiname":"Jabba Kangra Doga",
    "gn:country_code":"PK",
    "gn:dem":1348,
    "gn:feature_class":"P",
    "gn:feature_code":"PPL",
    "gn:name":"Jabba Kangra Doga",
    "gn:population":0,
    "gn:timezone":"Asia/Karachi",
    "iso:country":"PK",
    "name:und_x_variant":[
        "Jabba Kangar Doga"
    ],
    "wof:name":"Jabba Kangra Doga",
    "wof:placetype":"locality"
},
  "geometry": {"coordinates":[72.93559999999999,34.30191],"type":"Point"}
}