{
  "type": "Feature",
  "properties": {
    "gn:admin1_code":"4",
    "gn:asciiname":"Dhok Muhammad Khan",
    "gn:country_code":"PK",
    "gn:dem":222,
    "gn:feature_class":"P",
    "gn:feature_code":"PPL",
    "gn:name":"Dhok Muhammad Khan",
    "gn:population":0,
    "gn:timezone":"Asia/Karachi",
    "iso:country":"PK",
    "name:und_x_variant":[
        "Dhak Muhammad Kh\u0101n",
        "Dhok Muhammad Khan"
    ],
    "wof:name":"Dhok Muhammad Khan",
    "wof:placetype":"locality"
},
  "geometry": {"coordinates":[73.68358000000001,32.62608],"type":"Point"}
}