{
  "type": "Feature",
  "properties": {
    "gn:admin1_code":"4.0",
    "gn:asciiname":"Basti Awanwala",
    "gn:country_code":"PK",
    "gn:dem":113,
    "gn:feature_class":"P",
    "gn:feature_code":"PPL",
    "gn:name":"Basti Awanwala",
    "gn:population":0,
    "gn:timezone":"Asia/Karachi",
    "iso:country":"PK",
    "name:und_x_variant":[
        "Q\u0101ziw\u0101li"
    ],
    "wof:name":"Basti Awanwala",
    "wof:placetype":"locality"
},
  "geometry": {"coordinates":[71.18069,29.9379],"type":"Point"}
}