{
  "type": "Feature",
  "properties": {
    "gn:admin1_code":"7.0",
    "gn:asciiname":"Henzal Pam",
    "gn:country_code":"PK",
    "gn:dem":1519,
    "gn:feature_class":"P",
    "gn:feature_code":"PPL",
    "gn:name":"Henzal Pam",
    "gn:population":0,
    "gn:timezone":"Asia/Karachi",
    "iso:country":"PK",
    "name:und_x_variant":[
        "Henzal K\u0101\u012bn",
        "Henzal",
        "Henzal Pam"
    ],
    "wof:name":"Henzal Pam",
    "wof:placetype":"locality"
},
  "geometry": {"coordinates":[74.20843000000001,35.95348],"type":"Point"}
}