{
  "type": "Feature",
  "properties": {
    "gn:admin1_code":"4",
    "gn:asciiname":"Chak One Hundred Eight- Fifteen Left",
    "gn:country_code":"PK",
    "gn:dem":143,
    "gn:feature_class":"P",
    "gn:feature_code":"PPL",
    "gn:name":"Chak One Hundred Eight- Fifteen Left",
    "gn:population":0,
    "gn:timezone":"Asia/Karachi",
    "iso:country":"PK",
    "name:und_x_variant":[
        "Chak One Hundred Eight-Fifteen L"
    ],
    "wof:name":"Chak One Hundred Eight- Fifteen Left",
    "wof:placetype":"locality"
},
  "geometry": {"coordinates":[72.23276,30.34829],"type":"Point"}
}