{
  "type": "Feature",
  "properties": {
    "gn:admin1_code":"3.0",
    "gn:asciiname":"Aldo",
    "gn:country_code":"PK",
    "gn:dem":325,
    "gn:feature_class":"P",
    "gn:feature_code":"PPL",
    "gn:name":"Aldo",
    "gn:population":0,
    "gn:timezone":"Asia/Karachi",
    "iso:country":"PK",
    "name:ceb_x_preferred":[
        "Aldo"
    ],
    "name:epo_x_preferred":[
        "Aldo"
    ],
    "name:fra_x_preferred":[
        "Aldo"
    ],
    "name:heb_x_preferred":[
        "\u05d0\u05dc\u05d3\u05d5"
    ],
    "name:ita_x_preferred":[
        "Aldo"
    ],
    "name:jpn_x_preferred":[
        "\u30a2\u30eb\u30c9"
    ],
    "name:srp_x_preferred":[
        "AldO"
    ],
    "name:swe_x_preferred":[
        "Aldo"
    ],
    "wof:name":"Aldo",
    "wof:placetype":"locality"
},
  "geometry": {"coordinates":[72.58068,33.98057],"type":"Point"}
}