{
  "type": "Feature",
  "properties": {
    "gn:admin1_code":"4",
    "gn:asciiname":"Roulia",
    "gn:country_code":"PK",
    "gn:dem":290,
    "gn:feature_class":"P",
    "gn:feature_code":"PPL",
    "gn:name":"Roulia",
    "gn:population":0,
    "gn:timezone":"Asia/Karachi",
    "iso:country":"PK",
    "name:und_x_variant":[
        "R\u0101ulia"
    ],
    "wof:name":"Roulia",
    "wof:placetype":"locality"
},
  "geometry": {"coordinates":[74.06498000000001,32.79667],"type":"Point"}
}