{
  "type": "Feature",
  "properties": {
    "gn:admin1_code":"6",
    "gn:asciiname":"Chobsar",
    "gn:country_code":"PK",
    "gn:dem":2899,
    "gn:feature_class":"P",
    "gn:feature_code":"PPL",
    "gn:name":"Chobsar",
    "gn:population":0,
    "gn:timezone":"Asia/Karachi",
    "iso:country":"PK",
    "wof:name":"Chobsar",
    "wof:placetype":"locality"
},
  "geometry": {"coordinates":[73.52296,34.54015],"type":"Point"}
}