{
  "type": "Feature",
  "properties": {
    "gn:admin1_code":"4.0",
    "gn:asciiname":"Dhok Sittala",
    "gn:country_code":"PK",
    "gn:dem":438,
    "gn:feature_class":"P",
    "gn:feature_code":"PPL",
    "gn:name":"Dhok Sittala",
    "gn:population":0,
    "gn:timezone":"Asia/Karachi",
    "iso:country":"PK",
    "name:und_x_variant":[
        "Shat\u0101la"
    ],
    "wof:name":"Dhok Sittala",
    "wof:placetype":"locality"
},
  "geometry": {"coordinates":[71.86736999999999,32.61216],"type":"Point"}
}