{
  "type": "Feature",
  "properties": {
    "gn:admin1_code":"3",
    "gn:asciiname":"Merer",
    "gn:country_code":"PK",
    "gn:dem":763,
    "gn:feature_class":"P",
    "gn:feature_code":"PPL",
    "gn:name":"Merer",
    "gn:population":0,
    "gn:timezone":"Asia/Karachi",
    "iso:country":"PK",
    "name:und_x_variant":[
        "Marer"
    ],
    "wof:name":"Merer",
    "wof:placetype":"locality"
},
  "geometry": {"coordinates":[72.82451,34.7701],"type":"Point"}
}