{
  "type": "Feature",
  "properties": {
    "gn:admin1_code":"04",
    "gn:asciiname":"Chak Two Hundred Thirty-four",
    "gn:country_code":"PK",
    "gn:dem":196,
    "gn:feature_class":"P",
    "gn:feature_code":"PPL",
    "gn:name":"Chak Two Hundred Thirty-four",
    "gn:population":0,
    "gn:timezone":"Asia/Karachi",
    "iso:country":"PK",
    "name:und_x_variant":[
        "Paniala",
        "Pati\u0101la",
        "Chak Two Hundred Thirty-four"
    ],
    "wof:name":"Chak Two Hundred Thirty-four",
    "wof:placetype":"locality"
},
  "geometry": {"coordinates":[73.50624999999999,31.40896],"type":"Point"}
}