{
  "type": "Feature",
  "properties": {
    "gn:admin1_code":"4",
    "gn:asciiname":"Chak Three Hundred Five Gugera Branch",
    "gn:country_code":"PK",
    "gn:dem":151,
    "gn:feature_class":"P",
    "gn:feature_code":"PPL",
    "gn:name":"Chak Three Hundred Five Gugera Branch",
    "gn:population":0,
    "gn:timezone":"Asia/Karachi",
    "iso:country":"PK",
    "name:und_x_variant":[
        "Chak Three Hundred Five GB",
        "Zam\u0101natpur",
        "Chak Three Hundred Five Gugera Branch"
    ],
    "wof:name":"Chak Three Hundred Five Gugera Branch",
    "wof:placetype":"locality"
},
  "geometry": {"coordinates":[72.33424000000002,30.89724],"type":"Point"}
}