{
  "type": "Feature",
  "properties": {
    "gn:admin1_code":"5.0",
    "gn:asciiname":"Bahar Khan Jo Goth",
    "gn:country_code":"PK",
    "gn:dem":55,
    "gn:feature_class":"P",
    "gn:feature_code":"PPL",
    "gn:name":"Bahar Khan Jo Goth",
    "gn:population":0,
    "gn:timezone":"Asia/Karachi",
    "iso:country":"PK",
    "name:und_x_variant":[
        "Bah\u0101r Kh\u0101n"
    ],
    "wof:name":"Bahar Khan Jo Goth",
    "wof:placetype":"locality"
},
  "geometry": {"coordinates":[68.68916999999999,27.47275],"type":"Point"}
}