{
  "type": "Feature",
  "properties": {
    "gn:admin1_code":"4.0",
    "gn:asciiname":"Dhera",
    "gn:country_code":"PK",
    "gn:dem":880,
    "gn:feature_class":"P",
    "gn:feature_code":"PPL",
    "gn:name":"Dhera",
    "gn:population":0,
    "gn:timezone":"Asia/Karachi",
    "iso:country":"PK",
    "name:und_x_variant":[
        "Dera",
        "Dehra",
        "Dhera"
    ],
    "wof:name":"Dhera",
    "wof:placetype":"locality"
},
  "geometry": {"coordinates":[73.11891999999997,32.78738],"type":"Point"}
}