{
  "type": "Feature",
  "properties": {
    "gn:admin1_code":"3",
    "gn:asciiname":"Shahwai",
    "gn:country_code":"PK",
    "gn:dem":975,
    "gn:feature_class":"P",
    "gn:feature_code":"PPL",
    "gn:name":"Shahwai",
    "gn:population":0,
    "gn:timezone":"Asia/Karachi",
    "iso:country":"PK",
    "name:und_x_variant":[
        "Shawai",
        "Sh\u0101fiwai",
        "Shahwai"
    ],
    "wof:name":"Shahwai",
    "wof:placetype":"locality"
},
  "geometry": {"coordinates":[72.71167,34.38644],"type":"Point"}
}