{
  "type": "Feature",
  "properties": {
    "gn:admin1_code":"2",
    "gn:asciiname":"Nasir Pir",
    "gn:country_code":"PK",
    "gn:dem":1234,
    "gn:feature_class":"P",
    "gn:feature_code":"PPL",
    "gn:name":"Nasir Pir",
    "gn:population":0,
    "gn:timezone":"Asia/Karachi",
    "iso:country":"PK",
    "wof:name":"Nasir Pir",
    "wof:placetype":"locality"
},
  "geometry": {"coordinates":[68.91169000000001,30.39604000000001],"type":"Point"}
}