{
  "type": "Feature",
  "properties": {
    "gn:admin1_code":"7.0",
    "gn:asciiname":"Gorabad",
    "gn:country_code":"PK",
    "gn:dem":2406,
    "gn:feature_class":"P",
    "gn:feature_code":"PPL",
    "gn:name":"Gorabad",
    "gn:population":0,
    "gn:timezone":"Asia/Karachi",
    "iso:country":"PK",
    "name:und_x_variant":[
        "Gor"
    ],
    "wof:name":"Gorabad",
    "wof:placetype":"locality"
},
  "geometry": {"coordinates":[74.50568,35.53176],"type":"Point"}
}