{
  "type": "Feature",
  "properties": {
    "gn:admin1_code":"4",
    "gn:asciiname":"Chah Iniatwala",
    "gn:country_code":"PK",
    "gn:dem":133,
    "gn:feature_class":"P",
    "gn:feature_code":"PPL",
    "gn:name":"Chah Iniatwala",
    "gn:population":0,
    "gn:timezone":"Asia/Karachi",
    "iso:country":"PK",
    "name:und_x_variant":[
        "In\u0101itw\u0101la"
    ],
    "wof:name":"Chah Iniatwala",
    "wof:placetype":"locality"
},
  "geometry": {"coordinates":[71.78683000000002,30.51073],"type":"Point"}
}