{
  "type": "Feature",
  "properties": {
    "gn:admin1_code":"4",
    "gn:asciiname":"Janduwal",
    "gn:country_code":"PK",
    "gn:dem":175,
    "gn:feature_class":"P",
    "gn:feature_code":"PPL",
    "gn:name":"Janduwal",
    "gn:population":0,
    "gn:timezone":"Asia/Karachi",
    "iso:country":"PK",
    "name:und_x_variant":[
        "Janduw\u0101l Kohna"
    ],
    "wof:name":"Janduwal",
    "wof:placetype":"locality"
},
  "geometry": {"coordinates":[73.74209999999999,30.70018],"type":"Point"}
}