{
  "type": "Feature",
  "properties": {
    "gn:admin1_code":"3.0",
    "gn:asciiname":"Besehkai",
    "gn:country_code":"PK",
    "gn:dem":1024,
    "gn:feature_class":"P",
    "gn:feature_code":"PPL",
    "gn:name":"Besehkai",
    "gn:population":0,
    "gn:timezone":"Asia/Karachi",
    "iso:country":"PK",
    "name:und_x_variant":[
        "Bihaki",
        "Bihakki",
        "Besehkai"
    ],
    "wof:name":"Besehkai",
    "wof:placetype":"locality"
},
  "geometry": {"coordinates":[73.02327,34.10761],"type":"Point"}
}