{
  "type": "Feature",
  "properties": {
    "gn:admin1_code":"5",
    "gn:asciiname":"Goth Khair Muhammad Khambara",
    "gn:country_code":"PK",
    "gn:dem":77,
    "gn:feature_class":"P",
    "gn:feature_code":"PPL",
    "gn:name":"Goth Khair Muhammad Khambara",
    "gn:population":0,
    "gn:timezone":"Asia/Karachi",
    "iso:country":"PK",
    "name:und_x_variant":[
        "Khair Muhammad Khambra"
    ],
    "wof:name":"Goth Khair Muhammad Khambara",
    "wof:placetype":"locality"
},
  "geometry": {"coordinates":[69.81088000000001,28.29354],"type":"Point"}
}