{
  "type": "Feature",
  "properties": {
    "gn:admin1_code":"05",
    "gn:asciiname":"Goth Nagar Chandio",
    "gn:country_code":"PK",
    "gn:dem":38,
    "gn:feature_class":"P",
    "gn:feature_code":"PPL",
    "gn:name":"Goth Nagar Chandio",
    "gn:population":0,
    "gn:timezone":"Asia/Karachi",
    "iso:country":"PK",
    "name:und_x_variant":[
        "Mangar Ch\u0101ndio"
    ],
    "wof:name":"Goth Nagar Chandio",
    "wof:placetype":"locality"
},
  "geometry": {"coordinates":[68.05289999999999,26.34058],"type":"Point"}
}