{
  "type": "Feature",
  "properties": {
    "gn:admin1_code":"2.0",
    "gn:asciiname":"Ali Bakhsh",
    "gn:country_code":"PK",
    "gn:dem":717,
    "gn:feature_class":"P",
    "gn:feature_code":"PPL",
    "gn:name":"Ali Bakhsh",
    "gn:population":0,
    "gn:timezone":"Asia/Karachi",
    "iso:country":"PK",
    "wof:name":"Ali Bakhsh",
    "wof:placetype":"locality"
},
  "geometry": {"coordinates":[66.92146,26.74248],"type":"Point"}
}