{
  "type": "Feature",
  "properties": {
    "gn:admin1_code":"3.0",
    "gn:asciiname":"Shirin Baihk",
    "gn:country_code":"PK",
    "gn:dem":3593,
    "gn:feature_class":"P",
    "gn:feature_code":"PPL",
    "gn:name":"Shirin Baihk",
    "gn:population":0,
    "gn:timezone":"Asia/Karachi",
    "iso:country":"PK",
    "wof:name":"Shirin Baihk",
    "wof:placetype":"locality"
},
  "geometry": {"coordinates":[73.57051,35.36554],"type":"Point"}
}