{
  "type": "Feature",
  "properties": {
    "gn:admin1_code":"4",
    "gn:asciiname":"Dera Lalu",
    "gn:country_code":"PK",
    "gn:dem":192,
    "gn:feature_class":"P",
    "gn:feature_code":"PPL",
    "gn:name":"Dera Lalu",
    "gn:population":0,
    "gn:timezone":"Asia/Karachi",
    "iso:country":"PK",
    "name:und_x_variant":[
        "L\u0101lu"
    ],
    "wof:name":"Dera Lalu",
    "wof:placetype":"locality"
},
  "geometry": {"coordinates":[72.11344,32.27472],"type":"Point"}
}