{
  "type": "Feature",
  "properties": {
    "gn:admin1_code":"4",
    "gn:asciiname":"Chak Two Hundred Forty",
    "gn:country_code":"PK",
    "gn:dem":172,
    "gn:feature_class":"P",
    "gn:feature_code":"PPL",
    "gn:name":"Chak Two Hundred Forty",
    "gn:population":0,
    "gn:timezone":"Asia/Karachi",
    "iso:country":"PK",
    "name:eng_x_preferred":[
        "Chak Two Hundred Forty"
    ],
    "name:und_x_variant":[
        "Adhl\u0101na",
        "Hindi\u0101na"
    ],
    "wof:name":"Chak Two Hundred Forty",
    "wof:placetype":"locality"
},
  "geometry": {"coordinates":[72.70350000000001,31.48054],"type":"Point"}
}