{
  "type": "Feature",
  "properties": {
    "gn:admin1_code":"6.0",
    "gn:asciiname":"Sakian",
    "gn:country_code":"PK",
    "gn:dem":2557,
    "gn:feature_class":"P",
    "gn:feature_code":"PPL",
    "gn:name":"Sakian",
    "gn:population":0,
    "gn:timezone":"Asia/Karachi",
    "iso:country":"PK",
    "wof:name":"Sakian",
    "wof:placetype":"locality"
},
  "geometry": {"coordinates":[74.00219,33.94446],"type":"Point"}
}