{
  "type": "Feature",
  "properties": {
    "gn:admin1_code":"3.0",
    "gn:asciiname":"Kalu Maira",
    "gn:country_code":"PK",
    "gn:dem":889,
    "gn:feature_class":"P",
    "gn:feature_code":"PPL",
    "gn:name":"Kalu Maira",
    "gn:population":0,
    "gn:timezone":"Asia/Karachi",
    "iso:country":"PK",
    "name:und_x_variant":[
        "Kalu Mera",
        "Kalu Maira"
    ],
    "wof:name":"Kalu Maira",
    "wof:placetype":"locality"
},
  "geometry": {"coordinates":[73.09841,34.04547],"type":"Point"}
}