{
  "type": "Feature",
  "properties": {
    "gn:admin1_code":"4",
    "gn:asciiname":"Khara",
    "gn:country_code":"PK",
    "gn:dem":119,
    "gn:feature_class":"P",
    "gn:feature_code":"PPL",
    "gn:name":"Khara",
    "gn:population":0,
    "gn:timezone":"Asia/Karachi",
    "iso:country":"PK",
    "name:ceb_x_preferred":[
        "Khara"
    ],
    "name:deu_x_preferred":[
        "Khara"
    ],
    "name:new_x_preferred":[
        "\u0916\u0930\u093e"
    ],
    "name:swe_x_preferred":[
        "Khara"
    ],
    "wof:name":"Khara",
    "wof:placetype":"locality"
},
  "geometry": {"coordinates":[71.08534,30.04401],"type":"Point"}
}