{
  "type": "Feature",
  "properties": {
    "gn:admin1_code":"4.0",
    "gn:asciiname":"Ghamrola",
    "gn:country_code":"PK",
    "gn:dem":288,
    "gn:feature_class":"P",
    "gn:feature_code":"PPL",
    "gn:name":"Ghamrola",
    "gn:population":0,
    "gn:timezone":"Asia/Karachi",
    "iso:country":"PK",
    "name:und_x_variant":[
        "Ghamrula",
        "Ghamrola"
    ],
    "wof:name":"Ghamrola",
    "wof:placetype":"locality"
},
  "geometry": {"coordinates":[75.00161999999997,32.39586],"type":"Point"}
}