{
  "type": "Feature",
  "properties": {
    "gn:admin1_code":"04",
    "gn:asciiname":"Chak Four Hundred Ninety",
    "gn:country_code":"PK",
    "gn:dem":169,
    "gn:feature_class":"P",
    "gn:feature_code":"PPL",
    "gn:name":"Chak Four Hundred Ninety",
    "gn:population":0,
    "gn:timezone":"Asia/Karachi",
    "iso:country":"PK",
    "name:und_x_variant":[
        "M\u0101nakpur",
        "M\u0101nkpur"
    ],
    "wof:name":"Chak Four Hundred Ninety",
    "wof:placetype":"locality"
},
  "geometry": {"coordinates":[72.82571999999998,30.88725],"type":"Point"}
}