{
  "type": "Feature",
  "properties": {
    "gn:admin1_code":"03",
    "gn:asciiname":"Tarlajar",
    "gn:country_code":"PK",
    "gn:dem":3186,
    "gn:feature_class":"P",
    "gn:feature_code":"PPL",
    "gn:name":"Tarlajar",
    "gn:population":0,
    "gn:timezone":"Asia/Karachi",
    "iso:country":"PK",
    "name:und_x_variant":[
        "Tarla Jor"
    ],
    "wof:name":"Tarlajar",
    "wof:placetype":"locality"
},
  "geometry": {"coordinates":[73.95195,35.0093],"type":"Point"}
}