{
  "type": "Feature",
  "properties": {
    "gn:admin1_code":"6",
    "gn:asciiname":"Kainthi",
    "gn:country_code":"PK",
    "gn:dem":793,
    "gn:feature_class":"P",
    "gn:feature_code":"PPL",
    "gn:name":"Kainthi",
    "gn:population":0,
    "gn:timezone":"Asia/Karachi",
    "iso:country":"PK",
    "name:und_x_variant":[
        "Kainhi"
    ],
    "wof:name":"Kainthi",
    "wof:placetype":"locality"
},
  "geometry": {"coordinates":[74.0578,33.30687],"type":"Point"}
}