{
  "type": "Feature",
  "properties": {
    "gn:admin1_code":"4.0",
    "gn:asciiname":"Chak Sixty-seven D",
    "gn:country_code":"PK",
    "gn:dem":166,
    "gn:feature_class":"P",
    "gn:feature_code":"PPL",
    "gn:name":"Chak Sixty-seven D",
    "gn:population":0,
    "gn:timezone":"Asia/Karachi",
    "iso:country":"PK",
    "name:und_x_variant":[
        "Rak\u012banw\u0101la"
    ],
    "wof:name":"Chak Sixty-seven D",
    "wof:placetype":"locality"
},
  "geometry": {"coordinates":[73.3918,30.51668],"type":"Point"}
}