{
  "type": "Feature",
  "properties": {
    "gn:admin1_code":"2.0",
    "gn:asciiname":"Shaikh Ali Karez",
    "gn:country_code":"PK",
    "gn:dem":1600,
    "gn:feature_class":"P",
    "gn:feature_code":"PPL",
    "gn:name":"Shaikh Ali Karez",
    "gn:population":0,
    "gn:timezone":"Asia/Karachi",
    "iso:country":"PK",
    "wof:name":"Shaikh Ali Karez",
    "wof:placetype":"locality"
},
  "geometry": {"coordinates":[66.95952,30.26776],"type":"Point"}
}