{
  "type": "Feature",
  "properties": {
    "gn:admin1_code":"2.0",
    "gn:asciiname":"Lakarai Kili",
    "gn:country_code":"PK",
    "gn:dem":1848,
    "gn:feature_class":"P",
    "gn:feature_code":"PPL",
    "gn:name":"Lakarai Kili",
    "gn:population":0,
    "gn:timezone":"Asia/Karachi",
    "iso:country":"PK",
    "wof:name":"Lakarai Kili",
    "wof:placetype":"locality"
},
  "geometry": {"coordinates":[66.45406,30.5836],"type":"Point"}
}