{
  "type": "Feature",
  "properties": {
    "gn:admin1_code":"2",
    "gn:asciiname":"Thal Gola",
    "gn:country_code":"PK",
    "gn:dem":107,
    "gn:feature_class":"P",
    "gn:feature_code":"PPL",
    "gn:name":"Thal Gola",
    "gn:population":0,
    "gn:timezone":"Asia/Karachi",
    "iso:country":"PK",
    "wof:name":"Thal Gola",
    "wof:placetype":"locality"
},
  "geometry": {"coordinates":[67.65611,29.1411],"type":"Point"}
}