{
  "type": "Feature",
  "properties": {
    "gn:admin1_code":"3.0",
    "gn:asciiname":"Zakria Dhok",
    "gn:country_code":"PK",
    "gn:dem":386,
    "gn:feature_class":"P",
    "gn:feature_code":"PPL",
    "gn:name":"Zakria Dhok",
    "gn:population":0,
    "gn:timezone":"Asia/Karachi",
    "iso:country":"PK",
    "wof:name":"Zakria Dhok",
    "wof:placetype":"locality"
},
  "geometry": {"coordinates":[71.58756,33.44233],"type":"Point"}
}