{
  "type": "Feature",
  "properties": {
    "gn:admin1_code":"4",
    "gn:asciiname":"Sarobe",
    "gn:country_code":"PK",
    "gn:dem":239,
    "gn:feature_class":"P",
    "gn:feature_code":"PPL",
    "gn:name":"Sarobe",
    "gn:population":0,
    "gn:timezone":"Asia/Karachi",
    "iso:country":"PK",
    "wof:name":"Sarobe",
    "wof:placetype":"locality"
},
  "geometry": {"coordinates":[74.42833,32.60088],"type":"Point"}
}