{
  "type": "Feature",
  "properties": {
    "gn:admin1_code":"3.0",
    "gn:asciiname":"Ushdaruh",
    "gn:country_code":"PK",
    "gn:dem":3727,
    "gn:feature_class":"P",
    "gn:feature_code":"PPL",
    "gn:name":"Ushdaruh",
    "gn:population":0,
    "gn:timezone":"Asia/Karachi",
    "iso:country":"PK",
    "wof:name":"Ushdaruh",
    "wof:placetype":"locality"
},
  "geometry": {"coordinates":[73.37,36.8536],"type":"Point"}
}