{
  "type": "Feature",
  "properties": {
    "gn:admin1_code":"3.0",
    "gn:asciiname":"Atteran",
    "gn:country_code":"PK",
    "gn:dem":969,
    "gn:feature_class":"P",
    "gn:feature_code":"PPL",
    "gn:name":"Atteran",
    "gn:population":0,
    "gn:timezone":"Asia/Karachi",
    "iso:country":"PK",
    "name:eng_x_preferred":[
        "Ateran"
    ],
    "wof:name":"Atteran",
    "wof:placetype":"locality"
},
  "geometry": {"coordinates":[73.21947,33.86395],"type":"Point"}
}