{
  "type": "Feature",
  "properties": {
    "gn:admin1_code":"6",
    "gn:asciiname":"Narat",
    "gn:country_code":"PK",
    "gn:dem":1353,
    "gn:feature_class":"P",
    "gn:feature_code":"PPL",
    "gn:name":"Narat",
    "gn:population":0,
    "gn:timezone":"Asia/Karachi",
    "iso:country":"PK",
    "wof:name":"Narat",
    "wof:placetype":"locality"
},
  "geometry": {"coordinates":[73.5766,34.19239],"type":"Point"}
}