{
  "type": "Feature",
  "properties": {
    "gn:admin1_code":"6",
    "gn:asciiname":"Narat",
    "gn:country_code":"PK",
    "gn:dem":1353,
    "gn:feature_class":"P",
    "gn:feature_code":"PPL",
    "gn:name":"Narat",
    "gn:population":0,
    "gn:timezone":"Asia/Karachi",
    "iso:country":"PK",
    "name:bos_x_preferred":[
        "Narat"
    ],
    "name:fra_x_preferred":[
        "Narat"
    ],
    "name:rus_x_preferred":[
        "\u041d\u0430\u0440\u0430\u0442"
    ],
    "name:slv_x_preferred":[
        "Narat"
    ],
    "name:srp_x_preferred":[
        "\u041d\u0430\u0440\u0430\u0442"
    ],
    "wof:name":"Narat",
    "wof:placetype":"locality"
},
  "geometry": {"coordinates":[73.5766,34.19239],"type":"Point"}
}