{
  "type": "Feature",
  "properties": {
    "gn:admin1_code":"3",
    "gn:asciiname":"Kharairai",
    "gn:country_code":"PK",
    "gn:dem":1128,
    "gn:feature_class":"P",
    "gn:feature_code":"PPL",
    "gn:name":"Kharairai",
    "gn:population":0,
    "gn:timezone":"Asia/Karachi",
    "iso:country":"PK",
    "wof:name":"Kharairai",
    "wof:placetype":"locality"
},
  "geometry": {"coordinates":[72.40505999999998,34.93321],"type":"Point"}
}