{
  "type": "Feature",
  "properties": {
    "gn:admin1_code":"4.0",
    "gn:asciiname":"Kirri Ziarat",
    "gn:country_code":"PK",
    "gn:dem":294,
    "gn:feature_class":"P",
    "gn:feature_code":"PPL",
    "gn:name":"Kirri Ziarat",
    "gn:population":0,
    "gn:timezone":"Asia/Karachi",
    "iso:country":"PK",
    "wof:name":"Kirri Ziarat",
    "wof:placetype":"locality"
},
  "geometry": {"coordinates":[71.76405,33.06027],"type":"Point"}
}