{
  "type": "Feature",
  "properties": {
    "gn:admin1_code":"4",
    "gn:asciiname":"Chak Three Hundred Eleven Gugera Branch",
    "gn:country_code":"PK",
    "gn:dem":149,
    "gn:feature_class":"P",
    "gn:feature_code":"PPL",
    "gn:name":"Chak Three Hundred Eleven Gugera Branch",
    "gn:population":0,
    "gn:timezone":"Asia/Karachi",
    "iso:country":"PK",
    "name:und_x_variant":[
        "Chak Three Hundred Eleven GB",
        "Wains Aw\u0101n",
        "Chak Three Hundred Eleven Gugera Branch"
    ],
    "wof:name":"Chak Three Hundred Eleven Gugera Branch",
    "wof:placetype":"locality"
},
  "geometry": {"coordinates":[72.31394,30.82996],"type":"Point"}
}