{
  "type": "Feature",
  "properties": {
    "gn:admin1_code":"4.0",
    "gn:asciiname":"Bhatewala",
    "gn:country_code":"PK",
    "gn:dem":144,
    "gn:feature_class":"P",
    "gn:feature_code":"PPL",
    "gn:name":"Bhatew\u0101la",
    "gn:population":0,
    "gn:timezone":"Asia/Karachi",
    "iso:country":"PK",
    "name:eng_x_preferred":[
        "Bhatew\u0101la"
    ],
    "wof:name":"Bhatewala",
    "wof:placetype":"locality"
},
  "geometry": {"coordinates":[70.97815,30.76671],"type":"Point"}
}