{
  "type": "Feature",
  "properties": {
    "gn:admin1_code":"1.0",
    "gn:asciiname":"Haqdarra Kili",
    "gn:country_code":"PK",
    "gn:dem":2120,
    "gn:feature_class":"P",
    "gn:feature_code":"PPL",
    "gn:name":"Haqdarra Kili",
    "gn:population":0,
    "gn:timezone":"Asia/Karachi",
    "iso:country":"PK",
    "name:und_x_variant":[
        "Haqdara",
        "Haqdarra",
        "Haqdarra Kili"
    ],
    "wof:name":"Haqdarra Kili",
    "wof:placetype":"locality"
},
  "geometry": {"coordinates":[69.8922,33.92892],"type":"Point"}
}