{
  "type": "Feature",
  "properties": {
    "gn:admin1_code":"2.0",
    "gn:asciiname":"Kili Said Khan",
    "gn:country_code":"PK",
    "gn:dem":792,
    "gn:feature_class":"P",
    "gn:feature_code":"PPL",
    "gn:name":"Kili Said Khan",
    "gn:population":0,
    "gn:timezone":"Asia/Karachi",
    "iso:country":"PK",
    "wof:name":"Kili Said Khan",
    "wof:placetype":"locality"
},
  "geometry": {"coordinates":[65.59974,28.6926],"type":"Point"}
}