{
  "type": "Feature",
  "properties": {
    "gn:admin1_code":"4.0",
    "gn:asciiname":"Chak Balochian",
    "gn:country_code":"PK",
    "gn:dem":172,
    "gn:feature_class":"P",
    "gn:feature_code":"PPL",
    "gn:name":"Chak Balochian",
    "gn:population":0,
    "gn:timezone":"Asia/Karachi",
    "iso:country":"PK",
    "wof:name":"Chak Balochian",
    "wof:placetype":"locality"
},
  "geometry": {"coordinates":[73.49361999999998,30.7072],"type":"Point"}
}