{
  "type": "Feature",
  "properties": {
    "gn:admin1_code":"2.0",
    "gn:asciiname":"Goth Gul Muhammad",
    "gn:country_code":"PK",
    "gn:dem":124,
    "gn:feature_class":"P",
    "gn:feature_code":"PPL",
    "gn:name":"Goth Gul Muhammad",
    "gn:population":0,
    "gn:timezone":"Asia/Karachi",
    "iso:country":"PK",
    "name:eng_x_preferred":[
        "Goth Gul Muhammad"
    ],
    "wof:name":"Goth Gul Muhammad",
    "wof:placetype":"locality"
},
  "geometry": {"coordinates":[66.96127,25.20656],"type":"Point"}
}