{
  "type": "Feature",
  "properties": {
    "gn:admin1_code":"4",
    "gn:asciiname":"Jaba",
    "gn:country_code":"PK",
    "gn:dem":566,
    "gn:feature_class":"P",
    "gn:feature_code":"PPL",
    "gn:name":"Jaba",
    "gn:population":0,
    "gn:timezone":"Asia/Karachi",
    "iso:country":"PK",
    "name:ceb_x_preferred":[
        "Jaba"
    ],
    "name:deu_x_preferred":[
        "Jaba"
    ],
    "name:fra_x_preferred":[
        "Jaba"
    ],
    "name:heb_x_preferred":[
        "\u05d2'\u05d1\u05e2"
    ],
    "name:hun_x_preferred":[
        "Jaba"
    ],
    "name:ita_x_preferred":[
        "Jaba"
    ],
    "name:nld_x_preferred":[
        "Jaba"
    ],
    "name:pol_x_preferred":[
        "Jaba"
    ],
    "name:por_x_preferred":[
        "Jab\u00e1"
    ],
    "name:rus_x_preferred":[
        "\u0414\u0436\u0430\u0431\u0430"
    ],
    "name:swe_x_preferred":[
        "Jaba"
    ],
    "wof:name":"Jaba",
    "wof:placetype":"locality"
},
  "geometry": {"coordinates":[72.21071999999999,32.7543],"type":"Point"}
}