{
  "type": "Feature",
  "properties": {
    "gn:admin1_code":"3.0",
    "gn:asciiname":"Banda Khandoran",
    "gn:country_code":"PK",
    "gn:dem":264,
    "gn:feature_class":"P",
    "gn:feature_code":"PPL",
    "gn:name":"Banda Khandoran",
    "gn:population":0,
    "gn:timezone":"Asia/Karachi",
    "iso:country":"PK",
    "wof:name":"Banda Khandoran",
    "wof:placetype":"locality"
},
  "geometry": {"coordinates":[70.83754,32.65238],"type":"Point"}
}