{
  "type": "Feature",
  "properties": {
    "gn:admin1_code":"2.0",
    "gn:asciiname":"Dadozai Kili",
    "gn:country_code":"PK",
    "gn:dem":1677,
    "gn:feature_class":"P",
    "gn:feature_code":"PPL",
    "gn:name":"Dadozai Kili",
    "gn:population":0,
    "gn:timezone":"Asia/Karachi",
    "iso:country":"PK",
    "name:und_x_variant":[
        "Dod\u0101zai Kili",
        "D\u0101do Zai",
        "Dadozai Kili"
    ],
    "wof:name":"Dadozai Kili",
    "wof:placetype":"locality"
},
  "geometry": {"coordinates":[69.38789,31.01686],"type":"Point"}
}