{
  "type": "Feature",
  "properties": {
    "gn:admin1_code":"3.0",
    "gn:asciiname":"Dandarai",
    "gn:country_code":"PK",
    "gn:dem":589,
    "gn:feature_class":"P",
    "gn:feature_code":"PPL",
    "gn:name":"Dandarai",
    "gn:population":0,
    "gn:timezone":"Asia/Karachi",
    "iso:country":"PK",
    "wof:name":"Dandarai",
    "wof:placetype":"locality"
},
  "geometry": {"coordinates":[72.79416999999999,34.56649],"type":"Point"}
}