{
  "type": "Feature",
  "properties": {
    "gn:admin1_code":"2",
    "gn:asciiname":"Khokhar Lahri",
    "gn:country_code":"PK",
    "gn:dem":93,
    "gn:feature_class":"P",
    "gn:feature_code":"PPL",
    "gn:name":"Khokhar Lahri",
    "gn:population":0,
    "gn:timezone":"Asia/Karachi",
    "iso:country":"PK",
    "wof:name":"Khokhar Lahri",
    "wof:placetype":"locality"
},
  "geometry": {"coordinates":[67.86511999999999,29.1406],"type":"Point"}
}