{
  "type": "Feature",
  "properties": {
    "gn:admin1_code":"4.0",
    "gn:asciiname":"Chandrami",
    "gn:country_code":"PK",
    "gn:dem":81,
    "gn:feature_class":"P",
    "gn:feature_code":"PPL",
    "gn:name":"Chandrami",
    "gn:population":0,
    "gn:timezone":"Asia/Karachi",
    "iso:country":"PK",
    "name:fas_x_preferred":[
        "\u0686\u0627\u0646\u062f\u0631\u0627\u0645\u06cc"
    ],
    "name:urd_x_preferred":[
        "\u0686\u0627\u0646\u062f \u0631\u0627\u0645\u06cc"
    ],
    "wof:name":"Chandrami",
    "wof:placetype":"locality"
},
  "geometry": {"coordinates":[70.17256,28.32968],"type":"Point"}
}