{
  "type": "Feature",
  "properties": {
    "gn:admin1_code":"4",
    "gn:asciiname":"Sapewala Kund",
    "gn:country_code":"PK",
    "gn:dem":546,
    "gn:feature_class":"P",
    "gn:feature_code":"PPL",
    "gn:name":"Sapewala Kund",
    "gn:population":0,
    "gn:timezone":"Asia/Karachi",
    "iso:country":"PK",
    "wof:name":"Sapewala Kund",
    "wof:placetype":"locality"
},
  "geometry": {"coordinates":[72.09036,32.6527],"type":"Point"}
}