{
  "type": "Feature",
  "properties": {
    "gn:admin1_code":"4",
    "gn:asciiname":"Mohra Mahmud",
    "gn:country_code":"PK",
    "gn:dem":495,
    "gn:feature_class":"P",
    "gn:feature_code":"PPL",
    "gn:name":"Mohra Mahmud",
    "gn:population":0,
    "gn:timezone":"Asia/Karachi",
    "iso:country":"PK",
    "name:und_x_variant":[
        "Mahm\u016bd Mohra"
    ],
    "wof:name":"Mohra Mahmud",
    "wof:placetype":"locality"
},
  "geometry": {"coordinates":[73.17019000000001,32.94841],"type":"Point"}
}