{
  "type": "Feature",
  "properties": {
    "gn:admin1_code":"7.0",
    "gn:asciiname":"Mankial",
    "gn:country_code":"PK",
    "gn:dem":2513,
    "gn:feature_class":"P",
    "gn:feature_code":"PPL",
    "gn:name":"Mankial",
    "gn:population":0,
    "gn:timezone":"Asia/Karachi",
    "iso:country":"PK",
    "name:und_x_variant":[
        "Mainki\u0101l"
    ],
    "wof:name":"Mankial",
    "wof:placetype":"locality"
},
  "geometry": {"coordinates":[74.88925999999999,35.25788],"type":"Point"}
}