{
  "type": "Feature",
  "properties": {
    "gn:admin1_code":"2.0",
    "gn:asciiname":"Abdu Goth",
    "gn:country_code":"PK",
    "gn:dem":714,
    "gn:feature_class":"P",
    "gn:feature_code":"PPL",
    "gn:name":"Abdu Goth",
    "gn:population":0,
    "gn:timezone":"Asia/Karachi",
    "iso:country":"PK",
    "wof:name":"Abdu Goth",
    "wof:placetype":"locality"
},
  "geometry": {"coordinates":[66.7717,26.26868],"type":"Point"}
}