{
  "type": "Feature",
  "properties": {
    "gn:admin1_code":"4",
    "gn:asciiname":"Dhok Telian",
    "gn:country_code":"PK",
    "gn:dem":481,
    "gn:feature_class":"P",
    "gn:feature_code":"PPL",
    "gn:name":"Dhok Telian",
    "gn:population":0,
    "gn:timezone":"Asia/Karachi",
    "iso:country":"PK",
    "wof:name":"Dhok Telian",
    "wof:placetype":"locality"
},
  "geometry": {"coordinates":[73.34983000000003,33.18494],"type":"Point"}
}