{
  "type": "Feature",
  "properties": {
    "gn:admin1_code":"3.0",
    "gn:asciiname":"Parez",
    "gn:country_code":"PK",
    "gn:dem":401,
    "gn:feature_class":"P",
    "gn:feature_code":"PPL",
    "gn:name":"Parez",
    "gn:population":0,
    "gn:timezone":"Asia/Karachi",
    "iso:country":"PK",
    "wof:name":"Parez",
    "wof:placetype":"locality"
},
  "geometry": {"coordinates":[70.57191,32.99859],"type":"Point"}
}