{
  "type": "Feature",
  "properties": {
    "gn:admin1_code":"2.0",
    "gn:asciiname":"Skhobi Dildor",
    "gn:country_code":"PK",
    "gn:dem":2211,
    "gn:feature_class":"P",
    "gn:feature_code":"PPL",
    "gn:name":"Skhobi Dildor",
    "gn:population":0,
    "gn:timezone":"Asia/Karachi",
    "iso:country":"PK",
    "wof:name":"Skhobi Dildor",
    "wof:placetype":"locality"
},
  "geometry": {"coordinates":[67.75904,31.029],"type":"Point"}
}