{
  "type": "Feature",
  "properties": {
    "gn:admin1_code":"2.0",
    "gn:asciiname":"Goth Sheikh Nur Muhammad",
    "gn:country_code":"PK",
    "gn:dem":39,
    "gn:feature_class":"P",
    "gn:feature_code":"PPLL",
    "gn:name":"Goth Sheikh Nur Muhammad",
    "gn:population":0,
    "gn:timezone":"Asia/Karachi",
    "iso:country":"PK",
    "wof:name":"Goth Sheikh Nur Muhammad",
    "wof:placetype":"locality"
},
  "geometry": {"coordinates":[66.5951,25.84062],"type":"Point"}
}