{
  "type": "Feature",
  "properties": {
    "gn:admin1_code":"3.0",
    "gn:asciiname":"Garah Bukhtiar",
    "gn:country_code":"PK",
    "gn:dem":228,
    "gn:feature_class":"P",
    "gn:feature_code":"PPL",
    "gn:name":"Garah Bukhtiar",
    "gn:population":0,
    "gn:timezone":"Asia/Karachi",
    "iso:country":"PK",
    "name:und_x_variant":[
        "Garah Bakhtiy\u0101r"
    ],
    "wof:name":"Garah Bukhtiar",
    "wof:placetype":"locality"
},
  "geometry": {"coordinates":[70.41786,32.00612],"type":"Point"}
}