{
  "type": "Feature",
  "properties": {
    "gn:admin1_code":"4",
    "gn:asciiname":"Sarinwala",
    "gn:country_code":"PK",
    "gn:dem":126,
    "gn:feature_class":"P",
    "gn:feature_code":"PPL",
    "gn:name":"Sar\u012bnw\u0101la",
    "gn:population":0,
    "gn:timezone":"Asia/Karachi",
    "iso:country":"PK",
    "name:eng_x_preferred":[
        "Sar\u012bnw\u0101la"
    ],
    "wof:name":"Sarinwala",
    "wof:placetype":"locality"
},
  "geometry": {"coordinates":[70.98191,30.32762],"type":"Point"}
}