{
  "type": "Feature",
  "properties": {
    "gn:admin1_code":"5.0",
    "gn:asciiname":"Goth Haji Hamza Khan Maltani",
    "gn:country_code":"PK",
    "gn:dem":28,
    "gn:feature_class":"P",
    "gn:feature_code":"PPL",
    "gn:name":"Goth Haji Hamza Khan Maltani",
    "gn:population":0,
    "gn:timezone":"Asia/Karachi",
    "iso:country":"PK",
    "wof:name":"Goth Haji Hamza Khan Maltani",
    "wof:placetype":"locality"
},
  "geometry": {"coordinates":[68.57101999999999,25.7642],"type":"Point"}
}