{
  "type": "Feature",
  "properties": {
    "gn:admin1_code":"6.0",
    "gn:asciiname":"Aimallyas",
    "gn:country_code":"PK",
    "gn:dem":239,
    "gn:feature_class":"P",
    "gn:feature_code":"PPL",
    "gn:name":"Aimallyas",
    "gn:population":0,
    "gn:timezone":"Asia/Karachi",
    "iso:country":"PK",
    "name:und_x_variant":[
        "Aima Ladian"
    ],
    "wof:name":"Aimallyas",
    "wof:placetype":"locality"
},
  "geometry": {"coordinates":[73.73023000000001,33.00055],"type":"Point"}
}