{
  "type": "Feature",
  "properties": {
    "gn:admin1_code":"2",
    "gn:asciiname":"Bangla",
    "gn:country_code":"PK",
    "gn:dem":988,
    "gn:feature_class":"P",
    "gn:feature_code":"PPL",
    "gn:name":"Bangla",
    "gn:population":0,
    "gn:timezone":"Asia/Karachi",
    "iso:country":"PK",
    "name:und_x_variant":[
        "Lagh\u0101ri Kot"
    ],
    "wof:name":"Bangla",
    "wof:placetype":"locality"
},
  "geometry": {"coordinates":[69.43174999999999,29.77624],"type":"Point"}
}