{
  "type": "Feature",
  "properties": {
    "gn:admin1_code":"4.0",
    "gn:asciiname":"Chak One Hundred Fifty",
    "gn:country_code":"PK",
    "gn:dem":81,
    "gn:feature_class":"P",
    "gn:feature_code":"PPL",
    "gn:name":"Chak One Hundred Fifty",
    "gn:population":0,
    "gn:timezone":"Asia/Karachi",
    "iso:country":"PK",
    "name:und_x_variant":[
        "Chak One Hundred Fifty P"
    ],
    "wof:name":"Chak One Hundred Fifty",
    "wof:placetype":"locality"
},
  "geometry": {"coordinates":[70.18359,28.27206],"type":"Point"}
}