{
  "type": "Feature",
  "properties": {
    "gn:admin1_code":"6",
    "gn:asciiname":"Trekanna",
    "gn:country_code":"PK",
    "gn:dem":3078,
    "gn:feature_class":"P",
    "gn:feature_code":"PPL",
    "gn:name":"Trekanna",
    "gn:population":0,
    "gn:timezone":"Asia/Karachi",
    "iso:country":"PK",
    "wof:name":"Trekanna",
    "wof:placetype":"locality"
},
  "geometry": {"coordinates":[73.57113000000003,34.57152],"type":"Point"}
}