{
  "type": "Feature",
  "properties": {
    "gn:admin1_code":"4.0",
    "gn:asciiname":"Pari Parial",
    "gn:country_code":"PK",
    "gn:dem":550,
    "gn:feature_class":"P",
    "gn:feature_code":"PPL",
    "gn:name":"Pari Parial",
    "gn:population":0,
    "gn:timezone":"Asia/Karachi",
    "iso:country":"PK",
    "wof:name":"Pari Parial",
    "wof:placetype":"locality"
},
  "geometry": {"coordinates":[73.21465999999999,33.28696],"type":"Point"}
}