{
  "type": "Feature",
  "properties": {
    "gn:admin1_code":"6.0",
    "gn:asciiname":"Dakkhana Bazar",
    "gn:country_code":"PK",
    "gn:dem":902,
    "gn:feature_class":"P",
    "gn:feature_code":"PPL",
    "gn:name":"Dakkhana Bazar",
    "gn:population":0,
    "gn:timezone":"Asia/Karachi",
    "iso:country":"PK",
    "wof:name":"Dakkhana Bazar",
    "wof:placetype":"locality"
},
  "geometry": {"coordinates":[74.13699,33.35188],"type":"Point"}
}