{
  "type": "Feature",
  "properties": {
    "gn:admin1_code":"4",
    "gn:asciiname":"Chak One Hundred Twelve Thal Development Authority",
    "gn:country_code":"PK",
    "gn:dem":151,
    "gn:feature_class":"P",
    "gn:feature_code":"PPL",
    "gn:name":"Chak One Hundred Twelve Thal Development Authority",
    "gn:population":0,
    "gn:timezone":"Asia/Karachi",
    "iso:country":"PK",
    "name:und_x_variant":[
        "Chak 112 TDA",
        "Chak One Hundred Twelve TDA",
        "Chak One Hundred Twelve Thal Development Authority"
    ],
    "wof:name":"Chak One Hundred Twelve Thal Development Authority",
    "wof:placetype":"locality"
},
  "geometry": {"coordinates":[71.04391,31.07623],"type":"Point"}
}