{
  "type": "Feature",
  "properties": {
    "gn:admin1_code":"2.0",
    "gn:asciiname":"Kili Shafi Muhammad",
    "gn:country_code":"PK",
    "gn:dem":706,
    "gn:feature_class":"P",
    "gn:feature_code":"PPL",
    "gn:name":"Kili Shafi Muhammad",
    "gn:population":0,
    "gn:timezone":"Asia/Karachi",
    "iso:country":"PK",
    "name:und_x_variant":[
        "Kili Umar J\u0101n",
        "Umar J\u0101n Kili",
        "Kili Shafi Muhammad"
    ],
    "wof:name":"Kili Shafi Muhammad",
    "wof:placetype":"locality"
},
  "geometry": {"coordinates":[65.4666,28.43648],"type":"Point"}
}