{
  "type": "Feature",
  "properties": {
    "gn:admin1_code":"4",
    "gn:asciiname":"Kerwara",
    "gn:country_code":"PK",
    "gn:dem":205,
    "gn:feature_class":"P",
    "gn:feature_code":"PPL",
    "gn:name":"Kerwara",
    "gn:population":0,
    "gn:timezone":"Asia/Karachi",
    "iso:country":"PK",
    "name:und_x_variant":[
        "Kerw\u0101ran"
    ],
    "wof:name":"Kerwara",
    "wof:placetype":"locality"
},
  "geometry": {"coordinates":[73.72593000000001,31.57608],"type":"Point"}
}