{
  "type": "Feature",
  "properties": {
    "gn:admin1_code":"2.0",
    "gn:asciiname":"New Kili Khadharzai",
    "gn:country_code":"PK",
    "gn:dem":1583,
    "gn:feature_class":"P",
    "gn:feature_code":"PPL",
    "gn:name":"New Kili Khadharzai",
    "gn:population":0,
    "gn:timezone":"Asia/Karachi",
    "iso:country":"PK",
    "wof:name":"New Kili Khadharzai",
    "wof:placetype":"locality"
},
  "geometry": {"coordinates":[66.98494000000001,30.38393],"type":"Point"}
}