{
  "type": "Feature",
  "properties": {
    "gn:admin1_code":"4",
    "gn:asciiname":"Nia Chah",
    "gn:country_code":"PK",
    "gn:dem":135,
    "gn:feature_class":"P",
    "gn:feature_code":"PPL",
    "gn:name":"Nia Chah",
    "gn:population":0,
    "gn:timezone":"Asia/Karachi",
    "iso:country":"PK",
    "name:und_x_variant":[
        "N\u0101w\u0101n Ch\u0101n"
    ],
    "wof:name":"Nia Chah",
    "wof:placetype":"locality"
},
  "geometry": {"coordinates":[70.93254,30.63059],"type":"Point"}
}