{
  "type": "Feature",
  "properties": {
    "gn:admin1_code":"2.0",
    "gn:asciiname":"Goth Karam Ali",
    "gn:country_code":"PK",
    "gn:dem":64,
    "gn:feature_class":"P",
    "gn:feature_code":"PPL",
    "gn:name":"Goth Karam Ali",
    "gn:population":0,
    "gn:timezone":"Asia/Karachi",
    "iso:country":"PK",
    "wof:name":"Goth Karam Ali",
    "wof:placetype":"locality"
},
  "geometry": {"coordinates":[68.0658,28.43466],"type":"Point"}
}