{
  "type": "Feature",
  "properties": {
    "gn:admin1_code":"4.0",
    "gn:asciiname":"Kamili Mirza",
    "gn:country_code":"PK",
    "gn:dem":473,
    "gn:feature_class":"P",
    "gn:feature_code":"PPL",
    "gn:name":"Kamili Mirza",
    "gn:population":0,
    "gn:timezone":"Asia/Karachi",
    "iso:country":"PK",
    "name:und_x_variant":[
        "Kambli Mirzian",
        "K\u0101mili Mirza",
        "Kamili Mirza"
    ],
    "wof:name":"Kamili Mirza",
    "wof:placetype":"locality"
},
  "geometry": {"coordinates":[73.354,33.37827],"type":"Point"}
}