{
  "type": "Feature",
  "properties": {
    "gn:admin1_code":"2.0",
    "gn:asciiname":"Khezai",
    "gn:country_code":"PK",
    "gn:dem":1882,
    "gn:feature_class":"P",
    "gn:feature_code":"PPL",
    "gn:name":"Khezai",
    "gn:population":0,
    "gn:timezone":"Asia/Karachi",
    "iso:country":"PK",
    "name:eng_x_preferred":[
        "Khezai"
    ],
    "wof:name":"Khezai",
    "wof:placetype":"locality"
},
  "geometry": {"coordinates":[67.04025,30.83439000000001],"type":"Point"}
}