{
  "type": "Feature",
  "properties": {
    "gn:admin1_code":"04",
    "gn:asciiname":"Title",
    "gn:country_code":"PK",
    "gn:dem":213,
    "gn:feature_class":"P",
    "gn:feature_code":"PPL",
    "gn:name":"Title",
    "gn:population":0,
    "gn:timezone":"Asia/Karachi",
    "iso:country":"PK",
    "name:und_x_variant":[
        "Tatle",
        "Tat\u012ble",
        "Title"
    ],
    "wof:name":"Title",
    "wof:placetype":"locality"
},
  "geometry": {"coordinates":[74.47723000000001,31.39043],"type":"Point"}
}