{
  "type": "Feature",
  "properties": {
    "gn:admin1_code":"04",
    "gn:asciiname":"Title",
    "gn:country_code":"PK",
    "gn:dem":213,
    "gn:feature_class":"P",
    "gn:feature_code":"PPL",
    "gn:name":"Title",
    "gn:population":0,
    "gn:timezone":"Asia/Karachi",
    "iso:country":"PK",
    "name:ara_x_preferred":[
        "\u0644\u0642\u0628 \u0634\u0631\u0641\u064a"
    ],
    "name:azb_x_preferred":[
        "\u0644\u0642\u0628"
    ],
    "name:bel_x_preferred":[
        "\u0422\u044b\u0442\u0443\u043b"
    ],
    "name:bos_x_preferred":[
        "Titula"
    ],
    "name:bul_x_preferred":[
        "\u0422\u0438\u0442\u043b\u0430"
    ],
    "name:dan_x_preferred":[
        "Titel"
    ],
    "name:epo_x_preferred":[
        "Titolo"
    ],
    "name:est_x_preferred":[
        "Tiitel"
    ],
    "name:fas_x_preferred":[
        "\u0644\u0642\u0628"
    ],
    "name:hrv_x_preferred":[
        "Titula"
    ],
    "name:hun_x_preferred":[
        "C\u00edm"
    ],
    "name:ind_x_preferred":[
        "Jenis gelar"
    ],
    "name:isl_x_preferred":[
        "Titill"
    ],
    "name:ita_x_preferred":[
        "Titolo"
    ],
    "name:jav_x_preferred":[
        "Sesebutan"
    ],
    "name:kan_x_preferred":[
        "\u0cac\u0cbf\u0cb0\u0cc1\u0ca6\u0cc1"
    ],
    "name:kaz_x_preferred":[
        "\u0414\u04d9\u0440\u0435\u0436\u0435"
    ],
    "name:lit_x_preferred":[
        "Titulas"
    ],
    "name:msa_x_preferred":[
        "Gelaran"
    ],
    "name:nno_x_preferred":[
        "Tittel"
    ],
    "name:rus_x_preferred":[
        "\u0422\u0438\u0442\u0443\u043b"
    ],
    "name:sco_x_preferred":[
        "Teetle"
    ],
    "name:slv_x_preferred":[
        "Naziv"
    ],
    "name:sqi_x_preferred":[
        "Titulli"
    ],
    "name:srp_x_preferred":[
        "\u0421\u043f\u0438\u0441\u0430\u043a \u0442\u0438\u0442\u0443\u043b\u0430"
    ],
    "name:swa_x_preferred":[
        "Cheo"
    ],
    "name:swe_x_preferred":[
        "Titel"
    ],
    "name:tha_x_preferred":[
        "\u0e04\u0e33\u0e19\u0e33\u0e2b\u0e19\u0e49\u0e32\u0e0a\u0e37\u0e48\u0e2d"
    ],
    "name:ukr_x_preferred":[
        "\u0422\u0438\u0442\u0443\u043b"
    ],
    "name:und_x_variant":[
        "Tatle",
        "Tat\u012ble",
        "Title"
    ],
    "name:vie_x_preferred":[
        "Ch\u1ee9c danh"
    ],
    "wof:name":"Title",
    "wof:placetype":"locality"
},
  "geometry": {"coordinates":[74.47723000000001,31.39043],"type":"Point"}
}