{
  "type": "Feature",
  "properties": {
    "gn:admin1_code":"6",
    "gn:asciiname":"Sar Baihk",
    "gn:country_code":"PK",
    "gn:dem":2703,
    "gn:feature_class":"P",
    "gn:feature_code":"PPL",
    "gn:name":"Sar Baihk",
    "gn:population":0,
    "gn:timezone":"Asia/Karachi",
    "iso:country":"PK",
    "wof:name":"Sar Baihk",
    "wof:placetype":"locality"
},
  "geometry": {"coordinates":[73.78061,34.6702],"type":"Point"}
}