{
  "type": "Feature",
  "properties": {
    "gn:admin1_code":"04",
    "gn:asciiname":"Chak Mohar Singh",
    "gn:country_code":"PK",
    "gn:dem":160,
    "gn:feature_class":"P",
    "gn:feature_code":"PPL",
    "gn:name":"Chak Mohar Singh",
    "gn:population":0,
    "gn:timezone":"Asia/Karachi",
    "iso:country":"PK",
    "name:und_x_variant":[
        "Kot Mohar Singh"
    ],
    "wof:name":"Chak Mohar Singh",
    "wof:placetype":"locality"
},
  "geometry": {"coordinates":[73.20010000000001,30.34853],"type":"Point"}
}