{
  "type": "Feature",
  "properties": {
    "iso:country":"PK",
    "name:hin_x_preferred":[
        "\u0935\u093e\u0930\u093e\u0939"
    ],
    "name:snd_x_preferred":[
        "\u0648\u0627\u0631\u06be"
    ],
    "qs:gn_country":"PK",
    "qs:gn_fcode":"PPL",
    "qs:gn_pop":18724,
    "qs:name":"Warah",
    "qs:name_adm0":"Pakistan",
    "qs:name_adm1":"Sindh",
    "qs:photos":0,
    "qs:photos_1k":0,
    "qs:photos_9k":0,
    "qs:photos_9r":0,
    "qs:photos_all":0,
    "qs:photos_sr":0,
    "qs:placetype":"Town",
    "qs:pop_sr":"6",
    "qs:woe_adm0":23424922,
    "wof:name":"Warah",
    "wof:placetype":"locality",
    "wof:population":18724
},
  "geometry": {"coordinates":[67.79776,27.44808],"type":"Point"}
}