{
  "type": "Feature",
  "properties": {
    "gn:admin1_code":"4.0",
    "gn:asciiname":"Usmanwala",
    "gn:country_code":"PK",
    "gn:dem":246,
    "gn:feature_class":"P",
    "gn:feature_code":"PPL",
    "gn:name":"Usm\u0101nw\u0101la",
    "gn:population":0,
    "gn:timezone":"Asia/Karachi",
    "iso:country":"PK",
    "wof:name":"Usmanwala",
    "wof:placetype":"locality"
},
  "geometry": {"coordinates":[71.73326999999998,32.58327],"type":"Point"}
}