{
  "type": "Feature",
  "properties": {
    "gn:admin1_code":"8.0",
    "gn:asciiname":"Gurha Sardar",
    "gn:country_code":"PK",
    "gn:dem":505,
    "gn:feature_class":"P",
    "gn:feature_code":"PPL",
    "gn:name":"Gurha Sardar",
    "gn:population":0,
    "gn:timezone":"Asia/Karachi",
    "iso:country":"PK",
    "wof:name":"Gurha Sardar",
    "wof:placetype":"neighbourhood"
},
  "geometry": {"coordinates":[73.16339000000001,33.63296],"type":"Point"}
}