{
  "type": "Feature",
  "properties": {
    "gn:admin1_code":"4.0",
    "gn:asciiname":"Thatha Khokharan",
    "gn:country_code":"PK",
    "gn:dem":207,
    "gn:feature_class":"P",
    "gn:feature_code":"PPL",
    "gn:name":"Thatha Khokharan",
    "gn:population":0,
    "gn:timezone":"Asia/Karachi",
    "iso:country":"PK",
    "name:und_x_variant":[
        "Thatta Khokhar\u0101n"
    ],
    "wof:name":"Thatha Khokharan",
    "wof:placetype":"locality"
},
  "geometry": {"coordinates":[73.67383000000002,32.05228],"type":"Point"}
}