{
  "type": "Feature",
  "properties": {
    "gn:admin1_code":"4.0",
    "gn:asciiname":"Basti Gori",
    "gn:country_code":"PK",
    "gn:dem":113,
    "gn:feature_class":"P",
    "gn:feature_code":"PPL",
    "gn:name":"Basti Gori",
    "gn:population":0,
    "gn:timezone":"Asia/Karachi",
    "iso:country":"PK",
    "name:und_x_variant":[
        "Basti Budh"
    ],
    "wof:name":"Basti Gori",
    "wof:placetype":"locality"
},
  "geometry": {"coordinates":[70.39528,29.6054],"type":"Point"}
}