{
  "type": "Feature",
  "properties": {
    "gn:admin1_code":"5.0",
    "gn:asciiname":"Akbarabad",
    "gn:country_code":"PK",
    "gn:dem":49,
    "gn:feature_class":"P",
    "gn:feature_code":"PPL",
    "gn:name":"Akbarabad",
    "gn:population":0,
    "gn:timezone":"Asia/Karachi",
    "iso:country":"PK",
    "name:ara_x_preferred":[
        "\u0623\u06a9\u0628\u0631 \u0623\u0628\u0627\u062f"
    ],
    "name:fas_x_preferred":[
        "\u0627\u06a9\u0628\u0631\u0622\u0628\u0627\u062f"
    ],
    "name:ron_x_preferred":[
        "Akbarabad"
    ],
    "wof:name":"Akbarabad",
    "wof:placetype":"locality"
},
  "geometry": {"coordinates":[68.3293,27.11518],"type":"Point"}
}