{
  "type": "Feature",
  "properties": {
    "gn:admin1_code":"4",
    "gn:asciiname":"Chak One Hundred Sixty Eastern Bar",
    "gn:country_code":"PK",
    "gn:dem":144,
    "gn:feature_class":"P",
    "gn:feature_code":"PPL",
    "gn:name":"Chak One Hundred Sixty Eastern Bar",
    "gn:population":0,
    "gn:timezone":"Asia/Karachi",
    "iso:country":"PK",
    "name:und_x_variant":[
        "Chak One Hundred Sixty EB"
    ],
    "wof:name":"Chak One Hundred Sixty Eastern Bar",
    "wof:placetype":"locality"
},
  "geometry": {"coordinates":[72.53520999999998,30.17048],"type":"Point"}
}