{
  "type": "Feature",
  "properties": {
    "gn:admin1_code":"04",
    "gn:asciiname":"Nari Shimali",
    "gn:country_code":"PK",
    "gn:dem":149,
    "gn:feature_class":"P",
    "gn:feature_code":"PPL",
    "gn:name":"Nari Shimali",
    "gn:population":0,
    "gn:timezone":"Asia/Karachi",
    "iso:country":"PK",
    "name:und_x_variant":[
        "Nari Shumali",
        "Nari Shimali"
    ],
    "wof:name":"Nari Shimali",
    "wof:placetype":"locality"
},
  "geometry": {"coordinates":[70.67348,30.84787],"type":"Point"}
}