{
  "type": "Feature",
  "properties": {
    "gn:admin1_code":"4",
    "gn:asciiname":"Chak Three Hundred Ninety-two Jhang Branch",
    "gn:country_code":"PK",
    "gn:dem":154,
    "gn:feature_class":"P",
    "gn:feature_code":"PPL",
    "gn:name":"Chak Three Hundred Ninety-two Jhang Branch",
    "gn:population":0,
    "gn:timezone":"Asia/Karachi",
    "iso:country":"PK",
    "name:und_x_variant":[
        "Chak Three Hundred Ninety-Two JB",
        "Chuti\u0101la",
        "Garh Chut\u0101la",
        "Chak Three Hundred Ninety-two Jhang Branch",
        "Chott\u0101la"
    ],
    "wof:name":"Chak Three Hundred Ninety-two Jhang Branch",
    "wof:placetype":"locality"
},
  "geometry": {"coordinates":[72.43507,30.98545],"type":"Point"}
}