{
  "type": "Feature",
  "properties": {
    "gn:admin1_code":"5.0",
    "gn:asciiname":"Kola Kolhi Jo Goth",
    "gn:country_code":"PK",
    "gn:dem":31,
    "gn:feature_class":"P",
    "gn:feature_code":"PPL",
    "gn:name":"Kola Kolhi Jo Goth",
    "gn:population":0,
    "gn:timezone":"Asia/Karachi",
    "iso:country":"PK",
    "wof:name":"Kola Kolhi Jo Goth",
    "wof:placetype":"locality"
},
  "geometry": {"coordinates":[70.28610999999999,24.47307],"type":"Point"}
}