{
  "type": "Feature",
  "properties": {
    "gn:admin1_code":"3",
    "gn:asciiname":"Khazrai",
    "gn:country_code":"PK",
    "gn:dem":1563,
    "gn:feature_class":"P",
    "gn:feature_code":"PPL",
    "gn:name":"Khazrai",
    "gn:population":0,
    "gn:timezone":"Asia/Karachi",
    "iso:country":"PK",
    "wof:name":"Khazrai",
    "wof:placetype":"locality"
},
  "geometry": {"coordinates":[72.00757,34.82014],"type":"Point"}
}