{
  "type": "Feature",
  "properties": {
    "gn:admin1_code":"3",
    "gn:asciiname":"Bar Lalku",
    "gn:country_code":"PK",
    "gn:dem":1963,
    "gn:feature_class":"P",
    "gn:feature_code":"PPL",
    "gn:name":"Bar Lalku",
    "gn:population":0,
    "gn:timezone":"Asia/Karachi",
    "iso:country":"PK",
    "wof:name":"Bar Lalku",
    "wof:placetype":"locality"
},
  "geometry": {"coordinates":[72.38746,35.13663],"type":"Point"}
}