{
  "type": "Feature",
  "properties": {
    "gn:admin1_code":"3.0",
    "gn:asciiname":"Shamdara",
    "gn:country_code":"PK",
    "gn:dem":1817,
    "gn:feature_class":"P",
    "gn:feature_code":"PPL",
    "gn:name":"Shamdara",
    "gn:population":0,
    "gn:timezone":"Asia/Karachi",
    "iso:country":"PK",
    "name:und_x_variant":[
        "Sh\u0101mr\u0101d"
    ],
    "wof:name":"Shamdara",
    "wof:placetype":"locality"
},
  "geometry": {"coordinates":[72.95469,35.01345],"type":"Point"}
}