{
  "type": "Feature",
  "properties": {
    "gn:admin1_code":"1.0",
    "gn:asciiname":"Ziarat Faizulla",
    "gn:country_code":"PK",
    "gn:dem":1892,
    "gn:feature_class":"P",
    "gn:feature_code":"PPL",
    "gn:name":"Ziarat Faizulla",
    "gn:population":0,
    "gn:timezone":"Asia/Karachi",
    "iso:country":"PK",
    "wof:name":"Ziarat Faizulla",
    "wof:placetype":"locality"
},
  "geometry": {"coordinates":[70.86774,33.76527],"type":"Point"}
}