{
  "type": "Feature",
  "properties": {
    "gn:admin1_code":"5",
    "gn:asciiname":"Haji Minho Khan",
    "gn:country_code":"PK",
    "gn:dem":50,
    "gn:feature_class":"P",
    "gn:feature_code":"PPL",
    "gn:name":"Haji Minho Khan",
    "gn:population":0,
    "gn:timezone":"Asia/Karachi",
    "iso:country":"PK",
    "name:und_x_variant":[
        "Goth H\u0101ji Minho Kh\u0101n"
    ],
    "wof:name":"Haji Minho Khan",
    "wof:placetype":"locality"
},
  "geometry": {"coordinates":[67.39463000000001,26.55746],"type":"Point"}
}