{
  "type": "Feature",
  "properties": {
    "gn:admin1_code":"3",
    "gn:asciiname":"Sara Shah",
    "gn:country_code":"PK",
    "gn:dem":2401,
    "gn:feature_class":"P",
    "gn:feature_code":"PPL",
    "gn:name":"Sara Shah",
    "gn:population":0,
    "gn:timezone":"Asia/Karachi",
    "iso:country":"PK",
    "wof:name":"Sara Shah",
    "wof:placetype":"locality"
},
  "geometry": {"coordinates":[72.51315,34.77404],"type":"Point"}
}