{
  "type": "Feature",
  "properties": {
    "gn:admin1_code":"6",
    "gn:asciiname":"Pothi",
    "gn:country_code":"PK",
    "gn:dem":358,
    "gn:feature_class":"P",
    "gn:feature_code":"PPL",
    "gn:name":"Pothi",
    "gn:population":0,
    "gn:timezone":"Asia/Karachi",
    "iso:country":"PK",
    "name:und_x_variant":[
        "Pathi",
        "Pothi"
    ],
    "wof:name":"Pothi",
    "wof:placetype":"locality"
},
  "geometry": {"coordinates":[73.76652,33.11441],"type":"Point"}
}