{
  "type": "Feature",
  "properties": {
    "gn:admin1_code":"3",
    "gn:asciiname":"Maira",
    "gn:country_code":"PK",
    "gn:dem":1381,
    "gn:feature_class":"P",
    "gn:feature_code":"PPL",
    "gn:name":"Maira",
    "gn:population":0,
    "gn:timezone":"Asia/Karachi",
    "iso:country":"PK",
    "wof:name":"Maira",
    "wof:placetype":"locality"
},
  "geometry": {"coordinates":[72.74769999999999,34.615],"type":"Point"}
}