{
  "type": "Feature",
  "properties": {
    "gn:admin1_code":"3.0",
    "gn:asciiname":"Paja",
    "gn:country_code":"PK",
    "gn:dem":2155,
    "gn:feature_class":"P",
    "gn:feature_code":"PPL",
    "gn:name":"Paja",
    "gn:population":0,
    "gn:timezone":"Asia/Karachi",
    "iso:country":"PK",
    "name:fas_x_preferred":[
        "\u067e\u0627\u062c\u0627"
    ],
    "name:glk_x_preferred":[
        "\u067e\u0627\u062c\u0627"
    ],
    "name:mzn_x_preferred":[
        "\u067e\u0627\u062c\u0627"
    ],
    "wof:name":"Paja",
    "wof:placetype":"locality"
},
  "geometry": {"coordinates":[73.27696999999998,34.65947],"type":"Point"}
}