{
  "type": "Feature",
  "properties": {
    "gn:admin1_code":"4.0",
    "gn:asciiname":"Khartop",
    "gn:country_code":"PK",
    "gn:dem":350,
    "gn:feature_class":"P",
    "gn:feature_code":"PPL",
    "gn:name":"Khartop",
    "gn:population":0,
    "gn:timezone":"Asia/Karachi",
    "iso:country":"PK",
    "wof:name":"Khartop",
    "wof:placetype":"locality"
},
  "geometry": {"coordinates":[71.55454,33.05275],"type":"Point"}
}