{
  "type": "Feature",
  "properties": {
    "gn:admin1_code":"5",
    "gn:asciiname":"Sher Khan Marri",
    "gn:country_code":"PK",
    "gn:dem":20,
    "gn:feature_class":"P",
    "gn:feature_code":"PPL",
    "gn:name":"Sher Kh\u0101n Marri",
    "gn:population":0,
    "gn:timezone":"Asia/Karachi",
    "iso:country":"PK",
    "wof:name":"Sher Khan Marri",
    "wof:placetype":"locality"
},
  "geometry": {"coordinates":[68.96389000000001,25.69722],"type":"Point"}
}