{
  "type": "Feature",
  "properties": {
    "gn:admin1_code":"4.0",
    "gn:asciiname":"Chitta Mor",
    "gn:country_code":"PK",
    "gn:dem":1891,
    "gn:feature_class":"P",
    "gn:feature_code":"PPL",
    "gn:name":"Chitta Mor",
    "gn:population":0,
    "gn:timezone":"Asia/Karachi",
    "iso:country":"PK",
    "name:eng_x_preferred":[
        "Chitta Mor"
    ],
    "wof:name":"Chitta Mor",
    "wof:placetype":"locality"
},
  "geometry": {"coordinates":[73.3806,33.91179],"type":"Point"}
}