{
  "type": "Feature",
  "properties": {
    "gn:admin1_code":"5.0",
    "gn:asciiname":"Haji Shamiso Detho",
    "gn:country_code":"PK",
    "gn:dem":113,
    "gn:feature_class":"P",
    "gn:feature_code":"PPL",
    "gn:name":"Haji Shamiso Detho",
    "gn:population":0,
    "gn:timezone":"Asia/Karachi",
    "iso:country":"PK",
    "wof:name":"Haji Shamiso Detho",
    "wof:placetype":"locality"
},
  "geometry": {"coordinates":[67.86781999999999,25.45373],"type":"Point"}
}