{
  "type": "Feature",
  "properties": {
    "gn:admin1_code":"4",
    "gn:asciiname":"Hithar Binda",
    "gn:country_code":"PK",
    "gn:dem":143,
    "gn:feature_class":"P",
    "gn:feature_code":"PPL",
    "gn:name":"Hithar Binda",
    "gn:population":0,
    "gn:timezone":"Asia/Karachi",
    "iso:country":"PK",
    "name:und_x_variant":[
        "Sh\u0101hr\u0101hw\u0101la",
        "Hith\u0101r Bhinda",
        "Hithar Binda"
    ],
    "wof:name":"Hithar Binda",
    "wof:placetype":"locality"
},
  "geometry": {"coordinates":[72.69081,29.83642],"type":"Point"}
}