{
  "type": "Feature",
  "properties": {
    "gn:admin1_code":"3.0",
    "gn:asciiname":"Shahbaz Khan Kot",
    "gn:country_code":"PK",
    "gn:dem":306,
    "gn:feature_class":"P",
    "gn:feature_code":"PPL",
    "gn:name":"Shahbaz Khan Kot",
    "gn:population":0,
    "gn:timezone":"Asia/Karachi",
    "iso:country":"PK",
    "wof:name":"Shahbaz Khan Kot",
    "wof:placetype":"locality"
},
  "geometry": {"coordinates":[70.17771999999999,32.11242],"type":"Point"}
}