{
  "type": "Feature",
  "properties": {
    "gn:admin1_code":"4",
    "gn:asciiname":"Lodhi Joja",
    "gn:country_code":"PK",
    "gn:dem":231,
    "gn:feature_class":"P",
    "gn:feature_code":"PPL",
    "gn:name":"Lodhi Joja",
    "gn:population":0,
    "gn:timezone":"Asia/Karachi",
    "iso:country":"PK",
    "name:und_x_variant":[
        "Lodi Jajja"
    ],
    "wof:name":"Lodhi Joja",
    "wof:placetype":"locality"
},
  "geometry": {"coordinates":[74.56324000000002,32.14718],"type":"Point"}
}