{
  "type": "Feature",
  "properties": {
    "gn:admin1_code":"4",
    "gn:asciiname":"Chonwala",
    "gn:country_code":"PK",
    "gn:dem":121,
    "gn:feature_class":"P",
    "gn:feature_code":"PPL",
    "gn:name":"Chonwala",
    "gn:population":0,
    "gn:timezone":"Asia/Karachi",
    "iso:country":"PK",
    "name:eng_x_preferred":[
        "Chanw\u0101la"
    ],
    "wof:name":"Chonwala",
    "wof:placetype":"locality"
},
  "geometry": {"coordinates":[70.92837,30.12316],"type":"Point"}
}