{
  "type": "Feature",
  "properties": {
    "gn:admin1_code":"4.0",
    "gn:asciiname":"Chah Hastewala",
    "gn:country_code":"PK",
    "gn:dem":159,
    "gn:feature_class":"P",
    "gn:feature_code":"PPL",
    "gn:name":"Chah Hastewala",
    "gn:population":0,
    "gn:timezone":"Asia/Karachi",
    "iso:country":"PK",
    "name:und_x_variant":[
        "Ch\u0101h Hastiw\u0101la"
    ],
    "wof:name":"Chah Hastewala",
    "wof:placetype":"locality"
},
  "geometry": {"coordinates":[72.38989000000002,31.36847],"type":"Point"}
}