{
  "type": "Feature",
  "properties": {
    "gn:admin1_code":"4.0",
    "gn:asciiname":"Shah Faisal Town",
    "gn:country_code":"PK",
    "gn:dem":145,
    "gn:feature_class":"P",
    "gn:feature_code":"PPL",
    "gn:name":"Shah Faisal Town",
    "gn:population":0,
    "gn:timezone":"Asia/Karachi",
    "iso:country":"PK",
    "name:fas_x_preferred":[
        "\u0634\u0647\u0631\u06a9 \u0634\u0627\u0647 \u0641\u06cc\u0635\u0644"
    ],
    "name:rus_x_preferred":[
        "\u0428\u0430\u0445-\u0424\u0430\u0439\u0441\u0430\u043b"
    ],
    "name:urd_x_preferred":[
        "\u0634\u0627\u06c1 \u0641\u06cc\u0635\u0644 \u0679\u0627\u0624\u0646"
    ],
    "wof:name":"Shah Faisal Town",
    "wof:placetype":"neighbourhood"
},
  "geometry": {"coordinates":[72.70332999999999,30.1638],"type":"Point"}
}