{
  "type": "Feature",
  "properties": {
    "gn:admin1_code":"4.0",
    "gn:asciiname":"Dhok Kamaran",
    "gn:country_code":"PK",
    "gn:dem":427,
    "gn:feature_class":"P",
    "gn:feature_code":"PPL",
    "gn:name":"Dhok Kamaran",
    "gn:population":0,
    "gn:timezone":"Asia/Karachi",
    "iso:country":"PK",
    "wof:name":"Dhok Kamaran",
    "wof:placetype":"locality"
},
  "geometry": {"coordinates":[73.43205,33.11817],"type":"Point"}
}