{
  "type": "Feature",
  "properties": {
    "gn:admin1_code":"03",
    "gn:asciiname":"Pind Gakhra",
    "gn:country_code":"PK",
    "gn:dem":512,
    "gn:feature_class":"P",
    "gn:feature_code":"PPL",
    "gn:name":"Pind Gakhra",
    "gn:population":0,
    "gn:timezone":"Asia/Karachi",
    "iso:country":"PK",
    "wof:name":"Pind Gakhra",
    "wof:placetype":"locality"
},
  "geometry": {"coordinates":[72.84361,33.77709],"type":"Point"}
}