{
  "type": "Feature",
  "properties": {
    "gn:admin1_code":"2.0",
    "gn:asciiname":"Kucha",
    "gn:country_code":"PK",
    "gn:dem":1616,
    "gn:feature_class":"P",
    "gn:feature_code":"PPL",
    "gn:name":"Kucha",
    "gn:population":0,
    "gn:timezone":"Asia/Karachi",
    "iso:country":"PK",
    "wof:name":"Kucha",
    "wof:placetype":"locality"
},
  "geometry": {"coordinates":[66.26045000000001,28.14712],"type":"Point"}
}