{
  "type": "Feature",
  "properties": {
    "gn:admin1_code":"2.0",
    "gn:asciiname":"Kucha",
    "gn:country_code":"PK",
    "gn:dem":1616,
    "gn:feature_class":"P",
    "gn:feature_code":"PPL",
    "gn:name":"Kucha",
    "gn:population":0,
    "gn:timezone":"Asia/Karachi",
    "iso:country":"PK",
    "name:cat_x_preferred":[
        "Kutxa"
    ],
    "name:fas_x_preferred":[
        "\u06a9\u0648\u0686\u0627"
    ],
    "name:hak_x_preferred":[
        "Khi\u00fb-tsh\u1e73\u0300"
    ],
    "name:hin_x_preferred":[
        "\u0915\u0942\u091a\u093e \u0930\u093e\u091c\u094d\u092f"
    ],
    "name:ind_x_preferred":[
        "Kucha"
    ],
    "name:ita_x_preferred":[
        "Kucha"
    ],
    "name:nld_x_preferred":[
        "Kuqa"
    ],
    "name:pnb_x_preferred":[
        "\u06a9\u0648\u0686\u0627 \u0631\u0627\u062c"
    ],
    "name:por_x_preferred":[
        "Kucha"
    ],
    "name:rus_x_preferred":[
        "\u041a\u0443\u0447\u0430"
    ],
    "name:ukr_x_preferred":[
        "\u041a\u0443\u0447\u0430"
    ],
    "name:vie_x_preferred":[
        "Quy T\u1eeb"
    ],
    "wof:name":"Kucha",
    "wof:placetype":"locality"
},
  "geometry": {"coordinates":[66.26045000000001,28.14712],"type":"Point"}
}