{
  "type": "Feature",
  "properties": {
    "gn:admin1_code":"5",
    "gn:asciiname":"Goth Khair Muhammad Jakhro",
    "gn:country_code":"PK",
    "gn:dem":51,
    "gn:feature_class":"P",
    "gn:feature_code":"PPL",
    "gn:name":"Goth Khair Muhammad Jakhro",
    "gn:population":0,
    "gn:timezone":"Asia/Karachi",
    "iso:country":"PK",
    "name:und_x_variant":[
        "Goth Khair Muhammad J\u0101khra",
        "Khairo Jhati\u0101l",
        "Goth Khair Muhammad Jakhro"
    ],
    "wof:name":"Goth Khair Muhammad Jakhro",
    "wof:placetype":"locality"
},
  "geometry": {"coordinates":[68.03864,27.26426],"type":"Point"}
}