{
  "type": "Feature",
  "properties": {
    "gn:admin1_code":"5",
    "gn:asciiname":"Shaie jo Goth",
    "gn:country_code":"PK",
    "gn:dem":67,
    "gn:feature_class":"P",
    "gn:feature_code":"PPL",
    "gn:name":"Shaie jo Goth",
    "gn:population":0,
    "gn:timezone":"Asia/Karachi",
    "iso:country":"PK",
    "wof:name":"Shaie jo Goth",
    "wof:placetype":"locality"
},
  "geometry": {"coordinates":[69.16667,27.59722],"type":"Point"}
}