{
  "type": "Feature",
  "properties": {
    "gn:admin1_code":"4.0",
    "gn:asciiname":"Wainswala",
    "gn:country_code":"PK",
    "gn:dem":111,
    "gn:feature_class":"P",
    "gn:feature_code":"PPL",
    "gn:name":"Wainswala",
    "gn:population":0,
    "gn:timezone":"Asia/Karachi",
    "iso:country":"PK",
    "wof:name":"Wainswala",
    "wof:placetype":"locality"
},
  "geometry": {"coordinates":[70.5078,29.70436],"type":"Point"}
}