{
  "type": "Feature",
  "properties": {
    "gn:admin1_code":"2.0",
    "gn:asciiname":"Kili Mahbub",
    "gn:country_code":"PK",
    "gn:dem":1485,
    "gn:feature_class":"P",
    "gn:feature_code":"PPL",
    "gn:name":"Kili Mahbub",
    "gn:population":0,
    "gn:timezone":"Asia/Karachi",
    "iso:country":"PK",
    "wof:name":"Kili Mahbub",
    "wof:placetype":"locality"
},
  "geometry": {"coordinates":[66.50839999999999,30.9434],"type":"Point"}
}