{
  "type": "Feature",
  "properties": {
    "gn:admin1_code":"4.0",
    "gn:asciiname":"Marchapur Khurd",
    "gn:country_code":"PK",
    "gn:dem":259,
    "gn:feature_class":"P",
    "gn:feature_code":"PPL",
    "gn:name":"Marchapur Khurd",
    "gn:population":0,
    "gn:timezone":"Asia/Karachi",
    "iso:country":"PK",
    "wof:name":"Marchapur Khurd",
    "wof:placetype":"locality"
},
  "geometry": {"coordinates":[74.70990999999999,32.47428],"type":"Point"}
}