{
  "type": "Feature",
  "properties": {
    "gn:admin1_code":"3",
    "gn:asciiname":"Shikai Dheri",
    "gn:country_code":"PK",
    "gn:dem":352,
    "gn:feature_class":"P",
    "gn:feature_code":"PPL",
    "gn:name":"Shikai Dheri",
    "gn:population":0,
    "gn:timezone":"Asia/Karachi",
    "iso:country":"PK",
    "wof:name":"Shikai Dheri",
    "wof:placetype":"locality"
},
  "geometry": {"coordinates":[72.27221999999998,34.03333],"type":"Point"}
}