{
  "type": "Feature",
  "properties": {
    "gn:admin1_code":"4",
    "gn:asciiname":"Lot Sixty-one A",
    "gn:country_code":"PK",
    "gn:dem":181,
    "gn:feature_class":"P",
    "gn:feature_code":"PPL",
    "gn:name":"Lot Sixty-one A",
    "gn:population":0,
    "gn:timezone":"Asia/Karachi",
    "iso:country":"PK",
    "wof:name":"Lot Sixty-one A",
    "wof:placetype":"locality"
},
  "geometry": {"coordinates":[71.28889000000002,31.79444],"type":"Point"}
}