{
  "type": "Feature",
  "properties": {
    "gn:admin1_code":"5",
    "gn:asciiname":"Goth Jiwan Kolachi",
    "gn:country_code":"PK",
    "gn:dem":61,
    "gn:feature_class":"P",
    "gn:feature_code":"PPL",
    "gn:name":"Goth Jiwan Kolachi",
    "gn:population":0,
    "gn:timezone":"Asia/Karachi",
    "iso:country":"PK",
    "name:und_x_variant":[
        "Goth Liwan Kol\u0101chi"
    ],
    "wof:name":"Goth Jiwan Kolachi",
    "wof:placetype":"locality"
},
  "geometry": {"coordinates":[69.34917,27.992],"type":"Point"}
}