{
  "type": "Feature",
  "properties": {
    "gn:admin1_code":"4.0",
    "gn:asciiname":"Sehr",
    "gn:country_code":"PK",
    "gn:dem":1526,
    "gn:feature_class":"P",
    "gn:feature_code":"PPL",
    "gn:name":"Sehr",
    "gn:population":0,
    "gn:timezone":"Asia/Karachi",
    "iso:country":"PK",
    "name:eng_x_preferred":[
        "Sehr"
    ],
    "wof:name":"Sehr",
    "wof:placetype":"locality"
},
  "geometry": {"coordinates":[73.36128000000002,33.92026],"type":"Point"}
}