{
  "type": "Feature",
  "properties": {
    "gn:admin1_code":"1.0",
    "gn:asciiname":"Gula Nur Kor",
    "gn:country_code":"PK",
    "gn:dem":816,
    "gn:feature_class":"P",
    "gn:feature_code":"PPL",
    "gn:name":"Gula Nur Kor",
    "gn:population":0,
    "gn:timezone":"Asia/Karachi",
    "iso:country":"PK",
    "name:und_x_variant":[
        "Gul Khan Kor"
    ],
    "wof:name":"Gula Nur Kor",
    "wof:placetype":"locality"
},
  "geometry": {"coordinates":[71.45023,34.41041],"type":"Point"}
}