{
  "type": "Feature",
  "properties": {
    "gn:admin1_code":"3.0",
    "gn:asciiname":"Spere Kili",
    "gn:country_code":"PK",
    "gn:dem":393,
    "gn:feature_class":"P",
    "gn:feature_code":"PPL",
    "gn:name":"Spere Kili",
    "gn:population":0,
    "gn:timezone":"Asia/Karachi",
    "iso:country":"PK",
    "wof:name":"Spere Kili",
    "wof:placetype":"locality"
},
  "geometry": {"coordinates":[70.60666999999999,33.02917],"type":"Point"}
}