{
  "type": "Feature",
  "properties": {
    "gn:admin1_code":"4.0",
    "gn:asciiname":"Sarai Miani",
    "gn:country_code":"PK",
    "gn:dem":981,
    "gn:feature_class":"P",
    "gn:feature_code":"PPL",
    "gn:name":"Sarai Miani",
    "gn:population":0,
    "gn:timezone":"Asia/Karachi",
    "iso:country":"PK",
    "name:und_x_variant":[
        "Sar\u0101i"
    ],
    "wof:name":"Sarai Miani",
    "wof:placetype":"locality"
},
  "geometry": {"coordinates":[71.89176999999999,32.52598],"type":"Point"}
}