{
  "type": "Feature",
  "properties": {
    "gn:admin1_code":"4.0",
    "gn:asciiname":"Basti Dadpotra",
    "gn:country_code":"PK",
    "gn:dem":111,
    "gn:feature_class":"P",
    "gn:feature_code":"PPL",
    "gn:name":"Basti Dadpotra",
    "gn:population":0,
    "gn:timezone":"Asia/Karachi",
    "iso:country":"PK",
    "name:und_x_variant":[
        "Basti Dad Potre"
    ],
    "wof:name":"Basti Dadpotra",
    "wof:placetype":"locality"
},
  "geometry": {"coordinates":[71.47026,29.18995],"type":"Point"}
}