{
  "type": "Feature",
  "properties": {
    "gn:admin1_code":"2.0",
    "gn:asciiname":"Kili Haji Muhammad Bakhsh Ramezai",
    "gn:country_code":"PK",
    "gn:dem":1381,
    "gn:feature_class":"P",
    "gn:feature_code":"PPL",
    "gn:name":"Kili Haji Muhammad Bakhsh Ramezai",
    "gn:population":0,
    "gn:timezone":"Asia/Karachi",
    "iso:country":"PK",
    "wof:name":"Kili Haji Muhammad Bakhsh Ramezai",
    "wof:placetype":"locality"
},
  "geometry": {"coordinates":[66.59081999999999,28.05182000000001],"type":"Point"}
}