{
  "type": "Feature",
  "properties": {
    "gn:admin1_code":"3.0",
    "gn:asciiname":"Bezat",
    "gn:country_code":"PK",
    "gn:dem":526,
    "gn:feature_class":"P",
    "gn:feature_code":"PPL",
    "gn:name":"Bezat",
    "gn:population":0,
    "gn:timezone":"Asia/Karachi",
    "iso:country":"PK",
    "name:eng_x_preferred":[
        "B\u0101zat"
    ],
    "wof:name":"Bezat",
    "wof:placetype":"locality"
},
  "geometry": {"coordinates":[72.32526,34.42496],"type":"Point"}
}