{
  "type": "Feature",
  "properties": {
    "gn:admin1_code":"2.0",
    "gn:asciiname":"Goth Budda",
    "gn:country_code":"PK",
    "gn:dem":502,
    "gn:feature_class":"P",
    "gn:feature_code":"PPL",
    "gn:name":"Goth Budda",
    "gn:population":0,
    "gn:timezone":"Asia/Karachi",
    "iso:country":"PK",
    "wof:name":"Goth Budda",
    "wof:placetype":"locality"
},
  "geometry": {"coordinates":[66.79899,26.08775],"type":"Point"}
}