{
  "type": "Feature",
  "properties": {
    "gn:admin1_code":"4.0",
    "gn:asciiname":"Sayiedabad",
    "gn:country_code":"PK",
    "gn:dem":150,
    "gn:feature_class":"P",
    "gn:feature_code":"PPL",
    "gn:name":"Sayiedabad",
    "gn:population":0,
    "gn:timezone":"Asia/Karachi",
    "iso:country":"PK",
    "name:und_x_variant":[
        "Said\u0101b\u0101d"
    ],
    "wof:name":"Sayiedabad",
    "wof:placetype":"locality"
},
  "geometry": {"coordinates":[72.20818,30.96962000000001],"type":"Point"}
}