{
  "type": "Feature",
  "properties": {
    "gn:admin1_code":"3",
    "gn:asciiname":"Darmai",
    "gn:country_code":"PK",
    "gn:dem":1423,
    "gn:feature_class":"P",
    "gn:feature_code":"PPL",
    "gn:name":"Darmai",
    "gn:population":0,
    "gn:timezone":"Asia/Karachi",
    "iso:country":"PK",
    "wof:name":"Darmai",
    "wof:placetype":"locality"
},
  "geometry": {"coordinates":[72.44606,35.08105],"type":"Point"}
}