{
  "type": "Feature",
  "properties": {
    "gn:admin1_code":"3",
    "gn:asciiname":"Darmai",
    "gn:country_code":"PK",
    "gn:dem":1423,
    "gn:feature_class":"P",
    "gn:feature_code":"PPL",
    "gn:name":"Darmai",
    "gn:population":0,
    "gn:timezone":"Asia/Karachi",
    "iso:country":"PK",
    "name:fas_x_preferred":[
        "\u062f\u0631\u0645\u06cc\u06cc"
    ],
    "name:urd_x_preferred":[
        "\u062f\u0631\u0645\u0626\u06cc"
    ],
    "wof:name":"Darmai",
    "wof:placetype":"locality"
},
  "geometry": {"coordinates":[72.44606,35.08105],"type":"Point"}
}