{
  "type": "Feature",
  "properties": {
    "gn:admin1_code":"4.0",
    "gn:asciiname":"Sheikh Sabir",
    "gn:country_code":"PK",
    "gn:dem":512,
    "gn:feature_class":"P",
    "gn:feature_code":"PPL",
    "gn:name":"Sheikh Sabir",
    "gn:population":0,
    "gn:timezone":"Asia/Karachi",
    "iso:country":"PK",
    "wof:name":"Sheikh Sabir",
    "wof:placetype":"locality"
},
  "geometry": {"coordinates":[72.57868000000001,33.4181],"type":"Point"}
}