{
  "type": "Feature",
  "properties": {
    "gn:admin1_code":"3",
    "gn:asciiname":"Ghundakai",
    "gn:country_code":"PK",
    "gn:dem":1515,
    "gn:feature_class":"P",
    "gn:feature_code":"PPL",
    "gn:name":"Ghundakai",
    "gn:population":0,
    "gn:timezone":"Asia/Karachi",
    "iso:country":"PK",
    "wof:name":"Ghundakai",
    "wof:placetype":"locality"
},
  "geometry": {"coordinates":[72.54386,34.62324],"type":"Point"}
}