{
  "type": "Feature",
  "properties": {
    "gn:admin1_code":"5.0",
    "gn:asciiname":"Barthanwaro Tar",
    "gn:country_code":"PK",
    "gn:dem":85,
    "gn:feature_class":"P",
    "gn:feature_code":"PPL",
    "gn:name":"Barthanwaro Tar",
    "gn:population":0,
    "gn:timezone":"Asia/Karachi",
    "iso:country":"PK",
    "wof:name":"Barthanwaro Tar",
    "wof:placetype":"locality"
},
  "geometry": {"coordinates":[70.17556999999999,26.41908],"type":"Point"}
}