{
  "type": "Feature",
  "properties": {
    "gn:admin1_code":"4",
    "gn:asciiname":"Dhok Kade Khan",
    "gn:country_code":"PK",
    "gn:dem":465,
    "gn:feature_class":"P",
    "gn:feature_code":"PPL",
    "gn:name":"Dhok Kade Khan",
    "gn:population":0,
    "gn:timezone":"Asia/Karachi",
    "iso:country":"PK",
    "wof:name":"Dhok Kade Khan",
    "wof:placetype":"locality"
},
  "geometry": {"coordinates":[73.42233,33.17297],"type":"Point"}
}