{
  "type": "Feature",
  "properties": {
    "gn:admin1_code":"7.0",
    "gn:asciiname":"Gul Chu",
    "gn:country_code":"PK",
    "gn:dem":2491,
    "gn:feature_class":"P",
    "gn:feature_code":"PPL",
    "gn:name":"Gul Chu",
    "gn:population":0,
    "gn:timezone":"Asia/Karachi",
    "iso:country":"PK",
    "wof:name":"Gul Chu",
    "wof:placetype":"locality"
},
  "geometry": {"coordinates":[75.34104000000001,35.46816],"type":"Point"}
}