{
  "type": "Feature",
  "properties": {
    "gn:admin1_code":"4",
    "gn:asciiname":"Juma Sera",
    "gn:country_code":"PK",
    "gn:dem":100,
    "gn:feature_class":"P",
    "gn:feature_code":"PPL",
    "gn:name":"Juma Sera",
    "gn:population":0,
    "gn:timezone":"Asia/Karachi",
    "iso:country":"PK",
    "name:und_x_variant":[
        "Juma Seyra"
    ],
    "wof:name":"Juma Sera",
    "wof:placetype":"locality"
},
  "geometry": {"coordinates":[70.4143,29.31482],"type":"Point"}
}