{
  "type": "Feature",
  "properties": {
    "gn:admin1_code":"1.0",
    "gn:asciiname":"Khawaja Ki",
    "gn:country_code":"PK",
    "gn:dem":606,
    "gn:feature_class":"P",
    "gn:feature_code":"PPL",
    "gn:name":"Khawaja Ki",
    "gn:population":0,
    "gn:timezone":"Asia/Karachi",
    "iso:country":"PK",
    "name:und_x_variant":[
        "Khwaja Ki",
        "Khwaj\u0101ki",
        "Khawaja Ki"
    ],
    "wof:name":"Khawaja Ki",
    "wof:placetype":"locality"
},
  "geometry": {"coordinates":[71.72594000000002,33.61272],"type":"Point"}
}