{
  "type": "Feature",
  "properties": {
    "gn:admin1_code":"02",
    "gn:asciiname":"Roghi",
    "gn:country_code":"PK",
    "gn:dem":973,
    "gn:feature_class":"P",
    "gn:feature_code":"PPL",
    "gn:name":"Roghi",
    "gn:population":0,
    "gn:timezone":"Asia/Karachi",
    "iso:country":"PK",
    "wof:name":"Roghi",
    "wof:placetype":"locality"
},
  "geometry": {"coordinates":[67.94783000000001,30.13301],"type":"Point"}
}