{
  "type": "Feature",
  "properties": {
    "gn:admin1_code":"4.0",
    "gn:asciiname":"Rodi Dheri",
    "gn:country_code":"PK",
    "gn:dem":373,
    "gn:feature_class":"P",
    "gn:feature_code":"PPL",
    "gn:name":"Rodi Dheri",
    "gn:population":0,
    "gn:timezone":"Asia/Karachi",
    "iso:country":"PK",
    "wof:name":"Rodi Dheri",
    "wof:placetype":"locality"
},
  "geometry": {"coordinates":[72.15222,33.62361],"type":"Point"}
}