{
  "type": "Feature",
  "properties": {
    "gn:admin1_code":"4.0",
    "gn:asciiname":"Veji",
    "gn:country_code":"PK",
    "gn:dem":1280,
    "gn:feature_class":"P",
    "gn:feature_code":"PPL",
    "gn:name":"Veji",
    "gn:population":0,
    "gn:timezone":"Asia/Karachi",
    "iso:country":"PK",
    "wof:name":"Veji",
    "wof:placetype":"locality"
},
  "geometry": {"coordinates":[70.10596,30.58061],"type":"Point"}
}