{
  "type": "Feature",
  "properties": {
    "gn:admin1_code":"5.0",
    "gn:asciiname":"Khuda Bakhsh Kaka",
    "gn:country_code":"PK",
    "gn:dem":29,
    "gn:feature_class":"P",
    "gn:feature_code":"PPL",
    "gn:name":"Khuda Bakhsh Kaka",
    "gn:population":0,
    "gn:timezone":"Asia/Karachi",
    "iso:country":"PK",
    "name:und_x_variant":[
        "Khoda Bakhsh Kaka",
        "Khuda Bakhsh Kaka"
    ],
    "wof:name":"Khuda Bakhsh Kaka",
    "wof:placetype":"locality"
},
  "geometry": {"coordinates":[68.41119999999999,26.03248],"type":"Point"}
}