{
  "type": "Feature",
  "properties": {
    "gn:admin1_code":"1.0",
    "gn:asciiname":"Sadarai",
    "gn:country_code":"PK",
    "gn:dem":1427,
    "gn:feature_class":"P",
    "gn:feature_code":"PPL",
    "gn:name":"Sadarai",
    "gn:population":0,
    "gn:timezone":"Asia/Karachi",
    "iso:country":"PK",
    "wof:name":"Sadarai",
    "wof:placetype":"locality"
},
  "geometry": {"coordinates":[70.76855999999999,33.6396],"type":"Point"}
}