{
  "type": "Feature",
  "properties": {
    "gn:admin1_code":"5",
    "gn:asciiname":"Sumar Khan Jafri",
    "gn:country_code":"PK",
    "gn:dem":65,
    "gn:feature_class":"P",
    "gn:feature_code":"PPL",
    "gn:name":"Sumar Khan Jafri",
    "gn:population":0,
    "gn:timezone":"Asia/Karachi",
    "iso:country":"PK",
    "name:und_x_variant":[
        "Sukhi Chach\u0101r"
    ],
    "wof:name":"Sumar Khan Jafri",
    "wof:placetype":"locality"
},
  "geometry": {"coordinates":[68.95694,28.22858],"type":"Point"}
}