{
  "type": "Feature",
  "properties": {
    "gn:admin1_code":"5.0",
    "gn:asciiname":"Goth Musa",
    "gn:country_code":"PK",
    "gn:dem":11,
    "gn:feature_class":"P",
    "gn:feature_code":"PPL",
    "gn:name":"Goth Musa",
    "gn:population":0,
    "gn:timezone":"Asia/Karachi",
    "iso:country":"PK",
    "name:und_x_variant":[
        "Goth Misau",
        "Goth Misag",
        "Goth Musa"
    ],
    "wof:name":"Goth Musa",
    "wof:placetype":"locality"
},
  "geometry": {"coordinates":[66.69193,24.86463],"type":"Point"}
}