{
  "type": "Feature",
  "properties": {
    "gn:admin1_code":"5",
    "gn:asciiname":"Goth Wali Khan Lashari",
    "gn:country_code":"PK",
    "gn:dem":25,
    "gn:feature_class":"P",
    "gn:feature_code":"PPL",
    "gn:name":"Goth Wali Khan Lashari",
    "gn:population":0,
    "gn:timezone":"Asia/Karachi",
    "iso:country":"PK",
    "name:und_x_variant":[
        "Goth Ali Wali"
    ],
    "wof:name":"Goth Wali Khan Lashari",
    "wof:placetype":"locality"
},
  "geometry": {"coordinates":[68.56124,25.92536],"type":"Point"}
}