{
  "type": "Feature",
  "properties": {
    "gn:admin1_code":"3.0",
    "gn:asciiname":"Zashtalli",
    "gn:country_code":"PK",
    "gn:dem":3345,
    "gn:feature_class":"P",
    "gn:feature_code":"PPL",
    "gn:name":"Zashtalli",
    "gn:population":0,
    "gn:timezone":"Asia/Karachi",
    "iso:country":"PK",
    "wof:name":"Zashtalli",
    "wof:placetype":"locality"
},
  "geometry": {"coordinates":[71.70739,35.94648],"type":"Point"}
}