{
  "type": "Feature",
  "properties": {
    "gn:country":"PK",
    "gn:fcode":"PPL",
    "gn:pop":139726,
    "iso:country":"PK",
    "name:ara_x_preferred":[
        "\u063a\u0648\u062c\u0631\u0627"
    ],
    "name:ben_x_preferred":[
        "\u0997\u099c\u09b0\u09be"
    ],
    "name:ceb_x_preferred":[
        "Ibbetson\u0101b\u0101d"
    ],
    "name:dan_x_preferred":[
        "Gojra"
    ],
    "name:ell_x_preferred":[
        "\u0393\u03ba\u03cc\u03c4\u03b6\u03c1\u03b1"
    ],
    "name:eng_x_preferred":[
        "Gojra"
    ],
    "name:fas_x_preferred":[
        "\u06af\u0648\u062c\u0631\u0647\u060c \u067e\u0627\u06a9\u0633\u062a\u0627\u0646"
    ],
    "name:fas_x_variant":[
        "\u06af\u0648\u062c\u0631\u0647"
    ],
    "name:fin_x_preferred":[
        "Gojra"
    ],
    "name:fra_x_preferred":[
        "Gojra"
    ],
    "name:guj_x_preferred":[
        "\u0a97\u0acb\u0a9c\u0ab0\u0abe"
    ],
    "name:hin_x_preferred":[
        "\u0917\u094b\u091c\u0930\u093e"
    ],
    "name:ind_x_preferred":[
        "Gojra"
    ],
    "name:ita_x_preferred":[
        "Gojra"
    ],
    "name:jpn_x_preferred":[
        "\u30b4\u30b8\u30e5\u30e9"
    ],
    "name:kan_x_preferred":[
        "\u0c97\u0ccb\u0c9c\u0ccd\u0cb0\u0cbe"
    ],
    "name:kor_x_preferred":[
        "\uace0\uc9c0\ub77c"
    ],
    "name:lav_x_preferred":[
        "God\u017era"
    ],
    "name:lit_x_preferred":[
        "Goira"
    ],
    "name:mar_x_preferred":[
        "\u0917\u094b\u091c\u0930\u093e"
    ],
    "name:msa_x_preferred":[
        "Gojra"
    ],
    "name:nld_x_preferred":[
        "Gojra"
    ],
    "name:nob_x_preferred":[
        "Gojra"
    ],
    "name:pnb_x_preferred":[
        "\u06af\u0648\u062c\u0631\u06c1"
    ],
    "name:pol_x_preferred":[
        "Gojra"
    ],
    "name:por_x_preferred":[
        "Gojra"
    ],
    "name:pus_x_preferred":[
        "\u06af\u0648\u062c\u0631\u0627"
    ],
    "name:rus_x_preferred":[
        "\u0413\u043e\u0434\u0436\u0440\u0430"
    ],
    "name:sin_x_preferred":[
        "\u0d9c\u0ddc\u0da2\u0dca\u0dbb\u0dcf"
    ],
    "name:spa_x_preferred":[
        "Gorja"
    ],
    "name:srp_x_preferred":[
        "\u0413\u043e\u0458\u0440\u0430"
    ],
    "name:swe_x_preferred":[
        "Gojra"
    ],
    "name:tam_x_preferred":[
        "\u0b95\u0bc1\u0b9c\u0bcd\u0bb0\u0bbe"
    ],
    "name:tel_x_preferred":[
        "\u0c17\u0c4b\u0c1c\u0c4d\u0c30"
    ],
    "name:tha_x_preferred":[
        "\u0e01\u0e2d\u0e08\u0e23\u0e32"
    ],
    "name:tur_x_preferred":[
        "Gojra"
    ],
    "name:ukr_x_preferred":[
        "\u0413\u043e\u0434\u0436\u0440\u0430"
    ],
    "name:urd_x_preferred":[
        "\u06af\u0648\u062c\u0631\u06c1"
    ],
    "name:vie_x_preferred":[
        "Gojra"
    ],
    "name:war_x_preferred":[
        "Gojra"
    ],
    "qs:name":"Gojra",
    "qs:photos_9r":0,
    "qs:photos_sr":0,
    "qs:pop_sr":"9",
    "wd:wordcount":1123,
    "wof:name":"Gojra",
    "wof:placetype":"locality",
    "wof:population":139726
},
  "geometry": {"coordinates":[72.68656,31.14874],"type":"Point"}
}