{
  "type": "Feature",
  "properties": {
    "gn:admin1_code":"1.0",
    "gn:asciiname":"Khawaja Khizar",
    "gn:country_code":"PK",
    "gn:dem":1429,
    "gn:feature_class":"P",
    "gn:feature_code":"PPL",
    "gn:name":"Khawaja Khizar",
    "gn:population":0,
    "gn:timezone":"Asia/Karachi",
    "iso:country":"PK",
    "wof:name":"Khawaja Khizar",
    "wof:placetype":"locality"
},
  "geometry": {"coordinates":[70.89927,33.64085],"type":"Point"}
}