{
  "type": "Feature",
  "properties": {
    "gn:admin1_code":"7.0",
    "gn:asciiname":"Khaltaro",
    "gn:country_code":"PK",
    "gn:dem":2564,
    "gn:feature_class":"P",
    "gn:feature_code":"PPL",
    "gn:name":"Khaltaro",
    "gn:population":0,
    "gn:timezone":"Asia/Karachi",
    "iso:country":"PK",
    "wof:name":"Khaltaro",
    "wof:placetype":"locality"
},
  "geometry": {"coordinates":[74.71545,35.91348],"type":"Point"}
}