{
  "type": "Feature",
  "properties": {
    "gn:admin1_code":"04",
    "gn:asciiname":"Nihang",
    "gn:country_code":"PK",
    "gn:dem":168,
    "gn:feature_class":"P",
    "gn:feature_code":"PPL",
    "gn:name":"Nihang",
    "gn:population":0,
    "gn:timezone":"Asia/Karachi",
    "iso:country":"PK",
    "name:fra_x_preferred":[
        "Nihang"
    ],
    "name:mar_x_preferred":[
        "\u0928\u093f\u0939\u0902\u0917"
    ],
    "name:pan_x_preferred":[
        "\u0a28\u0a3f\u0a39\u0a70\u0a17 \u0a38\u0a3f\u0a70\u0a18"
    ],
    "name:pnb_x_preferred":[
        "\u0646\u06cc\u06c1\u0646\u06af"
    ],
    "name:tam_x_preferred":[
        "\u0ba8\u0bbf\u0b95\u0bbe\u0b99\u0bcd"
    ],
    "name:ukr_x_preferred":[
        "\u0410\u043a\u0430\u043b\u0456"
    ],
    "wof:name":"Nihang",
    "wof:placetype":"locality"
},
  "geometry": {"coordinates":[72.28675,31.83546],"type":"Point"}
}