{
  "type": "Feature",
  "properties": {
    "gn:admin1_code":"2.0",
    "gn:asciiname":"Narai Kili",
    "gn:country_code":"PK",
    "gn:dem":1915,
    "gn:feature_class":"P",
    "gn:feature_code":"PPL",
    "gn:name":"Narai Kili",
    "gn:population":0,
    "gn:timezone":"Asia/Karachi",
    "iso:country":"PK",
    "wof:name":"Narai Kili",
    "wof:placetype":"locality"
},
  "geometry": {"coordinates":[68.62291,31.10871],"type":"Point"}
}