{
  "type": "Feature",
  "properties": {
    "gn:admin1_code":"2",
    "gn:asciiname":"Qubba Amir Khan",
    "gn:country_code":"PK",
    "gn:dem":56,
    "gn:feature_class":"P",
    "gn:feature_code":"PPL",
    "gn:name":"Qubba Amir Khan",
    "gn:population":0,
    "gn:timezone":"Asia/Karachi",
    "iso:country":"PK",
    "name:und_x_variant":[
        "Qubba \u0100m\u012br Kh\u0101n"
    ],
    "wof:name":"Qubba Amir Khan",
    "wof:placetype":"locality"
},
  "geometry": {"coordinates":[68.17446,28.23055],"type":"Point"}
}