{
  "type": "Feature",
  "properties": {
    "gn:admin1_code":"1.0",
    "gn:asciiname":"Tandiwal",
    "gn:country_code":"PK",
    "gn:dem":587,
    "gn:feature_class":"P",
    "gn:feature_code":"PPL",
    "gn:name":"Tandiwal",
    "gn:population":0,
    "gn:timezone":"Asia/Karachi",
    "iso:country":"PK",
    "name:und_x_variant":[
        "Arah Khel"
    ],
    "wof:name":"Tandiwal",
    "wof:placetype":"locality"
},
  "geometry": {"coordinates":[71.71996999999998,33.6079],"type":"Point"}
}