{
  "type": "Feature",
  "properties": {
    "gn:admin1_code":"3.0",
    "gn:asciiname":"Ado",
    "gn:country_code":"PK",
    "gn:dem":842,
    "gn:feature_class":"P",
    "gn:feature_code":"PPL",
    "gn:name":"Ado",
    "gn:population":0,
    "gn:timezone":"Asia/Karachi",
    "iso:country":"PK",
    "name:und_x_variant":[
        "\u0100de"
    ],
    "wof:name":"Ado",
    "wof:placetype":"locality"
},
  "geometry": {"coordinates":[72.95025,34.72638],"type":"Point"}
}