{
  "type": "Feature",
  "properties": {
    "gn:admin1_code":"3",
    "gn:asciiname":"Hari Nakka",
    "gn:country_code":"PK",
    "gn:dem":1953,
    "gn:feature_class":"P",
    "gn:feature_code":"PPL",
    "gn:name":"Hari Nakka",
    "gn:population":0,
    "gn:timezone":"Asia/Karachi",
    "iso:country":"PK",
    "wof:name":"Hari Nakka",
    "wof:placetype":"locality"
},
  "geometry": {"coordinates":[73.18416999999999,34.61958],"type":"Point"}
}