{
  "type": "Feature",
  "properties": {
    "gn:admin1_code":"4.0",
    "gn:asciiname":"Ahmadabad Shamai",
    "gn:country_code":"PK",
    "gn:dem":172,
    "gn:feature_class":"P",
    "gn:feature_code":"PPL",
    "gn:name":"Ahmadabad Shamai",
    "gn:population":0,
    "gn:timezone":"Asia/Karachi",
    "iso:country":"PK",
    "name:und_x_variant":[
        "Ahmad\u0101b\u0101d Shimali"
    ],
    "wof:name":"Ahmadabad Shamai",
    "wof:placetype":"locality"
},
  "geometry": {"coordinates":[72.19635,31.83234],"type":"Point"}
}