{
  "type": "Feature",
  "properties": {
    "gn:admin1_code":"7.0",
    "gn:asciiname":"Spindrainj Charagah",
    "gn:country_code":"PK",
    "gn:dem":3939,
    "gn:feature_class":"P",
    "gn:feature_code":"PPL",
    "gn:name":"Spindrainj Charagah",
    "gn:population":0,
    "gn:timezone":"Asia/Karachi",
    "iso:country":"PK",
    "wof:name":"Spindrainj Charagah",
    "wof:placetype":"locality"
},
  "geometry": {"coordinates":[74.62373000000002,36.79894],"type":"Point"}
}