{
  "type": "Feature",
  "properties": {
    "gn:admin1_code":"1.0",
    "gn:asciiname":"Ghakhai",
    "gn:country_code":"PK",
    "gn:dem":2357,
    "gn:feature_class":"P",
    "gn:feature_code":"PPL",
    "gn:name":"Ghakhai",
    "gn:population":0,
    "gn:timezone":"Asia/Karachi",
    "iso:country":"PK",
    "name:und_x_variant":[
        "Ghakai"
    ],
    "wof:name":"Ghakhai",
    "wof:placetype":"locality"
},
  "geometry": {"coordinates":[70.32895000000001,33.8508],"type":"Point"}
}