{
  "type": "Feature",
  "properties": {
    "gn:admin1_code":"01",
    "gn:asciiname":"Rukhan Khel",
    "gn:country_code":"PK",
    "gn:dem":539,
    "gn:feature_class":"P",
    "gn:feature_code":"PPL",
    "gn:name":"Rukhan Khel",
    "gn:population":0,
    "gn:timezone":"Asia/Karachi",
    "iso:country":"PK",
    "wof:name":"Rukhan Khel",
    "wof:placetype":"locality"
},
  "geometry": {"coordinates":[71.62312,33.74127],"type":"Point"}
}