{
  "type": "Feature",
  "properties": {
    "gn:admin1_code":"4",
    "gn:asciiname":"Ahmadwala",
    "gn:country_code":"PK",
    "gn:dem":169,
    "gn:feature_class":"P",
    "gn:feature_code":"PPL",
    "gn:name":"Ahmadwala",
    "gn:population":0,
    "gn:timezone":"Asia/Karachi",
    "iso:country":"PK",
    "name:und_x_variant":[
        "Pur\u0101na Ahmadw\u0101la"
    ],
    "wof:name":"Ahmadwala",
    "wof:placetype":"locality"
},
  "geometry": {"coordinates":[71.18118,31.55813],"type":"Point"}
}