{
  "type": "Feature",
  "properties": {
    "gn:admin1_code":"3",
    "gn:asciiname":"Ghazi Banda",
    "gn:country_code":"PK",
    "gn:dem":978,
    "gn:feature_class":"P",
    "gn:feature_code":"PPL",
    "gn:name":"Ghazi Banda",
    "gn:population":0,
    "gn:timezone":"Asia/Karachi",
    "iso:country":"PK",
    "name:eng_x_preferred":[
        "Mom\u0101nra"
    ],
    "wof:name":"Ghazi Banda",
    "wof:placetype":"locality"
},
  "geometry": {"coordinates":[72.37628000000002,34.41529],"type":"Point"}
}