{
  "type": "Feature",
  "properties": {
    "gn:admin1_code":"5",
    "gn:asciiname":"Goth Lakhano Khaskheli",
    "gn:country_code":"PK",
    "gn:dem":19,
    "gn:feature_class":"P",
    "gn:feature_code":"PPL",
    "gn:name":"Goth Lakhano Khaskheli",
    "gn:population":0,
    "gn:timezone":"Asia/Karachi",
    "iso:country":"PK",
    "name:und_x_variant":[
        "Goth Lakhno Kh\u0101skheli"
    ],
    "wof:name":"Goth Lakhano Khaskheli",
    "wof:placetype":"locality"
},
  "geometry": {"coordinates":[68.95759,25.69732],"type":"Point"}
}