{
  "type": "Feature",
  "properties": {
    "gn:admin1_code":"2.0",
    "gn:asciiname":"Wach Sanzalai Kili",
    "gn:country_code":"PK",
    "gn:dem":1877,
    "gn:feature_class":"P",
    "gn:feature_code":"PPL",
    "gn:name":"Wach Sanzalai Kili",
    "gn:population":0,
    "gn:timezone":"Asia/Karachi",
    "iso:country":"PK",
    "name:und_x_variant":[
        "Wach Sanzaiai Kili"
    ],
    "wof:name":"Wach Sanzalai Kili",
    "wof:placetype":"locality"
},
  "geometry": {"coordinates":[69.00690999999999,31.42722],"type":"Point"}
}