{
  "type": "Feature",
  "properties": {
    "gn:admin1_code":"2",
    "gn:asciiname":"Killi Haji Abdur Rehman",
    "gn:country_code":"PK",
    "gn:dem":2259,
    "gn:feature_class":"P",
    "gn:feature_code":"PPL",
    "gn:name":"Killi Haji Abdur Rehman",
    "gn:population":0,
    "gn:timezone":"Asia/Karachi",
    "iso:country":"PK",
    "name:und_x_variant":[
        "Ch\u0101u Kach"
    ],
    "wof:name":"Killi Haji Abdur Rehman",
    "wof:placetype":"locality"
},
  "geometry": {"coordinates":[66.95909,31.03248],"type":"Point"}
}