{
  "type": "Feature",
  "properties": {
    "gn:admin1_code":"4",
    "gn:asciiname":"Dewanwala",
    "gn:country_code":"PK",
    "gn:dem":133,
    "gn:feature_class":"P",
    "gn:feature_code":"PPL",
    "gn:name":"Dewanwala",
    "gn:population":0,
    "gn:timezone":"Asia/Karachi",
    "iso:country":"PK",
    "name:und_x_variant":[
        "D\u012bw\u0101nw\u0101la"
    ],
    "wof:name":"Dewanwala",
    "wof:placetype":"locality"
},
  "geometry": {"coordinates":[71.11506,30.44443],"type":"Point"}
}