{
  "type": "Feature",
  "properties": {
    "gn:admin1_code":"4",
    "gn:asciiname":"Takht Ramwala",
    "gn:country_code":"PK",
    "gn:dem":121,
    "gn:feature_class":"P",
    "gn:feature_code":"PPL",
    "gn:name":"Takht Ramwala",
    "gn:population":0,
    "gn:timezone":"Asia/Karachi",
    "iso:country":"PK",
    "wof:name":"Takht Ramwala",
    "wof:placetype":"locality"
},
  "geometry": {"coordinates":[71.72221999999999,29.77083],"type":"Point"}
}