{
  "type": "Feature",
  "properties": {
    "gn:admin1_code":"1.0",
    "gn:asciiname":"Narai",
    "gn:country_code":"PK",
    "gn:dem":697,
    "gn:feature_class":"P",
    "gn:feature_code":"PPL",
    "gn:name":"Narai",
    "gn:population":0,
    "gn:timezone":"Asia/Karachi",
    "iso:country":"PK",
    "wof:name":"Narai",
    "wof:placetype":"locality"
},
  "geometry": {"coordinates":[71.24475,34.2627],"type":"Point"}
}