{
  "type": "Feature",
  "properties": {
    "gn:admin1_code":"6",
    "gn:asciiname":"Nika",
    "gn:country_code":"PK",
    "gn:dem":747,
    "gn:feature_class":"P",
    "gn:feature_code":"PPL",
    "gn:name":"Nika",
    "gn:population":0,
    "gn:timezone":"Asia/Karachi",
    "iso:country":"PK",
    "name:aze_x_preferred":[
        "Nika"
    ],
    "name:bel_x_preferred":[
        "\u041d\u0456\u043a\u0430"
    ],
    "name:ceb_x_preferred":[
        "Nika"
    ],
    "name:ces_x_preferred":[
        "Nika"
    ],
    "name:deu_x_preferred":[
        "Nika"
    ],
    "name:fas_x_preferred":[
        "\u0646\u06cc\u06a9\u0627"
    ],
    "name:fra_x_preferred":[
        "Nika"
    ],
    "name:heb_x_preferred":[
        "\u05e0\u05d9\u05e7\u05d4"
    ],
    "name:ita_x_preferred":[
        "Nika"
    ],
    "name:rus_x_preferred":[
        "\u041d\u0438\u043a\u0430"
    ],
    "name:slk_x_preferred":[
        "Nika"
    ],
    "name:slv_x_preferred":[
        "Nika"
    ],
    "name:spa_x_preferred":[
        "Nika"
    ],
    "name:srp_x_preferred":[
        "\u041d\u0438\u043a\u0430"
    ],
    "name:swe_x_preferred":[
        "Nika"
    ],
    "wof:name":"Nika",
    "wof:placetype":"locality"
},
  "geometry": {"coordinates":[74.14154000000001,33.03064000000001],"type":"Point"}
}