{
  "type": "Feature",
  "properties": {
    "gn:admin1_code":"6",
    "gn:asciiname":"Nika",
    "gn:country_code":"PK",
    "gn:dem":747,
    "gn:feature_class":"P",
    "gn:feature_code":"PPL",
    "gn:name":"Nika",
    "gn:population":0,
    "gn:timezone":"Asia/Karachi",
    "iso:country":"PK",
    "wof:name":"Nika",
    "wof:placetype":"locality"
},
  "geometry": {"coordinates":[74.14154000000001,33.03064000000001],"type":"Point"}
}