{
  "type": "Feature",
  "properties": {
    "gn:admin1_code":"03",
    "gn:asciiname":"Mankial",
    "gn:country_code":"PK",
    "gn:dem":1670,
    "gn:feature_class":"P",
    "gn:feature_code":"PPL",
    "gn:name":"Mankial",
    "gn:population":0,
    "gn:timezone":"Asia/Karachi",
    "iso:country":"PK",
    "wof:name":"Mankial",
    "wof:placetype":"locality"
},
  "geometry": {"coordinates":[72.61498,35.32516],"type":"Point"}
}