{
  "type": "Feature",
  "properties": {
    "gn:admin1_code":"5.0",
    "gn:asciiname":"Lakhio Tar",
    "gn:country_code":"PK",
    "gn:dem":56,
    "gn:feature_class":"P",
    "gn:feature_code":"PPL",
    "gn:name":"Lakhio Tar",
    "gn:population":0,
    "gn:timezone":"Asia/Karachi",
    "iso:country":"PK",
    "name:und_x_variant":[
        "L\u0101khio"
    ],
    "wof:name":"Lakhio Tar",
    "wof:placetype":"locality"
},
  "geometry": {"coordinates":[69.77064,26.20968],"type":"Point"}
}