{
  "type": "Feature",
  "properties": {
    "gn:admin1_code":"01",
    "gn:asciiname":"Changabazo",
    "gn:country_code":"PK",
    "gn:dem":1995,
    "gn:feature_class":"P",
    "gn:feature_code":"PPL",
    "gn:name":"Changabazo",
    "gn:population":0,
    "gn:timezone":"Asia/Karachi",
    "iso:country":"PK",
    "name:und_x_variant":[
        "Changab\u0101zo"
    ],
    "wof:name":"Changabazo",
    "wof:placetype":"locality"
},
  "geometry": {"coordinates":[70.75071,33.61784],"type":"Point"}
}