{
  "type": "Feature",
  "properties": {
    "gn:admin1_code":"7.0",
    "gn:asciiname":"Kur",
    "gn:country_code":"PK",
    "gn:dem":2487,
    "gn:feature_class":"P",
    "gn:feature_code":"PPL",
    "gn:name":"Kur",
    "gn:population":0,
    "gn:timezone":"Asia/Karachi",
    "iso:country":"PK",
    "name:cat_x_preferred":[
        "Kur"
    ],
    "name:deu_x_preferred":[
        "Kur"
    ],
    "name:eus_x_preferred":[
        "Kur"
    ],
    "name:fas_x_preferred":[
        "\u06a9\u0648\u0631"
    ],
    "name:hun_x_preferred":[
        "Kur"
    ],
    "name:hye_x_preferred":[
        "\u053f\u0578\u0582\u0580"
    ],
    "name:ita_x_preferred":[
        "Kur"
    ],
    "name:jpn_x_preferred":[
        "\u30af\u30eb"
    ],
    "name:kur_x_preferred":[
        "Kur"
    ],
    "name:mkd_x_preferred":[
        "\u041a\u0443\u0440"
    ],
    "name:nld_x_preferred":[
        "Kur"
    ],
    "name:pol_x_preferred":[
        "Kur"
    ],
    "name:spa_x_preferred":[
        "Kur"
    ],
    "name:swe_x_preferred":[
        "Kur"
    ],
    "name:tur_x_preferred":[
        "Kur"
    ],
    "name:zho_x_preferred":[
        "\u5e93\u5c14"
    ],
    "wof:name":"Kur",
    "wof:placetype":"locality"
},
  "geometry": {"coordinates":[76.42829999999999,35.16097],"type":"Point"}
}