{
  "type": "Feature",
  "properties": {
    "gn:admin1_code":"3.0",
    "gn:asciiname":"Khon Rambil",
    "gn:country_code":"PK",
    "gn:dem":2299,
    "gn:feature_class":"P",
    "gn:feature_code":"PPL",
    "gn:name":"Khon Rambil",
    "gn:population":0,
    "gn:timezone":"Asia/Karachi",
    "iso:country":"PK",
    "wof:name":"Khon Rambil",
    "wof:placetype":"locality"
},
  "geometry": {"coordinates":[72.92307,35.61138],"type":"Point"}
}