{
  "type": "Feature",
  "properties": {
    "gn:admin1_code":"2.0",
    "gn:asciiname":"Qadir Dad Jaoh",
    "gn:country_code":"PK",
    "gn:dem":519,
    "gn:feature_class":"P",
    "gn:feature_code":"PPL",
    "gn:name":"Qadir Dad Jaoh",
    "gn:population":0,
    "gn:timezone":"Asia/Karachi",
    "iso:country":"PK",
    "name:und_x_variant":[
        "Q\u0101dird\u0101d"
    ],
    "wof:name":"Qadir Dad Jaoh",
    "wof:placetype":"locality"
},
  "geometry": {"coordinates":[65.21301,26.42286],"type":"Point"}
}