{
  "type": "Feature",
  "properties": {
    "gn:admin1_code":"2.0",
    "gn:asciiname":"Sawal Kili",
    "gn:country_code":"PK",
    "gn:dem":1123,
    "gn:feature_class":"P",
    "gn:feature_code":"PPL",
    "gn:name":"Sawal Kili",
    "gn:population":0,
    "gn:timezone":"Asia/Karachi",
    "iso:country":"PK",
    "wof:name":"Sawal Kili",
    "wof:placetype":"locality"
},
  "geometry": {"coordinates":[68.57481,30.18983],"type":"Point"}
}