{
  "type": "Feature",
  "properties": {
    "iso:country":"PK",
    "name:deu_x_preferred":[
        "Bhalwal"
    ],
    "name:fra_x_preferred":[
        "Bhalwal"
    ],
    "name:hin_x_preferred":[
        "\u092d\u0932\u0935\u093e\u0932"
    ],
    "name:pnb_x_preferred":[
        "\u0628\u06be\u0644\u0648\u0627\u0644"
    ],
    "name:por_x_preferred":[
        "Bhalwal"
    ],
    "name:pus_x_preferred":[
        "\u0628\u0627\u0644\u0648\u0627\u0644"
    ],
    "name:unk_x_variant":[
        "Bhalw\u0101l"
    ],
    "name:urd_x_preferred":[
        "\u0628\u06be\u0644\u0648\u0627\u0644"
    ],
    "qs:gn_country":"PK",
    "qs:gn_fcode":"PPL",
    "qs:gn_pop":74744,
    "qs:name":"Bhalwal",
    "qs:name_adm0":"Pakistan",
    "qs:name_adm1":"Punjab",
    "qs:photos":0,
    "qs:photos_1k":0,
    "qs:photos_9k":1,
    "qs:photos_9r":2,
    "qs:photos_all":50,
    "qs:photos_sr":0,
    "qs:placetype":"Town",
    "qs:pop_sr":"8",
    "qs:woe_adm0":23424922,
    "wd:wordcount":117,
    "wof:name":"Bhalwal",
    "wof:placetype":"locality",
    "wof:population":74744
},
  "geometry": {"coordinates":[72.90425,32.27204],"type":"Point"}
}