{
  "type": "Feature",
  "properties": {
    "iso:country":"PK",
    "name:ara_x_preferred":[
        "\u0628\u0647\u0644\u0648\u0627\u0644"
    ],
    "name:ben_x_preferred":[
        "\u09ad\u09be\u0993\u09af\u09bc\u09be\u09b2"
    ],
    "name:dan_x_preferred":[
        "Bhalwal"
    ],
    "name:deu_x_preferred":[
        "Bhalwal"
    ],
    "name:ell_x_preferred":[
        "\u039c\u03c0\u03c7\u03b1\u03bb\u03b2\u03ac\u03bb"
    ],
    "name:eng_x_preferred":[
        "Bhalwal"
    ],
    "name:fas_x_preferred":[
        "\u0628\u0647\u0644\u0648\u0627\u0644"
    ],
    "name:fin_x_preferred":[
        "Bhalwal"
    ],
    "name:fra_x_preferred":[
        "Bhalwal"
    ],
    "name:guj_x_preferred":[
        "\u0aad\u0abe\u0ab2\u0ab5\u0abe\u0ab2"
    ],
    "name:hin_x_preferred":[
        "\u092d\u0932\u0935\u093e\u0932"
    ],
    "name:ind_x_preferred":[
        "Bhalwal"
    ],
    "name:ita_x_preferred":[
        "Bhalwal"
    ],
    "name:jpn_x_preferred":[
        "\u30d0\u30eb\u30ef\u30eb"
    ],
    "name:kan_x_preferred":[
        "\u0cad\u0cb2\u0ccd\u0cb5\u0cbe\u0cb2\u0ccd"
    ],
    "name:kor_x_preferred":[
        "\ubc14\ud558\uc648"
    ],
    "name:lav_x_preferred":[
        "Bhalvala"
    ],
    "name:lit_x_preferred":[
        "Balvalas"
    ],
    "name:mar_x_preferred":[
        "\u092d\u093e\u0932\u0935\u093e\u0932"
    ],
    "name:msa_x_preferred":[
        "Bhalwal"
    ],
    "name:nld_x_preferred":[
        "Bhalwal"
    ],
    "name:nob_x_preferred":[
        "Bhalwal"
    ],
    "name:pnb_x_preferred":[
        "\u0628\u06be\u0644\u0648\u0627\u0644"
    ],
    "name:pol_x_preferred":[
        "Bhalwal"
    ],
    "name:por_x_preferred":[
        "Bhalwal"
    ],
    "name:pus_x_preferred":[
        "\u0628\u0627\u0644\u0648\u0627\u0644"
    ],
    "name:rus_x_preferred":[
        "\u0411\u0445\u0430\u043b\u0432\u0430\u043b"
    ],
    "name:sin_x_preferred":[
        "\u0db7\u0dcf\u0dbd\u0dca\u0dc0\u0dbd\u0dca"
    ],
    "name:spa_x_preferred":[
        "Bhalwai"
    ],
    "name:swe_x_preferred":[
        "Bhalwal"
    ],
    "name:tam_x_preferred":[
        "\u0baa\u0bbe\u0bb2\u0bcd\u0bb5\u0bbe\u0bb3\u0bcd"
    ],
    "name:tel_x_preferred":[
        "\u0c2c\u0c32\u0c4d\u0c35\u0c3e\u0c32\u0c4d"
    ],
    "name:tha_x_preferred":[
        "\u0e1a\u0e2e\u0e32\u0e27\u0e31\u0e25"
    ],
    "name:tur_x_preferred":[
        "Bhalwal"
    ],
    "name:ukr_x_preferred":[
        "\u0411\u0433\u0430\u043b\u0432\u0430\u043b"
    ],
    "name:und_x_variant":[
        "Bhalw\u0101l"
    ],
    "name:urd_x_preferred":[
        "\u0628\u06be\u0644\u0648\u0627\u0644"
    ],
    "name:vie_x_preferred":[
        "Bhalwal"
    ],
    "qs:gn_country":"PK",
    "qs:gn_fcode":"PPL",
    "qs:gn_pop":74744,
    "qs:name":"Bhalwal",
    "qs:name_adm0":"Pakistan",
    "qs:name_adm1":"Punjab",
    "qs:photos":0,
    "qs:photos_1k":0,
    "qs:photos_9k":1,
    "qs:photos_9r":2,
    "qs:photos_all":50,
    "qs:photos_sr":0,
    "qs:placetype":"Town",
    "qs:pop_sr":"8",
    "qs:woe_adm0":23424922,
    "wd:wordcount":117,
    "wof:name":"Bhalwal",
    "wof:placetype":"locality",
    "wof:population":74744
},
  "geometry": {"coordinates":[72.90425,32.27204],"type":"Point"}
}