{
  "type": "Feature",
  "properties": {
    "gn:admin1_code":"4.0",
    "gn:asciiname":"Rakh Pilawais",
    "gn:country_code":"PK",
    "gn:dem":187,
    "gn:feature_class":"P",
    "gn:feature_code":"PPL",
    "gn:name":"Rakh Pilawais",
    "gn:population":0,
    "gn:timezone":"Asia/Karachi",
    "iso:country":"PK",
    "wof:name":"Rakh Pilawais",
    "wof:placetype":"locality"
},
  "geometry": {"coordinates":[71.96838000000002,32.06869],"type":"Point"}
}