{
  "type": "Feature",
  "properties": {
    "gn:admin1_code":"2.0",
    "gn:asciiname":"Rais Muhammad",
    "gn:country_code":"PK",
    "gn:dem":63,
    "gn:feature_class":"P",
    "gn:feature_code":"PPL",
    "gn:name":"Rais Muhammad",
    "gn:population":0,
    "gn:timezone":"Asia/Karachi",
    "iso:country":"PK",
    "name:und_x_variant":[
        "Ra\u012bs Muhammad W\u0101ja"
    ],
    "wof:name":"Rais Muhammad",
    "wof:placetype":"locality"
},
  "geometry": {"coordinates":[67.94377,28.45692],"type":"Point"}
}