{
  "type": "Feature",
  "properties": {
    "gn:admin1_code":"4.0",
    "gn:asciiname":"Qaziabad",
    "gn:country_code":"PK",
    "gn:dem":151,
    "gn:feature_class":"P",
    "gn:feature_code":"PPL",
    "gn:name":"Qaziabad",
    "gn:population":0,
    "gn:timezone":"Asia/Karachi",
    "iso:country":"PK",
    "name:fas_x_preferred":[
        "\u0642\u0627\u0636\u06cc\u200c\u0622\u0628\u0627\u062f"
    ],
    "wof:name":"Qaziabad",
    "wof:placetype":"locality"
},
  "geometry": {"coordinates":[71.20662,31.08298],"type":"Point"}
}