{
  "type": "Feature",
  "properties": {
    "gn:admin1_code":"2.0",
    "gn:asciiname":"Tangai",
    "gn:country_code":"PK",
    "gn:dem":2444,
    "gn:feature_class":"P",
    "gn:feature_code":"PPL",
    "gn:name":"Tangai",
    "gn:population":0,
    "gn:timezone":"Asia/Karachi",
    "iso:country":"PK",
    "name:eng_x_preferred":[
        "Tangai"
    ],
    "wof:name":"Tangai",
    "wof:placetype":"locality"
},
  "geometry": {"coordinates":[67.42865999999999,30.9679],"type":"Point"}
}