{
  "type": "Feature",
  "properties": {
    "gn:admin1_code":"2.0",
    "gn:asciiname":"Khudezai",
    "gn:country_code":"PK",
    "gn:dem":1370,
    "gn:feature_class":"P",
    "gn:feature_code":"PPL",
    "gn:name":"Khudezai",
    "gn:population":0,
    "gn:timezone":"Asia/Karachi",
    "iso:country":"PK",
    "wof:name":"Khudezai",
    "wof:placetype":"locality"
},
  "geometry": {"coordinates":[69.90396,31.20193],"type":"Point"}
}