{
  "type": "Feature",
  "properties": {
    "gn:admin1_code":"04",
    "gn:asciiname":"Nir Khian",
    "gn:country_code":"PK",
    "gn:dem":261,
    "gn:feature_class":"P",
    "gn:feature_code":"PPL",
    "gn:name":"Nir Khian",
    "gn:population":0,
    "gn:timezone":"Asia/Karachi",
    "iso:country":"PK",
    "name:und_x_variant":[
        "Nir Khayan",
        "Nir Khian"
    ],
    "wof:name":"Nir Khian",
    "wof:placetype":"locality"
},
  "geometry": {"coordinates":[73.56418000000002,32.99436],"type":"Point"}
}