{
  "type": "Feature",
  "properties": {
    "gn:admin1_code":"6",
    "gn:asciiname":"Tatta Pani",
    "gn:country_code":"PK",
    "gn:dem":741,
    "gn:feature_class":"P",
    "gn:feature_code":"PPL",
    "gn:name":"Tatta Pani",
    "gn:population":0,
    "gn:timezone":"Asia/Karachi",
    "iso:country":"PK",
    "name:hin_x_preferred":[
        "\u0924\u0924\u094d\u0924\u093e\u092a\u093e\u0928\u0940"
    ],
    "name:und_x_variant":[
        "Dhan\u0101h"
    ],
    "wof:name":"Tatta Pani",
    "wof:placetype":"locality"
},
  "geometry": {"coordinates":[73.94988000000002,33.60773],"type":"Point"}
}