{
  "type": "Feature",
  "properties": {
    "gn:admin1_code":"4.0",
    "gn:asciiname":"Chak Forty-four - Five Left",
    "gn:country_code":"PK",
    "gn:dem":165,
    "gn:feature_class":"P",
    "gn:feature_code":"PPL",
    "gn:name":"Chak Forty-four - Five Left",
    "gn:population":0,
    "gn:timezone":"Asia/Karachi",
    "iso:country":"PK",
    "name:und_x_variant":[
        "Kakk\u016bana",
        "Kakho\u0101new\u0101la"
    ],
    "wof:name":"Chak Forty-four - Five Left",
    "wof:placetype":"locality"
},
  "geometry": {"coordinates":[73.29133,30.57913],"type":"Point"}
}