{
  "type": "Feature",
  "properties": {
    "gn:admin1_code":"4",
    "gn:asciiname":"Dhamanwali",
    "gn:country_code":"PK",
    "gn:dem":233,
    "gn:feature_class":"P",
    "gn:feature_code":"PPL",
    "gn:name":"Dhamanwali",
    "gn:population":0,
    "gn:timezone":"Asia/Karachi",
    "iso:country":"PK",
    "name:und_x_variant":[
        "Dh\u0101mi\u0101n"
    ],
    "wof:name":"Dhamanwali",
    "wof:placetype":"locality"
},
  "geometry": {"coordinates":[74.31016,32.49401],"type":"Point"}
}