{
  "type": "Feature",
  "properties": {
    "gn:admin1_code":"3",
    "gn:asciiname":"Tahangar",
    "gn:country_code":"PK",
    "gn:dem":1260,
    "gn:feature_class":"P",
    "gn:feature_code":"PPL",
    "gn:name":"Tahangar",
    "gn:population":0,
    "gn:timezone":"Asia/Karachi",
    "iso:country":"PK",
    "name:und_x_variant":[
        "Tangar"
    ],
    "wof:name":"Tahangar",
    "wof:placetype":"locality"
},
  "geometry": {"coordinates":[73.4033,34.62448],"type":"Point"}
}