{
  "type": "Feature",
  "properties": {
    "gn:admin1_code":"4.0",
    "gn:asciiname":"Gulshan Iqbal",
    "gn:country_code":"PK",
    "gn:dem":223,
    "gn:feature_class":"P",
    "gn:feature_code":"PPL",
    "gn:name":"Gulshan Iqbal",
    "gn:population":0,
    "gn:timezone":"Asia/Karachi",
    "iso:country":"PK",
    "wof:name":"Gulshan Iqbal",
    "wof:placetype":"locality"
},
  "geometry": {"coordinates":[73.58164000000002,32.65581],"type":"Point"}
}