{
  "type": "Feature",
  "properties": {
    "gn:admin1_code":"3.0",
    "gn:asciiname":"Kachkol Banda",
    "gn:country_code":"PK",
    "gn:dem":324,
    "gn:feature_class":"P",
    "gn:feature_code":"PPL",
    "gn:name":"Kachkol Banda",
    "gn:population":0,
    "gn:timezone":"Asia/Karachi",
    "iso:country":"PK",
    "wof:name":"Kachkol Banda",
    "wof:placetype":"locality"
},
  "geometry": {"coordinates":[72.52876999999999,34.09155],"type":"Point"}
}