{
  "type": "Feature",
  "properties": {
    "gn:admin1_code":"5.0",
    "gn:asciiname":"Goth Burtullah",
    "gn:country_code":"PK",
    "gn:dem":40,
    "gn:feature_class":"P",
    "gn:feature_code":"PPL",
    "gn:name":"Goth Burtullah",
    "gn:population":0,
    "gn:timezone":"Asia/Karachi",
    "iso:country":"PK",
    "name:und_x_variant":[
        "Batt\u0101li"
    ],
    "wof:name":"Goth Burtullah",
    "wof:placetype":"locality"
},
  "geometry": {"coordinates":[70.90123,24.59944],"type":"Point"}
}