{
  "type": "Feature",
  "properties": {
    "gn:admin1_code":"4.0",
    "gn:asciiname":"Bhialian",
    "gn:country_code":"PK",
    "gn:dem":1434,
    "gn:feature_class":"P",
    "gn:feature_code":"PPL",
    "gn:name":"Bhialian",
    "gn:population":0,
    "gn:timezone":"Asia/Karachi",
    "iso:country":"PK",
    "name:und_x_variant":[
        "Pi\u0101ll\u0101n"
    ],
    "wof:name":"Bhialian",
    "wof:placetype":"locality"
},
  "geometry": {"coordinates":[73.51739999999999,33.71491],"type":"Point"}
}