{
  "type": "Feature",
  "properties": {
    "gn:admin1_code":"4",
    "gn:asciiname":"Basti Abdul Qadir Dehr",
    "gn:country_code":"PK",
    "gn:dem":80,
    "gn:feature_class":"P",
    "gn:feature_code":"PPL",
    "gn:name":"Basti Abdul Qadir Dehr",
    "gn:population":0,
    "gn:timezone":"Asia/Karachi",
    "iso:country":"PK",
    "name:und_x_variant":[
        "Dost Muhammad"
    ],
    "wof:name":"Basti Abdul Qadir Dehr",
    "wof:placetype":"locality"
},
  "geometry": {"coordinates":[69.95886,28.35763],"type":"Point"}
}