{
  "type": "Feature",
  "properties": {
    "gn:admin1_code":"2.0",
    "gn:asciiname":"Chhiri Potani",
    "gn:country_code":"PK",
    "gn:dem":875,
    "gn:feature_class":"P",
    "gn:feature_code":"PPL",
    "gn:name":"Chhiri Potani",
    "gn:population":0,
    "gn:timezone":"Asia/Karachi",
    "iso:country":"PK",
    "name:und_x_variant":[
        "Chhiri Pot\u0101ni"
    ],
    "wof:name":"Chhiri Potani",
    "wof:placetype":"locality"
},
  "geometry": {"coordinates":[63.0105,26.45994],"type":"Point"}
}