{
  "type": "Feature",
  "properties": {
    "gn:admin1_code":"4",
    "gn:asciiname":"Chak Three Hundred Ten Jhang Branch",
    "gn:country_code":"PK",
    "gn:dem":165,
    "gn:feature_class":"P",
    "gn:feature_code":"PPL",
    "gn:name":"Chak Three Hundred Ten Jhang Branch",
    "gn:population":0,
    "gn:timezone":"Asia/Karachi",
    "iso:country":"PK",
    "name:und_x_variant":[
        "Thatta Bhop\u0101l",
        "Chak Number Three Hundred Ten",
        "Chak Three Hundred Ten Jhang Branch",
        "Thatta"
    ],
    "wof:name":"Chak Three Hundred Ten Jhang Branch",
    "wof:placetype":"locality"
},
  "geometry": {"coordinates":[72.56307,31.12605],"type":"Point"}
}