{
  "type": "Feature",
  "properties": {
    "gn:admin1_code":"4",
    "gn:asciiname":"Gulbahar Waldi",
    "gn:country_code":"PK",
    "gn:dem":258,
    "gn:feature_class":"P",
    "gn:feature_code":"PPL",
    "gn:name":"Gulbahar Waldi",
    "gn:population":0,
    "gn:timezone":"Asia/Karachi",
    "iso:country":"PK",
    "name:und_x_variant":[
        "Gul Bahar Kalan",
        "Gulbah\u0101r Waldi"
    ],
    "wof:name":"Gulbahar Waldi",
    "wof:placetype":"locality"
},
  "geometry": {"coordinates":[74.59356,32.55867],"type":"Point"}
}