{
  "type": "Feature",
  "properties": {
    "gn:admin1_code":"5",
    "gn:asciiname":"Goth Ghulam Rasul Khaskheli",
    "gn:country_code":"PK",
    "gn:dem":12,
    "gn:feature_class":"P",
    "gn:feature_code":"PPL",
    "gn:name":"Goth Ghulam Rasul Khaskheli",
    "gn:population":0,
    "gn:timezone":"Asia/Karachi",
    "iso:country":"PK",
    "name:und_x_variant":[
        "H\u0101ji Abdull\u0101h Kh\u0101skheli"
    ],
    "wof:name":"Goth Ghulam Rasul Khaskheli",
    "wof:placetype":"locality"
},
  "geometry": {"coordinates":[69.39504000000001,25.25503],"type":"Point"}
}