{
  "type": "Feature",
  "properties": {
    "gn:admin1_code":"4",
    "gn:asciiname":"Kacha Pind",
    "gn:country_code":"PK",
    "gn:dem":197,
    "gn:feature_class":"P",
    "gn:feature_code":"PPL",
    "gn:name":"Kacha Pind",
    "gn:population":0,
    "gn:timezone":"Asia/Karachi",
    "iso:country":"PK",
    "name:und_x_variant":[
        "Kacha"
    ],
    "wof:name":"Kacha Pind",
    "wof:placetype":"locality"
},
  "geometry": {"coordinates":[73.58634000000001,31.43495],"type":"Point"}
}