{
  "type": "Feature",
  "properties": {
    "gn:admin1_code":"4",
    "gn:asciiname":"Kikarwala Khu",
    "gn:country_code":"PK",
    "gn:dem":139,
    "gn:feature_class":"P",
    "gn:feature_code":"PPL",
    "gn:name":"Kikarwala Khu",
    "gn:population":0,
    "gn:timezone":"Asia/Karachi",
    "iso:country":"PK",
    "name:und_x_variant":[
        "Khu K\u012bkriw\u0101la"
    ],
    "wof:name":"Kikarwala Khu",
    "wof:placetype":"locality"
},
  "geometry": {"coordinates":[72.01347,30.72247],"type":"Point"}
}