{
  "type": "Feature",
  "properties": {
    "gn:admin1_code":"3.0",
    "gn:asciiname":"Satti",
    "gn:country_code":"PK",
    "gn:dem":380,
    "gn:feature_class":"P",
    "gn:feature_code":"PPL",
    "gn:name":"Satti",
    "gn:population":0,
    "gn:timezone":"Asia/Karachi",
    "iso:country":"PK",
    "name:und_x_variant":[
        "Siti"
    ],
    "wof:name":"Satti",
    "wof:placetype":"locality"
},
  "geometry": {"coordinates":[70.63158,33.03683],"type":"Point"}
}