{
  "type": "Feature",
  "properties": {
    "gn:admin1_code":"4.0",
    "gn:asciiname":"Basti Usmanpur",
    "gn:country_code":"PK",
    "gn:dem":99,
    "gn:feature_class":"P",
    "gn:feature_code":"PPL",
    "gn:name":"Basti Usmanpur",
    "gn:population":0,
    "gn:timezone":"Asia/Karachi",
    "iso:country":"PK",
    "wof:name":"Basti Usmanpur",
    "wof:placetype":"locality"
},
  "geometry": {"coordinates":[70.26906,29.2059],"type":"Point"}
}