{
  "type": "Feature",
  "properties": {
    "gn:admin1_code":"1.0",
    "gn:asciiname":"Uria Khel",
    "gn:country_code":"PK",
    "gn:dem":1894,
    "gn:feature_class":"P",
    "gn:feature_code":"PPL",
    "gn:name":"Uria Khel",
    "gn:population":0,
    "gn:timezone":"Asia/Karachi",
    "iso:country":"PK",
    "wof:name":"Uria Khel",
    "wof:placetype":"locality"
},
  "geometry": {"coordinates":[70.81039,33.74296],"type":"Point"}
}