{
  "type": "Feature",
  "properties": {
    "gn:admin1_code":"4.0",
    "gn:asciiname":"Khu Shahadat",
    "gn:country_code":"PK",
    "gn:dem":197,
    "gn:feature_class":"P",
    "gn:feature_code":"PPL",
    "gn:name":"Khu Shahadat",
    "gn:population":0,
    "gn:timezone":"Asia/Karachi",
    "iso:country":"PK",
    "name:und_x_variant":[
        "Khui Sh\u0101duki"
    ],
    "wof:name":"Khu Shahadat",
    "wof:placetype":"locality"
},
  "geometry": {"coordinates":[73.34478,31.94637],"type":"Point"}
}