{
  "type": "Feature",
  "properties": {
    "gn:admin1_code":"6",
    "gn:asciiname":"Khalana Bazar",
    "gn:country_code":"PK",
    "gn:dem":1664,
    "gn:feature_class":"P",
    "gn:feature_code":"PPL",
    "gn:name":"Khalana Bazar",
    "gn:population":0,
    "gn:timezone":"Asia/Kolkata",
    "iso:country":"PK",
    "name:und_x_variant":[
        "Khali\u0101na Kal\u0101n"
    ],
    "wof:name":"Khalana Bazar",
    "wof:placetype":"locality"
},
  "geometry": {"coordinates":[73.88630000000001,34.07102],"type":"Point"}
}