{
  "type": "Feature",
  "properties": {
    "gn:admin1_code":"4.0",
    "gn:asciiname":"Khewanan Dera",
    "gn:country_code":"PK",
    "gn:dem":192,
    "gn:feature_class":"P",
    "gn:feature_code":"PPL",
    "gn:name":"Khewanan Dera",
    "gn:population":0,
    "gn:timezone":"Asia/Karachi",
    "iso:country":"PK",
    "name:und_x_variant":[
        "Koew\u0101n\u0101n Dera",
        "Khewanan Dera"
    ],
    "wof:name":"Khewanan Dera",
    "wof:placetype":"locality"
},
  "geometry": {"coordinates":[72.74160000000001,32.18375],"type":"Point"}
}