{
  "type": "Feature",
  "properties": {
    "gn:admin1_code":"3",
    "gn:asciiname":"Dhuran Banda",
    "gn:country_code":"PK",
    "gn:dem":403,
    "gn:feature_class":"P",
    "gn:feature_code":"PPL",
    "gn:name":"Dhuran Banda",
    "gn:population":0,
    "gn:timezone":"Asia/Karachi",
    "iso:country":"PK",
    "name:und_x_variant":[
        "Dhoran B\u0101nda"
    ],
    "wof:name":"Dhuran Banda",
    "wof:placetype":"locality"
},
  "geometry": {"coordinates":[70.93026,33.06077],"type":"Point"}
}