{
  "type": "Feature",
  "properties": {
    "gn:admin1_code":"4",
    "gn:asciiname":"Chak One Hundred Thirty-four",
    "gn:country_code":"PK",
    "gn:dem":147,
    "gn:feature_class":"P",
    "gn:feature_code":"PPL",
    "gn:name":"Chak One Hundred Thirty-four",
    "gn:population":0,
    "gn:timezone":"Asia/Karachi",
    "iso:country":"PK",
    "wof:name":"Chak One Hundred Thirty-four",
    "wof:placetype":"locality"
},
  "geometry": {"coordinates":[71.06466999999998,30.97439],"type":"Point"}
}