{
  "type": "Feature",
  "properties": {
    "gn:admin1_code":"2",
    "gn:asciiname":"Tauda Gullazai",
    "gn:country_code":"PK",
    "gn:dem":1614,
    "gn:feature_class":"P",
    "gn:feature_code":"PPL",
    "gn:name":"Tauda Gullazai",
    "gn:population":0,
    "gn:timezone":"Asia/Karachi",
    "iso:country":"PK",
    "name:und_x_variant":[
        "T\u0101uda Galazai"
    ],
    "wof:name":"Tauda Gullazai",
    "wof:placetype":"locality"
},
  "geometry": {"coordinates":[69.06323,30.67698],"type":"Point"}
}