{
  "type": "Feature",
  "properties": {
    "gn:admin1_code":"7.0",
    "gn:asciiname":"Talis",
    "gn:country_code":"PK",
    "gn:dem":2642,
    "gn:feature_class":"P",
    "gn:feature_code":"PPL",
    "gn:name":"Talis",
    "gn:population":0,
    "gn:timezone":"Asia/Karachi",
    "iso:country":"PK",
    "wof:name":"Talis",
    "wof:placetype":"locality"
},
  "geometry": {"coordinates":[76.39074000000002,35.26665999999999],"type":"Point"}
}