{
  "type": "Feature",
  "properties": {
    "gn:admin1_code":"5",
    "gn:asciiname":"Sabal Gaho",
    "gn:country_code":"PK",
    "gn:dem":55,
    "gn:feature_class":"P",
    "gn:feature_code":"PPL",
    "gn:name":"Sabal Gaho",
    "gn:population":0,
    "gn:timezone":"Asia/Karachi",
    "iso:country":"PK",
    "name:und_x_variant":[
        "S\u0101bel G\u0101ho"
    ],
    "wof:name":"Sabal Gaho",
    "wof:placetype":"locality"
},
  "geometry": {"coordinates":[68.65409,27.35342],"type":"Point"}
}