{
  "type": "Feature",
  "properties": {
    "gn:admin1_code":"2.0",
    "gn:asciiname":"Badezai",
    "gn:country_code":"PK",
    "gn:dem":1519,
    "gn:feature_class":"P",
    "gn:feature_code":"PPL",
    "gn:name":"Badezai",
    "gn:population":0,
    "gn:timezone":"Asia/Karachi",
    "iso:country":"PK",
    "name:eng_x_preferred":[
        "B\u0101dezai"
    ],
    "wof:name":"Badezai",
    "wof:placetype":"locality"
},
  "geometry": {"coordinates":[67.05029999999999,30.70354],"type":"Point"}
}