{
  "type": "Feature",
  "properties": {
    "gn:admin1_code":"3.0",
    "gn:asciiname":"Khole",
    "gn:country_code":"PK",
    "gn:dem":223,
    "gn:feature_class":"P",
    "gn:feature_code":"PPL",
    "gn:name":"Khole",
    "gn:population":0,
    "gn:timezone":"Asia/Karachi",
    "iso:country":"PK",
    "name:und_x_variant":[
        "Khola"
    ],
    "wof:name":"Khole",
    "wof:placetype":"locality"
},
  "geometry": {"coordinates":[70.61721,32.18639],"type":"Point"}
}