{
  "type": "Feature",
  "properties": {
    "gn:admin1_code":"3.0",
    "gn:asciiname":"Kamal Chat",
    "gn:country_code":"PK",
    "gn:dem":3041,
    "gn:feature_class":"P",
    "gn:feature_code":"PPL",
    "gn:name":"Kamal Chat",
    "gn:population":0,
    "gn:timezone":"Asia/Karachi",
    "iso:country":"PK",
    "wof:name":"Kamal Chat",
    "wof:placetype":"locality"
},
  "geometry": {"coordinates":[72.47369999999999,36.4837],"type":"Point"}
}