{
  "type": "Feature",
  "properties": {
    "gn:admin1_code":"3",
    "gn:asciiname":"Panrashai",
    "gn:country_code":"PK",
    "gn:dem":3207,
    "gn:feature_class":"P",
    "gn:feature_code":"PPL",
    "gn:name":"Panrashai",
    "gn:population":0,
    "gn:timezone":"Asia/Karachi",
    "iso:country":"PK",
    "name:eng_x_preferred":[
        "Panrashai"
    ],
    "wof:name":"Panrashai",
    "wof:placetype":"locality"
},
  "geometry": {"coordinates":[72.65224000000001,35.24838],"type":"Point"}
}