{
  "type": "Feature",
  "properties": {
    "gn:admin1_code":"4.0",
    "gn:asciiname":"Chak One Hundred Sixty-Two NB",
    "gn:country_code":"PK",
    "gn:dem":165,
    "gn:feature_class":"P",
    "gn:feature_code":"PPL",
    "gn:name":"Chak One Hundred Sixty-Two NB",
    "gn:population":0,
    "gn:timezone":"Asia/Karachi",
    "iso:country":"PK",
    "name:und_x_variant":[
        "Chak 162 NB",
        "Chak One Hundred Sixty-Two NB",
        "Chak One Hundred Sixty-two"
    ],
    "wof:name":"Chak One Hundred Sixty-Two NB",
    "wof:placetype":"locality"
},
  "geometry": {"coordinates":[72.27410999999999,31.61189],"type":"Point"}
}