{
  "type": "Feature",
  "properties": {
    "gn:admin1_code":"3.0",
    "gn:asciiname":"Jhok Dinu",
    "gn:country_code":"PK",
    "gn:dem":227,
    "gn:feature_class":"P",
    "gn:feature_code":"PPL",
    "gn:name":"Jhok Dinu",
    "gn:population":0,
    "gn:timezone":"Asia/Karachi",
    "iso:country":"PK",
    "name:und_x_variant":[
        "Jhok Darkh\u0101nw\u0101li"
    ],
    "wof:name":"Jhok Dinu",
    "wof:placetype":"locality"
},
  "geometry": {"coordinates":[70.46659,31.34787],"type":"Point"}
}