{
  "type": "Feature",
  "properties": {
    "gn:admin1_code":"3.0",
    "gn:asciiname":"Quli Khel Kalle",
    "gn:country_code":"PK",
    "gn:dem":304,
    "gn:feature_class":"P",
    "gn:feature_code":"PPL",
    "gn:name":"Quli Khel Kalle",
    "gn:population":0,
    "gn:timezone":"Asia/Karachi",
    "iso:country":"PK",
    "name:und_x_variant":[
        "Abdul Khel"
    ],
    "wof:name":"Quli Khel Kalle",
    "wof:placetype":"locality"
},
  "geometry": {"coordinates":[70.41468,32.40252],"type":"Point"}
}