{
  "type": "Feature",
  "properties": {
    "gn:admin1_code":"2.0",
    "gn:asciiname":"Ziarat Haji Muhammad",
    "gn:country_code":"PK",
    "gn:dem":1170,
    "gn:feature_class":"P",
    "gn:feature_code":"PPL",
    "gn:name":"Ziarat Haji Muhammad",
    "gn:population":0,
    "gn:timezone":"Asia/Karachi",
    "iso:country":"PK",
    "wof:name":"Ziarat Haji Muhammad",
    "wof:placetype":"locality"
},
  "geometry": {"coordinates":[65.74206,27.39181],"type":"Point"}
}