{
  "type": "Feature",
  "properties": {
    "gn:admin1_code":"4.0",
    "gn:asciiname":"Ratnewala Kalan",
    "gn:country_code":"PK",
    "gn:dem":190,
    "gn:feature_class":"P",
    "gn:feature_code":"PPL",
    "gn:name":"Ratnew\u0101la Kal\u0101n",
    "gn:population":0,
    "gn:timezone":"Asia/Karachi",
    "iso:country":"PK",
    "wof:name":"Ratnewala Kalan",
    "wof:placetype":"locality"
},
  "geometry": {"coordinates":[74.40833000000001,30.95],"type":"Point"}
}