{
  "type": "Feature",
  "properties": {
    "gn:admin1_code":"3",
    "gn:asciiname":"Torusatta Banda",
    "gn:country_code":"PK",
    "gn:dem":2171,
    "gn:feature_class":"P",
    "gn:feature_code":"PPL",
    "gn:name":"Torusatta Banda",
    "gn:population":0,
    "gn:timezone":"Asia/Karachi",
    "iso:country":"PK",
    "wof:name":"Torusatta Banda",
    "wof:placetype":"locality"
},
  "geometry": {"coordinates":[72.19901999999998,34.96408],"type":"Point"}
}