{
  "type": "Feature",
  "properties": {
    "gn:admin1_code":"4",
    "gn:asciiname":"Basti Allahwasaya",
    "gn:country_code":"PK",
    "gn:dem":97,
    "gn:feature_class":"P",
    "gn:feature_code":"PPL",
    "gn:name":"Basti Allahwasaya",
    "gn:population":0,
    "gn:timezone":"Asia/Karachi",
    "iso:country":"PK",
    "name:und_x_variant":[
        "Basti Was\u0101ya N\u0101ich"
    ],
    "wof:name":"Basti Allahwasaya",
    "wof:placetype":"locality"
},
  "geometry": {"coordinates":[70.95466999999999,29.12809],"type":"Point"}
}