{
  "type": "Feature",
  "properties": {
    "gn:admin1_code":"3",
    "gn:asciiname":"Alakul",
    "gn:country_code":"PK",
    "gn:dem":1201,
    "gn:feature_class":"P",
    "gn:feature_code":"PPL",
    "gn:name":"Alakul",
    "gn:population":0,
    "gn:timezone":"Asia/Karachi",
    "iso:country":"PK",
    "name:eng_x_preferred":[
        "Alakul"
    ],
    "wof:name":"Alakul",
    "wof:placetype":"locality"
},
  "geometry": {"coordinates":[71.94199,35.12195999999999],"type":"Point"}
}