{
  "type": "Feature",
  "properties": {
    "gn:admin1_code":"1.0",
    "gn:asciiname":"Matkhuza",
    "gn:country_code":"PK",
    "gn:dem":1167,
    "gn:feature_class":"P",
    "gn:feature_code":"PPL",
    "gn:name":"Matkhuza",
    "gn:population":0,
    "gn:timezone":"Asia/Karachi",
    "iso:country":"PK",
    "wof:name":"Matkhuza",
    "wof:placetype":"locality"
},
  "geometry": {"coordinates":[70.31783,33.70083],"type":"Point"}
}