{
  "type": "Feature",
  "properties": {
    "gn:admin1_code":"01",
    "gn:asciiname":"Tsukri",
    "gn:country_code":"PK",
    "gn:dem":2182,
    "gn:feature_class":"P",
    "gn:feature_code":"PPL",
    "gn:name":"Tsukri",
    "gn:population":0,
    "gn:timezone":"Asia/Karachi",
    "iso:country":"PK",
    "wof:name":"Tsukri",
    "wof:placetype":"locality"
},
  "geometry": {"coordinates":[70.72471,33.72276],"type":"Point"}
}