{
  "type": "Feature",
  "properties": {
    "gn:admin1_code":"2.0",
    "gn:asciiname":"Kark",
    "gn:country_code":"PK",
    "gn:dem":593,
    "gn:feature_class":"P",
    "gn:feature_code":"PPL",
    "gn:name":"Kark",
    "gn:population":0,
    "gn:timezone":"Asia/Karachi",
    "iso:country":"PK",
    "name:ceb_x_preferred":[
        "Kark"
    ],
    "name:heb_x_preferred":[
        "\u05e7\u05e8\u05e7"
    ],
    "name:nds_x_preferred":[
        "Kark"
    ],
    "name:swe_x_preferred":[
        "Kark"
    ],
    "wof:name":"Kark",
    "wof:placetype":"locality"
},
  "geometry": {"coordinates":[63.09441,27.75192],"type":"Point"}
}