{
  "type": "Feature",
  "properties": {
    "gn:admin1_code":"3",
    "gn:asciiname":"Pharari",
    "gn:country_code":"PK",
    "gn:dem":709,
    "gn:feature_class":"P",
    "gn:feature_code":"PPL",
    "gn:name":"Pharari",
    "gn:population":0,
    "gn:timezone":"Asia/Karachi",
    "iso:country":"PK",
    "wof:name":"Pharari",
    "wof:placetype":"locality"
},
  "geometry": {"coordinates":[73.02646,34.03856],"type":"Point"}
}