{
  "type": "Feature",
  "properties": {
    "gn:admin1_code":"4.0",
    "gn:asciiname":"Mumtaz",
    "gn:country_code":"PK",
    "gn:dem":80,
    "gn:feature_class":"P",
    "gn:feature_code":"PPL",
    "gn:name":"Mumtaz",
    "gn:population":0,
    "gn:timezone":"Asia/Karachi",
    "iso:country":"PK",
    "name:aze_x_preferred":[
        "M\u00fcmtaz"
    ],
    "name:deu_x_preferred":[
        "Mumtaz"
    ],
    "name:fas_x_preferred":[
        "\u0645\u0645\u062a\u0627\u0632"
    ],
    "name:fra_x_preferred":[
        "Mumtaz"
    ],
    "name:rus_x_preferred":[
        "\u041c\u0443\u043c\u0442\u0430\u0437"
    ],
    "name:tam_x_preferred":[
        "\u0bae\u0bc1\u0bae\u0bcd\u0ba4\u0bbe\u0b9c\u0bcd"
    ],
    "name:tur_x_preferred":[
        "M\u00fcmtaz"
    ],
    "wof:name":"Mumtaz",
    "wof:placetype":"locality"
},
  "geometry": {"coordinates":[69.57127,28.34773],"type":"Point"}
}