{
  "type": "Feature",
  "properties": {
    "gn:admin1_code":"4.0",
    "gn:asciiname":"Dhok Fateh Mast",
    "gn:country_code":"PK",
    "gn:dem":411,
    "gn:feature_class":"P",
    "gn:feature_code":"PPL",
    "gn:name":"Dhok Fateh Mast",
    "gn:population":0,
    "gn:timezone":"Asia/Karachi",
    "iso:country":"PK",
    "wof:name":"Dhok Fateh Mast",
    "wof:placetype":"locality"
},
  "geometry": {"coordinates":[73.28452,32.89542],"type":"Point"}
}