{
  "type": "Feature",
  "properties": {
    "gn:admin1_code":"04",
    "gn:asciiname":"Thatta Nikka",
    "gn:country_code":"PK",
    "gn:dem":213,
    "gn:feature_class":"P",
    "gn:feature_code":"PPL",
    "gn:name":"Thatta Nikka",
    "gn:population":0,
    "gn:timezone":"Asia/Karachi",
    "iso:country":"PK",
    "name:und_x_variant":[
        "Thatha Neka",
        "Thatta Nikka"
    ],
    "wof:name":"Thatta Nikka",
    "wof:placetype":"locality"
},
  "geometry": {"coordinates":[73.755,32.39671],"type":"Point"}
}