{
  "type": "Feature",
  "properties": {
    "gn:admin1_code":"3",
    "gn:asciiname":"Sappar",
    "gn:country_code":"PK",
    "gn:dem":2002,
    "gn:feature_class":"P",
    "gn:feature_code":"PPL",
    "gn:name":"Sappar",
    "gn:population":0,
    "gn:timezone":"Asia/Karachi",
    "iso:country":"PK",
    "name:und_x_variant":[
        "Tsappar",
        "Sappar"
    ],
    "wof:name":"Sappar",
    "wof:placetype":"locality"
},
  "geometry": {"coordinates":[72.59498000000001,35.16023],"type":"Point"}
}