{
  "type": "Feature",
  "properties": {
    "gn:admin1_code":"3.0",
    "gn:asciiname":"Kaho",
    "gn:country_code":"PK",
    "gn:dem":2692,
    "gn:feature_class":"P",
    "gn:feature_code":"PPL",
    "gn:name":"Kaho",
    "gn:population":0,
    "gn:timezone":"Asia/Karachi",
    "iso:country":"PK",
    "name:ceb_x_preferred":[
        "Kaho"
    ],
    "name:deu_x_preferred":[
        "Kaho"
    ],
    "name:fra_x_preferred":[
        "Kaho"
    ],
    "name:ita_x_preferred":[
        "Kaho"
    ],
    "name:pol_x_preferred":[
        "Kaho"
    ],
    "name:swe_x_preferred":[
        "Kaho"
    ],
    "name:tha_x_preferred":[
        "\u0e04\u0e32\u0e42\u0e2e\u0e30"
    ],
    "wof:name":"Kaho",
    "wof:placetype":"locality"
},
  "geometry": {"coordinates":[72.70974,35.04078],"type":"Point"}
}