{
  "type": "Feature",
  "properties": {
    "gn:admin1_code":"3",
    "gn:asciiname":"Archalai Banda",
    "gn:country_code":"PK",
    "gn:dem":1641,
    "gn:feature_class":"P",
    "gn:feature_code":"PPL",
    "gn:name":"Archalai Banda",
    "gn:population":0,
    "gn:timezone":"Asia/Karachi",
    "iso:country":"PK",
    "wof:name":"Archalai Banda",
    "wof:placetype":"locality"
},
  "geometry": {"coordinates":[72.22945,34.94794],"type":"Point"}
}