{
  "type": "Feature",
  "properties": {
    "gn:admin1_code":"02",
    "gn:asciiname":"Tatagar",
    "gn:country_code":"PK",
    "gn:dem":1138,
    "gn:feature_class":"P",
    "gn:feature_code":"PPL",
    "gn:name":"Tatag\u0101r",
    "gn:population":0,
    "gn:timezone":"Asia/Karachi",
    "iso:country":"PK",
    "wof:name":"Tatagar",
    "wof:placetype":"locality"
},
  "geometry": {"coordinates":[64.93333,28.63333],"type":"Point"}
}