{
  "type": "Feature",
  "properties": {
    "gn:admin1_code":"4.0",
    "gn:asciiname":"Dhok Baddar",
    "gn:country_code":"PK",
    "gn:dem":385,
    "gn:feature_class":"P",
    "gn:feature_code":"PPL",
    "gn:name":"Dhok Baddar",
    "gn:population":0,
    "gn:timezone":"Asia/Karachi",
    "iso:country":"PK",
    "wof:name":"Dhok Baddar",
    "wof:placetype":"locality"
},
  "geometry": {"coordinates":[73.27645,32.95952],"type":"Point"}
}