{
  "type": "Feature",
  "properties": {
    "gn:admin1_code":"4",
    "gn:asciiname":"Rakh Bauwali",
    "gn:country_code":"PK",
    "gn:dem":213,
    "gn:feature_class":"P",
    "gn:feature_code":"PPL",
    "gn:name":"Rakh Bauwali",
    "gn:population":0,
    "gn:timezone":"Asia/Karachi",
    "iso:country":"PK",
    "name:und_x_variant":[
        "Rakh Baoli"
    ],
    "wof:name":"Rakh Bauwali",
    "wof:placetype":"locality"
},
  "geometry": {"coordinates":[73.85231,32.23155],"type":"Point"}
}