{
  "type": "Feature",
  "properties": {
    "gn:admin1_code":"4",
    "gn:asciiname":"Suraj Miani",
    "gn:country_code":"PK",
    "gn:dem":123,
    "gn:feature_class":"P",
    "gn:feature_code":"PPL",
    "gn:name":"Suraj Miani",
    "gn:population":0,
    "gn:timezone":"Asia/Karachi",
    "iso:country":"PK",
    "name:und_x_variant":[
        "S\u016bre Mi\u0101ni",
        "S\u0101re Mi\u0101ni",
        "Suraj Miani"
    ],
    "wof:name":"Suraj Miani",
    "wof:placetype":"locality"
},
  "geometry": {"coordinates":[71.43856,30.2193],"type":"Point"}
}