{
  "type": "Feature",
  "properties": {
    "gn:admin1_code":"3.0",
    "gn:asciiname":"Saleh Khan",
    "gn:country_code":"PK",
    "gn:dem":365,
    "gn:feature_class":"P",
    "gn:feature_code":"PPL",
    "gn:name":"Saleh Khan",
    "gn:population":0,
    "gn:timezone":"Asia/Karachi",
    "iso:country":"PK",
    "wof:name":"Saleh Khan",
    "wof:placetype":"locality"
},
  "geometry": {"coordinates":[70.61161,32.96143],"type":"Point"}
}