{
  "type": "Feature",
  "properties": {
    "gn:admin1_code":"2.0",
    "gn:asciiname":"Mirian Kalat",
    "gn:country_code":"PK",
    "gn:dem":709,
    "gn:feature_class":"P",
    "gn:feature_code":"PPL",
    "gn:name":"Mirian Kalat",
    "gn:population":0,
    "gn:timezone":"Asia/Karachi",
    "iso:country":"PK",
    "name:und_x_variant":[
        "M\u012br\u0101n Kal\u0101t"
    ],
    "wof:name":"Mirian Kalat",
    "wof:placetype":"locality"
},
  "geometry": {"coordinates":[65.46222,28.44903],"type":"Point"}
}