{
  "type": "Feature",
  "properties": {
    "gn:admin1_code":"2.0",
    "gn:asciiname":"Pir Bakhsh Bazar",
    "gn:country_code":"PK",
    "gn:dem":545,
    "gn:feature_class":"P",
    "gn:feature_code":"PPL",
    "gn:name":"Pir Bakhsh Bazar",
    "gn:population":0,
    "gn:timezone":"Asia/Karachi",
    "iso:country":"PK",
    "wof:name":"Pir Bakhsh Bazar",
    "wof:placetype":"locality"
},
  "geometry": {"coordinates":[64.83429,26.23479],"type":"Point"}
}