{
  "type": "Feature",
  "properties": {
    "gn:admin1_code":"5",
    "gn:asciiname":"Bibi Nur",
    "gn:country_code":"PK",
    "gn:dem":65,
    "gn:feature_class":"P",
    "gn:feature_code":"PPL",
    "gn:name":"Bibi Nur",
    "gn:population":0,
    "gn:timezone":"Asia/Karachi",
    "iso:country":"PK",
    "name:und_x_variant":[
        "All\u0101hda"
    ],
    "wof:name":"Bibi Nur",
    "wof:placetype":"locality"
},
  "geometry": {"coordinates":[68.78668,28.113],"type":"Point"}
}