{
  "type": "Feature",
  "properties": {
    "gn:admin1_code":"3.0",
    "gn:asciiname":"Sherdili Kili",
    "gn:country_code":"PK",
    "gn:dem":369,
    "gn:feature_class":"P",
    "gn:feature_code":"PPL",
    "gn:name":"Sherdili Kili",
    "gn:population":0,
    "gn:timezone":"Asia/Karachi",
    "iso:country":"PK",
    "wof:name":"Sherdili Kili",
    "wof:placetype":"locality"
},
  "geometry": {"coordinates":[70.59028000000001,32.96667],"type":"Point"}
}