{
  "type": "Feature",
  "properties": {
    "gn:admin1_code":"4.0",
    "gn:asciiname":"Sarthal Baungal",
    "gn:country_code":"PK",
    "gn:dem":771,
    "gn:feature_class":"P",
    "gn:feature_code":"PPL",
    "gn:name":"Sarthal Baungal",
    "gn:population":0,
    "gn:timezone":"Asia/Karachi",
    "iso:country":"PK",
    "name:eng_x_preferred":[
        "Sarthal Baungal"
    ],
    "wof:name":"Sarthal Baungal",
    "wof:placetype":"locality"
},
  "geometry": {"coordinates":[70.21799,30.05574],"type":"Point"}
}