{
  "type": "Feature",
  "properties": {
    "gn:admin1_code":"4",
    "gn:asciiname":"Sona Kosh",
    "gn:country_code":"PK",
    "gn:dem":77,
    "gn:feature_class":"P",
    "gn:feature_code":"PPL",
    "gn:name":"Sona Kosh",
    "gn:population":0,
    "gn:timezone":"Asia/Karachi",
    "iso:country":"PK",
    "name:und_x_variant":[
        "P\u012br Bakhsh"
    ],
    "wof:name":"Sona Kosh",
    "wof:placetype":"locality"
},
  "geometry": {"coordinates":[69.86893000000001,28.35453],"type":"Point"}
}