{
  "type": "Feature",
  "properties": {
    "gn:admin1_code":"4.0",
    "gn:asciiname":"Laddan Shah",
    "gn:country_code":"PK",
    "gn:dem":466,
    "gn:feature_class":"P",
    "gn:feature_code":"PPL",
    "gn:name":"Laddan Shah",
    "gn:population":0,
    "gn:timezone":"Asia/Karachi",
    "iso:country":"PK",
    "wof:name":"Laddan Shah",
    "wof:placetype":"locality"
},
  "geometry": {"coordinates":[72.74218,33.56153],"type":"Point"}
}