{
  "type": "Feature",
  "properties": {
    "gn:admin1_code":"2.0",
    "gn:asciiname":"Khuddi Mirullah",
    "gn:country_code":"PK",
    "gn:dem":2381,
    "gn:feature_class":"P",
    "gn:feature_code":"PPL",
    "gn:name":"Khuddi Mirullah",
    "gn:population":0,
    "gn:timezone":"Asia/Karachi",
    "iso:country":"PK",
    "wof:name":"Khuddi Mirullah",
    "wof:placetype":"locality"
},
  "geometry": {"coordinates":[66.82545,28.9659],"type":"Point"}
}