{
  "type": "Feature",
  "properties": {
    "gn:admin1_code":"4.0",
    "gn:asciiname":"Chandala",
    "gn:country_code":"PK",
    "gn:dem":220,
    "gn:feature_class":"P",
    "gn:feature_code":"PPL",
    "gn:name":"Chandala",
    "gn:population":0,
    "gn:timezone":"Asia/Karachi",
    "iso:country":"PK",
    "name:ben_x_preferred":[
        "\u099a\u09a3\u09cd\u09a1\u09be\u09b2"
    ],
    "name:cat_x_preferred":[
        "Chandala"
    ],
    "name:deu_x_preferred":[
        "Chandala"
    ],
    "name:fra_x_preferred":[
        "Chand\u00e2la"
    ],
    "name:hin_x_preferred":[
        "\u091a\u093e\u0902\u0921\u093e\u0932"
    ],
    "name:jpn_x_preferred":[
        "\u65c3\u9640\u7f85"
    ],
    "name:kan_x_preferred":[
        "\u0c9a\u0c82\u0ca1\u0cbe\u0cb2"
    ],
    "name:mya_x_preferred":[
        "\u1005\u100f\u1039\u100d\u102c\u101c"
    ],
    "name:pan_x_preferred":[
        "\u0a1a\u0a70\u0a21\u0a3e\u0a32"
    ],
    "name:por_x_preferred":[
        "Candala"
    ],
    "name:rus_x_preferred":[
        "\u0427\u0430\u043d\u0434\u0430\u043b\u0430"
    ],
    "name:spa_x_preferred":[
        "Chandala"
    ],
    "name:swe_x_preferred":[
        "Chandala"
    ],
    "name:tel_x_preferred":[
        "\u0c1a\u0c02\u0c21\u0c3e\u0c32\u0c41\u0c21\u0c41"
    ],
    "name:tha_x_preferred":[
        "\u0e08\u0e31\u0e13\u0e11\u0e32\u0e25"
    ],
    "name:urd_x_preferred":[
        "\u0686\u0646\u0688\u0627\u0644"
    ],
    "name:zho_x_preferred":[
        "\u65c3\u9640\u7f85"
    ],
    "wof:name":"Chandala",
    "wof:placetype":"locality"
},
  "geometry": {"coordinates":[74.28220999999998,31.95708],"type":"Point"}
}