{
  "type": "Feature",
  "properties": {
    "gn:admin1_code":"4",
    "gn:asciiname":"Chak Three Hundred Forty-five Eastern Bar",
    "gn:country_code":"PK",
    "gn:dem":155,
    "gn:feature_class":"P",
    "gn:feature_code":"PPL",
    "gn:name":"Chak Three Hundred Forty-five Eastern Bar",
    "gn:population":0,
    "gn:timezone":"Asia/Karachi",
    "iso:country":"PK",
    "name:und_x_variant":[
        "Ism\u0101\u012blpur"
    ],
    "wof:name":"Chak Three Hundred Forty-five Eastern Bar",
    "wof:placetype":"locality"
},
  "geometry": {"coordinates":[72.97364,30.33057],"type":"Point"}
}