{
  "type": "Feature",
  "properties": {
    "gn:admin1_code":"1.0",
    "gn:asciiname":"Sangrani",
    "gn:country_code":"PK",
    "gn:dem":1706,
    "gn:feature_class":"P",
    "gn:feature_code":"PPL",
    "gn:name":"Sangrani",
    "gn:population":0,
    "gn:timezone":"Asia/Karachi",
    "iso:country":"PK",
    "name:und_x_variant":[
        "Sangr\u0101na",
        "Songranai"
    ],
    "wof:name":"Sangrani",
    "wof:placetype":"locality"
},
  "geometry": {"coordinates":[70.93436,33.76753],"type":"Point"}
}