{
  "type": "Feature",
  "properties": {
    "gn:admin1_code":"7.0",
    "gn:asciiname":"Dosam Baihk",
    "gn:country_code":"PK",
    "gn:dem":4032,
    "gn:feature_class":"P",
    "gn:feature_code":"PPL",
    "gn:name":"Dosam Baihk",
    "gn:population":0,
    "gn:timezone":"Asia/Karachi",
    "iso:country":"PK",
    "wof:name":"Dosam Baihk",
    "wof:placetype":"locality"
},
  "geometry": {"coordinates":[75.43613000000001,35.23001],"type":"Point"}
}