{
  "type": "Feature",
  "properties": {
    "gn:admin1_code":"5.0",
    "gn:asciiname":"Jalal Chandio",
    "gn:country_code":"PK",
    "gn:dem":40,
    "gn:feature_class":"P",
    "gn:feature_code":"PPL",
    "gn:name":"Jalal Chandio",
    "gn:population":0,
    "gn:timezone":"Asia/Karachi",
    "iso:country":"PK",
    "name:snd_x_preferred":[
        "\u062c\u0644\u0627\u0644 \u0686\u0627\u0646\u068a\u064a\u0648"
    ],
    "name:und_x_variant":[
        "Jal\u0101i Ch\u0101ndio"
    ],
    "name:urd_x_preferred":[
        "\u062c\u0644\u0627\u0644 \u0686\u0627\u0646\u0688\u06cc\u0648"
    ],
    "wof:name":"Jalal Chandio",
    "wof:placetype":"locality"
},
  "geometry": {"coordinates":[68.20243000000001,26.64366],"type":"Point"}
}