{
  "type": "Feature",
  "properties": {
    "gn:admin1_code":"2.0",
    "gn:asciiname":"Kili Takri",
    "gn:country_code":"PK",
    "gn:dem":1642,
    "gn:feature_class":"P",
    "gn:feature_code":"PPL",
    "gn:name":"Kili Takri",
    "gn:population":0,
    "gn:timezone":"Asia/Karachi",
    "iso:country":"PK",
    "wof:name":"Kili Takri",
    "wof:placetype":"locality"
},
  "geometry": {"coordinates":[66.10457,29.27042],"type":"Point"}
}