{
  "type": "Feature",
  "properties": {
    "gn:admin1_code":"04",
    "gn:asciiname":"Chak Five Hundred Thirty-seven Rakh Branch",
    "gn:country_code":"PK",
    "gn:dem":205,
    "gn:feature_class":"P",
    "gn:feature_code":"PPL",
    "gn:name":"Chak Five Hundred Thirty-seven Rakh Branch",
    "gn:population":0,
    "gn:timezone":"Asia/Karachi",
    "iso:country":"PK",
    "name:und_x_variant":[
        "Malli\u0101nw\u0101li"
    ],
    "wof:name":"Chak Five Hundred Thirty-seven Rakh Branch",
    "wof:placetype":"locality"
},
  "geometry": {"coordinates":[73.70560999999999,31.65486],"type":"Point"}
}