{
  "type": "Feature",
  "properties": {
    "gn:admin1_code":"3.0",
    "gn:asciiname":"Langral",
    "gn:country_code":"PK",
    "gn:dem":1427,
    "gn:feature_class":"P",
    "gn:feature_code":"PPL",
    "gn:name":"Langral",
    "gn:population":0,
    "gn:timezone":"Asia/Karachi",
    "iso:country":"PK",
    "name:eng_x_preferred":[
        "Langral"
    ],
    "wof:name":"Langral",
    "wof:placetype":"locality"
},
  "geometry": {"coordinates":[73.30207,33.93782],"type":"Point"}
}