{
  "type": "Feature",
  "properties": {
    "iso:country":"PK",
    "qs:gn_pop":0,
    "qs:name":"Kotli Loharan East",
    "qs:name_adm0":"Pakistan",
    "qs:name_adm1":"Punjab",
    "qs:photos":11,
    "qs:photos_1k":2,
    "qs:photos_9k":1,
    "qs:photos_9r":1,
    "qs:photos_all":11,
    "qs:photos_sr":1,
    "qs:placetype":"Town",
    "qs:pop_sr":"0",
    "qs:woe_adm0":23424922,
    "wd:wordcount":600,
    "wof:name":"Kotli Loharan East",
    "wof:placetype":"locality"
},
  "geometry": {"coordinates":[74.49520099999999,32.565477],"type":"Point"}
}