{
  "type": "Feature",
  "properties": {
    "gn:admin1_code":"3",
    "gn:asciiname":"Bar Batai Banda",
    "gn:country_code":"PK",
    "gn:dem":1675,
    "gn:feature_class":"P",
    "gn:feature_code":"PPL",
    "gn:name":"Bar Batai Banda",
    "gn:population":0,
    "gn:timezone":"Asia/Karachi",
    "iso:country":"PK",
    "name:eng_x_preferred":[
        "Bar Batai Banda"
    ],
    "wof:name":"Bar Batai Banda",
    "wof:placetype":"locality"
},
  "geometry": {"coordinates":[72.2363,34.60155],"type":"Point"}
}