{
  "type": "Feature",
  "properties": {
    "gn:admin1_code":"2.0",
    "gn:asciiname":"Umerabad",
    "gn:country_code":"PK",
    "gn:dem":1655,
    "gn:feature_class":"P",
    "gn:feature_code":"PPL",
    "gn:name":"Umerabad",
    "gn:population":0,
    "gn:timezone":"Asia/Karachi",
    "iso:country":"PK",
    "wof:name":"Umerabad",
    "wof:placetype":"locality"
},
  "geometry": {"coordinates":[66.17289,28.19212000000001],"type":"Point"}
}