{
  "type": "Feature",
  "properties": {
    "gn:admin1_code":"04",
    "gn:asciiname":"Mianwal Ranjha",
    "gn:country_code":"PK",
    "gn:dem":214,
    "gn:feature_class":"P",
    "gn:feature_code":"PPL",
    "gn:name":"Mianwal Ranjha",
    "gn:population":0,
    "gn:timezone":"Asia/Karachi",
    "iso:country":"PK",
    "name:und_x_variant":[
        "Mi\u0101nw\u0101l"
    ],
    "wof:name":"Mianwal Ranjha",
    "wof:placetype":"locality"
},
  "geometry": {"coordinates":[73.44043000000001,32.38792],"type":"Point"}
}