{
  "type": "Feature",
  "properties": {
    "gn:admin1_code":"3.0",
    "gn:asciiname":"Koridab",
    "gn:country_code":"PK",
    "gn:dem":1548,
    "gn:feature_class":"P",
    "gn:feature_code":"PPL",
    "gn:name":"Koridab",
    "gn:population":0,
    "gn:timezone":"Asia/Karachi",
    "iso:country":"PK",
    "wof:name":"Koridab",
    "wof:placetype":"locality"
},
  "geometry": {"coordinates":[72.96753000000002,34.67341],"type":"Point"}
}