{
  "type": "Feature",
  "properties": {
    "gn:admin1_code":"04",
    "gn:asciiname":"Kotla Hasan Shah",
    "gn:country_code":"PK",
    "gn:dem":90,
    "gn:feature_class":"P",
    "gn:feature_code":"PPL",
    "gn:name":"Kotla Hasan Shah",
    "gn:population":0,
    "gn:timezone":"Asia/Karachi",
    "iso:country":"PK",
    "name:und_x_variant":[
        "Kotla Husain Shah",
        "Kotla Hasan Shah"
    ],
    "wof:name":"Kotla Hasan Shah",
    "wof:placetype":"locality"
},
  "geometry": {"coordinates":[70.18648,28.88181],"type":"Point"}
}