{
  "type": "Feature",
  "properties": {
    "gn:admin1_code":"4.0",
    "gn:asciiname":"Bandwani",
    "gn:country_code":"PK",
    "gn:dem":115,
    "gn:feature_class":"P",
    "gn:feature_code":"PPL",
    "gn:name":"Bandwani",
    "gn:population":0,
    "gn:timezone":"Asia/Karachi",
    "iso:country":"PK",
    "name:und_x_variant":[
        "Bandoani",
        "Bandwani"
    ],
    "wof:name":"Bandwani",
    "wof:placetype":"locality"
},
  "geometry": {"coordinates":[70.55964,29.9048],"type":"Point"}
}