{
  "type": "Feature",
  "properties": {
    "gn:admin1_code":"4.0",
    "gn:asciiname":"Ghik Budhal",
    "gn:country_code":"PK",
    "gn:dem":482,
    "gn:feature_class":"P",
    "gn:feature_code":"PPL",
    "gn:name":"Ghik Budhal",
    "gn:population":0,
    "gn:timezone":"Asia/Karachi",
    "iso:country":"PK",
    "name:und_x_variant":[
        "Ghik Badhal",
        "Ghik Budhal"
    ],
    "wof:name":"Ghik Budhal",
    "wof:placetype":"locality"
},
  "geometry": {"coordinates":[73.27882,33.16267],"type":"Point"}
}