{
  "type": "Feature",
  "properties": {
    "gn:admin1_code":"4",
    "gn:asciiname":"Chak Twenty-one SP",
    "gn:country_code":"PK",
    "gn:dem":168,
    "gn:feature_class":"P",
    "gn:feature_code":"PPL",
    "gn:name":"Chak Twenty-one SP",
    "gn:population":0,
    "gn:timezone":"Asia/Karachi",
    "iso:country":"PK",
    "name:und_x_variant":[
        "Chak Twenty-one"
    ],
    "wof:name":"Chak Twenty-one SP",
    "wof:placetype":"locality"
},
  "geometry": {"coordinates":[73.49160000000001,30.432],"type":"Point"}
}