{
  "type": "Feature",
  "properties": {
    "gn:admin1_code":"2.0",
    "gn:asciiname":"Khowasti",
    "gn:country_code":"PK",
    "gn:dem":843,
    "gn:feature_class":"P",
    "gn:feature_code":"PPL",
    "gn:name":"Khowasti",
    "gn:population":0,
    "gn:timezone":"Asia/Karachi",
    "iso:country":"PK",
    "wof:name":"Khowasti",
    "wof:placetype":"locality"
},
  "geometry": {"coordinates":[66.70749000000001,26.38654],"type":"Point"}
}