{
  "type": "Feature",
  "properties": {
    "gn:admin1_code":"2.0",
    "gn:asciiname":"Chagirdi Bazar",
    "gn:country_code":"PK",
    "gn:dem":30,
    "gn:feature_class":"P",
    "gn:feature_code":"PPL",
    "gn:name":"Chagirdi Bazar",
    "gn:population":0,
    "gn:timezone":"Asia/Karachi",
    "iso:country":"PK",
    "name:eng_x_preferred":[
        "Chagirdi Bazar"
    ],
    "wof:name":"Chagirdi Bazar",
    "wof:placetype":"locality"
},
  "geometry": {"coordinates":[62.74691,25.34768],"type":"Point"}
}