{
  "type": "Feature",
  "properties": {
    "gn:admin1_code":"5.0",
    "gn:asciiname":"Dharmishi Goth",
    "gn:country_code":"PK",
    "gn:dem":21,
    "gn:feature_class":"P",
    "gn:feature_code":"PPLF",
    "gn:name":"Dharmishi Goth",
    "gn:population":0,
    "gn:timezone":"Asia/Karachi",
    "iso:country":"PK",
    "name:eng_x_preferred":[
        "Dharmishi Goth"
    ],
    "wof:name":"Dharmishi Goth",
    "wof:placetype":"locality"
},
  "geometry": {"coordinates":[68.39076999999999,25.43513],"type":"Point"}
}