{
  "type": "Feature",
  "properties": {
    "gn:admin1_code":"4.0",
    "gn:asciiname":"Akramabad",
    "gn:country_code":"PK",
    "gn:dem":167,
    "gn:feature_class":"P",
    "gn:feature_code":"PPL",
    "gn:name":"Akramabad",
    "gn:population":0,
    "gn:timezone":"Asia/Karachi",
    "iso:country":"PK",
    "name:und_x_variant":[
        "Gar\u0101na"
    ],
    "wof:name":"Akramabad",
    "wof:placetype":"locality"
},
  "geometry": {"coordinates":[72.34421999999998,31.77907],"type":"Point"}
}