{
  "type": "Feature",
  "properties": {
    "gn:admin1_code":"5",
    "gn:asciiname":"Goth Khlifa",
    "gn:country_code":"PK",
    "gn:dem":53,
    "gn:feature_class":"P",
    "gn:feature_code":"PPL",
    "gn:name":"Goth Khlifa",
    "gn:population":0,
    "gn:timezone":"Asia/Karachi",
    "iso:country":"PK",
    "name:und_x_variant":[
        "Khal\u012bfa"
    ],
    "wof:name":"Goth Khlifa",
    "wof:placetype":"locality"
},
  "geometry": {"coordinates":[68.44393000000001,27.33632],"type":"Point"}
}