{
  "type": "Feature",
  "properties": {
    "gn:admin1_code":"7.0",
    "gn:asciiname":"Jalot",
    "gn:country_code":"PK",
    "gn:dem":1703,
    "gn:feature_class":"P",
    "gn:feature_code":"PPL",
    "gn:name":"Jalot",
    "gn:population":0,
    "gn:timezone":"Asia/Karachi",
    "iso:country":"PK",
    "wof:name":"Jalot",
    "wof:placetype":"locality"
},
  "geometry": {"coordinates":[74.0782,36.06546],"type":"Point"}
}