{
  "type": "Feature",
  "properties": {
    "gn:admin1_code":"5",
    "gn:asciiname":"Nur Muhammad Lashari",
    "gn:country_code":"PK",
    "gn:dem":25,
    "gn:feature_class":"P",
    "gn:feature_code":"PPL",
    "gn:name":"Nur Muhammad Lashari",
    "gn:population":0,
    "gn:timezone":"Asia/Karachi",
    "iso:country":"PK",
    "name:und_x_variant":[
        "N\u016br Kh\u0101n Lash\u0101ri"
    ],
    "wof:name":"Nur Muhammad Lashari",
    "wof:placetype":"locality"
},
  "geometry": {"coordinates":[68.53421999999999,25.44053],"type":"Point"}
}