{
  "type": "Feature",
  "properties": {
    "gn:admin1_code":"4",
    "gn:asciiname":"Chak Three Hundred Thirty-five Wester Bar",
    "gn:country_code":"PK",
    "gn:dem":125,
    "gn:feature_class":"P",
    "gn:feature_code":"PPL",
    "gn:name":"Chak Three Hundred Thirty-five Wester Bar",
    "gn:population":0,
    "gn:timezone":"Asia/Karachi",
    "iso:country":"PK",
    "name:und_x_variant":[
        "Chak Three Hundred Thirty-five WB"
    ],
    "wof:name":"Chak Three Hundred Thirty-five Wester Bar",
    "wof:placetype":"locality"
},
  "geometry": {"coordinates":[71.82096999999997,29.94827],"type":"Point"}
}