{
  "type": "Feature",
  "properties": {
    "gn:admin1_code":"4",
    "gn:asciiname":"Raziwala",
    "gn:country_code":"PK",
    "gn:dem":138,
    "gn:feature_class":"P",
    "gn:feature_code":"PPL",
    "gn:name":"Raziwala",
    "gn:population":0,
    "gn:timezone":"Asia/Karachi",
    "iso:country":"PK",
    "name:und_x_variant":[
        "R\u0101z\u012bw\u0101la"
    ],
    "wof:name":"Raziwala",
    "wof:placetype":"locality"
},
  "geometry": {"coordinates":[70.95788,30.65787000000001],"type":"Point"}
}