{
  "type": "Feature",
  "properties": {
    "gn:admin1_code":"1.0",
    "gn:asciiname":"Star Patai",
    "gn:country_code":"PK",
    "gn:dem":2634,
    "gn:feature_class":"P",
    "gn:feature_code":"PPL",
    "gn:name":"Star Patai",
    "gn:population":0,
    "gn:timezone":"Asia/Karachi",
    "iso:country":"PK",
    "name:und_x_variant":[
        "Star Pala",
        "Star Pata",
        "Star Patai"
    ],
    "wof:name":"Star Patai",
    "wof:placetype":"locality"
},
  "geometry": {"coordinates":[70.49292,33.85440999999999],"type":"Point"}
}