{
  "type": "Feature",
  "properties": {
    "gn:admin1_code":"5",
    "gn:asciiname":"Goth Fateh Muhammad",
    "gn:country_code":"PK",
    "gn:dem":75,
    "gn:feature_class":"P",
    "gn:feature_code":"PPL",
    "gn:name":"Goth Fateh Muhammad",
    "gn:population":0,
    "gn:timezone":"Asia/Karachi",
    "iso:country":"PK",
    "name:und_x_variant":[
        "Fateh Ali"
    ],
    "wof:name":"Goth Fateh Muhammad",
    "wof:placetype":"locality"
},
  "geometry": {"coordinates":[69.43037,28.41943],"type":"Point"}
}