{
  "type": "Feature",
  "properties": {
    "gn:admin1_code":"3",
    "gn:asciiname":"Shahidano Dheri",
    "gn:country_code":"PK",
    "gn:dem":350,
    "gn:feature_class":"P",
    "gn:feature_code":"PPL",
    "gn:name":"Shahidano Dheri",
    "gn:population":0,
    "gn:timezone":"Asia/Karachi",
    "iso:country":"PK",
    "name:eng_x_preferred":[
        "Balari Dheri"
    ],
    "wof:name":"Shahidano Dheri",
    "wof:placetype":"locality"
},
  "geometry": {"coordinates":[72.33189,34.12757],"type":"Point"}
}