{
  "type": "Feature",
  "properties": {
    "gn:admin1_code":"4.0",
    "gn:asciiname":"Bidar",
    "gn:country_code":"PK",
    "gn:dem":389,
    "gn:feature_class":"P",
    "gn:feature_code":"PPL",
    "gn:name":"Bidar",
    "gn:population":0,
    "gn:timezone":"Asia/Karachi",
    "iso:country":"PK",
    "name:ara_x_preferred":[
        "\u0628\u064a\u062f\u0627\u0631"
    ],
    "name:ben_x_preferred":[
        "\u09ac\u09bf\u09a6\u09b0"
    ],
    "name:bih_x_preferred":[
        "\u092c\u0940\u0926\u0930"
    ],
    "name:bpy_x_preferred":[
        "\u09ac\u09bf\u09a1\u09b0"
    ],
    "name:cat_x_preferred":[
        "Bidar"
    ],
    "name:ceb_x_preferred":[
        "B\u012bdar"
    ],
    "name:ces_x_preferred":[
        "B\u00eddar"
    ],
    "name:deu_x_preferred":[
        "Bidar"
    ],
    "name:ell_x_preferred":[
        "\u039c\u03c0\u03b9\u03bd\u03c4\u03ac\u03c1"
    ],
    "name:fas_x_preferred":[
        "\u0628\u06cc\u062f\u0631"
    ],
    "name:fra_x_preferred":[
        "B\u00eed\u00e2r"
    ],
    "name:heb_x_preferred":[
        "\u05d1\u05d9\u05d3\u05d0\u05e8"
    ],
    "name:hin_x_preferred":[
        "\u092c\u0940\u0926\u0930"
    ],
    "name:hun_x_preferred":[
        "Bidar"
    ],
    "name:ind_x_preferred":[
        "Bidar"
    ],
    "name:ita_x_preferred":[
        "Bidar"
    ],
    "name:jpn_x_preferred":[
        "\u30d3\u30fc\u30c0\u30eb"
    ],
    "name:kan_x_preferred":[
        "\u0cac\u0cc0\u0ca6\u0cb0"
    ],
    "name:mal_x_preferred":[
        "\u0d2c\u0d40\u0d26\u0d7c"
    ],
    "name:mar_x_preferred":[
        "\u092c\u0940\u0926\u0930"
    ],
    "name:mlg_x_preferred":[
        "Bidar"
    ],
    "name:msa_x_preferred":[
        "Bidar"
    ],
    "name:nep_x_preferred":[
        "\u092c\u0940\u0926\u0930"
    ],
    "name:new_x_preferred":[
        "\u092c\u0940\u0926\u0930"
    ],
    "name:nld_x_preferred":[
        "Bidar"
    ],
    "name:nor_x_preferred":[
        "Bidar"
    ],
    "name:pam_x_preferred":[
        "Bidar"
    ],
    "name:pnb_x_preferred":[
        "\u0645\u06cc\u0646\u06af\u0644\u0648\u0631"
    ],
    "name:pol_x_preferred":[
        "Bidar"
    ],
    "name:rus_x_preferred":[
        "\u0411\u0438\u0434\u0430\u0440"
    ],
    "name:san_x_preferred":[
        "\u092c\u0940\u0926\u0930\u0928\u0917\u0930\u092e\u094d"
    ],
    "name:spa_x_preferred":[
        "Bidar"
    ],
    "name:srp_x_preferred":[
        "\u0411\u0438\u0434\u0430\u0440"
    ],
    "name:swe_x_preferred":[
        "Bidar"
    ],
    "name:tam_x_preferred":[
        "\u0baa\u0bc0\u0ba4\u0bb0\u0bcd"
    ],
    "name:tur_x_preferred":[
        "Bidar"
    ],
    "name:ukr_x_preferred":[
        "\u0411\u0456\u0434\u0430\u0440"
    ],
    "name:urd_x_preferred":[
        "\u0628\u06cc\u062f\u0631"
    ],
    "name:vie_x_preferred":[
        "Bidar"
    ],
    "name:war_x_preferred":[
        "Bidar"
    ],
    "name:zho_x_preferred":[
        "\u6bd4\u5fb7\u723e"
    ],
    "wof:name":"Bidar",
    "wof:placetype":"locality"
},
  "geometry": {"coordinates":[71.83999,32.64573],"type":"Point"}
}