{
  "type": "Feature",
  "properties": {
    "gn:admin1_code":"4.0",
    "gn:asciiname":"Bidar",
    "gn:country_code":"PK",
    "gn:dem":389,
    "gn:feature_class":"P",
    "gn:feature_code":"PPL",
    "gn:name":"Bidar",
    "gn:population":0,
    "gn:timezone":"Asia/Karachi",
    "iso:country":"PK",
    "wof:name":"Bidar",
    "wof:placetype":"locality"
},
  "geometry": {"coordinates":[71.83999,32.64573],"type":"Point"}
}