{
  "type": "Feature",
  "properties": {
    "gn:admin1_code":"3.0",
    "gn:asciiname":"Garah Hayat Khan",
    "gn:country_code":"PK",
    "gn:dem":230,
    "gn:feature_class":"P",
    "gn:feature_code":"PPL",
    "gn:name":"Garah Hayat Khan",
    "gn:population":0,
    "gn:timezone":"Asia/Karachi",
    "iso:country":"PK",
    "wof:name":"Garah Hayat Khan",
    "wof:placetype":"locality"
},
  "geometry": {"coordinates":[70.44098000000002,32.06445],"type":"Point"}
}