{
  "type": "Feature",
  "properties": {
    "gn:admin1_code":"5.0",
    "gn:asciiname":"Mitho Khan Hoth",
    "gn:country_code":"PK",
    "gn:dem":28,
    "gn:feature_class":"P",
    "gn:feature_code":"PPL",
    "gn:name":"Mitho Khan Hoth",
    "gn:population":0,
    "gn:timezone":"Asia/Karachi",
    "iso:country":"PK",
    "wof:name":"Mitho Khan Hoth",
    "wof:placetype":"locality"
},
  "geometry": {"coordinates":[68.35958000000001,26.05129],"type":"Point"}
}