{
  "type": "Feature",
  "properties": {
    "gn:admin1_code":"3.0",
    "gn:asciiname":"Kotka Sher Bahadur Khan",
    "gn:country_code":"PK",
    "gn:dem":308,
    "gn:feature_class":"P",
    "gn:feature_code":"PPL",
    "gn:name":"Kotka Sher Bahadur Khan",
    "gn:population":0,
    "gn:timezone":"Asia/Karachi",
    "iso:country":"PK",
    "name:und_x_variant":[
        "Kotka Sher Bah\u0101dar Kh\u0101n"
    ],
    "wof:name":"Kotka Sher Bahadur Khan",
    "wof:placetype":"locality"
},
  "geometry": {"coordinates":[70.73103,32.83863],"type":"Point"}
}