{
  "type": "Feature",
  "properties": {
    "gn:admin1_code":"4",
    "gn:asciiname":"Chak Buta",
    "gn:country_code":"PK",
    "gn:dem":180,
    "gn:feature_class":"P",
    "gn:feature_code":"PPL",
    "gn:name":"Chak Buta",
    "gn:population":0,
    "gn:timezone":"Asia/Karachi",
    "iso:country":"PK",
    "name:und_x_variant":[
        "Chak B\u016bta R\u0101m"
    ],
    "wof:name":"Chak Buta",
    "wof:placetype":"locality"
},
  "geometry": {"coordinates":[73.9464,30.5874],"type":"Point"}
}