{
  "type": "Feature",
  "properties": {
    "gn:admin1_code":"4.0",
    "gn:asciiname":"Rani Koli",
    "gn:country_code":"PK",
    "gn:dem":120,
    "gn:feature_class":"P",
    "gn:feature_code":"PPL",
    "gn:name":"Rani Koli",
    "gn:population":0,
    "gn:timezone":"Asia/Karachi",
    "iso:country":"PK",
    "wof:name":"Rani Koli",
    "wof:placetype":"locality"
},
  "geometry": {"coordinates":[71.64089,29.75981],"type":"Point"}
}