{
  "type": "Feature",
  "properties": {
    "gn:admin1_code":"4",
    "gn:asciiname":"Ratti",
    "gn:country_code":"PK",
    "gn:dem":235,
    "gn:feature_class":"P",
    "gn:feature_code":"PPL",
    "gn:name":"Ratti",
    "gn:population":0,
    "gn:timezone":"Asia/Karachi",
    "iso:country":"PK",
    "name:deu_x_preferred":[
        "Rati"
    ],
    "name:hin_x_preferred":[
        "\u0930\u0924\u094d\u0924\u0940"
    ],
    "name:nld_x_preferred":[
        "Ratti"
    ],
    "wof:name":"Ratti",
    "wof:placetype":"locality"
},
  "geometry": {"coordinates":[74.10887,32.56108],"type":"Point"}
}