{
  "type": "Feature",
  "properties": {
    "gn:admin1_code":"1.0",
    "gn:asciiname":"Kharsin",
    "gn:country_code":"PK",
    "gn:dem":623,
    "gn:feature_class":"P",
    "gn:feature_code":"PPL",
    "gn:name":"Kharsin",
    "gn:population":0,
    "gn:timezone":"Asia/Karachi",
    "iso:country":"PK",
    "wof:name":"Kharsin",
    "wof:placetype":"locality"
},
  "geometry": {"coordinates":[70.73338000000003,33.12845],"type":"Point"}
}