{
  "type": "Feature",
  "properties": {
    "gn:admin1_code":"3.0",
    "gn:asciiname":"Sarwar Khan Kalle",
    "gn:country_code":"PK",
    "gn:dem":370,
    "gn:feature_class":"P",
    "gn:feature_code":"PPL",
    "gn:name":"Sarwar Khan Kalle",
    "gn:population":0,
    "gn:timezone":"Asia/Karachi",
    "iso:country":"PK",
    "wof:name":"Sarwar Khan Kalle",
    "wof:placetype":"locality"
},
  "geometry": {"coordinates":[71.66494,34.32258],"type":"Point"}
}