{
  "type": "Feature",
  "properties": {
    "gn:admin1_code":"2",
    "gn:asciiname":"Taleri",
    "gn:country_code":"PK",
    "gn:dem":1756,
    "gn:feature_class":"P",
    "gn:feature_code":"PPL",
    "gn:name":"Taleri",
    "gn:population":0,
    "gn:timezone":"Asia/Karachi",
    "iso:country":"PK",
    "name:und_x_variant":[
        "Tlerai"
    ],
    "wof:name":"Taleri",
    "wof:placetype":"locality"
},
  "geometry": {"coordinates":[68.39175,30.61814],"type":"Point"}
}