{
  "type": "Feature",
  "properties": {
    "gn:admin1_code":"2.0",
    "gn:asciiname":"Siab",
    "gn:country_code":"PK",
    "gn:dem":504,
    "gn:feature_class":"P",
    "gn:feature_code":"PPL",
    "gn:name":"Siab",
    "gn:population":0,
    "gn:timezone":"Asia/Karachi",
    "iso:country":"PK",
    "wof:name":"Siab",
    "wof:placetype":"locality"
},
  "geometry": {"coordinates":[63.22548000000001,28.16991],"type":"Point"}
}