{
  "type": "Feature",
  "properties": {
    "gn:admin1_code":"5",
    "gn:asciiname":"Kabul Machi",
    "gn:country_code":"PK",
    "gn:dem":75,
    "gn:feature_class":"P",
    "gn:feature_code":"PPL",
    "gn:name":"Kabul Machi",
    "gn:population":0,
    "gn:timezone":"Asia/Karachi",
    "iso:country":"PK",
    "name:und_x_variant":[
        "Kabul Khohato"
    ],
    "wof:name":"Kabul Machi",
    "wof:placetype":"locality"
},
  "geometry": {"coordinates":[69.62763000000001,28.06673],"type":"Point"}
}