{
  "type": "Feature",
  "properties": {
    "gn:admin1_code":"2.0",
    "gn:asciiname":"Chinal",
    "gn:country_code":"PK",
    "gn:dem":1267,
    "gn:feature_class":"P",
    "gn:feature_code":"PPL",
    "gn:name":"Chinal",
    "gn:population":0,
    "gn:timezone":"Asia/Karachi",
    "iso:country":"PK",
    "wof:name":"Chinal",
    "wof:placetype":"locality"
},
  "geometry": {"coordinates":[69.67596,30.01494000000001],"type":"Point"}
}