{
  "type": "Feature",
  "properties": {
    "gn:admin1_code":"3",
    "gn:asciiname":"Ghazikot",
    "gn:country_code":"PK",
    "gn:dem":1913,
    "gn:feature_class":"P",
    "gn:feature_code":"PPL",
    "gn:name":"Ghazikot",
    "gn:population":0,
    "gn:timezone":"Asia/Karachi",
    "iso:country":"PK",
    "name:und_x_variant":[
        "Gh\u0101z\u012bkot"
    ],
    "wof:name":"Ghazikot",
    "wof:placetype":"locality"
},
  "geometry": {"coordinates":[72.99013000000002,34.34614000000001],"type":"Point"}
}