{
  "type": "Feature",
  "properties": {
    "gn:admin1_code":"4.0",
    "gn:asciiname":"Water and Power Development Authority Town",
    "gn:country_code":"PK",
    "gn:dem":123,
    "gn:feature_class":"P",
    "gn:feature_code":"PPL",
    "gn:name":"Water and Power Development Authority Town",
    "gn:population":0,
    "gn:timezone":"Asia/Karachi",
    "iso:country":"PK",
    "wof:name":"Water and Power Development Authority Town",
    "wof:placetype":"locality"
},
  "geometry": {"coordinates":[71.50757,30.24551],"type":"Point"}
}