{
  "type": "Feature",
  "properties": {
    "gn:admin1_code":"5",
    "gn:asciiname":"Goth Vi Machhi",
    "gn:country_code":"PK",
    "gn:dem":30,
    "gn:feature_class":"P",
    "gn:feature_code":"PPL",
    "gn:name":"Goth Vi Machhi",
    "gn:population":0,
    "gn:timezone":"Asia/Karachi",
    "iso:country":"PK",
    "name:eng_x_preferred":[
        "H\u0101la Nawa"
    ],
    "wof:name":"Goth Vi Machhi",
    "wof:placetype":"locality"
},
  "geometry": {"coordinates":[68.41303000000001,25.8215],"type":"Point"}
}