{
  "type": "Feature",
  "properties": {
    "gn:admin1_code":"6",
    "gn:asciiname":"Gimba",
    "gn:country_code":"PK",
    "gn:dem":1545,
    "gn:feature_class":"P",
    "gn:feature_code":"PPL",
    "gn:name":"Gimba",
    "gn:population":0,
    "gn:timezone":"Asia/Karachi",
    "iso:country":"PK",
    "wof:name":"Gimba",
    "wof:placetype":"locality"
},
  "geometry": {"coordinates":[74.15475000000001,33.49874000000001],"type":"Point"}
}