{
  "type": "Feature",
  "properties": {
    "gn:admin1_code":"1.0",
    "gn:asciiname":"Tupehan",
    "gn:country_code":"PK",
    "gn:dem":2287,
    "gn:feature_class":"P",
    "gn:feature_code":"PPL",
    "gn:name":"Tupehan",
    "gn:population":0,
    "gn:timezone":"Asia/Karachi",
    "iso:country":"PK",
    "name:und_x_variant":[
        "Tupchan"
    ],
    "wof:name":"Tupehan",
    "wof:placetype":"locality"
},
  "geometry": {"coordinates":[70.47272,33.86742],"type":"Point"}
}