{
  "type": "Feature",
  "properties": {
    "gn:admin1_code":"05",
    "gn:asciiname":"Mithrio Charan",
    "gn:country_code":"PK",
    "gn:dem":137,
    "gn:feature_class":"P",
    "gn:feature_code":"PPL",
    "gn:name":"Mithrio Charan",
    "gn:population":0,
    "gn:timezone":"Asia/Karachi",
    "iso:country":"PK",
    "name:und_x_variant":[
        "Milhriyo Charan",
        "Mithrio Charan"
    ],
    "wof:name":"Mithrio Charan",
    "wof:placetype":"locality"
},
  "geometry": {"coordinates":[70.48333000000002,25.23333],"type":"Point"}
}