{
  "type": "Feature",
  "properties": {
    "gn:admin1_code":"1",
    "gn:asciiname":"Aghbargai Khullah",
    "gn:country_code":"PK",
    "gn:dem":1153,
    "gn:feature_class":"P",
    "gn:feature_code":"PPL",
    "gn:name":"Aghbargai Khullah",
    "gn:population":0,
    "gn:timezone":"Asia/Karachi",
    "iso:country":"PK",
    "name:fas_x_preferred":[
        "\u0627\u0642\u0628\u0631\u06af\u0627\u06cc \u06a9\u0648\u0644\u0627\u0647"
    ],
    "name:und_x_variant":[
        "Aghbargai"
    ],
    "name:urd_x_preferred":[
        "\u0627\u0642\u0628\u0631\u06af\u0627\u0626\u06cc \u06a9\u0648\u0644\u0627\u06c1"
    ],
    "wof:name":"Aghbargai Khullah",
    "wof:placetype":"locality"
},
  "geometry": {"coordinates":[69.94744,32.39592],"type":"Point"}
}