{
  "type": "Feature",
  "properties": {
    "gn:admin1_code":"1",
    "gn:asciiname":"Aghbargai Khullah",
    "gn:country_code":"PK",
    "gn:dem":1153,
    "gn:feature_class":"P",
    "gn:feature_code":"PPL",
    "gn:name":"Aghbargai Khullah",
    "gn:population":0,
    "gn:timezone":"Asia/Karachi",
    "iso:country":"PK",
    "name:und_x_variant":[
        "Aghbargai"
    ],
    "wof:name":"Aghbargai Khullah",
    "wof:placetype":"locality"
},
  "geometry": {"coordinates":[69.94744,32.39592],"type":"Point"}
}