{
  "type": "Feature",
  "properties": {
    "gn:admin1_code":"5.0",
    "gn:asciiname":"Goth Jaro Hingorja",
    "gn:country_code":"PK",
    "gn:dem":8,
    "gn:feature_class":"P",
    "gn:feature_code":"PPL",
    "gn:name":"Goth Jaro Hingorja",
    "gn:population":0,
    "gn:timezone":"Asia/Karachi",
    "iso:country":"PK",
    "name:und_x_variant":[
        "Goth Ali Muhammad"
    ],
    "wof:name":"Goth Jaro Hingorja",
    "wof:placetype":"locality"
},
  "geometry": {"coordinates":[67.78506999999999,24.67398],"type":"Point"}
}