{
  "type": "Feature",
  "properties": {
    "gn:admin1_code":"2.0",
    "gn:asciiname":"Shah Murad Gis",
    "gn:country_code":"PK",
    "gn:dem":1634,
    "gn:feature_class":"P",
    "gn:feature_code":"PPL",
    "gn:name":"Shah Murad Gis",
    "gn:population":0,
    "gn:timezone":"Asia/Karachi",
    "iso:country":"PK",
    "wof:name":"Shah Murad Gis",
    "wof:placetype":"locality"
},
  "geometry": {"coordinates":[63.78162,29.38781],"type":"Point"}
}