{
  "type": "Feature",
  "properties": {
    "gn:admin1_code":"01",
    "gn:asciiname":"Galamkankalay",
    "gn:country_code":"PK",
    "gn:dem":1295,
    "gn:feature_class":"P",
    "gn:feature_code":"PPL",
    "gn:name":"Galamkankalay",
    "gn:population":0,
    "gn:timezone":"Asia/Karachi",
    "iso:country":"PK",
    "name:und_x_variant":[
        "Ghul\u0101m Kh\u0101n K\u00ealay",
        "Gol\u0101mkh\u0101n Kalay",
        "\u063a\u0644\u0627\u0645 \u062e\u0627\u0646 \u06a9\u0644\u06cc"
    ],
    "wof:name":"Galamkankalay",
    "wof:placetype":"locality"
},
  "geometry": {"coordinates":[70.02927,33.14522],"type":"Point"}
}