{
  "type": "Feature",
  "properties": {
    "gn:admin1_code":"3",
    "gn:asciiname":"Banda Shahabuddin",
    "gn:country_code":"PK",
    "gn:dem":277,
    "gn:feature_class":"P",
    "gn:feature_code":"PPL",
    "gn:name":"Banda Shahabuddin",
    "gn:population":0,
    "gn:timezone":"Asia/Karachi",
    "iso:country":"PK",
    "wof:name":"Banda Shahabuddin",
    "wof:placetype":"locality"
},
  "geometry": {"coordinates":[71.02331,32.66019],"type":"Point"}
}