{
  "type": "Feature",
  "properties": {
    "gn:admin1_code":"3.0",
    "gn:asciiname":"Bhai Kot Number One",
    "gn:country_code":"PK",
    "gn:dem":360,
    "gn:feature_class":"P",
    "gn:feature_code":"PPL",
    "gn:name":"Bhai Kot Number One",
    "gn:population":0,
    "gn:timezone":"Asia/Karachi",
    "iso:country":"PK",
    "wof:name":"Bhai Kot Number One",
    "wof:placetype":"locality"
},
  "geometry": {"coordinates":[72.50385,34.1456],"type":"Point"}
}