{
  "type": "Feature",
  "properties": {
    "gn:admin1_code":"5.0",
    "gn:asciiname":"Ismail Khan Jatoi",
    "gn:country_code":"PK",
    "gn:dem":55,
    "gn:feature_class":"P",
    "gn:feature_code":"PPL",
    "gn:name":"Ismail Khan Jatoi",
    "gn:population":0,
    "gn:timezone":"Asia/Karachi",
    "iso:country":"PK",
    "name:eng_x_preferred":[
        "Goth Ismail Kh\u0101n"
    ],
    "wof:name":"Ismail Khan Jatoi",
    "wof:placetype":"locality"
},
  "geometry": {"coordinates":[68.55614,27.46555],"type":"Point"}
}