{
  "type": "Feature",
  "properties": {
    "gn:admin1_code":"1.0",
    "gn:asciiname":"Bakro Dheri",
    "gn:country_code":"PK",
    "gn:dem":519,
    "gn:feature_class":"P",
    "gn:feature_code":"PPL",
    "gn:name":"Bakro Dheri",
    "gn:population":0,
    "gn:timezone":"Asia/Karachi",
    "iso:country":"PK",
    "name:eng_x_preferred":[
        "Bakaro Dherai"
    ],
    "name:und_x_variant":[
        "Bakaroo Derai"
    ],
    "wof:name":"Bakro Dheri",
    "wof:placetype":"locality"
},
  "geometry": {"coordinates":[71.6375,34.41206],"type":"Point"}
}