{
  "type": "Feature",
  "properties": {
    "gn:admin1_code":"3.0",
    "gn:asciiname":"Gurangal Pain",
    "gn:country_code":"PK",
    "gn:dem":1833,
    "gn:feature_class":"P",
    "gn:feature_code":"PPL",
    "gn:name":"Gurangal Pain",
    "gn:population":0,
    "gn:timezone":"Asia/Karachi",
    "iso:country":"PK",
    "wof:name":"Gurangal Pain",
    "wof:placetype":"locality"
},
  "geometry": {"coordinates":[71.68293,35.42988],"type":"Point"}
}