{
  "type": "Feature",
  "properties": {
    "gn:admin1_code":"2.0",
    "gn:asciiname":"Gangai Melan",
    "gn:country_code":"PK",
    "gn:dem":1939,
    "gn:feature_class":"P",
    "gn:feature_code":"PPL",
    "gn:name":"Gangai Melan",
    "gn:population":0,
    "gn:timezone":"Asia/Karachi",
    "iso:country":"PK",
    "wof:name":"Gangai Melan",
    "wof:placetype":"locality"
},
  "geometry": {"coordinates":[68.55469000000001,31.11627],"type":"Point"}
}