{
  "type": "Feature",
  "properties": {
    "gn:admin1_code":"01",
    "gn:asciiname":"Ladha",
    "gn:country_code":"PK",
    "gn:dem":1725,
    "gn:feature_class":"P",
    "gn:feature_code":"PPL",
    "gn:name":"Ladha",
    "gn:population":0,
    "gn:timezone":"Asia/Karachi",
    "iso:country":"PK",
    "wof:name":"Ladha",
    "wof:placetype":"locality"
},
  "geometry": {"coordinates":[69.82907,32.56803],"type":"Point"}
}