{
  "type": "Feature",
  "properties": {
    "gn:admin1_code":"4",
    "gn:asciiname":"Boharwala",
    "gn:country_code":"PK",
    "gn:dem":167,
    "gn:feature_class":"P",
    "gn:feature_code":"PPL",
    "gn:name":"Boharwala",
    "gn:population":0,
    "gn:timezone":"Asia/Karachi",
    "iso:country":"PK",
    "name:fas_x_preferred":[
        "\u0628\u0648\u0647\u0631\u0648\u0627\u0644\u0627"
    ],
    "name:urd_x_preferred":[
        "\u0628\u0648\u06c1\u0691\u0648\u0627\u0644\u0627"
    ],
    "wof:name":"Boharwala",
    "wof:placetype":"locality"
},
  "geometry": {"coordinates":[71.14861999999999,31.55084],"type":"Point"}
}