{
  "type": "Feature",
  "properties": {
    "gn:admin1_code":"4.0",
    "gn:asciiname":"Dhok Rawal",
    "gn:country_code":"PK",
    "gn:dem":417,
    "gn:feature_class":"P",
    "gn:feature_code":"PPL",
    "gn:name":"Dhok Rawal",
    "gn:population":0,
    "gn:timezone":"Asia/Karachi",
    "iso:country":"PK",
    "name:und_x_variant":[
        "Dhok Raw\u0101l"
    ],
    "wof:name":"Dhok Rawal",
    "wof:placetype":"locality"
},
  "geometry": {"coordinates":[72.38561,33.20537],"type":"Point"}
}