{
  "type": "Feature",
  "properties": {
    "gn:admin1_code":"2.0",
    "gn:asciiname":"Gurgej Chah",
    "gn:country_code":"PK",
    "gn:dem":1516,
    "gn:feature_class":"P",
    "gn:feature_code":"PPL",
    "gn:name":"Gurgej Chah",
    "gn:population":0,
    "gn:timezone":"Asia/Karachi",
    "iso:country":"PK",
    "wof:name":"Gurgej Chah",
    "wof:placetype":"locality"
},
  "geometry": {"coordinates":[64.23824999999999,29.41394],"type":"Point"}
}