{
  "type": "Feature",
  "properties": {
    "gn:admin1_code":"6",
    "gn:asciiname":"Thund",
    "gn:country_code":"PK",
    "gn:dem":2571,
    "gn:feature_class":"P",
    "gn:feature_code":"PPL",
    "gn:name":"Thund",
    "gn:population":0,
    "gn:timezone":"Asia/Karachi",
    "iso:country":"PK",
    "name:und_x_variant":[
        "Chund",
        "Dhund"
    ],
    "wof:name":"Thund",
    "wof:placetype":"locality"
},
  "geometry": {"coordinates":[74.16214000000002,33.97136],"type":"Point"}
}