{
  "type": "Feature",
  "properties": {
    "gn:admin1_code":"2.0",
    "gn:asciiname":"Chhumb",
    "gn:country_code":"PK",
    "gn:dem":114,
    "gn:feature_class":"P",
    "gn:feature_code":"PPL",
    "gn:name":"Chhumb",
    "gn:population":0,
    "gn:timezone":"Asia/Karachi",
    "iso:country":"PK",
    "name:und_x_variant":[
        "Chhamb"
    ],
    "wof:name":"Chhumb",
    "wof:placetype":"locality"
},
  "geometry": {"coordinates":[67.59211999999999,29.14475],"type":"Point"}
}