{
  "type": "Feature",
  "properties": {
    "gn:admin1_code":"3.0",
    "gn:asciiname":"Hindu Kili",
    "gn:country_code":"PK",
    "gn:dem":344,
    "gn:feature_class":"P",
    "gn:feature_code":"PPL",
    "gn:name":"Hindu Kili",
    "gn:population":0,
    "gn:timezone":"Asia/Karachi",
    "iso:country":"PK",
    "name:eng_x_preferred":[
        "Hindu Kili"
    ],
    "wof:name":"Hindu Kili",
    "wof:placetype":"locality"
},
  "geometry": {"coordinates":[71.92419,34.27178],"type":"Point"}
}