{
  "type": "Feature",
  "properties": {
    "gn:admin1_code":"5.0",
    "gn:asciiname":"Goth Haji Husain Panhwar",
    "gn:country_code":"PK",
    "gn:dem":14,
    "gn:feature_class":"P",
    "gn:feature_code":"PPL",
    "gn:name":"Goth Haji Husain Panhwar",
    "gn:population":0,
    "gn:timezone":"Asia/Karachi",
    "iso:country":"PK",
    "wof:name":"Goth Haji Husain Panhwar",
    "wof:placetype":"locality"
},
  "geometry": {"coordinates":[69.39487,25.59837000000001],"type":"Point"}
}