{
  "type": "Feature",
  "properties": {
    "gn:admin1_code":"5",
    "gn:asciiname":"Goth Hamza Khan",
    "gn:country_code":"PK",
    "gn:dem":63,
    "gn:feature_class":"P",
    "gn:feature_code":"PPL",
    "gn:name":"Goth Hamza Khan",
    "gn:population":0,
    "gn:timezone":"Asia/Karachi",
    "iso:country":"PK",
    "name:und_x_variant":[
        "Hamza Kh\u0101n"
    ],
    "wof:name":"Goth Hamza Khan",
    "wof:placetype":"locality"
},
  "geometry": {"coordinates":[68.87383,28.4054],"type":"Point"}
}