{
  "type": "Feature",
  "properties": {
    "gn:admin1_code":"4",
    "gn:asciiname":"Chak One M",
    "gn:country_code":"PK",
    "gn:dem":121,
    "gn:feature_class":"P",
    "gn:feature_code":"PPL",
    "gn:name":"Chak One M",
    "gn:population":0,
    "gn:timezone":"Asia/Karachi",
    "iso:country":"PK",
    "name:und_x_variant":[
        "Chak One AM"
    ],
    "wof:name":"Chak One M",
    "wof:placetype":"locality"
},
  "geometry": {"coordinates":[72.05146999999999,29.85609],"type":"Point"}
}