{
  "type": "Feature",
  "properties": {
    "gn:admin1_code":"3",
    "gn:asciiname":"Urya",
    "gn:country_code":"PK",
    "gn:dem":379,
    "gn:feature_class":"P",
    "gn:feature_code":"PPL",
    "gn:name":"Urya",
    "gn:population":0,
    "gn:timezone":"Asia/Karachi",
    "iso:country":"PK",
    "name:eng_x_preferred":[
        "Ore"
    ],
    "wof:name":"Urya",
    "wof:placetype":"locality"
},
  "geometry": {"coordinates":[72.30821,34.27039],"type":"Point"}
}