{
  "type": "Feature",
  "properties": {
    "gn:admin1_code":"4.0",
    "gn:asciiname":"Rakh Baluch Khurd",
    "gn:country_code":"PK",
    "gn:dem":221,
    "gn:feature_class":"P",
    "gn:feature_code":"PPL",
    "gn:name":"Rakh Baluch Khurd",
    "gn:population":0,
    "gn:timezone":"Asia/Karachi",
    "iso:country":"PK",
    "wof:name":"Rakh Baluch Khurd",
    "wof:placetype":"locality"
},
  "geometry": {"coordinates":[73.59125,32.56249],"type":"Point"}
}