{
  "type": "Feature",
  "properties": {
    "gn:admin1_code":"2.0",
    "gn:asciiname":"Shishari",
    "gn:country_code":"PK",
    "gn:dem":1846,
    "gn:feature_class":"P",
    "gn:feature_code":"PPL",
    "gn:name":"Shishari",
    "gn:population":0,
    "gn:timezone":"Asia/Karachi",
    "iso:country":"PK",
    "wof:name":"Shishari",
    "wof:placetype":"locality"
},
  "geometry": {"coordinates":[66.07288,28.73959],"type":"Point"}
}