{
  "type": "Feature",
  "properties": {
    "gn:admin1_code":"4",
    "gn:asciiname":"Basti Ghulam Qadir Dangar",
    "gn:country_code":"PK",
    "gn:dem":98,
    "gn:feature_class":"P",
    "gn:feature_code":"PPL",
    "gn:name":"Basti Ghulam Qadir Dangar",
    "gn:population":0,
    "gn:timezone":"Asia/Karachi",
    "iso:country":"PK",
    "name:und_x_variant":[
        "Basti Ghul\u0101m Q\u0101dir Dangar",
        "M\u016bsa Dangar",
        "Basti Ghulam Qadir Dangar"
    ],
    "wof:name":"Basti Ghulam Qadir Dangar",
    "wof:placetype":"locality"
},
  "geometry": {"coordinates":[70.49679999999999,29.16032],"type":"Point"}
}