{
  "type": "Feature",
  "properties": {
    "gn:admin1_code":"4.0",
    "gn:asciiname":"Sikandarabad",
    "gn:country_code":"PK",
    "gn:dem":153,
    "gn:feature_class":"P",
    "gn:feature_code":"PPL",
    "gn:name":"Sikandarabad",
    "gn:population":0,
    "gn:timezone":"Asia/Karachi",
    "iso:country":"PK",
    "name:fas_x_preferred":[
        "\u0633\u06a9\u0646\u062f\u0631\u0622\u0628\u0627\u062f"
    ],
    "wof:name":"Sikandarabad",
    "wof:placetype":"locality"
},
  "geometry": {"coordinates":[73.15567,29.95405],"type":"Point"}
}