{
  "type": "Feature",
  "properties": {
    "gn:admin1_code":"4.0",
    "gn:asciiname":"Chak Ten-Gugera Distributary",
    "gn:country_code":"PK",
    "gn:dem":183,
    "gn:feature_class":"P",
    "gn:feature_code":"PPL",
    "gn:name":"Chak Ten-Gugera Distributary",
    "gn:population":0,
    "gn:timezone":"Asia/Karachi",
    "iso:country":"PK",
    "name:und_x_variant":[
        "Bhattiw\u0101la"
    ],
    "wof:name":"Chak Ten-Gugera Distributary",
    "wof:placetype":"locality"
},
  "geometry": {"coordinates":[73.54019,30.98838],"type":"Point"}
}