{
  "type": "Feature",
  "properties": {
    "gn:admin1_code":"6.0",
    "gn:asciiname":"Siroli",
    "gn:country_code":"PK",
    "gn:dem":1075,
    "gn:feature_class":"P",
    "gn:feature_code":"PPL",
    "gn:name":"Siroli",
    "gn:population":0,
    "gn:timezone":"Asia/Karachi",
    "iso:country":"PK",
    "name:und_x_variant":[
        "Sir\u016bli"
    ],
    "wof:name":"Siroli",
    "wof:placetype":"locality"
},
  "geometry": {"coordinates":[73.59728,33.83459000000001],"type":"Point"}
}