{
  "type": "Feature",
  "properties": {
    "gn:admin1_code":"2.0",
    "gn:asciiname":"Skhobi",
    "gn:country_code":"PK",
    "gn:dem":2137,
    "gn:feature_class":"P",
    "gn:feature_code":"PPL",
    "gn:name":"Skhobi",
    "gn:population":0,
    "gn:timezone":"Asia/Karachi",
    "iso:country":"PK",
    "wof:name":"Skhobi",
    "wof:placetype":"locality"
},
  "geometry": {"coordinates":[67.83548,31.02083],"type":"Point"}
}