{
  "type": "Feature",
  "properties": {
    "gn:admin1_code":"2.0",
    "gn:asciiname":"Abdullah Khan",
    "gn:country_code":"PK",
    "gn:dem":1256,
    "gn:feature_class":"P",
    "gn:feature_code":"PPL",
    "gn:name":"Abdullah Khan",
    "gn:population":0,
    "gn:timezone":"Asia/Karachi",
    "iso:country":"PK",
    "name:cat_x_preferred":[
        "Abdullah Khan"
    ],
    "wof:name":"Abdullah Khan",
    "wof:placetype":"locality"
},
  "geometry": {"coordinates":[64.32191,29.30571],"type":"Point"}
}