{
  "type": "Feature",
  "properties": {
    "gn:admin1_code":"5",
    "gn:asciiname":"Goth Naubal Sahuwal",
    "gn:country_code":"PK",
    "gn:dem":26,
    "gn:feature_class":"P",
    "gn:feature_code":"PPL",
    "gn:name":"Goth Naubal Sahuwal",
    "gn:population":0,
    "gn:timezone":"Asia/Karachi",
    "iso:country":"PK",
    "wof:name":"Goth Naubal Sahuwal",
    "wof:placetype":"locality"
},
  "geometry": {"coordinates":[68.52760000000001,25.72974],"type":"Point"}
}