{
  "type": "Feature",
  "properties": {
    "gn:admin1_code":"4.0",
    "gn:asciiname":"Karm Khel Chhapari",
    "gn:country_code":"PK",
    "gn:dem":905,
    "gn:feature_class":"P",
    "gn:feature_code":"PPL",
    "gn:name":"Karm Khel Chhapari",
    "gn:population":0,
    "gn:timezone":"Asia/Karachi",
    "iso:country":"PK",
    "name:und_x_variant":[
        "Karm Khel Chapara"
    ],
    "wof:name":"Karm Khel Chhapari",
    "wof:placetype":"locality"
},
  "geometry": {"coordinates":[71.47594000000002,33.1086],"type":"Point"}
}