{
  "type": "Feature",
  "properties": {
    "gn:admin1_code":"4.0",
    "gn:asciiname":"Chak Thrity-Eight Sharqi",
    "gn:country_code":"PK",
    "gn:dem":216,
    "gn:feature_class":"P",
    "gn:feature_code":"PPL",
    "gn:name":"Chak Thrity-Eight Sharqi",
    "gn:population":0,
    "gn:timezone":"Asia/Karachi",
    "iso:country":"PK",
    "name:und_x_variant":[
        "Dinga Chak"
    ],
    "wof:name":"Chak Thrity-Eight Sharqi",
    "wof:placetype":"locality"
},
  "geometry": {"coordinates":[73.46850999999999,32.49544],"type":"Point"}
}