{
  "type": "Feature",
  "properties": {
    "gn:admin1_code":"3.0",
    "gn:asciiname":"Kag",
    "gn:country_code":"PK",
    "gn:dem":480,
    "gn:feature_class":"P",
    "gn:feature_code":"PPL",
    "gn:name":"Kag",
    "gn:population":0,
    "gn:timezone":"Asia/Karachi",
    "iso:country":"PK",
    "wof:name":"Kag",
    "wof:placetype":"locality"
},
  "geometry": {"coordinates":[72.94271999999999,34.06728],"type":"Point"}
}