{
  "type": "Feature",
  "properties": {
    "gn:admin1_code":"4",
    "gn:asciiname":"Thakra",
    "gn:country_code":"PK",
    "gn:dem":344,
    "gn:feature_class":"P",
    "gn:feature_code":"PPL",
    "gn:name":"Thakra",
    "gn:population":0,
    "gn:timezone":"Asia/Karachi",
    "iso:country":"PK",
    "name:eng_x_preferred":[
        "Basti Thakras Dabh"
    ],
    "name:und_x_variant":[
        "Thakras Dabh",
        "Thakra"
    ],
    "wof:name":"Thakra",
    "wof:placetype":"locality"
},
  "geometry": {"coordinates":[70.37714,30.14171],"type":"Point"}
}