{
  "type": "Feature",
  "properties": {
    "gn:admin1_code":"3.0",
    "gn:asciiname":"Kotkai Bala",
    "gn:country_code":"PK",
    "gn:dem":2359,
    "gn:feature_class":"P",
    "gn:feature_code":"PPL",
    "gn:name":"Kotkai Bala",
    "gn:population":0,
    "gn:timezone":"Asia/Karachi",
    "iso:country":"PK",
    "wof:name":"Kotkai Bala",
    "wof:placetype":"locality"
},
  "geometry": {"coordinates":[73.63143000000002,34.7139],"type":"Point"}
}