{
  "type": "Feature",
  "properties": {
    "gn:admin1_code":"2.0",
    "gn:asciiname":"Qasai",
    "gn:country_code":"PK",
    "gn:dem":93,
    "gn:feature_class":"P",
    "gn:feature_code":"PPL",
    "gn:name":"Qasai",
    "gn:population":0,
    "gn:timezone":"Asia/Karachi",
    "iso:country":"PK",
    "name:und_x_variant":[
        "Shahr H\u0101ji S\u0101war"
    ],
    "wof:name":"Qasai",
    "wof:placetype":"locality"
},
  "geometry": {"coordinates":[67.48873,28.83183],"type":"Point"}
}