{
  "type": "Feature",
  "properties": {
    "gn:admin1_code":"04",
    "gn:asciiname":"Nawanshahr",
    "gn:country_code":"PK",
    "gn:dem":119,
    "gn:feature_class":"P",
    "gn:feature_code":"PPL",
    "gn:name":"Nawanshahr",
    "gn:population":0,
    "gn:timezone":"Asia/Karachi",
    "iso:country":"PK",
    "name:ben_x_preferred":[
        "\u09a8\u0993\u09af\u09bc\u09be\u09a8\u09b6\u09be\u09b9\u09b0"
    ],
    "name:bpy_x_preferred":[
        "\u09a8\u09f1\u09be\u09a8\u09b6\u09be\u09b9\u09b0"
    ],
    "name:hin_x_preferred":[
        "\u0928\u0935\u093e\u0902\u0936\u0939\u0930"
    ],
    "name:ita_x_preferred":[
        "Nawanshahr"
    ],
    "name:mar_x_preferred":[
        "\u0928\u0935\u093e\u0928 \u0936\u0939\u0930"
    ],
    "name:msa_x_preferred":[
        "Nawanshahr"
    ],
    "name:new_x_preferred":[
        "\u0928\u0935\u0928\u0936\u0939\u0930"
    ],
    "name:nld_x_preferred":[
        "Nawanshahr"
    ],
    "name:nor_x_preferred":[
        "Nawanshahr"
    ],
    "name:ori_x_preferred":[
        "\u0b28\u0b71\u0b3e\u0b28\u0b36\u0b3e\u0b39\u0b30"
    ],
    "name:san_x_preferred":[
        "\u0928\u0935\u093e\u0902\u0936\u0939\u0930-\u0928\u0917\u0930\u092e\u094d"
    ],
    "name:spa_x_preferred":[
        "Nawanshahr"
    ],
    "name:und_x_variant":[
        "Naw\u0101n Shahr",
        "Naw\u0101shahr",
        "Nawanshahr"
    ],
    "name:urd_x_preferred":[
        "\u0646\u0648\u0627\u06ba \u0634\u06c1\u0631"
    ],
    "name:vie_x_preferred":[
        "Nawanshahr"
    ],
    "name:zho_x_preferred":[
        "\u7eb3\u4e07\u65af\u54c8\u8d6b\u5c14"
    ],
    "wof:name":"Nawanshahr",
    "wof:placetype":"locality"
},
  "geometry": {"coordinates":[70.33299,29.45111],"type":"Point"}
}