{
  "type": "Feature",
  "properties": {
    "gn:admin1_code":"04",
    "gn:asciiname":"Nawanshahr",
    "gn:country_code":"PK",
    "gn:dem":119,
    "gn:feature_class":"P",
    "gn:feature_code":"PPL",
    "gn:name":"Nawanshahr",
    "gn:population":0,
    "gn:timezone":"Asia/Karachi",
    "iso:country":"PK",
    "name:und_x_variant":[
        "Naw\u0101n Shahr",
        "Naw\u0101shahr",
        "Nawanshahr"
    ],
    "wof:name":"Nawanshahr",
    "wof:placetype":"locality"
},
  "geometry": {"coordinates":[70.33299,29.45111],"type":"Point"}
}