{
  "type": "Feature",
  "properties": {
    "gn:admin1_code":"6",
    "gn:asciiname":"Takia",
    "gn:country_code":"PK",
    "gn:dem":2395,
    "gn:feature_class":"P",
    "gn:feature_code":"PPL",
    "gn:name":"Takia",
    "gn:population":0,
    "gn:timezone":"Asia/Karachi",
    "iso:country":"PK",
    "name:ceb_x_preferred":[
        "Takia"
    ],
    "name:deu_x_preferred":[
        "Takia"
    ],
    "name:swe_x_preferred":[
        "Takia"
    ],
    "wof:name":"Takia",
    "wof:placetype":"locality"
},
  "geometry": {"coordinates":[73.74013000000002,34.2793],"type":"Point"}
}