{
  "type": "Feature",
  "properties": {
    "gn:admin1_code":"2",
    "gn:asciiname":"Guzh Bhaint",
    "gn:country_code":"PK",
    "gn:dem":1145,
    "gn:feature_class":"P",
    "gn:feature_code":"PPL",
    "gn:name":"Guzh Bhaint",
    "gn:population":0,
    "gn:timezone":"Asia/Karachi",
    "iso:country":"PK",
    "name:und_x_variant":[
        "Robdar"
    ],
    "wof:name":"Guzh Bhaint",
    "wof:placetype":"locality"
},
  "geometry": {"coordinates":[67.2162,29.4095],"type":"Point"}
}