{
  "type": "Feature",
  "properties": {
    "gn:admin1_code":"4.0",
    "gn:asciiname":"Kamogi Canal Lodge",
    "gn:country_code":"PK",
    "gn:dem":201,
    "gn:feature_class":"P",
    "gn:feature_code":"PPL",
    "gn:name":"Kamogi Canal Lodge",
    "gn:population":0,
    "gn:timezone":"Asia/Karachi",
    "iso:country":"PK",
    "name:und_x_variant":[
        "Kamogil"
    ],
    "wof:name":"Kamogi Canal Lodge",
    "wof:placetype":"locality"
},
  "geometry": {"coordinates":[74.04434000000001,31.26007],"type":"Point"}
}