{
  "type": "Feature",
  "properties": {
    "gn:admin1_code":"03",
    "gn:asciiname":"Bargholai",
    "gn:country_code":"PK",
    "gn:dem":784,
    "gn:feature_class":"P",
    "gn:feature_code":"PPL",
    "gn:name":"Bargholai",
    "gn:population":0,
    "gn:timezone":"Asia/Karachi",
    "iso:country":"PK",
    "name:eng_x_preferred":[
        "Bargholai"
    ],
    "wof:name":"Bargholai",
    "wof:placetype":"locality"
},
  "geometry": {"coordinates":[71.73603,34.56068],"type":"Point"}
}