{
  "type": "Feature",
  "properties": {
    "gn:admin1_code":"6.0",
    "gn:asciiname":"Chak Mehun",
    "gn:country_code":"PK",
    "gn:dem":354,
    "gn:feature_class":"P",
    "gn:feature_code":"PPL",
    "gn:name":"Chak Mehun",
    "gn:population":0,
    "gn:timezone":"Asia/Karachi",
    "iso:country":"PK",
    "name:und_x_variant":[
        "Chak Mahesi\u0101n"
    ],
    "wof:name":"Chak Mehun",
    "wof:placetype":"locality"
},
  "geometry": {"coordinates":[73.5183,33.04881],"type":"Point"}
}