{
  "type": "Feature",
  "properties": {
    "gn:admin1_code":"2.0",
    "gn:asciiname":"Kili Chanal",
    "gn:country_code":"PK",
    "gn:dem":712,
    "gn:feature_class":"P",
    "gn:feature_code":"PPL",
    "gn:name":"Kili Chanal",
    "gn:population":0,
    "gn:timezone":"Asia/Karachi",
    "iso:country":"PK",
    "wof:name":"Kili Chanal",
    "wof:placetype":"locality"
},
  "geometry": {"coordinates":[65.52864,28.55876],"type":"Point"}
}