{
  "type": "Feature",
  "properties": {
    "gn:admin1_code":"6.0",
    "gn:asciiname":"Khumal",
    "gn:country_code":"PK",
    "gn:dem":413,
    "gn:feature_class":"P",
    "gn:feature_code":"PPL",
    "gn:name":"Khumal",
    "gn:population":0,
    "gn:timezone":"Asia/Karachi",
    "iso:country":"PK",
    "wof:name":"Khumal",
    "wof:placetype":"locality"
},
  "geometry": {"coordinates":[73.72364,33.15125],"type":"Point"}
}