{
  "type": "Feature",
  "properties": {
    "gn:admin1_code":"04",
    "gn:asciiname":"Chak Forty-one",
    "gn:country_code":"PK",
    "gn:dem":179,
    "gn:feature_class":"P",
    "gn:feature_code":"PPL",
    "gn:name":"Chak Forty-one",
    "gn:population":0,
    "gn:timezone":"Asia/Karachi",
    "iso:country":"PK",
    "name:und_x_variant":[
        "Sati\u0101na",
        "Chak Forty-one"
    ],
    "wof:name":"Chak Forty-one",
    "wof:placetype":"locality"
},
  "geometry": {"coordinates":[72.84269999999999,31.39524],"type":"Point"}
}