{
  "type": "Feature",
  "properties": {
    "gn:admin1_code":"5.0",
    "gn:asciiname":"Adha Khan Gadio",
    "gn:country_code":"PK",
    "gn:dem":42,
    "gn:feature_class":"P",
    "gn:feature_code":"PPL",
    "gn:name":"Adha Khan Gadio",
    "gn:population":0,
    "gn:timezone":"Asia/Karachi",
    "iso:country":"PK",
    "wof:name":"Adha Khan Gadio",
    "wof:placetype":"locality"
},
  "geometry": {"coordinates":[67.69776999999999,27.09932],"type":"Point"}
}