{
  "type": "Feature",
  "properties": {
    "gn:admin1_code":"4.0",
    "gn:asciiname":"Chak Three Hundred Forty-seven -One Hundred Twelve Gugera Branch",
    "gn:country_code":"PK",
    "gn:dem":156,
    "gn:feature_class":"P",
    "gn:feature_code":"PPL",
    "gn:name":"Chak Three Hundred Forty-seven -One Hundred Twelve Gugera Branch",
    "gn:population":0,
    "gn:timezone":"Asia/Karachi",
    "iso:country":"PK",
    "name:und_x_variant":[
        "Chak Three Hundred Forty-Seven-One/Two GB"
    ],
    "wof:name":"Chak Three Hundred Forty-seven -One Hundred Twelve Gugera Branch",
    "wof:placetype":"locality"
},
  "geometry": {"coordinates":[72.40659000000002,30.86161],"type":"Point"}
}