{
  "type": "Feature",
  "properties": {
    "gn:admin1_code":"2",
    "gn:asciiname":"Zakozai",
    "gn:country_code":"PK",
    "gn:dem":1700,
    "gn:feature_class":"P",
    "gn:feature_code":"PPL",
    "gn:name":"Zakozai",
    "gn:population":0,
    "gn:timezone":"Asia/Karachi",
    "iso:country":"PK",
    "wof:name":"Zakozai",
    "wof:placetype":"locality"
},
  "geometry": {"coordinates":[69.50419000000001,30.85376],"type":"Point"}
}