{
  "type": "Feature",
  "properties": {
    "gn:admin1_code":"3.0",
    "gn:asciiname":"Sadullah Khan Kalle",
    "gn:country_code":"PK",
    "gn:dem":309,
    "gn:feature_class":"P",
    "gn:feature_code":"PPL",
    "gn:name":"Sadullah Khan Kalle",
    "gn:population":0,
    "gn:timezone":"Asia/Karachi",
    "iso:country":"PK",
    "wof:name":"Sadullah Khan Kalle",
    "wof:placetype":"locality"
},
  "geometry": {"coordinates":[71.85796999999999,34.07026],"type":"Point"}
}