{
  "type": "Feature",
  "properties": {
    "gn:admin1_code":"3",
    "gn:asciiname":"Jango",
    "gn:country_code":"PK",
    "gn:dem":853,
    "gn:feature_class":"P",
    "gn:feature_code":"PPL",
    "gn:name":"Jango",
    "gn:population":0,
    "gn:timezone":"Asia/Karachi",
    "iso:country":"PK",
    "name:ceb_x_preferred":[
        "Jango"
    ],
    "name:deu_x_preferred":[
        "Jango"
    ],
    "name:eng_x_preferred":[
        "Jango"
    ],
    "name:fra_x_preferred":[
        "Jango"
    ],
    "name:ita_x_preferred":[
        "Jango"
    ],
    "name:nld_x_preferred":[
        "Jango"
    ],
    "name:spa_x_preferred":[
        "Jango"
    ],
    "name:swe_x_preferred":[
        "Jango"
    ],
    "wof:name":"Jango",
    "wof:placetype":"locality"
},
  "geometry": {"coordinates":[72.06065,34.73041],"type":"Point"}
}