{
  "type": "Feature",
  "properties": {
    "gn:admin1_code":"3.0",
    "gn:asciiname":"Ragh",
    "gn:country_code":"PK",
    "gn:dem":2768,
    "gn:feature_class":"P",
    "gn:feature_code":"PPL",
    "gn:name":"Ragh",
    "gn:population":0,
    "gn:timezone":"Asia/Karachi",
    "iso:country":"PK",
    "wof:name":"Ragh",
    "wof:placetype":"locality"
},
  "geometry": {"coordinates":[72.17492,36.36511],"type":"Point"}
}