{
  "type": "Feature",
  "properties": {
    "gn:admin1_code":"1",
    "gn:asciiname":"Paipali",
    "gn:country_code":"PK",
    "gn:dem":652,
    "gn:feature_class":"P",
    "gn:feature_code":"PPL",
    "gn:name":"Paipali",
    "gn:population":0,
    "gn:timezone":"Asia/Karachi",
    "iso:country":"PK",
    "name:und_x_variant":[
        "Pipali Kabul Khel"
    ],
    "wof:name":"Paipali",
    "wof:placetype":"locality"
},
  "geometry": {"coordinates":[70.50561999999999,33.26729],"type":"Point"}
}