{
  "type": "Feature",
  "properties": {
    "gn:admin1_code":"4",
    "gn:asciiname":"Sadhanwali",
    "gn:country_code":"PK",
    "gn:dem":240,
    "gn:feature_class":"P",
    "gn:feature_code":"PPL",
    "gn:name":"Sadhanwali",
    "gn:population":0,
    "gn:timezone":"Asia/Karachi",
    "iso:country":"PK",
    "wof:name":"Sadhanwali",
    "wof:placetype":"locality"
},
  "geometry": {"coordinates":[74.74774000000002,32.2278],"type":"Point"}
}