{
  "type": "Feature",
  "properties": {
    "gn:admin1_code":"7.0",
    "gn:asciiname":"Tatwai",
    "gn:country_code":"PK",
    "gn:dem":3541,
    "gn:feature_class":"P",
    "gn:feature_code":"PPL",
    "gn:name":"Tatwai",
    "gn:population":0,
    "gn:timezone":"Asia/Karachi",
    "iso:country":"PK",
    "wof:name":"Tatwai",
    "wof:placetype":"locality"
},
  "geometry": {"coordinates":[74.79092,35.26324],"type":"Point"}
}