{
  "type": "Feature",
  "properties": {
    "gn:admin1_code":"3",
    "gn:asciiname":"Surapo Manzai",
    "gn:country_code":"PK",
    "gn:dem":1828,
    "gn:feature_class":"P",
    "gn:feature_code":"PPL",
    "gn:name":"Surapo Manzai",
    "gn:population":0,
    "gn:timezone":"Asia/Karachi",
    "iso:country":"PK",
    "name:eng_x_preferred":[
        "Sarapo Manzai"
    ],
    "wof:name":"Surapo Manzai",
    "wof:placetype":"locality"
},
  "geometry": {"coordinates":[71.74539,35.02244],"type":"Point"}
}