{
  "type": "Feature",
  "properties": {
    "gn:admin1_code":"4",
    "gn:asciiname":"Khhajiwala",
    "gn:country_code":"PK",
    "gn:dem":126,
    "gn:feature_class":"P",
    "gn:feature_code":"PPL",
    "gn:name":"Khhajiwala",
    "gn:population":0,
    "gn:timezone":"Asia/Karachi",
    "iso:country":"PK",
    "name:eng_x_preferred":[
        "Khajj\u012bw\u0101la"
    ],
    "wof:name":"Khhajiwala",
    "wof:placetype":"locality"
},
  "geometry": {"coordinates":[70.99531,30.20692],"type":"Point"}
}