{
  "type": "Feature",
  "properties": {
    "gn:admin1_code":"5.0",
    "gn:asciiname":"Khair Muhammad Dhahri",
    "gn:country_code":"PK",
    "gn:dem":28,
    "gn:feature_class":"P",
    "gn:feature_code":"PPL",
    "gn:name":"Khair Muhammad Dhahri",
    "gn:population":0,
    "gn:timezone":"Asia/Karachi",
    "iso:country":"PK",
    "wof:name":"Khair Muhammad Dhahri",
    "wof:placetype":"locality"
},
  "geometry": {"coordinates":[68.60986,26.19135],"type":"Point"}
}