{
  "type": "Feature",
  "properties": {
    "gn:admin1_code":"4",
    "gn:asciiname":"Saigid Nau",
    "gn:country_code":"PK",
    "gn:dem":193,
    "gn:feature_class":"P",
    "gn:feature_code":"PPL",
    "gn:name":"Saigid Nau",
    "gn:population":0,
    "gn:timezone":"Asia/Karachi",
    "iso:country":"PK",
    "name:und_x_variant":[
        "Saiyid Nau"
    ],
    "wof:name":"Saigid Nau",
    "wof:placetype":"locality"
},
  "geometry": {"coordinates":[73.12804,31.99672],"type":"Point"}
}