{
  "type": "Feature",
  "properties": {
    "gn:admin1_code":"04",
    "gn:asciiname":"Nouthain",
    "gn:country_code":"PK",
    "gn:dem":387,
    "gn:feature_class":"P",
    "gn:feature_code":"PPL",
    "gn:name":"Nouthain",
    "gn:population":0,
    "gn:timezone":"Asia/Karachi",
    "iso:country":"PK",
    "name:und_x_variant":[
        "Nauthen",
        "Nautheh Mirwal",
        "Nauth M\u012brw\u0101l",
        "Nouthain"
    ],
    "wof:name":"Nouthain",
    "wof:placetype":"locality"
},
  "geometry": {"coordinates":[72.30235999999999,33.48682],"type":"Point"}
}