{
  "type": "Feature",
  "properties": {
    "gn:admin1_code":"4",
    "gn:asciiname":"Kachhi",
    "gn:country_code":"PK",
    "gn:dem":93,
    "gn:feature_class":"P",
    "gn:feature_code":"PPL",
    "gn:name":"Kachhi",
    "gn:population":0,
    "gn:timezone":"Asia/Karachi",
    "iso:country":"PK",
    "wof:name":"Kachhi",
    "wof:placetype":"locality"
},
  "geometry": {"coordinates":[70.82639,28.94167],"type":"Point"}
}