{
  "type": "Feature",
  "properties": {
    "gn:admin1_code":"2.0",
    "gn:asciiname":"Surpan",
    "gn:country_code":"PK",
    "gn:dem":2463,
    "gn:feature_class":"P",
    "gn:feature_code":"PPL",
    "gn:name":"Surpan",
    "gn:population":0,
    "gn:timezone":"Asia/Karachi",
    "iso:country":"PK",
    "wof:name":"Surpan",
    "wof:placetype":"locality"
},
  "geometry": {"coordinates":[67.60623000000001,30.58849],"type":"Point"}
}