{
  "type": "Feature",
  "properties": {
    "gn:admin1_code":"2.0",
    "gn:asciiname":"Haji Jan",
    "gn:country_code":"PK",
    "gn:dem":1167,
    "gn:feature_class":"P",
    "gn:feature_code":"PPL",
    "gn:name":"Haji Jan",
    "gn:population":0,
    "gn:timezone":"Asia/Karachi",
    "iso:country":"PK",
    "wof:name":"Haji Jan",
    "wof:placetype":"locality"
},
  "geometry": {"coordinates":[69.87886999999999,29.96494],"type":"Point"}
}