{
  "type": "Feature",
  "properties": {
    "gn:admin1_code":"4.0",
    "gn:asciiname":"Alawal",
    "gn:country_code":"PK",
    "gn:dem":454,
    "gn:feature_class":"P",
    "gn:feature_code":"PPL",
    "gn:name":"Alawal",
    "gn:population":0,
    "gn:timezone":"Asia/Karachi",
    "iso:country":"PK",
    "name:eng_x_preferred":[
        "Alawal"
    ],
    "wof:name":"Alawal",
    "wof:placetype":"locality"
},
  "geometry": {"coordinates":[72.66576999999999,33.03311],"type":"Point"}
}