{
  "type": "Feature",
  "properties": {
    "gn:admin1_code":"4.0",
    "gn:asciiname":"Bhutto Nagar",
    "gn:country_code":"PK",
    "gn:dem":140,
    "gn:feature_class":"P",
    "gn:feature_code":"PPL",
    "gn:name":"Bhutto Nagar",
    "gn:population":0,
    "gn:timezone":"Asia/Karachi",
    "iso:country":"PK",
    "wof:name":"Bhutto Nagar",
    "wof:placetype":"locality"
},
  "geometry": {"coordinates":[71.83804000000001,30.84839],"type":"Point"}
}