{
  "type": "Feature",
  "properties": {
    "gn:admin1_code":"5.0",
    "gn:asciiname":"Hingorno",
    "gn:country_code":"PK",
    "gn:dem":17,
    "gn:feature_class":"P",
    "gn:feature_code":"PPL",
    "gn:name":"Hingorno",
    "gn:population":0,
    "gn:timezone":"Asia/Karachi",
    "iso:country":"PK",
    "name:und_x_variant":[
        "Hingorio",
        "Hingornee",
        "Hingorno"
    ],
    "wof:name":"Hingorno",
    "wof:placetype":"locality"
},
  "geometry": {"coordinates":[69.17655999999999,25.73452],"type":"Point"}
}