{
  "type": "Feature",
  "properties": {
    "gn:admin1_code":"03",
    "gn:asciiname":"Mian Khan",
    "gn:country_code":"PK",
    "gn:dem":507,
    "gn:feature_class":"P",
    "gn:feature_code":"PPL",
    "gn:name":"Mian Khan",
    "gn:population":0,
    "gn:timezone":"Asia/Karachi",
    "iso:country":"PK",
    "name:eng_x_preferred":[
        "Mian Khan"
    ],
    "wof:name":"Mian Khan",
    "wof:placetype":"locality"
},
  "geometry": {"coordinates":[72.15853,34.45488],"type":"Point"}
}