{
  "type": "Feature",
  "properties": {
    "gn:admin1_code":"3.0",
    "gn:asciiname":"Shirin Banda",
    "gn:country_code":"PK",
    "gn:dem":424,
    "gn:feature_class":"P",
    "gn:feature_code":"PPL",
    "gn:name":"Shirin Banda",
    "gn:population":0,
    "gn:timezone":"Asia/Karachi",
    "iso:country":"PK",
    "wof:name":"Shirin Banda",
    "wof:placetype":"locality"
},
  "geometry": {"coordinates":[72.04243000000002,34.43085],"type":"Point"}
}