{
  "type": "Feature",
  "properties": {
    "gn:admin1_code":"5",
    "gn:asciiname":"Goth Thru Khan Zaur",
    "gn:country_code":"PK",
    "gn:dem":15,
    "gn:feature_class":"P",
    "gn:feature_code":"PPL",
    "gn:name":"Goth Thru Khan Zaur",
    "gn:population":0,
    "gn:timezone":"Asia/Karachi",
    "iso:country":"PK",
    "name:und_x_variant":[
        "Th\u0101ro Kh\u0101n Z\u0101ur"
    ],
    "wof:name":"Goth Thru Khan Zaur",
    "wof:placetype":"locality"
},
  "geometry": {"coordinates":[68.51425999999999,25.00718],"type":"Point"}
}