{
  "type": "Feature",
  "properties": {
    "gn:admin1_code":"4.0",
    "gn:asciiname":"Khanitak",
    "gn:country_code":"PK",
    "gn:dem":1520,
    "gn:feature_class":"P",
    "gn:feature_code":"PPL",
    "gn:name":"Khanit\u0101k",
    "gn:population":0,
    "gn:timezone":"Asia/Karachi",
    "iso:country":"PK",
    "name:eng_x_preferred":[
        "Khanit\u0101k"
    ],
    "wof:name":"Khanitak",
    "wof:placetype":"locality"
},
  "geometry": {"coordinates":[73.41970000000001,33.94302],"type":"Point"}
}