{
  "type": "Feature",
  "properties": {
    "gn:admin1_code":"4.0",
    "gn:asciiname":"Dhok Soba Khan",
    "gn:country_code":"PK",
    "gn:dem":420,
    "gn:feature_class":"P",
    "gn:feature_code":"PPL",
    "gn:name":"Dhok Soba Khan",
    "gn:population":0,
    "gn:timezone":"Asia/Karachi",
    "iso:country":"PK",
    "wof:name":"Dhok Soba Khan",
    "wof:placetype":"locality"
},
  "geometry": {"coordinates":[72.36493,33.48741],"type":"Point"}
}