{
  "type": "Feature",
  "properties": {
    "gn:admin1_code":"4",
    "gn:asciiname":"Chak Twenty-seven Thal Development Authority",
    "gn:country_code":"PK",
    "gn:dem":174,
    "gn:feature_class":"P",
    "gn:feature_code":"PPL",
    "gn:name":"Chak Twenty-seven Thal Development Authority",
    "gn:population":0,
    "gn:timezone":"Asia/Karachi",
    "iso:country":"PK",
    "name:und_x_variant":[
        "Chak 27 TDA"
    ],
    "wof:name":"Chak Twenty-seven Thal Development Authority",
    "wof:placetype":"locality"
},
  "geometry": {"coordinates":[71.14664999999999,31.68308],"type":"Point"}
}