{
  "type": "Feature",
  "properties": {
    "gn:admin1_code":"4",
    "gn:asciiname":"Basti Shahwali",
    "gn:country_code":"PK",
    "gn:dem":132,
    "gn:feature_class":"P",
    "gn:feature_code":"PPL",
    "gn:name":"Basti Shahwali",
    "gn:population":0,
    "gn:timezone":"Asia/Karachi",
    "iso:country":"PK",
    "name:und_x_variant":[
        "Sh\u0101h ki Basti"
    ],
    "wof:name":"Basti Shahwali",
    "wof:placetype":"locality"
},
  "geometry": {"coordinates":[72.32007,29.65226],"type":"Point"}
}