{
  "type": "Feature",
  "properties": {
    "gn:admin1_code":"3.0",
    "gn:asciiname":"Sahibdad Khan",
    "gn:country_code":"PK",
    "gn:dem":300,
    "gn:feature_class":"P",
    "gn:feature_code":"PPL",
    "gn:name":"Sahibdad Khan",
    "gn:population":0,
    "gn:timezone":"Asia/Karachi",
    "iso:country":"PK",
    "wof:name":"Sahibdad Khan",
    "wof:placetype":"locality"
},
  "geometry": {"coordinates":[70.77498,32.77795],"type":"Point"}
}