{
  "type": "Feature",
  "properties": {
    "gn:admin1_code":"7.0",
    "gn:asciiname":"Yasho Shtag",
    "gn:country_code":"PK",
    "gn:dem":3547,
    "gn:feature_class":"P",
    "gn:feature_code":"PPL",
    "gn:name":"Yasho Shtag",
    "gn:population":0,
    "gn:timezone":"Asia/Karachi",
    "iso:country":"PK",
    "wof:name":"Yasho Shtag",
    "wof:placetype":"locality"
},
  "geometry": {"coordinates":[74.26514,36.83663],"type":"Point"}
}