{
  "type": "Feature",
  "properties": {
    "gn:admin1_code":"3",
    "gn:asciiname":"Chinai Banda",
    "gn:country_code":"PK",
    "gn:dem":2009,
    "gn:feature_class":"P",
    "gn:feature_code":"PPL",
    "gn:name":"Chinai Banda",
    "gn:population":0,
    "gn:timezone":"Asia/Karachi",
    "iso:country":"PK",
    "name:und_x_variant":[
        "Ch\u012bnapatai",
        "Chinai Banda"
    ],
    "wof:name":"Chinai Banda",
    "wof:placetype":"locality"
},
  "geometry": {"coordinates":[72.68025,34.90918],"type":"Point"}
}