{
  "type": "Feature",
  "properties": {
    "gn:admin1_code":"4.0",
    "gn:asciiname":"Dera Dhundu Ram",
    "gn:country_code":"PK",
    "gn:dem":214,
    "gn:feature_class":"P",
    "gn:feature_code":"PPL",
    "gn:name":"Dera Dhundu Ram",
    "gn:population":0,
    "gn:timezone":"Asia/Karachi",
    "iso:country":"PK",
    "name:und_x_variant":[
        "Dera Dandu Ram",
        "Dera Dhundu Ram"
    ],
    "wof:name":"Dera Dhundu Ram",
    "wof:placetype":"locality"
},
  "geometry": {"coordinates":[73.85438000000001,32.10296],"type":"Point"}
}