{
  "type": "Feature",
  "properties": {
    "gn:admin1_code":"4",
    "gn:asciiname":"Basti Gulanwala Khu",
    "gn:country_code":"PK",
    "gn:dem":95,
    "gn:feature_class":"P",
    "gn:feature_code":"PPL",
    "gn:name":"Basti Gulanwala Khu",
    "gn:population":0,
    "gn:timezone":"Asia/Karachi",
    "iso:country":"PK",
    "name:und_x_variant":[
        "Basti Gulinw\u0101la Khu",
        "Gulanw\u0101la",
        "Basti Gulanwala Khu"
    ],
    "wof:name":"Basti Gulanwala Khu",
    "wof:placetype":"locality"
},
  "geometry": {"coordinates":[70.43592,29.17745],"type":"Point"}
}