{
  "type": "Feature",
  "properties": {
    "gn:admin1_code":"4",
    "gn:asciiname":"Basti Ghazipur",
    "gn:country_code":"PK",
    "gn:dem":95,
    "gn:feature_class":"P",
    "gn:feature_code":"PPL",
    "gn:name":"Basti Ghazipur",
    "gn:population":0,
    "gn:timezone":"Asia/Karachi",
    "iso:country":"PK",
    "name:und_x_variant":[
        "Basti N\u0101ich",
        "Gh\u0101z\u012bpur"
    ],
    "wof:name":"Basti Ghazipur",
    "wof:placetype":"locality"
},
  "geometry": {"coordinates":[70.90966999999998,29.09291],"type":"Point"}
}