{
  "type": "Feature",
  "properties": {
    "gn:admin1_code":"01",
    "gn:asciiname":"Bad-i-Samur",
    "gn:country_code":"PK",
    "gn:dem":922,
    "gn:feature_class":"P",
    "gn:feature_code":"PPL",
    "gn:name":"Bad-i-Samur",
    "gn:population":0,
    "gn:timezone":"Asia/Karachi",
    "iso:country":"PK",
    "name:und_x_variant":[
        "Badisamur"
    ],
    "wof:name":"Bad-i-Samur",
    "wof:placetype":"locality"
},
  "geometry": {"coordinates":[71.46504,34.74816],"type":"Point"}
}