{
  "type": "Feature",
  "properties": {
    "gn:admin1_code":"04",
    "gn:asciiname":"Kotla Mughlan",
    "gn:country_code":"PK",
    "gn:dem":109,
    "gn:feature_class":"P",
    "gn:feature_code":"PPL",
    "gn:name":"Kotla Mughlan",
    "gn:population":0,
    "gn:timezone":"Asia/Karachi",
    "iso:country":"PK",
    "name:und_x_variant":[
        "Kotla Mughlin",
        "Kotla Mughal\u0101n",
        "Kotla Mughlan"
    ],
    "wof:name":"Kotla Mughlan",
    "wof:placetype":"locality"
},
  "geometry": {"coordinates":[70.60755999999998,29.54828],"type":"Point"}
}