{
  "type": "Feature",
  "properties": {
    "gn:admin1_code":"3",
    "gn:asciiname":"Kotah",
    "gn:country_code":"PK",
    "gn:dem":772,
    "gn:feature_class":"P",
    "gn:feature_code":"PPL",
    "gn:name":"Kotah",
    "gn:population":0,
    "gn:timezone":"Asia/Karachi",
    "iso:country":"PK",
    "name:eng_x_preferred":[
        "Kotah"
    ],
    "wof:name":"Kotah",
    "wof:placetype":"locality"
},
  "geometry": {"coordinates":[72.15252,34.65095],"type":"Point"}
}