{
  "type": "Feature",
  "properties": {
    "gn:admin1_code":"4.0",
    "gn:asciiname":"Jeistiwala",
    "gn:country_code":"PK",
    "gn:dem":181,
    "gn:feature_class":"P",
    "gn:feature_code":"PPL",
    "gn:name":"Jeistiwala",
    "gn:population":0,
    "gn:timezone":"Asia/Karachi",
    "iso:country":"PK",
    "name:und_x_variant":[
        "Chak 74 N",
        "Jeistiwala",
        "Chak Seventy-four North"
    ],
    "wof:name":"Jeistiwala",
    "wof:placetype":"locality"
},
  "geometry": {"coordinates":[72.52930000000001,32.14125],"type":"Point"}
}