{
  "type": "Feature",
  "properties": {
    "gn:admin1_code":"4.0",
    "gn:asciiname":"Basti Haji Said Muhammad",
    "gn:country_code":"PK",
    "gn:dem":89,
    "gn:feature_class":"P",
    "gn:feature_code":"PPL",
    "gn:name":"Basti H\u0101ji Said Muhammad",
    "gn:population":0,
    "gn:timezone":"Asia/Karachi",
    "iso:country":"PK",
    "name:urd_x_preferred":[
        "Basti H\u0101ji Said Muhammad"
    ],
    "wof:name":"Basti Haji Said Muhammad",
    "wof:placetype":"locality"
},
  "geometry": {"coordinates":[70.67361,28.76111],"type":"Point"}
}