{
  "type": "Feature",
  "properties": {
    "gn:admin1_code":"3",
    "gn:asciiname":"Taghan",
    "gn:country_code":"PK",
    "gn:dem":1137,
    "gn:feature_class":"P",
    "gn:feature_code":"PPL",
    "gn:name":"Taghan",
    "gn:population":0,
    "gn:timezone":"Asia/Karachi",
    "iso:country":"PK",
    "name:ara_x_preferred":[
        "\u062a\u0627\u063a\u0627\u0646"
    ],
    "name:ceb_x_preferred":[
        "\u0162\u0101q\u0101n"
    ],
    "name:fas_x_preferred":[
        "\u062a\u0627\u063a\u0627\u0646"
    ],
    "name:swe_x_preferred":[
        "\u0162\u0101q\u0101n"
    ],
    "wof:name":"Taghan",
    "wof:placetype":"locality"
},
  "geometry": {"coordinates":[72.49453000000003,34.81638],"type":"Point"}
}