{
  "type": "Feature",
  "properties": {
    "gn:admin1_code":"3.0",
    "gn:asciiname":"Aorgarh Gali",
    "gn:country_code":"PK",
    "gn:dem":1599,
    "gn:feature_class":"P",
    "gn:feature_code":"PPL",
    "gn:name":"Aorgarh Gali",
    "gn:population":0,
    "gn:timezone":"Asia/Karachi",
    "iso:country":"PK",
    "wof:name":"Aorgarh Gali",
    "wof:placetype":"locality"
},
  "geometry": {"coordinates":[73.08077,34.4777],"type":"Point"}
}