{
  "type": "Feature",
  "properties": {
    "gn:admin1_code":"6",
    "gn:asciiname":"March Kot",
    "gn:country_code":"PK",
    "gn:dem":1721,
    "gn:feature_class":"P",
    "gn:feature_code":"PPL",
    "gn:name":"March Kot",
    "gn:population":0,
    "gn:timezone":"Asia/Karachi",
    "iso:country":"PK",
    "name:und_x_variant":[
        "M\u0101roh Kot",
        "M\u0101rch Kot"
    ],
    "wof:name":"March Kot",
    "wof:placetype":"locality"
},
  "geometry": {"coordinates":[73.97060999999999,33.88417],"type":"Point"}
}