{
  "type": "Feature",
  "properties": {
    "gn:admin1_code":"1.0",
    "gn:asciiname":"Rahim Khan Banda",
    "gn:country_code":"PK",
    "gn:dem":559,
    "gn:feature_class":"P",
    "gn:feature_code":"PPL",
    "gn:name":"Rahim Khan Banda",
    "gn:population":0,
    "gn:timezone":"Asia/Karachi",
    "iso:country":"PK",
    "wof:name":"Rahim Khan Banda",
    "wof:placetype":"locality"
},
  "geometry": {"coordinates":[71.57885999999998,34.51712],"type":"Point"}
}