{
  "type": "Feature",
  "properties": {
    "gn:admin1_code":"3",
    "gn:asciiname":"Saprakai",
    "gn:country_code":"PK",
    "gn:dem":1718,
    "gn:feature_class":"P",
    "gn:feature_code":"PPL",
    "gn:name":"Saprakai",
    "gn:population":0,
    "gn:timezone":"Asia/Karachi",
    "iso:country":"PK",
    "name:eng_x_preferred":[
        "Chupr\u0101kai"
    ],
    "wof:name":"Saprakai",
    "wof:placetype":"locality"
},
  "geometry": {"coordinates":[71.70665,35.00812],"type":"Point"}
}