{
  "type": "Feature",
  "properties": {
    "gn:admin1_code":"4.0",
    "gn:asciiname":"Basti Choraian",
    "gn:country_code":"PK",
    "gn:dem":100,
    "gn:feature_class":"P",
    "gn:feature_code":"PPL",
    "gn:name":"Basti Choraian",
    "gn:population":0,
    "gn:timezone":"Asia/Karachi",
    "iso:country":"PK",
    "name:und_x_variant":[
        "Basti Chur\u0101i\u0101n"
    ],
    "wof:name":"Basti Choraian",
    "wof:placetype":"locality"
},
  "geometry": {"coordinates":[70.80704,29.29838],"type":"Point"}
}