{
  "type": "Feature",
  "properties": {
    "gn:admin1_code":"4",
    "gn:asciiname":"Dera Sabedar Muhammad Fazil",
    "gn:country_code":"PK",
    "gn:dem":167,
    "gn:feature_class":"P",
    "gn:feature_code":"PPL",
    "gn:name":"Dera Sabedar Muhammad Fazil",
    "gn:population":0,
    "gn:timezone":"Asia/Karachi",
    "iso:country":"PK",
    "wof:name":"Dera Sabedar Muhammad Fazil",
    "wof:placetype":"locality"
},
  "geometry": {"coordinates":[71.46143000000002,31.44151],"type":"Point"}
}