{
  "type": "Feature",
  "properties": {
    "gn:admin1_code":"2.0",
    "gn:asciiname":"Goth Taj Muhammad Khosa",
    "gn:country_code":"PK",
    "gn:dem":58,
    "gn:feature_class":"P",
    "gn:feature_code":"PPL",
    "gn:name":"Goth Taj Muhammad Khosa",
    "gn:population":0,
    "gn:timezone":"Asia/Karachi",
    "iso:country":"PK",
    "wof:name":"Goth Taj Muhammad Khosa",
    "wof:placetype":"locality"
},
  "geometry": {"coordinates":[68.57668000000001,28.43875],"type":"Point"}
}