{
  "type": "Feature",
  "properties": {
    "gn:admin1_code":"03",
    "gn:asciiname":"Shahkahai",
    "gn:country_code":"PK",
    "gn:dem":1339,
    "gn:feature_class":"P",
    "gn:feature_code":"PPL",
    "gn:name":"Shahkahai",
    "gn:population":0,
    "gn:timezone":"Asia/Karachi",
    "iso:country":"PK",
    "wof:name":"Shahkahai",
    "wof:placetype":"locality"
},
  "geometry": {"coordinates":[71.97896,34.9778],"type":"Point"}
}