{
  "type": "Feature",
  "properties": {
    "gn:admin1_code":"4.0",
    "gn:asciiname":"Chak Twelve-Gugera Distributary",
    "gn:country_code":"PK",
    "gn:dem":180,
    "gn:feature_class":"P",
    "gn:feature_code":"PPL",
    "gn:name":"Chak Twelve-Gugera Distributary",
    "gn:population":0,
    "gn:timezone":"Asia/Karachi",
    "iso:country":"PK",
    "name:und_x_variant":[
        "Fauji\u0101nw\u0101la"
    ],
    "wof:name":"Chak Twelve-Gugera Distributary",
    "wof:placetype":"locality"
},
  "geometry": {"coordinates":[73.50556,30.98869],"type":"Point"}
}