{
  "type": "Feature",
  "properties": {
    "gn:admin1_code":"4",
    "gn:asciiname":"Chak Ninety-eight -Ten Right",
    "gn:country_code":"PK",
    "gn:dem":130,
    "gn:feature_class":"P",
    "gn:feature_code":"PPL",
    "gn:name":"Chak Ninety-eight -Ten Right",
    "gn:population":0,
    "gn:timezone":"Asia/Karachi",
    "iso:country":"PK",
    "wof:name":"Chak Ninety-eight -Ten Right",
    "wof:placetype":"locality"
},
  "geometry": {"coordinates":[71.92586999999997,30.13078],"type":"Point"}
}