{
  "type": "Feature",
  "properties": {
    "gn:admin1_code":"7.0",
    "gn:asciiname":"Bal Brok",
    "gn:country_code":"PK",
    "gn:dem":3032,
    "gn:feature_class":"P",
    "gn:feature_code":"PPL",
    "gn:name":"Bal Brok",
    "gn:population":0,
    "gn:timezone":"Asia/Karachi",
    "iso:country":"PK",
    "wof:name":"Bal Brok",
    "wof:placetype":"locality"
},
  "geometry": {"coordinates":[75.38115999999999,35.72016],"type":"Point"}
}