{
  "type": "Feature",
  "properties": {
    "gn:admin1_code":"5",
    "gn:asciiname":"Bhudho Shaikh",
    "gn:country_code":"PK",
    "gn:dem":52,
    "gn:feature_class":"P",
    "gn:feature_code":"PPL",
    "gn:name":"Bhudho Shaikh",
    "gn:population":0,
    "gn:timezone":"Asia/Karachi",
    "iso:country":"PK",
    "name:und_x_variant":[
        "Budha Shaikh"
    ],
    "wof:name":"Bhudho Shaikh",
    "wof:placetype":"locality"
},
  "geometry": {"coordinates":[68.17045,27.5491],"type":"Point"}
}