{
  "type": "Feature",
  "properties": {
    "gn:admin1_code":"2.0",
    "gn:asciiname":"Hakkili Kalag",
    "gn:country_code":"PK",
    "gn:dem":545,
    "gn:feature_class":"P",
    "gn:feature_code":"PPL",
    "gn:name":"Hakkili Kalag",
    "gn:population":0,
    "gn:timezone":"Asia/Karachi",
    "iso:country":"PK",
    "wof:name":"Hakkili Kalag",
    "wof:placetype":"locality"
},
  "geometry": {"coordinates":[63.70406,26.28554],"type":"Point"}
}