{
  "type": "Feature",
  "properties": {
    "gn:admin1_code":"4",
    "gn:asciiname":"Nurewala",
    "gn:country_code":"PK",
    "gn:dem":162,
    "gn:feature_class":"P",
    "gn:feature_code":"PPL",
    "gn:name":"Nurewala",
    "gn:population":0,
    "gn:timezone":"Asia/Karachi",
    "iso:country":"PK",
    "wof:name":"Nurewala",
    "wof:placetype":"locality"
},
  "geometry": {"coordinates":[72.71666999999999,30.68056],"type":"Point"}
}