{
  "type": "Feature",
  "properties": {
    "gn:admin1_code":"3.0",
    "gn:asciiname":"Banda Lowarge",
    "gn:country_code":"PK",
    "gn:dem":589,
    "gn:feature_class":"P",
    "gn:feature_code":"PPL",
    "gn:name":"Banda Lowarge",
    "gn:population":0,
    "gn:timezone":"Asia/Karachi",
    "iso:country":"PK",
    "wof:name":"Banda Lowarge",
    "wof:placetype":"locality"
},
  "geometry": {"coordinates":[71.31135999999999,33.25449],"type":"Point"}
}