{
  "type": "Feature",
  "properties": {
    "gn:admin1_code":"4",
    "gn:asciiname":"Kot Bela",
    "gn:country_code":"PK",
    "gn:dem":241,
    "gn:feature_class":"P",
    "gn:feature_code":"PPL",
    "gn:name":"Kot Bela",
    "gn:population":0,
    "gn:timezone":"Asia/Karachi",
    "iso:country":"PK",
    "wof:name":"Kot Bela",
    "wof:placetype":"locality"
},
  "geometry": {"coordinates":[74.03761999999998,32.63225],"type":"Point"}
}