{
  "type": "Feature",
  "properties": {
    "gn:admin1_code":"4",
    "gn:asciiname":"Lodhran",
    "gn:country_code":"PK",
    "gn:dem":114,
    "gn:feature_class":"P",
    "gn:feature_code":"PPL",
    "gn:name":"Lodhran",
    "gn:population":0,
    "gn:timezone":"Asia/Karachi",
    "iso:country":"PK",
    "name:eng_x_preferred":[
        "Lodhran"
    ],
    "name:urd_x_preferred":[
        "\u0644\u0648\u062f\u06be\u0631\u0627\u06ba"
    ],
    "wof:name":"Lodhran",
    "wof:placetype":"locality"
},
  "geometry": {"coordinates":[71.55,29.25694],"type":"Point"}
}