{
  "type": "Feature",
  "properties": {
    "gn:admin1_code":"4.0",
    "gn:asciiname":"Sher Dastwali",
    "gn:country_code":"PK",
    "gn:dem":383,
    "gn:feature_class":"P",
    "gn:feature_code":"PPL",
    "gn:name":"Sher Dastwali",
    "gn:population":0,
    "gn:timezone":"Asia/Karachi",
    "iso:country":"PK",
    "wof:name":"Sher Dastwali",
    "wof:placetype":"locality"
},
  "geometry": {"coordinates":[71.99476,32.81309],"type":"Point"}
}