{
  "type": "Feature",
  "properties": {
    "gn:admin1_code":"2.0",
    "gn:asciiname":"Kili Nobat",
    "gn:country_code":"PK",
    "gn:dem":1071,
    "gn:feature_class":"P",
    "gn:feature_code":"PPL",
    "gn:name":"Kili Nobat",
    "gn:population":0,
    "gn:timezone":"Asia/Karachi",
    "iso:country":"PK",
    "name:und_x_variant":[
        "Shahr Nobat"
    ],
    "wof:name":"Kili Nobat",
    "wof:placetype":"locality"
},
  "geometry": {"coordinates":[66.78215,27.7023],"type":"Point"}
}