{
  "type": "Feature",
  "properties": {
    "gn:admin1_code":"05",
    "gn:asciiname":"Goth Pathano Lank",
    "gn:country_code":"PK",
    "gn:dem":54,
    "gn:feature_class":"P",
    "gn:feature_code":"PPL",
    "gn:name":"Goth Pathano Lank",
    "gn:population":0,
    "gn:timezone":"Asia/Karachi",
    "iso:country":"PK",
    "name:und_x_variant":[
        "L\u0101rak Path\u0101no"
    ],
    "wof:name":"Goth Pathano Lank",
    "wof:placetype":"locality"
},
  "geometry": {"coordinates":[68.44765,27.30046],"type":"Point"}
}