{
  "type": "Feature",
  "properties": {
    "gn:admin1_code":"6",
    "gn:asciiname":"Muftian",
    "gn:country_code":"PK",
    "gn:dem":242,
    "gn:feature_class":"P",
    "gn:feature_code":"PPL",
    "gn:name":"Muftian",
    "gn:population":0,
    "gn:timezone":"Asia/Karachi",
    "iso:country":"PK",
    "name:urd_x_preferred":[
        "\u0645\u0641\u062a\u06cc\u0627\u06ba"
    ],
    "wof:name":"Muftian",
    "wof:placetype":"locality"
},
  "geometry": {"coordinates":[73.83010999999998,33.02162],"type":"Point"}
}