{
  "type": "Feature",
  "properties": {
    "gn:admin1_code":"5.0",
    "gn:asciiname":"Mula Bakhsh Sheikh",
    "gn:country_code":"PK",
    "gn:dem":56,
    "gn:feature_class":"P",
    "gn:feature_code":"PPL",
    "gn:name":"Mula Bakhsh Sheikh",
    "gn:population":0,
    "gn:timezone":"Asia/Karachi",
    "iso:country":"PK",
    "name:eng_x_preferred":[
        "Mula Bakhsh Sheikh"
    ],
    "wof:name":"Mula Bakhsh Sheikh",
    "wof:placetype":"locality"
},
  "geometry": {"coordinates":[68.72511999999999,27.45737],"type":"Point"}
}