{
  "type": "Feature",
  "properties": {
    "gn:admin1_code":"4",
    "gn:asciiname":"Basti Nur Ahmadwali",
    "gn:country_code":"PK",
    "gn:dem":164,
    "gn:feature_class":"P",
    "gn:feature_code":"PPL",
    "gn:name":"Basti Nur Ahmadwali",
    "gn:population":0,
    "gn:timezone":"Asia/Karachi",
    "iso:country":"PK",
    "name:und_x_variant":[
        "Jhok Nur Ahmad",
        "Jhok N\u016br Ahmadw\u0101li",
        "Basti Nur Ahmadwali"
    ],
    "wof:name":"Basti Nur Ahmadwali",
    "wof:placetype":"locality"
},
  "geometry": {"coordinates":[70.70625,31.13031],"type":"Point"}
}