{
  "type": "Feature",
  "properties": {
    "gn:admin1_code":"2",
    "gn:asciiname":"Goth Bar Khan",
    "gn:country_code":"PK",
    "gn:dem":57,
    "gn:feature_class":"P",
    "gn:feature_code":"PPL",
    "gn:name":"Goth Bar Khan",
    "gn:population":0,
    "gn:timezone":"Asia/Karachi",
    "iso:country":"PK",
    "wof:name":"Goth Bar Khan",
    "wof:placetype":"locality"
},
  "geometry": {"coordinates":[68.36333,28.33233],"type":"Point"}
}