{
  "type": "Feature",
  "properties": {
    "gn:admin1_code":"6.0",
    "gn:asciiname":"Magra",
    "gn:country_code":"PK",
    "gn:dem":2030,
    "gn:feature_class":"P",
    "gn:feature_code":"PPL",
    "gn:name":"Magra",
    "gn:population":0,
    "gn:timezone":"Asia/Karachi",
    "iso:country":"PK",
    "wof:name":"Magra",
    "wof:placetype":"locality"
},
  "geometry": {"coordinates":[73.574,34.54988],"type":"Point"}
}