{
  "type": "Feature",
  "properties": {
    "gn:admin1_code":"2.0",
    "gn:asciiname":"Goth Rasul Bakhsh",
    "gn:country_code":"PK",
    "gn:dem":1060,
    "gn:feature_class":"P",
    "gn:feature_code":"PPL",
    "gn:name":"Goth Rasul Bakhsh",
    "gn:population":0,
    "gn:timezone":"Asia/Karachi",
    "iso:country":"PK",
    "wof:name":"Goth Rasul Bakhsh",
    "wof:placetype":"locality"
},
  "geometry": {"coordinates":[66.32746999999999,26.8499],"type":"Point"}
}