{
  "type": "Feature",
  "properties": {
    "gn:admin1_code":"2.0",
    "gn:asciiname":"Makhalu",
    "gn:country_code":"PK",
    "gn:dem":881,
    "gn:feature_class":"P",
    "gn:feature_code":"PPL",
    "gn:name":"Makhalu",
    "gn:population":0,
    "gn:timezone":"Asia/Karachi",
    "iso:country":"PK",
    "wof:name":"Makhalu",
    "wof:placetype":"locality"
},
  "geometry": {"coordinates":[66.92633000000001,27.95864000000001],"type":"Point"}
}