{
  "type": "Feature",
  "properties": {
    "gn:admin1_code":"3.0",
    "gn:asciiname":"Chhapar",
    "gn:country_code":"PK",
    "gn:dem":818,
    "gn:feature_class":"P",
    "gn:feature_code":"PPL",
    "gn:name":"Chhapar",
    "gn:population":0,
    "gn:timezone":"Asia/Karachi",
    "iso:country":"PK",
    "wof:name":"Chhapar",
    "wof:placetype":"locality"
},
  "geometry": {"coordinates":[73.02495,33.92333],"type":"Point"}
}