{
  "type": "Feature",
  "properties": {
    "gn:admin1_code":"6.0",
    "gn:asciiname":"Katlan",
    "gn:country_code":"PK",
    "gn:dem":2369,
    "gn:feature_class":"P",
    "gn:feature_code":"PPL",
    "gn:name":"Katlan",
    "gn:population":0,
    "gn:timezone":"Asia/Karachi",
    "iso:country":"PK",
    "wof:name":"Katlan",
    "wof:placetype":"locality"
},
  "geometry": {"coordinates":[74.13593,33.93978],"type":"Point"}
}