{
  "type": "Feature",
  "properties": {
    "gn:admin1_code":"4.0",
    "gn:asciiname":"Ratri",
    "gn:country_code":"PK",
    "gn:dem":425,
    "gn:feature_class":"P",
    "gn:feature_code":"PPL",
    "gn:name":"Ratri",
    "gn:population":0,
    "gn:timezone":"Asia/Karachi",
    "iso:country":"PK",
    "name:jpn_x_preferred":[
        "\u30e9\u30fc\u30c8\u30ea\u30fc"
    ],
    "name:nno_x_preferred":[
        "Ratri"
    ],
    "name:pan_x_preferred":[
        "\u0a30\u0a3e\u0a24\u0a4d\u0a30\u0a40"
    ],
    "name:pol_x_preferred":[
        "Ratri"
    ],
    "name:swe_x_preferred":[
        "Ratri"
    ],
    "name:zho_x_preferred":[
        "\u62ff\u5fb7\u5229"
    ],
    "wof:name":"Ratri",
    "wof:placetype":"locality"
},
  "geometry": {"coordinates":[73.00295,33.29665],"type":"Point"}
}