{
  "type": "Feature",
  "properties": {
    "gn:admin1_code":"4.0",
    "gn:asciiname":"Bathuwala",
    "gn:country_code":"PK",
    "gn:dem":110,
    "gn:feature_class":"P",
    "gn:feature_code":"PPL",
    "gn:name":"Bathuwala",
    "gn:population":0,
    "gn:timezone":"Asia/Karachi",
    "iso:country":"PK",
    "name:und_x_variant":[
        "Bathuw\u0101la"
    ],
    "wof:name":"Bathuwala",
    "wof:placetype":"locality"
},
  "geometry": {"coordinates":[71.32295000000001,29.72336],"type":"Point"}
}