{
  "type": "Feature",
  "properties": {
    "gn:admin1_code":"2.0",
    "gn:asciiname":"Malik Inam",
    "gn:country_code":"PK",
    "gn:dem":1455,
    "gn:feature_class":"P",
    "gn:feature_code":"PPL",
    "gn:name":"Malik Inam",
    "gn:population":0,
    "gn:timezone":"Asia/Karachi",
    "iso:country":"PK",
    "wof:name":"Malik Inam",
    "wof:placetype":"locality"
},
  "geometry": {"coordinates":[66.62529000000001,30.56647],"type":"Point"}
}