{
  "type": "Feature",
  "properties": {
    "gn:admin1_code":"4.0",
    "gn:asciiname":"Samanabad",
    "gn:country_code":"PK",
    "gn:dem":213,
    "gn:feature_class":"P",
    "gn:feature_code":"PPL",
    "gn:name":"Samanabad",
    "gn:population":0,
    "gn:timezone":"Asia/Karachi",
    "iso:country":"PK",
    "name:fas_x_preferred":[
        "\u0633\u0645\u0646\u200c\u0622\u0628\u0627\u062f"
    ],
    "name:urd_x_preferred":[
        "\u0633\u0645\u0646 \u0622\u0628\u0627\u062f"
    ],
    "wof:name":"Samanabad",
    "wof:placetype":"locality"
},
  "geometry": {"coordinates":[74.07303,31.85167],"type":"Point"}
}