{
  "type": "Feature",
  "properties": {
    "gn:admin1_code":"3",
    "gn:asciiname":"Londai",
    "gn:country_code":"PK",
    "gn:dem":2397,
    "gn:feature_class":"P",
    "gn:feature_code":"PPL",
    "gn:name":"Londai",
    "gn:population":0,
    "gn:timezone":"Asia/Karachi",
    "iso:country":"PK",
    "name:und_x_variant":[
        "Landai"
    ],
    "wof:name":"Londai",
    "wof:placetype":"locality"
},
  "geometry": {"coordinates":[72.83319,34.82495],"type":"Point"}
}