{
  "type": "Feature",
  "properties": {
    "gn:admin1_code":"05",
    "gn:asciiname":"Samun Wah",
    "gn:cc2":"PK",
    "gn:country_code":"PK",
    "gn:dem":67,
    "gn:feature_class":"P",
    "gn:feature_code":"PPL",
    "gn:name":"Samun Wah",
    "gn:population":0,
    "gn:timezone":"Asia/Karachi",
    "iso:country":"PK",
    "name:und_x_variant":[
        "Samowah",
        "Samun Wah"
    ],
    "wof:name":"Samun Wah",
    "wof:placetype":"locality"
},
  "geometry": {"coordinates":[69.36667,27.91667],"type":"Point"}
}