{
  "type": "Feature",
  "properties": {
    "gn:admin1_code":"4",
    "gn:asciiname":"Adamra",
    "gn:country_code":"PK",
    "gn:dem":244,
    "gn:feature_class":"P",
    "gn:feature_code":"PPL",
    "gn:name":"Adamra",
    "gn:population":0,
    "gn:timezone":"Asia/Karachi",
    "iso:country":"PK",
    "name:und_x_variant":[
        "\u0100damdar\u0101z"
    ],
    "wof:name":"Adamra",
    "wof:placetype":"locality"
},
  "geometry": {"coordinates":[74.47914,32.39852],"type":"Point"}
}