{
  "type": "Feature",
  "properties": {
    "gn:admin1_code":"02",
    "gn:asciiname":"Saiyid Salar Ziarat",
    "gn:country_code":"PK",
    "gn:dem":848,
    "gn:feature_class":"P",
    "gn:feature_code":"PPL",
    "gn:name":"Saiyid S\u0101l\u0101r Zi\u0101rat",
    "gn:population":0,
    "gn:timezone":"Asia/Karachi",
    "iso:country":"PK",
    "wof:name":"Saiyid Salar Ziarat",
    "wof:placetype":"locality"
},
  "geometry": {"coordinates":[64.71666999999999,29.21667],"type":"Point"}
}