{
  "type": "Feature",
  "properties": {
    "gn:admin1_code":"03",
    "gn:asciiname":"Mangar Khel",
    "gn:country_code":"PK",
    "gn:dem":920,
    "gn:feature_class":"P",
    "gn:feature_code":"PPL",
    "gn:name":"Mangar Khel",
    "gn:population":0,
    "gn:timezone":"Asia/Karachi",
    "iso:country":"PK",
    "wof:name":"Mangar Khel",
    "wof:placetype":"locality"
},
  "geometry": {"coordinates":[71.28115,33.12051],"type":"Point"}
}