{
  "type": "Feature",
  "properties": {
    "gn:admin1_code":"5",
    "gn:asciiname":"Goth Musa Jamali",
    "gn:country_code":"PK",
    "gn:dem":50,
    "gn:feature_class":"P",
    "gn:feature_code":"PPL",
    "gn:name":"Goth Musa Jamali",
    "gn:population":0,
    "gn:timezone":"Asia/Karachi",
    "iso:country":"PK",
    "name:und_x_variant":[
        "Goth M\u016bsa Kh\u0101n",
        "Goth H\u0101ji Khair Muhammad"
    ],
    "wof:name":"Goth Musa Jamali",
    "wof:placetype":"locality"
},
  "geometry": {"coordinates":[67.43318000000001,26.64773],"type":"Point"}
}