{
  "type": "Feature",
  "properties": {
    "gn:admin1_code":"5.0",
    "gn:asciiname":"Goth Dodhi Halepota",
    "gn:country_code":"PK",
    "gn:dem":50,
    "gn:feature_class":"P",
    "gn:feature_code":"PPL",
    "gn:name":"Goth Dodhi Halepota",
    "gn:population":0,
    "gn:timezone":"Asia/Karachi",
    "iso:country":"PK",
    "name:und_x_variant":[
        "Goth Dadhi Halepota"
    ],
    "wof:name":"Goth Dodhi Halepota",
    "wof:placetype":"locality"
},
  "geometry": {"coordinates":[68.41988000000001,26.97375],"type":"Point"}
}