{
  "type": "Feature",
  "properties": {
    "gn:admin1_code":"4.0",
    "gn:asciiname":"Ilyaspur",
    "gn:country_code":"PK",
    "gn:dem":250,
    "gn:feature_class":"P",
    "gn:feature_code":"PPL",
    "gn:name":"Ilyaspur",
    "gn:population":0,
    "gn:timezone":"Asia/Karachi",
    "iso:country":"PK",
    "name:und_x_variant":[
        "Ili\u0101spur"
    ],
    "wof:name":"Ilyaspur",
    "wof:placetype":"locality"
},
  "geometry": {"coordinates":[75.23770999999998,32.15731],"type":"Point"}
}