{
  "type": "Feature",
  "properties": {
    "gn:admin1_code":"4.0",
    "gn:asciiname":"Daki Ghulam Khanwala",
    "gn:country_code":"PK",
    "gn:dem":192,
    "gn:feature_class":"P",
    "gn:feature_code":"PPL",
    "gn:name":"Daki Ghulam Khanwala",
    "gn:population":0,
    "gn:timezone":"Asia/Karachi",
    "iso:country":"PK",
    "wof:name":"Daki Ghulam Khanwala",
    "wof:placetype":"locality"
},
  "geometry": {"coordinates":[71.5106,32.06477],"type":"Point"}
}