{
  "type": "Feature",
  "properties": {
    "gn:admin1_code":"04",
    "gn:asciiname":"Tibbi Mahl",
    "gn:country_code":"PK",
    "gn:dem":230,
    "gn:feature_class":"P",
    "gn:feature_code":"PPL",
    "gn:name":"Tibbi Mahl",
    "gn:population":0,
    "gn:timezone":"Asia/Karachi",
    "iso:country":"PK",
    "name:und_x_variant":[
        "Tibbi Mahal",
        "Tibbi Mahl",
        "Tibbi Mahel"
    ],
    "wof:name":"Tibbi Mahl",
    "wof:placetype":"locality"
},
  "geometry": {"coordinates":[73.71972,32.72058],"type":"Point"}
}