{
  "type": "Feature",
  "properties": {
    "gn:admin1_code":"2.0",
    "gn:asciiname":"Bakhtiarzai",
    "gn:country_code":"PK",
    "gn:dem":1500,
    "gn:feature_class":"P",
    "gn:feature_code":"PPL",
    "gn:name":"Bakhtiarzai",
    "gn:population":0,
    "gn:timezone":"Asia/Karachi",
    "iso:country":"PK",
    "name:und_x_variant":[
        "Bakhtarzai"
    ],
    "wof:name":"Bakhtiarzai",
    "wof:placetype":"locality"
},
  "geometry": {"coordinates":[66.95761,30.69677],"type":"Point"}
}