{
  "type": "Feature",
  "properties": {
    "gn:admin1_code":"4.0",
    "gn:asciiname":"Chak One Hundred Fourteen North Panjnad",
    "gn:country_code":"PK",
    "gn:dem":91,
    "gn:feature_class":"P",
    "gn:feature_code":"PPL",
    "gn:name":"Chak One Hundred Fourteen North Panjnad",
    "gn:population":0,
    "gn:timezone":"Asia/Karachi",
    "iso:country":"PK",
    "name:und_x_variant":[
        "Chak One Hundred Fourteen NP"
    ],
    "wof:name":"Chak One Hundred Fourteen North Panjnad",
    "wof:placetype":"locality"
},
  "geometry": {"coordinates":[70.68300000000001,28.71419],"type":"Point"}
}