{
  "type": "Feature",
  "properties": {
    "gn:admin1_code":"5",
    "gn:asciiname":"Goth Rawal Chandio",
    "gn:country_code":"PK",
    "gn:dem":37,
    "gn:feature_class":"P",
    "gn:feature_code":"PPL",
    "gn:name":"Goth Rawal Chandio",
    "gn:population":0,
    "gn:timezone":"Asia/Karachi",
    "iso:country":"PK",
    "wof:name":"Goth Rawal Chandio",
    "wof:placetype":"locality"
},
  "geometry": {"coordinates":[68.08781999999999,26.33552],"type":"Point"}
}