{
  "type": "Feature",
  "properties": {
    "gn:admin1_code":"3.0",
    "gn:asciiname":"Surmul",
    "gn:country_code":"PK",
    "gn:dem":999,
    "gn:feature_class":"P",
    "gn:feature_code":"PPL",
    "gn:name":"Surmul",
    "gn:population":0,
    "gn:timezone":"Asia/Karachi",
    "iso:country":"PK",
    "wof:name":"Surmul",
    "wof:placetype":"locality"
},
  "geometry": {"coordinates":[72.83613000000003,34.55106],"type":"Point"}
}