{
  "type": "Feature",
  "properties": {
    "gn:admin1_code":"4.0",
    "gn:asciiname":"Arsal Town",
    "gn:country_code":"PK",
    "gn:dem":228,
    "gn:feature_class":"P",
    "gn:feature_code":"PPL",
    "gn:name":"Arsal Town",
    "gn:population":0,
    "gn:timezone":"Asia/Karachi",
    "iso:country":"PK",
    "wof:name":"Arsal Town",
    "wof:placetype":"locality"
},
  "geometry": {"coordinates":[73.68989000000001,32.91582],"type":"Point"}
}