{
  "type": "Feature",
  "properties": {
    "gn:admin1_code":"7.0",
    "gn:asciiname":"Khanqah",
    "gn:country_code":"PK",
    "gn:dem":2457,
    "gn:feature_class":"P",
    "gn:feature_code":"PPL",
    "gn:name":"Khanqah",
    "gn:population":0,
    "gn:timezone":"Asia/Karachi",
    "iso:country":"PK",
    "wof:name":"Khanqah",
    "wof:placetype":"locality"
},
  "geometry": {"coordinates":[76.12680999999998,35.2077],"type":"Point"}
}