{
  "type": "Feature",
  "properties": {
    "gn:admin1_code":"7.0",
    "gn:asciiname":"Khanqah",
    "gn:country_code":"PK",
    "gn:dem":2457,
    "gn:feature_class":"P",
    "gn:feature_code":"PPL",
    "gn:name":"Khanqah",
    "gn:population":0,
    "gn:timezone":"Asia/Karachi",
    "iso:country":"PK",
    "name:ara_x_preferred":[
        "\u062e\u0627\u0646\u0642\u0627\u0647"
    ],
    "name:aze_x_preferred":[
        "Xan\u0259gah"
    ],
    "name:bos_x_preferred":[
        "Tekija"
    ],
    "name:bul_x_preferred":[
        "\u0422\u0435\u043a\u0435"
    ],
    "name:deu_x_preferred":[
        "Tekke"
    ],
    "name:ell_x_preferred":[
        "\u03a4\u03b5\u03ba\u03ad\u03c2"
    ],
    "name:fas_x_preferred":[
        "\u062e\u0627\u0646\u06af\u0627\u0647"
    ],
    "name:fra_x_preferred":[
        "Khanqah"
    ],
    "name:hrv_x_preferred":[
        "Tekija"
    ],
    "name:hun_x_preferred":[
        "Tekke"
    ],
    "name:hye_x_preferred":[
        "\u053d\u0561\u0576\u0561\u056f\u0561"
    ],
    "name:ind_x_preferred":[
        "Khanqah"
    ],
    "name:ita_x_preferred":[
        "Khanqa"
    ],
    "name:jpn_x_preferred":[
        "\u30c6\u30c3\u30b1"
    ],
    "name:kaz_x_preferred":[
        "\u0425\u0430\u043d\u0430\u043a\u0430"
    ],
    "name:lit_x_preferred":[
        "Chanaka"
    ],
    "name:mal_x_preferred":[
        "\u0d38\u0d3e\u0d35\u0d3f\u0d2f"
    ],
    "name:mkd_x_preferred":[
        "\u0422\u0435\u045c\u0435"
    ],
    "name:pol_x_preferred":[
        "Chanaka"
    ],
    "name:por_x_preferred":[
        "Tekke"
    ],
    "name:rus_x_preferred":[
        "\u0425\u0430\u043d\u0430\u043a\u0430"
    ],
    "name:slv_x_preferred":[
        "Tekija"
    ],
    "name:spa_x_preferred":[
        "Khanqah"
    ],
    "name:sqi_x_preferred":[
        "Teqeja"
    ],
    "name:srp_x_preferred":[
        "\u0422\u0435\u043a\u0438\u0458\u0430"
    ],
    "name:swe_x_preferred":[
        "Khanaqa"
    ],
    "name:tur_x_preferred":[
        "Tekke"
    ],
    "name:ukr_x_preferred":[
        "\u0425\u0430\u043d\u0430\u043a\u0430"
    ],
    "name:urd_x_preferred":[
        "\u062e\u0627\u0646\u0642\u0627\u06c1"
    ],
    "name:uzb_x_preferred":[
        "Xonaqoh"
    ],
    "name:zho_x_preferred":[
        "\u54c8\u7d0d\u5361"
    ],
    "wof:name":"Khanqah",
    "wof:placetype":"locality"
},
  "geometry": {"coordinates":[76.12680999999998,35.2077],"type":"Point"}
}