{
  "type": "Feature",
  "properties": {
    "gn:admin1_code":"4",
    "gn:asciiname":"Jhok Muhammad Darewali",
    "gn:country_code":"PK",
    "gn:dem":163,
    "gn:feature_class":"P",
    "gn:feature_code":"PPL",
    "gn:name":"Jhok Muhammad Darewali",
    "gn:population":0,
    "gn:timezone":"Asia/Karachi",
    "iso:country":"PK",
    "name:und_x_variant":[
        "Jhok Muhammad Durr\u012bw\u0101li"
    ],
    "wof:name":"Jhok Muhammad Darewali",
    "wof:placetype":"locality"
},
  "geometry": {"coordinates":[70.66169000000002,30.55102],"type":"Point"}
}