{
  "type": "Feature",
  "properties": {
    "gn:admin1_code":"4.0",
    "gn:asciiname":"Chak Two Hundred Fifty-nine Gugera Branch",
    "gn:country_code":"PK",
    "gn:dem":161,
    "gn:feature_class":"P",
    "gn:feature_code":"PPL",
    "gn:name":"Chak Two Hundred Fifty-nine Gugera Branch",
    "gn:population":0,
    "gn:timezone":"Asia/Karachi",
    "iso:country":"PK",
    "name:und_x_variant":[
        "Chak Two Hundred Fifty-Nine",
        "Chir\u0101ghpur",
        "Chak Two Hundred Fifty-nine Gugera Branch"
    ],
    "wof:name":"Chak Two Hundred Fifty-nine Gugera Branch",
    "wof:placetype":"locality"
},
  "geometry": {"coordinates":[72.63209999999999,30.84081],"type":"Point"}
}