{
  "type": "Feature",
  "properties": {
    "gn:admin1_code":"4.0",
    "gn:asciiname":"Tibba",
    "gn:country_code":"PK",
    "gn:dem":206,
    "gn:feature_class":"P",
    "gn:feature_code":"PPL",
    "gn:name":"Tibba",
    "gn:population":0,
    "gn:timezone":"Asia/Karachi",
    "iso:country":"PK",
    "name:mal_x_preferred":[
        "\u0d1f\u0d3f\u0d2c\u0d4d\u0d2c"
    ],
    "name:pan_x_preferred":[
        "\u0a24\u0a3f\u0a71\u0a2c\u0a3e"
    ],
    "wof:name":"Tibba",
    "wof:placetype":"locality"
},
  "geometry": {"coordinates":[74.20214,31.62971],"type":"Point"}
}