{
  "type": "Feature",
  "properties": {
    "gn:admin1_code":"4",
    "gn:asciiname":"Basti Muhammad Aslam Pitafi",
    "gn:country_code":"PK",
    "gn:dem":105,
    "gn:feature_class":"P",
    "gn:feature_code":"PPL",
    "gn:name":"Basti Muhammad Aslam Pitafi",
    "gn:population":0,
    "gn:timezone":"Asia/Karachi",
    "iso:country":"PK",
    "name:und_x_variant":[
        "M\u016bsa Kh\u0101n Pit\u0101fi"
    ],
    "wof:name":"Basti Muhammad Aslam Pitafi",
    "wof:placetype":"locality"
},
  "geometry": {"coordinates":[70.73604,29.59001],"type":"Point"}
}