{
  "type": "Feature",
  "properties": {
    "gn:admin1_code":"3.0",
    "gn:asciiname":"Samian",
    "gn:country_code":"PK",
    "gn:dem":1422,
    "gn:feature_class":"P",
    "gn:feature_code":"PPL",
    "gn:name":"Samian",
    "gn:population":0,
    "gn:timezone":"Asia/Karachi",
    "iso:country":"PK",
    "wof:name":"Samian",
    "wof:placetype":"locality"
},
  "geometry": {"coordinates":[73.29428,34.33734],"type":"Point"}
}