{
  "type": "Feature",
  "properties": {
    "gn:admin1_code":"5",
    "gn:asciiname":"Mir Muhammad Tagar",
    "gn:country_code":"PK",
    "gn:dem":44,
    "gn:feature_class":"P",
    "gn:feature_code":"PPL",
    "gn:name":"Mir Muhammad Tagar",
    "gn:population":0,
    "gn:timezone":"Asia/Karachi",
    "iso:country":"PK",
    "name:und_x_variant":[
        "M\u012br Muhammad Tagar"
    ],
    "wof:name":"Mir Muhammad Tagar",
    "wof:placetype":"locality"
},
  "geometry": {"coordinates":[68.11315,26.86875],"type":"Point"}
}