{
  "type": "Feature",
  "properties": {
    "gn:admin1_code":"5",
    "gn:asciiname":"Goth Pagaro",
    "gn:country_code":"PK",
    "gn:dem":57,
    "gn:feature_class":"P",
    "gn:feature_code":"PPL",
    "gn:name":"Goth Pagaro",
    "gn:population":0,
    "gn:timezone":"Asia/Karachi",
    "iso:country":"PK",
    "name:und_x_variant":[
        "P\u0101g\u0101ro"
    ],
    "wof:name":"Goth Pagaro",
    "wof:placetype":"locality"
},
  "geometry": {"coordinates":[68.33923,27.73677],"type":"Point"}
}