{
  "type": "Feature",
  "properties": {
    "gn:admin1_code":"5",
    "gn:asciiname":"Goth Muhammad Hajano",
    "gn:country_code":"PK",
    "gn:dem":27,
    "gn:feature_class":"P",
    "gn:feature_code":"PPL",
    "gn:name":"Goth Muhammad Hajano",
    "gn:population":0,
    "gn:timezone":"Asia/Karachi",
    "iso:country":"PK",
    "name:und_x_variant":[
        "Goth Muhammad Haj\u0101no"
    ],
    "wof:name":"Goth Muhammad Hajano",
    "wof:placetype":"locality"
},
  "geometry": {"coordinates":[68.63306,25.59896],"type":"Point"}
}