{
  "type": "Feature",
  "properties": {
    "gn:admin1_code":"2.0",
    "gn:asciiname":"Jhalak",
    "gn:country_code":"PK",
    "gn:dem":2081,
    "gn:feature_class":"P",
    "gn:feature_code":"PPL",
    "gn:name":"Jhalak",
    "gn:population":0,
    "gn:timezone":"Asia/Karachi",
    "iso:country":"PK",
    "name:eng_x_preferred":[
        "Jalak"
    ],
    "wof:name":"Jhalak",
    "wof:placetype":"locality"
},
  "geometry": {"coordinates":[67.35605,30.70291],"type":"Point"}
}