{
  "type": "Feature",
  "properties": {
    "gn:admin1_code":"2.0",
    "gn:asciiname":"Dak Bazar",
    "gn:country_code":"PK",
    "gn:dem":552,
    "gn:feature_class":"P",
    "gn:feature_code":"PPL",
    "gn:name":"Dak Bazar",
    "gn:population":0,
    "gn:timezone":"Asia/Karachi",
    "iso:country":"PK",
    "name:und_x_variant":[
        "D\u0101k"
    ],
    "wof:name":"Dak Bazar",
    "wof:placetype":"locality"
},
  "geometry": {"coordinates":[64.91571999999999,26.2416],"type":"Point"}
}