{
  "type": "Feature",
  "properties": {
    "gn:admin1_code":"6",
    "gn:asciiname":"Darhal",
    "gn:country_code":"PK",
    "gn:dem":717,
    "gn:feature_class":"P",
    "gn:feature_code":"PPL",
    "gn:name":"Darhal",
    "gn:population":0,
    "gn:timezone":"Asia/Karachi",
    "iso:country":"PK",
    "name:und_x_variant":[
        "Nihari",
        "Darhal"
    ],
    "wof:name":"Darhal",
    "wof:placetype":"locality"
},
  "geometry": {"coordinates":[73.96528000000001,33.13472],"type":"Point"}
}