{
  "type": "Feature",
  "properties": {
    "gn:admin1_code":"4.0",
    "gn:asciiname":"Kanli",
    "gn:country_code":"PK",
    "gn:dem":419,
    "gn:feature_class":"P",
    "gn:feature_code":"PPL",
    "gn:name":"Kanli",
    "gn:population":0,
    "gn:timezone":"Asia/Karachi",
    "iso:country":"PK",
    "name:und_x_variant":[
        "K\u0101hli"
    ],
    "wof:name":"Kanli",
    "wof:placetype":"locality"
},
  "geometry": {"coordinates":[73.53744,33.34266],"type":"Point"}
}