{
  "type": "Feature",
  "properties": {
    "gn:admin1_code":"4",
    "gn:asciiname":"Jhok Kukra",
    "gn:country_code":"PK",
    "gn:dem":195,
    "gn:feature_class":"P",
    "gn:feature_code":"PPL",
    "gn:name":"Jhok Kukra",
    "gn:population":0,
    "gn:timezone":"Asia/Karachi",
    "iso:country":"PK",
    "name:und_x_variant":[
        "Jhok Lukra"
    ],
    "wof:name":"Jhok Kukra",
    "wof:placetype":"locality"
},
  "geometry": {"coordinates":[70.54718000000003,30.9053],"type":"Point"}
}