{
  "type": "Feature",
  "properties": {
    "gn:admin1_code":"6",
    "gn:asciiname":"Saran",
    "gn:country_code":"PK",
    "gn:dem":2437,
    "gn:feature_class":"P",
    "gn:feature_code":"PPL",
    "gn:name":"Saran",
    "gn:population":0,
    "gn:timezone":"Asia/Karachi",
    "iso:country":"PK",
    "name:und_x_variant":[
        "Sarr\u0101n"
    ],
    "wof:name":"Saran",
    "wof:placetype":"locality"
},
  "geometry": {"coordinates":[73.86435999999998,34.0629],"type":"Point"}
}