{
  "type": "Feature",
  "properties": {
    "gn:admin1_code":"4",
    "gn:asciiname":"Chak Forty-three",
    "gn:country_code":"PK",
    "gn:dem":199,
    "gn:feature_class":"P",
    "gn:feature_code":"PPL",
    "gn:name":"Chak Forty-three",
    "gn:population":0,
    "gn:timezone":"Asia/Karachi",
    "iso:country":"PK",
    "name:und_x_variant":[
        "Mull\u0101nw\u0101la"
    ],
    "wof:name":"Chak Forty-three",
    "wof:placetype":"locality"
},
  "geometry": {"coordinates":[73.87051,31.04888],"type":"Point"}
}