{
  "type": "Feature",
  "properties": {
    "gn:admin1_code":"4",
    "gn:asciiname":"Basti Wasir",
    "gn:country_code":"PK",
    "gn:dem":133,
    "gn:feature_class":"P",
    "gn:feature_code":"PPL",
    "gn:name":"Basti Wasir",
    "gn:population":0,
    "gn:timezone":"Asia/Karachi",
    "iso:country":"PK",
    "name:und_x_variant":[
        "Was\u012br"
    ],
    "wof:name":"Basti Wasir",
    "wof:placetype":"locality"
},
  "geometry": {"coordinates":[72.30426,29.62657],"type":"Point"}
}