{
  "type": "Feature",
  "properties": {
    "gn:admin1_code":"1.0",
    "gn:asciiname":"Mundi Khel",
    "gn:country_code":"PK",
    "gn:dem":828,
    "gn:feature_class":"P",
    "gn:feature_code":"PPL",
    "gn:name":"Mundi Khel",
    "gn:population":0,
    "gn:timezone":"Asia/Karachi",
    "iso:country":"PK",
    "wof:name":"Mundi Khel",
    "wof:placetype":"locality"
},
  "geometry": {"coordinates":[71.40584,34.42579],"type":"Point"}
}