{
  "type": "Feature",
  "properties": {
    "gn:admin1_code":"3.0",
    "gn:asciiname":"Kolalabad",
    "gn:country_code":"PK",
    "gn:dem":349,
    "gn:feature_class":"P",
    "gn:feature_code":"PPL",
    "gn:name":"Kolalabad",
    "gn:population":0,
    "gn:timezone":"Asia/Karachi",
    "iso:country":"PK",
    "name:eng_x_preferred":[
        "Gulalabad"
    ],
    "wof:name":"Kolalabad",
    "wof:placetype":"locality"
},
  "geometry": {"coordinates":[72.23951,34.2989],"type":"Point"}
}