{
  "type": "Feature",
  "properties": {
    "gn:admin1_code":"2.0",
    "gn:asciiname":"Kili Mahmudabad Koti",
    "gn:country_code":"PK",
    "gn:dem":2493,
    "gn:feature_class":"P",
    "gn:feature_code":"PPL",
    "gn:name":"Kili Mahmudabad Koti",
    "gn:population":0,
    "gn:timezone":"Asia/Karachi",
    "iso:country":"PK",
    "name:und_x_variant":[
        "Kote",
        "Koti",
        "Kili Mahmudabad Koti"
    ],
    "wof:name":"Kili Mahmudabad Koti",
    "wof:placetype":"locality"
},
  "geometry": {"coordinates":[67.60821999999999,30.62842],"type":"Point"}
}