{
  "type": "Feature",
  "properties": {
    "gn:admin1_code":"5",
    "gn:asciiname":"Goth Pir Chandram",
    "gn:country_code":"PK",
    "gn:dem":57,
    "gn:feature_class":"P",
    "gn:feature_code":"PPL",
    "gn:name":"Goth Pir Chandram",
    "gn:population":0,
    "gn:timezone":"Asia/Karachi",
    "iso:country":"PK",
    "name:und_x_variant":[
        "P\u012br Chandr\u0101m"
    ],
    "wof:name":"Goth Pir Chandram",
    "wof:placetype":"locality"
},
  "geometry": {"coordinates":[68.42215,27.79798],"type":"Point"}
}