{
  "type": "Feature",
  "properties": {
    "gn:admin1_code":"5",
    "gn:asciiname":"Mir Bahar jo Goth",
    "gn:country_code":"PK",
    "gn:dem":36,
    "gn:feature_class":"P",
    "gn:feature_code":"PPL",
    "gn:name":"Mir Bahar jo Goth",
    "gn:population":0,
    "gn:timezone":"Asia/Karachi",
    "iso:country":"PK",
    "name:und_x_variant":[
        "M\u012br Bahr"
    ],
    "wof:name":"Mir Bahar jo Goth",
    "wof:placetype":"locality"
},
  "geometry": {"coordinates":[67.69544,26.48359],"type":"Point"}
}