{
  "type": "Feature",
  "properties": {
    "gn:admin1_code":"01",
    "gn:asciiname":"Ghwaghasai",
    "gn:country_code":"PK",
    "gn:dem":890,
    "gn:feature_class":"P",
    "gn:feature_code":"PPL",
    "gn:name":"Ghwaghasai",
    "gn:population":0,
    "gn:timezone":"Asia/Karachi",
    "iso:country":"PK",
    "name:und_x_variant":[
        "Ghwagbasai"
    ],
    "wof:name":"Ghwaghasai",
    "wof:placetype":"locality"
},
  "geometry": {"coordinates":[71.48269999999999,34.70496],"type":"Point"}
}