{
  "type": "Feature",
  "properties": {
    "gn:admin1_code":"5.0",
    "gn:asciiname":"Rais Allah Bakhsh Dahri Presing Cotton Factory",
    "gn:country_code":"PK",
    "gn:dem":42,
    "gn:feature_class":"P",
    "gn:feature_code":"PPL",
    "gn:name":"Rais Allah Bakhsh Dahri Presing Cotton Factory",
    "gn:population":0,
    "gn:timezone":"Asia/Karachi",
    "iso:country":"PK",
    "wof:name":"Rais Allah Bakhsh Dahri Presing Cotton Factory",
    "wof:placetype":"locality"
},
  "geometry": {"coordinates":[68.30396,26.58431],"type":"Point"}
}