{
  "type": "Feature",
  "properties": {
    "gn:admin1_code":"1.0",
    "gn:asciiname":"Turab Garhi",
    "gn:country_code":"PK",
    "gn:dem":1954,
    "gn:feature_class":"P",
    "gn:feature_code":"PPL",
    "gn:name":"Turab Garhi",
    "gn:population":0,
    "gn:timezone":"Asia/Karachi",
    "iso:country":"PK",
    "name:und_x_variant":[
        "Tur\u0101h Garhi"
    ],
    "wof:name":"Turab Garhi",
    "wof:placetype":"locality"
},
  "geometry": {"coordinates":[70.80149,33.74729],"type":"Point"}
}