{
  "type": "Feature",
  "properties": {
    "gn:admin1_code":"4.0",
    "gn:asciiname":"Basti Akhtar Ali",
    "gn:country_code":"PK",
    "gn:dem":82,
    "gn:feature_class":"P",
    "gn:feature_code":"PPL",
    "gn:name":"Basti Akhtar Ali",
    "gn:population":0,
    "gn:timezone":"Asia/Karachi",
    "iso:country":"PK",
    "wof:name":"Basti Akhtar Ali",
    "wof:placetype":"locality"
},
  "geometry": {"coordinates":[70.36275999999999,28.47894],"type":"Point"}
}