{
  "type": "Feature",
  "properties": {
    "gn:admin1_code":"4",
    "gn:asciiname":"Jethewala",
    "gn:country_code":"PK",
    "gn:dem":184,
    "gn:feature_class":"P",
    "gn:feature_code":"PPL",
    "gn:name":"Jethewala",
    "gn:population":0,
    "gn:timezone":"Asia/Karachi",
    "iso:country":"PK",
    "name:und_x_variant":[
        "Jethw\u0101la"
    ],
    "wof:name":"Jethewala",
    "wof:placetype":"locality"
},
  "geometry": {"coordinates":[71.20555999999998,31.89939],"type":"Point"}
}