{
  "type": "Feature",
  "properties": {
    "gn:admin1_code":"6",
    "gn:asciiname":"Dabbar",
    "gn:country_code":"PK",
    "gn:dem":2691,
    "gn:feature_class":"P",
    "gn:feature_code":"PPL",
    "gn:name":"Dabbar",
    "gn:population":0,
    "gn:timezone":"Asia/Karachi",
    "iso:country":"PK",
    "wof:name":"Dabbar",
    "wof:placetype":"locality"
},
  "geometry": {"coordinates":[73.70081999999999,34.28417],"type":"Point"}
}