{
  "type": "Feature",
  "properties": {
    "gn:admin1_code":"3.0",
    "gn:asciiname":"Bhab",
    "gn:country_code":"PK",
    "gn:dem":1141,
    "gn:feature_class":"P",
    "gn:feature_code":"PPL",
    "gn:name":"Bhab",
    "gn:population":0,
    "gn:timezone":"Asia/Karachi",
    "iso:country":"PK",
    "wof:name":"Bhab",
    "wof:placetype":"locality"
},
  "geometry": {"coordinates":[73.06432,34.63402],"type":"Point"}
}