{
  "type": "Feature",
  "properties": {
    "gn:admin1_code":"4.0",
    "gn:asciiname":"Noor House",
    "gn:country_code":"PK",
    "gn:dem":496,
    "gn:feature_class":"P",
    "gn:feature_code":"PPLF",
    "gn:name":"Noor House",
    "gn:population":0,
    "gn:timezone":"Asia/Karachi",
    "iso:country":"PK",
    "wof:name":"Noor House",
    "wof:placetype":"locality"
},
  "geometry": {"coordinates":[72.19534,32.85975999999999],"type":"Point"}
}