{
  "type": "Feature",
  "properties": {
    "gn:admin1_code":"1.0",
    "gn:asciiname":"Maland Dam",
    "gn:country_code":"PK",
    "gn:dem":2355,
    "gn:feature_class":"P",
    "gn:feature_code":"PPL",
    "gn:name":"Maland Dam",
    "gn:population":0,
    "gn:timezone":"Asia/Karachi",
    "iso:country":"PK",
    "wof:name":"Maland Dam",
    "wof:placetype":"locality"
},
  "geometry": {"coordinates":[70.08738000000001,33.96465999999999],"type":"Point"}
}