{
  "type": "Feature",
  "properties": {
    "gn:admin1_code":"3",
    "gn:asciiname":"Liganai",
    "gn:country_code":"PK",
    "gn:dem":933,
    "gn:feature_class":"P",
    "gn:feature_code":"PPL",
    "gn:name":"Liganai",
    "gn:population":0,
    "gn:timezone":"Asia/Karachi",
    "iso:country":"PK",
    "name:und_x_variant":[
        "Lig\u0101nrai"
    ],
    "wof:name":"Liganai",
    "wof:placetype":"locality"
},
  "geometry": {"coordinates":[72.30656999999999,34.58841],"type":"Point"}
}