{
  "type": "Feature",
  "properties": {
    "gn:admin1_code":"4.0",
    "gn:asciiname":"Dhok Mullan",
    "gn:country_code":"PK",
    "gn:dem":592,
    "gn:feature_class":"P",
    "gn:feature_code":"PPL",
    "gn:name":"Dhok Mullan",
    "gn:population":0,
    "gn:timezone":"Asia/Karachi",
    "iso:country":"PK",
    "name:und_x_variant":[
        "Adm\u0101l"
    ],
    "wof:name":"Dhok Mullan",
    "wof:placetype":"locality"
},
  "geometry": {"coordinates":[73.32746999999998,33.51886],"type":"Point"}
}