{
  "type": "Feature",
  "properties": {
    "gn:admin1_code":"2",
    "gn:asciiname":"Sumalari",
    "gn:country_code":"PK",
    "gn:dem":1552,
    "gn:feature_class":"P",
    "gn:feature_code":"PPL",
    "gn:name":"Sumalari",
    "gn:population":0,
    "gn:timezone":"Asia/Karachi",
    "iso:country":"PK",
    "wof:name":"Sumalari",
    "wof:placetype":"locality"
},
  "geometry": {"coordinates":[66.28497,27.96254],"type":"Point"}
}