{
  "type": "Feature",
  "properties": {
    "gn:admin1_code":"1.0",
    "gn:asciiname":"Khaza",
    "gn:country_code":"PK",
    "gn:dem":1339,
    "gn:feature_class":"P",
    "gn:feature_code":"PPL",
    "gn:name":"Khaza",
    "gn:population":0,
    "gn:timezone":"Asia/Karachi",
    "iso:country":"PK",
    "wof:name":"Khaza",
    "wof:placetype":"locality"
},
  "geometry": {"coordinates":[71.15810999999999,33.80631],"type":"Point"}
}