{
  "type": "Feature",
  "properties": {
    "gn:admin1_code":"2.0",
    "gn:asciiname":"As Tangi",
    "gn:country_code":"PK",
    "gn:dem":1637,
    "gn:feature_class":"P",
    "gn:feature_code":"PPLL",
    "gn:name":"As Tangi",
    "gn:population":0,
    "gn:timezone":"Asia/Karachi",
    "iso:country":"PK",
    "name:eng_x_preferred":[
        "As Tangi"
    ],
    "wof:name":"As Tangi",
    "wof:placetype":"locality"
},
  "geometry": {"coordinates":[67.30049,30.10422],"type":"Point"}
}