{
  "type": "Feature",
  "properties": {
    "gn:admin1_code":"4.0",
    "gn:asciiname":"Kharappa",
    "gn:country_code":"PK",
    "gn:dem":473,
    "gn:feature_class":"P",
    "gn:feature_code":"PPL",
    "gn:name":"Kharappa",
    "gn:population":0,
    "gn:timezone":"Asia/Karachi",
    "iso:country":"PK",
    "wof:name":"Kharappa",
    "wof:placetype":"locality"
},
  "geometry": {"coordinates":[70.33377,31.07594000000001],"type":"Point"}
}