{
  "type": "Feature",
  "properties": {
    "gn:admin1_code":"5.0",
    "gn:asciiname":"Goth Qadir Bakhsh",
    "gn:country_code":"PK",
    "gn:dem":53,
    "gn:feature_class":"P",
    "gn:feature_code":"PPL",
    "gn:name":"Goth Qadir Bakhsh",
    "gn:population":0,
    "gn:timezone":"Asia/Karachi",
    "iso:country":"PK",
    "name:eng_x_preferred":[
        "Goth Qadir Bakhsh"
    ],
    "wof:name":"Goth Qadir Bakhsh",
    "wof:placetype":"locality"
},
  "geometry": {"coordinates":[68.5617,27.39879],"type":"Point"}
}