{
  "type": "Feature",
  "properties": {
    "gn:admin1_code":"05",
    "gn:asciiname":"Hashim Takro",
    "gn:country_code":"PK",
    "gn:dem":-1,
    "gn:feature_class":"P",
    "gn:feature_code":"PPL",
    "gn:name":"Hashim Takro",
    "gn:population":0,
    "gn:timezone":"Asia/Karachi",
    "iso:country":"PK",
    "wof:name":"Hashim Takro",
    "wof:placetype":"locality"
},
  "geometry": {"coordinates":[67.44911,24.05093],"type":"Point"}
}