{
  "type": "Feature",
  "properties": {
    "gn:admin1_code":"7.0",
    "gn:asciiname":"Ghulmit",
    "gn:country_code":"PK",
    "gn:dem":1972,
    "gn:feature_class":"P",
    "gn:feature_code":"PPL",
    "gn:name":"Ghulmit",
    "gn:population":0,
    "gn:timezone":"Asia/Karachi",
    "iso:country":"PK",
    "name:und_x_variant":[
        "Gulmat"
    ],
    "wof:name":"Ghulmit",
    "wof:placetype":"locality"
},
  "geometry": {"coordinates":[74.48336,36.24062],"type":"Point"}
}