{
  "type": "Feature",
  "properties": {
    "gn:admin1_code":"3",
    "gn:asciiname":"Gonar Kat",
    "gn:country_code":"PK",
    "gn:dem":1290,
    "gn:feature_class":"P",
    "gn:feature_code":"PPL",
    "gn:name":"Gonar Kat",
    "gn:population":0,
    "gn:timezone":"Asia/Karachi",
    "iso:country":"PK",
    "name:eng_x_preferred":[
        "G\u0101warkat"
    ],
    "wof:name":"Gonar Kat",
    "wof:placetype":"locality"
},
  "geometry": {"coordinates":[71.78814,35.01219],"type":"Point"}
}