{
  "type": "Feature",
  "properties": {
    "gn:admin1_code":"5.0",
    "gn:asciiname":"Goth Saleh Muhammad Subedar",
    "gn:country_code":"PK",
    "gn:dem":143,
    "gn:feature_class":"P",
    "gn:feature_code":"PPL",
    "gn:name":"Goth Saleh Muhammad Subedar",
    "gn:population":0,
    "gn:timezone":"Asia/Karachi",
    "iso:country":"PK",
    "name:und_x_variant":[
        "Sulaim\u0101n Subed\u0101r",
        "Goth Saleh Muhammad Subedar"
    ],
    "wof:name":"Goth Saleh Muhammad Subedar",
    "wof:placetype":"locality"
},
  "geometry": {"coordinates":[67.6033,24.98887],"type":"Point"}
}