{
  "type": "Feature",
  "properties": {
    "gn:admin1_code":"3.0",
    "gn:asciiname":"Pir Kalle",
    "gn:country_code":"PK",
    "gn:dem":329,
    "gn:feature_class":"P",
    "gn:feature_code":"PPL",
    "gn:name":"Pir Kalle",
    "gn:population":0,
    "gn:timezone":"Asia/Karachi",
    "iso:country":"PK",
    "name:eng_x_preferred":[
        "P\u012br Kili"
    ],
    "wof:name":"Pir Kalle",
    "wof:placetype":"locality"
},
  "geometry": {"coordinates":[71.50312,34.12918],"type":"Point"}
}