{
  "type": "Feature",
  "properties": {
    "gn:admin1_code":"5",
    "gn:asciiname":"Khan Muammad Thaim",
    "gn:country_code":"PK",
    "gn:dem":20,
    "gn:feature_class":"P",
    "gn:feature_code":"PPL",
    "gn:name":"Khan Muammad Thaim",
    "gn:population":0,
    "gn:timezone":"Asia/Karachi",
    "iso:country":"PK",
    "name:und_x_variant":[
        "Muhammad Kh\u0101n Thahim"
    ],
    "wof:name":"Khan Muammad Thaim",
    "wof:placetype":"locality"
},
  "geometry": {"coordinates":[68.68812,25.26567],"type":"Point"}
}