{
  "type": "Feature",
  "properties": {
    "gn:admin1_code":"7.0",
    "gn:asciiname":"Pashot",
    "gn:country_code":"PK",
    "gn:dem":3143,
    "gn:feature_class":"P",
    "gn:feature_code":"PPL",
    "gn:name":"Pashot",
    "gn:population":0,
    "gn:timezone":"Asia/Karachi",
    "iso:country":"PK",
    "wof:name":"Pashot",
    "wof:placetype":"locality"
},
  "geometry": {"coordinates":[73.65219999999999,35.75102000000001],"type":"Point"}
}