{
  "type": "Feature",
  "properties": {
    "gn:admin1_code":"3.0",
    "gn:asciiname":"Mira Din",
    "gn:country_code":"PK",
    "gn:dem":424,
    "gn:feature_class":"P",
    "gn:feature_code":"PPL",
    "gn:name":"Mira Din",
    "gn:population":0,
    "gn:timezone":"Asia/Karachi",
    "iso:country":"PK",
    "wof:name":"Mira Din",
    "wof:placetype":"locality"
},
  "geometry": {"coordinates":[70.48402,32.93893],"type":"Point"}
}