{
  "type": "Feature",
  "properties": {
    "gn:admin1_code":"3",
    "gn:asciiname":"Naredalai",
    "gn:country_code":"PK",
    "gn:dem":1807,
    "gn:feature_class":"P",
    "gn:feature_code":"PPL",
    "gn:name":"Naredalai",
    "gn:population":0,
    "gn:timezone":"Asia/Karachi",
    "iso:country":"PK",
    "wof:name":"Naredalai",
    "wof:placetype":"locality"
},
  "geometry": {"coordinates":[72.73331999999998,35.0299],"type":"Point"}
}