{
  "type": "Feature",
  "properties": {
    "gn:admin1_code":"5",
    "gn:asciiname":"Goth Bachu Faqir Monjhar",
    "gn:country_code":"PK",
    "gn:dem":64,
    "gn:feature_class":"P",
    "gn:feature_code":"PPL",
    "gn:name":"Goth Bachu Faqir Monjhar",
    "gn:population":0,
    "gn:timezone":"Asia/Karachi",
    "iso:country":"PK",
    "name:eng_x_preferred":[
        "Goth Bachu Faqir Monjhar"
    ],
    "name:und_x_variant":[
        "Goth Bachu Faqir"
    ],
    "wof:name":"Goth Bachu Faqir Monjhar",
    "wof:placetype":"locality"
},
  "geometry": {"coordinates":[68.08507,25.20851],"type":"Point"}
}