{
  "type": "Feature",
  "properties": {
    "iso:country":"PK",
    "name:unk_x_variant":[
        "Naushera Virkhan"
    ],
    "qs:gn_country":"PK",
    "qs:gn_fcode":"PPL",
    "qs:gn_pop":40853,
    "qs:name":"Naushahra Virkhan",
    "qs:name_adm0":"Pakistan",
    "qs:name_adm1":"Punjab",
    "qs:photos":0,
    "qs:photos_1k":0,
    "qs:photos_9k":0,
    "qs:photos_9r":0,
    "qs:photos_all":0,
    "qs:photos_sr":0,
    "qs:placetype":"Town",
    "qs:pop_sr":"7",
    "qs:woe_adm0":23424922,
    "wof:name":"Naushahra Virkhan",
    "wof:placetype":"locality",
    "wof:population":40853
},
  "geometry": {"coordinates":[73.97225,31.96284],"type":"Point"}
}