{
  "type": "Feature",
  "properties": {
    "gn:admin1_code":"5",
    "gn:asciiname":"Saleh Dahri",
    "gn:country_code":"PK",
    "gn:dem":40,
    "gn:feature_class":"P",
    "gn:feature_code":"PPL",
    "gn:name":"Saleh Dahri",
    "gn:population":0,
    "gn:timezone":"Asia/Karachi",
    "iso:country":"PK",
    "wof:name":"Saleh Dahri",
    "wof:placetype":"locality"
},
  "geometry": {"coordinates":[68.03728000000001,26.47283],"type":"Point"}
}