{
  "type": "Feature",
  "properties": {
    "gn:admin1_code":"3.0",
    "gn:asciiname":"Bognam Banda",
    "gn:country_code":"PK",
    "gn:dem":503,
    "gn:feature_class":"P",
    "gn:feature_code":"PPL",
    "gn:name":"Bognam Banda",
    "gn:population":0,
    "gn:timezone":"Asia/Karachi",
    "iso:country":"PK",
    "wof:name":"Bognam Banda",
    "wof:placetype":"locality"
},
  "geometry": {"coordinates":[71.82958000000001,34.50554],"type":"Point"}
}