{
  "type": "Feature",
  "properties": {
    "gn:admin1_code":"04",
    "gn:asciiname":"Tarkhanwala",
    "gn:country_code":"PK",
    "gn:dem":171,
    "gn:feature_class":"P",
    "gn:feature_code":"PPL",
    "gn:name":"Tarkhanwala",
    "gn:population":0,
    "gn:timezone":"Asia/Karachi",
    "iso:country":"PK",
    "name:und_x_variant":[
        "Tirkhanwala",
        "Tarkhanwala",
        "Terkh\u0101nw\u0101la"
    ],
    "wof:name":"Tarkhanwala",
    "wof:placetype":"locality"
},
  "geometry": {"coordinates":[72.32613000000001,31.83692000000001],"type":"Point"}
}