{
  "type": "Feature",
  "properties": {
    "gn:admin1_code":"2",
    "gn:asciiname":"Basti Choti",
    "gn:country_code":"PK",
    "gn:dem":1201,
    "gn:feature_class":"P",
    "gn:feature_code":"PPL",
    "gn:name":"Basti Choti",
    "gn:population":0,
    "gn:timezone":"Asia/Karachi",
    "iso:country":"PK",
    "name:und_x_variant":[
        "Choti"
    ],
    "wof:name":"Basti Choti",
    "wof:placetype":"locality"
},
  "geometry": {"coordinates":[69.60811,29.97294],"type":"Point"}
}