{
  "type": "Feature",
  "properties": {
    "gn:admin1_code":"04",
    "gn:asciiname":"Chak One Hundred Sixty-four Gugera Branch",
    "gn:country_code":"PK",
    "gn:dem":164,
    "gn:feature_class":"P",
    "gn:feature_code":"PPL",
    "gn:name":"Chak One Hundred Sixty-four Gugera Branch",
    "gn:population":0,
    "gn:timezone":"Asia/Karachi",
    "iso:country":"PK",
    "name:und_x_variant":[
        "Nijharpur",
        "Chak Number One Hundred Sixty-Four",
        "Chak One Hundred Sixty-four Gugera Branch",
        "Sheikh\u0101n"
    ],
    "wof:name":"Chak One Hundred Sixty-four Gugera Branch",
    "wof:placetype":"locality"
},
  "geometry": {"coordinates":[72.63955,31.04213],"type":"Point"}
}