{
  "type": "Feature",
  "properties": {
    "gn:admin1_code":"4",
    "gn:asciiname":"Hidayetwala",
    "gn:country_code":"PK",
    "gn:dem":134,
    "gn:feature_class":"P",
    "gn:feature_code":"PPL",
    "gn:name":"Hidayetwala",
    "gn:population":0,
    "gn:timezone":"Asia/Karachi",
    "iso:country":"PK",
    "name:und_x_variant":[
        "Hid\u0101yatw\u0101la"
    ],
    "wof:name":"Hidayetwala",
    "wof:placetype":"locality"
},
  "geometry": {"coordinates":[71.73824,30.64514],"type":"Point"}
}