{
  "type": "Feature",
  "properties": {
    "gn:admin1_code":"5.0",
    "gn:asciiname":"Goth Allu",
    "gn:country_code":"PK",
    "gn:dem":222,
    "gn:feature_class":"P",
    "gn:feature_code":"PPL",
    "gn:name":"Goth Allu",
    "gn:population":0,
    "gn:timezone":"Asia/Karachi",
    "iso:country":"PK",
    "wof:name":"Goth Allu",
    "wof:placetype":"locality"
},
  "geometry": {"coordinates":[67.38885000000001,25.50154],"type":"Point"}
}