{
  "type": "Feature",
  "properties": {
    "gn:admin1_code":"6",
    "gn:asciiname":"Ghasipur",
    "gn:country_code":"PK",
    "gn:dem":239,
    "gn:feature_class":"P",
    "gn:feature_code":"PPL",
    "gn:name":"Ghasipur",
    "gn:population":0,
    "gn:timezone":"Asia/Karachi",
    "iso:country":"PK",
    "wof:name":"Ghasipur",
    "wof:placetype":"locality"
},
  "geometry": {"coordinates":[73.79831,33.03708],"type":"Point"}
}