{
  "type": "Feature",
  "properties": {
    "gn:admin1_code":"4.0",
    "gn:asciiname":"Basti Raikhanwali",
    "gn:country_code":"PK",
    "gn:dem":156,
    "gn:feature_class":"P",
    "gn:feature_code":"PPL",
    "gn:name":"Basti Raikhanwali",
    "gn:population":0,
    "gn:timezone":"Asia/Karachi",
    "iso:country":"PK",
    "wof:name":"Basti Raikhanwali",
    "wof:placetype":"locality"
},
  "geometry": {"coordinates":[73.06716,29.86722],"type":"Point"}
}