{
  "type": "Feature",
  "properties": {
    "gn:admin1_code":"4",
    "gn:asciiname":"Gagge",
    "gn:country_code":"PK",
    "gn:dem":234,
    "gn:feature_class":"P",
    "gn:feature_code":"PPL",
    "gn:name":"Gagge",
    "gn:population":0,
    "gn:timezone":"Asia/Karachi",
    "iso:country":"PK",
    "wof:name":"Gagge",
    "wof:placetype":"locality"
},
  "geometry": {"coordinates":[74.62151999999998,32.17113],"type":"Point"}
}