{
  "type": "Feature",
  "properties": {
    "gn:admin1_code":"3.0",
    "gn:asciiname":"Azad Khan Kili",
    "gn:country_code":"PK",
    "gn:dem":341,
    "gn:feature_class":"P",
    "gn:feature_code":"PPL",
    "gn:name":"Azad Khan Kili",
    "gn:population":0,
    "gn:timezone":"Asia/Karachi",
    "iso:country":"PK",
    "name:und_x_variant":[
        "Am\u0101n Gul Kili"
    ],
    "wof:name":"Azad Khan Kili",
    "wof:placetype":"locality"
},
  "geometry": {"coordinates":[71.43838000000002,34.14217],"type":"Point"}
}