{
  "type": "Feature",
  "properties": {
    "gn:admin1_code":"3.0",
    "gn:asciiname":"Khubela",
    "gn:country_code":"PK",
    "gn:dem":2965,
    "gn:feature_class":"P",
    "gn:feature_code":"PPL",
    "gn:name":"Khubela",
    "gn:population":0,
    "gn:timezone":"Asia/Karachi",
    "iso:country":"PK",
    "wof:name":"Khubela",
    "wof:placetype":"locality"
},
  "geometry": {"coordinates":[71.92798000000001,35.4428],"type":"Point"}
}