{
  "type": "Feature",
  "properties": {
    "gn:admin1_code":"6",
    "gn:asciiname":"Mal",
    "gn:country_code":"PK",
    "gn:dem":982,
    "gn:feature_class":"P",
    "gn:feature_code":"PPL",
    "gn:name":"Mal",
    "gn:population":0,
    "gn:timezone":"Asia/Karachi",
    "iso:country":"PK",
    "wof:name":"Mal",
    "wof:placetype":"locality"
},
  "geometry": {"coordinates":[73.76194,33.66137],"type":"Point"}
}