{
  "type": "Feature",
  "properties": {
    "gn:admin1_code":"7.0",
    "gn:asciiname":"Suk",
    "gn:country_code":"PK",
    "gn:dem":2351,
    "gn:feature_class":"P",
    "gn:feature_code":"PPL",
    "gn:name":"Suk",
    "gn:population":0,
    "gn:timezone":"Asia/Karachi",
    "iso:country":"PK",
    "wof:name":"Suk",
    "wof:placetype":"locality"
},
  "geometry": {"coordinates":[76.00158,35.08648],"type":"Point"}
}