{
  "type": "Feature",
  "properties": {
    "gn:admin1_code":"3.0",
    "gn:asciiname":"Bato Lal",
    "gn:country_code":"PK",
    "gn:dem":2468,
    "gn:feature_class":"P",
    "gn:feature_code":"PPL",
    "gn:name":"Bato Lal",
    "gn:population":0,
    "gn:timezone":"Asia/Karachi",
    "iso:country":"PK",
    "wof:name":"Bato Lal",
    "wof:placetype":"locality"
},
  "geometry": {"coordinates":[72.55821,35.56418],"type":"Point"}
}