{
  "type": "Feature",
  "properties": {
    "gn:admin1_code":"6",
    "gn:asciiname":"Dadia",
    "gn:country_code":"PK",
    "gn:dem":1861,
    "gn:feature_class":"P",
    "gn:feature_code":"PPL",
    "gn:name":"Dadia",
    "gn:population":0,
    "gn:timezone":"Asia/Karachi",
    "iso:country":"PK",
    "name:bul_x_preferred":[
        "\u0427\u0430\u043c\u043a\u044c\u043e\u0439"
    ],
    "name:ceb_x_preferred":[
        "Dad\u00eda"
    ],
    "name:ell_x_preferred":[
        "\u0394\u03b1\u03b4\u03b9\u03ac \u0388\u03b2\u03c1\u03bf\u03c5"
    ],
    "name:ron_x_preferred":[
        "Dadia"
    ],
    "name:spa_x_preferred":[
        "Dadia"
    ],
    "name:swe_x_preferred":[
        "Dad\u00eda"
    ],
    "name:und_x_variant":[
        "Dadlya"
    ],
    "wof:name":"Dadia",
    "wof:placetype":"locality"
},
  "geometry": {"coordinates":[73.79843000000002,34.00393],"type":"Point"}
}