{
  "type": "Feature",
  "properties": {
    "gn:admin1_code":"6",
    "gn:asciiname":"Dadia",
    "gn:country_code":"PK",
    "gn:dem":1861,
    "gn:feature_class":"P",
    "gn:feature_code":"PPL",
    "gn:name":"Dadia",
    "gn:population":0,
    "gn:timezone":"Asia/Karachi",
    "iso:country":"PK",
    "name:und_x_variant":[
        "Dadlya"
    ],
    "wof:name":"Dadia",
    "wof:placetype":"locality"
},
  "geometry": {"coordinates":[73.79843000000002,34.00393],"type":"Point"}
}