{
  "type": "Feature",
  "properties": {
    "gn:admin1_code":"3",
    "gn:asciiname":"Banara",
    "gn:country_code":"PK",
    "gn:dem":1269,
    "gn:feature_class":"P",
    "gn:feature_code":"PPL",
    "gn:name":"Banara",
    "gn:population":0,
    "gn:timezone":"Asia/Karachi",
    "iso:country":"PK",
    "wof:name":"Banara",
    "wof:placetype":"locality"
},
  "geometry": {"coordinates":[73.03440000000001,34.6271],"type":"Point"}
}