{
  "type": "Feature",
  "properties": {
    "gn:admin1_code":"3",
    "gn:asciiname":"Mullan",
    "gn:country_code":"PK",
    "gn:dem":1644,
    "gn:feature_class":"P",
    "gn:feature_code":"PPL",
    "gn:name":"Mullan",
    "gn:population":0,
    "gn:timezone":"Asia/Karachi",
    "iso:country":"PK",
    "name:deu_x_preferred":[
        "Mullan"
    ],
    "name:epo_x_preferred":[
        "Mullan"
    ],
    "name:fra_x_preferred":[
        "Mullan"
    ],
    "name:por_x_preferred":[
        "Mullan"
    ],
    "name:rus_x_preferred":[
        "\u041c\u0430\u043b\u043b\u0430\u043d"
    ],
    "wof:name":"Mullan",
    "wof:placetype":"locality"
},
  "geometry": {"coordinates":[73.37326,34.62742],"type":"Point"}
}