{
  "type": "Feature",
  "properties": {
    "gn:admin1_code":"3",
    "gn:asciiname":"Chitiala Dheri",
    "gn:country_code":"PK",
    "gn:dem":357,
    "gn:feature_class":"P",
    "gn:feature_code":"PPL",
    "gn:name":"Chitiala Dheri",
    "gn:population":0,
    "gn:timezone":"Asia/Karachi",
    "iso:country":"PK",
    "name:eng_x_preferred":[
        "Chitial Dheri"
    ],
    "name:und_x_variant":[
        "Chitlai Dheri",
        "Chitiala Dheri"
    ],
    "wof:name":"Chitiala Dheri",
    "wof:placetype":"locality"
},
  "geometry": {"coordinates":[72.32278000000002,34.30239],"type":"Point"}
}