{
  "type": "Feature",
  "properties": {
    "gn:admin1_code":"2.0",
    "gn:asciiname":"Kalan Chah",
    "gn:country_code":"PK",
    "gn:dem":1213,
    "gn:feature_class":"P",
    "gn:feature_code":"PPL",
    "gn:name":"Kalan Chah",
    "gn:population":0,
    "gn:timezone":"Asia/Karachi",
    "iso:country":"PK",
    "wof:name":"Kalan Chah",
    "wof:placetype":"locality"
},
  "geometry": {"coordinates":[64.56603,27.18558],"type":"Point"}
}