{
  "type": "Feature",
  "properties": {
    "gn:admin1_code":"5.0",
    "gn:asciiname":"Liabal Khan Burrho",
    "gn:country_code":"PK",
    "gn:dem":68,
    "gn:feature_class":"P",
    "gn:feature_code":"PPL",
    "gn:name":"Liabal Khan Burrho",
    "gn:population":0,
    "gn:timezone":"Asia/Karachi",
    "iso:country":"PK",
    "wof:name":"Liabal Khan Burrho",
    "wof:placetype":"locality"
},
  "geometry": {"coordinates":[68.71607,28.15598],"type":"Point"}
}