{
  "type": "Feature",
  "properties": {
    "iso:country":"PK",
    "name:ceb_x_preferred":[
        "Darya Kh\u0101n"
    ],
    "name:eng_x_preferred":[
        "Darya Khan"
    ],
    "name:fas_x_preferred":[
        "\u062f\u0631\u06cc\u0627\u062e\u0627\u0646"
    ],
    "name:fra_x_preferred":[
        "Darya Khan"
    ],
    "name:hin_x_preferred":[
        "\u0926\u0930\u092f\u093e \u0916\u093e\u0928"
    ],
    "name:nld_x_preferred":[
        "Darya Khan"
    ],
    "name:pnb_x_preferred":[
        "\u062f\u0631\u06cc\u0627 \u062e\u0627\u0646"
    ],
    "name:por_x_preferred":[
        "Darya Khan"
    ],
    "name:und_x_variant":[
        "Darya Khan Daggar"
    ],
    "name:urd_x_preferred":[
        "\u062f\u0631\u06cc\u0627 \u062e\u0627\u0646"
    ],
    "qs:gn_country":"PK",
    "qs:gn_fcode":"PPL",
    "qs:gn_pop":15048,
    "qs:name":"Darya Khan",
    "qs:name_adm0":"Pakistan",
    "qs:name_adm1":"Punjab",
    "qs:photos":0,
    "qs:photos_1k":0,
    "qs:photos_9k":0,
    "qs:photos_9r":0,
    "qs:photos_all":0,
    "qs:photos_sr":0,
    "qs:placetype":"Town",
    "qs:pop_sr":"6",
    "qs:woe_adm0":23424922,
    "wd:wordcount":159,
    "wof:name":"Darya Khan",
    "wof:placetype":"locality",
    "wof:population":15048
},
  "geometry": {"coordinates":[71.10393999999999,31.79123],"type":"Point"}
}