{
  "type": "Feature",
  "properties": {
    "gn:admin1_code":"4",
    "gn:asciiname":"Chak Thirty-five Khadir Branch",
    "gn:country_code":"PK",
    "gn:dem":148,
    "gn:feature_class":"P",
    "gn:feature_code":"PPL",
    "gn:name":"Chak Thirty-five Khadir Branch",
    "gn:population":0,
    "gn:timezone":"Asia/Karachi",
    "iso:country":"PK",
    "name:und_x_variant":[
        "Chak Thirty-five"
    ],
    "wof:name":"Chak Thirty-five Khadir Branch",
    "wof:placetype":"locality"
},
  "geometry": {"coordinates":[72.90730000000001,30.0749],"type":"Point"}
}