{
  "type": "Feature",
  "properties": {
    "gn:admin1_code":"3",
    "gn:asciiname":"Sunai Banda",
    "gn:country_code":"PK",
    "gn:dem":2871,
    "gn:feature_class":"P",
    "gn:feature_code":"PPL",
    "gn:name":"Sunai Banda",
    "gn:population":0,
    "gn:timezone":"Asia/Karachi",
    "iso:country":"PK",
    "name:eng_x_preferred":[
        "Sunai Banda"
    ],
    "name:und_x_variant":[
        "Katwai"
    ],
    "wof:name":"Sunai Banda",
    "wof:placetype":"locality"
},
  "geometry": {"coordinates":[71.58431,35.10476],"type":"Point"}
}