{
  "type": "Feature",
  "properties": {
    "gn:admin1_code":"6",
    "gn:asciiname":"Dhaniat",
    "gn:country_code":"PK",
    "gn:dem":1551,
    "gn:feature_class":"P",
    "gn:feature_code":"PPL",
    "gn:name":"Dhaniat",
    "gn:population":0,
    "gn:timezone":"Asia/Kolkata",
    "iso:country":"PK",
    "name:und_x_variant":[
        "Dainyar"
    ],
    "wof:name":"Dhaniat",
    "wof:placetype":"locality"
},
  "geometry": {"coordinates":[73.92989,34.63663],"type":"Point"}
}