{
  "type": "Feature",
  "properties": {
    "gn:admin1_code":"04",
    "gn:asciiname":"Kunt",
    "gn:country_code":"PK",
    "gn:dem":500,
    "gn:feature_class":"P",
    "gn:feature_code":"PPL",
    "gn:name":"Kunt",
    "gn:population":0,
    "gn:timezone":"Asia/Karachi",
    "iso:country":"PK",
    "name:und_x_variant":[
        "Kaunt",
        "Kunt"
    ],
    "wof:name":"Kunt",
    "wof:placetype":"locality"
},
  "geometry": {"coordinates":[73.02318000000002,33.10417],"type":"Point"}
}