{
  "type": "Feature",
  "properties": {
    "gn:admin1_code":"4.0",
    "gn:asciiname":"Qadirabad",
    "gn:country_code":"PK",
    "gn:dem":161,
    "gn:feature_class":"P",
    "gn:feature_code":"PPL",
    "gn:name":"Qadirabad",
    "gn:population":0,
    "gn:timezone":"Asia/Karachi",
    "iso:country":"PK",
    "name:fas_x_preferred":[
        "\u0642\u0627\u062f\u0631\u0622\u0628\u0627\u062f"
    ],
    "name:pnb_x_preferred":[
        "\u0642\u0627\u062f\u0631\u0622\u0628\u0627\u062f"
    ],
    "name:por_x_preferred":[
        "Qadirabad"
    ],
    "name:urd_x_preferred":[
        "\u0642\u0627\u062f\u0631 \u0622\u0628\u0627\u062f"
    ],
    "wof:name":"Qadirabad",
    "wof:placetype":"locality"
},
  "geometry": {"coordinates":[73.13518000000001,29.86986],"type":"Point"}
}