{
  "type": "Feature",
  "properties": {
    "gn:admin1_code":"04",
    "gn:asciiname":"Mahmud Kot",
    "gn:country_code":"PK",
    "gn:dem":193,
    "gn:feature_class":"P",
    "gn:feature_code":"PPL",
    "gn:name":"Mahmud Kot",
    "gn:population":0,
    "gn:timezone":"Asia/Karachi",
    "iso:country":"PK",
    "name:und_x_variant":[
        "Mahm\u016bd Ko",
        "Mahmud Kot",
        "Chak Seven NB",
        "Chak 7 NB",
        "Chak Seven North Branch"
    ],
    "wof:name":"Mahmud Kot",
    "wof:placetype":"locality"
},
  "geometry": {"coordinates":[72.89315000000001,32.29020999999999],"type":"Point"}
}