{
  "type": "Feature",
  "properties": {
    "gn:admin1_code":"3.0",
    "gn:asciiname":"Luge Banda",
    "gn:country_code":"PK",
    "gn:dem":2091,
    "gn:feature_class":"P",
    "gn:feature_code":"PPL",
    "gn:name":"Luge Banda",
    "gn:population":0,
    "gn:timezone":"Asia/Karachi",
    "iso:country":"PK",
    "wof:name":"Luge Banda",
    "wof:placetype":"locality"
},
  "geometry": {"coordinates":[72.75480999999998,35.07985],"type":"Point"}
}