{
  "type": "Feature",
  "properties": {
    "gn:admin1_code":"04",
    "gn:asciiname":"Saiyyidwaia",
    "gn:country_code":"PK",
    "gn:dem":202,
    "gn:feature_class":"P",
    "gn:feature_code":"PPL",
    "gn:name":"Saiyyidwaia",
    "gn:population":0,
    "gn:timezone":"Asia/Karachi",
    "iso:country":"PK",
    "name:und_x_variant":[
        "Saidwala",
        "Saiyidw\u0101la",
        "Saiyyidwaia"
    ],
    "wof:name":"Saiyyidwaia",
    "wof:placetype":"locality"
},
  "geometry": {"coordinates":[73.43889,32.02435999999999],"type":"Point"}
}