{
  "type": "Feature",
  "properties": {
    "gn:admin1_code":"1.0",
    "gn:asciiname":"Tando Kalle",
    "gn:country_code":"PK",
    "gn:dem":1164,
    "gn:feature_class":"P",
    "gn:feature_code":"PPL",
    "gn:name":"Tando Kalle",
    "gn:population":0,
    "gn:timezone":"Asia/Karachi",
    "iso:country":"PK",
    "wof:name":"Tando Kalle",
    "wof:placetype":"locality"
},
  "geometry": {"coordinates":[70.31531,33.6946],"type":"Point"}
}