{
  "type": "Feature",
  "properties": {
    "gn:admin1_code":"4",
    "gn:asciiname":"Ziarat Muhammad Husain Shah",
    "gn:country_code":"PK",
    "gn:dem":167,
    "gn:feature_class":"P",
    "gn:feature_code":"PPL",
    "gn:name":"Ziarat Muhammad Husain Shah",
    "gn:population":0,
    "gn:timezone":"Asia/Karachi",
    "iso:country":"PK",
    "name:und_x_variant":[
        "Zi\u0101rat Muhammad Husain Sh\u0101h"
    ],
    "wof:name":"Ziarat Muhammad Husain Shah",
    "wof:placetype":"locality"
},
  "geometry": {"coordinates":[72.07278000000002,31.33584],"type":"Point"}
}