{
  "type": "Feature",
  "properties": {
    "gn:admin1_code":"3.0",
    "gn:asciiname":"Kanr",
    "gn:country_code":"PK",
    "gn:dem":2566,
    "gn:feature_class":"P",
    "gn:feature_code":"PPL",
    "gn:name":"Kanr",
    "gn:population":0,
    "gn:timezone":"Asia/Karachi",
    "iso:country":"PK",
    "wof:name":"Kanr",
    "wof:placetype":"locality"
},
  "geometry": {"coordinates":[73.08046999999998,35.51308],"type":"Point"}
}