{
  "type": "Feature",
  "properties": {
    "gn:admin1_code":"5",
    "gn:asciiname":"Mehr Khan Mamdani",
    "gn:country_code":"PK",
    "gn:dem":70,
    "gn:feature_class":"P",
    "gn:feature_code":"PPL",
    "gn:name":"Mehr Khan Mamdani",
    "gn:population":0,
    "gn:timezone":"Asia/Karachi",
    "iso:country":"PK",
    "wof:name":"Mehr Khan Mamdani",
    "wof:placetype":"locality"
},
  "geometry": {"coordinates":[69.25139,28.15833],"type":"Point"}
}