{
  "type": "Feature",
  "properties": {
    "gn:admin1_code":"4",
    "gn:asciiname":"Luku",
    "gn:country_code":"PK",
    "gn:dem":188,
    "gn:feature_class":"P",
    "gn:feature_code":"PPL",
    "gn:name":"Luku",
    "gn:population":0,
    "gn:timezone":"Asia/Karachi",
    "iso:country":"PK",
    "wof:name":"Luku",
    "wof:placetype":"locality"
},
  "geometry": {"coordinates":[72.08008000000002,32.04855],"type":"Point"}
}