{
  "type": "Feature",
  "properties": {
    "gn:admin1_code":"4.0",
    "gn:asciiname":"Adda Double Phatak",
    "gn:country_code":"PK",
    "gn:dem":167,
    "gn:feature_class":"P",
    "gn:feature_code":"PPL",
    "gn:name":"Adda Double Phatak",
    "gn:population":0,
    "gn:timezone":"Asia/Karachi",
    "iso:country":"PK",
    "wof:name":"Adda Double Phatak",
    "wof:placetype":"locality"
},
  "geometry": {"coordinates":[73.55082,30.13395],"type":"Point"}
}