{
  "type": "Feature",
  "properties": {
    "gn:admin1_code":"4.0",
    "gn:asciiname":"Dhok Chakki",
    "gn:country_code":"PK",
    "gn:dem":370,
    "gn:feature_class":"P",
    "gn:feature_code":"PPL",
    "gn:name":"Dhok Chakki",
    "gn:population":0,
    "gn:timezone":"Asia/Karachi",
    "iso:country":"PK",
    "name:und_x_variant":[
        "Chakki Dhok",
        "Dhok Chakki"
    ],
    "wof:name":"Dhok Chakki",
    "wof:placetype":"locality"
},
  "geometry": {"coordinates":[71.96789,33.17862],"type":"Point"}
}