{
  "type": "Feature",
  "properties": {
    "gn:admin1_code":"6",
    "gn:asciiname":"Kandoli",
    "gn:country_code":"PK",
    "gn:dem":1956,
    "gn:feature_class":"P",
    "gn:feature_code":"PPL",
    "gn:name":"Kandoli",
    "gn:population":0,
    "gn:timezone":"Asia/Karachi",
    "iso:country":"PK",
    "name:und_x_variant":[
        "Khandali"
    ],
    "wof:name":"Kandoli",
    "wof:placetype":"locality"
},
  "geometry": {"coordinates":[73.60111999999999,34.36278],"type":"Point"}
}