{
  "type": "Feature",
  "properties": {
    "gn:admin1_code":"3",
    "gn:asciiname":"Kandar",
    "gn:country_code":"PK",
    "gn:dem":724,
    "gn:feature_class":"P",
    "gn:feature_code":"PPL",
    "gn:name":"Kandar",
    "gn:population":0,
    "gn:timezone":"Asia/Karachi",
    "iso:country":"PK",
    "name:vie_x_preferred":[
        "Kandar"
    ],
    "wof:name":"Kandar",
    "wof:placetype":"locality"
},
  "geometry": {"coordinates":[72.70165,34.42095],"type":"Point"}
}