{
  "type": "Feature",
  "properties": {
    "gn:admin1_code":"4.0",
    "gn:asciiname":"Chak Forty-three Fateh",
    "gn:country_code":"PK",
    "gn:dem":152,
    "gn:feature_class":"P",
    "gn:feature_code":"PPL",
    "gn:name":"Chak Forty-three Fateh",
    "gn:population":0,
    "gn:timezone":"Asia/Karachi",
    "iso:country":"PK",
    "wof:name":"Chak Forty-three Fateh",
    "wof:placetype":"locality"
},
  "geometry": {"coordinates":[72.86038000000001,29.73079],"type":"Point"}
}