{
  "type": "Feature",
  "properties": {
    "gn:admin1_code":"4.0",
    "gn:asciiname":"Mahalla Hayatpura",
    "gn:country_code":"PK",
    "gn:dem":282,
    "gn:feature_class":"P",
    "gn:feature_code":"PPL",
    "gn:name":"Mahalla Hayatpura",
    "gn:population":0,
    "gn:timezone":"Asia/Karachi",
    "iso:country":"PK",
    "wof:name":"Mahalla Hayatpura",
    "wof:placetype":"locality"
},
  "geometry": {"coordinates":[73.85297,32.80244],"type":"Point"}
}