{
  "type": "Feature",
  "properties": {
    "gn:admin1_code":"4.0",
    "gn:asciiname":"Kotha Pind",
    "gn:country_code":"PK",
    "gn:dem":387,
    "gn:feature_class":"P",
    "gn:feature_code":"PPL",
    "gn:name":"Kotha Pind",
    "gn:population":0,
    "gn:timezone":"Asia/Karachi",
    "iso:country":"PK",
    "wof:name":"Kotha Pind",
    "wof:placetype":"locality"
},
  "geometry": {"coordinates":[72.54057,33.71188],"type":"Point"}
}