{
  "type": "Feature",
  "properties": {
    "gn:admin1_code":"5.0",
    "gn:asciiname":"Goth Ghazi",
    "gn:country_code":"PK",
    "gn:dem":60,
    "gn:feature_class":"P",
    "gn:feature_code":"PPL",
    "gn:name":"Goth Ghazi",
    "gn:population":0,
    "gn:timezone":"Asia/Karachi",
    "iso:country":"PK",
    "name:eng_x_preferred":[
        "Goth Gh\u0101zi"
    ],
    "wof:name":"Goth Ghazi",
    "wof:placetype":"locality"
},
  "geometry": {"coordinates":[68.71359,27.80291],"type":"Point"}
}