{
  "type": "Feature",
  "properties": {
    "gn:admin1_code":"4",
    "gn:asciiname":"Chak Eighty-nine",
    "gn:country_code":"PK",
    "gn:dem":184,
    "gn:feature_class":"P",
    "gn:feature_code":"PPL",
    "gn:name":"Chak Eighty-nine",
    "gn:population":0,
    "gn:timezone":"Asia/Karachi",
    "iso:country":"PK",
    "name:und_x_variant":[
        "Chukera",
        "Im\u0101mpura"
    ],
    "wof:name":"Chak Eighty-nine",
    "wof:placetype":"locality"
},
  "geometry": {"coordinates":[73.47669,31.54023],"type":"Point"}
}