{
  "type": "Feature",
  "properties": {
    "gn:admin1_code":"5.0",
    "gn:asciiname":"Goth Muhammad Laiq",
    "gn:country_code":"PK",
    "gn:dem":55,
    "gn:feature_class":"P",
    "gn:feature_code":"PPL",
    "gn:name":"Goth Muhammad Laiq",
    "gn:population":0,
    "gn:timezone":"Asia/Karachi",
    "iso:country":"PK",
    "name:eng_x_preferred":[
        "Goth Muhammad Laiq Rajper"
    ],
    "wof:name":"Goth Muhammad Laiq",
    "wof:placetype":"locality"
},
  "geometry": {"coordinates":[68.55054,27.29948],"type":"Point"}
}