{
  "type": "Feature",
  "properties": {
    "gn:admin1_code":"2.0",
    "gn:asciiname":"Abdul Ghani Gis",
    "gn:country_code":"PK",
    "gn:dem":1486,
    "gn:feature_class":"P",
    "gn:feature_code":"PPL",
    "gn:name":"Abdul Ghani Gis",
    "gn:population":0,
    "gn:timezone":"Asia/Karachi",
    "iso:country":"PK",
    "wof:name":"Abdul Ghani Gis",
    "wof:placetype":"locality"
},
  "geometry": {"coordinates":[63.96416,29.3189],"type":"Point"}
}