{
  "type": "Feature",
  "properties": {
    "gn:admin1_code":"5",
    "gn:asciiname":"Khuda Bakhsh",
    "gn:country_code":"PK",
    "gn:dem":25,
    "gn:feature_class":"P",
    "gn:feature_code":"PPL",
    "gn:name":"Khuda Bakhsh",
    "gn:population":0,
    "gn:timezone":"Asia/Karachi",
    "iso:country":"PK",
    "wof:name":"Khuda Bakhsh",
    "wof:placetype":"locality"
},
  "geometry": {"coordinates":[68.73524999999999,26.1351],"type":"Point"}
}