{
  "type": "Feature",
  "properties": {
    "gn:admin1_code":"3.0",
    "gn:asciiname":"Banda Tarakai",
    "gn:country_code":"PK",
    "gn:dem":431,
    "gn:feature_class":"P",
    "gn:feature_code":"PPL",
    "gn:name":"B\u0101nda Tarakai",
    "gn:population":0,
    "gn:timezone":"Asia/Karachi",
    "iso:country":"PK",
    "wof:name":"Banda Tarakai",
    "wof:placetype":"locality"
},
  "geometry": {"coordinates":[71.06667,32.78333],"type":"Point"}
}