{
  "type": "Feature",
  "properties": {
    "gn:admin1_code":"4.0",
    "gn:asciiname":"Ghadha",
    "gn:country_code":"PK",
    "gn:dem":239,
    "gn:feature_class":"P",
    "gn:feature_code":"PPL",
    "gn:name":"Ghadha",
    "gn:population":0,
    "gn:timezone":"Asia/Karachi",
    "iso:country":"PK",
    "name:und_x_variant":[
        "Dhoda",
        "Dhodha",
        "Ghadha"
    ],
    "wof:name":"Ghadha",
    "wof:placetype":"locality"
},
  "geometry": {"coordinates":[74.69334000000001,32.16137],"type":"Point"}
}