{
  "type": "Feature",
  "properties": {
    "gn:admin1_code":"04",
    "gn:asciiname":"Thatti Shahani",
    "gn:country_code":"PK",
    "gn:dem":173,
    "gn:feature_class":"P",
    "gn:feature_code":"PPL",
    "gn:name":"Thatti Shahani",
    "gn:population":0,
    "gn:timezone":"Asia/Karachi",
    "iso:country":"PK",
    "name:und_x_variant":[
        "Thatti Sh\u0101hni"
    ],
    "wof:name":"Thatti Shahani",
    "wof:placetype":"locality"
},
  "geometry": {"coordinates":[72.30249000000001,31.97323],"type":"Point"}
}