{
  "type": "Feature",
  "properties": {
    "gn:admin1_code":"4",
    "gn:asciiname":"Umar Din",
    "gn:country_code":"PK",
    "gn:dem":168,
    "gn:feature_class":"P",
    "gn:feature_code":"PPL",
    "gn:name":"Umar Din",
    "gn:population":0,
    "gn:timezone":"Asia/Karachi",
    "iso:country":"PK",
    "name:und_x_variant":[
        "Umard\u012bnw\u0101la"
    ],
    "wof:name":"Umar Din",
    "wof:placetype":"locality"
},
  "geometry": {"coordinates":[71.37127,31.49294],"type":"Point"}
}