{
  "type": "Feature",
  "properties": {
    "gn:admin1_code":"3.0",
    "gn:asciiname":"Pialo Baihk",
    "gn:country_code":"PK",
    "gn:dem":3780,
    "gn:feature_class":"P",
    "gn:feature_code":"PPL",
    "gn:name":"Pialo Baihk",
    "gn:population":0,
    "gn:timezone":"Asia/Karachi",
    "iso:country":"PK",
    "wof:name":"Pialo Baihk",
    "wof:placetype":"locality"
},
  "geometry": {"coordinates":[73.83972,35.1256],"type":"Point"}
}