{
  "type": "Feature",
  "properties": {
    "gn:admin1_code":"5.0",
    "gn:asciiname":"Goth Mango Khan",
    "gn:country_code":"PK",
    "gn:dem":54,
    "gn:feature_class":"P",
    "gn:feature_code":"PPL",
    "gn:name":"Goth Mango Khan",
    "gn:population":0,
    "gn:timezone":"Asia/Karachi",
    "iso:country":"PK",
    "name:eng_x_preferred":[
        "Goth Mungho Kh\u0101n Ch\u0101ndio"
    ],
    "wof:name":"Goth Mango Khan",
    "wof:placetype":"locality"
},
  "geometry": {"coordinates":[68.60055,27.46058],"type":"Point"}
}