{
  "type": "Feature",
  "properties": {
    "gn:admin1_code":"2.0",
    "gn:asciiname":"Kili Asad Khan",
    "gn:country_code":"PK",
    "gn:dem":1619,
    "gn:feature_class":"P",
    "gn:feature_code":"PPL",
    "gn:name":"Kili Asad Khan",
    "gn:population":0,
    "gn:timezone":"Asia/Karachi",
    "iso:country":"PK",
    "wof:name":"Kili Asad Khan",
    "wof:placetype":"locality"
},
  "geometry": {"coordinates":[66.33551,29.70081],"type":"Point"}
}