{
  "type": "Feature",
  "properties": {
    "gn:admin1_code":"2.0",
    "gn:asciiname":"Kili Abdul Rehman",
    "gn:country_code":"PK",
    "gn:dem":1158,
    "gn:feature_class":"P",
    "gn:feature_code":"PPL",
    "gn:name":"Kili Abdul Rehman",
    "gn:population":0,
    "gn:timezone":"Asia/Karachi",
    "iso:country":"PK",
    "wof:name":"Kili Abdul Rehman",
    "wof:placetype":"locality"
},
  "geometry": {"coordinates":[63.38522,29.23235],"type":"Point"}
}