{
  "type": "Feature",
  "properties": {
    "gn:admin1_code":"3.0",
    "gn:asciiname":"Tarari",
    "gn:country_code":"PK",
    "gn:dem":1262,
    "gn:feature_class":"P",
    "gn:feature_code":"PPL",
    "gn:name":"Tarari",
    "gn:population":0,
    "gn:timezone":"Asia/Karachi",
    "iso:country":"PK",
    "name:pol_x_preferred":[
        "Torrenza"
    ],
    "wof:name":"Tarari",
    "wof:placetype":"locality"
},
  "geometry": {"coordinates":[72.91104,34.34725],"type":"Point"}
}