{
  "type": "Feature",
  "properties": {
    "gn:admin1_code":"5.0",
    "gn:asciiname":"Hussain Rajar Ji Wand",
    "gn:country_code":"PK",
    "gn:dem":49,
    "gn:feature_class":"P",
    "gn:feature_code":"PPL",
    "gn:name":"Hussain Rajar Ji Wand",
    "gn:population":0,
    "gn:timezone":"Asia/Karachi",
    "iso:country":"PK",
    "wof:name":"Hussain Rajar Ji Wand",
    "wof:placetype":"locality"
},
  "geometry": {"coordinates":[69.59356,25.94073],"type":"Point"}
}