{
  "type": "Feature",
  "properties": {
    "gn:admin1_code":"4",
    "gn:asciiname":"Chhanni Rahmat Khan",
    "gn:country_code":"PK",
    "gn:dem":192,
    "gn:feature_class":"P",
    "gn:feature_code":"PPL",
    "gn:name":"Chhanni Rahmat Khan",
    "gn:population":0,
    "gn:timezone":"Asia/Karachi",
    "iso:country":"PK",
    "wof:name":"Chhanni Rahmat Khan",
    "wof:placetype":"locality"
},
  "geometry": {"coordinates":[73.19060999999998,31.94785],"type":"Point"}
}