{
  "type": "Feature",
  "properties": {
    "gn:admin1_code":"3",
    "gn:asciiname":"Kopra",
    "gn:country_code":"PK",
    "gn:dem":2488,
    "gn:feature_class":"P",
    "gn:feature_code":"PPL",
    "gn:name":"Kopra",
    "gn:population":0,
    "gn:timezone":"Asia/Karachi",
    "iso:country":"PK",
    "name:und_x_variant":[
        "Bhir",
        "Kopra"
    ],
    "wof:name":"Kopra",
    "wof:placetype":"locality"
},
  "geometry": {"coordinates":[73.39454000000001,34.56159],"type":"Point"}
}