{
  "type": "Feature",
  "properties": {
    "gn:admin1_code":"4.0",
    "gn:asciiname":"Atial",
    "gn:country_code":"PK",
    "gn:dem":252,
    "gn:feature_class":"P",
    "gn:feature_code":"PPL",
    "gn:name":"Atial",
    "gn:population":0,
    "gn:timezone":"Asia/Karachi",
    "iso:country":"PK",
    "wof:name":"Atial",
    "wof:placetype":"locality"
},
  "geometry": {"coordinates":[75.21666999999999,32.15],"type":"Point"}
}