{
  "type": "Feature",
  "properties": {
    "gn:admin1_code":"2.0",
    "gn:asciiname":"Kili Muhammad Bakhsh",
    "gn:country_code":"PK",
    "gn:dem":1847,
    "gn:feature_class":"P",
    "gn:feature_code":"PPL",
    "gn:name":"Kili Muhammad Bakhsh",
    "gn:population":0,
    "gn:timezone":"Asia/Karachi",
    "iso:country":"PK",
    "wof:name":"Kili Muhammad Bakhsh",
    "wof:placetype":"locality"
},
  "geometry": {"coordinates":[66.16840000000001,28.61969],"type":"Point"}
}