{
  "type": "Feature",
  "properties": {
    "gn:admin1_code":"03",
    "gn:asciiname":"Qalagai",
    "gn:country_code":"PK",
    "gn:dem":954,
    "gn:feature_class":"P",
    "gn:feature_code":"PPL",
    "gn:name":"Qalagai",
    "gn:population":0,
    "gn:timezone":"Asia/Karachi",
    "iso:country":"PK",
    "wof:name":"Qalagai",
    "wof:placetype":"locality"
},
  "geometry": {"coordinates":[71.91235,34.84139],"type":"Point"}
}