{
  "type": "Feature",
  "properties": {
    "gn:admin1_code":"4.0",
    "gn:asciiname":"Chak Thirty-one Dara Nawab Branch",
    "gn:country_code":"PK",
    "gn:dem":106,
    "gn:feature_class":"P",
    "gn:feature_code":"PPL",
    "gn:name":"Chak Thirty-one Dara Nawab Branch",
    "gn:population":0,
    "gn:timezone":"Asia/Karachi",
    "iso:country":"PK",
    "name:und_x_variant":[
        "Chak 31 D N B"
    ],
    "wof:name":"Chak Thirty-one Dara Nawab Branch",
    "wof:placetype":"locality"
},
  "geometry": {"coordinates":[71.34359000000001,29.07338],"type":"Point"}
}