{
  "type": "Feature",
  "properties": {
    "gn:admin1_code":"4",
    "gn:asciiname":"Dera Dilasa Khanwala",
    "gn:country_code":"PK",
    "gn:dem":239,
    "gn:feature_class":"P",
    "gn:feature_code":"PPL",
    "gn:name":"Dera Dilasa Khanwala",
    "gn:population":0,
    "gn:timezone":"Asia/Karachi",
    "iso:country":"PK",
    "name:und_x_variant":[
        "Dera Dil\u0101sa Kh\u0101n"
    ],
    "wof:name":"Dera Dilasa Khanwala",
    "wof:placetype":"locality"
},
  "geometry": {"coordinates":[71.62781,32.75503],"type":"Point"}
}