{
  "type": "Feature",
  "properties": {
    "gn:admin1_code":"6",
    "gn:asciiname":"Sanja",
    "gn:country_code":"PK",
    "gn:dem":593,
    "gn:feature_class":"P",
    "gn:feature_code":"PPL",
    "gn:name":"Sanja",
    "gn:population":0,
    "gn:timezone":"Asia/Karachi",
    "iso:country":"PK",
    "name:deu_x_preferred":[
        "Sanja"
    ],
    "name:fin_x_preferred":[
        "Sanja"
    ],
    "name:slv_x_preferred":[
        "Sanja"
    ],
    "name:und_x_variant":[
        "Pail",
        "Sanghar"
    ],
    "wof:name":"Sanja",
    "wof:placetype":"locality"
},
  "geometry": {"coordinates":[74.14049,33.0017],"type":"Point"}
}