{
  "type": "Feature",
  "properties": {
    "gn:admin1_code":"4.0",
    "gn:asciiname":"Hayat Laiwala",
    "gn:country_code":"PK",
    "gn:dem":140,
    "gn:feature_class":"P",
    "gn:feature_code":"PPL",
    "gn:name":"Hayat Laiwala",
    "gn:population":0,
    "gn:timezone":"Asia/Karachi",
    "iso:country":"PK",
    "wof:name":"Hayat Laiwala",
    "wof:placetype":"locality"
},
  "geometry": {"coordinates":[71.51486,30.82879],"type":"Point"}
}