{
  "type": "Feature",
  "properties": {
    "gn:admin1_code":"2.0",
    "gn:asciiname":"Muhammad Rasul Kili",
    "gn:country_code":"PK",
    "gn:dem":1584,
    "gn:feature_class":"P",
    "gn:feature_code":"PPL",
    "gn:name":"Muhammad Rasul Kili",
    "gn:population":0,
    "gn:timezone":"Asia/Karachi",
    "iso:country":"PK",
    "wof:name":"Muhammad Rasul Kili",
    "wof:placetype":"locality"
},
  "geometry": {"coordinates":[68.21531,30.77145],"type":"Point"}
}