{
  "type": "Feature",
  "properties": {
    "gn:admin1_code":"3.0",
    "gn:asciiname":"Sher Di Kalle",
    "gn:country_code":"PK",
    "gn:dem":340,
    "gn:feature_class":"P",
    "gn:feature_code":"PPL",
    "gn:name":"Sher Di Kalle",
    "gn:population":0,
    "gn:timezone":"Asia/Karachi",
    "iso:country":"PK",
    "name:eng_x_preferred":[
        "Sher Di Kalle"
    ],
    "name:und_x_variant":[
        "Sherdil Kili"
    ],
    "wof:name":"Sher Di Kalle",
    "wof:placetype":"locality"
},
  "geometry": {"coordinates":[71.74724999999999,34.26695],"type":"Point"}
}