{
  "type": "Feature",
  "properties": {
    "gn:admin1_code":"1.0",
    "gn:asciiname":"Kirta",
    "gn:country_code":"PK",
    "gn:dem":640,
    "gn:feature_class":"P",
    "gn:feature_code":"PPL",
    "gn:name":"Kirta",
    "gn:population":0,
    "gn:timezone":"Asia/Karachi",
    "iso:country":"PK",
    "wof:name":"Kirta",
    "wof:placetype":"locality"
},
  "geometry": {"coordinates":[70.31286,32.94661],"type":"Point"}
}