{
  "type": "Feature",
  "properties": {
    "gn:admin1_code":"4",
    "gn:asciiname":"Paharwala",
    "gn:country_code":"PK",
    "gn:dem":138,
    "gn:feature_class":"P",
    "gn:feature_code":"PPL",
    "gn:name":"Paharwala",
    "gn:population":0,
    "gn:timezone":"Asia/Karachi",
    "iso:country":"PK",
    "name:und_x_variant":[
        "Pahorw\u0101la"
    ],
    "wof:name":"Paharwala",
    "wof:placetype":"locality"
},
  "geometry": {"coordinates":[71.00083000000002,30.62924000000001],"type":"Point"}
}