{
  "type": "Feature",
  "properties": {
    "gn:admin1_code":"5",
    "gn:asciiname":"Dokri",
    "gn:country_code":"PK",
    "gn:dem":46,
    "gn:feature_class":"P",
    "gn:feature_code":"PPL",
    "gn:name":"Dokri",
    "gn:population":0,
    "gn:timezone":"Asia/Karachi",
    "iso:country":"PK",
    "name:ceb_x_preferred":[
        "Dokri"
    ],
    "name:eng_x_preferred":[
        "Dokri"
    ],
    "name:fas_x_preferred":[
        "\u062f\u06a9\u0631\u06cc"
    ],
    "name:fra_x_preferred":[
        "Dokri"
    ],
    "name:hin_x_preferred":[
        "\u0921\u094b\u0915\u0930\u0940"
    ],
    "name:pnb_x_preferred":[
        "\u0688\u0648\u06a9\u0631\u06cc"
    ],
    "name:snd_x_preferred":[
        "\u068f\u0648\u06aa\u0631\u064a"
    ],
    "name:urd_x_preferred":[
        "\u0688\u0648\u06a9\u0631\u06cc"
    ],
    "wof:name":"Dokri",
    "wof:placetype":"locality"
},
  "geometry": {"coordinates":[68.18947,26.94701],"type":"Point"}
}