{
  "type": "Feature",
  "properties": {
    "gn:admin1_code":"4",
    "gn:asciiname":"Ganjianwali Kalan",
    "gn:country_code":"PK",
    "gn:dem":240,
    "gn:feature_class":"P",
    "gn:feature_code":"PPL",
    "gn:name":"Ganjianwali Kalan",
    "gn:population":0,
    "gn:timezone":"Asia/Karachi",
    "iso:country":"PK",
    "wof:name":"Ganjianwali Kalan",
    "wof:placetype":"locality"
},
  "geometry": {"coordinates":[74.42735999999999,32.46644000000001],"type":"Point"}
}