{
  "type": "Feature",
  "properties": {
    "gn:admin1_code":"4",
    "gn:asciiname":"Chak Five Hundred Three Gugera",
    "gn:country_code":"PK",
    "gn:dem":164,
    "gn:feature_class":"P",
    "gn:feature_code":"PPL",
    "gn:name":"Chak Five Hundred Three Gugera",
    "gn:population":0,
    "gn:timezone":"Asia/Karachi",
    "iso:country":"PK",
    "name:und_x_variant":[
        "Dh\u0101l Mard\u0101na",
        "Mard\u0101na"
    ],
    "wof:name":"Chak Five Hundred Three Gugera",
    "wof:placetype":"locality"
},
  "geometry": {"coordinates":[72.77748000000003,30.75592],"type":"Point"}
}