{
  "type": "Feature",
  "properties": {
    "gn:admin1_code":"4",
    "gn:asciiname":"Tibbi Marthan",
    "gn:country_code":"PK",
    "gn:dem":190,
    "gn:feature_class":"P",
    "gn:feature_code":"PPL",
    "gn:name":"Tibbi Marthan",
    "gn:population":0,
    "gn:timezone":"Asia/Karachi",
    "iso:country":"PK",
    "name:und_x_variant":[
        "Marohi Tibbi"
    ],
    "wof:name":"Tibbi Marthan",
    "wof:placetype":"locality"
},
  "geometry": {"coordinates":[73.72877,31.27209],"type":"Point"}
}