{
  "type": "Feature",
  "properties": {
    "gn:admin1_code":"7.0",
    "gn:asciiname":"Bitnki",
    "gn:country_code":"PK",
    "gn:dem":3247,
    "gn:feature_class":"P",
    "gn:feature_code":"PPL",
    "gn:name":"Bitnki",
    "gn:population":0,
    "gn:timezone":"Asia/Karachi",
    "iso:country":"PK",
    "name:und_x_variant":[
        "Bit\u0101nki"
    ],
    "wof:name":"Bitnki",
    "wof:placetype":"locality"
},
  "geometry": {"coordinates":[73.19189,36.50116],"type":"Point"}
}