{
  "type": "Feature",
  "properties": {
    "gn:admin1_code":"3.0",
    "gn:asciiname":"Bar Chil",
    "gn:country_code":"PK",
    "gn:dem":414,
    "gn:feature_class":"P",
    "gn:feature_code":"PPL",
    "gn:name":"Bar Chil",
    "gn:population":0,
    "gn:timezone":"Asia/Karachi",
    "iso:country":"PK",
    "name:eng_x_preferred":[
        "Bar Chehal"
    ],
    "wof:name":"Bar Chil",
    "wof:placetype":"locality"
},
  "geometry": {"coordinates":[71.75400999999999,34.38143],"type":"Point"}
}