{
  "type": "Feature",
  "properties": {
    "gn:admin1_code":"5",
    "gn:asciiname":"Goth Muhammad Zaman Sihor",
    "gn:country_code":"PK",
    "gn:dem":18,
    "gn:feature_class":"P",
    "gn:feature_code":"PPL",
    "gn:name":"Goth Muhammad Zaman Sihor",
    "gn:population":0,
    "gn:timezone":"Asia/Karachi",
    "iso:country":"PK",
    "name:und_x_variant":[
        "Goth Muhammad Zam\u0101n Sihar"
    ],
    "wof:name":"Goth Muhammad Zaman Sihor",
    "wof:placetype":"locality"
},
  "geometry": {"coordinates":[69.1807,25.68727],"type":"Point"}
}