{
  "type": "Feature",
  "properties": {
    "gn:admin1_code":"3.0",
    "gn:asciiname":"Khadai Kalle",
    "gn:country_code":"PK",
    "gn:dem":382,
    "gn:feature_class":"P",
    "gn:feature_code":"PPL",
    "gn:name":"Khadai Kalle",
    "gn:population":0,
    "gn:timezone":"Asia/Karachi",
    "iso:country":"PK",
    "name:eng_x_preferred":[
        "Khadi Kalle"
    ],
    "wof:name":"Khadai Kalle",
    "wof:placetype":"locality"
},
  "geometry": {"coordinates":[71.66337,34.3394],"type":"Point"}
}