{
  "type": "Feature",
  "properties": {
    "gn:admin1_code":"5",
    "gn:asciiname":"Diro Dino Jatai",
    "gn:country_code":"PK",
    "gn:dem":64,
    "gn:feature_class":"P",
    "gn:feature_code":"PPL",
    "gn:name":"Diro Dino Jatai",
    "gn:population":0,
    "gn:timezone":"Asia/Karachi",
    "iso:country":"PK",
    "name:und_x_variant":[
        "Jatoi"
    ],
    "wof:name":"Diro Dino Jatai",
    "wof:placetype":"locality"
},
  "geometry": {"coordinates":[69.05983000000001,27.78779],"type":"Point"}
}