{
  "type": "Feature",
  "properties": {
    "gn:admin1_code":"4.0",
    "gn:asciiname":"Chak Two Hundred Sixty-one",
    "gn:country_code":"PK",
    "gn:dem":163,
    "gn:feature_class":"P",
    "gn:feature_code":"PPL",
    "gn:name":"Chak Two Hundred Sixty-one",
    "gn:population":0,
    "gn:timezone":"Asia/Karachi",
    "iso:country":"PK",
    "name:eng_x_preferred":[
        "Chak Two Hundred Sixty-one"
    ],
    "name:und_x_variant":[
        "Hum\u0101y\u016bn Bharw\u0101ni",
        "Kot Ham\u0101y\u016bn Bharw\u0101na"
    ],
    "wof:name":"Chak Two Hundred Sixty-one",
    "wof:placetype":"locality"
},
  "geometry": {"coordinates":[72.51776,31.39194],"type":"Point"}
}