{
  "type": "Feature",
  "properties": {
    "gn:admin1_code":"4.0",
    "gn:asciiname":"Kot Sethan",
    "gn:country_code":"PK",
    "gn:dem":205,
    "gn:feature_class":"P",
    "gn:feature_code":"PPL",
    "gn:name":"Kot Sethan",
    "gn:population":0,
    "gn:timezone":"Asia/Karachi",
    "iso:country":"PK",
    "name:und_x_variant":[
        "Chak Seth"
    ],
    "wof:name":"Kot Sethan",
    "wof:placetype":"locality"
},
  "geometry": {"coordinates":[73.85847,31.67978],"type":"Point"}
}