{
  "type": "Feature",
  "properties": {
    "gn:admin1_code":"4.0",
    "gn:asciiname":"Basti Meroiy",
    "gn:country_code":"PK",
    "gn:dem":84,
    "gn:feature_class":"P",
    "gn:feature_code":"PPL",
    "gn:name":"Basti Meroiy",
    "gn:population":0,
    "gn:timezone":"Asia/Karachi",
    "iso:country":"PK",
    "name:und_x_variant":[
        "Basti Miroi"
    ],
    "wof:name":"Basti Meroiy",
    "wof:placetype":"locality"
},
  "geometry": {"coordinates":[70.06759,28.75784],"type":"Point"}
}