{
  "type": "Feature",
  "properties": {
    "gn:admin1_code":"4.0",
    "gn:asciiname":"Chak Three Hundred Fifty-eight",
    "gn:country_code":"PK",
    "gn:dem":148,
    "gn:feature_class":"P",
    "gn:feature_code":"PPL",
    "gn:name":"Chak Three Hundred Fifty-eight",
    "gn:population":0,
    "gn:timezone":"Asia/Karachi",
    "iso:country":"PK",
    "name:und_x_variant":[
        "Channun Chot\u0101la"
    ],
    "wof:name":"Chak Three Hundred Fifty-eight",
    "wof:placetype":"locality"
},
  "geometry": {"coordinates":[71.20031,30.91361],"type":"Point"}
}