{
  "type": "Feature",
  "properties": {
    "gn:admin1_code":"7.0",
    "gn:asciiname":"Tholdas",
    "gn:country_code":"PK",
    "gn:dem":2394,
    "gn:feature_class":"P",
    "gn:feature_code":"PPL",
    "gn:name":"Tholdas",
    "gn:population":0,
    "gn:timezone":"Asia/Karachi",
    "iso:country":"PK",
    "name:und_x_variant":[
        "Tholdi Gorkun"
    ],
    "wof:name":"Tholdas",
    "wof:placetype":"locality"
},
  "geometry": {"coordinates":[76.11995,35.028],"type":"Point"}
}