{
  "type": "Feature",
  "properties": {
    "gn:admin1_code":"05",
    "gn:asciiname":"Goth Phullo Bandir",
    "gn:country_code":"PK",
    "gn:dem":61,
    "gn:feature_class":"P",
    "gn:feature_code":"PPL",
    "gn:name":"Goth Phullo Bandir",
    "gn:population":0,
    "gn:timezone":"Asia/Karachi",
    "iso:country":"PK",
    "name:und_x_variant":[
        "Phulo",
        "Phullo",
        "Goth Phullo Bandir"
    ],
    "wof:name":"Goth Phullo Bandir",
    "wof:placetype":"locality"
},
  "geometry": {"coordinates":[68.40468,27.52903],"type":"Point"}
}