{
  "type": "Feature",
  "properties": {
    "gn:admin1_code":"7.0",
    "gn:asciiname":"Pesat",
    "gn:country_code":"PK",
    "gn:dem":3266,
    "gn:feature_class":"P",
    "gn:feature_code":"PPL",
    "gn:name":"Pesat",
    "gn:population":0,
    "gn:timezone":"Asia/Karachi",
    "iso:country":"PK",
    "wof:name":"Pesat",
    "wof:placetype":"locality"
},
  "geometry": {"coordinates":[74.19141999999999,35.17326],"type":"Point"}
}