{
  "type": "Feature",
  "properties": {
    "gn:admin1_code":"4.0",
    "gn:asciiname":"Saidanwali Shamali",
    "gn:country_code":"PK",
    "gn:dem":167,
    "gn:feature_class":"P",
    "gn:feature_code":"PPL",
    "gn:name":"Said\u0101nw\u0101li Sham\u0101li",
    "gn:population":0,
    "gn:timezone":"Asia/Karachi",
    "iso:country":"PK",
    "wof:name":"Saidanwali Shamali",
    "wof:placetype":"locality"
},
  "geometry": {"coordinates":[71.30677,31.56881],"type":"Point"}
}