{
  "type": "Feature",
  "properties": {
    "gn:admin1_code":"3",
    "gn:asciiname":"Misuch",
    "gn:country_code":"PK",
    "gn:dem":1732,
    "gn:feature_class":"P",
    "gn:feature_code":"PPL",
    "gn:name":"Misuch",
    "gn:population":0,
    "gn:timezone":"Asia/Karachi",
    "iso:country":"PK",
    "name:und_x_variant":[
        "Masach"
    ],
    "wof:name":"Misuch",
    "wof:placetype":"locality"
},
  "geometry": {"coordinates":[73.39144,34.62568],"type":"Point"}
}