{
  "type": "Feature",
  "properties": {
    "gn:admin1_code":"6.0",
    "gn:asciiname":"Rariala",
    "gn:country_code":"PK",
    "gn:dem":360,
    "gn:feature_class":"P",
    "gn:feature_code":"PPL",
    "gn:name":"Rariala",
    "gn:population":0,
    "gn:timezone":"Asia/Karachi",
    "iso:country":"PK",
    "wof:name":"Rariala",
    "wof:placetype":"locality"
},
  "geometry": {"coordinates":[74.18415,32.92739],"type":"Point"}
}