{
  "type": "Feature",
  "properties": {
    "iso:country":"PK",
    "name:ara_x_preferred":[
        "\u062d\u0636\u0631\u0648"
    ],
    "name:ceb_x_preferred":[
        "Hazro"
    ],
    "name:eng_x_preferred":[
        "Hazro"
    ],
    "name:fas_x_preferred":[
        "\u062d\u0636\u0631\u0648"
    ],
    "name:fra_x_preferred":[
        "Hazro"
    ],
    "name:ind_x_preferred":[
        "hazro"
    ],
    "name:nld_x_preferred":[
        "Hazro"
    ],
    "name:pnb_x_preferred":[
        "\u062d\u0636\u0631\u0648"
    ],
    "name:por_x_preferred":[
        "Hazro"
    ],
    "name:unk_x_variant":[
        "Hazro City"
    ],
    "name:urd_x_preferred":[
        "\u062d\u0636\u0631\u0648"
    ],
    "qs:gn_country":"PK",
    "qs:gn_fcode":"PPL",
    "qs:gn_pop":26309,
    "qs:name":"Hazro",
    "qs:name_adm0":"Pakistan",
    "qs:name_adm1":"Punjab",
    "qs:photos":0,
    "qs:photos_1k":0,
    "qs:photos_9k":1,
    "qs:photos_9r":1,
    "qs:photos_all":1,
    "qs:photos_sr":0,
    "qs:placetype":"Town",
    "qs:pop_sr":"7",
    "qs:woe_adm0":23424922,
    "wd:wordcount":307,
    "wof:name":"Hazro",
    "wof:placetype":"locality",
    "wof:population":26309
},
  "geometry": {"coordinates":[72.49212,33.90914],"type":"Point"}
}