{
  "type": "Feature",
  "properties": {
    "gn:admin1_code":"2.0",
    "gn:asciiname":"Sinzalai Kili",
    "gn:country_code":"PK",
    "gn:dem":2128,
    "gn:feature_class":"P",
    "gn:feature_code":"PPL",
    "gn:name":"Sinzalai Kili",
    "gn:population":0,
    "gn:timezone":"Asia/Karachi",
    "iso:country":"PK",
    "wof:name":"Sinzalai Kili",
    "wof:placetype":"locality"
},
  "geometry": {"coordinates":[68.27033,31.03561],"type":"Point"}
}