{
  "type": "Feature",
  "properties": {
    "gn:admin1_code":"5.0",
    "gn:asciiname":"Gadda Khaskheli",
    "gn:country_code":"PK",
    "gn:dem":6,
    "gn:feature_class":"P",
    "gn:feature_code":"PPL",
    "gn:name":"Gadda Khaskheli",
    "gn:population":0,
    "gn:timezone":"Asia/Karachi",
    "iso:country":"PK",
    "name:und_x_variant":[
        "Kh\u0101shkeli",
        "Gadda Khaskheli"
    ],
    "wof:name":"Gadda Khaskheli",
    "wof:placetype":"locality"
},
  "geometry": {"coordinates":[67.69230999999999,24.711],"type":"Point"}
}