{
  "type": "Feature",
  "properties": {
    "gn:admin1_code":"7.0",
    "gn:asciiname":"Balor Khan di Baihk",
    "gn:country_code":"PK",
    "gn:dem":3742,
    "gn:feature_class":"P",
    "gn:feature_code":"PPL",
    "gn:name":"Balor Khan di Baihk",
    "gn:population":0,
    "gn:timezone":"Asia/Karachi",
    "iso:country":"PK",
    "wof:name":"Balor Khan di Baihk",
    "wof:placetype":"locality"
},
  "geometry": {"coordinates":[73.67289,35.92815],"type":"Point"}
}