{
  "type": "Feature",
  "properties": {
    "gn:admin1_code":"6",
    "gn:asciiname":"Chhambar",
    "gn:country_code":"PK",
    "gn:dem":1917,
    "gn:feature_class":"P",
    "gn:feature_code":"PPL",
    "gn:name":"Chhambar",
    "gn:population":0,
    "gn:timezone":"Asia/Karachi",
    "iso:country":"PK",
    "wof:name":"Chhambar",
    "wof:placetype":"locality"
},
  "geometry": {"coordinates":[73.99871,33.91294],"type":"Point"}
}