{
  "type": "Feature",
  "properties": {
    "gn:admin1_code":"7.0",
    "gn:asciiname":"Mushpar",
    "gn:country_code":"PK",
    "gn:dem":2800,
    "gn:feature_class":"P",
    "gn:feature_code":"PPL",
    "gn:name":"Mushpar",
    "gn:population":0,
    "gn:timezone":"Asia/Karachi",
    "iso:country":"PK",
    "wof:name":"Mushpar",
    "wof:placetype":"locality"
},
  "geometry": {"coordinates":[74.05481999999998,35.30577],"type":"Point"}
}