{
  "type": "Feature",
  "properties": {
    "gn:admin1_code":"4.0",
    "gn:asciiname":"Bhabra",
    "gn:country_code":"PK",
    "gn:dem":198,
    "gn:feature_class":"P",
    "gn:feature_code":"PPL",
    "gn:name":"Bhabra",
    "gn:population":0,
    "gn:timezone":"Asia/Karachi",
    "iso:country":"PK",
    "name:und_x_variant":[
        "Bhabhra",
        "Bhabra"
    ],
    "wof:name":"Bhabra",
    "wof:placetype":"locality"
},
  "geometry": {"coordinates":[73.21724,32.22729],"type":"Point"}
}