{
  "type": "Feature",
  "properties": {
    "gn:admin1_code":"5",
    "gn:asciiname":"Shahidabad",
    "gn:country_code":"PK",
    "gn:dem":21,
    "gn:feature_class":"P",
    "gn:feature_code":"PPL",
    "gn:name":"Sh\u0101h\u012bd\u0101b\u0101d",
    "gn:population":0,
    "gn:timezone":"Asia/Karachi",
    "iso:country":"PK",
    "wof:name":"Shahidabad",
    "wof:placetype":"locality"
},
  "geometry": {"coordinates":[68.96250000000001,25.30417000000001],"type":"Point"}
}