{
  "type": "Feature",
  "properties": {
    "gn:admin1_code":"4",
    "gn:asciiname":"Chak Ninety-three Gugera Branch",
    "gn:country_code":"PK",
    "gn:dem":195,
    "gn:feature_class":"P",
    "gn:feature_code":"PPL",
    "gn:name":"Chak Ninety-three Gugera Branch",
    "gn:population":0,
    "gn:timezone":"Asia/Karachi",
    "iso:country":"PK",
    "name:und_x_variant":[
        "Kandu\u0101na"
    ],
    "wof:name":"Chak Ninety-three Gugera Branch",
    "wof:placetype":"locality"
},
  "geometry": {"coordinates":[73.48201999999998,31.44903],"type":"Point"}
}