{
  "type": "Feature",
  "properties": {
    "gn:admin1_code":"5",
    "gn:asciiname":"Nawan Tar",
    "gn:country_code":"PK",
    "gn:dem":38,
    "gn:feature_class":"P",
    "gn:feature_code":"PPL",
    "gn:name":"Nawan Tar",
    "gn:population":0,
    "gn:timezone":"Asia/Karachi",
    "iso:country":"PK",
    "wof:name":"Nawan Tar",
    "wof:placetype":"locality"
},
  "geometry": {"coordinates":[69.25591,26.40111],"type":"Point"}
}