{
  "type": "Feature",
  "properties": {
    "gn:admin1_code":"3.0",
    "gn:asciiname":"Seta",
    "gn:country_code":"PK",
    "gn:dem":1716,
    "gn:feature_class":"P",
    "gn:feature_code":"PPL",
    "gn:name":"Seta",
    "gn:population":0,
    "gn:timezone":"Asia/Karachi",
    "iso:country":"PK",
    "name:deu_x_preferred":[
        "Seta"
    ],
    "name:epo_x_preferred":[
        "\u0124eto"
    ],
    "name:fra_x_preferred":[
        "Seta"
    ],
    "name:hun_x_preferred":[
        "Szeta"
    ],
    "name:ita_x_preferred":[
        "Setae"
    ],
    "name:nld_x_preferred":[
        "Seta"
    ],
    "name:pol_x_preferred":[
        "Szczecinka"
    ],
    "wof:name":"Seta",
    "wof:placetype":"locality"
},
  "geometry": {"coordinates":[72.95329,34.61713],"type":"Point"}
}