{
  "type": "Feature",
  "properties": {
    "gn:admin1_code":"04",
    "gn:asciiname":"Mianwali Qaraishian",
    "gn:country_code":"PK",
    "gn:dem":90,
    "gn:feature_class":"P",
    "gn:feature_code":"PPL",
    "gn:name":"Mianwali Qaraishian",
    "gn:population":0,
    "gn:timezone":"Asia/Karachi",
    "iso:country":"PK",
    "name:und_x_variant":[
        "Mianwali Qureshian",
        "Mi\u0101nw\u0101li Kareshian",
        "Mianwali Qaraishian",
        "Mi\u0101nw\u0101li Quraishi\u0101n"
    ],
    "wof:name":"Mianwali Qaraishian",
    "wof:placetype":"locality"
},
  "geometry": {"coordinates":[70.39952,28.66071],"type":"Point"}
}