{
  "type": "Feature",
  "properties": {
    "gn:admin1_code":"4.0",
    "gn:asciiname":"Harpoke",
    "gn:country_code":"PK",
    "gn:dem":217,
    "gn:feature_class":"P",
    "gn:feature_code":"PPL",
    "gn:name":"Harpoke",
    "gn:population":0,
    "gn:timezone":"Asia/Karachi",
    "iso:country":"PK",
    "name:und_x_variant":[
        "Narpoki",
        "Harpoki",
        "Herpoke",
        "Harpoke"
    ],
    "wof:name":"Harpoke",
    "wof:placetype":"locality"
},
  "geometry": {"coordinates":[74.13656,31.91055],"type":"Point"}
}