{
  "type": "Feature",
  "properties": {
    "gn:admin1_code":"4",
    "gn:asciiname":"Wahi Mochianwali",
    "gn:country_code":"PK",
    "gn:dem":111,
    "gn:feature_class":"P",
    "gn:feature_code":"PPL",
    "gn:name":"Wahi Mochianwali",
    "gn:population":0,
    "gn:timezone":"Asia/Karachi",
    "iso:country":"PK",
    "name:und_x_variant":[
        "W\u0101hi Mochi\u0101n"
    ],
    "wof:name":"Wahi Mochianwali",
    "wof:placetype":"locality"
},
  "geometry": {"coordinates":[71.33725,29.30091],"type":"Point"}
}