{
  "type": "Feature",
  "properties": {
    "gn:admin1_code":"4",
    "gn:asciiname":"Chak Loharan",
    "gn:country_code":"PK",
    "gn:dem":250,
    "gn:feature_class":"P",
    "gn:feature_code":"PPL",
    "gn:name":"Chak Loharan",
    "gn:population":0,
    "gn:timezone":"Asia/Karachi",
    "iso:country":"PK",
    "name:und_x_variant":[
        "Chak Lwar\u0101nda"
    ],
    "wof:name":"Chak Loharan",
    "wof:placetype":"locality"
},
  "geometry": {"coordinates":[74.64976999999998,32.42039],"type":"Point"}
}