{
  "type": "Feature",
  "properties": {
    "gn:admin1_code":"3",
    "gn:asciiname":"Danna",
    "gn:country_code":"PK",
    "gn:dem":1223,
    "gn:feature_class":"P",
    "gn:feature_code":"PPL",
    "gn:name":"Danna",
    "gn:population":0,
    "gn:timezone":"Asia/Karachi",
    "iso:country":"PK",
    "name:ceb_x_preferred":[
        "Danna"
    ],
    "name:deu_x_preferred":[
        "Danna"
    ],
    "name:fra_x_preferred":[
        "Danna"
    ],
    "name:ita_x_preferred":[
        "Danna"
    ],
    "name:rus_x_preferred":[
        "\u0414\u0430\u043d\u043d\u0430"
    ],
    "name:swe_x_preferred":[
        "Danna"
    ],
    "name:und_x_variant":[
        "Danna B\u0101ndi"
    ],
    "wof:name":"Danna",
    "wof:placetype":"locality"
},
  "geometry": {"coordinates":[73.14438,34.35602],"type":"Point"}
}