{
  "type": "Feature",
  "properties": {
    "gn:admin1_code":"2.0",
    "gn:asciiname":"Kili Gharibabad Topian",
    "gn:country_code":"PK",
    "gn:dem":739,
    "gn:feature_class":"P",
    "gn:feature_code":"PPL",
    "gn:name":"Kili Gharibabad Topian",
    "gn:population":0,
    "gn:timezone":"Asia/Karachi",
    "iso:country":"PK",
    "name:und_x_variant":[
        "Kili Gharib\u0101b\u0101d"
    ],
    "wof:name":"Kili Gharibabad Topian",
    "wof:placetype":"locality"
},
  "geometry": {"coordinates":[65.56846999999999,28.62941],"type":"Point"}
}