{
  "type": "Feature",
  "properties": {
    "gn:admin1_code":"8.0",
    "gn:asciiname":"Cherah",
    "gn:country_code":"PK",
    "gn:dem":593,
    "gn:feature_class":"P",
    "gn:feature_code":"PPL",
    "gn:name":"Cher\u0101h",
    "gn:population":0,
    "gn:timezone":"Asia/Karachi",
    "iso:country":"PK",
    "wof:name":"Cherah",
    "wof:placetype":"locality"
},
  "geometry": {"coordinates":[73.28274,33.64583],"type":"Point"}
}