{
  "type": "Feature",
  "properties": {
    "gn:admin1_code":"1.0",
    "gn:asciiname":"Retara",
    "gn:country_code":"PK",
    "gn:dem":1658,
    "gn:feature_class":"P",
    "gn:feature_code":"PPL",
    "gn:name":"Retara",
    "gn:population":0,
    "gn:timezone":"Asia/Karachi",
    "iso:country":"PK",
    "wof:name":"Retara",
    "wof:placetype":"locality"
},
  "geometry": {"coordinates":[71.06950000000001,34.5604],"type":"Point"}
}