{
  "type": "Feature",
  "properties": {
    "gn:admin1_code":"4.0",
    "gn:asciiname":"Kanwali",
    "gn:country_code":"PK",
    "gn:dem":432,
    "gn:feature_class":"P",
    "gn:feature_code":"PPL",
    "gn:name":"Kanwali",
    "gn:population":0,
    "gn:timezone":"Asia/Karachi",
    "iso:country":"PK",
    "name:hin_x_preferred":[
        "\u0915\u093e\u0902\u0935\u0932\u0940"
    ],
    "wof:name":"Kanwali",
    "wof:placetype":"locality"
},
  "geometry": {"coordinates":[72.03043000000002,32.75069000000001],"type":"Point"}
}