{
  "type": "Feature",
  "properties": {
    "gn:admin1_code":"3.0",
    "gn:asciiname":"Shonkan Mohaian",
    "gn:country_code":"PK",
    "gn:dem":1341,
    "gn:feature_class":"P",
    "gn:feature_code":"PPL",
    "gn:name":"Shonkan Mohaian",
    "gn:population":0,
    "gn:timezone":"Asia/Karachi",
    "iso:country":"PK",
    "wof:name":"Shonkan Mohaian",
    "wof:placetype":"locality"
},
  "geometry": {"coordinates":[73.1587,34.27274],"type":"Point"}
}