{
  "type": "Feature",
  "properties": {
    "gn:admin1_code":"4",
    "gn:asciiname":"Basti Dinewala",
    "gn:country_code":"PK",
    "gn:dem":133,
    "gn:feature_class":"P",
    "gn:feature_code":"PPL",
    "gn:name":"Basti Dinewala",
    "gn:population":0,
    "gn:timezone":"Asia/Karachi",
    "iso:country":"PK",
    "name:und_x_variant":[
        "D\u012brew\u0101la"
    ],
    "wof:name":"Basti Dinewala",
    "wof:placetype":"locality"
},
  "geometry": {"coordinates":[71.89775,30.33526],"type":"Point"}
}