{
  "type": "Feature",
  "properties": {
    "gn:admin1_code":"3",
    "gn:asciiname":"Kalegah",
    "gn:country_code":"PK",
    "gn:dem":1097,
    "gn:feature_class":"P",
    "gn:feature_code":"PPL",
    "gn:name":"Kalegah",
    "gn:population":0,
    "gn:timezone":"Asia/Karachi",
    "iso:country":"PK",
    "name:und_x_variant":[
        "Koleg\u0101h"
    ],
    "wof:name":"Kalegah",
    "wof:placetype":"locality"
},
  "geometry": {"coordinates":[73.26365,34.51603],"type":"Point"}
}