{
  "type": "Feature",
  "properties": {
    "gn:admin1_code":"4",
    "gn:asciiname":"Chak Thirty-nine Desert Branch",
    "gn:country_code":"PK",
    "gn:dem":121,
    "gn:feature_class":"P",
    "gn:feature_code":"PPL",
    "gn:name":"Chak Thirty-nine Desert Branch",
    "gn:population":0,
    "gn:timezone":"Asia/Karachi",
    "iso:country":"PK",
    "name:und_x_variant":[
        "Chak Thirty-nine D B"
    ],
    "wof:name":"Chak Thirty-nine Desert Branch",
    "wof:placetype":"locality"
},
  "geometry": {"coordinates":[71.84562,29.2296],"type":"Point"}
}