{
  "type": "Feature",
  "properties": {
    "gn:admin1_code":"1.0",
    "gn:asciiname":"Badame Kalle",
    "gn:country_code":"PK",
    "gn:dem":2133,
    "gn:feature_class":"P",
    "gn:feature_code":"PPL",
    "gn:name":"Badame Kalle",
    "gn:population":0,
    "gn:timezone":"Asia/Karachi",
    "iso:country":"PK",
    "wof:name":"Badame Kalle",
    "wof:placetype":"locality"
},
  "geometry": {"coordinates":[70.77478000000001,33.68932],"type":"Point"}
}