{
  "type": "Feature",
  "properties": {
    "gn:admin1_code":"2.0",
    "gn:asciiname":"Kili Pholad",
    "gn:country_code":"PK",
    "gn:dem":983,
    "gn:feature_class":"P",
    "gn:feature_code":"PPL",
    "gn:name":"Kili Pholad",
    "gn:population":0,
    "gn:timezone":"Asia/Karachi",
    "iso:country":"PK",
    "wof:name":"Kili Pholad",
    "wof:placetype":"locality"
},
  "geometry": {"coordinates":[66.14941,27.02955],"type":"Point"}
}