{
  "type": "Feature",
  "properties": {
    "gn:admin1_code":"4.0",
    "gn:asciiname":"Chak Haiderabad Nawan",
    "gn:country_code":"PK",
    "gn:dem":173,
    "gn:feature_class":"P",
    "gn:feature_code":"PPL",
    "gn:name":"Chak Haiderabad Nawan",
    "gn:population":0,
    "gn:timezone":"Asia/Karachi",
    "iso:country":"PK",
    "name:und_x_variant":[
        "Chak Haidar\u0101b\u0101d"
    ],
    "wof:name":"Chak Haiderabad Nawan",
    "wof:placetype":"locality"
},
  "geometry": {"coordinates":[73.6721,30.40304],"type":"Point"}
}