{
  "type": "Feature",
  "properties": {
    "gn:admin1_code":"1.0",
    "gn:asciiname":"Hurmaz Kalle",
    "gn:country_code":"PK",
    "gn:dem":688,
    "gn:feature_class":"P",
    "gn:feature_code":"PPL",
    "gn:name":"Hurmaz Kalle",
    "gn:population":0,
    "gn:timezone":"Asia/Karachi",
    "iso:country":"PK",
    "name:und_x_variant":[
        "Hurmaz"
    ],
    "wof:name":"Hurmaz Kalle",
    "wof:placetype":"locality"
},
  "geometry": {"coordinates":[70.25374000000001,32.96552],"type":"Point"}
}