{
  "type": "Feature",
  "properties": {
    "gn:admin1_code":"4",
    "gn:asciiname":"Chak Five Hundred Eleven Gugera Branch",
    "gn:country_code":"PK",
    "gn:dem":164,
    "gn:feature_class":"P",
    "gn:feature_code":"PPL",
    "gn:name":"Chak Five Hundred Eleven Gugera Branch",
    "gn:population":0,
    "gn:timezone":"Asia/Karachi",
    "iso:country":"PK",
    "name:und_x_variant":[
        "Chak Five Hundred Eleven GB",
        "J\u0101m Kur\u0101I",
        "Jiwew\u0101la",
        "Chak Five Hundred Eleven Gugera Branch",
        "Jiweka"
    ],
    "wof:name":"Chak Five Hundred Eleven Gugera Branch",
    "wof:placetype":"locality"
},
  "geometry": {"coordinates":[72.73994999999999,30.81317],"type":"Point"}
}