{
  "type": "Feature",
  "properties": {
    "gn:admin1_code":"2.0",
    "gn:asciiname":"Kili Muhammad Musa",
    "gn:country_code":"PK",
    "gn:dem":1226,
    "gn:feature_class":"P",
    "gn:feature_code":"PPL",
    "gn:name":"Kili Muhammad Musa",
    "gn:population":0,
    "gn:timezone":"Asia/Karachi",
    "iso:country":"PK",
    "name:und_x_variant":[
        "H\u0101ji Ab\u0101d"
    ],
    "wof:name":"Kili Muhammad Musa",
    "wof:placetype":"locality"
},
  "geometry": {"coordinates":[66.30115000000001,27.27421],"type":"Point"}
}