{
  "type": "Feature",
  "properties": {
    "gn:admin1_code":"4",
    "gn:asciiname":"Basti Dusti",
    "gn:country_code":"PK",
    "gn:dem":102,
    "gn:feature_class":"P",
    "gn:feature_code":"PPL",
    "gn:name":"Basti Dusti",
    "gn:population":0,
    "gn:timezone":"Asia/Karachi",
    "iso:country":"PK",
    "name:und_x_variant":[
        "Basti Mori Dasti"
    ],
    "wof:name":"Basti Dusti",
    "wof:placetype":"locality"
},
  "geometry": {"coordinates":[70.54763,29.35674],"type":"Point"}
}