{
  "type": "Feature",
  "properties": {
    "gn:admin1_code":"4",
    "gn:asciiname":"Bhaun Sharqi",
    "gn:country_code":"PK",
    "gn:dem":174,
    "gn:feature_class":"P",
    "gn:feature_code":"PPL",
    "gn:name":"Bhaun Sharqi",
    "gn:population":0,
    "gn:timezone":"Asia/Karachi",
    "iso:country":"PK",
    "wof:name":"Bhaun Sharqi",
    "wof:placetype":"locality"
},
  "geometry": {"coordinates":[71.08333,31.86944],"type":"Point"}
}