{
  "type": "Feature",
  "properties": {
    "gn:admin1_code":"2",
    "gn:asciiname":"Faizullah Shahr",
    "gn:country_code":"PK",
    "gn:dem":928,
    "gn:feature_class":"P",
    "gn:feature_code":"PPL",
    "gn:name":"Faizullah Shahr",
    "gn:population":0,
    "gn:timezone":"Asia/Karachi",
    "iso:country":"PK",
    "name:eng_x_preferred":[
        "Faizullah Shahr"
    ],
    "wof:name":"Faizullah Shahr",
    "wof:placetype":"locality"
},
  "geometry": {"coordinates":[68.75773000000001,30.01061],"type":"Point"}
}