{
  "type": "Feature",
  "properties": {
    "gn:admin1_code":"4.0",
    "gn:asciiname":"Lodhran",
    "gn:country_code":"PK",
    "gn:dem":105,
    "gn:feature_class":"P",
    "gn:feature_code":"PPL",
    "gn:name":"Lodhr\u0101n",
    "gn:population":0,
    "gn:timezone":"Asia/Karachi",
    "iso:country":"PK",
    "wof:name":"Lodhran",
    "wof:placetype":"locality"
},
  "geometry": {"coordinates":[71.22358,29.307],"type":"Point"}
}