{
  "type": "Feature",
  "properties": {
    "gn:admin1_code":"4.0",
    "gn:asciiname":"Bhur",
    "gn:country_code":"PK",
    "gn:dem":174,
    "gn:feature_class":"P",
    "gn:feature_code":"PPL",
    "gn:name":"Bhur",
    "gn:population":0,
    "gn:timezone":"Asia/Karachi",
    "iso:country":"PK",
    "name:ceb_x_preferred":[
        "Bhoor"
    ],
    "name:msa_x_preferred":[
        "Bhoor"
    ],
    "name:nep_x_preferred":[
        "\u092d\u0941\u0930"
    ],
    "name:new_x_preferred":[
        "\u092d\u0941\u0930"
    ],
    "name:pol_x_preferred":[
        "Bhoor"
    ],
    "name:und_x_variant":[
        "Bohr",
        "Bhur"
    ],
    "wof:name":"Bhur",
    "wof:placetype":"locality"
},
  "geometry": {"coordinates":[73.12156999999998,30.78853],"type":"Point"}
}