{
  "type": "Feature",
  "properties": {
    "gn:admin1_code":"4.0",
    "gn:asciiname":"Basti Pidri",
    "gn:country_code":"PK",
    "gn:dem":1187,
    "gn:feature_class":"P",
    "gn:feature_code":"PPL",
    "gn:name":"Basti Pidri",
    "gn:population":0,
    "gn:timezone":"Asia/Karachi",
    "iso:country":"PK",
    "wof:name":"Basti Pidri",
    "wof:placetype":"locality"
},
  "geometry": {"coordinates":[69.92336999999999,29.96252],"type":"Point"}
}