{
  "type": "Feature",
  "properties": {
    "gn:admin1_code":"2.0",
    "gn:asciiname":"Roshanabad",
    "gn:country_code":"PK",
    "gn:dem":1610,
    "gn:feature_class":"P",
    "gn:feature_code":"PPL",
    "gn:name":"Roshanabad",
    "gn:population":0,
    "gn:timezone":"Asia/Karachi",
    "iso:country":"PK",
    "wof:name":"Roshanabad",
    "wof:placetype":"locality"
},
  "geometry": {"coordinates":[66.10727,28.20196],"type":"Point"}
}