{
  "type": "Feature",
  "properties": {
    "gn:admin1_code":"03",
    "gn:asciiname":"Wazir Kili",
    "gn:country_code":"PK",
    "gn:dem":334,
    "gn:feature_class":"P",
    "gn:feature_code":"PPL",
    "gn:name":"Wazir Kili",
    "gn:population":0,
    "gn:timezone":"Asia/Karachi",
    "iso:country":"PK",
    "name:und_x_variant":[
        "Wazir Kalli",
        "Wazir Kili"
    ],
    "wof:name":"Wazir Kili",
    "wof:placetype":"locality"
},
  "geometry": {"coordinates":[71.47688000000002,34.16718],"type":"Point"}
}