{
  "type": "Feature",
  "properties": {
    "gn:admin1_code":"3.0",
    "gn:asciiname":"Anzaro Kalle Qala",
    "gn:country_code":"PK",
    "gn:dem":374,
    "gn:feature_class":"P",
    "gn:feature_code":"PPL",
    "gn:name":"Anzaro Kalle Qala",
    "gn:population":0,
    "gn:timezone":"Asia/Karachi",
    "iso:country":"PK",
    "name:eng_x_preferred":[
        "\u012anzar Kalle"
    ],
    "name:und_x_variant":[
        "Inzar Kili",
        "Anzaro Kalle Qala"
    ],
    "wof:name":"Anzaro Kalle Qala",
    "wof:placetype":"locality"
},
  "geometry": {"coordinates":[71.68163,34.32961],"type":"Point"}
}