{
  "type": "Feature",
  "properties": {
    "gn:admin1_code":"2.0",
    "gn:asciiname":"Haji Muhammad Jan Sasoli",
    "gn:country_code":"PK",
    "gn:dem":931,
    "gn:feature_class":"P",
    "gn:feature_code":"PPL",
    "gn:name":"Haji Muhammad Jan Sasoli",
    "gn:population":0,
    "gn:timezone":"Asia/Karachi",
    "iso:country":"PK",
    "name:und_x_variant":[
        "Shik\u0101ri Bent"
    ],
    "wof:name":"Haji Muhammad Jan Sasoli",
    "wof:placetype":"locality"
},
  "geometry": {"coordinates":[65.64504000000001,28.8462],"type":"Point"}
}