{
  "type": "Feature",
  "properties": {
    "gn:admin1_code":"04",
    "gn:asciiname":"Saghar Pur",
    "gn:country_code":"PK",
    "gn:dem":207,
    "gn:feature_class":"P",
    "gn:feature_code":"PPL",
    "gn:name":"Saghar Pur",
    "gn:population":0,
    "gn:timezone":"Asia/Karachi",
    "iso:country":"PK",
    "name:fas_x_preferred":[
        "\u0633\u0627\u063a\u0631\u067e\u0648\u0631"
    ],
    "name:und_x_variant":[
        "S\u0101gharpur"
    ],
    "name:urd_x_preferred":[
        "\u0633\u0627\u063a\u0631 \u067e\u0631"
    ],
    "wof:name":"Saghar Pur",
    "wof:placetype":"locality"
},
  "geometry": {"coordinates":[73.33757,32.64966],"type":"Point"}
}