{
  "type": "Feature",
  "properties": {
    "gn:admin1_code":"3.0",
    "gn:asciiname":"Gagra",
    "gn:country_code":"PK",
    "gn:dem":668,
    "gn:feature_class":"P",
    "gn:feature_code":"PPL",
    "gn:name":"Gagra",
    "gn:population":0,
    "gn:timezone":"Asia/Karachi",
    "iso:country":"PK",
    "name:und_x_variant":[
        "Gogra"
    ],
    "wof:name":"Gagra",
    "wof:placetype":"locality"
},
  "geometry": {"coordinates":[72.54138,34.47768],"type":"Point"}
}