{
  "type": "Feature",
  "properties": {
    "gn:admin1_code":"5.0",
    "gn:asciiname":"Baloch Goth",
    "gn:country_code":"PK",
    "gn:dem":60,
    "gn:feature_class":"P",
    "gn:feature_code":"PPL",
    "gn:name":"Baloch Goth",
    "gn:population":0,
    "gn:timezone":"Asia/Karachi",
    "iso:country":"PK",
    "name:eng_x_preferred":[
        "Baloch Goth"
    ],
    "name:snd_x_preferred":[
        "\u0628\u0644\u0648\u0686 \u06b3\u0648\u067a"
    ],
    "wof:name":"Baloch Goth",
    "wof:placetype":"locality"
},
  "geometry": {"coordinates":[68.53553000000001,27.78592],"type":"Point"}
}