{
  "type": "Feature",
  "properties": {
    "gn:admin1_code":"3",
    "gn:asciiname":"Bhalkri",
    "gn:country_code":"PK",
    "gn:dem":2314,
    "gn:feature_class":"P",
    "gn:feature_code":"PPL",
    "gn:name":"Bhalkri",
    "gn:population":0,
    "gn:timezone":"Asia/Karachi",
    "iso:country":"PK",
    "name:und_x_variant":[
        "Bhakri\u0101n"
    ],
    "wof:name":"Bhalkri",
    "wof:placetype":"locality"
},
  "geometry": {"coordinates":[73.51635999999998,34.81333],"type":"Point"}
}