{
  "type": "Feature",
  "properties": {
    "gn:admin1_code":"4.0",
    "gn:asciiname":"Chak Ninety-nine Rakh Branch",
    "gn:country_code":"PK",
    "gn:dem":193,
    "gn:feature_class":"P",
    "gn:feature_code":"PPL",
    "gn:name":"Chak Ninety-nine Rakh Branch",
    "gn:population":0,
    "gn:timezone":"Asia/Karachi",
    "iso:country":"PK",
    "name:und_x_variant":[
        "Jandiala Kalan",
        "Jandi\u0101la",
        "Chak Ninety-nine Rakh Branch"
    ],
    "wof:name":"Chak Ninety-nine Rakh Branch",
    "wof:placetype":"locality"
},
  "geometry": {"coordinates":[73.37866,31.46817],"type":"Point"}
}