{
  "type": "Feature",
  "properties": {
    "gn:admin1_code":"4",
    "gn:asciiname":"Husainwala",
    "gn:country_code":"PK",
    "gn:dem":126,
    "gn:feature_class":"P",
    "gn:feature_code":"PPL",
    "gn:name":"Husainw\u0101la",
    "gn:population":0,
    "gn:timezone":"Asia/Karachi",
    "iso:country":"PK",
    "name:eng_x_preferred":[
        "Husainw\u0101la"
    ],
    "wof:name":"Husainwala",
    "wof:placetype":"locality"
},
  "geometry": {"coordinates":[70.97156,30.32845],"type":"Point"}
}