{
  "type": "Feature",
  "properties": {
    "gn:admin1_code":"4",
    "gn:asciiname":"Mianiwala",
    "gn:country_code":"PK",
    "gn:dem":123,
    "gn:feature_class":"P",
    "gn:feature_code":"PPL",
    "gn:name":"Mianiwala",
    "gn:population":0,
    "gn:timezone":"Asia/Karachi",
    "iso:country":"PK",
    "name:eng_x_preferred":[
        "Mi\u0101n\u012bw\u0101la"
    ],
    "wof:name":"Mianiwala",
    "wof:placetype":"locality"
},
  "geometry": {"coordinates":[70.95815999999998,30.08864],"type":"Point"}
}