{
  "type": "Feature",
  "properties": {
    "gn:admin1_code":"5",
    "gn:asciiname":"Goth Nur Muhammad Siayal",
    "gn:country_code":"PK",
    "gn:dem":54,
    "gn:feature_class":"P",
    "gn:feature_code":"PPL",
    "gn:name":"Goth Nur Muhammad Siayal",
    "gn:population":0,
    "gn:timezone":"Asia/Karachi",
    "iso:country":"PK",
    "name:und_x_variant":[
        "Goth N\u016br Muhammad Si\u0101l"
    ],
    "wof:name":"Goth Nur Muhammad Siayal",
    "wof:placetype":"locality"
},
  "geometry": {"coordinates":[68.51204,27.33442],"type":"Point"}
}