{
  "type": "Feature",
  "properties": {
    "gn:admin1_code":"5",
    "gn:asciiname":"Allah Waraio",
    "gn:country_code":"PK",
    "gn:dem":66,
    "gn:feature_class":"P",
    "gn:feature_code":"PPL",
    "gn:name":"Allah Waraio",
    "gn:population":0,
    "gn:timezone":"Asia/Karachi",
    "iso:country":"PK",
    "name:und_x_variant":[
        "Alah War\u0101io"
    ],
    "wof:name":"Allah Waraio",
    "wof:placetype":"locality"
},
  "geometry": {"coordinates":[68.82163,28.18087],"type":"Point"}
}