{
  "type": "Feature",
  "properties": {
    "gn:admin1_code":"2.0",
    "gn:asciiname":"Rodlin",
    "gn:country_code":"PK",
    "gn:dem":1460,
    "gn:feature_class":"P",
    "gn:feature_code":"PPL",
    "gn:name":"Rodlin",
    "gn:population":0,
    "gn:timezone":"Asia/Karachi",
    "iso:country":"PK",
    "name:und_x_variant":[
        "Rodl\u012bn"
    ],
    "wof:name":"Rodlin",
    "wof:placetype":"locality"
},
  "geometry": {"coordinates":[68.57293,30.38476],"type":"Point"}
}