{
  "type": "Feature",
  "properties": {
    "gn:admin1_code":"1.0",
    "gn:asciiname":"Chinaro Kalle",
    "gn:country_code":"PK",
    "gn:dem":1269,
    "gn:feature_class":"P",
    "gn:feature_code":"PPL",
    "gn:name":"Chinaro Kalle",
    "gn:population":0,
    "gn:timezone":"Asia/Karachi",
    "iso:country":"PK",
    "wof:name":"Chinaro Kalle",
    "wof:placetype":"locality"
},
  "geometry": {"coordinates":[70.26835,33.75601],"type":"Point"}
}