{
  "type": "Feature",
  "properties": {
    "gn:admin1_code":"3",
    "gn:asciiname":"Bhatian",
    "gn:country_code":"PK",
    "gn:dem":937,
    "gn:feature_class":"P",
    "gn:feature_code":"PPL",
    "gn:name":"Bhatian",
    "gn:population":0,
    "gn:timezone":"Asia/Karachi",
    "iso:country":"PK",
    "wof:name":"Bhatian",
    "wof:placetype":"locality"
},
  "geometry": {"coordinates":[73.12113000000002,34.43137],"type":"Point"}
}