{
  "type": "Feature",
  "properties": {
    "gn:admin1_code":"3",
    "gn:asciiname":"Serai",
    "gn:country_code":"PK",
    "gn:dem":621,
    "gn:feature_class":"P",
    "gn:feature_code":"PPL",
    "gn:name":"Serai",
    "gn:population":0,
    "gn:timezone":"Asia/Karachi",
    "iso:country":"PK",
    "name:und_x_variant":[
        "Sira"
    ],
    "wof:name":"Serai",
    "wof:placetype":"locality"
},
  "geometry": {"coordinates":[72.60325999999998,34.24067],"type":"Point"}
}