{
  "type": "Feature",
  "properties": {
    "gn:admin1_code":"4",
    "gn:asciiname":"Muhammad Sharifwala",
    "gn:country_code":"PK",
    "gn:dem":93,
    "gn:feature_class":"P",
    "gn:feature_code":"PPL",
    "gn:name":"Muhammad Sharifwala",
    "gn:population":0,
    "gn:timezone":"Asia/Karachi",
    "iso:country":"PK",
    "name:und_x_variant":[
        "Muhammad Sharifw\u0101la"
    ],
    "wof:name":"Muhammad Sharifwala",
    "wof:placetype":"neighbourhood"
},
  "geometry": {"coordinates":[70.33992000000001,29.09241],"type":"Point"}
}