{
  "type": "Feature",
  "properties": {
    "gn:admin1_code":"5.0",
    "gn:asciiname":"Gadra",
    "gn:country_code":"PK",
    "gn:dem":141,
    "gn:feature_class":"P",
    "gn:feature_code":"PPL",
    "gn:name":"Gadra",
    "gn:population":0,
    "gn:timezone":"Asia/Karachi",
    "iso:country":"PK",
    "name:und_x_variant":[
        "Godra",
        "Gadro",
        "Gadra"
    ],
    "wof:name":"Gadra",
    "wof:placetype":"locality"
},
  "geometry": {"coordinates":[70.62364000000002,25.66591],"type":"Point"}
}