{
  "type": "Feature",
  "properties": {
    "gn:admin1_code":"4.0",
    "gn:asciiname":"Kot Ahdian",
    "gn:country_code":"PK",
    "gn:dem":216,
    "gn:feature_class":"P",
    "gn:feature_code":"PPL",
    "gn:name":"Kot Ahdian",
    "gn:population":0,
    "gn:timezone":"Asia/Karachi",
    "iso:country":"PK",
    "name:und_x_variant":[
        "Dhengr\u0101nw\u0101li",
        "Rakh Ahdi\u0101n",
        "Kot Ahdian"
    ],
    "wof:name":"Kot Ahdian",
    "wof:placetype":"locality"
},
  "geometry": {"coordinates":[74.42408,31.82464],"type":"Point"}
}