{
  "type": "Feature",
  "properties": {
    "gn:admin1_code":"2.0",
    "gn:asciiname":"Kabir Khan Badini Kili",
    "gn:country_code":"PK",
    "gn:dem":957,
    "gn:feature_class":"P",
    "gn:feature_code":"PPL",
    "gn:name":"Kabir Khan Badini Kili",
    "gn:population":0,
    "gn:timezone":"Asia/Karachi",
    "iso:country":"PK",
    "wof:name":"Kabir Khan Badini Kili",
    "wof:placetype":"locality"
},
  "geometry": {"coordinates":[65.98524999999999,29.64538],"type":"Point"}
}