{
  "type": "Feature",
  "properties": {
    "gn:admin1_code":"4",
    "gn:asciiname":"Moman Khurd",
    "gn:country_code":"PK",
    "gn:dem":242,
    "gn:feature_class":"P",
    "gn:feature_code":"PPL",
    "gn:name":"Moman Khurd",
    "gn:population":0,
    "gn:timezone":"Asia/Karachi",
    "iso:country":"PK",
    "name:und_x_variant":[
        "Naw\u0101n",
        "Mom\u0101n"
    ],
    "wof:name":"Moman Khurd",
    "wof:placetype":"locality"
},
  "geometry": {"coordinates":[74.45905999999999,32.46615],"type":"Point"}
}