{
  "type": "Feature",
  "properties": {
    "gn:admin1_code":"6",
    "gn:asciiname":"Kalpur",
    "gn:country_code":"PK",
    "gn:dem":1634,
    "gn:feature_class":"P",
    "gn:feature_code":"PPL",
    "gn:name":"Kalpur",
    "gn:population":0,
    "gn:timezone":"Asia/Karachi",
    "iso:country":"PK",
    "name:und_x_variant":[
        "Katpur"
    ],
    "wof:name":"Kalpur",
    "wof:placetype":"locality"
},
  "geometry": {"coordinates":[73.83783000000003,33.75882],"type":"Point"}
}