{
  "type": "Feature",
  "properties": {
    "gn:admin1_code":"2",
    "gn:asciiname":"Ghulam Mustafa",
    "gn:country_code":"PK",
    "gn:dem":53,
    "gn:feature_class":"P",
    "gn:feature_code":"PPL",
    "gn:name":"Ghulam Mustafa",
    "gn:population":0,
    "gn:timezone":"Asia/Karachi",
    "iso:country":"PK",
    "name:und_x_variant":[
        "Ghul\u0101m Mast\u0101fa"
    ],
    "name:urd_x_preferred":[
        "\u063a\u0644\u0627\u0645 \u0645\u0635\u0637\u0641\u06cc\u0670"
    ],
    "wof:name":"Ghulam Mustafa",
    "wof:placetype":"locality"
},
  "geometry": {"coordinates":[67.99370999999999,28.1616],"type":"Point"}
}