{
  "type": "Feature",
  "properties": {
    "gn:admin1_code":"04",
    "gn:asciiname":"Nari",
    "gn:country_code":"PK",
    "gn:dem":203,
    "gn:feature_class":"P",
    "gn:feature_code":"PPL",
    "gn:name":"Nari",
    "gn:population":0,
    "gn:timezone":"Asia/Karachi",
    "iso:country":"PK",
    "name:ceb_x_preferred":[
        "Nari"
    ],
    "name:deu_x_preferred":[
        "Nari"
    ],
    "name:swe_x_preferred":[
        "Nari"
    ],
    "name:ukr_x_preferred":[
        "\u041d\u0430\u0440\u0456"
    ],
    "name:und_x_variant":[
        "Nari Shumali"
    ],
    "wof:name":"Nari",
    "wof:placetype":"locality"
},
  "geometry": {"coordinates":[72.40966999999998,32.46892],"type":"Point"}
}