{
  "type": "Feature",
  "properties": {
    "gn:admin1_code":"6",
    "gn:asciiname":"Banala",
    "gn:country_code":"PK",
    "gn:dem":1191,
    "gn:feature_class":"P",
    "gn:feature_code":"PPL",
    "gn:name":"Banala",
    "gn:population":0,
    "gn:timezone":"Asia/Karachi",
    "iso:country":"PK",
    "wof:name":"Banala",
    "wof:placetype":"locality"
},
  "geometry": {"coordinates":[74.11111,33.50556],"type":"Point"}
}