{
  "type": "Feature",
  "properties": {
    "gn:admin1_code":"4.0",
    "gn:asciiname":"Chak Two Hundred Twenty-three Thal Development Authority",
    "gn:country_code":"PK",
    "gn:dem":158,
    "gn:feature_class":"P",
    "gn:feature_code":"PPL",
    "gn:name":"Chak Two Hundred Twenty-three Thal Development Authority",
    "gn:population":0,
    "gn:timezone":"Asia/Karachi",
    "iso:country":"PK",
    "name:und_x_variant":[
        "Chak Two Hundred Twenty-Three TDA",
        "Chak 223 TDA",
        "Chak Two Hundred Twenty-three Thal Development Authority"
    ],
    "wof:name":"Chak Two Hundred Twenty-three Thal Development Authority",
    "wof:placetype":"locality"
},
  "geometry": {"coordinates":[71.1764,31.26395],"type":"Point"}
}