{
  "type": "Feature",
  "properties": {
    "gn:admin1_code":"3",
    "gn:asciiname":"Aghzan",
    "gn:country_code":"PK",
    "gn:dem":646,
    "gn:feature_class":"P",
    "gn:feature_code":"PPL",
    "gn:name":"Aghzan",
    "gn:population":0,
    "gn:timezone":"Asia/Karachi",
    "iso:country":"PK",
    "wof:name":"Aghzan",
    "wof:placetype":"locality"
},
  "geometry": {"coordinates":[71.14241,32.31998],"type":"Point"}
}