{
  "type": "Feature",
  "properties": {
    "gn:admin1_code":"1.0",
    "gn:asciiname":"Shogi Pila Khel",
    "gn:country_code":"PK",
    "gn:dem":972,
    "gn:feature_class":"P",
    "gn:feature_code":"PPL",
    "gn:name":"Shogi Pila Khel",
    "gn:population":0,
    "gn:timezone":"Asia/Karachi",
    "iso:country":"PK",
    "name:und_x_variant":[
        "Dakai Kalai",
        "Dakai Khula",
        "Shogi Pila Khel"
    ],
    "wof:name":"Shogi Pila Khel",
    "wof:placetype":"locality"
},
  "geometry": {"coordinates":[70.15289,32.79655],"type":"Point"}
}