{
  "type": "Feature",
  "properties": {
    "gn:admin1_code":"3.0",
    "gn:asciiname":"Bandi Attai Khan",
    "gn:country_code":"PK",
    "gn:dem":1025,
    "gn:feature_class":"P",
    "gn:feature_code":"PPL",
    "gn:name":"Bandi Attai Khan",
    "gn:population":0,
    "gn:timezone":"Asia/Karachi",
    "iso:country":"PK",
    "name:und_x_variant":[
        "B\u0101nda At\u0101i Kh\u0101n"
    ],
    "wof:name":"Bandi Attai Khan",
    "wof:placetype":"locality"
},
  "geometry": {"coordinates":[73.21941,34.04533],"type":"Point"}
}