{
  "type": "Feature",
  "properties": {
    "gn:admin1_code":"4.0",
    "gn:asciiname":"Buzdar Shimali",
    "gn:country_code":"PK",
    "gn:dem":181,
    "gn:feature_class":"P",
    "gn:feature_code":"PPL",
    "gn:name":"Buzdar Shimali",
    "gn:population":0,
    "gn:timezone":"Asia/Karachi",
    "iso:country":"PK",
    "name:und_x_variant":[
        "Buzd\u0101r",
        "Buzdar Shimali"
    ],
    "wof:name":"Buzdar Shimali",
    "wof:placetype":"locality"
},
  "geometry": {"coordinates":[70.64360000000001,31.19375],"type":"Point"}
}