{
  "type": "Feature",
  "properties": {
    "gn:admin1_code":"1.0",
    "gn:asciiname":"Anb",
    "gn:country_code":"PK",
    "gn:dem":394,
    "gn:feature_class":"P",
    "gn:feature_code":"PPL",
    "gn:name":"Anb",
    "gn:population":0,
    "gn:timezone":"Asia/Karachi",
    "iso:country":"PK",
    "name:ara_x_preferred":[
        "\u0627\u0646\u0628"
    ],
    "name:fas_x_preferred":[
        "\u0627\u0646\u0628"
    ],
    "name:pol_x_preferred":[
        "Anb"
    ],
    "name:vie_x_preferred":[
        "Anb"
    ],
    "wof:name":"Anb",
    "wof:placetype":"locality"
},
  "geometry": {"coordinates":[73.70959000000001,33.34781],"type":"Point"}
}