{
  "type": "Feature",
  "properties": {
    "gn:admin1_code":"4.0",
    "gn:asciiname":"Chak Forty-eight ML",
    "gn:country_code":"PK",
    "gn:dem":183,
    "gn:feature_class":"P",
    "gn:feature_code":"PPL",
    "gn:name":"Chak Forty-eight ML",
    "gn:population":0,
    "gn:timezone":"Asia/Karachi",
    "iso:country":"PK",
    "name:und_x_variant":[
        "Chak Forty-Eight TDA",
        "Chak 48 TDA",
        "Chak Forty-eight ML"
    ],
    "wof:name":"Chak Forty-eight ML",
    "wof:placetype":"locality"
},
  "geometry": {"coordinates":[71.24068,31.815],"type":"Point"}
}