{
  "type": "Feature",
  "properties": {
    "gn:admin1_code":"4.0",
    "gn:asciiname":"Mihrab di Goth",
    "gn:country_code":"PK",
    "gn:dem":115,
    "gn:feature_class":"P",
    "gn:feature_code":"PPL",
    "gn:name":"Mihrab di Goth",
    "gn:population":0,
    "gn:timezone":"Asia/Karachi",
    "iso:country":"PK",
    "name:eng_x_preferred":[
        "Mehr\u0101b di Goth"
    ],
    "name:eng_x_variant":[
        "Goth Mahr\u0101b",
        "Goth Mehrab"
    ],
    "name:und_x_variant":[
        "Goth Mehrab",
        "Mihrab di Goth"
    ],
    "wof:name":"Mihrab di Goth",
    "wof:placetype":"locality"
},
  "geometry": {"coordinates":[71.51331,29.24103],"type":"Point"}
}