{
  "type": "Feature",
  "properties": {
    "gn:admin1_code":"5",
    "gn:asciiname":"Gai Jangi",
    "gn:country_code":"PK",
    "gn:dem":66,
    "gn:feature_class":"P",
    "gn:feature_code":"PPL",
    "gn:name":"Gai Jangi",
    "gn:population":0,
    "gn:timezone":"Asia/Karachi",
    "iso:country":"PK",
    "name:und_x_variant":[
        "Shesar Sonra"
    ],
    "wof:name":"Gai Jangi",
    "wof:placetype":"locality"
},
  "geometry": {"coordinates":[68.86332,28.10335],"type":"Point"}
}