{
  "type": "Feature",
  "properties": {
    "gn:admin1_code":"2.0",
    "gn:asciiname":"Hassan",
    "gn:country_code":"PK",
    "gn:dem":62,
    "gn:feature_class":"P",
    "gn:feature_code":"PPL",
    "gn:name":"Hassan",
    "gn:population":0,
    "gn:timezone":"Asia/Karachi",
    "iso:country":"PK",
    "name:ara_x_preferred":[
        "\u062d\u0633\u0646"
    ],
    "name:bih_x_preferred":[
        "\u0939\u093e\u0938\u0928"
    ],
    "name:cat_x_preferred":[
        "Hassan"
    ],
    "name:ceb_x_preferred":[
        "Hassan"
    ],
    "name:deu_x_preferred":[
        "Hassan"
    ],
    "name:fin_x_preferred":[
        "Hassan"
    ],
    "name:fra_x_preferred":[
        "Hassan"
    ],
    "name:heb_x_preferred":[
        "\u05d7\u05e1\u05df"
    ],
    "name:ita_x_preferred":[
        "Hassan"
    ],
    "name:jpn_x_preferred":[
        "\u30cf\u30b5\u30f3"
    ],
    "name:kaz_x_preferred":[
        "\u0425\u0430\u0441\u0430\u043d"
    ],
    "name:nld_x_preferred":[
        "Hassan"
    ],
    "name:oss_x_preferred":[
        "\u0425\u0430\u0441\u0430\u043d"
    ],
    "name:rus_x_preferred":[
        "\u0425\u0430\u0441\u0441\u0430\u043d"
    ],
    "name:spa_x_preferred":[
        "Hassan"
    ],
    "name:swe_x_preferred":[
        "Hassan"
    ],
    "name:ukr_x_preferred":[
        "\u0413\u0430\u0441\u0441\u0430\u043d"
    ],
    "wof:name":"Hassan",
    "wof:placetype":"locality"
},
  "geometry": {"coordinates":[62.54753,25.91765],"type":"Point"}
}