{
  "type": "Feature",
  "properties": {
    "gn:admin1_code":"5",
    "gn:asciiname":"Ahmad Lund",
    "gn:country_code":"PK",
    "gn:dem":20,
    "gn:feature_class":"P",
    "gn:feature_code":"PPL",
    "gn:name":"Ahmad Lund",
    "gn:population":0,
    "gn:timezone":"Asia/Karachi",
    "iso:country":"PK",
    "name:und_x_variant":[
        "Goth Ahmad Lund",
        "Goth Ahmmad Lund",
        "Ahmad Lund"
    ],
    "wof:name":"Ahmad Lund",
    "wof:placetype":"locality"
},
  "geometry": {"coordinates":[68.74807,25.33917000000001],"type":"Point"}
}