{
  "type": "Feature",
  "properties": {
    "gn:admin1_code":"2",
    "gn:asciiname":"Rahim Khan",
    "gn:country_code":"PK",
    "gn:dem":1646,
    "gn:feature_class":"P",
    "gn:feature_code":"PPL",
    "gn:name":"Rahim Khan",
    "gn:population":0,
    "gn:timezone":"Asia/Karachi",
    "iso:country":"PK",
    "wof:name":"Rahim Khan",
    "wof:placetype":"locality"
},
  "geometry": {"coordinates":[66.09744999999999,28.3486],"type":"Point"}
}