{
  "type": "Feature",
  "properties": {
    "gn:admin1_code":"3.0",
    "gn:asciiname":"Harian",
    "gn:country_code":"PK",
    "gn:dem":1584,
    "gn:feature_class":"P",
    "gn:feature_code":"PPL",
    "gn:name":"Harian",
    "gn:population":0,
    "gn:timezone":"Asia/Karachi",
    "iso:country":"PK",
    "wof:name":"Harian",
    "wof:placetype":"locality"
},
  "geometry": {"coordinates":[73.02396,35.17943],"type":"Point"}
}