{
  "type": "Feature",
  "properties": {
    "gn:admin1_code":"04",
    "gn:asciiname":"Murad Dasti",
    "gn:country_code":"PK",
    "gn:dem":131,
    "gn:feature_class":"P",
    "gn:feature_code":"PPL",
    "gn:name":"Murad Dasti",
    "gn:population":0,
    "gn:timezone":"Asia/Karachi",
    "iso:country":"PK",
    "name:eng_x_preferred":[
        "Murad Dasti"
    ],
    "wof:name":"Murad Dasti",
    "wof:placetype":"locality"
},
  "geometry": {"coordinates":[70.63909,30.29659],"type":"Point"}
}