{
  "type": "Feature",
  "properties": {
    "gn:admin1_code":"05",
    "gn:asciiname":"Purai Tar",
    "gn:country_code":"PK",
    "gn:dem":28,
    "gn:feature_class":"P",
    "gn:feature_code":"PPL",
    "gn:name":"Purai Tar",
    "gn:population":0,
    "gn:timezone":"Asia/Karachi",
    "iso:country":"PK",
    "name:und_x_variant":[
        "Pooraee",
        "Purai",
        "Purai Tar"
    ],
    "wof:name":"Purai Tar",
    "wof:placetype":"locality"
},
  "geometry": {"coordinates":[69.30474,26.057],"type":"Point"}
}