{
  "type": "Feature",
  "properties": {
    "gn:admin1_code":"2",
    "gn:asciiname":"Zebgari",
    "gn:country_code":"PK",
    "gn:dem":2463,
    "gn:feature_class":"P",
    "gn:feature_code":"PPL",
    "gn:name":"Zebgari",
    "gn:population":0,
    "gn:timezone":"Asia/Karachi",
    "iso:country":"PK",
    "name:eng_x_preferred":[
        "Zebgari"
    ],
    "wof:name":"Zebgari",
    "wof:placetype":"locality"
},
  "geometry": {"coordinates":[67.53222,31.09],"type":"Point"}
}