{
  "type": "Feature",
  "properties": {
    "gn:admin1_code":"01",
    "gn:asciiname":"Qazi Koruna",
    "gn:country_code":"PK",
    "gn:dem":1033,
    "gn:feature_class":"P",
    "gn:feature_code":"PPL",
    "gn:name":"Qazi Koruna",
    "gn:population":0,
    "gn:timezone":"Asia/Karachi",
    "iso:country":"PK",
    "name:und_x_variant":[
        "Q\u0101zi Koruna"
    ],
    "wof:name":"Qazi Koruna",
    "wof:placetype":"locality"
},
  "geometry": {"coordinates":[71.34787,34.68929],"type":"Point"}
}