{
  "type": "Feature",
  "properties": {
    "gn:admin1_code":"4",
    "gn:asciiname":"Dhalm Balgan",
    "gn:country_code":"PK",
    "gn:dem":240,
    "gn:feature_class":"P",
    "gn:feature_code":"PPL",
    "gn:name":"Dhalm Balgan",
    "gn:population":0,
    "gn:timezone":"Asia/Karachi",
    "iso:country":"PK",
    "name:und_x_variant":[
        "Dhilam",
        "Balgan"
    ],
    "wof:name":"Dhalm Balgan",
    "wof:placetype":"locality"
},
  "geometry": {"coordinates":[74.33819,32.42658],"type":"Point"}
}