{
  "type": "Feature",
  "properties": {
    "gn:admin1_code":"3",
    "gn:asciiname":"Karazai",
    "gn:country_code":"PK",
    "gn:dem":685,
    "gn:feature_class":"P",
    "gn:feature_code":"PPL",
    "gn:name":"Karazai",
    "gn:population":0,
    "gn:timezone":"Asia/Karachi",
    "iso:country":"PK",
    "name:und_x_variant":[
        "K\u0101rezai"
    ],
    "wof:name":"Karazai",
    "wof:placetype":"locality"
},
  "geometry": {"coordinates":[72.66605,34.4436],"type":"Point"}
}