{
  "type": "Feature",
  "properties": {
    "gn:admin1_code":"4.0",
    "gn:asciiname":"Chaudhary Azizwali Jhalar",
    "gn:country_code":"PK",
    "gn:dem":202,
    "gn:feature_class":"P",
    "gn:feature_code":"PPL",
    "gn:name":"Chaudhary Azizwali Jhalar",
    "gn:population":0,
    "gn:timezone":"Asia/Karachi",
    "iso:country":"PK",
    "wof:name":"Chaudhary Azizwali Jhalar",
    "wof:placetype":"locality"
},
  "geometry": {"coordinates":[74.05346999999998,31.18014],"type":"Point"}
}