{
  "type": "Feature",
  "properties": {
    "gn:admin1_code":"2.0",
    "gn:asciiname":"Shahdan Kili",
    "gn:country_code":"PK",
    "gn:dem":2537,
    "gn:feature_class":"P",
    "gn:feature_code":"PPL",
    "gn:name":"Shahdan Kili",
    "gn:population":0,
    "gn:timezone":"Asia/Karachi",
    "iso:country":"PK",
    "wof:name":"Shahdan Kili",
    "wof:placetype":"locality"
},
  "geometry": {"coordinates":[67.82239,30.35172],"type":"Point"}
}