{
  "type": "Feature",
  "properties": {
    "gn:admin1_code":"2",
    "gn:asciiname":"Psha",
    "gn:country_code":"PK",
    "gn:dem":2328,
    "gn:feature_class":"P",
    "gn:feature_code":"PPL",
    "gn:name":"Psha",
    "gn:population":0,
    "gn:timezone":"Asia/Karachi",
    "iso:country":"PK",
    "name:eng_x_preferred":[
        "Psha"
    ],
    "wof:name":"Psha",
    "wof:placetype":"locality"
},
  "geometry": {"coordinates":[67.65817,31.05216],"type":"Point"}
}