{
  "type": "Feature",
  "properties": {
    "gn:admin1_code":"6",
    "gn:asciiname":"Tired",
    "gn:country_code":"PK",
    "gn:dem":577,
    "gn:feature_class":"P",
    "gn:feature_code":"PPL",
    "gn:name":"Tired",
    "gn:population":0,
    "gn:timezone":"Asia/Karachi",
    "iso:country":"PK",
    "name:ara_x_preferred":[
        "\u062a\u0639\u0628"
    ],
    "name:und_x_variant":[
        "Tirod"
    ],
    "wof:name":"Tired",
    "wof:placetype":"locality"
},
  "geometry": {"coordinates":[74.15231,33.00462],"type":"Point"}
}