{
  "type": "Feature",
  "properties": {
    "gn:admin1_code":"3",
    "gn:asciiname":"Haramian",
    "gn:country_code":"PK",
    "gn:dem":1864,
    "gn:feature_class":"P",
    "gn:feature_code":"PPL",
    "gn:name":"Haramian",
    "gn:population":0,
    "gn:timezone":"Asia/Karachi",
    "iso:country":"PK",
    "name:eng_x_preferred":[
        "Haramian"
    ],
    "wof:name":"Haramian",
    "wof:placetype":"locality"
},
  "geometry": {"coordinates":[71.79613000000001,35.17868],"type":"Point"}
}