{
  "type": "Feature",
  "properties": {
    "gn:admin1_code":"1.0",
    "gn:asciiname":"Ghat Sarobi",
    "gn:country_code":"PK",
    "gn:dem":1052,
    "gn:feature_class":"P",
    "gn:feature_code":"PPL",
    "gn:name":"Ghat Sarobi",
    "gn:population":0,
    "gn:timezone":"Asia/Karachi",
    "iso:country":"PK",
    "wof:name":"Ghat Sarobi",
    "wof:placetype":"locality"
},
  "geometry": {"coordinates":[70.1053,32.89233],"type":"Point"}
}