{
  "type": "Feature",
  "properties": {
    "gn:admin1_code":"3",
    "gn:asciiname":"Dhudial",
    "gn:country_code":"PK",
    "gn:dem":1227,
    "gn:feature_class":"P",
    "gn:feature_code":"PPL",
    "gn:name":"Dhudial",
    "gn:population":0,
    "gn:timezone":"Asia/Karachi",
    "iso:country":"PK",
    "name:fas_x_preferred":[
        "\u062f\u0647\u062f\u06cc\u0627\u0644"
    ],
    "name:hin_x_preferred":[
        "\u0922\u094c\u0921\u093f\u092f\u093e\u0932"
    ],
    "name:urd_x_preferred":[
        "\u0688\u06be\u0688\u06cc\u0627\u0644"
    ],
    "wof:name":"Dhudial",
    "wof:placetype":"locality"
},
  "geometry": {"coordinates":[73.27101,34.16474],"type":"Point"}
}