{
  "type": "Feature",
  "properties": {
    "gn:admin1_code":"4",
    "gn:asciiname":"Chak One Hundred Eight Northern Branch",
    "gn:country_code":"PK",
    "gn:dem":182,
    "gn:feature_class":"P",
    "gn:feature_code":"PPL",
    "gn:name":"Chak One Hundred Eight Northern Branch",
    "gn:population":0,
    "gn:timezone":"Asia/Karachi",
    "iso:country":"PK",
    "name:und_x_variant":[
        "Chak One Hundred Eight NB"
    ],
    "wof:name":"Chak One Hundred Eight Northern Branch",
    "wof:placetype":"locality"
},
  "geometry": {"coordinates":[72.55806,31.97495],"type":"Point"}
}