{
  "type": "Feature",
  "properties": {
    "gn:admin1_code":"4",
    "gn:asciiname":"Basti Ahmad Bakhsh",
    "gn:country_code":"PK",
    "gn:dem":102,
    "gn:feature_class":"P",
    "gn:feature_code":"PPL",
    "gn:name":"Basti Ahmad Bakhsh",
    "gn:population":0,
    "gn:timezone":"Asia/Karachi",
    "iso:country":"PK",
    "name:und_x_variant":[
        "Basti Bohar",
        "Basti Ahmed Bakhsh"
    ],
    "wof:name":"Basti Ahmad Bakhsh",
    "wof:placetype":"locality"
},
  "geometry": {"coordinates":[70.51777,29.39178],"type":"Point"}
}