{
  "type": "Feature",
  "properties": {
    "gn:admin1_code":"02",
    "gn:asciiname":"Morghani Jhik",
    "gn:country_code":"PK",
    "gn:dem":5,
    "gn:feature_class":"P",
    "gn:feature_code":"PPL",
    "gn:name":"Morghani Jhik",
    "gn:population":0,
    "gn:timezone":"Asia/Karachi",
    "iso:country":"PK",
    "name:und_x_variant":[
        "Murgh\u0101ni Jh\u012bk"
    ],
    "wof:name":"Morghani Jhik",
    "wof:placetype":"locality"
},
  "geometry": {"coordinates":[64.16183000000001,25.33513],"type":"Point"}
}