{
  "type": "Feature",
  "properties": {
    "gn:admin1_code":"5.0",
    "gn:asciiname":"Bachal Rind",
    "gn:country_code":"PK",
    "gn:dem":10,
    "gn:feature_class":"P",
    "gn:feature_code":"PPL",
    "gn:name":"Bachal Rind",
    "gn:population":0,
    "gn:timezone":"Asia/Karachi",
    "iso:country":"PK",
    "name:eng_x_preferred":[
        "Bachchal Rind"
    ],
    "wof:name":"Bachal Rind",
    "wof:placetype":"locality"
},
  "geometry": {"coordinates":[68.07694000000001,24.52428],"type":"Point"}
}