{
  "type": "Feature",
  "properties": {
    "gn:admin1_code":"5",
    "gn:asciiname":"Goth Rashid Khan Khoso",
    "gn:country_code":"PK",
    "gn:dem":18,
    "gn:feature_class":"P",
    "gn:feature_code":"PPL",
    "gn:name":"Goth Rashid Khan Khoso",
    "gn:population":0,
    "gn:timezone":"Asia/Karachi",
    "iso:country":"PK",
    "name:und_x_variant":[
        "H\u0101ji At\u0101ro"
    ],
    "wof:name":"Goth Rashid Khan Khoso",
    "wof:placetype":"locality"
},
  "geometry": {"coordinates":[68.71417,25.13282],"type":"Point"}
}