{
  "type": "Feature",
  "properties": {
    "gn:admin1_code":"4",
    "gn:asciiname":"Buddhe da Khu",
    "gn:country_code":"PK",
    "gn:dem":95,
    "gn:feature_class":"P",
    "gn:feature_code":"PPL",
    "gn:name":"Buddhe da Khu",
    "gn:population":0,
    "gn:timezone":"Asia/Karachi",
    "iso:country":"PK",
    "wof:name":"Buddhe da Khu",
    "wof:placetype":"locality"
},
  "geometry": {"coordinates":[70.77083,28.94583],"type":"Point"}
}