{
  "type": "Feature",
  "properties": {
    "gn:admin1_code":"3",
    "gn:asciiname":"Ghanamrang",
    "gn:country_code":"PK",
    "gn:dem":1621,
    "gn:feature_class":"P",
    "gn:feature_code":"PPL",
    "gn:name":"Ghanamrang",
    "gn:population":0,
    "gn:timezone":"Asia/Karachi",
    "iso:country":"PK",
    "wof:name":"Ghanamrang",
    "wof:placetype":"locality"
},
  "geometry": {"coordinates":[73.01685000000001,34.85395],"type":"Point"}
}