{
  "type": "Feature",
  "properties": {
    "gn:admin1_code":"4",
    "gn:asciiname":"Allewali Khurd",
    "gn:country_code":"PK",
    "gn:dem":235,
    "gn:feature_class":"P",
    "gn:feature_code":"PPL",
    "gn:name":"Allewali Khurd",
    "gn:population":0,
    "gn:timezone":"Asia/Karachi",
    "iso:country":"PK",
    "name:und_x_variant":[
        "Allehw\u0101li"
    ],
    "wof:name":"Allewali Khurd",
    "wof:placetype":"locality"
},
  "geometry": {"coordinates":[74.3794,32.46135],"type":"Point"}
}