{
  "type": "Feature",
  "properties": {
    "gn:admin1_code":"2",
    "gn:asciiname":"Bandaro",
    "gn:country_code":"PK",
    "gn:dem":1102,
    "gn:feature_class":"P",
    "gn:feature_code":"PPL",
    "gn:name":"Bandaro",
    "gn:population":0,
    "gn:timezone":"Asia/Karachi",
    "iso:country":"PK",
    "name:und_x_variant":[
        "Bahr\u0101m Kh\u0101n"
    ],
    "wof:name":"Bandaro",
    "wof:placetype":"locality"
},
  "geometry": {"coordinates":[66.19053000000001,27.48556],"type":"Point"}
}