{
  "type": "Feature",
  "properties": {
    "gn:admin1_code":"07",
    "gn:asciiname":"Ponedas",
    "gn:country_code":"PK",
    "gn:dem":2240,
    "gn:feature_class":"P",
    "gn:feature_code":"PPL",
    "gn:name":"Ponedas",
    "gn:population":0,
    "gn:timezone":"Asia/Karachi",
    "iso:country":"PK",
    "wof:name":"Ponedas",
    "wof:placetype":"locality"
},
  "geometry": {"coordinates":[75.446,35.45307000000001],"type":"Point"}
}