{
  "type": "Feature",
  "properties": {
    "gn:admin1_code":"6",
    "gn:asciiname":"Bhalewali",
    "gn:country_code":"PK",
    "gn:dem":272,
    "gn:feature_class":"P",
    "gn:feature_code":"PPL",
    "gn:name":"Bhalewali",
    "gn:population":0,
    "gn:timezone":"Asia/Karachi",
    "iso:country":"PK",
    "name:und_x_variant":[
        "B\u0101hle\u0101l"
    ],
    "wof:name":"Bhalewali",
    "wof:placetype":"locality"
},
  "geometry": {"coordinates":[74.40538000000002,32.83559],"type":"Point"}
}