{
  "type": "Feature",
  "properties": {
    "gn:admin1_code":"4.0",
    "gn:asciiname":"Mochian Ki Dhok",
    "gn:country_code":"PK",
    "gn:dem":408,
    "gn:feature_class":"P",
    "gn:feature_code":"PPL",
    "gn:name":"Mochi\u0101n Ki Dhok",
    "gn:population":0,
    "gn:timezone":"Asia/Karachi",
    "iso:country":"PK",
    "wof:name":"Mochian Ki Dhok",
    "wof:placetype":"locality"
},
  "geometry": {"coordinates":[71.85666999999999,33.23778],"type":"Point"}
}