{
  "type": "Feature",
  "properties": {
    "gn:admin1_code":"4.0",
    "gn:asciiname":"Thatta Nanika",
    "gn:country_code":"PK",
    "gn:dem":196,
    "gn:feature_class":"P",
    "gn:feature_code":"PPL",
    "gn:name":"Thatta Nanika",
    "gn:population":0,
    "gn:timezone":"Asia/Karachi",
    "iso:country":"PK",
    "name:und_x_variant":[
        "Khhichi\u0101n"
    ],
    "wof:name":"Thatta Nanika",
    "wof:placetype":"locality"
},
  "geometry": {"coordinates":[73.35151999999999,31.95208],"type":"Point"}
}