{
  "type": "Feature",
  "properties": {
    "gn:admin1_code":"2.0",
    "gn:asciiname":"Goth Muhammad Uman",
    "gn:country_code":"PK",
    "gn:dem":491,
    "gn:feature_class":"P",
    "gn:feature_code":"PPL",
    "gn:name":"Goth Muhammad Uman",
    "gn:population":0,
    "gn:timezone":"Asia/Karachi",
    "iso:country":"PK",
    "wof:name":"Goth Muhammad Uman",
    "wof:placetype":"locality"
},
  "geometry": {"coordinates":[66.91133000000001,25.97643],"type":"Point"}
}