{
  "type": "Feature",
  "properties": {
    "gn:admin1_code":"2.0",
    "gn:asciiname":"Indar Bes",
    "gn:country_code":"PK",
    "gn:dem":2535,
    "gn:feature_class":"P",
    "gn:feature_code":"PPL",
    "gn:name":"Indar Bes",
    "gn:population":0,
    "gn:timezone":"Asia/Karachi",
    "iso:country":"PK",
    "name:und_x_variant":[
        "Indarbaes",
        "Indar Bes"
    ],
    "wof:name":"Indar Bes",
    "wof:placetype":"locality"
},
  "geometry": {"coordinates":[67.78815999999999,30.95832],"type":"Point"}
}