{
  "type": "Feature",
  "properties": {
    "gn:admin1_code":"4",
    "gn:asciiname":"Atuwala",
    "gn:country_code":"PK",
    "gn:dem":191,
    "gn:feature_class":"P",
    "gn:feature_code":"PPL",
    "gn:name":"Atuwala",
    "gn:population":0,
    "gn:timezone":"Asia/Karachi",
    "iso:country":"PK",
    "wof:name":"Atuwala",
    "wof:placetype":"locality"
},
  "geometry": {"coordinates":[74.34999999999999,30.79444],"type":"Point"}
}