{
  "type": "Feature",
  "properties": {
    "gn:admin1_code":"1.0",
    "gn:asciiname":"Kirra",
    "gn:country_code":"PK",
    "gn:dem":616,
    "gn:feature_class":"P",
    "gn:feature_code":"PPL",
    "gn:name":"Kirra",
    "gn:population":0,
    "gn:timezone":"Asia/Karachi",
    "iso:country":"PK",
    "name:ell_x_preferred":[
        "\u039a\u03af\u03c1\u03c1\u03b1"
    ],
    "name:und_x_variant":[
        "Kirre",
        "Kirra"
    ],
    "wof:name":"Kirra",
    "wof:placetype":"locality"
},
  "geometry": {"coordinates":[70.49234,33.21068],"type":"Point"}
}