{
  "type": "Feature",
  "properties": {
    "gn:admin1_code":"4.0",
    "gn:asciiname":"Dhok Lund",
    "gn:country_code":"PK",
    "gn:dem":403,
    "gn:feature_class":"P",
    "gn:feature_code":"PPL",
    "gn:name":"Dhok Lund",
    "gn:population":0,
    "gn:timezone":"Asia/Karachi",
    "iso:country":"PK",
    "name:und_x_variant":[
        "Dhok Lunda"
    ],
    "wof:name":"Dhok Lund",
    "wof:placetype":"locality"
},
  "geometry": {"coordinates":[72.21885,33.39377],"type":"Point"}
}