{
  "type": "Feature",
  "properties": {
    "gn:admin1_code":"2.0",
    "gn:asciiname":"Kili Qasar",
    "gn:country_code":"PK",
    "gn:dem":1732,
    "gn:feature_class":"P",
    "gn:feature_code":"PPL",
    "gn:name":"Kili Qasar",
    "gn:population":0,
    "gn:timezone":"Asia/Karachi",
    "iso:country":"PK",
    "name:und_x_variant":[
        "Faq\u012br Kili",
        "Kili Kasai",
        "Kili Qasar"
    ],
    "wof:name":"Kili Qasar",
    "wof:placetype":"locality"
},
  "geometry": {"coordinates":[69.77741999999999,31.43513],"type":"Point"}
}