{
  "type": "Feature",
  "properties": {
    "gn:admin1_code":"4.0",
    "gn:asciiname":"Kot Sohnda",
    "gn:country_code":"PK",
    "gn:dem":208,
    "gn:feature_class":"P",
    "gn:feature_code":"PPL",
    "gn:name":"Kot Sohnda",
    "gn:population":0,
    "gn:timezone":"Asia/Karachi",
    "iso:country":"PK",
    "name:und_x_variant":[
        "Kot Sonda"
    ],
    "wof:name":"Kot Sohnda",
    "wof:placetype":"locality"
},
  "geometry": {"coordinates":[73.77603000000001,31.77597],"type":"Point"}
}