{
  "type": "Feature",
  "properties": {
    "gn:admin1_code":"3.0",
    "gn:asciiname":"Dang Lakhtai Payan",
    "gn:country_code":"PK",
    "gn:dem":321,
    "gn:feature_class":"P",
    "gn:feature_code":"PPL",
    "gn:name":"Dang Lakhtai Payan",
    "gn:population":0,
    "gn:timezone":"Asia/Karachi",
    "iso:country":"PK",
    "name:eng_x_preferred":[
        "Dang Lakhte"
    ],
    "name:und_x_variant":[
        "Dang Lakhta",
        "Dang Lakhtai Payan"
    ],
    "wof:name":"Dang Lakhtai Payan",
    "wof:placetype":"locality"
},
  "geometry": {"coordinates":[71.53485000000001,34.14523],"type":"Point"}
}