{
  "type": "Feature",
  "properties": {
    "gn:admin1_code":"03",
    "gn:asciiname":"Zarkani",
    "gn:country_code":"PK",
    "gn:dem":263,
    "gn:feature_class":"P",
    "gn:feature_code":"PPL",
    "gn:name":"Zarkani",
    "gn:population":0,
    "gn:timezone":"Asia/Karachi",
    "iso:country":"PK",
    "name:und_x_variant":[
        "Zark\u0101n",
        "Zarkani"
    ],
    "wof:name":"Zarkani",
    "wof:placetype":"locality"
},
  "geometry": {"coordinates":[70.2615,31.83108],"type":"Point"}
}