{
  "type": "Feature",
  "properties": {
    "gn:admin1_code":"3.0",
    "gn:asciiname":"Sais Mandai",
    "gn:country_code":"PK",
    "gn:dem":284,
    "gn:feature_class":"P",
    "gn:feature_code":"PPL",
    "gn:name":"Sais Mandai",
    "gn:population":0,
    "gn:timezone":"Asia/Karachi",
    "iso:country":"PK",
    "name:eng_x_preferred":[
        "S\u0101\u012bs Mandi"
    ],
    "wof:name":"Sais Mandai",
    "wof:placetype":"locality"
},
  "geometry": {"coordinates":[71.98732,34.04372],"type":"Point"}
}