{
  "type": "Feature",
  "properties": {
    "gn:admin1_code":"5.0",
    "gn:asciiname":"Haji Khan Muhammad Jalbani",
    "gn:country_code":"PK",
    "gn:dem":39,
    "gn:feature_class":"P",
    "gn:feature_code":"PPL",
    "gn:name":"Haji Khan Muhammad Jalbani",
    "gn:population":0,
    "gn:timezone":"Asia/Karachi",
    "iso:country":"PK",
    "wof:name":"Haji Khan Muhammad Jalbani",
    "wof:placetype":"locality"
},
  "geometry": {"coordinates":[68.31456,26.48198],"type":"Point"}
}