{
  "type": "Feature",
  "properties": {
    "gn:admin1_code":"4.0",
    "gn:asciiname":"Chak Five Hundred Fourteen Gugera Branch",
    "gn:country_code":"PK",
    "gn:dem":163,
    "gn:feature_class":"P",
    "gn:feature_code":"PPL",
    "gn:name":"Chak Five Hundred Fourteen Gugera Branch",
    "gn:population":0,
    "gn:timezone":"Asia/Karachi",
    "iso:country":"PK",
    "name:und_x_variant":[
        "Kathia Chak",
        "Chak Five Hundred Fourteen GB",
        "K\u0101thia",
        "K\u0101th\u012b\u0101nw\u0101la",
        "Chak Five Hundred Fourteen Gugera Branch",
        "Kathi\u0101nw\u0101la"
    ],
    "wof:name":"Chak Five Hundred Fourteen Gugera Branch",
    "wof:placetype":"locality"
},
  "geometry": {"coordinates":[72.74011,30.78006],"type":"Point"}
}