{
  "type": "Feature",
  "properties": {
    "gn:admin1_code":"2.0",
    "gn:asciiname":"Buleda Cross",
    "gn:country_code":"PK",
    "gn:dem":708,
    "gn:feature_class":"P",
    "gn:feature_code":"PPL",
    "gn:name":"Buleda Cross",
    "gn:population":0,
    "gn:timezone":"Asia/Karachi",
    "iso:country":"PK",
    "wof:name":"Buleda Cross",
    "wof:placetype":"locality"
},
  "geometry": {"coordinates":[63.98852,26.39271],"type":"Point"}
}