{
  "type": "Feature",
  "properties": {
    "gn:admin1_code":"1.0",
    "gn:asciiname":"Inayaitullah Dhand",
    "gn:country_code":"PK",
    "gn:dem":811,
    "gn:feature_class":"P",
    "gn:feature_code":"PPL",
    "gn:name":"Inayaitullah Dhand",
    "gn:population":0,
    "gn:timezone":"Asia/Karachi",
    "iso:country":"PK",
    "wof:name":"Inayaitullah Dhand",
    "wof:placetype":"locality"
},
  "geometry": {"coordinates":[71.28629000000002,33.90887],"type":"Point"}
}