{
  "type": "Feature",
  "properties": {
    "gn:admin1_code":"7.0",
    "gn:asciiname":"Doli",
    "gn:country_code":"PK",
    "gn:dem":3452,
    "gn:feature_class":"P",
    "gn:feature_code":"PPL",
    "gn:name":"Doli",
    "gn:population":0,
    "gn:timezone":"Asia/Karachi",
    "iso:country":"PK",
    "name:bos_x_preferred":[
        "Doli"
    ],
    "name:ceb_x_preferred":[
        "Doli"
    ],
    "name:deu_x_preferred":[
        "Doli"
    ],
    "name:fra_x_preferred":[
        "Doli"
    ],
    "name:swe_x_preferred":[
        "Doli"
    ],
    "wof:name":"Doli",
    "wof:placetype":"locality"
},
  "geometry": {"coordinates":[73.5116,36.39673],"type":"Point"}
}