{
  "type": "Feature",
  "properties": {
    "gn:admin1_code":"4.0",
    "gn:asciiname":"Sarewali",
    "gn:country_code":"PK",
    "gn:dem":514,
    "gn:feature_class":"P",
    "gn:feature_code":"PPL",
    "gn:name":"Sarewali",
    "gn:population":0,
    "gn:timezone":"Asia/Karachi",
    "iso:country":"PK",
    "name:und_x_variant":[
        "Sadhew\u0101li"
    ],
    "wof:name":"Sarewali",
    "wof:placetype":"locality"
},
  "geometry": {"coordinates":[71.96344000000001,32.60803],"type":"Point"}
}