{
  "type": "Feature",
  "properties": {
    "gn:admin1_code":"2.0",
    "gn:asciiname":"Mashkai",
    "gn:country_code":"PK",
    "gn:dem":843,
    "gn:feature_class":"P",
    "gn:feature_code":"PPL",
    "gn:name":"Mashkai",
    "gn:population":0,
    "gn:timezone":"Asia/Karachi",
    "iso:country":"PK",
    "wof:name":"Mashkai",
    "wof:placetype":"locality"
},
  "geometry": {"coordinates":[65.43365,26.88573],"type":"Point"}
}