{
  "type": "Feature",
  "properties": {
    "gn:admin1_code":"2.0",
    "gn:asciiname":"Mashkai",
    "gn:country_code":"PK",
    "gn:dem":843,
    "gn:feature_class":"P",
    "gn:feature_code":"PPL",
    "gn:name":"Mashkai",
    "gn:population":0,
    "gn:timezone":"Asia/Karachi",
    "iso:country":"PK",
    "name:fas_x_preferred":[
        "\u0645\u0627\u0634\u06a9\u0626\u06cc"
    ],
    "name:snd_x_preferred":[
        "\u0645\u0627\u0634\u06aa\u0626\u064a"
    ],
    "name:urd_x_preferred":[
        "\u0645\u0627\u0634\u06a9\u0626\u06cc"
    ],
    "wof:name":"Mashkai",
    "wof:placetype":"locality"
},
  "geometry": {"coordinates":[65.43365,26.88573],"type":"Point"}
}