{
  "type": "Feature",
  "properties": {
    "gn:admin1_code":"04",
    "gn:asciiname":"Nahranwala",
    "gn:country_code":"PK",
    "gn:dem":172,
    "gn:feature_class":"P",
    "gn:feature_code":"PPL",
    "gn:name":"Nahranwala",
    "gn:population":0,
    "gn:timezone":"Asia/Karachi",
    "iso:country":"PK",
    "name:und_x_variant":[
        "Nehranwala",
        "Nahranwala"
    ],
    "wof:name":"Nahranwala",
    "wof:placetype":"locality"
},
  "geometry": {"coordinates":[73.46248,30.59292],"type":"Point"}
}