{
  "type": "Feature",
  "properties": {
    "gn:admin1_code":"5",
    "gn:asciiname":"Haji Ghulam Hydar Kapri",
    "gn:country_code":"PK",
    "gn:dem":12,
    "gn:feature_class":"P",
    "gn:feature_code":"PPL",
    "gn:name":"Haji Ghulam Hydar Kapri",
    "gn:population":0,
    "gn:timezone":"Asia/Karachi",
    "iso:country":"PK",
    "name:und_x_variant":[
        "Jam\u0101l Kh\u0101n"
    ],
    "wof:name":"Haji Ghulam Hydar Kapri",
    "wof:placetype":"locality"
},
  "geometry": {"coordinates":[69.48025,25.32889],"type":"Point"}
}