{
  "type": "Feature",
  "properties": {
    "gn:admin1_code":"2.0",
    "gn:asciiname":"Chedgi Ghis",
    "gn:country_code":"PK",
    "gn:dem":858,
    "gn:feature_class":"P",
    "gn:feature_code":"PPL",
    "gn:name":"Chedgi Ghis",
    "gn:population":0,
    "gn:timezone":"Asia/Karachi",
    "iso:country":"PK",
    "wof:name":"Chedgi Ghis",
    "wof:placetype":"locality"
},
  "geometry": {"coordinates":[63.35128,27.15514000000001],"type":"Point"}
}