{
  "type": "Feature",
  "properties": {
    "gn:admin1_code":"4.0",
    "gn:asciiname":"Membranwala",
    "gn:country_code":"PK",
    "gn:dem":187,
    "gn:feature_class":"P",
    "gn:feature_code":"PPL",
    "gn:name":"Membranwala",
    "gn:population":0,
    "gn:timezone":"Asia/Karachi",
    "iso:country":"PK",
    "wof:name":"Membranwala",
    "wof:placetype":"locality"
},
  "geometry": {"coordinates":[74.11748,30.82794],"type":"Point"}
}