{
  "type": "Feature",
  "properties": {
    "gn:admin1_code":"4",
    "gn:asciiname":"Basti Kalu Pitafi",
    "gn:country_code":"PK",
    "gn:dem":159,
    "gn:feature_class":"P",
    "gn:feature_code":"PPL",
    "gn:name":"Basti Kalu Pitafi",
    "gn:population":0,
    "gn:timezone":"Asia/Karachi",
    "iso:country":"PK",
    "name:und_x_variant":[
        "Basti Marete",
        "Basti Marhatte"
    ],
    "wof:name":"Basti Kalu Pitafi",
    "wof:placetype":"locality"
},
  "geometry": {"coordinates":[70.11284999999999,29.51451],"type":"Point"}
}