{
  "type": "Feature",
  "properties": {
    "gn:admin1_code":"3",
    "gn:asciiname":"Josacha",
    "gn:country_code":"PK",
    "gn:dem":1611,
    "gn:feature_class":"P",
    "gn:feature_code":"PPL",
    "gn:name":"Josacha",
    "gn:population":0,
    "gn:timezone":"Asia/Karachi",
    "iso:country":"PK",
    "name:und_x_variant":[
        "Jausach"
    ],
    "wof:name":"Josacha",
    "wof:placetype":"locality"
},
  "geometry": {"coordinates":[73.37586,34.53151],"type":"Point"}
}