{
  "type": "Feature",
  "properties": {
    "gn:admin1_code":"2.0",
    "gn:asciiname":"Nabi Bukhsh",
    "gn:country_code":"PK",
    "gn:dem":909,
    "gn:feature_class":"P",
    "gn:feature_code":"PPL",
    "gn:name":"Nabi Bukhsh",
    "gn:population":0,
    "gn:timezone":"Asia/Karachi",
    "iso:country":"PK",
    "wof:name":"Nabi Bukhsh",
    "wof:placetype":"locality"
},
  "geometry": {"coordinates":[66.71518,26.44573],"type":"Point"}
}