{
  "type": "Feature",
  "properties": {
    "gn:admin1_code":"5.0",
    "gn:asciiname":"Ghand Tar",
    "gn:country_code":"PK",
    "gn:dem":31,
    "gn:feature_class":"P",
    "gn:feature_code":"PPL",
    "gn:name":"Ghand Tar",
    "gn:population":0,
    "gn:timezone":"Asia/Karachi",
    "iso:country":"PK",
    "name:und_x_variant":[
        "Ghandter",
        "Ghand Tar",
        "Gandtar"
    ],
    "wof:name":"Ghand Tar",
    "wof:placetype":"locality"
},
  "geometry": {"coordinates":[68.42300999999999,26.29847],"type":"Point"}
}