{
  "type": "Feature",
  "properties": {
    "gn:admin1_code":"04",
    "gn:asciiname":"Wahi Salamat Rae",
    "gn:country_code":"PK",
    "gn:dem":114,
    "gn:feature_class":"P",
    "gn:feature_code":"PPL",
    "gn:name":"Wahi Salamat Rae",
    "gn:population":0,
    "gn:timezone":"Asia/Karachi",
    "iso:country":"PK",
    "name:und_x_variant":[
        "Wahi Sal\u0101mat R\u0101i"
    ],
    "wof:name":"Wahi Salamat Rae",
    "wof:placetype":"locality"
},
  "geometry": {"coordinates":[71.46486,29.58563],"type":"Point"}
}