{
  "type": "Feature",
  "properties": {
    "gn:admin1_code":"4.0",
    "gn:asciiname":"Kot Reshan Din",
    "gn:country_code":"PK",
    "gn:dem":209,
    "gn:feature_class":"P",
    "gn:feature_code":"PPL",
    "gn:name":"Kot Reshan Din",
    "gn:population":0,
    "gn:timezone":"Asia/Karachi",
    "iso:country":"PK",
    "name:und_x_variant":[
        "Kot Roshand\u012bn"
    ],
    "wof:name":"Kot Reshan Din",
    "wof:placetype":"locality"
},
  "geometry": {"coordinates":[73.86736999999999,31.60685],"type":"Point"}
}