{
  "type": "Feature",
  "properties": {
    "gn:admin1_code":"2.0",
    "gn:asciiname":"Kalai",
    "gn:country_code":"PK",
    "gn:dem":1868,
    "gn:feature_class":"P",
    "gn:feature_code":"PPL",
    "gn:name":"Kalai",
    "gn:population":0,
    "gn:timezone":"Asia/Karachi",
    "iso:country":"PK",
    "wof:name":"Kalai",
    "wof:placetype":"locality"
},
  "geometry": {"coordinates":[66.62125999999999,30.82788],"type":"Point"}
}