{
  "type": "Feature",
  "properties": {
    "gn:admin1_code":"2.0",
    "gn:asciiname":"Murad Khan",
    "gn:country_code":"PK",
    "gn:dem":498,
    "gn:feature_class":"P",
    "gn:feature_code":"PPL",
    "gn:name":"Mur\u0101d Kh\u0101n",
    "gn:population":0,
    "gn:timezone":"Asia/Karachi",
    "iso:country":"PK",
    "wof:name":"Murad Khan",
    "wof:placetype":"locality"
},
  "geometry": {"coordinates":[65.47778000000001,26.52361],"type":"Point"}
}