{
  "type": "Feature",
  "properties": {
    "gn:admin1_code":"2",
    "gn:asciiname":"Sialu Kor",
    "gn:country_code":"PK",
    "gn:dem":1261,
    "gn:feature_class":"P",
    "gn:feature_code":"PPL",
    "gn:name":"Sialu Kor",
    "gn:population":0,
    "gn:timezone":"Asia/Karachi",
    "iso:country":"PK",
    "wof:name":"Sialu Kor",
    "wof:placetype":"locality"
},
  "geometry": {"coordinates":[69.58110000000001,30.23294000000001],"type":"Point"}
}