{
  "type": "Feature",
  "properties": {
    "gn:admin1_code":"4.0",
    "gn:asciiname":"Khu Gujranwala",
    "gn:country_code":"PK",
    "gn:dem":181,
    "gn:feature_class":"P",
    "gn:feature_code":"PPL",
    "gn:name":"Khu Gujranwala",
    "gn:population":0,
    "gn:timezone":"Asia/Karachi",
    "iso:country":"PK",
    "wof:name":"Khu Gujranwala",
    "wof:placetype":"locality"
},
  "geometry": {"coordinates":[73.97091999999998,30.91193],"type":"Point"}
}