{
  "type": "Feature",
  "properties": {
    "gn:admin1_code":"4.0",
    "gn:asciiname":"Thatta Paharka",
    "gn:country_code":"PK",
    "gn:dem":180,
    "gn:feature_class":"P",
    "gn:feature_code":"PPL",
    "gn:name":"Thatta Paharka",
    "gn:population":0,
    "gn:timezone":"Asia/Karachi",
    "iso:country":"PK",
    "name:und_x_variant":[
        "Thatta Pah\u0101r"
    ],
    "wof:name":"Thatta Paharka",
    "wof:placetype":"locality"
},
  "geometry": {"coordinates":[73.43597,30.98945],"type":"Point"}
}