{
  "type": "Feature",
  "properties": {
    "gn:admin1_code":"2.0",
    "gn:asciiname":"Khuda Bukhsh Meraji",
    "gn:country_code":"PK",
    "gn:dem":818,
    "gn:feature_class":"P",
    "gn:feature_code":"PPL",
    "gn:name":"Khuda Bukhsh Meraji",
    "gn:population":0,
    "gn:timezone":"Asia/Karachi",
    "iso:country":"PK",
    "wof:name":"Khuda Bukhsh Meraji",
    "wof:placetype":"locality"
},
  "geometry": {"coordinates":[66.72024,26.37164000000001],"type":"Point"}
}