{
  "type": "Feature",
  "properties": {
    "gn:admin1_code":"04",
    "gn:asciiname":"Ramri",
    "gn:country_code":"PK",
    "gn:dem":271,
    "gn:feature_class":"P",
    "gn:feature_code":"PPL",
    "gn:name":"Ramri",
    "gn:population":0,
    "gn:timezone":"Asia/Karachi",
    "iso:country":"PK",
    "name:und_x_variant":[
        "Rambri",
        "R\u0101mri",
        "Ramri"
    ],
    "wof:name":"Ramri",
    "wof:placetype":"locality"
},
  "geometry": {"coordinates":[75.03756,32.31681],"type":"Point"}
}