{
  "type": "Feature",
  "properties": {
    "gn:admin1_code":"4.0",
    "gn:asciiname":"Moinabad",
    "gn:country_code":"PK",
    "gn:dem":90,
    "gn:feature_class":"P",
    "gn:feature_code":"PPL",
    "gn:name":"Moinabad",
    "gn:population":0,
    "gn:timezone":"Asia/Karachi",
    "iso:country":"PK",
    "name:fas_x_preferred":[
        "\u0645\u0639\u06cc\u0646\u200c\u0622\u0628\u0627\u062f"
    ],
    "name:und_x_variant":[
        "Mo\u012bn\u0101b\u0101d",
        "Moinabad"
    ],
    "wof:name":"Moinabad",
    "wof:placetype":"locality"
},
  "geometry": {"coordinates":[70.73234000000002,28.73403],"type":"Point"}
}