{
  "type": "Feature",
  "properties": {
    "gn:admin1_code":"3",
    "gn:asciiname":"Chamhat",
    "gn:country_code":"PK",
    "gn:dem":889,
    "gn:feature_class":"P",
    "gn:feature_code":"PPL",
    "gn:name":"Chamhat",
    "gn:population":0,
    "gn:timezone":"Asia/Karachi",
    "iso:country":"PK",
    "name:und_x_variant":[
        "Chamath"
    ],
    "wof:name":"Chamhat",
    "wof:placetype":"locality"
},
  "geometry": {"coordinates":[73.06522,34.36715],"type":"Point"}
}