{
  "type": "Feature",
  "properties": {
    "gn:admin1_code":"3.0",
    "gn:asciiname":"Madak Lasht",
    "gn:country_code":"PK",
    "gn:dem":3169,
    "gn:feature_class":"P",
    "gn:feature_code":"PPL",
    "gn:name":"Madak Lasht",
    "gn:population":0,
    "gn:timezone":"Asia/Karachi",
    "iso:country":"PK",
    "wof:name":"Madak Lasht",
    "wof:placetype":"locality"
},
  "geometry": {"coordinates":[72.32481,36.35108],"type":"Point"}
}