{
  "type": "Feature",
  "properties": {
    "gn:admin1_code":"5",
    "gn:asciiname":"Goth Jam Bilal Waso",
    "gn:country_code":"PK",
    "gn:dem":72,
    "gn:feature_class":"P",
    "gn:feature_code":"PPL",
    "gn:name":"Goth Jam Bilal Waso",
    "gn:population":0,
    "gn:timezone":"Asia/Karachi",
    "iso:country":"PK",
    "name:und_x_variant":[
        "Jam Bil\u0101l W\u0101so"
    ],
    "wof:name":"Goth Jam Bilal Waso",
    "wof:placetype":"locality"
},
  "geometry": {"coordinates":[69.36855,28.07456],"type":"Point"}
}