{
  "type": "Feature",
  "properties": {
    "gn:admin1_code":"4",
    "gn:asciiname":"Chak Manzurabad",
    "gn:country_code":"PK",
    "gn:dem":141,
    "gn:feature_class":"P",
    "gn:feature_code":"PPL",
    "gn:name":"Chak Manzurabad",
    "gn:population":0,
    "gn:timezone":"Asia/Karachi",
    "iso:country":"PK",
    "name:und_x_variant":[
        "Chak Manzar\u0101b\u0101d"
    ],
    "wof:name":"Chak Manzurabad",
    "wof:placetype":"locality"
},
  "geometry": {"coordinates":[71.95209,30.60312],"type":"Point"}
}