{
  "type": "Feature",
  "properties": {
    "gn:admin1_code":"4",
    "gn:asciiname":"Khotiwala",
    "gn:country_code":"PK",
    "gn:dem":152,
    "gn:feature_class":"P",
    "gn:feature_code":"PPL",
    "gn:name":"Khotiwala",
    "gn:population":0,
    "gn:timezone":"Asia/Karachi",
    "iso:country":"PK",
    "name:und_x_variant":[
        "Khothaw\u0101la"
    ],
    "wof:name":"Khotiwala",
    "wof:placetype":"locality"
},
  "geometry": {"coordinates":[71.62665,31.14675],"type":"Point"}
}