{
  "type": "Feature",
  "properties": {
    "gn:admin1_code":"6",
    "gn:asciiname":"Dora Tung",
    "gn:country_code":"PK",
    "gn:dem":2691,
    "gn:feature_class":"P",
    "gn:feature_code":"PPL",
    "gn:name":"Dora Tung",
    "gn:population":0,
    "gn:timezone":"Asia/Karachi",
    "iso:country":"PK",
    "wof:name":"Dora Tung",
    "wof:placetype":"locality"
},
  "geometry": {"coordinates":[73.93628000000002,34.2639],"type":"Point"}
}