{
  "type": "Feature",
  "properties": {
    "gn:admin1_code":"4",
    "gn:asciiname":"Khurane Mirasiwala",
    "gn:country_code":"PK",
    "gn:dem":147,
    "gn:feature_class":"P",
    "gn:feature_code":"PPL",
    "gn:name":"Khurane Mirasiwala",
    "gn:population":0,
    "gn:timezone":"Asia/Karachi",
    "iso:country":"PK",
    "name:und_x_variant":[
        "Khur\u0101na Mir\u0101siw\u0101la"
    ],
    "wof:name":"Khurane Mirasiwala",
    "wof:placetype":"locality"
},
  "geometry": {"coordinates":[71.62104000000002,31.01369],"type":"Point"}
}