{
  "type": "Feature",
  "properties": {
    "gn:admin1_code":"01",
    "gn:asciiname":"Katai Shal",
    "gn:country_code":"PK",
    "gn:dem":969,
    "gn:feature_class":"P",
    "gn:feature_code":"PPL",
    "gn:name":"Katai Shal",
    "gn:population":0,
    "gn:timezone":"Asia/Karachi",
    "iso:country":"PK",
    "name:eng_x_preferred":[
        "Kota Sh\u0101h"
    ],
    "wof:name":"Katai Shal",
    "wof:placetype":"locality"
},
  "geometry": {"coordinates":[71.68788000000001,34.72778],"type":"Point"}
}