{
  "type": "Feature",
  "properties": {
    "gn:admin1_code":"3.0",
    "gn:asciiname":"Namb",
    "gn:country_code":"PK",
    "gn:dem":1099,
    "gn:feature_class":"P",
    "gn:feature_code":"PPL",
    "gn:name":"Namb",
    "gn:population":0,
    "gn:timezone":"Asia/Karachi",
    "iso:country":"PK",
    "name:eng_x_preferred":[
        "Namb"
    ],
    "wof:name":"Namb",
    "wof:placetype":"locality"
},
  "geometry": {"coordinates":[73.28409000000001,33.88617],"type":"Point"}
}