{
  "type": "Feature",
  "properties": {
    "gn:admin1_code":"2",
    "gn:asciiname":"Kili Malik",
    "gn:country_code":"PK",
    "gn:dem":844,
    "gn:feature_class":"P",
    "gn:feature_code":"PPL",
    "gn:name":"Kili Malik",
    "gn:population":0,
    "gn:timezone":"Asia/Karachi",
    "iso:country":"PK",
    "name:und_x_variant":[
        "Kili Malik \u012asu"
    ],
    "wof:name":"Kili Malik",
    "wof:placetype":"locality"
},
  "geometry": {"coordinates":[65.66315999999999,29.17808],"type":"Point"}
}