{
  "type": "Feature",
  "properties": {
    "gn:admin1_code":"04",
    "gn:asciiname":"Kot Jiwa",
    "gn:country_code":"PK",
    "gn:dem":217,
    "gn:feature_class":"P",
    "gn:feature_code":"PPL",
    "gn:name":"Kot Jiwa",
    "gn:population":0,
    "gn:timezone":"Asia/Karachi",
    "iso:country":"PK",
    "wof:name":"Kot Jiwa",
    "wof:placetype":"locality"
},
  "geometry": {"coordinates":[73.94785999999998,32.15885],"type":"Point"}
}