{
  "type": "Feature",
  "properties": {
    "gn:admin1_code":"01",
    "gn:asciiname":"Shama",
    "gn:country_code":"PK",
    "gn:dem":776,
    "gn:feature_class":"P",
    "gn:feature_code":"PPL",
    "gn:name":"Shama",
    "gn:population":0,
    "gn:timezone":"Asia/Karachi",
    "iso:country":"PK",
    "name:ceb_x_preferred":[
        "Shama"
    ],
    "name:deu_x_preferred":[
        "Shama"
    ],
    "name:fra_x_preferred":[
        "Shama"
    ],
    "name:swe_x_preferred":[
        "Shama"
    ],
    "wof:name":"Shama",
    "wof:placetype":"locality"
},
  "geometry": {"coordinates":[71.47075,34.60242],"type":"Point"}
}