{
  "type": "Feature",
  "properties": {
    "gn:admin1_code":"4.0",
    "gn:asciiname":"Mojuke Mallian",
    "gn:country_code":"PK",
    "gn:dem":211,
    "gn:feature_class":"P",
    "gn:feature_code":"PPL",
    "gn:name":"Mojuke Mallian",
    "gn:population":0,
    "gn:timezone":"Asia/Karachi",
    "iso:country":"PK",
    "name:und_x_variant":[
        "Maujoke Malli\u0101h"
    ],
    "wof:name":"Mojuke Mallian",
    "wof:placetype":"locality"
},
  "geometry": {"coordinates":[74.07156999999999,31.75171],"type":"Point"}
}