{
  "type": "Feature",
  "properties": {
    "gn:admin1_code":"3.0",
    "gn:asciiname":"Kechi Kamar",
    "gn:country_code":"PK",
    "gn:dem":257,
    "gn:feature_class":"P",
    "gn:feature_code":"PPL",
    "gn:name":"Kechi Kamar",
    "gn:population":0,
    "gn:timezone":"Asia/Karachi",
    "iso:country":"PK",
    "name:und_x_variant":[
        "Kachi Kamar",
        "Kechi Kamar"
    ],
    "wof:name":"Kechi Kamar",
    "wof:placetype":"locality"
},
  "geometry": {"coordinates":[70.98149000000002,32.66257],"type":"Point"}
}