{
  "type": "Feature",
  "properties": {
    "gn:admin1_code":"5",
    "gn:asciiname":"Goth Agha Bakhshal Khan",
    "gn:country_code":"PK",
    "gn:dem":59,
    "gn:feature_class":"P",
    "gn:feature_code":"PPL",
    "gn:name":"Goth Agha Bakhshal Khan",
    "gn:population":0,
    "gn:timezone":"Asia/Karachi",
    "iso:country":"PK",
    "name:und_x_variant":[
        "Path\u0101n"
    ],
    "wof:name":"Goth Agha Bakhshal Khan",
    "wof:placetype":"locality"
},
  "geometry": {"coordinates":[68.38336,28.09965],"type":"Point"}
}