{
  "type": "Feature",
  "properties": {
    "gn:admin1_code":"4",
    "gn:asciiname":"Saiyidwala",
    "gn:country_code":"PK",
    "gn:dem":159,
    "gn:feature_class":"P",
    "gn:feature_code":"PPL",
    "gn:name":"Saiyidwala",
    "gn:population":0,
    "gn:timezone":"Asia/Karachi",
    "iso:country":"PK",
    "wof:name":"Saiyidwala",
    "wof:placetype":"locality"
},
  "geometry": {"coordinates":[71.05143000000002,31.26386],"type":"Point"}
}