{
  "type": "Feature",
  "properties": {
    "gn:admin1_code":"4",
    "gn:asciiname":"Masitwala",
    "gn:country_code":"PK",
    "gn:dem":218,
    "gn:feature_class":"P",
    "gn:feature_code":"PPL",
    "gn:name":"Masitwala",
    "gn:population":0,
    "gn:timezone":"Asia/Karachi",
    "iso:country":"PK",
    "name:und_x_variant":[
        "Mas\u012bt"
    ],
    "wof:name":"Masitwala",
    "wof:placetype":"locality"
},
  "geometry": {"coordinates":[71.23317,32.64550999999999],"type":"Point"}
}