{
  "type": "Feature",
  "properties": {
    "gn:admin1_code":"01",
    "gn:asciiname":"Ajdarra",
    "gn:country_code":"PK",
    "gn:dem":724,
    "gn:feature_class":"P",
    "gn:feature_code":"PPL",
    "gn:name":"Ajdarra",
    "gn:population":0,
    "gn:timezone":"Asia/Karachi",
    "iso:country":"PK",
    "name:fas_x_preferred":[
        "\u0639\u0627\u062c\u200c\u062f\u0631\u0647"
    ],
    "name:und_x_variant":[
        "Ajdara"
    ],
    "wof:name":"Ajdarra",
    "wof:placetype":"locality"
},
  "geometry": {"coordinates":[71.46115,34.59551],"type":"Point"}
}