{
  "type": "Feature",
  "properties": {
    "gn:admin1_code":"7.0",
    "gn:asciiname":"Matesha",
    "gn:country_code":"PK",
    "gn:dem":3044,
    "gn:feature_class":"P",
    "gn:feature_code":"PPL",
    "gn:name":"Matesha",
    "gn:population":0,
    "gn:timezone":"Asia/Karachi",
    "iso:country":"PK",
    "wof:name":"Matesha",
    "wof:placetype":"locality"
},
  "geometry": {"coordinates":[76.16064,35.25502],"type":"Point"}
}