{
  "type": "Feature",
  "properties": {
    "gn:admin1_code":"3",
    "gn:asciiname":"Jumadera",
    "gn:country_code":"PK",
    "gn:dem":1727,
    "gn:feature_class":"P",
    "gn:feature_code":"PPL",
    "gn:name":"Jumadera",
    "gn:population":0,
    "gn:timezone":"Asia/Karachi",
    "iso:country":"PK",
    "wof:name":"Jumadera",
    "wof:placetype":"locality"
},
  "geometry": {"coordinates":[72.69634000000001,34.60583],"type":"Point"}
}