{
  "type": "Feature",
  "properties": {
    "gn:admin1_code":"5.0",
    "gn:asciiname":"Goth Usman Rustamani",
    "gn:country_code":"PK",
    "gn:dem":322,
    "gn:feature_class":"P",
    "gn:feature_code":"PPL",
    "gn:name":"Goth Usman Rustamani",
    "gn:population":0,
    "gn:timezone":"Asia/Karachi",
    "iso:country":"PK",
    "wof:name":"Goth Usman Rustamani",
    "wof:placetype":"locality"
},
  "geometry": {"coordinates":[67.23430999999999,27.19496],"type":"Point"}
}