{
  "type": "Feature",
  "properties": {
    "gn:admin1_code":"4",
    "gn:asciiname":"Korewala",
    "gn:country_code":"PK",
    "gn:dem":104,
    "gn:feature_class":"P",
    "gn:feature_code":"PPL",
    "gn:name":"Korewala",
    "gn:population":0,
    "gn:timezone":"Asia/Karachi",
    "iso:country":"PK",
    "name:und_x_variant":[
        "Kaurew\u0101la"
    ],
    "wof:name":"Korewala",
    "wof:placetype":"locality"
},
  "geometry": {"coordinates":[70.53095999999999,29.44951],"type":"Point"}
}