{
  "type": "Feature",
  "properties": {
    "gn:admin1_code":"4.0",
    "gn:asciiname":"Basti Afzal",
    "gn:country_code":"PK",
    "gn:dem":102,
    "gn:feature_class":"P",
    "gn:feature_code":"PPL",
    "gn:name":"Basti Afzal",
    "gn:population":0,
    "gn:timezone":"Asia/Karachi",
    "iso:country":"PK",
    "name:und_x_variant":[
        "Basti Afzal Buzd\u0101r"
    ],
    "wof:name":"Basti Afzal",
    "wof:placetype":"locality"
},
  "geometry": {"coordinates":[70.25503,29.225],"type":"Point"}
}