{
  "type": "Feature",
  "properties": {
    "gn:admin1_code":"5.0",
    "gn:asciiname":"Sachal Khan",
    "gn:country_code":"PK",
    "gn:dem":56,
    "gn:feature_class":"P",
    "gn:feature_code":"PPL",
    "gn:name":"Sachal Khan",
    "gn:population":0,
    "gn:timezone":"Asia/Karachi",
    "iso:country":"PK",
    "name:eng_x_preferred":[
        "Goth Sachal Kh\u0101n"
    ],
    "wof:name":"Sachal Khan",
    "wof:placetype":"locality"
},
  "geometry": {"coordinates":[68.56636,27.48853],"type":"Point"}
}