{
  "type": "Feature",
  "properties": {
    "gn:admin1_code":"7.0",
    "gn:asciiname":"Ispah",
    "gn:country_code":"PK",
    "gn:dem":2890,
    "gn:feature_class":"P",
    "gn:feature_code":"PPL",
    "gn:name":"Ispah",
    "gn:population":0,
    "gn:timezone":"Asia/Karachi",
    "iso:country":"PK",
    "name:und_x_variant":[
        "Aspa"
    ],
    "wof:name":"Ispah",
    "wof:placetype":"locality"
},
  "geometry": {"coordinates":[74.85566999999998,35.0206],"type":"Point"}
}