{
  "type": "Feature",
  "properties": {
    "gn:admin1_code":"01",
    "gn:asciiname":"Shah Mir",
    "gn:country_code":"PK",
    "gn:dem":746,
    "gn:feature_class":"P",
    "gn:feature_code":"PPL",
    "gn:name":"Shah Mir",
    "gn:population":0,
    "gn:timezone":"Asia/Karachi",
    "iso:country":"PK",
    "name:azb_x_preferred":[
        "\u0634\u0645\u0633 \u0627\u0644\u062f\u06cc\u0646 \u0634\u0627\u0647\u0645\u06cc\u0631"
    ],
    "name:jpn_x_preferred":[
        "\u30b7\u30e3\u30fc\u30fb\u30df\u30fc\u30eb"
    ],
    "name:und_x_variant":[
        "Sp\u012bnw\u0101m"
    ],
    "wof:name":"Shah Mir",
    "wof:placetype":"locality"
},
  "geometry": {"coordinates":[70.38077,33.18017],"type":"Point"}
}