{
  "type": "Feature",
  "properties": {
    "gn:admin1_code":"4.0",
    "gn:asciiname":"Chak One Hundred Ninety-two Eastern Bank",
    "gn:country_code":"PK",
    "gn:dem":141,
    "gn:feature_class":"P",
    "gn:feature_code":"PPL",
    "gn:name":"Chak One Hundred Ninety-two Eastern Bank",
    "gn:population":0,
    "gn:timezone":"Asia/Karachi",
    "iso:country":"PK",
    "wof:name":"Chak One Hundred Ninety-two Eastern Bank",
    "wof:placetype":"locality"
},
  "geometry": {"coordinates":[72.41186,30.14405],"type":"Point"}
}