{
  "type": "Feature",
  "properties": {
    "gn:admin1_code":"4",
    "gn:asciiname":"Basti Lal",
    "gn:country_code":"PK",
    "gn:dem":143,
    "gn:feature_class":"P",
    "gn:feature_code":"PPL",
    "gn:name":"Basti Lal",
    "gn:population":0,
    "gn:timezone":"Asia/Karachi",
    "iso:country":"PK",
    "name:eng_x_preferred":[
        "Basti Lal"
    ],
    "wof:name":"Basti Lal",
    "wof:placetype":"locality"
},
  "geometry": {"coordinates":[70.60656,30.28402],"type":"Point"}
}