{
  "type": "Feature",
  "properties": {
    "gn:admin1_code":"2",
    "gn:asciiname":"Aioto",
    "gn:country_code":"PK",
    "gn:dem":117,
    "gn:feature_class":"P",
    "gn:feature_code":"PPL",
    "gn:name":"Aioto",
    "gn:population":0,
    "gn:timezone":"Asia/Karachi",
    "iso:country":"PK",
    "name:und_x_variant":[
        "Hijo Kh\u0101n"
    ],
    "wof:name":"Aioto",
    "wof:placetype":"locality"
},
  "geometry": {"coordinates":[67.58173000000001,29.14296],"type":"Point"}
}