{
  "type": "Feature",
  "properties": {
    "gn:admin1_code":"3.0",
    "gn:asciiname":"Majuhan",
    "gn:country_code":"PK",
    "gn:dem":1526,
    "gn:feature_class":"P",
    "gn:feature_code":"PPL",
    "gn:name":"Majuhan",
    "gn:population":0,
    "gn:timezone":"Asia/Karachi",
    "iso:country":"PK",
    "name:eng_x_preferred":[
        "Majuhan"
    ],
    "wof:name":"Majuhan",
    "wof:placetype":"locality"
},
  "geometry": {"coordinates":[73.1985,33.95497],"type":"Point"}
}