{
  "type": "Feature",
  "properties": {
    "gn:admin1_code":"04",
    "gn:asciiname":"Kot Jan Muhammad",
    "gn:country_code":"PK",
    "gn:dem":207,
    "gn:feature_class":"P",
    "gn:feature_code":"PPL",
    "gn:name":"Kot Jan Muhammad",
    "gn:population":0,
    "gn:timezone":"Asia/Karachi",
    "iso:country":"PK",
    "name:und_x_variant":[
        "Kot Jan Muhammad Khokhar",
        "Kot Jan Muhammad"
    ],
    "wof:name":"Kot Jan Muhammad",
    "wof:placetype":"locality"
},
  "geometry": {"coordinates":[73.57486999999998,32.24048],"type":"Point"}
}