{
  "type": "Feature",
  "properties": {
    "gn:admin1_code":"4.0",
    "gn:asciiname":"Basti Khirani",
    "gn:country_code":"PK",
    "gn:dem":141,
    "gn:feature_class":"P",
    "gn:feature_code":"PPL",
    "gn:name":"Basti Khirani",
    "gn:population":0,
    "gn:timezone":"Asia/Karachi",
    "iso:country":"PK",
    "wof:name":"Basti Khirani",
    "wof:placetype":"locality"
},
  "geometry": {"coordinates":[70.89591999999998,30.76672],"type":"Point"}
}