{
  "type": "Feature",
  "properties": {
    "gn:admin1_code":"6",
    "gn:asciiname":"Lambi Mohri",
    "gn:country_code":"PK",
    "gn:dem":3168,
    "gn:feature_class":"P",
    "gn:feature_code":"PPL",
    "gn:name":"Lambi Mohri",
    "gn:population":0,
    "gn:timezone":"Asia/Karachi",
    "iso:country":"PK",
    "name:und_x_variant":[
        "Lammi Mohri"
    ],
    "wof:name":"Lambi Mohri",
    "wof:placetype":"locality"
},
  "geometry": {"coordinates":[73.49654,34.56313],"type":"Point"}
}