{
  "type": "Feature",
  "properties": {
    "gn:admin1_code":"3.0",
    "gn:asciiname":"Kuz Kalle",
    "gn:country_code":"PK",
    "gn:dem":389,
    "gn:feature_class":"P",
    "gn:feature_code":"PPL",
    "gn:name":"Kuz Kalle",
    "gn:population":0,
    "gn:timezone":"Asia/Karachi",
    "iso:country":"PK",
    "wof:name":"Kuz Kalle",
    "wof:placetype":"locality"
},
  "geometry": {"coordinates":[71.82371999999999,34.35357],"type":"Point"}
}