{
  "type": "Feature",
  "properties": {
    "gn:admin1_code":"2.0",
    "gn:asciiname":"Mohim Khan",
    "gn:country_code":"PK",
    "gn:dem":1068,
    "gn:feature_class":"P",
    "gn:feature_code":"PPL",
    "gn:name":"Mohim Khan",
    "gn:population":0,
    "gn:timezone":"Asia/Karachi",
    "iso:country":"PK",
    "name:eng_x_preferred":[
        "Mohim Khan"
    ],
    "wof:name":"Mohim Khan",
    "wof:placetype":"locality"
},
  "geometry": {"coordinates":[69.47081,29.87007],"type":"Point"}
}