{
  "type": "Feature",
  "properties": {
    "gn:admin1_code":"2.0",
    "gn:asciiname":"Kallag Kalat",
    "gn:country_code":"PK",
    "gn:dem":535,
    "gn:feature_class":"P",
    "gn:feature_code":"PPL",
    "gn:name":"Kallag Kalat",
    "gn:population":0,
    "gn:timezone":"Asia/Karachi",
    "iso:country":"PK",
    "name:und_x_variant":[
        "Kallag"
    ],
    "wof:name":"Kallag Kalat",
    "wof:placetype":"locality"
},
  "geometry": {"coordinates":[63.01313,27.88954],"type":"Point"}
}