{
  "type": "Feature",
  "properties": {
    "gn:admin1_code":"7.0",
    "gn:asciiname":"Kati Bran",
    "gn:country_code":"PK",
    "gn:dem":2547,
    "gn:feature_class":"P",
    "gn:feature_code":"PPL",
    "gn:name":"Kati Bran",
    "gn:population":0,
    "gn:timezone":"Asia/Karachi",
    "iso:country":"PK",
    "name:und_x_variant":[
        "Huldoro"
    ],
    "wof:name":"Kati Bran",
    "wof:placetype":"locality"
},
  "geometry": {"coordinates":[75.40269000000001,35.79826],"type":"Point"}
}