{
  "type": "Feature",
  "properties": {
    "gn:admin1_code":"01",
    "gn:asciiname":"Piro Khel",
    "gn:country_code":"PK",
    "gn:dem":1165,
    "gn:feature_class":"P",
    "gn:feature_code":"PPL",
    "gn:name":"Piro Khel",
    "gn:population":0,
    "gn:timezone":"Asia/Karachi",
    "iso:country":"PK",
    "name:und_x_variant":[
        "P\u012bro Khel"
    ],
    "wof:name":"Piro Khel",
    "wof:placetype":"locality"
},
  "geometry": {"coordinates":[71.16856999999997,34.13115999999999],"type":"Point"}
}