{
  "type": "Feature",
  "properties": {
    "gn:admin1_code":"6.0",
    "gn:asciiname":"Nalla Musalmanan",
    "gn:country_code":"PK",
    "gn:dem":615,
    "gn:feature_class":"P",
    "gn:feature_code":"PPL",
    "gn:name":"Nalla Musalmanan",
    "gn:population":0,
    "gn:timezone":"Asia/Karachi",
    "iso:country":"PK",
    "name:und_x_variant":[
        "Nala Musalm\u0101n\u0101n"
    ],
    "wof:name":"Nalla Musalmanan",
    "wof:placetype":"locality"
},
  "geometry": {"coordinates":[73.52266999999998,33.46123],"type":"Point"}
}