{
  "type": "Feature",
  "properties": {
    "gn:admin1_code":"4",
    "gn:asciiname":"Basti Bohar",
    "gn:country_code":"PK",
    "gn:dem":92,
    "gn:feature_class":"P",
    "gn:feature_code":"PPL",
    "gn:name":"Basti Bohar",
    "gn:population":0,
    "gn:timezone":"Asia/Karachi",
    "iso:country":"PK",
    "name:und_x_variant":[
        "Bohar"
    ],
    "wof:name":"Basti Bohar",
    "wof:placetype":"locality"
},
  "geometry": {"coordinates":[70.80528000000002,28.89245],"type":"Point"}
}