{
  "type": "Feature",
  "properties": {
    "gn:admin1_code":"4",
    "gn:asciiname":"Basti Dajal",
    "gn:country_code":"PK",
    "gn:dem":167,
    "gn:feature_class":"P",
    "gn:feature_code":"PPL",
    "gn:name":"Basti Dajal",
    "gn:population":0,
    "gn:timezone":"Asia/Karachi",
    "iso:country":"PK",
    "name:und_x_variant":[
        "D\u0101jal",
        "D\u0101ja",
        "Basti Dajal"
    ],
    "wof:name":"Basti Dajal",
    "wof:placetype":"locality"
},
  "geometry": {"coordinates":[70.99521999999997,31.73284],"type":"Point"}
}