{
  "type": "Feature",
  "properties": {
    "gn:admin1_code":"04",
    "gn:asciiname":"Chak Four -Four Left",
    "gn:country_code":"PK",
    "gn:dem":181,
    "gn:feature_class":"P",
    "gn:feature_code":"PPL",
    "gn:name":"Chak Four -Four Left",
    "gn:population":0,
    "gn:timezone":"Asia/Karachi",
    "iso:country":"PK",
    "name:und_x_variant":[
        "Panditpur",
        "Pandatpur"
    ],
    "wof:name":"Chak Four -Four Left",
    "wof:placetype":"locality"
},
  "geometry": {"coordinates":[73.42142,30.78149],"type":"Point"}
}