{
  "type": "Feature",
  "properties": {
    "gn:admin1_code":"4",
    "gn:asciiname":"Chak Forty-six -Ten Right",
    "gn:country_code":"PK",
    "gn:dem":133,
    "gn:feature_class":"P",
    "gn:feature_code":"PPL",
    "gn:name":"Chak Forty-six -Ten Right",
    "gn:population":0,
    "gn:timezone":"Asia/Karachi",
    "iso:country":"PK",
    "name:und_x_variant":[
        "Chak Forty-six"
    ],
    "wof:name":"Chak Forty-six -Ten Right",
    "wof:placetype":"locality"
},
  "geometry": {"coordinates":[72.04174999999999,30.13105],"type":"Point"}
}