{
  "type": "Feature",
  "properties": {
    "gn:admin1_code":"04",
    "gn:asciiname":"Mehr",
    "gn:country_code":"PK",
    "gn:dem":326,
    "gn:feature_class":"P",
    "gn:feature_code":"PPL",
    "gn:name":"Mehr",
    "gn:population":0,
    "gn:timezone":"Asia/Karachi",
    "iso:country":"PK",
    "name:und_x_variant":[
        "Mair",
        "Mehr"
    ],
    "wof:name":"Mehr",
    "wof:placetype":"locality"
},
  "geometry": {"coordinates":[73.93541999999999,32.86779],"type":"Point"}
}