{
  "type": "Feature",
  "properties": {
    "gn:admin1_code":"4.0",
    "gn:asciiname":"Mudwala Khurd",
    "gn:country_code":"PK",
    "gn:dem":205,
    "gn:feature_class":"P",
    "gn:feature_code":"PPL",
    "gn:name":"Mudwala Khurd",
    "gn:population":0,
    "gn:timezone":"Asia/Karachi",
    "iso:country":"PK",
    "wof:name":"Mudwala Khurd",
    "wof:placetype":"locality"
},
  "geometry": {"coordinates":[74.07441999999998,31.63487000000001],"type":"Point"}
}