{
  "type": "Feature",
  "properties": {
    "gn:admin1_code":"3",
    "gn:asciiname":"Khanori",
    "gn:country_code":"PK",
    "gn:dem":2096,
    "gn:feature_class":"P",
    "gn:feature_code":"PPL",
    "gn:name":"Khanori",
    "gn:population":0,
    "gn:timezone":"Asia/Karachi",
    "iso:country":"PK",
    "wof:name":"Khanori",
    "wof:placetype":"locality"
},
  "geometry": {"coordinates":[73.39190000000001,34.59831],"type":"Point"}
}