{
  "type": "Feature",
  "properties": {
    "gn:admin1_code":"7.0",
    "gn:asciiname":"Chukutans",
    "gn:country_code":"PK",
    "gn:dem":3959,
    "gn:feature_class":"P",
    "gn:feature_code":"PPL",
    "gn:name":"Chukutans",
    "gn:population":0,
    "gn:timezone":"Asia/Karachi",
    "iso:country":"PK",
    "name:und_x_variant":[
        "Ch\u016bk\u016brans"
    ],
    "wof:name":"Chukutans",
    "wof:placetype":"locality"
},
  "geometry": {"coordinates":[74.90196,36.13423],"type":"Point"}
}