{
  "type": "Feature",
  "properties": {
    "gn:admin1_code":"6.0",
    "gn:asciiname":"Danna",
    "gn:country_code":"PK",
    "gn:dem":1993,
    "gn:feature_class":"P",
    "gn:feature_code":"PPL",
    "gn:name":"Danna",
    "gn:population":0,
    "gn:timezone":"Asia/Karachi",
    "iso:country":"PK",
    "wof:name":"Danna",
    "wof:placetype":"locality"
},
  "geometry": {"coordinates":[73.71293,33.84899],"type":"Point"}
}