{
  "type": "Feature",
  "properties": {
    "gn:admin1_code":"3.0",
    "gn:asciiname":"Mangala",
    "gn:country_code":"PK",
    "gn:dem":1552,
    "gn:feature_class":"P",
    "gn:feature_code":"PPL",
    "gn:name":"Mangala",
    "gn:population":0,
    "gn:timezone":"Asia/Karachi",
    "iso:country":"PK",
    "name:ben_x_preferred":[
        "\u09ae\u0999\u09cd\u0997\u09b2"
    ],
    "name:bos_x_preferred":[
        "Mangala"
    ],
    "name:eng_x_preferred":[
        "Mangala"
    ],
    "name:fra_x_preferred":[
        "Mangala"
    ],
    "name:hin_x_preferred":[
        "\u092e\u0902\u0917\u0932"
    ],
    "name:ind_x_preferred":[
        "Anggaraka"
    ],
    "name:mar_x_preferred":[
        "\u092e\u0902\u0917\u0933"
    ],
    "name:nor_x_preferred":[
        "Mangala"
    ],
    "name:pol_x_preferred":[
        "Mangala"
    ],
    "name:por_x_preferred":[
        "Mangala"
    ],
    "name:rus_x_preferred":[
        "\u041c\u0430\u043d\u0433\u0430\u043b\u0430"
    ],
    "name:tam_x_preferred":[
        "\u0b85\u0b99\u0bcd\u0b95\u0bbe\u0bb0\u0b95\u0ba9\u0bcd"
    ],
    "name:tel_x_preferred":[
        "\u0c05\u0c02\u0c17\u0c3e\u0c30\u0c15\u0c41\u0c21\u0c41"
    ],
    "name:tha_x_preferred":[
        "\u0e1e\u0e23\u0e30\u0e2d\u0e31\u0e07\u0e04\u0e32\u0e23"
    ],
    "name:ukr_x_preferred":[
        "\u041c\u0430\u043d\u0433\u0430\u043b\u0430"
    ],
    "wof:name":"Mangala",
    "wof:placetype":"locality"
},
  "geometry": {"coordinates":[72.08953000000002,35.35064000000001],"type":"Point"}
}