{
  "type": "Feature",
  "properties": {
    "gn:admin1_code":"3.0",
    "gn:asciiname":"Mangala",
    "gn:country_code":"PK",
    "gn:dem":1552,
    "gn:feature_class":"P",
    "gn:feature_code":"PPL",
    "gn:name":"Mangala",
    "gn:population":0,
    "gn:timezone":"Asia/Karachi",
    "iso:country":"PK",
    "name:eng_x_preferred":[
        "Mangala"
    ],
    "wof:name":"Mangala",
    "wof:placetype":"locality"
},
  "geometry": {"coordinates":[72.08953000000002,35.35064000000001],"type":"Point"}
}