{
  "type": "Feature",
  "properties": {
    "gn:admin1_code":"5.0",
    "gn:asciiname":"Goth Hayat Mahi",
    "gn:country_code":"PK",
    "gn:dem":52,
    "gn:feature_class":"P",
    "gn:feature_code":"PPL",
    "gn:name":"Goth Hayat Mahi",
    "gn:population":0,
    "gn:timezone":"Asia/Karachi",
    "iso:country":"PK",
    "name:und_x_variant":[
        "Hay\u0101t M\u0101chhi"
    ],
    "wof:name":"Goth Hayat Mahi",
    "wof:placetype":"locality"
},
  "geometry": {"coordinates":[68.64029000000001,27.27601],"type":"Point"}
}