{
  "type": "Feature",
  "properties": {
    "gn:admin1_code":"4.0",
    "gn:asciiname":"Dhok Jama",
    "gn:country_code":"PK",
    "gn:dem":422,
    "gn:feature_class":"P",
    "gn:feature_code":"PPL",
    "gn:name":"Dhok Jama",
    "gn:population":0,
    "gn:timezone":"Asia/Karachi",
    "iso:country":"PK",
    "wof:name":"Dhok Jama",
    "wof:placetype":"locality"
},
  "geometry": {"coordinates":[72.68944999999999,33.79487],"type":"Point"}
}