{
  "type": "Feature",
  "properties": {
    "gn:admin1_code":"08",
    "gn:asciiname":"Sher Dhamial",
    "gn:country_code":"PK",
    "gn:dem":527,
    "gn:feature_class":"P",
    "gn:feature_code":"PPL",
    "gn:name":"Sher Dhamial",
    "gn:population":0,
    "gn:timezone":"Asia/Karachi",
    "iso:country":"PK",
    "wof:name":"Sher Dhamial",
    "wof:placetype":"locality"
},
  "geometry": {"coordinates":[73.20624000000002,33.58322],"type":"Point"}
}