{
  "type": "Feature",
  "properties": {
    "gn:admin1_code":"4.0",
    "gn:asciiname":"Ichogil Kalan",
    "gn:country_code":"PK",
    "gn:dem":218,
    "gn:feature_class":"P",
    "gn:feature_code":"PPL",
    "gn:name":"Ichogil Kalan",
    "gn:population":0,
    "gn:timezone":"Asia/Karachi",
    "iso:country":"PK",
    "name:und_x_variant":[
        "Ichogil Utt\u0101r"
    ],
    "wof:name":"Ichogil Kalan",
    "wof:placetype":"locality"
},
  "geometry": {"coordinates":[74.50265,31.68033],"type":"Point"}
}