{
  "type": "Feature",
  "properties": {
    "gn:admin1_code":"3",
    "gn:asciiname":"Dulai Kandao",
    "gn:country_code":"PK",
    "gn:dem":1519,
    "gn:feature_class":"P",
    "gn:feature_code":"PPL",
    "gn:name":"Dulai Kandao",
    "gn:population":0,
    "gn:timezone":"Asia/Karachi",
    "iso:country":"PK",
    "wof:name":"Dulai Kandao",
    "wof:placetype":"locality"
},
  "geometry": {"coordinates":[72.07863,34.86993],"type":"Point"}
}