{
  "type": "Feature",
  "properties": {
    "gn:admin1_code":"1.0",
    "gn:asciiname":"Fateh Khel",
    "gn:country_code":"PK",
    "gn:dem":825,
    "gn:feature_class":"P",
    "gn:feature_code":"PPL",
    "gn:name":"Fateh Khel",
    "gn:population":0,
    "gn:timezone":"Asia/Karachi",
    "iso:country":"PK",
    "wof:name":"Fateh Khel",
    "wof:placetype":"locality"
},
  "geometry": {"coordinates":[70.38880999999998,33.23328],"type":"Point"}
}