{
  "type": "Feature",
  "properties": {
    "gn:admin1_code":"5.0",
    "gn:asciiname":"Goth Allahdino",
    "gn:country_code":"PK",
    "gn:dem":277,
    "gn:feature_class":"P",
    "gn:feature_code":"PPL",
    "gn:name":"Goth Allahdino",
    "gn:population":0,
    "gn:timezone":"Asia/Karachi",
    "iso:country":"PK",
    "wof:name":"Goth Allahdino",
    "wof:placetype":"locality"
},
  "geometry": {"coordinates":[67.42415,25.27288],"type":"Point"}
}