{
  "type": "Feature",
  "properties": {
    "gn:admin1_code":"4.0",
    "gn:asciiname":"Ziarat",
    "gn:country_code":"PK",
    "gn:dem":187,
    "gn:feature_class":"P",
    "gn:feature_code":"PPL",
    "gn:name":"Ziarat",
    "gn:population":0,
    "gn:timezone":"Asia/Karachi",
    "iso:country":"PK",
    "name:ben_x_preferred":[
        "\u099c\u09bf\u09af\u09bc\u09be\u09b0\u09a4"
    ],
    "name:ceb_x_preferred":[
        "Zi\u0101rat"
    ],
    "name:fas_x_preferred":[
        "\u0632\u06cc\u0627\u0631\u062a"
    ],
    "name:fra_x_preferred":[
        "Ziarat"
    ],
    "name:ind_x_preferred":[
        "Ziarat"
    ],
    "name:ita_x_preferred":[
        "Ziarat"
    ],
    "name:msa_x_preferred":[
        "Ziarat"
    ],
    "name:pnb_x_preferred":[
        "\u062a\u0635\u06cc\u0644 \u0632\u06cc\u0627\u0631\u062a"
    ],
    "name:rus_x_preferred":[
        "\u0417\u0438\u0430\u0440\u0430\u0442"
    ],
    "name:spa_x_preferred":[
        "Ziarat"
    ],
    "name:swe_x_preferred":[
        "Ziarat"
    ],
    "name:urd_x_preferred":[
        "\u0632\u06cc\u0627\u0631\u062a"
    ],
    "wof:name":"Ziarat",
    "wof:placetype":"locality"
},
  "geometry": {"coordinates":[74.01226,30.9279],"type":"Point"}
}