{
  "type": "Feature",
  "properties": {
    "gn:admin1_code":"2.0",
    "gn:asciiname":"Ali Gul Kili",
    "gn:country_code":"PK",
    "gn:dem":1256,
    "gn:feature_class":"P",
    "gn:feature_code":"PPL",
    "gn:name":"Ali Gul Kili",
    "gn:population":0,
    "gn:timezone":"Asia/Karachi",
    "iso:country":"PK",
    "wof:name":"Ali Gul Kili",
    "wof:placetype":"locality"
},
  "geometry": {"coordinates":[66.38514000000001,30.87846],"type":"Point"}
}