{
  "type": "Feature",
  "properties": {
    "gn:admin1_code":"4.0",
    "gn:asciiname":"Bado Ratta",
    "gn:country_code":"PK",
    "gn:dem":216,
    "gn:feature_class":"P",
    "gn:feature_code":"PPL",
    "gn:name":"Bado Ratta",
    "gn:population":0,
    "gn:timezone":"Asia/Karachi",
    "iso:country":"PK",
    "name:und_x_variant":[
        "Baddo Ratta",
        "Bado Ratta"
    ],
    "wof:name":"Bado Ratta",
    "wof:placetype":"locality"
},
  "geometry": {"coordinates":[73.99377,31.93791],"type":"Point"}
}