{
  "type": "Feature",
  "properties": {
    "gn:admin1_code":"4.0",
    "gn:asciiname":"Simbl",
    "gn:country_code":"PK",
    "gn:dem":308,
    "gn:feature_class":"P",
    "gn:feature_code":"PPL",
    "gn:name":"Simbl",
    "gn:population":0,
    "gn:timezone":"Asia/Karachi",
    "iso:country":"PK",
    "wof:name":"Simbl",
    "wof:placetype":"locality"
},
  "geometry": {"coordinates":[75.11689,32.42326],"type":"Point"}
}