{
  "type": "Feature",
  "properties": {
    "gn:admin1_code":"4",
    "gn:asciiname":"Basti Munir Baluch",
    "gn:country_code":"PK",
    "gn:dem":104,
    "gn:feature_class":"P",
    "gn:feature_code":"PPL",
    "gn:name":"Basti Munir Baluch",
    "gn:population":0,
    "gn:timezone":"Asia/Karachi",
    "iso:country":"PK",
    "name:und_x_variant":[
        "M\u0101mu Baluch",
        "Mammun Baloch",
        "Basti Munir Baluch"
    ],
    "wof:name":"Basti Munir Baluch",
    "wof:placetype":"locality"
},
  "geometry": {"coordinates":[71.09688,29.30316],"type":"Point"}
}