{
  "type": "Feature",
  "properties": {
    "gn:admin1_code":"04",
    "gn:asciiname":"Kudhar",
    "gn:country_code":"PK",
    "gn:dem":824,
    "gn:feature_class":"P",
    "gn:feature_code":"PPL",
    "gn:name":"Kudhar",
    "gn:population":0,
    "gn:timezone":"Asia/Karachi",
    "iso:country":"PK",
    "name:und_x_variant":[
        "Kadhar",
        "Kudhar"
    ],
    "wof:name":"Kudhar",
    "wof:placetype":"locality"
},
  "geometry": {"coordinates":[72.47463,32.65593],"type":"Point"}
}