{
  "type": "Feature",
  "properties": {
    "gn:admin1_code":"2.0",
    "gn:asciiname":"Kaleri",
    "gn:country_code":"PK",
    "gn:dem":918,
    "gn:feature_class":"P",
    "gn:feature_code":"PPL",
    "gn:name":"Kaleri",
    "gn:population":0,
    "gn:timezone":"Asia/Karachi",
    "iso:country":"PK",
    "wof:name":"Kaleri",
    "wof:placetype":"locality"
},
  "geometry": {"coordinates":[63.19976,26.65439000000001],"type":"Point"}
}