{
  "type": "Feature",
  "properties": {
    "gn:admin1_code":"2.0",
    "gn:asciiname":"Malak",
    "gn:country_code":"PK",
    "gn:dem":2002,
    "gn:feature_class":"P",
    "gn:feature_code":"PPL",
    "gn:name":"Malak",
    "gn:population":0,
    "gn:timezone":"Asia/Karachi",
    "iso:country":"PK",
    "name:eng_x_preferred":[
        "Malak"
    ],
    "name:ita_x_preferred":[
        "Malak"
    ],
    "name:msa_x_preferred":[
        "Malak"
    ],
    "name:nor_x_preferred":[
        "Malak"
    ],
    "name:swe_x_preferred":[
        "Malak"
    ],
    "wof:name":"Malak",
    "wof:placetype":"locality"
},
  "geometry": {"coordinates":[67.33548,30.7622],"type":"Point"}
}