{
  "type": "Feature",
  "properties": {
    "gn:admin1_code":"1.0",
    "gn:asciiname":"Mamarey",
    "gn:country_code":"PK",
    "gn:dem":694,
    "gn:feature_class":"P",
    "gn:feature_code":"PPL",
    "gn:name":"Mamarey",
    "gn:population":0,
    "gn:timezone":"Asia/Karachi",
    "iso:country":"PK",
    "wof:name":"Mamarey",
    "wof:placetype":"locality"
},
  "geometry": {"coordinates":[71.30816,33.83578],"type":"Point"}
}