{
  "type": "Feature",
  "properties": {
    "gn:admin1_code":"4.0",
    "gn:asciiname":"DaRakh Branchar Baba Shah",
    "gn:country_code":"PK",
    "gn:dem":172,
    "gn:feature_class":"P",
    "gn:feature_code":"PPL",
    "gn:name":"DaRakh Branchar Baba Shah",
    "gn:population":0,
    "gn:timezone":"Asia/Karachi",
    "iso:country":"PK",
    "wof:name":"DaRakh Branchar Baba Shah",
    "wof:placetype":"locality"
},
  "geometry": {"coordinates":[72.86787,31.03129],"type":"Point"}
}