{
  "type": "Feature",
  "properties": {
    "gn:admin1_code":"3",
    "gn:asciiname":"Kutli",
    "gn:country_code":"PK",
    "gn:dem":579,
    "gn:feature_class":"P",
    "gn:feature_code":"PPL",
    "gn:name":"Kutli",
    "gn:population":0,
    "gn:timezone":"Asia/Karachi",
    "iso:country":"PK",
    "wof:name":"Kutli",
    "wof:placetype":"locality"
},
  "geometry": {"coordinates":[72.99145,34.12409],"type":"Point"}
}