{
  "type": "Feature",
  "properties": {
    "gn:admin1_code":"2.0",
    "gn:asciiname":"Salachian",
    "gn:country_code":"PK",
    "gn:dem":931,
    "gn:feature_class":"P",
    "gn:feature_code":"PPL",
    "gn:name":"Salachian",
    "gn:population":0,
    "gn:timezone":"Asia/Karachi",
    "iso:country":"PK",
    "wof:name":"Salachian",
    "wof:placetype":"locality"
},
  "geometry": {"coordinates":[68.48508000000001,30.00691],"type":"Point"}
}