{
  "type": "Feature",
  "properties": {
    "gn:admin1_code":"3",
    "gn:asciiname":"Sher Khanwala",
    "gn:country_code":"PK",
    "gn:dem":178,
    "gn:feature_class":"P",
    "gn:feature_code":"PPL",
    "gn:name":"Sher Khanwala",
    "gn:population":0,
    "gn:timezone":"Asia/Karachi",
    "iso:country":"PK",
    "name:und_x_variant":[
        "Sher Kh\u0101nw\u0101la",
        "Serh\u0101nw\u0101la",
        "Sher Khanwala"
    ],
    "wof:name":"Sher Khanwala",
    "wof:placetype":"locality"
},
  "geometry": {"coordinates":[71.01725,32.06303],"type":"Point"}
}