{
  "type": "Feature",
  "properties": {
    "gn:admin1_code":"6",
    "gn:asciiname":"Sarut",
    "gn:country_code":"PK",
    "gn:dem":815,
    "gn:feature_class":"P",
    "gn:feature_code":"PPL",
    "gn:name":"Sarut",
    "gn:population":0,
    "gn:timezone":"Asia/Karachi",
    "iso:country":"PK",
    "name:fas_x_preferred":[
        "\u0633\u0631\u0648\u062a"
    ],
    "name:und_x_variant":[
        "Sar\u0101t"
    ],
    "wof:name":"Sarut",
    "wof:placetype":"locality"
},
  "geometry": {"coordinates":[74.12466999999999,33.03400999999999],"type":"Point"}
}