{
  "type": "Feature",
  "properties": {
    "gn:admin1_code":"4.0",
    "gn:asciiname":"Chak Eighty-eight - Five Right",
    "gn:country_code":"PK",
    "gn:dem":159,
    "gn:feature_class":"P",
    "gn:feature_code":"PPL",
    "gn:name":"Chak Eighty-eight - Five Right",
    "gn:population":0,
    "gn:timezone":"Asia/Karachi",
    "iso:country":"PK",
    "wof:name":"Chak Eighty-eight - Five Right",
    "wof:placetype":"locality"
},
  "geometry": {"coordinates":[73.16389000000002,29.54932],"type":"Point"}
}