{
  "type": "Feature",
  "properties": {
    "gn:admin1_code":"04",
    "gn:asciiname":"Pipli Saiyidan",
    "gn:country_code":"PK",
    "gn:dem":182,
    "gn:feature_class":"P",
    "gn:feature_code":"PPL",
    "gn:name":"Pipli Saiyidan",
    "gn:population":0,
    "gn:timezone":"Asia/Karachi",
    "iso:country":"PK",
    "name:und_x_variant":[
        "Pipli Sayyadan",
        "Pipli Said\u0101n",
        "Pipli Saiyidan"
    ],
    "wof:name":"Pipli Saiyidan",
    "wof:placetype":"locality"
},
  "geometry": {"coordinates":[72.22742,31.9891],"type":"Point"}
}