{
  "type": "Feature",
  "properties": {
    "gn:admin1_code":"2.0",
    "gn:asciiname":"Abdur Rehman",
    "gn:country_code":"PK",
    "gn:dem":2048,
    "gn:feature_class":"P",
    "gn:feature_code":"PPL",
    "gn:name":"Abdur Rehman",
    "gn:population":0,
    "gn:timezone":"Asia/Karachi",
    "iso:country":"PK",
    "wof:name":"Abdur Rehman",
    "wof:placetype":"locality"
},
  "geometry": {"coordinates":[66.5241,28.82303],"type":"Point"}
}