{
  "type": "Feature",
  "properties": {
    "gn:admin1_code":"4",
    "gn:asciiname":"Mithewala",
    "gn:country_code":"PK",
    "gn:dem":132,
    "gn:feature_class":"P",
    "gn:feature_code":"PPL",
    "gn:name":"Mithewala",
    "gn:population":0,
    "gn:timezone":"Asia/Karachi",
    "iso:country":"PK",
    "name:und_x_variant":[
        "Mitthew\u0101la"
    ],
    "wof:name":"Mithewala",
    "wof:placetype":"locality"
},
  "geometry": {"coordinates":[72.18874,29.8686],"type":"Point"}
}