{
  "type": "Feature",
  "properties": {
    "gn:admin1_code":"2.0",
    "gn:asciiname":"Kili Wal",
    "gn:country_code":"PK",
    "gn:dem":1641,
    "gn:feature_class":"P",
    "gn:feature_code":"PPL",
    "gn:name":"Kili Wal",
    "gn:population":0,
    "gn:timezone":"Asia/Karachi",
    "iso:country":"PK",
    "wof:name":"Kili Wal",
    "wof:placetype":"locality"
},
  "geometry": {"coordinates":[66.93186999999999,30.76958],"type":"Point"}
}