{
  "type": "Feature",
  "properties": {
    "gn:admin1_code":"4.0",
    "gn:asciiname":"Dera Nagan",
    "gn:country_code":"PK",
    "gn:dem":206,
    "gn:feature_class":"P",
    "gn:feature_code":"PPL",
    "gn:name":"Dera Nagan",
    "gn:population":0,
    "gn:timezone":"Asia/Karachi",
    "iso:country":"PK",
    "name:und_x_variant":[
        "Nag\u0101nw\u0101la"
    ],
    "wof:name":"Dera Nagan",
    "wof:placetype":"locality"
},
  "geometry": {"coordinates":[73.80877,31.72725],"type":"Point"}
}