{
  "type": "Feature",
  "properties": {
    "gn:admin1_code":"3.0",
    "gn:asciiname":"Lakkan Talao",
    "gn:country_code":"PK",
    "gn:dem":352,
    "gn:feature_class":"P",
    "gn:feature_code":"PPL",
    "gn:name":"Lakkan Talao",
    "gn:population":0,
    "gn:timezone":"Asia/Karachi",
    "iso:country":"PK",
    "wof:name":"Lakkan Talao",
    "wof:placetype":"locality"
},
  "geometry": {"coordinates":[71.93172,33.66982],"type":"Point"}
}