{
  "type": "Feature",
  "properties": {
    "gn:admin1_code":"4.0",
    "gn:asciiname":"Manjuali",
    "gn:country_code":"PK",
    "gn:dem":213,
    "gn:feature_class":"P",
    "gn:feature_code":"PPL",
    "gn:name":"Manjuali",
    "gn:population":0,
    "gn:timezone":"Asia/Karachi",
    "iso:country":"PK",
    "name:und_x_variant":[
        "Monihw\u0101li",
        "Manjhw\u0101li",
        "Manjuali"
    ],
    "wof:name":"Manjuali",
    "wof:placetype":"locality"
},
  "geometry": {"coordinates":[73.87485,31.9962],"type":"Point"}
}