{
  "type": "Feature",
  "properties": {
    "gn:admin1_code":"3.0",
    "gn:asciiname":"Kikot",
    "gn:country_code":"PK",
    "gn:dem":1017,
    "gn:feature_class":"P",
    "gn:feature_code":"PPL",
    "gn:name":"Kikot",
    "gn:population":0,
    "gn:timezone":"Asia/Karachi",
    "iso:country":"PK",
    "wof:name":"Kikot",
    "wof:placetype":"locality"
},
  "geometry": {"coordinates":[73.18979,33.8563],"type":"Point"}
}