{
  "type": "Feature",
  "properties": {
    "gn:admin1_code":"4.0",
    "gn:asciiname":"Haidarabad",
    "gn:country_code":"PK",
    "gn:dem":209,
    "gn:feature_class":"P",
    "gn:feature_code":"PPL",
    "gn:name":"Haidarabad",
    "gn:population":0,
    "gn:timezone":"Asia/Karachi",
    "iso:country":"PK",
    "wof:name":"Haidarabad",
    "wof:placetype":"locality"
},
  "geometry": {"coordinates":[74.20699999999999,31.41737],"type":"Point"}
}