{
  "type": "Feature",
  "properties": {
    "gn:admin1_code":"3.0",
    "gn:asciiname":"Jabbi Haidar Shah",
    "gn:country_code":"PK",
    "gn:dem":1248,
    "gn:feature_class":"P",
    "gn:feature_code":"PPL",
    "gn:name":"Jabbi Haidar Shah",
    "gn:population":0,
    "gn:timezone":"Asia/Karachi",
    "iso:country":"PK",
    "name:und_x_variant":[
        "Jabbi"
    ],
    "wof:name":"Jabbi Haidar Shah",
    "wof:placetype":"locality"
},
  "geometry": {"coordinates":[73.41039000000001,34.41479],"type":"Point"}
}