{
  "type": "Feature",
  "properties": {
    "gn:admin1_code":"4.0",
    "gn:asciiname":"Jadiwala",
    "gn:country_code":"PK",
    "gn:dem":235,
    "gn:feature_class":"P",
    "gn:feature_code":"PPL",
    "gn:name":"Jadiwala",
    "gn:population":0,
    "gn:timezone":"Asia/Karachi",
    "iso:country":"PK",
    "name:und_x_variant":[
        "Nar\u0101nji"
    ],
    "wof:name":"Jadiwala",
    "wof:placetype":"locality"
},
  "geometry": {"coordinates":[70.42433,31.24791],"type":"Point"}
}