{
  "type": "Feature",
  "properties": {
    "gn:admin1_code":"2.0",
    "gn:asciiname":"Surdab",
    "gn:country_code":"PK",
    "gn:dem":1620,
    "gn:feature_class":"P",
    "gn:feature_code":"PPL",
    "gn:name":"Surdab",
    "gn:population":0,
    "gn:timezone":"Asia/Karachi",
    "iso:country":"PK",
    "name:und_x_variant":[
        "Sur Dab"
    ],
    "wof:name":"Surdab",
    "wof:placetype":"locality"
},
  "geometry": {"coordinates":[67.07046,30.48195],"type":"Point"}
}