{
  "type": "Feature",
  "properties": {
    "gn:admin1_code":"01",
    "gn:asciiname":"Ali Jan Kalle",
    "gn:country_code":"PK",
    "gn:dem":863,
    "gn:feature_class":"P",
    "gn:feature_code":"PPL",
    "gn:name":"Ali Jan Kalle",
    "gn:population":0,
    "gn:timezone":"Asia/Karachi",
    "iso:country":"PK",
    "name:eng_x_preferred":[
        "Al\u012bj\u0101n Kili"
    ],
    "name:und_x_variant":[
        "Ali Jan"
    ],
    "wof:name":"Ali Jan Kalle",
    "wof:placetype":"locality"
},
  "geometry": {"coordinates":[71.51300000000001,34.71579000000001],"type":"Point"}
}