{
  "type": "Feature",
  "properties": {
    "gn:admin1_code":"2.0",
    "gn:asciiname":"Sardar Yar Muhammad",
    "gn:country_code":"PK",
    "gn:dem":64,
    "gn:feature_class":"P",
    "gn:feature_code":"PPL",
    "gn:name":"Sardar Yar Muhammad",
    "gn:population":0,
    "gn:timezone":"Asia/Karachi",
    "iso:country":"PK",
    "wof:name":"Sardar Yar Muhammad",
    "wof:placetype":"locality"
},
  "geometry": {"coordinates":[68.2531,28.47464],"type":"Point"}
}