{
  "type": "Feature",
  "properties": {
    "gn:admin1_code":"4",
    "gn:asciiname":"Shaikhwala",
    "gn:country_code":"PK",
    "gn:dem":130,
    "gn:feature_class":"P",
    "gn:feature_code":"PPL",
    "gn:name":"Shaikhwala",
    "gn:population":0,
    "gn:timezone":"Asia/Karachi",
    "iso:country":"PK",
    "name:und_x_variant":[
        "Shaikw\u0101la"
    ],
    "wof:name":"Shaikhwala",
    "wof:placetype":"locality"
},
  "geometry": {"coordinates":[71.2296,30.39025],"type":"Point"}
}