{
  "type": "Feature",
  "properties": {
    "gn:admin1_code":"05",
    "gn:asciiname":"Wandki Wassi",
    "gn:country_code":"PK",
    "gn:dem":25,
    "gn:feature_class":"P",
    "gn:feature_code":"PPL",
    "gn:name":"Wandki Wassi",
    "gn:population":0,
    "gn:timezone":"Asia/Karachi",
    "iso:country":"PK",
    "name:eng_x_preferred":[
        "W\u0101nki Wassi"
    ],
    "name:und_x_variant":[
        "Vanki Vassi",
        "W\u0101nki Wasi",
        "Wandki Wassi"
    ],
    "wof:name":"Wandki Wassi",
    "wof:placetype":"locality"
},
  "geometry": {"coordinates":[68.44649,25.46248],"type":"Point"}
}