{
  "type": "Feature",
  "properties": {
    "gn:admin1_code":"4",
    "gn:asciiname":"Chak Eight A Bahawal Canal",
    "gn:country_code":"PK",
    "gn:dem":121,
    "gn:feature_class":"P",
    "gn:feature_code":"PPL",
    "gn:name":"Chak Eight A Bahawal Canal",
    "gn:population":0,
    "gn:timezone":"Asia/Karachi",
    "iso:country":"PK",
    "name:eng_x_preferred":[
        "Chak Eight A"
    ],
    "name:und_x_variant":[
        "Patd\u0101nwala"
    ],
    "wof:name":"Chak Eight A Bahawal Canal",
    "wof:placetype":"locality"
},
  "geometry": {"coordinates":[71.77561999999998,29.36643],"type":"Point"}
}