{
  "type": "Feature",
  "properties": {
    "gn:admin1_code":"3.0",
    "gn:asciiname":"Shamat Khel",
    "gn:country_code":"PK",
    "gn:dem":364,
    "gn:feature_class":"P",
    "gn:feature_code":"PPL",
    "gn:name":"Shamat Khel",
    "gn:population":0,
    "gn:timezone":"Asia/Karachi",
    "iso:country":"PK",
    "name:eng_x_preferred":[
        "Khwar Kalle"
    ],
    "name:und_x_variant":[
        "Ab\u0101zai Fort",
        "Shamat Khel"
    ],
    "wof:name":"Shamat Khel",
    "wof:placetype":"locality"
},
  "geometry": {"coordinates":[71.57793000000002,34.29802],"type":"Point"}
}