{
  "type": "Feature",
  "properties": {
    "gn:admin1_code":"03",
    "gn:asciiname":"Sher Kili",
    "gn:country_code":"PK",
    "gn:dem":336,
    "gn:feature_class":"P",
    "gn:feature_code":"PPL",
    "gn:name":"Sher Kili",
    "gn:population":0,
    "gn:timezone":"Asia/Karachi",
    "iso:country":"PK",
    "name:und_x_variant":[
        "Sher Kalli",
        "Sher Kili"
    ],
    "wof:name":"Sher Kili",
    "wof:placetype":"locality"
},
  "geometry": {"coordinates":[71.47126,34.14927],"type":"Point"}
}