{
  "type": "Feature",
  "properties": {
    "gn:admin1_code":"4.0",
    "gn:asciiname":"Basti Islamwala",
    "gn:country_code":"PK",
    "gn:dem":145,
    "gn:feature_class":"P",
    "gn:feature_code":"PPL",
    "gn:name":"Basti Islamwala",
    "gn:population":0,
    "gn:timezone":"Asia/Karachi",
    "iso:country":"PK",
    "name:und_x_variant":[
        "Isl\u0101mw\u0101la"
    ],
    "wof:name":"Basti Islamwala",
    "wof:placetype":"locality"
},
  "geometry": {"coordinates":[72.02148000000003,30.98336],"type":"Point"}
}