{
  "type": "Feature",
  "properties": {
    "gn:admin1_code":"3",
    "gn:asciiname":"Kanra China",
    "gn:country_code":"PK",
    "gn:dem":908,
    "gn:feature_class":"P",
    "gn:feature_code":"PPL",
    "gn:name":"Kanra China",
    "gn:population":0,
    "gn:timezone":"Asia/Karachi",
    "iso:country":"PK",
    "wof:name":"Kanra China",
    "wof:placetype":"locality"
},
  "geometry": {"coordinates":[70.70409000000002,33.40085],"type":"Point"}
}