{
  "type": "Feature",
  "properties": {
    "gn:admin1_code":"1.0",
    "gn:asciiname":"Tara Kili",
    "gn:country_code":"PK",
    "gn:dem":1477,
    "gn:feature_class":"P",
    "gn:feature_code":"PPL",
    "gn:name":"Tara Kili",
    "gn:population":0,
    "gn:timezone":"Asia/Karachi",
    "iso:country":"PK",
    "wof:name":"Tara Kili",
    "wof:placetype":"locality"
},
  "geometry": {"coordinates":[70.84619000000001,33.91591],"type":"Point"}
}