{
  "type": "Feature",
  "properties": {
    "gn:admin1_code":"5",
    "gn:asciiname":"Goth Ismail Sumro",
    "gn:country_code":"PK",
    "gn:dem":17,
    "gn:feature_class":"P",
    "gn:feature_code":"PPL",
    "gn:name":"Goth Ismail Sumro",
    "gn:population":0,
    "gn:timezone":"Asia/Karachi",
    "iso:country":"PK",
    "name:eng_x_preferred":[
        "Goth Ism\u0101\u012bl S\u016bmro"
    ],
    "wof:name":"Goth Ismail Sumro",
    "wof:placetype":"locality"
},
  "geometry": {"coordinates":[68.34748,25.07777],"type":"Point"}
}