{
  "type": "Feature",
  "properties": {
    "gn:admin1_code":"4.0",
    "gn:asciiname":"Nustar",
    "gn:country_code":"PK",
    "gn:dem":209,
    "gn:feature_class":"P",
    "gn:feature_code":"PPL",
    "gn:name":"Nustar",
    "gn:population":0,
    "gn:timezone":"Asia/Karachi",
    "iso:country":"PK",
    "name:und_x_variant":[
        "Thatta Ali"
    ],
    "wof:name":"Nustar",
    "wof:placetype":"locality"
},
  "geometry": {"coordinates":[73.75368,31.82523],"type":"Point"}
}