{
  "type": "Feature",
  "properties": {
    "gn:admin1_code":"04",
    "gn:asciiname":"Chak Twenty-four Jhang Branch",
    "gn:country_code":"PK",
    "gn:dem":191,
    "gn:feature_class":"P",
    "gn:feature_code":"PPL",
    "gn:name":"Chak Twenty-four Jhang Branch",
    "gn:population":0,
    "gn:timezone":"Asia/Karachi",
    "iso:country":"PK",
    "name:und_x_variant":[
        "Koru T\u0101na",
        "Chak Twenty-Four",
        "L\u0101hori\u0101nw\u0101la",
        "Chak Twenty-four Jhang Branch"
    ],
    "wof:name":"Chak Twenty-four Jhang Branch",
    "wof:placetype":"locality"
},
  "geometry": {"coordinates":[73.14731,31.64596],"type":"Point"}
}