{
  "type": "Feature",
  "properties": {
    "gn:admin1_code":"4.0",
    "gn:asciiname":"Khajror Khas",
    "gn:country_code":"PK",
    "gn:dem":243,
    "gn:feature_class":"P",
    "gn:feature_code":"PPL",
    "gn:name":"Khajror Khas",
    "gn:population":0,
    "gn:timezone":"Asia/Karachi",
    "iso:country":"PK",
    "wof:name":"Khajror Khas",
    "wof:placetype":"locality"
},
  "geometry": {"coordinates":[74.99714,32.14704],"type":"Point"}
}