{
  "type": "Feature",
  "properties": {
    "gn:admin1_code":"04",
    "gn:asciiname":"Marh Rashid",
    "gn:country_code":"PK",
    "gn:dem":103,
    "gn:feature_class":"P",
    "gn:feature_code":"PPL",
    "gn:name":"Marh Rashid",
    "gn:population":0,
    "gn:timezone":"Asia/Karachi",
    "iso:country":"PK",
    "name:und_x_variant":[
        "Mad Rash\u012bd"
    ],
    "wof:name":"Marh Rashid",
    "wof:placetype":"locality"
},
  "geometry": {"coordinates":[71.1996,29.17837],"type":"Point"}
}