{
  "type": "Feature",
  "properties": {
    "gn:admin1_code":"4.0",
    "gn:asciiname":"Chak One Hundred Thirty-Five NB",
    "gn:country_code":"PK",
    "gn:dem":176,
    "gn:feature_class":"P",
    "gn:feature_code":"PPL",
    "gn:name":"Chak One Hundred Thirty-Five NB",
    "gn:population":0,
    "gn:timezone":"Asia/Karachi",
    "iso:country":"PK",
    "name:und_x_variant":[
        "Chak One Hundred Thirty-Five",
        "Chak 135 NB"
    ],
    "wof:name":"Chak One Hundred Thirty-Five NB",
    "wof:placetype":"locality"
},
  "geometry": {"coordinates":[72.46391,31.74493],"type":"Point"}
}