{
  "type": "Feature",
  "properties": {
    "gn:admin1_code":"04",
    "gn:asciiname":"Punwal",
    "gn:country_code":"PK",
    "gn:dem":246,
    "gn:feature_class":"P",
    "gn:feature_code":"PPL",
    "gn:name":"Punwal",
    "gn:population":0,
    "gn:timezone":"Asia/Karachi",
    "iso:country":"PK",
    "name:und_x_variant":[
        "Panwal",
        "Punw\u0101l",
        "Pannuwal"
    ],
    "wof:name":"Punwal",
    "wof:placetype":"locality"
},
  "geometry": {"coordinates":[74.53830000000001,32.60006],"type":"Point"}
}