{
  "type": "Feature",
  "properties": {
    "gn:admin1_code":"2.0",
    "gn:asciiname":"Safar Khan Umrani",
    "gn:country_code":"PK",
    "gn:dem":57,
    "gn:feature_class":"P",
    "gn:feature_code":"PPL",
    "gn:name":"Safar Khan Umrani",
    "gn:population":0,
    "gn:timezone":"Asia/Karachi",
    "iso:country":"PK",
    "name:und_x_variant":[
        "Safar Kh\u0101n Anbr\u0101ni"
    ],
    "wof:name":"Safar Khan Umrani",
    "wof:placetype":"locality"
},
  "geometry": {"coordinates":[68.14376999999999,28.31484],"type":"Point"}
}