{
  "type": "Feature",
  "properties": {
    "gn:admin1_code":"5",
    "gn:asciiname":"Goth Muqim Wasan Makrani",
    "gn:country_code":"PK",
    "gn:dem":25,
    "gn:feature_class":"P",
    "gn:feature_code":"PPL",
    "gn:name":"Goth Muqim Wasan Makrani",
    "gn:population":0,
    "gn:timezone":"Asia/Karachi",
    "iso:country":"PK",
    "name:und_x_variant":[
        "Goth Muq\u012bm Was\u0101n"
    ],
    "wof:name":"Goth Muqim Wasan Makrani",
    "wof:placetype":"locality"
},
  "geometry": {"coordinates":[68.71128,25.76858],"type":"Point"}
}