{
  "type": "Feature",
  "properties": {
    "gn:admin1_code":"4",
    "gn:asciiname":"Bhabrianwala",
    "gn:country_code":"PK",
    "gn:dem":245,
    "gn:feature_class":"P",
    "gn:feature_code":"PPL",
    "gn:name":"Bhabrianwala",
    "gn:population":0,
    "gn:timezone":"Asia/Karachi",
    "iso:country":"PK",
    "wof:name":"Bhabrianwala",
    "wof:placetype":"locality"
},
  "geometry": {"coordinates":[74.48045999999999,32.48158],"type":"Point"}
}