{
  "type": "Feature",
  "properties": {
    "gn:admin1_code":"6.0",
    "gn:asciiname":"Hilian",
    "gn:country_code":"PK",
    "gn:dem":1193,
    "gn:feature_class":"P",
    "gn:feature_code":"PPL",
    "gn:name":"Hilian",
    "gn:population":0,
    "gn:timezone":"Asia/Karachi",
    "iso:country":"PK",
    "wof:name":"Hilian",
    "wof:placetype":"locality"
},
  "geometry": {"coordinates":[73.72089,33.80393],"type":"Point"}
}