{
  "type": "Feature",
  "properties": {
    "gn:admin1_code":"7.0",
    "gn:asciiname":"Shuta",
    "gn:country_code":"PK",
    "gn:dem":1924,
    "gn:feature_class":"P",
    "gn:feature_code":"PPL",
    "gn:name":"Shuta",
    "gn:population":0,
    "gn:timezone":"Asia/Karachi",
    "iso:country":"PK",
    "wof:name":"Shuta",
    "wof:placetype":"locality"
},
  "geometry": {"coordinates":[74.64201,35.83235999999999],"type":"Point"}
}