{
  "type": "Feature",
  "properties": {
    "gn:admin1_code":"4",
    "gn:asciiname":"Shah Balgwala",
    "gn:country_code":"PK",
    "gn:dem":183,
    "gn:feature_class":"P",
    "gn:feature_code":"PPL",
    "gn:name":"Shah Balgwala",
    "gn:population":0,
    "gn:timezone":"Asia/Karachi",
    "iso:country":"PK",
    "name:und_x_variant":[
        "Sh\u0101h Beg\u0101w\u0101la"
    ],
    "wof:name":"Shah Balgwala",
    "wof:placetype":"locality"
},
  "geometry": {"coordinates":[72.18655,31.92135],"type":"Point"}
}