{
  "type": "Feature",
  "properties": {
    "gn:admin1_code":"3",
    "gn:asciiname":"Parabek",
    "gn:country_code":"PK",
    "gn:dem":2445,
    "gn:feature_class":"P",
    "gn:feature_code":"PPL",
    "gn:name":"Parabek",
    "gn:population":0,
    "gn:timezone":"Asia/Karachi",
    "iso:country":"PK",
    "name:urd_x_preferred":[
        "P\u0101r\u0101bek"
    ],
    "name:urd_x_variant":[
        "\u067e\u064e\u0627\u0631\u064e\u0627\u0628\u06cc\u06a9"
    ],
    "wof:name":"Parabek",
    "wof:placetype":"locality"
},
  "geometry": {"coordinates":[71.48921,35.99162000000001],"type":"Point"}
}