{
  "type": "Feature",
  "properties": {
    "gn:admin1_code":"2.0",
    "gn:asciiname":"Shalu",
    "gn:country_code":"PK",
    "gn:dem":1028,
    "gn:feature_class":"P",
    "gn:feature_code":"PPL",
    "gn:name":"Shalu",
    "gn:population":0,
    "gn:timezone":"Asia/Karachi",
    "iso:country":"PK",
    "name:deu_x_preferred":[
        "Shalu"
    ],
    "name:nld_x_preferred":[
        "Shalu"
    ],
    "wof:name":"Shalu",
    "wof:placetype":"locality"
},
  "geometry": {"coordinates":[69.40316999999999,29.79986],"type":"Point"}
}