{
  "type": "Feature",
  "properties": {
    "gn:admin1_code":"5.0",
    "gn:asciiname":"Goth Arain",
    "gn:country_code":"PK",
    "gn:dem":37,
    "gn:feature_class":"P",
    "gn:feature_code":"PPL",
    "gn:name":"Goth Arain",
    "gn:population":0,
    "gn:timezone":"Asia/Karachi",
    "iso:country":"PK",
    "wof:name":"Goth Arain",
    "wof:placetype":"locality"
},
  "geometry": {"coordinates":[68.01342,26.55699000000001],"type":"Point"}
}