{
  "type": "Feature",
  "properties": {
    "gn:admin1_code":"7.0",
    "gn:asciiname":"Shaindar",
    "gn:country_code":"PK",
    "gn:dem":3849,
    "gn:feature_class":"P",
    "gn:feature_code":"PPL",
    "gn:name":"Shaindar",
    "gn:population":0,
    "gn:timezone":"Asia/Karachi",
    "iso:country":"PK",
    "wof:name":"Shaindar",
    "wof:placetype":"locality"
},
  "geometry": {"coordinates":[73.91134,35.2373],"type":"Point"}
}