{
  "type": "Feature",
  "properties": {
    "gn:admin1_code":"4.0",
    "gn:asciiname":"Bastiwala",
    "gn:country_code":"PK",
    "gn:dem":144,
    "gn:feature_class":"P",
    "gn:feature_code":"PPL",
    "gn:name":"Bastiwala",
    "gn:population":0,
    "gn:timezone":"Asia/Karachi",
    "iso:country":"PK",
    "name:eng_x_preferred":[
        "Khu Bastiw\u0101la"
    ],
    "wof:name":"Bastiwala",
    "wof:placetype":"locality"
},
  "geometry": {"coordinates":[71.99208,31.05561],"type":"Point"}
}