{
  "type": "Feature",
  "properties": {
    "gn:admin1_code":"2.0",
    "gn:asciiname":"Kulachi",
    "gn:country_code":"PK",
    "gn:dem":87,
    "gn:feature_class":"P",
    "gn:feature_code":"PPL",
    "gn:name":"Kulachi",
    "gn:population":0,
    "gn:timezone":"Asia/Karachi",
    "iso:country":"PK",
    "wof:name":"Kulachi",
    "wof:placetype":"locality"
},
  "geometry": {"coordinates":[67.67259,28.88792],"type":"Point"}
}