{
  "type": "Feature",
  "properties": {
    "gn:admin1_code":"5.0",
    "gn:asciiname":"Goth Amin Muhammad Rajar",
    "gn:country_code":"PK",
    "gn:dem":11,
    "gn:feature_class":"P",
    "gn:feature_code":"PPL",
    "gn:name":"Goth Amin Muhammad Rajar",
    "gn:population":0,
    "gn:timezone":"Asia/Karachi",
    "iso:country":"PK",
    "wof:name":"Goth Amin Muhammad Rajar",
    "wof:placetype":"locality"
},
  "geometry": {"coordinates":[69.43493000000001,25.49179],"type":"Point"}
}