{
  "type": "Feature",
  "properties": {
    "gn:admin1_code":"4",
    "gn:asciiname":"Chak Thirteen Dullewala Branch",
    "gn:country_code":"PK",
    "gn:dem":195,
    "gn:feature_class":"P",
    "gn:feature_code":"PPL",
    "gn:name":"Chak Thirteen Dullewala Branch",
    "gn:population":0,
    "gn:timezone":"Asia/Karachi",
    "iso:country":"PK",
    "name:und_x_variant":[
        "Chak Thirteen DB"
    ],
    "wof:name":"Chak Thirteen Dullewala Branch",
    "wof:placetype":"locality"
},
  "geometry": {"coordinates":[71.62218,32.2546],"type":"Point"}
}