{
  "type": "Feature",
  "properties": {
    "gn:admin1_code":"4.0",
    "gn:asciiname":"Hardaspur",
    "gn:country_code":"PK",
    "gn:dem":246,
    "gn:feature_class":"P",
    "gn:feature_code":"PPL",
    "gn:name":"Hardaspur",
    "gn:population":0,
    "gn:timezone":"Asia/Karachi",
    "iso:country":"PK",
    "name:und_x_variant":[
        "Harbaspur",
        "Hardaspur"
    ],
    "wof:name":"Hardaspur",
    "wof:placetype":"locality"
},
  "geometry": {"coordinates":[74.15272,32.64219],"type":"Point"}
}