{
  "type": "Feature",
  "properties": {
    "gn:admin1_code":"7.0",
    "gn:asciiname":"Nurbat",
    "gn:country_code":"PK",
    "gn:dem":2630,
    "gn:feature_class":"P",
    "gn:feature_code":"PPL",
    "gn:name":"Nurbat",
    "gn:population":0,
    "gn:timezone":"Asia/Karachi",
    "iso:country":"PK",
    "wof:name":"Nurbat",
    "wof:placetype":"locality"
},
  "geometry": {"coordinates":[74.09481,35.23578],"type":"Point"}
}