{
  "type": "Feature",
  "properties": {
    "gn:admin1_code":"2.0",
    "gn:asciiname":"Rangun Karuna",
    "gn:country_code":"PK",
    "gn:dem":2397,
    "gn:feature_class":"P",
    "gn:feature_code":"PPL",
    "gn:name":"Rangun Karuna",
    "gn:population":0,
    "gn:timezone":"Asia/Karachi",
    "iso:country":"PK",
    "wof:name":"Rangun Karuna",
    "wof:placetype":"locality"
},
  "geometry": {"coordinates":[67.9477,30.63828],"type":"Point"}
}