{
  "type": "Feature",
  "properties": {
    "gn:admin1_code":"4",
    "gn:asciiname":"Jhandirwah",
    "gn:country_code":"PK",
    "gn:dem":126,
    "gn:feature_class":"P",
    "gn:feature_code":"PPL",
    "gn:name":"Jhandirwah",
    "gn:population":0,
    "gn:timezone":"Asia/Karachi",
    "iso:country":"PK",
    "wof:name":"Jhandirwah",
    "wof:placetype":"locality"
},
  "geometry": {"coordinates":[71.89721999999998,29.87917],"type":"Point"}
}