{
  "type": "Feature",
  "properties": {
    "gn:admin1_code":"1.0",
    "gn:asciiname":"Aziz Khel",
    "gn:country_code":"PK",
    "gn:dem":754,
    "gn:feature_class":"P",
    "gn:feature_code":"PPL",
    "gn:name":"Aziz Khel",
    "gn:population":0,
    "gn:timezone":"Asia/Karachi",
    "iso:country":"PK",
    "name:und_x_variant":[
        "Ad\u012bn Sh\u0101h Kot",
        "Aziz Khel"
    ],
    "wof:name":"Aziz Khel",
    "wof:placetype":"locality"
},
  "geometry": {"coordinates":[70.18330999999999,32.98078],"type":"Point"}
}