{
  "type": "Feature",
  "properties": {
    "gn:admin1_code":"5.0",
    "gn:asciiname":"Goth Haji Usman",
    "gn:country_code":"PK",
    "gn:dem":15,
    "gn:feature_class":"P",
    "gn:feature_code":"PPL",
    "gn:name":"Goth H\u0101ji Usm\u0101n",
    "gn:population":0,
    "gn:timezone":"Asia/Karachi",
    "iso:country":"PK",
    "wof:name":"Goth Haji Usman",
    "wof:placetype":"locality"
},
  "geometry": {"coordinates":[68.94069,25.1026],"type":"Point"}
}