{
  "type": "Feature",
  "properties": {
    "gn:admin1_code":"4",
    "gn:asciiname":"Chak One Hundred Twenty-eight Southern Branch",
    "gn:country_code":"PK",
    "gn:dem":183,
    "gn:feature_class":"P",
    "gn:feature_code":"PPL",
    "gn:name":"Chak One Hundred Twenty-eight Southern Branch",
    "gn:population":0,
    "gn:timezone":"Asia/Karachi",
    "iso:country":"PK",
    "name:und_x_variant":[
        "Chak One Hundred Twenty-eight SB"
    ],
    "wof:name":"Chak One Hundred Twenty-eight Southern Branch",
    "wof:placetype":"locality"
},
  "geometry": {"coordinates":[72.64615000000001,31.86443],"type":"Point"}
}