{
  "type": "Feature",
  "properties": {
    "gn:admin1_code":"4",
    "gn:asciiname":"Mirza",
    "gn:country_code":"PK",
    "gn:dem":275,
    "gn:feature_class":"P",
    "gn:feature_code":"PPL",
    "gn:name":"Mirza",
    "gn:population":0,
    "gn:timezone":"Asia/Karachi",
    "iso:country":"PK",
    "wof:name":"Mirza",
    "wof:placetype":"locality"
},
  "geometry": {"coordinates":[74.18965,32.75029],"type":"Point"}
}