{
  "type": "Feature",
  "properties": {
    "gn:admin1_code":"4.0",
    "gn:asciiname":"Bhura Hayal",
    "gn:country_code":"PK",
    "gn:dem":664,
    "gn:feature_class":"P",
    "gn:feature_code":"PPL",
    "gn:name":"Bhura Hayal",
    "gn:population":0,
    "gn:timezone":"Asia/Karachi",
    "iso:country":"PK",
    "name:fas_x_preferred":[
        "\u0628\u0647\u0648\u0631\u0627 \u062d\u06cc\u0627\u0644"
    ],
    "name:und_x_variant":[
        "Bh\u016bra Hayat"
    ],
    "name:urd_x_preferred":[
        "\u0628\u06be\u0648\u0631\u0627 \u062d\u06cc\u0627\u0644"
    ],
    "wof:name":"Bhura Hayal",
    "wof:placetype":"locality"
},
  "geometry": {"coordinates":[73.39142,33.51425],"type":"Point"}
}