{
  "type": "Feature",
  "properties": {
    "gn:admin1_code":"1",
    "gn:asciiname":"Spin Kharai",
    "gn:country_code":"PK",
    "gn:dem":1702,
    "gn:feature_class":"P",
    "gn:feature_code":"PPL",
    "gn:name":"Spin Kharai",
    "gn:population":0,
    "gn:timezone":"Asia/Karachi",
    "iso:country":"PK",
    "wof:name":"Spin Kharai",
    "wof:placetype":"locality"
},
  "geometry": {"coordinates":[69.90595999999999,32.53548],"type":"Point"}
}