{
  "type": "Feature",
  "properties": {
    "gn:admin1_code":"2.0",
    "gn:asciiname":"Mangayzai",
    "gn:country_code":"PK",
    "gn:dem":1679,
    "gn:feature_class":"P",
    "gn:feature_code":"PPL",
    "gn:name":"Mangayzai",
    "gn:population":0,
    "gn:timezone":"Asia/Karachi",
    "iso:country":"PK",
    "wof:name":"Mangayzai",
    "wof:placetype":"locality"
},
  "geometry": {"coordinates":[66.17171,28.22368],"type":"Point"}
}