{
  "type": "Feature",
  "properties": {
    "gn:admin1_code":"4.0",
    "gn:asciiname":"Hitharwala",
    "gn:country_code":"PK",
    "gn:dem":119,
    "gn:feature_class":"P",
    "gn:feature_code":"PPL",
    "gn:name":"Hitharwala",
    "gn:population":0,
    "gn:timezone":"Asia/Karachi",
    "iso:country":"PK",
    "name:eng_x_preferred":[
        "Hitharwala"
    ],
    "name:eng_x_variant":[
        "Hitarwala"
    ],
    "wof:name":"Hitharwala",
    "wof:placetype":"locality"
},
  "geometry": {"coordinates":[70.97480999999998,30.01695],"type":"Point"}
}