{
  "type": "Feature",
  "properties": {
    "gn:admin1_code":"2.0",
    "gn:asciiname":"Hashim",
    "gn:country_code":"PK",
    "gn:dem":45,
    "gn:feature_class":"P",
    "gn:feature_code":"PPL",
    "gn:name":"Hashim",
    "gn:population":0,
    "gn:timezone":"Asia/Karachi",
    "iso:country":"PK",
    "name:ara_x_preferred":[
        "\u0647\u0627\u0634\u0645"
    ],
    "name:deu_x_preferred":[
        "Hashim"
    ],
    "name:jpn_x_preferred":[
        "\u30cf\u30fc\u30b7\u30e0"
    ],
    "name:rus_x_preferred":[
        "\u0425\u0430\u0448\u0438\u043c"
    ],
    "name:ukr_x_preferred":[
        "\u0425\u0430\u0448\u0438\u043c"
    ],
    "wof:name":"Hashim",
    "wof:placetype":"locality"
},
  "geometry": {"coordinates":[67.73139,28.33608],"type":"Point"}
}