{
  "type": "Feature",
  "properties": {
    "gn:admin1_code":"3.0",
    "gn:asciiname":"Batial",
    "gn:country_code":"PK",
    "gn:dem":1055,
    "gn:feature_class":"P",
    "gn:feature_code":"PPL",
    "gn:name":"Batial",
    "gn:population":0,
    "gn:timezone":"Asia/Karachi",
    "iso:country":"PK",
    "name:und_x_variant":[
        "Buti\u0101la"
    ],
    "wof:name":"Batial",
    "wof:placetype":"locality"
},
  "geometry": {"coordinates":[73.13011999999998,34.14271],"type":"Point"}
}