{
  "type": "Feature",
  "properties": {
    "gn:admin1_code":"4.0",
    "gn:asciiname":"Ser",
    "gn:country_code":"PK",
    "gn:dem":1284,
    "gn:feature_class":"P",
    "gn:feature_code":"PPL",
    "gn:name":"Ser",
    "gn:population":0,
    "gn:timezone":"Asia/Karachi",
    "iso:country":"PK",
    "wof:name":"Ser",
    "wof:placetype":"locality"
},
  "geometry": {"coordinates":[73.52614,33.84601],"type":"Point"}
}