{
  "type": "Feature",
  "properties": {
    "gn:admin1_code":"2",
    "gn:asciiname":"Sarah Bidrang",
    "gn:country_code":"PK",
    "gn:dem":1237,
    "gn:feature_class":"P",
    "gn:feature_code":"PPL",
    "gn:name":"Sarah Bidrang",
    "gn:population":0,
    "gn:timezone":"Asia/Karachi",
    "iso:country":"PK",
    "name:und_x_variant":[
        "S\u0101hra Bidrang"
    ],
    "wof:name":"Sarah Bidrang",
    "wof:placetype":"locality"
},
  "geometry": {"coordinates":[66.30785,27.29276],"type":"Point"}
}