{
  "type": "Feature",
  "properties": {
    "gn:admin1_code":"3",
    "gn:asciiname":"Darwaza",
    "gn:country_code":"PK",
    "gn:dem":1589,
    "gn:feature_class":"P",
    "gn:feature_code":"PPL",
    "gn:name":"Darwaza",
    "gn:population":0,
    "gn:timezone":"Asia/Karachi",
    "iso:country":"PK",
    "wof:name":"Darwaza",
    "wof:placetype":"locality"
},
  "geometry": {"coordinates":[73.42503000000001,34.01073],"type":"Point"}
}