{
  "type": "Feature",
  "properties": {
    "gn:admin1_code":"2.0",
    "gn:asciiname":"Kerki Dhal",
    "gn:country_code":"PK",
    "gn:dem":1118,
    "gn:feature_class":"P",
    "gn:feature_code":"PPL",
    "gn:name":"Kerki Dhal",
    "gn:population":0,
    "gn:timezone":"Asia/Karachi",
    "iso:country":"PK",
    "wof:name":"Kerki Dhal",
    "wof:placetype":"locality"
},
  "geometry": {"coordinates":[64.92229,27.00261],"type":"Point"}
}