{
  "type": "Feature",
  "properties": {
    "gn:admin1_code":"3.0",
    "gn:asciiname":"Sifat Banda",
    "gn:country_code":"PK",
    "gn:dem":794,
    "gn:feature_class":"P",
    "gn:feature_code":"PPL",
    "gn:name":"Sifat Banda",
    "gn:population":0,
    "gn:timezone":"Asia/Karachi",
    "iso:country":"PK",
    "wof:name":"Sifat Banda",
    "wof:placetype":"locality"
},
  "geometry": {"coordinates":[71.11190000000001,33.53193],"type":"Point"}
}