{
  "type": "Feature",
  "properties": {
    "gn:admin1_code":"3",
    "gn:asciiname":"Bandagai",
    "gn:country_code":"PK",
    "gn:dem":1259,
    "gn:feature_class":"P",
    "gn:feature_code":"PPL",
    "gn:name":"Bandagai",
    "gn:population":0,
    "gn:timezone":"Asia/Karachi",
    "iso:country":"PK",
    "name:und_x_variant":[
        "B\u0101ndigai"
    ],
    "wof:name":"Bandagai",
    "wof:placetype":"locality"
},
  "geometry": {"coordinates":[73.05495000000001,34.59304],"type":"Point"}
}