{
  "type": "Feature",
  "properties": {
    "gn:admin1_code":"3.0",
    "gn:asciiname":"Karbogha",
    "gn:country_code":"PK",
    "gn:dem":970,
    "gn:feature_class":"P",
    "gn:feature_code":"PPL",
    "gn:name":"Karbogha",
    "gn:population":0,
    "gn:timezone":"Asia/Karachi",
    "iso:country":"PK",
    "wof:name":"Karbogha",
    "wof:placetype":"locality"
},
  "geometry": {"coordinates":[70.77225,33.35091],"type":"Point"}
}