{
  "type": "Feature",
  "properties": {
    "gn:admin1_code":"6.0",
    "gn:asciiname":"Uich",
    "gn:country_code":"PK",
    "gn:dem":2213,
    "gn:feature_class":"P",
    "gn:feature_code":"PPL",
    "gn:name":"Uich",
    "gn:population":0,
    "gn:timezone":"Asia/Karachi",
    "iso:country":"PK",
    "wof:name":"Uich",
    "wof:placetype":"locality"
},
  "geometry": {"coordinates":[74.2176,33.94737],"type":"Point"}
}