{
  "type": "Feature",
  "properties": {
    "gn:admin1_code":"5.0",
    "gn:asciiname":"Goth Long Jat",
    "gn:country_code":"PK",
    "gn:dem":20,
    "gn:feature_class":"P",
    "gn:feature_code":"PPL",
    "gn:name":"Goth Long Jat",
    "gn:population":0,
    "gn:timezone":"Asia/Karachi",
    "iso:country":"PK",
    "name:und_x_variant":[
        "Goth Habshi Kolhi"
    ],
    "wof:name":"Goth Long Jat",
    "wof:placetype":"locality"
},
  "geometry": {"coordinates":[68.54774999999999,25.11173],"type":"Point"}
}