{
  "type": "Feature",
  "properties": {
    "gn:admin1_code":"4.0",
    "gn:asciiname":"Bahadar Baluch",
    "gn:country_code":"PK",
    "gn:dem":130,
    "gn:feature_class":"P",
    "gn:feature_code":"PPL",
    "gn:name":"Bahadar Baluch",
    "gn:population":0,
    "gn:timezone":"Asia/Karachi",
    "iso:country":"PK",
    "name:und_x_variant":[
        "Bahadur Baluch",
        "Bah\u0101dur Baloch",
        "Bahadar Baluch"
    ],
    "wof:name":"Bahadar Baluch",
    "wof:placetype":"locality"
},
  "geometry": {"coordinates":[72.16611,29.82482000000001],"type":"Point"}
}