{
  "type": "Feature",
  "properties": {
    "gn:admin1_code":"3",
    "gn:asciiname":"Shinteri",
    "gn:country_code":"PK",
    "gn:dem":1573,
    "gn:feature_class":"P",
    "gn:feature_code":"PPL",
    "gn:name":"Shinteri",
    "gn:population":0,
    "gn:timezone":"Asia/Karachi",
    "iso:country":"PK",
    "name:eng_x_preferred":[
        "Shinter Koro"
    ],
    "wof:name":"Shinteri",
    "wof:placetype":"locality"
},
  "geometry": {"coordinates":[71.70095000000001,35.38725],"type":"Point"}
}