{
  "type": "Feature",
  "properties": {
    "gn:admin1_code":"4.0",
    "gn:asciiname":"Gardai",
    "gn:country_code":"PK",
    "gn:dem":696,
    "gn:feature_class":"P",
    "gn:feature_code":"PPL",
    "gn:name":"Gardai",
    "gn:population":0,
    "gn:timezone":"Asia/Karachi",
    "iso:country":"PK",
    "wof:name":"Gardai",
    "wof:placetype":"locality"
},
  "geometry": {"coordinates":[71.49093000000001,33.09808],"type":"Point"}
}