{
  "type": "Feature",
  "properties": {
    "gn:admin1_code":"2.0",
    "gn:asciiname":"Abdul Malik",
    "gn:country_code":"PK",
    "gn:dem":1528,
    "gn:feature_class":"P",
    "gn:feature_code":"PPL",
    "gn:name":"Abdul Malik",
    "gn:population":0,
    "gn:timezone":"Asia/Karachi",
    "iso:country":"PK",
    "wof:name":"Abdul Malik",
    "wof:placetype":"locality"
},
  "geometry": {"coordinates":[68.58069999999999,30.82591],"type":"Point"}
}