{
  "type": "Feature",
  "properties": {
    "gn:admin1_code":"2.0",
    "gn:asciiname":"Abdul Malik",
    "gn:country_code":"PK",
    "gn:dem":1528,
    "gn:feature_class":"P",
    "gn:feature_code":"PPL",
    "gn:name":"Abdul Malik",
    "gn:population":0,
    "gn:timezone":"Asia/Karachi",
    "iso:country":"PK",
    "name:ara_x_preferred":[
        "\u0639\u0628\u062f \u0627\u0644\u0645\u0644\u0643"
    ],
    "name:ben_x_preferred":[
        "\u0986\u09ac\u09a6\u09c1\u09b2 \u09ae\u09be\u09b2\u09c7\u0995"
    ],
    "name:cat_x_preferred":[
        "Abd-al-M\u00e0lik"
    ],
    "name:deu_x_preferred":[
        "Abd al-Malik"
    ],
    "name:fra_x_preferred":[
        "Abd al-Malik"
    ],
    "name:ukr_x_preferred":[
        "\u0410\u0431\u0434 \u0430\u043b\u044c-\u041c\u0430\u043b\u0456\u043a"
    ],
    "wof:name":"Abdul Malik",
    "wof:placetype":"locality"
},
  "geometry": {"coordinates":[68.58069999999999,30.82591],"type":"Point"}
}