{
  "type": "Feature",
  "properties": {
    "gn:admin1_code":"6",
    "gn:asciiname":"Niya Daura",
    "gn:country_code":"PK",
    "gn:dem":379,
    "gn:feature_class":"P",
    "gn:feature_code":"PPL",
    "gn:name":"Niya Daura",
    "gn:population":0,
    "gn:timezone":"Asia/Karachi",
    "iso:country":"PK",
    "name:und_x_variant":[
        "Naya Daura",
        "Niya Daura"
    ],
    "wof:name":"Niya Daura",
    "wof:placetype":"locality"
},
  "geometry": {"coordinates":[73.99479000000002,33.00731],"type":"Point"}
}