{
  "type": "Feature",
  "properties": {
    "gn:admin1_code":"3.0",
    "gn:asciiname":"Ghari Khel",
    "gn:country_code":"PK",
    "gn:dem":790,
    "gn:feature_class":"P",
    "gn:feature_code":"PPL",
    "gn:name":"Ghari Khel",
    "gn:population":0,
    "gn:timezone":"Asia/Karachi",
    "iso:country":"PK",
    "name:und_x_variant":[
        "Garhi Khel"
    ],
    "wof:name":"Ghari Khel",
    "wof:placetype":"locality"
},
  "geometry": {"coordinates":[71.26841,33.17036],"type":"Point"}
}