{
  "type": "Feature",
  "properties": {
    "gn:admin1_code":"5",
    "gn:asciiname":"Goth Khamiso Mangrio",
    "gn:country_code":"PK",
    "gn:dem":47,
    "gn:feature_class":"P",
    "gn:feature_code":"PPL",
    "gn:name":"Goth Khamiso Mangrio",
    "gn:population":0,
    "gn:timezone":"Asia/Karachi",
    "iso:country":"PK",
    "name:und_x_variant":[
        "Goth Kham\u012bso M\u0101ngrio"
    ],
    "wof:name":"Goth Khamiso Mangrio",
    "wof:placetype":"locality"
},
  "geometry": {"coordinates":[68.22651,27.03971],"type":"Point"}
}