{
  "type": "Feature",
  "properties": {
    "gn:admin1_code":"04",
    "gn:asciiname":"Kuri Dulal",
    "gn:country_code":"PK",
    "gn:dem":504,
    "gn:feature_class":"P",
    "gn:feature_code":"PPL",
    "gn:name":"Kuri Dulal",
    "gn:population":0,
    "gn:timezone":"Asia/Karachi",
    "iso:country":"PK",
    "name:pnb_x_preferred":[
        "\u06a9\u0691\u06cc \u0688\u0644\u0627\u0644"
    ],
    "name:und_x_variant":[
        "Kuri Dolal",
        "Kuri Dulal"
    ],
    "name:urd_x_preferred":[
        "\u06a9\u0631\u06cc \u062f\u0648\u0644\u0627\u0644"
    ],
    "wof:name":"Kuri Dulal",
    "wof:placetype":"locality"
},
  "geometry": {"coordinates":[73.26366999999998,33.38437],"type":"Point"}
}