{
  "type": "Feature",
  "properties": {
    "gn:admin1_code":"3.0",
    "gn:asciiname":"Lali Banda",
    "gn:country_code":"PK",
    "gn:dem":481,
    "gn:feature_class":"P",
    "gn:feature_code":"PPL",
    "gn:name":"Lali Banda",
    "gn:population":0,
    "gn:timezone":"Asia/Karachi",
    "iso:country":"PK",
    "wof:name":"Lali Banda",
    "wof:placetype":"locality"
},
  "geometry": {"coordinates":[71.053,32.27982],"type":"Point"}
}