{
  "type": "Feature",
  "properties": {
    "gn:admin1_code":"1.0",
    "gn:asciiname":"Fateh Salle",
    "gn:country_code":"PK",
    "gn:dem":503,
    "gn:feature_class":"P",
    "gn:feature_code":"PPL",
    "gn:name":"Fateh Salle",
    "gn:population":0,
    "gn:timezone":"Asia/Karachi",
    "iso:country":"PK",
    "name:eng_x_preferred":[
        "Fateh Sale"
    ],
    "wof:name":"Fateh Salle",
    "wof:placetype":"locality"
},
  "geometry": {"coordinates":[71.64100999999999,34.41012],"type":"Point"}
}