{
  "type": "Feature",
  "properties": {
    "gn:admin1_code":"4.0",
    "gn:asciiname":"Manthar",
    "gn:country_code":"PK",
    "gn:dem":78,
    "gn:feature_class":"P",
    "gn:feature_code":"PPL",
    "gn:name":"Manthar",
    "gn:population":0,
    "gn:timezone":"Asia/Karachi",
    "iso:country":"PK",
    "wof:name":"Manthar",
    "wof:placetype":"locality"
},
  "geometry": {"coordinates":[70.23164,28.18893],"type":"Point"}
}