{
  "type": "Feature",
  "properties": {
    "gn:admin1_code":"5.0",
    "gn:asciiname":"Goth Vedhria",
    "gn:country_code":"PK",
    "gn:dem":8,
    "gn:feature_class":"P",
    "gn:feature_code":"PPL",
    "gn:name":"Goth Vedhria",
    "gn:population":0,
    "gn:timezone":"Asia/Karachi",
    "iso:country":"PK",
    "wof:name":"Goth Vedhria",
    "wof:placetype":"locality"
},
  "geometry": {"coordinates":[67.9149,24.49674],"type":"Point"}
}