{
  "type": "Feature",
  "properties": {
    "gn:admin1_code":"1.0",
    "gn:asciiname":"Shamal Masi",
    "gn:country_code":"PK",
    "gn:dem":1917,
    "gn:feature_class":"P",
    "gn:feature_code":"PPL",
    "gn:name":"Shamal Masi",
    "gn:population":0,
    "gn:timezone":"Asia/Karachi",
    "iso:country":"PK",
    "name:und_x_variant":[
        "Nari Garhi"
    ],
    "wof:name":"Shamal Masi",
    "wof:placetype":"locality"
},
  "geometry": {"coordinates":[70.80927,33.74859],"type":"Point"}
}