{
  "type": "Feature",
  "properties": {
    "gn:admin1_code":"4",
    "gn:asciiname":"Silbandwala",
    "gn:country_code":"PK",
    "gn:dem":112,
    "gn:feature_class":"P",
    "gn:feature_code":"PPL",
    "gn:name":"Silbandwala",
    "gn:population":0,
    "gn:timezone":"Asia/Karachi",
    "iso:country":"PK",
    "name:und_x_variant":[
        "Silband\u0101nw\u0101li",
        "Basti Silband\u0101nw\u0101li",
        "Silbandwala"
    ],
    "wof:name":"Silbandwala",
    "wof:placetype":"locality"
},
  "geometry": {"coordinates":[71.42794000000001,29.41333],"type":"Point"}
}