{
  "type": "Feature",
  "properties": {
    "gn:admin1_code":"2.0",
    "gn:asciiname":"Katho Dasht",
    "gn:country_code":"PK",
    "gn:dem":1786,
    "gn:feature_class":"P",
    "gn:feature_code":"PPL",
    "gn:name":"Katho Dasht",
    "gn:population":0,
    "gn:timezone":"Asia/Karachi",
    "iso:country":"PK",
    "wof:name":"Katho Dasht",
    "wof:placetype":"locality"
},
  "geometry": {"coordinates":[66.55077,27.5641],"type":"Point"}
}