{
  "type": "Feature",
  "properties": {
    "gn:admin1_code":"5",
    "gn:asciiname":"Juman Mangrio",
    "gn:country_code":"PK",
    "gn:dem":63,
    "gn:feature_class":"P",
    "gn:feature_code":"PPL",
    "gn:name":"Juman Mangrio",
    "gn:population":0,
    "gn:timezone":"Asia/Karachi",
    "iso:country":"PK",
    "name:und_x_variant":[
        "Juman Mangria"
    ],
    "wof:name":"Juman Mangrio",
    "wof:placetype":"locality"
},
  "geometry": {"coordinates":[69.15080999999999,27.70478],"type":"Point"}
}