{
  "type": "Feature",
  "properties": {
    "gn:admin1_code":"4.0",
    "gn:asciiname":"Gulistari Cinema",
    "gn:country_code":"PK",
    "gn:dem":170,
    "gn:feature_class":"P",
    "gn:feature_code":"PPL",
    "gn:name":"Gulistari Cinema",
    "gn:population":0,
    "gn:timezone":"Asia/Karachi",
    "iso:country":"PK",
    "wof:name":"Gulistari Cinema",
    "wof:placetype":"neighbourhood"
},
  "geometry": {"coordinates":[72.68197000000001,31.15695],"type":"Point"}
}