{
  "type": "Feature",
  "properties": {
    "gn:admin1_code":"3.0",
    "gn:asciiname":"Kangar",
    "gn:country_code":"PK",
    "gn:dem":1206,
    "gn:feature_class":"P",
    "gn:feature_code":"PPL",
    "gn:name":"Kangar",
    "gn:population":0,
    "gn:timezone":"Asia/Karachi",
    "iso:country":"PK",
    "name:eng_x_preferred":[
        "Kangar"
    ],
    "wof:name":"Kangar",
    "wof:placetype":"locality"
},
  "geometry": {"coordinates":[73.28193,33.92254000000001],"type":"Point"}
}