{
  "type": "Feature",
  "properties": {
    "gn:admin1_code":"3",
    "gn:asciiname":"Chhapri",
    "gn:country_code":"PK",
    "gn:dem":1457,
    "gn:feature_class":"P",
    "gn:feature_code":"PPL",
    "gn:name":"Chhapri",
    "gn:population":0,
    "gn:timezone":"Asia/Karachi",
    "iso:country":"PK",
    "wof:name":"Chhapri",
    "wof:placetype":"locality"
},
  "geometry": {"coordinates":[72.95859,34.49261],"type":"Point"}
}