{
  "type": "Feature",
  "properties": {
    "gn:admin1_code":"4.0",
    "gn:asciiname":"Chak One Hundred Twenty-nine Murad",
    "gn:country_code":"PK",
    "gn:dem":154,
    "gn:feature_class":"P",
    "gn:feature_code":"PPL",
    "gn:name":"Chak One Hundred Twenty-nine Murad",
    "gn:population":0,
    "gn:timezone":"Asia/Karachi",
    "iso:country":"PK",
    "wof:name":"Chak One Hundred Twenty-nine Murad",
    "wof:placetype":"locality"
},
  "geometry": {"coordinates":[72.88339000000001,29.66011],"type":"Point"}
}