{
  "type": "Feature",
  "properties": {
    "gn:admin1_code":"6.0",
    "gn:asciiname":"Akali",
    "gn:country_code":"PK",
    "gn:dem":1203,
    "gn:feature_class":"P",
    "gn:feature_code":"PPL",
    "gn:name":"Akali",
    "gn:population":0,
    "gn:timezone":"Asia/Karachi",
    "iso:country":"PK",
    "name:mal_x_preferred":[
        "\u0d05\u0d15\u0d3e\u0d32\u0d3f"
    ],
    "wof:name":"Akali",
    "wof:placetype":"locality"
},
  "geometry": {"coordinates":[73.99458,33.55636],"type":"Point"}
}