{
  "type": "Feature",
  "properties": {
    "gn:admin1_code":"2.0",
    "gn:asciiname":"Mut Qobul",
    "gn:country_code":"PK",
    "gn:dem":73,
    "gn:feature_class":"P",
    "gn:feature_code":"PPL",
    "gn:name":"Mut Qobul",
    "gn:population":0,
    "gn:timezone":"Asia/Karachi",
    "iso:country":"PK",
    "name:und_x_variant":[
        "Mat Qabul"
    ],
    "wof:name":"Mut Qobul",
    "wof:placetype":"locality"
},
  "geometry": {"coordinates":[67.83497,28.64309],"type":"Point"}
}