{
  "type": "Feature",
  "properties": {
    "gn:admin1_code":"1.0",
    "gn:asciiname":"Mir Zara",
    "gn:country_code":"PK",
    "gn:dem":1332,
    "gn:feature_class":"P",
    "gn:feature_code":"PPL",
    "gn:name":"Mir Zara",
    "gn:population":0,
    "gn:timezone":"Asia/Karachi",
    "iso:country":"PK",
    "wof:name":"Mir Zara",
    "wof:placetype":"locality"
},
  "geometry": {"coordinates":[70.86468000000001,33.64611],"type":"Point"}
}