{
  "type": "Feature",
  "properties": {
    "gn:admin1_code":"5",
    "gn:asciiname":"Saiyid Ghulam Shah",
    "gn:country_code":"PK",
    "gn:dem":54,
    "gn:feature_class":"P",
    "gn:feature_code":"PPL",
    "gn:name":"Saiyid Ghulam Shah",
    "gn:population":0,
    "gn:timezone":"Asia/Karachi",
    "iso:country":"PK",
    "name:und_x_variant":[
        "Tal\u0101nan"
    ],
    "wof:name":"Saiyid Ghulam Shah",
    "wof:placetype":"locality"
},
  "geometry": {"coordinates":[68.25506999999999,28.20832],"type":"Point"}
}