{
  "type": "Feature",
  "properties": {
    "gn:admin1_code":"5.0",
    "gn:asciiname":"Allaho Hingorijo",
    "gn:country_code":"PK",
    "gn:dem":7,
    "gn:feature_class":"P",
    "gn:feature_code":"PPL",
    "gn:name":"Allaho Hingorijo",
    "gn:population":0,
    "gn:timezone":"Asia/Karachi",
    "iso:country":"PK",
    "name:und_x_variant":[
        "All\u0101hno Hingorjo"
    ],
    "wof:name":"Allaho Hingorijo",
    "wof:placetype":"locality"
},
  "geometry": {"coordinates":[68.22235999999999,24.33646],"type":"Point"}
}