{
  "type": "Feature",
  "properties": {
    "gn:admin1_code":"03",
    "gn:asciiname":"Ranwal",
    "gn:country_code":"PK",
    "gn:dem":246,
    "gn:feature_class":"P",
    "gn:feature_code":"PPL",
    "gn:name":"Ranwal",
    "gn:population":0,
    "gn:timezone":"Asia/Karachi",
    "iso:country":"PK",
    "wof:name":"Ranwal",
    "wof:placetype":"locality"
},
  "geometry": {"coordinates":[70.43978,32.18791],"type":"Point"}
}