{
  "type": "Feature",
  "properties": {
    "gn:admin1_code":"7.0",
    "gn:asciiname":"Jud Baihk",
    "gn:country_code":"PK",
    "gn:dem":3689,
    "gn:feature_class":"P",
    "gn:feature_code":"PPL",
    "gn:name":"Jud Baihk",
    "gn:population":0,
    "gn:timezone":"Asia/Karachi",
    "iso:country":"PK",
    "wof:name":"Jud Baihk",
    "wof:placetype":"locality"
},
  "geometry": {"coordinates":[73.14019999999999,35.97465],"type":"Point"}
}