{
  "type": "Feature",
  "properties": {
    "gn:admin1_code":"4",
    "gn:asciiname":"Chana Da Dera",
    "gn:country_code":"PK",
    "gn:dem":207,
    "gn:feature_class":"P",
    "gn:feature_code":"PPL",
    "gn:name":"Chana Da Dera",
    "gn:population":0,
    "gn:timezone":"Asia/Karachi",
    "iso:country":"PK",
    "name:und_x_variant":[
        "Chanan da Dera"
    ],
    "wof:name":"Chana Da Dera",
    "wof:placetype":"locality"
},
  "geometry": {"coordinates":[73.11582,32.38212],"type":"Point"}
}