{
  "type": "Feature",
  "properties": {
    "gn:admin1_code":"2.0",
    "gn:asciiname":"Shin Tora Khulla",
    "gn:country_code":"PK",
    "gn:dem":2123,
    "gn:feature_class":"P",
    "gn:feature_code":"PPL",
    "gn:name":"Shin Tora Khulla",
    "gn:population":0,
    "gn:timezone":"Asia/Karachi",
    "iso:country":"PK",
    "wof:name":"Shin Tora Khulla",
    "wof:placetype":"locality"
},
  "geometry": {"coordinates":[67.37408000000001,30.59556],"type":"Point"}
}