{
  "type": "Feature",
  "properties": {
    "gn:admin1_code":"4.0",
    "gn:asciiname":"Kakki Kohna",
    "gn:cc2":"PK",
    "gn:country_code":"PK",
    "gn:dem":143,
    "gn:feature_class":"P",
    "gn:feature_code":"PPL",
    "gn:name":"Kakki Kohna",
    "gn:population":0,
    "gn:timezone":"Asia/Karachi",
    "iso:country":"PK",
    "name:und_x_variant":[
        "Kakki Kuhna"
    ],
    "wof:name":"Kakki Kohna",
    "wof:placetype":"locality"
},
  "geometry": {"coordinates":[72.18333,30.83333],"type":"Point"}
}