{
  "type": "Feature",
  "properties": {
    "gn:admin1_code":"2.0",
    "gn:asciiname":"Wadal Bazar",
    "gn:country_code":"PK",
    "gn:dem":678,
    "gn:feature_class":"P",
    "gn:feature_code":"PPL",
    "gn:name":"Wadal Bazar",
    "gn:population":0,
    "gn:timezone":"Asia/Karachi",
    "iso:country":"PK",
    "wof:name":"Wadal Bazar",
    "wof:placetype":"locality"
},
  "geometry": {"coordinates":[64.163,26.27882],"type":"Point"}
}