{
  "type": "Feature",
  "properties": {
    "gn:admin1_code":"4",
    "gn:asciiname":"Chah Pathanwala",
    "gn:country_code":"PK",
    "gn:dem":116,
    "gn:feature_class":"P",
    "gn:feature_code":"PPL",
    "gn:name":"Chah Pathanwala",
    "gn:population":0,
    "gn:timezone":"Asia/Karachi",
    "iso:country":"PK",
    "name:und_x_variant":[
        "Path\u0101nw\u0101la"
    ],
    "wof:name":"Chah Pathanwala",
    "wof:placetype":"locality"
},
  "geometry": {"coordinates":[71.64471,29.6032],"type":"Point"}
}