{
  "type": "Feature",
  "properties": {
    "gn:admin1_code":"6",
    "gn:asciiname":"Jhat Baihk",
    "gn:country_code":"PK",
    "gn:dem":2700,
    "gn:feature_class":"P",
    "gn:feature_code":"PPL",
    "gn:name":"Jhat Baihk",
    "gn:population":0,
    "gn:timezone":"Asia/Karachi",
    "iso:country":"PK",
    "name:und_x_variant":[
        "J\u0101t Baihk"
    ],
    "wof:name":"Jhat Baihk",
    "wof:placetype":"locality"
},
  "geometry": {"coordinates":[73.78426999999998,34.66656],"type":"Point"}
}