{
  "type": "Feature",
  "properties": {
    "gn:admin1_code":"7.0",
    "gn:asciiname":"Guisher di Baihk",
    "gn:country_code":"PK",
    "gn:dem":3371,
    "gn:feature_class":"P",
    "gn:feature_code":"PPL",
    "gn:name":"Guisher di Baihk",
    "gn:population":0,
    "gn:timezone":"Asia/Karachi",
    "iso:country":"PK",
    "wof:name":"Guisher di Baihk",
    "wof:placetype":"locality"
},
  "geometry": {"coordinates":[73.96554999999999,35.79282],"type":"Point"}
}