{
  "type": "Feature",
  "properties": {
    "gn:admin1_code":"4",
    "gn:asciiname":"Tallwandi Inayat Khan",
    "gn:country_code":"PK",
    "gn:dem":241,
    "gn:feature_class":"P",
    "gn:feature_code":"PPL",
    "gn:name":"Tallwandi Inayat Khan",
    "gn:population":0,
    "gn:timezone":"Asia/Karachi",
    "iso:country":"PK",
    "name:und_x_variant":[
        "Talwandi In\u0101yat Kh\u0101n"
    ],
    "wof:name":"Tallwandi Inayat Khan",
    "wof:placetype":"locality"
},
  "geometry": {"coordinates":[74.66168,32.23217],"type":"Point"}
}