{
  "type": "Feature",
  "properties": {
    "gn:admin1_code":"5",
    "gn:asciiname":"Gajjan jo Wand",
    "gn:country_code":"PK",
    "gn:dem":77,
    "gn:feature_class":"P",
    "gn:feature_code":"PPL",
    "gn:name":"Gajjan jo Wand",
    "gn:population":0,
    "gn:timezone":"Asia/Karachi",
    "iso:country":"PK",
    "wof:name":"Gajjan jo Wand",
    "wof:placetype":"locality"
},
  "geometry": {"coordinates":[69.44048000000001,26.68281],"type":"Point"}
}