{
  "type": "Feature",
  "properties": {
    "gn:admin1_code":"1.0",
    "gn:asciiname":"Warzi Naraikai",
    "gn:country_code":"PK",
    "gn:dem":1755,
    "gn:feature_class":"P",
    "gn:feature_code":"PPL",
    "gn:name":"Warzi Naraikai",
    "gn:population":0,
    "gn:timezone":"Asia/Karachi",
    "iso:country":"PK",
    "wof:name":"Warzi Naraikai",
    "wof:placetype":"locality"
},
  "geometry": {"coordinates":[69.63719,32.40095],"type":"Point"}
}