{
  "type": "Feature",
  "properties": {
    "gn:admin1_code":"4.0",
    "gn:asciiname":"Liaquatabad",
    "gn:country_code":"PK",
    "gn:dem":84,
    "gn:feature_class":"P",
    "gn:feature_code":"PPL",
    "gn:name":"Liaquatabad",
    "gn:population":0,
    "gn:timezone":"Asia/Karachi",
    "iso:country":"PK",
    "name:und_x_variant":[
        "Li\u0101qat\u0101b\u0101d"
    ],
    "wof:name":"Liaquatabad",
    "wof:placetype":"locality"
},
  "geometry": {"coordinates":[69.99079999999999,28.73194],"type":"Point"}
}