{
  "type": "Feature",
  "properties": {
    "gn:admin1_code":"5.0",
    "gn:asciiname":"Muhammad Uras Palari",
    "gn:country_code":"PK",
    "gn:dem":123,
    "gn:feature_class":"P",
    "gn:feature_code":"PPL",
    "gn:name":"Muhammad Uras Palari",
    "gn:population":0,
    "gn:timezone":"Asia/Karachi",
    "iso:country":"PK",
    "wof:name":"Muhammad Uras Palari",
    "wof:placetype":"locality"
},
  "geometry": {"coordinates":[67.83215,25.40255],"type":"Point"}
}