{
  "type": "Feature",
  "properties": {
    "gn:admin1_code":"5",
    "gn:asciiname":"Goth Lal Watani",
    "gn:country_code":"PK",
    "gn:dem":53,
    "gn:feature_class":"P",
    "gn:feature_code":"PPL",
    "gn:name":"Goth Lal Watani",
    "gn:population":0,
    "gn:timezone":"Asia/Karachi",
    "iso:country":"PK",
    "name:und_x_variant":[
        "L\u0101l W\u0101tani"
    ],
    "wof:name":"Goth Lal Watani",
    "wof:placetype":"locality"
},
  "geometry": {"coordinates":[68.49561,27.29842],"type":"Point"}
}