{
  "type": "Feature",
  "properties": {
    "gn:admin1_code":"3.0",
    "gn:asciiname":"Shul",
    "gn:country_code":"PK",
    "gn:dem":2440,
    "gn:feature_class":"P",
    "gn:feature_code":"PPL",
    "gn:name":"Shul",
    "gn:population":0,
    "gn:timezone":"Asia/Karachi",
    "iso:country":"PK",
    "wof:name":"Shul",
    "wof:placetype":"locality"
},
  "geometry": {"coordinates":[71.67357,36.15371],"type":"Point"}
}