{
  "type": "Feature",
  "properties": {
    "gn:admin1_code":"1.0",
    "gn:asciiname":"Balogai",
    "gn:country_code":"PK",
    "gn:dem":598,
    "gn:feature_class":"P",
    "gn:feature_code":"PPL",
    "gn:name":"Balogai",
    "gn:population":0,
    "gn:timezone":"Asia/Karachi",
    "iso:country":"PK",
    "name:eng_x_preferred":[
        "Balogai"
    ],
    "wof:name":"Balogai",
    "wof:placetype":"locality"
},
  "geometry": {"coordinates":[71.59425,34.42329],"type":"Point"}
}