{
  "type": "Feature",
  "properties": {
    "gn:admin1_code":"5",
    "gn:asciiname":"Goth Salari Machhi",
    "gn:country_code":"PK",
    "gn:dem":50,
    "gn:feature_class":"P",
    "gn:feature_code":"PPL",
    "gn:name":"Goth Salari Machhi",
    "gn:population":0,
    "gn:timezone":"Asia/Karachi",
    "iso:country":"PK",
    "name:und_x_variant":[
        "S\u0101l\u0101ri M\u0101chhi"
    ],
    "wof:name":"Goth Salari Machhi",
    "wof:placetype":"locality"
},
  "geometry": {"coordinates":[68.48289,27.27222],"type":"Point"}
}