{
  "type": "Feature",
  "properties": {
    "gn:admin1_code":"3",
    "gn:asciiname":"Jabrai",
    "gn:country_code":"PK",
    "gn:dem":1485,
    "gn:feature_class":"P",
    "gn:feature_code":"PPL",
    "gn:name":"Jabrai",
    "gn:population":0,
    "gn:timezone":"Asia/Karachi",
    "iso:country":"PK",
    "wof:name":"Jabrai",
    "wof:placetype":"locality"
},
  "geometry": {"coordinates":[73.01696,34.88118],"type":"Point"}
}