{
  "type": "Feature",
  "properties": {
    "gn:admin1_code":"5.0",
    "gn:asciiname":"Sadoros",
    "gn:country_code":"PK",
    "gn:dem":47,
    "gn:feature_class":"P",
    "gn:feature_code":"PPL",
    "gn:name":"Sadoros",
    "gn:population":0,
    "gn:timezone":"Asia/Karachi",
    "iso:country":"PK",
    "name:und_x_variant":[
        "S\u0101dalwa"
    ],
    "wof:name":"Sadoros",
    "wof:placetype":"locality"
},
  "geometry": {"coordinates":[70.79255000000001,24.43692],"type":"Point"}
}