{
  "type": "Feature",
  "properties": {
    "gn:admin1_code":"3.0",
    "gn:asciiname":"Singur",
    "gn:country_code":"PK",
    "gn:dem":1573,
    "gn:feature_class":"P",
    "gn:feature_code":"PPL",
    "gn:name":"Singur",
    "gn:population":0,
    "gn:timezone":"Asia/Karachi",
    "iso:country":"PK",
    "name:ben_x_preferred":[
        "\u09b8\u09bf\u0999\u09cd\u0997\u09c1\u09b0"
    ],
    "name:bpy_x_preferred":[
        "\u09b8\u09bf\u0999\u09cd\u0997\u09c1\u09b0"
    ],
    "name:ceb_x_preferred":[
        "Singur"
    ],
    "name:hif_x_preferred":[
        "Singur"
    ],
    "name:hin_x_preferred":[
        "\u0938\u093f\u0902\u0917\u0942\u0930"
    ],
    "name:ind_x_preferred":[
        "Singur"
    ],
    "name:ita_x_preferred":[
        "Singur"
    ],
    "name:msa_x_preferred":[
        "Singur"
    ],
    "name:nld_x_preferred":[
        "Singur"
    ],
    "name:por_x_preferred":[
        "Singur"
    ],
    "name:swe_x_preferred":[
        "Singur"
    ],
    "name:urd_x_preferred":[
        "Singor"
    ],
    "name:urd_x_variant":[
        "\u0633\u0650\u0646\u0652\u06af\u0648\u0631"
    ],
    "name:vie_x_preferred":[
        "Singur"
    ],
    "name:zho_x_preferred":[
        "\u8f9b\u683c\u4e4c\u5c14"
    ],
    "wof:name":"Singur",
    "wof:placetype":"locality"
},
  "geometry": {"coordinates":[71.79862,35.89891],"type":"Point"}
}