{
  "type": "Feature",
  "properties": {
    "gn:admin1_code":"3.0",
    "gn:asciiname":"Singur",
    "gn:country_code":"PK",
    "gn:dem":1573,
    "gn:feature_class":"P",
    "gn:feature_code":"PPL",
    "gn:name":"Singur",
    "gn:population":0,
    "gn:timezone":"Asia/Karachi",
    "iso:country":"PK",
    "name:urd_x_preferred":[
        "Singor"
    ],
    "name:urd_x_variant":[
        "\u0633\u0650\u0646\u0652\u06af\u0648\u0631"
    ],
    "wof:name":"Singur",
    "wof:placetype":"locality"
},
  "geometry": {"coordinates":[71.79862,35.89891],"type":"Point"}
}