{
  "type": "Feature",
  "properties": {
    "gn:admin1_code":"2.0",
    "gn:asciiname":"Goth Mehram Khan",
    "gn:country_code":"PK",
    "gn:dem":61,
    "gn:feature_class":"P",
    "gn:feature_code":"PPL",
    "gn:name":"Goth Mehram Khan",
    "gn:population":0,
    "gn:timezone":"Asia/Karachi",
    "iso:country":"PK",
    "wof:name":"Goth Mehram Khan",
    "wof:placetype":"locality"
},
  "geometry": {"coordinates":[67.9395,28.3257],"type":"Point"}
}