{
  "type": "Feature",
  "properties": {
    "gn:admin1_code":"4.0",
    "gn:asciiname":"Burj Ahmad Khan",
    "gn:country_code":"PK",
    "gn:dem":207,
    "gn:feature_class":"P",
    "gn:feature_code":"PPL",
    "gn:name":"Burj Ahmad Khan",
    "gn:population":0,
    "gn:timezone":"Asia/Karachi",
    "iso:country":"PK",
    "wof:name":"Burj Ahmad Khan",
    "wof:placetype":"locality"
},
  "geometry": {"coordinates":[73.27152,32.62977],"type":"Point"}
}