{
  "type": "Feature",
  "properties": {
    "gn:admin1_code":"7.0",
    "gn:asciiname":"Dadar Lasht",
    "gn:country_code":"PK",
    "gn:dem":3220,
    "gn:feature_class":"P",
    "gn:feature_code":"PPL",
    "gn:name":"Dadar Lasht",
    "gn:population":0,
    "gn:timezone":"Asia/Karachi",
    "iso:country":"PK",
    "wof:name":"Dadar Lasht",
    "wof:placetype":"locality"
},
  "geometry": {"coordinates":[72.7286,36.1624],"type":"Point"}
}