{
  "type": "Feature",
  "properties": {
    "gn:admin1_code":"3",
    "gn:asciiname":"Kater",
    "gn:country_code":"PK",
    "gn:dem":2045,
    "gn:feature_class":"P",
    "gn:feature_code":"PPL",
    "gn:name":"Kater",
    "gn:population":0,
    "gn:timezone":"Asia/Karachi",
    "iso:country":"PK",
    "name:eng_x_preferred":[
        "Kater"
    ],
    "wof:name":"Kater",
    "wof:placetype":"locality"
},
  "geometry": {"coordinates":[71.95284000000002,35.37369],"type":"Point"}
}