{
  "type": "Feature",
  "properties": {
    "gn:admin1_code":"2",
    "gn:asciiname":"Tor Daman",
    "gn:country_code":"PK",
    "gn:dem":1932,
    "gn:feature_class":"P",
    "gn:feature_code":"PPL",
    "gn:name":"Tor Daman",
    "gn:population":0,
    "gn:timezone":"Asia/Karachi",
    "iso:country":"PK",
    "name:eng_x_preferred":[
        "Tor Daman"
    ],
    "wof:name":"Tor Daman",
    "wof:placetype":"locality"
},
  "geometry": {"coordinates":[67.32011,30.5978],"type":"Point"}
}