{
  "type": "Feature",
  "properties": {
    "gn:admin1_code":"4.0",
    "gn:asciiname":"Kailuanwala",
    "gn:country_code":"PK",
    "gn:dem":167,
    "gn:feature_class":"P",
    "gn:feature_code":"PPL",
    "gn:name":"Kailuanwala",
    "gn:population":0,
    "gn:timezone":"Asia/Karachi",
    "iso:country":"PK",
    "wof:name":"Kailuanwala",
    "wof:placetype":"locality"
},
  "geometry": {"coordinates":[71.19566999999998,31.53442],"type":"Point"}
}