{
  "type": "Feature",
  "properties": {
    "gn:admin1_code":"7.0",
    "gn:asciiname":"Lato Harai",
    "gn:country_code":"PK",
    "gn:dem":3853,
    "gn:feature_class":"P",
    "gn:feature_code":"PPL",
    "gn:name":"Lato Harai",
    "gn:population":0,
    "gn:timezone":"Asia/Karachi",
    "iso:country":"PK",
    "wof:name":"Lato Harai",
    "wof:placetype":"locality"
},
  "geometry": {"coordinates":[73.59179,36.07487],"type":"Point"}
}