{
  "type": "Feature",
  "properties": {
    "gn:admin1_code":"4.0",
    "gn:asciiname":"Kund Haji",
    "gn:country_code":"PK",
    "gn:dem":386,
    "gn:feature_class":"P",
    "gn:feature_code":"PPL",
    "gn:name":"Kund Haji",
    "gn:population":0,
    "gn:timezone":"Asia/Karachi",
    "iso:country":"PK",
    "wof:name":"Kund Haji",
    "wof:placetype":"locality"
},
  "geometry": {"coordinates":[72.58753,33.83192],"type":"Point"}
}