{
  "type": "Feature",
  "properties": {
    "gn:admin1_code":"4.0",
    "gn:asciiname":"Jag Bhatti",
    "gn:country_code":"PK",
    "gn:dem":196,
    "gn:feature_class":"P",
    "gn:feature_code":"PPL",
    "gn:name":"Jag Bhatti",
    "gn:population":0,
    "gn:timezone":"Asia/Karachi",
    "iso:country":"PK",
    "name:und_x_variant":[
        "Chak Bhatti"
    ],
    "wof:name":"Jag Bhatti",
    "wof:placetype":"locality"
},
  "geometry": {"coordinates":[73.34435999999999,32.04477],"type":"Point"}
}