{
  "type": "Feature",
  "properties": {
    "gn:admin1_code":"6",
    "gn:asciiname":"Kakhato",
    "gn:country_code":"PK",
    "gn:dem":1051,
    "gn:feature_class":"P",
    "gn:feature_code":"PPL",
    "gn:name":"Kakhato",
    "gn:population":0,
    "gn:timezone":"Asia/Karachi",
    "iso:country":"PK",
    "name:und_x_variant":[
        "Phajuta",
        "Dhor Bazar"
    ],
    "wof:name":"Kakhato",
    "wof:placetype":"locality"
},
  "geometry": {"coordinates":[73.91743000000002,33.71695],"type":"Point"}
}