{
  "type": "Feature",
  "properties": {
    "gn:admin1_code":"2.0",
    "gn:asciiname":"Kili Nur Muhammad",
    "gn:country_code":"PK",
    "gn:dem":609,
    "gn:feature_class":"P",
    "gn:feature_code":"PPL",
    "gn:name":"Kili Nur Muhammad",
    "gn:population":0,
    "gn:timezone":"Asia/Karachi",
    "iso:country":"PK",
    "wof:name":"Kili Nur Muhammad",
    "wof:placetype":"locality"
},
  "geometry": {"coordinates":[64.38911,28.33974000000001],"type":"Point"}
}