{
  "type": "Feature",
  "properties": {
    "gn:admin1_code":"5",
    "gn:asciiname":"Goth Hahi Moujai",
    "gn:country_code":"PK",
    "gn:dem":51,
    "gn:feature_class":"P",
    "gn:feature_code":"PPL",
    "gn:name":"Goth Hahi Moujai",
    "gn:population":0,
    "gn:timezone":"Asia/Karachi",
    "iso:country":"PK",
    "name:und_x_variant":[
        "H\u0101mid Muj\u0101i"
    ],
    "wof:name":"Goth Hahi Moujai",
    "wof:placetype":"locality"
},
  "geometry": {"coordinates":[68.45224,27.10507],"type":"Point"}
}