{
  "type": "Feature",
  "properties": {
    "gn:admin1_code":"4.0",
    "gn:asciiname":"Dheri",
    "gn:cc2":"PK",
    "gn:country_code":"PK",
    "gn:dem":271,
    "gn:feature_class":"P",
    "gn:feature_code":"PPL",
    "gn:name":"Dheri",
    "gn:population":0,
    "gn:timezone":"Asia/Karachi",
    "iso:country":"PK",
    "name:und_x_variant":[
        "Dheri Hardo",
        "Dheri"
    ],
    "wof:name":"Dheri",
    "wof:placetype":"locality"
},
  "geometry": {"coordinates":[73.66667,33.03333],"type":"Point"}
}