{
  "type": "Feature",
  "properties": {
    "gn:admin1_code":"3.0",
    "gn:asciiname":"Jallozai",
    "gn:country_code":"PK",
    "gn:dem":423,
    "gn:feature_class":"P",
    "gn:feature_code":"PPL",
    "gn:name":"Jallozai",
    "gn:population":0,
    "gn:timezone":"Asia/Karachi",
    "iso:country":"PK",
    "name:und_x_variant":[
        "Jailozai",
        "Jalozai",
        "Jallozai"
    ],
    "wof:name":"Jallozai",
    "wof:placetype":"locality"
},
  "geometry": {"coordinates":[71.81822,33.91165],"type":"Point"}
}