{
  "type": "Feature",
  "properties": {
    "gn:admin1_code":"3.0",
    "gn:asciiname":"Jallozai",
    "gn:country_code":"PK",
    "gn:dem":423,
    "gn:feature_class":"P",
    "gn:feature_code":"PPL",
    "gn:name":"Jallozai",
    "gn:population":0,
    "gn:timezone":"Asia/Karachi",
    "iso:country":"PK",
    "name:deu_x_preferred":[
        "Jalozai"
    ],
    "name:jpn_x_preferred":[
        "\u30b8\u30e3\u30ed\u30b6\u30a4"
    ],
    "name:spa_x_preferred":[
        "Jalozai"
    ],
    "name:und_x_variant":[
        "Jailozai",
        "Jallozai"
    ],
    "name:urd_x_preferred":[
        "\u062c\u0644\u0648\u0632\u0626\u06cc"
    ],
    "wof:name":"Jallozai",
    "wof:placetype":"locality"
},
  "geometry": {"coordinates":[71.81822,33.91165],"type":"Point"}
}