{
  "type": "Feature",
  "properties": {
    "gn:admin1_code":"5",
    "gn:asciiname":"Haji Qamar Din",
    "gn:country_code":"PK",
    "gn:dem":44,
    "gn:feature_class":"P",
    "gn:feature_code":"PPL",
    "gn:name":"Haji Qamar Din",
    "gn:population":0,
    "gn:timezone":"Asia/Karachi",
    "iso:country":"PK",
    "name:und_x_variant":[
        "Haji Qamar D\u012bn Chand\u012ba"
    ],
    "wof:name":"Haji Qamar Din",
    "wof:placetype":"locality"
},
  "geometry": {"coordinates":[68.12517,26.63963],"type":"Point"}
}