{
  "type": "Feature",
  "properties": {
    "gn:admin1_code":"5.0",
    "gn:asciiname":"Baha",
    "gn:country_code":"PK",
    "gn:dem":9,
    "gn:feature_class":"P",
    "gn:feature_code":"PPL",
    "gn:name":"Baha",
    "gn:population":0,
    "gn:timezone":"Asia/Karachi",
    "iso:country":"PK",
    "name:ceb_x_preferred":[
        "Baha"
    ],
    "name:deu_x_preferred":[
        "Baha"
    ],
    "name:msa_x_preferred":[
        "Baha"
    ],
    "name:pol_x_preferred":[
        "Baha"
    ],
    "name:rus_x_preferred":[
        "\u0411\u0430\u0445\u0430"
    ],
    "name:swe_x_preferred":[
        "Baha"
    ],
    "wof:name":"Baha",
    "wof:placetype":"locality"
},
  "geometry": {"coordinates":[67.99462,24.4238],"type":"Point"}
}