{
  "type": "Feature",
  "properties": {
    "gn:admin1_code":"2.0",
    "gn:asciiname":"Kili Khudave Dost",
    "gn:country_code":"PK",
    "gn:dem":1992,
    "gn:feature_class":"P",
    "gn:feature_code":"PPL",
    "gn:name":"Kili Khudave Dost",
    "gn:population":0,
    "gn:timezone":"Asia/Karachi",
    "iso:country":"PK",
    "wof:name":"Kili Khudave Dost",
    "wof:placetype":"locality"
},
  "geometry": {"coordinates":[66.40182,30.63583],"type":"Point"}
}