{
  "type": "Feature",
  "properties": {
    "gn:admin1_code":"4",
    "gn:asciiname":"Wahdat Colony",
    "gn:country_code":"PK",
    "gn:dem":121,
    "gn:feature_class":"P",
    "gn:feature_code":"PPL",
    "gn:name":"Wahdat Colony",
    "gn:population":0,
    "gn:timezone":"Asia/Karachi",
    "iso:country":"PK",
    "name:eng_x_preferred":[
        "Wahdat Colony"
    ],
    "name:urd_x_preferred":[
        "\u0648\u062d\u062f\u062a \u06a9\u0627\u0644\u0648\u0646\u06cc"
    ],
    "wof:name":"Wahdat Colony",
    "wof:placetype":"neighbourhood"
},
  "geometry": {"coordinates":[71.49722,30.20556],"type":"Point"}
}