{
  "type": "Feature",
  "properties": {
    "gn:admin1_code":"2.0",
    "gn:asciiname":"Phurki",
    "gn:country_code":"PK",
    "gn:dem":1155,
    "gn:feature_class":"P",
    "gn:feature_code":"PPL",
    "gn:name":"Phurki",
    "gn:population":0,
    "gn:timezone":"Asia/Karachi",
    "iso:country":"PK",
    "wof:name":"Phurki",
    "wof:placetype":"locality"
},
  "geometry": {"coordinates":[66.21758,27.60965],"type":"Point"}
}