{
  "type": "Feature",
  "properties": {
    "gn:admin1_code":"2.0",
    "gn:asciiname":"Miran Bazar",
    "gn:country_code":"PK",
    "gn:dem":19,
    "gn:feature_class":"P",
    "gn:feature_code":"PPL",
    "gn:name":"Miran Bazar",
    "gn:population":0,
    "gn:timezone":"Asia/Karachi",
    "iso:country":"PK",
    "name:und_x_variant":[
        "M\u012bran"
    ],
    "wof:name":"Miran Bazar",
    "wof:placetype":"locality"
},
  "geometry": {"coordinates":[61.95899,25.52045],"type":"Point"}
}