{
  "type": "Feature",
  "properties": {
    "gn:admin1_code":"5.0",
    "gn:asciiname":"Goth Muhammad Khan Sumro Doctor",
    "gn:country_code":"PK",
    "gn:dem":14,
    "gn:feature_class":"P",
    "gn:feature_code":"PPL",
    "gn:name":"Goth Muhammad Khan Sumro Doctor",
    "gn:population":0,
    "gn:timezone":"Asia/Karachi",
    "iso:country":"PK",
    "wof:name":"Goth Muhammad Khan Sumro Doctor",
    "wof:placetype":"locality"
},
  "geometry": {"coordinates":[67.98459,24.7751],"type":"Point"}
}