{
  "type": "Feature",
  "properties": {
    "gn:admin1_code":"4.0",
    "gn:asciiname":"Hafiz Habibullah Bhutto",
    "gn:cc2":"PK",
    "gn:country_code":"PK",
    "gn:dem":165,
    "gn:feature_class":"P",
    "gn:feature_code":"PPL",
    "gn:name":"H\u0101f\u012bz Hab\u012bbullah Bhutto",
    "gn:population":0,
    "gn:timezone":"Asia/Karachi",
    "iso:country":"PK",
    "name:und_x_variant":[
        "H\u0101f\u012bzpur",
        "H\u0101f\u012bz Hab\u012bbullah Bhutto"
    ],
    "wof:name":"Hafiz Habibullah Bhutto",
    "wof:placetype":"locality"
},
  "geometry": {"coordinates":[72.81667,30.61667000000001],"type":"Point"}
}