{
  "type": "Feature",
  "properties": {
    "gn:admin1_code":"3",
    "gn:asciiname":"Wandah Khokhar",
    "gn:country_code":"PK",
    "gn:dem":199,
    "gn:feature_class":"P",
    "gn:feature_code":"PPL",
    "gn:name":"Wandah Khokhar",
    "gn:population":0,
    "gn:timezone":"Asia/Karachi",
    "iso:country":"PK",
    "name:und_x_variant":[
        "W\u0101ndah Khokar",
        "Wandah Khokhar"
    ],
    "wof:name":"Wandah Khokhar",
    "wof:placetype":"locality"
},
  "geometry": {"coordinates":[70.70503000000002,31.98939],"type":"Point"}
}