{
  "type": "Feature",
  "properties": {
    "gn:admin1_code":"4",
    "gn:asciiname":"Diwanwala",
    "gn:country_code":"PK",
    "gn:dem":113,
    "gn:feature_class":"P",
    "gn:feature_code":"PPL",
    "gn:name":"Diwanwala",
    "gn:population":0,
    "gn:timezone":"Asia/Karachi",
    "iso:country":"PK",
    "name:und_x_variant":[
        "J\u0101niw\u0101la"
    ],
    "wof:name":"Diwanwala",
    "wof:placetype":"locality"
},
  "geometry": {"coordinates":[70.57271,29.8742],"type":"Point"}
}