{
  "type": "Feature",
  "properties": {
    "gn:admin1_code":"4",
    "gn:asciiname":"Farid Ki Jhalar",
    "gn:country_code":"PK",
    "gn:dem":134,
    "gn:feature_class":"P",
    "gn:feature_code":"PPL",
    "gn:name":"Farid Ki Jhalar",
    "gn:population":0,
    "gn:timezone":"Asia/Karachi",
    "iso:country":"PK",
    "wof:name":"Farid Ki Jhalar",
    "wof:placetype":"locality"
},
  "geometry": {"coordinates":[71.842,30.58817],"type":"Point"}
}