{
  "type": "Feature",
  "properties": {
    "gn:admin1_code":"1.0",
    "gn:asciiname":"Baza",
    "gn:country_code":"PK",
    "gn:dem":2148,
    "gn:feature_class":"P",
    "gn:feature_code":"PPL",
    "gn:name":"Baza",
    "gn:population":0,
    "gn:timezone":"Asia/Karachi",
    "iso:country":"PK",
    "name:aze_x_preferred":[
        "Baza"
    ],
    "name:bos_x_preferred":[
        "Baza"
    ],
    "name:bre_x_preferred":[
        "Baza"
    ],
    "name:ceb_x_preferred":[
        "Baza"
    ],
    "name:chv_x_preferred":[
        "\u0411\u0430\u0437\u0430"
    ],
    "name:hrv_x_preferred":[
        "Baza"
    ],
    "name:ita_x_preferred":[
        "Baza"
    ],
    "name:pol_x_preferred":[
        "Baza"
    ],
    "name:ron_x_preferred":[
        "Baz\u0103"
    ],
    "name:rus_x_preferred":[
        "\u0411\u0430\u0437\u0430"
    ],
    "name:slk_x_preferred":[
        "Baza"
    ],
    "name:slv_x_preferred":[
        "Baza"
    ],
    "name:spa_x_preferred":[
        "Baza"
    ],
    "name:srp_x_preferred":[
        "\u0411\u0430\u0437\u0430"
    ],
    "name:swe_x_preferred":[
        "Baza"
    ],
    "name:tur_x_preferred":[
        "Baza"
    ],
    "name:ukr_x_preferred":[
        "\u0411\u0430\u0437\u0430"
    ],
    "name:und_x_variant":[
        "Baza Killi"
    ],
    "wof:name":"Baza",
    "wof:placetype":"locality"
},
  "geometry": {"coordinates":[70.3677,33.845],"type":"Point"}
}