{
  "type": "Feature",
  "properties": {
    "gn:admin1_code":"1.0",
    "gn:asciiname":"Baza",
    "gn:country_code":"PK",
    "gn:dem":2148,
    "gn:feature_class":"P",
    "gn:feature_code":"PPL",
    "gn:name":"Baza",
    "gn:population":0,
    "gn:timezone":"Asia/Karachi",
    "iso:country":"PK",
    "name:und_x_variant":[
        "Baza Killi"
    ],
    "wof:name":"Baza",
    "wof:placetype":"locality"
},
  "geometry": {"coordinates":[70.3677,33.845],"type":"Point"}
}