{
  "type": "Feature",
  "properties": {
    "gn:admin1_code":"3",
    "gn:asciiname":"Narshak",
    "gn:country_code":"PK",
    "gn:dem":325,
    "gn:feature_class":"P",
    "gn:feature_code":"PPL",
    "gn:name":"Narshak",
    "gn:population":0,
    "gn:timezone":"Asia/Karachi",
    "iso:country":"PK",
    "name:eng_x_preferred":[
        "Narshak"
    ],
    "wof:name":"Narshak",
    "wof:placetype":"locality"
},
  "geometry": {"coordinates":[72.1482,34.26535],"type":"Point"}
}