{
  "type": "Feature",
  "properties": {
    "gn:admin1_code":"2.0",
    "gn:asciiname":"Zaimki Kili",
    "gn:country_code":"PK",
    "gn:dem":2440,
    "gn:feature_class":"P",
    "gn:feature_code":"PPL",
    "gn:name":"Zaimki Kili",
    "gn:population":0,
    "gn:timezone":"Asia/Karachi",
    "iso:country":"PK",
    "wof:name":"Zaimki Kili",
    "wof:placetype":"locality"
},
  "geometry": {"coordinates":[68.44232,31.19669],"type":"Point"}
}