{
  "type": "Feature",
  "properties": {
    "gn:admin1_code":"6.0",
    "gn:asciiname":"Palet Saidar",
    "gn:country_code":"PK",
    "gn:dem":513,
    "gn:feature_class":"P",
    "gn:feature_code":"PPL",
    "gn:name":"Palet Saidar",
    "gn:population":0,
    "gn:timezone":"Asia/Karachi",
    "iso:country":"PK",
    "wof:name":"Palet Saidar",
    "wof:placetype":"locality"
},
  "geometry": {"coordinates":[73.68312,33.54267],"type":"Point"}
}