{
  "type": "Feature",
  "properties": {
    "gn:admin1_code":"4.0",
    "gn:asciiname":"Firoz Watuan",
    "gn:country_code":"PK",
    "gn:dem":205,
    "gn:feature_class":"P",
    "gn:feature_code":"PPL",
    "gn:name":"Firoz Watuan",
    "gn:population":0,
    "gn:timezone":"Asia/Karachi",
    "iso:country":"PK",
    "name:und_x_variant":[
        "Feroze",
        "F\u012broz",
        "Firoz Watuan"
    ],
    "wof:name":"Firoz Watuan",
    "wof:placetype":"locality"
},
  "geometry": {"coordinates":[73.81477,31.59235],"type":"Point"}
}