{
  "type": "Feature",
  "properties": {
    "gn:admin1_code":"3.0",
    "gn:asciiname":"Ghorzandai",
    "gn:country_code":"PK",
    "gn:dem":646,
    "gn:feature_class":"P",
    "gn:feature_code":"PPL",
    "gn:name":"Ghorzandai",
    "gn:population":0,
    "gn:timezone":"Asia/Karachi",
    "iso:country":"PK",
    "name:und_x_variant":[
        "Ghurzandi",
        "Ghorzandi",
        "Ghorzandai"
    ],
    "wof:name":"Ghorzandai",
    "wof:placetype":"locality"
},
  "geometry": {"coordinates":[71.17208000000002,33.38515],"type":"Point"}
}