{
  "type": "Feature",
  "properties": {
    "gn:admin1_code":"3.0",
    "gn:asciiname":"Patai",
    "gn:country_code":"PK",
    "gn:dem":702,
    "gn:feature_class":"P",
    "gn:feature_code":"PPL",
    "gn:name":"Patai",
    "gn:population":0,
    "gn:timezone":"Asia/Karachi",
    "iso:country":"PK",
    "name:und_x_variant":[
        "Pata B\u0101nda"
    ],
    "wof:name":"Patai",
    "wof:placetype":"locality"
},
  "geometry": {"coordinates":[72.71437,34.46916],"type":"Point"}
}