{
  "type": "Feature",
  "properties": {
    "gn:admin1_code":"4.0",
    "gn:asciiname":"Naushohra",
    "gn:country_code":"PK",
    "gn:dem":187,
    "gn:feature_class":"P",
    "gn:feature_code":"PPL",
    "gn:name":"Naushohra",
    "gn:population":0,
    "gn:timezone":"Asia/Karachi",
    "iso:country":"PK",
    "name:und_x_variant":[
        "Naushahra"
    ],
    "wof:name":"Naushohra",
    "wof:placetype":"locality"
},
  "geometry": {"coordinates":[71.21384,32.25295999999999],"type":"Point"}
}