{
  "type": "Feature",
  "properties": {
    "gn:admin1_code":"4.0",
    "gn:asciiname":"Torang Mela",
    "gn:country_code":"PK",
    "gn:dem":379,
    "gn:feature_class":"P",
    "gn:feature_code":"PPL",
    "gn:name":"Torang Mela",
    "gn:population":0,
    "gn:timezone":"Asia/Karachi",
    "iso:country":"PK",
    "name:und_x_variant":[
        "Turakhel Mela"
    ],
    "wof:name":"Torang Mela",
    "wof:placetype":"locality"
},
  "geometry": {"coordinates":[71.82115,33.23543],"type":"Point"}
}