{
  "type": "Feature",
  "properties": {
    "gn:admin1_code":"2",
    "gn:asciiname":"Mandawal",
    "gn:country_code":"PK",
    "gn:dem":1679,
    "gn:feature_class":"P",
    "gn:feature_code":"PPL",
    "gn:name":"Mandawal",
    "gn:population":0,
    "gn:timezone":"Asia/Karachi",
    "iso:country":"PK",
    "name:und_x_variant":[
        "M\u0101nd\u0101nw\u0101la"
    ],
    "wof:name":"Mandawal",
    "wof:placetype":"locality"
},
  "geometry": {"coordinates":[66.19476999999999,28.36033],"type":"Point"}
}