{
  "type": "Feature",
  "properties": {
    "gn:admin1_code":"3.0",
    "gn:asciiname":"Banda Abdul Samad",
    "gn:country_code":"PK",
    "gn:dem":413,
    "gn:feature_class":"P",
    "gn:feature_code":"PPL",
    "gn:name":"Banda Abdul Samad",
    "gn:population":0,
    "gn:timezone":"Asia/Karachi",
    "iso:country":"PK",
    "name:und_x_variant":[
        "Banda Abdul Samad Khan",
        "Banda Abdul Samad"
    ],
    "wof:name":"Banda Abdul Samad",
    "wof:placetype":"locality"
},
  "geometry": {"coordinates":[71.48064000000002,33.45926],"type":"Point"}
}