{
  "type": "Feature",
  "properties": {
    "gn:admin1_code":"6.0",
    "gn:asciiname":"Puhti Baihk",
    "gn:country_code":"PK",
    "gn:dem":2743,
    "gn:feature_class":"P",
    "gn:feature_code":"PPL",
    "gn:name":"Puhti Baihk",
    "gn:population":0,
    "gn:timezone":"Asia/Karachi",
    "iso:country":"PK",
    "wof:name":"Puhti Baihk",
    "wof:placetype":"locality"
},
  "geometry": {"coordinates":[73.44315999999998,34.50648],"type":"Point"}
}