{
  "type": "Feature",
  "properties": {
    "gn:admin1_code":"4",
    "gn:asciiname":"Tatkiwala",
    "gn:country_code":"PK",
    "gn:dem":173,
    "gn:feature_class":"P",
    "gn:feature_code":"PPL",
    "gn:name":"Tatkiwala",
    "gn:population":0,
    "gn:timezone":"Asia/Karachi",
    "iso:country":"PK",
    "name:und_x_variant":[
        "Tatk\u012bw\u0101la",
        "Titk\u012bw\u0101la",
        "Tatkiwala"
    ],
    "wof:name":"Tatkiwala",
    "wof:placetype":"locality"
},
  "geometry": {"coordinates":[71.2033,31.67137],"type":"Point"}
}