{
  "type": "Feature",
  "properties": {
    "gn:admin1_code":"4.0",
    "gn:asciiname":"Patiala",
    "gn:country_code":"PK",
    "gn:dem":200,
    "gn:feature_class":"P",
    "gn:feature_code":"PPL",
    "gn:name":"Patiala",
    "gn:population":0,
    "gn:timezone":"Asia/Karachi",
    "iso:country":"PK",
    "name:und_x_variant":[
        "Tapi\u0101la"
    ],
    "wof:name":"Patiala",
    "wof:placetype":"locality"
},
  "geometry": {"coordinates":[73.89059,31.53091],"type":"Point"}
}