{
  "type": "Feature",
  "properties": {
    "gn:admin1_code":"5.0",
    "gn:asciiname":"Goth Allah Bakhsh",
    "gn:country_code":"PK",
    "gn:dem":248,
    "gn:feature_class":"P",
    "gn:feature_code":"PPL",
    "gn:name":"Goth All\u0101h Bakhsh",
    "gn:population":0,
    "gn:timezone":"Asia/Karachi",
    "iso:country":"PK",
    "wof:name":"Goth Allah Bakhsh",
    "wof:placetype":"locality"
},
  "geometry": {"coordinates":[67.60589,25.43001],"type":"Point"}
}