{
  "type": "Feature",
  "properties": {
    "gn:admin1_code":"5",
    "gn:asciiname":"Lahno Faqir Jatoi",
    "gn:country_code":"PK",
    "gn:dem":41,
    "gn:feature_class":"P",
    "gn:feature_code":"PPL",
    "gn:name":"Lahno Faqir Jatoi",
    "gn:population":0,
    "gn:timezone":"Asia/Karachi",
    "iso:country":"PK",
    "name:und_x_variant":[
        "Laeno Faq\u012br D\u0101hri",
        "Lanno Faq\u012br J\u0101toi",
        "Lahno Faqir Jatoi"
    ],
    "wof:name":"Lahno Faqir Jatoi",
    "wof:placetype":"locality"
},
  "geometry": {"coordinates":[68.13114,26.71198],"type":"Point"}
}