{
  "type": "Feature",
  "properties": {
    "gn:admin1_code":"3",
    "gn:asciiname":"Achro Banda",
    "gn:country_code":"PK",
    "gn:dem":2343,
    "gn:feature_class":"P",
    "gn:feature_code":"PPL",
    "gn:name":"Achro Banda",
    "gn:population":0,
    "gn:timezone":"Asia/Karachi",
    "iso:country":"PK",
    "wof:name":"Achro Banda",
    "wof:placetype":"locality"
},
  "geometry": {"coordinates":[72.58450000000001,34.84569],"type":"Point"}
}