{
  "type": "Feature",
  "properties": {
    "gn:admin1_code":"7.0",
    "gn:asciiname":"Kha",
    "gn:country_code":"PK",
    "gn:dem":1538,
    "gn:feature_class":"P",
    "gn:feature_code":"PPL",
    "gn:name":"Kha",
    "gn:population":0,
    "gn:timezone":"Asia/Karachi",
    "iso:country":"PK",
    "name:deu_x_preferred":[
        "Kha"
    ],
    "wof:name":"Kha",
    "wof:placetype":"locality"
},
  "geometry": {"coordinates":[74.29319,36.0522],"type":"Point"}
}