{
  "type": "Feature",
  "properties": {
    "gn:admin1_code":"4.0",
    "gn:asciiname":"Haqiqa Char",
    "gn:country_code":"PK",
    "gn:dem":268,
    "gn:feature_class":"P",
    "gn:feature_code":"PPL",
    "gn:name":"Haqiqa Char",
    "gn:population":0,
    "gn:timezone":"Asia/Karachi",
    "iso:country":"PK",
    "wof:name":"Haqiqa Char",
    "wof:placetype":"locality"
},
  "geometry": {"coordinates":[73.85417,32.7811],"type":"Point"}
}