{
  "type": "Feature",
  "properties": {
    "gn:admin1_code":"4.0",
    "gn:asciiname":"Paka Mari",
    "gn:country_code":"PK",
    "gn:dem":184,
    "gn:feature_class":"P",
    "gn:feature_code":"PPL",
    "gn:name":"Paka Mari",
    "gn:population":0,
    "gn:timezone":"Asia/Karachi",
    "iso:country":"PK",
    "name:und_x_variant":[
        "Pakkam\u0101ri",
        "Paka Mari",
        "Farzand Al\u012bw\u0101la"
    ],
    "wof:name":"Paka Mari",
    "wof:placetype":"neighbourhood"
},
  "geometry": {"coordinates":[73.13333,31.43333],"type":"Point"}
}