{
  "type": "Feature",
  "properties": {
    "gn:admin1_code":"3.0",
    "gn:asciiname":"Shikari Baihk",
    "gn:country_code":"PK",
    "gn:dem":3332,
    "gn:feature_class":"P",
    "gn:feature_code":"PPL",
    "gn:name":"Shikari Baihk",
    "gn:population":0,
    "gn:timezone":"Asia/Karachi",
    "iso:country":"PK",
    "wof:name":"Shikari Baihk",
    "wof:placetype":"locality"
},
  "geometry": {"coordinates":[73.8301,35.17345],"type":"Point"}
}