{
  "type": "Feature",
  "properties": {
    "gn:admin1_code":"5",
    "gn:asciiname":"Goth Miro Kapri",
    "gn:country_code":"PK",
    "gn:dem":12,
    "gn:feature_class":"P",
    "gn:feature_code":"PPL",
    "gn:name":"Goth Miro Kapri",
    "gn:population":0,
    "gn:timezone":"Asia/Karachi",
    "iso:country":"PK",
    "name:und_x_variant":[
        "Sobdar Kapri"
    ],
    "wof:name":"Goth Miro Kapri",
    "wof:placetype":"locality"
},
  "geometry": {"coordinates":[69.45255999999999,25.25788],"type":"Point"}
}