{
  "type": "Feature",
  "properties": {
    "gn:admin1_code":"4.0",
    "gn:asciiname":"Mumtazabad",
    "gn:country_code":"PK",
    "gn:dem":148,
    "gn:feature_class":"P",
    "gn:feature_code":"PPL",
    "gn:name":"Mumtazabad",
    "gn:population":0,
    "gn:timezone":"Asia/Karachi",
    "iso:country":"PK",
    "name:fas_x_preferred":[
        "\u0645\u0645\u062a\u0627\u0632\u0622\u0628\u0627\u062f"
    ],
    "name:urd_x_preferred":[
        "\u0645\u0645\u062a\u0627\u0632 \u0622\u0628\u0627\u062f"
    ],
    "wof:name":"Mumtazabad",
    "wof:placetype":"locality"
},
  "geometry": {"coordinates":[72.35436,30.61923],"type":"Point"}
}