{
  "type": "Feature",
  "properties": {
    "gn:admin1_code":"5.0",
    "gn:asciiname":"Goth Nur Muhammad Panhwar",
    "gn:country_code":"PK",
    "gn:dem":16,
    "gn:feature_class":"P",
    "gn:feature_code":"PPL",
    "gn:name":"Goth Nur Muhammad Panhwar",
    "gn:population":0,
    "gn:timezone":"Asia/Karachi",
    "iso:country":"PK",
    "wof:name":"Goth Nur Muhammad Panhwar",
    "wof:placetype":"locality"
},
  "geometry": {"coordinates":[69.36351999999999,25.61761],"type":"Point"}
}