{
  "type": "Feature",
  "properties": {
    "gn:admin1_code":"4.0",
    "gn:asciiname":"Nai Abadi",
    "gn:country_code":"PK",
    "gn:dem":250,
    "gn:feature_class":"P",
    "gn:feature_code":"PPL",
    "gn:name":"Nai Abadi",
    "gn:population":0,
    "gn:timezone":"Asia/Karachi",
    "iso:country":"PK",
    "wof:name":"Nai Abadi",
    "wof:placetype":"locality"
},
  "geometry": {"coordinates":[73.76982,32.89118],"type":"Point"}
}