{
  "type": "Feature",
  "properties": {
    "gn:admin1_code":"3.0",
    "gn:asciiname":"Sherdil Kili",
    "gn:country_code":"PK",
    "gn:dem":333,
    "gn:feature_class":"P",
    "gn:feature_code":"PPL",
    "gn:name":"Sherdil Kili",
    "gn:population":0,
    "gn:timezone":"Asia/Karachi",
    "iso:country":"PK",
    "name:und_x_variant":[
        "Ghilji Kili"
    ],
    "wof:name":"Sherdil Kili",
    "wof:placetype":"locality"
},
  "geometry": {"coordinates":[71.47273,34.12426],"type":"Point"}
}