{
  "type": "Feature",
  "properties": {
    "gn:admin1_code":"2.0",
    "gn:asciiname":"Khuddi Abdul Majid",
    "gn:country_code":"PK",
    "gn:dem":1866,
    "gn:feature_class":"P",
    "gn:feature_code":"PPL",
    "gn:name":"Khuddi Abdul Majid",
    "gn:population":0,
    "gn:timezone":"Asia/Karachi",
    "iso:country":"PK",
    "wof:name":"Khuddi Abdul Majid",
    "wof:placetype":"locality"
},
  "geometry": {"coordinates":[66.76334,28.77348],"type":"Point"}
}