{
  "type": "Feature",
  "properties": {
    "gn:admin1_code":"5",
    "gn:asciiname":"Jamat Samu",
    "gn:country_code":"PK",
    "gn:dem":74,
    "gn:feature_class":"P",
    "gn:feature_code":"PPL",
    "gn:name":"Jamat Samu",
    "gn:population":0,
    "gn:timezone":"Asia/Karachi",
    "iso:country":"PK",
    "wof:name":"Jamat Samu",
    "wof:placetype":"locality"
},
  "geometry": {"coordinates":[69.57680999999999,28.08939],"type":"Point"}
}