{
  "type": "Feature",
  "properties": {
    "gn:admin1_code":"3.0",
    "gn:asciiname":"Ghaziabad",
    "gn:country_code":"PK",
    "gn:dem":488,
    "gn:feature_class":"P",
    "gn:feature_code":"PPL",
    "gn:name":"Ghaziabad",
    "gn:population":0,
    "gn:timezone":"Asia/Karachi",
    "iso:country":"PK",
    "name:ceb_x_preferred":[
        "Ghaziabad"
    ],
    "name:nld_x_preferred":[
        "Ghaziabad"
    ],
    "name:nor_x_preferred":[
        "Ghaziabad"
    ],
    "name:pol_x_preferred":[
        "Ghaziabad"
    ],
    "name:pus_x_preferred":[
        "\u063a\u0627\u0632\u064a \u0627\u0628\u0627\u062f"
    ],
    "name:swe_x_preferred":[
        "Ghaziabad"
    ],
    "name:ukr_x_preferred":[
        "\u0490\u0430\u0437\u0456\u0430\u0431\u0430\u0434"
    ],
    "wof:name":"Ghaziabad",
    "wof:placetype":"locality"
},
  "geometry": {"coordinates":[71.54791,33.80101],"type":"Point"}
}