{
  "type": "Feature",
  "properties": {
    "gn:admin1_code":"01",
    "gn:asciiname":"Warza",
    "gn:country_code":"PK",
    "gn:dem":1718,
    "gn:feature_class":"P",
    "gn:feature_code":"PPL",
    "gn:name":"Warza",
    "gn:population":0,
    "gn:timezone":"Asia/Karachi",
    "iso:country":"PK",
    "name:bak_x_preferred":[
        "\u0412\u0430\u0440\u0446\u0430"
    ],
    "name:ceb_x_preferred":[
        "Warza"
    ],
    "name:deu_x_preferred":[
        "Warza"
    ],
    "name:epo_x_preferred":[
        "Warza"
    ],
    "name:eus_x_preferred":[
        "Warza"
    ],
    "name:fas_x_preferred":[
        "\u0648\u0627\u0631\u062a\u0633\u0627"
    ],
    "name:fra_x_preferred":[
        "Warza"
    ],
    "name:hun_x_preferred":[
        "Warza"
    ],
    "name:ita_x_preferred":[
        "Warza"
    ],
    "name:kaz_x_preferred":[
        "\u0412\u0430\u0440\u0446\u0430"
    ],
    "name:kir_x_preferred":[
        "\u0412\u0430\u0440\u0446\u0430"
    ],
    "name:mkd_x_preferred":[
        "\u0412\u0430\u0440\u0446\u0430"
    ],
    "name:msa_x_preferred":[
        "Warza"
    ],
    "name:nld_x_preferred":[
        "Warza"
    ],
    "name:pol_x_preferred":[
        "Warza"
    ],
    "name:por_x_preferred":[
        "Warza"
    ],
    "name:ron_x_preferred":[
        "Warza"
    ],
    "name:rus_x_preferred":[
        "\u0412\u0430\u0440\u0446\u0430"
    ],
    "name:spa_x_preferred":[
        "Warza"
    ],
    "name:srp_x_preferred":[
        "\u0412\u0430\u0440\u0446\u0430"
    ],
    "name:ukr_x_preferred":[
        "\u0412\u0430\u0440\u0446\u0430"
    ],
    "name:uzb_x_preferred":[
        "Warza"
    ],
    "name:vie_x_preferred":[
        "Warza"
    ],
    "name:vol_x_preferred":[
        "Warza"
    ],
    "name:war_x_preferred":[
        "Warza"
    ],
    "name:zho_x_preferred":[
        "\u74e6\u5c14\u5bdf"
    ],
    "wof:name":"Warza",
    "wof:placetype":"locality"
},
  "geometry": {"coordinates":[69.68139000000001,32.40972],"type":"Point"}
}