{
  "type": "Feature",
  "properties": {
    "gn:admin1_code":"01",
    "gn:asciiname":"Warza",
    "gn:country_code":"PK",
    "gn:dem":1718,
    "gn:feature_class":"P",
    "gn:feature_code":"PPL",
    "gn:name":"Warza",
    "gn:population":0,
    "gn:timezone":"Asia/Karachi",
    "iso:country":"PK",
    "wof:name":"Warza",
    "wof:placetype":"locality"
},
  "geometry": {"coordinates":[69.68139000000001,32.40972],"type":"Point"}
}