{
  "type": "Feature",
  "properties": {
    "gn:admin1_code":"4",
    "gn:asciiname":"Chak Four Hundred Ninety-nine Eastern Bar",
    "gn:country_code":"PK",
    "gn:dem":147,
    "gn:feature_class":"P",
    "gn:feature_code":"PPL",
    "gn:name":"Chak Four Hundred Ninety-nine Eastern Bar",
    "gn:population":0,
    "gn:timezone":"Asia/Karachi",
    "iso:country":"PK",
    "name:und_x_variant":[
        "Chak Four Hundred Ninety-nine EB"
    ],
    "wof:name":"Chak Four Hundred Ninety-nine Eastern Bar",
    "wof:placetype":"locality"
},
  "geometry": {"coordinates":[72.63844,30.2207],"type":"Point"}
}