{
  "type": "Feature",
  "properties": {
    "gn:admin1_code":"1.0",
    "gn:asciiname":"Sarlara",
    "gn:country_code":"PK",
    "gn:dem":1153,
    "gn:feature_class":"P",
    "gn:feature_code":"PPL",
    "gn:name":"Sarlara",
    "gn:population":0,
    "gn:timezone":"Asia/Karachi",
    "iso:country":"PK",
    "name:und_x_variant":[
        "Matta"
    ],
    "wof:name":"Sarlara",
    "wof:placetype":"locality"
},
  "geometry": {"coordinates":[71.14100999999999,34.64874],"type":"Point"}
}