{
  "type": "Feature",
  "properties": {
    "gn:admin1_code":"4",
    "gn:asciiname":"Sadiqabad",
    "gn:country_code":"PK",
    "gn:dem":297,
    "gn:feature_class":"P",
    "gn:feature_code":"PPL",
    "gn:name":"Sadiqabad",
    "gn:population":0,
    "gn:timezone":"Asia/Karachi",
    "iso:country":"PK",
    "name:und_x_variant":[
        "Sadigabad",
        "Sadig\u0101b\u0101d",
        "Sadiqabad"
    ],
    "wof:name":"Sadiqabad",
    "wof:placetype":"locality"
},
  "geometry": {"coordinates":[74.04544,32.86360999999999],"type":"Point"}
}