{
  "type": "Feature",
  "properties": {
    "gn:admin1_code":"4.0",
    "gn:asciiname":"Kaliana",
    "gn:country_code":"PK",
    "gn:dem":162,
    "gn:feature_class":"P",
    "gn:feature_code":"PPL",
    "gn:name":"Kaliana",
    "gn:population":0,
    "gn:timezone":"Asia/Karachi",
    "iso:country":"PK",
    "name:und_x_variant":[
        "Kalyana",
        "Kaliana"
    ],
    "wof:name":"Kaliana",
    "wof:placetype":"locality"
},
  "geometry": {"coordinates":[73.22809000000002,30.25915],"type":"Point"}
}