{
  "type": "Feature",
  "properties": {
    "gn:admin1_code":"6",
    "gn:asciiname":"Sarnela",
    "gn:country_code":"PK",
    "gn:dem":608,
    "gn:feature_class":"P",
    "gn:feature_code":"PPL",
    "gn:name":"Sarnela",
    "gn:population":0,
    "gn:timezone":"Asia/Karachi",
    "iso:country":"PK",
    "name:und_x_variant":[
        "Sarneja"
    ],
    "wof:name":"Sarnela",
    "wof:placetype":"locality"
},
  "geometry": {"coordinates":[74.02889999999999,33.12594],"type":"Point"}
}