{
  "type": "Feature",
  "properties": {
    "gn:admin1_code":"4.0",
    "gn:asciiname":"Baseera",
    "gn:country_code":"PK",
    "gn:dem":122,
    "gn:feature_class":"P",
    "gn:feature_code":"PPL",
    "gn:name":"Baseera",
    "gn:population":0,
    "gn:timezone":"Asia/Karachi",
    "iso:country":"PK",
    "wof:name":"Baseera",
    "wof:placetype":"locality"
},
  "geometry": {"coordinates":[71.05573000000003,30.07771],"type":"Point"}
}