{
  "type": "Feature",
  "properties": {
    "gn:admin1_code":"4.0",
    "gn:asciiname":"Faridpur",
    "gn:country_code":"PK",
    "gn:dem":122,
    "gn:feature_class":"P",
    "gn:feature_code":"PPL",
    "gn:name":"Faridpur",
    "gn:population":0,
    "gn:timezone":"Asia/Karachi",
    "iso:country":"PK",
    "name:bpy_x_preferred":[
        "\u09ab\u09b0\u09bf\u09a6\u09aa\u09c1\u09b0"
    ],
    "name:ceb_x_preferred":[
        "Faridpur"
    ],
    "name:ita_x_preferred":[
        "Faridpur"
    ],
    "name:nld_x_preferred":[
        "Faridpur"
    ],
    "name:pol_x_preferred":[
        "Faridpur"
    ],
    "name:rus_x_preferred":[
        "\u0424\u0430\u0440\u0438\u0434\u043f\u0443\u0440"
    ],
    "name:swe_x_preferred":[
        "Faridpur"
    ],
    "wof:name":"Faridpur",
    "wof:placetype":"locality"
},
  "geometry": {"coordinates":[71.57004000000001,30.0465],"type":"Point"}
}