{
  "type": "Feature",
  "properties": {
    "gn:admin1_code":"2.0",
    "gn:asciiname":"Uskai",
    "gn:country_code":"PK",
    "gn:dem":2387,
    "gn:feature_class":"P",
    "gn:feature_code":"PPL",
    "gn:name":"Uskai",
    "gn:population":0,
    "gn:timezone":"Asia/Karachi",
    "iso:country":"PK",
    "name:eng_x_preferred":[
        "Uskai"
    ],
    "wof:name":"Uskai",
    "wof:placetype":"locality"
},
  "geometry": {"coordinates":[67.34914999999999,30.99498],"type":"Point"}
}