{
  "type": "Feature",
  "properties": {
    "gn:admin1_code":"02",
    "gn:asciiname":"Goth Mur Muhammad Saryan",
    "gn:country_code":"PK",
    "gn:dem":165,
    "gn:feature_class":"P",
    "gn:feature_code":"PPL",
    "gn:name":"Goth Mur Muhammad Saryan",
    "gn:population":0,
    "gn:timezone":"Asia/Karachi",
    "iso:country":"PK",
    "name:und_x_variant":[
        "Goth N\u016br Muhammad"
    ],
    "wof:name":"Goth Mur Muhammad Saryan",
    "wof:placetype":"locality"
},
  "geometry": {"coordinates":[66.24264000000001,26.35474],"type":"Point"}
}