{
  "type": "Feature",
  "properties": {
    "gn:admin1_code":"6",
    "gn:asciiname":"Nar Haji",
    "gn:country_code":"PK",
    "gn:dem":1636,
    "gn:feature_class":"P",
    "gn:feature_code":"PPL",
    "gn:name":"Nar Haji",
    "gn:population":0,
    "gn:timezone":"Asia/Kolkata",
    "iso:country":"PK",
    "wof:name":"Nar Haji",
    "wof:placetype":"locality"
},
  "geometry": {"coordinates":[73.83206,34.43319],"type":"Point"}
}