{
  "type": "Feature",
  "properties": {
    "gn:admin1_code":"4.0",
    "gn:asciiname":"Bhurari",
    "gn:country_code":"PK",
    "gn:dem":216,
    "gn:feature_class":"P",
    "gn:feature_code":"PPL",
    "gn:name":"Bhurari",
    "gn:population":0,
    "gn:timezone":"Asia/Karachi",
    "iso:country":"PK",
    "wof:name":"Bhurari",
    "wof:placetype":"locality"
},
  "geometry": {"coordinates":[74.14715,31.97135],"type":"Point"}
}