{
  "type": "Feature",
  "properties": {
    "gn:admin1_code":"4",
    "gn:asciiname":"Basti Paru Shah",
    "gn:country_code":"PK",
    "gn:dem":81,
    "gn:feature_class":"P",
    "gn:feature_code":"PPL",
    "gn:name":"Basti P\u0101ru Sh\u0101h",
    "gn:population":0,
    "gn:timezone":"Asia/Karachi",
    "iso:country":"PK",
    "wof:name":"Basti Paru Shah",
    "wof:placetype":"locality"
},
  "geometry": {"coordinates":[69.94583,28.52917],"type":"Point"}
}