{
  "type": "Feature",
  "properties": {
    "gn:admin1_code":"5.0",
    "gn:asciiname":"Reti",
    "gn:country_code":"PK",
    "gn:dem":46,
    "gn:feature_class":"P",
    "gn:feature_code":"PPL",
    "gn:name":"Reti",
    "gn:population":0,
    "gn:timezone":"Asia/Karachi",
    "iso:country":"PK",
    "name:deu_x_preferred":[
        "R\u00e9ti"
    ],
    "name:fra_x_preferred":[
        "R\u00e9ti"
    ],
    "name:hun_x_preferred":[
        "R\u00e9ti"
    ],
    "name:ita_x_preferred":[
        "Reti"
    ],
    "name:lav_x_preferred":[
        "R\u0113ti"
    ],
    "name:nld_x_preferred":[
        "Reti"
    ],
    "name:rus_x_preferred":[
        "\u0420\u0435\u0442\u0438"
    ],
    "wof:name":"Reti",
    "wof:placetype":"locality"
},
  "geometry": {"coordinates":[67.84472,27.85495],"type":"Point"}
}