{
  "type": "Feature",
  "properties": {
    "gn:admin1_code":"04",
    "gn:asciiname":"Kot Kakka",
    "gn:country_code":"PK",
    "gn:dem":217,
    "gn:feature_class":"P",
    "gn:feature_code":"PPL",
    "gn:name":"Kot Kakka",
    "gn:population":0,
    "gn:timezone":"Asia/Karachi",
    "iso:country":"PK",
    "name:und_x_variant":[
        "Kot Gahkka",
        "Kot Kakka"
    ],
    "wof:name":"Kot Kakka",
    "wof:placetype":"locality"
},
  "geometry": {"coordinates":[73.85894999999999,32.4801],"type":"Point"}
}