{
  "type": "Feature",
  "properties": {
    "gn:admin1_code":"4.0",
    "gn:asciiname":"Basti Ghulam Hussain Dadpotro",
    "gn:country_code":"PK",
    "gn:dem":96,
    "gn:feature_class":"P",
    "gn:feature_code":"PPL",
    "gn:name":"Basti Ghul\u0101m Hussain D\u0101dpotro",
    "gn:population":0,
    "gn:timezone":"Asia/Karachi",
    "iso:country":"PK",
    "wof:name":"Basti Ghulam Hussain Dadpotro",
    "wof:placetype":"locality"
},
  "geometry": {"coordinates":[70.46346,29.15252000000001],"type":"Point"}
}