{
  "type": "Feature",
  "properties": {
    "gn:admin1_code":"1.0",
    "gn:asciiname":"Khatkai Sharif",
    "gn:country_code":"PK",
    "gn:dem":376,
    "gn:feature_class":"P",
    "gn:feature_code":"PPL",
    "gn:name":"Khatkai Sharif",
    "gn:population":0,
    "gn:timezone":"Asia/Karachi",
    "iso:country":"PK",
    "name:und_x_variant":[
        "Khatki"
    ],
    "wof:name":"Khatkai Sharif",
    "wof:placetype":"locality"
},
  "geometry": {"coordinates":[71.4175,34.20277],"type":"Point"}
}