{
  "type": "Feature",
  "properties": {
    "gn:admin1_code":"4",
    "gn:asciiname":"Sonara Garwanwala",
    "gn:country_code":"PK",
    "gn:dem":168,
    "gn:feature_class":"P",
    "gn:feature_code":"PPL",
    "gn:name":"Sonara Garw\u0101nw\u0101la",
    "gn:population":0,
    "gn:timezone":"Asia/Karachi",
    "iso:country":"PK",
    "wof:name":"Sonara Garwanwala",
    "wof:placetype":"locality"
},
  "geometry": {"coordinates":[71.12361,31.52639000000001],"type":"Point"}
}