{
  "type": "Feature",
  "properties": {
    "gn:admin1_code":"6",
    "gn:asciiname":"Dangar",
    "gn:country_code":"PK",
    "gn:dem":2295,
    "gn:feature_class":"P",
    "gn:feature_code":"PPL",
    "gn:name":"Dangar",
    "gn:population":0,
    "gn:timezone":"Asia/Karachi",
    "iso:country":"PK",
    "name:ceb_x_preferred":[
        "Dangar"
    ],
    "name:fra_x_preferred":[
        "Dangar"
    ],
    "name:swe_x_preferred":[
        "Dangar"
    ],
    "name:und_x_variant":[
        "Dangar Baihk"
    ],
    "wof:name":"Dangar",
    "wof:placetype":"locality"
},
  "geometry": {"coordinates":[74.16861999999998,34.73733],"type":"Point"}
}