{
  "type": "Feature",
  "properties": {
    "gn:admin1_code":"4",
    "gn:asciiname":"Bohriwala Gurha",
    "gn:country_code":"PK",
    "gn:dem":288,
    "gn:feature_class":"P",
    "gn:feature_code":"PPL",
    "gn:name":"Bohriwala Gurha",
    "gn:population":0,
    "gn:timezone":"Asia/Karachi",
    "iso:country":"PK",
    "name:und_x_variant":[
        "Buriw\u0101la Gora"
    ],
    "wof:name":"Bohriwala Gurha",
    "wof:placetype":"locality"
},
  "geometry": {"coordinates":[73.9105,32.97188],"type":"Point"}
}