{
  "type": "Feature",
  "properties": {
    "gn:admin1_code":"3",
    "gn:asciiname":"Shahinwar Kishmar",
    "gn:country_code":"PK",
    "gn:dem":3266,
    "gn:feature_class":"P",
    "gn:feature_code":"PPL",
    "gn:name":"Shahinwar Kishmar",
    "gn:population":0,
    "gn:timezone":"Asia/Karachi",
    "iso:country":"PK",
    "name:eng_x_preferred":[
        "Shahinwar Kishmar"
    ],
    "wof:name":"Shahinwar Kishmar",
    "wof:placetype":"locality"
},
  "geometry": {"coordinates":[71.58975,35.95756],"type":"Point"}
}