{
  "type": "Feature",
  "properties": {
    "gn:admin1_code":"4.0",
    "gn:asciiname":"Chak Fifteen Ghagh",
    "gn:country_code":"PK",
    "gn:dem":140,
    "gn:feature_class":"P",
    "gn:feature_code":"PPL",
    "gn:name":"Chak Fifteen Ghagh",
    "gn:population":0,
    "gn:timezone":"Asia/Karachi",
    "iso:country":"PK",
    "name:und_x_variant":[
        "Chak Fifteen Gagh"
    ],
    "wof:name":"Chak Fifteen Ghagh",
    "wof:placetype":"locality"
},
  "geometry": {"coordinates":[72.03076999999998,30.67949],"type":"Point"}
}