{
  "type": "Feature",
  "properties": {
    "iso:country":"PK",
    "name:dut_x_preferred":[
        "Matli"
    ],
    "name:eng_x_preferred":[
        "Matli"
    ],
    "name:spa_x_preferred":[
        "Matli"
    ],
    "name:urd_x_preferred":[
        "\u0645\u0627\u062a\u0644\u06cc"
    ],
    "qs:gn_country":"PK",
    "qs:gn_fcode":"PPL",
    "qs:gn_pop":50398,
    "qs:name":"Matli",
    "qs:name_adm0":"Pakistan",
    "qs:name_adm1":"Sindh",
    "qs:photos":0,
    "qs:photos_1k":0,
    "qs:photos_9k":0,
    "qs:photos_9r":0,
    "qs:photos_all":0,
    "qs:photos_sr":0,
    "qs:placetype":"Town",
    "qs:pop_sr":"8",
    "qs:woe_adm0":23424922,
    "wd:wordcount":319,
    "wof:name":"Matli",
    "wof:placetype":"locality",
    "wof:population":50398
},
  "geometry": {"coordinates":[68.65568,25.04312],"type":"Point"}
}