{
  "type": "Feature",
  "properties": {
    "gn:admin1_code":"03",
    "gn:asciiname":"Torunai",
    "gn:country_code":"PK",
    "gn:dem":1173,
    "gn:feature_class":"P",
    "gn:feature_code":"PPL",
    "gn:name":"Torunai",
    "gn:population":0,
    "gn:timezone":"Asia/Karachi",
    "iso:country":"PK",
    "wof:name":"Torunai",
    "wof:placetype":"locality"
},
  "geometry": {"coordinates":[71.98631,34.83201],"type":"Point"}
}