{
  "type": "Feature",
  "properties": {
    "gn:admin1_code":"6",
    "gn:asciiname":"Takia Waris",
    "gn:country_code":"PK",
    "gn:dem":1154,
    "gn:feature_class":"P",
    "gn:feature_code":"PPL",
    "gn:name":"Takia Waris",
    "gn:population":0,
    "gn:timezone":"Asia/Karachi",
    "iso:country":"PK",
    "wof:name":"Takia Waris",
    "wof:placetype":"locality"
},
  "geometry": {"coordinates":[73.53755,34.44172],"type":"Point"}
}