{
  "type": "Feature",
  "properties": {
    "gn:admin1_code":"2.0",
    "gn:asciiname":"Kili Malik Amir",
    "gn:country_code":"PK",
    "gn:dem":2100,
    "gn:feature_class":"P",
    "gn:feature_code":"PPL",
    "gn:name":"Kili Malik Amir",
    "gn:population":0,
    "gn:timezone":"Asia/Karachi",
    "iso:country":"PK",
    "wof:name":"Kili Malik Amir",
    "wof:placetype":"locality"
},
  "geometry": {"coordinates":[68.33414,31.6792],"type":"Point"}
}