{
  "type": "Feature",
  "properties": {
    "gn:admin1_code":"2.0",
    "gn:asciiname":"Malia Kili",
    "gn:country_code":"PK",
    "gn:dem":1286,
    "gn:feature_class":"P",
    "gn:feature_code":"PPL",
    "gn:name":"Malia Kili",
    "gn:population":0,
    "gn:timezone":"Asia/Karachi",
    "iso:country":"PK",
    "wof:name":"Malia Kili",
    "wof:placetype":"locality"
},
  "geometry": {"coordinates":[67.95578,30.19279],"type":"Point"}
}