{
  "type": "Feature",
  "properties": {
    "gn:admin1_code":"2.0",
    "gn:asciiname":"Khadarzal",
    "gn:country_code":"PK",
    "gn:dem":1563,
    "gn:feature_class":"P",
    "gn:feature_code":"PPL",
    "gn:name":"Khadarzal",
    "gn:population":0,
    "gn:timezone":"Asia/Karachi",
    "iso:country":"PK",
    "name:und_x_variant":[
        "Khadarzai"
    ],
    "wof:name":"Khadarzal",
    "wof:placetype":"locality"
},
  "geometry": {"coordinates":[66.98031,30.38708],"type":"Point"}
}