{
  "type": "Feature",
  "properties": {
    "gn:admin1_code":"2.0",
    "gn:asciiname":"Kili Mola Fateh Khan",
    "gn:country_code":"PK",
    "gn:dem":2046,
    "gn:feature_class":"P",
    "gn:feature_code":"PPL",
    "gn:name":"Kili Mola Fateh Khan",
    "gn:population":0,
    "gn:timezone":"Asia/Karachi",
    "iso:country":"PK",
    "name:und_x_variant":[
        "Kili Mulla F\u0101teh Muhammad"
    ],
    "wof:name":"Kili Mola Fateh Khan",
    "wof:placetype":"locality"
},
  "geometry": {"coordinates":[68.89202,31.40165],"type":"Point"}
}