{
  "type": "Feature",
  "properties": {
    "gn:admin1_code":"4",
    "gn:asciiname":"Hafizdbad",
    "gn:country_code":"PK",
    "gn:dem":198,
    "gn:feature_class":"P",
    "gn:feature_code":"PPL",
    "gn:name":"Hafizdbad",
    "gn:population":0,
    "gn:timezone":"Asia/Karachi",
    "iso:country":"PK",
    "name:und_x_variant":[
        "H\u0101fiz\u0101bad"
    ],
    "wof:name":"Hafizdbad",
    "wof:placetype":"locality"
},
  "geometry": {"coordinates":[73.07455,32.23096],"type":"Point"}
}