{
  "type": "Feature",
  "properties": {
    "gn:admin1_code":"2",
    "gn:asciiname":"Gehwargari",
    "gn:country_code":"PK",
    "gn:dem":106,
    "gn:feature_class":"P",
    "gn:feature_code":"PPL",
    "gn:name":"Gehwargari",
    "gn:population":0,
    "gn:timezone":"Asia/Karachi",
    "iso:country":"PK",
    "name:und_x_variant":[
        "Dosa"
    ],
    "wof:name":"Gehwargari",
    "wof:placetype":"locality"
},
  "geometry": {"coordinates":[67.90215000000001,29.23286],"type":"Point"}
}