{
  "type": "Feature",
  "properties": {
    "gn:admin1_code":"4.0",
    "gn:asciiname":"Duman",
    "gn:country_code":"PK",
    "gn:dem":428,
    "gn:feature_class":"P",
    "gn:feature_code":"PPL",
    "gn:name":"Duman",
    "gn:population":0,
    "gn:timezone":"Asia/Karachi",
    "iso:country":"PK",
    "name:deu_x_preferred":[
        "Duman"
    ],
    "name:und_x_variant":[
        "Dhumman"
    ],
    "wof:name":"Duman",
    "wof:placetype":"locality"
},
  "geometry": {"coordinates":[73.07855000000001,32.92649],"type":"Point"}
}