{
  "type": "Feature",
  "properties": {
    "gn:admin1_code":"3.0",
    "gn:asciiname":"Bamma",
    "gn:country_code":"PK",
    "gn:dem":470,
    "gn:feature_class":"P",
    "gn:feature_code":"PPL",
    "gn:name":"Bamma",
    "gn:population":0,
    "gn:timezone":"Asia/Karachi",
    "iso:country":"PK",
    "name:und_x_variant":[
        "Baman",
        "Bamma"
    ],
    "wof:name":"Bamma",
    "wof:placetype":"locality"
},
  "geometry": {"coordinates":[71.37376999999999,33.5295],"type":"Point"}
}