{
  "type": "Feature",
  "properties": {
    "gn:admin1_code":"5",
    "gn:asciiname":"Masti Khan",
    "gn:country_code":"PK",
    "gn:dem":66,
    "gn:feature_class":"P",
    "gn:feature_code":"PPL",
    "gn:name":"Masti Khan",
    "gn:population":0,
    "gn:timezone":"Asia/Karachi",
    "iso:country":"PK",
    "wof:name":"Masti Khan",
    "wof:placetype":"locality"
},
  "geometry": {"coordinates":[68.71666999999999,27.98333],"type":"Point"}
}