{
  "type": "Feature",
  "properties": {
    "gn:admin1_code":"4.0",
    "gn:asciiname":"Palot Gujarwala",
    "gn:country_code":"PK",
    "gn:dem":484,
    "gn:feature_class":"P",
    "gn:feature_code":"PPL",
    "gn:name":"Palot Gujarwala",
    "gn:population":0,
    "gn:timezone":"Asia/Karachi",
    "iso:country":"PK",
    "wof:name":"Palot Gujarwala",
    "wof:placetype":"locality"
},
  "geometry": {"coordinates":[72.7281,33.69375],"type":"Point"}
}