{
  "type": "Feature",
  "properties": {
    "gn:admin1_code":"5.0",
    "gn:asciiname":"Chatrio",
    "gn:country_code":"PK",
    "gn:dem":97,
    "gn:feature_class":"P",
    "gn:feature_code":"PPL",
    "gn:name":"Chatrio",
    "gn:population":0,
    "gn:timezone":"Asia/Karachi",
    "iso:country":"PK",
    "wof:name":"Chatrio",
    "wof:placetype":"locality"
},
  "geometry": {"coordinates":[70.29023000000001,25.28721],"type":"Point"}
}