{
  "type": "Feature",
  "properties": {
    "gn:admin1_code":"05",
    "gn:asciiname":"Goth Zer Pir",
    "gn:country_code":"PK",
    "gn:dem":27,
    "gn:feature_class":"P",
    "gn:feature_code":"PPL",
    "gn:name":"Goth Zer Pir",
    "gn:population":0,
    "gn:timezone":"Asia/Karachi",
    "iso:country":"PK",
    "name:eng_x_preferred":[
        "Zer P\u012br"
    ],
    "name:und_x_variant":[
        "Zerp\u012br",
        "Goth Zer Pir"
    ],
    "wof:name":"Goth Zer Pir",
    "wof:placetype":"locality"
},
  "geometry": {"coordinates":[68.47072,25.95498],"type":"Point"}
}