{
  "type": "Feature",
  "properties": {
    "gn:admin1_code":"6",
    "gn:asciiname":"Urni",
    "gn:country_code":"PK",
    "gn:dem":2722,
    "gn:feature_class":"P",
    "gn:feature_code":"PPL",
    "gn:name":"Urni",
    "gn:population":0,
    "gn:timezone":"Asia/Karachi",
    "iso:country":"PK",
    "wof:name":"Urni",
    "wof:placetype":"locality"
},
  "geometry": {"coordinates":[73.89648000000003,34.21043],"type":"Point"}
}