{
  "type": "Feature",
  "properties": {
    "gn:admin1_code":"04",
    "gn:asciiname":"Chak Three Hundred Eighty-nine Gugera Branch",
    "gn:country_code":"PK",
    "gn:dem":173,
    "gn:feature_class":"P",
    "gn:feature_code":"PPL",
    "gn:name":"Chak Three Hundred Eighty-nine Gugera Branch",
    "gn:population":0,
    "gn:timezone":"Asia/Karachi",
    "iso:country":"PK",
    "name:und_x_variant":[
        "S\u0101lehpur"
    ],
    "wof:name":"Chak Three Hundred Eighty-nine Gugera Branch",
    "wof:placetype":"locality"
},
  "geometry": {"coordinates":[72.95389,31.1054],"type":"Point"}
}