{
  "type": "Feature",
  "properties": {
    "gn:admin1_code":"2",
    "gn:asciiname":"Muhammad Khan",
    "gn:country_code":"PK",
    "gn:dem":1777,
    "gn:feature_class":"P",
    "gn:feature_code":"PPL",
    "gn:name":"Muhammad Khan",
    "gn:population":0,
    "gn:timezone":"Asia/Karachi",
    "iso:country":"PK",
    "wof:name":"Muhammad Khan",
    "wof:placetype":"locality"
},
  "geometry": {"coordinates":[67.04299,29.93906],"type":"Point"}
}