{
  "type": "Feature",
  "properties": {
    "gn:admin1_code":"4.0",
    "gn:asciiname":"Chaudhry Chana",
    "gn:country_code":"PK",
    "gn:dem":228,
    "gn:feature_class":"P",
    "gn:feature_code":"PPL",
    "gn:name":"Chaudhry Chana",
    "gn:population":0,
    "gn:timezone":"Asia/Karachi",
    "iso:country":"PK",
    "name:und_x_variant":[
        "Kal\u0101n"
    ],
    "wof:name":"Chaudhry Chana",
    "wof:placetype":"locality"
},
  "geometry": {"coordinates":[74.76823,31.97501],"type":"Point"}
}