{
  "type": "Feature",
  "properties": {
    "gn:admin1_code":"02",
    "gn:asciiname":"Teznap",
    "gn:country_code":"PK",
    "gn:dem":1310,
    "gn:feature_class":"P",
    "gn:feature_code":"PPL",
    "gn:name":"Teznap",
    "gn:population":0,
    "gn:timezone":"Asia/Karachi",
    "iso:country":"PK",
    "wof:name":"Teznap",
    "wof:placetype":"locality"
},
  "geometry": {"coordinates":[63.63333000000001,29.31667],"type":"Point"}
}