{
  "type": "Feature",
  "properties": {
    "gn:admin1_code":"3",
    "gn:asciiname":"Laj Kubri",
    "gn:country_code":"PK",
    "gn:dem":1274,
    "gn:feature_class":"P",
    "gn:feature_code":"PPL",
    "gn:name":"Laj Kubri",
    "gn:population":0,
    "gn:timezone":"Asia/Karachi",
    "iso:country":"PK",
    "name:und_x_variant":[
        "Lachuprai"
    ],
    "wof:name":"Laj Kubri",
    "wof:placetype":"locality"
},
  "geometry": {"coordinates":[73.02379000000001,34.60773],"type":"Point"}
}