{
  "type": "Feature",
  "properties": {
    "gn:admin1_code":"4",
    "gn:asciiname":"Patti Nat",
    "gn:country_code":"PK",
    "gn:dem":230,
    "gn:feature_class":"P",
    "gn:feature_code":"PPL",
    "gn:name":"Patti Nat",
    "gn:population":0,
    "gn:timezone":"Asia/Karachi",
    "iso:country":"PK",
    "name:und_x_variant":[
        "Nat"
    ],
    "wof:name":"Patti Nat",
    "wof:placetype":"locality"
},
  "geometry": {"coordinates":[74.12085,32.53168],"type":"Point"}
}