{
  "type": "Feature",
  "properties": {
    "gn:admin1_code":"4",
    "gn:asciiname":"Pathanwala",
    "gn:country_code":"PK",
    "gn:dem":135,
    "gn:feature_class":"P",
    "gn:feature_code":"PPL",
    "gn:name":"Pathanwala",
    "gn:population":0,
    "gn:timezone":"Asia/Karachi",
    "iso:country":"PK",
    "name:und_x_variant":[
        "Path\u0101new\u0101la"
    ],
    "wof:name":"Pathanwala",
    "wof:placetype":"locality"
},
  "geometry": {"coordinates":[71.84789000000001,30.42056],"type":"Point"}
}