{
  "type": "Feature",
  "properties": {
    "gn:admin1_code":"4",
    "gn:asciiname":"Bastr Mokra Mastoi",
    "gn:country_code":"PK",
    "gn:dem":73,
    "gn:feature_class":"P",
    "gn:feature_code":"PPL",
    "gn:name":"Bastr Mokra Mastoi",
    "gn:population":0,
    "gn:timezone":"Asia/Karachi",
    "iso:country":"PK",
    "name:und_x_variant":[
        "Mokora Mastoi"
    ],
    "wof:name":"Bastr Mokra Mastoi",
    "wof:placetype":"locality"
},
  "geometry": {"coordinates":[69.843,28.30264],"type":"Point"}
}