{
  "type": "Feature",
  "properties": {
    "gn:admin1_code":"5",
    "gn:asciiname":"Darya Beg Mughal",
    "gn:country_code":"PK",
    "gn:dem":26,
    "gn:feature_class":"P",
    "gn:feature_code":"PPL",
    "gn:name":"Darya Beg Mughal",
    "gn:population":0,
    "gn:timezone":"Asia/Karachi",
    "iso:country":"PK",
    "name:eng_x_preferred":[
        "Darya Beg Mughal"
    ],
    "wof:name":"Darya Beg Mughal",
    "wof:placetype":"locality"
},
  "geometry": {"coordinates":[68.37979,25.4697],"type":"Point"}
}