{
  "type": "Feature",
  "properties": {
    "gn:admin1_code":"5",
    "gn:asciiname":"Rojtal",
    "gn:country_code":"PK",
    "gn:dem":31,
    "gn:feature_class":"P",
    "gn:feature_code":"PPL",
    "gn:name":"Rojtal",
    "gn:population":0,
    "gn:timezone":"Asia/Karachi",
    "iso:country":"PK",
    "name:und_x_variant":[
        "Rudd\u0101l"
    ],
    "wof:name":"Rojtal",
    "wof:placetype":"locality"
},
  "geometry": {"coordinates":[69.56211,24.87156],"type":"Point"}
}