{
  "type": "Feature",
  "properties": {
    "gn:admin1_code":"4",
    "gn:asciiname":"Sian",
    "gn:country_code":"PK",
    "gn:dem":256,
    "gn:feature_class":"P",
    "gn:feature_code":"PPL",
    "gn:name":"Sian",
    "gn:population":0,
    "gn:timezone":"Asia/Karachi",
    "iso:country":"PK",
    "wof:name":"Sian",
    "wof:placetype":"locality"
},
  "geometry": {"coordinates":[74.60625999999998,32.53078],"type":"Point"}
}