{
  "type": "Feature",
  "properties": {
    "gn:admin1_code":"4",
    "gn:asciiname":"Basti Sonak Bela",
    "gn:country_code":"PK",
    "gn:dem":103,
    "gn:feature_class":"P",
    "gn:feature_code":"PPL",
    "gn:name":"Basti Sonak Bela",
    "gn:population":0,
    "gn:timezone":"Asia/Karachi",
    "iso:country":"PK",
    "name:und_x_variant":[
        "Sonak Bela",
        "Sanak Bela",
        "Basti Sonak Bela"
    ],
    "wof:name":"Basti Sonak Bela",
    "wof:placetype":"locality"
},
  "geometry": {"coordinates":[71.08076,29.3059],"type":"Point"}
}