{
  "type": "Feature",
  "properties": {
    "gn:admin1_code":"5",
    "gn:asciiname":"Jamali",
    "gn:country_code":"PK",
    "gn:dem":10,
    "gn:feature_class":"P",
    "gn:feature_code":"PPL",
    "gn:name":"Jamali",
    "gn:population":0,
    "gn:timezone":"Asia/Karachi",
    "iso:country":"PK",
    "name:ceb_x_preferred":[
        "Jamali"
    ],
    "name:deu_x_preferred":[
        "Jamali"
    ],
    "name:fas_x_preferred":[
        "\u062c\u0645\u0627\u0644\u06cc"
    ],
    "name:fra_x_preferred":[
        "Jamali"
    ],
    "name:snd_x_preferred":[
        "\u062c\u0645\u0627\u0644\u064a"
    ],
    "name:swe_x_preferred":[
        "Jamali"
    ],
    "name:urd_x_preferred":[
        "\u062c\u0645\u0627\u0644\u06cc"
    ],
    "wof:name":"Jamali",
    "wof:placetype":"locality"
},
  "geometry": {"coordinates":[69.22194,24.96337],"type":"Point"}
}