{
  "type": "Feature",
  "properties": {
    "gn:admin1_code":"04",
    "gn:asciiname":"Ramgarh",
    "gn:country_code":"PK",
    "gn:dem":215,
    "gn:feature_class":"P",
    "gn:feature_code":"PPL",
    "gn:name":"Ramgarh",
    "gn:population":0,
    "gn:timezone":"Asia/Karachi",
    "iso:country":"PK",
    "name:cat_x_preferred":[
        "Ramgarh"
    ],
    "name:ceb_x_preferred":[
        "Ramgarh"
    ],
    "name:deu_x_preferred":[
        "Ramgarh"
    ],
    "name:eng_x_preferred":[
        "Ramgarh"
    ],
    "name:ita_x_preferred":[
        "Ramgarh"
    ],
    "name:pol_x_preferred":[
        "Ramgarh"
    ],
    "name:rus_x_preferred":[
        "\u0420\u0430\u043c\u0433\u0430\u0440\u0445"
    ],
    "name:swe_x_preferred":[
        "Ramgarh"
    ],
    "name:urd_x_preferred":[
        "\u0631\u0627\u0645 \u06af\u0691\u06be"
    ],
    "wof:name":"Ramgarh",
    "wof:placetype":"locality"
},
  "geometry": {"coordinates":[73.86306999999999,32.10195],"type":"Point"}
}