{
  "type": "Feature",
  "properties": {
    "gn:admin1_code":"5",
    "gn:asciiname":"Goth Jan Muhammad Hingoro",
    "gn:country_code":"PK",
    "gn:dem":15,
    "gn:feature_class":"P",
    "gn:feature_code":"PPL",
    "gn:name":"Goth Jan Muhammad Hingoro",
    "gn:population":0,
    "gn:timezone":"Asia/Karachi",
    "iso:country":"PK",
    "name:und_x_variant":[
        "Dulla Hingorjo"
    ],
    "wof:name":"Goth Jan Muhammad Hingoro",
    "wof:placetype":"locality"
},
  "geometry": {"coordinates":[69.38786,25.87619],"type":"Point"}
}