{
  "type": "Feature",
  "properties": {
    "gn:admin1_code":"4.0",
    "gn:asciiname":"Fatahpur",
    "gn:country_code":"PK",
    "gn:dem":201,
    "gn:feature_class":"P",
    "gn:feature_code":"PPL",
    "gn:name":"Fatahpur",
    "gn:population":0,
    "gn:timezone":"Asia/Karachi",
    "iso:country":"PK",
    "name:und_x_variant":[
        "Fatehpur"
    ],
    "wof:name":"Fatahpur",
    "wof:placetype":"locality"
},
  "geometry": {"coordinates":[73.50161999999997,32.06632],"type":"Point"}
}