{
  "type": "Feature",
  "properties": {
    "gn:admin1_code":"5",
    "gn:asciiname":"Goth Hamzo Khan Darkhan",
    "gn:country_code":"PK",
    "gn:dem":55,
    "gn:feature_class":"P",
    "gn:feature_code":"PPL",
    "gn:name":"Goth Hamzo Khan Darkhan",
    "gn:population":0,
    "gn:timezone":"Asia/Karachi",
    "iso:country":"PK",
    "name:und_x_variant":[
        "Hamza Darkhan"
    ],
    "wof:name":"Goth Hamzo Khan Darkhan",
    "wof:placetype":"locality"
},
  "geometry": {"coordinates":[68.4592,27.9079],"type":"Point"}
}