{
  "type": "Feature",
  "properties": {
    "gn:admin1_code":"2.0",
    "gn:asciiname":"Rindak",
    "gn:country_code":"PK",
    "gn:dem":1723,
    "gn:feature_class":"P",
    "gn:feature_code":"PPL",
    "gn:name":"Rindak",
    "gn:population":0,
    "gn:timezone":"Asia/Karachi",
    "iso:country":"PK",
    "wof:name":"Rindak",
    "wof:placetype":"locality"
},
  "geometry": {"coordinates":[66.77316,29.71673],"type":"Point"}
}