{
  "type": "Feature",
  "properties": {
    "gn:admin1_code":"2",
    "gn:asciiname":"Kurram Kili",
    "gn:country_code":"PK",
    "gn:dem":1405,
    "gn:feature_class":"P",
    "gn:feature_code":"PPL",
    "gn:name":"Kurram Kili",
    "gn:population":0,
    "gn:timezone":"Asia/Karachi",
    "iso:country":"PK",
    "wof:name":"Kurram Kili",
    "wof:placetype":"locality"
},
  "geometry": {"coordinates":[69.13117,30.6016],"type":"Point"}
}