{
  "type": "Feature",
  "properties": {
    "gn:admin1_code":"5.0",
    "gn:asciiname":"Ket",
    "gn:country_code":"PK",
    "gn:dem":14,
    "gn:feature_class":"P",
    "gn:feature_code":"PPL",
    "gn:name":"Ket",
    "gn:population":0,
    "gn:timezone":"Asia/Karachi",
    "iso:country":"PK",
    "name:cat_x_preferred":[
        "Ket"
    ],
    "name:ceb_x_preferred":[
        "Ket"
    ],
    "name:deu_x_preferred":[
        "Ket"
    ],
    "name:eng_x_preferred":[
        "Ket"
    ],
    "name:fin_x_preferred":[
        "Ket"
    ],
    "name:nld_x_preferred":[
        "Ket"
    ],
    "name:pol_x_preferred":[
        "Ket"
    ],
    "name:swe_x_preferred":[
        "Ket"
    ],
    "wof:name":"Ket",
    "wof:placetype":"locality"
},
  "geometry": {"coordinates":[68.1591,24.72981],"type":"Point"}
}