{
  "type": "Feature",
  "properties": {
    "gn:admin1_code":"5",
    "gn:asciiname":"Bangla",
    "gn:country_code":"PK",
    "gn:dem":11,
    "gn:feature_class":"P",
    "gn:feature_code":"PPL",
    "gn:name":"Bangla",
    "gn:population":0,
    "gn:timezone":"Asia/Karachi",
    "iso:country":"PK",
    "name:asm_x_preferred":[
        "\u09ac\u09be\u0982\u09b2\u09be"
    ],
    "name:ben_x_preferred":[
        "\u09ac\u09be\u0982\u09b2\u09be"
    ],
    "name:ceb_x_preferred":[
        "Bangla"
    ],
    "name:ita_x_preferred":[
        "Bangla"
    ],
    "name:swe_x_preferred":[
        "Bangla"
    ],
    "name:und_x_variant":[
        "Bangla P\u012br Mur\u0101d Ali"
    ],
    "wof:name":"Bangla",
    "wof:placetype":"locality"
},
  "geometry": {"coordinates":[69.20809,24.97265],"type":"Point"}
}