{
  "type": "Feature",
  "properties": {
    "gn:admin1_code":"4.0",
    "gn:asciiname":"Panj Dher Mor",
    "gn:country_code":"PK",
    "gn:dem":371,
    "gn:feature_class":"P",
    "gn:feature_code":"PPL",
    "gn:name":"Panj Dher Mor",
    "gn:population":0,
    "gn:timezone":"Asia/Karachi",
    "iso:country":"PK",
    "wof:name":"Panj Dher Mor",
    "wof:placetype":"locality"
},
  "geometry": {"coordinates":[71.98905999999999,33.18131],"type":"Point"}
}