{
  "type": "Feature",
  "properties": {
    "gn:admin1_code":"3",
    "gn:asciiname":"Lamm",
    "gn:country_code":"PK",
    "gn:dem":1515,
    "gn:feature_class":"P",
    "gn:feature_code":"PPL",
    "gn:name":"Lamm",
    "gn:population":0,
    "gn:timezone":"Asia/Karachi",
    "iso:country":"PK",
    "name:und_x_variant":[
        "Lammi"
    ],
    "wof:name":"Lamm",
    "wof:placetype":"locality"
},
  "geometry": {"coordinates":[73.10724999999999,34.66918],"type":"Point"}
}