{
  "type": "Feature",
  "properties": {
    "gn:admin1_code":"4",
    "gn:asciiname":"Chak Eighteen- Eight Right",
    "gn:country_code":"PK",
    "gn:dem":143,
    "gn:feature_class":"P",
    "gn:feature_code":"PPL",
    "gn:name":"Chak Eighteen- Eight Right",
    "gn:population":0,
    "gn:timezone":"Asia/Karachi",
    "iso:country":"PK",
    "name:und_x_variant":[
        "Chak Eighteen-Eight R",
        "Shakr\u016bda",
        "Shak\u016bra",
        "Chak Eighteen- Eight Right"
    ],
    "wof:name":"Chak Eighteen- Eight Right",
    "wof:placetype":"locality"
},
  "geometry": {"coordinates":[72.2077,30.4807],"type":"Point"}
}