{
  "type": "Feature",
  "properties": {
    "gn:admin1_code":"7.0",
    "gn:asciiname":"Atabad",
    "gn:country_code":"PK",
    "gn:dem":3738,
    "gn:feature_class":"P",
    "gn:feature_code":"PPL",
    "gn:name":"Atabad",
    "gn:population":0,
    "gn:timezone":"Asia/Karachi",
    "iso:country":"PK",
    "wof:name":"Atabad",
    "wof:placetype":"locality"
},
  "geometry": {"coordinates":[74.82921999999998,36.32552],"type":"Point"}
}