{
  "type": "Feature",
  "properties": {
    "gn:admin1_code":"7.0",
    "gn:asciiname":"Kapohan",
    "gn:country_code":"PK",
    "gn:dem":2246,
    "gn:feature_class":"P",
    "gn:feature_code":"PPL",
    "gn:name":"Kapohan",
    "gn:population":0,
    "gn:timezone":"Asia/Karachi",
    "iso:country":"PK",
    "name:und_x_variant":[
        "Kapehan"
    ],
    "wof:name":"Kapohan",
    "wof:placetype":"locality"
},
  "geometry": {"coordinates":[75.74019,35.30076],"type":"Point"}
}