{
  "type": "Feature",
  "properties": {
    "gn:admin1_code":"4",
    "gn:asciiname":"Sadwal Kalan",
    "gn:country_code":"PK",
    "gn:dem":308,
    "gn:feature_class":"P",
    "gn:feature_code":"PPL",
    "gn:name":"Sadwal Kalan",
    "gn:population":0,
    "gn:timezone":"Asia/Karachi",
    "iso:country":"PK",
    "name:und_x_variant":[
        "Badda Sadw\u0101l"
    ],
    "name:urd_x_preferred":[
        "\u0633\u0688\u0648\u0644 \u06a9\u0644\u0627\u06ba"
    ],
    "wof:name":"Sadwal Kalan",
    "wof:placetype":"locality"
},
  "geometry": {"coordinates":[74.10988,32.84147],"type":"Point"}
}