{
  "type": "Feature",
  "properties": {
    "gn:admin1_code":"3.0",
    "gn:asciiname":"Shuck Sar",
    "gn:country_code":"PK",
    "gn:dem":1833,
    "gn:feature_class":"P",
    "gn:feature_code":"PPL",
    "gn:name":"Shuck Sar",
    "gn:population":0,
    "gn:timezone":"Asia/Karachi",
    "iso:country":"PK",
    "wof:name":"Shuck Sar",
    "wof:placetype":"locality"
},
  "geometry": {"coordinates":[73.20079,35.03813],"type":"Point"}
}