{
  "type": "Feature",
  "properties": {
    "gn:admin1_code":"7.0",
    "gn:asciiname":"Falolingkish",
    "gn:country_code":"PK",
    "gn:dem":3327,
    "gn:feature_class":"P",
    "gn:feature_code":"PPL",
    "gn:name":"Falolingkish",
    "gn:population":0,
    "gn:timezone":"Asia/Karachi",
    "iso:country":"PK",
    "wof:name":"Falolingkish",
    "wof:placetype":"locality"
},
  "geometry": {"coordinates":[75.04395,36.16567],"type":"Point"}
}