{
  "type": "Feature",
  "properties": {
    "gn:admin1_code":"4.0",
    "gn:asciiname":"Chah Dambra",
    "gn:country_code":"PK",
    "gn:dem":124,
    "gn:feature_class":"P",
    "gn:feature_code":"PPL",
    "gn:name":"Chah Dambra",
    "gn:population":0,
    "gn:timezone":"Asia/Karachi",
    "iso:country":"PK",
    "name:eng_x_preferred":[
        "Dambri\u0101w\u0101la"
    ],
    "wof:name":"Chah Dambra",
    "wof:placetype":"locality"
},
  "geometry": {"coordinates":[70.62915,30.07431],"type":"Point"}
}