{
  "type": "Feature",
  "properties": {
    "gn:admin1_code":"1.0",
    "gn:asciiname":"Sheikh Dada",
    "gn:country_code":"PK",
    "gn:dem":847,
    "gn:feature_class":"P",
    "gn:feature_code":"PPL",
    "gn:name":"Sheikh Dada",
    "gn:population":0,
    "gn:timezone":"Asia/Karachi",
    "iso:country":"PK",
    "wof:name":"Sheikh Dada",
    "wof:placetype":"locality"
},
  "geometry": {"coordinates":[70.07303,32.38782],"type":"Point"}
}