{
  "type": "Feature",
  "properties": {
    "gn:admin1_code":"04",
    "gn:asciiname":"Kotli Rai Abubakr",
    "gn:country_code":"PK",
    "gn:dem":206,
    "gn:feature_class":"P",
    "gn:feature_code":"PPL",
    "gn:name":"Kotli Rai Abubakr",
    "gn:population":0,
    "gn:timezone":"Asia/Karachi",
    "iso:country":"PK",
    "name:und_x_variant":[
        "Kotli R\u0101i Abu Bakar"
    ],
    "wof:name":"Kotli Rai Abubakr",
    "wof:placetype":"locality"
},
  "geometry": {"coordinates":[74.27854000000001,31.10142],"type":"Point"}
}