{
  "type": "Feature",
  "properties": {
    "gn:admin1_code":"3.0",
    "gn:asciiname":"Gulabad",
    "gn:country_code":"PK",
    "gn:dem":376,
    "gn:feature_class":"P",
    "gn:feature_code":"PPL",
    "gn:name":"Gulabad",
    "gn:population":0,
    "gn:timezone":"Asia/Karachi",
    "iso:country":"PK",
    "name:eng_x_preferred":[
        "Guli"
    ],
    "wof:name":"Gulabad",
    "wof:placetype":"locality"
},
  "geometry": {"coordinates":[71.94515,34.36815],"type":"Point"}
}