{
  "type": "Feature",
  "properties": {
    "gn:admin1_code":"3.0",
    "gn:asciiname":"Gulabad",
    "gn:country_code":"PK",
    "gn:dem":376,
    "gn:feature_class":"P",
    "gn:feature_code":"PPL",
    "gn:name":"Gulabad",
    "gn:population":0,
    "gn:timezone":"Asia/Karachi",
    "iso:country":"PK",
    "name:azb_x_preferred":[
        "\u06af\u0648\u0644\u200c\u0622\u0628\u0627\u062f"
    ],
    "name:eng_x_preferred":[
        "Guli"
    ],
    "name:fas_x_preferred":[
        "\u06af\u0644\u200c\u0622\u0628\u0627\u062f"
    ],
    "name:kik_x_preferred":[
        "Gulobod"
    ],
    "name:rus_x_preferred":[
        "\u0413\u044e\u043b\u0430\u0431\u0430\u0434"
    ],
    "name:tur_x_preferred":[
        "G\u00fclabad"
    ],
    "name:urd_x_preferred":[
        "\u06af\u0648\u0644 \u0622\u0628\u0627\u062f"
    ],
    "name:uzb_x_preferred":[
        "Gulobod"
    ],
    "wof:name":"Gulabad",
    "wof:placetype":"locality"
},
  "geometry": {"coordinates":[71.94515,34.36815],"type":"Point"}
}