{
  "type": "Feature",
  "properties": {
    "gn:admin1_code":"3.0",
    "gn:asciiname":"Bahram Shah",
    "gn:country_code":"PK",
    "gn:dem":381,
    "gn:feature_class":"P",
    "gn:feature_code":"PPL",
    "gn:name":"Bahr\u0101m Sh\u0101h",
    "gn:population":0,
    "gn:timezone":"Asia/Karachi",
    "iso:country":"PK",
    "wof:name":"Bahram Shah",
    "wof:placetype":"locality"
},
  "geometry": {"coordinates":[70.50778000000003,32.90667],"type":"Point"}
}