{
  "type": "Feature",
  "properties": {
    "gn:admin1_code":"1",
    "gn:asciiname":"Wargoro Kas",
    "gn:country_code":"PK",
    "gn:dem":1013,
    "gn:feature_class":"P",
    "gn:feature_code":"PPL",
    "gn:name":"Wargoro Kas",
    "gn:population":0,
    "gn:timezone":"Asia/Karachi",
    "iso:country":"PK",
    "wof:name":"Wargoro Kas",
    "wof:placetype":"locality"
},
  "geometry": {"coordinates":[69.91694,32.27944],"type":"Point"}
}