{
  "type": "Feature",
  "properties": {
    "gn:admin1_code":"4",
    "gn:asciiname":"Chak One Hundred D N B",
    "gn:country_code":"PK",
    "gn:dem":106,
    "gn:feature_class":"P",
    "gn:feature_code":"PPL",
    "gn:name":"Chak One Hundred D N B",
    "gn:population":0,
    "gn:timezone":"Asia/Karachi",
    "iso:country":"PK",
    "name:und_x_variant":[
        "Chak 100 D N B"
    ],
    "wof:name":"Chak One Hundred D N B",
    "wof:placetype":"locality"
},
  "geometry": {"coordinates":[71.29281999999998,29.02681],"type":"Point"}
}