{
  "type": "Feature",
  "properties": {
    "gn:admin1_code":"3.0",
    "gn:asciiname":"Salimabad",
    "gn:country_code":"PK",
    "gn:dem":421,
    "gn:feature_class":"P",
    "gn:feature_code":"PPL",
    "gn:name":"Salimabad",
    "gn:population":0,
    "gn:timezone":"Asia/Karachi",
    "iso:country":"PK",
    "name:eng_x_preferred":[
        "Saleemab\u0101d"
    ],
    "wof:name":"Salimabad",
    "wof:placetype":"locality"
},
  "geometry": {"coordinates":[71.93293,34.44422],"type":"Point"}
}