{
  "type": "Feature",
  "properties": {
    "gn:admin1_code":"2",
    "gn:asciiname":"Alhanda Khan Jamali",
    "gn:country_code":"PK",
    "gn:dem":51,
    "gn:feature_class":"P",
    "gn:feature_code":"PPL",
    "gn:name":"Alhanda Khan Jamali",
    "gn:population":0,
    "gn:timezone":"Asia/Karachi",
    "iso:country":"PK",
    "wof:name":"Alhanda Khan Jamali",
    "wof:placetype":"locality"
},
  "geometry": {"coordinates":[67.97043000000001,28.03664],"type":"Point"}
}