{
  "type": "Feature",
  "properties": {
    "gn:admin1_code":"4",
    "gn:asciiname":"Chak One Hundred Thirty-six",
    "gn:country_code":"PK",
    "gn:dem":192,
    "gn:feature_class":"P",
    "gn:feature_code":"PPL",
    "gn:name":"Chak One Hundred Thirty-six",
    "gn:population":0,
    "gn:timezone":"Asia/Karachi",
    "iso:country":"PK",
    "name:und_x_variant":[
        "Pakrew\u0101la",
        "Bakhrew\u0101li"
    ],
    "wof:name":"Chak One Hundred Thirty-six",
    "wof:placetype":"locality"
},
  "geometry": {"coordinates":[73.18304000000001,31.67988],"type":"Point"}
}