{
  "type": "Feature",
  "properties": {
    "gn:admin1_code":"5.0",
    "gn:asciiname":"Goth Shadad",
    "gn:country_code":"PK",
    "gn:dem":102,
    "gn:feature_class":"P",
    "gn:feature_code":"PPL",
    "gn:name":"Goth Shadad",
    "gn:population":0,
    "gn:timezone":"Asia/Karachi",
    "iso:country":"PK",
    "name:und_x_variant":[
        "Goth Sh\u0101h Beg"
    ],
    "wof:name":"Goth Shadad",
    "wof:placetype":"locality"
},
  "geometry": {"coordinates":[67.09238000000001,25.13371],"type":"Point"}
}