{
  "type": "Feature",
  "properties": {
    "gn:admin1_code":"5",
    "gn:asciiname":"Golo Potho",
    "gn:country_code":"PK",
    "gn:dem":44,
    "gn:feature_class":"P",
    "gn:feature_code":"PPL",
    "gn:name":"Golo Potho",
    "gn:population":0,
    "gn:timezone":"Asia/Karachi",
    "iso:country":"PK",
    "name:und_x_variant":[
        "Ghota Pat"
    ],
    "wof:name":"Golo Potho",
    "wof:placetype":"locality"
},
  "geometry": {"coordinates":[67.97869,26.72339],"type":"Point"}
}