{
  "type": "Feature",
  "properties": {
    "gn:admin1_code":"04",
    "gn:asciiname":"Qaim Bharwana",
    "gn:country_code":"PK",
    "gn:dem":149,
    "gn:feature_class":"P",
    "gn:feature_code":"PPL",
    "gn:name":"Qaim Bharwana",
    "gn:population":0,
    "gn:timezone":"Asia/Karachi",
    "iso:country":"PK",
    "name:fas_x_preferred":[
        "\u0642\u0627\u0626\u0645 \u0628\u0647\u0631\u0648\u0627\u0646\u0647"
    ],
    "name:und_x_variant":[
        "Kaim Bharwana",
        "Q\u0101in Bharw\u0101na",
        "Qaim Bharwana"
    ],
    "name:urd_x_preferred":[
        "\u0642\u0627\u0626\u0645 \u0628\u06be\u0631\u0648\u0627\u0646\u06c1"
    ],
    "wof:name":"Qaim Bharwana",
    "wof:placetype":"locality"
},
  "geometry": {"coordinates":[72.15185,30.96259],"type":"Point"}
}