{
  "type": "Feature",
  "properties": {
    "gn:admin1_code":"4.0",
    "gn:asciiname":"Jajupur",
    "gn:country_code":"PK",
    "gn:dem":245,
    "gn:feature_class":"P",
    "gn:feature_code":"PPL",
    "gn:name":"Jajupur",
    "gn:population":0,
    "gn:timezone":"Asia/Karachi",
    "iso:country":"PK",
    "name:und_x_variant":[
        "J\u0101j\u016bpur"
    ],
    "wof:name":"Jajupur",
    "wof:placetype":"locality"
},
  "geometry": {"coordinates":[74.69258000000001,32.303],"type":"Point"}
}