{
  "type": "Feature",
  "properties": {
    "gn:admin1_code":"4",
    "gn:asciiname":"Jhok Nur Ahmadwali",
    "gn:country_code":"PK",
    "gn:dem":168,
    "gn:feature_class":"P",
    "gn:feature_code":"PPL",
    "gn:name":"Jhok Nur Ahmadwali",
    "gn:population":0,
    "gn:timezone":"Asia/Karachi",
    "iso:country":"PK",
    "wof:name":"Jhok Nur Ahmadwali",
    "wof:placetype":"locality"
},
  "geometry": {"coordinates":[70.65009999999999,31.108],"type":"Point"}
}