{
  "type": "Feature",
  "properties": {
    "gn:admin1_code":"5",
    "gn:asciiname":"Goth Wado Salaro",
    "gn:country_code":"PK",
    "gn:dem":28,
    "gn:feature_class":"P",
    "gn:feature_code":"PPL",
    "gn:name":"Goth Wado Salaro",
    "gn:population":0,
    "gn:timezone":"Asia/Karachi",
    "iso:country":"PK",
    "name:eng_x_preferred":[
        "Wado Sal\u0101ro"
    ],
    "wof:name":"Goth Wado Salaro",
    "wof:placetype":"locality"
},
  "geometry": {"coordinates":[68.44405,25.74846],"type":"Point"}
}