{
  "type": "Feature",
  "properties": {
    "gn:admin1_code":"01",
    "gn:asciiname":"Sadokai Banda",
    "gn:country_code":"PK",
    "gn:dem":1592,
    "gn:feature_class":"P",
    "gn:feature_code":"PPL",
    "gn:name":"Sadokai Banda",
    "gn:population":0,
    "gn:timezone":"Asia/Karachi",
    "iso:country":"PK",
    "name:eng_x_preferred":[
        "Sadokai Banda"
    ],
    "name:und_x_variant":[
        "Sadoki Banda"
    ],
    "wof:name":"Sadokai Banda",
    "wof:placetype":"locality"
},
  "geometry": {"coordinates":[71.57804,34.91053],"type":"Point"}
}