{
  "type": "Feature",
  "properties": {
    "gn:admin1_code":"1.0",
    "gn:asciiname":"Sheikhan Durmai",
    "gn:country_code":"PK",
    "gn:dem":677,
    "gn:feature_class":"P",
    "gn:feature_code":"PPL",
    "gn:name":"Sheikhan Durmai",
    "gn:population":0,
    "gn:timezone":"Asia/Karachi",
    "iso:country":"PK",
    "wof:name":"Sheikhan Durmai",
    "wof:placetype":"locality"
},
  "geometry": {"coordinates":[71.32113000000003,33.88614],"type":"Point"}
}