{
  "type": "Feature",
  "properties": {
    "gn:admin1_code":"3.0",
    "gn:asciiname":"Bacha Garhi",
    "gn:country_code":"PK",
    "gn:dem":328,
    "gn:feature_class":"P",
    "gn:feature_code":"PPL",
    "gn:name":"Bacha Garhi",
    "gn:population":0,
    "gn:timezone":"Asia/Karachi",
    "iso:country":"PK",
    "name:eng_x_preferred":[
        "B\u0101cha S\u0101hib Garhi"
    ],
    "wof:name":"Bacha Garhi",
    "wof:placetype":"locality"
},
  "geometry": {"coordinates":[71.63186999999998,34.22346],"type":"Point"}
}