{
  "type": "Feature",
  "properties": {
    "gn:admin1_code":"7.0",
    "gn:asciiname":"Zuri",
    "gn:country_code":"PK",
    "gn:dem":1501,
    "gn:feature_class":"P",
    "gn:feature_code":"PPL",
    "gn:name":"Zuri",
    "gn:population":0,
    "gn:timezone":"Asia/Karachi",
    "iso:country":"PK",
    "name:ceb_x_preferred":[
        "Zuri"
    ],
    "name:ita_x_preferred":[
        "Zuri"
    ],
    "name:swe_x_preferred":[
        "Zuri"
    ],
    "wof:name":"Zuri",
    "wof:placetype":"locality"
},
  "geometry": {"coordinates":[74.37692,35.88763],"type":"Point"}
}