{
  "type": "Feature",
  "properties": {
    "gn:admin1_code":"3.0",
    "gn:asciiname":"Malik Shahi",
    "gn:country_code":"PK",
    "gn:dem":374,
    "gn:feature_class":"P",
    "gn:feature_code":"PPL",
    "gn:name":"Malik Shahi",
    "gn:population":0,
    "gn:timezone":"Asia/Karachi",
    "iso:country":"PK",
    "wof:name":"Malik Shahi",
    "wof:placetype":"locality"
},
  "geometry": {"coordinates":[70.51584,32.83135],"type":"Point"}
}