{
  "type": "Feature",
  "properties": {
    "gn:admin1_code":"2.0",
    "gn:asciiname":"Garkal",
    "gn:country_code":"PK",
    "gn:dem":1130,
    "gn:feature_class":"P",
    "gn:feature_code":"PPL",
    "gn:name":"Garkal",
    "gn:population":0,
    "gn:timezone":"Asia/Karachi",
    "iso:country":"PK",
    "wof:name":"Garkal",
    "wof:placetype":"locality"
},
  "geometry": {"coordinates":[64.79470000000001,26.9416],"type":"Point"}
}