{
  "type": "Feature",
  "properties": {
    "gn:admin1_code":"1.0",
    "gn:asciiname":"Kurumb Banda",
    "gn:country_code":"PK",
    "gn:dem":716,
    "gn:feature_class":"P",
    "gn:feature_code":"PPL",
    "gn:name":"Kurumb Banda",
    "gn:population":0,
    "gn:timezone":"Asia/Karachi",
    "iso:country":"PK",
    "wof:name":"Kurumb Banda",
    "wof:placetype":"locality"
},
  "geometry": {"coordinates":[71.29007,34.27307],"type":"Point"}
}