{
  "type": "Feature",
  "properties": {
    "gn:admin1_code":"4.0",
    "gn:asciiname":"Maqbara Ghulam Muhammad",
    "gn:country_code":"PK",
    "gn:dem":170,
    "gn:feature_class":"P",
    "gn:feature_code":"PPL",
    "gn:name":"Maqbara Ghulam Muhammad",
    "gn:population":0,
    "gn:timezone":"Asia/Karachi",
    "iso:country":"PK",
    "wof:name":"Maqbara Ghulam Muhammad",
    "wof:placetype":"locality"
},
  "geometry": {"coordinates":[72.48056,31.80694],"type":"Point"}
}