{
  "type": "Feature",
  "properties": {
    "gn:admin1_code":"4",
    "gn:asciiname":"Thatta Hiran",
    "gn:country_code":"PK",
    "gn:dem":221,
    "gn:feature_class":"P",
    "gn:feature_code":"PPL",
    "gn:name":"Thatta Hiran",
    "gn:population":0,
    "gn:timezone":"Asia/Karachi",
    "iso:country":"PK",
    "name:und_x_variant":[
        "Thatta Hear"
    ],
    "wof:name":"Thatta Hiran",
    "wof:placetype":"locality"
},
  "geometry": {"coordinates":[74.03449999999999,32.20267],"type":"Point"}
}