{
  "type": "Feature",
  "properties": {
    "gn:admin1_code":"03",
    "gn:asciiname":"Kauna Ghazni Khel",
    "gn:country_code":"PK",
    "gn:dem":297,
    "gn:feature_class":"P",
    "gn:feature_code":"PPL",
    "gn:name":"Kauna Ghazni Khel",
    "gn:population":0,
    "gn:timezone":"Asia/Karachi",
    "iso:country":"PK",
    "wof:name":"Kauna Ghazni Khel",
    "wof:placetype":"locality"
},
  "geometry": {"coordinates":[70.74751999999999,32.54508],"type":"Point"}
}