{
  "type": "Feature",
  "properties": {
    "gn:admin1_code":"2.0",
    "gn:asciiname":"Yaghi",
    "gn:country_code":"PK",
    "gn:dem":2150,
    "gn:feature_class":"P",
    "gn:feature_code":"PPL",
    "gn:name":"Yaghi",
    "gn:population":0,
    "gn:timezone":"Asia/Karachi",
    "iso:country":"PK",
    "wof:name":"Yaghi",
    "wof:placetype":"locality"
},
  "geometry": {"coordinates":[66.63795,28.61134],"type":"Point"}
}