{
  "type": "Feature",
  "properties": {
    "gn:admin1_code":"5.0",
    "gn:asciiname":"Goth Nasir Balech",
    "gn:country_code":"PK",
    "gn:dem":25,
    "gn:feature_class":"P",
    "gn:feature_code":"PPL",
    "gn:name":"Goth Nasir Balech",
    "gn:population":0,
    "gn:timezone":"Asia/Karachi",
    "iso:country":"PK",
    "name:eng_x_preferred":[
        "Goth Nasir Balech"
    ],
    "wof:name":"Goth Nasir Balech",
    "wof:placetype":"locality"
},
  "geometry": {"coordinates":[68.31912,25.35901],"type":"Point"}
}