{
  "type": "Feature",
  "properties": {
    "gn:admin1_code":"4.0",
    "gn:asciiname":"Dadwala",
    "gn:country_code":"PK",
    "gn:dem":171,
    "gn:feature_class":"P",
    "gn:feature_code":"PPL",
    "gn:name":"Dadwala",
    "gn:population":0,
    "gn:timezone":"Asia/Karachi",
    "iso:country":"PK",
    "wof:name":"Dadwala",
    "wof:placetype":"locality"
},
  "geometry": {"coordinates":[71.90385000000001,31.47508],"type":"Point"}
}