{
  "type": "Feature",
  "properties": {
    "gn:admin1_code":"2.0",
    "gn:asciiname":"Mantu",
    "gn:country_code":"PK",
    "gn:dem":1964,
    "gn:feature_class":"P",
    "gn:feature_code":"PPL",
    "gn:name":"Mantu",
    "gn:population":0,
    "gn:timezone":"Asia/Karachi",
    "iso:country":"PK",
    "wof:name":"Mantu",
    "wof:placetype":"locality"
},
  "geometry": {"coordinates":[66.41034999999999,30.49407],"type":"Point"}
}