{
  "type": "Feature",
  "properties": {
    "gn:admin1_code":"3.0",
    "gn:asciiname":"Mandarra",
    "gn:country_code":"PK",
    "gn:dem":765,
    "gn:feature_class":"P",
    "gn:feature_code":"PPL",
    "gn:name":"Mandarra",
    "gn:population":0,
    "gn:timezone":"Asia/Karachi",
    "iso:country":"PK",
    "wof:name":"Mandarra",
    "wof:placetype":"locality"
},
  "geometry": {"coordinates":[72.4181,34.51528],"type":"Point"}
}