{
  "type": "Feature",
  "properties": {
    "gn:admin1_code":"3",
    "gn:asciiname":"Chobek",
    "gn:country_code":"PK",
    "gn:dem":1589,
    "gn:feature_class":"P",
    "gn:feature_code":"PPL",
    "gn:name":"Chobek",
    "gn:population":0,
    "gn:timezone":"Asia/Karachi",
    "iso:country":"PK",
    "name:eng_x_preferred":[
        "Chobek"
    ],
    "wof:name":"Chobek",
    "wof:placetype":"locality"
},
  "geometry": {"coordinates":[72.59188,35.2486],"type":"Point"}
}