{
  "type": "Feature",
  "properties": {
    "gn:admin1_code":"4",
    "gn:asciiname":"Karian",
    "gn:country_code":"PK",
    "gn:dem":168,
    "gn:feature_class":"P",
    "gn:feature_code":"PPL",
    "gn:name":"K\u0101ri\u0101n",
    "gn:population":0,
    "gn:timezone":"Asia/Karachi",
    "iso:country":"PK",
    "wof:name":"Karian",
    "wof:placetype":"locality"
},
  "geometry": {"coordinates":[73.48333000000002,30.46944],"type":"Point"}
}