{
  "type": "Feature",
  "properties": {
    "gn:admin1_code":"2",
    "gn:asciiname":"Goth Trappa",
    "gn:country_code":"PK",
    "gn:dem":10,
    "gn:feature_class":"P",
    "gn:feature_code":"PPL",
    "gn:name":"Goth Trappa",
    "gn:population":0,
    "gn:timezone":"Asia/Karachi",
    "iso:country":"PK",
    "name:eng_x_preferred":[
        "Goth Trappa"
    ],
    "wof:name":"Goth Trappa",
    "wof:placetype":"locality"
},
  "geometry": {"coordinates":[66.54161999999999,25.62715],"type":"Point"}
}