{
  "type": "Feature",
  "properties": {
    "gn:admin1_code":"3.0",
    "gn:asciiname":"Shahu",
    "gn:country_code":"PK",
    "gn:dem":2133,
    "gn:feature_class":"P",
    "gn:feature_code":"PPL",
    "gn:name":"Shahu",
    "gn:population":0,
    "gn:timezone":"Asia/Karachi",
    "iso:country":"PK",
    "wof:name":"Shahu",
    "wof:placetype":"locality"
},
  "geometry": {"coordinates":[72.60553,35.50241],"type":"Point"}
}