{
  "type": "Feature",
  "properties": {
    "gn:admin1_code":"3",
    "gn:asciiname":"Ranial",
    "gn:country_code":"PK",
    "gn:dem":865,
    "gn:feature_class":"P",
    "gn:feature_code":"PPL",
    "gn:name":"Ranial",
    "gn:population":0,
    "gn:timezone":"Asia/Karachi",
    "iso:country":"PK",
    "wof:name":"Ranial",
    "wof:placetype":"locality"
},
  "geometry": {"coordinates":[72.7974,34.89614],"type":"Point"}
}