{
  "type": "Feature",
  "properties": {
    "gn:admin1_code":"2.0",
    "gn:asciiname":"Bahindar Gar Jo Goth",
    "gn:country_code":"PK",
    "gn:dem":291,
    "gn:feature_class":"P",
    "gn:feature_code":"PPL",
    "gn:name":"Bahindar Gar Jo Goth",
    "gn:population":0,
    "gn:timezone":"Asia/Karachi",
    "iso:country":"PK",
    "name:und_x_variant":[
        "Bh\u0101ngar Jo Goth"
    ],
    "wof:name":"Bahindar Gar Jo Goth",
    "wof:placetype":"locality"
},
  "geometry": {"coordinates":[67.38611,25.85149],"type":"Point"}
}