{
  "type": "Feature",
  "properties": {
    "gn:admin1_code":"4.0",
    "gn:asciiname":"Chak Four Hundred Thirty - Six Right",
    "gn:country_code":"PK",
    "gn:dem":149,
    "gn:feature_class":"P",
    "gn:feature_code":"PPL",
    "gn:name":"Chak Four Hundred Thirty - Six Right",
    "gn:population":0,
    "gn:timezone":"Asia/Karachi",
    "iso:country":"PK",
    "name:und_x_variant":[
        "Sham\u0101li"
    ],
    "wof:name":"Chak Four Hundred Thirty - Six Right",
    "wof:placetype":"locality"
},
  "geometry": {"coordinates":[72.88035000000001,29.49709],"type":"Point"}
}