{
  "type": "Feature",
  "properties": {
    "gn:admin1_code":"01",
    "gn:asciiname":"Dag Qala",
    "gn:country_code":"PK",
    "gn:dem":688,
    "gn:feature_class":"P",
    "gn:feature_code":"PPL",
    "gn:name":"Dag Qala",
    "gn:population":0,
    "gn:timezone":"Asia/Karachi",
    "iso:country":"PK",
    "wof:name":"Dag Qala",
    "wof:placetype":"locality"
},
  "geometry": {"coordinates":[71.27273000000002,34.50348],"type":"Point"}
}