{
  "type": "Feature",
  "properties": {
    "gn:admin1_code":"3",
    "gn:asciiname":"Kandar",
    "gn:country_code":"PK",
    "gn:dem":1431,
    "gn:feature_class":"P",
    "gn:feature_code":"PPL",
    "gn:name":"Kandar",
    "gn:population":0,
    "gn:timezone":"Asia/Karachi",
    "iso:country":"PK",
    "wof:name":"Kandar",
    "wof:placetype":"locality"
},
  "geometry": {"coordinates":[73.00402,34.34376],"type":"Point"}
}