{
  "type": "Feature",
  "properties": {
    "gn:admin1_code":"4.0",
    "gn:asciiname":"Jura",
    "gn:country_code":"PK",
    "gn:dem":192,
    "gn:feature_class":"P",
    "gn:feature_code":"PPL",
    "gn:name":"Jura",
    "gn:population":0,
    "gn:timezone":"Asia/Karachi",
    "iso:country":"PK",
    "name:als_x_preferred":[
        "Jura"
    ],
    "name:ara_x_preferred":[
        "\u062c\u0648\u0631\u0627"
    ],
    "name:arg_x_preferred":[
        "Jura"
    ],
    "name:bel_x_preferred":[
        "\u042e\u0440\u0430"
    ],
    "name:ben_x_preferred":[
        "\u099c\u09c1\u09b0\u09be"
    ],
    "name:bre_x_preferred":[
        "Jura"
    ],
    "name:bul_x_preferred":[
        "\u042e\u0440\u0430"
    ],
    "name:cat_x_preferred":[
        "Jura"
    ],
    "name:ceb_x_preferred":[
        "Jura"
    ],
    "name:ces_x_preferred":[
        "Jura"
    ],
    "name:chv_x_preferred":[
        "\u042e\u0440\u0430"
    ],
    "name:cym_x_preferred":[
        "Jura"
    ],
    "name:dan_x_preferred":[
        "Jura"
    ],
    "name:deu_x_preferred":[
        "Jura"
    ],
    "name:epo_x_preferred":[
        "Jura"
    ],
    "name:est_x_preferred":[
        "Jura"
    ],
    "name:eus_x_preferred":[
        "Jura"
    ],
    "name:fas_x_preferred":[
        "\u0698\u0648\u0631\u0627"
    ],
    "name:fin_x_preferred":[
        "Jura"
    ],
    "name:fra_x_preferred":[
        "Jura"
    ],
    "name:gla_x_preferred":[
        "Jura"
    ],
    "name:glg_x_preferred":[
        "Jura"
    ],
    "name:heb_x_preferred":[
        "\u05d6'\u05d5\u05e8\u05d4"
    ],
    "name:hrv_x_preferred":[
        "Jura"
    ],
    "name:hun_x_preferred":[
        "Jura"
    ],
    "name:ind_x_preferred":[
        "Jura"
    ],
    "name:isl_x_preferred":[
        "J\u00fara"
    ],
    "name:ita_x_preferred":[
        "Jura"
    ],
    "name:jpn_x_preferred":[
        "\u30b8\u30e5\u30e9"
    ],
    "name:lav_x_preferred":[
        "Jura"
    ],
    "name:lim_x_preferred":[
        "Jura"
    ],
    "name:lmo_x_preferred":[
        "Jura"
    ],
    "name:ltz_x_preferred":[
        "Jura"
    ],
    "name:nds_x_preferred":[
        "Jura"
    ],
    "name:nld_x_preferred":[
        "Jura"
    ],
    "name:nno_x_preferred":[
        "Jura"
    ],
    "name:nor_x_preferred":[
        "Jura"
    ],
    "name:oci_x_preferred":[
        "Jura"
    ],
    "name:pol_x_preferred":[
        "Jura"
    ],
    "name:por_x_preferred":[
        "Jura"
    ],
    "name:ron_x_preferred":[
        "Jura"
    ],
    "name:rus_x_preferred":[
        "\u042e\u0440\u0430"
    ],
    "name:slk_x_preferred":[
        "Jura"
    ],
    "name:spa_x_preferred":[
        "Jura"
    ],
    "name:sqi_x_preferred":[
        "Jura"
    ],
    "name:srp_x_preferred":[
        "\u0408\u0443\u0440\u0430"
    ],
    "name:swe_x_preferred":[
        "Jura"
    ],
    "name:tur_x_preferred":[
        "Jura"
    ],
    "name:ukr_x_preferred":[
        "\u042e\u0440\u0430"
    ],
    "name:und_x_variant":[
        "Jaura",
        "Jaora"
    ],
    "name:vie_x_preferred":[
        "D\u00e3y Jura"
    ],
    "name:vie_x_variant":[
        "Jura"
    ],
    "wof:name":"Jura",
    "wof:placetype":"locality"
},
  "geometry": {"coordinates":[74.38324,31.01401],"type":"Point"}
}