{
  "type": "Feature",
  "properties": {
    "gn:admin1_code":"4.0",
    "gn:asciiname":"Jura",
    "gn:country_code":"PK",
    "gn:dem":192,
    "gn:feature_class":"P",
    "gn:feature_code":"PPL",
    "gn:name":"Jura",
    "gn:population":0,
    "gn:timezone":"Asia/Karachi",
    "iso:country":"PK",
    "name:und_x_variant":[
        "Jaura",
        "Jaora",
        "Jura"
    ],
    "wof:name":"Jura",
    "wof:placetype":"locality"
},
  "geometry": {"coordinates":[74.38324,31.01401],"type":"Point"}
}