{
  "type": "Feature",
  "properties": {
    "gn:admin1_code":"4.0",
    "gn:asciiname":"Khurram Jawaya",
    "gn:country_code":"PK",
    "gn:dem":195,
    "gn:feature_class":"P",
    "gn:feature_code":"PPL",
    "gn:name":"Khurram Jawaya",
    "gn:population":0,
    "gn:timezone":"Asia/Karachi",
    "iso:country":"PK",
    "name:und_x_variant":[
        "Khurram Jow\u0101ya"
    ],
    "wof:name":"Khurram Jawaya",
    "wof:placetype":"locality"
},
  "geometry": {"coordinates":[73.28881,32.01549],"type":"Point"}
}