{
  "type": "Feature",
  "properties": {
    "gn:admin1_code":"4",
    "gn:asciiname":"Chak Forty M",
    "gn:country_code":"PK",
    "gn:dem":123,
    "gn:feature_class":"P",
    "gn:feature_code":"PPL",
    "gn:name":"Chak Forty M",
    "gn:population":0,
    "gn:timezone":"Asia/Karachi",
    "iso:country":"PK",
    "name:und_x_variant":[
        "Chak 40 M"
    ],
    "wof:name":"Chak Forty M",
    "wof:placetype":"locality"
},
  "geometry": {"coordinates":[71.63363000000003,29.73953],"type":"Point"}
}