{
  "type": "Feature",
  "properties": {
    "gn:admin1_code":"3.0",
    "gn:asciiname":"Derai",
    "gn:country_code":"PK",
    "gn:dem":1163,
    "gn:feature_class":"P",
    "gn:feature_code":"PPL",
    "gn:name":"Derai",
    "gn:population":0,
    "gn:timezone":"Asia/Karachi",
    "iso:country":"PK",
    "name:eng_x_preferred":[
        "Derai"
    ],
    "wof:name":"Derai",
    "wof:placetype":"locality"
},
  "geometry": {"coordinates":[71.60944000000001,34.94972],"type":"Point"}
}