{
  "type": "Feature",
  "properties": {
    "gn:admin1_code":"4.0",
    "gn:asciiname":"Dhok Lohara",
    "gn:country_code":"PK",
    "gn:dem":1158,
    "gn:feature_class":"P",
    "gn:feature_code":"PPL",
    "gn:name":"Dhok Lohara",
    "gn:population":0,
    "gn:timezone":"Asia/Karachi",
    "iso:country":"PK",
    "wof:name":"Dhok Lohara",
    "wof:placetype":"locality"
},
  "geometry": {"coordinates":[73.52731999999997,33.67229],"type":"Point"}
}