{
  "type": "Feature",
  "properties": {
    "iso:country":"PK",
    "name:und_x_colloquial":[
        "Gaanji",
        "Ganji"
    ],
    "name:und_x_preferred":[
        "G\u00e5nji"
    ],
    "name:unk_x_variant":[
        "G\u00e5nji"
    ],
    "qs:gn_adm0_cc":"PK",
    "qs:gn_local":1174872,
    "qs:gn_nam_loc":"Karachi, Sindh, PK",
    "qs:gn_namadm1":"05",
    "qs:local_max":2851,
    "qs:local_sum":5348,
    "qs:localhoods":21,
    "qs:name":"G\u00e5nji",
    "qs:name_adm0":"Pakistan",
    "qs:name_adm1":"Sindh",
    "qs:name_local":"Karachi",
    "qs:photo_max":21,
    "qs:photo_sum":57,
    "qs:placetype":"Suburb",
    "qs:quad_count":4,
    "qs:woe_adm0":23424922,
    "qs:woe_adm1":2346499,
    "qs:woe_adm2":0,
    "qs:woe_lau":0,
    "qs:woe_local":2211096,
    "qs:woe_ver":"7.10.0",
    "wof:lang":[
        "unk"
    ],
    "wof:name":"G\u00e5nji",
    "wof:placetype":"neighbourhood"
},
  "geometry": {"coordinates":[66.997529,24.848602],"type":"Point"}
}