{
  "type": "Feature",
  "properties": {
    "gn:admin1_code":"4.0",
    "gn:asciiname":"Chak Seventy-four Gugera Branch",
    "gn:country_code":"PK",
    "gn:dem":184,
    "gn:feature_class":"P",
    "gn:feature_code":"PPL",
    "gn:name":"Chak Seventy-four Gugera Branch",
    "gn:population":0,
    "gn:timezone":"Asia/Karachi",
    "iso:country":"PK",
    "name:und_x_variant":[
        "Bars\u012bn",
        "Chak Seventy-Four GB",
        "Chak Seventy-four Gugera Branch"
    ],
    "wof:name":"Chak Seventy-four Gugera Branch",
    "wof:placetype":"locality"
},
  "geometry": {"coordinates":[73.18248,31.2892],"type":"Point"}
}