{
  "type": "Feature",
  "properties": {
    "gn:admin1_code":"2.0",
    "gn:asciiname":"Shermabad",
    "gn:country_code":"PK",
    "gn:dem":1581,
    "gn:feature_class":"P",
    "gn:feature_code":"PPL",
    "gn:name":"Shermabad",
    "gn:population":0,
    "gn:timezone":"Asia/Karachi",
    "iso:country":"PK",
    "wof:name":"Shermabad",
    "wof:placetype":"locality"
},
  "geometry": {"coordinates":[67.03367,30.42831],"type":"Point"}
}