{
  "type": "Feature",
  "properties": {
    "gn:admin1_code":"3.0",
    "gn:asciiname":"Garhi Mian Jan",
    "gn:country_code":"PK",
    "gn:dem":419,
    "gn:feature_class":"P",
    "gn:feature_code":"PPL",
    "gn:name":"Garhi Mian Jan",
    "gn:population":0,
    "gn:timezone":"Asia/Karachi",
    "iso:country":"PK",
    "name:und_x_variant":[
        "Garhi Mi\u0101ng\u0101n"
    ],
    "wof:name":"Garhi Mian Jan",
    "wof:placetype":"locality"
},
  "geometry": {"coordinates":[71.48784999999999,33.46348],"type":"Point"}
}