{
  "type": "Feature",
  "properties": {
    "gn:admin1_code":"03",
    "gn:asciiname":"Bara Chikho",
    "gn:country_code":"PK",
    "gn:dem":966,
    "gn:feature_class":"P",
    "gn:feature_code":"PPL",
    "gn:name":"Bara Chikho",
    "gn:population":0,
    "gn:timezone":"Asia/Karachi",
    "iso:country":"PK",
    "name:eng_x_preferred":[
        "Bar Ch\u012bkho"
    ],
    "wof:name":"Bara Chikho",
    "wof:placetype":"locality"
},
  "geometry": {"coordinates":[71.96670999999998,34.73615],"type":"Point"}
}