{
  "type": "Feature",
  "properties": {
    "gn:admin1_code":"5",
    "gn:asciiname":"Goth Jafarabad",
    "gn:country_code":"PK",
    "gn:dem":64,
    "gn:feature_class":"P",
    "gn:feature_code":"PPL",
    "gn:name":"Goth Jafarabad",
    "gn:population":0,
    "gn:timezone":"Asia/Karachi",
    "iso:country":"PK",
    "name:und_x_variant":[
        "J\u0101far\u0101b\u0101d"
    ],
    "wof:name":"Goth Jafarabad",
    "wof:placetype":"locality"
},
  "geometry": {"coordinates":[68.82004999999999,27.75176],"type":"Point"}
}