{
  "type": "Feature",
  "properties": {
    "gn:admin1_code":"4.0",
    "gn:asciiname":"Massuwala",
    "gn:country_code":"PK",
    "gn:dem":122,
    "gn:feature_class":"P",
    "gn:feature_code":"PPL",
    "gn:name":"Massuwala",
    "gn:population":0,
    "gn:timezone":"Asia/Karachi",
    "iso:country":"PK",
    "wof:name":"Massuwala",
    "wof:placetype":"locality"
},
  "geometry": {"coordinates":[71.20721999999998,30.16606],"type":"Point"}
}