{
  "type": "Feature",
  "properties": {
    "gn:admin1_code":"4",
    "gn:asciiname":"Burj Bupal",
    "gn:country_code":"PK",
    "gn:dem":178,
    "gn:feature_class":"P",
    "gn:feature_code":"PPL",
    "gn:name":"Burj Bupal",
    "gn:population":0,
    "gn:timezone":"Asia/Karachi",
    "iso:country":"PK",
    "name:und_x_variant":[
        "Burj B\u0101hbal"
    ],
    "wof:name":"Burj Bupal",
    "wof:placetype":"locality"
},
  "geometry": {"coordinates":[72.88561999999997,31.73688],"type":"Point"}
}