{
  "type": "Feature",
  "properties": {
    "gn:admin1_code":"4",
    "gn:asciiname":"Chak Fifteen Dolewala Branch",
    "gn:country_code":"PK",
    "gn:dem":198,
    "gn:feature_class":"P",
    "gn:feature_code":"PPL",
    "gn:name":"Chak Fifteen Dolewala Branch",
    "gn:population":0,
    "gn:timezone":"Asia/Karachi",
    "iso:country":"PK",
    "name:und_x_variant":[
        "Chak Fifteen DB"
    ],
    "wof:name":"Chak Fifteen Dolewala Branch",
    "wof:placetype":"locality"
},
  "geometry": {"coordinates":[71.65093,32.23862],"type":"Point"}
}