{
  "type": "Feature",
  "properties": {
    "gn:admin1_code":"2.0",
    "gn:asciiname":"Muhamad Saleha Kili",
    "gn:country_code":"PK",
    "gn:dem":477,
    "gn:feature_class":"P",
    "gn:feature_code":"PPL",
    "gn:name":"Muhamad Saleha Kili",
    "gn:population":0,
    "gn:timezone":"Asia/Karachi",
    "iso:country":"PK",
    "wof:name":"Muhamad Saleha Kili",
    "wof:placetype":"locality"
},
  "geometry": {"coordinates":[63.35232,26.31533],"type":"Point"}
}