{
  "type": "Feature",
  "properties": {
    "gn:admin1_code":"2.0",
    "gn:asciiname":"Aziz Muhammad Hotel",
    "gn:country_code":"PK",
    "gn:dem":473,
    "gn:feature_class":"P",
    "gn:feature_code":"PPL",
    "gn:name":"Aziz Muhammad Hotel",
    "gn:population":0,
    "gn:timezone":"Asia/Karachi",
    "iso:country":"PK",
    "wof:name":"Aziz Muhammad Hotel",
    "wof:placetype":"locality"
},
  "geometry": {"coordinates":[65.38363000000001,26.45439],"type":"Point"}
}