{
  "type": "Feature",
  "properties": {
    "gn:admin1_code":"4.0",
    "gn:asciiname":"Chak Three Hundred Fifty-nine Jhang Branch",
    "gn:country_code":"PK",
    "gn:dem":163,
    "gn:feature_class":"P",
    "gn:feature_code":"PPL",
    "gn:name":"Chak Three Hundred Fifty-nine Jhang Branch",
    "gn:population":0,
    "gn:timezone":"Asia/Karachi",
    "iso:country":"PK",
    "name:und_x_variant":[
        "Dhai Pai Nangal",
        "Dhepi N\u0101ngal",
        "Chak Number Three Hundred Fifty-Nine",
        "Chak Three Hundred Fifty-nine Jhang Branch",
        "Ohpi Nang\u0101l"
    ],
    "wof:name":"Chak Three Hundred Fifty-nine Jhang Branch",
    "wof:placetype":"locality"
},
  "geometry": {"coordinates":[72.55953000000002,31.16783],"type":"Point"}
}