{
  "type": "Feature",
  "properties": {
    "gn:admin1_code":"7.0",
    "gn:asciiname":"Doro",
    "gn:country_code":"PK",
    "gn:dem":2204,
    "gn:feature_class":"P",
    "gn:feature_code":"PPL",
    "gn:name":"Doro",
    "gn:population":0,
    "gn:timezone":"Asia/Karachi",
    "iso:country":"PK",
    "name:ceb_x_preferred":[
        "Doro"
    ],
    "name:dan_x_preferred":[
        "Doro"
    ],
    "name:deu_x_preferred":[
        "Doro"
    ],
    "name:fra_x_preferred":[
        "Doro"
    ],
    "name:ita_x_preferred":[
        "Doro"
    ],
    "name:nld_x_preferred":[
        "Doro"
    ],
    "name:por_x_preferred":[
        "Doro"
    ],
    "name:sco_x_preferred":[
        "Doro"
    ],
    "name:spa_x_preferred":[
        "Doro"
    ],
    "name:swe_x_preferred":[
        "Doro"
    ],
    "name:uzb_x_preferred":[
        "Doro"
    ],
    "wof:name":"Doro",
    "wof:placetype":"locality"
},
  "geometry": {"coordinates":[75.46311,35.44264000000001],"type":"Point"}
}