{
  "type": "Feature",
  "properties": {
    "gn:admin1_code":"4",
    "gn:asciiname":"Dlure",
    "gn:country_code":"PK",
    "gn:dem":260,
    "gn:feature_class":"P",
    "gn:feature_code":"PPL",
    "gn:name":"Dlure",
    "gn:population":0,
    "gn:timezone":"Asia/Karachi",
    "iso:country":"PK",
    "name:und_x_variant":[
        "Dhul",
        "Dlure"
    ],
    "wof:name":"Dlure",
    "wof:placetype":"locality"
},
  "geometry": {"coordinates":[74.63439,32.58269],"type":"Point"}
}