{
  "type": "Feature",
  "properties": {
    "gn:admin1_code":"2",
    "gn:asciiname":"Ishaqzai",
    "gn:country_code":"PK",
    "gn:dem":1868,
    "gn:feature_class":"P",
    "gn:feature_code":"PPL",
    "gn:name":"Ishaqzai",
    "gn:population":0,
    "gn:timezone":"Asia/Karachi",
    "iso:country":"PK",
    "name:und_x_variant":[
        "Shahr Faiz Muhammad"
    ],
    "wof:name":"Ishaqzai",
    "wof:placetype":"locality"
},
  "geometry": {"coordinates":[66.36206,28.99827],"type":"Point"}
}