{
  "type": "Feature",
  "properties": {
    "gn:admin1_code":"7.0",
    "gn:asciiname":"Phugach",
    "gn:country_code":"PK",
    "gn:dem":1503,
    "gn:feature_class":"P",
    "gn:feature_code":"PPL",
    "gn:name":"Phugach",
    "gn:population":0,
    "gn:timezone":"Asia/Karachi",
    "iso:country":"PK",
    "wof:name":"Phugach",
    "wof:placetype":"locality"
},
  "geometry": {"coordinates":[73.58056999999999,35.62002000000001],"type":"Point"}
}