{
  "type": "Feature",
  "properties": {
    "gn:admin1_code":"6",
    "gn:asciiname":"Tikki Nilam",
    "gn:country_code":"PK",
    "gn:dem":1759,
    "gn:feature_class":"P",
    "gn:feature_code":"PPL",
    "gn:name":"Tikki Nilam",
    "gn:population":0,
    "gn:timezone":"Asia/Kolkata",
    "iso:country":"PK",
    "name:und_x_variant":[
        "N\u012blam",
        "Nilam"
    ],
    "wof:name":"Tikki Nilam",
    "wof:placetype":"locality"
},
  "geometry": {"coordinates":[73.93998000000001,34.66103],"type":"Point"}
}