{
  "type": "Feature",
  "properties": {
    "gn:admin1_code":"2.0",
    "gn:asciiname":"Goth Jatfar Khan Lehri",
    "gn:country_code":"PK",
    "gn:dem":63,
    "gn:feature_class":"P",
    "gn:feature_code":"PPL",
    "gn:name":"Goth Jatfar Khan Lehri",
    "gn:population":0,
    "gn:timezone":"Asia/Karachi",
    "iso:country":"PK",
    "wof:name":"Goth Jatfar Khan Lehri",
    "wof:placetype":"locality"
},
  "geometry": {"coordinates":[67.88911,28.38011],"type":"Point"}
}