{
  "type": "Feature",
  "properties": {
    "gn:admin1_code":"2",
    "gn:asciiname":"Sardar Rustam Khan",
    "gn:country_code":"PK",
    "gn:dem":54,
    "gn:feature_class":"P",
    "gn:feature_code":"PPL",
    "gn:name":"Sardar Rustam Khan",
    "gn:population":0,
    "gn:timezone":"Asia/Karachi",
    "iso:country":"PK",
    "name:und_x_variant":[
        "Goth Sard\u0101r Rustam Kh\u0101n"
    ],
    "wof:name":"Sardar Rustam Khan",
    "wof:placetype":"locality"
},
  "geometry": {"coordinates":[68.06623,28.18303],"type":"Point"}
}