{
  "type": "Feature",
  "properties": {
    "gn:admin1_code":"5.0",
    "gn:asciiname":"Munshi Husain Bukhsh",
    "gn:country_code":"PK",
    "gn:dem":55,
    "gn:feature_class":"P",
    "gn:feature_code":"PPL",
    "gn:name":"Munshi Husain Bukhsh",
    "gn:population":0,
    "gn:timezone":"Asia/Karachi",
    "iso:country":"PK",
    "name:und_x_variant":[
        "Munshi Husain Bakhsh"
    ],
    "wof:name":"Munshi Husain Bukhsh",
    "wof:placetype":"locality"
},
  "geometry": {"coordinates":[68.6536,27.40674000000001],"type":"Point"}
}