{
  "type": "Feature",
  "properties": {
    "gn:admin1_code":"4.0",
    "gn:asciiname":"Jattalwala",
    "gn:country_code":"PK",
    "gn:dem":99,
    "gn:feature_class":"P",
    "gn:feature_code":"PPL",
    "gn:name":"Jattalw\u0101la",
    "gn:population":0,
    "gn:timezone":"Asia/Karachi",
    "iso:country":"PK",
    "name:und_x_variant":[
        "Haidarw\u0101la"
    ],
    "wof:name":"Jattalwala",
    "wof:placetype":"locality"
},
  "geometry": {"coordinates":[70.78072,29.3335],"type":"Point"}
}