{
  "type": "Feature",
  "properties": {
    "gn:admin1_code":"2.0",
    "gn:asciiname":"Haji Alu",
    "gn:country_code":"PK",
    "gn:dem":694,
    "gn:feature_class":"P",
    "gn:feature_code":"PPL",
    "gn:name":"Haji Alu",
    "gn:population":0,
    "gn:timezone":"Asia/Karachi",
    "iso:country":"PK",
    "wof:name":"Haji Alu",
    "wof:placetype":"locality"
},
  "geometry": {"coordinates":[66.63330999999999,26.35819],"type":"Point"}
}