{
  "type": "Feature",
  "properties": {
    "gn:admin1_code":"5.0",
    "gn:asciiname":"Goth Dhani Bakhsh Ganghan",
    "gn:country_code":"PK",
    "gn:dem":172,
    "gn:feature_class":"P",
    "gn:feature_code":"PPL",
    "gn:name":"Goth Dhani Bakhsh Ganghan",
    "gn:population":0,
    "gn:timezone":"Asia/Karachi",
    "iso:country":"PK",
    "name:und_x_variant":[
        "Goth G\u0101ngan"
    ],
    "wof:name":"Goth Dhani Bakhsh Ganghan",
    "wof:placetype":"locality"
},
  "geometry": {"coordinates":[67.80034999999999,25.68556],"type":"Point"}
}