{
  "type": "Feature",
  "properties": {
    "gn:admin1_code":"4",
    "gn:asciiname":"Gul ke Kathie",
    "gn:country_code":"PK",
    "gn:dem":166,
    "gn:feature_class":"P",
    "gn:feature_code":"PPL",
    "gn:name":"Gul ke Kathie",
    "gn:population":0,
    "gn:timezone":"Asia/Karachi",
    "iso:country":"PK",
    "name:und_x_variant":[
        "Sal\u0101bat ke K\u0101thia"
    ],
    "wof:name":"Gul ke Kathie",
    "wof:placetype":"locality"
},
  "geometry": {"coordinates":[72.94844999999999,30.68664],"type":"Point"}
}