{
  "type": "Feature",
  "properties": {
    "gn:admin1_code":"4",
    "gn:asciiname":"Sahar",
    "gn:country_code":"PK",
    "gn:dem":232,
    "gn:feature_class":"P",
    "gn:feature_code":"PPL",
    "gn:name":"Sahar",
    "gn:population":0,
    "gn:timezone":"Asia/Karachi",
    "iso:country":"PK",
    "name:ceb_x_preferred":[
        "Sahar"
    ],
    "name:deu_x_preferred":[
        "Sahar"
    ],
    "name:heb_x_preferred":[
        "\u05e1\u05d4\u05e8"
    ],
    "name:rus_x_preferred":[
        "\u0421\u0430\u0445\u0430\u0440"
    ],
    "name:vep_x_preferred":[
        "Sahar"
    ],
    "wof:name":"Sahar",
    "wof:placetype":"locality"
},
  "geometry": {"coordinates":[74.56931999999998,32.22545],"type":"Point"}
}