{
  "type": "Feature",
  "properties": {
    "gn:admin1_code":"04",
    "gn:asciiname":"Jhou Mirasi",
    "gn:country_code":"PK",
    "gn:dem":122,
    "gn:feature_class":"P",
    "gn:feature_code":"PPL",
    "gn:name":"Jhou Mirasi",
    "gn:population":0,
    "gn:timezone":"Asia/Karachi",
    "iso:country":"PK",
    "name:und_x_variant":[
        "Nohanwali",
        "N\u016bhanw\u0101la",
        "Jhou Mirasi"
    ],
    "wof:name":"Jhou Mirasi",
    "wof:placetype":"locality"
},
  "geometry": {"coordinates":[70.98208000000002,29.97249],"type":"Point"}
}