{
  "type": "Feature",
  "properties": {
    "gn:admin1_code":"5.0",
    "gn:asciiname":"Goth Khan Wah",
    "gn:country_code":"PK",
    "gn:dem":57,
    "gn:feature_class":"P",
    "gn:feature_code":"PPL",
    "gn:name":"Goth Khan Wah",
    "gn:population":0,
    "gn:timezone":"Asia/Karachi",
    "iso:country":"PK",
    "name:und_x_variant":[
        "Kh\u0101nw\u0101h"
    ],
    "wof:name":"Goth Khan Wah",
    "wof:placetype":"locality"
},
  "geometry": {"coordinates":[68.34281,27.72389],"type":"Point"}
}