{
  "type": "Feature",
  "properties": {
    "gn:admin1_code":"03",
    "gn:asciiname":"Koterpan",
    "gn:country_code":"PK",
    "gn:dem":370,
    "gn:feature_class":"P",
    "gn:feature_code":"PPL",
    "gn:name":"Koterpan",
    "gn:population":0,
    "gn:timezone":"Asia/Karachi",
    "iso:country":"PK",
    "name:eng_x_preferred":[
        "Kotarp\u0101n"
    ],
    "wof:name":"Koterpan",
    "wof:placetype":"locality"
},
  "geometry": {"coordinates":[72.22073,34.31967],"type":"Point"}
}