{
  "type": "Feature",
  "properties": {
    "gn:admin1_code":"6",
    "gn:admin2_code":"005",
    "gn:asciiname":"Mohra Balidara",
    "gn:country_code":"PK",
    "gn:dem":1490,
    "gn:feature_class":"P",
    "gn:feature_code":"PPL",
    "gn:name":"Mohra Balidara",
    "gn:population":0,
    "gn:timezone":"Asia/Karachi",
    "iso:country":"PK",
    "name:und_x_variant":[
        "Mohra Boridar",
        "Mohra Barid\u0101ra"
    ],
    "wof:name":"Mohra Balidara",
    "wof:placetype":"locality"
},
  "geometry": {"coordinates":[74.16714,33.42477],"type":"Point"}
}