{
  "type": "Feature",
  "properties": {
    "gn:admin1_code":"4.0",
    "gn:asciiname":"Kumharan di Basti",
    "gn:country_code":"PK",
    "gn:dem":111,
    "gn:feature_class":"P",
    "gn:feature_code":"PPL",
    "gn:name":"Kumharan di Basti",
    "gn:population":0,
    "gn:timezone":"Asia/Karachi",
    "iso:country":"PK",
    "name:und_x_variant":[
        "Ghul\u0101mw\u0101la"
    ],
    "wof:name":"Kumharan di Basti",
    "wof:placetype":"locality"
},
  "geometry": {"coordinates":[71.25816,29.69281],"type":"Point"}
}