{
  "type": "Feature",
  "properties": {
    "gn:admin1_code":"2.0",
    "gn:asciiname":"Mulla Jumma Kili",
    "gn:country_code":"PK",
    "gn:dem":1623,
    "gn:feature_class":"P",
    "gn:feature_code":"PPL",
    "gn:name":"Mulla Jumma Kili",
    "gn:population":0,
    "gn:timezone":"Asia/Karachi",
    "iso:country":"PK",
    "wof:name":"Mulla Jumma Kili",
    "wof:placetype":"locality"
},
  "geometry": {"coordinates":[64.25725,29.44799],"type":"Point"}
}