{
  "type": "Feature",
  "properties": {
    "gn:admin1_code":"4.0",
    "gn:asciiname":"Chak Eighty-three North Panjnad",
    "gn:country_code":"PK",
    "gn:dem":86,
    "gn:feature_class":"P",
    "gn:feature_code":"PPL",
    "gn:name":"Chak Eighty-three North Panjnad",
    "gn:population":0,
    "gn:timezone":"Asia/Karachi",
    "iso:country":"PK",
    "name:und_x_variant":[
        "Chak Sam\u0101n"
    ],
    "wof:name":"Chak Eighty-three North Panjnad",
    "wof:placetype":"locality"
},
  "geometry": {"coordinates":[70.40947,28.55663],"type":"Point"}
}