{
  "type": "Feature",
  "properties": {
    "gn:admin1_code":"3.0",
    "gn:asciiname":"Nawi Garhi",
    "gn:country_code":"PK",
    "gn:dem":1188,
    "gn:feature_class":"P",
    "gn:feature_code":"PPL",
    "gn:name":"Nawi Garhi",
    "gn:population":0,
    "gn:timezone":"Asia/Karachi",
    "iso:country":"PK",
    "wof:name":"Nawi Garhi",
    "wof:placetype":"locality"
},
  "geometry": {"coordinates":[72.99664,34.5074],"type":"Point"}
}