{
  "type": "Feature",
  "properties": {
    "gn:admin1_code":"6",
    "gn:asciiname":"Jahunja",
    "gn:country_code":"PK",
    "gn:dem":332,
    "gn:feature_class":"P",
    "gn:feature_code":"PPL",
    "gn:name":"Jahunja",
    "gn:population":0,
    "gn:timezone":"Asia/Karachi",
    "iso:country":"PK",
    "name:und_x_variant":[
        "Lhunja"
    ],
    "wof:name":"Jahunja",
    "wof:placetype":"locality"
},
  "geometry": {"coordinates":[74.02014,32.9542],"type":"Point"}
}