{
  "type": "Feature",
  "properties": {
    "gn:admin1_code":"7.0",
    "gn:asciiname":"Shqmro Khun",
    "gn:country_code":"PK",
    "gn:dem":1718,
    "gn:feature_class":"P",
    "gn:feature_code":"PPL",
    "gn:name":"Shqmro Khun",
    "gn:population":0,
    "gn:timezone":"Asia/Karachi",
    "iso:country":"PK",
    "wof:name":"Shqmro Khun",
    "wof:placetype":"locality"
},
  "geometry": {"coordinates":[74.03763000000002,35.37880999999999],"type":"Point"}
}