{
  "type": "Feature",
  "properties": {
    "gn:admin1_code":"5",
    "gn:asciiname":"Abu Talib Sipio",
    "gn:country_code":"PK",
    "gn:dem":24,
    "gn:feature_class":"P",
    "gn:feature_code":"PPL",
    "gn:name":"Abu Talib Sipio",
    "gn:population":0,
    "gn:timezone":"Asia/Karachi",
    "iso:country":"PK",
    "wof:name":"Abu Talib Sipio",
    "wof:placetype":"locality"
},
  "geometry": {"coordinates":[68.52225,25.46886],"type":"Point"}
}