{
  "type": "Feature",
  "properties": {
    "gn:admin1_code":"3.0",
    "gn:asciiname":"Ayaz Khan",
    "gn:country_code":"PK",
    "gn:dem":299,
    "gn:feature_class":"P",
    "gn:feature_code":"PPL",
    "gn:name":"Ayaz Khan",
    "gn:population":0,
    "gn:timezone":"Asia/Karachi",
    "iso:country":"PK",
    "wof:name":"Ayaz Khan",
    "wof:placetype":"locality"
},
  "geometry": {"coordinates":[70.76009000000001,32.76174],"type":"Point"}
}