{
  "type": "Feature",
  "properties": {
    "gn:admin1_code":"4.0",
    "gn:asciiname":"Chak Wisao",
    "gn:country_code":"PK",
    "gn:dem":167,
    "gn:feature_class":"P",
    "gn:feature_code":"PPL",
    "gn:name":"Chak Wisao",
    "gn:population":0,
    "gn:timezone":"Asia/Karachi",
    "iso:country":"PK",
    "name:und_x_variant":[
        "Was\u0101u"
    ],
    "wof:name":"Chak Wisao",
    "wof:placetype":"locality"
},
  "geometry": {"coordinates":[73.41508,30.57883],"type":"Point"}
}