{
  "type": "Feature",
  "properties": {
    "gn:admin1_code":"04",
    "gn:asciiname":"Chak Three Hundred Five",
    "gn:country_code":"PK",
    "gn:dem":166,
    "gn:feature_class":"P",
    "gn:feature_code":"PPL",
    "gn:name":"Chak Three Hundred Five",
    "gn:population":0,
    "gn:timezone":"Asia/Karachi",
    "iso:country":"PK",
    "name:und_x_variant":[
        "Mansurw\u0101li",
        "Chak Number Three Hundred Five",
        "Chak Three Hundred Five",
        "Mass\u016brw\u0101la"
    ],
    "wof:name":"Chak Three Hundred Five",
    "wof:placetype":"locality"
},
  "geometry": {"coordinates":[72.60513,31.16314],"type":"Point"}
}