{
  "type": "Feature",
  "properties": {
    "gn:admin1_code":"05",
    "gn:asciiname":"Goth Sumco",
    "gn:country_code":"PK",
    "gn:dem":225,
    "gn:feature_class":"P",
    "gn:feature_code":"PPL",
    "gn:name":"Goth Sumco",
    "gn:population":0,
    "gn:timezone":"Asia/Karachi",
    "iso:country":"PK",
    "wof:name":"Goth Sumco",
    "wof:placetype":"locality"
},
  "geometry": {"coordinates":[67.34999999999999,25.68333],"type":"Point"}
}