{
  "type": "Feature",
  "properties": {
    "gn:admin1_code":"5",
    "gn:asciiname":"Goth Wisario Wasan",
    "gn:country_code":"PK",
    "gn:dem":21,
    "gn:feature_class":"P",
    "gn:feature_code":"PPL",
    "gn:name":"Goth Wisario Wasan",
    "gn:population":0,
    "gn:timezone":"Asia/Karachi",
    "iso:country":"PK",
    "name:und_x_variant":[
        "Goth Wis\u0101rio Wass\u0101n"
    ],
    "wof:name":"Goth Wisario Wasan",
    "wof:placetype":"locality"
},
  "geometry": {"coordinates":[68.6493,25.21073],"type":"Point"}
}