{
  "type": "Feature",
  "properties": {
    "gn:admin1_code":"4.0",
    "gn:asciiname":"Basti Badh Raibana",
    "gn:country_code":"PK",
    "gn:dem":142,
    "gn:feature_class":"P",
    "gn:feature_code":"PPL",
    "gn:name":"Basti Badh Raibana",
    "gn:population":0,
    "gn:timezone":"Asia/Karachi",
    "iso:country":"PK",
    "name:und_x_variant":[
        "Badh Rajb\u0101na"
    ],
    "wof:name":"Basti Badh Raibana",
    "wof:placetype":"locality"
},
  "geometry": {"coordinates":[72.02195,30.83921],"type":"Point"}
}