{
  "type": "Feature",
  "properties": {
    "gn:admin1_code":"6.0",
    "gn:asciiname":"Titrot",
    "gn:country_code":"PK",
    "gn:dem":1172,
    "gn:feature_class":"P",
    "gn:feature_code":"PPL",
    "gn:name":"Titrot",
    "gn:population":0,
    "gn:timezone":"Asia/Karachi",
    "iso:country":"PK",
    "wof:name":"Titrot",
    "wof:placetype":"locality"
},
  "geometry": {"coordinates":[73.64494999999999,33.96209],"type":"Point"}
}