{
  "type": "Feature",
  "properties": {
    "gn:admin1_code":"2.0",
    "gn:asciiname":"Ghaggar Khan",
    "gn:country_code":"PK",
    "gn:dem":1295,
    "gn:feature_class":"P",
    "gn:feature_code":"PPL",
    "gn:name":"Ghaggar Khan",
    "gn:population":0,
    "gn:timezone":"Asia/Karachi",
    "iso:country":"PK",
    "wof:name":"Ghaggar Khan",
    "wof:placetype":"locality"
},
  "geometry": {"coordinates":[69.91909,30.89436],"type":"Point"}
}