{
  "type": "Feature",
  "properties": {
    "gn:admin1_code":"6",
    "gn:asciiname":"Simbin",
    "gn:country_code":"PK",
    "gn:dem":711,
    "gn:feature_class":"P",
    "gn:feature_code":"PPL",
    "gn:name":"Simbin",
    "gn:population":0,
    "gn:timezone":"Asia/Karachi",
    "iso:country":"PK",
    "wof:name":"Simbin",
    "wof:placetype":"locality"
},
  "geometry": {"coordinates":[74.03329000000002,33.05789],"type":"Point"}
}