{
  "type": "Feature",
  "properties": {
    "gn:admin1_code":"4",
    "gn:asciiname":"Machhike Goraya",
    "gn:country_code":"PK",
    "gn:dem":226,
    "gn:feature_class":"P",
    "gn:feature_code":"PPL",
    "gn:name":"Machhike Goraya",
    "gn:population":0,
    "gn:timezone":"Asia/Karachi",
    "iso:country":"PK",
    "name:und_x_variant":[
        "M\u0101chh\u012bke"
    ],
    "wof:name":"Machhike Goraya",
    "wof:placetype":"locality"
},
  "geometry": {"coordinates":[74.27013000000002,32.11473],"type":"Point"}
}