{
  "type": "Feature",
  "properties": {
    "gn:admin1_code":"7.0",
    "gn:asciiname":"Khechak",
    "gn:country_code":"PK",
    "gn:dem":2141,
    "gn:feature_class":"P",
    "gn:feature_code":"PPL",
    "gn:name":"Khechak",
    "gn:population":0,
    "gn:timezone":"Asia/Karachi",
    "iso:country":"PK",
    "wof:name":"Khechak",
    "wof:placetype":"locality"
},
  "geometry": {"coordinates":[74.82664,35.41332],"type":"Point"}
}