{
  "type": "Feature",
  "properties": {
    "gn:admin1_code":"5",
    "gn:asciiname":"Ahsan Ali Shah",
    "gn:country_code":"PK",
    "gn:dem":42,
    "gn:feature_class":"P",
    "gn:feature_code":"PPL",
    "gn:name":"Ahsan Ali Shah",
    "gn:population":0,
    "gn:timezone":"Asia/Karachi",
    "iso:country":"PK",
    "wof:name":"Ahsan Ali Shah",
    "wof:placetype":"locality"
},
  "geometry": {"coordinates":[68.16053000000001,26.76315],"type":"Point"}
}