{
  "type": "Feature",
  "properties": {
    "gn:admin1_code":"2.0",
    "gn:asciiname":"Lawang Khan",
    "gn:country_code":"PK",
    "gn:dem":103,
    "gn:feature_class":"P",
    "gn:feature_code":"PPL",
    "gn:name":"Lawang Khan",
    "gn:population":0,
    "gn:timezone":"Asia/Karachi",
    "iso:country":"PK",
    "name:und_x_variant":[
        "Bangal"
    ],
    "wof:name":"Lawang Khan",
    "wof:placetype":"locality"
},
  "geometry": {"coordinates":[67.4165,28.76583],"type":"Point"}
}