{
  "type": "Feature",
  "properties": {
    "gn:admin1_code":"05",
    "gn:asciiname":"Goth Nabi Bakhsh Mastoi",
    "gn:country_code":"PK",
    "gn:dem":50,
    "gn:feature_class":"P",
    "gn:feature_code":"PPL",
    "gn:name":"Goth Nabi Bakhsh Mastoi",
    "gn:population":0,
    "gn:timezone":"Asia/Karachi",
    "iso:country":"PK",
    "name:und_x_variant":[
        "Nabi Bux Mastoi",
        "Goth Nabi Bakhsh Mastoi",
        "Nabi Bakhsh Jatoi"
    ],
    "wof:name":"Goth Nabi Bakhsh Mastoi",
    "wof:placetype":"locality"
},
  "geometry": {"coordinates":[68.01336999999999,27.77482],"type":"Point"}
}