{
  "type": "Feature",
  "properties": {
    "gn:admin1_code":"04",
    "gn:asciiname":"Nepal",
    "gn:country_code":"PK",
    "gn:dem":217,
    "gn:feature_class":"P",
    "gn:feature_code":"PPL",
    "gn:name":"Nepal",
    "gn:population":0,
    "gn:timezone":"Asia/Karachi",
    "iso:country":"PK",
    "name:und_x_variant":[
        "Nupal",
        "Rora Nep\u0101l",
        "Nepal"
    ],
    "wof:name":"Nepal",
    "wof:placetype":"locality"
},
  "geometry": {"coordinates":[74.47165,31.37156],"type":"Point"}
}