{
  "type": "Feature",
  "properties": {
    "gn:admin1_code":"4.0",
    "gn:asciiname":"Nai Basti",
    "gn:country_code":"PK",
    "gn:dem":128,
    "gn:feature_class":"P",
    "gn:feature_code":"PPL",
    "gn:name":"Nai Basti",
    "gn:population":0,
    "gn:timezone":"Asia/Karachi",
    "iso:country":"PK",
    "name:eng_x_preferred":[
        "Nai Basti"
    ],
    "wof:name":"Nai Basti",
    "wof:placetype":"locality"
},
  "geometry": {"coordinates":[71.93331999999999,29.45046],"type":"Point"}
}