{
  "type": "Feature",
  "properties": {
    "gn:admin1_code":"05",
    "gn:asciiname":"Goth Mehrab Pur",
    "gn:country_code":"PK",
    "gn:dem":54,
    "gn:feature_class":"P",
    "gn:feature_code":"PPL",
    "gn:name":"Goth Mehrab Pur",
    "gn:population":0,
    "gn:timezone":"Asia/Karachi",
    "iso:country":"PK",
    "name:und_x_variant":[
        "Mahrabpur",
        "Mihr\u0101bpur",
        "Mehr\u0101bpur",
        "Goth Mehrab Pur"
    ],
    "wof:name":"Goth Mehrab Pur",
    "wof:placetype":"locality"
},
  "geometry": {"coordinates":[68.11667,27.42262],"type":"Point"}
}