{
  "type": "Feature",
  "properties": {
    "gn:admin1_code":"2.0",
    "gn:asciiname":"Pechi Karez",
    "gn:country_code":"PK",
    "gn:dem":2256,
    "gn:feature_class":"P",
    "gn:feature_code":"PPL",
    "gn:name":"Pechi Karez",
    "gn:population":0,
    "gn:timezone":"Asia/Karachi",
    "iso:country":"PK",
    "name:und_x_variant":[
        "Skhobai",
        "P\u012bchi K\u0101rez",
        "Pechi Karez"
    ],
    "wof:name":"Pechi Karez",
    "wof:placetype":"locality"
},
  "geometry": {"coordinates":[67.66083,30.4364],"type":"Point"}
}