{
  "type": "Feature",
  "properties": {
    "gn:admin1_code":"3",
    "gn:asciiname":"Charona",
    "gn:country_code":"PK",
    "gn:dem":1446,
    "gn:feature_class":"P",
    "gn:feature_code":"PPL",
    "gn:name":"Charona",
    "gn:population":0,
    "gn:timezone":"Asia/Karachi",
    "iso:country":"PK",
    "name:und_x_variant":[
        "Chh\u0101r Kili",
        "Ch\u0101rgalai"
    ],
    "wof:name":"Charona",
    "wof:placetype":"locality"
},
  "geometry": {"coordinates":[72.74930000000001,34.32507],"type":"Point"}
}