{
  "type": "Feature",
  "properties": {
    "gn:admin1_code":"4",
    "gn:asciiname":"Chak Four Hundred Eighty-three Thal Development Authority",
    "gn:country_code":"PK",
    "gn:dem":139,
    "gn:feature_class":"P",
    "gn:feature_code":"PPL",
    "gn:name":"Chak Four Hundred Eighty-three Thal Development Authority",
    "gn:population":0,
    "gn:timezone":"Asia/Karachi",
    "iso:country":"PK",
    "name:und_x_variant":[
        "Chak Four Hundred Eighty-Three TDA",
        "Jat B\u0101ra",
        "Chak Four Hundred Eighty-three Thal Development Authority"
    ],
    "wof:name":"Chak Four Hundred Eighty-three Thal Development Authority",
    "wof:placetype":"locality"
},
  "geometry": {"coordinates":[71.46661,30.76413],"type":"Point"}
}