{
  "type": "Feature",
  "properties": {
    "gn:admin1_code":"3.0",
    "gn:asciiname":"Dilshad Kas",
    "gn:country_code":"PK",
    "gn:dem":1320,
    "gn:feature_class":"P",
    "gn:feature_code":"PPL",
    "gn:name":"Dilshad Kas",
    "gn:population":0,
    "gn:timezone":"Asia/Karachi",
    "iso:country":"PK",
    "wof:name":"Dilshad Kas",
    "wof:placetype":"locality"
},
  "geometry": {"coordinates":[71.84009,35.12436],"type":"Point"}
}