{
  "type": "Feature",
  "properties": {
    "gn:admin1_code":"4",
    "gn:asciiname":"Chak Nasir Khan",
    "gn:country_code":"PK",
    "gn:dem":170,
    "gn:feature_class":"P",
    "gn:feature_code":"PPL",
    "gn:name":"Chak Nasir Khan",
    "gn:population":0,
    "gn:timezone":"Asia/Karachi",
    "iso:country":"PK",
    "name:und_x_variant":[
        "Mahmunke N\u0101sir Kh\u0101n"
    ],
    "wof:name":"Chak Nasir Khan",
    "wof:placetype":"locality"
},
  "geometry": {"coordinates":[73.52153,30.3383],"type":"Point"}
}