{
  "type": "Feature",
  "properties": {
    "gn:admin1_code":"4",
    "gn:asciiname":"Kurnali",
    "gn:country_code":"PK",
    "gn:dem":535,
    "gn:feature_class":"P",
    "gn:feature_code":"PPL",
    "gn:name":"Kurnali",
    "gn:population":0,
    "gn:timezone":"Asia/Karachi",
    "iso:country":"PK",
    "wof:name":"Kurnali",
    "wof:placetype":"locality"
},
  "geometry": {"coordinates":[73.17751,33.2386],"type":"Point"}
}