{
  "type": "Feature",
  "properties": {
    "gn:admin1_code":"1.0",
    "gn:asciiname":"Kuna Tangai Darra",
    "gn:country_code":"PK",
    "gn:dem":999,
    "gn:feature_class":"P",
    "gn:feature_code":"PPL",
    "gn:name":"Kuna Tangai Darra",
    "gn:population":0,
    "gn:timezone":"Asia/Karachi",
    "iso:country":"PK",
    "wof:name":"Kuna Tangai Darra",
    "wof:placetype":"locality"
},
  "geometry": {"coordinates":[71.54488000000001,34.60529],"type":"Point"}
}