{
  "type": "Feature",
  "properties": {
    "gn:admin1_code":"2.0",
    "gn:asciiname":"Abdul Ramzan",
    "gn:country_code":"PK",
    "gn:dem":1618,
    "gn:feature_class":"P",
    "gn:feature_code":"PPL",
    "gn:name":"Abdul Ramzan",
    "gn:population":0,
    "gn:timezone":"Asia/Karachi",
    "iso:country":"PK",
    "wof:name":"Abdul Ramzan",
    "wof:placetype":"locality"
},
  "geometry": {"coordinates":[66.11728000000001,28.2337],"type":"Point"}
}