{
  "type": "Feature",
  "properties": {
    "gn:admin1_code":"4",
    "gn:asciiname":"Chak Thirty-five Bahawal Canal Gharib",
    "gn:country_code":"PK",
    "gn:dem":130,
    "gn:feature_class":"P",
    "gn:feature_code":"PPL",
    "gn:name":"Chak Thirty-five Bahawal Canal Gharib",
    "gn:population":0,
    "gn:timezone":"Asia/Karachi",
    "iso:country":"PK",
    "name:eng_x_preferred":[
        "Chak Thirty-five"
    ],
    "wof:name":"Chak Thirty-five Bahawal Canal Gharib",
    "wof:placetype":"locality"
},
  "geometry": {"coordinates":[71.96485,29.42209],"type":"Point"}
}