{
  "type": "Feature",
  "properties": {
    "gn:admin1_code":"04",
    "gn:asciiname":"Bana Mohra",
    "gn:country_code":"PK",
    "gn:dem":571,
    "gn:feature_class":"P",
    "gn:feature_code":"PPL",
    "gn:name":"Bana Mohra",
    "gn:population":0,
    "gn:timezone":"Asia/Karachi",
    "iso:country":"PK",
    "name:und_x_variant":[
        "Bann na Mohra"
    ],
    "wof:name":"Bana Mohra",
    "wof:placetype":"locality"
},
  "geometry": {"coordinates":[73.36973,33.46341],"type":"Point"}
}