{
  "type": "Feature",
  "properties": {
    "gn:admin1_code":"2.0",
    "gn:asciiname":"Kili Gazki",
    "gn:country_code":"PK",
    "gn:dem":1258,
    "gn:feature_class":"P",
    "gn:feature_code":"PPL",
    "gn:name":"Kili Gazki",
    "gn:population":0,
    "gn:timezone":"Asia/Karachi",
    "iso:country":"PK",
    "name:und_x_variant":[
        "Gazki"
    ],
    "wof:name":"Kili Gazki",
    "wof:placetype":"locality"
},
  "geometry": {"coordinates":[66.42381999999999,27.31807],"type":"Point"}
}