{
  "type": "Feature",
  "properties": {
    "gn:admin1_code":"4.0",
    "gn:asciiname":"Bagh Kehna",
    "gn:country_code":"PK",
    "gn:dem":194,
    "gn:feature_class":"P",
    "gn:feature_code":"PPL",
    "gn:name":"Bagh Kehna",
    "gn:population":0,
    "gn:timezone":"Asia/Karachi",
    "iso:country":"PK",
    "name:und_x_variant":[
        "B\u0101gh",
        "B\u0101gh Kohna",
        "Bagh Kehna"
    ],
    "wof:name":"Bagh Kehna",
    "wof:placetype":"locality"
},
  "geometry": {"coordinates":[73.27145,31.94359],"type":"Point"}
}