{
  "type": "Feature",
  "properties": {
    "gn:admin1_code":"4.0",
    "gn:asciiname":"Dhok Nathenwali",
    "gn:country_code":"PK",
    "gn:dem":495,
    "gn:feature_class":"P",
    "gn:feature_code":"PPL",
    "gn:name":"Dhok Nathenwali",
    "gn:population":0,
    "gn:timezone":"Asia/Karachi",
    "iso:country":"PK",
    "name:und_x_variant":[
        "Dhok Nathiw\u0101la"
    ],
    "wof:name":"Dhok Nathenwali",
    "wof:placetype":"locality"
},
  "geometry": {"coordinates":[72.53673000000001,33.39384],"type":"Point"}
}