{
  "type": "Feature",
  "properties": {
    "gn:admin1_code":"4.0",
    "gn:asciiname":"Fatehabad",
    "gn:country_code":"PK",
    "gn:dem":207,
    "gn:feature_class":"P",
    "gn:feature_code":"PPL",
    "gn:name":"Fatehabad",
    "gn:population":0,
    "gn:timezone":"Asia/Karachi",
    "iso:country":"PK",
    "name:und_x_variant":[
        "Feteh\u0101b\u0101d"
    ],
    "wof:name":"Fatehabad",
    "wof:placetype":"locality"
},
  "geometry": {"coordinates":[74.22126,31.42506],"type":"Point"}
}