{
  "type": "Feature",
  "properties": {
    "gn:admin1_code":"4.0",
    "gn:asciiname":"Fatehabad",
    "gn:country_code":"PK",
    "gn:dem":207,
    "gn:feature_class":"P",
    "gn:feature_code":"PPL",
    "gn:name":"Fatehabad",
    "gn:population":0,
    "gn:timezone":"Asia/Karachi",
    "iso:country":"PK",
    "name:ara_x_preferred":[
        "\u0641\u0627\u062a\u062d \u0623\u0628\u0627\u062f"
    ],
    "name:ben_x_preferred":[
        "\u09ab\u09a4\u09c7\u09b9\u09be\u09ac\u09be\u09a6"
    ],
    "name:deu_x_preferred":[
        "Fatehabad"
    ],
    "name:ita_x_preferred":[
        "Fatehabad"
    ],
    "name:msa_x_preferred":[
        "Fatehabad"
    ],
    "name:nld_x_preferred":[
        "Fatehabad"
    ],
    "name:pol_x_preferred":[
        "Fatehabad"
    ],
    "name:und_x_variant":[
        "Feteh\u0101b\u0101d"
    ],
    "wof:name":"Fatehabad",
    "wof:placetype":"locality"
},
  "geometry": {"coordinates":[74.22126,31.42506],"type":"Point"}
}