{
  "type": "Feature",
  "properties": {
    "gn:admin1_code":"4.0",
    "gn:asciiname":"Basti Gul Bahar Punjabi",
    "gn:country_code":"PK",
    "gn:dem":78,
    "gn:feature_class":"P",
    "gn:feature_code":"PPL",
    "gn:name":"Basti Gul Bahar Punjabi",
    "gn:population":0,
    "gn:timezone":"Asia/Karachi",
    "iso:country":"PK",
    "wof:name":"Basti Gul Bahar Punjabi",
    "wof:placetype":"locality"
},
  "geometry": {"coordinates":[69.90116,28.36563],"type":"Point"}
}