{
  "type": "Feature",
  "properties": {
    "gn:admin1_code":"04",
    "gn:asciiname":"Chak Sixty-seven Jakh Branch",
    "gn:country_code":"PK",
    "gn:dem":181,
    "gn:feature_class":"P",
    "gn:feature_code":"PPL",
    "gn:name":"Chak Sixty-seven Jakh Branch",
    "gn:population":0,
    "gn:timezone":"Asia/Karachi",
    "iso:country":"PK",
    "name:und_x_variant":[
        "Sidhar",
        "Chak Sixty-Seven",
        "Chak Sixty-seven Jakh Branch",
        "Sidh\u0101r"
    ],
    "wof:name":"Chak Sixty-seven Jakh Branch",
    "wof:placetype":"locality"
},
  "geometry": {"coordinates":[72.94041,31.36987],"type":"Point"}
}