{
  "type": "Feature",
  "properties": {
    "gn:admin1_code":"03",
    "gn:asciiname":"Makhan",
    "gn:country_code":"PK",
    "gn:dem":512,
    "gn:feature_class":"P",
    "gn:feature_code":"PPL",
    "gn:name":"Makhan",
    "gn:population":0,
    "gn:timezone":"Asia/Karachi",
    "iso:country":"PK",
    "wof:name":"Makhan",
    "wof:placetype":"locality"
},
  "geometry": {"coordinates":[72.94163,34.02602],"type":"Point"}
}