{
  "type": "Feature",
  "properties": {
    "gn:admin1_code":"4.0",
    "gn:asciiname":"Chak Sixty-five-Four Right",
    "gn:country_code":"PK",
    "gn:dem":175,
    "gn:feature_class":"P",
    "gn:feature_code":"PPL",
    "gn:name":"Chak Sixty-five-Four Right",
    "gn:population":0,
    "gn:timezone":"Asia/Karachi",
    "iso:country":"PK",
    "name:und_x_variant":[
        "Day\u0101lnagar",
        "Dar\u0101lnagar"
    ],
    "wof:name":"Chak Sixty-five-Four Right",
    "wof:placetype":"locality"
},
  "geometry": {"coordinates":[73.23733,30.79456],"type":"Point"}
}