{
  "type": "Feature",
  "properties": {
    "gn:admin1_code":"3",
    "gn:asciiname":"Pirkand",
    "gn:country_code":"PK",
    "gn:dem":1847,
    "gn:feature_class":"P",
    "gn:feature_code":"PPL",
    "gn:name":"Pirkand",
    "gn:population":0,
    "gn:timezone":"Asia/Karachi",
    "iso:country":"PK",
    "wof:name":"Pirkand",
    "wof:placetype":"locality"
},
  "geometry": {"coordinates":[72.31525000000001,35.0927],"type":"Point"}
}