{
  "type": "Feature",
  "properties": {
    "gn:admin1_code":"3.0",
    "gn:asciiname":"Kach Kotai Asad Khan",
    "gn:country_code":"PK",
    "gn:dem":386,
    "gn:feature_class":"P",
    "gn:feature_code":"PPL",
    "gn:name":"Kach Kotai Asad Khan",
    "gn:population":0,
    "gn:timezone":"Asia/Karachi",
    "iso:country":"PK",
    "name:und_x_variant":[
        "Kachkotai Asad Kh\u0101n"
    ],
    "wof:name":"Kach Kotai Asad Khan",
    "wof:placetype":"locality"
},
  "geometry": {"coordinates":[70.60457,33.0147],"type":"Point"}
}