{
  "type": "Feature",
  "properties": {
    "gn:admin1_code":"6",
    "gn:asciiname":"Marwali",
    "gn:country_code":"PK",
    "gn:dem":2855,
    "gn:feature_class":"P",
    "gn:feature_code":"PPL",
    "gn:name":"Marwali",
    "gn:population":0,
    "gn:timezone":"Asia/Karachi",
    "iso:country":"PK",
    "name:und_x_variant":[
        "M\u0101nw\u0101la",
        "M\u0101rw\u0101la"
    ],
    "wof:name":"Marwali",
    "wof:placetype":"locality"
},
  "geometry": {"coordinates":[74.00851,33.96073],"type":"Point"}
}