{
  "type": "Feature",
  "properties": {
    "gn:admin1_code":"2.0",
    "gn:asciiname":"Murad Bazar",
    "gn:country_code":"PK",
    "gn:dem":890,
    "gn:feature_class":"P",
    "gn:feature_code":"PPL",
    "gn:name":"Murad Bazar",
    "gn:population":0,
    "gn:timezone":"Asia/Karachi",
    "iso:country":"PK",
    "wof:name":"Murad Bazar",
    "wof:placetype":"locality"
},
  "geometry": {"coordinates":[63.47083000000001,26.63685],"type":"Point"}
}