{
  "type": "Feature",
  "properties": {
    "gn:admin1_code":"4.0",
    "gn:asciiname":"Dhok Kashmirian",
    "gn:country_code":"PK",
    "gn:dem":494,
    "gn:feature_class":"P",
    "gn:feature_code":"PPL",
    "gn:name":"Dhok Kashmirian",
    "gn:population":0,
    "gn:timezone":"Asia/Karachi",
    "iso:country":"PK",
    "wof:name":"Dhok Kashmirian",
    "wof:placetype":"locality"
},
  "geometry": {"coordinates":[72.96297,33.48567],"type":"Point"}
}