{
  "type": "Feature",
  "properties": {
    "gn:admin1_code":"04",
    "gn:asciiname":"Rahmuke",
    "gn:country_code":"PK",
    "gn:dem":166,
    "gn:feature_class":"P",
    "gn:feature_code":"PPL",
    "gn:name":"Rahmuke",
    "gn:population":0,
    "gn:timezone":"Asia/Karachi",
    "iso:country":"PK",
    "name:und_x_variant":[
        "Rehmunka",
        "Rahm\u016bnke",
        "Rahmuke"
    ],
    "wof:name":"Rahmuke",
    "wof:placetype":"locality"
},
  "geometry": {"coordinates":[73.57221,30.26476],"type":"Point"}
}