{
  "type": "Feature",
  "properties": {
    "gn:admin1_code":"5",
    "gn:asciiname":"Mithu Hajiani",
    "gn:country_code":"PK",
    "gn:dem":22,
    "gn:feature_class":"P",
    "gn:feature_code":"PPL",
    "gn:name":"Mithu Hajiani",
    "gn:population":0,
    "gn:timezone":"Asia/Karachi",
    "iso:country":"PK",
    "name:eng_x_preferred":[
        "Mithu H\u0101ji\u0101na"
    ],
    "wof:name":"Mithu Hajiani",
    "wof:placetype":"locality"
},
  "geometry": {"coordinates":[68.43340999999999,25.48449],"type":"Point"}
}