{
  "type": "Feature",
  "properties": {
    "gn:admin1_code":"5.0",
    "gn:asciiname":"Dhandharo",
    "gn:country_code":"PK",
    "gn:dem":33,
    "gn:feature_class":"P",
    "gn:feature_code":"PPL",
    "gn:name":"Dhandharo",
    "gn:population":0,
    "gn:timezone":"Asia/Karachi",
    "iso:country":"PK",
    "name:und_x_variant":[
        "Dhandoro"
    ],
    "wof:name":"Dhandharo",
    "wof:placetype":"locality"
},
  "geometry": {"coordinates":[70.69838,24.61596],"type":"Point"}
}