{
  "type": "Feature",
  "properties": {
    "gn:admin1_code":"5",
    "gn:asciiname":"Goth Nendro",
    "gn:country_code":"PK",
    "gn:dem":77,
    "gn:feature_class":"P",
    "gn:feature_code":"PPL",
    "gn:name":"Goth Nendro",
    "gn:population":0,
    "gn:timezone":"Asia/Karachi",
    "iso:country":"PK",
    "name:und_x_variant":[
        "Nendro"
    ],
    "wof:name":"Goth Nendro",
    "wof:placetype":"locality"
},
  "geometry": {"coordinates":[69.23727,26.78174000000001],"type":"Point"}
}