{
  "type": "Feature",
  "properties": {
    "gn:admin1_code":"4.0",
    "gn:asciiname":"Kail",
    "gn:country_code":"PK",
    "gn:dem":169,
    "gn:feature_class":"P",
    "gn:feature_code":"PPL",
    "gn:name":"Kail",
    "gn:population":0,
    "gn:timezone":"Asia/Karachi",
    "iso:country":"PK",
    "name:ceb_x_preferred":[
        "Kail"
    ],
    "name:deu_x_preferred":[
        "Kail"
    ],
    "name:epo_x_preferred":[
        "Kail"
    ],
    "name:eus_x_preferred":[
        "Kail"
    ],
    "name:fra_x_preferred":[
        "Kail"
    ],
    "name:hun_x_preferred":[
        "Kail"
    ],
    "name:ita_x_preferred":[
        "Kail"
    ],
    "name:msa_x_preferred":[
        "Kail"
    ],
    "name:nld_x_preferred":[
        "Kail"
    ],
    "name:pol_x_preferred":[
        "Kail"
    ],
    "name:por_x_preferred":[
        "Kail"
    ],
    "name:ron_x_preferred":[
        "Kail"
    ],
    "name:rus_x_preferred":[
        "\u041a\u0430\u0439\u043b\u044c"
    ],
    "name:spa_x_preferred":[
        "Kail"
    ],
    "name:srp_x_preferred":[
        "\u041a\u0430\u0458\u043b"
    ],
    "name:ukr_x_preferred":[
        "\u041a\u0430\u0439\u043b\u044c"
    ],
    "name:uzb_x_preferred":[
        "Kail"
    ],
    "name:vie_x_preferred":[
        "Kail"
    ],
    "name:vol_x_preferred":[
        "Kail"
    ],
    "name:war_x_preferred":[
        "Kail"
    ],
    "wof:name":"Kail",
    "wof:placetype":"locality"
},
  "geometry": {"coordinates":[71.06392,31.71835],"type":"Point"}
}