{
  "type": "Feature",
  "properties": {
    "gn:admin1_code":"4",
    "gn:asciiname":"Tangwaniwala",
    "gn:country_code":"PK",
    "gn:dem":142,
    "gn:feature_class":"P",
    "gn:feature_code":"PPL",
    "gn:name":"Tangwaniwala",
    "gn:population":0,
    "gn:timezone":"Asia/Karachi",
    "iso:country":"PK",
    "name:und_x_variant":[
        "T\u0101ng\u012bw\u0101la"
    ],
    "wof:name":"Tangwaniwala",
    "wof:placetype":"locality"
},
  "geometry": {"coordinates":[70.88602,30.7092],"type":"Point"}
}