{
  "type": "Feature",
  "properties": {
    "gn:admin1_code":"7.0",
    "gn:asciiname":"Yasur",
    "gn:country_code":"PK",
    "gn:dem":3527,
    "gn:feature_class":"P",
    "gn:feature_code":"PPL",
    "gn:name":"Yasur",
    "gn:population":0,
    "gn:timezone":"Asia/Karachi",
    "iso:country":"PK",
    "wof:name":"Yasur",
    "wof:placetype":"locality"
},
  "geometry": {"coordinates":[73.58351999999999,35.97475],"type":"Point"}
}