{
  "type": "Feature",
  "properties": {
    "gn:admin1_code":"3.0",
    "gn:asciiname":"Zarba Din",
    "gn:country_code":"PK",
    "gn:dem":414,
    "gn:feature_class":"P",
    "gn:feature_code":"PPL",
    "gn:name":"Zarba Din",
    "gn:population":0,
    "gn:timezone":"Asia/Karachi",
    "iso:country":"PK",
    "wof:name":"Zarba Din",
    "wof:placetype":"locality"
},
  "geometry": {"coordinates":[70.49509999999999,32.93674],"type":"Point"}
}