{
  "type": "Feature",
  "properties": {
    "gn:admin1_code":"2.0",
    "gn:asciiname":"Ghulam Muhammad",
    "gn:country_code":"PK",
    "gn:dem":2184,
    "gn:feature_class":"P",
    "gn:feature_code":"PPL",
    "gn:name":"Ghulam Muhammad",
    "gn:population":0,
    "gn:timezone":"Asia/Karachi",
    "iso:country":"PK",
    "wof:name":"Ghulam Muhammad",
    "wof:placetype":"locality"
},
  "geometry": {"coordinates":[66.71921,31.08945],"type":"Point"}
}