{
  "type": "Feature",
  "properties": {
    "gn:admin1_code":"3.0",
    "gn:asciiname":"Par",
    "gn:country_code":"PK",
    "gn:dem":1810,
    "gn:feature_class":"P",
    "gn:feature_code":"PPL",
    "gn:name":"Par",
    "gn:population":0,
    "gn:timezone":"Asia/Karachi",
    "iso:country":"PK",
    "name:ces_x_preferred":[
        "Par"
    ],
    "name:fin_x_preferred":[
        "Par"
    ],
    "name:heb_x_preferred":[
        "\u05e4\u05e8"
    ],
    "name:nld_x_preferred":[
        "Par"
    ],
    "name:nor_x_preferred":[
        "Par"
    ],
    "name:pol_x_preferred":[
        "Par"
    ],
    "name:por_x_preferred":[
        "Par"
    ],
    "name:ron_x_preferred":[
        "Par"
    ],
    "name:spa_x_preferred":[
        "Par"
    ],
    "name:swe_x_preferred":[
        "Par"
    ],
    "name:tur_x_preferred":[
        "Par"
    ],
    "wof:name":"Par",
    "wof:placetype":"locality"
},
  "geometry": {"coordinates":[73.11657,35.04123],"type":"Point"}
}