{
  "type": "Feature",
  "properties": {
    "gn:admin1_code":"4",
    "gn:asciiname":"Chak One Hundred Seventy Eastern Bar",
    "gn:country_code":"PK",
    "gn:dem":145,
    "gn:feature_class":"P",
    "gn:feature_code":"PPL",
    "gn:name":"Chak One Hundred Seventy Eastern Bar",
    "gn:population":0,
    "gn:timezone":"Asia/Karachi",
    "iso:country":"PK",
    "name:und_x_variant":[
        "Chak One Hundred Seventy EB"
    ],
    "wof:name":"Chak One Hundred Seventy Eastern Bar",
    "wof:placetype":"locality"
},
  "geometry": {"coordinates":[72.51616,30.1854],"type":"Point"}
}