{
  "type": "Feature",
  "properties": {
    "gn:admin1_code":"04",
    "gn:asciiname":"Mandaha Kalia",
    "gn:country_code":"PK",
    "gn:dem":162,
    "gn:feature_class":"P",
    "gn:feature_code":"PPL",
    "gn:name":"Mandaha Kalia",
    "gn:population":0,
    "gn:timezone":"Asia/Karachi",
    "iso:country":"PK",
    "name:und_x_variant":[
        "Mamd\u0101na Kal\u0101n"
    ],
    "wof:name":"Mandaha Kalia",
    "wof:placetype":"locality"
},
  "geometry": {"coordinates":[72.6768,30.65576],"type":"Point"}
}