{
  "type": "Feature",
  "properties": {
    "gn:admin1_code":"2.0",
    "gn:asciiname":"Paizai",
    "gn:country_code":"PK",
    "gn:dem":1485,
    "gn:feature_class":"P",
    "gn:feature_code":"PPL",
    "gn:name":"Paizai",
    "gn:population":0,
    "gn:timezone":"Asia/Karachi",
    "iso:country":"PK",
    "wof:name":"Paizai",
    "wof:placetype":"locality"
},
  "geometry": {"coordinates":[66.69038,30.66566],"type":"Point"}
}