{
  "type": "Feature",
  "properties": {
    "gn:admin1_code":"4.0",
    "gn:asciiname":"Chah Qaim",
    "gn:country_code":"PK",
    "gn:dem":144,
    "gn:feature_class":"P",
    "gn:feature_code":"PPL",
    "gn:name":"Chah Qaim",
    "gn:population":0,
    "gn:timezone":"Asia/Karachi",
    "iso:country":"PK",
    "name:und_x_variant":[
        "Basti Q\u0101im"
    ],
    "wof:name":"Chah Qaim",
    "wof:placetype":"locality"
},
  "geometry": {"coordinates":[72.17963,30.92705],"type":"Point"}
}