{
  "type": "Feature",
  "properties": {
    "gn:admin1_code":"4.0",
    "gn:asciiname":"Tahlo Shani",
    "gn:country_code":"PK",
    "gn:dem":348,
    "gn:feature_class":"P",
    "gn:feature_code":"PPL",
    "gn:name":"Tahlo Shani",
    "gn:population":0,
    "gn:timezone":"Asia/Karachi",
    "iso:country":"PK",
    "wof:name":"Tahlo Shani",
    "wof:placetype":"locality"
},
  "geometry": {"coordinates":[69.95178,29.26997],"type":"Point"}
}