{
  "type": "Feature",
  "properties": {
    "gn:admin1_code":"4.0",
    "gn:asciiname":"Chakka Bail",
    "gn:country_code":"PK",
    "gn:dem":982,
    "gn:feature_class":"P",
    "gn:feature_code":"PPL",
    "gn:name":"Chakka Bail",
    "gn:population":0,
    "gn:timezone":"Asia/Karachi",
    "iso:country":"PK",
    "name:eng_x_preferred":[
        "Chakka Bail"
    ],
    "wof:name":"Chakka Bail",
    "wof:placetype":"locality"
},
  "geometry": {"coordinates":[73.43807,33.75155],"type":"Point"}
}