{
  "type": "Feature",
  "properties": {
    "gn:admin1_code":"5.0",
    "gn:asciiname":"Goth Urs Khaskheli",
    "gn:country_code":"PK",
    "gn:dem":13,
    "gn:feature_class":"P",
    "gn:feature_code":"PPL",
    "gn:name":"Goth Urs Khaskheli",
    "gn:population":0,
    "gn:timezone":"Asia/Karachi",
    "iso:country":"PK",
    "wof:name":"Goth Urs Khaskheli",
    "wof:placetype":"locality"
},
  "geometry": {"coordinates":[68.15904999999999,24.84589],"type":"Point"}
}