{
  "type": "Feature",
  "properties": {
    "gn:admin1_code":"3",
    "gn:asciiname":"Tinka",
    "gn:country_code":"PK",
    "gn:dem":2097,
    "gn:feature_class":"P",
    "gn:feature_code":"PPL",
    "gn:name":"Tinka",
    "gn:population":0,
    "gn:timezone":"Asia/Karachi",
    "iso:country":"PK",
    "name:eng_x_preferred":[
        "Tinka"
    ],
    "wof:name":"Tinka",
    "wof:placetype":"locality"
},
  "geometry": {"coordinates":[72.60361,35.34826],"type":"Point"}
}