{
  "type": "Feature",
  "properties": {
    "gn:admin1_code":"4.0",
    "gn:asciiname":"Chak Two Hundred Seventy-two Hakra Right Nai Abadi",
    "gn:country_code":"PK",
    "gn:dem":146,
    "gn:feature_class":"P",
    "gn:feature_code":"PPL",
    "gn:name":"Chak Two Hundred Seventy-two Hakra Right Nai Abadi",
    "gn:population":0,
    "gn:timezone":"Asia/Karachi",
    "iso:country":"PK",
    "wof:name":"Chak Two Hundred Seventy-two Hakra Right Nai Abadi",
    "wof:placetype":"locality"
},
  "geometry": {"coordinates":[72.86573,29.19371],"type":"Point"}
}