{
  "type": "Feature",
  "properties": {
    "gn:admin1_code":"7.0",
    "gn:asciiname":"Gaman Das",
    "gn:country_code":"PK",
    "gn:dem":2083,
    "gn:feature_class":"P",
    "gn:feature_code":"PPL",
    "gn:name":"Gaman Das",
    "gn:population":0,
    "gn:timezone":"Asia/Karachi",
    "iso:country":"PK",
    "wof:name":"Gaman Das",
    "wof:placetype":"locality"
},
  "geometry": {"coordinates":[74.52768,36.24738],"type":"Point"}
}