{
  "type": "Feature",
  "properties": {
    "gn:admin1_code":"3",
    "gn:asciiname":"Raht",
    "gn:country_code":"PK",
    "gn:dem":2884,
    "gn:feature_class":"P",
    "gn:feature_code":"PPL",
    "gn:name":"Raht",
    "gn:population":0,
    "gn:timezone":"Asia/Karachi",
    "iso:country":"PK",
    "name:eng_x_preferred":[
        "Raht"
    ],
    "wof:name":"Raht",
    "wof:placetype":"locality"
},
  "geometry": {"coordinates":[71.92971999999997,35.59667],"type":"Point"}
}