{
  "type": "Feature",
  "properties": {
    "gn:admin1_code":"2.0",
    "gn:asciiname":"Haji Mir Khan",
    "gn:country_code":"PK",
    "gn:dem":1248,
    "gn:feature_class":"P",
    "gn:feature_code":"PPL",
    "gn:name":"Haji Mir Khan",
    "gn:population":0,
    "gn:timezone":"Asia/Karachi",
    "iso:country":"PK",
    "wof:name":"Haji Mir Khan",
    "wof:placetype":"locality"
},
  "geometry": {"coordinates":[69.87059000000001,30.21261],"type":"Point"}
}