{
  "type": "Feature",
  "properties": {
    "gn:admin1_code":"3.0",
    "gn:asciiname":"Kothon",
    "gn:country_code":"PK",
    "gn:dem":1790,
    "gn:feature_class":"P",
    "gn:feature_code":"PPL",
    "gn:name":"Kothon",
    "gn:population":0,
    "gn:timezone":"Asia/Karachi",
    "iso:country":"PK",
    "wof:name":"Kothon",
    "wof:placetype":"locality"
},
  "geometry": {"coordinates":[73.41468,34.22298],"type":"Point"}
}