{
  "type": "Feature",
  "properties": {
    "gn:admin1_code":"3.0",
    "gn:asciiname":"Laspur Ghari",
    "gn:country_code":"PK",
    "gn:dem":3790,
    "gn:feature_class":"P",
    "gn:feature_code":"PPL",
    "gn:name":"Laspur Ghari",
    "gn:population":0,
    "gn:timezone":"Asia/Karachi",
    "iso:country":"PK",
    "wof:name":"Laspur Ghari",
    "wof:placetype":"locality"
},
  "geometry": {"coordinates":[72.51555,36.06014],"type":"Point"}
}