{
  "type": "Feature",
  "properties": {
    "gn:admin1_code":"01",
    "gn:asciiname":"Gorondo Kili",
    "gn:country_code":"PK",
    "gn:dem":1858,
    "gn:feature_class":"P",
    "gn:feature_code":"PPL",
    "gn:name":"Gorondo Kili",
    "gn:population":0,
    "gn:timezone":"Asia/Karachi",
    "iso:country":"PK",
    "name:und_x_variant":[
        "Gorando Kili"
    ],
    "wof:name":"Gorondo Kili",
    "wof:placetype":"locality"
},
  "geometry": {"coordinates":[70.62985999999999,33.68592],"type":"Point"}
}