{
  "type": "Feature",
  "properties": {
    "gn:admin1_code":"4",
    "gn:asciiname":"Kharl Mahabbatpur",
    "gn:country_code":"PK",
    "gn:dem":210,
    "gn:feature_class":"P",
    "gn:feature_code":"PPL",
    "gn:name":"Kharl Mahabbatpur",
    "gn:population":0,
    "gn:timezone":"Asia/Karachi",
    "iso:country":"PK",
    "wof:name":"Kharl Mahabbatpur",
    "wof:placetype":"locality"
},
  "geometry": {"coordinates":[73.43008,32.61719],"type":"Point"}
}