{
  "type": "Feature",
  "properties": {
    "gn:admin1_code":"5",
    "gn:asciiname":"Mehrab Khan",
    "gn:country_code":"PK",
    "gn:dem":72,
    "gn:feature_class":"P",
    "gn:feature_code":"PPL",
    "gn:name":"Mehrab Khan",
    "gn:population":0,
    "gn:timezone":"Asia/Karachi",
    "iso:country":"PK",
    "name:und_x_variant":[
        "Mehr\u0101b Kh\u0101n"
    ],
    "wof:name":"Mehrab Khan",
    "wof:placetype":"locality"
},
  "geometry": {"coordinates":[69.57958000000001,28.07813],"type":"Point"}
}