{
  "type": "Feature",
  "properties": {
    "gn:admin1_code":"4.0",
    "gn:asciiname":"Basti Madgari",
    "gn:country_code":"PK",
    "gn:dem":160,
    "gn:feature_class":"P",
    "gn:feature_code":"PPL",
    "gn:name":"Basti Madgari",
    "gn:population":0,
    "gn:timezone":"Asia/Karachi",
    "iso:country":"PK",
    "wof:name":"Basti Madgari",
    "wof:placetype":"locality"
},
  "geometry": {"coordinates":[70.96819000000001,31.26206],"type":"Point"}
}