{
  "type": "Feature",
  "properties": {
    "gn:admin1_code":"3",
    "gn:asciiname":"Roh",
    "gn:country_code":"PK",
    "gn:dem":568,
    "gn:feature_class":"P",
    "gn:feature_code":"PPL",
    "gn:name":"Roh",
    "gn:population":0,
    "gn:timezone":"Asia/Karachi",
    "iso:country":"PK",
    "name:kor_x_preferred":[
        "\ub178"
    ],
    "name:und_x_variant":[
        "Bal\u0101nda"
    ],
    "wof:name":"Roh",
    "wof:placetype":"locality"
},
  "geometry": {"coordinates":[72.88188000000002,34.25914],"type":"Point"}
}