{
  "type": "Feature",
  "properties": {
    "gn:admin1_code":"6.0",
    "gn:asciiname":"Lateri",
    "gn:country_code":"PK",
    "gn:dem":1307,
    "gn:feature_class":"P",
    "gn:feature_code":"PPL",
    "gn:name":"Lateri",
    "gn:population":0,
    "gn:timezone":"Asia/Karachi",
    "iso:country":"PK",
    "wof:name":"Lateri",
    "wof:placetype":"locality"
},
  "geometry": {"coordinates":[74.05988000000001,33.4929],"type":"Point"}
}