{
  "type": "Feature",
  "properties": {
    "gn:admin1_code":"6.0",
    "gn:asciiname":"Lateri",
    "gn:country_code":"PK",
    "gn:dem":1307,
    "gn:feature_class":"P",
    "gn:feature_code":"PPL",
    "gn:name":"Lateri",
    "gn:population":0,
    "gn:timezone":"Asia/Karachi",
    "iso:country":"PK",
    "name:ben_x_preferred":[
        "\u09b2\u09be\u09a4\u09c7\u09b0\u09bf"
    ],
    "name:bpy_x_preferred":[
        "\u09b2\u09be\u09a4\u09c7\u09b0\u09bf"
    ],
    "name:ita_x_preferred":[
        "Lateri"
    ],
    "name:mlg_x_preferred":[
        "Lateri"
    ],
    "name:msa_x_preferred":[
        "Lateri"
    ],
    "name:new_x_preferred":[
        "\u0932\u0924\u0947\u0930\u0940"
    ],
    "name:nld_x_preferred":[
        "Lateri"
    ],
    "name:por_x_preferred":[
        "Lateri"
    ],
    "name:spa_x_preferred":[
        "Lateri"
    ],
    "name:urd_x_preferred":[
        "\u0644\u0627\u062a\u06cc\u0631\u06cc"
    ],
    "name:vie_x_preferred":[
        "Lateri"
    ],
    "name:zho_x_preferred":[
        "\u62c9\u6cf0\u91cc"
    ],
    "wof:name":"Lateri",
    "wof:placetype":"locality"
},
  "geometry": {"coordinates":[74.05988000000001,33.4929],"type":"Point"}
}