{
  "type": "Feature",
  "properties": {
    "gn:admin1_code":"2.0",
    "gn:asciiname":"Bali Ba",
    "gn:country_code":"PK",
    "gn:dem":1429,
    "gn:feature_class":"P",
    "gn:feature_code":"PPL",
    "gn:name":"Bali Ba",
    "gn:population":0,
    "gn:timezone":"Asia/Karachi",
    "iso:country":"PK",
    "wof:name":"Bali Ba",
    "wof:placetype":"locality"
},
  "geometry": {"coordinates":[66.84220000000001,28.41737],"type":"Point"}
}