{
  "type": "Feature",
  "properties": {
    "gn:admin1_code":"01",
    "gn:asciiname":"Gadamar",
    "gn:country_code":"PK",
    "gn:dem":884,
    "gn:feature_class":"P",
    "gn:feature_code":"PPL",
    "gn:name":"Gadamar",
    "gn:population":0,
    "gn:timezone":"Asia/Karachi",
    "iso:country":"PK",
    "name:eng_x_preferred":[
        "Gadam\u0101r"
    ],
    "wof:name":"Gadamar",
    "wof:placetype":"locality"
},
  "geometry": {"coordinates":[71.67726999999999,34.67116],"type":"Point"}
}