{
  "type": "Feature",
  "properties": {
    "gn:admin1_code":"5",
    "gn:asciiname":"Khan Rind",
    "gn:country_code":"PK",
    "gn:dem":28,
    "gn:feature_class":"P",
    "gn:feature_code":"PPL",
    "gn:name":"Khan Rind",
    "gn:population":0,
    "gn:timezone":"Asia/Karachi",
    "iso:country":"PK",
    "wof:name":"Khan Rind",
    "wof:placetype":"locality"
},
  "geometry": {"coordinates":[68.56823,26.05793],"type":"Point"}
}