{
  "type": "Feature",
  "properties": {
    "gn:admin1_code":"4",
    "gn:asciiname":"Mohallah",
    "gn:country_code":"PK",
    "gn:dem":231,
    "gn:feature_class":"P",
    "gn:feature_code":"PPL",
    "gn:name":"Mohallah",
    "gn:population":0,
    "gn:timezone":"Asia/Karachi",
    "iso:country":"PK",
    "name:und_x_variant":[
        "Mahallah"
    ],
    "wof:name":"Mohallah",
    "wof:placetype":"locality"
},
  "geometry": {"coordinates":[74.08761,32.59353],"type":"Point"}
}