{
  "type": "Feature",
  "properties": {
    "gn:admin1_code":"4.0",
    "gn:asciiname":"Dhok Kachanwala",
    "gn:country_code":"PK",
    "gn:dem":487,
    "gn:feature_class":"P",
    "gn:feature_code":"PPL",
    "gn:name":"Dhok Kachanwala",
    "gn:population":0,
    "gn:timezone":"Asia/Karachi",
    "iso:country":"PK",
    "wof:name":"Dhok Kachanwala",
    "wof:placetype":"locality"
},
  "geometry": {"coordinates":[72.68786999999998,32.87397],"type":"Point"}
}