{
  "type": "Feature",
  "properties": {
    "gn:admin1_code":"4",
    "gn:asciiname":"Basti Bhand",
    "gn:country_code":"PK",
    "gn:dem":107,
    "gn:feature_class":"P",
    "gn:feature_code":"PPL",
    "gn:name":"Basti Bhand",
    "gn:population":0,
    "gn:timezone":"Asia/Karachi",
    "iso:country":"PK",
    "name:und_x_variant":[
        "Basti Bh\u0101nd"
    ],
    "wof:name":"Basti Bhand",
    "wof:placetype":"locality"
},
  "geometry": {"coordinates":[70.75889000000002,29.57735],"type":"Point"}
}