{
  "type": "Feature",
  "properties": {
    "gn:admin1_code":"4",
    "gn:asciiname":"Bhagwal",
    "gn:country_code":"PK",
    "gn:dem":485,
    "gn:feature_class":"P",
    "gn:feature_code":"PPL",
    "gn:name":"Bhagwal",
    "gn:population":0,
    "gn:timezone":"Asia/Karachi",
    "iso:country":"PK",
    "name:fas_x_preferred":[
        "\u0628\u0647\u0627\u06af\u0648\u0627\u0644"
    ],
    "name:und_x_variant":[
        "Chak Begw\u0101l"
    ],
    "name:urd_x_preferred":[
        "\u0628\u06be\u0627\u06af\u0648\u0627\u0644"
    ],
    "wof:name":"Bhagwal",
    "wof:placetype":"locality"
},
  "geometry": {"coordinates":[73.22058,33.16249000000001],"type":"Point"}
}