{
  "type": "Feature",
  "properties": {
    "gn:admin1_code":"4",
    "gn:asciiname":"Bhagwal",
    "gn:country_code":"PK",
    "gn:dem":485,
    "gn:feature_class":"P",
    "gn:feature_code":"PPL",
    "gn:name":"Bhagwal",
    "gn:population":0,
    "gn:timezone":"Asia/Karachi",
    "iso:country":"PK",
    "name:und_x_variant":[
        "Chak Begw\u0101l"
    ],
    "wof:name":"Bhagwal",
    "wof:placetype":"locality"
},
  "geometry": {"coordinates":[73.22058,33.16249000000001],"type":"Point"}
}