{
  "type": "Feature",
  "properties": {
    "gn:admin1_code":"5.0",
    "gn:asciiname":"Faiz Muhammad Pathan",
    "gn:country_code":"PK",
    "gn:dem":33,
    "gn:feature_class":"P",
    "gn:feature_code":"PPL",
    "gn:name":"Faiz Muhammad Pathan",
    "gn:population":0,
    "gn:timezone":"Asia/Karachi",
    "iso:country":"PK",
    "wof:name":"Faiz Muhammad Pathan",
    "wof:placetype":"locality"
},
  "geometry": {"coordinates":[68.40649000000001,26.37534],"type":"Point"}
}