{
  "type": "Feature",
  "properties": {
    "gn:admin1_code":"1.0",
    "gn:asciiname":"Baota Ghundai",
    "gn:country_code":"PK",
    "gn:dem":686,
    "gn:feature_class":"P",
    "gn:feature_code":"PPL",
    "gn:name":"Baota Ghundai",
    "gn:population":0,
    "gn:timezone":"Asia/Karachi",
    "iso:country":"PK",
    "wof:name":"Baota Ghundai",
    "wof:placetype":"locality"
},
  "geometry": {"coordinates":[71.27556,34.48159],"type":"Point"}
}