{
  "type": "Feature",
  "properties": {
    "gn:admin1_code":"08",
    "gn:asciiname":"Sahana",
    "gn:country_code":"PK",
    "gn:dem":492,
    "gn:feature_class":"P",
    "gn:feature_code":"PPL",
    "gn:name":"Sahana",
    "gn:population":0,
    "gn:timezone":"Asia/Karachi",
    "iso:country":"PK",
    "name:und_x_variant":[
        "Sih\u0101na",
        "Sahana"
    ],
    "wof:name":"Sahana",
    "wof:placetype":"locality"
},
  "geometry": {"coordinates":[73.13670999999999,33.654],"type":"Point"}
}