{
  "type": "Feature",
  "properties": {
    "gn:admin1_code":"4",
    "gn:asciiname":"Gardo",
    "gn:country_code":"PK",
    "gn:dem":1105,
    "gn:feature_class":"P",
    "gn:feature_code":"PPL",
    "gn:name":"Gardo",
    "gn:population":0,
    "gn:timezone":"Asia/Karachi",
    "iso:country":"PK",
    "name:und_x_variant":[
        "Kachi Kothi Tanki"
    ],
    "wof:name":"Gardo",
    "wof:placetype":"locality"
},
  "geometry": {"coordinates":[70.03245,29.95624],"type":"Point"}
}