{
  "type": "Feature",
  "properties": {
    "gn:admin1_code":"2.0",
    "gn:asciiname":"Ghwanzakal",
    "gn:country_code":"PK",
    "gn:dem":2198,
    "gn:feature_class":"P",
    "gn:feature_code":"PPL",
    "gn:name":"Ghwanzakal",
    "gn:population":0,
    "gn:timezone":"Asia/Karachi",
    "iso:country":"PK",
    "name:eng_x_preferred":[
        "Ghwanzakai"
    ],
    "wof:name":"Ghwanzakal",
    "wof:placetype":"locality"
},
  "geometry": {"coordinates":[67.28319999999999,30.69033],"type":"Point"}
}