{
  "type": "Feature",
  "properties": {
    "gn:admin1_code":"04",
    "gn:asciiname":"Tarpai",
    "gn:cc2":"PK",
    "gn:country_code":"PK",
    "gn:dem":258,
    "gn:feature_class":"P",
    "gn:feature_code":"PPL",
    "gn:name":"Tarpai",
    "gn:population":0,
    "gn:timezone":"Asia/Karachi",
    "iso:country":"PK",
    "name:und_x_variant":[
        "Tarpaee",
        "Tarpai"
    ],
    "wof:name":"Tarpai",
    "wof:placetype":"locality"
},
  "geometry": {"coordinates":[75.26666999999998,32.23333],"type":"Point"}
}