{
  "type": "Feature",
  "properties": {
    "gn:admin1_code":"1.0",
    "gn:asciiname":"Bafar Khel",
    "gn:country_code":"PK",
    "gn:dem":1314,
    "gn:feature_class":"P",
    "gn:feature_code":"PPL",
    "gn:name":"Bafar Khel",
    "gn:population":0,
    "gn:timezone":"Asia/Karachi",
    "iso:country":"PK",
    "name:und_x_variant":[
        "Abdul Khel"
    ],
    "wof:name":"Bafar Khel",
    "wof:placetype":"locality"
},
  "geometry": {"coordinates":[70.90199,33.91392],"type":"Point"}
}