{
  "type": "Feature",
  "properties": {
    "gn:admin1_code":"4.0",
    "gn:asciiname":"Saghari Khurd",
    "gn:country_code":"PK",
    "gn:dem":554,
    "gn:feature_class":"P",
    "gn:feature_code":"PPL",
    "gn:name":"Saghari Khurd",
    "gn:population":0,
    "gn:timezone":"Asia/Karachi",
    "iso:country":"PK",
    "name:und_x_variant":[
        "Sagri Khurd"
    ],
    "wof:name":"Saghari Khurd",
    "wof:placetype":"locality"
},
  "geometry": {"coordinates":[73.24773,33.46665],"type":"Point"}
}