{
  "type": "Feature",
  "properties": {
    "gn:admin1_code":"3",
    "gn:asciiname":"Garhn",
    "gn:country_code":"PK",
    "gn:dem":2061,
    "gn:feature_class":"P",
    "gn:feature_code":"PPL",
    "gn:name":"Garhn",
    "gn:population":0,
    "gn:timezone":"Asia/Karachi",
    "iso:country":"PK",
    "wof:name":"Garhn",
    "wof:placetype":"locality"
},
  "geometry": {"coordinates":[73.3509,34.11821],"type":"Point"}
}