{
  "type": "Feature",
  "properties": {
    "gn:admin1_code":"04",
    "gn:asciiname":"Sihanna",
    "gn:country_code":"PK",
    "gn:dem":1121,
    "gn:feature_class":"P",
    "gn:feature_code":"PPL",
    "gn:name":"Sihanna",
    "gn:population":0,
    "gn:timezone":"Asia/Karachi",
    "iso:country":"PK",
    "name:und_x_variant":[
        "Sehna",
        "Sihanna"
    ],
    "wof:name":"Sihanna",
    "wof:placetype":"locality"
},
  "geometry": {"coordinates":[73.50706,33.95617],"type":"Point"}
}