{
  "type": "Feature",
  "properties": {
    "gn:admin1_code":"4",
    "gn:asciiname":"Begewala",
    "gn:country_code":"PK",
    "gn:dem":137,
    "gn:feature_class":"P",
    "gn:feature_code":"PPL",
    "gn:name":"Begewala",
    "gn:population":0,
    "gn:timezone":"Asia/Karachi",
    "iso:country":"PK",
    "name:und_x_variant":[
        "Beggew\u0101la"
    ],
    "wof:name":"Begewala",
    "wof:placetype":"locality"
},
  "geometry": {"coordinates":[71.71899000000001,30.75299],"type":"Point"}
}