{
  "type": "Feature",
  "properties": {
    "gn:admin1_code":"4.0",
    "gn:asciiname":"Kichahad",
    "gn:country_code":"PK",
    "gn:dem":1104,
    "gn:feature_class":"P",
    "gn:feature_code":"PPL",
    "gn:name":"Kichahad",
    "gn:population":0,
    "gn:timezone":"Asia/Karachi",
    "iso:country":"PK",
    "wof:name":"Kichahad",
    "wof:placetype":"locality"
},
  "geometry": {"coordinates":[70.11613,30.63917],"type":"Point"}
}