{
  "type": "Feature",
  "properties": {
    "gn:admin1_code":"5.0",
    "gn:asciiname":"Goth Dali",
    "gn:country_code":"PK",
    "gn:dem":112,
    "gn:feature_class":"P",
    "gn:feature_code":"PPL",
    "gn:name":"Goth Dali",
    "gn:population":0,
    "gn:timezone":"Asia/Karachi",
    "iso:country":"PK",
    "name:und_x_variant":[
        "D\u0101li"
    ],
    "wof:name":"Goth Dali",
    "wof:placetype":"locality"
},
  "geometry": {"coordinates":[70.51153000000002,25.47119],"type":"Point"}
}