{
  "type": "Feature",
  "properties": {
    "gn:admin1_code":"3.0",
    "gn:asciiname":"Dherai Baihk",
    "gn:country_code":"PK",
    "gn:dem":3937,
    "gn:feature_class":"P",
    "gn:feature_code":"PPL",
    "gn:name":"Dherai Baihk",
    "gn:population":0,
    "gn:timezone":"Asia/Karachi",
    "iso:country":"PK",
    "wof:name":"Dherai Baihk",
    "wof:placetype":"locality"
},
  "geometry": {"coordinates":[72.73380999999998,35.77902],"type":"Point"}
}