{
  "type": "Feature",
  "properties": {
    "gn:admin1_code":"6",
    "gn:asciiname":"Pir Kot",
    "gn:country_code":"PK",
    "gn:dem":1664,
    "gn:feature_class":"P",
    "gn:feature_code":"PPL",
    "gn:name":"Pir Kot",
    "gn:population":0,
    "gn:timezone":"Asia/Karachi",
    "iso:country":"PK",
    "wof:name":"Pir Kot",
    "wof:placetype":"locality"
},
  "geometry": {"coordinates":[73.86213000000002,33.8404],"type":"Point"}
}