{
  "type": "Feature",
  "properties": {
    "gn:admin1_code":"5.0",
    "gn:asciiname":"Muhammad Ali Jokhio Goth",
    "gn:country_code":"PK",
    "gn:dem":7,
    "gn:feature_class":"P",
    "gn:feature_code":"PPL",
    "gn:name":"Muhammad Ali Jokhio Goth",
    "gn:population":0,
    "gn:timezone":"Asia/Karachi",
    "iso:country":"PK",
    "name:und_x_variant":[
        "Muhammad Ali Goth Jokhio"
    ],
    "wof:name":"Muhammad Ali Jokhio Goth",
    "wof:placetype":"locality"
},
  "geometry": {"coordinates":[67.63301,24.55487],"type":"Point"}
}