{
  "type": "Feature",
  "properties": {
    "gn:admin1_code":"4",
    "gn:asciiname":"Basti Rahimdad",
    "gn:country_code":"PK",
    "gn:dem":116,
    "gn:feature_class":"P",
    "gn:feature_code":"PPL",
    "gn:name":"Basti Rahimdad",
    "gn:population":0,
    "gn:timezone":"Asia/Karachi",
    "iso:country":"PK",
    "name:eng_x_preferred":[
        "Basti Rahimdad"
    ],
    "wof:name":"Basti Rahimdad",
    "wof:placetype":"locality"
},
  "geometry": {"coordinates":[71.65364,29.3532],"type":"Point"}
}