{
  "type": "Feature",
  "properties": {
    "gn:admin1_code":"4",
    "gn:asciiname":"Bhabewala",
    "gn:country_code":"PK",
    "gn:dem":113,
    "gn:feature_class":"P",
    "gn:feature_code":"PPL",
    "gn:name":"Bhabewala",
    "gn:population":0,
    "gn:timezone":"Asia/Karachi",
    "iso:country":"PK",
    "name:und_x_variant":[
        "Bhabaw\u0101la"
    ],
    "wof:name":"Bhabewala",
    "wof:placetype":"locality"
},
  "geometry": {"coordinates":[70.57250999999999,29.80485],"type":"Point"}
}