{
  "type": "Feature",
  "properties": {
    "gn:admin1_code":"6",
    "gn:asciiname":"Sandial",
    "gn:country_code":"PK",
    "gn:dem":379,
    "gn:feature_class":"P",
    "gn:feature_code":"PPL",
    "gn:name":"Sandial",
    "gn:population":0,
    "gn:timezone":"Asia/Karachi",
    "iso:country":"PK",
    "name:und_x_variant":[
        "Sundal",
        "Sandial"
    ],
    "wof:name":"Sandial",
    "wof:placetype":"locality"
},
  "geometry": {"coordinates":[73.86154999999999,33.16517],"type":"Point"}
}