{
  "type": "Feature",
  "properties": {
    "gn:admin1_code":"7.0",
    "gn:asciiname":"Turkha",
    "gn:country_code":"PK",
    "gn:dem":3238,
    "gn:feature_class":"P",
    "gn:feature_code":"PPL",
    "gn:name":"Turkha",
    "gn:population":0,
    "gn:timezone":"Asia/Karachi",
    "iso:country":"PK",
    "wof:name":"Turkha",
    "wof:placetype":"locality"
},
  "geometry": {"coordinates":[76.08497,35.21399],"type":"Point"}
}