{
  "type": "Feature",
  "properties": {
    "gn:admin1_code":"4.0",
    "gn:asciiname":"Kamalpur Chishtian",
    "gn:country_code":"PK",
    "gn:dem":244,
    "gn:feature_class":"P",
    "gn:feature_code":"PPL",
    "gn:name":"Kamalpur Chishtian",
    "gn:population":0,
    "gn:timezone":"Asia/Karachi",
    "iso:country":"PK",
    "name:und_x_variant":[
        "Kamalpur",
        "Kamalpur Chishtian"
    ],
    "wof:name":"Kamalpur Chishtian",
    "wof:placetype":"locality"
},
  "geometry": {"coordinates":[74.70777,32.26165],"type":"Point"}
}