{
  "type": "Feature",
  "properties": {
    "gn:admin1_code":"5",
    "gn:asciiname":"Goth Arab Panhwar",
    "gn:country_code":"PK",
    "gn:dem":14,
    "gn:feature_class":"P",
    "gn:feature_code":"PPL",
    "gn:name":"Goth Arab Panhwar",
    "gn:population":0,
    "gn:timezone":"Asia/Karachi",
    "iso:country":"PK",
    "name:und_x_variant":[
        "Goth Wadero \u0100rib Panwhar"
    ],
    "wof:name":"Goth Arab Panhwar",
    "wof:placetype":"locality"
},
  "geometry": {"coordinates":[69.20814,25.71875],"type":"Point"}
}