{
  "type": "Feature",
  "properties": {
    "gn:admin1_code":"3.0",
    "gn:asciiname":"Lal Gul",
    "gn:country_code":"PK",
    "gn:dem":411,
    "gn:feature_class":"P",
    "gn:feature_code":"PPL",
    "gn:name":"Lal Gul",
    "gn:population":0,
    "gn:timezone":"Asia/Karachi",
    "iso:country":"PK",
    "wof:name":"Lal Gul",
    "wof:placetype":"locality"
},
  "geometry": {"coordinates":[70.53485999999999,33.00496],"type":"Point"}
}