{
  "type": "Feature",
  "properties": {
    "gn:admin1_code":"5.0",
    "gn:asciiname":"Goth Janib Buraro",
    "gn:country_code":"PK",
    "gn:dem":23,
    "gn:feature_class":"P",
    "gn:feature_code":"PPL",
    "gn:name":"Goth Janib Buraro",
    "gn:population":0,
    "gn:timezone":"Asia/Karachi",
    "iso:country":"PK",
    "wof:name":"Goth Janib Buraro",
    "wof:placetype":"locality"
},
  "geometry": {"coordinates":[68.65878000000001,25.8921],"type":"Point"}
}