{
  "type": "Feature",
  "properties": {
    "gn:admin1_code":"5.0",
    "gn:asciiname":"Goth Haji Anwar Ali Quraishi",
    "gn:country_code":"PK",
    "gn:dem":25,
    "gn:feature_class":"P",
    "gn:feature_code":"PPL",
    "gn:name":"Goth Haji Anwar Ali Quraishi",
    "gn:population":0,
    "gn:timezone":"Asia/Karachi",
    "iso:country":"PK",
    "wof:name":"Goth Haji Anwar Ali Quraishi",
    "wof:placetype":"locality"
},
  "geometry": {"coordinates":[68.62915,25.90202],"type":"Point"}
}