{
  "type": "Feature",
  "properties": {
    "gn:admin1_code":"7.0",
    "gn:asciiname":"Mula Aliwa",
    "gn:country_code":"PK",
    "gn:dem":2509,
    "gn:feature_class":"P",
    "gn:feature_code":"PPL",
    "gn:name":"Mula Aliwa",
    "gn:population":0,
    "gn:timezone":"Asia/Karachi",
    "iso:country":"PK",
    "wof:name":"Mula Aliwa",
    "wof:placetype":"locality"
},
  "geometry": {"coordinates":[76.32225,35.16737],"type":"Point"}
}