{
  "type": "Feature",
  "properties": {
    "gn:admin1_code":"2.0",
    "gn:asciiname":"Shahr Mulla Abdul Hakim",
    "gn:country_code":"PK",
    "gn:dem":2159,
    "gn:feature_class":"P",
    "gn:feature_code":"PPL",
    "gn:name":"Shahr Mulla Abdul Hakim",
    "gn:population":0,
    "gn:timezone":"Asia/Karachi",
    "iso:country":"PK",
    "wof:name":"Shahr Mulla Abdul Hakim",
    "wof:placetype":"locality"
},
  "geometry": {"coordinates":[66.60661999999999,28.90688],"type":"Point"}
}