{
  "type": "Feature",
  "properties": {
    "gn:admin1_code":"2.0",
    "gn:asciiname":"Hamza",
    "gn:country_code":"PK",
    "gn:dem":56,
    "gn:feature_class":"P",
    "gn:feature_code":"PPL",
    "gn:name":"Hamza",
    "gn:population":0,
    "gn:timezone":"Asia/Karachi",
    "iso:country":"PK",
    "name:ara_x_preferred":[
        "\u0647\u0645\u0632\u0629"
    ],
    "name:aze_x_preferred":[
        "H\u0259mz\u0259"
    ],
    "name:bar_x_preferred":[
        "Hamza"
    ],
    "name:ckb_x_preferred":[
        "\u06be\u06d5\u0645\u0632\u06d5"
    ],
    "name:deu_x_preferred":[
        "Hamza"
    ],
    "name:epo_x_preferred":[
        "Hamza"
    ],
    "name:fra_x_preferred":[
        "Hamza"
    ],
    "name:ind_x_preferred":[
        "Hamzah"
    ],
    "name:ita_x_preferred":[
        "Hamza"
    ],
    "name:msa_x_preferred":[
        "Hamzah"
    ],
    "name:nld_x_preferred":[
        "Hamza"
    ],
    "name:pol_x_preferred":[
        "Hamza"
    ],
    "name:rus_x_preferred":[
        "\u0425\u0430\u043c\u0437\u0430"
    ],
    "name:slk_x_preferred":[
        "Hamza"
    ],
    "name:srp_x_preferred":[
        "\u0425\u0430\u043c\u0437\u0430"
    ],
    "name:tat_x_preferred":[
        "\u04ba\u04d9\u043c\u0437\u04d9"
    ],
    "name:tha_x_preferred":[
        "\u0e2e\u0e31\u0e21\u0e0b\u0e30\u0e2e\u0e4c"
    ],
    "name:tur_x_preferred":[
        "Hemze"
    ],
    "name:uig_x_preferred":[
        "\u06be\u06d5\u0645\u0632\u06d5"
    ],
    "name:ukr_x_preferred":[
        "\u0413\u0430\u043c\u0437\u0430"
    ],
    "name:urd_x_preferred":[
        "\u06c1\u0645\u0632\u06c1"
    ],
    "wof:name":"Hamza",
    "wof:placetype":"locality"
},
  "geometry": {"coordinates":[68.12618000000001,28.23201],"type":"Point"}
}