{
  "type": "Feature",
  "properties": {
    "gn:admin1_code":"2.0",
    "gn:asciiname":"Ibrahim Khel",
    "gn:country_code":"PK",
    "gn:dem":1744,
    "gn:feature_class":"P",
    "gn:feature_code":"PPL",
    "gn:name":"Ibrahim Khel",
    "gn:population":0,
    "gn:timezone":"Asia/Karachi",
    "iso:country":"PK",
    "name:und_x_variant":[
        "Ib\u0101h\u012bm Kili",
        "Ibr\u0101h\u012bm Kili",
        "Ibrahim Khel"
    ],
    "wof:name":"Ibrahim Khel",
    "wof:placetype":"locality"
},
  "geometry": {"coordinates":[69.64106,31.24799],"type":"Point"}
}