{
  "type": "Feature",
  "properties": {
    "gn:admin1_code":"1",
    "gn:asciiname":"Sata Aba Khel",
    "gn:country_code":"PK",
    "gn:dem":1650,
    "gn:feature_class":"P",
    "gn:feature_code":"PPL",
    "gn:name":"Sata Aba Khel",
    "gn:population":0,
    "gn:timezone":"Asia/Karachi",
    "iso:country":"PK",
    "wof:name":"Sata Aba Khel",
    "wof:placetype":"locality"
},
  "geometry": {"coordinates":[69.85636,32.57634],"type":"Point"}
}