{
  "type": "Feature",
  "properties": {
    "gn:admin1_code":"6",
    "gn:asciiname":"Padhar",
    "gn:country_code":"PK",
    "gn:dem":1556,
    "gn:feature_class":"P",
    "gn:feature_code":"PPL",
    "gn:name":"Padhar",
    "gn:population":0,
    "gn:timezone":"Asia/Karachi",
    "iso:country":"PK",
    "name:und_x_variant":[
        "Panai",
        "P\u0101nas"
    ],
    "wof:name":"Padhar",
    "wof:placetype":"locality"
},
  "geometry": {"coordinates":[74.03524,33.88289],"type":"Point"}
}