{
  "type": "Feature",
  "properties": {
    "gn:admin1_code":"2",
    "gn:asciiname":"Archina",
    "gn:country_code":"PK",
    "gn:dem":1678,
    "gn:feature_class":"P",
    "gn:feature_code":"PPL",
    "gn:name":"Arch\u012bna",
    "gn:population":0,
    "gn:timezone":"Asia/Karachi",
    "iso:country":"PK",
    "wof:name":"Archina",
    "wof:placetype":"locality"
},
  "geometry": {"coordinates":[66.36389,28.18056],"type":"Point"}
}