{
  "type": "Feature",
  "properties": {
    "gn:admin1_code":"3.0",
    "gn:asciiname":"Shishai Baihk",
    "gn:country_code":"PK",
    "gn:dem":3033,
    "gn:feature_class":"P",
    "gn:feature_code":"PPL",
    "gn:name":"Shishai Baihk",
    "gn:population":0,
    "gn:timezone":"Asia/Karachi",
    "iso:country":"PK",
    "wof:name":"Shishai Baihk",
    "wof:placetype":"locality"
},
  "geometry": {"coordinates":[73.72603000000002,35.43435],"type":"Point"}
}