{
  "type": "Feature",
  "properties": {
    "gn:admin1_code":"6",
    "gn:asciiname":"Bhutti",
    "gn:country_code":"PK",
    "gn:dem":2036,
    "gn:feature_class":"P",
    "gn:feature_code":"PPL",
    "gn:name":"Bhutti",
    "gn:population":0,
    "gn:timezone":"Asia/Karachi",
    "iso:country":"PK",
    "wof:name":"Bhutti",
    "wof:placetype":"locality"
},
  "geometry": {"coordinates":[73.69167,34.04889],"type":"Point"}
}