{
  "type": "Feature",
  "properties": {
    "gn:admin1_code":"4",
    "gn:asciiname":"Dara Kial",
    "gn:country_code":"PK",
    "gn:dem":496,
    "gn:feature_class":"P",
    "gn:feature_code":"PPL",
    "gn:name":"Dara Kial",
    "gn:population":0,
    "gn:timezone":"Asia/Karachi",
    "iso:country":"PK",
    "name:und_x_variant":[
        "Kiald\u0101ra"
    ],
    "wof:name":"Dara Kial",
    "wof:placetype":"locality"
},
  "geometry": {"coordinates":[73.3403,33.13346],"type":"Point"}
}