{
  "type": "Feature",
  "properties": {
    "gn:admin1_code":"4.0",
    "gn:asciiname":"Latkiwali Daril",
    "gn:country_code":"PK",
    "gn:dem":92,
    "gn:feature_class":"P",
    "gn:feature_code":"PPL",
    "gn:name":"Latkiwali Daril",
    "gn:population":0,
    "gn:timezone":"Asia/Karachi",
    "iso:country":"PK",
    "wof:name":"Latkiwali Daril",
    "wof:placetype":"locality"
},
  "geometry": {"coordinates":[70.56126999999999,28.56751],"type":"Point"}
}