{
  "type": "Feature",
  "properties": {
    "gn:admin1_code":"3.0",
    "gn:asciiname":"Chaliar",
    "gn:country_code":"PK",
    "gn:dem":1128,
    "gn:feature_class":"P",
    "gn:feature_code":"PPL",
    "gn:name":"Chaliar",
    "gn:population":0,
    "gn:timezone":"Asia/Karachi",
    "iso:country":"PK",
    "name:und_x_variant":[
        "Chalyar",
        "Chaliar"
    ],
    "wof:name":"Chaliar",
    "wof:placetype":"locality"
},
  "geometry": {"coordinates":[72.46441,34.95532],"type":"Point"}
}