{
  "type": "Feature",
  "properties": {
    "gn:admin1_code":"3.0",
    "gn:asciiname":"Karshat",
    "gn:country_code":"PK",
    "gn:dem":2251,
    "gn:feature_class":"P",
    "gn:feature_code":"PPL",
    "gn:name":"Karshat",
    "gn:population":0,
    "gn:timezone":"Asia/Karachi",
    "iso:country":"PK",
    "wof:name":"Karshat",
    "wof:placetype":"locality"
},
  "geometry": {"coordinates":[72.73343,35.09141],"type":"Point"}
}