{
  "type": "Feature",
  "properties": {
    "gn:admin1_code":"5",
    "gn:asciiname":"Imam Bakhsh",
    "gn:country_code":"PK",
    "gn:dem":68,
    "gn:feature_class":"P",
    "gn:feature_code":"PPL",
    "gn:name":"Imam Bakhsh",
    "gn:population":0,
    "gn:timezone":"Asia/Karachi",
    "iso:country":"PK",
    "name:und_x_variant":[
        "Goth Im\u0101m Bakhsh"
    ],
    "wof:name":"Imam Bakhsh",
    "wof:placetype":"locality"
},
  "geometry": {"coordinates":[69.05119999999999,28.32941],"type":"Point"}
}