{
  "type": "Feature",
  "properties": {
    "gn:admin1_code":"4.0",
    "gn:asciiname":"Chak Wahan",
    "gn:country_code":"PK",
    "gn:dem":83,
    "gn:feature_class":"P",
    "gn:feature_code":"PPL",
    "gn:name":"Chak Wahan",
    "gn:population":0,
    "gn:timezone":"Asia/Karachi",
    "iso:country":"PK",
    "wof:name":"Chak Wahan",
    "wof:placetype":"locality"
},
  "geometry": {"coordinates":[70.24433000000001,28.47769000000001],"type":"Point"}
}