{
  "type": "Feature",
  "properties": {
    "gn:admin1_code":"2.0",
    "gn:asciiname":"Addozai Kili",
    "gn:country_code":"PK",
    "gn:dem":1824,
    "gn:feature_class":"P",
    "gn:feature_code":"PPL",
    "gn:name":"Addozai Kili",
    "gn:population":0,
    "gn:timezone":"Asia/Karachi",
    "iso:country":"PK",
    "name:und_x_variant":[
        "Adozai Kili"
    ],
    "wof:name":"Addozai Kili",
    "wof:placetype":"locality"
},
  "geometry": {"coordinates":[69.49701999999999,30.93551],"type":"Point"}
}