{
  "type": "Feature",
  "properties": {
    "gn:admin1_code":"2.0",
    "gn:asciiname":"Klair Kuchh",
    "gn:country_code":"PK",
    "gn:dem":91,
    "gn:feature_class":"P",
    "gn:feature_code":"PPL",
    "gn:name":"Klair Kuchh",
    "gn:population":0,
    "gn:timezone":"Asia/Karachi",
    "iso:country":"PK",
    "name:eng_x_preferred":[
        "Klair Kuchh"
    ],
    "wof:name":"Klair Kuchh",
    "wof:placetype":"locality"
},
  "geometry": {"coordinates":[62.22391999999999,25.49308],"type":"Point"}
}