{
  "type": "Feature",
  "properties": {
    "gn:admin1_code":"3.0",
    "gn:asciiname":"Dodba Banda",
    "gn:country_code":"PK",
    "gn:dem":2499,
    "gn:feature_class":"P",
    "gn:feature_code":"PPL",
    "gn:name":"Dodba Banda",
    "gn:population":0,
    "gn:timezone":"Asia/Karachi",
    "iso:country":"PK",
    "wof:name":"Dodba Banda",
    "wof:placetype":"locality"
},
  "geometry": {"coordinates":[71.93736,35.25119],"type":"Point"}
}