{
  "type": "Feature",
  "properties": {
    "gn:admin1_code":"04",
    "gn:asciiname":"Lange",
    "gn:country_code":"PK",
    "gn:dem":242,
    "gn:feature_class":"P",
    "gn:feature_code":"PPL",
    "gn:name":"Lange",
    "gn:population":0,
    "gn:timezone":"Asia/Karachi",
    "iso:country":"PK",
    "name:bel_x_preferred":[
        "\u041b\u0430\u043d\u0433\u044d"
    ],
    "name:cat_x_preferred":[
        "Lange"
    ],
    "name:ceb_x_preferred":[
        "Lange"
    ],
    "name:ces_x_preferred":[
        "Lange"
    ],
    "name:dan_x_preferred":[
        "Lange"
    ],
    "name:epo_x_preferred":[
        "Lange"
    ],
    "name:fin_x_preferred":[
        "Lange"
    ],
    "name:fra_x_preferred":[
        "Lange"
    ],
    "name:heb_x_preferred":[
        "\u05dc\u05e0\u05d2\u05d4"
    ],
    "name:ita_x_preferred":[
        "Lange"
    ],
    "name:jpn_x_preferred":[
        "\u30e9\u30f3\u30b2"
    ],
    "name:nld_x_preferred":[
        "Lange"
    ],
    "name:por_x_preferred":[
        "Lange"
    ],
    "name:rus_x_preferred":[
        "\u041b\u0430\u043d\u0433\u0435"
    ],
    "name:spa_x_preferred":[
        "Lange"
    ],
    "name:swe_x_preferred":[
        "Lange"
    ],
    "name:ukr_x_preferred":[
        "\u041b\u0430\u043d\u0433\u0435"
    ],
    "name:und_x_variant":[
        "Langge",
        "Langen",
        "Lange"
    ],
    "name:vol_x_preferred":[
        "Lange"
    ],
    "wof:name":"Lange",
    "wof:placetype":"locality"
},
  "geometry": {"coordinates":[74.64060000000001,32.32276],"type":"Point"}
}