{
  "type": "Feature",
  "properties": {
    "gn:admin1_code":"6",
    "gn:asciiname":"Mohra Batila",
    "gn:country_code":"PK",
    "gn:dem":1428,
    "gn:feature_class":"P",
    "gn:feature_code":"PPL",
    "gn:name":"Mohra Batila",
    "gn:population":0,
    "gn:timezone":"Asia/Karachi",
    "iso:country":"PK",
    "name:und_x_variant":[
        "Mohra Botila"
    ],
    "wof:name":"Mohra Batila",
    "wof:placetype":"locality"
},
  "geometry": {"coordinates":[74.15170999999999,33.42646],"type":"Point"}
}