{
  "type": "Feature",
  "properties": {
    "gn:admin1_code":"5",
    "gn:asciiname":"Goth Sheral Khan Marri",
    "gn:country_code":"PK",
    "gn:dem":24,
    "gn:feature_class":"P",
    "gn:feature_code":"PPL",
    "gn:name":"Goth Sheral Khan Marri",
    "gn:population":0,
    "gn:timezone":"Asia/Karachi",
    "iso:country":"PK",
    "name:und_x_variant":[
        "Goth Khandu Kh\u0101skheli"
    ],
    "wof:name":"Goth Sheral Khan Marri",
    "wof:placetype":"locality"
},
  "geometry": {"coordinates":[68.85636,25.84238],"type":"Point"}
}