{
  "type": "Feature",
  "properties": {
    "gn:admin1_code":"3.0",
    "gn:asciiname":"Phalla",
    "gn:country_code":"PK",
    "gn:dem":994,
    "gn:feature_class":"P",
    "gn:feature_code":"PPL",
    "gn:name":"Phalla",
    "gn:population":0,
    "gn:timezone":"Asia/Karachi",
    "iso:country":"PK",
    "name:eng_x_preferred":[
        "Phalia"
    ],
    "wof:name":"Phalla",
    "wof:placetype":"locality"
},
  "geometry": {"coordinates":[73.21876,33.86728],"type":"Point"}
}