{
  "type": "Feature",
  "properties": {
    "gn:admin1_code":"5",
    "gn:asciiname":"Sulaiman Rahu",
    "gn:country_code":"PK",
    "gn:dem":40,
    "gn:feature_class":"P",
    "gn:feature_code":"PPL",
    "gn:name":"Sulaiman Rahu",
    "gn:population":0,
    "gn:timezone":"Asia/Karachi",
    "iso:country":"PK",
    "wof:name":"Sulaiman Rahu",
    "wof:placetype":"locality"
},
  "geometry": {"coordinates":[68.05983000000001,26.44066],"type":"Point"}
}