{
  "type": "Feature",
  "properties": {
    "gn:admin1_code":"4.0",
    "gn:asciiname":"Khanuana",
    "gn:country_code":"PK",
    "gn:dem":168,
    "gn:feature_class":"P",
    "gn:feature_code":"PPL",
    "gn:name":"Khanuana",
    "gn:population":0,
    "gn:timezone":"Asia/Karachi",
    "iso:country":"PK",
    "name:und_x_variant":[
        "Khanu\u0101na"
    ],
    "wof:name":"Khanuana",
    "wof:placetype":"locality"
},
  "geometry": {"coordinates":[72.48288000000002,31.47999],"type":"Point"}
}