{
  "type": "Feature",
  "properties": {
    "gn:admin1_code":"5.0",
    "gn:asciiname":"Kitari",
    "gn:country_code":"PK",
    "gn:dem":132,
    "gn:feature_class":"P",
    "gn:feature_code":"PPL",
    "gn:name":"Kitari",
    "gn:population":0,
    "gn:timezone":"Asia/Karachi",
    "iso:country":"PK",
    "wof:name":"Kitari",
    "wof:placetype":"locality"
},
  "geometry": {"coordinates":[70.62281,25.19913],"type":"Point"}
}