{
  "type": "Feature",
  "properties": {
    "gn:admin1_code":"4",
    "gn:asciiname":"Mahmudwala",
    "gn:country_code":"PK",
    "gn:dem":135,
    "gn:feature_class":"P",
    "gn:feature_code":"PPL",
    "gn:name":"Mahmudwala",
    "gn:population":0,
    "gn:timezone":"Asia/Karachi",
    "iso:country":"PK",
    "name:und_x_variant":[
        "Mahm\u016bdew\u0101la"
    ],
    "wof:name":"Mahmudwala",
    "wof:placetype":"locality"
},
  "geometry": {"coordinates":[71.73835,30.42845],"type":"Point"}
}