{
  "type": "Feature",
  "properties": {
    "gn:admin1_code":"4.0",
    "gn:admin2_code":"7418964.0",
    "gn:asciiname":"Chak Misri",
    "gn:country_code":"PK",
    "gn:dem":808,
    "gn:feature_class":"P",
    "gn:feature_code":"PPL",
    "gn:name":"Chak Misri",
    "gn:population":0,
    "gn:timezone":"Asia/Karachi",
    "iso:country":"PK",
    "wof:name":"Chak Misri",
    "wof:placetype":"locality"
},
  "geometry": {"coordinates":[72.7025,32.71064000000001],"type":"Point"}
}