{
  "type": "Feature",
  "properties": {
    "gn:admin1_code":"4.0",
    "gn:asciiname":"Banda Salim Khan",
    "gn:country_code":"PK",
    "gn:dem":305,
    "gn:feature_class":"P",
    "gn:feature_code":"PPL",
    "gn:name":"B\u0101nda Sal\u012bm Kh\u0101n",
    "gn:population":0,
    "gn:timezone":"Asia/Karachi",
    "iso:country":"PK",
    "wof:name":"Banda Salim Khan",
    "wof:placetype":"locality"
},
  "geometry": {"coordinates":[71.18333,32.88333],"type":"Point"}
}