{
  "type": "Feature",
  "properties": {
    "gn:admin1_code":"2.0",
    "gn:asciiname":"Chagai",
    "gn:country_code":"PK",
    "gn:dem":854,
    "gn:feature_class":"P",
    "gn:feature_code":"PPL",
    "gn:name":"Chagai",
    "gn:population":0,
    "gn:timezone":"Asia/Karachi",
    "iso:country":"PK",
    "name:cat_x_preferred":[
        "Chagai"
    ],
    "name:snd_x_preferred":[
        "\u0686\u0627\u063a\u064a"
    ],
    "wof:name":"Chagai",
    "wof:placetype":"locality"
},
  "geometry": {"coordinates":[64.69750999999999,29.35393],"type":"Point"}
}