{
  "type": "Feature",
  "properties": {
    "gn:admin1_code":"4.0",
    "gn:asciiname":"Aslana Khu",
    "gn:country_code":"PK",
    "gn:dem":183,
    "gn:feature_class":"P",
    "gn:feature_code":"PPL",
    "gn:name":"Aslana Khu",
    "gn:population":0,
    "gn:timezone":"Asia/Karachi",
    "iso:country":"PK",
    "wof:name":"Aslana Khu",
    "wof:placetype":"locality"
},
  "geometry": {"coordinates":[73.62720999999998,30.96625],"type":"Point"}
}