{
  "type": "Feature",
  "properties": {
    "gn:admin1_code":"7.0",
    "gn:asciiname":"Bubind",
    "gn:country_code":"PK",
    "gn:dem":3295,
    "gn:feature_class":"P",
    "gn:feature_code":"PPL",
    "gn:name":"Bubind",
    "gn:population":0,
    "gn:timezone":"Asia/Karachi",
    "iso:country":"PK",
    "wof:name":"Bubind",
    "wof:placetype":"locality"
},
  "geometry": {"coordinates":[75.06354,35.22613],"type":"Point"}
}