{
  "type": "Feature",
  "properties": {
    "gn:admin1_code":"4.0",
    "gn:asciiname":"Tamri",
    "gn:country_code":"PK",
    "gn:dem":86,
    "gn:feature_class":"P",
    "gn:feature_code":"PPL",
    "gn:name":"Tamri",
    "gn:population":0,
    "gn:timezone":"Asia/Karachi",
    "iso:country":"PK",
    "name:ara_x_preferred":[
        "\u062a\u0627\u0645\u0631\u064a"
    ],
    "name:cat_x_preferred":[
        "Tamri"
    ],
    "name:ceb_x_preferred":[
        "Tamri"
    ],
    "name:eus_x_preferred":[
        "Tamri"
    ],
    "name:fra_x_preferred":[
        "Tamri"
    ],
    "name:ita_x_preferred":[
        "Tamri"
    ],
    "name:kat_x_preferred":[
        "\u10e2\u10d0\u10db\u10e0\u10d8"
    ],
    "name:por_x_preferred":[
        "Tamri"
    ],
    "name:swe_x_preferred":[
        "Tamri"
    ],
    "wof:name":"Tamri",
    "wof:placetype":"locality"
},
  "geometry": {"coordinates":[70.26104000000001,28.57742],"type":"Point"}
}