{
  "type": "Feature",
  "properties": {
    "gn:admin1_code":"2.0",
    "gn:asciiname":"Haji Abdur-Rahman",
    "gn:country_code":"PK",
    "gn:dem":1097,
    "gn:feature_class":"P",
    "gn:feature_code":"PPL",
    "gn:name":"Haji Abdur-Rahman",
    "gn:population":0,
    "gn:timezone":"Asia/Karachi",
    "iso:country":"PK",
    "wof:name":"Haji Abdur-Rahman",
    "wof:placetype":"locality"
},
  "geometry": {"coordinates":[68.53294,30.15489],"type":"Point"}
}