{
  "type": "Feature",
  "properties": {
    "gn:admin1_code":"04",
    "gn:asciiname":"Thatti Said Shamir",
    "gn:country_code":"PK",
    "gn:dem":173,
    "gn:feature_class":"P",
    "gn:feature_code":"PPL",
    "gn:name":"Thatti Said Shamir",
    "gn:population":0,
    "gn:timezone":"Asia/Karachi",
    "iso:country":"PK",
    "name:und_x_variant":[
        "Thatti Saiyid Shamir",
        "Thatti Said Sh\u0101hmir",
        "Thatti Said Shamir"
    ],
    "wof:name":"Thatti Said Shamir",
    "wof:placetype":"locality"
},
  "geometry": {"coordinates":[72.30249999999999,31.93596],"type":"Point"}
}