{
  "type": "Feature",
  "properties": {
    "gn:admin1_code":"4.0",
    "gn:asciiname":"Adalzai",
    "gn:country_code":"PK",
    "gn:dem":312,
    "gn:feature_class":"P",
    "gn:feature_code":"PPL",
    "gn:name":"Adalzai",
    "gn:population":0,
    "gn:timezone":"Asia/Karachi",
    "iso:country":"PK",
    "wof:name":"Adalzai",
    "wof:placetype":"locality"
},
  "geometry": {"coordinates":[72.46718,33.95366],"type":"Point"}
}