{
  "type": "Feature",
  "properties": {
    "gn:admin1_code":"3.0",
    "gn:asciiname":"Kattah Khel",
    "gn:country_code":"PK",
    "gn:dem":536,
    "gn:feature_class":"P",
    "gn:feature_code":"PPL",
    "gn:name":"Kattah Khel",
    "gn:population":0,
    "gn:timezone":"Asia/Karachi",
    "iso:country":"PK",
    "name:und_x_variant":[
        "Katta Khel",
        "Kattah Khel"
    ],
    "wof:name":"Kattah Khel",
    "wof:placetype":"locality"
},
  "geometry": {"coordinates":[71.05954,32.3624],"type":"Point"}
}