{
  "type": "Feature",
  "properties": {
    "gn:admin1_code":"3",
    "gn:asciiname":"Chhamber",
    "gn:country_code":"PK",
    "gn:dem":2340,
    "gn:feature_class":"P",
    "gn:feature_code":"PPL",
    "gn:name":"Chhamber",
    "gn:population":0,
    "gn:timezone":"Asia/Karachi",
    "iso:country":"PK",
    "name:und_x_variant":[
        "Chambar"
    ],
    "wof:name":"Chhamber",
    "wof:placetype":"locality"
},
  "geometry": {"coordinates":[73.61889000000002,34.87685],"type":"Point"}
}