{
  "type": "Feature",
  "properties": {
    "gn:admin1_code":"4.0",
    "gn:asciiname":"Basti Gaddani",
    "gn:country_code":"PK",
    "gn:dem":125,
    "gn:feature_class":"P",
    "gn:feature_code":"PPL",
    "gn:name":"Basti Gaddani",
    "gn:population":0,
    "gn:timezone":"Asia/Karachi",
    "iso:country":"PK",
    "name:und_x_variant":[
        "Gadden",
        "Gaddan",
        "Basti Gaddani"
    ],
    "wof:name":"Basti Gaddani",
    "wof:placetype":"locality"
},
  "geometry": {"coordinates":[72.00546999999997,29.48366],"type":"Point"}
}