{
  "type": "Feature",
  "properties": {
    "gn:admin1_code":"5",
    "gn:asciiname":"Mauladino Marfani",
    "gn:country_code":"PK",
    "gn:dem":60,
    "gn:feature_class":"P",
    "gn:feature_code":"PPL",
    "gn:name":"Mauladino Marfani",
    "gn:population":0,
    "gn:timezone":"Asia/Karachi",
    "iso:country":"PK",
    "name:und_x_variant":[
        "Mauledino M\u0101rf\u0101ni"
    ],
    "wof:name":"Mauladino Marfani",
    "wof:placetype":"locality"
},
  "geometry": {"coordinates":[68.42756999999999,28.10345],"type":"Point"}
}