{
  "type": "Feature",
  "properties": {
    "gn:admin1_code":"5.0",
    "gn:asciiname":"Goth Muhammad Isa Dad",
    "gn:country_code":"PK",
    "gn:dem":87,
    "gn:feature_class":"P",
    "gn:feature_code":"PPL",
    "gn:name":"Goth Muhammad Isa Dad",
    "gn:population":0,
    "gn:timezone":"Asia/Karachi",
    "iso:country":"PK",
    "wof:name":"Goth Muhammad Isa Dad",
    "wof:placetype":"locality"
},
  "geometry": {"coordinates":[67.10396999999999,25.08739],"type":"Point"}
}