{
  "type": "Feature",
  "properties": {
    "gn:admin1_code":"5",
    "gn:asciiname":"Qutab Baluch",
    "gn:country_code":"PK",
    "gn:dem":63,
    "gn:feature_class":"P",
    "gn:feature_code":"PPL",
    "gn:name":"Qutab Baluch",
    "gn:population":0,
    "gn:timezone":"Asia/Karachi",
    "iso:country":"PK",
    "name:und_x_variant":[
        "Qutab Beluch"
    ],
    "wof:name":"Qutab Baluch",
    "wof:placetype":"locality"
},
  "geometry": {"coordinates":[69.25928,27.86708],"type":"Point"}
}