{
  "type": "Feature",
  "properties": {
    "gn:admin1_code":"3",
    "gn:asciiname":"Sandapatai",
    "gn:country_code":"PK",
    "gn:dem":1771,
    "gn:feature_class":"P",
    "gn:feature_code":"PPL",
    "gn:name":"Sandapatai",
    "gn:population":0,
    "gn:timezone":"Asia/Karachi",
    "iso:country":"PK",
    "wof:name":"Sandapatai",
    "wof:placetype":"locality"
},
  "geometry": {"coordinates":[72.63531999999999,34.64064],"type":"Point"}
}