{
  "type": "Feature",
  "properties": {
    "gn:admin1_code":"4",
    "gn:asciiname":"Mirza Tahir",
    "gn:country_code":"PK",
    "gn:dem":244,
    "gn:feature_class":"P",
    "gn:feature_code":"PPL",
    "gn:name":"Mirza Tahir",
    "gn:population":0,
    "gn:timezone":"Asia/Karachi",
    "iso:country":"PK",
    "name:und_x_variant":[
        "T\u0101har"
    ],
    "wof:name":"Mirza Tahir",
    "wof:placetype":"locality"
},
  "geometry": {"coordinates":[73.77800999999999,32.73809],"type":"Point"}
}