{
  "type": "Feature",
  "properties": {
    "gn:admin1_code":"5.0",
    "gn:asciiname":"Goth Wali Muhammad Nahrio",
    "gn:country_code":"PK",
    "gn:dem":6,
    "gn:feature_class":"P",
    "gn:feature_code":"PPL",
    "gn:name":"Goth Wali Muhammad Nahrio",
    "gn:population":0,
    "gn:timezone":"Asia/Karachi",
    "iso:country":"PK",
    "name:und_x_variant":[
        "Goth Wali Muhammad Nahria"
    ],
    "wof:name":"Goth Wali Muhammad Nahrio",
    "wof:placetype":"locality"
},
  "geometry": {"coordinates":[68.28451,24.48146],"type":"Point"}
}