{
  "type": "Feature",
  "properties": {
    "gn:admin1_code":"2.0",
    "gn:asciiname":"Ucha Taki Coy L Ors",
    "gn:country_code":"PK",
    "gn:dem":2003,
    "gn:feature_class":"P",
    "gn:feature_code":"PPL",
    "gn:name":"Ucha Taki Coy L Ors",
    "gn:population":0,
    "gn:timezone":"Asia/Karachi",
    "iso:country":"PK",
    "name:und_x_variant":[
        "Ucha T\u0101ki"
    ],
    "wof:name":"Ucha Taki Coy L Ors",
    "wof:placetype":"locality"
},
  "geometry": {"coordinates":[67.86094,30.74335],"type":"Point"}
}