{
  "type": "Feature",
  "properties": {
    "gn:admin1_code":"3.0",
    "gn:asciiname":"Gatar",
    "gn:country_code":"PK",
    "gn:dem":210,
    "gn:feature_class":"P",
    "gn:feature_code":"PPL",
    "gn:name":"Gatar",
    "gn:population":0,
    "gn:timezone":"Asia/Karachi",
    "iso:country":"PK",
    "name:und_x_variant":[
        "\u012asa Gat\u0101r",
        "Gatar"
    ],
    "wof:name":"Gatar",
    "wof:placetype":"locality"
},
  "geometry": {"coordinates":[70.44674000000001,31.60699],"type":"Point"}
}