{
  "type": "Feature",
  "properties": {
    "gn:admin1_code":"4.0",
    "gn:asciiname":"Girot",
    "gn:country_code":"PK",
    "gn:dem":179,
    "gn:feature_class":"P",
    "gn:feature_code":"PPL",
    "gn:name":"Girot",
    "gn:population":0,
    "gn:timezone":"Asia/Karachi",
    "iso:country":"PK",
    "name:fas_x_preferred":[
        "\u06af\u0631\u0648\u062a"
    ],
    "name:und_x_variant":[
        "Girote",
        "Girot"
    ],
    "name:urd_x_preferred":[
        "\u06af\u0631\u0648\u0679"
    ],
    "wof:name":"Girot",
    "wof:placetype":"locality"
},
  "geometry": {"coordinates":[72.27405999999998,32.08582],"type":"Point"}
}