{
  "type": "Feature",
  "properties": {
    "gn:admin1_code":"2.0",
    "gn:asciiname":"Bagdar Pisi",
    "gn:country_code":"PK",
    "gn:dem":35,
    "gn:feature_class":"P",
    "gn:feature_code":"PPL",
    "gn:name":"Bagdar Pisi",
    "gn:population":0,
    "gn:timezone":"Asia/Karachi",
    "iso:country":"PK",
    "wof:name":"Bagdar Pisi",
    "wof:placetype":"locality"
},
  "geometry": {"coordinates":[62.11184,25.72885],"type":"Point"}
}