{
  "type": "Feature",
  "properties": {
    "gn:admin1_code":"3",
    "gn:asciiname":"Razzaq",
    "gn:country_code":"PK",
    "gn:dem":1194,
    "gn:feature_class":"P",
    "gn:feature_code":"PPL",
    "gn:name":"Razzaq",
    "gn:population":0,
    "gn:timezone":"Asia/Karachi",
    "iso:country":"PK",
    "wof:name":"Razzaq",
    "wof:placetype":"locality"
},
  "geometry": {"coordinates":[73.02999,34.34924],"type":"Point"}
}