{
  "type": "Feature",
  "properties": {
    "gn:admin1_code":"3",
    "gn:asciiname":"Razzaq",
    "gn:country_code":"PK",
    "gn:dem":1194,
    "gn:feature_class":"P",
    "gn:feature_code":"PPL",
    "gn:name":"Razzaq",
    "gn:population":0,
    "gn:timezone":"Asia/Karachi",
    "iso:country":"PK",
    "name:ara_x_preferred":[
        "\u0627\u0644\u0631\u0632\u0627\u0642"
    ],
    "name:aze_x_preferred":[
        "\u018fr-Razz\u0259q"
    ],
    "name:deu_x_preferred":[
        "Razzaq"
    ],
    "name:fas_x_preferred":[
        "\u0631\u0632\u0627\u0642"
    ],
    "name:tat_x_preferred":[
        "\u04d8\u0440-\u0420\u0430\u0437\u0437\u04d9\u043a"
    ],
    "name:urd_x_preferred":[
        "\u0627\u0644\u0631\u0632\u0627\u0642"
    ],
    "name:uzb_x_preferred":[
        "Ar-Razak"
    ],
    "wof:name":"Razzaq",
    "wof:placetype":"locality"
},
  "geometry": {"coordinates":[73.02999,34.34924],"type":"Point"}
}