{
  "type": "Feature",
  "properties": {
    "gn:admin1_code":"3",
    "gn:asciiname":"Qadira Banda",
    "gn:country_code":"PK",
    "gn:dem":1251,
    "gn:feature_class":"P",
    "gn:feature_code":"PPL",
    "gn:name":"Qadira Banda",
    "gn:population":0,
    "gn:timezone":"Asia/Karachi",
    "iso:country":"PK",
    "wof:name":"Qadira Banda",
    "wof:placetype":"locality"
},
  "geometry": {"coordinates":[72.96566999999997,34.77559],"type":"Point"}
}