{
  "type": "Feature",
  "properties": {
    "gn:admin1_code":"2.0",
    "gn:asciiname":"Surna Kach",
    "gn:country_code":"PK",
    "gn:dem":1876,
    "gn:feature_class":"P",
    "gn:feature_code":"PPL",
    "gn:name":"Surna Kach",
    "gn:population":0,
    "gn:timezone":"Asia/Karachi",
    "iso:country":"PK",
    "name:eng_x_preferred":[
        "Surna Kach"
    ],
    "wof:name":"Surna Kach",
    "wof:placetype":"locality"
},
  "geometry": {"coordinates":[67.14373000000001,30.82541],"type":"Point"}
}