{
  "type": "Feature",
  "properties": {
    "gn:admin1_code":"2.0",
    "gn:asciiname":"Goth Kocha",
    "gn:country_code":"PK",
    "gn:dem":290,
    "gn:feature_class":"P",
    "gn:feature_code":"PPL",
    "gn:name":"Goth Kocha",
    "gn:population":0,
    "gn:timezone":"Asia/Karachi",
    "iso:country":"PK",
    "wof:name":"Goth Kocha",
    "wof:placetype":"locality"
},
  "geometry": {"coordinates":[67.17787,26.1449],"type":"Point"}
}