{
  "type": "Feature",
  "properties": {
    "gn:admin1_code":"1.0",
    "gn:asciiname":"Sappare",
    "gn:country_code":"PK",
    "gn:dem":549,
    "gn:feature_class":"P",
    "gn:feature_code":"PPL",
    "gn:name":"Sappare",
    "gn:population":0,
    "gn:timezone":"Asia/Karachi",
    "iso:country":"PK",
    "name:eng_x_preferred":[
        "Sappare"
    ],
    "name:und_x_variant":[
        "K\u016bz Tsapparai"
    ],
    "wof:name":"Sappare",
    "wof:placetype":"locality"
},
  "geometry": {"coordinates":[71.56026,34.36011],"type":"Point"}
}