{
  "type": "Feature",
  "properties": {
    "gn:admin1_code":"1.0",
    "gn:asciiname":"Ranguta Bagal",
    "gn:country_code":"PK",
    "gn:dem":2049,
    "gn:feature_class":"P",
    "gn:feature_code":"PPL",
    "gn:name":"Ranguta Bagal",
    "gn:population":0,
    "gn:timezone":"Asia/Karachi",
    "iso:country":"PK",
    "name:und_x_variant":[
        "Ranguto Bagal"
    ],
    "wof:name":"Ranguta Bagal",
    "wof:placetype":"locality"
},
  "geometry": {"coordinates":[70.3069,33.88758],"type":"Point"}
}