{
  "type": "Feature",
  "properties": {
    "gn:admin1_code":"6.0",
    "gn:asciiname":"Danja",
    "gn:country_code":"PK",
    "gn:dem":1430,
    "gn:feature_class":"P",
    "gn:feature_code":"PPL",
    "gn:name":"Danja",
    "gn:population":0,
    "gn:timezone":"Asia/Karachi",
    "iso:country":"PK",
    "name:ceb_x_preferred":[
        "Danja"
    ],
    "name:fra_x_preferred":[
        "Danja"
    ],
    "name:hun_x_preferred":[
        "Danja"
    ],
    "name:ita_x_preferred":[
        "Danja"
    ],
    "wof:name":"Danja",
    "wof:placetype":"locality"
},
  "geometry": {"coordinates":[73.67891,33.74088],"type":"Point"}
}