{
  "type": "Feature",
  "properties": {
    "gn:admin1_code":"7.0",
    "gn:asciiname":"Katpana",
    "gn:country_code":"PK",
    "gn:dem":2194,
    "gn:feature_class":"P",
    "gn:feature_code":"PPL",
    "gn:name":"Katpana",
    "gn:population":0,
    "gn:timezone":"Asia/Karachi",
    "iso:country":"PK",
    "name:und_x_variant":[
        "Kapashna"
    ],
    "wof:name":"Katpana",
    "wof:placetype":"locality"
},
  "geometry": {"coordinates":[75.58049,35.31937],"type":"Point"}
}