{
  "type": "Feature",
  "properties": {
    "gn:admin1_code":"03",
    "gn:asciiname":"Malli Khel Bala",
    "gn:country_code":"PK",
    "gn:dem":626,
    "gn:feature_class":"P",
    "gn:feature_code":"PPL",
    "gn:name":"Malli Khel Bala",
    "gn:population":0,
    "gn:timezone":"Asia/Karachi",
    "iso:country":"PK",
    "name:und_x_variant":[
        "Malli Khel",
        "Mali Khel",
        "Bar Malli Khel",
        "Malli Khel Bala"
    ],
    "wof:name":"Malli Khel Bala",
    "wof:placetype":"locality"
},
  "geometry": {"coordinates":[72.10963000000002,33.89384],"type":"Point"}
}