{
  "type": "Feature",
  "properties": {
    "gn:admin1_code":"5",
    "gn:asciiname":"Goth Dewan Baso Mal",
    "gn:country_code":"PK",
    "gn:dem":12,
    "gn:feature_class":"P",
    "gn:feature_code":"PPL",
    "gn:name":"Goth Dewan Baso Mal",
    "gn:population":0,
    "gn:timezone":"Asia/Karachi",
    "iso:country":"PK",
    "name:und_x_variant":[
        "Goth B\u0101reji"
    ],
    "wof:name":"Goth Dewan Baso Mal",
    "wof:placetype":"locality"
},
  "geometry": {"coordinates":[69.22190000000001,25.48153],"type":"Point"}
}