{
  "type": "Feature",
  "properties": {
    "gn:admin1_code":"3.0",
    "gn:asciiname":"Shimlai",
    "gn:country_code":"PK",
    "gn:dem":1352,
    "gn:feature_class":"P",
    "gn:feature_code":"PPL",
    "gn:name":"Shimlai",
    "gn:population":0,
    "gn:timezone":"Asia/Karachi",
    "iso:country":"PK",
    "wof:name":"Shimlai",
    "wof:placetype":"locality"
},
  "geometry": {"coordinates":[73.20228,34.17276],"type":"Point"}
}