{
  "type": "Feature",
  "properties": {
    "gn:admin1_code":"5",
    "gn:asciiname":"Goth Qazi Badal Mahar",
    "gn:country_code":"PK",
    "gn:dem":66,
    "gn:feature_class":"P",
    "gn:feature_code":"PPL",
    "gn:name":"Goth Qazi Badal Mahar",
    "gn:population":0,
    "gn:timezone":"Asia/Karachi",
    "iso:country":"PK",
    "name:und_x_variant":[
        "Goth Q\u0101zi Mahar",
        "Goth Q\u0101zi",
        "Goth Qazi Badal Mahar"
    ],
    "wof:name":"Goth Qazi Badal Mahar",
    "wof:placetype":"locality"
},
  "geometry": {"coordinates":[69.2881,27.84515],"type":"Point"}
}