{
  "type": "Feature",
  "properties": {
    "gn:admin1_code":"1.0",
    "gn:asciiname":"Faqiran",
    "gn:country_code":"PK",
    "gn:dem":1387,
    "gn:feature_class":"P",
    "gn:feature_code":"PPL",
    "gn:name":"Faqiran",
    "gn:population":0,
    "gn:timezone":"Asia/Karachi",
    "iso:country":"PK",
    "name:und_x_variant":[
        "Faq\u012br\u0101n"
    ],
    "wof:name":"Faqiran",
    "wof:placetype":"locality"
},
  "geometry": {"coordinates":[70.83091999999998,33.65361],"type":"Point"}
}