{
  "type": "Feature",
  "properties": {
    "gn:admin1_code":"4",
    "gn:asciiname":"Chanor",
    "gn:country_code":"PK",
    "gn:dem":258,
    "gn:feature_class":"P",
    "gn:feature_code":"PPL",
    "gn:name":"Chanor",
    "gn:population":0,
    "gn:timezone":"Asia/Karachi",
    "iso:country":"PK",
    "wof:name":"Chanor",
    "wof:placetype":"locality"
},
  "geometry": {"coordinates":[74.65209,32.71731],"type":"Point"}
}