{
  "type": "Feature",
  "properties": {
    "gn:admin1_code":"6.0",
    "gn:asciiname":"Desah",
    "gn:country_code":"PK",
    "gn:dem":1620,
    "gn:feature_class":"P",
    "gn:feature_code":"PPL",
    "gn:name":"Desah",
    "gn:population":0,
    "gn:timezone":"Asia/Karachi",
    "iso:country":"PK",
    "wof:name":"Desah",
    "wof:placetype":"locality"
},
  "geometry": {"coordinates":[73.85639999999999,33.71107],"type":"Point"}
}