{
  "type": "Feature",
  "properties": {
    "gn:admin1_code":"04",
    "gn:asciiname":"Joia Musalli",
    "gn:country_code":"PK",
    "gn:dem":160,
    "gn:feature_class":"P",
    "gn:feature_code":"PPL",
    "gn:name":"Joia Musalli",
    "gn:population":0,
    "gn:timezone":"Asia/Karachi",
    "iso:country":"PK",
    "name:und_x_variant":[
        "Musalli",
        "Thatti Musalli",
        "Joia Musalli"
    ],
    "wof:name":"Joia Musalli",
    "wof:placetype":"locality"
},
  "geometry": {"coordinates":[72.10991999999997,31.48978],"type":"Point"}
}