{
  "type": "Feature",
  "properties": {
    "gn:admin1_code":"5.0",
    "gn:asciiname":"Goth Naik Muhammad",
    "gn:country_code":"PK",
    "gn:dem":104,
    "gn:feature_class":"P",
    "gn:feature_code":"PPL",
    "gn:name":"Goth Naik Muhammad",
    "gn:population":0,
    "gn:timezone":"Asia/Karachi",
    "iso:country":"PK",
    "wof:name":"Goth Naik Muhammad",
    "wof:placetype":"locality"
},
  "geometry": {"coordinates":[67.10262,25.12151],"type":"Point"}
}