{
  "type": "Feature",
  "properties": {
    "gn:admin1_code":"4.0",
    "gn:asciiname":"Bhaitian di Bhini",
    "gn:country_code":"PK",
    "gn:dem":130,
    "gn:feature_class":"P",
    "gn:feature_code":"PPL",
    "gn:name":"Bhaitian di Bhini",
    "gn:population":0,
    "gn:timezone":"Asia/Karachi",
    "iso:country":"PK",
    "wof:name":"Bhaitian di Bhini",
    "wof:placetype":"locality"
},
  "geometry": {"coordinates":[71.97060999999999,30.12793],"type":"Point"}
}