{
  "type": "Feature",
  "properties": {
    "gn:admin1_code":"4",
    "gn:asciiname":"Chak One Hundred Nine Jhang Branch",
    "gn:country_code":"PK",
    "gn:dem":188,
    "gn:feature_class":"P",
    "gn:feature_code":"PPL",
    "gn:name":"Chak One Hundred Nine Jhang Branch",
    "gn:population":0,
    "gn:timezone":"Asia/Karachi",
    "iso:country":"PK",
    "name:und_x_variant":[
        "Chak One Hundred Nine",
        "Chak Tiw\u0101na",
        "Chak One Hundred Nine Jhang Branch",
        "Nilli\u0101nw\u0101la"
    ],
    "wof:name":"Chak One Hundred Nine Jhang Branch",
    "wof:placetype":"locality"
},
  "geometry": {"coordinates":[73.12826,31.58489],"type":"Point"}
}