{
  "type": "Feature",
  "properties": {
    "gn:admin1_code":"2.0",
    "gn:asciiname":"Yar Muhammad",
    "gn:country_code":"PK",
    "gn:dem":1815,
    "gn:feature_class":"P",
    "gn:feature_code":"PPL",
    "gn:name":"Yar Muhammad",
    "gn:population":0,
    "gn:timezone":"Asia/Karachi",
    "iso:country":"PK",
    "wof:name":"Yar Muhammad",
    "wof:placetype":"locality"
},
  "geometry": {"coordinates":[66.80790999999999,28.7272],"type":"Point"}
}