{
  "type": "Feature",
  "properties": {
    "gn:admin1_code":"3.0",
    "gn:asciiname":"Shamsuddin",
    "gn:country_code":"PK",
    "gn:dem":1271,
    "gn:feature_class":"P",
    "gn:feature_code":"PPL",
    "gn:name":"Shamsuddin",
    "gn:population":0,
    "gn:timezone":"Asia/Karachi",
    "iso:country":"PK",
    "name:und_x_variant":[
        "Shamsudd\u012bn Kili"
    ],
    "wof:name":"Shamsuddin",
    "wof:placetype":"locality"
},
  "geometry": {"coordinates":[70.80540000000001,33.54854],"type":"Point"}
}