{
  "type": "Feature",
  "properties": {
    "gn:admin1_code":"3.0",
    "gn:asciiname":"Sabandi",
    "gn:country_code":"PK",
    "gn:dem":390,
    "gn:feature_class":"P",
    "gn:feature_code":"PPL",
    "gn:name":"Sabandi",
    "gn:population":0,
    "gn:timezone":"Asia/Karachi",
    "iso:country":"PK",
    "name:eng_x_preferred":[
        "Sadull\u0101h Mi\u0101n Kor\u016bna"
    ],
    "wof:name":"Sabandi",
    "wof:placetype":"locality"
},
  "geometry": {"coordinates":[71.81515999999998,34.32941],"type":"Point"}
}