{
  "type": "Feature",
  "properties": {
    "gn:admin1_code":"3",
    "gn:asciiname":"Khabbal Pain",
    "gn:country_code":"PK",
    "gn:dem":1853,
    "gn:feature_class":"P",
    "gn:feature_code":"PPL",
    "gn:name":"Khabbal Pain",
    "gn:population":0,
    "gn:timezone":"Asia/Karachi",
    "iso:country":"PK",
    "name:und_x_variant":[
        "Khabbal Tarla"
    ],
    "wof:name":"Khabbal Pain",
    "wof:placetype":"locality"
},
  "geometry": {"coordinates":[73.03664999999999,34.54618],"type":"Point"}
}