{
  "type": "Feature",
  "properties": {
    "gn:admin1_code":"3.0",
    "gn:asciiname":"Lohar Gali",
    "gn:country_code":"PK",
    "gn:dem":1197,
    "gn:feature_class":"P",
    "gn:feature_code":"PPL",
    "gn:name":"Lohar Gali",
    "gn:population":0,
    "gn:timezone":"Asia/Karachi",
    "iso:country":"PK",
    "wof:name":"Lohar Gali",
    "wof:placetype":"locality"
},
  "geometry": {"coordinates":[73.41746999999999,34.3332],"type":"Point"}
}