{
  "type": "Feature",
  "properties": {
    "gn:admin1_code":"2.0",
    "gn:asciiname":"Hassan Jui",
    "gn:country_code":"PK",
    "gn:dem":1501,
    "gn:feature_class":"P",
    "gn:feature_code":"PPL",
    "gn:name":"Hassan Jui",
    "gn:population":0,
    "gn:timezone":"Asia/Karachi",
    "iso:country":"PK",
    "wof:name":"Hassan Jui",
    "wof:placetype":"locality"
},
  "geometry": {"coordinates":[67.12505,29.234],"type":"Point"}
}