{
  "type": "Feature",
  "properties": {
    "gn:admin1_code":"6",
    "gn:asciiname":"Banjuta",
    "gn:country_code":"PK",
    "gn:dem":1056,
    "gn:feature_class":"P",
    "gn:feature_code":"PPL",
    "gn:name":"Banjuta",
    "gn:population":0,
    "gn:timezone":"Asia/Karachi",
    "iso:country":"PK",
    "name:und_x_variant":[
        "N\u0101r"
    ],
    "wof:name":"Banjuta",
    "wof:placetype":"locality"
},
  "geometry": {"coordinates":[73.76156999999998,33.67227],"type":"Point"}
}