{
  "type": "Feature",
  "properties": {
    "gn:admin1_code":"1.0",
    "gn:asciiname":"Khadar Ziarat",
    "gn:country_code":"PK",
    "gn:dem":827,
    "gn:feature_class":"P",
    "gn:feature_code":"PPL",
    "gn:name":"Khadar Ziarat",
    "gn:population":0,
    "gn:timezone":"Asia/Karachi",
    "iso:country":"PK",
    "wof:name":"Khadar Ziarat",
    "wof:placetype":"locality"
},
  "geometry": {"coordinates":[70.36886,32.59525],"type":"Point"}
}