{
  "type": "Feature",
  "properties": {
    "gn:admin1_code":"04",
    "gn:asciiname":"Sahnpal",
    "gn:country_code":"PK",
    "gn:dem":213,
    "gn:feature_class":"P",
    "gn:feature_code":"PPL",
    "gn:name":"Sahnpal",
    "gn:population":0,
    "gn:timezone":"Asia/Karachi",
    "iso:country":"PK",
    "name:und_x_variant":[
        "S\u0101hanp\u0101l"
    ],
    "wof:name":"Sahnpal",
    "wof:placetype":"locality"
},
  "geometry": {"coordinates":[73.72816999999998,32.38454],"type":"Point"}
}