{
  "type": "Feature",
  "properties": {
    "gn:admin1_code":"4",
    "gn:asciiname":"Kot Pir Fazl",
    "gn:country_code":"PK",
    "gn:dem":199,
    "gn:feature_class":"P",
    "gn:feature_code":"PPL",
    "gn:name":"Kot P\u012br Fazl",
    "gn:population":0,
    "gn:timezone":"Asia/Karachi",
    "iso:country":"PK",
    "wof:name":"Kot Pir Fazl",
    "wof:placetype":"locality"
},
  "geometry": {"coordinates":[73.95416999999998,31.21111],"type":"Point"}
}