{
  "type": "Feature",
  "properties": {
    "gn:admin1_code":"5.0",
    "gn:asciiname":"Goth Mian Muhammad Rajpar",
    "gn:country_code":"PK",
    "gn:dem":41,
    "gn:feature_class":"P",
    "gn:feature_code":"PPL",
    "gn:name":"Goth Mian Muhammad Rajpar",
    "gn:population":0,
    "gn:timezone":"Asia/Karachi",
    "iso:country":"PK",
    "wof:name":"Goth Mian Muhammad Rajpar",
    "wof:placetype":"locality"
},
  "geometry": {"coordinates":[68.40666999999999,26.7073],"type":"Point"}
}