{
  "type": "Feature",
  "properties": {
    "gn:admin1_code":"4.0",
    "gn:asciiname":"Chak Forty-three - Four Left",
    "gn:country_code":"PK",
    "gn:dem":165,
    "gn:feature_class":"P",
    "gn:feature_code":"PPL",
    "gn:name":"Chak Forty-three - Four Left",
    "gn:population":0,
    "gn:timezone":"Asia/Karachi",
    "iso:country":"PK",
    "name:und_x_variant":[
        "Jaipur"
    ],
    "wof:name":"Chak Forty-three - Four Left",
    "wof:placetype":"locality"
},
  "geometry": {"coordinates":[73.30386,30.57677],"type":"Point"}
}