{
  "type": "Feature",
  "properties": {
    "gn:admin1_code":"2.0",
    "gn:asciiname":"Mikkis Ki Dak",
    "gn:country_code":"PK",
    "gn:dem":38,
    "gn:feature_class":"P",
    "gn:feature_code":"PPL",
    "gn:name":"Mikkis Ki Dak",
    "gn:population":0,
    "gn:timezone":"Asia/Karachi",
    "iso:country":"PK",
    "wof:name":"Mikkis Ki Dak",
    "wof:placetype":"locality"
},
  "geometry": {"coordinates":[63.14363,25.48852],"type":"Point"}
}