{
  "type": "Feature",
  "properties": {
    "gn:admin1_code":"2.0",
    "gn:asciiname":"Kili Waris Khan",
    "gn:country_code":"PK",
    "gn:dem":916,
    "gn:feature_class":"P",
    "gn:feature_code":"PPL",
    "gn:name":"Kili Waris Khan",
    "gn:population":0,
    "gn:timezone":"Asia/Karachi",
    "iso:country":"PK",
    "wof:name":"Kili Waris Khan",
    "wof:placetype":"locality"
},
  "geometry": {"coordinates":[65.45068000000001,28.83833],"type":"Point"}
}