{
  "type": "Feature",
  "properties": {
    "gn:admin1_code":"4",
    "gn:asciiname":"Nune Bhikhi",
    "gn:country_code":"PK",
    "gn:dem":234,
    "gn:feature_class":"P",
    "gn:feature_code":"PPL",
    "gn:name":"Nune Bhikhi",
    "gn:population":0,
    "gn:timezone":"Asia/Karachi",
    "iso:country":"PK",
    "name:und_x_variant":[
        "N\u016bne Bhikni"
    ],
    "wof:name":"Nune Bhikhi",
    "wof:placetype":"locality"
},
  "geometry": {"coordinates":[74.60852,32.24865],"type":"Point"}
}