{
  "type": "Feature",
  "properties": {
    "gn:admin1_code":"2.0",
    "gn:asciiname":"Jamalzai",
    "gn:country_code":"PK",
    "gn:dem":1894,
    "gn:feature_class":"P",
    "gn:feature_code":"PPL",
    "gn:name":"Jamalzai",
    "gn:population":0,
    "gn:timezone":"Asia/Karachi",
    "iso:country":"PK",
    "wof:name":"Jamalzai",
    "wof:placetype":"locality"
},
  "geometry": {"coordinates":[66.31211,28.8791],"type":"Point"}
}