{
  "type": "Feature",
  "properties": {
    "gn:admin1_code":"3.0",
    "gn:asciiname":"Sanek",
    "gn:country_code":"PK",
    "gn:dem":2584,
    "gn:feature_class":"P",
    "gn:feature_code":"PPL",
    "gn:name":"Sanek",
    "gn:population":0,
    "gn:timezone":"Asia/Karachi",
    "iso:country":"PK",
    "wof:name":"Sanek",
    "wof:placetype":"locality"
},
  "geometry": {"coordinates":[71.54071,35.9724],"type":"Point"}
}