{
  "type": "Feature",
  "properties": {
    "gn:admin1_code":"3",
    "gn:asciiname":"Mohra",
    "gn:country_code":"PK",
    "gn:dem":776,
    "gn:feature_class":"P",
    "gn:feature_code":"PPL",
    "gn:name":"Mohra",
    "gn:population":0,
    "gn:timezone":"Asia/Karachi",
    "iso:country":"PK",
    "wof:name":"Mohra",
    "wof:placetype":"locality"
},
  "geometry": {"coordinates":[73.07080000000001,34.0994],"type":"Point"}
}