{
  "type": "Feature",
  "properties": {
    "gn:admin1_code":"4",
    "gn:asciiname":"Thatta Rawan",
    "gn:country_code":"PK",
    "gn:dem":224,
    "gn:feature_class":"P",
    "gn:feature_code":"PPL",
    "gn:name":"Thatta Rawan",
    "gn:population":0,
    "gn:timezone":"Asia/Karachi",
    "iso:country":"PK",
    "name:und_x_variant":[
        "Thatta Raw\u0101n da"
    ],
    "wof:name":"Thatta Rawan",
    "wof:placetype":"neighbourhood"
},
  "geometry": {"coordinates":[74.24865,32.14767],"type":"Point"}
}