{
  "type": "Feature",
  "properties": {
    "gn:admin1_code":"4.0",
    "gn:asciiname":"Khurpa Chak",
    "gn:country_code":"PK",
    "gn:dem":207,
    "gn:feature_class":"P",
    "gn:feature_code":"PPL",
    "gn:name":"Khurpa Chak",
    "gn:population":0,
    "gn:timezone":"Asia/Karachi",
    "iso:country":"PK",
    "name:und_x_variant":[
        "Khurpe Chak"
    ],
    "wof:name":"Khurpa Chak",
    "wof:placetype":"locality"
},
  "geometry": {"coordinates":[74.27042,31.25973],"type":"Point"}
}