{
  "type": "Feature",
  "properties": {
    "gn:admin1_code":"4",
    "gn:asciiname":"Ramanwala",
    "gn:country_code":"PK",
    "gn:dem":130,
    "gn:feature_class":"P",
    "gn:feature_code":"PPL",
    "gn:name":"Ramanwala",
    "gn:population":0,
    "gn:timezone":"Asia/Karachi",
    "iso:country":"PK",
    "name:eng_x_preferred":[
        "Ramanwala"
    ],
    "wof:name":"Ramanwala",
    "wof:placetype":"locality"
},
  "geometry": {"coordinates":[70.72441999999999,30.32221],"type":"Point"}
}