{
  "type": "Feature",
  "properties": {
    "gn:admin1_code":"4.0",
    "gn:asciiname":"Malkuko Kha",
    "gn:country_code":"PK",
    "gn:dem":176,
    "gn:feature_class":"P",
    "gn:feature_code":"PPL",
    "gn:name":"Malkuko Kha",
    "gn:population":0,
    "gn:timezone":"Asia/Karachi",
    "iso:country":"PK",
    "name:und_x_variant":[
        "Malku Ka Khu"
    ],
    "wof:name":"Malkuko Kha",
    "wof:placetype":"locality"
},
  "geometry": {"coordinates":[72.76501,31.58694],"type":"Point"}
}