{
  "type": "Feature",
  "properties": {
    "gn:admin1_code":"4",
    "gn:asciiname":"Chah Sabit Kharral",
    "gn:country_code":"PK",
    "gn:dem":156,
    "gn:feature_class":"P",
    "gn:feature_code":"PPL",
    "gn:name":"Chah Sabit Kharral",
    "gn:population":0,
    "gn:timezone":"Asia/Karachi",
    "iso:country":"PK",
    "wof:name":"Chah Sabit Kharral",
    "wof:placetype":"locality"
},
  "geometry": {"coordinates":[72.59721999999999,30.63333],"type":"Point"}
}