{
  "type": "Feature",
  "properties": {
    "gn:admin1_code":"4",
    "gn:asciiname":"Basti Baluchian",
    "gn:country_code":"PK",
    "gn:dem":99,
    "gn:feature_class":"P",
    "gn:feature_code":"PPL",
    "gn:name":"Basti Baluchian",
    "gn:population":0,
    "gn:timezone":"Asia/Karachi",
    "iso:country":"PK",
    "name:und_x_variant":[
        "M\u016bsa Hora"
    ],
    "wof:name":"Basti Baluchian",
    "wof:placetype":"locality"
},
  "geometry": {"coordinates":[70.45683000000002,29.33041],"type":"Point"}
}