{
  "type": "Feature",
  "properties": {
    "gn:admin1_code":"6.0",
    "gn:asciiname":"Nagaithal",
    "gn:country_code":"PK",
    "gn:dem":2052,
    "gn:feature_class":"P",
    "gn:feature_code":"PPL",
    "gn:name":"Nagaithal",
    "gn:population":0,
    "gn:timezone":"Asia/Karachi",
    "iso:country":"PK",
    "name:und_x_variant":[
        "N\u0101ge Thul"
    ],
    "wof:name":"Nagaithal",
    "wof:placetype":"locality"
},
  "geometry": {"coordinates":[73.7175,33.743],"type":"Point"}
}