{
  "type": "Feature",
  "properties": {
    "gn:admin1_code":"2.0",
    "gn:asciiname":"Takri Rahmat Shah",
    "gn:country_code":"PK",
    "gn:dem":113,
    "gn:feature_class":"P",
    "gn:feature_code":"PPL",
    "gn:name":"Takri Rahmat Shah",
    "gn:population":0,
    "gn:timezone":"Asia/Karachi",
    "iso:country":"PK",
    "wof:name":"Takri Rahmat Shah",
    "wof:placetype":"locality"
},
  "geometry": {"coordinates":[67.43631999999999,29.00319],"type":"Point"}
}