{
  "type": "Feature",
  "properties": {
    "gn:admin1_code":"5.0",
    "gn:asciiname":"Shahmir ji Dhani",
    "gn:country_code":"PK",
    "gn:dem":44,
    "gn:feature_class":"P",
    "gn:feature_code":"PPL",
    "gn:name":"Shahmir ji Dhani",
    "gn:population":0,
    "gn:timezone":"Asia/Karachi",
    "iso:country":"PK",
    "wof:name":"Shahmir ji Dhani",
    "wof:placetype":"locality"
},
  "geometry": {"coordinates":[69.83738000000001,25.51906],"type":"Point"}
}