{
  "type": "Feature",
  "properties": {
    "gn:admin1_code":"4",
    "gn:asciiname":"Nur Ahmedwali Bhaini",
    "gn:country_code":"PK",
    "gn:dem":158,
    "gn:feature_class":"P",
    "gn:feature_code":"PPL",
    "gn:name":"Nur Ahmedwali Bhaini",
    "gn:population":0,
    "gn:timezone":"Asia/Karachi",
    "iso:country":"PK",
    "name:und_x_variant":[
        "Hay\u0101t ke K\u0101thia"
    ],
    "wof:name":"Nur Ahmedwali Bhaini",
    "wof:placetype":"locality"
},
  "geometry": {"coordinates":[72.66908000000002,30.5857],"type":"Point"}
}