{
  "type": "Feature",
  "properties": {
    "gn:admin1_code":"3.0",
    "gn:asciiname":"Daman Dok",
    "gn:country_code":"PK",
    "gn:dem":2353,
    "gn:feature_class":"P",
    "gn:feature_code":"PPL",
    "gn:name":"Daman Dok",
    "gn:population":0,
    "gn:timezone":"Asia/Karachi",
    "iso:country":"PK",
    "name:eng_x_preferred":[
        "Daman Dok"
    ],
    "wof:name":"Daman Dok",
    "wof:placetype":"locality"
},
  "geometry": {"coordinates":[72.01961999999997,35.92215],"type":"Point"}
}