{
  "type": "Feature",
  "properties": {
    "gn:admin1_code":"3.0",
    "gn:asciiname":"Pandi",
    "gn:country_code":"PK",
    "gn:dem":1547,
    "gn:feature_class":"P",
    "gn:feature_code":"PPL",
    "gn:name":"Pandi",
    "gn:population":0,
    "gn:timezone":"Asia/Karachi",
    "iso:country":"PK",
    "name:ceb_x_preferred":[
        "Pandi"
    ],
    "name:deu_x_preferred":[
        "Pandi"
    ],
    "name:ita_x_preferred":[
        "Pandi"
    ],
    "name:nld_x_preferred":[
        "Pandi"
    ],
    "name:swe_x_preferred":[
        "Pandi"
    ],
    "name:war_x_preferred":[
        "Pandi"
    ],
    "wof:name":"Pandi",
    "wof:placetype":"locality"
},
  "geometry": {"coordinates":[73.46848,34.17437],"type":"Point"}
}