{
  "type": "Feature",
  "properties": {
    "gn:admin1_code":"4.0",
    "gn:asciiname":"Zain Shahid",
    "gn:country_code":"PK",
    "gn:dem":568,
    "gn:feature_class":"P",
    "gn:feature_code":"PPL",
    "gn:name":"Zain Shahid",
    "gn:population":0,
    "gn:timezone":"Asia/Karachi",
    "iso:country":"PK",
    "wof:name":"Zain Shahid",
    "wof:placetype":"locality"
},
  "geometry": {"coordinates":[70.46834,30.58736],"type":"Point"}
}