{
  "type": "Feature",
  "properties": {
    "gn:admin1_code":"6.0",
    "gn:asciiname":"Chhani Gujran",
    "gn:country_code":"PK",
    "gn:dem":275,
    "gn:feature_class":"P",
    "gn:feature_code":"PPL",
    "gn:name":"Chhani Gujran",
    "gn:population":0,
    "gn:timezone":"Asia/Karachi",
    "iso:country":"PK",
    "name:und_x_variant":[
        "Chhani",
        "Chhan",
        "Chhani Gujran"
    ],
    "wof:name":"Chhani Gujran",
    "wof:placetype":"locality"
},
  "geometry": {"coordinates":[73.60979,33.06086],"type":"Point"}
}