{
  "type": "Feature",
  "properties": {
    "gn:admin1_code":"3.0",
    "gn:asciiname":"Khalaqdad Kalla",
    "gn:country_code":"PK",
    "gn:dem":382,
    "gn:feature_class":"P",
    "gn:feature_code":"PPL",
    "gn:name":"Khalaqdad Kalla",
    "gn:population":0,
    "gn:timezone":"Asia/Karachi",
    "iso:country":"PK",
    "name:und_x_variant":[
        "Khalagd\u0101d Kalla",
        "Kh\u0101lakd\u0101d",
        "Khalaqdad Kalla"
    ],
    "wof:name":"Khalaqdad Kalla",
    "wof:placetype":"locality"
},
  "geometry": {"coordinates":[70.90384,32.9524],"type":"Point"}
}