{
  "type": "Feature",
  "properties": {
    "gn:admin1_code":"5",
    "gn:asciiname":"Goth Haji Ibrahim Hingoro",
    "gn:country_code":"PK",
    "gn:dem":22,
    "gn:feature_class":"P",
    "gn:feature_code":"PPL",
    "gn:name":"Goth Haji Ibrahim Hingoro",
    "gn:population":0,
    "gn:timezone":"Asia/Karachi",
    "iso:country":"PK",
    "wof:name":"Goth Haji Ibrahim Hingoro",
    "wof:placetype":"locality"
},
  "geometry": {"coordinates":[68.58365000000001,25.24028],"type":"Point"}
}