{
  "type": "Feature",
  "properties": {
    "gn:admin1_code":"4.0",
    "gn:asciiname":"Charhan",
    "gn:country_code":"PK",
    "gn:dem":1168,
    "gn:feature_class":"P",
    "gn:feature_code":"PPL",
    "gn:name":"Charhan",
    "gn:population":0,
    "gn:timezone":"Asia/Karachi",
    "iso:country":"PK",
    "name:eng_x_preferred":[
        "Ch\u016brih\u0101n"
    ],
    "name:fas_x_preferred":[
        "\u0686\u0631\u0647\u0627\u0646"
    ],
    "name:pnb_x_preferred":[
        "\u0686\u0631\u062e\u0627\u0646"
    ],
    "name:urd_x_preferred":[
        "\u0686\u0691\u06c1\u0627\u06ba"
    ],
    "wof:name":"Charhan",
    "wof:placetype":"locality"
},
  "geometry": {"coordinates":[73.44541,33.7741],"type":"Point"}
}