{
  "type": "Feature",
  "properties": {
    "gn:admin1_code":"6.0",
    "gn:asciiname":"Makral",
    "gn:country_code":"PK",
    "gn:dem":927,
    "gn:feature_class":"P",
    "gn:feature_code":"PPL",
    "gn:name":"Makral",
    "gn:population":0,
    "gn:timezone":"Asia/Karachi",
    "iso:country":"PK",
    "wof:name":"Makral",
    "wof:placetype":"locality"
},
  "geometry": {"coordinates":[74.03050999999998,33.49378],"type":"Point"}
}