{
  "type": "Feature",
  "properties": {
    "gn:admin1_code":"04",
    "gn:asciiname":"Chak Eleven Jhang Branch",
    "gn:country_code":"PK",
    "gn:dem":194,
    "gn:feature_class":"P",
    "gn:feature_code":"PPL",
    "gn:name":"Chak Eleven Jhang Branch",
    "gn:population":0,
    "gn:timezone":"Asia/Karachi",
    "iso:country":"PK",
    "name:und_x_variant":[
        "Chak Eleven J B",
        "Sidhu\u0101nw\u0101la",
        "Sandhw\u0101nw\u0101la",
        "Chak Eleven Jhang Branch",
        "Sidhw\u0101nw\u0101la"
    ],
    "wof:name":"Chak Eleven Jhang Branch",
    "wof:placetype":"locality"
},
  "geometry": {"coordinates":[73.18070999999998,31.77741],"type":"Point"}
}