{
  "type": "Feature",
  "properties": {
    "gn:admin1_code":"4.0",
    "gn:asciiname":"Dhok Pasi",
    "gn:country_code":"PK",
    "gn:dem":478,
    "gn:feature_class":"P",
    "gn:feature_code":"PPL",
    "gn:name":"Dhok Pasi",
    "gn:population":0,
    "gn:timezone":"Asia/Karachi",
    "iso:country":"PK",
    "name:und_x_variant":[
        "Dhok Passi"
    ],
    "wof:name":"Dhok Pasi",
    "wof:placetype":"locality"
},
  "geometry": {"coordinates":[72.86405999999999,33.48188],"type":"Point"}
}