{
  "type": "Feature",
  "properties": {
    "gn:admin1_code":"2.0",
    "gn:asciiname":"Mazar Dan Halq",
    "gn:country_code":"PK",
    "gn:dem":890,
    "gn:feature_class":"P",
    "gn:feature_code":"PPL",
    "gn:name":"Mazar Dan Halq",
    "gn:population":0,
    "gn:timezone":"Asia/Karachi",
    "iso:country":"PK",
    "wof:name":"Mazar Dan Halq",
    "wof:placetype":"locality"
},
  "geometry": {"coordinates":[63.90751,26.93795],"type":"Point"}
}