{
  "type": "Feature",
  "properties": {
    "gn:admin1_code":"2",
    "gn:asciiname":"Kili Rodini",
    "gn:country_code":"PK",
    "gn:dem":1567,
    "gn:feature_class":"P",
    "gn:feature_code":"PPL",
    "gn:name":"Kili Rodini",
    "gn:population":0,
    "gn:timezone":"Asia/Karachi",
    "iso:country":"PK",
    "name:und_x_variant":[
        "Fateh Kh\u0101n"
    ],
    "wof:name":"Kili Rodini",
    "wof:placetype":"locality"
},
  "geometry": {"coordinates":[66.40028000000001,29.61427],"type":"Point"}
}