{
  "type": "Feature",
  "properties": {
    "gn:admin1_code":"1.0",
    "gn:asciiname":"Kaniar",
    "gn:country_code":"PK",
    "gn:dem":587,
    "gn:feature_class":"P",
    "gn:feature_code":"PPL",
    "gn:name":"Kaniar",
    "gn:population":0,
    "gn:timezone":"Asia/Karachi",
    "iso:country":"PK",
    "wof:name":"Kaniar",
    "wof:placetype":"locality"
},
  "geometry": {"coordinates":[73.64904,33.49473],"type":"Point"}
}