{
  "type": "Feature",
  "properties": {
    "gn:admin1_code":"4",
    "gn:asciiname":"Chak Seventy-three Thal Development Authority",
    "gn:country_code":"PK",
    "gn:dem":163,
    "gn:feature_class":"P",
    "gn:feature_code":"PPL",
    "gn:name":"Chak Seventy-three Thal Development Authority",
    "gn:population":0,
    "gn:timezone":"Asia/Karachi",
    "iso:country":"PK",
    "name:und_x_variant":[
        "Chak Seventy-Three TDA",
        "Chak Sixty-four TDA",
        "Chak 73 TDA",
        "Chak Seventy-three Thal Development Authority"
    ],
    "wof:name":"Chak Seventy-three Thal Development Authority",
    "wof:placetype":"locality"
},
  "geometry": {"coordinates":[71.15618000000001,31.4126],"type":"Point"}
}