{
  "type": "Feature",
  "properties": {
    "gn:admin1_code":"2.0",
    "gn:asciiname":"Haji Shahil",
    "gn:country_code":"PK",
    "gn:dem":1533,
    "gn:feature_class":"P",
    "gn:feature_code":"PPL",
    "gn:name":"Haji Shahil",
    "gn:population":0,
    "gn:timezone":"Asia/Karachi",
    "iso:country":"PK",
    "wof:name":"Haji Shahil",
    "wof:placetype":"locality"
},
  "geometry": {"coordinates":[66.35821999999999,28.06518],"type":"Point"}
}