{
  "type": "Feature",
  "properties": {
    "gn:admin1_code":"4",
    "gn:asciiname":"Mineka Thatta",
    "gn:country_code":"PK",
    "gn:dem":184,
    "gn:feature_class":"P",
    "gn:feature_code":"PPL",
    "gn:name":"Mineka Thatta",
    "gn:population":0,
    "gn:timezone":"Asia/Karachi",
    "iso:country":"PK",
    "name:und_x_variant":[
        "Thatta Am\u012bn"
    ],
    "wof:name":"Mineka Thatta",
    "wof:placetype":"locality"
},
  "geometry": {"coordinates":[73.43833000000002,31.2048],"type":"Point"}
}