{
  "type": "Feature",
  "properties": {
    "gn:admin1_code":"4",
    "gn:asciiname":"Suniarewala",
    "gn:country_code":"PK",
    "gn:dem":124,
    "gn:feature_class":"P",
    "gn:feature_code":"PPL",
    "gn:name":"Suniarewala",
    "gn:population":0,
    "gn:timezone":"Asia/Karachi",
    "iso:country":"PK",
    "name:und_x_variant":[
        "Sun\u0101rew\u0101la"
    ],
    "wof:name":"Suniarewala",
    "wof:placetype":"locality"
},
  "geometry": {"coordinates":[71.0538,30.22873],"type":"Point"}
}