{
  "type": "Feature",
  "properties": {
    "gn:admin1_code":"4",
    "gn:asciiname":"Basti Jumma Khan",
    "gn:country_code":"PK",
    "gn:dem":101,
    "gn:feature_class":"P",
    "gn:feature_code":"PPL",
    "gn:name":"Basti Jumma Khan",
    "gn:population":0,
    "gn:timezone":"Asia/Karachi",
    "iso:country":"PK",
    "name:und_x_variant":[
        "Basti Haram Kh\u0101n Gop\u0101ng"
    ],
    "wof:name":"Basti Jumma Khan",
    "wof:placetype":"locality"
},
  "geometry": {"coordinates":[70.5547,29.23241],"type":"Point"}
}