{
  "type": "Feature",
  "properties": {
    "gn:admin1_code":"3",
    "gn:asciiname":"Shaftalu",
    "gn:country_code":"PK",
    "gn:dem":1222,
    "gn:feature_class":"P",
    "gn:feature_code":"PPL",
    "gn:name":"Shaftalu",
    "gn:population":0,
    "gn:timezone":"Asia/Karachi",
    "iso:country":"PK",
    "name:und_x_variant":[
        "Shaft\u0101l",
        "Shaftalu"
    ],
    "wof:name":"Shaftalu",
    "wof:placetype":"locality"
},
  "geometry": {"coordinates":[72.6688,34.538],"type":"Point"}
}