{
  "type": "Feature",
  "properties": {
    "gn:admin1_code":"2.0",
    "gn:asciiname":"Basti Dil Murad",
    "gn:country_code":"PK",
    "gn:dem":1113,
    "gn:feature_class":"P",
    "gn:feature_code":"PPL",
    "gn:name":"Basti Dil Murad",
    "gn:population":0,
    "gn:timezone":"Asia/Karachi",
    "iso:country":"PK",
    "wof:name":"Basti Dil Murad",
    "wof:placetype":"locality"
},
  "geometry": {"coordinates":[69.88348000000001,30.0343],"type":"Point"}
}