{
  "type": "Feature",
  "properties": {
    "gn:admin1_code":"5.0",
    "gn:asciiname":"Hoji Muhammad Saleh",
    "gn:country_code":"PK",
    "gn:dem":7,
    "gn:feature_class":"P",
    "gn:feature_code":"PPL",
    "gn:name":"Hoji Muhammad Saleh",
    "gn:population":0,
    "gn:timezone":"Asia/Karachi",
    "iso:country":"PK",
    "wof:name":"Hoji Muhammad Saleh",
    "wof:placetype":"locality"
},
  "geometry": {"coordinates":[68.93361999999999,24.57514],"type":"Point"}
}