{
  "type": "Feature",
  "properties": {
    "gn:admin1_code":"03",
    "gn:asciiname":"Sarpatai",
    "gn:country_code":"PK",
    "gn:dem":1888,
    "gn:feature_class":"P",
    "gn:feature_code":"PPL",
    "gn:name":"Sarpatai",
    "gn:population":0,
    "gn:timezone":"Asia/Karachi",
    "iso:country":"PK",
    "name:eng_x_preferred":[
        "Sarpatai"
    ],
    "wof:name":"Sarpatai",
    "wof:placetype":"locality"
},
  "geometry": {"coordinates":[71.87971,34.96691],"type":"Point"}
}