{
  "type": "Feature",
  "properties": {
    "gn:admin1_code":"4.0",
    "gn:asciiname":"Jan Muhammad di Basti",
    "gn:country_code":"PK",
    "gn:dem":146,
    "gn:feature_class":"P",
    "gn:feature_code":"PPL",
    "gn:name":"Jan Muhammad di Basti",
    "gn:population":0,
    "gn:timezone":"Asia/Karachi",
    "iso:country":"PK",
    "wof:name":"Jan Muhammad di Basti",
    "wof:placetype":"locality"
},
  "geometry": {"coordinates":[72.83707,29.96523],"type":"Point"}
}