{
  "type": "Feature",
  "properties": {
    "gn:admin1_code":"4",
    "gn:asciiname":"Baluchanwala",
    "gn:country_code":"PK",
    "gn:dem":196,
    "gn:feature_class":"P",
    "gn:feature_code":"PPL",
    "gn:name":"Baluchanwala",
    "gn:population":0,
    "gn:timezone":"Asia/Karachi",
    "iso:country":"PK",
    "name:und_x_variant":[
        "Balochw\u0101la"
    ],
    "wof:name":"Baluchanwala",
    "wof:placetype":"locality"
},
  "geometry": {"coordinates":[71.64076,32.09009],"type":"Point"}
}