{
  "type": "Feature",
  "properties": {
    "gn:admin1_code":"3.0",
    "gn:asciiname":"Kodinka",
    "gn:country_code":"PK",
    "gn:dem":341,
    "gn:feature_class":"P",
    "gn:feature_code":"PPL",
    "gn:name":"Kodinka",
    "gn:population":0,
    "gn:timezone":"Asia/Karachi",
    "iso:country":"PK",
    "wof:name":"Kodinka",
    "wof:placetype":"locality"
},
  "geometry": {"coordinates":[72.0459,34.27981],"type":"Point"}
}