{
  "type": "Feature",
  "properties": {
    "gn:admin1_code":"6.0",
    "gn:asciiname":"Dhok Jattan",
    "gn:country_code":"PK",
    "gn:dem":452,
    "gn:feature_class":"P",
    "gn:feature_code":"PPL",
    "gn:name":"Dhok Jattan",
    "gn:population":0,
    "gn:timezone":"Asia/Karachi",
    "iso:country":"PK",
    "wof:name":"Dhok Jattan",
    "wof:placetype":"locality"
},
  "geometry": {"coordinates":[73.64073,33.17733],"type":"Point"}
}