{
  "type": "Feature",
  "properties": {
    "gn:admin1_code":"4.0",
    "gn:asciiname":"Basti Kotli",
    "gn:country_code":"PK",
    "gn:dem":91,
    "gn:feature_class":"P",
    "gn:feature_code":"PPL",
    "gn:name":"Basti Kotli",
    "gn:population":0,
    "gn:timezone":"Asia/Karachi",
    "iso:country":"PK",
    "name:urd_x_preferred":[
        "Basti Kotli"
    ],
    "wof:name":"Basti Kotli",
    "wof:placetype":"locality"
},
  "geometry": {"coordinates":[70.60556,28.81667],"type":"Point"}
}