{
  "type": "Feature",
  "properties": {
    "gn:admin1_code":"3",
    "gn:asciiname":"Utal Shal",
    "gn:country_code":"PK",
    "gn:dem":3686,
    "gn:feature_class":"P",
    "gn:feature_code":"PPL",
    "gn:name":"Utal Shal",
    "gn:population":0,
    "gn:timezone":"Asia/Karachi",
    "iso:country":"PK",
    "name:eng_x_preferred":[
        "Utal Shal"
    ],
    "wof:name":"Utal Shal",
    "wof:placetype":"locality"
},
  "geometry": {"coordinates":[71.95416999999998,35.60639000000001],"type":"Point"}
}