{
  "type": "Feature",
  "properties": {
    "gn:admin1_code":"5.0",
    "gn:asciiname":"Kumhar Pali",
    "gn:country_code":"PK",
    "gn:dem":132,
    "gn:feature_class":"P",
    "gn:feature_code":"PPL",
    "gn:name":"Kumhar Pali",
    "gn:population":0,
    "gn:timezone":"Asia/Karachi",
    "iso:country":"PK",
    "name:und_x_variant":[
        "Kamhr\u0101r Pali"
    ],
    "wof:name":"Kumhar Pali",
    "wof:placetype":"locality"
},
  "geometry": {"coordinates":[70.54834,25.24527],"type":"Point"}
}