{
  "type": "Feature",
  "properties": {
    "gn:admin1_code":"4",
    "gn:asciiname":"Kharal Azim Thal",
    "gn:country_code":"PK",
    "gn:dem":141,
    "gn:feature_class":"P",
    "gn:feature_code":"PPL",
    "gn:name":"Kharal Az\u012bm Thal",
    "gn:population":0,
    "gn:timezone":"Asia/Karachi",
    "iso:country":"PK",
    "wof:name":"Kharal Azim Thal",
    "wof:placetype":"locality"
},
  "geometry": {"coordinates":[71.075,30.7875],"type":"Point"}
}