{
  "type": "Feature",
  "properties": {
    "gn:admin1_code":"3",
    "gn:asciiname":"Garai",
    "gn:country_code":"PK",
    "gn:dem":1646,
    "gn:feature_class":"P",
    "gn:feature_code":"PPL",
    "gn:name":"G\u0101rai",
    "gn:population":0,
    "gn:timezone":"Asia/Karachi",
    "iso:country":"PK",
    "wof:name":"Garai",
    "wof:placetype":"locality"
},
  "geometry": {"coordinates":[72.60139000000002,35.28194000000001],"type":"Point"}
}