{
  "type": "Feature",
  "properties": {
    "gn:admin1_code":"4.0",
    "gn:asciiname":"Phallo Devto",
    "gn:country_code":"PK",
    "gn:dem":212,
    "gn:feature_class":"P",
    "gn:feature_code":"PPL",
    "gn:name":"Phallo Devto",
    "gn:population":0,
    "gn:timezone":"Asia/Karachi",
    "iso:country":"PK",
    "name:und_x_variant":[
        "Phallo Devia"
    ],
    "wof:name":"Phallo Devto",
    "wof:placetype":"locality"
},
  "geometry": {"coordinates":[74.10890000000001,31.80211],"type":"Point"}
}