{
  "type": "Feature",
  "properties": {
    "gn:admin1_code":"1.0",
    "gn:asciiname":"Darak Mela",
    "gn:country_code":"PK",
    "gn:dem":1182,
    "gn:feature_class":"P",
    "gn:feature_code":"PPL",
    "gn:name":"Darak Mela",
    "gn:population":0,
    "gn:timezone":"Asia/Karachi",
    "iso:country":"PK",
    "wof:name":"Darak Mela",
    "wof:placetype":"locality"
},
  "geometry": {"coordinates":[70.33606,32.62455],"type":"Point"}
}