{
  "type": "Feature",
  "properties": {
    "gn:admin1_code":"5",
    "gn:asciiname":"Wali Dino Kerio",
    "gn:country_code":"PK",
    "gn:dem":52,
    "gn:feature_class":"P",
    "gn:feature_code":"PPL",
    "gn:name":"Wali Dino Kerio",
    "gn:population":0,
    "gn:timezone":"Asia/Karachi",
    "iso:country":"PK",
    "name:und_x_variant":[
        "Si\u0101l"
    ],
    "wof:name":"Wali Dino Kerio",
    "wof:placetype":"locality"
},
  "geometry": {"coordinates":[68.66046999999999,27.17149],"type":"Point"}
}