{
  "type": "Feature",
  "properties": {
    "gn:admin1_code":"3.0",
    "gn:asciiname":"Purkesap",
    "gn:country_code":"PK",
    "gn:dem":2386,
    "gn:feature_class":"P",
    "gn:feature_code":"PPL",
    "gn:name":"Purkesap",
    "gn:population":0,
    "gn:timezone":"Asia/Karachi",
    "iso:country":"PK",
    "wof:name":"Purkesap",
    "wof:placetype":"locality"
},
  "geometry": {"coordinates":[72.55202,36.31854000000001],"type":"Point"}
}