{
  "type": "Feature",
  "properties": {
    "gn:admin1_code":"4",
    "gn:asciiname":"Bakhshwala",
    "gn:country_code":"PK",
    "gn:dem":139,
    "gn:feature_class":"P",
    "gn:feature_code":"PPL",
    "gn:name":"Bakhshw\u0101la",
    "gn:population":0,
    "gn:timezone":"Asia/Karachi",
    "iso:country":"PK",
    "wof:name":"Bakhshwala",
    "wof:placetype":"locality"
},
  "geometry": {"coordinates":[71.30833,30.75],"type":"Point"}
}