{
  "type": "Feature",
  "properties": {
    "gn:admin1_code":"4.0",
    "gn:asciiname":"Dhok Muhammad",
    "gn:country_code":"PK",
    "gn:dem":370,
    "gn:feature_class":"P",
    "gn:feature_code":"PPL",
    "gn:name":"Dhok Muhammad",
    "gn:population":0,
    "gn:timezone":"Asia/Karachi",
    "iso:country":"PK",
    "name:und_x_variant":[
        "Daru Muhammade",
        "Dhok Muhammad"
    ],
    "wof:name":"Dhok Muhammad",
    "wof:placetype":"locality"
},
  "geometry": {"coordinates":[71.95988,33.16867],"type":"Point"}
}