{
  "type": "Feature",
  "properties": {
    "gn:admin1_code":"01",
    "gn:asciiname":"Zangai",
    "gn:country_code":"PK",
    "gn:dem":1867,
    "gn:feature_class":"P",
    "gn:feature_code":"PPL",
    "gn:name":"Zangai",
    "gn:population":0,
    "gn:timezone":"Asia/Karachi",
    "iso:country":"PK",
    "wof:name":"Zangai",
    "wof:placetype":"locality"
},
  "geometry": {"coordinates":[70.71239,33.79215],"type":"Point"}
}