{
  "type": "Feature",
  "properties": {
    "gn:admin1_code":"3",
    "gn:asciiname":"Baknai",
    "gn:country_code":"PK",
    "gn:dem":2270,
    "gn:feature_class":"P",
    "gn:feature_code":"PPL",
    "gn:name":"Baknai",
    "gn:population":0,
    "gn:timezone":"Asia/Karachi",
    "iso:country":"PK",
    "wof:name":"Baknai",
    "wof:placetype":"locality"
},
  "geometry": {"coordinates":[72.59583000000001,35.40722],"type":"Point"}
}