{
  "type": "Feature",
  "properties": {
    "gn:admin1_code":"3.0",
    "gn:asciiname":"Burjogh",
    "gn:country_code":"PK",
    "gn:dem":2541,
    "gn:feature_class":"P",
    "gn:feature_code":"PPL",
    "gn:name":"Burjogh",
    "gn:population":0,
    "gn:timezone":"Asia/Karachi",
    "iso:country":"PK",
    "wof:name":"Burjogh",
    "wof:placetype":"locality"
},
  "geometry": {"coordinates":[71.54682,35.97894],"type":"Point"}
}