{
  "type": "Feature",
  "properties": {
    "gn:admin1_code":"4.0",
    "gn:asciiname":"Haliai Banda",
    "gn:country_code":"PK",
    "gn:dem":993,
    "gn:feature_class":"P",
    "gn:feature_code":"PPL",
    "gn:name":"Haliai Banda",
    "gn:population":0,
    "gn:timezone":"Asia/Karachi",
    "iso:country":"PK",
    "wof:name":"Haliai Banda",
    "wof:placetype":"locality"
},
  "geometry": {"coordinates":[71.44176,33.15478],"type":"Point"}
}