{
  "type": "Feature",
  "properties": {
    "gn:admin1_code":"4.0",
    "gn:asciiname":"Palahi Mohra",
    "gn:country_code":"PK",
    "gn:dem":529,
    "gn:feature_class":"P",
    "gn:feature_code":"PPL",
    "gn:name":"Palahi Mohra",
    "gn:population":0,
    "gn:timezone":"Asia/Karachi",
    "iso:country":"PK",
    "wof:name":"Palahi Mohra",
    "wof:placetype":"locality"
},
  "geometry": {"coordinates":[73.58886,33.53888],"type":"Point"}
}