{
  "type": "Feature",
  "properties": {
    "gn:admin1_code":"1",
    "gn:asciiname":"Samiar",
    "gn:country_code":"PK",
    "gn:dem":1194,
    "gn:feature_class":"P",
    "gn:feature_code":"PPL",
    "gn:name":"Samiar",
    "gn:population":0,
    "gn:timezone":"Asia/Karachi",
    "iso:country":"PK",
    "name:und_x_variant":[
        "Sami\u0101r Kot"
    ],
    "wof:name":"Samiar",
    "wof:placetype":"locality"
},
  "geometry": {"coordinates":[69.78747,32.94874],"type":"Point"}
}