{
  "type": "Feature",
  "properties": {
    "gn:admin1_code":"5.0",
    "gn:asciiname":"Goth Karam Ali Baloch",
    "gn:country_code":"PK",
    "gn:dem":3,
    "gn:feature_class":"P",
    "gn:feature_code":"PPL",
    "gn:name":"Goth Karam Ali Baloch",
    "gn:population":0,
    "gn:timezone":"Asia/Karachi",
    "iso:country":"PK",
    "wof:name":"Goth Karam Ali Baloch",
    "wof:placetype":"locality"
},
  "geometry": {"coordinates":[67.52167,24.68557],"type":"Point"}
}