{
  "type": "Feature",
  "properties": {
    "gn:admin1_code":"4",
    "gn:asciiname":"Kot Hait Ram",
    "gn:country_code":"PK",
    "gn:dem":196,
    "gn:feature_class":"P",
    "gn:feature_code":"PPL",
    "gn:name":"Kot Hait Ram",
    "gn:population":0,
    "gn:timezone":"Asia/Karachi",
    "iso:country":"PK",
    "name:und_x_variant":[
        "Kot Het R\u0101m"
    ],
    "wof:name":"Kot Hait Ram",
    "wof:placetype":"locality"
},
  "geometry": {"coordinates":[73.86631,31.13974],"type":"Point"}
}