{
  "type": "Feature",
  "properties": {
    "gn:admin1_code":"6",
    "gn:asciiname":"Jigla",
    "gn:country_code":"PK",
    "gn:dem":1004,
    "gn:feature_class":"P",
    "gn:feature_code":"PPL",
    "gn:name":"Jigla",
    "gn:population":0,
    "gn:timezone":"Asia/Karachi",
    "iso:country":"PK",
    "name:und_x_variant":[
        "Jigal"
    ],
    "wof:name":"Jigla",
    "wof:placetype":"locality"
},
  "geometry": {"coordinates":[73.75673,34.16964],"type":"Point"}
}