{
  "type": "Feature",
  "properties": {
    "gn:admin1_code":"5",
    "gn:asciiname":"Phul Tongal",
    "gn:country_code":"PK",
    "gn:dem":37,
    "gn:feature_class":"P",
    "gn:feature_code":"PPL",
    "gn:name":"Phul Tongal",
    "gn:population":0,
    "gn:timezone":"Asia/Karachi",
    "iso:country":"PK",
    "name:eng_x_preferred":[
        "Phul Tongal"
    ],
    "wof:name":"Phul Tongal",
    "wof:placetype":"locality"
},
  "geometry": {"coordinates":[68.27741999999999,25.60057],"type":"Point"}
}