{
  "type": "Feature",
  "properties": {
    "gn:admin1_code":"7.0",
    "gn:asciiname":"Khil",
    "gn:country_code":"PK",
    "gn:dem":3168,
    "gn:feature_class":"P",
    "gn:feature_code":"PPL",
    "gn:name":"Khil",
    "gn:population":0,
    "gn:timezone":"Asia/Karachi",
    "iso:country":"PK",
    "name:und_x_variant":[
        "Kil"
    ],
    "wof:name":"Khil",
    "wof:placetype":"locality"
},
  "geometry": {"coordinates":[74.55717,36.8177],"type":"Point"}
}