{
  "type": "Feature",
  "properties": {
    "gn:admin1_code":"4",
    "gn:asciiname":"Bole",
    "gn:country_code":"PK",
    "gn:dem":224,
    "gn:feature_class":"P",
    "gn:feature_code":"PPL",
    "gn:name":"Bole",
    "gn:population":0,
    "gn:timezone":"Asia/Karachi",
    "iso:country":"PK",
    "name:ceb_x_preferred":[
        "Bole"
    ],
    "name:deu_x_preferred":[
        "Bole"
    ],
    "name:fra_x_preferred":[
        "Bole"
    ],
    "name:ita_x_preferred":[
        "Bole"
    ],
    "name:nld_x_preferred":[
        "Bole"
    ],
    "name:pol_x_preferred":[
        "Bole"
    ],
    "name:swe_x_preferred":[
        "Bole"
    ],
    "name:wln_x_preferred":[
        "Bole"
    ],
    "wof:name":"Bole",
    "wof:placetype":"locality"
},
  "geometry": {"coordinates":[74.54069,32.05673],"type":"Point"}
}