{
  "type": "Feature",
  "properties": {
    "gn:admin1_code":"2.0",
    "gn:asciiname":"Chakki Noghai",
    "gn:country_code":"PK",
    "gn:dem":1516,
    "gn:feature_class":"P",
    "gn:feature_code":"PPL",
    "gn:name":"Chakki Noghai",
    "gn:population":0,
    "gn:timezone":"Asia/Karachi",
    "iso:country":"PK",
    "wof:name":"Chakki Noghai",
    "wof:placetype":"locality"
},
  "geometry": {"coordinates":[66.44287,28.07065],"type":"Point"}
}