{
  "type": "Feature",
  "properties": {
    "gn:admin1_code":"4",
    "gn:asciiname":"Basti Raiwah",
    "gn:country_code":"PK",
    "gn:dem":93,
    "gn:feature_class":"P",
    "gn:feature_code":"PPL",
    "gn:name":"Basti Raiwah",
    "gn:population":0,
    "gn:timezone":"Asia/Karachi",
    "iso:country":"PK",
    "name:und_x_variant":[
        "R\u0101jaur"
    ],
    "wof:name":"Basti Raiwah",
    "wof:placetype":"locality"
},
  "geometry": {"coordinates":[70.8544,28.9149],"type":"Point"}
}