{
  "type": "Feature",
  "properties": {
    "gn:admin1_code":"2.0",
    "gn:asciiname":"Kandrach",
    "gn:country_code":"PK",
    "gn:dem":36,
    "gn:feature_class":"P",
    "gn:feature_code":"PPL",
    "gn:name":"Kandrach",
    "gn:population":0,
    "gn:timezone":"Asia/Karachi",
    "iso:country":"PK",
    "name:und_x_variant":[
        "Khundrack",
        "Kanr\u0101ch",
        "Kandrach"
    ],
    "wof:name":"Kandrach",
    "wof:placetype":"locality"
},
  "geometry": {"coordinates":[65.45829999999999,25.4824],"type":"Point"}
}