{
  "type": "Feature",
  "properties": {
    "gn:admin1_code":"6",
    "gn:asciiname":"Zian",
    "gn:country_code":"PK",
    "gn:dem":2603,
    "gn:feature_class":"P",
    "gn:feature_code":"PPL",
    "gn:name":"Zian",
    "gn:population":0,
    "gn:timezone":"Asia/Karachi",
    "iso:country":"PK",
    "wof:name":"Zian",
    "wof:placetype":"locality"
},
  "geometry": {"coordinates":[74.93056,34.69861],"type":"Point"}
}