{
  "type": "Feature",
  "properties": {
    "gn:admin1_code":"4.0",
    "gn:asciiname":"Wanda Minawal",
    "gn:country_code":"PK",
    "gn:dem":305,
    "gn:feature_class":"P",
    "gn:feature_code":"PPL",
    "gn:name":"Wanda Minawal",
    "gn:population":0,
    "gn:timezone":"Asia/Karachi",
    "iso:country":"PK",
    "wof:name":"Wanda Minawal",
    "wof:placetype":"locality"
},
  "geometry": {"coordinates":[71.17232,32.81486],"type":"Point"}
}