{
  "type": "Feature",
  "properties": {
    "gn:admin1_code":"7.0",
    "gn:asciiname":"Haiderama Baihk",
    "gn:country_code":"PK",
    "gn:dem":4069,
    "gn:feature_class":"P",
    "gn:feature_code":"PPL",
    "gn:name":"Haiderama Baihk",
    "gn:population":0,
    "gn:timezone":"Asia/Karachi",
    "iso:country":"PK",
    "wof:name":"Haiderama Baihk",
    "wof:placetype":"locality"
},
  "geometry": {"coordinates":[75.68244,35.17128],"type":"Point"}
}