{
  "type": "Feature",
  "properties": {
    "gn:admin1_code":"4.0",
    "gn:asciiname":"Dhok Ahmed Khan",
    "gn:country_code":"PK",
    "gn:dem":468,
    "gn:feature_class":"P",
    "gn:feature_code":"PPL",
    "gn:name":"Dhok Ahmed Khan",
    "gn:population":0,
    "gn:timezone":"Asia/Karachi",
    "iso:country":"PK",
    "wof:name":"Dhok Ahmed Khan",
    "wof:placetype":"locality"
},
  "geometry": {"coordinates":[72.85763,33.45542],"type":"Point"}
}