{
  "type": "Feature",
  "properties": {
    "gn:admin1_code":"5.0",
    "gn:asciiname":"Khalipha Mian Matho",
    "gn:country_code":"PK",
    "gn:dem":11,
    "gn:feature_class":"P",
    "gn:feature_code":"PPL",
    "gn:name":"Khalipha Mian Matho",
    "gn:population":0,
    "gn:timezone":"Asia/Karachi",
    "iso:country":"PK",
    "name:eng_x_preferred":[
        "Khalipha Mian Matho"
    ],
    "wof:name":"Khalipha Mian Matho",
    "wof:placetype":"locality"
},
  "geometry": {"coordinates":[68.43738,24.69741],"type":"Point"}
}