{
  "type": "Feature",
  "properties": {
    "gn:admin1_code":"1.0",
    "gn:asciiname":"Ezhdangai",
    "gn:country_code":"PK",
    "gn:dem":850,
    "gn:feature_class":"P",
    "gn:feature_code":"PPL",
    "gn:name":"Ezhdangai",
    "gn:population":0,
    "gn:timezone":"Asia/Karachi",
    "iso:country":"PK",
    "wof:name":"Ezhdangai",
    "wof:placetype":"locality"
},
  "geometry": {"coordinates":[70.36563000000001,32.59721],"type":"Point"}
}