{
  "type": "Feature",
  "properties": {
    "gn:admin1_code":"4",
    "gn:asciiname":"Addipur",
    "gn:country_code":"PK",
    "gn:dem":158,
    "gn:feature_class":"P",
    "gn:feature_code":"PPL",
    "gn:name":"Add\u012bpur",
    "gn:population":0,
    "gn:timezone":"Asia/Karachi",
    "iso:country":"PK",
    "wof:name":"Addipur",
    "wof:placetype":"locality"
},
  "geometry": {"coordinates":[73.37778,30.29861],"type":"Point"}
}