{
  "type": "Feature",
  "properties": {
    "gn:admin1_code":"3",
    "gn:asciiname":"Chhat",
    "gn:country_code":"PK",
    "gn:dem":3151,
    "gn:feature_class":"P",
    "gn:feature_code":"PPL",
    "gn:name":"Chhat",
    "gn:population":0,
    "gn:timezone":"Asia/Karachi",
    "iso:country":"PK",
    "name:und_x_variant":[
        "Jhath"
    ],
    "wof:name":"Chhat",
    "wof:placetype":"locality"
},
  "geometry": {"coordinates":[73.6233,34.77891],"type":"Point"}
}