{
  "type": "Feature",
  "properties": {
    "gn:admin1_code":"4",
    "gn:asciiname":"Kaniwala",
    "gn:country_code":"PK",
    "gn:dem":151,
    "gn:feature_class":"P",
    "gn:feature_code":"PPL",
    "gn:name":"Kaniwala",
    "gn:population":0,
    "gn:timezone":"Asia/Karachi",
    "iso:country":"PK",
    "name:und_x_variant":[
        "Kaniw\u0101la"
    ],
    "wof:name":"Kaniwala",
    "wof:placetype":"locality"
},
  "geometry": {"coordinates":[71.35701999999998,31.06583],"type":"Point"}
}