{
  "type": "Feature",
  "properties": {
    "gn:admin1_code":"5",
    "gn:asciiname":"Goth Lal Shah",
    "gn:country_code":"PK",
    "gn:dem":18,
    "gn:feature_class":"P",
    "gn:feature_code":"PPL",
    "gn:name":"Goth Lal Shah",
    "gn:population":0,
    "gn:timezone":"Asia/Karachi",
    "iso:country":"PK",
    "name:und_x_variant":[
        "L\u0101l Sh\u0101h"
    ],
    "wof:name":"Goth Lal Shah",
    "wof:placetype":"locality"
},
  "geometry": {"coordinates":[68.64627,25.15218],"type":"Point"}
}