{
  "type": "Feature",
  "properties": {
    "gn:admin1_code":"4",
    "gn:asciiname":"Jhok Sunari",
    "gn:country_code":"PK",
    "gn:dem":178,
    "gn:feature_class":"P",
    "gn:feature_code":"PPL",
    "gn:name":"Jhok Sun\u0101ri",
    "gn:population":0,
    "gn:timezone":"Asia/Karachi",
    "iso:country":"PK",
    "wof:name":"Jhok Sunari",
    "wof:placetype":"locality"
},
  "geometry": {"coordinates":[73.17361,31.05833],"type":"Point"}
}