{
  "type": "Feature",
  "properties": {
    "gn:admin1_code":"2.0",
    "gn:asciiname":"Kili Sher Muhammad",
    "gn:country_code":"PK",
    "gn:dem":1852,
    "gn:feature_class":"P",
    "gn:feature_code":"PPL",
    "gn:name":"Kili Sher Muhammad",
    "gn:population":0,
    "gn:timezone":"Asia/Karachi",
    "iso:country":"PK",
    "name:und_x_variant":[
        "Sarmaghai"
    ],
    "wof:name":"Kili Sher Muhammad",
    "wof:placetype":"locality"
},
  "geometry": {"coordinates":[68.59966,31.47723],"type":"Point"}
}