{
  "type": "Feature",
  "properties": {
    "gn:admin1_code":"4",
    "gn:asciiname":"Ranjha Wadani",
    "gn:country_code":"PK",
    "gn:dem":137,
    "gn:feature_class":"P",
    "gn:feature_code":"PPL",
    "gn:name":"R\u0101njha Wad\u0101ni",
    "gn:population":0,
    "gn:timezone":"Asia/Karachi",
    "iso:country":"PK",
    "wof:name":"Ranjha Wadani",
    "wof:placetype":"locality"
},
  "geometry": {"coordinates":[70.54516,30.01818],"type":"Point"}
}