{
  "type": "Feature",
  "properties": {
    "gn:admin1_code":"2",
    "gn:asciiname":"Basti Maulvi Abdul Haq",
    "gn:country_code":"PK",
    "gn:dem":1208,
    "gn:feature_class":"P",
    "gn:feature_code":"PPL",
    "gn:name":"Basti Maulvi Abdul Haq",
    "gn:population":0,
    "gn:timezone":"Asia/Karachi",
    "iso:country":"PK",
    "name:und_x_variant":[
        "Kam\u0101l Q\u0101im\u0101ni"
    ],
    "wof:name":"Basti Maulvi Abdul Haq",
    "wof:placetype":"locality"
},
  "geometry": {"coordinates":[69.69325000000001,29.97352],"type":"Point"}
}