{
  "type": "Feature",
  "properties": {
    "gn:admin1_code":"2.0",
    "gn:asciiname":"Kili Baran",
    "gn:country_code":"PK",
    "gn:dem":713,
    "gn:feature_class":"P",
    "gn:feature_code":"PPL",
    "gn:name":"Kili Baran",
    "gn:population":0,
    "gn:timezone":"Asia/Karachi",
    "iso:country":"PK",
    "name:und_x_variant":[
        "Titi"
    ],
    "wof:name":"Kili Baran",
    "wof:placetype":"locality"
},
  "geometry": {"coordinates":[65.4896,28.555],"type":"Point"}
}