{
  "type": "Feature",
  "properties": {
    "gn:admin1_code":"2",
    "gn:asciiname":"Basti Haji Amir Muhammad",
    "gn:country_code":"PK",
    "gn:dem":1289,
    "gn:feature_class":"P",
    "gn:feature_code":"PPL",
    "gn:name":"Basti Haji Amir Muhammad",
    "gn:population":0,
    "gn:timezone":"Asia/Karachi",
    "iso:country":"PK",
    "name:und_x_variant":[
        "P\u012br Muhammad Basti"
    ],
    "wof:name":"Basti Haji Amir Muhammad",
    "wof:placetype":"locality"
},
  "geometry": {"coordinates":[69.89366,30.28786],"type":"Point"}
}