{
  "type": "Feature",
  "properties": {
    "gn:admin1_code":"2",
    "gn:asciiname":"Mauladad",
    "gn:country_code":"PK",
    "gn:dem":674,
    "gn:feature_class":"P",
    "gn:feature_code":"PPL",
    "gn:name":"Mauladad",
    "gn:population":0,
    "gn:timezone":"Asia/Karachi",
    "iso:country":"PK",
    "wof:name":"Mauladad",
    "wof:placetype":"locality"
},
  "geometry": {"coordinates":[65.12130000000001,28.4523],"type":"Point"}
}