{
  "type": "Feature",
  "properties": {
    "gn:admin1_code":"4.0",
    "gn:asciiname":"Dhok Malah",
    "gn:country_code":"PK",
    "gn:dem":281,
    "gn:feature_class":"P",
    "gn:feature_code":"PPL",
    "gn:name":"Dhok Malah",
    "gn:population":0,
    "gn:timezone":"Asia/Karachi",
    "iso:country":"PK",
    "name:und_x_variant":[
        "Dhok Mah\u0101ng\u0101n",
        "Dhok Moh\u0101na"
    ],
    "wof:name":"Dhok Malah",
    "wof:placetype":"locality"
},
  "geometry": {"coordinates":[71.80055,33.01444],"type":"Point"}
}