{
  "type": "Feature",
  "properties": {
    "gn:admin1_code":"4.0",
    "gn:asciiname":"Chak One Hundred Fifty",
    "gn:country_code":"PK",
    "gn:dem":183,
    "gn:feature_class":"P",
    "gn:feature_code":"PPL",
    "gn:name":"Chak One Hundred Fifty",
    "gn:population":0,
    "gn:timezone":"Asia/Karachi",
    "iso:country":"PK",
    "name:und_x_variant":[
        "Malakpur",
        "Chak One Hundred Fifty",
        "Khokhr\u0101nda Chak",
        "Khoknarw\u0101la",
        "Khokhranda"
    ],
    "wof:name":"Chak One Hundred Fifty",
    "wof:placetype":"locality"
},
  "geometry": {"coordinates":[72.87349,31.50878],"type":"Point"}
}