{
  "type": "Feature",
  "properties": {
    "gn:admin1_code":"3",
    "gn:asciiname":"Nanhua Khurd",
    "gn:country_code":"PK",
    "gn:dem":970,
    "gn:feature_class":"P",
    "gn:feature_code":"PPL",
    "gn:name":"Nanhua Khurd",
    "gn:population":0,
    "gn:timezone":"Asia/Karachi",
    "iso:country":"PK",
    "name:und_x_variant":[
        "Nanoha Khurd"
    ],
    "wof:name":"Nanhua Khurd",
    "wof:placetype":"locality"
},
  "geometry": {"coordinates":[73.11968,34.24722],"type":"Point"}
}