{
  "type": "Feature",
  "properties": {
    "gn:admin1_code":"3.0",
    "gn:asciiname":"Falak Sair Banal",
    "gn:country_code":"PK",
    "gn:dem":2868,
    "gn:feature_class":"P",
    "gn:feature_code":"PPL",
    "gn:name":"Falak Sair Banal",
    "gn:population":0,
    "gn:timezone":"Asia/Karachi",
    "iso:country":"PK",
    "wof:name":"Falak Sair Banal",
    "wof:placetype":"locality"
},
  "geometry": {"coordinates":[72.68271999999997,35.67975],"type":"Point"}
}