{
  "type": "Feature",
  "properties": {
    "gn:admin1_code":"5",
    "gn:asciiname":"Gaoth Wario Metlo",
    "gn:country_code":"PK",
    "gn:dem":55,
    "gn:feature_class":"P",
    "gn:feature_code":"PPL",
    "gn:name":"Gaoth Wario Metlo",
    "gn:population":0,
    "gn:timezone":"Asia/Karachi",
    "iso:country":"PK",
    "name:und_x_variant":[
        "Wario Mitro"
    ],
    "wof:name":"Gaoth Wario Metlo",
    "wof:placetype":"locality"
},
  "geometry": {"coordinates":[68.61742,27.51785],"type":"Point"}
}