{
  "type": "Feature",
  "properties": {
    "gn:admin1_code":"4",
    "gn:asciiname":"Basti Shaikhan",
    "gn:country_code":"PK",
    "gn:dem":95,
    "gn:feature_class":"P",
    "gn:feature_code":"PPL",
    "gn:name":"Basti Shaikhan",
    "gn:population":0,
    "gn:timezone":"Asia/Karachi",
    "iso:country":"PK",
    "name:und_x_variant":[
        "Basti Shaikh"
    ],
    "wof:name":"Basti Shaikhan",
    "wof:placetype":"locality"
},
  "geometry": {"coordinates":[70.84184999999999,28.86827000000001],"type":"Point"}
}