{
  "type": "Feature",
  "properties": {
    "gn:admin1_code":"6.0",
    "gn:asciiname":"Domail",
    "gn:country_code":"PK",
    "gn:dem":4072,
    "gn:feature_class":"P",
    "gn:feature_code":"PPL",
    "gn:name":"Domail",
    "gn:population":0,
    "gn:timezone":"Asia/Karachi",
    "iso:country":"PK",
    "wof:name":"Domail",
    "wof:placetype":"locality"
},
  "geometry": {"coordinates":[73.99439,34.81268],"type":"Point"}
}