{
  "type": "Feature",
  "properties": {
    "gn:admin1_code":"4.0",
    "gn:asciiname":"Kotla Chudduanda",
    "gn:country_code":"PK",
    "gn:dem":184,
    "gn:feature_class":"P",
    "gn:feature_code":"PPL",
    "gn:name":"Kotla Chudduanda",
    "gn:population":0,
    "gn:timezone":"Asia/Karachi",
    "iso:country":"PK",
    "name:und_x_variant":[
        "Kotla Chaddu"
    ],
    "wof:name":"Kotla Chudduanda",
    "wof:placetype":"locality"
},
  "geometry": {"coordinates":[72.52058000000002,32.34004],"type":"Point"}
}