{
  "type": "Feature",
  "properties": {
    "gn:admin1_code":"1.0",
    "gn:asciiname":"Bugham Dhand",
    "gn:country_code":"PK",
    "gn:dem":2459,
    "gn:feature_class":"P",
    "gn:feature_code":"PPL",
    "gn:name":"Bugham Dhand",
    "gn:population":0,
    "gn:timezone":"Asia/Karachi",
    "iso:country":"PK",
    "name:und_x_variant":[
        "Bughak Uhand",
        "Bughak Dhand",
        "Bugham Dhand"
    ],
    "wof:name":"Bugham Dhand",
    "wof:placetype":"locality"
},
  "geometry": {"coordinates":[70.03299,33.98899],"type":"Point"}
}