{
  "type": "Feature",
  "properties": {
    "gn:admin1_code":"5",
    "gn:asciiname":"Goth Sultan Magsi",
    "gn:country_code":"PK",
    "gn:dem":70,
    "gn:feature_class":"P",
    "gn:feature_code":"PPL",
    "gn:name":"Goth Sultan Magsi",
    "gn:population":0,
    "gn:timezone":"Asia/Karachi",
    "iso:country":"PK",
    "name:und_x_variant":[
        "Rehmunwali",
        "Rehm\u0101nwali",
        "Goth Sultan Magsi"
    ],
    "wof:name":"Goth Sultan Magsi",
    "wof:placetype":"locality"
},
  "geometry": {"coordinates":[69.30449,27.9995],"type":"Point"}
}