{
  "type": "Feature",
  "properties": {
    "gn:admin1_code":"3.0",
    "gn:asciiname":"Afzalabad",
    "gn:country_code":"PK",
    "gn:dem":336,
    "gn:feature_class":"P",
    "gn:feature_code":"PPL",
    "gn:name":"Afzalabad",
    "gn:population":0,
    "gn:timezone":"Asia/Karachi",
    "iso:country":"PK",
    "name:eng_x_preferred":[
        "Afzalabad"
    ],
    "name:fas_x_preferred":[
        "\u0627\u0641\u0636\u0644\u200c\u0622\u0628\u0627\u062f"
    ],
    "name:und_x_variant":[
        "Afzal\u0101h\u0101d"
    ],
    "wof:name":"Afzalabad",
    "wof:placetype":"locality"
},
  "geometry": {"coordinates":[71.99309000000002,34.28185],"type":"Point"}
}