{
  "type": "Feature",
  "properties": {
    "gn:admin1_code":"6.0",
    "gn:asciiname":"Hattian Bala",
    "gn:country_code":"PK",
    "gn:dem":948,
    "gn:feature_class":"P",
    "gn:feature_code":"PPL",
    "gn:name":"Hattian Bala",
    "gn:population":0,
    "gn:timezone":"Asia/Karachi",
    "iso:country":"PK",
    "name:hin_x_preferred":[
        "\u0939\u091f\u094d\u091f\u093f\u092f\u093e\u0901 \u092c\u093e\u0932\u093e"
    ],
    "name:und_x_variant":[
        "Hati\u0101n"
    ],
    "name:urd_x_preferred":[
        "\u06c1\u0679\u06cc\u0627\u06ba \u0628\u0627\u0644\u0627"
    ],
    "wof:name":"Hattian Bala",
    "wof:placetype":"locality"
},
  "geometry": {"coordinates":[73.73379,34.1704],"type":"Point"}
}