{
  "type": "Feature",
  "properties": {
    "gn:admin1_code":"4",
    "gn:asciiname":"Rani Tibba",
    "gn:country_code":"PK",
    "gn:dem":190,
    "gn:feature_class":"P",
    "gn:feature_code":"PPL",
    "gn:name":"Rani Tibba",
    "gn:population":0,
    "gn:timezone":"Asia/Karachi",
    "iso:country":"PK",
    "name:und_x_variant":[
        "R\u0101ni ki Tibbi"
    ],
    "wof:name":"Rani Tibba",
    "wof:placetype":"locality"
},
  "geometry": {"coordinates":[73.64735,31.37312],"type":"Point"}
}