{
  "type": "Feature",
  "properties": {
    "gn:admin1_code":"3.0",
    "gn:asciiname":"Satanr Cham",
    "gn:country_code":"PK",
    "gn:dem":1878,
    "gn:feature_class":"P",
    "gn:feature_code":"PPL",
    "gn:name":"Satanr Cham",
    "gn:population":0,
    "gn:timezone":"Asia/Karachi",
    "iso:country":"PK",
    "wof:name":"Satanr Cham",
    "wof:placetype":"locality"
},
  "geometry": {"coordinates":[72.51664,35.1706],"type":"Point"}
}