{
  "type": "Feature",
  "properties": {
    "gn:admin1_code":"4",
    "gn:asciiname":"Nabipur",
    "gn:country_code":"PK",
    "gn:dem":150,
    "gn:feature_class":"P",
    "gn:feature_code":"PPL",
    "gn:name":"Nabipur",
    "gn:population":0,
    "gn:timezone":"Asia/Karachi",
    "iso:country":"PK",
    "wof:name":"Nabipur",
    "wof:placetype":"locality"
},
  "geometry": {"coordinates":[72.72667,30.15483],"type":"Point"}
}