{
  "type": "Feature",
  "properties": {
    "gn:admin1_code":"4.0",
    "gn:asciiname":"Dhok Ban Aklal",
    "gn:country_code":"PK",
    "gn:dem":583,
    "gn:feature_class":"P",
    "gn:feature_code":"PPL",
    "gn:name":"Dhok Ban Aklal",
    "gn:population":0,
    "gn:timezone":"Asia/Karachi",
    "iso:country":"PK",
    "wof:name":"Dhok Ban Aklal",
    "wof:placetype":"locality"
},
  "geometry": {"coordinates":[72.30062,32.79061],"type":"Point"}
}