{
  "type": "Feature",
  "properties": {
    "gn:admin1_code":"2.0",
    "gn:asciiname":"Chashma Raghah Kili",
    "gn:country_code":"PK",
    "gn:dem":1543,
    "gn:feature_class":"P",
    "gn:feature_code":"PPL",
    "gn:name":"Chashma Raghah Kili",
    "gn:population":0,
    "gn:timezone":"Asia/Karachi",
    "iso:country":"PK",
    "name:und_x_variant":[
        "Chashma R\u0101ghah"
    ],
    "wof:name":"Chashma Raghah Kili",
    "wof:placetype":"locality"
},
  "geometry": {"coordinates":[69.94006999999999,31.30705],"type":"Point"}
}