{
  "type": "Feature",
  "properties": {
    "gn:admin1_code":"3.0",
    "gn:asciiname":"Chalandara",
    "gn:country_code":"PK",
    "gn:dem":1206,
    "gn:feature_class":"P",
    "gn:feature_code":"PPL",
    "gn:name":"Chalandara",
    "gn:population":0,
    "gn:timezone":"Asia/Karachi",
    "iso:country":"PK",
    "name:und_x_variant":[
        "Chalundri",
        "Chalandrai",
        "Chalandara"
    ],
    "wof:name":"Chalandara",
    "wof:placetype":"locality"
},
  "geometry": {"coordinates":[72.68926,34.57274],"type":"Point"}
}