{
  "type": "Feature",
  "properties": {
    "gn:admin1_code":"4",
    "gn:asciiname":"Chhina",
    "gn:country_code":"PK",
    "gn:dem":165,
    "gn:feature_class":"P",
    "gn:feature_code":"PPL",
    "gn:name":"Chhina",
    "gn:population":0,
    "gn:timezone":"Asia/Karachi",
    "iso:country":"PK",
    "name:hin_x_preferred":[
        "\u091b\u0940\u0928\u093e"
    ],
    "wof:name":"Chhina",
    "wof:placetype":"locality"
},
  "geometry": {"coordinates":[73.42012,30.32008],"type":"Point"}
}