{
  "type": "Feature",
  "properties": {
    "gn:admin1_code":"03",
    "gn:asciiname":"Ibrahim Khan",
    "gn:country_code":"PK",
    "gn:dem":313,
    "gn:feature_class":"P",
    "gn:feature_code":"PPL",
    "gn:name":"Ibrahim Khan",
    "gn:population":0,
    "gn:timezone":"Asia/Karachi",
    "iso:country":"PK",
    "name:aze_x_preferred":[
        "\u0130brahim xan"
    ],
    "name:fas_x_preferred":[
        "\u0627\u0628\u0631\u0627\u0647\u06cc\u0645\u200c\u062e\u0627\u0646"
    ],
    "wof:name":"Ibrahim Khan",
    "wof:placetype":"locality"
},
  "geometry": {"coordinates":[70.73611,32.84],"type":"Point"}
}