{
  "type": "Feature",
  "properties": {
    "gn:admin1_code":"4",
    "gn:asciiname":"Basti Maulvi Jamil Ahmad Ahmadani",
    "gn:country_code":"PK",
    "gn:dem":105,
    "gn:feature_class":"P",
    "gn:feature_code":"PPL",
    "gn:name":"Basti Maulvi Jamil Ahmad Ahmadani",
    "gn:population":0,
    "gn:timezone":"Asia/Karachi",
    "iso:country":"PK",
    "name:und_x_variant":[
        "Maulvi Gulz\u0101r"
    ],
    "wof:name":"Basti Maulvi Jamil Ahmad Ahmadani",
    "wof:placetype":"locality"
},
  "geometry": {"coordinates":[70.38523000000001,29.33027],"type":"Point"}
}