{
  "type": "Feature",
  "properties": {
    "gn:admin1_code":"3",
    "gn:asciiname":"Kuai",
    "gn:country_code":"PK",
    "gn:dem":1556,
    "gn:feature_class":"P",
    "gn:feature_code":"PPL",
    "gn:name":"Kuai",
    "gn:population":0,
    "gn:timezone":"Asia/Karachi",
    "iso:country":"PK",
    "name:deu_x_preferred":[
        "Kuai"
    ],
    "wof:name":"Kuai",
    "wof:placetype":"locality"
},
  "geometry": {"coordinates":[72.84855999999998,34.91873],"type":"Point"}
}