{
  "type": "Feature",
  "properties": {
    "gn:admin1_code":"5",
    "gn:asciiname":"Goth Haji Ibrahim",
    "gn:country_code":"PK",
    "gn:dem":50,
    "gn:feature_class":"P",
    "gn:feature_code":"PPL",
    "gn:name":"Goth Haji Ibrahim",
    "gn:population":0,
    "gn:timezone":"Asia/Karachi",
    "iso:country":"PK",
    "name:und_x_variant":[
        "Goth H\u0101ji Ibr\u0101h\u012bm"
    ],
    "wof:name":"Goth Haji Ibrahim",
    "wof:placetype":"locality"
},
  "geometry": {"coordinates":[68.23737,27.13632],"type":"Point"}
}