{
  "type": "Feature",
  "properties": {
    "gn:admin1_code":"5",
    "gn:asciiname":"Goth Kamil Laghari",
    "gn:country_code":"PK",
    "gn:dem":25,
    "gn:feature_class":"P",
    "gn:feature_code":"PPL",
    "gn:name":"Goth Kamil Laghari",
    "gn:population":0,
    "gn:timezone":"Asia/Karachi",
    "iso:country":"PK",
    "name:und_x_variant":[
        "Goth K\u0101mil Lagh\u0101ri"
    ],
    "wof:name":"Goth Kamil Laghari",
    "wof:placetype":"locality"
},
  "geometry": {"coordinates":[68.60715,25.97227],"type":"Point"}
}