{
  "type": "Feature",
  "properties": {
    "gn:admin1_code":"5",
    "gn:asciiname":"Muhammad Ali Kalepota",
    "gn:country_code":"PK",
    "gn:dem":11,
    "gn:feature_class":"P",
    "gn:feature_code":"PPL",
    "gn:name":"Muhammad Ali Kalepota",
    "gn:population":0,
    "gn:timezone":"Asia/Karachi",
    "iso:country":"PK",
    "name:und_x_variant":[
        "All\u0101hno H\u0101lepota"
    ],
    "wof:name":"Muhammad Ali Kalepota",
    "wof:placetype":"locality"
},
  "geometry": {"coordinates":[69.10124,24.94324],"type":"Point"}
}