{
  "type": "Feature",
  "properties": {
    "gn:admin1_code":"5.0",
    "gn:asciiname":"Haji Nur Muhammad",
    "gn:country_code":"PK",
    "gn:dem":29,
    "gn:feature_class":"P",
    "gn:feature_code":"PPL",
    "gn:name":"Haji Nur Muhammad",
    "gn:population":0,
    "gn:timezone":"Asia/Karachi",
    "iso:country":"PK",
    "name:und_x_variant":[
        "H\u0101ji Nur Muhammad"
    ],
    "wof:name":"Haji Nur Muhammad",
    "wof:placetype":"locality"
},
  "geometry": {"coordinates":[68.47114999999999,26.1293],"type":"Point"}
}