{
  "type": "Feature",
  "properties": {
    "gn:admin1_code":"4.0",
    "gn:asciiname":"Daduana",
    "gn:country_code":"PK",
    "gn:dem":157,
    "gn:feature_class":"P",
    "gn:feature_code":"PPL",
    "gn:name":"Daduana",
    "gn:population":0,
    "gn:timezone":"Asia/Karachi",
    "iso:country":"PK",
    "wof:name":"Daduana",
    "wof:placetype":"locality"
},
  "geometry": {"coordinates":[72.31796999999997,31.4036],"type":"Point"}
}