{
  "type": "Feature",
  "properties": {
    "gn:admin1_code":"4.0",
    "gn:asciiname":"Haveli Bala Singh",
    "gn:country_code":"PK",
    "gn:dem":204,
    "gn:feature_class":"P",
    "gn:feature_code":"PPL",
    "gn:name":"Haveli Bala Singh",
    "gn:population":0,
    "gn:timezone":"Asia/Karachi",
    "iso:country":"PK",
    "wof:name":"Haveli Bala Singh",
    "wof:placetype":"locality"
},
  "geometry": {"coordinates":[74.18290999999998,31.19932],"type":"Point"}
}