{
  "type": "Feature",
  "properties": {
    "gn:admin1_code":"4.0",
    "gn:asciiname":"Dhariala Jalib",
    "gn:country_code":"PK",
    "gn:dem":209,
    "gn:feature_class":"P",
    "gn:feature_code":"PPL",
    "gn:name":"Dhariala Jalib",
    "gn:population":0,
    "gn:timezone":"Asia/Karachi",
    "iso:country":"PK",
    "name:und_x_variant":[
        "Daryala Jalap",
        "Dhari\u0101la",
        "Dhariala Jalib"
    ],
    "wof:name":"Dhariala Jalib",
    "wof:placetype":"locality"
},
  "geometry": {"coordinates":[73.22117,32.65048],"type":"Point"}
}