{
  "type": "Feature",
  "properties": {
    "gn:admin1_code":"5",
    "gn:asciiname":"Goth Razi Bhugio",
    "gn:country_code":"PK",
    "gn:dem":36,
    "gn:feature_class":"P",
    "gn:feature_code":"PPL",
    "gn:name":"Goth Razi Bhugio",
    "gn:population":0,
    "gn:timezone":"Asia/Karachi",
    "iso:country":"PK",
    "name:und_x_variant":[
        "R\u0101zi Bhugio"
    ],
    "wof:name":"Goth Razi Bhugio",
    "wof:placetype":"locality"
},
  "geometry": {"coordinates":[68.01085,26.40679],"type":"Point"}
}