{
  "type": "Feature",
  "properties": {
    "gn:admin1_code":"4",
    "gn:asciiname":"Muhabbat Pur",
    "gn:country_code":"PK",
    "gn:dem":106,
    "gn:feature_class":"P",
    "gn:feature_code":"PPL",
    "gn:name":"Muhabbat Pur",
    "gn:population":0,
    "gn:timezone":"Asia/Karachi",
    "iso:country":"PK",
    "name:und_x_variant":[
        "Mohabbatpur"
    ],
    "wof:name":"Muhabbat Pur",
    "wof:placetype":"locality"
},
  "geometry": {"coordinates":[71.28251,29.15524000000001],"type":"Point"}
}