{
  "type": "Feature",
  "properties": {
    "gn:admin1_code":"5",
    "gn:asciiname":"Modo",
    "gn:country_code":"PK",
    "gn:dem":13,
    "gn:feature_class":"P",
    "gn:feature_code":"PPL",
    "gn:name":"Modo",
    "gn:population":0,
    "gn:timezone":"Asia/Karachi",
    "iso:country":"PK",
    "name:ceb_x_preferred":[
        "Modo"
    ],
    "name:dan_x_preferred":[
        "Modo"
    ],
    "name:deu_x_preferred":[
        "Modo"
    ],
    "name:fra_x_preferred":[
        "Modo"
    ],
    "name:glg_x_preferred":[
        "Modo"
    ],
    "name:ita_x_preferred":[
        "Modo"
    ],
    "name:nld_x_preferred":[
        "Modo"
    ],
    "name:por_x_preferred":[
        "Modo"
    ],
    "name:rus_x_preferred":[
        "\u041c\u043e\u0434\u043e"
    ],
    "name:spa_x_preferred":[
        "Modo"
    ],
    "name:swe_x_preferred":[
        "Modo"
    ],
    "wof:name":"Modo",
    "wof:placetype":"locality"
},
  "geometry": {"coordinates":[69.28333000000001,25.34028],"type":"Point"}
}