{
  "type": "Feature",
  "properties": {
    "gn:admin1_code":"4",
    "gn:asciiname":"Kasab",
    "gn:country_code":"PK",
    "gn:dem":260,
    "gn:feature_class":"P",
    "gn:feature_code":"PPL",
    "gn:name":"Kasab",
    "gn:population":0,
    "gn:timezone":"Asia/Karachi",
    "iso:country":"PK",
    "wof:name":"Kasab",
    "wof:placetype":"locality"
},
  "geometry": {"coordinates":[74.30475,32.7105],"type":"Point"}
}