{
  "type": "Feature",
  "properties": {
    "gn:admin1_code":"3.0",
    "gn:asciiname":"Nala",
    "gn:country_code":"PK",
    "gn:dem":1837,
    "gn:feature_class":"P",
    "gn:feature_code":"PPL",
    "gn:name":"Nala",
    "gn:population":0,
    "gn:timezone":"Asia/Karachi",
    "iso:country":"PK",
    "name:eng_x_preferred":[
        "Nala"
    ],
    "wof:name":"Nala",
    "wof:placetype":"locality"
},
  "geometry": {"coordinates":[73.36615999999999,33.97984],"type":"Point"}
}