{
  "type": "Feature",
  "properties": {
    "gn:admin1_code":"5",
    "gn:asciiname":"Qadir Dad Dumbki",
    "gn:country_code":"PK",
    "gn:dem":72,
    "gn:feature_class":"P",
    "gn:feature_code":"PPL",
    "gn:name":"Qadir Dad Dumbki",
    "gn:population":0,
    "gn:timezone":"Asia/Karachi",
    "iso:country":"PK",
    "wof:name":"Qadir Dad Dumbki",
    "wof:placetype":"locality"
},
  "geometry": {"coordinates":[69.29616,28.40213],"type":"Point"}
}