{
  "type": "Feature",
  "properties": {
    "gn:admin1_code":"5",
    "gn:asciiname":"Ibrahim Mahtam",
    "gn:country_code":"PK",
    "gn:dem":63,
    "gn:feature_class":"P",
    "gn:feature_code":"PPL",
    "gn:name":"Ibrahim Mahtam",
    "gn:population":0,
    "gn:timezone":"Asia/Karachi",
    "iso:country":"PK",
    "wof:name":"Ibrahim Mahtam",
    "wof:placetype":"locality"
},
  "geometry": {"coordinates":[69.28745000000001,27.68349000000001],"type":"Point"}
}