{
  "type": "Feature",
  "properties": {
    "gn:admin1_code":"6",
    "gn:asciiname":"Nari",
    "gn:country_code":"PK",
    "gn:dem":1889,
    "gn:feature_class":"P",
    "gn:feature_code":"PPL",
    "gn:name":"Nari",
    "gn:population":0,
    "gn:timezone":"Asia/Karachi",
    "iso:country":"PK",
    "wof:name":"Nari",
    "wof:placetype":"locality"
},
  "geometry": {"coordinates":[73.58344,34.3508],"type":"Point"}
}