{
  "type": "Feature",
  "properties": {
    "gn:admin1_code":"4.0",
    "gn:asciiname":"Yaruwala",
    "gn:country_code":"PK",
    "gn:dem":102,
    "gn:feature_class":"P",
    "gn:feature_code":"PPL",
    "gn:name":"Yaruwala",
    "gn:population":0,
    "gn:timezone":"Asia/Karachi",
    "iso:country":"PK",
    "name:und_x_variant":[
        "Kh\u0101jiw\u0101la"
    ],
    "wof:name":"Yaruwala",
    "wof:placetype":"locality"
},
  "geometry": {"coordinates":[70.91896,29.36056],"type":"Point"}
}