{
  "type": "Feature",
  "properties": {
    "gn:admin1_code":"4.0",
    "gn:asciiname":"Daduwali",
    "gn:country_code":"PK",
    "gn:dem":201,
    "gn:feature_class":"P",
    "gn:feature_code":"PPL",
    "gn:name":"D\u0101duw\u0101li",
    "gn:population":0,
    "gn:timezone":"Asia/Karachi",
    "iso:country":"PK",
    "wof:name":"Daduwali",
    "wof:placetype":"locality"
},
  "geometry": {"coordinates":[73.81555999999998,31.5025],"type":"Point"}
}