{
  "type": "Feature",
  "properties": {
    "gn:admin1_code":"3.0",
    "gn:asciiname":"Dado Bhaik",
    "gn:country_code":"PK",
    "gn:dem":2803,
    "gn:feature_class":"P",
    "gn:feature_code":"PPL",
    "gn:name":"Dado Bhaik",
    "gn:population":0,
    "gn:timezone":"Asia/Karachi",
    "iso:country":"PK",
    "wof:name":"Dado Bhaik",
    "wof:placetype":"locality"
},
  "geometry": {"coordinates":[73.58535000000001,35.18088],"type":"Point"}
}