{
  "type": "Feature",
  "properties": {
    "gn:admin1_code":"3.0",
    "gn:asciiname":"Hurnara",
    "gn:country_code":"PK",
    "gn:dem":1250,
    "gn:feature_class":"P",
    "gn:feature_code":"PPL",
    "gn:name":"Hurnara",
    "gn:population":0,
    "gn:timezone":"Asia/Karachi",
    "iso:country":"PK",
    "name:und_x_variant":[
        "Harn\u0101ra"
    ],
    "wof:name":"Hurnara",
    "wof:placetype":"locality"
},
  "geometry": {"coordinates":[73.26584,34.05491],"type":"Point"}
}