{
  "type": "Feature",
  "properties": {
    "gn:admin1_code":"5",
    "gn:asciiname":"Abdul Qadir Sangrani",
    "gn:country_code":"PK",
    "gn:dem":25,
    "gn:feature_class":"P",
    "gn:feature_code":"PPL",
    "gn:name":"Abdul Qadir Sangrani",
    "gn:population":0,
    "gn:timezone":"Asia/Karachi",
    "iso:country":"PK",
    "name:und_x_variant":[
        "Abdul Q\u0101dir Sanjr\u0101ni"
    ],
    "wof:name":"Abdul Qadir Sangrani",
    "wof:placetype":"locality"
},
  "geometry": {"coordinates":[68.67963,26.13032],"type":"Point"}
}