{
  "type": "Feature",
  "properties": {
    "gn:admin1_code":"6",
    "gn:asciiname":"Hari Dori",
    "gn:country_code":"PK",
    "gn:dem":2016,
    "gn:feature_class":"P",
    "gn:feature_code":"PPL",
    "gn:name":"Hari Dori",
    "gn:population":0,
    "gn:timezone":"Asia/Karachi",
    "iso:country":"PK",
    "name:und_x_variant":[
        "Hari Dari"
    ],
    "wof:name":"Hari Dori",
    "wof:placetype":"locality"
},
  "geometry": {"coordinates":[74.18563,33.91528],"type":"Point"}
}