{
  "type": "Feature",
  "properties": {
    "gn:admin1_code":"5",
    "gn:asciiname":"Goth Khamiso",
    "gn:country_code":"PK",
    "gn:dem":45,
    "gn:feature_class":"P",
    "gn:feature_code":"PPL",
    "gn:name":"Goth Khamiso",
    "gn:population":0,
    "gn:timezone":"Asia/Karachi",
    "iso:country":"PK",
    "name:und_x_variant":[
        "Goth Kam\u0101l"
    ],
    "wof:name":"Goth Khamiso",
    "wof:placetype":"locality"
},
  "geometry": {"coordinates":[67.89846999999999,27.03422],"type":"Point"}
}