{
  "type": "Feature",
  "properties": {
    "gn:admin1_code":"4.0",
    "gn:asciiname":"Bet Rahia Ali",
    "gn:country_code":"PK",
    "gn:dem":110,
    "gn:feature_class":"P",
    "gn:feature_code":"PPL",
    "gn:name":"Bet Rahia Ali",
    "gn:population":0,
    "gn:timezone":"Asia/Karachi",
    "iso:country":"PK",
    "name:und_x_variant":[
        "Bet Ra Ali",
        "Bet R\u0101i Ali",
        "Bet Rahia Ali"
    ],
    "wof:name":"Bet Rahia Ali",
    "wof:placetype":"locality"
},
  "geometry": {"coordinates":[70.98865000000001,29.82088],"type":"Point"}
}