{
  "type": "Feature",
  "properties": {
    "gn:admin1_code":"01",
    "gn:asciiname":"Sarwai Kare",
    "gn:country_code":"PK",
    "gn:dem":1855,
    "gn:feature_class":"P",
    "gn:feature_code":"PPL",
    "gn:name":"Sarwai Kare",
    "gn:population":0,
    "gn:timezone":"Asia/Karachi",
    "iso:country":"PK",
    "name:und_x_variant":[
        "Sarwai Kanrai",
        "Sawarai Kili"
    ],
    "wof:name":"Sarwai Kare",
    "wof:placetype":"locality"
},
  "geometry": {"coordinates":[70.64673000000001,33.64485999999999],"type":"Point"}
}