{
  "type": "Feature",
  "properties": {
    "gn:admin1_code":"05",
    "gn:asciiname":"Goth Wariam Chachar",
    "gn:country_code":"PK",
    "gn:dem":66,
    "gn:feature_class":"P",
    "gn:feature_code":"PPL",
    "gn:name":"Goth Wariam Chachar",
    "gn:population":0,
    "gn:timezone":"Asia/Karachi",
    "iso:country":"PK",
    "name:und_x_variant":[
        "Warlam Ch\u0101char",
        "Goth Wariam Chachar"
    ],
    "wof:name":"Goth Wariam Chachar",
    "wof:placetype":"locality"
},
  "geometry": {"coordinates":[69.34558,27.85257],"type":"Point"}
}