{
  "type": "Feature",
  "properties": {
    "gn:admin1_code":"4.0",
    "gn:asciiname":"Thatti Mian Rage",
    "gn:country_code":"PK",
    "gn:dem":177,
    "gn:feature_class":"P",
    "gn:feature_code":"PPL",
    "gn:name":"Thatti Mian Rage",
    "gn:population":0,
    "gn:timezone":"Asia/Karachi",
    "iso:country":"PK",
    "name:und_x_variant":[
        "Thatti Mi\u0101n R\u0101njhan"
    ],
    "wof:name":"Thatti Mian Rage",
    "wof:placetype":"locality"
},
  "geometry": {"coordinates":[72.35598,32.08922],"type":"Point"}
}