{
  "type": "Feature",
  "properties": {
    "gn:admin1_code":"2.0",
    "gn:asciiname":"Kili Jumma Khan",
    "gn:country_code":"PK",
    "gn:dem":1367,
    "gn:feature_class":"P",
    "gn:feature_code":"PPL",
    "gn:name":"Kili Jumma Khan",
    "gn:population":0,
    "gn:timezone":"Asia/Karachi",
    "iso:country":"PK",
    "wof:name":"Kili Jumma Khan",
    "wof:placetype":"locality"
},
  "geometry": {"coordinates":[66.12267,29.50371],"type":"Point"}
}