{
  "type": "Feature",
  "properties": {
    "gn:admin1_code":"5.0",
    "gn:asciiname":"Wania jo Tar",
    "gn:country_code":"PK",
    "gn:dem":51,
    "gn:feature_class":"P",
    "gn:feature_code":"PPL",
    "gn:name":"Wania jo Tar",
    "gn:population":0,
    "gn:timezone":"Asia/Karachi",
    "iso:country":"PK",
    "name:und_x_variant":[
        "Ladhe jo Tar"
    ],
    "wof:name":"Wania jo Tar",
    "wof:placetype":"locality"
},
  "geometry": {"coordinates":[70.0104,24.6919],"type":"Point"}
}