{
  "type": "Feature",
  "properties": {
    "gn:admin1_code":"4.0",
    "gn:asciiname":"Baba Shah Din",
    "gn:country_code":"PK",
    "gn:dem":212,
    "gn:feature_class":"P",
    "gn:feature_code":"PPL",
    "gn:name":"Baba Shah Din",
    "gn:population":0,
    "gn:timezone":"Asia/Karachi",
    "iso:country":"PK",
    "name:eng_x_preferred":[
        "Baba Shah Din"
    ],
    "wof:name":"Baba Shah Din",
    "wof:placetype":"locality"
},
  "geometry": {"coordinates":[74.41670000000001,31.4216],"type":"Point"}
}