{
  "type": "Feature",
  "properties": {
    "gn:admin1_code":"4.0",
    "gn:asciiname":"Kharorawala",
    "gn:country_code":"PK",
    "gn:dem":143,
    "gn:feature_class":"P",
    "gn:feature_code":"PPL",
    "gn:name":"Kharorawala",
    "gn:population":0,
    "gn:timezone":"Asia/Karachi",
    "iso:country":"PK",
    "name:und_x_variant":[
        "Khararew\u0101la"
    ],
    "wof:name":"Kharorawala",
    "wof:placetype":"locality"
},
  "geometry": {"coordinates":[70.91540000000001,30.8521],"type":"Point"}
}