{
  "type": "Feature",
  "properties": {
    "gn:admin1_code":"04",
    "gn:asciiname":"Zorkot",
    "gn:country_code":"PK",
    "gn:dem":125,
    "gn:feature_class":"P",
    "gn:feature_code":"PPL",
    "gn:name":"Zorkot",
    "gn:population":0,
    "gn:timezone":"Asia/Karachi",
    "iso:country":"PK",
    "wof:name":"Zorkot",
    "wof:placetype":"locality"
},
  "geometry": {"coordinates":[71.73125,30.0429],"type":"Point"}
}