{
  "type": "Feature",
  "properties": {
    "gn:admin1_code":"5.0",
    "gn:asciiname":"Goth Pario",
    "gn:country_code":"PK",
    "gn:dem":333,
    "gn:feature_class":"P",
    "gn:feature_code":"PPL",
    "gn:name":"Goth Pario",
    "gn:population":0,
    "gn:timezone":"Asia/Karachi",
    "iso:country":"PK",
    "name:und_x_variant":[
        "Goth Paryo"
    ],
    "wof:name":"Goth Pario",
    "wof:placetype":"locality"
},
  "geometry": {"coordinates":[67.51105,25.61085],"type":"Point"}
}