{
  "type": "Feature",
  "properties": {
    "gn:admin1_code":"5.0",
    "gn:asciiname":"Muhammad Yusuf Bhurgari",
    "gn:country_code":"PK",
    "gn:dem":10,
    "gn:feature_class":"P",
    "gn:feature_code":"PPL",
    "gn:name":"Muhammad Yusuf Bhurgari",
    "gn:population":0,
    "gn:timezone":"Asia/Karachi",
    "iso:country":"PK",
    "wof:name":"Muhammad Yusuf Bhurgari",
    "wof:placetype":"locality"
},
  "geometry": {"coordinates":[69.49431,25.18432],"type":"Point"}
}