{
  "type": "Feature",
  "properties": {
    "gn:admin1_code":"2.0",
    "gn:asciiname":"Shabere",
    "gn:country_code":"PK",
    "gn:dem":1650,
    "gn:feature_class":"P",
    "gn:feature_code":"PPL",
    "gn:name":"Shabere",
    "gn:population":0,
    "gn:timezone":"Asia/Karachi",
    "iso:country":"PK",
    "name:und_x_variant":[
        "Sh\u0101bore"
    ],
    "wof:name":"Shabere",
    "wof:placetype":"locality"
},
  "geometry": {"coordinates":[69.93108000000001,31.03952],"type":"Point"}
}