{
  "type": "Feature",
  "properties": {
    "gn:admin1_code":"6",
    "gn:asciiname":"Katha",
    "gn:country_code":"PK",
    "gn:dem":1759,
    "gn:feature_class":"P",
    "gn:feature_code":"PPL",
    "gn:name":"Katha",
    "gn:population":0,
    "gn:timezone":"Asia/Karachi",
    "iso:country":"PK",
    "name:ceb_x_preferred":[
        "Katha"
    ],
    "name:swe_x_preferred":[
        "Katha"
    ],
    "wof:name":"Katha",
    "wof:placetype":"locality"
},
  "geometry": {"coordinates":[73.77394,34.42904],"type":"Point"}
}