{
  "type": "Feature",
  "properties": {
    "gn:admin1_code":"2.0",
    "gn:asciiname":"Kaza",
    "gn:country_code":"PK",
    "gn:dem":1416,
    "gn:feature_class":"P",
    "gn:feature_code":"PPL",
    "gn:name":"Kaza",
    "gn:population":0,
    "gn:timezone":"Asia/Karachi",
    "iso:country":"PK",
    "name:ara_x_preferred":[
        "\u0642\u0636\u0627\u0621"
    ],
    "name:bul_x_preferred":[
        "\u041a\u0430\u0430\u0437\u0430"
    ],
    "name:ckb_x_preferred":[
        "\u0642\u06d5\u0632\u0627"
    ],
    "name:ell_x_preferred":[
        "\u039a\u03b1\u03b6\u03ac\u03c2"
    ],
    "name:fra_x_preferred":[
        "Caza"
    ],
    "name:hin_x_preferred":[
        "\u0915\u093c\u091c\u093c\u093e"
    ],
    "name:hrv_x_preferred":[
        "Kadiluk"
    ],
    "name:ita_x_preferred":[
        "Qa\u1e0d\u0101\u02be"
    ],
    "name:mkd_x_preferred":[
        "\u041a\u0430\u0437\u0430"
    ],
    "name:pol_x_preferred":[
        "Kaza"
    ],
    "name:rus_x_preferred":[
        "\u041a\u0430\u0437\u0430"
    ],
    "name:slv_x_preferred":[
        "Kaza"
    ],
    "name:sqi_x_preferred":[
        "Kazaja"
    ],
    "name:srp_x_preferred":[
        "\u041a\u0430\u0437\u0430"
    ],
    "name:ukr_x_preferred":[
        "\u041a\u0430\u0437\u0430"
    ],
    "name:urd_x_preferred":[
        "\u0642\u0636\u0627\u0621"
    ],
    "name:vie_x_preferred":[
        "Kaza"
    ],
    "wof:name":"Kaza",
    "wof:placetype":"locality"
},
  "geometry": {"coordinates":[69.68042,30.35851],"type":"Point"}
}