{
  "type": "Feature",
  "properties": {
    "gn:admin1_code":"2.0",
    "gn:asciiname":"Kaza",
    "gn:country_code":"PK",
    "gn:dem":1416,
    "gn:feature_class":"P",
    "gn:feature_code":"PPL",
    "gn:name":"Kaza",
    "gn:population":0,
    "gn:timezone":"Asia/Karachi",
    "iso:country":"PK",
    "wof:name":"Kaza",
    "wof:placetype":"locality"
},
  "geometry": {"coordinates":[69.68042,30.35851],"type":"Point"}
}