{
  "type": "Feature",
  "properties": {
    "gn:admin1_code":"4",
    "gn:asciiname":"Chak Ninety-four Gugera Branch",
    "gn:country_code":"PK",
    "gn:dem":194,
    "gn:feature_class":"P",
    "gn:feature_code":"PPL",
    "gn:name":"Chak Ninety-four Gugera Branch",
    "gn:population":0,
    "gn:timezone":"Asia/Karachi",
    "iso:country":"PK",
    "name:und_x_variant":[
        "Shankar"
    ],
    "wof:name":"Chak Ninety-four Gugera Branch",
    "wof:placetype":"locality"
},
  "geometry": {"coordinates":[73.46989000000001,31.43262],"type":"Point"}
}