{
  "type": "Feature",
  "properties": {
    "gn:admin1_code":"4",
    "gn:asciiname":"Chak Forty-three -Ten Right",
    "gn:country_code":"PK",
    "gn:dem":137,
    "gn:feature_class":"P",
    "gn:feature_code":"PPL",
    "gn:name":"Chak Forty-three -Ten Right",
    "gn:population":0,
    "gn:timezone":"Asia/Karachi",
    "iso:country":"PK",
    "name:und_x_variant":[
        "R\u0101jew\u0101la"
    ],
    "wof:name":"Chak Forty-three -Ten Right",
    "wof:placetype":"locality"
},
  "geometry": {"coordinates":[72.05767,30.19315],"type":"Point"}
}