{
  "type": "Feature",
  "properties": {
    "gn:admin1_code":"4",
    "gn:asciiname":"Chak One Hundred Ninety-three Eastern Bar",
    "gn:country_code":"PK",
    "gn:dem":149,
    "gn:feature_class":"P",
    "gn:feature_code":"PPL",
    "gn:name":"Chak One Hundred Ninety-three Eastern Bar",
    "gn:population":0,
    "gn:timezone":"Asia/Karachi",
    "iso:country":"PK",
    "name:und_x_variant":[
        "Chak One Hundred Ninety-three"
    ],
    "wof:name":"Chak One Hundred Ninety-three Eastern Bar",
    "wof:placetype":"locality"
},
  "geometry": {"coordinates":[72.80938,30.23522],"type":"Point"}
}