{
  "type": "Feature",
  "properties": {
    "gn:admin1_code":"04",
    "gn:asciiname":"Chak Madhu",
    "gn:country_code":"PK",
    "gn:dem":231,
    "gn:feature_class":"P",
    "gn:feature_code":"PPL",
    "gn:name":"Chak Madhu",
    "gn:population":0,
    "gn:timezone":"Asia/Karachi",
    "iso:country":"PK",
    "name:fas_x_preferred":[
        "\u0631\u0627\u06cc\u0647 \u0686\u06a9 \u0645\u062f\u0648"
    ],
    "name:und_x_variant":[
        "Raya Chak Mado",
        "Raiya Chak Maddu",
        "Chak Madhu"
    ],
    "name:urd_x_preferred":[
        "\u0631\u0627\u06cc\u06c1 \u0686\u06a9 \u0645\u062f\u0648"
    ],
    "wof:name":"Chak Madhu",
    "wof:placetype":"locality"
},
  "geometry": {"coordinates":[73.68476,32.92674],"type":"Point"}
}