{
  "type": "Feature",
  "properties": {
    "gn:admin1_code":"04",
    "gn:asciiname":"Chak Madhu",
    "gn:country_code":"PK",
    "gn:dem":231,
    "gn:feature_class":"P",
    "gn:feature_code":"PPL",
    "gn:name":"Chak Madhu",
    "gn:population":0,
    "gn:timezone":"Asia/Karachi",
    "iso:country":"PK",
    "name:und_x_variant":[
        "Raya Chak Mado",
        "Raiya Chak Maddu",
        "Chak Madhu"
    ],
    "wof:name":"Chak Madhu",
    "wof:placetype":"locality"
},
  "geometry": {"coordinates":[73.68476,32.92674],"type":"Point"}
}