{
  "type": "Feature",
  "properties": {
    "gn:admin1_code":"5.0",
    "gn:asciiname":"Muhammad Fazil",
    "gn:country_code":"PK",
    "gn:dem":254,
    "gn:feature_class":"P",
    "gn:feature_code":"PPL",
    "gn:name":"Muhammad Fazil",
    "gn:population":0,
    "gn:timezone":"Asia/Karachi",
    "iso:country":"PK",
    "name:und_x_variant":[
        "Goth Muhammad F\u0101zil"
    ],
    "wof:name":"Muhammad Fazil",
    "wof:placetype":"locality"
},
  "geometry": {"coordinates":[67.5735,25.30034],"type":"Point"}
}