{
  "type": "Feature",
  "properties": {
    "gn:admin1_code":"04",
    "gn:asciiname":"Chak Sixty-five -Twelve Left",
    "gn:country_code":"PK",
    "gn:dem":148,
    "gn:feature_class":"P",
    "gn:feature_code":"PPL",
    "gn:name":"Chak Sixty-five -Twelve Left",
    "gn:population":0,
    "gn:timezone":"Asia/Karachi",
    "iso:country":"PK",
    "name:und_x_variant":[
        "Sh\u0101h Husain",
        "Sh\u0101h Hussain"
    ],
    "wof:name":"Chak Sixty-five -Twelve Left",
    "wof:placetype":"locality"
},
  "geometry": {"coordinates":[72.54288000000003,30.2905],"type":"Point"}
}