{
  "type": "Feature",
  "properties": {
    "gn:admin1_code":"2.0",
    "gn:asciiname":"Kili Musa Khan",
    "gn:country_code":"PK",
    "gn:dem":2413,
    "gn:feature_class":"P",
    "gn:feature_code":"PPL",
    "gn:name":"Kili Musa Khan",
    "gn:population":0,
    "gn:timezone":"Asia/Karachi",
    "iso:country":"PK",
    "wof:name":"Kili Musa Khan",
    "wof:placetype":"locality"
},
  "geometry": {"coordinates":[67.11444,31.00215],"type":"Point"}
}