{
  "type": "Feature",
  "properties": {
    "gn:admin1_code":"4",
    "gn:asciiname":"Wazira Gadhoke",
    "gn:country_code":"PK",
    "gn:dem":170,
    "gn:feature_class":"P",
    "gn:feature_code":"PPL",
    "gn:name":"Wazira Gadhoke",
    "gn:population":0,
    "gn:timezone":"Asia/Karachi",
    "iso:country":"PK",
    "name:und_x_variant":[
        "Waz\u012bra",
        "Waz\u012bra Gaddhoka"
    ],
    "wof:name":"Wazira Gadhoke",
    "wof:placetype":"locality"
},
  "geometry": {"coordinates":[73.69459999999999,30.30014000000001],"type":"Point"}
}