{
  "type": "Feature",
  "properties": {
    "gn:admin1_code":"1.0",
    "gn:asciiname":"Shangir",
    "gn:country_code":"PK",
    "gn:dem":619,
    "gn:feature_class":"P",
    "gn:feature_code":"PPL",
    "gn:name":"Shangir",
    "gn:population":0,
    "gn:timezone":"Asia/Karachi",
    "iso:country":"PK",
    "wof:name":"Shangir",
    "wof:placetype":"locality"
},
  "geometry": {"coordinates":[71.32366999999998,34.06708],"type":"Point"}
}