{
  "type": "Feature",
  "properties": {
    "gn:admin1_code":"1.0",
    "gn:asciiname":"Kunj Alizai",
    "gn:country_code":"PK",
    "gn:dem":1495,
    "gn:feature_class":"P",
    "gn:feature_code":"PPL",
    "gn:name":"Kunj Alizai",
    "gn:population":0,
    "gn:timezone":"Asia/Karachi",
    "iso:country":"PK",
    "name:und_x_variant":[
        "Kambar Ali Kili"
    ],
    "wof:name":"Kunj Alizai",
    "wof:placetype":"locality"
},
  "geometry": {"coordinates":[70.03161999999999,33.81907],"type":"Point"}
}