{
  "type": "Feature",
  "properties": {
    "gn:admin1_code":"7.0",
    "gn:asciiname":"Gamba Thang",
    "gn:country_code":"PK",
    "gn:dem":2879,
    "gn:feature_class":"P",
    "gn:feature_code":"PPL",
    "gn:name":"Gamba Thang",
    "gn:population":0,
    "gn:timezone":"Asia/Karachi",
    "iso:country":"PK",
    "wof:name":"Gamba Thang",
    "wof:placetype":"locality"
},
  "geometry": {"coordinates":[76.65505999999998,35.26358],"type":"Point"}
}