{
  "type": "Feature",
  "properties": {
    "gn:admin1_code":"4.0",
    "gn:asciiname":"Charala",
    "gn:country_code":"PK",
    "gn:dem":179,
    "gn:feature_class":"P",
    "gn:feature_code":"PPL",
    "gn:name":"Charala",
    "gn:population":0,
    "gn:timezone":"Asia/Karachi",
    "iso:country":"PK",
    "name:und_x_variant":[
        "Chakr\u0101la",
        "Charala"
    ],
    "wof:name":"Charala",
    "wof:placetype":"locality"
},
  "geometry": {"coordinates":[72.36471999999998,32.10581],"type":"Point"}
}