{
  "type": "Feature",
  "properties": {
    "iso:country":"PK",
    "name:fas_x_preferred":[
        "\u0647\u062f\u0627\u0644\u06cc"
    ],
    "name:fra_x_preferred":[
        "Hadali"
    ],
    "name:por_x_preferred":[
        "Hadali"
    ],
    "name:spa_x_preferred":[
        "Hadali"
    ],
    "name:urd_x_preferred":[
        "\u06c1\u0688\u0627\u0644\u06cc"
    ],
    "name:vie_x_preferred":[
        "Hadali"
    ],
    "qs:gn_country":"PK",
    "qs:gn_fcode":"PPL",
    "qs:gn_pop":49663,
    "qs:name":"Hadali",
    "qs:name_adm0":"Pakistan",
    "qs:name_adm1":"Punjab",
    "qs:photos":0,
    "qs:photos_1k":0,
    "qs:photos_9k":0,
    "qs:photos_9r":0,
    "qs:photos_all":0,
    "qs:photos_sr":0,
    "qs:placetype":"Town",
    "qs:pop_sr":"7",
    "qs:woe_adm0":23424922,
    "wd:wordcount":358,
    "wof:name":"Hadali",
    "wof:placetype":"locality",
    "wof:population":49663
},
  "geometry": {"coordinates":[74.56904,32.64132],"type":"Point"}
}