{
  "type": "Feature",
  "properties": {
    "gn:admin1_code":"4",
    "gn:asciiname":"Dost Muhammad Talai",
    "gn:country_code":"PK",
    "gn:dem":512,
    "gn:feature_class":"P",
    "gn:feature_code":"PPL",
    "gn:name":"Dost Muhammad Talai",
    "gn:population":0,
    "gn:timezone":"Asia/Karachi",
    "iso:country":"PK",
    "wof:name":"Dost Muhammad Talai",
    "wof:placetype":"locality"
},
  "geometry": {"coordinates":[70.04418000000001,29.78366],"type":"Point"}
}