{
  "type": "Feature",
  "properties": {
    "gn:admin1_code":"4",
    "gn:asciiname":"Chah Lal Awanwala",
    "gn:country_code":"PK",
    "gn:dem":185,
    "gn:feature_class":"P",
    "gn:feature_code":"PPL",
    "gn:name":"Chah Lal Awanwala",
    "gn:population":0,
    "gn:timezone":"Asia/Karachi",
    "iso:country":"PK",
    "name:und_x_variant":[
        "Ch\u0101h L\u0101lw\u0101la"
    ],
    "wof:name":"Chah Lal Awanwala",
    "wof:placetype":"locality"
},
  "geometry": {"coordinates":[71.30703000000003,31.90701],"type":"Point"}
}