{
  "type": "Feature",
  "properties": {
    "gn:admin1_code":"3.0",
    "gn:asciiname":"Markande",
    "gn:country_code":"PK",
    "gn:dem":783,
    "gn:feature_class":"P",
    "gn:feature_code":"PPL",
    "gn:name":"Markande",
    "gn:population":0,
    "gn:timezone":"Asia/Karachi",
    "iso:country":"PK",
    "wof:name":"Markande",
    "wof:placetype":"locality"
},
  "geometry": {"coordinates":[72.48674,34.54712],"type":"Point"}
}