{
  "type": "Feature",
  "properties": {
    "gn:admin1_code":"5",
    "gn:asciiname":"Goth Phakrato Mahar",
    "gn:country_code":"PK",
    "gn:dem":70,
    "gn:feature_class":"P",
    "gn:feature_code":"PPL",
    "gn:name":"Goth Phakrato Mahar",
    "gn:population":0,
    "gn:timezone":"Asia/Karachi",
    "iso:country":"PK",
    "name:und_x_variant":[
        "Phekrato"
    ],
    "wof:name":"Goth Phakrato Mahar",
    "wof:placetype":"locality"
},
  "geometry": {"coordinates":[69.49658000000001,28.03299],"type":"Point"}
}