{
  "type": "Feature",
  "properties": {
    "gn:admin1_code":"5",
    "gn:asciiname":"Yar Muhammad Jagirani",
    "gn:country_code":"PK",
    "gn:dem":52,
    "gn:feature_class":"P",
    "gn:feature_code":"PPL",
    "gn:name":"Yar Muhammad Jagirani",
    "gn:population":0,
    "gn:timezone":"Asia/Karachi",
    "iso:country":"PK",
    "name:und_x_variant":[
        "Chakr\u0101ni"
    ],
    "wof:name":"Yar Muhammad Jagirani",
    "wof:placetype":"locality"
},
  "geometry": {"coordinates":[68.51264999999999,27.20256],"type":"Point"}
}