{
  "type": "Feature",
  "properties": {
    "gn:admin1_code":"3",
    "gn:asciiname":"Thhathi Khurd",
    "gn:country_code":"PK",
    "gn:dem":958,
    "gn:feature_class":"P",
    "gn:feature_code":"PPL",
    "gn:name":"Thhathi Khurd",
    "gn:population":0,
    "gn:timezone":"Asia/Karachi",
    "iso:country":"PK",
    "name:und_x_variant":[
        "Th\u0101thi"
    ],
    "wof:name":"Thhathi Khurd",
    "wof:placetype":"locality"
},
  "geometry": {"coordinates":[73.05412,34.38772],"type":"Point"}
}