{
  "type": "Feature",
  "properties": {
    "gn:admin1_code":"4",
    "gn:asciiname":"Ojhriwala",
    "gn:country_code":"PK",
    "gn:dem":132,
    "gn:feature_class":"P",
    "gn:feature_code":"PPL",
    "gn:name":"Ojhr\u012bw\u0101la",
    "gn:population":0,
    "gn:timezone":"Asia/Karachi",
    "iso:country":"PK",
    "name:eng_x_preferred":[
        "Ojhr\u012bw\u0101la"
    ],
    "wof:name":"Ojhriwala",
    "wof:placetype":"locality"
},
  "geometry": {"coordinates":[70.92198,30.48753],"type":"Point"}
}