{
  "type": "Feature",
  "properties": {
    "gn:admin1_code":"2",
    "gn:asciiname":"Wahib Haveli",
    "gn:country_code":"PK",
    "gn:dem":1403,
    "gn:feature_class":"P",
    "gn:feature_code":"PPL",
    "gn:name":"Wahib Haveli",
    "gn:population":0,
    "gn:timezone":"Asia/Karachi",
    "iso:country":"PK",
    "name:und_x_variant":[
        "Wah\u0101b ka Haweli"
    ],
    "wof:name":"Wahib Haveli",
    "wof:placetype":"locality"
},
  "geometry": {"coordinates":[69.72505,30.08757],"type":"Point"}
}