{
  "type": "Feature",
  "properties": {
    "gn:admin1_code":"5",
    "gn:asciiname":"Goth Chaudh",
    "gn:country_code":"PK",
    "gn:dem":33,
    "gn:feature_class":"P",
    "gn:feature_code":"PPL",
    "gn:name":"Goth Chaudh",
    "gn:population":0,
    "gn:timezone":"Asia/Karachi",
    "iso:country":"PK",
    "name:und_x_variant":[
        "Goth Chaudhri Naz\u012br Ahmad"
    ],
    "wof:name":"Goth Chaudh",
    "wof:placetype":"locality"
},
  "geometry": {"coordinates":[68.58665999999999,26.37403],"type":"Point"}
}