{
  "type": "Feature",
  "properties": {
    "gn:admin1_code":"4",
    "gn:asciiname":"Chodhwal",
    "gn:country_code":"PK",
    "gn:dem":248,
    "gn:feature_class":"P",
    "gn:feature_code":"PPL",
    "gn:name":"Chodhwal",
    "gn:population":0,
    "gn:timezone":"Asia/Karachi",
    "iso:country":"PK",
    "name:und_x_variant":[
        "Chaodhow\u0101l"
    ],
    "wof:name":"Chodhwal",
    "wof:placetype":"locality"
},
  "geometry": {"coordinates":[74.14488,32.66942],"type":"Point"}
}