{
  "type": "Feature",
  "properties": {
    "gn:admin1_code":"3",
    "gn:asciiname":"Burj",
    "gn:country_code":"PK",
    "gn:dem":3359,
    "gn:feature_class":"P",
    "gn:feature_code":"PPL",
    "gn:name":"Burj",
    "gn:population":0,
    "gn:timezone":"Asia/Karachi",
    "iso:country":"PK",
    "name:ceb_x_preferred":[
        "Burj"
    ],
    "name:deu_x_preferred":[
        "Burj"
    ],
    "name:fra_x_preferred":[
        "Burj"
    ],
    "name:heb_x_preferred":[
        "\u05d1\u05d5\u05e8\u05d2'"
    ],
    "name:hin_x_preferred":[
        "\u092c\u0941\u0930\u094d\u091c"
    ],
    "name:swe_x_preferred":[
        "Burj"
    ],
    "name:uzb_x_preferred":[
        "Burj"
    ],
    "wof:name":"Burj",
    "wof:placetype":"locality"
},
  "geometry": {"coordinates":[73.22221999999999,34.86389],"type":"Point"}
}