{
  "type": "Feature",
  "properties": {
    "gn:admin1_code":"03",
    "gn:asciiname":"Kaso",
    "gn:country_code":"PK",
    "gn:dem":1638,
    "gn:feature_class":"P",
    "gn:feature_code":"PPL",
    "gn:name":"Kaso",
    "gn:population":0,
    "gn:timezone":"Asia/Karachi",
    "iso:country":"PK",
    "name:ceb_x_preferred":[
        "Kaso"
    ],
    "name:eng_x_preferred":[
        "Kaso"
    ],
    "name:swe_x_preferred":[
        "Kaso"
    ],
    "wof:name":"Kaso",
    "wof:placetype":"locality"
},
  "geometry": {"coordinates":[71.98488,34.79564],"type":"Point"}
}