{
  "type": "Feature",
  "properties": {
    "gn:admin1_code":"2.0",
    "gn:asciiname":"Goth Abdul",
    "gn:country_code":"PK",
    "gn:dem":293,
    "gn:feature_class":"P",
    "gn:feature_code":"PPL",
    "gn:name":"Goth Abdul",
    "gn:population":0,
    "gn:timezone":"Asia/Karachi",
    "iso:country":"PK",
    "wof:name":"Goth Abdul",
    "wof:placetype":"locality"
},
  "geometry": {"coordinates":[67.16915999999999,26.20463],"type":"Point"}
}