{
  "type": "Feature",
  "properties": {
    "gn:admin1_code":"2.0",
    "gn:asciiname":"Gulab Karez",
    "gn:country_code":"PK",
    "gn:dem":1887,
    "gn:feature_class":"P",
    "gn:feature_code":"PPL",
    "gn:name":"Gulab Karez",
    "gn:population":0,
    "gn:timezone":"Asia/Karachi",
    "iso:country":"PK",
    "wof:name":"Gulab Karez",
    "wof:placetype":"locality"
},
  "geometry": {"coordinates":[68.21252,30.44400000000001],"type":"Point"}
}