{
  "type": "Feature",
  "properties": {
    "gn:admin1_code":"5",
    "gn:asciiname":"Goth Maluk Khan",
    "gn:country_code":"PK",
    "gn:dem":76,
    "gn:feature_class":"P",
    "gn:feature_code":"PPL",
    "gn:name":"Goth Maluk Khan",
    "gn:population":0,
    "gn:timezone":"Asia/Karachi",
    "iso:country":"PK",
    "name:und_x_variant":[
        "Daryah Kh\u0101n"
    ],
    "wof:name":"Goth Maluk Khan",
    "wof:placetype":"locality"
},
  "geometry": {"coordinates":[69.48574000000001,28.37593],"type":"Point"}
}