{
  "type": "Feature",
  "properties": {
    "gn:admin1_code":"5.0",
    "gn:asciiname":"Usman Nokri Hotal",
    "gn:country_code":"PK",
    "gn:dem":40,
    "gn:feature_class":"P",
    "gn:feature_code":"PPL",
    "gn:name":"Usman Nokri Hotal",
    "gn:population":0,
    "gn:timezone":"Asia/Karachi",
    "iso:country":"PK",
    "wof:name":"Usman Nokri Hotal",
    "wof:placetype":"locality"
},
  "geometry": {"coordinates":[69.91824,25.22788],"type":"Point"}
}