{
  "type": "Feature",
  "properties": {
    "gn:admin1_code":"4.0",
    "gn:asciiname":"Rajwal",
    "gn:country_code":"PK",
    "gn:dem":477,
    "gn:feature_class":"P",
    "gn:feature_code":"PPL",
    "gn:name":"Rajwal",
    "gn:population":0,
    "gn:timezone":"Asia/Karachi",
    "iso:country":"PK",
    "wof:name":"Rajwal",
    "wof:placetype":"locality"
},
  "geometry": {"coordinates":[73.39794999999999,33.11684],"type":"Point"}
}