{
  "type": "Feature",
  "properties": {
    "gn:admin1_code":"2.0",
    "gn:asciiname":"Mozo Nur Muhammad Dilran",
    "gn:country_code":"PK",
    "gn:dem":1164,
    "gn:feature_class":"P",
    "gn:feature_code":"PPL",
    "gn:name":"Mozo Nur Muhammad Dilran",
    "gn:population":0,
    "gn:timezone":"Asia/Karachi",
    "iso:country":"PK",
    "wof:name":"Mozo Nur Muhammad Dilran",
    "wof:placetype":"locality"
},
  "geometry": {"coordinates":[67.14081999999999,27.57454],"type":"Point"}
}