{
  "type": "Feature",
  "properties": {
    "iso:country":"PK",
    "name:eng_x_preferred":[
        "Zafarwal"
    ],
    "name:fre_x_preferred":[
        "Zafarwal"
    ],
    "name:unk_x_variant":[
        "Zafarw\u0101l"
    ],
    "name:urd_x_preferred":[
        "\u0638\u0641\u0631\u0648\u0627\u0644"
    ],
    "qs:gn_country":"PK",
    "qs:gn_fcode":"PPL",
    "qs:gn_pop":23078,
    "qs:name":"Zaffarwal",
    "qs:name_adm0":"Pakistan",
    "qs:name_adm1":"Punjab",
    "qs:photos":0,
    "qs:photos_1k":0,
    "qs:photos_9k":0,
    "qs:photos_9r":0,
    "qs:photos_all":0,
    "qs:photos_sr":0,
    "qs:placetype":"Town",
    "qs:pop_sr":"7",
    "qs:woe_adm0":23424922,
    "wof:name":"Zaffarwal",
    "wof:placetype":"locality",
    "wof:population":23078
},
  "geometry": {"coordinates":[74.89987000000001,32.34631],"type":"Point"}
}