{
  "type": "Feature",
  "properties": {
    "gn:admin1_code":"3.0",
    "gn:asciiname":"Khushal Garhi",
    "gn:country_code":"PK",
    "gn:dem":395,
    "gn:feature_class":"P",
    "gn:feature_code":"PPL",
    "gn:name":"Khushal Garhi",
    "gn:population":0,
    "gn:timezone":"Asia/Karachi",
    "iso:country":"PK",
    "name:eng_x_preferred":[
        "Khushh\u0101igarh"
    ],
    "name:eng_x_variant":[
        "Faq\u012br\u0101b\u0101d"
    ],
    "wof:name":"Khushal Garhi",
    "wof:placetype":"locality"
},
  "geometry": {"coordinates":[71.88436,34.38772],"type":"Point"}
}