{
  "type": "Feature",
  "properties": {
    "gn:admin1_code":"3",
    "gn:asciiname":"Babar Qala",
    "gn:country_code":"PK",
    "gn:dem":314,
    "gn:feature_class":"P",
    "gn:feature_code":"PPL",
    "gn:name":"Babar Qala",
    "gn:population":0,
    "gn:timezone":"Asia/Karachi",
    "iso:country":"PK",
    "name:eng_x_preferred":[
        "B\u0101bar Kili"
    ],
    "wof:name":"Babar Qala",
    "wof:placetype":"locality"
},
  "geometry": {"coordinates":[72.05965,34.07303],"type":"Point"}
}