{
  "type": "Feature",
  "properties": {
    "gn:admin1_code":"4.0",
    "gn:asciiname":"Nai Ath Kassi",
    "gn:country_code":"PK",
    "gn:dem":133,
    "gn:feature_class":"P",
    "gn:feature_code":"PPL",
    "gn:name":"Nai Ath Kassi",
    "gn:population":0,
    "gn:timezone":"Asia/Karachi",
    "iso:country":"PK",
    "wof:name":"Nai Ath Kassi",
    "wof:placetype":"locality"
},
  "geometry": {"coordinates":[71.81978000000002,30.31003],"type":"Point"}
}