{
  "type": "Feature",
  "properties": {
    "gn:admin1_code":"04",
    "gn:asciiname":"Nawa Sighu",
    "gn:country_code":"PK",
    "gn:dem":183,
    "gn:feature_class":"P",
    "gn:feature_code":"PPL",
    "gn:name":"Nawa Sighu",
    "gn:population":0,
    "gn:timezone":"Asia/Karachi",
    "iso:country":"PK",
    "name:und_x_variant":[
        "Nawan Saggu",
        "Nawa Sighu"
    ],
    "wof:name":"Nawa Sighu",
    "wof:placetype":"locality"
},
  "geometry": {"coordinates":[71.85279,31.72774],"type":"Point"}
}