{
  "type": "Feature",
  "properties": {
    "gn:admin1_code":"5",
    "gn:asciiname":"Qazi Yar Muhammad",
    "gn:country_code":"PK",
    "gn:dem":23,
    "gn:feature_class":"P",
    "gn:feature_code":"PPL",
    "gn:name":"Qazi Yar Muhammad",
    "gn:population":0,
    "gn:timezone":"Asia/Karachi",
    "iso:country":"PK",
    "wof:name":"Qazi Yar Muhammad",
    "wof:placetype":"locality"
},
  "geometry": {"coordinates":[69.01279,25.82168],"type":"Point"}
}