{
  "type": "Feature",
  "properties": {
    "gn:admin1_code":"6.0",
    "gn:asciiname":"Nala",
    "gn:country_code":"PK",
    "gn:dem":623,
    "gn:feature_class":"P",
    "gn:feature_code":"PPL",
    "gn:name":"Nala",
    "gn:population":0,
    "gn:timezone":"Asia/Karachi",
    "iso:country":"PK",
    "wof:name":"Nala",
    "wof:placetype":"locality"
},
  "geometry": {"coordinates":[73.83736999999998,33.53161],"type":"Point"}
}