{
  "type": "Feature",
  "properties": {
    "gn:admin1_code":"04",
    "gn:asciiname":"Mangot",
    "gn:country_code":"PK",
    "gn:dem":543,
    "gn:feature_class":"P",
    "gn:feature_code":"PPL",
    "gn:name":"Mangot",
    "gn:population":0,
    "gn:timezone":"Asia/Karachi",
    "iso:country":"PK",
    "wof:name":"Mangot",
    "wof:placetype":"locality"
},
  "geometry": {"coordinates":[73.22429,33.01773],"type":"Point"}
}