{
  "type": "Feature",
  "properties": {
    "gn:admin1_code":"2.0",
    "gn:asciiname":"Chhota Bazar",
    "gn:country_code":"PK",
    "gn:dem":31,
    "gn:feature_class":"P",
    "gn:feature_code":"PPL",
    "gn:name":"Chhota Bazar",
    "gn:population":0,
    "gn:timezone":"Asia/Karachi",
    "iso:country":"PK",
    "wof:name":"Chhota Bazar",
    "wof:placetype":"locality"
},
  "geometry": {"coordinates":[66.76519,24.97009],"type":"Point"}
}