{
  "type": "Feature",
  "properties": {
    "gn:admin1_code":"4.0",
    "gn:asciiname":"Kotla Fauja",
    "gn:country_code":"PK",
    "gn:dem":92,
    "gn:feature_class":"P",
    "gn:feature_code":"PPL",
    "gn:name":"Kotla Fauja",
    "gn:population":0,
    "gn:timezone":"Asia/Karachi",
    "iso:country":"PK",
    "name:und_x_variant":[
        "Kotla Fauj Ali"
    ],
    "wof:name":"Kotla Fauja",
    "wof:placetype":"locality"
},
  "geometry": {"coordinates":[70.31009,28.94065],"type":"Point"}
}