{
  "type": "Feature",
  "properties": {
    "gn:admin1_code":"4",
    "gn:asciiname":"Dhadra",
    "gn:country_code":"PK",
    "gn:dem":232,
    "gn:feature_class":"P",
    "gn:feature_code":"PPL",
    "gn:name":"Dhadra",
    "gn:population":0,
    "gn:timezone":"Asia/Karachi",
    "iso:country":"PK",
    "name:und_x_variant":[
        "Dodhra"
    ],
    "wof:name":"Dhadra",
    "wof:placetype":"locality"
},
  "geometry": {"coordinates":[74.01143,32.55372],"type":"Point"}
}