{
  "type": "Feature",
  "properties": {
    "gn:admin1_code":"4",
    "gn:asciiname":"Basti Muhammad Allahwali",
    "gn:country_code":"PK",
    "gn:dem":147,
    "gn:feature_class":"P",
    "gn:feature_code":"PPL",
    "gn:name":"Basti Muhammad Allahwali",
    "gn:population":0,
    "gn:timezone":"Asia/Karachi",
    "iso:country":"PK",
    "name:und_x_variant":[
        "Basti Muhammad \u0100la"
    ],
    "wof:name":"Basti Muhammad Allahwali",
    "wof:placetype":"locality"
},
  "geometry": {"coordinates":[72.13254000000001,31.03038],"type":"Point"}
}