{
  "type": "Feature",
  "properties": {
    "gn:admin1_code":"6",
    "gn:asciiname":"Amral",
    "gn:country_code":"PK",
    "gn:dem":1099,
    "gn:feature_class":"P",
    "gn:feature_code":"PPL",
    "gn:name":"Amral",
    "gn:population":0,
    "gn:timezone":"Asia/Karachi",
    "iso:country":"PK",
    "wof:name":"Amral",
    "wof:placetype":"locality"
},
  "geometry": {"coordinates":[74.00024000000001,33.33006],"type":"Point"}
}