{
  "type": "Feature",
  "properties": {
    "gn:admin1_code":"04",
    "gn:asciiname":"Wahali Zer",
    "gn:country_code":"PK",
    "gn:dem":765,
    "gn:feature_class":"P",
    "gn:feature_code":"PPL",
    "gn:name":"Wahali Zer",
    "gn:population":0,
    "gn:timezone":"Asia/Karachi",
    "iso:country":"PK",
    "name:und_x_variant":[
        "Wahali Hardo",
        "Wah\u0101li",
        "Wahali Zer"
    ],
    "wof:name":"Wahali Zer",
    "wof:placetype":"locality"
},
  "geometry": {"coordinates":[73.04268,32.75575],"type":"Point"}
}