{
  "type": "Feature",
  "properties": {
    "gn:admin1_code":"5",
    "gn:asciiname":"Goth Budho Wahan",
    "gn:country_code":"PK",
    "gn:dem":55,
    "gn:feature_class":"P",
    "gn:feature_code":"PPL",
    "gn:name":"Goth Budho Wahan",
    "gn:population":0,
    "gn:timezone":"Asia/Karachi",
    "iso:country":"PK",
    "name:und_x_variant":[
        "Budha W\u0101h\u0101n"
    ],
    "wof:name":"Goth Budho Wahan",
    "wof:placetype":"locality"
},
  "geometry": {"coordinates":[68.12902,27.42503],"type":"Point"}
}