{
  "type": "Feature",
  "properties": {
    "gn:admin1_code":"5.0",
    "gn:asciiname":"Kandrah",
    "gn:country_code":"PK",
    "gn:dem":11,
    "gn:feature_class":"P",
    "gn:feature_code":"PPL",
    "gn:name":"Kandrah",
    "gn:population":0,
    "gn:timezone":"Asia/Karachi",
    "iso:country":"PK",
    "name:und_x_variant":[
        "Kandra"
    ],
    "wof:name":"Kandrah",
    "wof:placetype":"locality"
},
  "geometry": {"coordinates":[68.16068,24.64011],"type":"Point"}
}