{
  "type": "Feature",
  "properties": {
    "gn:admin1_code":"04",
    "gn:asciiname":"Muhammadpur Diwan",
    "gn:country_code":"PK",
    "gn:dem":102,
    "gn:feature_class":"P",
    "gn:feature_code":"PPL",
    "gn:name":"Muhammadpur Diwan",
    "gn:population":0,
    "gn:timezone":"Asia/Karachi",
    "iso:country":"PK",
    "name:und_x_variant":[
        "Muhammadpur",
        "Muhammadpur Diwan"
    ],
    "name:urd_x_preferred":[
        "\u0645\u062d\u0645\u062f \u067e\u0648\u0631 \u062f\u06cc\u0648\u0627\u0646"
    ],
    "wof:name":"Muhammadpur Diwan",
    "wof:placetype":"locality"
},
  "geometry": {"coordinates":[70.51089,29.47155],"type":"Point"}
}