{
  "type": "Feature",
  "properties": {
    "gn:admin1_code":"4.0",
    "gn:asciiname":"Warwari",
    "gn:country_code":"PK",
    "gn:dem":75,
    "gn:feature_class":"P",
    "gn:feature_code":"PPL",
    "gn:name":"Warwari",
    "gn:population":0,
    "gn:timezone":"Asia/Karachi",
    "iso:country":"PK",
    "wof:name":"Warwari",
    "wof:placetype":"locality"
},
  "geometry": {"coordinates":[69.9678,28.13648],"type":"Point"}
}