{
  "type": "Feature",
  "properties": {
    "gn:admin1_code":"4",
    "gn:asciiname":"Chak One Hundred Seventy-eight Western Bar",
    "gn:country_code":"PK",
    "gn:dem":124,
    "gn:feature_class":"P",
    "gn:feature_code":"PPL",
    "gn:name":"Chak One Hundred Seventy-eight Western Bar",
    "gn:population":0,
    "gn:timezone":"Asia/Karachi",
    "iso:country":"PK",
    "name:und_x_variant":[
        "Chak One Hundred Seventy-one"
    ],
    "wof:name":"Chak One Hundred Seventy-eight Western Bar",
    "wof:placetype":"locality"
},
  "geometry": {"coordinates":[72.11894000000002,29.97668],"type":"Point"}
}