{
  "type": "Feature",
  "properties": {
    "gn:admin1_code":"4.0",
    "gn:asciiname":"Darhrai",
    "gn:country_code":"PK",
    "gn:dem":1051,
    "gn:feature_class":"P",
    "gn:feature_code":"PPL",
    "gn:name":"Darhrai",
    "gn:population":0,
    "gn:timezone":"Asia/Karachi",
    "iso:country":"PK",
    "wof:name":"Darhrai",
    "wof:placetype":"locality"
},
  "geometry": {"coordinates":[73.52379999999999,33.77715999999999],"type":"Point"}
}