{
  "type": "Feature",
  "properties": {
    "gn:admin1_code":"7.0",
    "gn:asciiname":"Jalil Khan di Baihk",
    "gn:country_code":"PK",
    "gn:dem":4112,
    "gn:feature_class":"P",
    "gn:feature_code":"PPL",
    "gn:name":"Jalil Khan di Baihk",
    "gn:population":0,
    "gn:timezone":"Asia/Karachi",
    "iso:country":"PK",
    "wof:name":"Jalil Khan di Baihk",
    "wof:placetype":"locality"
},
  "geometry": {"coordinates":[73.72091999999998,35.89556],"type":"Point"}
}