{
  "type": "Feature",
  "properties": {
    "gn:admin1_code":"3",
    "gn:asciiname":"Hariala Nakka",
    "gn:country_code":"PK",
    "gn:dem":1203,
    "gn:feature_class":"P",
    "gn:feature_code":"PPL",
    "gn:name":"Hariala Nakka",
    "gn:population":0,
    "gn:timezone":"Asia/Karachi",
    "iso:country":"PK",
    "wof:name":"Hariala Nakka",
    "wof:placetype":"locality"
},
  "geometry": {"coordinates":[73.22546,34.30305],"type":"Point"}
}