{
  "type": "Feature",
  "properties": {
    "gn:admin1_code":"4",
    "gn:asciiname":"Basti Weyan",
    "gn:country_code":"PK",
    "gn:dem":93,
    "gn:feature_class":"P",
    "gn:feature_code":"PPL",
    "gn:name":"Basti Wey\u0101n",
    "gn:population":0,
    "gn:timezone":"Asia/Karachi",
    "iso:country":"PK",
    "wof:name":"Basti Weyan",
    "wof:placetype":"locality"
},
  "geometry": {"coordinates":[70.80694,28.97083],"type":"Point"}
}