{
  "type": "Feature",
  "properties": {
    "gn:admin1_code":"6",
    "gn:asciiname":"Komili",
    "gn:country_code":"PK",
    "gn:dem":601,
    "gn:feature_class":"P",
    "gn:feature_code":"PPL",
    "gn:name":"Komili",
    "gn:population":0,
    "gn:timezone":"Asia/Karachi",
    "iso:country":"PK",
    "wof:name":"Komili",
    "wof:placetype":"locality"
},
  "geometry": {"coordinates":[73.86320000000001,33.46274],"type":"Point"}
}