{
  "type": "Feature",
  "properties": {
    "gn:admin1_code":"4",
    "gn:asciiname":"Mumhar",
    "gn:country_code":"PK",
    "gn:dem":182,
    "gn:feature_class":"P",
    "gn:feature_code":"PPL",
    "gn:name":"Mumhar",
    "gn:population":0,
    "gn:timezone":"Asia/Karachi",
    "iso:country":"PK",
    "name:und_x_variant":[
        "Mumbhar"
    ],
    "wof:name":"Mumhar",
    "wof:placetype":"locality"
},
  "geometry": {"coordinates":[73.34495,31.04526],"type":"Point"}
}