{
  "type": "Feature",
  "properties": {
    "gn:admin1_code":"2.0",
    "gn:asciiname":"Tora Morghar Kili",
    "gn:country_code":"PK",
    "gn:dem":1910,
    "gn:feature_class":"P",
    "gn:feature_code":"PPL",
    "gn:name":"Tora Morghar Kili",
    "gn:population":0,
    "gn:timezone":"Asia/Karachi",
    "iso:country":"PK",
    "name:und_x_variant":[
        "Tor Murghe Kili",
        "Tora Morghar Kili"
    ],
    "wof:name":"Tora Morghar Kili",
    "wof:placetype":"locality"
},
  "geometry": {"coordinates":[69.69779,31.62461],"type":"Point"}
}