{
  "type": "Feature",
  "properties": {
    "gn:admin1_code":"4.0",
    "gn:asciiname":"Dhok Nawab Khan",
    "gn:country_code":"PK",
    "gn:dem":441,
    "gn:feature_class":"P",
    "gn:feature_code":"PPL",
    "gn:name":"Dhok Nawab Khan",
    "gn:population":0,
    "gn:timezone":"Asia/Karachi",
    "iso:country":"PK",
    "wof:name":"Dhok Nawab Khan",
    "wof:placetype":"locality"
},
  "geometry": {"coordinates":[72.22669999999999,33.35922],"type":"Point"}
}