{
  "type": "Feature",
  "properties": {
    "gn:admin1_code":"5",
    "gn:asciiname":"Goth Perano Dal",
    "gn:country_code":"PK",
    "gn:dem":19,
    "gn:feature_class":"P",
    "gn:feature_code":"PPL",
    "gn:name":"Goth Perano Dal",
    "gn:population":0,
    "gn:timezone":"Asia/Karachi",
    "iso:country":"PK",
    "name:und_x_variant":[
        "Pir\u0101no Dal"
    ],
    "wof:name":"Goth Perano Dal",
    "wof:placetype":"locality"
},
  "geometry": {"coordinates":[68.80953000000001,25.32298],"type":"Point"}
}