{
  "type": "Feature",
  "properties": {
    "gn:admin1_code":"4",
    "gn:asciiname":"Abdalpur",
    "gn:country_code":"PK",
    "gn:dem":209,
    "gn:feature_class":"P",
    "gn:feature_code":"PPL",
    "gn:name":"Abdalpur",
    "gn:population":0,
    "gn:timezone":"Asia/Karachi",
    "iso:country":"PK",
    "name:und_x_variant":[
        "Abbalpur"
    ],
    "wof:name":"Abdalpur",
    "wof:placetype":"locality"
},
  "geometry": {"coordinates":[73.14788,32.42016],"type":"Point"}
}