{
  "type": "Feature",
  "properties": {
    "gn:admin1_code":"5",
    "gn:asciiname":"Goth Muhammad Hasan Bugti",
    "gn:country_code":"PK",
    "gn:dem":66,
    "gn:feature_class":"P",
    "gn:feature_code":"PPL",
    "gn:name":"Goth Muhammad Hasan Bugti",
    "gn:population":0,
    "gn:timezone":"Asia/Karachi",
    "iso:country":"PK",
    "name:und_x_variant":[
        "Muhammad Hassan Bugti"
    ],
    "wof:name":"Goth Muhammad Hasan Bugti",
    "wof:placetype":"locality"
},
  "geometry": {"coordinates":[69.0177,28.37662000000001],"type":"Point"}
}