{
  "type": "Feature",
  "properties": {
    "gn:admin1_code":"4.0",
    "gn:asciiname":"Daggar Shada",
    "gn:country_code":"PK",
    "gn:dem":198,
    "gn:feature_class":"P",
    "gn:feature_code":"PPL",
    "gn:name":"Daggar Shada",
    "gn:population":0,
    "gn:timezone":"Asia/Karachi",
    "iso:country":"PK",
    "wof:name":"Daggar Shada",
    "wof:placetype":"locality"
},
  "geometry": {"coordinates":[71.34999999999999,32.63333],"type":"Point"}
}