{
  "type": "Feature",
  "properties": {
    "gn:admin1_code":"2.0",
    "gn:asciiname":"Sra Ghubarg Kili",
    "gn:country_code":"PK",
    "gn:dem":1516,
    "gn:feature_class":"P",
    "gn:feature_code":"PPL",
    "gn:name":"Sra Ghubarg Kili",
    "gn:population":0,
    "gn:timezone":"Asia/Karachi",
    "iso:country":"PK",
    "name:und_x_variant":[
        "Khwazhai Kili",
        "Khwaznai Kili",
        "Sra Ghubarg Kili"
    ],
    "wof:name":"Sra Ghubarg Kili",
    "wof:placetype":"locality"
},
  "geometry": {"coordinates":[69.14135999999999,31.11893],"type":"Point"}
}