{
  "type": "Feature",
  "properties": {
    "gn:admin1_code":"3.0",
    "gn:asciiname":"Badshah",
    "gn:country_code":"PK",
    "gn:dem":359,
    "gn:feature_class":"P",
    "gn:feature_code":"PPL",
    "gn:name":"Badshah",
    "gn:population":0,
    "gn:timezone":"Asia/Karachi",
    "iso:country":"PK",
    "name:eng_x_preferred":[
        "Badshah"
    ],
    "name:und_x_variant":[
        "P\u0101cha"
    ],
    "wof:name":"Badshah",
    "wof:placetype":"locality"
},
  "geometry": {"coordinates":[71.83377,34.2855],"type":"Point"}
}