{
  "type": "Feature",
  "properties": {
    "gn:admin1_code":"4",
    "gn:asciiname":"Chak Two Dullewala Branch",
    "gn:country_code":"PK",
    "gn:dem":206,
    "gn:feature_class":"P",
    "gn:feature_code":"PPL",
    "gn:name":"Chak Two Dullewala Branch",
    "gn:population":0,
    "gn:timezone":"Asia/Karachi",
    "iso:country":"PK",
    "name:und_x_variant":[
        "Chak Two DB"
    ],
    "wof:name":"Chak Two Dullewala Branch",
    "wof:placetype":"locality"
},
  "geometry": {"coordinates":[71.52387,32.40625],"type":"Point"}
}