{
  "type": "Feature",
  "properties": {
    "gn:admin1_code":"7.0",
    "gn:asciiname":"Kotmul",
    "gn:country_code":"PK",
    "gn:dem":2405,
    "gn:feature_class":"P",
    "gn:feature_code":"PPL",
    "gn:name":"Kotmul",
    "gn:population":0,
    "gn:timezone":"Asia/Karachi",
    "iso:country":"PK",
    "wof:name":"Kotmul",
    "wof:placetype":"locality"
},
  "geometry": {"coordinates":[75.1339,35.59403],"type":"Point"}
}