{
  "type": "Feature",
  "properties": {
    "gn:admin1_code":"4.0",
    "gn:asciiname":"Chhoi",
    "gn:country_code":"PK",
    "gn:dem":369,
    "gn:feature_class":"P",
    "gn:feature_code":"PPL",
    "gn:name":"Chhoi",
    "gn:population":0,
    "gn:timezone":"Asia/Karachi",
    "iso:country":"PK",
    "name:und_x_variant":[
        "Chnoi"
    ],
    "wof:name":"Chhoi",
    "wof:placetype":"locality"
},
  "geometry": {"coordinates":[72.21828000000002,33.72461],"type":"Point"}
}