{
  "type": "Feature",
  "properties": {
    "gn:admin1_code":"5",
    "gn:asciiname":"Goth Mehrab Burro",
    "gn:country_code":"PK",
    "gn:dem":56,
    "gn:feature_class":"P",
    "gn:feature_code":"PPL",
    "gn:name":"Goth Mehrab Burro",
    "gn:population":0,
    "gn:timezone":"Asia/Karachi",
    "iso:country":"PK",
    "name:und_x_variant":[
        "Mehr Burra"
    ],
    "wof:name":"Goth Mehrab Burro",
    "wof:placetype":"locality"
},
  "geometry": {"coordinates":[68.27246,27.85057],"type":"Point"}
}