{
  "type": "Feature",
  "properties": {
    "gn:admin1_code":"4.0",
    "gn:asciiname":"Chak One Hundred Seventy-one Eastern Bar",
    "gn:country_code":"PK",
    "gn:dem":154,
    "gn:feature_class":"P",
    "gn:feature_code":"PPL",
    "gn:name":"Chak One Hundred Seventy-one Eastern Bar",
    "gn:population":0,
    "gn:timezone":"Asia/Karachi",
    "iso:country":"PK",
    "name:und_x_variant":[
        "Janakpur Dogra",
        "Janakpur Dogar"
    ],
    "wof:name":"Chak One Hundred Seventy-one Eastern Bar",
    "wof:placetype":"locality"
},
  "geometry": {"coordinates":[72.9267,30.28258],"type":"Point"}
}