{
  "type": "Feature",
  "properties": {
    "gn:admin1_code":"3.0",
    "gn:asciiname":"Bandi Pirdad",
    "gn:country_code":"PK",
    "gn:dem":724,
    "gn:feature_class":"P",
    "gn:feature_code":"PPL",
    "gn:name":"Bandi Pirdad",
    "gn:population":0,
    "gn:timezone":"Asia/Karachi",
    "iso:country":"PK",
    "wof:name":"Bandi Pirdad",
    "wof:placetype":"locality"
},
  "geometry": {"coordinates":[73.05221,34.06073],"type":"Point"}
}