{
  "type": "Feature",
  "properties": {
    "gn:admin1_code":"4.0",
    "gn:asciiname":"Basti Qazi Abdul Rahman",
    "gn:country_code":"PK",
    "gn:dem":82,
    "gn:feature_class":"P",
    "gn:feature_code":"PPL",
    "gn:name":"Basti Qazi Abdul Rahman",
    "gn:population":0,
    "gn:timezone":"Asia/Karachi",
    "iso:country":"PK",
    "wof:name":"Basti Qazi Abdul Rahman",
    "wof:placetype":"locality"
},
  "geometry": {"coordinates":[70.42838,28.44069],"type":"Point"}
}