{
  "type": "Feature",
  "properties": {
    "gn:admin1_code":"6",
    "gn:asciiname":"Pirinnian",
    "gn:country_code":"PK",
    "gn:dem":1130,
    "gn:feature_class":"P",
    "gn:feature_code":"PPL",
    "gn:name":"Pirinnian",
    "gn:population":0,
    "gn:timezone":"Asia/Karachi",
    "iso:country":"PK",
    "name:und_x_variant":[
        "Parini\u0101n"
    ],
    "wof:name":"Pirinnian",
    "wof:placetype":"locality"
},
  "geometry": {"coordinates":[73.90459,33.64329],"type":"Point"}
}