{
  "type": "Feature",
  "properties": {
    "gn:admin1_code":"2.0",
    "gn:asciiname":"Islamabad",
    "gn:country_code":"PK",
    "gn:dem":64,
    "gn:feature_class":"P",
    "gn:feature_code":"PPL",
    "gn:name":"Islamabad",
    "gn:population":0,
    "gn:timezone":"Asia/Karachi",
    "iso:country":"PK",
    "name:und_x_variant":[
        "Naw\u0101b Sh\u0101h",
        "Nawab Shah\u012b"
    ],
    "wof:name":"Islamabad",
    "wof:placetype":"locality"
},
  "geometry": {"coordinates":[67.91835999999999,28.40291],"type":"Point"}
}