{
  "type": "Feature",
  "properties": {
    "gn:admin1_code":"5.0",
    "gn:asciiname":"Haji Ali Nawa",
    "gn:country_code":"PK",
    "gn:dem":57,
    "gn:feature_class":"P",
    "gn:feature_code":"PPL",
    "gn:name":"Haji Ali Nawa",
    "gn:population":0,
    "gn:timezone":"Asia/Karachi",
    "iso:country":"PK",
    "name:eng_x_preferred":[
        "Haji Ali Nawa"
    ],
    "wof:name":"Haji Ali Nawa",
    "wof:placetype":"locality"
},
  "geometry": {"coordinates":[68.59855,27.29764],"type":"Point"}
}