{
  "type": "Feature",
  "properties": {
    "gn:admin1_code":"3.0",
    "gn:asciiname":"Abdullah Khan",
    "gn:country_code":"PK",
    "gn:dem":318,
    "gn:feature_class":"P",
    "gn:feature_code":"PPL",
    "gn:name":"Abdullah Khan",
    "gn:population":0,
    "gn:timezone":"Asia/Karachi",
    "iso:country":"PK",
    "wof:name":"Abdullah Khan",
    "wof:placetype":"locality"
},
  "geometry": {"coordinates":[70.69844999999999,32.898],"type":"Point"}
}