{
  "type": "Feature",
  "properties": {
    "gn:admin1_code":"5.0",
    "gn:asciiname":"Dal Goth",
    "gn:country_code":"PK",
    "gn:dem":8,
    "gn:feature_class":"P",
    "gn:feature_code":"PPL",
    "gn:name":"Dal Goth",
    "gn:population":0,
    "gn:timezone":"Asia/Karachi",
    "iso:country":"PK",
    "name:eng_x_preferred":[
        "Sum\u0101r Dal"
    ],
    "wof:name":"Dal Goth",
    "wof:placetype":"locality"
},
  "geometry": {"coordinates":[68.38041,24.74085],"type":"Point"}
}