{
  "type": "Feature",
  "properties": {
    "gn:admin1_code":"2.0",
    "gn:asciiname":"Kili Rais Ghulam Muhammad",
    "gn:country_code":"PK",
    "gn:dem":1070,
    "gn:feature_class":"P",
    "gn:feature_code":"PPL",
    "gn:name":"Kili Rais Ghulam Muhammad",
    "gn:population":0,
    "gn:timezone":"Asia/Karachi",
    "iso:country":"PK",
    "name:und_x_variant":[
        "Shahr Raees Ghul\u0101m Muhammad"
    ],
    "wof:name":"Kili Rais Ghulam Muhammad",
    "wof:placetype":"locality"
},
  "geometry": {"coordinates":[66.78385,27.7106],"type":"Point"}
}