{
  "type": "Feature",
  "properties": {
    "gn:admin1_code":"5.0",
    "gn:asciiname":"Goth Baehhal Patafi",
    "gn:country_code":"PK",
    "gn:dem":40,
    "gn:feature_class":"P",
    "gn:feature_code":"PPL",
    "gn:name":"Goth Baehhal Patafi",
    "gn:population":0,
    "gn:timezone":"Asia/Karachi",
    "iso:country":"PK",
    "name:und_x_variant":[
        "Pit\u0101fi"
    ],
    "wof:name":"Goth Baehhal Patafi",
    "wof:placetype":"locality"
},
  "geometry": {"coordinates":[68.34329,26.59479],"type":"Point"}
}