{
  "type": "Feature",
  "properties": {
    "gn:admin1_code":"04",
    "gn:asciiname":"Panwan",
    "gn:country_code":"PK",
    "gn:dem":242,
    "gn:feature_class":"P",
    "gn:feature_code":"PPL",
    "gn:name":"Panwan",
    "gn:population":0,
    "gn:timezone":"Asia/Karachi",
    "iso:country":"PK",
    "name:fas_x_preferred":[
        "\u067e\u0646\u0648\u0627\u0646"
    ],
    "name:und_x_variant":[
        "Pinwan",
        "Panwan"
    ],
    "name:urd_x_preferred":[
        "\u067e\u0646\u0648\u0627\u06ba"
    ],
    "wof:name":"Panwan",
    "wof:placetype":"locality"
},
  "geometry": {"coordinates":[75.01952,32.10713],"type":"Point"}
}