{
  "type": "Feature",
  "properties": {
    "gn:admin1_code":"1.0",
    "gn:asciiname":"Lewa Ghar",
    "gn:country_code":"PK",
    "gn:dem":2068,
    "gn:feature_class":"P",
    "gn:feature_code":"PPL",
    "gn:name":"Lewa Ghar",
    "gn:population":0,
    "gn:timezone":"Asia/Karachi",
    "iso:country":"PK",
    "name:und_x_variant":[
        "Lewb Ghar",
        "Lewo Ghar",
        "Lewa Ghar"
    ],
    "wof:name":"Lewa Ghar",
    "wof:placetype":"locality"
},
  "geometry": {"coordinates":[69.57989000000001,33.02816],"type":"Point"}
}