{
  "type": "Feature",
  "properties": {
    "gn:admin1_code":"6.0",
    "gn:asciiname":"Bhangala",
    "gn:country_code":"PK",
    "gn:dem":463,
    "gn:feature_class":"P",
    "gn:feature_code":"PPL",
    "gn:name":"Bhangala",
    "gn:population":0,
    "gn:timezone":"Asia/Karachi",
    "iso:country":"PK",
    "name:fas_x_preferred":[
        "\u0628\u0646\u06af\u0627\u0644\u0627"
    ],
    "name:pan_x_preferred":[
        "\u0a2d\u0a70\u0a17\u0a3e\u0a32\u0a3e"
    ],
    "name:und_x_variant":[
        "Bhangalah",
        "Bhangala"
    ],
    "wof:name":"Bhangala",
    "wof:placetype":"locality"
},
  "geometry": {"coordinates":[73.52563000000001,33.15116],"type":"Point"}
}