{
  "type": "Feature",
  "properties": {
    "gn:admin1_code":"5",
    "gn:asciiname":"Goth Dingano Buzdar",
    "gn:country_code":"PK",
    "gn:dem":19,
    "gn:feature_class":"P",
    "gn:feature_code":"PPL",
    "gn:name":"Goth Dingano Buzdar",
    "gn:population":0,
    "gn:timezone":"Asia/Karachi",
    "iso:country":"PK",
    "name:und_x_variant":[
        "D\u0101gan jo Goth"
    ],
    "wof:name":"Goth Dingano Buzdar",
    "wof:placetype":"locality"
},
  "geometry": {"coordinates":[68.91341,25.4438],"type":"Point"}
}