{
  "type": "Feature",
  "properties": {
    "gn:admin1_code":"5",
    "gn:asciiname":"Ali Nawaz",
    "gn:country_code":"PK",
    "gn:dem":32,
    "gn:feature_class":"P",
    "gn:feature_code":"PPL",
    "gn:name":"Ali Nawaz",
    "gn:population":0,
    "gn:timezone":"Asia/Karachi",
    "iso:country":"PK",
    "wof:name":"Ali Nawaz",
    "wof:placetype":"locality"
},
  "geometry": {"coordinates":[68.58603000000001,26.25755],"type":"Point"}
}