{
  "type": "Feature",
  "properties": {
    "gn:admin1_code":"4",
    "gn:asciiname":"Darya",
    "gn:country_code":"PK",
    "gn:dem":268,
    "gn:feature_class":"P",
    "gn:feature_code":"PPL",
    "gn:name":"Darya",
    "gn:population":0,
    "gn:timezone":"Asia/Karachi",
    "iso:country":"PK",
    "wof:name":"Darya",
    "wof:placetype":"locality"
},
  "geometry": {"coordinates":[74.29167,32.725],"type":"Point"}
}