{
  "type": "Feature",
  "properties": {
    "gn:admin1_code":"04",
    "gn:asciiname":"Kot Khushhal",
    "gn:country_code":"PK",
    "gn:dem":163,
    "gn:feature_class":"P",
    "gn:feature_code":"PPL",
    "gn:name":"Kot Khushhal",
    "gn:population":0,
    "gn:timezone":"Asia/Karachi",
    "iso:country":"PK",
    "name:und_x_variant":[
        "Kot Khushal",
        "Kot Khushhal"
    ],
    "wof:name":"Kot Khushhal",
    "wof:placetype":"locality"
},
  "geometry": {"coordinates":[72.23088,31.66142],"type":"Point"}
}