{
  "type": "Feature",
  "properties": {
    "gn:admin1_code":"3.0",
    "gn:asciiname":"Gantel",
    "gn:country_code":"PK",
    "gn:dem":2085,
    "gn:feature_class":"P",
    "gn:feature_code":"PPL",
    "gn:name":"Gantel",
    "gn:population":0,
    "gn:timezone":"Asia/Karachi",
    "iso:country":"PK",
    "wof:name":"Gantel",
    "wof:placetype":"locality"
},
  "geometry": {"coordinates":[73.09695000000001,34.87805],"type":"Point"}
}