{
  "type": "Feature",
  "properties": {
    "gn:admin1_code":"4",
    "gn:asciiname":"Mellowala",
    "gn:country_code":"PK",
    "gn:dem":224,
    "gn:feature_class":"P",
    "gn:feature_code":"PPL",
    "gn:name":"Mellowala",
    "gn:population":0,
    "gn:timezone":"Asia/Karachi",
    "iso:country":"PK",
    "name:und_x_variant":[
        "Mehlaw\u0101la"
    ],
    "wof:name":"Mellowala",
    "wof:placetype":"locality"
},
  "geometry": {"coordinates":[74.22215,32.05721],"type":"Point"}
}