{
  "type": "Feature",
  "properties": {
    "gn:admin1_code":"04",
    "gn:asciiname":"Mohra Mast",
    "gn:country_code":"PK",
    "gn:dem":438,
    "gn:feature_class":"P",
    "gn:feature_code":"PPL",
    "gn:name":"Mohra Mast",
    "gn:population":0,
    "gn:timezone":"Asia/Karachi",
    "iso:country":"PK",
    "wof:name":"Mohra Mast",
    "wof:placetype":"locality"
},
  "geometry": {"coordinates":[73.07458000000003,32.89218],"type":"Point"}
}