{
  "type": "Feature",
  "properties": {
    "gn:admin1_code":"2.0",
    "gn:asciiname":"Jangal",
    "gn:country_code":"PK",
    "gn:dem":701,
    "gn:feature_class":"P",
    "gn:feature_code":"PPL",
    "gn:name":"Jangal",
    "gn:population":0,
    "gn:timezone":"Asia/Karachi",
    "iso:country":"PK",
    "name:ara_x_preferred":[
        "\u062c\u0646\u063a\u0644"
    ],
    "name:aze_x_preferred":[
        "C\u0259ng\u0259l"
    ],
    "name:ceb_x_preferred":[
        "Jangal"
    ],
    "name:fas_x_preferred":[
        "\u062c\u0646\u06af\u0644"
    ],
    "name:ita_x_preferred":[
        "Jangal"
    ],
    "name:mlg_x_preferred":[
        "Jangal"
    ],
    "name:swe_x_preferred":[
        "Jangal"
    ],
    "name:tur_x_preferred":[
        "Cengel"
    ],
    "name:und_x_variant":[
        "\u0100lam Kh\u0101n"
    ],
    "wof:name":"Jangal",
    "wof:placetype":"locality"
},
  "geometry": {"coordinates":[65.43276,28.47915],"type":"Point"}
}