{
  "type": "Feature",
  "properties": {
    "gn:admin1_code":"3.0",
    "gn:asciiname":"Karinda",
    "gn:country_code":"PK",
    "gn:dem":1249,
    "gn:feature_class":"P",
    "gn:feature_code":"PPL",
    "gn:name":"Karinda",
    "gn:population":0,
    "gn:timezone":"Asia/Karachi",
    "iso:country":"PK",
    "wof:name":"Karinda",
    "wof:placetype":"locality"
},
  "geometry": {"coordinates":[72.75108,34.71157],"type":"Point"}
}