{
  "type": "Feature",
  "properties": {
    "gn:admin1_code":"04",
    "gn:asciiname":"Thakurwala",
    "gn:country_code":"PK",
    "gn:dem":123,
    "gn:feature_class":"P",
    "gn:feature_code":"PPL",
    "gn:name":"Thakurwala",
    "gn:population":0,
    "gn:timezone":"Asia/Karachi",
    "iso:country":"PK",
    "name:und_x_variant":[
        "Thakarwala",
        "Th\u0101kurw\u0101la",
        "Thakurwala"
    ],
    "wof:name":"Thakurwala",
    "wof:placetype":"locality"
},
  "geometry": {"coordinates":[71.53272,30.04831],"type":"Point"}
}