{
  "type": "Feature",
  "properties": {
    "gn:admin1_code":"5.0",
    "gn:asciiname":"Khuda Bakhsh",
    "gn:cc2":"PK",
    "gn:country_code":"PK",
    "gn:dem":52,
    "gn:feature_class":"P",
    "gn:feature_code":"PPL",
    "gn:name":"Khuda Bakhsh",
    "gn:population":0,
    "gn:timezone":"Asia/Karachi",
    "iso:country":"PK",
    "name:und_x_variant":[
        "Khuda Bux Kubhar",
        "Khuda Bakhsh"
    ],
    "wof:name":"Khuda Bakhsh",
    "wof:placetype":"locality"
},
  "geometry": {"coordinates":[68.46666999999999,27.18333],"type":"Point"}
}