{
  "type": "Feature",
  "properties": {
    "gn:admin1_code":"2.0",
    "gn:asciiname":"Argan Chah",
    "gn:country_code":"PK",
    "gn:dem":570,
    "gn:feature_class":"P",
    "gn:feature_code":"PPL",
    "gn:name":"Argan Chah",
    "gn:population":0,
    "gn:timezone":"Asia/Karachi",
    "iso:country":"PK",
    "wof:name":"Argan Chah",
    "wof:placetype":"locality"
},
  "geometry": {"coordinates":[64.38128,27.73485],"type":"Point"}
}