{
  "type": "Feature",
  "properties": {
    "gn:admin1_code":"4.0",
    "gn:asciiname":"Aputh Bahadur",
    "gn:country_code":"PK",
    "gn:dem":163,
    "gn:feature_class":"P",
    "gn:feature_code":"PPL",
    "gn:name":"Aputh Bahadur",
    "gn:population":0,
    "gn:timezone":"Asia/Karachi",
    "iso:country":"PK",
    "name:und_x_variant":[
        "Aputh Bahadur Shah",
        "Aputh Bahadur"
    ],
    "wof:name":"Aputh Bahadur",
    "wof:placetype":"locality"
},
  "geometry": {"coordinates":[72.46666999999999,31.53333],"type":"Point"}
}