{
  "type": "Feature",
  "properties": {
    "gn:admin1_code":"5.0",
    "gn:asciiname":"Goth Nai Gud",
    "gn:country_code":"PK",
    "gn:dem":51,
    "gn:feature_class":"P",
    "gn:feature_code":"PPL",
    "gn:name":"Goth Nai Gud",
    "gn:population":0,
    "gn:timezone":"Asia/Karachi",
    "iso:country":"PK",
    "name:und_x_variant":[
        "Nero Gudd",
        "Goth Nai Gud",
        "Gud"
    ],
    "wof:name":"Goth Nai Gud",
    "wof:placetype":"locality"
},
  "geometry": {"coordinates":[68.1795,27.38131],"type":"Point"}
}