{
  "type": "Feature",
  "properties": {
    "gn:admin1_code":"4.0",
    "gn:asciiname":"Ahmad Nawaz Ahir",
    "gn:country_code":"PK",
    "gn:dem":142,
    "gn:feature_class":"P",
    "gn:feature_code":"PPL",
    "gn:name":"Ahmad Nawaz Ahir",
    "gn:population":0,
    "gn:timezone":"Asia/Karachi",
    "iso:country":"PK",
    "wof:name":"Ahmad Nawaz Ahir",
    "wof:placetype":"locality"
},
  "geometry": {"coordinates":[71.68262,30.76293],"type":"Point"}
}