{
  "type": "Feature",
  "properties": {
    "gn:admin1_code":"5.0",
    "gn:asciiname":"Sarhari",
    "gn:country_code":"PK",
    "gn:dem":32,
    "gn:feature_class":"P",
    "gn:feature_code":"PPL",
    "gn:name":"Sarhari",
    "gn:population":0,
    "gn:timezone":"Asia/Karachi",
    "iso:country":"PK",
    "name:und_x_variant":[
        "Sarh\u0101ri",
        "Sarhari"
    ],
    "name:urd_x_preferred":[
        "\u0633\u0631\u06c1\u0627\u0631\u06cc"
    ],
    "wof:name":"Sarhari",
    "wof:placetype":"neighbourhood"
},
  "geometry": {"coordinates":[68.48136,26.0981],"type":"Point"}
}