{
  "type": "Feature",
  "properties": {
    "gn:admin1_code":"03",
    "gn:asciiname":"Lahori Kalle",
    "gn:country_code":"PK",
    "gn:dem":875,
    "gn:feature_class":"P",
    "gn:feature_code":"PPL",
    "gn:name":"Lahori Kalle",
    "gn:population":0,
    "gn:timezone":"Asia/Karachi",
    "iso:country":"PK",
    "name:und_x_variant":[
        "Lahori Kili"
    ],
    "wof:name":"Lahori Kalle",
    "wof:placetype":"locality"
},
  "geometry": {"coordinates":[70.66113,33.36428],"type":"Point"}
}