{
  "type": "Feature",
  "properties": {
    "gn:admin1_code":"4.0",
    "gn:asciiname":"Hirajabad",
    "gn:country_code":"PK",
    "gn:dem":146,
    "gn:feature_class":"P",
    "gn:feature_code":"PPL",
    "gn:name":"Hir\u0101j\u0101b\u0101d",
    "gn:population":0,
    "gn:timezone":"Asia/Karachi",
    "iso:country":"PK",
    "wof:name":"Hirajabad",
    "wof:placetype":"locality"
},
  "geometry": {"coordinates":[72.31667,30.36667000000001],"type":"Point"}
}