{
  "type": "Feature",
  "properties": {
    "gn:admin1_code":"3.0",
    "gn:asciiname":"Zimun Ghari",
    "gn:country_code":"PK",
    "gn:dem":3486,
    "gn:feature_class":"P",
    "gn:feature_code":"PPL",
    "gn:name":"Zimun Ghari",
    "gn:population":0,
    "gn:timezone":"Asia/Karachi",
    "iso:country":"PK",
    "wof:name":"Zimun Ghari",
    "wof:placetype":"locality"
},
  "geometry": {"coordinates":[71.38533000000002,36.08021],"type":"Point"}
}