{
  "type": "Feature",
  "properties": {
    "gn:admin1_code":"4.0",
    "gn:asciiname":"Saiyed Muhammad Shah Bukhari",
    "gn:country_code":"PK",
    "gn:dem":136,
    "gn:feature_class":"P",
    "gn:feature_code":"PPL",
    "gn:name":"Saiyed Muhammad Shah Bukhari",
    "gn:population":0,
    "gn:timezone":"Asia/Karachi",
    "iso:country":"PK",
    "wof:name":"Saiyed Muhammad Shah Bukhari",
    "wof:placetype":"locality"
},
  "geometry": {"coordinates":[71.90416999999999,30.44213],"type":"Point"}
}