{
  "type": "Feature",
  "properties": {
    "gn:admin1_code":"4",
    "gn:asciiname":"Matikiwala",
    "gn:country_code":"PK",
    "gn:dem":118,
    "gn:feature_class":"P",
    "gn:feature_code":"PPL",
    "gn:name":"Matikiwala",
    "gn:population":0,
    "gn:timezone":"Asia/Karachi",
    "iso:country":"PK",
    "name:und_x_variant":[
        "Maitlew\u0101la"
    ],
    "wof:name":"Matikiwala",
    "wof:placetype":"locality"
},
  "geometry": {"coordinates":[70.66821,30.09219],"type":"Point"}
}