{
  "type": "Feature",
  "properties": {
    "gn:admin1_code":"4.0",
    "gn:asciiname":"Chak Seventeen North Branch",
    "gn:country_code":"PK",
    "gn:dem":194,
    "gn:feature_class":"P",
    "gn:feature_code":"PPL",
    "gn:name":"Chak Seventeen North Branch",
    "gn:population":0,
    "gn:timezone":"Asia/Karachi",
    "iso:country":"PK",
    "name:und_x_variant":[
        "Chak Jhaw\u0101ri\u0101n",
        "Chak 17 NB",
        "Chak Seventeen NB",
        "Chak Seventeen North Branch",
        "Jowarian"
    ],
    "wof:name":"Chak Seventeen North Branch",
    "wof:placetype":"locality"
},
  "geometry": {"coordinates":[72.79513,32.27749],"type":"Point"}
}