{
  "type": "Feature",
  "properties": {
    "gn:admin1_code":"4.0",
    "gn:asciiname":"Akhori",
    "gn:country_code":"PK",
    "gn:dem":367,
    "gn:feature_class":"P",
    "gn:feature_code":"PPL",
    "gn:name":"Akhori",
    "gn:population":0,
    "gn:timezone":"Asia/Karachi",
    "iso:country":"PK",
    "name:fas_x_preferred":[
        "\u0627\u06a9\u0647\u0648\u0631\u06cc"
    ],
    "name:urd_x_preferred":[
        "\u0627\u06a9\u06be\u0648\u0631\u06cc"
    ],
    "wof:name":"Akhori",
    "wof:placetype":"locality"
},
  "geometry": {"coordinates":[72.45334,33.6928],"type":"Point"}
}