{
  "type": "Feature",
  "properties": {
    "gn:admin1_code":"3",
    "gn:asciiname":"Kashkar Banda",
    "gn:country_code":"PK",
    "gn:dem":1511,
    "gn:feature_class":"P",
    "gn:feature_code":"PPL",
    "gn:name":"Kashkar Banda",
    "gn:population":0,
    "gn:timezone":"Asia/Karachi",
    "iso:country":"PK",
    "wof:name":"Kashkar Banda",
    "wof:placetype":"locality"
},
  "geometry": {"coordinates":[72.20132,34.87029],"type":"Point"}
}