{
  "type": "Feature",
  "properties": {
    "gn:admin1_code":"4",
    "gn:asciiname":"Tibbi Maiwali",
    "gn:country_code":"PK",
    "gn:dem":120,
    "gn:feature_class":"P",
    "gn:feature_code":"PPL",
    "gn:name":"Tibbi Maiwali",
    "gn:population":0,
    "gn:timezone":"Asia/Karachi",
    "iso:country":"PK",
    "name:eng_x_preferred":[
        "Tibbi Mahiw\u0101li"
    ],
    "wof:name":"Tibbi Maiwali",
    "wof:placetype":"locality"
},
  "geometry": {"coordinates":[71.79125999999999,29.42695],"type":"Point"}
}