{
  "type": "Feature",
  "properties": {
    "gn:admin1_code":"01",
    "gn:asciiname":"Nazar Mena",
    "gn:country_code":"PK",
    "gn:dem":1030,
    "gn:feature_class":"P",
    "gn:feature_code":"PPL",
    "gn:name":"Nazar Mena",
    "gn:population":0,
    "gn:timezone":"Asia/Karachi",
    "iso:country":"PK",
    "name:eng_x_preferred":[
        "Nazar Mena"
    ],
    "name:und_x_variant":[
        "Nazar Maina"
    ],
    "wof:name":"Nazar Mena",
    "wof:placetype":"locality"
},
  "geometry": {"coordinates":[71.61544000000001,34.67318],"type":"Point"}
}