{
  "type": "Feature",
  "properties": {
    "gn:admin1_code":"2.0",
    "gn:asciiname":"Spin Tangai Kili",
    "gn:country_code":"PK",
    "gn:dem":1451,
    "gn:feature_class":"P",
    "gn:feature_code":"PPL",
    "gn:name":"Spin Tangai Kili",
    "gn:population":0,
    "gn:timezone":"Asia/Karachi",
    "iso:country":"PK",
    "wof:name":"Spin Tangai Kili",
    "wof:placetype":"locality"
},
  "geometry": {"coordinates":[69.45724,31.56824000000001],"type":"Point"}
}