{
  "type": "Feature",
  "properties": {
    "gn:admin1_code":"6",
    "gn:asciiname":"Dhani Bar",
    "gn:country_code":"PK",
    "gn:dem":855,
    "gn:feature_class":"P",
    "gn:feature_code":"PPL",
    "gn:name":"Dhani Bar",
    "gn:population":0,
    "gn:timezone":"Asia/Karachi",
    "iso:country":"PK",
    "name:und_x_variant":[
        "Dhanni"
    ],
    "wof:name":"Dhani Bar",
    "wof:placetype":"locality"
},
  "geometry": {"coordinates":[73.47784,34.40637],"type":"Point"}
}