{
  "type": "Feature",
  "properties": {
    "gn:admin1_code":"4",
    "gn:asciiname":"Basti Kulalan",
    "gn:country_code":"PK",
    "gn:dem":94,
    "gn:feature_class":"P",
    "gn:feature_code":"PPL",
    "gn:name":"Basti Kulalan",
    "gn:population":0,
    "gn:timezone":"Asia/Karachi",
    "iso:country":"PK",
    "name:und_x_variant":[
        "Kal\u0101l"
    ],
    "wof:name":"Basti Kulalan",
    "wof:placetype":"locality"
},
  "geometry": {"coordinates":[70.92945,28.92996],"type":"Point"}
}