{
  "type": "Feature",
  "properties": {
    "gn:admin1_code":"2.0",
    "gn:asciiname":"Wumad Kili",
    "gn:country_code":"PK",
    "gn:dem":2526,
    "gn:feature_class":"P",
    "gn:feature_code":"PPL",
    "gn:name":"Wumad Kili",
    "gn:population":0,
    "gn:timezone":"Asia/Karachi",
    "iso:country":"PK",
    "wof:name":"Wumad Kili",
    "wof:placetype":"locality"
},
  "geometry": {"coordinates":[67.64341999999999,30.63186],"type":"Point"}
}