{
  "type": "Feature",
  "properties": {
    "gn:admin1_code":"2.0",
    "gn:asciiname":"Ghaibizai",
    "gn:country_code":"PK",
    "gn:dem":1592,
    "gn:feature_class":"P",
    "gn:feature_code":"PPL",
    "gn:name":"Ghaibizai",
    "gn:population":0,
    "gn:timezone":"Asia/Karachi",
    "iso:country":"PK",
    "wof:name":"Ghaibizai",
    "wof:placetype":"locality"
},
  "geometry": {"coordinates":[66.77701999999999,30.17893],"type":"Point"}
}