{
  "type": "Feature",
  "properties": {
    "gn:admin1_code":"2",
    "gn:asciiname":"Ali Bakhsh",
    "gn:country_code":"PK",
    "gn:dem":1183,
    "gn:feature_class":"P",
    "gn:feature_code":"PPL",
    "gn:name":"Ali Bakhsh",
    "gn:population":0,
    "gn:timezone":"Asia/Karachi",
    "iso:country":"PK",
    "wof:name":"Ali Bakhsh",
    "wof:placetype":"locality"
},
  "geometry": {"coordinates":[69.28509,29.93285],"type":"Point"}
}