{
  "type": "Feature",
  "properties": {
    "gn:admin1_code":"3",
    "gn:asciiname":"Kuz Nar",
    "gn:country_code":"PK",
    "gn:dem":2883,
    "gn:feature_class":"P",
    "gn:feature_code":"PPL",
    "gn:name":"Kuz Nar",
    "gn:population":0,
    "gn:timezone":"Asia/Karachi",
    "iso:country":"PK",
    "wof:name":"Kuz Nar",
    "wof:placetype":"locality"
},
  "geometry": {"coordinates":[73.27078,34.86976],"type":"Point"}
}