{
  "type": "Feature",
  "properties": {
    "gn:admin1_code":"5",
    "gn:asciiname":"Goth Saidpur",
    "gn:country_code":"PK",
    "gn:dem":60,
    "gn:feature_class":"P",
    "gn:feature_code":"PPL",
    "gn:name":"Goth Saidpur",
    "gn:population":0,
    "gn:timezone":"Asia/Karachi",
    "iso:country":"PK",
    "name:und_x_variant":[
        "Saidpur"
    ],
    "wof:name":"Goth Saidpur",
    "wof:placetype":"locality"
},
  "geometry": {"coordinates":[68.54352,27.58349],"type":"Point"}
}