{
  "type": "Feature",
  "properties": {
    "gn:admin1_code":"2.0",
    "gn:asciiname":"Shakra",
    "gn:country_code":"PK",
    "gn:dem":902,
    "gn:feature_class":"P",
    "gn:feature_code":"PPL",
    "gn:name":"Shakra",
    "gn:population":0,
    "gn:timezone":"Asia/Karachi",
    "iso:country":"PK",
    "name:deu_x_preferred":[
        "Shakra"
    ],
    "name:fra_x_preferred":[
        "Shakra"
    ],
    "name:ita_x_preferred":[
        "Shakra"
    ],
    "name:pol_x_preferred":[
        "Shakra"
    ],
    "name:swe_x_preferred":[
        "Shakra"
    ],
    "wof:name":"Shakra",
    "wof:placetype":"locality"
},
  "geometry": {"coordinates":[65.74905,29.47176],"type":"Point"}
}