{
  "type": "Feature",
  "properties": {
    "gn:admin1_code":"4.0",
    "gn:asciiname":"Pir Phai",
    "gn:country_code":"PK",
    "gn:dem":237,
    "gn:feature_class":"P",
    "gn:feature_code":"PPL",
    "gn:name":"Pir Phai",
    "gn:population":0,
    "gn:timezone":"Asia/Karachi",
    "iso:country":"PK",
    "wof:name":"Pir Phai",
    "wof:placetype":"locality"
},
  "geometry": {"coordinates":[71.70214,33.01247],"type":"Point"}
}