{
  "type": "Feature",
  "properties": {
    "gn:admin1_code":"4.0",
    "gn:asciiname":"Chak One Hundred Eighty-one Eastern Bar",
    "gn:country_code":"PK",
    "gn:dem":153,
    "gn:feature_class":"P",
    "gn:feature_code":"PPL",
    "gn:name":"Chak One Hundred Eighty-one Eastern Bar",
    "gn:population":0,
    "gn:timezone":"Asia/Karachi",
    "iso:country":"PK",
    "name:und_x_variant":[
        "Fyz\u0101b\u0101d",
        "Faiz\u0101b\u0101d",
        "Chak One Hundred Eighty-one Eastern Bar"
    ],
    "wof:name":"Chak One Hundred Eighty-one Eastern Bar",
    "wof:placetype":"locality"
},
  "geometry": {"coordinates":[72.86043000000002,30.26283],"type":"Point"}
}