{
  "type": "Feature",
  "properties": {
    "gn:admin1_code":"03",
    "gn:asciiname":"Sarobi",
    "gn:country_code":"PK",
    "gn:dem":881,
    "gn:feature_class":"P",
    "gn:feature_code":"PPL",
    "gn:name":"Sarobi",
    "gn:population":0,
    "gn:timezone":"Asia/Karachi",
    "iso:country":"PK",
    "name:und_x_variant":[
        "Saroba"
    ],
    "wof:name":"Sarobi",
    "wof:placetype":"locality"
},
  "geometry": {"coordinates":[71.35825,33.09635],"type":"Point"}
}