{
  "type": "Feature",
  "properties": {
    "gn:admin1_code":"5.0",
    "gn:asciiname":"Bakhtiar Burerra",
    "gn:country_code":"PK",
    "gn:dem":46,
    "gn:feature_class":"P",
    "gn:feature_code":"PPL",
    "gn:name":"Bakhtiar Burerra",
    "gn:population":0,
    "gn:timezone":"Asia/Karachi",
    "iso:country":"PK",
    "name:und_x_variant":[
        "Bakhti\u0101r Burerra"
    ],
    "wof:name":"Bakhtiar Burerra",
    "wof:placetype":"locality"
},
  "geometry": {"coordinates":[67.78022,27.58007000000001],"type":"Point"}
}