{
  "type": "Feature",
  "properties": {
    "gn:admin1_code":"4.0",
    "gn:asciiname":"Kamonke Khurd",
    "gn:country_code":"PK",
    "gn:dem":217,
    "gn:feature_class":"P",
    "gn:feature_code":"PPL",
    "gn:name":"Kamonke Khurd",
    "gn:population":0,
    "gn:timezone":"Asia/Karachi",
    "iso:country":"PK",
    "name:und_x_variant":[
        "Kamoke",
        "Kamonke Khurd",
        "K\u0101moki"
    ],
    "wof:name":"Kamonke Khurd",
    "wof:placetype":"locality"
},
  "geometry": {"coordinates":[73.84478,32.41415],"type":"Point"}
}