{
  "type": "Feature",
  "properties": {
    "gn:admin1_code":"03",
    "gn:asciiname":"Kot Azam",
    "gn:country_code":"PK",
    "gn:dem":285,
    "gn:feature_class":"P",
    "gn:feature_code":"PPL",
    "gn:name":"Kot Azam",
    "gn:population":0,
    "gn:timezone":"Asia/Karachi",
    "iso:country":"PK",
    "wof:name":"Kot Azam",
    "wof:placetype":"locality"
},
  "geometry": {"coordinates":[70.20021,32.08854],"type":"Point"}
}