{
  "type": "Feature",
  "properties": {
    "gn:admin1_code":"04",
    "gn:asciiname":"Mamdana",
    "gn:country_code":"PK",
    "gn:dem":206,
    "gn:feature_class":"P",
    "gn:feature_code":"PPL",
    "gn:name":"Mamdana",
    "gn:population":0,
    "gn:timezone":"Asia/Karachi",
    "iso:country":"PK",
    "name:und_x_variant":[
        "Mamdarna",
        "Mamduna",
        "Mamdana"
    ],
    "wof:name":"Mamdana",
    "wof:placetype":"locality"
},
  "geometry": {"coordinates":[73.24464999999999,32.30685],"type":"Point"}
}