{
  "type": "Feature",
  "properties": {
    "gn:admin1_code":"2.0",
    "gn:asciiname":"Pirdan",
    "gn:country_code":"PK",
    "gn:dem":815,
    "gn:feature_class":"P",
    "gn:feature_code":"PPL",
    "gn:name":"Pirdan",
    "gn:population":0,
    "gn:timezone":"Asia/Karachi",
    "iso:country":"PK",
    "wof:name":"Pirdan",
    "wof:placetype":"locality"
},
  "geometry": {"coordinates":[62.8871,26.47185],"type":"Point"}
}