{
  "type": "Feature",
  "properties": {
    "gn:admin1_code":"5",
    "gn:asciiname":"Dato Khaskhali",
    "gn:country_code":"PK",
    "gn:dem":27,
    "gn:feature_class":"P",
    "gn:feature_code":"PPL",
    "gn:name":"Dato Khaskhali",
    "gn:population":0,
    "gn:timezone":"Asia/Karachi",
    "iso:country":"PK",
    "name:und_x_variant":[
        "D\u0101to Kh\u0101skheli"
    ],
    "wof:name":"Dato Khaskhali",
    "wof:placetype":"locality"
},
  "geometry": {"coordinates":[68.57254,26.07207],"type":"Point"}
}