{
  "type": "Feature",
  "properties": {
    "gn:admin1_code":"03",
    "gn:asciiname":"Qasima",
    "gn:country_code":"PK",
    "gn:dem":800,
    "gn:feature_class":"P",
    "gn:feature_code":"PPL",
    "gn:name":"Qasima",
    "gn:population":0,
    "gn:timezone":"Asia/Karachi",
    "iso:country":"PK",
    "name:und_x_variant":[
        "Qasama",
        "Qasima"
    ],
    "wof:name":"Qasima",
    "wof:placetype":"locality"
},
  "geometry": {"coordinates":[72.78614,34.57186],"type":"Point"}
}