{
  "type": "Feature",
  "properties": {
    "gn:admin1_code":"3",
    "gn:asciiname":"Shai",
    "gn:country_code":"PK",
    "gn:dem":1965,
    "gn:feature_class":"P",
    "gn:feature_code":"PPL",
    "gn:name":"Shai",
    "gn:population":0,
    "gn:timezone":"Asia/Karachi",
    "iso:country":"PK",
    "wof:name":"Shai",
    "wof:placetype":"locality"
},
  "geometry": {"coordinates":[72.72189,34.5691],"type":"Point"}
}