{
  "type": "Feature",
  "properties": {
    "gn:admin1_code":"3",
    "gn:asciiname":"Shai",
    "gn:country_code":"PK",
    "gn:dem":1965,
    "gn:feature_class":"P",
    "gn:feature_code":"PPL",
    "gn:name":"Shai",
    "gn:population":0,
    "gn:timezone":"Asia/Karachi",
    "iso:country":"PK",
    "name:cat_x_preferred":[
        "Shait"
    ],
    "name:deu_x_preferred":[
        "Schai"
    ],
    "name:fas_x_preferred":[
        "\u0634\u0627\u06cc"
    ],
    "name:fin_x_preferred":[
        "Shay"
    ],
    "name:fra_x_preferred":[
        "Chai"
    ],
    "name:hun_x_preferred":[
        "Sai"
    ],
    "name:ind_x_preferred":[
        "Shai"
    ],
    "name:ita_x_preferred":[
        "Shai"
    ],
    "name:jpn_x_preferred":[
        "\u30b7\u30e3\u30a4"
    ],
    "name:lit_x_preferred":[
        "\u0160ai"
    ],
    "name:msa_x_preferred":[
        "Dewi Shai"
    ],
    "name:por_x_preferred":[
        "Shai"
    ],
    "name:rus_x_preferred":[
        "\u0428\u0430\u0438"
    ],
    "name:slv_x_preferred":[
        "\u0160ai"
    ],
    "name:swe_x_preferred":[
        "Shai"
    ],
    "name:ukr_x_preferred":[
        "\u0428\u0430\u0456"
    ],
    "wof:name":"Shai",
    "wof:placetype":"locality"
},
  "geometry": {"coordinates":[72.72189,34.5691],"type":"Point"}
}