{
  "type": "Feature",
  "properties": {
    "gn:admin1_code":"3.0",
    "gn:asciiname":"Bakht Amin",
    "gn:country_code":"PK",
    "gn:dem":860,
    "gn:feature_class":"P",
    "gn:feature_code":"PPL",
    "gn:name":"Bakht Amin",
    "gn:population":0,
    "gn:timezone":"Asia/Karachi",
    "iso:country":"PK",
    "wof:name":"Bakht Amin",
    "wof:placetype":"locality"
},
  "geometry": {"coordinates":[72.27370000000001,34.71429000000001],"type":"Point"}
}