{
  "type": "Feature",
  "properties": {
    "gn:admin1_code":"1.0",
    "gn:asciiname":"Gezdai Kachkai",
    "gn:country_code":"PK",
    "gn:dem":1347,
    "gn:feature_class":"P",
    "gn:feature_code":"PPL",
    "gn:name":"Gezdai Kachkai",
    "gn:population":0,
    "gn:timezone":"Asia/Karachi",
    "iso:country":"PK",
    "wof:name":"Gezdai Kachkai",
    "wof:placetype":"locality"
},
  "geometry": {"coordinates":[70.32468,32.64573],"type":"Point"}
}