{
  "type": "Feature",
  "properties": {
    "gn:admin1_code":"3.0",
    "gn:asciiname":"Gayal",
    "gn:country_code":"PK",
    "gn:dem":1673,
    "gn:feature_class":"P",
    "gn:feature_code":"PPL",
    "gn:name":"Gayal",
    "gn:population":0,
    "gn:timezone":"Asia/Karachi",
    "iso:country":"PK",
    "wof:name":"Gayal",
    "wof:placetype":"locality"
},
  "geometry": {"coordinates":[73.16763,35.40936],"type":"Point"}
}