{
  "type": "Feature",
  "properties": {
    "gn:admin1_code":"3.0",
    "gn:asciiname":"Gayal",
    "gn:country_code":"PK",
    "gn:dem":1673,
    "gn:feature_class":"P",
    "gn:feature_code":"PPL",
    "gn:name":"Gayal",
    "gn:population":0,
    "gn:timezone":"Asia/Karachi",
    "iso:country":"PK",
    "name:ara_x_preferred":[
        "\u063a\u0627\u064a\u0627\u0644"
    ],
    "name:ava_x_preferred":[
        "\u0413\u0430\u0443\u0440"
    ],
    "name:ben_x_preferred":[
        "\u0997\u09af\u09bc\u09be\u09b2"
    ],
    "name:bre_x_preferred":[
        "Gayal"
    ],
    "name:cat_x_preferred":[
        "Gaial"
    ],
    "name:ceb_x_preferred":[
        "Bos frontalis"
    ],
    "name:ces_x_preferred":[
        "Gayal"
    ],
    "name:dan_x_preferred":[
        "Gayal"
    ],
    "name:epo_x_preferred":[
        "Gajalo"
    ],
    "name:eus_x_preferred":[
        "Bos frontalis"
    ],
    "name:fas_x_preferred":[
        "\u06af\u06cc\u0627\u0644"
    ],
    "name:gle_x_preferred":[
        "Gadh\u00e1l"
    ],
    "name:heb_x_preferred":[
        "\u05d2\u05d0\u05d9\u05d0\u05dc"
    ],
    "name:hin_x_preferred":[
        "\u092e\u093f\u0925\u0941\u0928"
    ],
    "name:ina_x_preferred":[
        "Gayal"
    ],
    "name:ind_x_preferred":[
        "Gayal"
    ],
    "name:kab_x_preferred":[
        "Agayal"
    ],
    "name:kan_x_preferred":[
        "\u0c97\u0cc7\u0caf\u0cb2\u0ccd"
    ],
    "name:mal_x_preferred":[
        "\u0d2e\u0d3f\u0d25\u0d41\u0d7b"
    ],
    "name:mya_x_preferred":[
        "\u1014\u103d\u102c\u1038\u1014\u1031\u102c\u1000\u103a"
    ],
    "name:pnb_x_preferred":[
        "\u06af\u06cc\u0627\u0644"
    ],
    "name:pol_x_preferred":[
        "Gajal udomowiony"
    ],
    "name:por_x_preferred":[
        "Bos frontalis"
    ],
    "name:spa_x_preferred":[
        "Bos frontalis"
    ],
    "name:tam_x_preferred":[
        "\u0b95\u0baf\u0bbe\u0bb2\u0bcd"
    ],
    "name:udm_x_preferred":[
        "\u0413\u0430\u0443\u0440"
    ],
    "name:ukr_x_preferred":[
        "\u0413\u0430\u044f\u043b"
    ],
    "name:war_x_preferred":[
        "Bos frontalis"
    ],
    "wof:name":"Gayal",
    "wof:placetype":"locality"
},
  "geometry": {"coordinates":[73.16763,35.40936],"type":"Point"}
}