{
  "type": "Feature",
  "properties": {
    "gn:admin1_code":"4.0",
    "gn:asciiname":"Chak Five Hundred Thirteen",
    "gn:country_code":"PK",
    "gn:dem":162,
    "gn:feature_class":"P",
    "gn:feature_code":"PPL",
    "gn:name":"Chak Five Hundred Thirteen",
    "gn:population":0,
    "gn:timezone":"Asia/Karachi",
    "iso:country":"PK",
    "name:und_x_variant":[
        "Jhok Chanwar",
        "Chak Five Hundred Thirteen GB",
        "Jhok Channar",
        "Jhamtanw\u0101la",
        "Chak Five Hundred Thirteen",
        "Jomt\u0101nwala"
    ],
    "wof:name":"Chak Five Hundred Thirteen",
    "wof:placetype":"locality"
},
  "geometry": {"coordinates":[72.71817,30.79304],"type":"Point"}
}