{
  "type": "Feature",
  "properties": {
    "gn:admin1_code":"2.0",
    "gn:asciiname":"Jafri",
    "gn:cc2":"PK",
    "gn:country_code":"PK",
    "gn:dem":8,
    "gn:feature_class":"P",
    "gn:feature_code":"PPL",
    "gn:name":"Jafri",
    "gn:population":0,
    "gn:timezone":"Asia/Karachi",
    "iso:country":"PK",
    "name:und_x_variant":[
        "Ja\u2019afari",
        "J\u0101fari",
        "Jafri"
    ],
    "wof:name":"Jafri",
    "wof:placetype":"locality"
},
  "geometry": {"coordinates":[64.31999999999999,25.43972],"type":"Point"}
}