{
  "type": "Feature",
  "properties": {
    "gn:admin1_code":"5.0",
    "gn:asciiname":"Husain Magsi",
    "gn:country_code":"PK",
    "gn:dem":32,
    "gn:feature_class":"P",
    "gn:feature_code":"PPL",
    "gn:name":"Husain Magsi",
    "gn:population":0,
    "gn:timezone":"Asia/Karachi",
    "iso:country":"PK",
    "wof:name":"Husain Magsi",
    "wof:placetype":"neighbourhood"
},
  "geometry": {"coordinates":[68.38193,26.24019],"type":"Point"}
}