{
  "type": "Feature",
  "properties": {
    "gn:admin1_code":"4.0",
    "gn:asciiname":"Dadu",
    "gn:country_code":"PK",
    "gn:dem":1130,
    "gn:feature_class":"P",
    "gn:feature_code":"PPL",
    "gn:name":"Dadu",
    "gn:population":0,
    "gn:timezone":"Asia/Karachi",
    "iso:country":"PK",
    "name:ceb_x_preferred":[
        "Dadu"
    ],
    "name:ces_x_preferred":[
        "Ta-tu"
    ],
    "name:deu_x_preferred":[
        "Dadu"
    ],
    "name:fra_x_preferred":[
        "Dadu"
    ],
    "name:ind_x_preferred":[
        "Dadu"
    ],
    "name:nld_x_preferred":[
        "Dadu"
    ],
    "name:nor_x_preferred":[
        "Dadu"
    ],
    "name:scn_x_preferred":[
        "Dadu"
    ],
    "name:swe_x_preferred":[
        "Dadu"
    ],
    "wof:name":"Dadu",
    "wof:placetype":"locality"
},
  "geometry": {"coordinates":[70.1875,30.35702],"type":"Point"}
}