{
  "type": "Feature",
  "properties": {
    "gn:admin1_code":"5",
    "gn:asciiname":"Rahim Khan Jamali",
    "gn:country_code":"PK",
    "gn:dem":52,
    "gn:feature_class":"P",
    "gn:feature_code":"PPL",
    "gn:name":"Rahim Khan Jamali",
    "gn:population":0,
    "gn:timezone":"Asia/Karachi",
    "iso:country":"PK",
    "name:und_x_variant":[
        "Reh\u0101n Kh\u0101n Jam\u0101li"
    ],
    "wof:name":"Rahim Khan Jamali",
    "wof:placetype":"locality"
},
  "geometry": {"coordinates":[68.10136999999999,28.09961],"type":"Point"}
}