{
  "type": "Feature",
  "properties": {
    "gn:admin1_code":"4",
    "gn:asciiname":"Chak Three Hundred Twenty-one Eastern Bar",
    "gn:country_code":"PK",
    "gn:dem":146,
    "gn:feature_class":"P",
    "gn:feature_code":"PPL",
    "gn:name":"Chak Three Hundred Twenty-one Eastern Bar",
    "gn:population":0,
    "gn:timezone":"Asia/Karachi",
    "iso:country":"PK",
    "name:und_x_variant":[
        "Chak Three Hundred Twenty-one EB"
    ],
    "wof:name":"Chak Three Hundred Twenty-one Eastern Bar",
    "wof:placetype":"locality"
},
  "geometry": {"coordinates":[72.74054,30.07448],"type":"Point"}
}