{
  "type": "Feature",
  "properties": {
    "gn:admin1_code":"4.0",
    "gn:asciiname":"Chak Three Hundred Seventy-Seven Jhang Branch",
    "gn:country_code":"PK",
    "gn:dem":162,
    "gn:feature_class":"P",
    "gn:feature_code":"PPL",
    "gn:name":"Chak Three Hundred Seventy-Seven Jhang Branch",
    "gn:population":0,
    "gn:timezone":"Asia/Karachi",
    "iso:country":"PK",
    "name:und_x_variant":[
        "Jh\u0101w\u0101n",
        "Jh\u0101nw\u0101n",
        "Chak Number Three Hundred Seventy-Seven",
        "Chak Three Hundred Seventy-Seven Jhang Branch"
    ],
    "wof:name":"Chak Three Hundred Seventy-Seven Jhang Branch",
    "wof:placetype":"locality"
},
  "geometry": {"coordinates":[72.52055,31.07834],"type":"Point"}
}