{
  "type": "Feature",
  "properties": {
    "gn:admin1_code":"2.0",
    "gn:asciiname":"Kili Amir Muhammad Azam",
    "gn:country_code":"PK",
    "gn:dem":1054,
    "gn:feature_class":"P",
    "gn:feature_code":"PPL",
    "gn:name":"Kili Amir Muhammad Azam",
    "gn:population":0,
    "gn:timezone":"Asia/Karachi",
    "iso:country":"PK",
    "name:und_x_variant":[
        "Kili Mir Muhammad Azam"
    ],
    "wof:name":"Kili Amir Muhammad Azam",
    "wof:placetype":"locality"
},
  "geometry": {"coordinates":[65.29229000000001,28.82926],"type":"Point"}
}