{
  "type": "Feature",
  "properties": {
    "gn:admin1_code":"3.0",
    "gn:asciiname":"Baringin",
    "gn:country_code":"PK",
    "gn:dem":413,
    "gn:feature_class":"P",
    "gn:feature_code":"PPL",
    "gn:name":"Baringin",
    "gn:population":0,
    "gn:timezone":"Asia/Karachi",
    "iso:country":"PK",
    "name:eng_x_preferred":[
        "Saringin"
    ],
    "name:und_x_variant":[
        "Bar\u012bnganr",
        "Bar\u012bnagar",
        "Barnigun",
        "Baringin"
    ],
    "wof:name":"Baringin",
    "wof:placetype":"locality"
},
  "geometry": {"coordinates":[72.29644999999999,34.3799],"type":"Point"}
}