{
  "type": "Feature",
  "properties": {
    "gn:admin1_code":"5",
    "gn:asciiname":"Goth Murad",
    "gn:country_code":"PK",
    "gn:dem":74,
    "gn:feature_class":"P",
    "gn:feature_code":"PPL",
    "gn:name":"Goth Murad",
    "gn:population":0,
    "gn:timezone":"Asia/Karachi",
    "iso:country":"PK",
    "name:und_x_variant":[
        "Goth Mur\u0101d Kh\u0101n"
    ],
    "wof:name":"Goth Murad",
    "wof:placetype":"locality"
},
  "geometry": {"coordinates":[69.43250999999999,27.23394],"type":"Point"}
}