{
  "type": "Feature",
  "properties": {
    "gn:admin1_code":"4.0",
    "gn:asciiname":"Chak Forty-one -Gogera Distributary",
    "gn:country_code":"PK",
    "gn:dem":178,
    "gn:feature_class":"P",
    "gn:feature_code":"PPL",
    "gn:name":"Chak Forty-one -Gogera Distributary",
    "gn:population":0,
    "gn:timezone":"Asia/Karachi",
    "iso:country":"PK",
    "name:und_x_variant":[
        "Kukr\u0101nw\u0101la"
    ],
    "wof:name":"Chak Forty-one -Gogera Distributary",
    "wof:placetype":"locality"
},
  "geometry": {"coordinates":[73.33328,30.88985],"type":"Point"}
}