{
  "type": "Feature",
  "properties": {
    "gn:admin1_code":"3",
    "gn:asciiname":"Mari Maqarrap Shah",
    "gn:country_code":"PK",
    "gn:dem":875,
    "gn:feature_class":"P",
    "gn:feature_code":"PPL",
    "gn:name":"Mari Maqarrap Shah",
    "gn:population":0,
    "gn:timezone":"Asia/Karachi",
    "iso:country":"PK",
    "name:und_x_variant":[
        "M\u0101ri Muqarrab Sh\u0101h"
    ],
    "wof:name":"Mari Maqarrap Shah",
    "wof:placetype":"locality"
},
  "geometry": {"coordinates":[73.15185,34.38468],"type":"Point"}
}