{
  "type": "Feature",
  "properties": {
    "gn:admin1_code":"7.0",
    "gn:asciiname":"Ghar Buchang",
    "gn:country_code":"PK",
    "gn:dem":2864,
    "gn:feature_class":"P",
    "gn:feature_code":"PPL",
    "gn:name":"Ghar Buchang",
    "gn:population":0,
    "gn:timezone":"Asia/Karachi",
    "iso:country":"PK",
    "wof:name":"Ghar Buchang",
    "wof:placetype":"locality"
},
  "geometry": {"coordinates":[76.32593,35.14783],"type":"Point"}
}