{
  "type": "Feature",
  "properties": {
    "gn:admin1_code":"05",
    "gn:asciiname":"Goth Alano Souda",
    "gn:country_code":"PK",
    "gn:dem":4,
    "gn:feature_class":"P",
    "gn:feature_code":"PPL",
    "gn:name":"Goth Alano Souda",
    "gn:population":0,
    "gn:timezone":"Asia/Karachi",
    "iso:country":"PK",
    "name:und_x_variant":[
        "Goth Al\u0101na Soda"
    ],
    "wof:name":"Goth Alano Souda",
    "wof:placetype":"locality"
},
  "geometry": {"coordinates":[67.74336,24.37792],"type":"Point"}
}