{
  "type": "Feature",
  "properties": {
    "gn:admin1_code":"3",
    "gn:asciiname":"Hazara Kacha",
    "gn:country_code":"PK",
    "gn:dem":166,
    "gn:feature_class":"P",
    "gn:feature_code":"PPL",
    "gn:name":"Hazara Kacha",
    "gn:population":0,
    "gn:timezone":"Asia/Karachi",
    "iso:country":"PK",
    "name:und_x_variant":[
        "Jhok Haz\u0101ra",
        "Hazara Kacha"
    ],
    "wof:name":"Hazara Kacha",
    "wof:placetype":"locality"
},
  "geometry": {"coordinates":[70.79944,31.57312],"type":"Point"}
}