{
  "type": "Feature",
  "properties": {
    "gn:admin1_code":"2.0",
    "gn:asciiname":"Abdul Karim Bakhlani",
    "gn:country_code":"PK",
    "gn:dem":72,
    "gn:feature_class":"P",
    "gn:feature_code":"PPL",
    "gn:name":"Abdul Karim Bakhlani",
    "gn:population":0,
    "gn:timezone":"Asia/Karachi",
    "iso:country":"PK",
    "wof:name":"Abdul Karim Bakhlani",
    "wof:placetype":"locality"
},
  "geometry": {"coordinates":[68.93445,28.46146],"type":"Point"}
}