{
  "type": "Feature",
  "properties": {
    "gn:admin1_code":"4",
    "gn:asciiname":"Larkki",
    "gn:country_code":"PK",
    "gn:dem":222,
    "gn:feature_class":"P",
    "gn:feature_code":"PPL",
    "gn:name":"Larkki",
    "gn:population":0,
    "gn:timezone":"Asia/Karachi",
    "iso:country":"PK",
    "name:und_x_variant":[
        "Lurikke"
    ],
    "wof:name":"Larkki",
    "wof:placetype":"locality"
},
  "geometry": {"coordinates":[74.24181,32.06897],"type":"Point"}
}