{
  "type": "Feature",
  "properties": {
    "gn:admin1_code":"4",
    "gn:asciiname":"Chuhi Mohla",
    "gn:country_code":"PK",
    "gn:dem":245,
    "gn:feature_class":"P",
    "gn:feature_code":"PPL",
    "gn:name":"Chuhi Mohla",
    "gn:population":0,
    "gn:timezone":"Asia/Karachi",
    "iso:country":"PK",
    "wof:name":"Chuhi Mohla",
    "wof:placetype":"locality"
},
  "geometry": {"coordinates":[74.48066,32.48135],"type":"Point"}
}