{
  "type": "Feature",
  "properties": {
    "gn:admin1_code":"2.0",
    "gn:asciiname":"Muhammad Hussain Kili",
    "gn:country_code":"PK",
    "gn:dem":1019,
    "gn:feature_class":"P",
    "gn:feature_code":"PPL",
    "gn:name":"Muhammad Hussain Kili",
    "gn:population":0,
    "gn:timezone":"Asia/Karachi",
    "iso:country":"PK",
    "wof:name":"Muhammad Hussain Kili",
    "wof:placetype":"locality"
},
  "geometry": {"coordinates":[64.13994,29.06257],"type":"Point"}
}