{
  "type": "Feature",
  "properties": {
    "gn:admin1_code":"4",
    "gn:asciiname":"Basti Garhur",
    "gn:country_code":"PK",
    "gn:dem":107,
    "gn:feature_class":"P",
    "gn:feature_code":"PPL",
    "gn:name":"Basti Garhur",
    "gn:population":0,
    "gn:timezone":"Asia/Karachi",
    "iso:country":"PK",
    "name:und_x_variant":[
        "Basti Garhoor",
        "Basti Gr\u0101on",
        "Basti Garhur"
    ],
    "wof:name":"Basti Garhur",
    "wof:placetype":"locality"
},
  "geometry": {"coordinates":[71.34191,29.19335],"type":"Point"}
}