{
  "type": "Feature",
  "properties": {
    "gn:admin1_code":"5",
    "gn:asciiname":"Bandhio Tar",
    "gn:country_code":"PK",
    "gn:dem":33,
    "gn:feature_class":"P",
    "gn:feature_code":"PPL",
    "gn:name":"Bandhio Tar",
    "gn:population":0,
    "gn:timezone":"Asia/Karachi",
    "iso:country":"PK",
    "name:und_x_variant":[
        "B\u0101ndhio Tar"
    ],
    "wof:name":"Bandhio Tar",
    "wof:placetype":"locality"
},
  "geometry": {"coordinates":[69.32101999999999,26.33379],"type":"Point"}
}