{
  "type": "Feature",
  "properties": {
    "gn:admin1_code":"1.0",
    "gn:asciiname":"Bizati Haji Kalle",
    "gn:country_code":"PK",
    "gn:dem":606,
    "gn:feature_class":"P",
    "gn:feature_code":"PPL",
    "gn:name":"Bizati Haji Kalle",
    "gn:population":0,
    "gn:timezone":"Asia/Karachi",
    "iso:country":"PK",
    "wof:name":"Bizati Haji Kalle",
    "wof:placetype":"locality"
},
  "geometry": {"coordinates":[71.35024,33.86894],"type":"Point"}
}