{
  "type": "Feature",
  "properties": {
    "gn:admin1_code":"3",
    "gn:asciiname":"Shahid Pani",
    "gn:country_code":"PK",
    "gn:dem":2838,
    "gn:feature_class":"P",
    "gn:feature_code":"PPL",
    "gn:name":"Shahid Pani",
    "gn:population":0,
    "gn:timezone":"Asia/Karachi",
    "iso:country":"PK",
    "name:und_x_variant":[
        "Shah\u012bdp\u0101ni"
    ],
    "wof:name":"Shahid Pani",
    "wof:placetype":"locality"
},
  "geometry": {"coordinates":[73.29817,34.65147],"type":"Point"}
}