{
  "type": "Feature",
  "properties": {
    "gn:admin1_code":"03",
    "gn:asciiname":"Shera",
    "gn:country_code":"PK",
    "gn:dem":982,
    "gn:feature_class":"P",
    "gn:feature_code":"PPL",
    "gn:name":"Shera",
    "gn:population":0,
    "gn:timezone":"Asia/Karachi",
    "iso:country":"PK",
    "name:eng_x_preferred":[
        "Shera"
    ],
    "wof:name":"Shera",
    "wof:placetype":"locality"
},
  "geometry": {"coordinates":[71.80555,34.87072],"type":"Point"}
}