{
  "type": "Feature",
  "properties": {
    "gn:admin1_code":"1.0",
    "gn:asciiname":"Darai",
    "gn:country_code":"PK",
    "gn:dem":1293,
    "gn:feature_class":"P",
    "gn:feature_code":"PPL",
    "gn:name":"Darai",
    "gn:population":0,
    "gn:timezone":"Asia/Karachi",
    "iso:country":"PK",
    "wof:name":"Darai",
    "wof:placetype":"locality"
},
  "geometry": {"coordinates":[70.9109,33.92319000000001],"type":"Point"}
}