{
  "type": "Feature",
  "properties": {
    "gn:admin1_code":"4",
    "gn:asciiname":"Chak Seven Hundred Thirteen Gogera Branch",
    "gn:country_code":"PK",
    "gn:dem":155,
    "gn:feature_class":"P",
    "gn:feature_code":"PPL",
    "gn:name":"Chak Seven Hundred Thirteen Gogera Branch",
    "gn:population":0,
    "gn:timezone":"Asia/Karachi",
    "iso:country":"PK",
    "wof:name":"Chak Seven Hundred Thirteen Gogera Branch",
    "wof:placetype":"locality"
},
  "geometry": {"coordinates":[72.6164,30.71236],"type":"Point"}
}