{
  "type": "Feature",
  "properties": {
    "gn:admin1_code":"2.0",
    "gn:asciiname":"Chini Kherz",
    "gn:country_code":"PK",
    "gn:dem":1346,
    "gn:feature_class":"P",
    "gn:feature_code":"PPL",
    "gn:name":"Chini Kherz",
    "gn:population":0,
    "gn:timezone":"Asia/Karachi",
    "iso:country":"PK",
    "name:und_x_variant":[
        "Chini Khezai"
    ],
    "wof:name":"Chini Kherz",
    "wof:placetype":"locality"
},
  "geometry": {"coordinates":[70.02605,30.7011],"type":"Point"}
}