{
  "type": "Feature",
  "properties": {
    "gn:admin1_code":"4.0",
    "gn:asciiname":"Chak Fifty-one/Twelve M",
    "gn:country_code":"PK",
    "gn:dem":185,
    "gn:feature_class":"P",
    "gn:feature_code":"PPL",
    "gn:name":"Chak Fifty-one/Twelve M",
    "gn:population":0,
    "gn:timezone":"Asia/Karachi",
    "iso:country":"PK",
    "name:und_x_variant":[
        "Chak 51/12 MB Zafar\u0101b\u0101d"
    ],
    "wof:name":"Chak Fifty-one/Twelve M",
    "wof:placetype":"locality"
},
  "geometry": {"coordinates":[72.26501999999998,32.23559],"type":"Point"}
}