{
  "type": "Feature",
  "properties": {
    "gn:admin1_code":"4",
    "gn:asciiname":"Rasulpur Dhuddike",
    "gn:country_code":"PK",
    "gn:dem":168,
    "gn:feature_class":"P",
    "gn:feature_code":"PPL",
    "gn:name":"Rasulpur Dhuddike",
    "gn:population":0,
    "gn:timezone":"Asia/Karachi",
    "iso:country":"PK",
    "name:und_x_variant":[
        "Ras\u016blpur"
    ],
    "wof:name":"Rasulpur Dhuddike",
    "wof:placetype":"locality"
},
  "geometry": {"coordinates":[73.69638,30.29463],"type":"Point"}
}