{
  "type": "Feature",
  "properties": {
    "gn:admin1_code":"3",
    "gn:asciiname":"Phaju Nakar",
    "gn:country_code":"PK",
    "gn:dem":1468,
    "gn:feature_class":"P",
    "gn:feature_code":"PPL",
    "gn:name":"Phaju Nakar",
    "gn:population":0,
    "gn:timezone":"Asia/Karachi",
    "iso:country":"PK",
    "wof:name":"Phaju Nakar",
    "wof:placetype":"locality"
},
  "geometry": {"coordinates":[73.46383,34.15161],"type":"Point"}
}