{
  "type": "Feature",
  "properties": {
    "gn:admin1_code":"4.0",
    "gn:asciiname":"Jajjha Abbasian",
    "gn:country_code":"PK",
    "gn:dem":94,
    "gn:feature_class":"P",
    "gn:feature_code":"PPL",
    "gn:name":"Jajjha Abbasian",
    "gn:population":0,
    "gn:timezone":"Asia/Karachi",
    "iso:country":"PK",
    "name:und_x_variant":[
        "Jajja",
        "Jajjah",
        "Jajjha",
        "Jajjha Abbasian"
    ],
    "wof:name":"Jajjha Abbasian",
    "wof:placetype":"locality"
},
  "geometry": {"coordinates":[70.56715,28.75397],"type":"Point"}
}