{
  "type": "Feature",
  "properties": {
    "gn:admin1_code":"4.0",
    "gn:asciiname":"Khanur",
    "gn:country_code":"PK",
    "gn:dem":272,
    "gn:feature_class":"P",
    "gn:feature_code":"PPL",
    "gn:name":"Khanur",
    "gn:population":0,
    "gn:timezone":"Asia/Karachi",
    "iso:country":"PK",
    "name:und_x_variant":[
        "Khanoor",
        "Khanor",
        "Khanur"
    ],
    "wof:name":"Khanur",
    "wof:placetype":"locality"
},
  "geometry": {"coordinates":[74.80695,32.47203],"type":"Point"}
}