{
  "type": "Feature",
  "properties": {
    "gn:admin1_code":"5.0",
    "gn:asciiname":"Paneli",
    "gn:country_code":"PK",
    "gn:dem":18,
    "gn:feature_class":"P",
    "gn:feature_code":"PPL",
    "gn:name":"Paneli",
    "gn:population":0,
    "gn:timezone":"Asia/Karachi",
    "iso:country":"PK",
    "name:und_x_variant":[
        "Panelo"
    ],
    "wof:name":"Paneli",
    "wof:placetype":"locality"
},
  "geometry": {"coordinates":[69.79321999999999,24.30235],"type":"Point"}
}