{
  "type": "Feature",
  "properties": {
    "gn:admin1_code":"5.0",
    "gn:asciiname":"Goth Dengro",
    "gn:country_code":"PK",
    "gn:dem":66,
    "gn:feature_class":"P",
    "gn:feature_code":"PPL",
    "gn:name":"Goth Dengro",
    "gn:population":0,
    "gn:timezone":"Asia/Karachi",
    "iso:country":"PK",
    "name:und_x_variant":[
        "Dengro",
        "Dingaro",
        "Goth Dengro"
    ],
    "wof:name":"Goth Dengro",
    "wof:placetype":"locality"
},
  "geometry": {"coordinates":[68.81536,27.78305],"type":"Point"}
}