{
  "type": "Feature",
  "properties": {
    "gn:admin1_code":"4",
    "gn:asciiname":"Thatta Bahadur Kharai",
    "gn:country_code":"PK",
    "gn:dem":193,
    "gn:feature_class":"P",
    "gn:feature_code":"PPL",
    "gn:name":"Thatta Bah\u0101dur Kharai",
    "gn:population":0,
    "gn:timezone":"Asia/Karachi",
    "iso:country":"PK",
    "wof:name":"Thatta Bahadur Kharai",
    "wof:placetype":"locality"
},
  "geometry": {"coordinates":[73.83889000000001,31.32917],"type":"Point"}
}