{
  "type": "Feature",
  "properties": {
    "gn:admin1_code":"3.0",
    "gn:asciiname":"Tor Kili",
    "gn:country_code":"PK",
    "gn:dem":415,
    "gn:feature_class":"P",
    "gn:feature_code":"PPL",
    "gn:name":"Tor Kili",
    "gn:population":0,
    "gn:timezone":"Asia/Karachi",
    "iso:country":"PK",
    "wof:name":"Tor Kili",
    "wof:placetype":"locality"
},
  "geometry": {"coordinates":[70.55320999999998,33.00938],"type":"Point"}
}