{
  "type": "Feature",
  "properties": {
    "gn:admin1_code":"1.0",
    "gn:asciiname":"Bar Mela",
    "gn:country_code":"PK",
    "gn:dem":1612,
    "gn:feature_class":"P",
    "gn:feature_code":"PPL",
    "gn:name":"Bar Mela",
    "gn:population":0,
    "gn:timezone":"Asia/Karachi",
    "iso:country":"PK",
    "wof:name":"Bar Mela",
    "wof:placetype":"locality"
},
  "geometry": {"coordinates":[70.71266,33.66445],"type":"Point"}
}