{
  "type": "Feature",
  "properties": {
    "gn:admin1_code":"4",
    "gn:asciiname":"Jhok Bakhrowali",
    "gn:country_code":"PK",
    "gn:dem":180,
    "gn:feature_class":"P",
    "gn:feature_code":"PPL",
    "gn:name":"Jhok Bakhrowali",
    "gn:population":0,
    "gn:timezone":"Asia/Karachi",
    "iso:country":"PK",
    "name:und_x_variant":[
        "Jhok Bakhro",
        "Jhok Bakhrowali"
    ],
    "wof:name":"Jhok Bakhrowali",
    "wof:placetype":"locality"
},
  "geometry": {"coordinates":[70.60460999999999,31.24414],"type":"Point"}
}