{
  "type": "Feature",
  "properties": {
    "gn:admin1_code":"4",
    "gn:asciiname":"Khan Joija",
    "gn:country_code":"PK",
    "gn:dem":231,
    "gn:feature_class":"P",
    "gn:feature_code":"PPL",
    "gn:name":"Khan Joija",
    "gn:population":0,
    "gn:timezone":"Asia/Karachi",
    "iso:country":"PK",
    "name:und_x_variant":[
        "Kh\u0101n Jajja",
        "Khan Joija"
    ],
    "wof:name":"Khan Joija",
    "wof:placetype":"locality"
},
  "geometry": {"coordinates":[74.58565,32.12095],"type":"Point"}
}