{
  "type": "Feature",
  "properties": {
    "gn:admin1_code":"4.0",
    "gn:asciiname":"Chak Four Hundred Fifty-five",
    "gn:country_code":"PK",
    "gn:dem":157,
    "gn:feature_class":"P",
    "gn:feature_code":"PPL",
    "gn:name":"Chak Four Hundred Fifty-five",
    "gn:population":0,
    "gn:timezone":"Asia/Karachi",
    "iso:country":"PK",
    "name:und_x_variant":[
        "Boharw\u0101la",
        "Chak 455",
        "Chak Four Hundred Fifty-five",
        "Boh\u0101rw\u0101la"
    ],
    "wof:name":"Chak Four Hundred Fifty-five",
    "wof:placetype":"locality"
},
  "geometry": {"coordinates":[72.4162,31.24128],"type":"Point"}
}