{
  "type": "Feature",
  "properties": {
    "gn:admin1_code":"01",
    "gn:asciiname":"Chappari",
    "gn:country_code":"PK",
    "gn:dem":888,
    "gn:feature_class":"P",
    "gn:feature_code":"PPL",
    "gn:name":"Chappari",
    "gn:population":0,
    "gn:timezone":"Asia/Karachi",
    "iso:country":"PK",
    "name:und_x_variant":[
        "Tsapparai"
    ],
    "wof:name":"Chappari",
    "wof:placetype":"locality"
},
  "geometry": {"coordinates":[70.69709,33.17489],"type":"Point"}
}