{
  "type": "Feature",
  "properties": {
    "gn:admin1_code":"3",
    "gn:asciiname":"Gand",
    "gn:country_code":"PK",
    "gn:dem":1554,
    "gn:feature_class":"P",
    "gn:feature_code":"PPL",
    "gn:name":"Gand",
    "gn:population":0,
    "gn:timezone":"Asia/Karachi",
    "iso:country":"PK",
    "name:ceb_x_preferred":[
        "Gand"
    ],
    "name:deu_x_preferred":[
        "Gand"
    ],
    "name:fra_x_preferred":[
        "Gand"
    ],
    "name:ita_x_preferred":[
        "Gand"
    ],
    "name:nld_x_preferred":[
        "Gand"
    ],
    "name:nor_x_preferred":[
        "Gand"
    ],
    "name:swe_x_preferred":[
        "Gand"
    ],
    "name:ukr_x_preferred":[
        "\u0413\u0430\u043d\u0434"
    ],
    "wof:name":"Gand",
    "wof:placetype":"locality"
},
  "geometry": {"coordinates":[72.91547,34.31299],"type":"Point"}
}