{
  "type": "Feature",
  "properties": {
    "gn:admin1_code":"3",
    "gn:asciiname":"Gand",
    "gn:country_code":"PK",
    "gn:dem":1554,
    "gn:feature_class":"P",
    "gn:feature_code":"PPL",
    "gn:name":"Gand",
    "gn:population":0,
    "gn:timezone":"Asia/Karachi",
    "iso:country":"PK",
    "wof:name":"Gand",
    "wof:placetype":"locality"
},
  "geometry": {"coordinates":[72.91547,34.31299],"type":"Point"}
}