{
  "type": "Feature",
  "properties": {
    "gn:admin1_code":"3.0",
    "gn:asciiname":"Tangai",
    "gn:country_code":"PK",
    "gn:dem":1655,
    "gn:feature_class":"P",
    "gn:feature_code":"PPL",
    "gn:name":"Tangai",
    "gn:population":0,
    "gn:timezone":"Asia/Karachi",
    "iso:country":"PK",
    "wof:name":"Tangai",
    "wof:placetype":"locality"
},
  "geometry": {"coordinates":[72.11196,35.071],"type":"Point"}
}