{
  "type": "Feature",
  "properties": {
    "gn:admin1_code":"4",
    "gn:asciiname":"Binda Bahu Shah",
    "gn:country_code":"PK",
    "gn:dem":163,
    "gn:feature_class":"P",
    "gn:feature_code":"PPL",
    "gn:name":"Binda Bahu Shah",
    "gn:population":0,
    "gn:timezone":"Asia/Karachi",
    "iso:country":"PK",
    "name:und_x_variant":[
        "Wariam Kh\u0101n",
        "Binda Bahu Shah"
    ],
    "wof:name":"Binda Bahu Shah",
    "wof:placetype":"locality"
},
  "geometry": {"coordinates":[70.95705,31.57583],"type":"Point"}
}