{
  "type": "Feature",
  "properties": {
    "gn:admin1_code":"5",
    "gn:asciiname":"Ramzan Brahui",
    "gn:country_code":"PK",
    "gn:dem":40,
    "gn:feature_class":"P",
    "gn:feature_code":"PPL",
    "gn:name":"Ramzan Brahui",
    "gn:population":0,
    "gn:timezone":"Asia/Karachi",
    "iso:country":"PK",
    "name:eng_x_preferred":[
        "Goth Nazar Muhammad"
    ],
    "wof:name":"Ramzan Brahui",
    "wof:placetype":"locality"
},
  "geometry": {"coordinates":[68.04422,25.07661],"type":"Point"}
}