{
  "type": "Feature",
  "properties": {
    "gn:admin1_code":"4.0",
    "gn:asciiname":"Alipur",
    "gn:country_code":"PK",
    "gn:dem":110,
    "gn:feature_class":"P",
    "gn:feature_code":"PPL",
    "gn:name":"Alipur",
    "gn:population":0,
    "gn:timezone":"Asia/Karachi",
    "iso:country":"PK",
    "name:cat_x_preferred":[
        "Alipur"
    ],
    "name:ceb_x_preferred":[
        "Alipur"
    ],
    "name:eng_x_preferred":[
        "Alipur"
    ],
    "name:swe_x_preferred":[
        "Alipur"
    ],
    "name:urd_x_preferred":[
        "\u0639\u0644\u06cc \u067e\u0648\u0631"
    ],
    "wof:name":"Alipur",
    "wof:placetype":"locality"
},
  "geometry": {"coordinates":[71.20105,29.565],"type":"Point"}
}