{
  "type": "Feature",
  "properties": {
    "gn:admin1_code":"3.0",
    "gn:asciiname":"Kotka Mian Khel",
    "gn:country_code":"PK",
    "gn:dem":361,
    "gn:feature_class":"P",
    "gn:feature_code":"PPL",
    "gn:name":"Kotka Mian Khel",
    "gn:population":0,
    "gn:timezone":"Asia/Karachi",
    "iso:country":"PK",
    "name:und_x_variant":[
        "Kotkai Mi\u0101n Khel",
        "Kotka Mian Khel"
    ],
    "wof:name":"Kotka Mian Khel",
    "wof:placetype":"locality"
},
  "geometry": {"coordinates":[70.62073000000002,32.96085],"type":"Point"}
}