{
  "type": "Feature",
  "properties": {
    "gn:admin1_code":"3.0",
    "gn:asciiname":"Kotka Kas",
    "gn:country_code":"PK",
    "gn:dem":330,
    "gn:feature_class":"P",
    "gn:feature_code":"PPL",
    "gn:name":"Kotka Kas",
    "gn:population":0,
    "gn:timezone":"Asia/Karachi",
    "iso:country":"PK",
    "name:und_x_variant":[
        "M\u012br\u0101sh"
    ],
    "wof:name":"Kotka Kas",
    "wof:placetype":"locality"
},
  "geometry": {"coordinates":[70.69755000000001,32.96518],"type":"Point"}
}