{
  "type": "Feature",
  "properties": {
    "gn:admin1_code":"3.0",
    "gn:asciiname":"Darunian",
    "gn:country_code":"PK",
    "gn:dem":707,
    "gn:feature_class":"P",
    "gn:feature_code":"PPL",
    "gn:name":"Darunian",
    "gn:population":0,
    "gn:timezone":"Asia/Karachi",
    "iso:country":"PK",
    "wof:name":"Darunian",
    "wof:placetype":"locality"
},
  "geometry": {"coordinates":[72.98143,33.91604],"type":"Point"}
}