{
  "type": "Feature",
  "properties": {
    "gn:admin1_code":"2.0",
    "gn:asciiname":"Kili Haji Rafique",
    "gn:country_code":"PK",
    "gn:dem":1746,
    "gn:feature_class":"P",
    "gn:feature_code":"PPL",
    "gn:name":"Kili Haji Rafique",
    "gn:population":0,
    "gn:timezone":"Asia/Karachi",
    "iso:country":"PK",
    "wof:name":"Kili Haji Rafique",
    "wof:placetype":"locality"
},
  "geometry": {"coordinates":[66.96485,30.06124],"type":"Point"}
}