{
  "type": "Feature",
  "properties": {
    "gn:admin1_code":"3",
    "gn:asciiname":"Nil Batla",
    "gn:country_code":"PK",
    "gn:dem":1168,
    "gn:feature_class":"P",
    "gn:feature_code":"PPL",
    "gn:name":"Nil Batla",
    "gn:population":0,
    "gn:timezone":"Asia/Karachi",
    "iso:country":"PK",
    "name:und_x_variant":[
        "Nilbatla Tarla"
    ],
    "wof:name":"Nil Batla",
    "wof:placetype":"locality"
},
  "geometry": {"coordinates":[72.91085,34.45559],"type":"Point"}
}