{
  "type": "Feature",
  "properties": {
    "gn:admin1_code":"5.0",
    "gn:asciiname":"Ghora Ghat",
    "gn:country_code":"PK",
    "gn:dem":68,
    "gn:feature_class":"P",
    "gn:feature_code":"PPL",
    "gn:name":"Ghora Ghat",
    "gn:population":0,
    "gn:timezone":"Asia/Karachi",
    "iso:country":"PK",
    "name:und_x_variant":[
        "Ghora Ghat Pako",
        "Ghora Ghat"
    ],
    "wof:name":"Ghora Ghat",
    "wof:placetype":"locality"
},
  "geometry": {"coordinates":[69.26228,28.20353],"type":"Point"}
}