{
  "type": "Feature",
  "properties": {
    "gn:admin1_code":"4.0",
    "gn:asciiname":"Chak Four Hundred Ninety-seven Thal Development Authority",
    "gn:country_code":"PK",
    "gn:dem":134,
    "gn:feature_class":"P",
    "gn:feature_code":"PPL",
    "gn:name":"Chak Four Hundred Ninety-seven Thal Development Authority",
    "gn:population":0,
    "gn:timezone":"Asia/Karachi",
    "iso:country":"PK",
    "name:und_x_variant":[
        "Chak Four Hundred Ninety-Seven TDA",
        "Chak 497 TDA",
        "Chak Four Hundred Ninety-seven Thal Development Authority"
    ],
    "wof:name":"Chak Four Hundred Ninety-seven Thal Development Authority",
    "wof:placetype":"locality"
},
  "geometry": {"coordinates":[71.44638,30.66589],"type":"Point"}
}