{
  "type": "Feature",
  "properties": {
    "gn:admin1_code":"05",
    "gn:asciiname":"Muhammad Siddiq Memon",
    "gn:country_code":"PK",
    "gn:dem":1,
    "gn:feature_class":"P",
    "gn:feature_code":"PPL",
    "gn:name":"Muhammad Siddiq Memon",
    "gn:population":0,
    "gn:timezone":"Asia/Karachi",
    "iso:country":"PK",
    "wof:name":"Muhammad Siddiq Memon",
    "wof:placetype":"locality"
},
  "geometry": {"coordinates":[67.6326,24.08806],"type":"Point"}
}