{
  "type": "Feature",
  "properties": {
    "gn:admin1_code":"4.0",
    "gn:asciiname":"Bher Hathial",
    "gn:country_code":"PK",
    "gn:dem":504,
    "gn:feature_class":"P",
    "gn:feature_code":"PPL",
    "gn:name":"Bher Hathial",
    "gn:population":0,
    "gn:timezone":"Asia/Karachi",
    "iso:country":"PK",
    "wof:name":"Bher Hathial",
    "wof:placetype":"locality"
},
  "geometry": {"coordinates":[73.08056999999999,33.22611],"type":"Point"}
}