{
  "type": "Feature",
  "properties": {
    "gn:admin1_code":"4",
    "gn:asciiname":"Nur Jamal",
    "gn:country_code":"PK",
    "gn:dem":176,
    "gn:feature_class":"P",
    "gn:feature_code":"PPL",
    "gn:name":"Nur Jamal",
    "gn:population":0,
    "gn:timezone":"Asia/Karachi",
    "iso:country":"PK",
    "name:und_x_variant":[
        "N\u016br Jamai"
    ],
    "wof:name":"Nur Jamal",
    "wof:placetype":"locality"
},
  "geometry": {"coordinates":[71.1056,31.94924],"type":"Point"}
}