{
  "type": "Feature",
  "properties": {
    "gn:admin1_code":"4.0",
    "gn:asciiname":"Chak Twenty-eight A - Four Left",
    "gn:country_code":"PK",
    "gn:dem":174,
    "gn:feature_class":"P",
    "gn:feature_code":"PPL",
    "gn:name":"Chak Twenty-eight A - Four Left",
    "gn:population":0,
    "gn:timezone":"Asia/Karachi",
    "iso:country":"PK",
    "name:und_x_variant":[
        "Chak Twenty-eight A Four L"
    ],
    "wof:name":"Chak Twenty-eight A - Four Left",
    "wof:placetype":"locality"
},
  "geometry": {"coordinates":[73.383,30.6967],"type":"Point"}
}