{
  "type": "Feature",
  "properties": {
    "gn:admin1_code":"2.0",
    "gn:asciiname":"Yarikhezi Melan",
    "gn:country_code":"PK",
    "gn:dem":1842,
    "gn:feature_class":"P",
    "gn:feature_code":"PPL",
    "gn:name":"Yarikhezi Melan",
    "gn:population":0,
    "gn:timezone":"Asia/Karachi",
    "iso:country":"PK",
    "wof:name":"Yarikhezi Melan",
    "wof:placetype":"locality"
},
  "geometry": {"coordinates":[68.66725,31.13209],"type":"Point"}
}