{
  "type": "Feature",
  "properties": {
    "gn:admin1_code":"01",
    "gn:asciiname":"Larozai",
    "gn:country_code":"PK",
    "gn:dem":2100,
    "gn:feature_class":"P",
    "gn:feature_code":"PPL",
    "gn:name":"Larozai",
    "gn:population":0,
    "gn:timezone":"Asia/Karachi",
    "iso:country":"PK",
    "name:und_x_variant":[
        "Lar Boza Ch\u012bna",
        "Lar Boza",
        "Larozai"
    ],
    "wof:name":"Larozai",
    "wof:placetype":"locality"
},
  "geometry": {"coordinates":[69.57978,32.48999],"type":"Point"}
}