{
  "type": "Feature",
  "properties": {
    "gn:admin1_code":"5.0",
    "gn:asciiname":"Latif Abupoto",
    "gn:country_code":"PK",
    "gn:dem":28,
    "gn:feature_class":"P",
    "gn:feature_code":"PPL",
    "gn:name":"Latif Abupoto",
    "gn:population":0,
    "gn:timezone":"Asia/Karachi",
    "iso:country":"PK",
    "wof:name":"Latif Abupoto",
    "wof:placetype":"locality"
},
  "geometry": {"coordinates":[69.07165000000001,26.30358],"type":"Point"}
}