{
  "type": "Feature",
  "properties": {
    "gn:admin1_code":"5.0",
    "gn:asciiname":"Haji Muhammad Laghari",
    "gn:country_code":"PK",
    "gn:dem":9,
    "gn:feature_class":"P",
    "gn:feature_code":"PPL",
    "gn:name":"Haji Muhammad Laghari",
    "gn:population":0,
    "gn:timezone":"Asia/Karachi",
    "iso:country":"PK",
    "name:eng_x_preferred":[
        "Haji Muhammad Laghari"
    ],
    "wof:name":"Haji Muhammad Laghari",
    "wof:placetype":"locality"
},
  "geometry": {"coordinates":[68.07906,24.50326],"type":"Point"}
}