{
  "type": "Feature",
  "properties": {
    "gn:admin1_code":"5",
    "gn:asciiname":"Goth Mir Muhammad Marfani",
    "gn:country_code":"PK",
    "gn:dem":57,
    "gn:feature_class":"P",
    "gn:feature_code":"PPL",
    "gn:name":"Goth Mir Muhammad Marfani",
    "gn:population":0,
    "gn:timezone":"Asia/Karachi",
    "iso:country":"PK",
    "name:und_x_variant":[
        "M\u012br Muhammad Marf\u0101ni"
    ],
    "wof:name":"Goth Mir Muhammad Marfani",
    "wof:placetype":"locality"
},
  "geometry": {"coordinates":[68.47790000000001,27.9341],"type":"Point"}
}