{
  "type": "Feature",
  "properties": {
    "gn:admin1_code":"6",
    "gn:asciiname":"Bheri",
    "gn:country_code":"PK",
    "gn:dem":1653,
    "gn:feature_class":"P",
    "gn:feature_code":"PPL",
    "gn:name":"Bheri",
    "gn:population":0,
    "gn:timezone":"Asia/Karachi",
    "iso:country":"PK",
    "name:slk_x_preferred":[
        "Bheri"
    ],
    "wof:name":"Bheri",
    "wof:placetype":"locality"
},
  "geometry": {"coordinates":[73.57132,34.52631],"type":"Point"}
}