{
  "type": "Feature",
  "properties": {
    "gn:admin1_code":"4.0",
    "gn:asciiname":"Dhok Manhukha",
    "gn:country_code":"PK",
    "gn:dem":425,
    "gn:feature_class":"P",
    "gn:feature_code":"PPL",
    "gn:name":"Dhok Manhukha",
    "gn:population":0,
    "gn:timezone":"Asia/Karachi",
    "iso:country":"PK",
    "name:und_x_variant":[
        "Mihokhew\u0101li Dhok"
    ],
    "wof:name":"Dhok Manhukha",
    "wof:placetype":"locality"
},
  "geometry": {"coordinates":[71.88921999999999,33.28885],"type":"Point"}
}