{
  "type": "Feature",
  "properties": {
    "gn:admin1_code":"4.0",
    "gn:asciiname":"Agumar",
    "gn:country_code":"PK",
    "gn:dem":450,
    "gn:feature_class":"P",
    "gn:feature_code":"PPL",
    "gn:name":"Agumar",
    "gn:population":0,
    "gn:timezone":"Asia/Karachi",
    "iso:country":"PK",
    "wof:name":"Agumar",
    "wof:placetype":"locality"
},
  "geometry": {"coordinates":[71.99628,32.65],"type":"Point"}
}