{
  "type": "Feature",
  "properties": {
    "gn:admin1_code":"8.0",
    "gn:asciiname":"Mandla",
    "gn:country_code":"PK",
    "gn:dem":647,
    "gn:feature_class":"P",
    "gn:feature_code":"PPL",
    "gn:name":"Mandla",
    "gn:population":0,
    "gn:timezone":"Asia/Karachi",
    "iso:country":"PK",
    "name:ben_x_preferred":[
        "\u09ae\u09a8\u09cd\u09a6\u09b2\u09be"
    ],
    "name:bpy_x_preferred":[
        "\u09ae\u09a8\u09cd\u09a6\u09b2\u09be"
    ],
    "name:cat_x_preferred":[
        "Mandla"
    ],
    "name:ceb_x_preferred":[
        "Mandl\u0101"
    ],
    "name:deu_x_preferred":[
        "Mandla"
    ],
    "name:eng_x_preferred":[
        "Mandia"
    ],
    "name:fas_x_preferred":[
        "\u0645\u0627\u0646\u062f\u0644\u0627"
    ],
    "name:fra_x_preferred":[
        "Mandla"
    ],
    "name:guj_x_preferred":[
        "\u0aae\u0a82\u0aa1\u0ab2\u0abe"
    ],
    "name:hin_x_preferred":[
        "\u092e\u0902\u0921\u0932\u093e"
    ],
    "name:ita_x_preferred":[
        "Mandla"
    ],
    "name:mar_x_preferred":[
        "\u092e\u0902\u0921\u0932\u093e"
    ],
    "name:mlg_x_preferred":[
        "Mandla"
    ],
    "name:msa_x_preferred":[
        "Mandla"
    ],
    "name:new_x_preferred":[
        "\u092e\u0928\u094d\u0926\u094d\u0932\u093e"
    ],
    "name:ori_x_preferred":[
        "\u0b2e\u0b3e\u0b28\u0b4d\u0b26\u0b4d\u0b32\u0b3e"
    ],
    "name:por_x_preferred":[
        "Mandla"
    ],
    "name:san_x_preferred":[
        "\u092e\u0923\u094d\u0921\u0932\u093e"
    ],
    "name:spa_x_preferred":[
        "Mandla"
    ],
    "name:swe_x_preferred":[
        "Mandla"
    ],
    "name:tam_x_preferred":[
        "\u0bae\u0ba3\u0bcd\u0b9f\u0bcd\u0bb2\u0bbe"
    ],
    "name:urd_x_preferred":[
        "\u0645\u0627\u0646\u0688\u0644\u0627"
    ],
    "name:vie_x_preferred":[
        "Mandla"
    ],
    "wof:name":"Mandla",
    "wof:placetype":"locality"
},
  "geometry": {"coordinates":[73.17256,33.76594],"type":"Point"}
}