{
  "type": "Feature",
  "properties": {
    "gn:admin1_code":"1",
    "gn:asciiname":"Karam Khel",
    "gn:country_code":"PK",
    "gn:dem":1059,
    "gn:feature_class":"P",
    "gn:feature_code":"PPL",
    "gn:name":"Karam Khel",
    "gn:population":0,
    "gn:timezone":"Asia/Karachi",
    "iso:country":"PK",
    "name:und_x_variant":[
        "Dotanni"
    ],
    "wof:name":"Karam Khel",
    "wof:placetype":"locality"
},
  "geometry": {"coordinates":[69.595,32.15806],"type":"Point"}
}