{
  "type": "Feature",
  "properties": {
    "gn:admin1_code":"3",
    "gn:asciiname":"Kachcha Kor",
    "gn:country_code":"PK",
    "gn:dem":1656,
    "gn:feature_class":"P",
    "gn:feature_code":"PPL",
    "gn:name":"Kachcha Kor",
    "gn:population":0,
    "gn:timezone":"Asia/Karachi",
    "iso:country":"PK",
    "wof:name":"Kachcha Kor",
    "wof:placetype":"locality"
},
  "geometry": {"coordinates":[72.45926999999998,34.73146],"type":"Point"}
}