{
  "type": "Feature",
  "properties": {
    "gn:admin1_code":"3.0",
    "gn:asciiname":"Led",
    "gn:country_code":"PK",
    "gn:dem":1909,
    "gn:feature_class":"P",
    "gn:feature_code":"PPL",
    "gn:name":"Led",
    "gn:population":0,
    "gn:timezone":"Asia/Karachi",
    "iso:country":"PK",
    "wof:name":"Led",
    "wof:placetype":"locality"
},
  "geometry": {"coordinates":[73.12288000000002,35.5099],"type":"Point"}
}