{
  "type": "Feature",
  "properties": {
    "gn:admin1_code":"5.0",
    "gn:asciiname":"Fida Dino Brahui",
    "gn:country_code":"PK",
    "gn:dem":12,
    "gn:feature_class":"P",
    "gn:feature_code":"PPL",
    "gn:name":"Fida Dino Brahui",
    "gn:population":0,
    "gn:timezone":"Asia/Karachi",
    "iso:country":"PK",
    "wof:name":"Fida Dino Brahui",
    "wof:placetype":"locality"
},
  "geometry": {"coordinates":[67.95149000000001,24.76282],"type":"Point"}
}