{
  "type": "Feature",
  "properties": {
    "gn:admin1_code":"02",
    "gn:asciiname":"Goth Brahui",
    "gn:country_code":"PK",
    "gn:dem":128,
    "gn:feature_class":"P",
    "gn:feature_code":"PPL",
    "gn:name":"Goth Brahui",
    "gn:population":0,
    "gn:timezone":"Asia/Karachi",
    "iso:country":"PK",
    "name:und_x_variant":[
        "Goth Rahail"
    ],
    "wof:name":"Goth Brahui",
    "wof:placetype":"locality"
},
  "geometry": {"coordinates":[67.13334,25.42251],"type":"Point"}
}