{
  "type": "Feature",
  "properties": {
    "gn:admin1_code":"7.0",
    "gn:asciiname":"Paronpi Brok",
    "gn:country_code":"PK",
    "gn:dem":4562,
    "gn:feature_class":"P",
    "gn:feature_code":"PPL",
    "gn:name":"Paronpi Brok",
    "gn:population":0,
    "gn:timezone":"Asia/Karachi",
    "iso:country":"PK",
    "wof:name":"Paronpi Brok",
    "wof:placetype":"locality"
},
  "geometry": {"coordinates":[76.60696999999998,35.15620999999999],"type":"Point"}
}