{
  "type": "Feature",
  "properties": {
    "gn:admin1_code":"4.0",
    "gn:asciiname":"Pattewali Baihk",
    "gn:country_code":"PK",
    "gn:dem":353,
    "gn:feature_class":"P",
    "gn:feature_code":"PPL",
    "gn:name":"Pattewali Baihk",
    "gn:population":0,
    "gn:timezone":"Asia/Karachi",
    "iso:country":"PK",
    "wof:name":"Pattewali Baihk",
    "wof:placetype":"locality"
},
  "geometry": {"coordinates":[72.42627,33.71547],"type":"Point"}
}