{
  "type": "Feature",
  "properties": {
    "gn:admin1_code":"6",
    "gn:asciiname":"Sharegi Baihk",
    "gn:country_code":"PK",
    "gn:dem":2503,
    "gn:feature_class":"P",
    "gn:feature_code":"PPL",
    "gn:name":"Sharegi Baihk",
    "gn:population":0,
    "gn:timezone":"Asia/Karachi",
    "iso:country":"PK",
    "name:und_x_variant":[
        "Sherogai Baihk",
        "Shar\u0113gi Baihk"
    ],
    "wof:name":"Sharegi Baihk",
    "wof:placetype":"locality"
},
  "geometry": {"coordinates":[74.38472,34.82917],"type":"Point"}
}