{
  "type": "Feature",
  "properties": {
    "gn:admin1_code":"04",
    "gn:asciiname":"Shah Nal",
    "gn:country_code":"PK",
    "gn:dem":112,
    "gn:feature_class":"P",
    "gn:feature_code":"PPL",
    "gn:name":"Shah Nal",
    "gn:population":0,
    "gn:timezone":"Asia/Karachi",
    "iso:country":"PK",
    "wof:name":"Shah Nal",
    "wof:placetype":"locality"
},
  "geometry": {"coordinates":[71.52945,29.59751],"type":"Point"}
}