{
  "type": "Feature",
  "properties": {
    "gn:admin1_code":"2.0",
    "gn:asciiname":"Sohr Karudi",
    "gn:country_code":"PK",
    "gn:dem":1260,
    "gn:feature_class":"P",
    "gn:feature_code":"PPL",
    "gn:name":"Sohr Karudi",
    "gn:population":0,
    "gn:timezone":"Asia/Karachi",
    "iso:country":"PK",
    "wof:name":"Sohr Karudi",
    "wof:placetype":"locality"
},
  "geometry": {"coordinates":[65.88953000000001,27.55177],"type":"Point"}
}