{
  "type": "Feature",
  "properties": {
    "gn:admin1_code":"04",
    "gn:asciiname":"Muhammad Dah",
    "gn:country_code":"PK",
    "gn:dem":116,
    "gn:feature_class":"P",
    "gn:feature_code":"PPL",
    "gn:name":"Muhammad Dah",
    "gn:population":0,
    "gn:timezone":"Asia/Karachi",
    "iso:country":"PK",
    "name:und_x_variant":[
        "Muhammad Daha",
        "Muhammad Dah"
    ],
    "wof:name":"Muhammad Dah",
    "wof:placetype":"locality"
},
  "geometry": {"coordinates":[70.98333000000002,29.96667],"type":"Point"}
}