{
  "type": "Feature",
  "properties": {
    "gn:admin1_code":"4.0",
    "gn:asciiname":"Dowala",
    "gn:country_code":"PK",
    "gn:dem":368,
    "gn:feature_class":"P",
    "gn:feature_code":"PPL",
    "gn:name":"Dowala",
    "gn:population":0,
    "gn:timezone":"Asia/Karachi",
    "iso:country":"PK",
    "wof:name":"Dowala",
    "wof:placetype":"locality"
},
  "geometry": {"coordinates":[73.48599,33.11863],"type":"Point"}
}