{
  "type": "Feature",
  "properties": {
    "gn:admin1_code":"3.0",
    "gn:asciiname":"Banda",
    "gn:country_code":"PK",
    "gn:dem":1527,
    "gn:feature_class":"P",
    "gn:feature_code":"PPL",
    "gn:name":"Banda",
    "gn:population":0,
    "gn:timezone":"Asia/Karachi",
    "iso:country":"PK",
    "wof:name":"Banda",
    "wof:placetype":"locality"
},
  "geometry": {"coordinates":[72.83105999999999,34.70771],"type":"Point"}
}