{
  "type": "Feature",
  "properties": {
    "gn:admin1_code":"2.0",
    "gn:asciiname":"Gazozai",
    "gn:country_code":"PK",
    "gn:dem":1113,
    "gn:feature_class":"P",
    "gn:feature_code":"PPL",
    "gn:name":"Gazozai",
    "gn:population":0,
    "gn:timezone":"Asia/Karachi",
    "iso:country":"PK",
    "name:und_x_variant":[
        "Gajozai"
    ],
    "wof:name":"Gazozai",
    "wof:placetype":"locality"
},
  "geometry": {"coordinates":[65.70573,27.22876],"type":"Point"}
}