{
  "type": "Feature",
  "properties": {
    "gn:admin1_code":"01",
    "gn:asciiname":"Titobai",
    "gn:country_code":"PK",
    "gn:dem":882,
    "gn:feature_class":"P",
    "gn:feature_code":"PPL",
    "gn:name":"Titobai",
    "gn:population":0,
    "gn:timezone":"Asia/Karachi",
    "iso:country":"PK",
    "name:eng_x_preferred":[
        "Titobai"
    ],
    "name:und_x_variant":[
        "Tidobai"
    ],
    "wof:name":"Titobai",
    "wof:placetype":"locality"
},
  "geometry": {"coordinates":[71.62446,34.63021],"type":"Point"}
}