{
  "type": "Feature",
  "properties": {
    "gn:admin1_code":"2",
    "gn:asciiname":"Zeebai Lundi Kili",
    "gn:country_code":"PK",
    "gn:dem":1483,
    "gn:feature_class":"P",
    "gn:feature_code":"PPL",
    "gn:name":"Zeebai Lundi Kili",
    "gn:population":0,
    "gn:timezone":"Asia/Karachi",
    "iso:country":"PK",
    "name:und_x_variant":[
        "Zaebai Lundi Kili"
    ],
    "wof:name":"Zeebai Lundi Kili",
    "wof:placetype":"locality"
},
  "geometry": {"coordinates":[69.67322,31.66875],"type":"Point"}
}