{
  "type": "Feature",
  "properties": {
    "gn:admin1_code":"2",
    "gn:asciiname":"Mohim Khan Brahui",
    "gn:country_code":"PK",
    "gn:dem":50,
    "gn:feature_class":"P",
    "gn:feature_code":"PPL",
    "gn:name":"Mohim Khan Brahui",
    "gn:population":0,
    "gn:timezone":"Asia/Karachi",
    "iso:country":"PK",
    "name:und_x_variant":[
        "Mah\u012bm Kh\u0101n",
        "Moh\u012bm Kh\u0101n",
        "Mohim Khan Brahui"
    ],
    "wof:name":"Mohim Khan Brahui",
    "wof:placetype":"locality"
},
  "geometry": {"coordinates":[67.93675,28.0537],"type":"Point"}
}