{
  "type": "Feature",
  "properties": {
    "gn:admin1_code":"4.0",
    "gn:asciiname":"Chautha Khan di Basti",
    "gn:country_code":"PK",
    "gn:dem":96,
    "gn:feature_class":"P",
    "gn:feature_code":"PPL",
    "gn:name":"Chautha Kh\u0101n di Basti",
    "gn:population":0,
    "gn:timezone":"Asia/Karachi",
    "iso:country":"PK",
    "wof:name":"Chautha Khan di Basti",
    "wof:placetype":"locality"
},
  "geometry": {"coordinates":[70.87348,29.12157],"type":"Point"}
}