{
  "type": "Feature",
  "properties": {
    "gn:admin1_code":"04",
    "gn:asciiname":"Saldera",
    "gn:country_code":"PK",
    "gn:dem":146,
    "gn:feature_class":"P",
    "gn:feature_code":"PPL",
    "gn:name":"Saldera",
    "gn:population":0,
    "gn:timezone":"Asia/Karachi",
    "iso:country":"PK",
    "name:und_x_variant":[
        "Saidera",
        "Saldera"
    ],
    "wof:name":"Saldera",
    "wof:placetype":"locality"
},
  "geometry": {"coordinates":[72.72013000000003,29.9659],"type":"Point"}
}