{
  "type": "Feature",
  "properties": {
    "gn:admin1_code":"4",
    "gn:asciiname":"Gondal",
    "gn:country_code":"PK",
    "gn:dem":266,
    "gn:feature_class":"P",
    "gn:feature_code":"PPL",
    "gn:name":"Gondal",
    "gn:population":0,
    "gn:timezone":"Asia/Karachi",
    "iso:country":"PK",
    "name:ceb_x_preferred":[
        "Gondal"
    ],
    "name:fra_x_preferred":[
        "Gondal"
    ],
    "name:msa_x_preferred":[
        "Gondal"
    ],
    "name:swe_x_preferred":[
        "Gondal"
    ],
    "wof:name":"Gondal",
    "wof:placetype":"locality"
},
  "geometry": {"coordinates":[74.28749999999999,32.70556],"type":"Point"}
}