{
  "type": "Feature",
  "properties": {
    "gn:admin1_code":"5.0",
    "gn:asciiname":"Ayoob Kandra Chowk",
    "gn:country_code":"PK",
    "gn:dem":19,
    "gn:feature_class":"P",
    "gn:feature_code":"PPL",
    "gn:name":"Ayoob Kandra Chowk",
    "gn:population":0,
    "gn:timezone":"Asia/Karachi",
    "iso:country":"PK",
    "wof:name":"Ayoob Kandra Chowk",
    "wof:placetype":"locality"
},
  "geometry": {"coordinates":[68.56328000000001,25.1278],"type":"Point"}
}