{
  "type": "Feature",
  "properties": {
    "gn:admin1_code":"5.0",
    "gn:asciiname":"Goth Dodo Khan Salar",
    "gn:country_code":"PK",
    "gn:dem":88,
    "gn:feature_class":"P",
    "gn:feature_code":"PPL",
    "gn:name":"Goth Dodo Khan Salar",
    "gn:population":0,
    "gn:timezone":"Asia/Karachi",
    "iso:country":"PK",
    "wof:name":"Goth Dodo Khan Salar",
    "wof:placetype":"locality"
},
  "geometry": {"coordinates":[67.43800999999999,24.92376],"type":"Point"}
}