{
  "type": "Feature",
  "properties": {
    "gn:admin1_code":"4",
    "gn:asciiname":"Jhuggian Jailo",
    "gn:country_code":"PK",
    "gn:dem":179,
    "gn:feature_class":"P",
    "gn:feature_code":"PPL",
    "gn:name":"Jhuggian Jailo",
    "gn:population":0,
    "gn:timezone":"Asia/Karachi",
    "iso:country":"PK",
    "name:und_x_variant":[
        "Jhuggi\u0101n Jalle"
    ],
    "wof:name":"Jhuggian Jailo",
    "wof:placetype":"locality"
},
  "geometry": {"coordinates":[73.80504999999999,30.7294],"type":"Point"}
}