{
  "type": "Feature",
  "properties": {
    "gn:admin1_code":"2.0",
    "gn:asciiname":"Horkai Kili",
    "gn:country_code":"PK",
    "gn:dem":1523,
    "gn:feature_class":"P",
    "gn:feature_code":"PPL",
    "gn:name":"Horkai Kili",
    "gn:population":0,
    "gn:timezone":"Asia/Karachi",
    "iso:country":"PK",
    "wof:name":"Horkai Kili",
    "wof:placetype":"locality"
},
  "geometry": {"coordinates":[69.33832,31.20553],"type":"Point"}
}