{
  "type": "Feature",
  "properties": {
    "gn:admin1_code":"3.0",
    "gn:asciiname":"Pari Kalai",
    "gn:country_code":"PK",
    "gn:dem":303,
    "gn:feature_class":"P",
    "gn:feature_code":"PPL",
    "gn:name":"Pari Kalai",
    "gn:population":0,
    "gn:timezone":"Asia/Karachi",
    "iso:country":"PK",
    "name:und_x_variant":[
        "M\u0101ndrai",
        "Pari Kalai"
    ],
    "wof:name":"Pari Kalai",
    "wof:placetype":"locality"
},
  "geometry": {"coordinates":[70.85684999999999,32.84648],"type":"Point"}
}