{
  "type": "Feature",
  "properties": {
    "gn:admin1_code":"6",
    "gn:asciiname":"Mehlum",
    "gn:country_code":"PK",
    "gn:dem":1594,
    "gn:feature_class":"P",
    "gn:feature_code":"PPL",
    "gn:name":"Mehlum",
    "gn:population":0,
    "gn:timezone":"Asia/Karachi",
    "iso:country":"PK",
    "name:und_x_variant":[
        "Metam",
        "Melam"
    ],
    "wof:name":"Mehlum",
    "wof:placetype":"locality"
},
  "geometry": {"coordinates":[73.52913000000002,34.2682],"type":"Point"}
}