{
  "type": "Feature",
  "properties": {
    "gn:admin1_code":"4.0",
    "gn:asciiname":"Hussainiabad",
    "gn:country_code":"PK",
    "gn:dem":139,
    "gn:feature_class":"P",
    "gn:feature_code":"PPL",
    "gn:name":"Hussainiabad",
    "gn:population":0,
    "gn:timezone":"Asia/Karachi",
    "iso:country":"PK",
    "name:und_x_variant":[
        "Hussainabad Awwal",
        "Husain\u0101b\u0101d",
        "Hussainiabad"
    ],
    "wof:name":"Hussainiabad",
    "wof:placetype":"locality"
},
  "geometry": {"coordinates":[72.00985,30.54531],"type":"Point"}
}