{
  "type": "Feature",
  "properties": {
    "gn:admin1_code":"3.0",
    "gn:asciiname":"Mithu Ghazni Khel",
    "gn:country_code":"PK",
    "gn:dem":302,
    "gn:feature_class":"P",
    "gn:feature_code":"PPL",
    "gn:name":"Mithu Ghazni Khel",
    "gn:population":0,
    "gn:timezone":"Asia/Karachi",
    "iso:country":"PK",
    "name:und_x_variant":[
        "Mithu",
        "Mithu Ghazni Khel"
    ],
    "wof:name":"Mithu Ghazni Khel",
    "wof:placetype":"locality"
},
  "geometry": {"coordinates":[70.77462,32.78466],"type":"Point"}
}