{
  "type": "Feature",
  "properties": {
    "gn:admin1_code":"4.0",
    "gn:asciiname":"Chak Sixty - D",
    "gn:country_code":"PK",
    "gn:dem":170,
    "gn:feature_class":"P",
    "gn:feature_code":"PPL",
    "gn:name":"Chak Sixty - D",
    "gn:population":0,
    "gn:timezone":"Asia/Karachi",
    "iso:country":"PK",
    "name:und_x_variant":[
        "Khokhr\u0101nw\u0101la"
    ],
    "wof:name":"Chak Sixty - D",
    "wof:placetype":"locality"
},
  "geometry": {"coordinates":[73.43063000000002,30.57446],"type":"Point"}
}