{
  "type": "Feature",
  "properties": {
    "gn:admin1_code":"4.0",
    "gn:asciiname":"Madiala",
    "gn:country_code":"PK",
    "gn:dem":330,
    "gn:feature_class":"P",
    "gn:feature_code":"PPL",
    "gn:name":"Madiala",
    "gn:population":0,
    "gn:timezone":"Asia/Karachi",
    "iso:country":"PK",
    "wof:name":"Madiala",
    "wof:placetype":"locality"
},
  "geometry": {"coordinates":[73.93494,32.86786],"type":"Point"}
}