{
  "type": "Feature",
  "properties": {
    "gn:admin1_code":"6",
    "gn:asciiname":"Banni",
    "gn:country_code":"PK",
    "gn:dem":2226,
    "gn:feature_class":"P",
    "gn:feature_code":"PPL",
    "gn:name":"Banni",
    "gn:population":0,
    "gn:timezone":"Asia/Karachi",
    "iso:country":"PK",
    "name:deu_x_preferred":[
        "Banni"
    ],
    "name:und_x_variant":[
        "Bani"
    ],
    "wof:name":"Banni",
    "wof:placetype":"locality"
},
  "geometry": {"coordinates":[73.6097,34.33652],"type":"Point"}
}