{
  "type": "Feature",
  "properties": {
    "gn:admin1_code":"3",
    "gn:asciiname":"Newe Banda",
    "gn:country_code":"PK",
    "gn:dem":1805,
    "gn:feature_class":"P",
    "gn:feature_code":"PPL",
    "gn:name":"Newe Banda",
    "gn:population":0,
    "gn:timezone":"Asia/Karachi",
    "iso:country":"PK",
    "name:und_x_variant":[
        "B\u0101nda",
        "Newe Banda"
    ],
    "wof:name":"Newe Banda",
    "wof:placetype":"locality"
},
  "geometry": {"coordinates":[72.58195000000001,35.15165],"type":"Point"}
}