{
  "type": "Feature",
  "properties": {
    "gn:admin1_code":"3",
    "gn:asciiname":"Melai",
    "gn:country_code":"PK",
    "gn:dem":669,
    "gn:feature_class":"P",
    "gn:feature_code":"PPL",
    "gn:name":"Melai",
    "gn:population":0,
    "gn:timezone":"Asia/Karachi",
    "iso:country":"PK",
    "name:und_x_variant":[
        "M\u012bl\u0101i"
    ],
    "wof:name":"Melai",
    "wof:placetype":"locality"
},
  "geometry": {"coordinates":[72.57269000000002,34.40019],"type":"Point"}
}