{
  "type": "Feature",
  "properties": {
    "gn:admin1_code":"3.0",
    "gn:asciiname":"Ghuchharsor Ghari",
    "gn:country_code":"PK",
    "gn:dem":3646,
    "gn:feature_class":"P",
    "gn:feature_code":"PPL",
    "gn:name":"Ghuchharsor Ghari",
    "gn:population":0,
    "gn:timezone":"Asia/Karachi",
    "iso:country":"PK",
    "name:eng_x_preferred":[
        "Ghuchh\u0101rsar Gh\u0101ri"
    ],
    "wof:name":"Ghuchharsor Ghari",
    "wof:placetype":"locality"
},
  "geometry": {"coordinates":[72.11877,35.84102],"type":"Point"}
}