{
  "type": "Feature",
  "properties": {
    "gn:admin1_code":"1.0",
    "gn:asciiname":"Paila Kalle",
    "gn:country_code":"PK",
    "gn:dem":1044,
    "gn:feature_class":"P",
    "gn:feature_code":"PPL",
    "gn:name":"Paila Kalle",
    "gn:population":0,
    "gn:timezone":"Asia/Karachi",
    "iso:country":"PK",
    "name:und_x_variant":[
        "Paila Kili"
    ],
    "wof:name":"Paila Kalle",
    "wof:placetype":"locality"
},
  "geometry": {"coordinates":[70.29144000000001,33.56556],"type":"Point"}
}