{
  "type": "Feature",
  "properties": {
    "gn:admin1_code":"7.0",
    "gn:asciiname":"Somal",
    "gn:country_code":"PK",
    "gn:dem":2593,
    "gn:feature_class":"P",
    "gn:feature_code":"PPL",
    "gn:name":"Somal",
    "gn:population":0,
    "gn:timezone":"Asia/Karachi",
    "iso:country":"PK",
    "name:und_x_variant":[
        "Sumah"
    ],
    "wof:name":"Somal",
    "wof:placetype":"locality"
},
  "geometry": {"coordinates":[73.96025999999998,35.28346],"type":"Point"}
}