{
  "type": "Feature",
  "properties": {
    "gn:admin1_code":"4.0",
    "gn:asciiname":"Buhllay Dahiyanwala",
    "gn:country_code":"PK",
    "gn:dem":212,
    "gn:feature_class":"P",
    "gn:feature_code":"PPL",
    "gn:name":"Buhllay Dahiyanwala",
    "gn:population":0,
    "gn:timezone":"Asia/Karachi",
    "iso:country":"PK",
    "name:und_x_variant":[
        "Bhulle B\u0101ne Sh\u0101h Khurd"
    ],
    "wof:name":"Buhllay Dahiyanwala",
    "wof:placetype":"locality"
},
  "geometry": {"coordinates":[74.29151,31.66125],"type":"Point"}
}