{
  "type": "Feature",
  "properties": {
    "gn:admin1_code":"5",
    "gn:asciiname":"Faizu Wand",
    "gn:country_code":"PK",
    "gn:dem":69,
    "gn:feature_class":"P",
    "gn:feature_code":"PPL",
    "gn:name":"Faizu Wand",
    "gn:population":0,
    "gn:timezone":"Asia/Karachi",
    "iso:country":"PK",
    "name:und_x_variant":[
        "Falzu",
        "Faizu Wand"
    ],
    "wof:name":"Faizu Wand",
    "wof:placetype":"locality"
},
  "geometry": {"coordinates":[69.27555,26.96328],"type":"Point"}
}