{
  "type": "Feature",
  "properties": {
    "gn:admin1_code":"3.0",
    "gn:asciiname":"Bangi Killi",
    "gn:country_code":"PK",
    "gn:dem":481,
    "gn:feature_class":"P",
    "gn:feature_code":"PPL",
    "gn:name":"Bangi Killi",
    "gn:population":0,
    "gn:timezone":"Asia/Karachi",
    "iso:country":"PK",
    "name:und_x_variant":[
        "Bangi Kili"
    ],
    "wof:name":"Bangi Killi",
    "wof:placetype":"locality"
},
  "geometry": {"coordinates":[71.03669000000002,32.93113],"type":"Point"}
}