{
  "type": "Feature",
  "properties": {
    "gn:admin1_code":"3",
    "gn:asciiname":"Mohra Muhammadu",
    "gn:country_code":"PK",
    "gn:dem":544,
    "gn:feature_class":"P",
    "gn:feature_code":"PPL",
    "gn:name":"Mohra Muhammadu",
    "gn:population":0,
    "gn:timezone":"Asia/Karachi",
    "iso:country":"PK",
    "wof:name":"Mohra Muhammadu",
    "wof:placetype":"locality"
},
  "geometry": {"coordinates":[72.96181999999997,34.01143],"type":"Point"}
}