{
  "type": "Feature",
  "properties": {
    "gn:admin1_code":"4.0",
    "gn:asciiname":"Joke Bela",
    "gn:country_code":"PK",
    "gn:dem":217,
    "gn:feature_class":"P",
    "gn:feature_code":"PPL",
    "gn:name":"Joke Bela",
    "gn:population":0,
    "gn:timezone":"Asia/Karachi",
    "iso:country":"PK",
    "name:und_x_variant":[
        "Jeoke Bela"
    ],
    "wof:name":"Joke Bela",
    "wof:placetype":"locality"
},
  "geometry": {"coordinates":[73.87945000000001,32.345],"type":"Point"}
}