{
  "type": "Feature",
  "properties": {
    "gn:admin1_code":"4.0",
    "gn:asciiname":"Dhok Sultan Khel",
    "gn:country_code":"PK",
    "gn:dem":387,
    "gn:feature_class":"P",
    "gn:feature_code":"PPL",
    "gn:name":"Dhok Sultan Khel",
    "gn:population":0,
    "gn:timezone":"Asia/Karachi",
    "iso:country":"PK",
    "wof:name":"Dhok Sultan Khel",
    "wof:placetype":"locality"
},
  "geometry": {"coordinates":[71.82923000000002,32.76769],"type":"Point"}
}