{
  "type": "Feature",
  "properties": {
    "gn:admin1_code":"2.0",
    "gn:asciiname":"Chengai",
    "gn:country_code":"PK",
    "gn:dem":2641,
    "gn:feature_class":"P",
    "gn:feature_code":"PPL",
    "gn:name":"Chengai",
    "gn:population":0,
    "gn:timezone":"Asia/Karachi",
    "iso:country":"PK",
    "wof:name":"Chengai",
    "wof:placetype":"locality"
},
  "geometry": {"coordinates":[67.51781,30.86617],"type":"Point"}
}