{
  "type": "Feature",
  "properties": {
    "gn:admin1_code":"2",
    "gn:asciiname":"Bhoral Khan",
    "gn:country_code":"PK",
    "gn:dem":51,
    "gn:feature_class":"P",
    "gn:feature_code":"PPL",
    "gn:name":"Bhoral Khan",
    "gn:population":0,
    "gn:timezone":"Asia/Karachi",
    "iso:country":"PK",
    "name:und_x_variant":[
        "Goth Bhoral Kh\u0101n"
    ],
    "wof:name":"Bhoral Khan",
    "wof:placetype":"locality"
},
  "geometry": {"coordinates":[67.9301,28.11164],"type":"Point"}
}