{
  "type": "Feature",
  "properties": {
    "gn:admin1_code":"5",
    "gn:asciiname":"Golu Panwhar",
    "gn:country_code":"PK",
    "gn:dem":17,
    "gn:feature_class":"P",
    "gn:feature_code":"PPL",
    "gn:name":"Golu Panwhar",
    "gn:population":0,
    "gn:timezone":"Asia/Karachi",
    "iso:country":"PK",
    "name:und_x_variant":[
        "Goth Panwhar",
        "Golu Pawnhar",
        "Golu Panwhar"
    ],
    "wof:name":"Golu Panwhar",
    "wof:placetype":"locality"
},
  "geometry": {"coordinates":[68.5175,25.23748],"type":"Point"}
}