{
  "type": "Feature",
  "properties": {
    "gn:admin1_code":"05",
    "gn:asciiname":"Tando Haidar",
    "gn:country_code":"PK",
    "gn:dem":23,
    "gn:feature_class":"P",
    "gn:feature_code":"PPL",
    "gn:name":"Tando Haidar",
    "gn:population":0,
    "gn:timezone":"Asia/Karachi",
    "iso:country":"PK",
    "name:eng_x_preferred":[
        "Tando Haidar"
    ],
    "name:und_x_variant":[
        "Tando Haider"
    ],
    "wof:name":"Tando Haidar",
    "wof:placetype":"locality"
},
  "geometry": {"coordinates":[68.42764,25.38668],"type":"Point"}
}