{
  "type": "Feature",
  "properties": {
    "gn:admin1_code":"5.0",
    "gn:asciiname":"Goth Ibrahim Mirwani",
    "gn:country_code":"PK",
    "gn:dem":43,
    "gn:feature_class":"P",
    "gn:feature_code":"PPL",
    "gn:name":"Goth Ibrahim Mirwani",
    "gn:population":0,
    "gn:timezone":"Asia/Karachi",
    "iso:country":"PK",
    "name:und_x_variant":[
        "Goth Ibr\u0101h\u012bm Mirani"
    ],
    "wof:name":"Goth Ibrahim Mirwani",
    "wof:placetype":"locality"
},
  "geometry": {"coordinates":[67.66409,27.32407000000001],"type":"Point"}
}