{
  "type": "Feature",
  "properties": {
    "gn:admin1_code":"01",
    "gn:asciiname":"Mir Khan Khel",
    "gn:country_code":"PK",
    "gn:dem":651,
    "gn:feature_class":"P",
    "gn:feature_code":"PPL",
    "gn:name":"Mir Khan Khel",
    "gn:population":0,
    "gn:timezone":"Asia/Karachi",
    "iso:country":"PK",
    "wof:name":"Mir Khan Khel",
    "wof:placetype":"locality"
},
  "geometry": {"coordinates":[70.32075,33.05292],"type":"Point"}
}