{
  "type": "Feature",
  "properties": {
    "gn:admin1_code":"4",
    "gn:asciiname":"Chak One Hundred Fifty-four Eastern Bar",
    "gn:country_code":"PK",
    "gn:dem":142,
    "gn:feature_class":"P",
    "gn:feature_code":"PPL",
    "gn:name":"Chak One Hundred Fifty-four Eastern Bar",
    "gn:population":0,
    "gn:timezone":"Asia/Karachi",
    "iso:country":"PK",
    "name:und_x_variant":[
        "Kand\u0101nw\u0101la",
        "Kari\u0101nw\u0101la"
    ],
    "wof:name":"Chak One Hundred Fifty-four Eastern Bar",
    "wof:placetype":"locality"
},
  "geometry": {"coordinates":[72.53355999999999,30.20396],"type":"Point"}
}