{
  "type": "Feature",
  "properties": {
    "gn:admin1_code":"4.0",
    "gn:asciiname":"Chak Forty-five",
    "gn:country_code":"PK",
    "gn:dem":210,
    "gn:feature_class":"P",
    "gn:feature_code":"PPL",
    "gn:name":"Chak Forty-five",
    "gn:population":0,
    "gn:timezone":"Asia/Karachi",
    "iso:country":"PK",
    "name:und_x_variant":[
        "Chak Number Forty-Five"
    ],
    "wof:name":"Chak Forty-five",
    "wof:placetype":"locality"
},
  "geometry": {"coordinates":[74.28224,31.73768],"type":"Point"}
}