{
  "type": "Feature",
  "properties": {
    "gn:admin1_code":"3.0",
    "gn:asciiname":"Makhad Khan",
    "gn:country_code":"PK",
    "gn:dem":433,
    "gn:feature_class":"P",
    "gn:feature_code":"PPL",
    "gn:name":"Makhad Khan",
    "gn:population":0,
    "gn:timezone":"Asia/Karachi",
    "iso:country":"PK",
    "name:und_x_variant":[
        "Makhad Kh\u0101d",
        "Makhad Khan"
    ],
    "wof:name":"Makhad Khan",
    "wof:placetype":"locality"
},
  "geometry": {"coordinates":[70.48226,32.94925],"type":"Point"}
}