{
  "type": "Feature",
  "properties": {
    "gn:admin1_code":"4.0",
    "gn:asciiname":"Dhok Lalian",
    "gn:country_code":"PK",
    "gn:dem":570,
    "gn:feature_class":"P",
    "gn:feature_code":"PPL",
    "gn:name":"Dhok Lalian",
    "gn:population":0,
    "gn:timezone":"Asia/Karachi",
    "iso:country":"PK",
    "wof:name":"Dhok Lalian",
    "wof:placetype":"locality"
},
  "geometry": {"coordinates":[73.28746,33.45859],"type":"Point"}
}