{
  "type": "Feature",
  "properties": {
    "gn:admin1_code":"4.0",
    "gn:asciiname":"Muhammad Naharwala",
    "gn:country_code":"PK",
    "gn:dem":116,
    "gn:feature_class":"P",
    "gn:feature_code":"PPL",
    "gn:name":"Muhammad Naharwala",
    "gn:population":0,
    "gn:timezone":"Asia/Karachi",
    "iso:country":"PK",
    "name:eng_x_preferred":[
        "Narharw\u0101la"
    ],
    "wof:name":"Muhammad Naharwala",
    "wof:placetype":"locality"
},
  "geometry": {"coordinates":[70.72530999999999,30.04703],"type":"Point"}
}