{
  "type": "Feature",
  "properties": {
    "gn:admin1_code":"4",
    "gn:asciiname":"Chak Seventy-three A",
    "gn:country_code":"PK",
    "gn:dem":89,
    "gn:feature_class":"P",
    "gn:feature_code":"PPL",
    "gn:name":"Chak Seventy-three A",
    "gn:population":0,
    "gn:timezone":"Asia/Karachi",
    "iso:country":"PK",
    "name:und_x_variant":[
        "Chak Number Seventy-three"
    ],
    "wof:name":"Chak Seventy-three A",
    "wof:placetype":"locality"
},
  "geometry": {"coordinates":[70.80020999999998,28.72366],"type":"Point"}
}