{
  "type": "Feature",
  "properties": {
    "gn:admin1_code":"1.0",
    "gn:asciiname":"Lal Jan Kili",
    "gn:country_code":"PK",
    "gn:dem":1218,
    "gn:feature_class":"P",
    "gn:feature_code":"PPL",
    "gn:name":"Lal Jan Kili",
    "gn:population":0,
    "gn:timezone":"Asia/Karachi",
    "iso:country":"PK",
    "name:und_x_variant":[
        "Haji Lal Jan Kili"
    ],
    "wof:name":"Lal Jan Kili",
    "wof:placetype":"locality"
},
  "geometry": {"coordinates":[70.95001999999999,33.92525],"type":"Point"}
}