{
  "type": "Feature",
  "properties": {
    "gn:admin1_code":"7.0",
    "gn:asciiname":"Ratankush",
    "gn:country_code":"PK",
    "gn:dem":3336,
    "gn:feature_class":"P",
    "gn:feature_code":"PPL",
    "gn:name":"Ratankush",
    "gn:population":0,
    "gn:timezone":"Asia/Karachi",
    "iso:country":"PK",
    "wof:name":"Ratankush",
    "wof:placetype":"locality"
},
  "geometry": {"coordinates":[73.14254,36.3937],"type":"Point"}
}