{
  "type": "Feature",
  "properties": {
    "gn:admin1_code":"2.0",
    "gn:asciiname":"Muhammad Amin Log",
    "gn:country_code":"PK",
    "gn:dem":29,
    "gn:feature_class":"P",
    "gn:feature_code":"PPL",
    "gn:name":"Muhammad Amin Log",
    "gn:population":0,
    "gn:timezone":"Asia/Karachi",
    "iso:country":"PK",
    "name:eng_x_preferred":[
        "Muhammad Amin Log"
    ],
    "wof:name":"Muhammad Amin Log",
    "wof:placetype":"locality"
},
  "geometry": {"coordinates":[62.53878,25.32704],"type":"Point"}
}