{
  "type": "Feature",
  "properties": {
    "gn:admin1_code":"2.0",
    "gn:asciiname":"Goth Haji Kalati",
    "gn:country_code":"PK",
    "gn:dem":22,
    "gn:feature_class":"P",
    "gn:feature_code":"PPL",
    "gn:name":"Goth Haji Kalati",
    "gn:population":0,
    "gn:timezone":"Asia/Karachi",
    "iso:country":"PK",
    "name:eng_x_preferred":[
        "Goth Haji Kalati"
    ],
    "wof:name":"Goth Haji Kalati",
    "wof:placetype":"locality"
},
  "geometry": {"coordinates":[66.72238,25.4254],"type":"Point"}
}