{
  "type": "Feature",
  "properties": {
    "gn:admin1_code":"1.0",
    "gn:asciiname":"Somar Gul Kalle",
    "gn:country_code":"PK",
    "gn:dem":527,
    "gn:feature_class":"P",
    "gn:feature_code":"PPL",
    "gn:name":"Somar Gul Kalle",
    "gn:population":0,
    "gn:timezone":"Asia/Karachi",
    "iso:country":"PK",
    "name:und_x_variant":[
        "Dw\u0101nizan"
    ],
    "wof:name":"Somar Gul Kalle",
    "wof:placetype":"locality"
},
  "geometry": {"coordinates":[71.77361999999999,33.6195],"type":"Point"}
}