{
  "type": "Feature",
  "properties": {
    "gn:admin1_code":"3",
    "gn:asciiname":"Hazara",
    "gn:country_code":"PK",
    "gn:dem":1600,
    "gn:feature_class":"P",
    "gn:feature_code":"PPL",
    "gn:name":"Hazara",
    "gn:population":0,
    "gn:timezone":"Asia/Karachi",
    "iso:country":"PK",
    "name:cat_x_preferred":[
        "Hazara"
    ],
    "name:deu_x_preferred":[
        "Hazara"
    ],
    "name:fas_x_preferred":[
        "\u0647\u0632\u0627\u0631\u0647"
    ],
    "name:mal_x_preferred":[
        "\u0d39\u0d38\u0d3e\u0d30"
    ],
    "wof:name":"Hazara",
    "wof:placetype":"locality"
},
  "geometry": {"coordinates":[72.13064,34.95363],"type":"Point"}
}