{
  "type": "Feature",
  "properties": {
    "gn:admin1_code":"3",
    "gn:asciiname":"Hazara",
    "gn:country_code":"PK",
    "gn:dem":1600,
    "gn:feature_class":"P",
    "gn:feature_code":"PPL",
    "gn:name":"Hazara",
    "gn:population":0,
    "gn:timezone":"Asia/Karachi",
    "iso:country":"PK",
    "wof:name":"Hazara",
    "wof:placetype":"locality"
},
  "geometry": {"coordinates":[72.13064,34.95363],"type":"Point"}
}