{
  "type": "Feature",
  "properties": {
    "gn:admin1_code":"05",
    "gn:asciiname":"Goth Wahi",
    "gn:country_code":"PK",
    "gn:dem":125,
    "gn:feature_class":"P",
    "gn:feature_code":"PPL",
    "gn:name":"Goth Wahi",
    "gn:population":0,
    "gn:timezone":"Asia/Karachi",
    "iso:country":"PK",
    "name:und_x_variant":[
        "Wahi Arab Khan",
        "W\u0101hi",
        "Goth Wahi"
    ],
    "wof:name":"Goth Wahi",
    "wof:placetype":"locality"
},
  "geometry": {"coordinates":[67.88548,25.48511],"type":"Point"}
}