{
  "type": "Feature",
  "properties": {
    "gn:admin1_code":"6",
    "gn:asciiname":"Balsuri",
    "gn:country_code":"PK",
    "gn:dem":876,
    "gn:feature_class":"P",
    "gn:feature_code":"PPL",
    "gn:name":"Balsuri",
    "gn:population":0,
    "gn:timezone":"Asia/Karachi",
    "iso:country":"PK",
    "name:und_x_variant":[
        "B\u0101lseri"
    ],
    "wof:name":"Balsuri",
    "wof:placetype":"locality"
},
  "geometry": {"coordinates":[73.55481,34.45039000000001],"type":"Point"}
}