{
  "type": "Feature",
  "properties": {
    "gn:admin1_code":"3.0",
    "gn:asciiname":"Dhup Banda",
    "gn:country_code":"PK",
    "gn:dem":3104,
    "gn:feature_class":"P",
    "gn:feature_code":"PPL",
    "gn:name":"Dhup Banda",
    "gn:population":0,
    "gn:timezone":"Asia/Karachi",
    "iso:country":"PK",
    "wof:name":"Dhup Banda",
    "wof:placetype":"locality"
},
  "geometry": {"coordinates":[72.83671,35.10643],"type":"Point"}
}