{
  "type": "Feature",
  "properties": {
    "gn:admin1_code":"2.0",
    "gn:asciiname":"Tharrahu",
    "gn:country_code":"PK",
    "gn:dem":1742,
    "gn:feature_class":"P",
    "gn:feature_code":"PPL",
    "gn:name":"Tharrahu",
    "gn:population":0,
    "gn:timezone":"Asia/Karachi",
    "iso:country":"PK",
    "wof:name":"Tharrahu",
    "wof:placetype":"locality"
},
  "geometry": {"coordinates":[66.69435,29.59555],"type":"Point"}
}