{
  "type": "Feature",
  "properties": {
    "gn:admin1_code":"6",
    "gn:asciiname":"Bagnu",
    "gn:country_code":"PK",
    "gn:dem":1969,
    "gn:feature_class":"P",
    "gn:feature_code":"PPL",
    "gn:name":"Bagnu",
    "gn:population":0,
    "gn:timezone":"Asia/Karachi",
    "iso:country":"PK",
    "wof:name":"Bagnu",
    "wof:placetype":"locality"
},
  "geometry": {"coordinates":[73.60196999999999,34.53061],"type":"Point"}
}