{
  "type": "Feature",
  "properties": {
    "gn:admin1_code":"4.0",
    "gn:asciiname":"Bardiana",
    "gn:country_code":"PK",
    "gn:dem":506,
    "gn:feature_class":"P",
    "gn:feature_code":"PPL",
    "gn:name":"Bardiana",
    "gn:population":0,
    "gn:timezone":"Asia/Karachi",
    "iso:country":"PK",
    "wof:name":"Bardiana",
    "wof:placetype":"locality"
},
  "geometry": {"coordinates":[73.20309,33.11094],"type":"Point"}
}