{
  "type": "Feature",
  "properties": {
    "gn:admin1_code":"5",
    "gn:asciiname":"Goth Ahmad",
    "gn:country_code":"PK",
    "gn:dem":10,
    "gn:feature_class":"P",
    "gn:feature_code":"PPL",
    "gn:name":"Goth Ahmad",
    "gn:population":0,
    "gn:timezone":"Asia/Karachi",
    "iso:country":"PK",
    "wof:name":"Goth Ahmad",
    "wof:placetype":"locality"
},
  "geometry": {"coordinates":[69.66370000000001,25.39423],"type":"Point"}
}