{
  "type": "Feature",
  "properties": {
    "gn:admin1_code":"5.0",
    "gn:asciiname":"Ali Muhammad",
    "gn:country_code":"PK",
    "gn:dem":11,
    "gn:feature_class":"P",
    "gn:feature_code":"PPL",
    "gn:name":"Ali Muhammad",
    "gn:population":0,
    "gn:timezone":"Asia/Karachi",
    "iso:country":"PK",
    "name:eng_x_preferred":[
        "Ali Muhammad Khalifa"
    ],
    "wof:name":"Ali Muhammad",
    "wof:placetype":"locality"
},
  "geometry": {"coordinates":[68.27491999999999,24.67688],"type":"Point"}
}