{
  "type": "Feature",
  "properties": {
    "gn:admin1_code":"01",
    "gn:asciiname":"Kuz Sapparai",
    "gn:country_code":"PK",
    "gn:dem":1088,
    "gn:feature_class":"P",
    "gn:feature_code":"PPL",
    "gn:name":"Kuz Sapparai",
    "gn:population":0,
    "gn:timezone":"Asia/Karachi",
    "iso:country":"PK",
    "name:eng_x_preferred":[
        "K\u016bz Tsapparai"
    ],
    "name:und_x_variant":[
        "Kuz Saparai"
    ],
    "wof:name":"Kuz Sapparai",
    "wof:placetype":"locality"
},
  "geometry": {"coordinates":[71.71132,34.6553],"type":"Point"}
}