{
  "type": "Feature",
  "properties": {
    "gn:admin1_code":"1.0",
    "gn:asciiname":"Baloch",
    "gn:country_code":"PK",
    "gn:dem":606,
    "gn:feature_class":"P",
    "gn:feature_code":"PPL",
    "gn:name":"Baloch",
    "gn:population":0,
    "gn:timezone":"Asia/Karachi",
    "iso:country":"PK",
    "wof:name":"Baloch",
    "wof:placetype":"locality"
},
  "geometry": {"coordinates":[70.34191,33.03534000000001],"type":"Point"}
}