{
  "type": "Feature",
  "properties": {
    "gn:admin1_code":"4.0",
    "gn:asciiname":"Dhok Raja Lal Khan",
    "gn:country_code":"PK",
    "gn:dem":415,
    "gn:feature_class":"P",
    "gn:feature_code":"PPL",
    "gn:name":"Dhok Raja Lal Khan",
    "gn:population":0,
    "gn:timezone":"Asia/Karachi",
    "iso:country":"PK",
    "name:und_x_variant":[
        "Pinh\u0101lan di Dhok"
    ],
    "wof:name":"Dhok Raja Lal Khan",
    "wof:placetype":"locality"
},
  "geometry": {"coordinates":[72.28277,33.04883],"type":"Point"}
}