{
  "type": "Feature",
  "properties": {
    "gn:admin1_code":"3",
    "gn:asciiname":"Sawar Maira",
    "gn:country_code":"PK",
    "gn:dem":479,
    "gn:feature_class":"P",
    "gn:feature_code":"PPL",
    "gn:name":"Sawar Maira",
    "gn:population":0,
    "gn:timezone":"Asia/Karachi",
    "iso:country":"PK",
    "name:und_x_variant":[
        "Sow\u0101r Maira"
    ],
    "wof:name":"Sawar Maira",
    "wof:placetype":"locality"
},
  "geometry": {"coordinates":[72.85911,34.20329],"type":"Point"}
}