{
  "type": "Feature",
  "properties": {
    "gn:admin1_code":"3.0",
    "gn:asciiname":"Bandai Kalle",
    "gn:country_code":"PK",
    "gn:dem":319,
    "gn:feature_class":"P",
    "gn:feature_code":"PPL",
    "gn:name":"Bandai Kalle",
    "gn:population":0,
    "gn:timezone":"Asia/Karachi",
    "iso:country":"PK",
    "wof:name":"Bandai Kalle",
    "wof:placetype":"locality"
},
  "geometry": {"coordinates":[72.13420000000001,34.10369],"type":"Point"}
}