{
  "type": "Feature",
  "properties": {
    "gn:admin1_code":"4",
    "gn:asciiname":"Shian Janubi",
    "gn:country_code":"PK",
    "gn:dem":171,
    "gn:feature_class":"P",
    "gn:feature_code":"PPL",
    "gn:name":"Shi\u0101n Janubi",
    "gn:population":0,
    "gn:timezone":"Asia/Karachi",
    "iso:country":"PK",
    "wof:name":"Shian Janubi",
    "wof:placetype":"locality"
},
  "geometry": {"coordinates":[71.34583000000001,31.62083],"type":"Point"}
}