{
  "type": "Feature",
  "properties": {
    "gn:admin1_code":"4",
    "gn:asciiname":"Bharewala",
    "gn:country_code":"PK",
    "gn:dem":195,
    "gn:feature_class":"P",
    "gn:feature_code":"PPL",
    "gn:name":"Bharewala",
    "gn:population":0,
    "gn:timezone":"Asia/Karachi",
    "iso:country":"PK",
    "name:und_x_variant":[
        "Bh\u0101riw\u0101la"
    ],
    "wof:name":"Bharewala",
    "wof:placetype":"locality"
},
  "geometry": {"coordinates":[71.52585999999999,32.24255],"type":"Point"}
}