{
  "type": "Feature",
  "properties": {
    "gn:admin1_code":"3",
    "gn:asciiname":"Bandi Kandao",
    "gn:country_code":"PK",
    "gn:dem":1930,
    "gn:feature_class":"P",
    "gn:feature_code":"PPL",
    "gn:name":"Bandi Kandao",
    "gn:population":0,
    "gn:timezone":"Asia/Karachi",
    "iso:country":"PK",
    "name:eng_x_preferred":[
        "B\u0101ndaikandao"
    ],
    "wof:name":"Bandi Kandao",
    "wof:placetype":"locality"
},
  "geometry": {"coordinates":[71.77875999999998,35.18098],"type":"Point"}
}