{
  "type": "Feature",
  "properties": {
    "gn:admin1_code":"3",
    "gn:asciiname":"Chattu",
    "gn:country_code":"PK",
    "gn:dem":1361,
    "gn:feature_class":"P",
    "gn:feature_code":"PPL",
    "gn:name":"Chattu",
    "gn:population":0,
    "gn:timezone":"Asia/Karachi",
    "iso:country":"PK",
    "name:und_x_variant":[
        "Chuttui"
    ],
    "wof:name":"Chattu",
    "wof:placetype":"locality"
},
  "geometry": {"coordinates":[73.28595,34.52514],"type":"Point"}
}