{
  "type": "Feature",
  "properties": {
    "gn:admin1_code":"5.0",
    "gn:asciiname":"Goth Kashmir Khan Bhangwar",
    "gn:country_code":"PK",
    "gn:dem":73,
    "gn:feature_class":"P",
    "gn:feature_code":"PPL",
    "gn:name":"Goth Kashmir Khan Bhangwar",
    "gn:population":0,
    "gn:timezone":"Asia/Karachi",
    "iso:country":"PK",
    "wof:name":"Goth Kashmir Khan Bhangwar",
    "wof:placetype":"locality"
},
  "geometry": {"coordinates":[69.36163000000001,28.22327],"type":"Point"}
}