{
  "type": "Feature",
  "properties": {
    "gn:admin1_code":"1.0",
    "gn:asciiname":"Lale Kas",
    "gn:country_code":"PK",
    "gn:dem":2030,
    "gn:feature_class":"P",
    "gn:feature_code":"PPL",
    "gn:name":"Lale Kas",
    "gn:population":0,
    "gn:timezone":"Asia/Karachi",
    "iso:country":"PK",
    "name:und_x_variant":[
        "Lolat Kats",
        "Lalai Kas"
    ],
    "wof:name":"Lale Kas",
    "wof:placetype":"locality"
},
  "geometry": {"coordinates":[70.66501,33.81612],"type":"Point"}
}