{
  "type": "Feature",
  "properties": {
    "gn:admin1_code":"2",
    "gn:asciiname":"Bundkhi",
    "gn:country_code":"PK",
    "gn:dem":1766,
    "gn:feature_class":"P",
    "gn:feature_code":"PPL",
    "gn:name":"Bundkhi",
    "gn:population":0,
    "gn:timezone":"Asia/Karachi",
    "iso:country":"PK",
    "name:und_x_variant":[
        "Bandkhr"
    ],
    "wof:name":"Bundkhi",
    "wof:placetype":"locality"
},
  "geometry": {"coordinates":[66.2709,28.55761],"type":"Point"}
}