{
  "type": "Feature",
  "properties": {
    "gn:admin1_code":"05",
    "gn:asciiname":"Goth Pir Watio",
    "gn:country_code":"PK",
    "gn:dem":51,
    "gn:feature_class":"P",
    "gn:feature_code":"PPL",
    "gn:name":"Goth Pir Watio",
    "gn:population":0,
    "gn:timezone":"Asia/Karachi",
    "iso:country":"PK",
    "name:und_x_variant":[
        "P\u012br Watio"
    ],
    "wof:name":"Goth Pir Watio",
    "wof:placetype":"locality"
},
  "geometry": {"coordinates":[68.33535999999999,27.12592],"type":"Point"}
}