{
  "type": "Feature",
  "properties": {
    "gn:admin1_code":"4.0",
    "gn:asciiname":"Garmula Virkan",
    "gn:country_code":"PK",
    "gn:dem":216,
    "gn:feature_class":"P",
    "gn:feature_code":"PPL",
    "gn:name":"Garmula Virkan",
    "gn:population":0,
    "gn:timezone":"Asia/Karachi",
    "iso:country":"PK",
    "name:und_x_variant":[
        "Gharmula",
        "Garm\u016bla",
        "Garmula Virkan"
    ],
    "wof:name":"Garmula Virkan",
    "wof:placetype":"locality"
},
  "geometry": {"coordinates":[73.95439,31.88164],"type":"Point"}
}