{
  "type": "Feature",
  "properties": {
    "gn:admin1_code":"2",
    "gn:asciiname":"Ghuzgai",
    "gn:country_code":"PK",
    "gn:dem":2570,
    "gn:feature_class":"P",
    "gn:feature_code":"PPL",
    "gn:name":"Ghuzgai",
    "gn:population":0,
    "gn:timezone":"Asia/Karachi",
    "iso:country":"PK",
    "wof:name":"Ghuzgai",
    "wof:placetype":"locality"
},
  "geometry": {"coordinates":[67.89161999999999,31.13355],"type":"Point"}
}