{
  "type": "Feature",
  "properties": {
    "gn:admin1_code":"03",
    "gn:asciiname":"Turlandai",
    "gn:country_code":"PK",
    "gn:dem":297,
    "gn:feature_class":"P",
    "gn:feature_code":"PPL",
    "gn:name":"Turlandai",
    "gn:population":0,
    "gn:timezone":"Asia/Karachi",
    "iso:country":"PK",
    "name:eng_x_preferred":[
        "Tulandi"
    ],
    "name:und_x_variant":[
        "Tulabandi",
        "Turlandai"
    ],
    "wof:name":"Turlandai",
    "wof:placetype":"locality"
},
  "geometry": {"coordinates":[71.81888000000002,34.08454],"type":"Point"}
}