{
  "type": "Feature",
  "properties": {
    "gn:admin1_code":"01",
    "gn:asciiname":"Shingar",
    "gn:country_code":"PK",
    "gn:dem":1082,
    "gn:feature_class":"P",
    "gn:feature_code":"PPL",
    "gn:name":"Shingar",
    "gn:population":0,
    "gn:timezone":"Asia/Karachi",
    "iso:country":"PK",
    "name:und_x_variant":[
        "Shanger"
    ],
    "wof:name":"Shingar",
    "wof:placetype":"locality"
},
  "geometry": {"coordinates":[71.32765999999999,34.68335],"type":"Point"}
}