{
  "type": "Feature",
  "properties": {
    "gn:admin1_code":"4",
    "gn:asciiname":"Sherdastwala",
    "gn:country_code":"PK",
    "gn:dem":418,
    "gn:feature_class":"P",
    "gn:feature_code":"PPL",
    "gn:name":"Sherdastwala",
    "gn:population":0,
    "gn:timezone":"Asia/Karachi",
    "iso:country":"PK",
    "wof:name":"Sherdastwala",
    "wof:placetype":"locality"
},
  "geometry": {"coordinates":[72.10623000000002,32.95024],"type":"Point"}
}