{
  "type": "Feature",
  "properties": {
    "gn:admin1_code":"4",
    "gn:asciiname":"Tikka Amrik Singh",
    "gn:country_code":"PK",
    "gn:dem":123,
    "gn:feature_class":"P",
    "gn:feature_code":"PPL",
    "gn:name":"Tikka Amrik Singh",
    "gn:population":0,
    "gn:timezone":"Asia/Karachi",
    "iso:country":"PK",
    "wof:name":"Tikka Amrik Singh",
    "wof:placetype":"locality"
},
  "geometry": {"coordinates":[71.86667,29.93333],"type":"Point"}
}