{
  "type": "Feature",
  "properties": {
    "gn:admin1_code":"2.0",
    "gn:asciiname":"Kili Malik Khuda Bakhsh",
    "gn:country_code":"PK",
    "gn:dem":716,
    "gn:feature_class":"P",
    "gn:feature_code":"PPL",
    "gn:name":"Kili Malik Khuda Bakhsh",
    "gn:population":0,
    "gn:timezone":"Asia/Karachi",
    "iso:country":"PK",
    "wof:name":"Kili Malik Khuda Bakhsh",
    "wof:placetype":"locality"
},
  "geometry": {"coordinates":[61.83746,28.63224],"type":"Point"}
}