{
  "type": "Feature",
  "properties": {
    "gn:admin1_code":"4",
    "gn:asciiname":"Basti Bhangianwali",
    "gn:country_code":"PK",
    "gn:dem":123,
    "gn:feature_class":"P",
    "gn:feature_code":"PPL",
    "gn:name":"Basti Bhangianwali",
    "gn:population":0,
    "gn:timezone":"Asia/Karachi",
    "iso:country":"PK",
    "name:und_x_variant":[
        "Basti Bhang\u012b\u0101w\u0101li"
    ],
    "wof:name":"Basti Bhangianwali",
    "wof:placetype":"locality"
},
  "geometry": {"coordinates":[71.8999,29.55271],"type":"Point"}
}