{
  "type": "Feature",
  "properties": {
    "gn:admin1_code":"2",
    "gn:asciiname":"Khushdil Khan",
    "gn:country_code":"PK",
    "gn:dem":1565,
    "gn:feature_class":"P",
    "gn:feature_code":"PPL",
    "gn:name":"Khushdil Khan",
    "gn:population":0,
    "gn:timezone":"Asia/Karachi",
    "iso:country":"PK",
    "name:eng_x_preferred":[
        "Khushdil Khan"
    ],
    "name:und_x_variant":[
        "Khushdil Kh\u0101n Qila"
    ],
    "wof:name":"Khushdil Khan",
    "wof:placetype":"locality"
},
  "geometry": {"coordinates":[67.11449,30.69707],"type":"Point"}
}