{
  "type": "Feature",
  "properties": {
    "gn:admin1_code":"1.0",
    "gn:asciiname":"Bang Colony",
    "gn:country_code":"PK",
    "gn:dem":283,
    "gn:feature_class":"P",
    "gn:feature_code":"PPL",
    "gn:name":"Bang Colony",
    "gn:population":0,
    "gn:timezone":"Asia/Karachi",
    "iso:country":"PK",
    "wof:name":"Bang Colony",
    "wof:placetype":"locality"
},
  "geometry": {"coordinates":[73.65666999999998,33.11741],"type":"Point"}
}