{
  "type": "Feature",
  "properties": {
    "gn:admin1_code":"2.0",
    "gn:asciiname":"Kaka Basti",
    "gn:country_code":"PK",
    "gn:dem":1022,
    "gn:feature_class":"P",
    "gn:feature_code":"PPL",
    "gn:name":"Kaka Basti",
    "gn:population":0,
    "gn:timezone":"Asia/Karachi",
    "iso:country":"PK",
    "wof:name":"Kaka Basti",
    "wof:placetype":"locality"
},
  "geometry": {"coordinates":[69.34965,29.7942],"type":"Point"}
}