{
  "type": "Feature",
  "properties": {
    "gn:admin1_code":"2.0",
    "gn:asciiname":"Goth Umar",
    "gn:country_code":"PK",
    "gn:dem":280,
    "gn:feature_class":"P",
    "gn:feature_code":"PPL",
    "gn:name":"Goth Umar",
    "gn:population":0,
    "gn:timezone":"Asia/Karachi",
    "iso:country":"PK",
    "wof:name":"Goth Umar",
    "wof:placetype":"locality"
},
  "geometry": {"coordinates":[67.38334999999999,25.83563],"type":"Point"}
}