{
  "type": "Feature",
  "properties": {
    "gn:admin1_code":"3.0",
    "gn:asciiname":"Behram Khel",
    "gn:country_code":"PK",
    "gn:dem":342,
    "gn:feature_class":"P",
    "gn:feature_code":"PPL",
    "gn:name":"Behram Khel",
    "gn:population":0,
    "gn:timezone":"Asia/Karachi",
    "iso:country":"PK",
    "name:und_x_variant":[
        "Bohr\u0101m Khel",
        "Behram Khel"
    ],
    "wof:name":"Behram Khel",
    "wof:placetype":"locality"
},
  "geometry": {"coordinates":[70.5774,32.57038],"type":"Point"}
}