{
  "type": "Feature",
  "properties": {
    "gn:admin1_code":"3.0",
    "gn:asciiname":"Kandao Banda",
    "gn:country_code":"PK",
    "gn:dem":2632,
    "gn:feature_class":"P",
    "gn:feature_code":"PPL",
    "gn:name":"Kandao Banda",
    "gn:population":0,
    "gn:timezone":"Asia/Karachi",
    "iso:country":"PK",
    "wof:name":"Kandao Banda",
    "wof:placetype":"locality"
},
  "geometry": {"coordinates":[72.70083000000002,35.04062],"type":"Point"}
}