{
  "type": "Feature",
  "properties": {
    "gn:admin1_code":"4.0",
    "gn:asciiname":"Sobhagiwali Dhok",
    "gn:country_code":"PK",
    "gn:dem":269,
    "gn:feature_class":"P",
    "gn:feature_code":"PPL",
    "gn:name":"Sobh\u0101giw\u0101li Dhok",
    "gn:population":0,
    "gn:timezone":"Asia/Karachi",
    "iso:country":"PK",
    "wof:name":"Sobhagiwali Dhok",
    "wof:placetype":"locality"
},
  "geometry": {"coordinates":[71.87778,33.07],"type":"Point"}
}