{
  "type": "Feature",
  "properties": {
    "gn:admin1_code":"3",
    "gn:asciiname":"Pursh Bando",
    "gn:country_code":"PK",
    "gn:dem":755,
    "gn:feature_class":"P",
    "gn:feature_code":"PPL",
    "gn:name":"Pursh Bando",
    "gn:population":0,
    "gn:timezone":"Asia/Karachi",
    "iso:country":"PK",
    "name:und_x_variant":[
        "Pursha B\u0101nda"
    ],
    "wof:name":"Pursh Bando",
    "wof:placetype":"locality"
},
  "geometry": {"coordinates":[71.2163,32.39064],"type":"Point"}
}