{
  "type": "Feature",
  "properties": {
    "gn:admin1_code":"3.0",
    "gn:asciiname":"Bahadar Koruna",
    "gn:country_code":"PK",
    "gn:dem":378,
    "gn:feature_class":"P",
    "gn:feature_code":"PPL",
    "gn:name":"Bahadar Koruna",
    "gn:population":0,
    "gn:timezone":"Asia/Karachi",
    "iso:country":"PK",
    "wof:name":"Bahadar Koruna",
    "wof:placetype":"locality"
},
  "geometry": {"coordinates":[71.85590999999999,34.34734],"type":"Point"}
}