{
  "type": "Feature",
  "properties": {
    "gn:admin1_code":"5.0",
    "gn:asciiname":"Goth Khal",
    "gn:country_code":"PK",
    "gn:dem":51,
    "gn:feature_class":"P",
    "gn:feature_code":"PPL",
    "gn:name":"Goth Khal",
    "gn:population":0,
    "gn:timezone":"Asia/Karachi",
    "iso:country":"PK",
    "name:und_x_variant":[
        "Q\u0101im Kh\u0101n"
    ],
    "wof:name":"Goth Khal",
    "wof:placetype":"locality"
},
  "geometry": {"coordinates":[67.937,27.60435],"type":"Point"}
}