{
  "type": "Feature",
  "properties": {
    "gn:admin1_code":"4.0",
    "gn:asciiname":"Bhulo Awan",
    "gn:country_code":"PK",
    "gn:dem":183,
    "gn:feature_class":"P",
    "gn:feature_code":"PPL",
    "gn:name":"Bhulo Awan",
    "gn:population":0,
    "gn:timezone":"Asia/Karachi",
    "iso:country":"PK",
    "name:und_x_variant":[
        "Aw\u0101n Bholu"
    ],
    "wof:name":"Bhulo Awan",
    "wof:placetype":"locality"
},
  "geometry": {"coordinates":[73.48940999999998,31.0703],"type":"Point"}
}