{
  "type": "Feature",
  "properties": {
    "gn:admin1_code":"4.0",
    "gn:asciiname":"Khalidabad",
    "gn:country_code":"PK",
    "gn:dem":229,
    "gn:feature_class":"P",
    "gn:feature_code":"PPL",
    "gn:name":"Khalidabad",
    "gn:population":0,
    "gn:timezone":"Asia/Karachi",
    "iso:country":"PK",
    "wof:name":"Khalidabad",
    "wof:placetype":"locality"
},
  "geometry": {"coordinates":[74.04648,32.55659],"type":"Point"}
}