{
  "type": "Feature",
  "properties": {
    "gn:admin1_code":"04",
    "gn:asciiname":"Phadriala",
    "gn:country_code":"PK",
    "gn:dem":464,
    "gn:feature_class":"P",
    "gn:feature_code":"PPL",
    "gn:name":"Phadriala",
    "gn:population":0,
    "gn:timezone":"Asia/Karachi",
    "iso:country":"PK",
    "name:und_x_variant":[
        "Padhr\u0101la"
    ],
    "wof:name":"Phadriala",
    "wof:placetype":"locality"
},
  "geometry": {"coordinates":[73.16079999999999,32.85038],"type":"Point"}
}