{
  "type": "Feature",
  "properties": {
    "gn:admin1_code":"3.0",
    "gn:asciiname":"Karghano Kalle",
    "gn:country_code":"PK",
    "gn:dem":431,
    "gn:feature_class":"P",
    "gn:feature_code":"PPL",
    "gn:name":"Karghano Kalle",
    "gn:population":0,
    "gn:timezone":"Asia/Karachi",
    "iso:country":"PK",
    "name:eng_x_preferred":[
        "Mair\u0101"
    ],
    "wof:name":"Karghano Kalle",
    "wof:placetype":"locality"
},
  "geometry": {"coordinates":[71.62541999999998,34.37745],"type":"Point"}
}