{
  "type": "Feature",
  "properties": {
    "gn:admin1_code":"3",
    "gn:asciiname":"Nind",
    "gn:country_code":"PK",
    "gn:dem":2013,
    "gn:feature_class":"P",
    "gn:feature_code":"PPL",
    "gn:name":"N\u012bnd",
    "gn:population":0,
    "gn:timezone":"Asia/Karachi",
    "iso:country":"PK",
    "wof:name":"Nind",
    "wof:placetype":"locality"
},
  "geometry": {"coordinates":[72.62056,35.22583],"type":"Point"}
}