{
  "type": "Feature",
  "properties": {
    "gn:admin1_code":"5",
    "gn:asciiname":"Bakhu",
    "gn:country_code":"PK",
    "gn:dem":52,
    "gn:feature_class":"P",
    "gn:feature_code":"PPL",
    "gn:name":"Bakhu",
    "gn:population":0,
    "gn:timezone":"Asia/Karachi",
    "iso:country":"PK",
    "name:und_x_variant":[
        "Bhakhu",
        "Bhakhon",
        "Bakhu"
    ],
    "wof:name":"Bakhu",
    "wof:placetype":"locality"
},
  "geometry": {"coordinates":[69.76531,24.9258],"type":"Point"}
}