{
  "type": "Feature",
  "properties": {
    "gn:admin1_code":"4.0",
    "gn:asciiname":"Dhok Malikwali",
    "gn:country_code":"PK",
    "gn:dem":858,
    "gn:feature_class":"P",
    "gn:feature_code":"PPL",
    "gn:name":"Dhok Malikwali",
    "gn:population":0,
    "gn:timezone":"Asia/Karachi",
    "iso:country":"PK",
    "wof:name":"Dhok Malikwali",
    "wof:placetype":"locality"
},
  "geometry": {"coordinates":[72.94195999999999,32.76022],"type":"Point"}
}