{
  "type": "Feature",
  "properties": {
    "gn:admin1_code":"04",
    "gn:asciiname":"Thatha Jahid Hasanwala",
    "gn:country_code":"PK",
    "gn:dem":199,
    "gn:feature_class":"P",
    "gn:feature_code":"PPL",
    "gn:name":"Thatha Jahid Hasanwala",
    "gn:population":0,
    "gn:timezone":"Asia/Karachi",
    "iso:country":"PK",
    "name:und_x_variant":[
        "Thatta Jahad Hasanwala",
        "Thatta J\u0101hid Hasanw\u0101la",
        "Thatha Jahid Hasanwala"
    ],
    "wof:name":"Thatha Jahid Hasanwala",
    "wof:placetype":"locality"
},
  "geometry": {"coordinates":[73.52155,32.07397],"type":"Point"}
}