{
  "type": "Feature",
  "properties": {
    "gn:admin1_code":"04",
    "gn:asciiname":"Thoa",
    "gn:country_code":"PK",
    "gn:dem":311,
    "gn:feature_class":"P",
    "gn:feature_code":"PPL",
    "gn:name":"Thoa",
    "gn:population":0,
    "gn:timezone":"Asia/Karachi",
    "iso:country":"PK",
    "name:und_x_variant":[
        "Thoha",
        "Thoa"
    ],
    "wof:name":"Thoa",
    "wof:placetype":"locality"
},
  "geometry": {"coordinates":[72.18281999999998,33.20655],"type":"Point"}
}