{
  "type": "Feature",
  "properties": {
    "gn:admin1_code":"1.0",
    "gn:asciiname":"Burjo",
    "gn:country_code":"PK",
    "gn:dem":1061,
    "gn:feature_class":"P",
    "gn:feature_code":"PPL",
    "gn:name":"Burjo",
    "gn:population":0,
    "gn:timezone":"Asia/Karachi",
    "iso:country":"PK",
    "wof:name":"Burjo",
    "wof:placetype":"locality"
},
  "geometry": {"coordinates":[70.47355,33.51535],"type":"Point"}
}