{
  "type": "Feature",
  "properties": {
    "gn:admin1_code":"1.0",
    "gn:asciiname":"Bobak",
    "gn:country_code":"PK",
    "gn:dem":1165,
    "gn:feature_class":"P",
    "gn:feature_code":"PPL",
    "gn:name":"Bobak",
    "gn:population":0,
    "gn:timezone":"Asia/Karachi",
    "iso:country":"PK",
    "wof:name":"Bobak",
    "wof:placetype":"locality"
},
  "geometry": {"coordinates":[71.15846999999999,34.55246],"type":"Point"}
}