{
  "type": "Feature",
  "properties": {
    "gn:admin1_code":"3.0",
    "gn:asciiname":"Barkale",
    "gn:country_code":"PK",
    "gn:dem":1859,
    "gn:feature_class":"P",
    "gn:feature_code":"PPL",
    "gn:name":"Barkale",
    "gn:population":0,
    "gn:timezone":"Asia/Karachi",
    "iso:country":"PK",
    "name:fas_x_preferred":[
        "\u06af\u0648\u0627\u0644\u062f\u06cc\u06cc"
    ],
    "name:und_x_variant":[
        "Gwaldai",
        "Barkale"
    ],
    "name:urd_x_preferred":[
        "\u06af\u0648\u0627\u0644\u062f\u0626\u06cc"
    ],
    "wof:name":"Barkale",
    "wof:placetype":"locality"
},
  "geometry": {"coordinates":[72.05306,35.42545],"type":"Point"}
}