{
  "type": "Feature",
  "properties": {
    "gn:admin1_code":"3.0",
    "gn:asciiname":"Aluli",
    "gn:country_code":"PK",
    "gn:dem":549,
    "gn:feature_class":"P",
    "gn:feature_code":"PPL",
    "gn:name":"Aluli",
    "gn:population":0,
    "gn:timezone":"Asia/Karachi",
    "iso:country":"PK",
    "name:und_x_variant":[
        "Aloli",
        "Aluli"
    ],
    "wof:name":"Aluli",
    "wof:placetype":"locality"
},
  "geometry": {"coordinates":[72.97463,34.08453],"type":"Point"}
}