{
  "type": "Feature",
  "properties": {
    "gn:admin1_code":"4.0",
    "gn:asciiname":"Chak Five Hundred Sixty-nine",
    "gn:country_code":"PK",
    "gn:dem":191,
    "gn:feature_class":"P",
    "gn:feature_code":"PPL",
    "gn:name":"Chak Five Hundred Sixty-nine",
    "gn:population":0,
    "gn:timezone":"Asia/Karachi",
    "iso:country":"PK",
    "name:und_x_variant":[
        "Bah\u0101dur Kh\u0101n"
    ],
    "wof:name":"Chak Five Hundred Sixty-nine",
    "wof:placetype":"locality"
},
  "geometry": {"coordinates":[73.55801,31.35452],"type":"Point"}
}