{
  "type": "Feature",
  "properties": {
    "gn:admin1_code":"3",
    "gn:asciiname":"Bakand",
    "gn:country_code":"PK",
    "gn:dem":796,
    "gn:feature_class":"P",
    "gn:feature_code":"PPL",
    "gn:name":"Bakand",
    "gn:population":0,
    "gn:timezone":"Asia/Karachi",
    "iso:country":"PK",
    "name:eng_x_preferred":[
        "B\u0101kandal"
    ],
    "wof:name":"Bakand",
    "wof:placetype":"locality"
},
  "geometry": {"coordinates":[72.00702,34.69148],"type":"Point"}
}