{
  "type": "Feature",
  "properties": {
    "gn:admin1_code":"03",
    "gn:asciiname":"Mastuj",
    "gn:country_code":"PK",
    "gn:dem":2316,
    "gn:feature_class":"P",
    "gn:feature_code":"PPL",
    "gn:name":"Mastuj",
    "gn:population":0,
    "gn:timezone":"Asia/Karachi",
    "iso:country":"PK",
    "name:urd_x_preferred":[
        "\u0645\u064e\u0633\u0652\u062a\u064f\u0648\u062c"
    ],
    "wof:name":"Mastuj",
    "wof:placetype":"locality"
},
  "geometry": {"coordinates":[72.51942,36.28356],"type":"Point"}
}