{
  "type": "Feature",
  "properties": {
    "gn:admin1_code":"03",
    "gn:asciiname":"Mastuj",
    "gn:country_code":"PK",
    "gn:dem":2316,
    "gn:feature_class":"P",
    "gn:feature_code":"PPL",
    "gn:name":"Mastuj",
    "gn:population":0,
    "gn:timezone":"Asia/Karachi",
    "iso:country":"PK",
    "name:cat_x_preferred":[
        "Mastuj"
    ],
    "name:fas_x_preferred":[
        "\u062a\u062d\u0635\u06cc\u0644 \u0645\u0633\u062a\u0648\u062c"
    ],
    "name:hin_x_preferred":[
        "\u092e\u0938\u0924\u0942\u091c"
    ],
    "name:urd_x_preferred":[
        "\u0645\u064e\u0633\u0652\u062a\u064f\u0648\u062c"
    ],
    "name:urd_x_variant":[
        "\u0645\u0633\u062a\u0648\u062c"
    ],
    "wof:name":"Mastuj",
    "wof:placetype":"locality"
},
  "geometry": {"coordinates":[72.51942,36.28356],"type":"Point"}
}