{
  "type": "Feature",
  "properties": {
    "gn:admin1_code":"4",
    "gn:asciiname":"Gulluwali",
    "gn:country_code":"PK",
    "gn:dem":91,
    "gn:feature_class":"P",
    "gn:feature_code":"PPL",
    "gn:name":"Gulluwali",
    "gn:population":0,
    "gn:timezone":"Asia/Karachi",
    "iso:country":"PK",
    "wof:name":"Gulluwali",
    "wof:placetype":"locality"
},
  "geometry": {"coordinates":[70.39190000000001,29.07413],"type":"Point"}
}