{
  "type": "Feature",
  "properties": {
    "gn:admin1_code":"2.0",
    "gn:asciiname":"Dumar",
    "gn:country_code":"PK",
    "gn:dem":1607,
    "gn:feature_class":"P",
    "gn:feature_code":"PPL",
    "gn:name":"Dumar",
    "gn:population":0,
    "gn:timezone":"Asia/Karachi",
    "iso:country":"PK",
    "wof:name":"Dumar",
    "wof:placetype":"locality"
},
  "geometry": {"coordinates":[66.77168,29.91557],"type":"Point"}
}