{
  "type": "Feature",
  "properties": {
    "gn:admin1_code":"5",
    "gn:asciiname":"Goth Wasaio Lakho",
    "gn:country_code":"PK",
    "gn:dem":28,
    "gn:feature_class":"P",
    "gn:feature_code":"PPL",
    "gn:name":"Goth Wasaio Lakho",
    "gn:population":0,
    "gn:timezone":"Asia/Karachi",
    "iso:country":"PK",
    "name:eng_x_preferred":[
        "Goth Was\u0101yo L\u0101kho"
    ],
    "wof:name":"Goth Wasaio Lakho",
    "wof:placetype":"locality"
},
  "geometry": {"coordinates":[68.50192,25.84268],"type":"Point"}
}