{
  "type": "Feature",
  "properties": {
    "gn:admin1_code":"5",
    "gn:asciiname":"Goth Khairo Gopang",
    "gn:country_code":"PK",
    "gn:dem":58,
    "gn:feature_class":"P",
    "gn:feature_code":"PPL",
    "gn:name":"Goth Khairo Gopang",
    "gn:population":0,
    "gn:timezone":"Asia/Karachi",
    "iso:country":"PK",
    "name:und_x_variant":[
        "Khairo Gop\u0101ng"
    ],
    "wof:name":"Goth Khairo Gopang",
    "wof:placetype":"locality"
},
  "geometry": {"coordinates":[67.42404999999999,26.71882],"type":"Point"}
}