{
  "type": "Feature",
  "properties": {
    "gn:admin1_code":"2.0",
    "gn:asciiname":"Band Kili",
    "gn:country_code":"PK",
    "gn:dem":2071,
    "gn:feature_class":"P",
    "gn:feature_code":"PPL",
    "gn:name":"Band Kili",
    "gn:population":0,
    "gn:timezone":"Asia/Karachi",
    "iso:country":"PK",
    "name:und_x_variant":[
        "Khw\u0101zhe",
        "Band Kili"
    ],
    "wof:name":"Band Kili",
    "wof:placetype":"locality"
},
  "geometry": {"coordinates":[69.69625000000001,31.61096],"type":"Point"}
}