{
  "type": "Feature",
  "properties": {
    "gn:admin1_code":"4",
    "gn:asciiname":"Katuwala Khu",
    "gn:country_code":"PK",
    "gn:dem":160,
    "gn:feature_class":"P",
    "gn:feature_code":"PPL",
    "gn:name":"Katuw\u0101la Khu",
    "gn:population":0,
    "gn:timezone":"Asia/Karachi",
    "iso:country":"PK",
    "wof:name":"Katuwala Khu",
    "wof:placetype":"locality"
},
  "geometry": {"coordinates":[71.01666999999998,31.33889000000001],"type":"Point"}
}