{
  "type": "Feature",
  "properties": {
    "gn:admin1_code":"3",
    "gn:asciiname":"Adrer",
    "gn:country_code":"PK",
    "gn:dem":2415,
    "gn:feature_class":"P",
    "gn:feature_code":"PPL",
    "gn:name":"Adrer",
    "gn:population":0,
    "gn:timezone":"Asia/Karachi",
    "iso:country":"PK",
    "wof:name":"Adrer",
    "wof:placetype":"locality"
},
  "geometry": {"coordinates":[72.61778000000002,35.25806],"type":"Point"}
}