{
  "type": "Feature",
  "properties": {
    "gn:admin1_code":"3",
    "gn:asciiname":"Kolanda Banda",
    "gn:country_code":"PK",
    "gn:dem":1782,
    "gn:feature_class":"P",
    "gn:feature_code":"PPL",
    "gn:name":"Kolanda Banda",
    "gn:population":0,
    "gn:timezone":"Asia/Karachi",
    "iso:country":"PK",
    "wof:name":"Kolanda Banda",
    "wof:placetype":"locality"
},
  "geometry": {"coordinates":[72.18885,34.91186],"type":"Point"}
}