{
  "type": "Feature",
  "properties": {
    "gn:admin1_code":"2.0",
    "gn:asciiname":"Malik Mir Dost Gis",
    "gn:country_code":"PK",
    "gn:dem":1408,
    "gn:feature_class":"P",
    "gn:feature_code":"PPL",
    "gn:name":"Malik Mir Dost Gis",
    "gn:population":0,
    "gn:timezone":"Asia/Karachi",
    "iso:country":"PK",
    "wof:name":"Malik Mir Dost Gis",
    "wof:placetype":"locality"
},
  "geometry": {"coordinates":[63.7682,29.26818],"type":"Point"}
}