{
  "type": "Feature",
  "properties": {
    "gn:admin1_code":"1.0",
    "gn:asciiname":"Had",
    "gn:country_code":"PK",
    "gn:dem":648,
    "gn:feature_class":"P",
    "gn:feature_code":"PPL",
    "gn:name":"Had",
    "gn:population":0,
    "gn:timezone":"Asia/Karachi",
    "iso:country":"PK",
    "name:ceb_x_preferred":[
        "Had"
    ],
    "name:ces_x_preferred":[
        "Had"
    ],
    "name:deu_x_preferred":[
        "Had"
    ],
    "name:hrv_x_preferred":[
        "Had"
    ],
    "name:slk_x_preferred":[
        "Had"
    ],
    "name:slv_x_preferred":[
        "Had"
    ],
    "wof:name":"Had",
    "wof:placetype":"locality"
},
  "geometry": {"coordinates":[71.44502,34.57294],"type":"Point"}
}