{
  "type": "Feature",
  "properties": {
    "gn:admin1_code":"5",
    "gn:asciiname":"Sinkhwar",
    "gn:country_code":"PK",
    "gn:dem":50,
    "gn:feature_class":"P",
    "gn:feature_code":"PPL",
    "gn:name":"Sinkhwar",
    "gn:population":0,
    "gn:timezone":"Asia/Karachi",
    "iso:country":"PK",
    "name:und_x_variant":[
        "Sinkhw\u0101ri"
    ],
    "wof:name":"Sinkhwar",
    "wof:placetype":"locality"
},
  "geometry": {"coordinates":[69.06985,26.93839],"type":"Point"}
}