{
  "type": "Feature",
  "properties": {
    "gn:admin1_code":"4.0",
    "gn:asciiname":"Dhok Bangial",
    "gn:country_code":"PK",
    "gn:dem":539,
    "gn:feature_class":"P",
    "gn:feature_code":"PPL",
    "gn:name":"Dhok Bangial",
    "gn:population":0,
    "gn:timezone":"Asia/Karachi",
    "iso:country":"PK",
    "wof:name":"Dhok Bangial",
    "wof:placetype":"locality"
},
  "geometry": {"coordinates":[73.24675000000001,33.33219],"type":"Point"}
}