{
  "type": "Feature",
  "properties": {
    "gn:admin1_code":"3.0",
    "gn:asciiname":"Sor Mor",
    "gn:country_code":"PK",
    "gn:dem":687,
    "gn:feature_class":"P",
    "gn:feature_code":"PPL",
    "gn:name":"Sor Mor",
    "gn:population":0,
    "gn:timezone":"Asia/Karachi",
    "iso:country":"PK",
    "wof:name":"Sor Mor",
    "wof:placetype":"locality"
},
  "geometry": {"coordinates":[71.78064999999999,34.63155],"type":"Point"}
}