{
  "type": "Feature",
  "properties": {
    "gn:admin1_code":"4",
    "gn:asciiname":"Rahim Hussain Arain",
    "gn:country_code":"PK",
    "gn:dem":99,
    "gn:feature_class":"P",
    "gn:feature_code":"PPL",
    "gn:name":"Rahim Hussain Arain",
    "gn:population":0,
    "gn:timezone":"Asia/Karachi",
    "iso:country":"PK",
    "name:und_x_variant":[
        "Jay\u0101hw\u0101la",
        "Jayahw\u0101la",
        "Rahim Hussain Arain"
    ],
    "wof:name":"Rahim Hussain Arain",
    "wof:placetype":"locality"
},
  "geometry": {"coordinates":[70.47485,29.27181],"type":"Point"}
}