{
  "type": "Feature",
  "properties": {
    "gn:admin1_code":"4",
    "gn:asciiname":"Basti Kandur",
    "gn:country_code":"PK",
    "gn:dem":134,
    "gn:feature_class":"P",
    "gn:feature_code":"PPL",
    "gn:name":"Basti Kandur",
    "gn:population":0,
    "gn:timezone":"Asia/Karachi",
    "iso:country":"PK",
    "name:und_x_variant":[
        "Kand\u016brw\u0101la"
    ],
    "wof:name":"Basti Kandur",
    "wof:placetype":"locality"
},
  "geometry": {"coordinates":[72.22776999999998,30.02296],"type":"Point"}
}