{
  "type": "Feature",
  "properties": {
    "gn:admin1_code":"2.0",
    "gn:asciiname":"Kili Umar Shah Dostin",
    "gn:country_code":"PK",
    "gn:dem":884,
    "gn:feature_class":"P",
    "gn:feature_code":"PPL",
    "gn:name":"Kili Umar Shah Dostin",
    "gn:population":0,
    "gn:timezone":"Asia/Karachi",
    "iso:country":"PK",
    "wof:name":"Kili Umar Shah Dostin",
    "wof:placetype":"locality"
},
  "geometry": {"coordinates":[65.437,29.52661],"type":"Point"}
}