{
  "type": "Feature",
  "properties": {
    "gn:admin1_code":"04",
    "gn:asciiname":"Sathuwali Jhok",
    "gn:country_code":"PK",
    "gn:dem":129,
    "gn:feature_class":"P",
    "gn:feature_code":"PPL",
    "gn:name":"Sathuwali Jhok",
    "gn:population":0,
    "gn:timezone":"Asia/Karachi",
    "iso:country":"PK",
    "name:und_x_variant":[
        "Satthu",
        "Sathu",
        "Sathuwali Jhok"
    ],
    "wof:name":"Sathuwali Jhok",
    "wof:placetype":"locality"
},
  "geometry": {"coordinates":[72.18895999999999,29.62152],"type":"Point"}
}