{
  "type": "Feature",
  "properties": {
    "gn:admin1_code":"2.0",
    "gn:asciiname":"Kili Umar",
    "gn:country_code":"PK",
    "gn:dem":1723,
    "gn:feature_class":"P",
    "gn:feature_code":"PPL",
    "gn:name":"Kili Umar",
    "gn:population":0,
    "gn:timezone":"Asia/Karachi",
    "iso:country":"PK",
    "wof:name":"Kili Umar",
    "wof:placetype":"locality"
},
  "geometry": {"coordinates":[66.40021999999999,28.24031],"type":"Point"}
}