{
  "type": "Feature",
  "properties": {
    "gn:admin1_code":"04",
    "gn:asciiname":"Pindi Awanan",
    "gn:country_code":"PK",
    "gn:dem":317,
    "gn:feature_class":"P",
    "gn:feature_code":"PPL",
    "gn:name":"Pindi Awanan",
    "gn:population":0,
    "gn:timezone":"Asia/Karachi",
    "iso:country":"PK",
    "name:und_x_variant":[
        "Pindi Awan",
        "Pindi Awanan"
    ],
    "wof:name":"Pindi Awanan",
    "wof:placetype":"locality"
},
  "geometry": {"coordinates":[74.11705000000001,32.8566],"type":"Point"}
}