{
  "type": "Feature",
  "properties": {
    "iso:country":"PK",
    "name:unk_x_variant":[
        "Sharakpur"
    ],
    "name:urd_x_preferred":[
        "\u0634\u0631\u0642\u067e\u0648\u0631 \u0634\u0631\u06cc\u0641"
    ],
    "qs:gn_country":"PK",
    "qs:gn_fcode":"PPL",
    "qs:gn_pop":31855,
    "qs:name":"Sharqpur",
    "qs:name_adm0":"Pakistan",
    "qs:name_adm1":"Punjab",
    "qs:photos":0,
    "qs:photos_1k":0,
    "qs:photos_9k":0,
    "qs:photos_9r":0,
    "qs:photos_all":0,
    "qs:photos_sr":0,
    "qs:placetype":"Town",
    "qs:pop_sr":"7",
    "qs:woe_adm0":23424922,
    "wd:wordcount":44,
    "wof:name":"Sharqpur",
    "wof:placetype":"locality",
    "wof:population":31855
},
  "geometry": {"coordinates":[74.09999999999999,31.46333],"type":"Point"}
}