{
  "type": "Feature",
  "properties": {
    "gn:admin1_code":"2.0",
    "gn:asciiname":"Abdul Rahim",
    "gn:country_code":"PK",
    "gn:dem":1553,
    "gn:feature_class":"P",
    "gn:feature_code":"PPL",
    "gn:name":"Abdul Rahim",
    "gn:population":0,
    "gn:timezone":"Asia/Karachi",
    "iso:country":"PK",
    "wof:name":"Abdul Rahim",
    "wof:placetype":"locality"
},
  "geometry": {"coordinates":[66.34478,28.05733],"type":"Point"}
}