{
  "type": "Feature",
  "properties": {
    "gn:admin1_code":"4",
    "gn:asciiname":"Khichian",
    "gn:country_code":"PK",
    "gn:dem":252,
    "gn:feature_class":"P",
    "gn:feature_code":"PPL",
    "gn:name":"Khichian",
    "gn:population":0,
    "gn:timezone":"Asia/Karachi",
    "iso:country":"PK",
    "name:und_x_variant":[
        "Rahimpur",
        "Khich\u012b\u0101n"
    ],
    "wof:name":"Khichian",
    "wof:placetype":"locality"
},
  "geometry": {"coordinates":[74.55167,32.54743],"type":"Point"}
}