{
  "type": "Feature",
  "properties": {
    "gn:admin1_code":"1.0",
    "gn:asciiname":"Abdullah Nur Kaskai",
    "gn:country_code":"PK",
    "gn:dem":1103,
    "gn:feature_class":"P",
    "gn:feature_code":"PPL",
    "gn:name":"Abdullah Nur Kaskai",
    "gn:population":0,
    "gn:timezone":"Asia/Karachi",
    "iso:country":"PK",
    "wof:name":"Abdullah Nur Kaskai",
    "wof:placetype":"locality"
},
  "geometry": {"coordinates":[70.00176,32.42503],"type":"Point"}
}