{
  "type": "Feature",
  "properties": {
    "gn:admin1_code":"1.0",
    "gn:asciiname":"Abdullah Nur Kaskai",
    "gn:country_code":"PK",
    "gn:dem":1103,
    "gn:feature_class":"P",
    "gn:feature_code":"PPL",
    "gn:name":"Abdullah Nur Kaskai",
    "gn:population":0,
    "gn:timezone":"Asia/Karachi",
    "iso:country":"PK",
    "name:fas_x_preferred":[
        "\u0639\u0628\u062f\u0627\u0644\u0644\u0647 \u0646\u0648\u0631 \u06a9\u0627\u0633\u06a9\u0627\u06cc"
    ],
    "wof:name":"Abdullah Nur Kaskai",
    "wof:placetype":"locality"
},
  "geometry": {"coordinates":[70.00176,32.42503],"type":"Point"}
}