{
  "type": "Feature",
  "properties": {
    "gn:country":"PK",
    "gn:fcode":"PPL",
    "gn:population":655,
    "iso:country":"PK",
    "qs:name":"Dhok Awan",
    "qs:photos_9r":0,
    "qs:photos_sr":0,
    "qs:pop_sr":"2",
    "wof:name":"Dhok Awan",
    "wof:placetype":"locality",
    "wof:population":655
},
  "geometry": {"coordinates":[72.52357000000001,32.84452],"type":"Point"}
}