{
  "type": "Feature",
  "properties": {
    "gn:admin1_code":"4",
    "gn:asciiname":"Ainwala",
    "gn:cc2":"PK",
    "gn:country_code":"PK",
    "gn:dem":125,
    "gn:feature_class":"P",
    "gn:feature_code":"PPL",
    "gn:name":"Ainw\u0101la",
    "gn:population":0,
    "gn:timezone":"Asia/Karachi",
    "iso:country":"PK",
    "name:und_x_variant":[
        "Naw\u0101n Al\u012bw\u0101la",
        "Ainw\u0101la"
    ],
    "wof:name":"Ainwala",
    "wof:placetype":"locality"
},
  "geometry": {"coordinates":[71.1875,30.27083],"type":"Point"}
}