{
  "type": "Feature",
  "properties": {
    "gn:admin1_code":"4",
    "gn:asciiname":"Kot Shahpur",
    "gn:country_code":"PK",
    "gn:dem":188,
    "gn:feature_class":"P",
    "gn:feature_code":"PPL",
    "gn:name":"Kot Shahpur",
    "gn:population":0,
    "gn:timezone":"Asia/Karachi",
    "iso:country":"PK",
    "name:und_x_variant":[
        "Sh\u0101hpur"
    ],
    "wof:name":"Kot Shahpur",
    "wof:placetype":"locality"
},
  "geometry": {"coordinates":[73.63327,31.25365],"type":"Point"}
}