{
  "type": "Feature",
  "properties": {
    "gn:admin1_code":"2.0",
    "gn:asciiname":"Chhad",
    "gn:country_code":"PK",
    "gn:dem":1256,
    "gn:feature_class":"P",
    "gn:feature_code":"PPL",
    "gn:name":"Chhad",
    "gn:population":0,
    "gn:timezone":"Asia/Karachi",
    "iso:country":"PK",
    "wof:name":"Chhad",
    "wof:placetype":"locality"
},
  "geometry": {"coordinates":[65.78407,27.55632],"type":"Point"}
}