{
  "type": "Feature",
  "properties": {
    "gn:admin1_code":"4",
    "gn:asciiname":"Thatta Kalu Nahra",
    "gn:country_code":"PK",
    "gn:dem":186,
    "gn:feature_class":"P",
    "gn:feature_code":"PPL",
    "gn:name":"Thatta K\u0101lu Nahra",
    "gn:population":0,
    "gn:timezone":"Asia/Karachi",
    "iso:country":"PK",
    "wof:name":"Thatta Kalu Nahra",
    "wof:placetype":"locality"
},
  "geometry": {"coordinates":[73.58333,31.28333],"type":"Point"}
}