{
  "type": "Feature",
  "properties": {
    "gn:admin1_code":"4.0",
    "gn:asciiname":"Chak Ninety-seven -Six Right",
    "gn:country_code":"PK",
    "gn:dem":169,
    "gn:feature_class":"P",
    "gn:feature_code":"PPL",
    "gn:name":"Chak Ninety-seven -Six Right",
    "gn:population":0,
    "gn:timezone":"Asia/Karachi",
    "iso:country":"PK",
    "wof:name":"Chak Ninety-seven -Six Right",
    "wof:placetype":"locality"
},
  "geometry": {"coordinates":[73.01914000000002,30.65813],"type":"Point"}
}