{
  "type": "Feature",
  "properties": {
    "gn:admin1_code":"2.0",
    "gn:asciiname":"Shishan Baian",
    "gn:country_code":"PK",
    "gn:dem":2510,
    "gn:feature_class":"P",
    "gn:feature_code":"PPL",
    "gn:name":"Shishan Baian",
    "gn:population":0,
    "gn:timezone":"Asia/Karachi",
    "iso:country":"PK",
    "wof:name":"Shishan Baian",
    "wof:placetype":"locality"
},
  "geometry": {"coordinates":[67.58265,30.97018],"type":"Point"}
}