{
  "type": "Feature",
  "properties": {
    "gn:admin1_code":"05",
    "gn:asciiname":"Goth Chatto",
    "gn:country_code":"PK",
    "gn:dem":299,
    "gn:feature_class":"P",
    "gn:feature_code":"PPL",
    "gn:name":"Goth Chatto",
    "gn:population":0,
    "gn:timezone":"Asia/Karachi",
    "iso:country":"PK",
    "name:und_x_variant":[
        "Goth Chutto"
    ],
    "wof:name":"Goth Chatto",
    "wof:placetype":"locality"
},
  "geometry": {"coordinates":[67.34004,25.37336],"type":"Point"}
}