{
  "type": "Feature",
  "properties": {
    "gn:admin1_code":"7.0",
    "gn:asciiname":"Dambudas",
    "gn:country_code":"PK",
    "gn:dem":2083,
    "gn:feature_class":"P",
    "gn:feature_code":"PPL",
    "gn:name":"Dambudas",
    "gn:population":0,
    "gn:timezone":"Asia/Karachi",
    "iso:country":"PK",
    "name:und_x_variant":[
        "Dumbudas"
    ],
    "wof:name":"Dambudas",
    "wof:placetype":"locality"
},
  "geometry": {"coordinates":[75.22493,35.59759000000001],"type":"Point"}
}