{
  "type": "Feature",
  "properties": {
    "gn:admin1_code":"4.0",
    "gn:asciiname":"Basti Sanjrani",
    "gn:country_code":"PK",
    "gn:dem":88,
    "gn:feature_class":"P",
    "gn:feature_code":"PPL",
    "gn:name":"Basti Sanjrani",
    "gn:population":0,
    "gn:timezone":"Asia/Karachi",
    "iso:country":"PK",
    "name:und_x_variant":[
        "Sanjr\u0101ni"
    ],
    "wof:name":"Basti Sanjrani",
    "wof:placetype":"locality"
},
  "geometry": {"coordinates":[70.23187,28.87286],"type":"Point"}
}