{
  "type": "Feature",
  "properties": {
    "gn:admin1_code":"04",
    "gn:asciiname":"Rakh Jabbi",
    "gn:country_code":"PK",
    "gn:dem":399,
    "gn:feature_class":"P",
    "gn:feature_code":"PPL",
    "gn:name":"Rakh Jabbi",
    "gn:population":0,
    "gn:timezone":"Asia/Karachi",
    "iso:country":"PK",
    "wof:name":"Rakh Jabbi",
    "wof:placetype":"locality"
},
  "geometry": {"coordinates":[72.26666999999998,33.45],"type":"Point"}
}