{
  "type": "Feature",
  "properties": {
    "gn:admin1_code":"2",
    "gn:asciiname":"Lanjani",
    "gn:country_code":"PK",
    "gn:dem":1244,
    "gn:feature_class":"P",
    "gn:feature_code":"PPL",
    "gn:name":"Lanjani",
    "gn:population":0,
    "gn:timezone":"Asia/Karachi",
    "iso:country":"PK",
    "wof:name":"Lanjani",
    "wof:placetype":"locality"
},
  "geometry": {"coordinates":[69.81531,30.08004],"type":"Point"}
}