{
  "type": "Feature",
  "properties": {
    "gn:admin1_code":"7.0",
    "gn:asciiname":"Chibo",
    "gn:country_code":"PK",
    "gn:dem":3111,
    "gn:feature_class":"P",
    "gn:feature_code":"PPL",
    "gn:name":"Chibo",
    "gn:population":0,
    "gn:timezone":"Asia/Karachi",
    "iso:country":"PK",
    "wof:name":"Chibo",
    "wof:placetype":"locality"
},
  "geometry": {"coordinates":[76.25163000000001,35.24626],"type":"Point"}
}