{
  "type": "Feature",
  "properties": {
    "gn:admin1_code":"1.0",
    "gn:asciiname":"Burqi Kili",
    "gn:country_code":"PK",
    "gn:dem":1652,
    "gn:feature_class":"P",
    "gn:feature_code":"PPL",
    "gn:name":"Burqi Kili",
    "gn:population":0,
    "gn:timezone":"Asia/Karachi",
    "iso:country":"PK",
    "name:und_x_variant":[
        "Burki",
        "Burgi",
        "Burqi",
        "Burqi Kili"
    ],
    "wof:name":"Burqi Kili",
    "wof:placetype":"locality"
},
  "geometry": {"coordinates":[69.95004,33.85635],"type":"Point"}
}