{
  "type": "Feature",
  "properties": {
    "gn:admin1_code":"3",
    "gn:asciiname":"Zakria Dherai",
    "gn:country_code":"PK",
    "gn:dem":305,
    "gn:feature_class":"P",
    "gn:feature_code":"PPL",
    "gn:name":"Zakria Dherai",
    "gn:population":0,
    "gn:timezone":"Asia/Karachi",
    "iso:country":"PK",
    "name:eng_x_preferred":[
        "Dheri Zakaria"
    ],
    "wof:name":"Zakria Dherai",
    "wof:placetype":"locality"
},
  "geometry": {"coordinates":[72.37765,34.02479],"type":"Point"}
}