{
  "type": "Feature",
  "properties": {
    "gn:admin1_code":"3.0",
    "gn:asciiname":"Mangarai",
    "gn:country_code":"PK",
    "gn:dem":3131,
    "gn:feature_class":"P",
    "gn:feature_code":"PPL",
    "gn:name":"Mangarai",
    "gn:population":0,
    "gn:timezone":"Asia/Karachi",
    "iso:country":"PK",
    "wof:name":"Mangarai",
    "wof:placetype":"locality"
},
  "geometry": {"coordinates":[72.68684,35.07239000000001],"type":"Point"}
}