{
  "type": "Feature",
  "properties": {
    "gn:admin1_code":"4.0",
    "gn:asciiname":"Rafiq Shahwala",
    "gn:country_code":"PK",
    "gn:dem":117,
    "gn:feature_class":"P",
    "gn:feature_code":"PPL",
    "gn:name":"Rafiq Shahwala",
    "gn:population":0,
    "gn:timezone":"Asia/Karachi",
    "iso:country":"PK",
    "wof:name":"Rafiq Shahwala",
    "wof:placetype":"locality"
},
  "geometry": {"coordinates":[71.63915,29.75659000000001],"type":"Point"}
}