{
  "type": "Feature",
  "properties": {
    "gn:admin1_code":"4",
    "gn:asciiname":"Basti Khatri",
    "gn:country_code":"PK",
    "gn:dem":82,
    "gn:feature_class":"P",
    "gn:feature_code":"PPL",
    "gn:name":"Basti Khatri",
    "gn:population":0,
    "gn:timezone":"Asia/Karachi",
    "iso:country":"PK",
    "name:und_x_variant":[
        "K\u0101thri"
    ],
    "wof:name":"Basti Khatri",
    "wof:placetype":"locality"
},
  "geometry": {"coordinates":[69.97854,28.42427],"type":"Point"}
}