{
  "type": "Feature",
  "properties": {
    "gn:admin1_code":"3",
    "gn:asciiname":"Bara Gali",
    "gn:country_code":"PK",
    "gn:dem":2305,
    "gn:feature_class":"P",
    "gn:feature_code":"PPL",
    "gn:name":"Bara Gali",
    "gn:population":0,
    "gn:timezone":"Asia/Karachi",
    "iso:country":"PK",
    "name:und_x_variant":[
        "B\u0101ra Gali Cantonment",
        "Bara Gali"
    ],
    "wof:name":"Bara Gali",
    "wof:placetype":"locality"
},
  "geometry": {"coordinates":[73.35646,34.0902],"type":"Point"}
}