{
  "type": "Feature",
  "properties": {
    "gn:admin1_code":"3.0",
    "gn:asciiname":"Battakundi",
    "gn:country_code":"PK",
    "gn:dem":2969,
    "gn:feature_class":"P",
    "gn:feature_code":"PPL",
    "gn:name":"Battakundi",
    "gn:population":0,
    "gn:timezone":"Asia/Karachi",
    "iso:country":"PK",
    "wof:name":"Battakundi",
    "wof:placetype":"locality"
},
  "geometry": {"coordinates":[73.76498000000002,34.92725],"type":"Point"}
}