{
  "type": "Feature",
  "properties": {
    "gn:admin1_code":"04",
    "gn:asciiname":"Seri Shajra",
    "gn:country_code":"PK",
    "gn:dem":113,
    "gn:feature_class":"P",
    "gn:feature_code":"PPL",
    "gn:name":"Seri Shajra",
    "gn:population":0,
    "gn:timezone":"Asia/Karachi",
    "iso:country":"PK",
    "name:und_x_variant":[
        "Seri"
    ],
    "wof:name":"Seri Shajra",
    "wof:placetype":"locality"
},
  "geometry": {"coordinates":[71.21370999999998,29.73107000000001],"type":"Point"}
}