{
  "type": "Feature",
  "properties": {
    "gn:admin1_code":"3",
    "gn:asciiname":"Jabbar",
    "gn:country_code":"PK",
    "gn:dem":1123,
    "gn:feature_class":"P",
    "gn:feature_code":"PPL",
    "gn:name":"Jabbar",
    "gn:population":0,
    "gn:timezone":"Asia/Karachi",
    "iso:country":"PK",
    "name:deu_x_preferred":[
        "Jabbar"
    ],
    "name:nds_x_preferred":[
        "Jabbar"
    ],
    "name:rus_x_preferred":[
        "\u0414\u0436\u0430\u0431\u0431\u0430\u0440"
    ],
    "name:tur_x_preferred":[
        "Cabbar"
    ],
    "name:ukr_x_preferred":[
        "\u0414\u0436\u0430\u0431\u0431\u0430\u0440"
    ],
    "wof:name":"Jabbar",
    "wof:placetype":"locality"
},
  "geometry": {"coordinates":[73.24287,34.52811],"type":"Point"}
}