{
  "type": "Feature",
  "properties": {
    "gn:admin1_code":"1",
    "gn:asciiname":"Bibi Raghzai",
    "gn:country_code":"PK",
    "gn:dem":1578,
    "gn:feature_class":"P",
    "gn:feature_code":"PPL",
    "gn:name":"Bibi Raghzai",
    "gn:population":0,
    "gn:timezone":"Asia/Karachi",
    "iso:country":"PK",
    "name:und_x_variant":[
        "Bibizai Raghzai"
    ],
    "wof:name":"Bibi Raghzai",
    "wof:placetype":"locality"
},
  "geometry": {"coordinates":[69.88148000000001,32.59246],"type":"Point"}
}