{
  "type": "Feature",
  "properties": {
    "gn:admin1_code":"4.0",
    "gn:asciiname":"Haji Nasir da Dera",
    "gn:country_code":"PK",
    "gn:dem":184,
    "gn:feature_class":"P",
    "gn:feature_code":"PPL",
    "gn:name":"Haji Nasir da Dera",
    "gn:population":0,
    "gn:timezone":"Asia/Karachi",
    "iso:country":"PK",
    "wof:name":"Haji Nasir da Dera",
    "wof:placetype":"locality"
},
  "geometry": {"coordinates":[71.86626,31.91147],"type":"Point"}
}