{
  "type": "Feature",
  "properties": {
    "gn:admin1_code":"4",
    "gn:asciiname":"Mahtab Shahwala",
    "gn:country_code":"PK",
    "gn:dem":159,
    "gn:feature_class":"P",
    "gn:feature_code":"PPL",
    "gn:name":"Mahtab Shahwala",
    "gn:population":0,
    "gn:timezone":"Asia/Karachi",
    "iso:country":"PK",
    "wof:name":"Mahtab Shahwala",
    "wof:placetype":"locality"
},
  "geometry": {"coordinates":[71.28791,31.36975],"type":"Point"}
}