{
  "type": "Feature",
  "properties": {
    "gn:admin1_code":"3",
    "gn:asciiname":"Bar Dewal Garhi",
    "gn:country_code":"PK",
    "gn:dem":907,
    "gn:feature_class":"P",
    "gn:feature_code":"PPL",
    "gn:name":"Bar Dewal Garhi",
    "gn:population":0,
    "gn:timezone":"Asia/Karachi",
    "iso:country":"PK",
    "name:und_x_variant":[
        "Bar Dewalgari"
    ],
    "wof:name":"Bar Dewal Garhi",
    "wof:placetype":"locality"
},
  "geometry": {"coordinates":[72.73291,34.24843],"type":"Point"}
}