{
  "type": "Feature",
  "properties": {
    "gn:admin1_code":"5.0",
    "gn:asciiname":"Landi Haji Ali Anwar Mahar",
    "gn:country_code":"PK",
    "gn:dem":70,
    "gn:feature_class":"P",
    "gn:feature_code":"PPL",
    "gn:name":"Landi Haji Ali Anwar Mahar",
    "gn:population":0,
    "gn:timezone":"Asia/Karachi",
    "iso:country":"PK",
    "wof:name":"Landi Haji Ali Anwar Mahar",
    "wof:placetype":"locality"
},
  "geometry": {"coordinates":[69.55118,27.74154],"type":"Point"}
}