{
  "type": "Feature",
  "properties": {
    "gn:admin1_code":"3.0",
    "gn:asciiname":"Sher Khan Mughal Khel",
    "gn:country_code":"PK",
    "gn:dem":306,
    "gn:feature_class":"P",
    "gn:feature_code":"PPL",
    "gn:name":"Sher Khan Mughal Khel",
    "gn:population":0,
    "gn:timezone":"Asia/Karachi",
    "iso:country":"PK",
    "name:und_x_variant":[
        "Sher Kh\u0101n \u012asa Khel"
    ],
    "wof:name":"Sher Khan Mughal Khel",
    "wof:placetype":"locality"
},
  "geometry": {"coordinates":[70.75917,32.81327],"type":"Point"}
}