{
  "type": "Feature",
  "properties": {
    "gn:admin1_code":"4.0",
    "gn:asciiname":"Dera Amir Khan Umrani",
    "gn:country_code":"PK",
    "gn:dem":82,
    "gn:feature_class":"P",
    "gn:feature_code":"PPL",
    "gn:name":"Dera Amir Khan Umrani",
    "gn:population":0,
    "gn:timezone":"Asia/Karachi",
    "iso:country":"PK",
    "wof:name":"Dera Amir Khan Umrani",
    "wof:placetype":"locality"
},
  "geometry": {"coordinates":[69.89957,28.5786],"type":"Point"}
}