{
  "type": "Feature",
  "properties": {
    "gn:admin1_code":"04",
    "gn:asciiname":"Tali",
    "gn:country_code":"PK",
    "gn:dem":160,
    "gn:feature_class":"P",
    "gn:feature_code":"PPL",
    "gn:name":"Tali",
    "gn:population":0,
    "gn:timezone":"Asia/Karachi",
    "iso:country":"PK",
    "name:ceb_x_preferred":[
        "Tali"
    ],
    "name:deu_x_preferred":[
        "Tali"
    ],
    "name:fin_x_preferred":[
        "Tali"
    ],
    "name:fra_x_preferred":[
        "Tali"
    ],
    "name:heb_x_preferred":[
        "\u05d8\u05dc\u05d9"
    ],
    "name:nld_x_preferred":[
        "Tali"
    ],
    "name:ron_x_preferred":[
        "Tali"
    ],
    "name:rus_x_preferred":[
        "\u0422\u0430\u043b\u0438"
    ],
    "name:swe_x_preferred":[
        "Tali"
    ],
    "name:und_x_variant":[
        "Talli"
    ],
    "wof:name":"Tali",
    "wof:placetype":"locality"
},
  "geometry": {"coordinates":[73.18895000000001,30.41064],"type":"Point"}
}