{
  "type": "Feature",
  "properties": {
    "gn:admin1_code":"4.0",
    "gn:asciiname":"Chak Three Hundred Ninety-six",
    "gn:country_code":"PK",
    "gn:dem":171,
    "gn:feature_class":"P",
    "gn:feature_code":"PPL",
    "gn:name":"Chak Three Hundred Ninety-six",
    "gn:population":0,
    "gn:timezone":"Asia/Karachi",
    "iso:country":"PK",
    "name:und_x_variant":[
        "B\u0101hu da Chak"
    ],
    "wof:name":"Chak Three Hundred Ninety-six",
    "wof:placetype":"locality"
},
  "geometry": {"coordinates":[73.02361999999999,30.96635],"type":"Point"}
}