{
  "type": "Feature",
  "properties": {
    "gn:admin1_code":"3.0",
    "gn:asciiname":"Kas",
    "gn:country_code":"PK",
    "gn:dem":1773,
    "gn:feature_class":"P",
    "gn:feature_code":"PPL",
    "gn:name":"Kas",
    "gn:population":0,
    "gn:timezone":"Asia/Karachi",
    "iso:country":"PK",
    "name:ast_x_preferred":[
        "Kes"
    ],
    "name:cat_x_preferred":[
        "Kas"
    ],
    "name:eus_x_preferred":[
        "Kas"
    ],
    "name:fra_x_preferred":[
        "Kas"
    ],
    "name:glg_x_preferred":[
        "Kas"
    ],
    "name:por_x_preferred":[
        "Kas"
    ],
    "name:spa_x_preferred":[
        "Kas"
    ],
    "name:tur_x_preferred":[
        "Kas"
    ],
    "name:und_x_variant":[
        "Kass",
        "Kas"
    ],
    "wof:name":"Kas",
    "wof:placetype":"locality"
},
  "geometry": {"coordinates":[72.71601,34.52889],"type":"Point"}
}