{
  "type": "Feature",
  "properties": {
    "gn:admin1_code":"04",
    "gn:asciiname":"Chak Five Hundred Eighty-three Gogera Branch",
    "gn:country_code":"PK",
    "gn:dem":186,
    "gn:feature_class":"P",
    "gn:feature_code":"PPL",
    "gn:name":"Chak Five Hundred Eighty-three Gogera Branch",
    "gn:population":0,
    "gn:timezone":"Asia/Karachi",
    "iso:country":"PK",
    "name:und_x_variant":[
        "Wan Ganeshpur",
        "V\u0101n Ganeshpura",
        "Chak Five Hundred Eighty-three Gogera Branch",
        "Wasir\u0101n da Chak"
    ],
    "wof:name":"Chak Five Hundred Eighty-three Gogera Branch",
    "wof:placetype":"locality"
},
  "geometry": {"coordinates":[73.48406999999997,31.22969],"type":"Point"}
}