{
  "type": "Feature",
  "properties": {
    "gn:admin1_code":"1.0",
    "gn:asciiname":"Pawa Sar",
    "gn:country_code":"PK",
    "gn:dem":687,
    "gn:feature_class":"P",
    "gn:feature_code":"PPL",
    "gn:name":"Pawa Sar",
    "gn:population":0,
    "gn:timezone":"Asia/Karachi",
    "iso:country":"PK",
    "wof:name":"Pawa Sar",
    "wof:placetype":"locality"
},
  "geometry": {"coordinates":[70.03721,31.76658],"type":"Point"}
}