{
  "type": "Feature",
  "properties": {
    "gn:admin1_code":"7.0",
    "gn:asciiname":"Jujilut",
    "gn:country_code":"PK",
    "gn:dem":3486,
    "gn:feature_class":"P",
    "gn:feature_code":"PPL",
    "gn:name":"Jujilut",
    "gn:population":0,
    "gn:timezone":"Asia/Karachi",
    "iso:country":"PK",
    "wof:name":"Jujilut",
    "wof:placetype":"locality"
},
  "geometry": {"coordinates":[73.52275999999998,35.9801],"type":"Point"}
}