{
  "type": "Feature",
  "properties": {
    "gn:admin1_code":"2.0",
    "gn:asciiname":"Siddique Suphangluna",
    "gn:country_code":"PK",
    "gn:dem":2433,
    "gn:feature_class":"P",
    "gn:feature_code":"PPL",
    "gn:name":"Siddique Suphangluna",
    "gn:population":0,
    "gn:timezone":"Asia/Karachi",
    "iso:country":"PK",
    "name:eng_x_preferred":[
        "Sidd\u012bq Spangluna"
    ],
    "wof:name":"Siddique Suphangluna",
    "wof:placetype":"locality"
},
  "geometry": {"coordinates":[67.44719000000001,30.78961],"type":"Point"}
}