{
  "type": "Feature",
  "properties": {
    "gn:admin1_code":"4.0",
    "gn:asciiname":"Chak Two Hundred Ten Rakh Branch",
    "gn:country_code":"PK",
    "gn:dem":186,
    "gn:feature_class":"P",
    "gn:feature_code":"PPL",
    "gn:name":"Chak Two Hundred Ten Rakh Branch",
    "gn:population":0,
    "gn:timezone":"Asia/Karachi",
    "iso:country":"PK",
    "name:und_x_variant":[
        "Lochhmanw\u0101la",
        "Chak Two Hundred Ten RB",
        "Chak Two Hundred Ten Rakh Branch"
    ],
    "wof:name":"Chak Two Hundred Ten Rakh Branch",
    "wof:placetype":"locality"
},
  "geometry": {"coordinates":[73.20777,31.43114000000001],"type":"Point"}
}