{
  "type": "Feature",
  "properties": {
    "gn:admin1_code":"4.0",
    "gn:asciiname":"Jhitwala",
    "gn:country_code":"PK",
    "gn:dem":120,
    "gn:feature_class":"P",
    "gn:feature_code":"PPL",
    "gn:name":"Jhitwala",
    "gn:population":0,
    "gn:timezone":"Asia/Karachi",
    "iso:country":"PK",
    "wof:name":"Jhitwala",
    "wof:placetype":"locality"
},
  "geometry": {"coordinates":[71.37343,29.96307],"type":"Point"}
}