{
  "type": "Feature",
  "properties": {
    "gn:admin1_code":"1.0",
    "gn:asciiname":"Dag",
    "gn:country_code":"PK",
    "gn:dem":1065,
    "gn:feature_class":"P",
    "gn:feature_code":"PPL",
    "gn:name":"Dag",
    "gn:population":0,
    "gn:timezone":"Asia/Karachi",
    "iso:country":"PK",
    "wof:name":"Dag",
    "wof:placetype":"locality"
},
  "geometry": {"coordinates":[71.38951,34.78193],"type":"Point"}
}