{
  "type": "Feature",
  "properties": {
    "gn:admin1_code":"5.0",
    "gn:asciiname":"Goth Tariq Aziz Dero",
    "gn:country_code":"PK",
    "gn:dem":28,
    "gn:feature_class":"P",
    "gn:feature_code":"PPL",
    "gn:name":"Goth Tariq Aziz Dero",
    "gn:population":0,
    "gn:timezone":"Asia/Karachi",
    "iso:country":"PK",
    "wof:name":"Goth Tariq Aziz Dero",
    "wof:placetype":"locality"
},
  "geometry": {"coordinates":[68.59203000000001,25.79465],"type":"Point"}
}