{
  "type": "Feature",
  "properties": {
    "gn:admin1_code":"5",
    "gn:asciiname":"Goth Lalu Machhi",
    "gn:country_code":"PK",
    "gn:dem":26,
    "gn:feature_class":"P",
    "gn:feature_code":"PPL",
    "gn:name":"Goth Lalu Machhi",
    "gn:population":0,
    "gn:timezone":"Asia/Karachi",
    "iso:country":"PK",
    "name:eng_x_preferred":[
        "L\u0101lu M\u0101chhi"
    ],
    "wof:name":"Goth Lalu Machhi",
    "wof:placetype":"locality"
},
  "geometry": {"coordinates":[68.49169999999999,25.74794],"type":"Point"}
}