{
  "type": "Feature",
  "properties": {
    "gn:admin1_code":"4.0",
    "gn:asciiname":"Suba Jalalani",
    "gn:country_code":"PK",
    "gn:dem":125,
    "gn:feature_class":"P",
    "gn:feature_code":"PPL",
    "gn:name":"Suba Jalalani",
    "gn:population":0,
    "gn:timezone":"Asia/Karachi",
    "iso:country":"PK",
    "name:und_x_variant":[
        "Subo Jaj\u0101i\u0101ni"
    ],
    "wof:name":"Suba Jalalani",
    "wof:placetype":"locality"
},
  "geometry": {"coordinates":[70.20084,29.33037],"type":"Point"}
}