{
  "type": "Feature",
  "properties": {
    "gn:admin1_code":"3.0",
    "gn:asciiname":"Juz",
    "gn:country_code":"PK",
    "gn:dem":1021,
    "gn:feature_class":"P",
    "gn:feature_code":"PPL",
    "gn:name":"Juz",
    "gn:population":0,
    "gn:timezone":"Asia/Karachi",
    "iso:country":"PK",
    "wof:name":"Juz",
    "wof:placetype":"locality"
},
  "geometry": {"coordinates":[72.39991999999999,34.63638],"type":"Point"}
}