{
  "type": "Feature",
  "properties": {
    "gn:admin1_code":"6",
    "gn:asciiname":"Hotriri",
    "gn:country_code":"PK",
    "gn:dem":2042,
    "gn:feature_class":"P",
    "gn:feature_code":"PPL",
    "gn:name":"Hotriri",
    "gn:population":0,
    "gn:timezone":"Asia/Karachi",
    "iso:country":"PK",
    "name:und_x_variant":[
        "Hotreri"
    ],
    "wof:name":"Hotriri",
    "wof:placetype":"locality"
},
  "geometry": {"coordinates":[73.76028000000002,34.11767],"type":"Point"}
}