{
  "type": "Feature",
  "properties": {
    "gn:admin1_code":"2",
    "gn:asciiname":"Udai",
    "gn:country_code":"PK",
    "gn:dem":2381,
    "gn:feature_class":"P",
    "gn:feature_code":"PPL",
    "gn:name":"Udai",
    "gn:population":0,
    "gn:timezone":"Asia/Karachi",
    "iso:country":"PK",
    "name:eng_x_preferred":[
        "Udia"
    ],
    "wof:name":"Udai",
    "wof:placetype":"locality"
},
  "geometry": {"coordinates":[67.67296,31.01839],"type":"Point"}
}