{
  "type": "Feature",
  "properties": {
    "gn:admin1_code":"4.0",
    "gn:asciiname":"Hut Basti",
    "gn:country_code":"PK",
    "gn:dem":119,
    "gn:feature_class":"P",
    "gn:feature_code":"PPL",
    "gn:name":"Hut Basti",
    "gn:population":0,
    "gn:timezone":"Asia/Karachi",
    "iso:country":"PK",
    "name:und_x_variant":[
        "H\u016bdi Basti",
        "Lanori Basti"
    ],
    "wof:name":"Hut Basti",
    "wof:placetype":"locality"
},
  "geometry": {"coordinates":[71.44405999999999,29.73771],"type":"Point"}
}