{
  "type": "Feature",
  "properties": {
    "gn:admin1_code":"5",
    "gn:asciiname":"Goth Bachal Dars",
    "gn:country_code":"PK",
    "gn:dem":21,
    "gn:feature_class":"P",
    "gn:feature_code":"PPL",
    "gn:name":"Goth Bachal Dars",
    "gn:population":0,
    "gn:timezone":"Asia/Karachi",
    "iso:country":"PK",
    "name:und_x_variant":[
        "Khidar Otho"
    ],
    "wof:name":"Goth Bachal Dars",
    "wof:placetype":"locality"
},
  "geometry": {"coordinates":[68.85275,25.36687],"type":"Point"}
}