{
  "type": "Feature",
  "properties": {
    "gn:admin1_code":"6",
    "gn:asciiname":"Pathra",
    "gn:country_code":"PK",
    "gn:dem":2772,
    "gn:feature_class":"P",
    "gn:feature_code":"PPL",
    "gn:name":"Pathra",
    "gn:population":0,
    "gn:timezone":"Asia/Karachi",
    "iso:country":"PK",
    "name:und_x_variant":[
        "Pathri"
    ],
    "wof:name":"Pathra",
    "wof:placetype":"locality"
},
  "geometry": {"coordinates":[73.73211999999999,34.50878],"type":"Point"}
}