{
  "type": "Feature",
  "properties": {
    "gn:admin1_code":"3.0",
    "gn:asciiname":"Janas",
    "gn:country_code":"PK",
    "gn:dem":1881,
    "gn:feature_class":"P",
    "gn:feature_code":"PPL",
    "gn:name":"Janas",
    "gn:population":0,
    "gn:timezone":"Asia/Karachi",
    "iso:country":"PK",
    "name:eng_x_preferred":[
        "Janas"
    ],
    "wof:name":"Janas",
    "wof:placetype":"locality"
},
  "geometry": {"coordinates":[72.03984,35.29649000000001],"type":"Point"}
}