{
  "type": "Feature",
  "properties": {
    "gn:admin1_code":"6",
    "gn:asciiname":"Khajuri",
    "gn:country_code":"PK",
    "gn:dem":440,
    "gn:feature_class":"P",
    "gn:feature_code":"PPL",
    "gn:name":"Khajuri",
    "gn:population":0,
    "gn:timezone":"Asia/Karachi",
    "iso:country":"PK",
    "name:und_x_variant":[
        "Khoj\u016bri"
    ],
    "wof:name":"Khajuri",
    "wof:placetype":"locality"
},
  "geometry": {"coordinates":[74.23465999999998,32.98283],"type":"Point"}
}