{
  "type": "Feature",
  "properties": {
    "gn:admin1_code":"6",
    "gn:asciiname":"Maryan",
    "gn:country_code":"PK",
    "gn:dem":1148,
    "gn:feature_class":"P",
    "gn:feature_code":"PPL",
    "gn:name":"Maryan",
    "gn:population":0,
    "gn:timezone":"Asia/Karachi",
    "iso:country":"PK",
    "name:und_x_variant":[
        "Mahrian",
        "Maryan",
        "M\u0101hry\u0101n"
    ],
    "wof:name":"Maryan",
    "wof:placetype":"locality"
},
  "geometry": {"coordinates":[74.01666999999998,33.51667],"type":"Point"}
}