{
  "type": "Feature",
  "properties": {
    "gn:admin1_code":"5",
    "gn:asciiname":"Goth Karam Ali Shah",
    "gn:country_code":"PK",
    "gn:dem":38,
    "gn:feature_class":"P",
    "gn:feature_code":"PPL",
    "gn:name":"Goth Karam Ali Shah",
    "gn:population":0,
    "gn:timezone":"Asia/Karachi",
    "iso:country":"PK",
    "name:und_x_variant":[
        "Karam Ali Sh\u0101h jo Tar",
        "Kh\u0101shkeli Haz\u016bri"
    ],
    "wof:name":"Goth Karam Ali Shah",
    "wof:placetype":"locality"
},
  "geometry": {"coordinates":[69.60824000000001,24.9098],"type":"Point"}
}