{
  "type": "Feature",
  "properties": {
    "gn:admin1_code":"4",
    "gn:asciiname":"Nanwali",
    "gn:country_code":"PK",
    "gn:dem":130,
    "gn:feature_class":"P",
    "gn:feature_code":"PPL",
    "gn:name":"Nanwali",
    "gn:population":0,
    "gn:timezone":"Asia/Karachi",
    "iso:country":"PK",
    "name:eng_x_preferred":[
        "N\u0101\u012bw\u0101la"
    ],
    "wof:name":"Nanwali",
    "wof:placetype":"locality"
},
  "geometry": {"coordinates":[70.89492,30.40998],"type":"Point"}
}