{
  "type": "Feature",
  "properties": {
    "gn:admin1_code":"5.0",
    "gn:asciiname":"Nawa Abad Saiyid",
    "gn:country_code":"PK",
    "gn:dem":56,
    "gn:feature_class":"P",
    "gn:feature_code":"PPL",
    "gn:name":"Nawa Abad Saiyid",
    "gn:population":0,
    "gn:timezone":"Asia/Karachi",
    "iso:country":"PK",
    "name:und_x_variant":[
        "Unar\u0101b\u0101d",
        "\u0100b\u0101d Nawa",
        "Nawa Abad Saiyid"
    ],
    "wof:name":"Nawa Abad Saiyid",
    "wof:placetype":"locality"
},
  "geometry": {"coordinates":[68.25403,27.47871],"type":"Point"}
}