{
  "type": "Feature",
  "properties": {
    "gn:admin1_code":"4",
    "gn:asciiname":"Fazahwali",
    "gn:country_code":"PK",
    "gn:dem":174,
    "gn:feature_class":"P",
    "gn:feature_code":"PPL",
    "gn:name":"Fazahwali",
    "gn:population":0,
    "gn:timezone":"Asia/Karachi",
    "iso:country":"PK",
    "name:und_x_variant":[
        "Fazalw\u0101la Khu"
    ],
    "wof:name":"Fazahwali",
    "wof:placetype":"locality"
},
  "geometry": {"coordinates":[72.79071999999999,31.71756],"type":"Point"}
}