{
  "type": "Feature",
  "properties": {
    "gn:admin1_code":"2.0",
    "gn:asciiname":"Ashon Ghis",
    "gn:country_code":"PK",
    "gn:dem":1098,
    "gn:feature_class":"P",
    "gn:feature_code":"PPL",
    "gn:name":"Ashon Ghis",
    "gn:population":0,
    "gn:timezone":"Asia/Karachi",
    "iso:country":"PK",
    "wof:name":"Ashon Ghis",
    "wof:placetype":"locality"
},
  "geometry": {"coordinates":[63.00933000000001,27.35089],"type":"Point"}
}