{
  "type": "Feature",
  "properties": {
    "gn:admin1_code":"2.0",
    "gn:asciiname":"Astashai",
    "gn:country_code":"PK",
    "gn:dem":1739,
    "gn:feature_class":"P",
    "gn:feature_code":"PPL",
    "gn:name":"Astashai",
    "gn:population":0,
    "gn:timezone":"Asia/Karachi",
    "iso:country":"PK",
    "wof:name":"Astashai",
    "wof:placetype":"locality"
},
  "geometry": {"coordinates":[69.8479,31.44758],"type":"Point"}
}