{
  "type": "Feature",
  "properties": {
    "gn:admin1_code":"3",
    "gn:asciiname":"Siri da Bara",
    "gn:country_code":"PK",
    "gn:dem":1618,
    "gn:feature_class":"P",
    "gn:feature_code":"PPL",
    "gn:name":"Siri da Bara",
    "gn:population":0,
    "gn:timezone":"Asia/Karachi",
    "iso:country":"PK",
    "name:und_x_variant":[
        "Sireda B\u0101ra"
    ],
    "wof:name":"Siri da Bara",
    "wof:placetype":"locality"
},
  "geometry": {"coordinates":[72.91655,34.33264],"type":"Point"}
}