{
  "type": "Feature",
  "properties": {
    "gn:admin1_code":"4.0",
    "gn:asciiname":"Nuri",
    "gn:country_code":"PK",
    "gn:dem":929,
    "gn:feature_class":"P",
    "gn:feature_code":"PPL",
    "gn:name":"Nuri",
    "gn:population":0,
    "gn:timezone":"Asia/Karachi",
    "iso:country":"PK",
    "wof:name":"Nuri",
    "wof:placetype":"locality"
},
  "geometry": {"coordinates":[71.99881999999999,32.51068],"type":"Point"}
}