{
  "type": "Feature",
  "properties": {
    "gn:admin1_code":"4.0",
    "gn:asciiname":"Nuri",
    "gn:country_code":"PK",
    "gn:dem":929,
    "gn:feature_class":"P",
    "gn:feature_code":"PPL",
    "gn:name":"Nuri",
    "gn:population":0,
    "gn:timezone":"Asia/Karachi",
    "iso:country":"PK",
    "name:ara_x_preferred":[
        "\u0646\u0648\u0631\u064a"
    ],
    "name:ast_x_preferred":[
        "Nuri"
    ],
    "name:bel_x_preferred":[
        "\u041d\u0443\u0440\u044b"
    ],
    "name:cat_x_preferred":[
        "Nuri"
    ],
    "name:epo_x_preferred":[
        "Nuri"
    ],
    "name:eus_x_preferred":[
        "Nuri"
    ],
    "name:fra_x_preferred":[
        "Nouri"
    ],
    "name:hun_x_preferred":[
        "Nuri"
    ],
    "name:ita_x_preferred":[
        "Nuri"
    ],
    "name:kat_x_preferred":[
        "\u10dc\u10e3\u10e0\u10d8"
    ],
    "name:pol_x_preferred":[
        "Nuri"
    ],
    "name:por_x_preferred":[
        "Nuri"
    ],
    "name:rus_x_preferred":[
        "\u041d\u0443\u0440\u0438"
    ],
    "name:spa_x_preferred":[
        "Nuri"
    ],
    "name:ukr_x_preferred":[
        "\u041d\u0443\u0440\u0456"
    ],
    "wof:name":"Nuri",
    "wof:placetype":"locality"
},
  "geometry": {"coordinates":[71.99881999999999,32.51068],"type":"Point"}
}