{
  "type": "Feature",
  "properties": {
    "gn:admin1_code":"5",
    "gn:asciiname":"Goth Fat",
    "gn:country_code":"PK",
    "gn:dem":58,
    "gn:feature_class":"P",
    "gn:feature_code":"PPL",
    "gn:name":"Goth Fat",
    "gn:population":0,
    "gn:timezone":"Asia/Karachi",
    "iso:country":"PK",
    "name:und_x_variant":[
        "Goth F\u0101t"
    ],
    "wof:name":"Goth Fat",
    "wof:placetype":"locality"
},
  "geometry": {"coordinates":[68.78205,27.55311],"type":"Point"}
}