{
  "type": "Feature",
  "properties": {
    "gn:admin1_code":"03",
    "gn:asciiname":"Kumharan Kalan",
    "gn:country_code":"PK",
    "gn:dem":1297,
    "gn:feature_class":"P",
    "gn:feature_code":"PPL",
    "gn:name":"Kumharan Kalan",
    "gn:population":0,
    "gn:timezone":"Asia/Karachi",
    "iso:country":"PK",
    "name:und_x_variant":[
        "Kamar",
        "Kumh\u0101r",
        "Kumharan Kalan"
    ],
    "wof:name":"Kumharan Kalan",
    "wof:placetype":"neighbourhood"
},
  "geometry": {"coordinates":[73.09059000000001,34.18741],"type":"Point"}
}