{
  "type": "Feature",
  "properties": {
    "gn:admin1_code":"4",
    "gn:asciiname":"Chah Muqimwala",
    "gn:country_code":"PK",
    "gn:dem":135,
    "gn:feature_class":"P",
    "gn:feature_code":"PPL",
    "gn:name":"Chah Muqimwala",
    "gn:population":0,
    "gn:timezone":"Asia/Karachi",
    "iso:country":"PK",
    "name:und_x_variant":[
        "Ch\u0101h Muq\u012bmew\u0101la"
    ],
    "wof:name":"Chah Muqimwala",
    "wof:placetype":"locality"
},
  "geometry": {"coordinates":[71.87419,30.59848],"type":"Point"}
}