{
  "type": "Feature",
  "properties": {
    "gn:admin1_code":"4",
    "gn:asciiname":"Mochiwala",
    "gn:country_code":"PK",
    "gn:dem":125,
    "gn:feature_class":"P",
    "gn:feature_code":"PPL",
    "gn:name":"Mochiwala",
    "gn:population":0,
    "gn:timezone":"Asia/Karachi",
    "iso:country":"PK",
    "name:eng_x_preferred":[
        "\u0100ri Moch\u012bw\u0101la"
    ],
    "wof:name":"Mochiwala",
    "wof:placetype":"locality"
},
  "geometry": {"coordinates":[70.95471999999999,30.17687],"type":"Point"}
}