{
  "type": "Feature",
  "properties": {
    "gn:admin1_code":"01",
    "gn:asciiname":"Dalanai",
    "gn:country_code":"PK",
    "gn:dem":2272,
    "gn:feature_class":"P",
    "gn:feature_code":"PPL",
    "gn:name":"Dalanai",
    "gn:population":0,
    "gn:timezone":"Asia/Karachi",
    "iso:country":"PK",
    "wof:name":"Dalanai",
    "wof:placetype":"locality"
},
  "geometry": {"coordinates":[70.72662,33.69393],"type":"Point"}
}