{
  "type": "Feature",
  "properties": {
    "gn:admin1_code":"4.0",
    "gn:asciiname":"Bagrian",
    "gn:country_code":"PK",
    "gn:dem":211,
    "gn:feature_class":"P",
    "gn:feature_code":"PPL",
    "gn:name":"Bagrian",
    "gn:population":0,
    "gn:timezone":"Asia/Karachi",
    "iso:country":"PK",
    "name:pan_x_preferred":[
        "\u0a2c\u0a3e\u0a17\u0a5c\u0a40\u0a06\u0a02"
    ],
    "name:und_x_variant":[
        "Bagari\u0101n Dharm Chand",
        "B\u0101gri\u0101n Dharam Chand",
        "Bagarian Dharam Chand",
        "Bagrian"
    ],
    "wof:name":"Bagrian",
    "wof:placetype":"locality"
},
  "geometry": {"coordinates":[74.29404,31.42251],"type":"Point"}
}