{
  "type": "Feature",
  "properties": {
    "gn:admin1_code":"4",
    "gn:asciiname":"Nunan di Dhari",
    "gn:country_code":"PK",
    "gn:dem":195,
    "gn:feature_class":"P",
    "gn:feature_code":"PPL",
    "gn:name":"Nunan di Dhari",
    "gn:population":0,
    "gn:timezone":"Asia/Karachi",
    "iso:country":"PK",
    "name:und_x_variant":[
        "N\u016bn\u0101n di Jhuggi\u0101n"
    ],
    "wof:name":"Nunan di Dhari",
    "wof:placetype":"locality"
},
  "geometry": {"coordinates":[73.88639000000001,31.2602],"type":"Point"}
}