{
  "type": "Feature",
  "properties": {
    "gn:admin1_code":"1.0",
    "gn:asciiname":"Sawanla Gorah",
    "gn:country_code":"PK",
    "gn:dem":372,
    "gn:feature_class":"P",
    "gn:feature_code":"PPL",
    "gn:name":"Sawanla Gorah",
    "gn:population":0,
    "gn:timezone":"Asia/Karachi",
    "iso:country":"PK",
    "name:und_x_variant":[
        "Sanw\u0101la"
    ],
    "wof:name":"Sawanla Gorah",
    "wof:placetype":"locality"
},
  "geometry": {"coordinates":[73.71786,33.17626],"type":"Point"}
}