{
  "type": "Feature",
  "properties": {
    "gn:admin1_code":"3.0",
    "gn:asciiname":"Umar Adda",
    "gn:country_code":"PK",
    "gn:dem":353,
    "gn:feature_class":"P",
    "gn:feature_code":"PPL",
    "gn:name":"Umar Adda",
    "gn:population":0,
    "gn:timezone":"Asia/Karachi",
    "iso:country":"PK",
    "wof:name":"Umar Adda",
    "wof:placetype":"locality"
},
  "geometry": {"coordinates":[70.75229,32.44880999999999],"type":"Point"}
}