{
  "type": "Feature",
  "properties": {
    "gn:admin1_code":"2.0",
    "gn:asciiname":"New Kili Gangalzai",
    "gn:country_code":"PK",
    "gn:dem":1537,
    "gn:feature_class":"P",
    "gn:feature_code":"PPL",
    "gn:name":"New Kili Gangalzai",
    "gn:population":0,
    "gn:timezone":"Asia/Karachi",
    "iso:country":"PK",
    "wof:name":"New Kili Gangalzai",
    "wof:placetype":"locality"
},
  "geometry": {"coordinates":[66.90016999999999,30.7485],"type":"Point"}
}