{
  "type": "Feature",
  "properties": {
    "gn:admin1_code":"2.0",
    "gn:asciiname":"Salam Kili",
    "gn:country_code":"PK",
    "gn:dem":1350,
    "gn:feature_class":"P",
    "gn:feature_code":"PPL",
    "gn:name":"Salam Kili",
    "gn:population":0,
    "gn:timezone":"Asia/Karachi",
    "iso:country":"PK",
    "wof:name":"Salam Kili",
    "wof:placetype":"locality"
},
  "geometry": {"coordinates":[69.37058,31.31252000000001],"type":"Point"}
}