{
  "type": "Feature",
  "properties": {
    "gn:admin1_code":"4",
    "gn:asciiname":"Basti Arain",
    "gn:country_code":"PK",
    "gn:dem":86,
    "gn:feature_class":"P",
    "gn:feature_code":"PPL",
    "gn:name":"Basti Arain",
    "gn:population":0,
    "gn:timezone":"Asia/Karachi",
    "iso:country":"PK",
    "name:und_x_variant":[
        "Basti Ar\u0101i\u0101n"
    ],
    "wof:name":"Basti Arain",
    "wof:placetype":"locality"
},
  "geometry": {"coordinates":[70.66937,28.54423],"type":"Point"}
}