{
  "type": "Feature",
  "properties": {
    "gn:admin1_code":"4",
    "gn:asciiname":"Dalwanwala",
    "gn:country_code":"PK",
    "gn:dem":160,
    "gn:feature_class":"P",
    "gn:feature_code":"PPL",
    "gn:name":"Dalwanwala",
    "gn:population":0,
    "gn:timezone":"Asia/Karachi",
    "iso:country":"PK",
    "name:und_x_variant":[
        "Dolw\u0101nw\u0101la"
    ],
    "wof:name":"Dalwanwala",
    "wof:placetype":"locality"
},
  "geometry": {"coordinates":[71.65134999999999,31.28878],"type":"Point"}
}