{
  "type": "Feature",
  "properties": {
    "gn:admin1_code":"2.0",
    "gn:asciiname":"Shah Mir Bhotani",
    "gn:country_code":"PK",
    "gn:dem":44,
    "gn:feature_class":"P",
    "gn:feature_code":"PPL",
    "gn:name":"Shah Mir Bhotani",
    "gn:population":0,
    "gn:timezone":"Asia/Karachi",
    "iso:country":"PK",
    "wof:name":"Shah Mir Bhotani",
    "wof:placetype":"locality"
},
  "geometry": {"coordinates":[67.61709999999999,28.23484],"type":"Point"}
}