{
  "type": "Feature",
  "properties": {
    "gn:admin1_code":"3.0",
    "gn:asciiname":"Arshadabad",
    "gn:country_code":"PK",
    "gn:dem":321,
    "gn:feature_class":"P",
    "gn:feature_code":"PPL",
    "gn:name":"Arshadabad",
    "gn:population":0,
    "gn:timezone":"Asia/Karachi",
    "iso:country":"PK",
    "name:eng_x_preferred":[
        "Irsh\u0101d\u0101b\u0101d"
    ],
    "wof:name":"Arshadabad",
    "wof:placetype":"locality"
},
  "geometry": {"coordinates":[71.52472,34.04073],"type":"Point"}
}