{
  "type": "Feature",
  "properties": {
    "gn:admin1_code":"4.0",
    "gn:asciiname":"Dhangar Khund",
    "gn:country_code":"PK",
    "gn:dem":522,
    "gn:feature_class":"P",
    "gn:feature_code":"PPL",
    "gn:name":"Dhangar Khund",
    "gn:population":0,
    "gn:timezone":"Asia/Karachi",
    "iso:country":"PK",
    "name:und_x_variant":[
        "D\u0101ngal Khund"
    ],
    "wof:name":"Dhangar Khund",
    "wof:placetype":"locality"
},
  "geometry": {"coordinates":[70.36926,30.72329],"type":"Point"}
}