{
  "type": "Feature",
  "properties": {
    "gn:admin1_code":"3.0",
    "gn:asciiname":"Sahibabad",
    "gn:country_code":"PK",
    "gn:dem":344,
    "gn:feature_class":"P",
    "gn:feature_code":"PPL",
    "gn:name":"Sahibabad",
    "gn:population":0,
    "gn:timezone":"Asia/Karachi",
    "iso:country":"PK",
    "name:fas_x_preferred":[
        "\u0635\u0627\u062d\u0628\u200c\u0622\u0628\u0627\u062f"
    ],
    "name:urd_x_preferred":[
        "\u0635\u0627\u062d\u0628 \u0622\u0628\u0627\u062f"
    ],
    "wof:name":"Sahibabad",
    "wof:placetype":"locality"
},
  "geometry": {"coordinates":[72.1561,34.31633],"type":"Point"}
}