{
  "type": "Feature",
  "properties": {
    "gn:admin1_code":"3.0",
    "gn:asciiname":"Sahibabad",
    "gn:country_code":"PK",
    "gn:dem":344,
    "gn:feature_class":"P",
    "gn:feature_code":"PPL",
    "gn:name":"Sahibabad",
    "gn:population":0,
    "gn:timezone":"Asia/Karachi",
    "iso:country":"PK",
    "wof:name":"Sahibabad",
    "wof:placetype":"locality"
},
  "geometry": {"coordinates":[72.1561,34.31633],"type":"Point"}
}