{
  "type": "Feature",
  "properties": {
    "gn:admin1_code":"4",
    "gn:asciiname":"Balachwala",
    "gn:country_code":"PK",
    "gn:dem":121,
    "gn:feature_class":"P",
    "gn:feature_code":"PPL",
    "gn:name":"Balachwala",
    "gn:population":0,
    "gn:timezone":"Asia/Karachi",
    "iso:country":"PK",
    "name:und_x_variant":[
        "Chabhakpur",
        "Chhabakw\u0101la"
    ],
    "wof:name":"Balachwala",
    "wof:placetype":"locality"
},
  "geometry": {"coordinates":[70.99064,29.90419],"type":"Point"}
}