{
  "type": "Feature",
  "properties": {
    "gn:country":"PK",
    "gn:fcode":"PPL",
    "gn:pop":8247,
    "iso:country":"PK",
    "name:unk_x_variant":[
        "Us\u2019mar Ruk Malpur"
    ],
    "qs:name":"\u0100dilpur",
    "qs:photos_9r":0,
    "qs:photos_sr":0,
    "qs:pop_sr":"5",
    "wof:name":"\u0100dilpur",
    "wof:placetype":"locality",
    "wof:population":8247
},
  "geometry": {"coordinates":[69.31868,27.93697],"type":"Point"}
}