{
  "type": "Feature",
  "properties": {
    "gn:admin1_code":"3.0",
    "gn:asciiname":"Banda Saiyid Ali",
    "gn:country_code":"PK",
    "gn:dem":326,
    "gn:feature_class":"P",
    "gn:feature_code":"PPL",
    "gn:name":"Banda Saiyid Ali",
    "gn:population":0,
    "gn:timezone":"Asia/Karachi",
    "iso:country":"PK",
    "wof:name":"Banda Saiyid Ali",
    "wof:placetype":"locality"
},
  "geometry": {"coordinates":[71.78933000000001,33.44864],"type":"Point"}
}