{
  "type": "Feature",
  "properties": {
    "gn:admin1_code":"2",
    "gn:asciiname":"Shirin Narai Mazghai",
    "gn:country_code":"PK",
    "gn:dem":2379,
    "gn:feature_class":"P",
    "gn:feature_code":"PPL",
    "gn:name":"Shirin Narai Mazghai",
    "gn:population":0,
    "gn:timezone":"Asia/Karachi",
    "iso:country":"PK",
    "wof:name":"Shirin Narai Mazghai",
    "wof:placetype":"locality"
},
  "geometry": {"coordinates":[67.96222,30.36526],"type":"Point"}
}