{
  "type": "Feature",
  "properties": {
    "gn:admin1_code":"6",
    "gn:asciiname":"Jhawala",
    "gn:country_code":"PK",
    "gn:dem":466,
    "gn:feature_class":"P",
    "gn:feature_code":"PPL",
    "gn:name":"Jhawala",
    "gn:population":0,
    "gn:timezone":"Asia/Karachi",
    "iso:country":"PK",
    "wof:name":"Jhawala",
    "wof:placetype":"locality"
},
  "geometry": {"coordinates":[73.76733,33.31916],"type":"Point"}
}