{
  "type": "Feature",
  "properties": {
    "gn:admin1_code":"3.0",
    "gn:asciiname":"Sharaf Mela Khel",
    "gn:country_code":"PK",
    "gn:dem":358,
    "gn:feature_class":"P",
    "gn:feature_code":"PPL",
    "gn:name":"Sharaf Mela Khel",
    "gn:population":0,
    "gn:timezone":"Asia/Karachi",
    "iso:country":"PK",
    "name:und_x_variant":[
        "Sharaf Mala Khel"
    ],
    "wof:name":"Sharaf Mela Khel",
    "wof:placetype":"locality"
},
  "geometry": {"coordinates":[70.65916,33.0168],"type":"Point"}
}