{
  "type": "Feature",
  "properties": {
    "gn:admin1_code":"3.0",
    "gn:asciiname":"Khaki",
    "gn:country_code":"PK",
    "gn:dem":180,
    "gn:feature_class":"P",
    "gn:feature_code":"PPL",
    "gn:name":"Khaki",
    "gn:population":0,
    "gn:timezone":"Asia/Karachi",
    "iso:country":"PK",
    "name:afr_x_preferred":[
        "Kakie"
    ],
    "name:ara_x_preferred":[
        "\u062e\u0627\u0643\u064a"
    ],
    "name:bel_x_preferred":[
        "\u0425\u0430\u043a\u0456"
    ],
    "name:cat_x_preferred":[
        "Caqui"
    ],
    "name:ces_x_preferred":[
        "Khaki"
    ],
    "name:cym_x_preferred":[
        "Caci"
    ],
    "name:dan_x_preferred":[
        "Khaki"
    ],
    "name:deu_x_preferred":[
        "Khaki"
    ],
    "name:epo_x_preferred":[
        "Kakia"
    ],
    "name:eus_x_preferred":[
        "Kaki"
    ],
    "name:fas_x_preferred":[
        "\u062e\u0627\u06a9\u06cc"
    ],
    "name:fin_x_preferred":[
        "Khaki"
    ],
    "name:fra_x_preferred":[
        "Kaki"
    ],
    "name:heb_x_preferred":[
        "\u05d7\u05d0\u05e7\u05d9"
    ],
    "name:hun_x_preferred":[
        "Khaki"
    ],
    "name:ind_x_preferred":[
        "Khaki"
    ],
    "name:ita_x_preferred":[
        "Cachi"
    ],
    "name:jpn_x_preferred":[
        "\u30ab\u30fc\u30ad\u8272"
    ],
    "name:kor_x_preferred":[
        "\uce74\ud0a4\uc0c9"
    ],
    "name:nld_x_preferred":[
        "Kaki"
    ],
    "name:nno_x_preferred":[
        "Kaki"
    ],
    "name:nor_x_preferred":[
        "Khaki"
    ],
    "name:pnb_x_preferred":[
        "\u062e\u0627\u06a9\u06cc"
    ],
    "name:pol_x_preferred":[
        "Khaki"
    ],
    "name:por_x_preferred":[
        "Caqui"
    ],
    "name:rus_x_preferred":[
        "\u0425\u0430\u043a\u0438"
    ],
    "name:slk_x_preferred":[
        "Kaki"
    ],
    "name:spa_x_preferred":[
        "Caqui"
    ],
    "name:srp_x_preferred":[
        "\u041a\u0430\u043a\u0438 \u0431\u043e\u0458\u0430"
    ],
    "name:swe_x_preferred":[
        "Khaki"
    ],
    "name:tat_x_preferred":[
        "\u0425\u0430\u043a\u0438"
    ],
    "name:tha_x_preferred":[
        "\u0e2a\u0e35\u0e01\u0e32\u0e01\u0e35"
    ],
    "name:ukr_x_preferred":[
        "\u0425\u0430\u043a\u0456"
    ],
    "name:urd_x_preferred":[
        "\u062e\u0627\u06a9\u06cc"
    ],
    "name:vie_x_preferred":[
        "Kaki"
    ],
    "name:zho_x_preferred":[
        "\u5361\u5176\u8272"
    ],
    "wof:name":"Khaki",
    "wof:placetype":"locality"
},
  "geometry": {"coordinates":[71.04563,32.07583],"type":"Point"}
}