{
  "type": "Feature",
  "properties": {
    "gn:admin1_code":"4.0",
    "gn:asciiname":"Natlan Khurd",
    "gn:country_code":"PK",
    "gn:dem":286,
    "gn:feature_class":"P",
    "gn:feature_code":"PPL",
    "gn:name":"Natlan Khurd",
    "gn:population":0,
    "gn:timezone":"Asia/Karachi",
    "iso:country":"PK",
    "wof:name":"Natlan Khurd",
    "wof:placetype":"locality"
},
  "geometry": {"coordinates":[75.17001999999999,32.35729],"type":"Point"}
}