{
  "type": "Feature",
  "properties": {
    "gn:admin1_code":"4.0",
    "gn:asciiname":"Satta Saidan",
    "gn:country_code":"PK",
    "gn:dem":613,
    "gn:feature_class":"P",
    "gn:feature_code":"PPL",
    "gn:name":"Satta Saidan",
    "gn:population":0,
    "gn:timezone":"Asia/Karachi",
    "iso:country":"PK",
    "name:und_x_variant":[
        "Satta"
    ],
    "wof:name":"Satta Saidan",
    "wof:placetype":"locality"
},
  "geometry": {"coordinates":[71.43746,33.21683],"type":"Point"}
}