{
  "type": "Feature",
  "properties": {
    "gn:admin1_code":"05",
    "gn:asciiname":"Goth Rustam",
    "gn:country_code":"PK",
    "gn:dem":66,
    "gn:feature_class":"P",
    "gn:feature_code":"PPL",
    "gn:name":"Goth Rustam",
    "gn:population":0,
    "gn:timezone":"Asia/Karachi",
    "iso:country":"PK",
    "name:und_x_variant":[
        "Rustam Indhar",
        "Goth Rustam"
    ],
    "wof:name":"Goth Rustam",
    "wof:placetype":"locality"
},
  "geometry": {"coordinates":[69.25091999999999,27.76677],"type":"Point"}
}