{
  "type": "Feature",
  "properties": {
    "gn:admin1_code":"3.0",
    "gn:asciiname":"Karimabad",
    "gn:country_code":"PK",
    "gn:dem":370,
    "gn:feature_class":"P",
    "gn:feature_code":"PPL",
    "gn:name":"Karimabad",
    "gn:population":0,
    "gn:timezone":"Asia/Karachi",
    "iso:country":"PK",
    "name:aze_x_preferred":[
        "K\u0259rimabad"
    ],
    "name:deu_x_preferred":[
        "Karimabad"
    ],
    "name:fas_x_preferred":[
        "\u06a9\u0631\u06cc\u0645\u200c\u0622\u0628\u0627\u062f"
    ],
    "name:ita_x_preferred":[
        "Karimabad"
    ],
    "wof:name":"Karimabad",
    "wof:placetype":"locality"
},
  "geometry": {"coordinates":[71.45313,34.02834],"type":"Point"}
}