{
  "type": "Feature",
  "properties": {
    "gn:admin1_code":"04",
    "gn:asciiname":"Thil",
    "gn:country_code":"PK",
    "gn:dem":271,
    "gn:feature_class":"P",
    "gn:feature_code":"PPL",
    "gn:name":"Thil",
    "gn:population":0,
    "gn:timezone":"Asia/Karachi",
    "iso:country":"PK",
    "name:und_x_variant":[
        "Thil Bakohal",
        "Thil Bakol",
        "Thil"
    ],
    "wof:name":"Thil",
    "wof:placetype":"locality"
},
  "geometry": {"coordinates":[73.88351999999998,32.96022],"type":"Point"}
}