{
  "type": "Feature",
  "properties": {
    "gn:admin1_code":"04",
    "gn:asciiname":"Thil",
    "gn:country_code":"PK",
    "gn:dem":271,
    "gn:feature_class":"P",
    "gn:feature_code":"PPL",
    "gn:name":"Thil",
    "gn:population":0,
    "gn:timezone":"Asia/Karachi",
    "iso:country":"PK",
    "name:cat_x_preferred":[
        "Thil"
    ],
    "name:ceb_x_preferred":[
        "Thil"
    ],
    "name:deu_x_preferred":[
        "Thil"
    ],
    "name:fra_x_preferred":[
        "Thil"
    ],
    "name:ita_x_preferred":[
        "Thil"
    ],
    "name:ltz_x_preferred":[
        "Thil"
    ],
    "name:nds_x_preferred":[
        "Thil"
    ],
    "name:nld_x_preferred":[
        "Thil"
    ],
    "name:oci_x_preferred":[
        "Thil"
    ],
    "name:pms_x_preferred":[
        "Thil"
    ],
    "name:pol_x_preferred":[
        "Thil"
    ],
    "name:por_x_preferred":[
        "Thil"
    ],
    "name:ron_x_preferred":[
        "Thil"
    ],
    "name:rus_x_preferred":[
        "\u0422\u0438\u043b\u044c"
    ],
    "name:slk_x_preferred":[
        "Thil"
    ],
    "name:spa_x_preferred":[
        "Thil"
    ],
    "name:swe_x_preferred":[
        "Thil"
    ],
    "name:ukr_x_preferred":[
        "\u0422\u0456\u0439"
    ],
    "name:und_x_variant":[
        "Thil Bakohal",
        "Thil Bakol",
        "Thil"
    ],
    "wof:name":"Thil",
    "wof:placetype":"locality"
},
  "geometry": {"coordinates":[73.88351999999998,32.96022],"type":"Point"}
}