{
  "type": "Feature",
  "properties": {
    "gn:admin1_code":"03",
    "gn:asciiname":"Nilgram",
    "gn:country_code":"PK",
    "gn:dem":1372,
    "gn:feature_class":"P",
    "gn:feature_code":"PPL",
    "gn:name":"Nilgram",
    "gn:population":0,
    "gn:timezone":"Asia/Karachi",
    "iso:country":"PK",
    "wof:name":"Nilgram",
    "wof:placetype":"locality"
},
  "geometry": {"coordinates":[72.33398000000003,34.95172],"type":"Point"}
}