{
  "type": "Feature",
  "properties": {
    "gn:admin1_code":"4.0",
    "gn:asciiname":"Khu Murad Ali",
    "gn:country_code":"PK",
    "gn:dem":128,
    "gn:feature_class":"P",
    "gn:feature_code":"PPL",
    "gn:name":"Khu Murad Ali",
    "gn:population":0,
    "gn:timezone":"Asia/Karachi",
    "iso:country":"PK",
    "name:eng_x_preferred":[
        "Khu Murad Ali"
    ],
    "wof:name":"Khu Murad Ali",
    "wof:placetype":"locality"
},
  "geometry": {"coordinates":[71.9392,29.96849000000001],"type":"Point"}
}