{
  "type": "Feature",
  "properties": {
    "gn:admin1_code":"4.0",
    "gn:asciiname":"Linda",
    "gn:country_code":"PK",
    "gn:dem":294,
    "gn:feature_class":"P",
    "gn:feature_code":"PPL",
    "gn:name":"Linda",
    "gn:population":0,
    "gn:timezone":"Asia/Karachi",
    "iso:country":"PK",
    "wof:name":"Linda",
    "wof:placetype":"locality"
},
  "geometry": {"coordinates":[73.96878000000002,32.93677],"type":"Point"}
}