{
  "type": "Feature",
  "properties": {
    "gn:admin1_code":"5.0",
    "gn:asciiname":"Misri Mandhro",
    "gn:country_code":"PK",
    "gn:dem":7,
    "gn:feature_class":"P",
    "gn:feature_code":"PPL",
    "gn:name":"Misri Mandhro",
    "gn:population":0,
    "gn:timezone":"Asia/Karachi",
    "iso:country":"PK",
    "wof:name":"Misri Mandhro",
    "wof:placetype":"locality"
},
  "geometry": {"coordinates":[68.72974000000001,24.50396],"type":"Point"}
}