{
  "type": "Feature",
  "properties": {
    "gn:admin1_code":"3",
    "gn:asciiname":"Bharthi",
    "gn:country_code":"PK",
    "gn:dem":3231,
    "gn:feature_class":"P",
    "gn:feature_code":"PPL",
    "gn:name":"Bharthi",
    "gn:population":0,
    "gn:timezone":"Asia/Karachi",
    "iso:country":"PK",
    "wof:name":"Bharthi",
    "wof:placetype":"locality"
},
  "geometry": {"coordinates":[73.63345,34.78477],"type":"Point"}
}