{
  "type": "Feature",
  "properties": {
    "gn:admin1_code":"2.0",
    "gn:asciiname":"Lakha",
    "gn:country_code":"PK",
    "gn:dem":772,
    "gn:feature_class":"P",
    "gn:feature_code":"PPLL",
    "gn:name":"Lakha",
    "gn:population":0,
    "gn:timezone":"Asia/Karachi",
    "iso:country":"PK",
    "wof:name":"Lakha",
    "wof:placetype":"locality"
},
  "geometry": {"coordinates":[70.23984,30.85968],"type":"Point"}
}