{
  "type": "Feature",
  "properties": {
    "gn:admin1_code":"2.0",
    "gn:asciiname":"Basti Mirabad",
    "gn:country_code":"PK",
    "gn:dem":93,
    "gn:feature_class":"P",
    "gn:feature_code":"PPL",
    "gn:name":"Basti Mirabad",
    "gn:population":0,
    "gn:timezone":"Asia/Karachi",
    "iso:country":"PK",
    "name:und_x_variant":[
        "Basti M\u012br Az\u0101d"
    ],
    "wof:name":"Basti Mirabad",
    "wof:placetype":"locality"
},
  "geometry": {"coordinates":[67.78614,28.98502],"type":"Point"}
}