{
  "type": "Feature",
  "properties": {
    "gn:admin1_code":"4.0",
    "gn:asciiname":"Chak Twelve - One Right",
    "gn:country_code":"PK",
    "gn:dem":154,
    "gn:feature_class":"P",
    "gn:feature_code":"PPL",
    "gn:name":"Chak Twelve - One Right",
    "gn:population":0,
    "gn:timezone":"Asia/Karachi",
    "iso:country":"PK",
    "wof:name":"Chak Twelve - One Right",
    "wof:placetype":"locality"
},
  "geometry": {"coordinates":[73.03281,29.6805],"type":"Point"}
}