{
  "type": "Feature",
  "properties": {
    "gn:admin1_code":"4.0",
    "gn:asciiname":"Kahna Bura",
    "gn:country_code":"PK",
    "gn:dem":168,
    "gn:feature_class":"P",
    "gn:feature_code":"PPL",
    "gn:name":"Kahna Bura",
    "gn:population":0,
    "gn:timezone":"Asia/Karachi",
    "iso:country":"PK",
    "wof:name":"Kahna Bura",
    "wof:placetype":"locality"
},
  "geometry": {"coordinates":[73.67364999999999,30.19506],"type":"Point"}
}