{
  "type": "Feature",
  "properties": {
    "gn:admin1_code":"5",
    "gn:asciiname":"Brahui Goth",
    "gn:country_code":"PK",
    "gn:dem":66,
    "gn:feature_class":"P",
    "gn:feature_code":"PPL",
    "gn:name":"Brahui Goth",
    "gn:population":0,
    "gn:timezone":"Asia/Karachi",
    "iso:country":"PK",
    "name:und_x_variant":[
        "Brohi"
    ],
    "wof:name":"Brahui Goth",
    "wof:placetype":"locality"
},
  "geometry": {"coordinates":[68.54521,27.95505],"type":"Point"}
}