{
  "type": "Feature",
  "properties": {
    "gn:admin1_code":"3.0",
    "gn:asciiname":"Kaniat",
    "gn:country_code":"PK",
    "gn:dem":715,
    "gn:feature_class":"P",
    "gn:feature_code":"PPL",
    "gn:name":"Kaniat",
    "gn:population":0,
    "gn:timezone":"Asia/Karachi",
    "iso:country":"PK",
    "wof:name":"Kaniat",
    "wof:placetype":"locality"
},
  "geometry": {"coordinates":[73.01065,33.93919],"type":"Point"}
}