{
  "type": "Feature",
  "properties": {
    "gn:admin1_code":"2.0",
    "gn:asciiname":"Kili Sultan Muhammad",
    "gn:country_code":"PK",
    "gn:dem":829,
    "gn:feature_class":"P",
    "gn:feature_code":"PPL",
    "gn:name":"Kili Sultan Muhammad",
    "gn:population":0,
    "gn:timezone":"Asia/Karachi",
    "iso:country":"PK",
    "wof:name":"Kili Sultan Muhammad",
    "wof:placetype":"locality"
},
  "geometry": {"coordinates":[64.69101999999999,28.95968],"type":"Point"}
}