{
  "type": "Feature",
  "properties": {
    "gn:admin1_code":"6",
    "gn:asciiname":"Mohra Nihar",
    "gn:country_code":"PK",
    "gn:dem":1167,
    "gn:feature_class":"P",
    "gn:feature_code":"PPL",
    "gn:name":"Mohra Nihar",
    "gn:population":0,
    "gn:timezone":"Asia/Karachi",
    "iso:country":"PK",
    "name:und_x_variant":[
        "Mohra Nih\u0101r",
        "Mohra Nih\u0101re"
    ],
    "wof:name":"Mohra Nihar",
    "wof:placetype":"locality"
},
  "geometry": {"coordinates":[74.13136999999998,33.39467],"type":"Point"}
}