{
  "type": "Feature",
  "properties": {
    "gn:admin1_code":"4",
    "gn:asciiname":"Basti Chandia",
    "gn:country_code":"PK",
    "gn:dem":117,
    "gn:feature_class":"P",
    "gn:feature_code":"PPL",
    "gn:name":"Basti Chandia",
    "gn:population":0,
    "gn:timezone":"Asia/Karachi",
    "iso:country":"PK",
    "name:und_x_variant":[
        "Bala Ch\u0101ndia"
    ],
    "wof:name":"Basti Chandia",
    "wof:placetype":"locality"
},
  "geometry": {"coordinates":[70.5508,29.93332],"type":"Point"}
}