{
  "type": "Feature",
  "properties": {
    "gn:admin1_code":"2",
    "gn:asciiname":"Jaunthal",
    "gn:country_code":"PK",
    "gn:dem":986,
    "gn:feature_class":"P",
    "gn:feature_code":"PPL",
    "gn:name":"Jaunthal",
    "gn:population":0,
    "gn:timezone":"Asia/Karachi",
    "iso:country":"PK",
    "wof:name":"Jaunthal",
    "wof:placetype":"locality"
},
  "geometry": {"coordinates":[69.40391,29.76857],"type":"Point"}
}