{
  "type": "Feature",
  "properties": {
    "gn:admin1_code":"02",
    "gn:asciiname":"Saiyid Lango Ziarat",
    "gn:country_code":"PK",
    "gn:dem":1403,
    "gn:feature_class":"P",
    "gn:feature_code":"PPL",
    "gn:name":"Saiyid Lango Ziarat",
    "gn:population":0,
    "gn:timezone":"Asia/Karachi",
    "iso:country":"PK",
    "wof:name":"Saiyid Lango Ziarat",
    "wof:placetype":"locality"
},
  "geometry": {"coordinates":[66.2315,29.59148],"type":"Point"}
}