{
  "type": "Feature",
  "properties": {
    "gn:admin1_code":"4.0",
    "gn:asciiname":"Paros Khel",
    "gn:country_code":"PK",
    "gn:dem":534,
    "gn:feature_class":"P",
    "gn:feature_code":"PPL",
    "gn:name":"Paros Khel",
    "gn:population":0,
    "gn:timezone":"Asia/Karachi",
    "iso:country":"PK",
    "name:und_x_variant":[
        "Paroz Khel"
    ],
    "wof:name":"Paros Khel",
    "wof:placetype":"locality"
},
  "geometry": {"coordinates":[71.61431999999998,33.02403],"type":"Point"}
}