{
  "type": "Feature",
  "properties": {
    "gn:admin1_code":"5",
    "gn:asciiname":"Goth Gano Narejo",
    "gn:country_code":"PK",
    "gn:dem":53,
    "gn:feature_class":"P",
    "gn:feature_code":"PPL",
    "gn:name":"Goth Gano Narejo",
    "gn:population":0,
    "gn:timezone":"Asia/Karachi",
    "iso:country":"PK",
    "name:und_x_variant":[
        "Gano N\u0101ra"
    ],
    "wof:name":"Goth Gano Narejo",
    "wof:placetype":"locality"
},
  "geometry": {"coordinates":[68.51589,27.52162],"type":"Point"}
}