{
  "type": "Feature",
  "properties": {
    "gn:admin1_code":"5",
    "gn:asciiname":"Jan Muhammad Brahui",
    "gn:country_code":"PK",
    "gn:dem":27,
    "gn:feature_class":"P",
    "gn:feature_code":"PPL",
    "gn:name":"Jan Muhammad Brahui",
    "gn:population":0,
    "gn:timezone":"Asia/Karachi",
    "iso:country":"PK",
    "name:und_x_variant":[
        "H\u0101ji J\u0101n Muhammad Br\u0101hui"
    ],
    "wof:name":"Jan Muhammad Brahui",
    "wof:placetype":"locality"
},
  "geometry": {"coordinates":[68.57306,26.01967],"type":"Point"}
}