{
  "type": "Feature",
  "properties": {
    "gn:admin1_code":"3.0",
    "gn:asciiname":"Besal di Mahle",
    "gn:country_code":"PK",
    "gn:dem":3537,
    "gn:feature_class":"P",
    "gn:feature_code":"PPL",
    "gn:name":"Besal di Mahle",
    "gn:population":0,
    "gn:timezone":"Asia/Karachi",
    "iso:country":"PK",
    "wof:name":"Besal di Mahle",
    "wof:placetype":"locality"
},
  "geometry": {"coordinates":[73.93239,35.03063],"type":"Point"}
}