{
  "type": "Feature",
  "properties": {
    "gn:admin1_code":"3.0",
    "gn:asciiname":"Jandka",
    "gn:country_code":"PK",
    "gn:dem":1471,
    "gn:feature_class":"P",
    "gn:feature_code":"PPL",
    "gn:name":"Jandka",
    "gn:population":0,
    "gn:timezone":"Asia/Karachi",
    "iso:country":"PK",
    "name:und_x_variant":[
        "Jandakha",
        "Jandakka",
        "Jandka"
    ],
    "wof:name":"Jandka",
    "wof:placetype":"locality"
},
  "geometry": {"coordinates":[73.14926,34.10462],"type":"Point"}
}