{
  "type": "Feature",
  "properties": {
    "gn:admin1_code":"4.0",
    "gn:asciiname":"Basti Jarwanwali",
    "gn:country_code":"PK",
    "gn:dem":152,
    "gn:feature_class":"P",
    "gn:feature_code":"PPL",
    "gn:name":"Basti Jarwanwali",
    "gn:population":0,
    "gn:timezone":"Asia/Karachi",
    "iso:country":"PK",
    "wof:name":"Basti Jarwanwali",
    "wof:placetype":"locality"
},
  "geometry": {"coordinates":[70.97126999999998,31.11429],"type":"Point"}
}