{
  "type": "Feature",
  "properties": {
    "gn:admin1_code":"4.0",
    "gn:asciiname":"Thatti Gadian",
    "gn:country_code":"PK",
    "gn:dem":175,
    "gn:feature_class":"P",
    "gn:feature_code":"PPL",
    "gn:name":"Thatti Gadian",
    "gn:population":0,
    "gn:timezone":"Asia/Karachi",
    "iso:country":"PK",
    "name:und_x_variant":[
        "Thatti Godi\u0101n"
    ],
    "wof:name":"Thatti Gadian",
    "wof:placetype":"locality"
},
  "geometry": {"coordinates":[72.32644999999999,32.06476],"type":"Point"}
}