{
  "type": "Feature",
  "properties": {
    "gn:admin1_code":"4.0",
    "gn:asciiname":"Dhok Hakiman",
    "gn:country_code":"PK",
    "gn:dem":381,
    "gn:feature_class":"P",
    "gn:feature_code":"PPL",
    "gn:name":"Dhok Hakiman",
    "gn:population":0,
    "gn:timezone":"Asia/Karachi",
    "iso:country":"PK",
    "wof:name":"Dhok Hakiman",
    "wof:placetype":"locality"
},
  "geometry": {"coordinates":[72.07633,32.90271],"type":"Point"}
}