{
  "type": "Feature",
  "properties": {
    "gn:admin1_code":"4",
    "gn:asciiname":"Buttewala",
    "gn:country_code":"PK",
    "gn:dem":192,
    "gn:feature_class":"P",
    "gn:feature_code":"PPL",
    "gn:name":"Buttewala",
    "gn:population":0,
    "gn:timezone":"Asia/Karachi",
    "iso:country":"PK",
    "name:und_x_variant":[
        "B\u016btiw\u0101la"
    ],
    "wof:name":"Buttewala",
    "wof:placetype":"locality"
},
  "geometry": {"coordinates":[73.18080999999999,31.6082],"type":"Point"}
}