{
  "type": "Feature",
  "properties": {
    "gn:admin1_code":"2.0",
    "gn:asciiname":"Parro Bhaggi",
    "gn:country_code":"PK",
    "gn:dem":737,
    "gn:feature_class":"P",
    "gn:feature_code":"PPL",
    "gn:name":"Parro Bhaggi",
    "gn:population":0,
    "gn:timezone":"Asia/Karachi",
    "iso:country":"PK",
    "wof:name":"Parro Bhaggi",
    "wof:placetype":"locality"
},
  "geometry": {"coordinates":[69.57711999999999,29.53355],"type":"Point"}
}