{
  "type": "Feature",
  "properties": {
    "gn:admin1_code":"02",
    "gn:asciiname":"Rig Malek",
    "gn:country_code":"PK",
    "gn:dem":739,
    "gn:feature_class":"P",
    "gn:feature_code":"PPL",
    "gn:name":"R\u012bg Malek",
    "gn:population":0,
    "gn:timezone":"Asia/Karachi",
    "iso:country":"PK",
    "name:fas_x_preferred":[
        "\u0631\u06cc\u06af \u0645\u0644\u06a9"
    ],
    "name:fas_x_variant":[
        "R\u012bg Malek"
    ],
    "wof:name":"Rig Malek",
    "wof:placetype":"locality"
},
  "geometry": {"coordinates":[61.7303,28.7458],"type":"Point"}
}