{
  "type": "Feature",
  "properties": {
    "gn:admin1_code":"2.0",
    "gn:asciiname":"Dallo",
    "gn:country_code":"PK",
    "gn:dem":1813,
    "gn:feature_class":"P",
    "gn:feature_code":"PPL",
    "gn:name":"Dallo",
    "gn:population":0,
    "gn:timezone":"Asia/Karachi",
    "iso:country":"PK",
    "name:eng_x_preferred":[
        "Dallo"
    ],
    "name:und_x_variant":[
        "Sham\u0101li"
    ],
    "wof:name":"Dallo",
    "wof:placetype":"locality"
},
  "geometry": {"coordinates":[66.41953000000001,29.16884000000001],"type":"Point"}
}