{
  "type": "Feature",
  "properties": {
    "gn:admin1_code":"3.0",
    "gn:asciiname":"Segan",
    "gn:country_code":"PK",
    "gn:dem":1122,
    "gn:feature_class":"P",
    "gn:feature_code":"PPL",
    "gn:name":"Segan",
    "gn:population":0,
    "gn:timezone":"Asia/Karachi",
    "iso:country":"PK",
    "name:heb_x_preferred":[
        "\u05e1\u05d2\u05df \u05d4\u05db\u05d4\u05e0\u05d9\u05dd"
    ],
    "wof:name":"Segan",
    "wof:placetype":"locality"
},
  "geometry": {"coordinates":[72.89844000000002,35.0738],"type":"Point"}
}