{
  "type": "Feature",
  "properties": {
    "gn:admin1_code":"5",
    "gn:asciiname":"Kot Ahmadian",
    "gn:country_code":"PK",
    "gn:dem":15,
    "gn:feature_class":"P",
    "gn:feature_code":"PPL",
    "gn:name":"Kot Ahmadian",
    "gn:population":0,
    "gn:timezone":"Asia/Karachi",
    "iso:country":"PK",
    "name:und_x_variant":[
        "Goth Ahmad\u0101n"
    ],
    "wof:name":"Kot Ahmadian",
    "wof:placetype":"locality"
},
  "geometry": {"coordinates":[68.97544000000001,25.17532000000001],"type":"Point"}
}