{
  "type": "Feature",
  "properties": {
    "gn:admin1_code":"5",
    "gn:asciiname":"Goth Mir Ghulam Ali Khan",
    "gn:country_code":"PK",
    "gn:dem":14,
    "gn:feature_class":"P",
    "gn:feature_code":"PPL",
    "gn:name":"Goth Mir Ghulam Ali Khan",
    "gn:population":0,
    "gn:timezone":"Asia/Karachi",
    "iso:country":"PK",
    "name:und_x_variant":[
        "Goth Jal\u0101l Jatoi",
        "Goth Mir Lutf Ali Kh\u0101n"
    ],
    "wof:name":"Goth Mir Ghulam Ali Khan",
    "wof:placetype":"locality"
},
  "geometry": {"coordinates":[69.17616,25.33865],"type":"Point"}
}