{
  "type": "Feature",
  "properties": {
    "gn:admin1_code":"2",
    "gn:asciiname":"Diwan",
    "gn:country_code":"PK",
    "gn:dem":1534,
    "gn:feature_class":"P",
    "gn:feature_code":"PPL",
    "gn:name":"Diwan",
    "gn:population":0,
    "gn:timezone":"Asia/Karachi",
    "iso:country":"PK",
    "wof:name":"Diwan",
    "wof:placetype":"locality"
},
  "geometry": {"coordinates":[68.40765999999999,30.74553],"type":"Point"}
}