{
  "type": "Feature",
  "properties": {
    "gn:admin1_code":"3.0",
    "gn:asciiname":"Pharwan",
    "gn:country_code":"PK",
    "gn:dem":1325,
    "gn:feature_class":"P",
    "gn:feature_code":"PPL",
    "gn:name":"Pharwan",
    "gn:population":0,
    "gn:timezone":"Asia/Karachi",
    "iso:country":"PK",
    "name:und_x_variant":[
        "Phurwa"
    ],
    "wof:name":"Pharwan",
    "wof:placetype":"locality"
},
  "geometry": {"coordinates":[73.17718000000001,35.30314],"type":"Point"}
}