{
  "type": "Feature",
  "properties": {
    "gn:admin1_code":"4.0",
    "gn:asciiname":"Chak Thirty-nine -Gogera Distributary",
    "gn:country_code":"PK",
    "gn:dem":181,
    "gn:feature_class":"P",
    "gn:feature_code":"PPL",
    "gn:name":"Chak Thirty-nine -Gogera Distributary",
    "gn:population":0,
    "gn:timezone":"Asia/Karachi",
    "iso:country":"PK",
    "name:und_x_variant":[
        "Ahath Bah\u0101dur Chand"
    ],
    "wof:name":"Chak Thirty-nine -Gogera Distributary",
    "wof:placetype":"locality"
},
  "geometry": {"coordinates":[73.37838000000001,30.89112],"type":"Point"}
}