{
  "type": "Feature",
  "properties": {
    "gn:admin1_code":"2.0",
    "gn:asciiname":"Bandkai",
    "gn:country_code":"PK",
    "gn:dem":1515,
    "gn:feature_class":"P",
    "gn:feature_code":"PPL",
    "gn:name":"Bandkai",
    "gn:population":0,
    "gn:timezone":"Asia/Karachi",
    "iso:country":"PK",
    "wof:name":"Bandkai",
    "wof:placetype":"locality"
},
  "geometry": {"coordinates":[68.68037,30.68567],"type":"Point"}
}