{
  "type": "Feature",
  "properties": {
    "gn:admin1_code":"3",
    "gn:asciiname":"Wichkari Seri",
    "gn:country_code":"PK",
    "gn:dem":2564,
    "gn:feature_class":"P",
    "gn:feature_code":"PPL",
    "gn:name":"Wichkari Seri",
    "gn:population":0,
    "gn:timezone":"Asia/Karachi",
    "iso:country":"PK",
    "name:und_x_variant":[
        "Wichk\u0101rli Seri"
    ],
    "wof:name":"Wichkari Seri",
    "wof:placetype":"locality"
},
  "geometry": {"coordinates":[73.49292,34.80811],"type":"Point"}
}