{
  "type": "Feature",
  "properties": {
    "gn:admin1_code":"01",
    "gn:asciiname":"Khawaja Payao",
    "gn:country_code":"PK",
    "gn:dem":1487,
    "gn:feature_class":"P",
    "gn:feature_code":"PPL",
    "gn:name":"Khawaja Payao",
    "gn:population":0,
    "gn:timezone":"Asia/Karachi",
    "iso:country":"PK",
    "name:und_x_variant":[
        "Khw\u0101ja Payao"
    ],
    "wof:name":"Khawaja Payao",
    "wof:placetype":"locality"
},
  "geometry": {"coordinates":[70.72592,33.64131],"type":"Point"}
}