{
  "type": "Feature",
  "properties": {
    "gn:admin1_code":"5",
    "gn:asciiname":"Kirar Nukhrach",
    "gn:country_code":"PK",
    "gn:dem":13,
    "gn:feature_class":"P",
    "gn:feature_code":"PPL",
    "gn:name":"Kirar Nukhr\u0101ch",
    "gn:population":0,
    "gn:timezone":"Asia/Karachi",
    "iso:country":"PK",
    "wof:name":"Kirar Nukhrach",
    "wof:placetype":"locality"
},
  "geometry": {"coordinates":[69.31806,25.75],"type":"Point"}
}