{
  "type": "Feature",
  "properties": {
    "gn:admin1_code":"5",
    "gn:asciiname":"Goth Dado Rind",
    "gn:country_code":"PK",
    "gn:dem":18,
    "gn:feature_class":"P",
    "gn:feature_code":"PPL",
    "gn:name":"Goth Dado Rind",
    "gn:population":0,
    "gn:timezone":"Asia/Karachi",
    "iso:country":"PK",
    "name:und_x_variant":[
        "D\u016bdo Rind"
    ],
    "wof:name":"Goth Dado Rind",
    "wof:placetype":"locality"
},
  "geometry": {"coordinates":[68.84465,25.31097],"type":"Point"}
}