{
  "type": "Feature",
  "properties": {
    "gn:admin1_code":"4.0",
    "gn:asciiname":"Chak Hundred Seventy-three",
    "gn:country_code":"PK",
    "gn:dem":90,
    "gn:feature_class":"P",
    "gn:feature_code":"PPL",
    "gn:name":"Chak Hundred Seventy-three",
    "gn:population":0,
    "gn:timezone":"Asia/Karachi",
    "iso:country":"PK",
    "wof:name":"Chak Hundred Seventy-three",
    "wof:placetype":"locality"
},
  "geometry": {"coordinates":[70.82425000000001,28.66443],"type":"Point"}
}