{
  "type": "Feature",
  "properties": {
    "gn:admin1_code":"2.0",
    "gn:asciiname":"Momin Bazar",
    "gn:country_code":"PK",
    "gn:dem":575,
    "gn:feature_class":"P",
    "gn:feature_code":"PPL",
    "gn:name":"Momin Bazar",
    "gn:population":0,
    "gn:timezone":"Asia/Karachi",
    "iso:country":"PK",
    "wof:name":"Momin Bazar",
    "wof:placetype":"locality"
},
  "geometry": {"coordinates":[64.23966,26.02917],"type":"Point"}
}