{
  "type": "Feature",
  "properties": {
    "gn:admin1_code":"2.0",
    "gn:asciiname":"Kach Basti",
    "gn:country_code":"PK",
    "gn:dem":1566,
    "gn:feature_class":"P",
    "gn:feature_code":"PPL",
    "gn:name":"Kach Basti",
    "gn:population":0,
    "gn:timezone":"Asia/Karachi",
    "iso:country":"PK",
    "name:und_x_variant":[
        "Kach",
        "Kach Basti"
    ],
    "wof:name":"Kach Basti",
    "wof:placetype":"locality"
},
  "geometry": {"coordinates":[69.73468000000001,30.1991],"type":"Point"}
}