{
  "type": "Feature",
  "properties": {
    "gn:admin1_code":"5",
    "gn:asciiname":"Khando Mahesar",
    "gn:country_code":"PK",
    "gn:dem":53,
    "gn:feature_class":"P",
    "gn:feature_code":"PPL",
    "gn:name":"Khando Mahesar",
    "gn:population":0,
    "gn:timezone":"Asia/Karachi",
    "iso:country":"PK",
    "name:und_x_variant":[
        "K\u0101ndo Mahesar"
    ],
    "wof:name":"Khando Mahesar",
    "wof:placetype":"locality"
},
  "geometry": {"coordinates":[68.15709,27.80698],"type":"Point"}
}