{
  "type": "Feature",
  "properties": {
    "gn:admin1_code":"4.0",
    "gn:asciiname":"Jiwan Garaya I",
    "gn:country_code":"PK",
    "gn:dem":226,
    "gn:feature_class":"P",
    "gn:feature_code":"PPL",
    "gn:name":"Jiwan Garaya I",
    "gn:population":0,
    "gn:timezone":"Asia/Karachi",
    "iso:country":"PK",
    "name:und_x_variant":[
        "I\u012bwan Gor\u0101ya"
    ],
    "wof:name":"Jiwan Garaya I",
    "wof:placetype":"locality"
},
  "geometry": {"coordinates":[74.62130000000001,31.9977],"type":"Point"}
}