{
  "type": "Feature",
  "properties": {
    "gn:admin1_code":"4.0",
    "gn:asciiname":"Rehimabad",
    "gn:country_code":"PK",
    "gn:dem":210,
    "gn:feature_class":"P",
    "gn:feature_code":"PPL",
    "gn:name":"Rehimabad",
    "gn:population":0,
    "gn:timezone":"Asia/Karachi",
    "iso:country":"PK",
    "name:und_x_variant":[
        "Rah\u012bm\u0101b\u0101d"
    ],
    "wof:name":"Rehimabad",
    "wof:placetype":"locality"
},
  "geometry": {"coordinates":[74.24429000000001,31.44259000000001],"type":"Point"}
}