{
  "type": "Feature",
  "properties": {
    "gn:admin1_code":"4.0",
    "gn:asciiname":"Chak One Hundred Fifty-three Rakh Branch",
    "gn:country_code":"PK",
    "gn:dem":190,
    "gn:feature_class":"P",
    "gn:feature_code":"PPL",
    "gn:name":"Chak One Hundred Fifty-three Rakh Branch",
    "gn:population":0,
    "gn:timezone":"Asia/Karachi",
    "iso:country":"PK",
    "name:und_x_variant":[
        "Bal\u0101nw\u0101la",
        "Batianwala",
        "Chak One Hundred Fifty-Four",
        "Bhagi\u0101ra",
        "Chak One Hundred Fifty-three Rakh Branch",
        "Bhagi\u0101n"
    ],
    "wof:name":"Chak One Hundred Fifty-three Rakh Branch",
    "wof:placetype":"locality"
},
  "geometry": {"coordinates":[73.24606,31.61337],"type":"Point"}
}