{
  "type": "Feature",
  "properties": {
    "gn:admin1_code":"4.0",
    "gn:asciiname":"Chopa",
    "gn:country_code":"PK",
    "gn:dem":149,
    "gn:feature_class":"P",
    "gn:feature_code":"PPL",
    "gn:name":"Chopa",
    "gn:population":0,
    "gn:timezone":"Asia/Karachi",
    "iso:country":"PK",
    "name:ceb_x_preferred":[
        "Chopa"
    ],
    "name:spa_x_preferred":[
        "Chopa"
    ],
    "name:swe_x_preferred":[
        "Chopa"
    ],
    "name:und_x_variant":[
        "Chak Chopa"
    ],
    "wof:name":"Chopa",
    "wof:placetype":"locality"
},
  "geometry": {"coordinates":[72.92529999999999,29.913],"type":"Point"}
}