{
  "type": "Feature",
  "properties": {
    "gn:admin1_code":"5.0",
    "gn:asciiname":"Deh Two Hundred Ninety-seven",
    "gn:country_code":"PK",
    "gn:dem":14,
    "gn:feature_class":"P",
    "gn:feature_code":"PPL",
    "gn:name":"Deh Two Hundred Ninety-seven",
    "gn:population":0,
    "gn:timezone":"Asia/Karachi",
    "iso:country":"PK",
    "name:und_x_variant":[
        "Nih\u0101l Chand"
    ],
    "wof:name":"Deh Two Hundred Ninety-seven",
    "wof:placetype":"locality"
},
  "geometry": {"coordinates":[69.26739000000001,25.23565],"type":"Point"}
}