{
  "type": "Feature",
  "properties": {
    "gn:admin1_code":"5.0",
    "gn:asciiname":"Goth Darya Khan Sahtani",
    "gn:country_code":"PK",
    "gn:dem":95,
    "gn:feature_class":"P",
    "gn:feature_code":"PPL",
    "gn:name":"Goth Darya Khan Sahtani",
    "gn:population":0,
    "gn:timezone":"Asia/Karachi",
    "iso:country":"PK",
    "wof:name":"Goth Darya Khan Sahtani",
    "wof:placetype":"locality"
},
  "geometry": {"coordinates":[67.19309,25.05651],"type":"Point"}
}