{
  "type": "Feature",
  "properties": {
    "gn:admin1_code":"6",
    "gn:asciiname":"Phero",
    "gn:country_code":"PK",
    "gn:dem":923,
    "gn:feature_class":"P",
    "gn:feature_code":"PPL",
    "gn:name":"Phero",
    "gn:population":0,
    "gn:timezone":"Asia/Karachi",
    "iso:country":"PK",
    "name:und_x_variant":[
        "Phera"
    ],
    "wof:name":"Phero",
    "wof:placetype":"locality"
},
  "geometry": {"coordinates":[74.00313,33.25041],"type":"Point"}
}