{
  "type": "Feature",
  "properties": {
    "gn:admin1_code":"2.0",
    "gn:asciiname":"Kili Lashkar Khan",
    "gn:country_code":"PK",
    "gn:dem":1063,
    "gn:feature_class":"P",
    "gn:feature_code":"PPL",
    "gn:name":"Kili Lashkar Khan",
    "gn:population":0,
    "gn:timezone":"Asia/Karachi",
    "iso:country":"PK",
    "wof:name":"Kili Lashkar Khan",
    "wof:placetype":"locality"
},
  "geometry": {"coordinates":[65.74451999999999,29.00084],"type":"Point"}
}