{
  "type": "Feature",
  "properties": {
    "gn:admin1_code":"03",
    "gn:asciiname":"Lund Khwar",
    "gn:country_code":"PK",
    "gn:dem":381,
    "gn:feature_class":"P",
    "gn:feature_code":"PPL",
    "gn:name":"Lund Khwar",
    "gn:population":0,
    "gn:timezone":"Asia/Karachi",
    "iso:country":"PK",
    "name:eng_x_preferred":[
        "Landkhwar"
    ],
    "name:snd_x_preferred":[
        "\u0644\u0648\u0646\u062f \u062e\u0648\u0699"
    ],
    "name:und_x_variant":[
        "Landwar"
    ],
    "name:urd_x_preferred":[
        "\u0644\u0648\u0646\u062f \u062e\u0648\u0691"
    ],
    "wof:name":"Lund Khwar",
    "wof:placetype":"locality"
},
  "geometry": {"coordinates":[71.9808,34.38802],"type":"Point"}
}