{
  "type": "Feature",
  "properties": {
    "gn:admin1_code":"3.0",
    "gn:asciiname":"Aju",
    "gn:country_code":"PK",
    "gn:dem":1076,
    "gn:feature_class":"P",
    "gn:feature_code":"PPL",
    "gn:name":"Aju",
    "gn:population":0,
    "gn:timezone":"Asia/Karachi",
    "iso:country":"PK",
    "name:eng_x_preferred":[
        "Aju"
    ],
    "name:und_x_variant":[
        "Ajoo"
    ],
    "wof:name":"Aju",
    "wof:placetype":"locality"
},
  "geometry": {"coordinates":[71.93159,34.76085],"type":"Point"}
}