{
  "type": "Feature",
  "properties": {
    "gn:admin1_code":"3.0",
    "gn:asciiname":"Aju",
    "gn:country_code":"PK",
    "gn:dem":1076,
    "gn:feature_class":"P",
    "gn:feature_code":"PPL",
    "gn:name":"Aju",
    "gn:population":0,
    "gn:timezone":"Asia/Karachi",
    "iso:country":"PK",
    "name:eng_x_preferred":[
        "Aju"
    ],
    "name:jpn_x_preferred":[
        "\u30a2\u30b8\u30e5"
    ],
    "name:mon_x_preferred":[
        "\u0410\u0436\u0443 \u0436\u0430\u043d\u0436\u0438\u043d"
    ],
    "name:rus_x_preferred":[
        "\u0410\u0434\u0436\u0443"
    ],
    "name:und_x_variant":[
        "Ajoo"
    ],
    "name:vie_x_preferred":[
        "Aju"
    ],
    "wof:name":"Aju",
    "wof:placetype":"locality"
},
  "geometry": {"coordinates":[71.93159,34.76085],"type":"Point"}
}