{
  "type": "Feature",
  "properties": {
    "gn:admin1_code":"4.0",
    "gn:asciiname":"Butewala",
    "gn:country_code":"PK",
    "gn:dem":123,
    "gn:feature_class":"P",
    "gn:feature_code":"PPL",
    "gn:name":"Butewala",
    "gn:population":0,
    "gn:timezone":"Asia/Karachi",
    "iso:country":"PK",
    "name:und_x_variant":[
        "B\u016btew\u0101la"
    ],
    "wof:name":"Butewala",
    "wof:placetype":"locality"
},
  "geometry": {"coordinates":[71.58026,30.0969],"type":"Point"}
}