{
  "type": "Feature",
  "properties": {
    "gn:admin1_code":"4.0",
    "gn:asciiname":"Jhugge Waraich",
    "gn:country_code":"PK",
    "gn:dem":163,
    "gn:feature_class":"P",
    "gn:feature_code":"PPL",
    "gn:name":"Jhugge Waraich",
    "gn:population":0,
    "gn:timezone":"Asia/Karachi",
    "iso:country":"PK",
    "name:und_x_variant":[
        "Zawarwala Kol"
    ],
    "wof:name":"Jhugge Waraich",
    "wof:placetype":"locality"
},
  "geometry": {"coordinates":[72.35404,31.60716],"type":"Point"}
}