{
  "type": "Feature",
  "properties": {
    "gn:admin1_code":"01",
    "gn:asciiname":"Mator",
    "gn:country_code":"PK",
    "gn:dem":887,
    "gn:feature_class":"P",
    "gn:feature_code":"PPL",
    "gn:name":"Mator",
    "gn:population":0,
    "gn:timezone":"Asia/Karachi",
    "iso:country":"PK",
    "name:eng_x_preferred":[
        "M\u0101tor"
    ],
    "wof:name":"Mator",
    "wof:placetype":"locality"
},
  "geometry": {"coordinates":[71.56954,34.8474],"type":"Point"}
}