{
  "type": "Feature",
  "properties": {
    "gn:admin1_code":"4",
    "gn:asciiname":"Faizabad",
    "gn:country_code":"PK",
    "gn:dem":136,
    "gn:feature_class":"P",
    "gn:feature_code":"PPL",
    "gn:name":"Faizabad",
    "gn:population":0,
    "gn:timezone":"Asia/Karachi",
    "iso:country":"PK",
    "name:ara_x_preferred":[
        "\u0641\u0627\u064a\u0632 \u0622\u0628\u0627\u062f"
    ],
    "name:aze_x_preferred":[
        "Feyzabad"
    ],
    "name:bih_x_preferred":[
        "\u092b\u0948\u091c\u093e\u092c\u093e\u0926"
    ],
    "name:bpy_x_preferred":[
        "\u09ab\u09c8\u099c\u09be\u09ac\u09be\u09a6"
    ],
    "name:cat_x_preferred":[
        "Faizabad"
    ],
    "name:ceb_x_preferred":[
        "Faiz\u0101b\u0101d"
    ],
    "name:deu_x_preferred":[
        "Faizabad"
    ],
    "name:fas_x_preferred":[
        "\u0641\u06cc\u0636\u200c\u0622\u0628\u0627\u062f"
    ],
    "name:fra_x_preferred":[
        "Faizabad"
    ],
    "name:hin_x_preferred":[
        "\u092b\u093c\u0948\u091c\u093c\u093e\u092c\u093e\u0926"
    ],
    "name:ita_x_preferred":[
        "Faizabad"
    ],
    "name:jpn_x_preferred":[
        "\u30d5\u30a1\u30a4\u30b6\u30fc\u30d0\u30fc\u30c9"
    ],
    "name:kor_x_preferred":[
        "\ud30c\uc774\uc790\ubc14\ub4dc"
    ],
    "name:mal_x_preferred":[
        "\u0d2b\u0d48\u0d38\u0d3e\u0d2c\u0d3e\u0d26\u0d4d"
    ],
    "name:mar_x_preferred":[
        "\u092b\u0948\u091c\u093e\u092c\u093e\u0926"
    ],
    "name:mlg_x_preferred":[
        "Faizabad"
    ],
    "name:msa_x_preferred":[
        "Faizabad"
    ],
    "name:new_x_preferred":[
        "\u092b\u0948\u091c\u093e\u092c\u093e\u0926"
    ],
    "name:nld_x_preferred":[
        "Faizabad"
    ],
    "name:ori_x_preferred":[
        "\u0b2b\u0b48\u0b1c\u0b3e\u0b2c\u0b3e\u0b26"
    ],
    "name:pam_x_preferred":[
        "Faizabad"
    ],
    "name:pan_x_preferred":[
        "\u0a2b\u0a3c\u0a48\u0a1c\u0a3c\u0a3e\u0a2c\u0a3e\u0a26"
    ],
    "name:pnb_x_preferred":[
        "\u0641\u06cc\u0636 \u0622\u0628\u0627\u062f"
    ],
    "name:pol_x_preferred":[
        "Faizabad"
    ],
    "name:por_x_preferred":[
        "Faizabad"
    ],
    "name:rus_x_preferred":[
        "\u0424\u0430\u0439\u0437\u0430\u0431\u0430\u0434"
    ],
    "name:san_x_preferred":[
        "\u092b\u0948\u091c\u093e\u092c\u093e\u0926\u094d"
    ],
    "name:swe_x_preferred":[
        "Faizabad"
    ],
    "name:tam_x_preferred":[
        "\u0baa\u0bc8\u0b9a\u0bbe\u0baa\u0bbe\u0ba4\u0bcd"
    ],
    "name:tur_x_preferred":[
        "Faizabad"
    ],
    "name:ukr_x_preferred":[
        "\u0424\u0430\u0439\u0437\u0430\u0431\u0430\u0434"
    ],
    "name:urd_x_preferred":[
        "\u0641\u06cc\u0636 \u0622\u0628\u0627\u062f"
    ],
    "name:vie_x_preferred":[
        "Faizabad"
    ],
    "name:war_x_preferred":[
        "Faizabad"
    ],
    "name:zho_x_preferred":[
        "\u6cd5\u624e\u5df4\u5fb7"
    ],
    "wof:name":"Faizabad",
    "wof:placetype":"locality"
},
  "geometry": {"coordinates":[71.15594,30.58018],"type":"Point"}
}