{
  "type": "Feature",
  "properties": {
    "gn:admin1_code":"08",
    "gn:asciiname":"Phulgran",
    "gn:country_code":"PK",
    "gn:dem":615,
    "gn:feature_class":"P",
    "gn:feature_code":"PPL",
    "gn:name":"Phulgran",
    "gn:population":0,
    "gn:timezone":"Asia/Karachi",
    "iso:country":"PK",
    "name:fas_x_preferred":[
        "\u067e\u0647\u0644\u06af\u0631\u0627\u0646"
    ],
    "name:urd_x_preferred":[
        "\u067e\u06be\u0644\u06af\u0631\u0627\u06ba"
    ],
    "wof:name":"Phulgran",
    "wof:placetype":"locality"
},
  "geometry": {"coordinates":[73.2218,33.74747],"type":"Point"}
}