{
  "type": "Feature",
  "properties": {
    "gn:admin1_code":"3.0",
    "gn:asciiname":"Hathi Maira",
    "gn:country_code":"PK",
    "gn:dem":967,
    "gn:feature_class":"P",
    "gn:feature_code":"PPL",
    "gn:name":"Hathi Maira",
    "gn:population":0,
    "gn:timezone":"Asia/Karachi",
    "iso:country":"PK",
    "name:und_x_variant":[
        "Hathimera",
        "Hathi Maira"
    ],
    "wof:name":"Hathi Maira",
    "wof:placetype":"locality"
},
  "geometry": {"coordinates":[73.23716,34.39275],"type":"Point"}
}