{
  "type": "Feature",
  "properties": {
    "gn:admin1_code":"04",
    "gn:asciiname":"Thatti Maharani",
    "gn:country_code":"PK",
    "gn:dem":157,
    "gn:feature_class":"P",
    "gn:feature_code":"PPL",
    "gn:name":"Thatti Maharani",
    "gn:population":0,
    "gn:timezone":"Asia/Karachi",
    "iso:country":"PK",
    "name:und_x_variant":[
        "Thatti Mahr\u0101ni"
    ],
    "wof:name":"Thatti Maharani",
    "wof:placetype":"locality"
},
  "geometry": {"coordinates":[72.11667,31.53333],"type":"Point"}
}