{
  "type": "Feature",
  "properties": {
    "gn:admin1_code":"3",
    "gn:asciiname":"Maira",
    "gn:country_code":"PK",
    "gn:dem":912,
    "gn:feature_class":"P",
    "gn:feature_code":"PPL",
    "gn:name":"Maira",
    "gn:population":0,
    "gn:timezone":"Asia/Karachi",
    "iso:country":"PK",
    "wof:name":"Maira",
    "wof:placetype":"locality"
},
  "geometry": {"coordinates":[72.61511999999998,34.56313],"type":"Point"}
}