{
  "type": "Feature",
  "properties": {
    "gn:admin1_code":"4.0",
    "gn:asciiname":"Faridabad",
    "gn:cc2":"PK",
    "gn:country_code":"PK",
    "gn:dem":179,
    "gn:feature_class":"P",
    "gn:feature_code":"PPL",
    "gn:name":"Far\u012bd\u0101b\u0101d",
    "gn:population":0,
    "gn:timezone":"Asia/Karachi",
    "iso:country":"PK",
    "name:eng_x_preferred":[
        "Far\u012bd\u0101b\u0101d"
    ],
    "name:und_x_variant":[
        "Farida Abad"
    ],
    "wof:name":"Faridabad",
    "wof:placetype":"locality"
},
  "geometry": {"coordinates":[70.43333,29.96667],"type":"Point"}
}