{
  "type": "Feature",
  "properties": {
    "gn:admin1_code":"2.0",
    "gn:asciiname":"Mozo Bilawal",
    "gn:country_code":"PK",
    "gn:dem":1006,
    "gn:feature_class":"P",
    "gn:feature_code":"PPL",
    "gn:name":"Mozo Bilawal",
    "gn:population":0,
    "gn:timezone":"Asia/Karachi",
    "iso:country":"PK",
    "name:und_x_variant":[
        "Bilawul"
    ],
    "wof:name":"Mozo Bilawal",
    "wof:placetype":"locality"
},
  "geometry": {"coordinates":[67.03638000000001,27.91683],"type":"Point"}
}