{
  "type": "Feature",
  "properties": {
    "gn:admin1_code":"3",
    "gn:asciiname":"Gat Sar Banda",
    "gn:country_code":"PK",
    "gn:dem":1682,
    "gn:feature_class":"P",
    "gn:feature_code":"PPL",
    "gn:name":"Gat Sar Banda",
    "gn:population":0,
    "gn:timezone":"Asia/Karachi",
    "iso:country":"PK",
    "wof:name":"Gat Sar Banda",
    "wof:placetype":"locality"
},
  "geometry": {"coordinates":[72.71185,34.88403],"type":"Point"}
}