{
  "type": "Feature",
  "properties": {
    "gn:admin1_code":"4.0",
    "gn:asciiname":"Khandagh bun Chashma",
    "gn:country_code":"PK",
    "gn:dem":1843,
    "gn:feature_class":"P",
    "gn:feature_code":"PPL",
    "gn:name":"Khandagh bun Chashma",
    "gn:population":0,
    "gn:timezone":"Asia/Karachi",
    "iso:country":"PK",
    "wof:name":"Khandagh bun Chashma",
    "wof:placetype":"locality"
},
  "geometry": {"coordinates":[70.09358,30.16686],"type":"Point"}
}