{
  "type": "Feature",
  "properties": {
    "gn:admin1_code":"1",
    "gn:asciiname":"Bar Chitto",
    "gn:country_code":"PK",
    "gn:dem":672,
    "gn:feature_class":"P",
    "gn:feature_code":"PPL",
    "gn:name":"Bar Chitto",
    "gn:population":0,
    "gn:timezone":"Asia/Karachi",
    "iso:country":"PK",
    "name:und_x_variant":[
        "Bar Chitta",
        "Bar Chitto"
    ],
    "wof:name":"Bar Chitto",
    "wof:placetype":"locality"
},
  "geometry": {"coordinates":[70.07845,31.64639],"type":"Point"}
}