{
  "type": "Feature",
  "properties": {
    "gn:admin1_code":"4.0",
    "gn:asciiname":"Bhapla Kachha",
    "gn:country_code":"PK",
    "gn:dem":98,
    "gn:feature_class":"P",
    "gn:feature_code":"PPL",
    "gn:name":"Bhapla Kachha",
    "gn:population":0,
    "gn:timezone":"Asia/Karachi",
    "iso:country":"PK",
    "name:und_x_variant":[
        "Bhanra Kachcha"
    ],
    "wof:name":"Bhapla Kachha",
    "wof:placetype":"locality"
},
  "geometry": {"coordinates":[70.6233,28.99115],"type":"Point"}
}