{
  "type": "Feature",
  "properties": {
    "gn:admin1_code":"5",
    "gn:asciiname":"Chak Number Five",
    "gn:country_code":"PK",
    "gn:dem":33,
    "gn:feature_class":"P",
    "gn:feature_code":"PPL",
    "gn:name":"Chak Number Five",
    "gn:population":0,
    "gn:timezone":"Asia/Karachi",
    "iso:country":"PK",
    "name:und_x_variant":[
        "Chak Five",
        "Chak 5",
        "Chak Number Five"
    ],
    "wof:name":"Chak Number Five",
    "wof:placetype":"locality"
},
  "geometry": {"coordinates":[68.59536999999999,26.42385],"type":"Point"}
}