{
  "type": "Feature",
  "properties": {
    "gn:admin1_code":"3.0",
    "gn:asciiname":"Shahbaz Dera",
    "gn:country_code":"PK",
    "gn:dem":294,
    "gn:feature_class":"P",
    "gn:feature_code":"PPL",
    "gn:name":"Shahbaz Dera",
    "gn:population":0,
    "gn:timezone":"Asia/Karachi",
    "iso:country":"PK",
    "wof:name":"Shahbaz Dera",
    "wof:placetype":"locality"
},
  "geometry": {"coordinates":[72.2641,33.96485],"type":"Point"}
}