{
  "type": "Feature",
  "properties": {
    "gn:admin1_code":"4",
    "gn:asciiname":"Jugwala",
    "gn:country_code":"PK",
    "gn:dem":113,
    "gn:feature_class":"P",
    "gn:feature_code":"PPL",
    "gn:name":"Jugwala",
    "gn:population":0,
    "gn:timezone":"Asia/Karachi",
    "iso:country":"PK",
    "name:und_x_variant":[
        "Maghi\u0101nw\u0101li"
    ],
    "wof:name":"Jugwala",
    "wof:placetype":"locality"
},
  "geometry": {"coordinates":[70.97869,29.83388],"type":"Point"}
}