{
  "type": "Feature",
  "properties": {
    "gn:admin1_code":"5.0",
    "gn:asciiname":"Manghan jo Tar",
    "gn:country_code":"PK",
    "gn:dem":58,
    "gn:feature_class":"P",
    "gn:feature_code":"PPL",
    "gn:name":"Manghan jo Tar",
    "gn:population":0,
    "gn:timezone":"Asia/Karachi",
    "iso:country":"PK",
    "name:und_x_variant":[
        "Maggan jo Tar"
    ],
    "wof:name":"Manghan jo Tar",
    "wof:placetype":"locality"
},
  "geometry": {"coordinates":[70.63038,24.72154],"type":"Point"}
}