{
  "type": "Feature",
  "properties": {
    "gn:admin1_code":"7.0",
    "gn:asciiname":"Gotam",
    "gn:country_code":"PK",
    "gn:dem":3587,
    "gn:feature_class":"P",
    "gn:feature_code":"PPL",
    "gn:name":"Gotam",
    "gn:population":0,
    "gn:timezone":"Asia/Karachi",
    "iso:country":"PK",
    "wof:name":"Gotam",
    "wof:placetype":"locality"
},
  "geometry": {"coordinates":[74.88875,35.50849],"type":"Point"}
}