{
  "type": "Feature",
  "properties": {
    "gn:admin1_code":"6",
    "gn:asciiname":"Shekh Bela",
    "gn:country_code":"PK",
    "gn:dem":1960,
    "gn:feature_class":"P",
    "gn:feature_code":"PPL",
    "gn:name":"Shekh Bela",
    "gn:population":0,
    "gn:timezone":"Asia/Karachi",
    "iso:country":"PK",
    "name:und_x_variant":[
        "Sh\u0101kh B\u0113la",
        "Shaikh Bela"
    ],
    "wof:name":"Shekh Bela",
    "wof:placetype":"locality"
},
  "geometry": {"coordinates":[74.28706,34.81623],"type":"Point"}
}