{
  "type": "Feature",
  "properties": {
    "gn:admin1_code":"7.0",
    "gn:asciiname":"Nazbardeh",
    "gn:country_code":"PK",
    "gn:dem":2682,
    "gn:feature_class":"P",
    "gn:feature_code":"PPL",
    "gn:name":"Nazbardeh",
    "gn:population":0,
    "gn:timezone":"Asia/Karachi",
    "iso:country":"PK",
    "wof:name":"Nazbardeh",
    "wof:placetype":"locality"
},
  "geometry": {"coordinates":[73.2634,36.3974],"type":"Point"}
}