{
  "type": "Feature",
  "properties": {
    "gn:admin1_code":"4.0",
    "gn:asciiname":"Khanpur Shimali",
    "gn:country_code":"PK",
    "gn:dem":121,
    "gn:feature_class":"P",
    "gn:feature_code":"PPL",
    "gn:name":"Khanpur Shimali",
    "gn:population":0,
    "gn:timezone":"Asia/Karachi",
    "iso:country":"PK",
    "name:und_x_variant":[
        "Khanpur Shumali",
        "Khanpur Shimali"
    ],
    "wof:name":"Khanpur Shimali",
    "wof:placetype":"locality"
},
  "geometry": {"coordinates":[71.22759000000001,30.14537],"type":"Point"}
}