{
  "type": "Feature",
  "properties": {
    "gn:admin1_code":"5",
    "gn:asciiname":"Faiz Muhammad Khoso",
    "gn:country_code":"PK",
    "gn:dem":45,
    "gn:feature_class":"P",
    "gn:feature_code":"PPL",
    "gn:name":"Faiz Muhammad Khoso",
    "gn:population":0,
    "gn:timezone":"Asia/Karachi",
    "iso:country":"PK",
    "name:und_x_variant":[
        "Goth Faiz Muhammad Khosa"
    ],
    "wof:name":"Faiz Muhammad Khoso",
    "wof:placetype":"locality"
},
  "geometry": {"coordinates":[68.22065000000001,27.01551],"type":"Point"}
}