{
  "type": "Feature",
  "properties": {
    "gn:admin1_code":"04",
    "gn:asciiname":"Lehri Kalro",
    "gn:country_code":"PK",
    "gn:dem":891,
    "gn:feature_class":"P",
    "gn:feature_code":"PPL",
    "gn:name":"Lehri Kalro",
    "gn:population":0,
    "gn:timezone":"Asia/Karachi",
    "iso:country":"PK",
    "name:und_x_variant":[
        "Lahri Kal\u0101r\u0101n"
    ],
    "wof:name":"Lehri Kalro",
    "wof:placetype":"locality"
},
  "geometry": {"coordinates":[73.09694,32.78254],"type":"Point"}
}