{
  "type": "Feature",
  "properties": {
    "gn:admin1_code":"4",
    "gn:asciiname":"Akram",
    "gn:country_code":"PK",
    "gn:dem":171,
    "gn:feature_class":"P",
    "gn:feature_code":"PPL",
    "gn:name":"Akram",
    "gn:population":0,
    "gn:timezone":"Asia/Karachi",
    "iso:country":"PK",
    "name:ara_x_preferred":[
        "\u0623\u0643\u0631\u0645"
    ],
    "name:fas_x_preferred":[
        "\u0627\u06a9\u0631\u0645"
    ],
    "name:fra_x_preferred":[
        "Akram"
    ],
    "name:rus_x_preferred":[
        "\u0410\u043a\u0440\u0430\u043c"
    ],
    "wof:name":"Akram",
    "wof:placetype":"locality"
},
  "geometry": {"coordinates":[71.71755999999998,31.47456],"type":"Point"}
}