{
  "type": "Feature",
  "properties": {
    "gn:admin1_code":"2.0",
    "gn:asciiname":"Goth Faiz Muhammad Sabra",
    "gn:country_code":"PK",
    "gn:dem":64,
    "gn:feature_class":"P",
    "gn:feature_code":"PPL",
    "gn:name":"Goth Faiz Muhammad Sabra",
    "gn:population":0,
    "gn:timezone":"Asia/Karachi",
    "iso:country":"PK",
    "wof:name":"Goth Faiz Muhammad Sabra",
    "wof:placetype":"locality"
},
  "geometry": {"coordinates":[66.49593,26.04217],"type":"Point"}
}