{
  "type": "Feature",
  "properties": {
    "gn:country":"PK",
    "gn:fcode":"PPLQ",
    "gn:population":6622,
    "iso:country":"PK",
    "name:und_x_variant":[
        "Khadar Kh\u0101k"
    ],
    "qs:name":"Khadan Kh\u0101k",
    "qs:photos_9r":0,
    "qs:photos_sr":0,
    "qs:pop_sr":"5",
    "wof:name":"Khadan Kh\u0101k",
    "wof:placetype":"locality",
    "wof:population":6622
},
  "geometry": {"coordinates":[67.70846,30.74774],"type":"Point"}
}