{
  "type": "Feature",
  "properties": {
    "gn:admin1_code":"7.0",
    "gn:asciiname":"Karpur Harel",
    "gn:country_code":"PK",
    "gn:dem":3599,
    "gn:feature_class":"P",
    "gn:feature_code":"PPL",
    "gn:name":"Karpur Harel",
    "gn:population":0,
    "gn:timezone":"Asia/Karachi",
    "iso:country":"PK",
    "wof:name":"Karpur Harel",
    "wof:placetype":"locality"
},
  "geometry": {"coordinates":[75.87998,35.46122000000001],"type":"Point"}
}