{
  "type": "Feature",
  "properties": {
    "gn:admin1_code":"4.0",
    "gn:asciiname":"Basti Lar",
    "gn:country_code":"PK",
    "gn:dem":87,
    "gn:feature_class":"P",
    "gn:feature_code":"PPL",
    "gn:name":"Basti L\u0101r",
    "gn:population":0,
    "gn:timezone":"Asia/Karachi",
    "iso:country":"PK",
    "name:urd_x_preferred":[
        "Basti L\u0101r"
    ],
    "wof:name":"Basti Lar",
    "wof:placetype":"locality"
},
  "geometry": {"coordinates":[70.74306,28.75972],"type":"Point"}
}