{
  "type": "Feature",
  "properties": {
    "gn:admin1_code":"3.0",
    "gn:asciiname":"Raja Sar",
    "gn:country_code":"PK",
    "gn:dem":2887,
    "gn:feature_class":"P",
    "gn:feature_code":"PPL",
    "gn:name":"Raja Sar",
    "gn:population":0,
    "gn:timezone":"Asia/Karachi",
    "iso:country":"PK",
    "wof:name":"Raja Sar",
    "wof:placetype":"locality"
},
  "geometry": {"coordinates":[73.32415,35.05678],"type":"Point"}
}