{
  "type": "Feature",
  "properties": {
    "gn:admin1_code":"3.0",
    "gn:asciiname":"Karirosam",
    "gn:country_code":"PK",
    "gn:dem":450,
    "gn:feature_class":"P",
    "gn:feature_code":"PPL",
    "gn:name":"Karirosam",
    "gn:population":0,
    "gn:timezone":"Asia/Karachi",
    "iso:country":"PK",
    "name:und_x_variant":[
        "Karirusam",
        "K\u0101rirosam",
        "Karirosam"
    ],
    "wof:name":"Karirosam",
    "wof:placetype":"locality"
},
  "geometry": {"coordinates":[71.46046,33.30295],"type":"Point"}
}