{
  "type": "Feature",
  "properties": {
    "gn:admin1_code":"2.0",
    "gn:asciiname":"Korask",
    "gn:country_code":"PK",
    "gn:dem":1272,
    "gn:feature_class":"P",
    "gn:feature_code":"PPL",
    "gn:name":"Korask",
    "gn:population":0,
    "gn:timezone":"Asia/Karachi",
    "iso:country":"PK",
    "wof:name":"Korask",
    "wof:placetype":"locality"
},
  "geometry": {"coordinates":[65.79498000000001,27.57442],"type":"Point"}
}