{
  "type": "Feature",
  "properties": {
    "gn:admin1_code":"4.0",
    "gn:asciiname":"Chak Three Hundred Sixty-five Eastern Bar",
    "gn:country_code":"PK",
    "gn:dem":152,
    "gn:feature_class":"P",
    "gn:feature_code":"PPL",
    "gn:name":"Chak Three Hundred Sixty-five Eastern Bar",
    "gn:population":0,
    "gn:timezone":"Asia/Karachi",
    "iso:country":"PK",
    "name:und_x_variant":[
        "Ghul\u0101m Nabiw\u0101li L\u0101t"
    ],
    "wof:name":"Chak Three Hundred Sixty-five Eastern Bar",
    "wof:placetype":"locality"
},
  "geometry": {"coordinates":[72.85568000000001,30.289],"type":"Point"}
}