{
  "type": "Feature",
  "properties": {
    "gn:admin1_code":"6",
    "gn:asciiname":"Chabrian",
    "gn:country_code":"PK",
    "gn:dem":265,
    "gn:feature_class":"P",
    "gn:feature_code":"PPL",
    "gn:name":"Chabrian",
    "gn:population":0,
    "gn:timezone":"Asia/Karachi",
    "iso:country":"PK",
    "name:und_x_variant":[
        "Dhok Jaral",
        "Chabrian"
    ],
    "wof:name":"Chabrian",
    "wof:placetype":"locality"
},
  "geometry": {"coordinates":[73.78086999999999,33.08059],"type":"Point"}
}