{
  "type": "Feature",
  "properties": {
    "gn:admin1_code":"6",
    "gn:asciiname":"Kalpor",
    "gn:country_code":"PK",
    "gn:dem":1382,
    "gn:feature_class":"P",
    "gn:feature_code":"PPL",
    "gn:name":"Kalpor",
    "gn:population":0,
    "gn:timezone":"Asia/Karachi",
    "iso:country":"PK",
    "name:und_x_variant":[
        "S\u0101lkhala"
    ],
    "wof:name":"Kalpor",
    "wof:placetype":"locality"
},
  "geometry": {"coordinates":[73.88821,34.56201],"type":"Point"}
}