{
  "type": "Feature",
  "properties": {
    "gn:admin1_code":"2.0",
    "gn:asciiname":"Zero Point Tower",
    "gn:country_code":"PK",
    "gn:dem":655,
    "gn:feature_class":"P",
    "gn:feature_code":"PPL",
    "gn:name":"Zero Point Tower",
    "gn:population":0,
    "gn:timezone":"Asia/Karachi",
    "iso:country":"PK",
    "wof:name":"Zero Point Tower",
    "wof:placetype":"locality"
},
  "geometry": {"coordinates":[69.1798,28.89654],"type":"Point"}
}