{
  "type": "Feature",
  "properties": {
    "gn:admin1_code":"2.0",
    "gn:asciiname":"Kili Allahabad",
    "gn:country_code":"PK",
    "gn:dem":1522,
    "gn:feature_class":"P",
    "gn:feature_code":"PPL",
    "gn:name":"Kili Allahabad",
    "gn:population":0,
    "gn:timezone":"Asia/Karachi",
    "iso:country":"PK",
    "wof:name":"Kili Allahabad",
    "wof:placetype":"locality"
},
  "geometry": {"coordinates":[66.45626999999999,29.83204000000001],"type":"Point"}
}