{
  "type": "Feature",
  "properties": {
    "gn:admin1_code":"1.0",
    "gn:asciiname":"Sher Khel",
    "gn:country_code":"PK",
    "gn:dem":1825,
    "gn:feature_class":"P",
    "gn:feature_code":"PPL",
    "gn:name":"Sher Khel",
    "gn:population":0,
    "gn:timezone":"Asia/Karachi",
    "iso:country":"PK",
    "wof:name":"Sher Khel",
    "wof:placetype":"locality"
},
  "geometry": {"coordinates":[70.78003000000002,33.79202],"type":"Point"}
}