{
  "type": "Feature",
  "properties": {
    "gn:admin1_code":"1.0",
    "gn:asciiname":"Zanga Khel",
    "gn:country_code":"PK",
    "gn:dem":1934,
    "gn:feature_class":"P",
    "gn:feature_code":"PPL",
    "gn:name":"Zanga Khel",
    "gn:population":0,
    "gn:timezone":"Asia/Karachi",
    "iso:country":"PK",
    "name:und_x_variant":[
        "Zanka Khel"
    ],
    "wof:name":"Zanga Khel",
    "wof:placetype":"locality"
},
  "geometry": {"coordinates":[70.80436,33.75279],"type":"Point"}
}