{
  "type": "Feature",
  "properties": {
    "gn:admin1_code":"5",
    "gn:asciiname":"Goth Allah Bakhsh Dalwani",
    "gn:country_code":"PK",
    "gn:dem":12,
    "gn:feature_class":"P",
    "gn:feature_code":"PPL",
    "gn:name":"Goth Allah Bakhsh Dalwani",
    "gn:population":0,
    "gn:timezone":"Asia/Karachi",
    "iso:country":"PK",
    "name:und_x_variant":[
        "All\u0101h Bakhsh Dalw\u0101ni"
    ],
    "wof:name":"Goth Allah Bakhsh Dalwani",
    "wof:placetype":"locality"
},
  "geometry": {"coordinates":[69.63114,25.25285],"type":"Point"}
}