{
  "type": "Feature",
  "properties": {
    "gn:admin1_code":"5.0",
    "gn:asciiname":"Yaqub Brangui",
    "gn:country_code":"PK",
    "gn:dem":40,
    "gn:feature_class":"P",
    "gn:feature_code":"PPL",
    "gn:name":"Yaqub Brangui",
    "gn:population":0,
    "gn:timezone":"Asia/Karachi",
    "iso:country":"PK",
    "name:eng_x_preferred":[
        "Yaq\u016bb Brahui"
    ],
    "wof:name":"Yaqub Brangui",
    "wof:placetype":"locality"
},
  "geometry": {"coordinates":[68.0757,25.08353],"type":"Point"}
}