{
  "type": "Feature",
  "properties": {
    "gn:admin1_code":"01",
    "gn:asciiname":"Sura Khel",
    "gn:country_code":"PK",
    "gn:dem":2297,
    "gn:feature_class":"P",
    "gn:feature_code":"PPL",
    "gn:name":"Sura Khel",
    "gn:population":0,
    "gn:timezone":"Asia/Karachi",
    "iso:country":"PK",
    "wof:name":"Sura Khel",
    "wof:placetype":"locality"
},
  "geometry": {"coordinates":[69.67156999999999,32.53762],"type":"Point"}
}