{
  "type": "Feature",
  "properties": {
    "gn:admin1_code":"04",
    "gn:asciiname":"Mundi Khel",
    "gn:country_code":"PK",
    "gn:dem":246,
    "gn:feature_class":"P",
    "gn:feature_code":"PPL",
    "gn:name":"Mundi Khel",
    "gn:population":0,
    "gn:timezone":"Asia/Karachi",
    "iso:country":"PK",
    "name:und_x_variant":[
        "Mandi Khel",
        "Mundi Khel"
    ],
    "wof:name":"Mundi Khel",
    "wof:placetype":"locality"
},
  "geometry": {"coordinates":[75.04722,32.12164],"type":"Point"}
}