{
  "type": "Feature",
  "properties": {
    "gn:admin1_code":"1.0",
    "gn:asciiname":"Jane",
    "gn:country_code":"PK",
    "gn:dem":1849,
    "gn:feature_class":"P",
    "gn:feature_code":"PPL",
    "gn:name":"Jane",
    "gn:population":0,
    "gn:timezone":"Asia/Karachi",
    "iso:country":"PK",
    "name:bre_x_preferred":[
        "Jane"
    ],
    "name:deu_x_preferred":[
        "Jane"
    ],
    "name:fin_x_preferred":[
        "Jane"
    ],
    "name:fra_x_preferred":[
        "Jane"
    ],
    "name:ind_x_preferred":[
        "Jane"
    ],
    "name:ita_x_preferred":[
        "Jane"
    ],
    "name:jpn_x_preferred":[
        "\u30b8\u30a7\u30fc\u30f3"
    ],
    "name:por_x_preferred":[
        "Jane"
    ],
    "name:rus_x_preferred":[
        "\u0414\u0436\u0435\u0439\u043d"
    ],
    "name:spa_x_preferred":[
        "Jane"
    ],
    "name:und_x_variant":[
        "Janu Maya"
    ],
    "wof:name":"Jane",
    "wof:placetype":"locality"
},
  "geometry": {"coordinates":[70.86205,33.72198],"type":"Point"}
}