{
  "type": "Feature",
  "properties": {
    "gn:admin1_code":"04",
    "gn:asciiname":"Ukhanwala",
    "gn:country_code":"PK",
    "gn:dem":170,
    "gn:feature_class":"P",
    "gn:feature_code":"PPL",
    "gn:name":"Ukhanwala",
    "gn:population":0,
    "gn:timezone":"Asia/Karachi",
    "iso:country":"PK",
    "name:und_x_variant":[
        "Okanwala",
        "Thatti Shah Kamir",
        "Ukhanwala"
    ],
    "wof:name":"Ukhanwala",
    "wof:placetype":"locality"
},
  "geometry": {"coordinates":[72.35545,31.83894],"type":"Point"}
}