{
  "type": "Feature",
  "properties": {
    "gn:admin1_code":"3",
    "gn:asciiname":"Eidgah",
    "gn:country_code":"PK",
    "gn:dem":900,
    "gn:feature_class":"P",
    "gn:feature_code":"PPL",
    "gn:name":"Eidgah",
    "gn:population":0,
    "gn:timezone":"Asia/Karachi",
    "iso:country":"PK",
    "name:ben_x_preferred":[
        "\u0988\u09a6\u0997\u09be\u09b9"
    ],
    "name:dan_x_preferred":[
        "Eidgah"
    ],
    "name:deu_x_preferred":[
        "\u02bf\u012adg\u0101h"
    ],
    "name:fas_x_preferred":[
        "\u0639\u06cc\u062f\u06af\u0627\u0647"
    ],
    "name:hin_x_preferred":[
        "\u0908\u0926 \u0917\u093e\u0939"
    ],
    "name:mal_x_preferred":[
        "\u0d08\u0d26\u0d4d \u0d17\u0d3e\u0d39\u0d4d"
    ],
    "name:pan_x_preferred":[
        "\u0a08\u0a26\u0a17\u0a3e\u0a39"
    ],
    "name:snd_x_preferred":[
        "\u0639\u064a\u062f\u06af\u0627\u06be"
    ],
    "name:swe_x_preferred":[
        "Eidgah"
    ],
    "name:und_x_variant":[
        "\u012adg\u0101h"
    ],
    "name:urd_x_preferred":[
        "\u0639\u06cc\u062f \u06af\u0627\u06c1"
    ],
    "wof:name":"Eidgah",
    "wof:placetype":"locality"
},
  "geometry": {"coordinates":[73.18914000000002,34.44269],"type":"Point"}
}