{
  "type": "Feature",
  "properties": {
    "gn:admin1_code":"3",
    "gn:asciiname":"Eidgah",
    "gn:country_code":"PK",
    "gn:dem":900,
    "gn:feature_class":"P",
    "gn:feature_code":"PPL",
    "gn:name":"Eidgah",
    "gn:population":0,
    "gn:timezone":"Asia/Karachi",
    "iso:country":"PK",
    "name:und_x_variant":[
        "\u012adg\u0101h"
    ],
    "wof:name":"Eidgah",
    "wof:placetype":"locality"
},
  "geometry": {"coordinates":[73.18914000000002,34.44269],"type":"Point"}
}