{
  "type": "Feature",
  "properties": {
    "gn:admin1_code":"2.0",
    "gn:asciiname":"Rohk",
    "gn:country_code":"PK",
    "gn:dem":1482,
    "gn:feature_class":"P",
    "gn:feature_code":"PPL",
    "gn:name":"Rohk",
    "gn:population":0,
    "gn:timezone":"Asia/Karachi",
    "iso:country":"PK",
    "wof:name":"Rohk",
    "wof:placetype":"locality"
},
  "geometry": {"coordinates":[69.41873000000001,31.60065],"type":"Point"}
}