{
  "type": "Feature",
  "properties": {
    "gn:admin1_code":"5",
    "gn:asciiname":"Goth Haji Punnun Marri",
    "gn:country_code":"PK",
    "gn:dem":19,
    "gn:feature_class":"P",
    "gn:feature_code":"PPL",
    "gn:name":"Goth H\u0101ji Punn\u016bn Marri",
    "gn:population":0,
    "gn:timezone":"Asia/Karachi",
    "iso:country":"PK",
    "wof:name":"Goth Haji Punnun Marri",
    "wof:placetype":"locality"
},
  "geometry": {"coordinates":[68.95416999999999,25.54722000000001],"type":"Point"}
}