{
  "type": "Feature",
  "properties": {
    "gn:admin1_code":"4.0",
    "gn:asciiname":"Mathin",
    "gn:country_code":"PK",
    "gn:dem":429,
    "gn:feature_class":"P",
    "gn:feature_code":"PPL",
    "gn:name":"Mathin",
    "gn:population":0,
    "gn:timezone":"Asia/Karachi",
    "iso:country":"PK",
    "wof:name":"Mathin",
    "wof:placetype":"locality"
},
  "geometry": {"coordinates":[72.37796999999998,33.54178],"type":"Point"}
}