{
  "type": "Feature",
  "properties": {
    "gn:admin1_code":"5.0",
    "gn:asciiname":"Haji Nur Din Wazirani",
    "gn:country_code":"PK",
    "gn:dem":74,
    "gn:feature_class":"P",
    "gn:feature_code":"PPL",
    "gn:name":"Haji Nur Din Wazirani",
    "gn:population":0,
    "gn:timezone":"Asia/Karachi",
    "iso:country":"PK",
    "wof:name":"Haji Nur Din Wazirani",
    "wof:placetype":"locality"
},
  "geometry": {"coordinates":[69.39029000000001,28.39437],"type":"Point"}
}