{
  "type": "Feature",
  "properties": {
    "gn:admin1_code":"5",
    "gn:asciiname":"Panni Goth",
    "gn:country_code":"PK",
    "gn:dem":65,
    "gn:feature_class":"P",
    "gn:feature_code":"PPL",
    "gn:name":"Panni Goth",
    "gn:population":0,
    "gn:timezone":"Asia/Karachi",
    "iso:country":"PK",
    "name:und_x_variant":[
        "Panni",
        "Pann",
        "Panni Goth"
    ],
    "wof:name":"Panni Goth",
    "wof:placetype":"locality"
},
  "geometry": {"coordinates":[69.22951,27.81473],"type":"Point"}
}