{
  "type": "Feature",
  "properties": {
    "gn:admin1_code":"4.0",
    "gn:asciiname":"Khul Meran",
    "gn:country_code":"PK",
    "gn:dem":217,
    "gn:feature_class":"P",
    "gn:feature_code":"PPL",
    "gn:name":"Kh\u016bl Mer\u0101n",
    "gn:population":0,
    "gn:timezone":"Asia/Karachi",
    "iso:country":"PK",
    "wof:name":"Khul Meran",
    "wof:placetype":"locality"
},
  "geometry": {"coordinates":[74.34972,31.58861],"type":"Point"}
}