{
  "type": "Feature",
  "properties": {
    "gn:admin1_code":"4",
    "gn:asciiname":"Tahliwala",
    "gn:country_code":"PK",
    "gn:dem":230,
    "gn:feature_class":"P",
    "gn:feature_code":"PPL",
    "gn:name":"Tahliwala",
    "gn:population":0,
    "gn:timezone":"Asia/Karachi",
    "iso:country":"PK",
    "wof:name":"Tahliwala",
    "wof:placetype":"locality"
},
  "geometry": {"coordinates":[74.18583000000002,32.50268],"type":"Point"}
}