{
  "type": "Feature",
  "properties": {
    "gn:admin1_code":"3",
    "gn:asciiname":"Fateh",
    "gn:country_code":"PK",
    "gn:dem":177,
    "gn:feature_class":"P",
    "gn:feature_code":"PPL",
    "gn:name":"Fateh",
    "gn:population":0,
    "gn:timezone":"Asia/Karachi",
    "iso:country":"PK",
    "wof:name":"Fateh",
    "wof:placetype":"locality"
},
  "geometry": {"coordinates":[70.80356,31.75052],"type":"Point"}
}