{
  "type": "Feature",
  "properties": {
    "gn:admin1_code":"4",
    "gn:asciiname":"Chak One Hundred Sixteen Southern Branch",
    "gn:country_code":"PK",
    "gn:dem":184,
    "gn:feature_class":"P",
    "gn:feature_code":"PPL",
    "gn:name":"Chak One Hundred Sixteen Southern Branch",
    "gn:population":0,
    "gn:timezone":"Asia/Karachi",
    "iso:country":"PK",
    "name:und_x_variant":[
        "Chak One Hundred Sixteen SB"
    ],
    "wof:name":"Chak One Hundred Sixteen Southern Branch",
    "wof:placetype":"locality"
},
  "geometry": {"coordinates":[72.68704,31.90992],"type":"Point"}
}