{
  "type": "Feature",
  "properties": {
    "gn:admin1_code":"4.0",
    "gn:asciiname":"Shafiqueabad",
    "gn:country_code":"PK",
    "gn:dem":148,
    "gn:feature_class":"P",
    "gn:feature_code":"PPL",
    "gn:name":"Shafiqueabad",
    "gn:population":0,
    "gn:timezone":"Asia/Karachi",
    "iso:country":"PK",
    "name:und_x_variant":[
        "Basti Sharif\u0101b\u0101d"
    ],
    "wof:name":"Shafiqueabad",
    "wof:placetype":"locality"
},
  "geometry": {"coordinates":[72.24160000000001,30.96509],"type":"Point"}
}