{
  "type": "Feature",
  "properties": {
    "gn:admin1_code":"7.0",
    "gn:asciiname":"Beyari",
    "gn:country_code":"PK",
    "gn:dem":2154,
    "gn:feature_class":"P",
    "gn:feature_code":"PPL",
    "gn:name":"Beyari",
    "gn:population":0,
    "gn:timezone":"Asia/Karachi",
    "iso:country":"PK",
    "wof:name":"Beyari",
    "wof:placetype":"locality"
},
  "geometry": {"coordinates":[73.65969,35.73539],"type":"Point"}
}