{
  "type": "Feature",
  "properties": {
    "gn:admin1_code":"2.0",
    "gn:asciiname":"Warikha",
    "gn:country_code":"PK",
    "gn:dem":1442,
    "gn:feature_class":"P",
    "gn:feature_code":"PPL",
    "gn:name":"Warikha",
    "gn:population":0,
    "gn:timezone":"Asia/Karachi",
    "iso:country":"PK",
    "wof:name":"Warikha",
    "wof:placetype":"locality"
},
  "geometry": {"coordinates":[68.24621999999999,30.04769000000001],"type":"Point"}
}