{
  "type": "Feature",
  "properties": {
    "gn:admin1_code":"4",
    "gn:asciiname":"Phulai",
    "gn:country_code":"PK",
    "gn:dem":842,
    "gn:feature_class":"P",
    "gn:feature_code":"PPL",
    "gn:name":"Phulai",
    "gn:population":0,
    "gn:timezone":"Asia/Karachi",
    "iso:country":"PK",
    "name:und_x_variant":[
        "Ph\u016blahi"
    ],
    "wof:name":"Phulai",
    "wof:placetype":"locality"
},
  "geometry": {"coordinates":[73.10871999999998,32.76362],"type":"Point"}
}