{
  "type": "Feature",
  "properties": {
    "gn:admin1_code":"2",
    "gn:asciiname":"Mall",
    "gn:country_code":"PK",
    "gn:dem":1787,
    "gn:feature_class":"P",
    "gn:feature_code":"PPL",
    "gn:name":"Mall",
    "gn:population":0,
    "gn:timezone":"Asia/Karachi",
    "iso:country":"PK",
    "name:ceb_x_preferred":[
        "Mall"
    ],
    "name:ces_x_preferred":[
        "Mall"
    ],
    "name:deu_x_preferred":[
        "Mall"
    ],
    "name:est_x_preferred":[
        "Mall"
    ],
    "name:ita_x_preferred":[
        "Mall"
    ],
    "name:nld_x_preferred":[
        "The Mall"
    ],
    "name:ron_x_preferred":[
        "Mall"
    ],
    "name:swe_x_preferred":[
        "Mall"
    ],
    "name:und_x_variant":[
        "Mali"
    ],
    "wof:name":"Mall",
    "wof:placetype":"locality"
},
  "geometry": {"coordinates":[67.0441,29.65683],"type":"Point"}
}