{
  "type": "Feature",
  "properties": {
    "gn:admin1_code":"5",
    "gn:asciiname":"Torbun Goth",
    "gn:country_code":"PK",
    "gn:dem":61,
    "gn:feature_class":"P",
    "gn:feature_code":"PPL",
    "gn:name":"Torbun Goth",
    "gn:population":0,
    "gn:timezone":"Asia/Karachi",
    "iso:country":"PK",
    "name:und_x_variant":[
        "Wand"
    ],
    "wof:name":"Torbun Goth",
    "wof:placetype":"locality"
},
  "geometry": {"coordinates":[68.55109,27.81366],"type":"Point"}
}