{
  "type": "Feature",
  "properties": {
    "gn:admin1_code":"05",
    "gn:asciiname":"Goth Palija",
    "gn:country_code":"PK",
    "gn:dem":60,
    "gn:feature_class":"P",
    "gn:feature_code":"PPL",
    "gn:name":"Goth Palija",
    "gn:population":0,
    "gn:timezone":"Asia/Karachi",
    "iso:country":"PK",
    "name:und_x_variant":[
        "Paleja",
        "Goth Palija",
        "Pal\u012bja"
    ],
    "wof:name":"Goth Palija",
    "wof:placetype":"locality"
},
  "geometry": {"coordinates":[68.48831,27.77122],"type":"Point"}
}