{
  "type": "Feature",
  "properties": {
    "gn:admin1_code":"3",
    "gn:asciiname":"Nig",
    "gn:country_code":"PK",
    "gn:dem":1880,
    "gn:feature_class":"P",
    "gn:feature_code":"PPL",
    "gn:name":"Nig",
    "gn:population":0,
    "gn:timezone":"Asia/Karachi",
    "iso:country":"PK",
    "wof:name":"Nig",
    "wof:placetype":"locality"
},
  "geometry": {"coordinates":[73.28724,34.63156],"type":"Point"}
}