{
  "type": "Feature",
  "properties": {
    "gn:admin1_code":"5.0",
    "gn:asciiname":"Rabo Jo Goth",
    "gn:country_code":"PK",
    "gn:dem":176,
    "gn:feature_class":"P",
    "gn:feature_code":"PPL",
    "gn:name":"Rabo Jo Goth",
    "gn:population":0,
    "gn:timezone":"Asia/Karachi",
    "iso:country":"PK",
    "name:und_x_variant":[
        "Rabbu jo Goth"
    ],
    "wof:name":"Rabo Jo Goth",
    "wof:placetype":"locality"
},
  "geometry": {"coordinates":[67.3424,25.60772],"type":"Point"}
}