{
  "type": "Feature",
  "properties": {
    "gn:admin1_code":"3.0",
    "gn:asciiname":"Data Durpori Khan",
    "gn:country_code":"PK",
    "gn:dem":1630,
    "gn:feature_class":"P",
    "gn:feature_code":"PPL",
    "gn:name":"Data Durpori Khan",
    "gn:population":0,
    "gn:timezone":"Asia/Karachi",
    "iso:country":"PK",
    "wof:name":"Data Durpori Khan",
    "wof:placetype":"locality"
},
  "geometry": {"coordinates":[73.31010999999999,33.88344],"type":"Point"}
}