{
  "type": "Feature",
  "properties": {
    "gn:admin1_code":"5.0",
    "gn:asciiname":"Diwahai Ji Wand",
    "gn:country_code":"PK",
    "gn:dem":45,
    "gn:feature_class":"P",
    "gn:feature_code":"PPL",
    "gn:name":"Diwahai Ji Wand",
    "gn:population":0,
    "gn:timezone":"Asia/Karachi",
    "iso:country":"PK",
    "wof:name":"Diwahai Ji Wand",
    "wof:placetype":"locality"
},
  "geometry": {"coordinates":[69.71467,24.50867],"type":"Point"}
}