{
  "type": "Feature",
  "properties": {
    "gn:admin1_code":"5",
    "gn:asciiname":"Goth Ahmad Kahn",
    "gn:country_code":"PK",
    "gn:dem":17,
    "gn:feature_class":"P",
    "gn:feature_code":"PPL",
    "gn:name":"Goth Ahmad Kahn",
    "gn:population":0,
    "gn:timezone":"Asia/Karachi",
    "iso:country":"PK",
    "name:und_x_variant":[
        "Goth Ahmad Kh\u0101n"
    ],
    "wof:name":"Goth Ahmad Kahn",
    "wof:placetype":"locality"
},
  "geometry": {"coordinates":[68.91674,25.49404],"type":"Point"}
}