{
  "type": "Feature",
  "properties": {
    "gn:admin1_code":"4",
    "gn:asciiname":"Tarkhananwala",
    "gn:country_code":"PK",
    "gn:dem":166,
    "gn:feature_class":"P",
    "gn:feature_code":"PPL",
    "gn:name":"Tarkhananwala",
    "gn:population":0,
    "gn:timezone":"Asia/Karachi",
    "iso:country":"PK",
    "name:und_x_variant":[
        "Ch\u0101h Tarkh\u0101nw\u0101la"
    ],
    "wof:name":"Tarkhananwala",
    "wof:placetype":"locality"
},
  "geometry": {"coordinates":[71.02337,31.64008],"type":"Point"}
}