{
  "type": "Feature",
  "properties": {
    "gn:admin1_code":"3",
    "gn:asciiname":"Kundi",
    "gn:country_code":"PK",
    "gn:dem":1680,
    "gn:feature_class":"P",
    "gn:feature_code":"PPL",
    "gn:name":"Kundi",
    "gn:population":0,
    "gn:timezone":"Asia/Karachi",
    "iso:country":"PK",
    "name:ceb_x_preferred":[
        "Kundi"
    ],
    "name:swe_x_preferred":[
        "Kundi"
    ],
    "name:und_x_variant":[
        "Kandi"
    ],
    "wof:name":"Kundi",
    "wof:placetype":"locality"
},
  "geometry": {"coordinates":[73.10799,34.69103],"type":"Point"}
}