{
  "type": "Feature",
  "properties": {
    "gn:admin1_code":"7.0",
    "gn:asciiname":"Dache",
    "gn:country_code":"PK",
    "gn:dem":1873,
    "gn:feature_class":"P",
    "gn:feature_code":"PPL",
    "gn:name":"Dache",
    "gn:population":0,
    "gn:timezone":"Asia/Karachi",
    "iso:country":"PK",
    "wof:name":"Dache",
    "wof:placetype":"locality"
},
  "geometry": {"coordinates":[74.75461,35.88621],"type":"Point"}
}