{
  "type": "Feature",
  "properties": {
    "gn:admin1_code":"6",
    "gn:asciiname":"Kalial",
    "gn:country_code":"PK",
    "gn:dem":366,
    "gn:feature_class":"P",
    "gn:feature_code":"PPL",
    "gn:name":"Kalial",
    "gn:population":0,
    "gn:timezone":"Asia/Karachi",
    "iso:country":"PK",
    "name:und_x_variant":[
        "New Kalial",
        "Kalial"
    ],
    "wof:name":"Kalial",
    "wof:placetype":"locality"
},
  "geometry": {"coordinates":[73.75634000000002,33.24106],"type":"Point"}
}