{
  "type": "Feature",
  "properties": {
    "gn:admin1_code":"5.0",
    "gn:asciiname":"Goth Arkohar",
    "gn:country_code":"PK",
    "gn:dem":65,
    "gn:feature_class":"P",
    "gn:feature_code":"PPL",
    "gn:name":"Goth Arkohar",
    "gn:population":0,
    "gn:timezone":"Asia/Karachi",
    "iso:country":"PK",
    "name:und_x_variant":[
        "Arkohur",
        "\u0100r Kohar",
        "Goth Arkohar"
    ],
    "wof:name":"Goth Arkohar",
    "wof:placetype":"locality"
},
  "geometry": {"coordinates":[69.18943,27.63328],"type":"Point"}
}