{
  "type": "Feature",
  "properties": {
    "gn:admin1_code":"5",
    "gn:asciiname":"Abdur Rehman",
    "gn:country_code":"PK",
    "gn:dem":51,
    "gn:feature_class":"P",
    "gn:feature_code":"PPL",
    "gn:name":"Abdur Rehman",
    "gn:population":0,
    "gn:timezone":"Asia/Karachi",
    "iso:country":"PK",
    "name:und_x_variant":[
        "W\u0101hid Bakhsh Br\u0101hui"
    ],
    "wof:name":"Abdur Rehman",
    "wof:placetype":"locality"
},
  "geometry": {"coordinates":[68.08507,28.03368],"type":"Point"}
}