{
  "type": "Feature",
  "properties": {
    "gn:admin1_code":"1",
    "gn:asciiname":"Dwe Gharlamai",
    "gn:country_code":"PK",
    "gn:dem":1512,
    "gn:feature_class":"P",
    "gn:feature_code":"PPL",
    "gn:name":"Dwe Gharlamai",
    "gn:population":0,
    "gn:timezone":"Asia/Karachi",
    "iso:country":"PK",
    "wof:name":"Dwe Gharlamai",
    "wof:placetype":"locality"
},
  "geometry": {"coordinates":[69.94136999999999,32.58583],"type":"Point"}
}