{
  "type": "Feature",
  "properties": {
    "gn:admin1_code":"04",
    "gn:asciiname":"Qila Mihan Singh",
    "gn:country_code":"PK",
    "gn:dem":224,
    "gn:feature_class":"P",
    "gn:feature_code":"PPL",
    "gn:name":"Qila Mihan Singh",
    "gn:population":0,
    "gn:timezone":"Asia/Karachi",
    "iso:country":"PK",
    "name:fas_x_preferred":[
        "\u0642\u0644\u0639\u0647 \u0645\u06cc\u0627\u0646 \u0633\u06cc\u0646\u06af"
    ],
    "name:und_x_variant":[
        "Qila Mian Singh",
        "Qila Mihan Singh"
    ],
    "name:urd_x_preferred":[
        "\u0642\u0644\u0639\u06c1 \u0645\u06cc\u0627\u0646 \u0633\u0646\u06af\u06be"
    ],
    "wof:name":"Qila Mihan Singh",
    "wof:placetype":"locality"
},
  "geometry": {"coordinates":[74.07764,32.10226],"type":"Point"}
}