{
  "type": "Feature",
  "properties": {
    "gn:admin1_code":"3.0",
    "gn:asciiname":"Halmaira Bala",
    "gn:country_code":"PK",
    "gn:dem":1208,
    "gn:feature_class":"P",
    "gn:feature_code":"PPL",
    "gn:name":"Halmaira Bala",
    "gn:population":0,
    "gn:timezone":"Asia/Karachi",
    "iso:country":"PK",
    "wof:name":"Halmaira Bala",
    "wof:placetype":"locality"
},
  "geometry": {"coordinates":[73.22315,34.24836],"type":"Point"}
}