{
  "type": "Feature",
  "properties": {
    "gn:admin1_code":"3.0",
    "gn:asciiname":"Macchhna",
    "gn:country_code":"PK",
    "gn:dem":1229,
    "gn:feature_class":"P",
    "gn:feature_code":"PPL",
    "gn:name":"Macchhna",
    "gn:population":0,
    "gn:timezone":"Asia/Karachi",
    "iso:country":"PK",
    "wof:name":"Macchhna",
    "wof:placetype":"locality"
},
  "geometry": {"coordinates":[73.30513000000001,33.92196],"type":"Point"}
}