{
  "type": "Feature",
  "properties": {
    "gn:admin1_code":"4",
    "gn:asciiname":"Warranwala Khu",
    "gn:country_code":"PK",
    "gn:dem":167,
    "gn:feature_class":"P",
    "gn:feature_code":"PPL",
    "gn:name":"Warranwala Khu",
    "gn:population":0,
    "gn:timezone":"Asia/Karachi",
    "iso:country":"PK",
    "name:und_x_variant":[
        "Naorang Jatr\u0101w\u0101la"
    ],
    "wof:name":"Warranwala Khu",
    "wof:placetype":"locality"
},
  "geometry": {"coordinates":[71.11739,31.48994],"type":"Point"}
}