{
  "type": "Feature",
  "properties": {
    "gn:admin1_code":"4.0",
    "gn:asciiname":"Dhok Kumbar",
    "gn:country_code":"PK",
    "gn:dem":385,
    "gn:feature_class":"P",
    "gn:feature_code":"PPL",
    "gn:name":"Dhok Kumbar",
    "gn:population":0,
    "gn:timezone":"Asia/Karachi",
    "iso:country":"PK",
    "name:und_x_variant":[
        "Dhok Ghumh\u0101r",
        "Dhok Ghumb\u0101r",
        "Dhok Kumbar"
    ],
    "wof:name":"Dhok Kumbar",
    "wof:placetype":"locality"
},
  "geometry": {"coordinates":[72.26834000000002,33.19177],"type":"Point"}
}