{
  "type": "Feature",
  "properties": {
    "gn:admin1_code":"03",
    "gn:asciiname":"Barwal",
    "gn:country_code":"PK",
    "gn:dem":624,
    "gn:feature_class":"P",
    "gn:feature_code":"PPL",
    "gn:name":"Barwal",
    "gn:population":0,
    "gn:timezone":"Asia/Karachi",
    "iso:country":"PK",
    "name:eng_x_preferred":[
        "Barwal"
    ],
    "wof:name":"Barwal",
    "wof:placetype":"locality"
},
  "geometry": {"coordinates":[71.81395999999999,34.59647],"type":"Point"}
}