{
  "type": "Feature",
  "properties": {
    "gn:admin1_code":"4",
    "gn:asciiname":"Chak One Hundred Seventeen B Thal Development Authority",
    "gn:country_code":"PK",
    "gn:dem":150,
    "gn:feature_class":"P",
    "gn:feature_code":"PPL",
    "gn:name":"Chak One Hundred Seventeen B Thal Development Authority",
    "gn:population":0,
    "gn:timezone":"Asia/Karachi",
    "iso:country":"PK",
    "name:und_x_variant":[
        "W\u0101ra Gishkori",
        "Chak Number One Hundred Seventeen B",
        "Chak One Hundred Seventeen B Thal Development Authority",
        "Chak No 117 B"
    ],
    "wof:name":"Chak One Hundred Seventeen B Thal Development Authority",
    "wof:placetype":"locality"
},
  "geometry": {"coordinates":[70.9374,31.03792],"type":"Point"}
}