{
  "type": "Feature",
  "properties": {
    "gn:admin1_code":"5.0",
    "gn:asciiname":"Goth Karani",
    "gn:country_code":"PK",
    "gn:dem":51,
    "gn:feature_class":"P",
    "gn:feature_code":"PPL",
    "gn:name":"Goth Karani",
    "gn:population":0,
    "gn:timezone":"Asia/Karachi",
    "iso:country":"PK",
    "name:und_x_variant":[
        "K\u0101r\u0101ni"
    ],
    "wof:name":"Goth Karani",
    "wof:placetype":"locality"
},
  "geometry": {"coordinates":[68.11196,27.26224],"type":"Point"}
}