{
  "type": "Feature",
  "properties": {
    "gn:admin1_code":"4.0",
    "gn:asciiname":"Kot Mian Nur Muhammad",
    "gn:country_code":"PK",
    "gn:dem":84,
    "gn:feature_class":"P",
    "gn:feature_code":"PPL",
    "gn:name":"Kot Mian Nur Muhammad",
    "gn:population":0,
    "gn:timezone":"Asia/Karachi",
    "iso:country":"PK",
    "wof:name":"Kot Mian Nur Muhammad",
    "wof:placetype":"locality"
},
  "geometry": {"coordinates":[70.63618000000002,28.54127],"type":"Point"}
}