{
  "type": "Feature",
  "properties": {
    "gn:admin1_code":"2",
    "gn:asciiname":"Muklawai",
    "gn:country_code":"PK",
    "gn:dem":1672,
    "gn:feature_class":"P",
    "gn:feature_code":"PPL",
    "gn:name":"Muklawai",
    "gn:population":0,
    "gn:timezone":"Asia/Karachi",
    "iso:country":"PK",
    "name:und_x_variant":[
        "Muklaw\u0101i"
    ],
    "wof:name":"Muklawai",
    "wof:placetype":"locality"
},
  "geometry": {"coordinates":[68.28769,30.279],"type":"Point"}
}