{
  "type": "Feature",
  "properties": {
    "gn:admin1_code":"7.0",
    "gn:asciiname":"Khalti",
    "gn:country_code":"PK",
    "gn:dem":2327,
    "gn:feature_class":"P",
    "gn:feature_code":"PPL",
    "gn:name":"Khalti",
    "gn:population":0,
    "gn:timezone":"Asia/Karachi",
    "iso:country":"PK",
    "name:fas_x_preferred":[
        "\u062e\u0627\u0644\u062a\u06cc"
    ],
    "name:und_x_variant":[
        "Khutti"
    ],
    "wof:name":"Khalti",
    "wof:placetype":"locality"
},
  "geometry": {"coordinates":[75.70761999999998,35.4761],"type":"Point"}
}