{
  "type": "Feature",
  "properties": {
    "gn:admin1_code":"3.0",
    "gn:asciiname":"Khora Kalle",
    "gn:country_code":"PK",
    "gn:dem":301,
    "gn:feature_class":"P",
    "gn:feature_code":"PPL",
    "gn:name":"Khora Kalle",
    "gn:population":0,
    "gn:timezone":"Asia/Karachi",
    "iso:country":"PK",
    "wof:name":"Khora Kalle",
    "wof:placetype":"locality"
},
  "geometry": {"coordinates":[71.94743000000003,34.13004],"type":"Point"}
}