{
  "type": "Feature",
  "properties": {
    "gn:admin1_code":"3.0",
    "gn:asciiname":"Pacha Kalle Banda",
    "gn:country_code":"PK",
    "gn:dem":1714,
    "gn:feature_class":"P",
    "gn:feature_code":"PPL",
    "gn:name":"Pacha Kalle Banda",
    "gn:population":0,
    "gn:timezone":"Asia/Karachi",
    "iso:country":"PK",
    "wof:name":"Pacha Kalle Banda",
    "wof:placetype":"locality"
},
  "geometry": {"coordinates":[72.21364,34.95206],"type":"Point"}
}