{
  "type": "Feature",
  "properties": {
    "gn:admin1_code":"5.0",
    "gn:asciiname":"Goth Nur Muhammad Uhar",
    "gn:country_code":"PK",
    "gn:dem":37,
    "gn:feature_class":"P",
    "gn:feature_code":"PPL",
    "gn:name":"Goth Nur Muhammad Uhar",
    "gn:population":0,
    "gn:timezone":"Asia/Karachi",
    "iso:country":"PK",
    "wof:name":"Goth Nur Muhammad Uhar",
    "wof:placetype":"locality"
},
  "geometry": {"coordinates":[68.00414000000001,26.29945],"type":"Point"}
}