{
  "type": "Feature",
  "properties": {
    "gn:admin1_code":"2.0",
    "gn:asciiname":"Lease Number Seven Colony",
    "gn:country_code":"PK",
    "gn:dem":1958,
    "gn:feature_class":"P",
    "gn:feature_code":"PPL",
    "gn:name":"Lease Number Seven Colony",
    "gn:population":0,
    "gn:timezone":"Asia/Karachi",
    "iso:country":"PK",
    "wof:name":"Lease Number Seven Colony",
    "wof:placetype":"locality"
},
  "geometry": {"coordinates":[67.25229,30.09354],"type":"Point"}
}