{
  "type": "Feature",
  "properties": {
    "gn:admin1_code":"3.0",
    "gn:asciiname":"Khan Khelan",
    "gn:country_code":"PK",
    "gn:dem":297,
    "gn:feature_class":"P",
    "gn:feature_code":"PPL",
    "gn:name":"Khan Khelan",
    "gn:population":0,
    "gn:timezone":"Asia/Karachi",
    "iso:country":"PK",
    "wof:name":"Khan Khelan",
    "wof:placetype":"locality"
},
  "geometry": {"coordinates":[70.7683,32.75906],"type":"Point"}
}