{
  "type": "Feature",
  "properties": {
    "gn:admin1_code":"4",
    "gn:asciiname":"Rangra",
    "gn:country_code":"PK",
    "gn:dem":264,
    "gn:feature_class":"P",
    "gn:feature_code":"PPL",
    "gn:name":"Rangra",
    "gn:population":0,
    "gn:timezone":"Asia/Karachi",
    "iso:country":"PK",
    "wof:name":"Rangra",
    "wof:placetype":"locality"
},
  "geometry": {"coordinates":[74.43724,32.73007],"type":"Point"}
}