{
  "type": "Feature",
  "properties": {
    "gn:admin1_code":"7.0",
    "gn:asciiname":"Mumargin",
    "gn:country_code":"PK",
    "gn:dem":2846,
    "gn:feature_class":"P",
    "gn:feature_code":"PPL",
    "gn:name":"Mumargin",
    "gn:population":0,
    "gn:timezone":"Asia/Karachi",
    "iso:country":"PK",
    "name:und_x_variant":[
        "Mumargia"
    ],
    "wof:name":"Mumargin",
    "wof:placetype":"locality"
},
  "geometry": {"coordinates":[73.95201,36.50432],"type":"Point"}
}