{
  "type": "Feature",
  "properties": {
    "gn:admin1_code":"4.0",
    "gn:asciiname":"Chak Miara",
    "gn:country_code":"PK",
    "gn:dem":264,
    "gn:feature_class":"P",
    "gn:feature_code":"PPL",
    "gn:name":"Chak Mi\u0101ra",
    "gn:population":0,
    "gn:timezone":"Asia/Karachi",
    "iso:country":"PK",
    "wof:name":"Chak Miara",
    "wof:placetype":"locality"
},
  "geometry": {"coordinates":[73.95336999999998,32.75324000000001],"type":"Point"}
}