{
  "type": "Feature",
  "properties": {
    "gn:admin1_code":"1.0",
    "gn:asciiname":"Zor Kalle",
    "gn:country_code":"PK",
    "gn:dem":2173,
    "gn:feature_class":"P",
    "gn:feature_code":"PPL",
    "gn:name":"Zor Kalle",
    "gn:population":0,
    "gn:timezone":"Asia/Karachi",
    "iso:country":"PK",
    "name:und_x_variant":[
        "Zor Tsappai"
    ],
    "wof:name":"Zor Kalle",
    "wof:placetype":"locality"
},
  "geometry": {"coordinates":[70.7979,33.69505],"type":"Point"}
}