{
  "type": "Feature",
  "properties": {
    "gn:admin1_code":"2.0",
    "gn:asciiname":"Kili Haji Hayat Khan",
    "gn:country_code":"PK",
    "gn:dem":1764,
    "gn:feature_class":"P",
    "gn:feature_code":"PPL",
    "gn:name":"Kili Haji Hayat Khan",
    "gn:population":0,
    "gn:timezone":"Asia/Karachi",
    "iso:country":"PK",
    "name:und_x_variant":[
        "Haji Hay\u0101t Kh\u0101n"
    ],
    "wof:name":"Kili Haji Hayat Khan",
    "wof:placetype":"locality"
},
  "geometry": {"coordinates":[66.63325999999999,29.35424],"type":"Point"}
}