{
  "type": "Feature",
  "properties": {
    "gn:admin1_code":"4",
    "gn:asciiname":"Chah Qaim Dinwala",
    "gn:country_code":"PK",
    "gn:dem":126,
    "gn:feature_class":"P",
    "gn:feature_code":"PPL",
    "gn:name":"Chah Qaim Dinwala",
    "gn:population":0,
    "gn:timezone":"Asia/Karachi",
    "iso:country":"PK",
    "name:und_x_variant":[
        "Ch\u0101h Qaim D\u012bnw\u0101la"
    ],
    "wof:name":"Chah Qaim Dinwala",
    "wof:placetype":"locality"
},
  "geometry": {"coordinates":[71.67289,30.12754],"type":"Point"}
}