{
  "type": "Feature",
  "properties": {
    "gn:admin1_code":"05",
    "gn:asciiname":"Rahki",
    "gn:country_code":"PK",
    "gn:dem":11,
    "gn:feature_class":"P",
    "gn:feature_code":"PPL",
    "gn:name":"Rahki",
    "gn:population":0,
    "gn:timezone":"Asia/Karachi",
    "iso:country":"PK",
    "name:und_x_variant":[
        "Rahiki",
        "Rahki"
    ],
    "wof:name":"Rahki",
    "wof:placetype":"locality"
},
  "geometry": {"coordinates":[68.55136,24.76398],"type":"Point"}
}