{
  "type": "Feature",
  "properties": {
    "gn:admin1_code":"4.0",
    "gn:asciiname":"Beata",
    "gn:country_code":"PK",
    "gn:dem":188,
    "gn:feature_class":"P",
    "gn:feature_code":"PPL",
    "gn:name":"Beata",
    "gn:population":0,
    "gn:timezone":"Asia/Karachi",
    "iso:country":"PK",
    "name:fin_x_preferred":[
        "Beata"
    ],
    "name:lit_x_preferred":[
        "Beata"
    ],
    "name:pol_x_preferred":[
        "Beata"
    ],
    "name:rus_x_preferred":[
        "\u0411\u0435\u0430\u0442\u0430"
    ],
    "name:swe_x_preferred":[
        "Beata"
    ],
    "name:und_x_variant":[
        "Beta"
    ],
    "name:vie_x_preferred":[
        "Beata"
    ],
    "wof:name":"Beata",
    "wof:placetype":"locality"
},
  "geometry": {"coordinates":[70.10746999999999,29.63939],"type":"Point"}
}