{
  "type": "Feature",
  "properties": {
    "gn:admin1_code":"4.0",
    "gn:asciiname":"Beata",
    "gn:country_code":"PK",
    "gn:dem":188,
    "gn:feature_class":"P",
    "gn:feature_code":"PPL",
    "gn:name":"Beata",
    "gn:population":0,
    "gn:timezone":"Asia/Karachi",
    "iso:country":"PK",
    "name:und_x_variant":[
        "Beta"
    ],
    "wof:name":"Beata",
    "wof:placetype":"locality"
},
  "geometry": {"coordinates":[70.10746999999999,29.63939],"type":"Point"}
}