{
  "type": "Feature",
  "properties": {
    "gn:admin1_code":"4",
    "gn:asciiname":"Pankhaiter",
    "gn:country_code":"PK",
    "gn:dem":725,
    "gn:feature_class":"P",
    "gn:feature_code":"PPL",
    "gn:name":"Pankhaiter",
    "gn:population":0,
    "gn:timezone":"Asia/Karachi",
    "iso:country":"PK",
    "name:und_x_variant":[
        "Pankhetar"
    ],
    "wof:name":"Pankhaiter",
    "wof:placetype":"locality"
},
  "geometry": {"coordinates":[72.06359999999999,32.46289],"type":"Point"}
}