{
  "type": "Feature",
  "properties": {
    "gn:admin1_code":"5",
    "gn:asciiname":"Genda Khaqi",
    "gn:country_code":"PK",
    "gn:dem":61,
    "gn:feature_class":"P",
    "gn:feature_code":"PPL",
    "gn:name":"Genda Khaqi",
    "gn:population":0,
    "gn:timezone":"Asia/Karachi",
    "iso:country":"PK",
    "name:und_x_variant":[
        "Gende Khoq\u012b"
    ],
    "wof:name":"Genda Khaqi",
    "wof:placetype":"locality"
},
  "geometry": {"coordinates":[69.09565000000001,27.70874],"type":"Point"}
}