{
  "type": "Feature",
  "properties": {
    "gn:admin1_code":"5.0",
    "gn:asciiname":"Goth Peroz Shah",
    "gn:country_code":"PK",
    "gn:dem":50,
    "gn:feature_class":"P",
    "gn:feature_code":"PPL",
    "gn:name":"Goth Peroz Shah",
    "gn:population":0,
    "gn:timezone":"Asia/Karachi",
    "iso:country":"PK",
    "name:und_x_variant":[
        "Perozshah",
        "F\u012broz Sh\u0101h",
        "Goth Parvez Sh\u0101h",
        "Goth Peroz Shah"
    ],
    "wof:name":"Goth Peroz Shah",
    "wof:placetype":"locality"
},
  "geometry": {"coordinates":[67.96554999999999,27.10445],"type":"Point"}
}