{
  "type": "Feature",
  "properties": {
    "gn:admin1_code":"4.0",
    "gn:asciiname":"Chak One Gajjiani B",
    "gn:country_code":"PK",
    "gn:dem":151,
    "gn:feature_class":"P",
    "gn:feature_code":"PPL",
    "gn:name":"Chak One Gajjiani B",
    "gn:population":0,
    "gn:timezone":"Asia/Karachi",
    "iso:country":"PK",
    "name:und_x_variant":[
        "Jattanwala"
    ],
    "wof:name":"Chak One Gajjiani B",
    "wof:placetype":"locality"
},
  "geometry": {"coordinates":[72.99794,29.8789],"type":"Point"}
}