{
  "type": "Feature",
  "properties": {
    "gn:admin1_code":"3",
    "gn:asciiname":"Bargai",
    "gn:country_code":"PK",
    "gn:dem":2292,
    "gn:feature_class":"P",
    "gn:feature_code":"PPL",
    "gn:name":"Bargai",
    "gn:population":0,
    "gn:timezone":"Asia/Karachi",
    "iso:country":"PK",
    "name:eng_x_preferred":[
        "Bragai"
    ],
    "wof:name":"Bargai",
    "wof:placetype":"locality"
},
  "geometry": {"coordinates":[71.59917,35.03604],"type":"Point"}
}