{
  "type": "Feature",
  "properties": {
    "gn:admin1_code":"5",
    "gn:asciiname":"Goth Qamaruddin Pahaur",
    "gn:country_code":"PK",
    "gn:dem":64,
    "gn:feature_class":"P",
    "gn:feature_code":"PPL",
    "gn:name":"Goth Qamaruddin Pahaur",
    "gn:population":0,
    "gn:timezone":"Asia/Karachi",
    "iso:country":"PK",
    "name:und_x_variant":[
        "M\u012br Pauhar"
    ],
    "wof:name":"Goth Qamaruddin Pahaur",
    "wof:placetype":"locality"
},
  "geometry": {"coordinates":[68.8556,28.07172000000001],"type":"Point"}
}