{
  "type": "Feature",
  "properties": {
    "gn:admin1_code":"1.0",
    "gn:asciiname":"Mughal Ghunda",
    "gn:country_code":"PK",
    "gn:dem":1530,
    "gn:feature_class":"P",
    "gn:feature_code":"PPL",
    "gn:name":"Mughal Ghunda",
    "gn:population":0,
    "gn:timezone":"Asia/Karachi",
    "iso:country":"PK",
    "wof:name":"Mughal Ghunda",
    "wof:placetype":"locality"
},
  "geometry": {"coordinates":[69.46993000000001,32.31525999999999],"type":"Point"}
}