{
  "type": "Feature",
  "properties": {
    "gn:admin1_code":"3.0",
    "gn:asciiname":"Mianji Khel",
    "gn:country_code":"PK",
    "gn:dem":405,
    "gn:feature_class":"P",
    "gn:feature_code":"PPL",
    "gn:name":"Mianji Khel",
    "gn:population":0,
    "gn:timezone":"Asia/Karachi",
    "iso:country":"PK",
    "wof:name":"Mianji Khel",
    "wof:placetype":"locality"
},
  "geometry": {"coordinates":[70.5707,33.00388],"type":"Point"}
}