{
  "type": "Feature",
  "properties": {
    "gn:admin1_code":"2",
    "gn:asciiname":"Sangas",
    "gn:country_code":"PK",
    "gn:dem":1419,
    "gn:feature_class":"P",
    "gn:feature_code":"PPL",
    "gn:name":"Sangas",
    "gn:population":0,
    "gn:timezone":"Asia/Karachi",
    "iso:country":"PK",
    "wof:name":"Sangas",
    "wof:placetype":"locality"
},
  "geometry": {"coordinates":[66.66275999999999,28.05611],"type":"Point"}
}