{
  "type": "Feature",
  "properties": {
    "gn:admin1_code":"2.0",
    "gn:asciiname":"Taraki",
    "gn:country_code":"PK",
    "gn:dem":1738,
    "gn:feature_class":"P",
    "gn:feature_code":"PPL",
    "gn:name":"Taraki",
    "gn:population":0,
    "gn:timezone":"Asia/Karachi",
    "iso:country":"PK",
    "name:ceb_x_preferred":[
        "Taraki"
    ],
    "name:swe_x_preferred":[
        "Taraki"
    ],
    "name:und_x_variant":[
        "Kili Tarakai"
    ],
    "wof:name":"Taraki",
    "wof:placetype":"locality"
},
  "geometry": {"coordinates":[69.82534,31.42031],"type":"Point"}
}