{
  "type": "Feature",
  "properties": {
    "gn:admin1_code":"3.0",
    "gn:asciiname":"Kotka Sadiq Khan",
    "gn:country_code":"PK",
    "gn:dem":347,
    "gn:feature_class":"P",
    "gn:feature_code":"PPL",
    "gn:name":"Kotka Sadiq Khan",
    "gn:population":0,
    "gn:timezone":"Asia/Karachi",
    "iso:country":"PK",
    "name:und_x_variant":[
        "Kotka S\u0101dki Kh\u0101n",
        "Kotka Sadiq Khan"
    ],
    "wof:name":"Kotka Sadiq Khan",
    "wof:placetype":"locality"
},
  "geometry": {"coordinates":[70.80231999999999,32.98807],"type":"Point"}
}