{
  "type": "Feature",
  "properties": {
    "gn:admin1_code":"2",
    "gn:asciiname":"Khwaju",
    "gn:country_code":"PK",
    "gn:dem":1037,
    "gn:feature_class":"P",
    "gn:feature_code":"PPL",
    "gn:name":"Khwaju",
    "gn:population":0,
    "gn:timezone":"Asia/Karachi",
    "iso:country":"PK",
    "wof:name":"Khwaju",
    "wof:placetype":"locality"
},
  "geometry": {"coordinates":[69.4263,29.80578],"type":"Point"}
}