{
  "type": "Feature",
  "properties": {
    "gn:admin1_code":"2.0",
    "gn:asciiname":"Muhammad Umer",
    "gn:country_code":"PK",
    "gn:dem":1838,
    "gn:feature_class":"P",
    "gn:feature_code":"PPL",
    "gn:name":"Muhammad Umer",
    "gn:population":0,
    "gn:timezone":"Asia/Karachi",
    "iso:country":"PK",
    "wof:name":"Muhammad Umer",
    "wof:placetype":"locality"
},
  "geometry": {"coordinates":[66.3192,28.68209],"type":"Point"}
}