{
  "type": "Feature",
  "properties": {
    "gn:admin1_code":"5.0",
    "gn:asciiname":"Hazra Kambah",
    "gn:country_code":"PK",
    "gn:dem":39,
    "gn:feature_class":"P",
    "gn:feature_code":"PPL",
    "gn:name":"Hazra Kambah",
    "gn:population":0,
    "gn:timezone":"Asia/Karachi",
    "iso:country":"PK",
    "wof:name":"Hazra Kambah",
    "wof:placetype":"locality"
},
  "geometry": {"coordinates":[68.01555,26.70481],"type":"Point"}
}