{
  "type": "Feature",
  "properties": {
    "gn:admin1_code":"4.0",
    "gn:asciiname":"Daulatpur",
    "gn:country_code":"PK",
    "gn:dem":537,
    "gn:feature_class":"P",
    "gn:feature_code":"PPL",
    "gn:name":"Daulatpur",
    "gn:population":0,
    "gn:timezone":"Asia/Karachi",
    "iso:country":"PK",
    "wof:name":"Daulatpur",
    "wof:placetype":"locality"
},
  "geometry": {"coordinates":[72.77630000000001,33.52213],"type":"Point"}
}