{
  "type": "Feature",
  "properties": {
    "gn:admin1_code":"2.0",
    "gn:asciiname":"Kili Haji Qadir Dad",
    "gn:country_code":"PK",
    "gn:dem":1963,
    "gn:feature_class":"P",
    "gn:feature_code":"PPL",
    "gn:name":"Kili Haji Qadir Dad",
    "gn:population":0,
    "gn:timezone":"Asia/Karachi",
    "iso:country":"PK",
    "wof:name":"Kili Haji Qadir Dad",
    "wof:placetype":"locality"
},
  "geometry": {"coordinates":[68.46467,31.57934],"type":"Point"}
}