{
  "type": "Feature",
  "properties": {
    "gn:admin1_code":"2.0",
    "gn:asciiname":"Kili Waris",
    "gn:country_code":"PK",
    "gn:dem":713,
    "gn:feature_class":"P",
    "gn:feature_code":"PPL",
    "gn:name":"Kili Waris",
    "gn:population":0,
    "gn:timezone":"Asia/Karachi",
    "iso:country":"PK",
    "wof:name":"Kili Waris",
    "wof:placetype":"locality"
},
  "geometry": {"coordinates":[65.53409000000001,28.5625],"type":"Point"}
}