{
  "type": "Feature",
  "properties": {
    "gn:admin1_code":"5.0",
    "gn:asciiname":"Sabul Khan Wand Burro",
    "gn:country_code":"PK",
    "gn:dem":52,
    "gn:feature_class":"P",
    "gn:feature_code":"PPL",
    "gn:name":"Sabul Khan Wand Burro",
    "gn:population":0,
    "gn:timezone":"Asia/Karachi",
    "iso:country":"PK",
    "name:und_x_variant":[
        "S\u0101bal W\u0101nd"
    ],
    "wof:name":"Sabul Khan Wand Burro",
    "wof:placetype":"locality"
},
  "geometry": {"coordinates":[68.13683,28.15139000000001],"type":"Point"}
}