{
  "type": "Feature",
  "properties": {
    "gn:admin1_code":"4.0",
    "gn:asciiname":"Basti Haji Muhammad Ramzan",
    "gn:country_code":"PK",
    "gn:dem":79,
    "gn:feature_class":"P",
    "gn:feature_code":"PPL",
    "gn:name":"Basti Haji Muhammad Ramzan",
    "gn:population":0,
    "gn:timezone":"Asia/Karachi",
    "iso:country":"PK",
    "wof:name":"Basti Haji Muhammad Ramzan",
    "wof:placetype":"locality"
},
  "geometry": {"coordinates":[69.92325,28.50007],"type":"Point"}
}