{
  "type": "Feature",
  "properties": {
    "gn:admin1_code":"3",
    "gn:asciiname":"Sapgai",
    "gn:country_code":"PK",
    "gn:dem":1373,
    "gn:feature_class":"P",
    "gn:feature_code":"PPL",
    "gn:name":"Sapgai",
    "gn:population":0,
    "gn:timezone":"Asia/Karachi",
    "iso:country":"PK",
    "name:und_x_variant":[
        "Sapgia",
        "Sapgai"
    ],
    "wof:name":"Sapgai",
    "wof:placetype":"locality"
},
  "geometry": {"coordinates":[72.34984,34.92201],"type":"Point"}
}