{
  "type": "Feature",
  "properties": {
    "gn:admin1_code":"4",
    "gn:asciiname":"Kot Walia",
    "gn:country_code":"PK",
    "gn:dem":188,
    "gn:feature_class":"P",
    "gn:feature_code":"PPL",
    "gn:name":"Kot Walia",
    "gn:population":0,
    "gn:timezone":"Asia/Karachi",
    "iso:country":"PK",
    "wof:name":"Kot Walia",
    "wof:placetype":"locality"
},
  "geometry": {"coordinates":[73.59999999999999,30.8625],"type":"Point"}
}