{
  "type": "Feature",
  "properties": {
    "gn:admin1_code":"1.0",
    "gn:asciiname":"Makhazai",
    "gn:country_code":"PK",
    "gn:dem":1068,
    "gn:feature_class":"P",
    "gn:feature_code":"PPL",
    "gn:name":"Makhazai",
    "gn:population":0,
    "gn:timezone":"Asia/Karachi",
    "iso:country":"PK",
    "wof:name":"Makhazai",
    "wof:placetype":"locality"
},
  "geometry": {"coordinates":[70.30634000000001,33.60989],"type":"Point"}
}