{
  "type": "Feature",
  "properties": {
    "gn:admin1_code":"4.0",
    "gn:asciiname":"Pir Jhangiwala",
    "gn:country_code":"PK",
    "gn:dem":541,
    "gn:feature_class":"P",
    "gn:feature_code":"PPL",
    "gn:name":"Pir Jhangiwala",
    "gn:population":0,
    "gn:timezone":"Asia/Karachi",
    "iso:country":"PK",
    "wof:name":"Pir Jhangiwala",
    "wof:placetype":"locality"
},
  "geometry": {"coordinates":[72.60709,32.88678],"type":"Point"}
}