{
  "type": "Feature",
  "properties": {
    "gn:admin1_code":"2.0",
    "gn:asciiname":"Kili Haja Malak",
    "gn:country_code":"PK",
    "gn:dem":1627,
    "gn:feature_class":"P",
    "gn:feature_code":"PPL",
    "gn:name":"Kili Haja Malak",
    "gn:population":0,
    "gn:timezone":"Asia/Karachi",
    "iso:country":"PK",
    "name:und_x_variant":[
        "Bohu Kh\u0101n Kili",
        "Rohu Kh\u0101n Kili",
        "Kili H\u0101ji Mal\u016bk",
        "Kili Haja Malak"
    ],
    "wof:name":"Kili Haja Malak",
    "wof:placetype":"locality"
},
  "geometry": {"coordinates":[66.51042,30.84605],"type":"Point"}
}