{
  "type": "Feature",
  "properties": {
    "gn:admin1_code":"4",
    "gn:asciiname":"Kotli Mutwalian",
    "gn:country_code":"PK",
    "gn:dem":224,
    "gn:feature_class":"P",
    "gn:feature_code":"PPL",
    "gn:name":"Kotli Mutwalian",
    "gn:population":0,
    "gn:timezone":"Asia/Karachi",
    "iso:country":"PK",
    "name:und_x_variant":[
        "Kotli Mutwalli\u0101n"
    ],
    "wof:name":"Kotli Mutwalian",
    "wof:placetype":"locality"
},
  "geometry": {"coordinates":[74.32468,32.10732],"type":"Point"}
}