{
  "type": "Feature",
  "properties": {
    "gn:admin1_code":"04",
    "gn:asciiname":"Manipura",
    "gn:country_code":"PK",
    "gn:dem":193,
    "gn:feature_class":"P",
    "gn:feature_code":"PPL",
    "gn:name":"Manipura",
    "gn:population":0,
    "gn:timezone":"Asia/Karachi",
    "iso:country":"PK",
    "name:ara_x_preferred":[
        "\u0645\u0627\u0646\u064a\u0628\u0648\u0631\u0627"
    ],
    "name:deu_x_preferred":[
        "Manipura"
    ],
    "name:fra_x_preferred":[
        "Manipura"
    ],
    "name:hin_x_preferred":[
        "\u092e\u0923\u093f\u092a\u0941\u0930 \u091a\u0915\u094d\u0930"
    ],
    "name:hrv_x_preferred":[
        "Manipura"
    ],
    "name:mar_x_preferred":[
        "\u092e\u0923\u093f\u092a\u0942\u0930 \u091a\u0915\u094d\u0930"
    ],
    "name:nld_x_preferred":[
        "Manipura"
    ],
    "name:pol_x_preferred":[
        "Manipura"
    ],
    "name:slk_x_preferred":[
        "Manipura"
    ],
    "name:spa_x_preferred":[
        "Manipura"
    ],
    "name:zho_x_preferred":[
        "\u592a\u967d\u795e\u7d93\u53e2"
    ],
    "wof:name":"Manipura",
    "wof:placetype":"locality"
},
  "geometry": {"coordinates":[72.90599,32.00558],"type":"Point"}
}