{
  "type": "Feature",
  "properties": {
    "gn:admin1_code":"4",
    "gn:asciiname":"Chak Thirty-seven",
    "gn:country_code":"PK",
    "gn:dem":186,
    "gn:feature_class":"P",
    "gn:feature_code":"PPL",
    "gn:name":"Chak Thirty-seven",
    "gn:population":0,
    "gn:timezone":"Asia/Karachi",
    "iso:country":"PK",
    "name:und_x_variant":[
        "Firaid\u016bnw\u0101la",
        "Far\u012bd\u016bnw\u0101la"
    ],
    "wof:name":"Chak Thirty-seven",
    "wof:placetype":"locality"
},
  "geometry": {"coordinates":[73.43474999999999,31.67259],"type":"Point"}
}