{
  "type": "Feature",
  "properties": {
    "gn:admin1_code":"3",
    "gn:asciiname":"Ghundi Kalle",
    "gn:country_code":"PK",
    "gn:dem":625,
    "gn:feature_class":"P",
    "gn:feature_code":"PPL",
    "gn:name":"Ghundi Kalle",
    "gn:population":0,
    "gn:timezone":"Asia/Karachi",
    "iso:country":"PK",
    "name:und_x_variant":[
        "B\u0101nda Ghol"
    ],
    "wof:name":"Ghundi Kalle",
    "wof:placetype":"locality"
},
  "geometry": {"coordinates":[70.8994,33.18551],"type":"Point"}
}