{
  "type": "Feature",
  "properties": {
    "gn:admin1_code":"4.0",
    "gn:asciiname":"Abbasi Mahalla",
    "gn:country_code":"PK",
    "gn:dem":1958,
    "gn:feature_class":"P",
    "gn:feature_code":"PPL",
    "gn:name":"Abbasi Mahalla",
    "gn:population":0,
    "gn:timezone":"Asia/Karachi",
    "iso:country":"PK",
    "name:eng_x_preferred":[
        "Abbasi Mahalla"
    ],
    "wof:name":"Abbasi Mahalla",
    "wof:placetype":"locality"
},
  "geometry": {"coordinates":[73.402,33.9014],"type":"Point"}
}