{
  "type": "Feature",
  "properties": {
    "gn:admin1_code":"4",
    "gn:asciiname":"Nawan Manga",
    "gn:country_code":"PK",
    "gn:dem":225,
    "gn:feature_class":"P",
    "gn:feature_code":"PPL",
    "gn:name":"Nawan Manga",
    "gn:population":0,
    "gn:timezone":"Asia/Karachi",
    "iso:country":"PK",
    "wof:name":"Nawan Manga",
    "wof:placetype":"locality"
},
  "geometry": {"coordinates":[74.54486999999997,32.07563],"type":"Point"}
}