{
  "type": "Feature",
  "properties": {
    "gn:admin1_code":"3.0",
    "gn:asciiname":"Gharibabad",
    "gn:country_code":"PK",
    "gn:dem":363,
    "gn:feature_class":"P",
    "gn:feature_code":"PPL",
    "gn:name":"Gharibabad",
    "gn:population":0,
    "gn:timezone":"Asia/Karachi",
    "iso:country":"PK",
    "name:diq_x_preferred":[
        "\u011eeribabad"
    ],
    "name:eng_x_preferred":[
        "Ghar\u012bb\u0101b\u0101d"
    ],
    "wof:name":"Gharibabad",
    "wof:placetype":"locality"
},
  "geometry": {"coordinates":[71.55240000000001,34.27645],"type":"Point"}
}