{
  "type": "Feature",
  "properties": {
    "gn:admin1_code":"3.0",
    "gn:asciiname":"Banda Lamba",
    "gn:country_code":"PK",
    "gn:dem":1290,
    "gn:feature_class":"P",
    "gn:feature_code":"PPL",
    "gn:name":"Banda Lamba",
    "gn:population":0,
    "gn:timezone":"Asia/Karachi",
    "iso:country":"PK",
    "name:und_x_variant":[
        "Banda Laman",
        "B\u0101nda Lamman",
        "Banda Lamba"
    ],
    "wof:name":"Banda Lamba",
    "wof:placetype":"locality"
},
  "geometry": {"coordinates":[73.20893000000002,34.20748],"type":"Point"}
}