{
  "type": "Feature",
  "properties": {
    "gn:admin1_code":"2.0",
    "gn:asciiname":"Nigangi",
    "gn:country_code":"PK",
    "gn:dem":2223,
    "gn:feature_class":"P",
    "gn:feature_code":"PPL",
    "gn:name":"Nigangi",
    "gn:population":0,
    "gn:timezone":"Asia/Karachi",
    "iso:country":"PK",
    "wof:name":"Nigangi",
    "wof:placetype":"locality"
},
  "geometry": {"coordinates":[67.70364000000001,31.07057],"type":"Point"}
}