{
  "type": "Feature",
  "properties": {
    "gn:admin1_code":"04",
    "gn:asciiname":"Samlal",
    "gn:country_code":"PK",
    "gn:dem":441,
    "gn:feature_class":"P",
    "gn:feature_code":"PPL",
    "gn:name":"Samlal",
    "gn:population":0,
    "gn:timezone":"Asia/Karachi",
    "iso:country":"PK",
    "wof:name":"Samlal",
    "wof:placetype":"locality"
},
  "geometry": {"coordinates":[73.0882,33.35774],"type":"Point"}
}