{
  "type": "Feature",
  "properties": {
    "gn:admin1_code":"2.0",
    "gn:asciiname":"Kili Majur",
    "gn:country_code":"PK",
    "gn:dem":1093,
    "gn:feature_class":"P",
    "gn:feature_code":"PPL",
    "gn:name":"Kili Majur",
    "gn:population":0,
    "gn:timezone":"Asia/Karachi",
    "iso:country":"PK",
    "wof:name":"Kili Majur",
    "wof:placetype":"locality"
},
  "geometry": {"coordinates":[66.86764000000001,28.14871],"type":"Point"}
}