{
  "type": "Feature",
  "properties": {
    "gn:admin1_code":"4.0",
    "gn:asciiname":"Banda Rallanwala",
    "gn:country_code":"PK",
    "gn:dem":282,
    "gn:feature_class":"P",
    "gn:feature_code":"PPL",
    "gn:name":"Banda Rallanwala",
    "gn:population":0,
    "gn:timezone":"Asia/Karachi",
    "iso:country":"PK",
    "name:und_x_variant":[
        "Fateh Kh\u0101n Rall\u0101w\u0101la",
        "Banda Rallanwala"
    ],
    "wof:name":"Banda Rallanwala",
    "wof:placetype":"locality"
},
  "geometry": {"coordinates":[71.18701,32.80396],"type":"Point"}
}