{
  "type": "Feature",
  "properties": {
    "gn:admin1_code":"4.0",
    "gn:asciiname":"Khawanda",
    "gn:country_code":"PK",
    "gn:dem":172,
    "gn:feature_class":"P",
    "gn:feature_code":"PPL",
    "gn:name":"Khawanda",
    "gn:population":0,
    "gn:timezone":"Asia/Karachi",
    "iso:country":"PK",
    "name:und_x_variant":[
        "Khunda"
    ],
    "wof:name":"Khawanda",
    "wof:placetype":"locality"
},
  "geometry": {"coordinates":[73.09390999999999,30.78278],"type":"Point"}
}