{
  "type": "Feature",
  "properties": {
    "gn:admin1_code":"04",
    "gn:asciiname":"Rum",
    "gn:country_code":"PK",
    "gn:dem":250,
    "gn:feature_class":"P",
    "gn:feature_code":"PPL",
    "gn:name":"Rum",
    "gn:population":0,
    "gn:timezone":"Asia/Karachi",
    "iso:country":"PK",
    "wof:name":"Rum",
    "wof:placetype":"locality"
},
  "geometry": {"coordinates":[74.58298000000001,32.64096],"type":"Point"}
}