{
  "type": "Feature",
  "properties": {
    "gn:admin1_code":"2.0",
    "gn:asciiname":"Sheher Dat",
    "gn:country_code":"PK",
    "gn:dem":1909,
    "gn:feature_class":"P",
    "gn:feature_code":"PPL",
    "gn:name":"Sheher Dat",
    "gn:population":0,
    "gn:timezone":"Asia/Karachi",
    "iso:country":"PK",
    "wof:name":"Sheher Dat",
    "wof:placetype":"locality"
},
  "geometry": {"coordinates":[66.31921,28.79888],"type":"Point"}
}