{
  "type": "Feature",
  "properties": {
    "gn:admin1_code":"1.0",
    "gn:asciiname":"Wani",
    "gn:country_code":"PK",
    "gn:dem":1275,
    "gn:feature_class":"P",
    "gn:feature_code":"PPL",
    "gn:name":"Wani",
    "gn:population":0,
    "gn:timezone":"Asia/Karachi",
    "iso:country":"PK",
    "wof:name":"Wani",
    "wof:placetype":"locality"
},
  "geometry": {"coordinates":[70.03251999999999,32.81803],"type":"Point"}
}