{
  "type": "Feature",
  "properties": {
    "gn:admin1_code":"2",
    "gn:asciiname":"Sumar Bandar",
    "gn:country_code":"PK",
    "gn:dem":14,
    "gn:feature_class":"P",
    "gn:feature_code":"PPL",
    "gn:name":"Sumar Bandar",
    "gn:population":0,
    "gn:timezone":"Asia/Karachi",
    "iso:country":"PK",
    "name:und_x_variant":[
        "K\u0101n Bir\u0101r",
        "Sumar Bandar"
    ],
    "wof:name":"Sumar Bandar",
    "wof:placetype":"locality"
},
  "geometry": {"coordinates":[66.12778,25.46111],"type":"Point"}
}