{
  "type": "Feature",
  "properties": {
    "gn:admin1_code":"4.0",
    "gn:asciiname":"Gajani",
    "gn:country_code":"PK",
    "gn:dem":131,
    "gn:feature_class":"P",
    "gn:feature_code":"PPL",
    "gn:name":"Gajani",
    "gn:population":0,
    "gn:timezone":"Asia/Karachi",
    "iso:country":"PK",
    "name:eng_x_preferred":[
        "Gajani"
    ],
    "name:eng_x_variant":[
        "Gujani"
    ],
    "name:und_x_variant":[
        "Gujani"
    ],
    "wof:name":"Gajani",
    "wof:placetype":"locality"
},
  "geometry": {"coordinates":[70.71465000000001,30.35031],"type":"Point"}
}