{
  "type": "Feature",
  "properties": {
    "gn:admin1_code":"5.0",
    "gn:asciiname":"Surrya jo Tar",
    "gn:country_code":"PK",
    "gn:dem":75,
    "gn:feature_class":"P",
    "gn:feature_code":"PPL",
    "gn:name":"Surrya jo Tar",
    "gn:population":0,
    "gn:timezone":"Asia/Karachi",
    "iso:country":"PK",
    "wof:name":"Surrya jo Tar",
    "wof:placetype":"locality"
},
  "geometry": {"coordinates":[70.11906999999999,24.79779],"type":"Point"}
}