{
  "type": "Feature",
  "properties": {
    "gn:admin1_code":"5",
    "gn:asciiname":"Goth Muhammad Ali Brahui",
    "gn:country_code":"PK",
    "gn:dem":24,
    "gn:feature_class":"P",
    "gn:feature_code":"PPL",
    "gn:name":"Goth Muhammad Ali Brahui",
    "gn:population":0,
    "gn:timezone":"Asia/Karachi",
    "iso:country":"PK",
    "name:eng_x_preferred":[
        "Goth Muhammad Shoro"
    ],
    "name:eng_x_variant":[
        "Goth Wali Muhammad Shoro",
        "Goth Muhammad Ali Shoro"
    ],
    "wof:name":"Goth Muhammad Ali Brahui",
    "wof:placetype":"locality"
},
  "geometry": {"coordinates":[68.29904999999999,25.27633],"type":"Point"}
}