{
  "type": "Feature",
  "properties": {
    "gn:admin1_code":"4",
    "gn:asciiname":"Chhani",
    "gn:country_code":"PK",
    "gn:dem":244,
    "gn:feature_class":"P",
    "gn:feature_code":"PPL",
    "gn:name":"Chhani",
    "gn:population":0,
    "gn:timezone":"Asia/Karachi",
    "iso:country":"PK",
    "name:und_x_variant":[
        "Shihni",
        "Chh\u0101ni"
    ],
    "wof:name":"Chhani",
    "wof:placetype":"locality"
},
  "geometry": {"coordinates":[74.52211,32.60454],"type":"Point"}
}