{
  "type": "Feature",
  "properties": {
    "gn:admin1_code":"4.0",
    "gn:asciiname":"Kirpalpur",
    "gn:country_code":"PK",
    "gn:dem":129,
    "gn:feature_class":"P",
    "gn:feature_code":"PPL",
    "gn:name":"Kirpalpur",
    "gn:population":0,
    "gn:timezone":"Asia/Karachi",
    "iso:country":"PK",
    "name:mal_x_preferred":[
        "\u0d15\u0d3f\u0d7c\u0d2a\u0d3e\u0d7d\u0d2a\u0d42\u0d7c"
    ],
    "wof:name":"Kirpalpur",
    "wof:placetype":"locality"
},
  "geometry": {"coordinates":[71.64269,30.23993],"type":"Point"}
}