{
  "type": "Feature",
  "properties": {
    "gn:admin1_code":"6",
    "gn:asciiname":"Bagnun Bhaik",
    "gn:country_code":"PK",
    "gn:dem":2235,
    "gn:feature_class":"P",
    "gn:feature_code":"PPL",
    "gn:name":"Bagnun Bhaik",
    "gn:population":0,
    "gn:timezone":"Asia/Karachi",
    "iso:country":"PK",
    "name:und_x_variant":[
        "Bagnu"
    ],
    "wof:name":"Bagnun Bhaik",
    "wof:placetype":"locality"
},
  "geometry": {"coordinates":[73.66806,34.3661],"type":"Point"}
}