{
  "type": "Feature",
  "properties": {
    "gn:admin1_code":"2.0",
    "gn:asciiname":"Manna Jille",
    "gn:country_code":"PK",
    "gn:dem":2261,
    "gn:feature_class":"P",
    "gn:feature_code":"PPL",
    "gn:name":"Manna Jille",
    "gn:population":0,
    "gn:timezone":"Asia/Karachi",
    "iso:country":"PK",
    "wof:name":"Manna Jille",
    "wof:placetype":"locality"
},
  "geometry": {"coordinates":[66.82316,31.05638],"type":"Point"}
}