{
  "type": "Feature",
  "properties": {
    "gn:admin1_code":"2",
    "gn:asciiname":"Gadi",
    "gn:country_code":"PK",
    "gn:dem":1097,
    "gn:feature_class":"P",
    "gn:feature_code":"PPL",
    "gn:name":"Gadi",
    "gn:population":0,
    "gn:timezone":"Asia/Karachi",
    "iso:country":"PK",
    "name:und_x_variant":[
        "Gadhi"
    ],
    "wof:name":"Gadi",
    "wof:placetype":"locality"
},
  "geometry": {"coordinates":[69.93595000000001,30.05303],"type":"Point"}
}