{
  "type": "Feature",
  "properties": {
    "gn:admin1_code":"4.0",
    "gn:asciiname":"Nalan",
    "gn:country_code":"PK",
    "gn:dem":826,
    "gn:feature_class":"P",
    "gn:feature_code":"PPL",
    "gn:name":"Nalan",
    "gn:population":0,
    "gn:timezone":"Asia/Karachi",
    "iso:country":"PK",
    "name:eng_x_preferred":[
        "Nali\u0101n"
    ],
    "name:tur_x_preferred":[
        "Nalan"
    ],
    "wof:name":"Nalan",
    "wof:placetype":"locality"
},
  "geometry": {"coordinates":[73.26875,33.82068],"type":"Point"}
}