{
  "type": "Feature",
  "properties": {
    "gn:admin1_code":"4.0",
    "gn:asciiname":"Rettekund",
    "gn:country_code":"PK",
    "gn:dem":478,
    "gn:feature_class":"P",
    "gn:feature_code":"PPL",
    "gn:name":"Rettekund",
    "gn:population":0,
    "gn:timezone":"Asia/Karachi",
    "iso:country":"PK",
    "name:und_x_variant":[
        "Rattekund"
    ],
    "wof:name":"Rettekund",
    "wof:placetype":"locality"
},
  "geometry": {"coordinates":[72.22465,33.63254000000001],"type":"Point"}
}