{
  "type": "Feature",
  "properties": {
    "gn:admin1_code":"2.0",
    "gn:asciiname":"Goth Fayyaz Muhammad",
    "gn:country_code":"PK",
    "gn:dem":61,
    "gn:feature_class":"P",
    "gn:feature_code":"PPL",
    "gn:name":"Goth Fayyaz Muhammad",
    "gn:population":0,
    "gn:timezone":"Asia/Karachi",
    "iso:country":"PK",
    "name:und_x_variant":[
        "Goth Faiz Muhammad"
    ],
    "wof:name":"Goth Fayyaz Muhammad",
    "wof:placetype":"locality"
},
  "geometry": {"coordinates":[67.94823000000001,28.36899],"type":"Point"}
}