{
  "type": "Feature",
  "properties": {
    "gn:admin1_code":"4.0",
    "gn:asciiname":"Goth Gahnawali",
    "gn:country_code":"PK",
    "gn:dem":116,
    "gn:feature_class":"P",
    "gn:feature_code":"PPL",
    "gn:name":"Goth Gahnawali",
    "gn:population":0,
    "gn:timezone":"Asia/Karachi",
    "iso:country":"PK",
    "name:eng_x_preferred":[
        "Goth Gahna"
    ],
    "name:eng_x_variant":[
        "Goth Gehna"
    ],
    "name:und_x_variant":[
        "Goth Gahnawali"
    ],
    "wof:name":"Goth Gahnawali",
    "wof:placetype":"locality"
},
  "geometry": {"coordinates":[71.55804000000001,29.37263],"type":"Point"}
}