{
  "type": "Feature",
  "properties": {
    "gn:admin1_code":"4.0",
    "gn:asciiname":"Basti Nazowala",
    "gn:country_code":"PK",
    "gn:dem":151,
    "gn:feature_class":"P",
    "gn:feature_code":"PPL",
    "gn:name":"Basti Nazowala",
    "gn:population":0,
    "gn:timezone":"Asia/Karachi",
    "iso:country":"PK",
    "name:und_x_variant":[
        "Ch\u0101h N\u0101zoisr\u0101w\u0101la"
    ],
    "wof:name":"Basti Nazowala",
    "wof:placetype":"locality"
},
  "geometry": {"coordinates":[70.90021999999998,31.16209000000001],"type":"Point"}
}