{
  "type": "Feature",
  "properties": {
    "gn:admin1_code":"3.0",
    "gn:asciiname":"Barawol",
    "gn:country_code":"PK",
    "gn:dem":1800,
    "gn:feature_class":"P",
    "gn:feature_code":"PPL",
    "gn:name":"Barawol",
    "gn:population":0,
    "gn:timezone":"Asia/Karachi",
    "iso:country":"PK",
    "wof:name":"Barawol",
    "wof:placetype":"locality"
},
  "geometry": {"coordinates":[71.65427,35.04375],"type":"Point"}
}