{
  "type": "Feature",
  "properties": {
    "gn:admin1_code":"5",
    "gn:asciiname":"Khabrot",
    "gn:country_code":"PK",
    "gn:dem":39,
    "gn:feature_class":"P",
    "gn:feature_code":"PPL",
    "gn:name":"Khabrot",
    "gn:population":0,
    "gn:timezone":"Asia/Karachi",
    "iso:country":"PK",
    "name:und_x_variant":[
        "Khambroth"
    ],
    "wof:name":"Khabrot",
    "wof:placetype":"locality"
},
  "geometry": {"coordinates":[67.78309,26.4314],"type":"Point"}
}