{
  "type": "Feature",
  "properties": {
    "gn:admin1_code":"6",
    "gn:asciiname":"Damin",
    "gn:country_code":"PK",
    "gn:dem":1770,
    "gn:feature_class":"P",
    "gn:feature_code":"PPL",
    "gn:name":"Damin",
    "gn:population":0,
    "gn:timezone":"Asia/Karachi",
    "iso:country":"PK",
    "name:ast_x_preferred":[
        "Damin"
    ],
    "name:cat_x_preferred":[
        "Damin"
    ],
    "name:deu_x_preferred":[
        "Demiin"
    ],
    "name:epo_x_preferred":[
        "Damino"
    ],
    "name:heb_x_preferred":[
        "\u05d3\u05de\u05d9\u05e0\u05d9\u05ea"
    ],
    "name:pol_x_preferred":[
        "J\u0119zyk damin"
    ],
    "name:rus_x_preferred":[
        "\u0414\u0430\u043c\u0438\u043d"
    ],
    "name:spa_x_preferred":[
        "Damin"
    ],
    "name:swe_x_preferred":[
        "Damin"
    ],
    "name:und_x_variant":[
        "D\u0101mar"
    ],
    "wof:name":"Damin",
    "wof:placetype":"locality"
},
  "geometry": {"coordinates":[73.78958,34.12065],"type":"Point"}
}