{
  "type": "Feature",
  "properties": {
    "gn:admin1_code":"4",
    "gn:asciiname":"Pakhwal",
    "gn:country_code":"PK",
    "gn:dem":199,
    "gn:feature_class":"P",
    "gn:feature_code":"PPL",
    "gn:name":"Pakhwal",
    "gn:population":0,
    "gn:timezone":"Asia/Karachi",
    "iso:country":"PK",
    "name:und_x_variant":[
        "Pakhow\u0101l"
    ],
    "wof:name":"Pakhwal",
    "wof:placetype":"locality"
},
  "geometry": {"coordinates":[73.08436999999998,32.51116],"type":"Point"}
}