{
  "type": "Feature",
  "properties": {
    "gn:admin1_code":"02",
    "gn:asciiname":"Nila",
    "gn:country_code":"PK",
    "gn:dem":1585,
    "gn:feature_class":"P",
    "gn:feature_code":"PPL",
    "gn:name":"Nila",
    "gn:population":0,
    "gn:timezone":"Asia/Karachi",
    "iso:country":"PK",
    "name:und_x_variant":[
        "Nelai",
        "N\u012blai",
        "Nila"
    ],
    "wof:name":"Nila",
    "wof:placetype":"locality"
},
  "geometry": {"coordinates":[67.05665999999999,30.43051],"type":"Point"}
}