{
  "type": "Feature",
  "properties": {
    "gn:admin1_code":"7.0",
    "gn:asciiname":"Pekhin",
    "gn:country_code":"PK",
    "gn:dem":3293,
    "gn:feature_class":"P",
    "gn:feature_code":"PPL",
    "gn:name":"Pekhin",
    "gn:population":0,
    "gn:timezone":"Asia/Karachi",
    "iso:country":"PK",
    "wof:name":"Pekhin",
    "wof:placetype":"locality"
},
  "geometry": {"coordinates":[74.0119,36.7081],"type":"Point"}
}