{
  "type": "Feature",
  "properties": {
    "gn:admin1_code":"3.0",
    "gn:asciiname":"Baungakhai",
    "gn:country_code":"PK",
    "gn:dem":521,
    "gn:feature_class":"P",
    "gn:feature_code":"PPL",
    "gn:name":"Baungakhai",
    "gn:population":0,
    "gn:timezone":"Asia/Karachi",
    "iso:country":"PK",
    "name:eng_x_preferred":[
        "Bangh\u0101khai"
    ],
    "name:und_x_variant":[
        "Bangh\u0101khi",
        "Baungakhai"
    ],
    "wof:name":"Baungakhai",
    "wof:placetype":"locality"
},
  "geometry": {"coordinates":[71.70012,34.46286],"type":"Point"}
}