{
  "type": "Feature",
  "properties": {
    "gn:admin1_code":"4.0",
    "gn:asciiname":"Basti Nur Muhammad Khan",
    "gn:country_code":"PK",
    "gn:dem":142,
    "gn:feature_class":"P",
    "gn:feature_code":"PPL",
    "gn:name":"Basti Nur Muhammad Khan",
    "gn:population":0,
    "gn:timezone":"Asia/Karachi",
    "iso:country":"PK",
    "wof:name":"Basti Nur Muhammad Khan",
    "wof:placetype":"locality"
},
  "geometry": {"coordinates":[72.48192,29.95448],"type":"Point"}
}