{
  "type": "Feature",
  "properties": {
    "gn:admin1_code":"4",
    "gn:asciiname":"Basti Jahanie",
    "gn:country_code":"PK",
    "gn:dem":104,
    "gn:feature_class":"P",
    "gn:feature_code":"PPL",
    "gn:name":"Basti Jahanie",
    "gn:population":0,
    "gn:timezone":"Asia/Karachi",
    "iso:country":"PK",
    "name:und_x_variant":[
        "Bith\u0101rew\u0101la"
    ],
    "wof:name":"Basti Jahanie",
    "wof:placetype":"locality"
},
  "geometry": {"coordinates":[70.79302,29.48385],"type":"Point"}
}