{
  "type": "Feature",
  "properties": {
    "gn:admin1_code":"3.0",
    "gn:asciiname":"Muri",
    "gn:country_code":"PK",
    "gn:dem":2059,
    "gn:feature_class":"P",
    "gn:feature_code":"PPL",
    "gn:name":"Muri",
    "gn:population":0,
    "gn:timezone":"Asia/Karachi",
    "iso:country":"PK",
    "wof:name":"Muri",
    "wof:placetype":"locality"
},
  "geometry": {"coordinates":[72.91405999999998,35.18099],"type":"Point"}
}