{
  "type": "Feature",
  "properties": {
    "gn:admin1_code":"3",
    "gn:asciiname":"Haula",
    "gn:country_code":"PK",
    "gn:dem":2570,
    "gn:feature_class":"P",
    "gn:feature_code":"PPL",
    "gn:name":"Haula",
    "gn:population":0,
    "gn:timezone":"Asia/Karachi",
    "iso:country":"PK",
    "wof:name":"Haula",
    "wof:placetype":"locality"
},
  "geometry": {"coordinates":[73.31121,34.72296],"type":"Point"}
}