{
  "type": "Feature",
  "properties": {
    "gn:admin1_code":"2.0",
    "gn:asciiname":"Muhammad Gul Kili",
    "gn:country_code":"PK",
    "gn:dem":1244,
    "gn:feature_class":"P",
    "gn:feature_code":"PPL",
    "gn:name":"Muhammad Gul Kili",
    "gn:population":0,
    "gn:timezone":"Asia/Karachi",
    "iso:country":"PK",
    "wof:name":"Muhammad Gul Kili",
    "wof:placetype":"locality"
},
  "geometry": {"coordinates":[66.38967,30.89903],"type":"Point"}
}