{
  "type": "Feature",
  "properties": {
    "gn:admin1_code":"4.0",
    "gn:asciiname":"Pindori",
    "gn:country_code":"PK",
    "gn:dem":264,
    "gn:feature_class":"P",
    "gn:feature_code":"PPL",
    "gn:name":"Pindori",
    "gn:population":0,
    "gn:timezone":"Asia/Karachi",
    "iso:country":"PK",
    "name:und_x_variant":[
        "Pindori\u0101n"
    ],
    "wof:name":"Pindori",
    "wof:placetype":"locality"
},
  "geometry": {"coordinates":[74.89881,32.31138],"type":"Point"}
}