{
  "type": "Feature",
  "properties": {
    "gn:admin1_code":"4.0",
    "gn:asciiname":"Nathuwala",
    "gn:country_code":"PK",
    "gn:dem":206,
    "gn:feature_class":"P",
    "gn:feature_code":"PPL",
    "gn:name":"Nathuwala",
    "gn:population":0,
    "gn:timezone":"Asia/Karachi",
    "iso:country":"PK",
    "name:und_x_variant":[
        "Nathth\u016bw\u0101la"
    ],
    "wof:name":"Nathuwala",
    "wof:placetype":"locality"
},
  "geometry": {"coordinates":[74.49259000000001,31.14627],"type":"Point"}
}