{
  "type": "Feature",
  "properties": {
    "gn:admin1_code":"1.0",
    "gn:asciiname":"Turi Kalle",
    "gn:country_code":"PK",
    "gn:dem":2106,
    "gn:feature_class":"P",
    "gn:feature_code":"PPL",
    "gn:name":"Turi Kalle",
    "gn:population":0,
    "gn:timezone":"Asia/Karachi",
    "iso:country":"PK",
    "wof:name":"Turi Kalle",
    "wof:placetype":"locality"
},
  "geometry": {"coordinates":[70.3849,33.84758],"type":"Point"}
}