{
  "type": "Feature",
  "properties": {
    "gn:admin1_code":"02",
    "gn:asciiname":"Mazarai",
    "gn:country_code":"PK",
    "gn:dem":1602,
    "gn:feature_class":"P",
    "gn:feature_code":"PPL",
    "gn:name":"Mazarai",
    "gn:population":0,
    "gn:timezone":"Asia/Karachi",
    "iso:country":"PK",
    "name:eng_x_preferred":[
        "Mazarai"
    ],
    "wof:name":"Mazarai",
    "wof:placetype":"locality"
},
  "geometry": {"coordinates":[66.99556,30.75895],"type":"Point"}
}