{
  "type": "Feature",
  "properties": {
    "gn:admin1_code":"5",
    "gn:asciiname":"Bhataro",
    "gn:country_code":"PK",
    "gn:dem":9,
    "gn:feature_class":"P",
    "gn:feature_code":"PPL",
    "gn:name":"Bhataro",
    "gn:population":0,
    "gn:timezone":"Asia/Karachi",
    "iso:country":"PK",
    "name:und_x_variant":[
        "Bhit\u0101ro"
    ],
    "wof:name":"Bhataro",
    "wof:placetype":"locality"
},
  "geometry": {"coordinates":[69.33575999999999,24.78764],"type":"Point"}
}