{
  "type": "Feature",
  "properties": {
    "gn:admin1_code":"04",
    "gn:asciiname":"Mohra Kudlathi",
    "gn:country_code":"PK",
    "gn:dem":480,
    "gn:feature_class":"P",
    "gn:feature_code":"PPL",
    "gn:name":"Mohra Kudlathi",
    "gn:population":0,
    "gn:timezone":"Asia/Karachi",
    "iso:country":"PK",
    "name:und_x_variant":[
        "Mohra Khud Lathi",
        "Mohra Kudlathi"
    ],
    "wof:name":"Mohra Kudlathi",
    "wof:placetype":"locality"
},
  "geometry": {"coordinates":[73.01715,32.97603],"type":"Point"}
}