{
  "type": "Feature",
  "properties": {
    "gn:admin1_code":"2.0",
    "gn:asciiname":"Goth Nur Muhammad",
    "gn:country_code":"PK",
    "gn:dem":190,
    "gn:feature_class":"P",
    "gn:feature_code":"PPL",
    "gn:name":"Goth Nur Muhammad",
    "gn:population":0,
    "gn:timezone":"Asia/Karachi",
    "iso:country":"PK",
    "name:eng_x_preferred":[
        "Goth Nur Muhammad"
    ],
    "wof:name":"Goth Nur Muhammad",
    "wof:placetype":"locality"
},
  "geometry": {"coordinates":[66.95508000000001,25.55503],"type":"Point"}
}