{
  "type": "Feature",
  "properties": {
    "gn:admin1_code":"04",
    "gn:asciiname":"Musial",
    "gn:country_code":"PK",
    "gn:dem":279,
    "gn:feature_class":"P",
    "gn:feature_code":"PPL",
    "gn:name":"Musial",
    "gn:population":0,
    "gn:timezone":"Asia/Karachi",
    "iso:country":"PK",
    "name:und_x_variant":[
        "Masyal",
        "Musial"
    ],
    "wof:name":"Musial",
    "wof:placetype":"locality"
},
  "geometry": {"coordinates":[74.88261999999997,32.43277],"type":"Point"}
}