{
  "type": "Feature",
  "properties": {
    "gn:admin1_code":"03",
    "gn:asciiname":"Ranra Manzai",
    "gn:country_code":"PK",
    "gn:dem":1450,
    "gn:feature_class":"P",
    "gn:feature_code":"PPL",
    "gn:name":"Ranra Manzai",
    "gn:population":0,
    "gn:timezone":"Asia/Karachi",
    "iso:country":"PK",
    "name:eng_x_preferred":[
        "Ranra Manzai"
    ],
    "wof:name":"Ranra Manzai",
    "wof:placetype":"locality"
},
  "geometry": {"coordinates":[71.86778000000002,34.97557],"type":"Point"}
}