{
  "type": "Feature",
  "properties": {
    "gn:admin1_code":"3.0",
    "gn:asciiname":"Yar Muhammad Kalle",
    "gn:country_code":"PK",
    "gn:dem":347,
    "gn:feature_class":"P",
    "gn:feature_code":"PPL",
    "gn:name":"Yar Muhammad Kalle",
    "gn:population":0,
    "gn:timezone":"Asia/Karachi",
    "iso:country":"PK",
    "wof:name":"Yar Muhammad Kalle",
    "wof:placetype":"locality"
},
  "geometry": {"coordinates":[71.6679,34.29488],"type":"Point"}
}