{
  "type": "Feature",
  "properties": {
    "gn:admin1_code":"2",
    "gn:asciiname":"Goth Haji",
    "gn:country_code":"PK",
    "gn:dem":18,
    "gn:feature_class":"P",
    "gn:feature_code":"PPL",
    "gn:name":"Goth Haji",
    "gn:population":0,
    "gn:timezone":"Asia/Karachi",
    "iso:country":"PK",
    "name:eng_x_preferred":[
        "Goth Haji"
    ],
    "wof:name":"Goth Haji",
    "wof:placetype":"locality"
},
  "geometry": {"coordinates":[66.65120999999999,25.55987],"type":"Point"}
}