{
  "type": "Feature",
  "properties": {
    "gn:admin1_code":"3.0",
    "gn:asciiname":"Lanjar",
    "gn:country_code":"PK",
    "gn:dem":1801,
    "gn:feature_class":"P",
    "gn:feature_code":"PPL",
    "gn:name":"Lanjar",
    "gn:population":0,
    "gn:timezone":"Asia/Karachi",
    "iso:country":"PK",
    "wof:name":"Lanjar",
    "wof:placetype":"locality"
},
  "geometry": {"coordinates":[71.9331,35.67969],"type":"Point"}
}