{
  "type": "Feature",
  "properties": {
    "gn:admin1_code":"3.0",
    "gn:asciiname":"Lanjar",
    "gn:country_code":"PK",
    "gn:dem":1801,
    "gn:feature_class":"P",
    "gn:feature_code":"PPL",
    "gn:name":"Lanjar",
    "gn:population":0,
    "gn:timezone":"Asia/Karachi",
    "iso:country":"PK",
    "name:ara_x_preferred":[
        "\u0644\u0627\u0646\u062c\u0627\u0631"
    ],
    "name:aze_x_preferred":[
        "Bir\u0259li"
    ],
    "name:fas_x_preferred":[
        "\u0644\u0627\u0646\u062c\u0627\u0631"
    ],
    "name:fra_x_preferred":[
        "Lanjar"
    ],
    "name:hye_x_preferred":[
        "\u053c\u0561\u0576\u057b\u0561\u057c"
    ],
    "name:ita_x_preferred":[
        "Landjar"
    ],
    "name:kat_x_preferred":[
        "\u10da\u10d0\u10dc\u10ef\u10d0\u10e0\u10d8"
    ],
    "name:msa_x_preferred":[
        "Lanjar"
    ],
    "name:spa_x_preferred":[
        "Lanjar"
    ],
    "name:ukr_x_preferred":[
        "\u041b\u0430\u043d\u0434\u0436\u0430\u0440"
    ],
    "name:urd_x_preferred":[
        "\u0644\u0627\u0646\u062c\u0627\u0631"
    ],
    "name:vie_x_preferred":[
        "Lanjar"
    ],
    "wof:name":"Lanjar",
    "wof:placetype":"locality"
},
  "geometry": {"coordinates":[71.9331,35.67969],"type":"Point"}
}