{
  "type": "Feature",
  "properties": {
    "gn:admin1_code":"2.0",
    "gn:asciiname":"Gwani Kalat",
    "gn:country_code":"PK",
    "gn:dem":1240,
    "gn:feature_class":"P",
    "gn:feature_code":"PPL",
    "gn:name":"Gw\u0101ni Kal\u0101t",
    "gn:population":0,
    "gn:timezone":"Asia/Karachi",
    "iso:country":"PK",
    "name:fas_x_preferred":[
        "\u06af\u0648\u0627\u0646\u06cc"
    ],
    "name:und_x_variant":[
        "Gw\u0101ni Kal\u0101t"
    ],
    "wof:name":"Gwani Kalat",
    "wof:placetype":"locality"
},
  "geometry": {"coordinates":[65.90000000000001,27.46667],"type":"Point"}
}