{
  "type": "Feature",
  "properties": {
    "gn:admin1_code":"3",
    "gn:asciiname":"Chamba",
    "gn:country_code":"PK",
    "gn:dem":2452,
    "gn:feature_class":"P",
    "gn:feature_code":"PPL",
    "gn:name":"Chamba",
    "gn:population":0,
    "gn:timezone":"Asia/Karachi",
    "iso:country":"PK",
    "wof:name":"Chamba",
    "wof:placetype":"locality"
},
  "geometry": {"coordinates":[73.63103000000002,34.74445],"type":"Point"}
}