{
  "type": "Feature",
  "properties": {
    "gn:admin1_code":"7.0",
    "gn:asciiname":"Borom-Harai",
    "gn:country_code":"PK",
    "gn:dem":3482,
    "gn:feature_class":"P",
    "gn:feature_code":"PPL",
    "gn:name":"Borom-Harai",
    "gn:population":0,
    "gn:timezone":"Asia/Karachi",
    "iso:country":"PK",
    "name:und_x_variant":[
        "Borom Harai"
    ],
    "wof:name":"Borom-Harai",
    "wof:placetype":"locality"
},
  "geometry": {"coordinates":[73.84470999999998,36.24422],"type":"Point"}
}