{
  "type": "Feature",
  "properties": {
    "gn:admin1_code":"3.0",
    "gn:asciiname":"Handi Karak",
    "gn:country_code":"PK",
    "gn:dem":666,
    "gn:feature_class":"P",
    "gn:feature_code":"PPL",
    "gn:name":"Handi Karak",
    "gn:population":0,
    "gn:timezone":"Asia/Karachi",
    "iso:country":"PK",
    "wof:name":"Handi Karak",
    "wof:placetype":"locality"
},
  "geometry": {"coordinates":[71.09191,33.13476],"type":"Point"}
}