{
  "type": "Feature",
  "properties": {
    "gn:admin1_code":"04",
    "gn:asciiname":"Visor",
    "gn:country_code":"PK",
    "gn:dem":493,
    "gn:feature_class":"P",
    "gn:feature_code":"PPL",
    "gn:name":"Visor",
    "gn:population":0,
    "gn:timezone":"Asia/Karachi",
    "iso:country":"PK",
    "name:cat_x_preferred":[
        "Visera"
    ],
    "name:epo_x_preferred":[
        "Viziero"
    ],
    "name:est_x_preferred":[
        "Visiir"
    ],
    "name:eus_x_preferred":[
        "Bisera"
    ],
    "name:hin_x_preferred":[
        "\u0935\u093e\u0907\u091c\u093c\u0930"
    ],
    "name:hrv_x_preferred":[
        "Vizir"
    ],
    "name:ido_x_preferred":[
        "Viziero"
    ],
    "name:ita_x_preferred":[
        "Visiera"
    ],
    "name:jpn_x_preferred":[
        "\u30d0\u30a4\u30b6\u30fc"
    ],
    "name:lat_x_preferred":[
        "Viseria"
    ],
    "name:lav_x_preferred":[
        "Sejsegs"
    ],
    "name:nld_x_preferred":[
        "Vizier"
    ],
    "name:rus_x_preferred":[
        "\u0417\u0430\u0431\u0440\u0430\u043b\u043e"
    ],
    "name:spa_x_preferred":[
        "Visera"
    ],
    "name:swe_x_preferred":[
        "Visir"
    ],
    "name:tur_x_preferred":[
        "Siperlik"
    ],
    "wof:name":"Visor",
    "wof:placetype":"locality"
},
  "geometry": {"coordinates":[71.51473,33.1073],"type":"Point"}
}