{
  "type": "Feature",
  "properties": {
    "gn:admin1_code":"04",
    "gn:asciiname":"Visor",
    "gn:country_code":"PK",
    "gn:dem":493,
    "gn:feature_class":"P",
    "gn:feature_code":"PPL",
    "gn:name":"Visor",
    "gn:population":0,
    "gn:timezone":"Asia/Karachi",
    "iso:country":"PK",
    "wof:name":"Visor",
    "wof:placetype":"locality"
},
  "geometry": {"coordinates":[71.51473,33.1073],"type":"Point"}
}