{
  "type": "Feature",
  "properties": {
    "gn:admin1_code":"5.0",
    "gn:asciiname":"Baprario Bhil",
    "gn:country_code":"PK",
    "gn:dem":92,
    "gn:feature_class":"P",
    "gn:feature_code":"PPL",
    "gn:name":"Baprario Bhil",
    "gn:population":0,
    "gn:timezone":"Asia/Karachi",
    "iso:country":"PK",
    "name:und_x_variant":[
        "Bapr\u0101ria"
    ],
    "wof:name":"Baprario Bhil",
    "wof:placetype":"locality"
},
  "geometry": {"coordinates":[70.29353,24.99971],"type":"Point"}
}