{
  "type": "Feature",
  "properties": {
    "gn:admin1_code":"2",
    "gn:asciiname":"Allahzai",
    "gn:country_code":"PK",
    "gn:dem":1653,
    "gn:feature_class":"P",
    "gn:feature_code":"PPL",
    "gn:name":"Allahzai",
    "gn:population":0,
    "gn:timezone":"Asia/Karachi",
    "iso:country":"PK",
    "wof:name":"Allahzai",
    "wof:placetype":"locality"
},
  "geometry": {"coordinates":[69.59543000000001,30.82924],"type":"Point"}
}