{
  "type": "Feature",
  "properties": {
    "gn:admin1_code":"5.0",
    "gn:asciiname":"Bakhte ji Dhani",
    "gn:country_code":"PK",
    "gn:dem":70,
    "gn:feature_class":"P",
    "gn:feature_code":"PPL",
    "gn:name":"Bakhte ji Dhani",
    "gn:population":0,
    "gn:timezone":"Asia/Karachi",
    "iso:country":"PK",
    "wof:name":"Bakhte ji Dhani",
    "wof:placetype":"locality"
},
  "geometry": {"coordinates":[70.76427,24.6895],"type":"Point"}
}