{
  "type": "Feature",
  "properties": {
    "gn:admin1_code":"2.0",
    "gn:asciiname":"Kili Khandian",
    "gn:country_code":"PK",
    "gn:dem":980,
    "gn:feature_class":"P",
    "gn:feature_code":"PPL",
    "gn:name":"Kili Khandian",
    "gn:population":0,
    "gn:timezone":"Asia/Karachi",
    "iso:country":"PK",
    "wof:name":"Kili Khandian",
    "wof:placetype":"locality"
},
  "geometry": {"coordinates":[67.84968000000001,30.11611],"type":"Point"}
}