{
  "type": "Feature",
  "properties": {
    "gn:admin1_code":"5",
    "gn:asciiname":"Rais Rasul Bakhsh",
    "gn:country_code":"PK",
    "gn:dem":9,
    "gn:feature_class":"P",
    "gn:feature_code":"PPL",
    "gn:name":"R\u0101is Ras\u016bl Bakhsh",
    "gn:population":0,
    "gn:timezone":"Asia/Karachi",
    "iso:country":"PK",
    "wof:name":"Rais Rasul Bakhsh",
    "wof:placetype":"locality"
},
  "geometry": {"coordinates":[69.42222,24.93056],"type":"Point"}
}