{
  "type": "Feature",
  "properties": {
    "gn:admin1_code":"4.0",
    "gn:asciiname":"Budh Jalal",
    "gn:country_code":"PK",
    "gn:dem":178,
    "gn:feature_class":"P",
    "gn:feature_code":"PPL",
    "gn:name":"Budh Jalal",
    "gn:population":0,
    "gn:timezone":"Asia/Karachi",
    "iso:country":"PK",
    "name:und_x_variant":[
        "Bund J\u0101l\u0101l Jahoka"
    ],
    "wof:name":"Budh Jalal",
    "wof:placetype":"locality"
},
  "geometry": {"coordinates":[73.37128,30.9212],"type":"Point"}
}