{
  "type": "Feature",
  "properties": {
    "gn:admin1_code":"4",
    "gn:asciiname":"Monian Thekrian",
    "gn:country_code":"PK",
    "gn:dem":227,
    "gn:feature_class":"P",
    "gn:feature_code":"PPL",
    "gn:name":"Monian Thekrian",
    "gn:population":0,
    "gn:timezone":"Asia/Karachi",
    "iso:country":"PK",
    "name:und_x_variant":[
        "Th\u012bkri\u0101n"
    ],
    "wof:name":"Monian Thekrian",
    "wof:placetype":"locality"
},
  "geometry": {"coordinates":[73.89126,32.55699],"type":"Point"}
}