{
  "type": "Feature",
  "properties": {
    "gn:admin1_code":"2.0",
    "gn:asciiname":"Kili Shafait Khan",
    "gn:country_code":"PK",
    "gn:dem":571,
    "gn:feature_class":"P",
    "gn:feature_code":"PPL",
    "gn:name":"Kili Shafait Khan",
    "gn:population":0,
    "gn:timezone":"Asia/Karachi",
    "iso:country":"PK",
    "name:und_x_variant":[
        "Khaz\u0101ne Band"
    ],
    "wof:name":"Kili Shafait Khan",
    "wof:placetype":"locality"
},
  "geometry": {"coordinates":[70.21495,31.24043],"type":"Point"}
}