{
  "type": "Feature",
  "properties": {
    "gn:admin1_code":"4.0",
    "gn:asciiname":"Malu",
    "gn:country_code":"PK",
    "gn:dem":230,
    "gn:feature_class":"P",
    "gn:feature_code":"PPL",
    "gn:name":"Malu",
    "gn:population":0,
    "gn:timezone":"Asia/Karachi",
    "iso:country":"PK",
    "name:cat_x_preferred":[
        "Malu"
    ],
    "name:ell_x_preferred":[
        "\u039c\u03b1\u03bb\u03bf\u03cd"
    ],
    "name:fra_x_preferred":[
        "Malu"
    ],
    "name:hrv_x_preferred":[
        "Malu"
    ],
    "name:new_x_preferred":[
        "\u092e\u093e\u0932\u0941"
    ],
    "wof:name":"Malu",
    "wof:placetype":"locality"
},
  "geometry": {"coordinates":[73.64454000000001,32.81087],"type":"Point"}
}