{
  "type": "Feature",
  "properties": {
    "gn:admin1_code":"4",
    "gn:asciiname":"Basti Shaikh Ibrahim",
    "gn:country_code":"PK",
    "gn:dem":165,
    "gn:feature_class":"P",
    "gn:feature_code":"PPL",
    "gn:name":"Basti Shaikh Ibrahim",
    "gn:population":0,
    "gn:timezone":"Asia/Karachi",
    "iso:country":"PK",
    "name:und_x_variant":[
        "Shaikh Ibr\u0101him",
        "Basti Shaikh Ibrahim"
    ],
    "wof:name":"Basti Shaikh Ibrahim",
    "wof:placetype":"locality"
},
  "geometry": {"coordinates":[70.65963000000001,31.08323],"type":"Point"}
}