{
  "type": "Feature",
  "properties": {
    "gn:admin1_code":"3.0",
    "gn:asciiname":"Basti Khokhranwali",
    "gn:country_code":"PK",
    "gn:dem":180,
    "gn:feature_class":"P",
    "gn:feature_code":"PPL",
    "gn:name":"Basti Khokhranwali",
    "gn:population":0,
    "gn:timezone":"Asia/Karachi",
    "iso:country":"PK",
    "name:und_x_variant":[
        "Basti Khokr\u0101nw\u0101li"
    ],
    "wof:name":"Basti Khokhranwali",
    "wof:placetype":"locality"
},
  "geometry": {"coordinates":[71.01359000000002,32.17155],"type":"Point"}
}