{
  "type": "Feature",
  "properties": {
    "gn:admin1_code":"3.0",
    "gn:asciiname":"Nar Paihk",
    "gn:country_code":"PK",
    "gn:dem":3768,
    "gn:feature_class":"P",
    "gn:feature_code":"PPL",
    "gn:name":"Nar Paihk",
    "gn:population":0,
    "gn:timezone":"Asia/Karachi",
    "iso:country":"PK",
    "wof:name":"Nar Paihk",
    "wof:placetype":"locality"
},
  "geometry": {"coordinates":[73.89931999999997,35.08743],"type":"Point"}
}