{
  "type": "Feature",
  "properties": {
    "gn:admin1_code":"5",
    "gn:asciiname":"Goth Pir",
    "gn:country_code":"PK",
    "gn:dem":61,
    "gn:feature_class":"P",
    "gn:feature_code":"PPL",
    "gn:name":"Goth Pir",
    "gn:population":0,
    "gn:timezone":"Asia/Karachi",
    "iso:country":"PK",
    "wof:name":"Goth Pir",
    "wof:placetype":"locality"
},
  "geometry": {"coordinates":[68.35262,27.65735],"type":"Point"}
}