{
  "type": "Feature",
  "properties": {
    "gn:admin1_code":"3.0",
    "gn:asciiname":"Chamiari",
    "gn:country_code":"PK",
    "gn:dem":608,
    "gn:feature_class":"P",
    "gn:feature_code":"PPL",
    "gn:name":"Chamiari",
    "gn:population":0,
    "gn:timezone":"Asia/Karachi",
    "iso:country":"PK",
    "wof:name":"Chamiari",
    "wof:placetype":"locality"
},
  "geometry": {"coordinates":[72.72725,33.97849],"type":"Point"}
}