{
  "type": "Feature",
  "properties": {
    "gn:admin1_code":"6",
    "gn:asciiname":"Kumgala",
    "gn:country_code":"PK",
    "gn:dem":1630,
    "gn:feature_class":"P",
    "gn:feature_code":"PPL",
    "gn:name":"Kumgala",
    "gn:population":0,
    "gn:timezone":"Asia/Karachi",
    "iso:country":"PK",
    "wof:name":"Kumgala",
    "wof:placetype":"locality"
},
  "geometry": {"coordinates":[74.16385,33.9215],"type":"Point"}
}