{
  "type": "Feature",
  "properties": {
    "gn:admin1_code":"5.0",
    "gn:asciiname":"Goth Karam Ali Gopang",
    "gn:country_code":"PK",
    "gn:dem":53,
    "gn:feature_class":"P",
    "gn:feature_code":"PPL",
    "gn:name":"Goth Karam Ali Gopang",
    "gn:population":0,
    "gn:timezone":"Asia/Karachi",
    "iso:country":"PK",
    "name:und_x_variant":[
        "Karam Ali Gop\u0101ng"
    ],
    "wof:name":"Goth Karam Ali Gopang",
    "wof:placetype":"locality"
},
  "geometry": {"coordinates":[68.11718,27.76497],"type":"Point"}
}