{
  "type": "Feature",
  "properties": {
    "gn:admin1_code":"03",
    "gn:asciiname":"Totaki Banda",
    "gn:country_code":"PK",
    "gn:dem":714,
    "gn:feature_class":"P",
    "gn:feature_code":"PPL",
    "gn:name":"Totaki Banda",
    "gn:population":0,
    "gn:timezone":"Asia/Karachi",
    "iso:country":"PK",
    "name:und_x_variant":[
        "Tutki",
        "Totaki",
        "Totaki Banda"
    ],
    "wof:name":"Totaki Banda",
    "wof:placetype":"locality"
},
  "geometry": {"coordinates":[71.10037,33.22166],"type":"Point"}
}