{
  "type": "Feature",
  "properties": {
    "gn:admin1_code":"4",
    "gn:asciiname":"Chak Thirty-nine South Branch",
    "gn:country_code":"PK",
    "gn:dem":188,
    "gn:feature_class":"P",
    "gn:feature_code":"PPL",
    "gn:name":"Chak Thirty-nine South Branch",
    "gn:population":0,
    "gn:timezone":"Asia/Karachi",
    "iso:country":"PK",
    "name:und_x_variant":[
        "Chak Thirty-nine SB"
    ],
    "wof:name":"Chak Thirty-nine South Branch",
    "wof:placetype":"locality"
},
  "geometry": {"coordinates":[72.81499000000002,31.93756],"type":"Point"}
}