{
  "type": "Feature",
  "properties": {
    "gn:admin1_code":"4.0",
    "gn:asciiname":"Kutianwali",
    "gn:country_code":"PK",
    "gn:dem":207,
    "gn:feature_class":"P",
    "gn:feature_code":"PPL",
    "gn:name":"Kutianwali",
    "gn:population":0,
    "gn:timezone":"Asia/Karachi",
    "iso:country":"PK",
    "name:und_x_variant":[
        "Katte\u0101nw\u0101li"
    ],
    "wof:name":"Kutianwali",
    "wof:placetype":"locality"
},
  "geometry": {"coordinates":[74.25126,31.24784],"type":"Point"}
}