{
  "type": "Feature",
  "properties": {
    "gn:admin1_code":"2.0",
    "gn:asciiname":"Zahmi",
    "gn:country_code":"PK",
    "gn:dem":1011,
    "gn:feature_class":"P",
    "gn:feature_code":"PPL",
    "gn:name":"Zahmi",
    "gn:population":0,
    "gn:timezone":"Asia/Karachi",
    "iso:country":"PK",
    "wof:name":"Zahmi",
    "wof:placetype":"locality"
},
  "geometry": {"coordinates":[64.16356999999999,27.01257],"type":"Point"}
}