{
  "type": "Feature",
  "properties": {
    "gn:admin1_code":"4",
    "gn:asciiname":"Chak Two Bahawal Canal Sharqi",
    "gn:country_code":"PK",
    "gn:dem":128,
    "gn:feature_class":"P",
    "gn:feature_code":"PPL",
    "gn:name":"Chak Two Bahawal Canal Sharqi",
    "gn:population":0,
    "gn:timezone":"Asia/Karachi",
    "iso:country":"PK",
    "name:eng_x_preferred":[
        "Chak Two B C Sharqi"
    ],
    "wof:name":"Chak Two Bahawal Canal Sharqi",
    "wof:placetype":"locality"
},
  "geometry": {"coordinates":[71.97154999999999,29.44212000000001],"type":"Point"}
}