{
  "type": "Feature",
  "properties": {
    "gn:admin1_code":"2.0",
    "gn:asciiname":"Padag Road",
    "gn:country_code":"PK",
    "gn:dem":810,
    "gn:feature_class":"P",
    "gn:feature_code":"PPL",
    "gn:name":"Padag Road",
    "gn:population":0,
    "gn:timezone":"Asia/Karachi",
    "iso:country":"PK",
    "wof:name":"Padag Road",
    "wof:placetype":"locality"
},
  "geometry": {"coordinates":[65.18119,29.10522000000001],"type":"Point"}
}