{
  "type": "Feature",
  "properties": {
    "gn:admin1_code":"3.0",
    "gn:asciiname":"Wanda Karim Khan",
    "gn:country_code":"PK",
    "gn:dem":409,
    "gn:feature_class":"P",
    "gn:feature_code":"PPL",
    "gn:name":"Wanda Karim Khan",
    "gn:population":0,
    "gn:timezone":"Asia/Karachi",
    "iso:country":"PK",
    "name:und_x_variant":[
        "Karim Kh\u0101n B\u0101nda"
    ],
    "wof:name":"Wanda Karim Khan",
    "wof:placetype":"locality"
},
  "geometry": {"coordinates":[70.73498000000002,32.37932],"type":"Point"}
}