{
  "type": "Feature",
  "properties": {
    "gn:admin1_code":"5.0",
    "gn:asciiname":"Wanhar",
    "gn:country_code":"PK",
    "gn:dem":108,
    "gn:feature_class":"P",
    "gn:feature_code":"PPL",
    "gn:name":"Wanhar",
    "gn:population":0,
    "gn:timezone":"Asia/Karachi",
    "iso:country":"PK",
    "name:und_x_variant":[
        "Varnh\u0101r"
    ],
    "wof:name":"Wanhar",
    "wof:placetype":"locality"
},
  "geometry": {"coordinates":[70.9402,24.92263],"type":"Point"}
}