{
  "type": "Feature",
  "properties": {
    "gn:admin1_code":"4.0",
    "gn:asciiname":"Chak One Hundred Twenty-seven Thal Development Authority",
    "gn:country_code":"PK",
    "gn:dem":147,
    "gn:feature_class":"P",
    "gn:feature_code":"PPL",
    "gn:name":"Chak One Hundred Twenty-seven Thal Development Authority",
    "gn:population":0,
    "gn:timezone":"Asia/Karachi",
    "iso:country":"PK",
    "name:und_x_variant":[
        "Chak 127 TDA",
        "Chak One Hundred Twenty-Seven TDA",
        "Chak One Hundred Twenty-seven Thal Development Authority"
    ],
    "wof:name":"Chak One Hundred Twenty-seven Thal Development Authority",
    "wof:placetype":"locality"
},
  "geometry": {"coordinates":[71.04786999999997,31.01319],"type":"Point"}
}