{
  "type": "Feature",
  "properties": {
    "gn:admin1_code":"05",
    "gn:asciiname":"Goth Budak",
    "gn:country_code":"PK",
    "gn:dem":50,
    "gn:feature_class":"P",
    "gn:feature_code":"PPL",
    "gn:name":"Goth Budak",
    "gn:population":0,
    "gn:timezone":"Asia/Karachi",
    "iso:country":"PK",
    "name:und_x_variant":[
        "Budak",
        "Biduk",
        "Goth Budak",
        "Budka"
    ],
    "wof:name":"Goth Budak",
    "wof:placetype":"locality"
},
  "geometry": {"coordinates":[68.19186999999999,26.9921],"type":"Point"}
}