{
  "type": "Feature",
  "properties": {
    "gn:admin1_code":"4",
    "gn:asciiname":"Thatti",
    "gn:country_code":"PK",
    "gn:dem":261,
    "gn:feature_class":"P",
    "gn:feature_code":"PPL",
    "gn:name":"Thatti",
    "gn:population":0,
    "gn:timezone":"Asia/Karachi",
    "iso:country":"PK",
    "name:und_x_variant":[
        "Thatti Kalan",
        "Thatti"
    ],
    "wof:name":"Thatti",
    "wof:placetype":"locality"
},
  "geometry": {"coordinates":[74.68176,32.52714],"type":"Point"}
}