{
  "type": "Feature",
  "properties": {
    "gn:admin1_code":"01",
    "gn:asciiname":"Tra",
    "gn:country_code":"PK",
    "gn:dem":1412,
    "gn:feature_class":"P",
    "gn:feature_code":"PPL",
    "gn:name":"Tra",
    "gn:population":0,
    "gn:timezone":"Asia/Karachi",
    "iso:country":"PK",
    "name:und_x_variant":[
        "Tora",
        "T\u0101ra"
    ],
    "wof:name":"Tra",
    "wof:placetype":"locality"
},
  "geometry": {"coordinates":[70.50506,33.56464],"type":"Point"}
}