{
  "type": "Feature",
  "properties": {
    "gn:admin1_code":"6",
    "gn:asciiname":"Chhara",
    "gn:country_code":"PK",
    "gn:dem":2138,
    "gn:feature_class":"P",
    "gn:feature_code":"PPL",
    "gn:name":"Chhara",
    "gn:population":0,
    "gn:timezone":"Asia/Karachi",
    "iso:country":"PK",
    "name:ceb_x_preferred":[
        "Chh\u0101ra"
    ],
    "name:spa_x_preferred":[
        "Chhara"
    ],
    "name:swe_x_preferred":[
        "Chh\u0101ra"
    ],
    "wof:name":"Chhara",
    "wof:placetype":"locality"
},
  "geometry": {"coordinates":[74.00814,33.92249],"type":"Point"}
}