{
  "type": "Feature",
  "properties": {
    "gn:admin1_code":"2.0",
    "gn:asciiname":"Ziba",
    "gn:country_code":"PK",
    "gn:dem":2154,
    "gn:feature_class":"P",
    "gn:feature_code":"PPL",
    "gn:name":"Ziba",
    "gn:population":0,
    "gn:timezone":"Asia/Karachi",
    "iso:country":"PK",
    "name:eng_x_preferred":[
        "Zi\u0101ba"
    ],
    "wof:name":"Ziba",
    "wof:placetype":"locality"
},
  "geometry": {"coordinates":[67.42752,30.70534],"type":"Point"}
}