{
  "type": "Feature",
  "properties": {
    "gn:admin1_code":"4",
    "gn:asciiname":"Allewali",
    "gn:country_code":"PK",
    "gn:dem":238,
    "gn:feature_class":"P",
    "gn:feature_code":"PPL",
    "gn:name":"Allewali",
    "gn:population":0,
    "gn:timezone":"Asia/Karachi",
    "iso:country":"PK",
    "wof:name":"Allewali",
    "wof:placetype":"locality"
},
  "geometry": {"coordinates":[74.37062,32.46789],"type":"Point"}
}