{
  "type": "Feature",
  "properties": {
    "gn:admin1_code":"4",
    "gn:asciiname":"Chak Thirty-eight A",
    "gn:country_code":"PK",
    "gn:dem":94,
    "gn:feature_class":"P",
    "gn:feature_code":"PPL",
    "gn:name":"Chak Thirty-eight A",
    "gn:population":0,
    "gn:timezone":"Asia/Karachi",
    "iso:country":"PK",
    "name:und_x_variant":[
        "Chak Thirty-eight"
    ],
    "wof:name":"Chak Thirty-eight A",
    "wof:placetype":"locality"
},
  "geometry": {"coordinates":[70.88244,28.82649],"type":"Point"}
}