{
  "type": "Feature",
  "properties": {
    "gn:admin1_code":"1",
    "gn:asciiname":"Jai Pishun",
    "gn:country_code":"PK",
    "gn:dem":2427,
    "gn:feature_class":"P",
    "gn:feature_code":"PPL",
    "gn:name":"Jai Pishun",
    "gn:population":0,
    "gn:timezone":"Asia/Karachi",
    "iso:country":"PK",
    "wof:name":"Jai Pishun",
    "wof:placetype":"locality"
},
  "geometry": {"coordinates":[69.76231999999999,32.7185],"type":"Point"}
}