{
  "type": "Feature",
  "properties": {
    "gn:admin1_code":"4",
    "gn:asciiname":"Mohra Kanial",
    "gn:country_code":"PK",
    "gn:dem":519,
    "gn:feature_class":"P",
    "gn:feature_code":"PPL",
    "gn:name":"Mohra Kanial",
    "gn:population":0,
    "gn:timezone":"Asia/Karachi",
    "iso:country":"PK",
    "wof:name":"Mohra Kanial",
    "wof:placetype":"locality"
},
  "geometry": {"coordinates":[73.30348000000002,33.07914],"type":"Point"}
}