{
  "type": "Feature",
  "properties": {
    "gn:admin1_code":"4.0",
    "gn:asciiname":"Ghulan Haidor Surani",
    "gn:country_code":"PK",
    "gn:dem":121,
    "gn:feature_class":"P",
    "gn:feature_code":"PPL",
    "gn:name":"Ghulan Haidor Surani",
    "gn:population":0,
    "gn:timezone":"Asia/Karachi",
    "iso:country":"PK",
    "name:eng_x_preferred":[
        "Ghul\u0101m Haidar Sur\u0101ni"
    ],
    "wof:name":"Ghulan Haidor Surani",
    "wof:placetype":"locality"
},
  "geometry": {"coordinates":[70.95251,30.08286],"type":"Point"}
}