{
  "type": "Feature",
  "properties": {
    "gn:admin1_code":"02",
    "gn:asciiname":"Shahdadzai",
    "gn:country_code":"PK",
    "gn:dem":1569,
    "gn:feature_class":"P",
    "gn:feature_code":"PPL",
    "gn:name":"Shahdadzai",
    "gn:population":0,
    "gn:timezone":"Asia/Karachi",
    "iso:country":"PK",
    "wof:name":"Shahdadzai",
    "wof:placetype":"locality"
},
  "geometry": {"coordinates":[66.08400999999999,28.14978],"type":"Point"}
}