{
  "type": "Feature",
  "properties": {
    "gn:admin1_code":"5",
    "gn:asciiname":"Lung jo Goth",
    "gn:country_code":"PK",
    "gn:dem":60,
    "gn:feature_class":"P",
    "gn:feature_code":"PPL",
    "gn:name":"Lung jo Goth",
    "gn:population":0,
    "gn:timezone":"Asia/Karachi",
    "iso:country":"PK",
    "name:und_x_variant":[
        "Laung Bhambhro"
    ],
    "wof:name":"Lung jo Goth",
    "wof:placetype":"locality"
},
  "geometry": {"coordinates":[68.99876999999999,27.47951],"type":"Point"}
}