{
  "type": "Feature",
  "properties": {
    "gn:admin1_code":"3",
    "gn:asciiname":"Ghafarban",
    "gn:country_code":"PK",
    "gn:dem":3366,
    "gn:feature_class":"P",
    "gn:feature_code":"PPL",
    "gn:name":"Ghafarb\u0101n",
    "gn:population":0,
    "gn:timezone":"Asia/Karachi",
    "iso:country":"PK",
    "wof:name":"Ghafarban",
    "wof:placetype":"locality"
},
  "geometry": {"coordinates":[72.56667,35.31806],"type":"Point"}
}