{
  "type": "Feature",
  "properties": {
    "gn:admin1_code":"2.0",
    "gn:asciiname":"Goth Raza Muhammad Chandlo",
    "gn:country_code":"PK",
    "gn:dem":437,
    "gn:feature_class":"P",
    "gn:feature_code":"PPL",
    "gn:name":"Goth Raza Muhammad Chandlo",
    "gn:population":0,
    "gn:timezone":"Asia/Karachi",
    "iso:country":"PK",
    "wof:name":"Goth Raza Muhammad Chandlo",
    "wof:placetype":"locality"
},
  "geometry": {"coordinates":[67.36841,27.85258],"type":"Point"}
}