{
  "type": "Feature",
  "properties": {
    "gn:admin1_code":"2",
    "gn:asciiname":"Basti Sham",
    "gn:country_code":"PK",
    "gn:dem":1137,
    "gn:feature_class":"P",
    "gn:feature_code":"PPL",
    "gn:name":"Basti Sham",
    "gn:population":0,
    "gn:timezone":"Asia/Karachi",
    "iso:country":"PK",
    "wof:name":"Basti Sham",
    "wof:placetype":"locality"
},
  "geometry": {"coordinates":[69.56402,29.92267],"type":"Point"}
}