{
  "type": "Feature",
  "properties": {
    "gn:admin1_code":"4.0",
    "gn:asciiname":"Bhinda Hussian Khan",
    "gn:country_code":"PK",
    "gn:dem":147,
    "gn:feature_class":"P",
    "gn:feature_code":"PPL",
    "gn:name":"Bhinda Hussian Khan",
    "gn:population":0,
    "gn:timezone":"Asia/Karachi",
    "iso:country":"PK",
    "wof:name":"Bhinda Hussian Khan",
    "wof:placetype":"locality"
},
  "geometry": {"coordinates":[72.80694,29.97856],"type":"Point"}
}