{
  "type": "Feature",
  "properties": {
    "gn:admin1_code":"6",
    "gn:asciiname":"Bangora",
    "gn:country_code":"PK",
    "gn:dem":628,
    "gn:feature_class":"P",
    "gn:feature_code":"PPL",
    "gn:name":"Bangora",
    "gn:population":0,
    "gn:timezone":"Asia/Karachi",
    "iso:country":"PK",
    "wof:name":"Bangora",
    "wof:placetype":"locality"
},
  "geometry": {"coordinates":[73.99343,33.0962],"type":"Point"}
}