{
  "type": "Feature",
  "properties": {
    "gn:admin1_code":"6",
    "gn:asciiname":"Nihari",
    "gn:country_code":"PK",
    "gn:dem":650,
    "gn:feature_class":"P",
    "gn:feature_code":"PPL",
    "gn:name":"Nihari",
    "gn:population":0,
    "gn:timezone":"Asia/Karachi",
    "iso:country":"PK",
    "name:und_x_variant":[
        "Jabba"
    ],
    "wof:name":"Nihari",
    "wof:placetype":"locality"
},
  "geometry": {"coordinates":[73.95721999999998,33.15065],"type":"Point"}
}