{
  "type": "Feature",
  "properties": {
    "gn:admin1_code":"6",
    "gn:asciiname":"Nihari",
    "gn:country_code":"PK",
    "gn:dem":650,
    "gn:feature_class":"P",
    "gn:feature_code":"PPL",
    "gn:name":"Nihari",
    "gn:population":0,
    "gn:timezone":"Asia/Karachi",
    "iso:country":"PK",
    "name:ara_x_preferred":[
        "\u0646\u0647\u0627\u0631\u064a"
    ],
    "name:ben_x_preferred":[
        "\u09a8\u09bf\u09b9\u09be\u09b0\u09c0"
    ],
    "name:hin_x_preferred":[
        "\u0928\u093f\u0939\u093e\u0930\u0940"
    ],
    "name:jpn_x_preferred":[
        "\u30cb\u30cf\u30ea"
    ],
    "name:pan_x_preferred":[
        "\u0a28\u0a3f\u0a39\u0a3e\u0a30\u0a40"
    ],
    "name:pnb_x_preferred":[
        "\u0646\u06c1\u0627\u0631\u06cc"
    ],
    "name:spa_x_preferred":[
        "Nihari"
    ],
    "name:und_x_variant":[
        "Jabba"
    ],
    "name:urd_x_preferred":[
        "\u0646\u06c1\u0627\u0631\u06cc"
    ],
    "name:vie_x_preferred":[
        "Nihari"
    ],
    "wof:name":"Nihari",
    "wof:placetype":"locality"
},
  "geometry": {"coordinates":[73.95721999999998,33.15065],"type":"Point"}
}