{
  "type": "Feature",
  "properties": {
    "gn:admin1_code":"5",
    "gn:asciiname":"Goth Detho",
    "gn:country_code":"PK",
    "gn:dem":26,
    "gn:feature_class":"P",
    "gn:feature_code":"PPL",
    "gn:name":"Goth Detho",
    "gn:population":0,
    "gn:timezone":"Asia/Karachi",
    "iso:country":"PK",
    "wof:name":"Goth Detho",
    "wof:placetype":"locality"
},
  "geometry": {"coordinates":[68.51281999999999,25.56969],"type":"Point"}
}