{
  "type": "Feature",
  "properties": {
    "gn:admin1_code":"6",
    "gn:asciiname":"Brani",
    "gn:country_code":"PK",
    "gn:dem":1131,
    "gn:feature_class":"P",
    "gn:feature_code":"PPL",
    "gn:name":"Brani",
    "gn:population":0,
    "gn:timezone":"Asia/Karachi",
    "iso:country":"PK",
    "name:und_x_variant":[
        "Bar\u0101ni"
    ],
    "wof:name":"Brani",
    "wof:placetype":"locality"
},
  "geometry": {"coordinates":[73.82441,34.16504],"type":"Point"}
}