{
  "type": "Feature",
  "properties": {
    "gn:admin1_code":"5",
    "gn:asciiname":"Goth Bhangal Dasti",
    "gn:country_code":"PK",
    "gn:dem":59,
    "gn:feature_class":"P",
    "gn:feature_code":"PPL",
    "gn:name":"Goth Bhangal Dasti",
    "gn:population":0,
    "gn:timezone":"Asia/Karachi",
    "iso:country":"PK",
    "name:und_x_variant":[
        "Goth Bangul Dasti"
    ],
    "wof:name":"Goth Bhangal Dasti",
    "wof:placetype":"locality"
},
  "geometry": {"coordinates":[68.45944,28.32963],"type":"Point"}
}