{
  "type": "Feature",
  "properties": {
    "gn:admin1_code":"5.0",
    "gn:asciiname":"Bharmalo",
    "gn:country_code":"PK",
    "gn:dem":29,
    "gn:feature_class":"P",
    "gn:feature_code":"PPL",
    "gn:name":"Bharmalo",
    "gn:population":0,
    "gn:timezone":"Asia/Karachi",
    "iso:country":"PK",
    "name:und_x_variant":[
        "Bharmalio"
    ],
    "wof:name":"Bharmalo",
    "wof:placetype":"locality"
},
  "geometry": {"coordinates":[69.78219,24.62063],"type":"Point"}
}