{
  "type": "Feature",
  "properties": {
    "gn:admin1_code":"4.0",
    "gn:asciiname":"Jhumbiyan Kalan",
    "gn:country_code":"PK",
    "gn:dem":273,
    "gn:feature_class":"P",
    "gn:feature_code":"PPL",
    "gn:name":"Jhumbiyan Kalan",
    "gn:population":0,
    "gn:timezone":"Asia/Karachi",
    "iso:country":"PK",
    "wof:name":"Jhumbiyan Kalan",
    "wof:placetype":"locality"
},
  "geometry": {"coordinates":[75.18446999999998,32.33307],"type":"Point"}
}