{
  "type": "Feature",
  "properties": {
    "gn:admin1_code":"5.0",
    "gn:asciiname":"Goth Khuwaja Muhammad Hashim",
    "gn:country_code":"PK",
    "gn:dem":9,
    "gn:feature_class":"P",
    "gn:feature_code":"PPL",
    "gn:name":"Goth Khuwaja Muhammad Hashim",
    "gn:population":0,
    "gn:timezone":"Asia/Karachi",
    "iso:country":"PK",
    "wof:name":"Goth Khuwaja Muhammad Hashim",
    "wof:placetype":"locality"
},
  "geometry": {"coordinates":[69.44173000000001,24.87802000000001],"type":"Point"}
}