{
  "type": "Feature",
  "properties": {
    "gn:admin1_code":"3.0",
    "gn:asciiname":"Pikhar Khui",
    "gn:country_code":"PK",
    "gn:dem":1572,
    "gn:feature_class":"P",
    "gn:feature_code":"PPL",
    "gn:name":"Pikhar Khui",
    "gn:population":0,
    "gn:timezone":"Asia/Karachi",
    "iso:country":"PK",
    "wof:name":"Pikhar Khui",
    "wof:placetype":"locality"
},
  "geometry": {"coordinates":[72.94011999999999,34.31137],"type":"Point"}
}