{
  "type": "Feature",
  "properties": {
    "gn:admin1_code":"3.0",
    "gn:asciiname":"Basti Khai",
    "gn:country_code":"PK",
    "gn:dem":436,
    "gn:feature_class":"P",
    "gn:feature_code":"PPL",
    "gn:name":"Basti Khai",
    "gn:population":0,
    "gn:timezone":"Asia/Karachi",
    "iso:country":"PK",
    "name:und_x_variant":[
        "Wesili Kh\u016bi"
    ],
    "wof:name":"Basti Khai",
    "wof:placetype":"locality"
},
  "geometry": {"coordinates":[71.62108000000001,33.83129],"type":"Point"}
}