{
  "type": "Feature",
  "properties": {
    "gn:admin1_code":"2.0",
    "gn:asciiname":"Chakku",
    "gn:country_code":"PK",
    "gn:dem":1375,
    "gn:feature_class":"P",
    "gn:feature_code":"PPL",
    "gn:name":"Chakku",
    "gn:population":0,
    "gn:timezone":"Asia/Karachi",
    "iso:country":"PK",
    "wof:name":"Chakku",
    "wof:placetype":"locality"
},
  "geometry": {"coordinates":[66.55847,27.95207000000001],"type":"Point"}
}