{
  "type": "Feature",
  "properties": {
    "gn:admin1_code":"4",
    "gn:asciiname":"Chaontra Dhok",
    "gn:country_code":"PK",
    "gn:dem":368,
    "gn:feature_class":"P",
    "gn:feature_code":"PPL",
    "gn:name":"Chaontra Dhok",
    "gn:population":0,
    "gn:timezone":"Asia/Karachi",
    "iso:country":"PK",
    "wof:name":"Chaontra Dhok",
    "wof:placetype":"locality"
},
  "geometry": {"coordinates":[73.44816,33.03274],"type":"Point"}
}