{
  "type": "Feature",
  "properties": {
    "gn:admin1_code":"2.0",
    "gn:asciiname":"Kili Haji Abdur Razzaq",
    "gn:country_code":"PK",
    "gn:dem":1569,
    "gn:feature_class":"P",
    "gn:feature_code":"PPL",
    "gn:name":"Kili Haji Abdur Razzaq",
    "gn:population":0,
    "gn:timezone":"Asia/Karachi",
    "iso:country":"PK",
    "name:und_x_variant":[
        "Kili H\u0101ji",
        "Kili H\u0101ji Abdur Raz\u0101q",
        "Kili Haji Abdur Razzaq"
    ],
    "wof:name":"Kili Haji Abdur Razzaq",
    "wof:placetype":"locality"
},
  "geometry": {"coordinates":[66.92723000000001,30.29835],"type":"Point"}
}