{
  "type": "Feature",
  "properties": {
    "gn:admin1_code":"4.0",
    "gn:asciiname":"Bahawal Shah di Basti",
    "gn:country_code":"PK",
    "gn:dem":141,
    "gn:feature_class":"P",
    "gn:feature_code":"PPL",
    "gn:name":"Bahawal Shah di Basti",
    "gn:population":0,
    "gn:timezone":"Asia/Karachi",
    "iso:country":"PK",
    "wof:name":"Bahawal Shah di Basti",
    "wof:placetype":"locality"
},
  "geometry": {"coordinates":[72.61123000000001,29.79556],"type":"Point"}
}