{
  "type": "Feature",
  "properties": {
    "gn:admin1_code":"4",
    "gn:asciiname":"Bandi Bakhsh",
    "gn:country_code":"PK",
    "gn:dem":138,
    "gn:feature_class":"P",
    "gn:feature_code":"PPL",
    "gn:name":"Bandi Bakhsh",
    "gn:population":0,
    "gn:timezone":"Asia/Karachi",
    "iso:country":"PK",
    "wof:name":"Bandi Bakhsh",
    "wof:placetype":"locality"
},
  "geometry": {"coordinates":[71.90664,30.73678],"type":"Point"}
}