{
  "type": "Feature",
  "properties": {
    "gn:admin1_code":"4.0",
    "gn:asciiname":"Tibba",
    "gn:country_code":"PK",
    "gn:dem":201,
    "gn:feature_class":"P",
    "gn:feature_code":"PPL",
    "gn:name":"Tibba",
    "gn:population":0,
    "gn:timezone":"Asia/Karachi",
    "iso:country":"PK",
    "name:und_x_variant":[
        "Afzal\u0101b\u0101d",
        "Tibba"
    ],
    "wof:name":"Tibba",
    "wof:placetype":"locality"
},
  "geometry": {"coordinates":[74.09638000000002,31.14891],"type":"Point"}
}