{
  "type": "Feature",
  "properties": {
    "gn:admin1_code":"4.0",
    "gn:asciiname":"Alman Sharqi",
    "gn:country_code":"PK",
    "gn:dem":154,
    "gn:feature_class":"P",
    "gn:feature_code":"PPL",
    "gn:name":"Alman Sharqi",
    "gn:population":0,
    "gn:timezone":"Asia/Karachi",
    "iso:country":"PK",
    "name:und_x_variant":[
        "Alm\u0101n"
    ],
    "wof:name":"Alman Sharqi",
    "wof:placetype":"locality"
},
  "geometry": {"coordinates":[72.13145,31.26896],"type":"Point"}
}