{
  "type": "Feature",
  "properties": {
    "gn:admin1_code":"4.0",
    "gn:asciiname":"Kurka",
    "gn:country_code":"PK",
    "gn:dem":123,
    "gn:feature_class":"P",
    "gn:feature_code":"PPL",
    "gn:name":"Kurka",
    "gn:population":0,
    "gn:timezone":"Asia/Karachi",
    "iso:country":"PK",
    "name:ara_x_preferred":[
        "\u0643\u0648\u0631\u0643\u0627"
    ],
    "name:fas_x_preferred":[
        "\u06a9\u0648\u0631\u06a9\u0627"
    ],
    "name:msa_x_preferred":[
        "Kurka"
    ],
    "name:por_x_preferred":[
        "Kurka"
    ],
    "name:ukr_x_preferred":[
        "\u0490\u0443\u0440\u043a\u0430"
    ],
    "wof:name":"Kurka",
    "wof:placetype":"locality"
},
  "geometry": {"coordinates":[70.8886,30.14201],"type":"Point"}
}