{
  "type": "Feature",
  "properties": {
    "gn:admin1_code":"5.0",
    "gn:asciiname":"Arz Muhammad Bughio",
    "gn:country_code":"PK",
    "gn:dem":43,
    "gn:feature_class":"P",
    "gn:feature_code":"PPL",
    "gn:name":"Arz Muhammad Bughio",
    "gn:population":0,
    "gn:timezone":"Asia/Karachi",
    "iso:country":"PK",
    "wof:name":"Arz Muhammad Bughio",
    "wof:placetype":"locality"
},
  "geometry": {"coordinates":[67.97201,26.60129],"type":"Point"}
}