{
  "type": "Feature",
  "properties": {
    "gn:admin1_code":"4.0",
    "gn:asciiname":"Dhok Ara",
    "gn:country_code":"PK",
    "gn:dem":432,
    "gn:feature_class":"P",
    "gn:feature_code":"PPL",
    "gn:name":"Dhok Ara",
    "gn:population":0,
    "gn:timezone":"Asia/Karachi",
    "iso:country":"PK",
    "name:und_x_variant":[
        "Dhok Tor Kh\u0101n"
    ],
    "wof:name":"Dhok Ara",
    "wof:placetype":"locality"
},
  "geometry": {"coordinates":[72.20976999999998,33.35448],"type":"Point"}
}