{
  "type": "Feature",
  "properties": {
    "gn:admin1_code":"5.0",
    "gn:asciiname":"Umid Ali ji Dhani",
    "gn:country_code":"PK",
    "gn:dem":134,
    "gn:feature_class":"P",
    "gn:feature_code":"PPL",
    "gn:name":"Umid Ali ji Dhani",
    "gn:population":0,
    "gn:timezone":"Asia/Karachi",
    "iso:country":"PK",
    "wof:name":"Umid Ali ji Dhani",
    "wof:placetype":"locality"
},
  "geometry": {"coordinates":[70.57982,25.32405],"type":"Point"}
}