{
  "type": "Feature",
  "properties": {
    "gn:admin1_code":"5",
    "gn:asciiname":"Goth Phutho",
    "gn:country_code":"PK",
    "gn:dem":28,
    "gn:feature_class":"P",
    "gn:feature_code":"PPL",
    "gn:name":"Goth Phutho",
    "gn:population":0,
    "gn:timezone":"Asia/Karachi",
    "iso:country":"PK",
    "name:eng_x_preferred":[
        "Phutho"
    ],
    "wof:name":"Goth Phutho",
    "wof:placetype":"locality"
},
  "geometry": {"coordinates":[68.41516999999999,25.89097000000001],"type":"Point"}
}