{
  "type": "Feature",
  "properties": {
    "gn:admin1_code":"02",
    "gn:asciiname":"Satakzai",
    "gn:country_code":"PK",
    "gn:dem":1770,
    "gn:feature_class":"P",
    "gn:feature_code":"PPL",
    "gn:name":"Satakzai",
    "gn:population":0,
    "gn:timezone":"Asia/Karachi",
    "iso:country":"PK",
    "wof:name":"Satakzai",
    "wof:placetype":"locality"
},
  "geometry": {"coordinates":[67.11372,29.76301],"type":"Point"}
}