{
  "type": "Feature",
  "properties": {
    "gn:admin1_code":"2.0",
    "gn:asciiname":"Deka Qasmani",
    "gn:country_code":"PK",
    "gn:dem":1136,
    "gn:feature_class":"P",
    "gn:feature_code":"PPL",
    "gn:name":"Deka Qasmani",
    "gn:population":0,
    "gn:timezone":"Asia/Karachi",
    "iso:country":"PK",
    "wof:name":"Deka Qasmani",
    "wof:placetype":"locality"
},
  "geometry": {"coordinates":[69.88831,30.08907],"type":"Point"}
}