{
  "type": "Feature",
  "properties": {
    "gn:admin1_code":"5",
    "gn:asciiname":"Goth Yusuf Hingoro",
    "gn:country_code":"PK",
    "gn:dem":22,
    "gn:feature_class":"P",
    "gn:feature_code":"PPL",
    "gn:name":"Goth Yusuf Hingoro",
    "gn:population":0,
    "gn:timezone":"Asia/Karachi",
    "iso:country":"PK",
    "name:und_x_variant":[
        "Goth Y\u016bsuf Hingoro"
    ],
    "wof:name":"Goth Yusuf Hingoro",
    "wof:placetype":"locality"
},
  "geometry": {"coordinates":[68.95477,25.86948],"type":"Point"}
}