{
  "type": "Feature",
  "properties": {
    "gn:admin1_code":"3",
    "gn:asciiname":"Dheri",
    "gn:country_code":"PK",
    "gn:dem":1776,
    "gn:feature_class":"P",
    "gn:feature_code":"PPL",
    "gn:name":"Dheri",
    "gn:population":0,
    "gn:timezone":"Asia/Karachi",
    "iso:country":"PK",
    "wof:name":"Dheri",
    "wof:placetype":"locality"
},
  "geometry": {"coordinates":[73.38521999999998,34.20328],"type":"Point"}
}