{
  "type": "Feature",
  "properties": {
    "gn:admin1_code":"4",
    "gn:asciiname":"Khu Mulanwala",
    "gn:country_code":"PK",
    "gn:dem":133,
    "gn:feature_class":"P",
    "gn:feature_code":"PPL",
    "gn:name":"Khu Mulanwala",
    "gn:population":0,
    "gn:timezone":"Asia/Karachi",
    "iso:country":"PK",
    "name:eng_x_preferred":[
        "Murl\u012bw\u0101la"
    ],
    "wof:name":"Khu Mulanwala",
    "wof:placetype":"locality"
},
  "geometry": {"coordinates":[70.67246999999998,30.33912],"type":"Point"}
}