{
  "type": "Feature",
  "properties": {
    "gn:admin1_code":"5.0",
    "gn:asciiname":"Haji Wasaio Jo Goth",
    "gn:country_code":"PK",
    "gn:dem":42,
    "gn:feature_class":"P",
    "gn:feature_code":"PPL",
    "gn:name":"Haji Wasaio Jo Goth",
    "gn:population":0,
    "gn:timezone":"Asia/Karachi",
    "iso:country":"PK",
    "wof:name":"Haji Wasaio Jo Goth",
    "wof:placetype":"locality"
},
  "geometry": {"coordinates":[69.79423,26.03923],"type":"Point"}
}