{
  "type": "Feature",
  "properties": {
    "gn:admin1_code":"04",
    "gn:asciiname":"Basti Kohar",
    "gn:country_code":"PK",
    "gn:dem":187,
    "gn:feature_class":"P",
    "gn:feature_code":"PPL",
    "gn:name":"Basti Kohar",
    "gn:population":0,
    "gn:timezone":"Asia/Karachi",
    "iso:country":"PK",
    "name:und_x_variant":[
        "Kuhar",
        "Koh\u0101r",
        "Basti Kohar"
    ],
    "wof:name":"Basti Kohar",
    "wof:placetype":"locality"
},
  "geometry": {"coordinates":[70.59281,31.1695],"type":"Point"}
}