{
  "type": "Feature",
  "properties": {
    "gn:admin1_code":"5",
    "gn:asciiname":"Goth Ahmad Khan Lund",
    "gn:country_code":"PK",
    "gn:dem":15,
    "gn:feature_class":"P",
    "gn:feature_code":"PPL",
    "gn:name":"Goth Ahmad Kh\u0101n Lund",
    "gn:population":0,
    "gn:timezone":"Asia/Karachi",
    "iso:country":"PK",
    "wof:name":"Goth Ahmad Khan Lund",
    "wof:placetype":"locality"
},
  "geometry": {"coordinates":[68.81389,25.05],"type":"Point"}
}