{
  "type": "Feature",
  "properties": {
    "gn:admin1_code":"3",
    "gn:asciiname":"Chind Kot",
    "gn:country_code":"PK",
    "gn:dem":1126,
    "gn:feature_class":"P",
    "gn:feature_code":"PPL",
    "gn:name":"Chind Kot",
    "gn:population":0,
    "gn:timezone":"Asia/Karachi",
    "iso:country":"PK",
    "name:und_x_variant":[
        "Chindkot"
    ],
    "wof:name":"Chind Kot",
    "wof:placetype":"locality"
},
  "geometry": {"coordinates":[72.99361999999998,34.48540999999999],"type":"Point"}
}