{
  "type": "Feature",
  "properties": {
    "gn:admin1_code":"04",
    "gn:asciiname":"Las",
    "gn:country_code":"PK",
    "gn:dem":753,
    "gn:feature_class":"P",
    "gn:feature_code":"PPL",
    "gn:name":"Las",
    "gn:population":0,
    "gn:timezone":"Asia/Karachi",
    "iso:country":"PK",
    "wof:name":"Las",
    "wof:placetype":"locality"
},
  "geometry": {"coordinates":[73.60833000000002,33.5754],"type":"Point"}
}