{
  "type": "Feature",
  "properties": {
    "gn:admin1_code":"5.0",
    "gn:asciiname":"Ahmad Kalwar",
    "gn:country_code":"PK",
    "gn:dem":68,
    "gn:feature_class":"P",
    "gn:feature_code":"PPL",
    "gn:name":"Ahmad Kalwar",
    "gn:population":0,
    "gn:timezone":"Asia/Karachi",
    "iso:country":"PK",
    "wof:name":"Ahmad Kalwar",
    "wof:placetype":"locality"
},
  "geometry": {"coordinates":[69.34803000000001,27.9452],"type":"Point"}
}