{
  "type": "Feature",
  "properties": {
    "gn:admin1_code":"3.0",
    "gn:asciiname":"Sho",
    "gn:country_code":"PK",
    "gn:dem":1015,
    "gn:feature_class":"P",
    "gn:feature_code":"PPL",
    "gn:name":"Sho",
    "gn:population":0,
    "gn:timezone":"Asia/Karachi",
    "iso:country":"PK",
    "name:ceb_x_preferred":[
        "Sho"
    ],
    "name:dan_x_preferred":[
        "Sho"
    ],
    "name:deu_x_preferred":[
        "Sho"
    ],
    "name:fra_x_preferred":[
        "Sho"
    ],
    "name:gla_x_preferred":[
        "Sho"
    ],
    "name:nld_x_preferred":[
        "Sho"
    ],
    "name:pol_x_preferred":[
        "Sho"
    ],
    "name:por_x_preferred":[
        "Sho"
    ],
    "name:spa_x_preferred":[
        "Sho"
    ],
    "name:swe_x_preferred":[
        "Sho"
    ],
    "wof:name":"Sho",
    "wof:placetype":"locality"
},
  "geometry": {"coordinates":[71.29566,33.01716],"type":"Point"}
}