{
  "type": "Feature",
  "properties": {
    "gn:admin1_code":"3",
    "gn:asciiname":"Segala",
    "gn:country_code":"PK",
    "gn:dem":1548,
    "gn:feature_class":"P",
    "gn:feature_code":"PPL",
    "gn:name":"Segala",
    "gn:population":0,
    "gn:timezone":"Asia/Karachi",
    "iso:country":"PK",
    "name:ceb_x_preferred":[
        "Segala"
    ],
    "name:deu_x_preferred":[
        "Segala"
    ],
    "name:eng_x_preferred":[
        "Segala"
    ],
    "name:fra_x_preferred":[
        "S\u00e9gala"
    ],
    "name:ita_x_preferred":[
        "Segala"
    ],
    "name:swe_x_preferred":[
        "Segala"
    ],
    "wof:name":"Segala",
    "wof:placetype":"locality"
},
  "geometry": {"coordinates":[72.59769,35.26076],"type":"Point"}
}