{
  "type": "Feature",
  "properties": {
    "gn:admin1_code":"4",
    "gn:asciiname":"Qallandarwala",
    "gn:country_code":"PK",
    "gn:dem":164,
    "gn:feature_class":"P",
    "gn:feature_code":"PPL",
    "gn:name":"Qallandarwala",
    "gn:population":0,
    "gn:timezone":"Asia/Karachi",
    "iso:country":"PK",
    "name:und_x_variant":[
        "Kalandarw\u0101la"
    ],
    "wof:name":"Qallandarwala",
    "wof:placetype":"locality"
},
  "geometry": {"coordinates":[72.56625,31.42711],"type":"Point"}
}