{
  "type": "Feature",
  "properties": {
    "gn:admin1_code":"4",
    "gn:asciiname":"Basti Chalbani",
    "gn:country_code":"PK",
    "gn:dem":104,
    "gn:feature_class":"P",
    "gn:feature_code":"PPL",
    "gn:name":"Basti Chalbani",
    "gn:population":0,
    "gn:timezone":"Asia/Karachi",
    "iso:country":"PK",
    "name:und_x_variant":[
        "Machal Jalb\u0101ni",
        "Basti Ubhechar",
        "Basti Chalbani"
    ],
    "wof:name":"Basti Chalbani",
    "wof:placetype":"locality"
},
  "geometry": {"coordinates":[71.0039,29.37833],"type":"Point"}
}