{
  "type": "Feature",
  "properties": {
    "gn:admin1_code":"5.0",
    "gn:asciiname":"Photo Khan Dasti",
    "gn:country_code":"PK",
    "gn:dem":48,
    "gn:feature_class":"P",
    "gn:feature_code":"PPL",
    "gn:name":"Photo Khan Dasti",
    "gn:population":0,
    "gn:timezone":"Asia/Karachi",
    "iso:country":"PK",
    "wof:name":"Photo Khan Dasti",
    "wof:placetype":"locality"
},
  "geometry": {"coordinates":[68.64718000000001,27.03969],"type":"Point"}
}