{
  "type": "Feature",
  "properties": {
    "gn:admin1_code":"3.0",
    "gn:asciiname":"Shailian Khum",
    "gn:country_code":"PK",
    "gn:dem":2775,
    "gn:feature_class":"P",
    "gn:feature_code":"PPL",
    "gn:name":"Shailian Khum",
    "gn:population":0,
    "gn:timezone":"Asia/Karachi",
    "iso:country":"PK",
    "wof:name":"Shailian Khum",
    "wof:placetype":"locality"
},
  "geometry": {"coordinates":[72.43734000000001,36.46262],"type":"Point"}
}