{
  "type": "Feature",
  "properties": {
    "gn:admin1_code":"4.0",
    "gn:asciiname":"Dera Awananda",
    "gn:country_code":"PK",
    "gn:dem":185,
    "gn:feature_class":"P",
    "gn:feature_code":"PPL",
    "gn:name":"Dera Awananda",
    "gn:population":0,
    "gn:timezone":"Asia/Karachi",
    "iso:country":"PK",
    "name:und_x_variant":[
        "Dera Aw\u0101n\u0101nd"
    ],
    "wof:name":"Dera Awananda",
    "wof:placetype":"locality"
},
  "geometry": {"coordinates":[72.49616,32.28420999999999],"type":"Point"}
}