{
  "type": "Feature",
  "properties": {
    "gn:admin1_code":"04",
    "gn:asciiname":"Allahwala",
    "gn:country_code":"PK",
    "gn:dem":163,
    "gn:feature_class":"P",
    "gn:feature_code":"PPL",
    "gn:name":"Allahwala",
    "gn:population":0,
    "gn:timezone":"Asia/Karachi",
    "iso:country":"PK",
    "name:und_x_variant":[
        "Patti Allanwali",
        "Patti Allanw\u0101la",
        "Allahwala"
    ],
    "wof:name":"Allahwala",
    "wof:placetype":"locality"
},
  "geometry": {"coordinates":[72.21579,31.70091],"type":"Point"}
}