{
  "type": "Feature",
  "properties": {
    "gn:admin1_code":"5.0",
    "gn:asciiname":"Darbelo",
    "gn:country_code":"PK",
    "gn:dem":54,
    "gn:feature_class":"P",
    "gn:feature_code":"PPL",
    "gn:name":"Darbelo",
    "gn:population":0,
    "gn:timezone":"Asia/Karachi",
    "iso:country":"PK",
    "name:und_x_variant":[
        "Darbeto",
        "Darbela",
        "Darbello",
        "Darbelo"
    ],
    "wof:name":"Darbelo",
    "wof:placetype":"locality"
},
  "geometry": {"coordinates":[68.12595,27.01646],"type":"Point"}
}