{
  "type": "Feature",
  "properties": {
    "gn:admin1_code":"3",
    "gn:asciiname":"Uch Banda",
    "gn:country_code":"PK",
    "gn:dem":2484,
    "gn:feature_class":"P",
    "gn:feature_code":"PPL",
    "gn:name":"Uch Banda",
    "gn:population":0,
    "gn:timezone":"Asia/Karachi",
    "iso:country":"PK",
    "name:eng_x_preferred":[
        "Una B\u0101nda"
    ],
    "wof:name":"Uch Banda",
    "wof:placetype":"locality"
},
  "geometry": {"coordinates":[71.86028,35.08657],"type":"Point"}
}