{
  "type": "Feature",
  "properties": {
    "gn:admin1_code":"3.0",
    "gn:asciiname":"Shahpar",
    "gn:country_code":"PK",
    "gn:dem":304,
    "gn:feature_class":"P",
    "gn:feature_code":"PPL",
    "gn:name":"Shahpar",
    "gn:population":0,
    "gn:timezone":"Asia/Karachi",
    "iso:country":"PK",
    "name:eng_x_preferred":[
        "Dawa"
    ],
    "wof:name":"Shahpar",
    "wof:placetype":"locality"
},
  "geometry": {"coordinates":[71.70241999999998,34.04613],"type":"Point"}
}