{
  "type": "Feature",
  "properties": {
    "gn:admin1_code":"5",
    "gn:asciiname":"Goth Abdul Hadi",
    "gn:country_code":"PK",
    "gn:dem":13,
    "gn:feature_class":"P",
    "gn:feature_code":"PPL",
    "gn:name":"Goth Abdul Hadi",
    "gn:population":0,
    "gn:timezone":"Asia/Karachi",
    "iso:country":"PK",
    "name:und_x_variant":[
        "Goth Abdul Haq Bhurgari"
    ],
    "wof:name":"Goth Abdul Hadi",
    "wof:placetype":"locality"
},
  "geometry": {"coordinates":[69.09453000000001,25.04558],"type":"Point"}
}