{
  "type": "Feature",
  "properties": {
    "gn:admin1_code":"5",
    "gn:asciiname":"Goth Shadi Khan Pitafi",
    "gn:country_code":"PK",
    "gn:dem":20,
    "gn:feature_class":"P",
    "gn:feature_code":"PPL",
    "gn:name":"Goth Shadi Khan Pitafi",
    "gn:population":0,
    "gn:timezone":"Asia/Karachi",
    "iso:country":"PK",
    "name:und_x_variant":[
        "Goth Sh\u0101h Kh\u0101n Pit\u0101fi"
    ],
    "wof:name":"Goth Shadi Khan Pitafi",
    "wof:placetype":"locality"
},
  "geometry": {"coordinates":[68.67829999999999,25.29608],"type":"Point"}
}