{
  "type": "Feature",
  "properties": {
    "gn:admin1_code":"3",
    "gn:asciiname":"Landai",
    "gn:country_code":"PK",
    "gn:dem":944,
    "gn:feature_class":"P",
    "gn:feature_code":"PPL",
    "gn:name":"Landai",
    "gn:population":0,
    "gn:timezone":"Asia/Karachi",
    "iso:country":"PK",
    "wof:name":"Landai",
    "wof:placetype":"locality"
},
  "geometry": {"coordinates":[73.12078000000002,34.4291],"type":"Point"}
}