{
  "type": "Feature",
  "properties": {
    "gn:admin1_code":"2.0",
    "gn:asciiname":"Fatha Makrani",
    "gn:country_code":"PK",
    "gn:dem":32,
    "gn:feature_class":"P",
    "gn:feature_code":"PPL",
    "gn:name":"Fatha Makrani",
    "gn:population":0,
    "gn:timezone":"Asia/Karachi",
    "iso:country":"PK",
    "name:eng_x_preferred":[
        "Goth Kh\u0101n Muhammad Baloch"
    ],
    "wof:name":"Fatha Makrani",
    "wof:placetype":"locality"
},
  "geometry": {"coordinates":[66.94711,25.05038],"type":"Point"}
}