{
  "type": "Feature",
  "properties": {
    "gn:admin1_code":"4",
    "gn:asciiname":"Chak Two Hundred Thirty-two Gugera Branch",
    "gn:country_code":"PK",
    "gn:dem":182,
    "gn:feature_class":"P",
    "gn:feature_code":"PPL",
    "gn:name":"Chak Two Hundred Thirty-two Gugera Branch",
    "gn:population":0,
    "gn:timezone":"Asia/Karachi",
    "iso:country":"PK",
    "name:und_x_variant":[
        "Guru Ka",
        "Hakiksang"
    ],
    "wof:name":"Chak Two Hundred Thirty-two Gugera Branch",
    "wof:placetype":"locality"
},
  "geometry": {"coordinates":[73.12898,31.16973],"type":"Point"}
}