{
  "type": "Feature",
  "properties": {
    "gn:admin1_code":"3.0",
    "gn:asciiname":"Wanda Surat Khan",
    "gn:country_code":"PK",
    "gn:dem":388,
    "gn:feature_class":"P",
    "gn:feature_code":"PPL",
    "gn:name":"Wanda Surat Khan",
    "gn:population":0,
    "gn:timezone":"Asia/Karachi",
    "iso:country":"PK",
    "wof:name":"Wanda Surat Khan",
    "wof:placetype":"locality"
},
  "geometry": {"coordinates":[71.11910999999998,32.52431],"type":"Point"}
}