{
  "type": "Feature",
  "properties": {
    "gn:admin1_code":"4.0",
    "gn:asciiname":"Daroli",
    "gn:country_code":"PK",
    "gn:dem":182,
    "gn:feature_class":"P",
    "gn:feature_code":"PPL",
    "gn:name":"Daroli",
    "gn:population":0,
    "gn:timezone":"Asia/Karachi",
    "iso:country":"PK",
    "name:vie_x_preferred":[
        "Daroli"
    ],
    "wof:name":"Daroli",
    "wof:placetype":"locality"
},
  "geometry": {"coordinates":[73.46344999999999,30.79498],"type":"Point"}
}