{
  "type": "Feature",
  "properties": {
    "gn:admin1_code":"4.0",
    "gn:asciiname":"Chak Panhatti",
    "gn:country_code":"PK",
    "gn:dem":605,
    "gn:feature_class":"P",
    "gn:feature_code":"PPL",
    "gn:name":"Chak Panhatti",
    "gn:population":0,
    "gn:timezone":"Asia/Karachi",
    "iso:country":"PK",
    "wof:name":"Chak Panhatti",
    "wof:placetype":"locality"
},
  "geometry": {"coordinates":[73.51861,33.61839000000001],"type":"Point"}
}