{
  "type": "Feature",
  "properties": {
    "gn:admin1_code":"4",
    "gn:asciiname":"Kalla Punwan",
    "gn:country_code":"PK",
    "gn:dem":230,
    "gn:feature_class":"P",
    "gn:feature_code":"PPL",
    "gn:name":"Kalla Punwan",
    "gn:population":0,
    "gn:timezone":"Asia/Karachi",
    "iso:country":"PK",
    "name:und_x_variant":[
        "K\u0101lra Punnu"
    ],
    "wof:name":"Kalla Punwan",
    "wof:placetype":"locality"
},
  "geometry": {"coordinates":[74.09865000000001,32.54967],"type":"Point"}
}