{
  "type": "Feature",
  "properties": {
    "gn:admin1_code":"4",
    "gn:asciiname":"Chah Tolewala",
    "gn:country_code":"PK",
    "gn:dem":134,
    "gn:feature_class":"P",
    "gn:feature_code":"PPL",
    "gn:name":"Chah Tolewala",
    "gn:population":0,
    "gn:timezone":"Asia/Karachi",
    "iso:country":"PK",
    "name:und_x_variant":[
        "Toli\u0101w\u0101la"
    ],
    "wof:name":"Chah Tolewala",
    "wof:placetype":"locality"
},
  "geometry": {"coordinates":[71.74677,30.32861],"type":"Point"}
}