{
  "type": "Feature",
  "properties": {
    "gn:admin1_code":"6",
    "gn:asciiname":"Khalabet Jhil",
    "gn:country_code":"PK",
    "gn:dem":340,
    "gn:feature_class":"P",
    "gn:feature_code":"PPL",
    "gn:name":"Khalabet Jhil",
    "gn:population":0,
    "gn:timezone":"Asia/Karachi",
    "iso:country":"PK",
    "wof:name":"Khalabet Jhil",
    "wof:placetype":"locality"
},
  "geometry": {"coordinates":[74.37014000000001,32.88391],"type":"Point"}
}