{
  "type": "Feature",
  "properties": {
    "gn:admin1_code":"05",
    "gn:asciiname":"Palh",
    "gn:country_code":"PK",
    "gn:dem":28,
    "gn:feature_class":"P",
    "gn:feature_code":"PPL",
    "gn:name":"Palh",
    "gn:population":0,
    "gn:timezone":"Asia/Karachi",
    "iso:country":"PK",
    "name:und_x_variant":[
        "Palhanjo"
    ],
    "wof:name":"Palh",
    "wof:placetype":"locality"
},
  "geometry": {"coordinates":[68.59123000000001,26.13455],"type":"Point"}
}