{
  "type": "Feature",
  "properties": {
    "gn:admin1_code":"1.0",
    "gn:asciiname":"Gardai",
    "gn:country_code":"PK",
    "gn:dem":1734,
    "gn:feature_class":"P",
    "gn:feature_code":"PPL",
    "gn:name":"Gardai",
    "gn:population":0,
    "gn:timezone":"Asia/Karachi",
    "iso:country":"PK",
    "name:und_x_variant":[
        "Badar Khel",
        "Gardai",
        "Gardi"
    ],
    "wof:name":"Gardai",
    "wof:placetype":"locality"
},
  "geometry": {"coordinates":[69.66710999999999,33.04071],"type":"Point"}
}