{
  "type": "Feature",
  "properties": {
    "gn:admin1_code":"4",
    "gn:asciiname":"Budhuwala Khu",
    "gn:country_code":"PK",
    "gn:dem":139,
    "gn:feature_class":"P",
    "gn:feature_code":"PPL",
    "gn:name":"Budhuwala Khu",
    "gn:population":0,
    "gn:timezone":"Asia/Karachi",
    "iso:country":"PK",
    "name:und_x_variant":[
        "Budhuw\u0101la"
    ],
    "wof:name":"Budhuwala Khu",
    "wof:placetype":"locality"
},
  "geometry": {"coordinates":[71.49396,30.77411],"type":"Point"}
}