{
  "type": "Feature",
  "properties": {
    "gn:admin1_code":"4",
    "gn:asciiname":"Lalapur",
    "gn:country_code":"PK",
    "gn:dem":218,
    "gn:feature_class":"P",
    "gn:feature_code":"PPL",
    "gn:name":"Lalapur",
    "gn:population":0,
    "gn:timezone":"Asia/Karachi",
    "iso:country":"PK",
    "name:und_x_variant":[
        "L\u0101l\u0101hpur"
    ],
    "wof:name":"Lalapur",
    "wof:placetype":"locality"
},
  "geometry": {"coordinates":[74.02321999999999,32.0177],"type":"Point"}
}