{
  "type": "Feature",
  "properties": {
    "gn:admin1_code":"4.0",
    "gn:asciiname":"Basti Jainwali",
    "gn:country_code":"PK",
    "gn:dem":86,
    "gn:feature_class":"P",
    "gn:feature_code":"PPL",
    "gn:name":"Basti Jainwali",
    "gn:population":0,
    "gn:timezone":"Asia/Karachi",
    "iso:country":"PK",
    "name:und_x_variant":[
        "Mahmud\u0101b\u0101d"
    ],
    "wof:name":"Basti Jainwali",
    "wof:placetype":"locality"
},
  "geometry": {"coordinates":[70.28180999999999,28.52922],"type":"Point"}
}