{
  "type": "Feature",
  "properties": {
    "gn:admin1_code":"4.0",
    "gn:asciiname":"Bhatiwala",
    "gn:country_code":"PK",
    "gn:dem":142,
    "gn:feature_class":"P",
    "gn:feature_code":"PPL",
    "gn:name":"Bhatiwala",
    "gn:population":0,
    "gn:timezone":"Asia/Karachi",
    "iso:country":"PK",
    "name:und_x_variant":[
        "Bastiw\u0101la"
    ],
    "wof:name":"Bhatiwala",
    "wof:placetype":"locality"
},
  "geometry": {"coordinates":[70.97045,30.8232],"type":"Point"}
}