{
  "type": "Feature",
  "properties": {
    "gn:admin1_code":"4.0",
    "gn:asciiname":"Mohra Phaphra",
    "gn:country_code":"PK",
    "gn:dem":497,
    "gn:feature_class":"P",
    "gn:feature_code":"PPL",
    "gn:name":"Mohra Phaphra",
    "gn:population":0,
    "gn:timezone":"Asia/Karachi",
    "iso:country":"PK",
    "wof:name":"Mohra Phaphra",
    "wof:placetype":"locality"
},
  "geometry": {"coordinates":[73.08065999999999,33.4131],"type":"Point"}
}