{
  "type": "Feature",
  "properties": {
    "gn:admin1_code":"5.0",
    "gn:asciiname":"Godanghri",
    "gn:country_code":"PK",
    "gn:dem":18,
    "gn:feature_class":"P",
    "gn:feature_code":"PPL",
    "gn:name":"Godanghri",
    "gn:population":0,
    "gn:timezone":"Asia/Karachi",
    "iso:country":"PK",
    "name:und_x_variant":[
        "God\u0101ngri"
    ],
    "wof:name":"Godanghri",
    "wof:placetype":"locality"
},
  "geometry": {"coordinates":[70.26694999999999,24.45667000000001],"type":"Point"}
}