{
  "type": "Feature",
  "properties": {
    "gn:admin1_code":"4.0",
    "gn:asciiname":"Khuewala Mohra",
    "gn:country_code":"PK",
    "gn:dem":585,
    "gn:feature_class":"P",
    "gn:feature_code":"PPL",
    "gn:name":"Khuewala Mohra",
    "gn:population":0,
    "gn:timezone":"Asia/Karachi",
    "iso:country":"PK",
    "wof:name":"Khuewala Mohra",
    "wof:placetype":"locality"
},
  "geometry": {"coordinates":[73.33226999999999,33.54128],"type":"Point"}
}