{
  "type": "Feature",
  "properties": {
    "gn:admin1_code":"4",
    "gn:asciiname":"Lakwala",
    "gn:country_code":"PK",
    "gn:dem":132,
    "gn:feature_class":"P",
    "gn:feature_code":"PPL",
    "gn:name":"Lakwala",
    "gn:population":0,
    "gn:timezone":"Asia/Karachi",
    "iso:country":"PK",
    "name:eng_x_preferred":[
        "Lakwala"
    ],
    "wof:name":"Lakwala",
    "wof:placetype":"locality"
},
  "geometry": {"coordinates":[70.89504000000002,30.44049],"type":"Point"}
}