{
  "type": "Feature",
  "properties": {
    "gn:admin1_code":"5.0",
    "gn:asciiname":"Sawan Faqir",
    "gn:country_code":"PK",
    "gn:dem":12,
    "gn:feature_class":"P",
    "gn:feature_code":"PPL",
    "gn:name":"Sawan Faqir",
    "gn:population":0,
    "gn:timezone":"Asia/Karachi",
    "iso:country":"PK",
    "name:und_x_variant":[
        "S\u0101wan Faq\u012br"
    ],
    "wof:name":"Sawan Faqir",
    "wof:placetype":"locality"
},
  "geometry": {"coordinates":[68.84403,24.63112000000001],"type":"Point"}
}