{
  "type": "Feature",
  "properties": {
    "gn:admin1_code":"3.0",
    "gn:asciiname":"Dwa Manzai",
    "gn:country_code":"PK",
    "gn:dem":358,
    "gn:feature_class":"P",
    "gn:feature_code":"PPL",
    "gn:name":"Dwa Manzai",
    "gn:population":0,
    "gn:timezone":"Asia/Karachi",
    "iso:country":"PK",
    "wof:name":"Dwa Manzai",
    "wof:placetype":"locality"
},
  "geometry": {"coordinates":[70.66461,33.03261],"type":"Point"}
}