{
  "type": "Feature",
  "properties": {
    "gn:admin1_code":"4.0",
    "gn:asciiname":"Wan Khan Shahu",
    "gn:country_code":"PK",
    "gn:dem":178,
    "gn:feature_class":"P",
    "gn:feature_code":"PPL",
    "gn:name":"Wan Khan Shahu",
    "gn:population":0,
    "gn:timezone":"Asia/Karachi",
    "iso:country":"PK",
    "wof:name":"Wan Khan Shahu",
    "wof:placetype":"locality"
},
  "geometry": {"coordinates":[73.21635000000001,30.87676],"type":"Point"}
}