{
  "type": "Feature",
  "properties": {
    "gn:admin1_code":"5.0",
    "gn:asciiname":"Allah Warayo Zardari",
    "gn:country_code":"PK",
    "gn:dem":34,
    "gn:feature_class":"P",
    "gn:feature_code":"PPL",
    "gn:name":"Allah Warayo Zardari",
    "gn:population":0,
    "gn:timezone":"Asia/Karachi",
    "iso:country":"PK",
    "wof:name":"Allah Warayo Zardari",
    "wof:placetype":"locality"
},
  "geometry": {"coordinates":[68.24096999999999,26.24358],"type":"Point"}
}