{
  "type": "Feature",
  "properties": {
    "gn:admin1_code":"3",
    "gn:asciiname":"Shahjahan Town",
    "gn:country_code":"PK",
    "gn:dem":172,
    "gn:feature_class":"P",
    "gn:feature_code":"PPL",
    "gn:name":"Shahjahan Town",
    "gn:population":0,
    "gn:timezone":"Asia/Karachi",
    "iso:country":"PK",
    "name:und_x_variant":[
        "Kachi Paindew\u0101li"
    ],
    "wof:name":"Shahjahan Town",
    "wof:placetype":"locality"
},
  "geometry": {"coordinates":[70.91349,31.83831],"type":"Point"}
}