{
  "type": "Feature",
  "properties": {
    "gn:admin1_code":"03",
    "gn:asciiname":"Shangwatai",
    "gn:country_code":"PK",
    "gn:dem":1164,
    "gn:feature_class":"P",
    "gn:feature_code":"PPL",
    "gn:name":"Shangwatai",
    "gn:population":0,
    "gn:timezone":"Asia/Karachi",
    "iso:country":"PK",
    "name:und_x_variant":[
        "Shangwati",
        "Shangwatai"
    ],
    "wof:name":"Shangwatai",
    "wof:placetype":"locality"
},
  "geometry": {"coordinates":[72.37364000000002,34.93783],"type":"Point"}
}