{
  "type": "Feature",
  "properties": {
    "gn:admin1_code":"2.0",
    "gn:asciiname":"Bukhtiar Khan Spelai Kili",
    "gn:country_code":"PK",
    "gn:dem":1922,
    "gn:feature_class":"P",
    "gn:feature_code":"PPL",
    "gn:name":"Bukhtiar Khan Spelai Kili",
    "gn:population":0,
    "gn:timezone":"Asia/Karachi",
    "iso:country":"PK",
    "wof:name":"Bukhtiar Khan Spelai Kili",
    "wof:placetype":"locality"
},
  "geometry": {"coordinates":[69.02800000000001,31.09177],"type":"Point"}
}