{
  "type": "Feature",
  "properties": {
    "gn:admin1_code":"4",
    "gn:asciiname":"Lahr",
    "gn:country_code":"PK",
    "gn:dem":787,
    "gn:feature_class":"P",
    "gn:feature_code":"PPL",
    "gn:name":"Lahr",
    "gn:population":0,
    "gn:timezone":"Asia/Karachi",
    "iso:country":"PK",
    "wof:name":"Lahr",
    "wof:placetype":"locality"
},
  "geometry": {"coordinates":[73.04756999999999,32.74788],"type":"Point"}
}