{
  "type": "Feature",
  "properties": {
    "gn:admin1_code":"4.0",
    "gn:asciiname":"Bhagsar",
    "gn:country_code":"PK",
    "gn:dem":89,
    "gn:feature_class":"P",
    "gn:feature_code":"PPL",
    "gn:name":"Bhagsar",
    "gn:population":0,
    "gn:timezone":"Asia/Karachi",
    "iso:country":"PK",
    "name:und_x_variant":[
        "Bhagsar Khas",
        "Bhagsar"
    ],
    "wof:name":"Bhagsar",
    "wof:placetype":"locality"
},
  "geometry": {"coordinates":[70.20741,28.83702000000001],"type":"Point"}
}