{
  "type": "Feature",
  "properties": {
    "gn:admin1_code":"4",
    "gn:asciiname":"Bhindar Kalan",
    "gn:country_code":"PK",
    "gn:dem":214,
    "gn:feature_class":"P",
    "gn:feature_code":"PPL",
    "gn:name":"Bhindar Kalan",
    "gn:population":0,
    "gn:timezone":"Asia/Karachi",
    "iso:country":"PK",
    "name:und_x_variant":[
        "Bhindar Khurd"
    ],
    "wof:name":"Bhindar Kalan",
    "wof:placetype":"locality"
},
  "geometry": {"coordinates":[73.73822,32.48477],"type":"Point"}
}