{
  "type": "Feature",
  "properties": {
    "gn:admin1_code":"4",
    "gn:asciiname":"Bhindar Kalan",
    "gn:country_code":"PK",
    "gn:dem":214,
    "gn:feature_class":"P",
    "gn:feature_code":"PPL",
    "gn:name":"Bhindar Kalan",
    "gn:population":0,
    "gn:timezone":"Asia/Karachi",
    "iso:country":"PK",
    "name:ceb_x_preferred":[
        "Bhindar Kal\u0101n"
    ],
    "name:fas_x_preferred":[
        "\u0628\u0647\u06cc\u0646\u062f\u0631 \u06a9\u0644\u0627\u0646"
    ],
    "name:und_x_variant":[
        "Bhindar Khurd"
    ],
    "name:urd_x_preferred":[
        "\u0628\u06be\u0646\u0688\u0631 \u06a9\u0644\u0627\u06ba"
    ],
    "wof:name":"Bhindar Kalan",
    "wof:placetype":"locality"
},
  "geometry": {"coordinates":[73.73822,32.48477],"type":"Point"}
}