{
  "type": "Feature",
  "properties": {
    "gn:country":"PK",
    "gn:fcode":"PPL",
    "gn:population":2986,
    "iso:country":"PK",
    "name:ceb_x_preferred":[
        "Cher\u0101t"
    ],
    "name:eng_x_preferred":[
        "Cherat"
    ],
    "name:fas_x_preferred":[
        "\u0686\u0631\u0627\u062a"
    ],
    "name:nld_x_preferred":[
        "Cherat"
    ],
    "name:pnb_x_preferred":[
        "\u0686\u0631\u0627\u0679"
    ],
    "name:por_x_preferred":[
        "Cherat"
    ],
    "name:rus_x_preferred":[
        "\u0427\u0435\u0440\u0430\u0442"
    ],
    "name:und_x_variant":[
        "Cher\u0101t Cantonement"
    ],
    "name:urd_x_preferred":[
        "\u0686\u0631\u0627\u0679"
    ],
    "name:zho_x_preferred":[
        "\u5091\u62c9\u7279"
    ],
    "qs_pg:aaroncc":"PK",
    "qs_pg:gn_country":"PK",
    "qs_pg:gn_fcode":"PPL",
    "qs_pg:gn_pop":2986,
    "qs_pg:name":"Cher\u0101t",
    "qs_pg:photos_9r":0,
    "qs_pg:photos_sr":0,
    "qs_pg:pop_sr":4,
    "qs_pg:qs_pg_placetype":"locality",
    "wof:name":"Cher\u0101t",
    "wof:placetype":"locality",
    "wof:population":2986
},
  "geometry": {"coordinates":[71.89153,33.82328],"type":"Point"}
}