{
  "type": "Feature",
  "properties": {
    "gn:admin1_code":"4",
    "gn:asciiname":"Muhadipur",
    "gn:country_code":"PK",
    "gn:dem":258,
    "gn:feature_class":"P",
    "gn:feature_code":"PPL",
    "gn:name":"Muhadipur",
    "gn:population":0,
    "gn:timezone":"Asia/Karachi",
    "iso:country":"PK",
    "name:und_x_variant":[
        "Mehdipur",
        "Muhadipur"
    ],
    "wof:name":"Muhadipur",
    "wof:placetype":"locality"
},
  "geometry": {"coordinates":[74.62380999999998,32.59096],"type":"Point"}
}