{
  "type": "Feature",
  "properties": {
    "gn:admin1_code":"4.0",
    "gn:asciiname":"Mad Jamal",
    "gn:country_code":"PK",
    "gn:dem":88,
    "gn:feature_class":"P",
    "gn:feature_code":"PPL",
    "gn:name":"Mad Jamal",
    "gn:population":0,
    "gn:timezone":"Asia/Karachi",
    "iso:country":"PK",
    "wof:name":"Mad Jamal",
    "wof:placetype":"locality"
},
  "geometry": {"coordinates":[70.44274,28.72449000000001],"type":"Point"}
}