{
  "type": "Feature",
  "properties": {
    "gn:admin1_code":"05",
    "gn:asciiname":"Thul",
    "gn:country_code":"PK",
    "gn:dem":44,
    "gn:feature_class":"P",
    "gn:feature_code":"PPL",
    "gn:name":"Thul",
    "gn:population":0,
    "gn:timezone":"Asia/Karachi",
    "iso:country":"PK",
    "name:und_x_variant":[
        "Thu Mir Khan",
        "Thul M\u012br Kh\u0101n"
    ],
    "wof:name":"Thul",
    "wof:placetype":"locality"
},
  "geometry": {"coordinates":[67.48248000000001,26.60769],"type":"Point"}
}