{
  "type": "Feature",
  "properties": {
    "gn:admin1_code":"05",
    "gn:asciiname":"Thul",
    "gn:country_code":"PK",
    "gn:dem":44,
    "gn:feature_class":"P",
    "gn:feature_code":"PPL",
    "gn:name":"Thul",
    "gn:population":0,
    "gn:timezone":"Asia/Karachi",
    "iso:country":"PK",
    "name:ceb_x_preferred":[
        "Thul"
    ],
    "name:eng_x_preferred":[
        "Thul"
    ],
    "name:fas_x_preferred":[
        "\u062a\u0647\u0648\u0644"
    ],
    "name:fra_x_preferred":[
        "Thul"
    ],
    "name:spa_x_preferred":[
        "Thul"
    ],
    "name:und_x_variant":[
        "Thu Mir Khan",
        "Thul M\u012br Kh\u0101n"
    ],
    "name:urd_x_preferred":[
        "\u062a\u06be\u0644"
    ],
    "wof:name":"Thul",
    "wof:placetype":"locality"
},
  "geometry": {"coordinates":[67.48248,26.60769],"type":"Point"}
}