{
  "type": "Feature",
  "properties": {
    "gn:admin1_code":"3.0",
    "gn:asciiname":"Sarkoh Banda",
    "gn:country_code":"PK",
    "gn:dem":3134,
    "gn:feature_class":"P",
    "gn:feature_code":"PPL",
    "gn:name":"Sarkoh Banda",
    "gn:population":0,
    "gn:timezone":"Asia/Karachi",
    "iso:country":"PK",
    "wof:name":"Sarkoh Banda",
    "wof:placetype":"locality"
},
  "geometry": {"coordinates":[71.93644,35.59161],"type":"Point"}
}