{
  "type": "Feature",
  "properties": {
    "gn:admin1_code":"5",
    "gn:asciiname":"Haji Abdul Wahid Goth",
    "gn:country_code":"PK",
    "gn:dem":72,
    "gn:feature_class":"P",
    "gn:feature_code":"PPL",
    "gn:name":"Haji Abdul Wahid Goth",
    "gn:population":0,
    "gn:timezone":"Asia/Karachi",
    "iso:country":"PK",
    "name:und_x_variant":[
        "Bakhsh Kh\u0101n Golo"
    ],
    "wof:name":"Haji Abdul Wahid Goth",
    "wof:placetype":"locality"
},
  "geometry": {"coordinates":[69.31116,28.26654000000001],"type":"Point"}
}