{
  "type": "Feature",
  "properties": {
    "gn:admin1_code":"4",
    "gn:asciiname":"Darbar Pir Roshan Shah",
    "gn:country_code":"PK",
    "gn:dem":151,
    "gn:feature_class":"P",
    "gn:feature_code":"PPL",
    "gn:name":"Darbar Pir Roshan Shah",
    "gn:population":0,
    "gn:timezone":"Asia/Karachi",
    "iso:country":"PK",
    "name:und_x_variant":[
        "P\u012br Roshan Sh\u0101h"
    ],
    "wof:name":"Darbar Pir Roshan Shah",
    "wof:placetype":"locality"
},
  "geometry": {"coordinates":[72.20325,31.24635],"type":"Point"}
}