{
  "type": "Feature",
  "properties": {
    "gn:admin1_code":"3.0",
    "gn:asciiname":"Chehl",
    "gn:country_code":"PK",
    "gn:dem":325,
    "gn:feature_class":"P",
    "gn:feature_code":"PPL",
    "gn:name":"Chehl",
    "gn:population":0,
    "gn:timezone":"Asia/Karachi",
    "iso:country":"PK",
    "name:eng_x_preferred":[
        "Chel"
    ],
    "name:und_x_variant":[
        "Chail",
        "Chehl"
    ],
    "wof:name":"Chehl",
    "wof:placetype":"locality"
},
  "geometry": {"coordinates":[71.99124,34.23485],"type":"Point"}
}