{
  "type": "Feature",
  "properties": {
    "gn:admin1_code":"3.0",
    "gn:asciiname":"Rahman Baihk",
    "gn:country_code":"PK",
    "gn:dem":3793,
    "gn:feature_class":"P",
    "gn:feature_code":"PPL",
    "gn:name":"Rahman Baihk",
    "gn:population":0,
    "gn:timezone":"Asia/Karachi",
    "iso:country":"PK",
    "wof:name":"Rahman Baihk",
    "wof:placetype":"locality"
},
  "geometry": {"coordinates":[74.042,35.1296],"type":"Point"}
}