{
  "type": "Feature",
  "properties": {
    "gn:admin1_code":"5",
    "gn:asciiname":"Thiba Jo Goth",
    "gn:country_code":"PK",
    "gn:dem":51,
    "gn:feature_class":"P",
    "gn:feature_code":"PPL",
    "gn:name":"Thiba Jo Goth",
    "gn:population":0,
    "gn:timezone":"Asia/Karachi",
    "iso:country":"PK",
    "name:und_x_variant":[
        "Theba"
    ],
    "wof:name":"Thiba Jo Goth",
    "wof:placetype":"locality"
},
  "geometry": {"coordinates":[68.40281999999999,27.15926],"type":"Point"}
}