{
  "type": "Feature",
  "properties": {
    "gn:admin1_code":"4.0",
    "gn:asciiname":"Aldani",
    "gn:country_code":"PK",
    "gn:dem":1057,
    "gn:feature_class":"P",
    "gn:feature_code":"PPL",
    "gn:name":"Aldani",
    "gn:population":0,
    "gn:timezone":"Asia/Karachi",
    "iso:country":"PK",
    "wof:name":"Aldani",
    "wof:placetype":"locality"
},
  "geometry": {"coordinates":[70.10579,30.42989],"type":"Point"}
}