{
  "type": "Feature",
  "properties": {
    "gn:admin1_code":"4.0",
    "gn:asciiname":"Gurmani",
    "gn:country_code":"PK",
    "gn:dem":128,
    "gn:feature_class":"P",
    "gn:feature_code":"PPL",
    "gn:name":"Gurmani",
    "gn:population":0,
    "gn:timezone":"Asia/Karachi",
    "iso:country":"PK",
    "name:eng_x_preferred":[
        "Gurmani"
    ],
    "wof:name":"Gurmani",
    "wof:placetype":"locality"
},
  "geometry": {"coordinates":[70.95755,30.26758],"type":"Point"}
}