{
  "type": "Feature",
  "properties": {
    "gn:admin1_code":"4.0",
    "gn:asciiname":"Walana",
    "gn:country_code":"PK",
    "gn:dem":79,
    "gn:feature_class":"P",
    "gn:feature_code":"PPL",
    "gn:name":"Walana",
    "gn:population":0,
    "gn:timezone":"Asia/Karachi",
    "iso:country":"PK",
    "name:fas_x_preferred":[
        "\u0648\u0644\u0627\u0646\u0647"
    ],
    "name:urd_x_preferred":[
        "\u0648\u0644\u0627\u0646\u06c1"
    ],
    "wof:name":"Walana",
    "wof:placetype":"locality"
},
  "geometry": {"coordinates":[70.01453000000001,28.2736],"type":"Point"}
}