{
  "type": "Feature",
  "properties": {
    "gn:admin1_code":"4.0",
    "gn:asciiname":"Dhok Daud Sharif",
    "gn:country_code":"PK",
    "gn:dem":225,
    "gn:feature_class":"P",
    "gn:feature_code":"PPL",
    "gn:name":"Dhok Daud Sharif",
    "gn:population":0,
    "gn:timezone":"Asia/Karachi",
    "iso:country":"PK",
    "name:und_x_variant":[
        "Dhok D\u0101\u016bd"
    ],
    "wof:name":"Dhok Daud Sharif",
    "wof:placetype":"locality"
},
  "geometry": {"coordinates":[73.59115,32.57254],"type":"Point"}
}