{
  "type": "Feature",
  "properties": {
    "gn:admin1_code":"03",
    "gn:asciiname":"Jabagai",
    "gn:country_code":"PK",
    "gn:dem":1307,
    "gn:feature_class":"P",
    "gn:feature_code":"PPL",
    "gn:name":"Jabagai",
    "gn:population":0,
    "gn:timezone":"Asia/Karachi",
    "iso:country":"PK",
    "name:eng_x_preferred":[
        "Jabagai"
    ],
    "wof:name":"Jabagai",
    "wof:placetype":"locality"
},
  "geometry": {"coordinates":[71.71966,34.89692],"type":"Point"}
}