{
  "type": "Feature",
  "properties": {
    "gn:admin1_code":"3.0",
    "gn:admin2_code":"Chitral",
    "gn:asciiname":"Haram",
    "gn:country_code":"PK",
    "gn:dem":2984,
    "gn:feature_class":"P",
    "gn:feature_code":"PPL",
    "gn:name":"Haram",
    "gn:population":0,
    "gn:timezone":"Asia/Karachi",
    "iso:country":"PK",
    "name:eng_x_preferred":[
        "Haram"
    ],
    "wof:name":"Haram",
    "wof:placetype":"locality"
},
  "geometry": {"coordinates":[72.04224000000001,35.69891],"type":"Point"}
}