{
  "type": "Feature",
  "properties": {
    "gn:admin1_code":"3.0",
    "gn:admin2_code":"Chitral",
    "gn:asciiname":"Haram",
    "gn:country_code":"PK",
    "gn:dem":2984,
    "gn:feature_class":"P",
    "gn:feature_code":"PPL",
    "gn:name":"Haram",
    "gn:population":0,
    "gn:timezone":"Asia/Karachi",
    "iso:country":"PK",
    "name:ara_x_preferred":[
        "\u062d\u0631\u0627\u0645"
    ],
    "name:aze_x_preferred":[
        "Haram"
    ],
    "name:bak_x_preferred":[
        "\u0425\u0430\u0440\u0430\u043c"
    ],
    "name:ben_x_preferred":[
        "\u09b9\u09be\u09b0\u09be\u09ae"
    ],
    "name:bos_x_preferred":[
        "Haram"
    ],
    "name:cat_x_preferred":[
        "H\u00e0ram"
    ],
    "name:che_x_preferred":[
        "\u0425\u044c\u0430\u0440\u0430\u043c"
    ],
    "name:dan_x_preferred":[
        "Haram"
    ],
    "name:deu_x_preferred":[
        "Har\u0101m"
    ],
    "name:diq_x_preferred":[
        "Heram"
    ],
    "name:eng_x_preferred":[
        "Haram"
    ],
    "name:epo_x_preferred":[
        "Haramo"
    ],
    "name:est_x_preferred":[
        "\u1e28ar\u0101m"
    ],
    "name:eus_x_preferred":[
        "Haraam"
    ],
    "name:fas_x_preferred":[
        "\u062d\u0631\u0627\u0645"
    ],
    "name:fin_x_preferred":[
        "Haram"
    ],
    "name:fra_x_preferred":[
        "Haram"
    ],
    "name:heb_x_preferred":[
        "\u05d7\u05e8\u05d0\u05dd"
    ],
    "name:hin_x_preferred":[
        "\u0939\u0930\u093e\u092e"
    ],
    "name:ind_x_preferred":[
        "Haram"
    ],
    "name:ita_x_preferred":[
        "Har\u0101m"
    ],
    "name:jav_x_preferred":[
        "Karam"
    ],
    "name:jpn_x_preferred":[
        "\u30cf\u30e9\u30fc\u30e0"
    ],
    "name:kaz_x_preferred":[
        "\u0425\u0430\u0440\u0430\u043c"
    ],
    "name:kir_x_preferred":[
        "\u0425\u0430\u0440\u0430\u043c"
    ],
    "name:lav_x_preferred":[
        "Har\u0101ms"
    ],
    "name:lit_x_preferred":[
        "Haram"
    ],
    "name:mal_x_preferred":[
        "\u0d39\u0d31\u0d3e\u0d02"
    ],
    "name:msa_x_preferred":[
        "Haram"
    ],
    "name:nor_x_preferred":[
        "Har\u0101m"
    ],
    "name:pan_x_preferred":[
        "\u0a39\u0a30\u0a3e\u0a2e"
    ],
    "name:pol_x_preferred":[
        "Haram"
    ],
    "name:por_x_preferred":[
        "Haraam"
    ],
    "name:rus_x_preferred":[
        "\u0425\u0430\u0440\u0430\u043c"
    ],
    "name:spa_x_preferred":[
        "Haram"
    ],
    "name:srp_x_preferred":[
        "Haram"
    ],
    "name:swe_x_preferred":[
        "Haram"
    ],
    "name:tam_x_preferred":[
        "\u0bb9\u0bb0\u0bbe\u0bae\u0bcd"
    ],
    "name:tel_x_preferred":[
        "\u0c39\u0c30\u0c3e\u0c2e\u0c4d"
    ],
    "name:tgk_x_preferred":[
        "\u04b2\u0430\u0440\u043e\u043c"
    ],
    "name:tha_x_preferred":[
        "\u0e2e\u0e30\u0e23\u0e2d\u0e21"
    ],
    "name:tur_x_preferred":[
        "Haram"
    ],
    "name:ukr_x_preferred":[
        "\u0425\u0430\u0440\u0430\u043c"
    ],
    "name:urd_x_preferred":[
        "\u062d\u0631\u0627\u0645"
    ],
    "name:zho_x_preferred":[
        "\u54c8\u62c9\u59c6"
    ],
    "wof:name":"Haram",
    "wof:placetype":"locality"
},
  "geometry": {"coordinates":[72.04224000000001,35.69891],"type":"Point"}
}