{
  "type": "Feature",
  "properties": {
    "gn:admin1_code":"5",
    "gn:asciiname":"Sumar Bughio",
    "gn:country_code":"PK",
    "gn:dem":43,
    "gn:feature_class":"P",
    "gn:feature_code":"PPL",
    "gn:name":"Sumar Bughio",
    "gn:population":0,
    "gn:timezone":"Asia/Karachi",
    "iso:country":"PK",
    "name:und_x_variant":[
        "Sumar Bagio"
    ],
    "wof:name":"Sumar Bughio",
    "wof:placetype":"locality"
},
  "geometry": {"coordinates":[67.86619,26.53531],"type":"Point"}
}