{
  "type": "Feature",
  "properties": {
    "gn:admin1_code":"2.0",
    "gn:asciiname":"Shah Kalag",
    "gn:country_code":"PK",
    "gn:dem":675,
    "gn:feature_class":"P",
    "gn:feature_code":"PPL",
    "gn:name":"Shah Kalag",
    "gn:population":0,
    "gn:timezone":"Asia/Karachi",
    "iso:country":"PK",
    "name:und_x_variant":[
        "Sh\u0101h Kalog"
    ],
    "wof:name":"Shah Kalag",
    "wof:placetype":"locality"
},
  "geometry": {"coordinates":[64.81818,26.32791],"type":"Point"}
}