{
  "type": "Feature",
  "properties": {
    "gn:admin1_code":"3.0",
    "gn:asciiname":"Beorai",
    "gn:country_code":"PK",
    "gn:dem":2292,
    "gn:feature_class":"P",
    "gn:feature_code":"PPL",
    "gn:name":"Beorai",
    "gn:population":0,
    "gn:timezone":"Asia/Karachi",
    "iso:country":"PK",
    "name:eng_x_preferred":[
        "Beorai"
    ],
    "wof:name":"Beorai",
    "wof:placetype":"locality"
},
  "geometry": {"coordinates":[71.68333,35.46667],"type":"Point"}
}