{
  "type": "Feature",
  "properties": {
    "gn:admin1_code":"6",
    "gn:asciiname":"Chhatreri",
    "gn:country_code":"PK",
    "gn:dem":791,
    "gn:feature_class":"P",
    "gn:feature_code":"PPL",
    "gn:name":"Chhatreri",
    "gn:population":0,
    "gn:timezone":"Asia/Karachi",
    "iso:country":"PK",
    "name:und_x_variant":[
        "Chhattreri"
    ],
    "wof:name":"Chhatreri",
    "wof:placetype":"locality"
},
  "geometry": {"coordinates":[73.94951,33.65687],"type":"Point"}
}