{
  "type": "Feature",
  "properties": {
    "gn:admin1_code":"5.0",
    "gn:asciiname":"Goth Ibrahim Panhwa",
    "gn:country_code":"PK",
    "gn:dem":7,
    "gn:feature_class":"P",
    "gn:feature_code":"PPL",
    "gn:name":"Goth Ibrahim Panhwa",
    "gn:population":0,
    "gn:timezone":"Asia/Karachi",
    "iso:country":"PK",
    "name:und_x_variant":[
        "Abdul Rahm\u0101n",
        "Ibr\u0101h\u012bm Panwhar",
        "Goth Ibrahim Panhwa"
    ],
    "wof:name":"Goth Ibrahim Panhwa",
    "wof:placetype":"locality"
},
  "geometry": {"coordinates":[67.74914,24.67799],"type":"Point"}
}