{
  "type": "Feature",
  "properties": {
    "gn:admin1_code":"4",
    "gn:asciiname":"Asranwan Mari",
    "gn:country_code":"PK",
    "gn:dem":113,
    "gn:feature_class":"P",
    "gn:feature_code":"PPL",
    "gn:name":"Asranwan Mari",
    "gn:population":0,
    "gn:timezone":"Asia/Karachi",
    "iso:country":"PK",
    "name:und_x_variant":[
        "San\u0101w\u0101n M\u0101ri",
        "Asr\u0101nw\u0101la",
        "Asranwan Mari"
    ],
    "wof:name":"Asranwan Mari",
    "wof:placetype":"locality"
},
  "geometry": {"coordinates":[71.49460000000001,29.49215],"type":"Point"}
}