{
  "type": "Feature",
  "properties": {
    "gn:admin1_code":"4.0",
    "gn:asciiname":"Eight D Maruf",
    "gn:country_code":"PK",
    "gn:dem":178,
    "gn:feature_class":"P",
    "gn:feature_code":"PPL",
    "gn:name":"Eight D Maruf",
    "gn:population":0,
    "gn:timezone":"Asia/Karachi",
    "iso:country":"PK",
    "wof:name":"Eight D Maruf",
    "wof:placetype":"locality"
},
  "geometry": {"coordinates":[73.85669,30.56151],"type":"Point"}
}