{
  "type": "Feature",
  "properties": {
    "gn:admin1_code":"3.0",
    "gn:asciiname":"Faqira Abad",
    "gn:country_code":"PK",
    "gn:dem":351,
    "gn:feature_class":"P",
    "gn:feature_code":"PPL",
    "gn:name":"Faqira Abad",
    "gn:population":0,
    "gn:timezone":"Asia/Karachi",
    "iso:country":"PK",
    "name:eng_x_preferred":[
        "Faqira Abad"
    ],
    "wof:name":"Faqira Abad",
    "wof:placetype":"locality"
},
  "geometry": {"coordinates":[71.91114,34.33869],"type":"Point"}
}