{
  "type": "Feature",
  "properties": {
    "gn:admin1_code":"2.0",
    "gn:asciiname":"Allahabad",
    "gn:country_code":"PK",
    "gn:dem":1551,
    "gn:feature_class":"P",
    "gn:feature_code":"PPL",
    "gn:name":"Allahabad",
    "gn:population":0,
    "gn:timezone":"Asia/Karachi",
    "iso:country":"PK",
    "name:eng_x_preferred":[
        "Allahabad"
    ],
    "wof:name":"Allahabad",
    "wof:placetype":"locality"
},
  "geometry": {"coordinates":[67.01446999999999,30.6049],"type":"Point"}
}