{
  "type": "Feature",
  "properties": {
    "gn:admin1_code":"1.0",
    "gn:asciiname":"Soghar",
    "gn:country_code":"PK",
    "gn:dem":2077,
    "gn:feature_class":"P",
    "gn:feature_code":"PPL",
    "gn:name":"Soghar",
    "gn:population":0,
    "gn:timezone":"Asia/Karachi",
    "iso:country":"PK",
    "wof:name":"Soghar",
    "wof:placetype":"locality"
},
  "geometry": {"coordinates":[70.25789,33.90211],"type":"Point"}
}