{
  "type": "Feature",
  "properties": {
    "gn:admin1_code":"8.0",
    "gn:asciiname":"Dhok Joha",
    "gn:country_code":"PK",
    "gn:dem":577,
    "gn:feature_class":"P",
    "gn:feature_code":"PPL",
    "gn:name":"Dhok Joha",
    "gn:population":0,
    "gn:timezone":"Asia/Karachi",
    "iso:country":"PK",
    "name:und_x_variant":[
        "Dhok Johd",
        "Joha",
        "Dhok Joha"
    ],
    "wof:name":"Dhok Joha",
    "wof:placetype":"locality"
},
  "geometry": {"coordinates":[72.91705,33.6757],"type":"Point"}
}