{
  "type": "Feature",
  "properties": {
    "gn:admin1_code":"3.0",
    "gn:asciiname":"Nasirabad",
    "gn:country_code":"PK",
    "gn:dem":735,
    "gn:feature_class":"P",
    "gn:feature_code":"PPL",
    "gn:name":"Nasirabad",
    "gn:population":0,
    "gn:timezone":"Asia/Karachi",
    "iso:country":"PK",
    "name:ceb_x_preferred":[
        "Nasirabad"
    ],
    "name:eng_x_preferred":[
        "Nasirabad"
    ],
    "name:fas_x_preferred":[
        "\u0646\u0635\u06cc\u0631\u0622\u0628\u0627\u062f"
    ],
    "name:mzn_x_preferred":[
        "\u0646\u0635\u06cc\u0631\u0622\u0628\u0627\u062f"
    ],
    "name:swe_x_preferred":[
        "Nasirabad"
    ],
    "name:urd_x_preferred":[
        "\u0646\u0635\u06cc\u0631\u0622\u0628\u0627\u062f"
    ],
    "wof:name":"Nasirabad",
    "wof:placetype":"locality"
},
  "geometry": {"coordinates":[72.42928000000001,34.51898],"type":"Point"}
}