{
  "type": "Feature",
  "properties": {
    "gn:admin1_code":"4",
    "gn:asciiname":"Chah Goganwala",
    "gn:country_code":"PK",
    "gn:dem":151,
    "gn:feature_class":"P",
    "gn:feature_code":"PPL",
    "gn:name":"Chah Goganwala",
    "gn:population":0,
    "gn:timezone":"Asia/Karachi",
    "iso:country":"PK",
    "name:und_x_variant":[
        "Goganw\u0101la",
        "Chah Goganwala"
    ],
    "wof:name":"Chah Goganwala",
    "wof:placetype":"locality"
},
  "geometry": {"coordinates":[70.70635,31.02932],"type":"Point"}
}