{
  "type": "Feature",
  "properties": {
    "gn:admin1_code":"4.0",
    "gn:asciiname":"Akhtarabad",
    "gn:country_code":"PK",
    "gn:dem":189,
    "gn:feature_class":"P",
    "gn:feature_code":"PPL",
    "gn:name":"Akhtarabad",
    "gn:population":0,
    "gn:timezone":"Asia/Karachi",
    "iso:country":"PK",
    "name:ceb_x_preferred":[
        "Akhtar\u0101b\u0101d"
    ],
    "name:fas_x_preferred":[
        "\u0627\u062e\u062a\u0631\u0622\u0628\u0627\u062f"
    ],
    "name:swe_x_preferred":[
        "Akhtar\u0101b\u0101d"
    ],
    "wof:name":"Akhtarabad",
    "wof:placetype":"locality"
},
  "geometry": {"coordinates":[73.68053,30.92374],"type":"Point"}
}