{
  "type": "Feature",
  "properties": {
    "gn:admin1_code":"2",
    "gn:asciiname":"Wal Zarkun",
    "gn:country_code":"PK",
    "gn:dem":1015,
    "gn:feature_class":"P",
    "gn:feature_code":"PPL",
    "gn:name":"Wal Zarkun",
    "gn:population":0,
    "gn:timezone":"Asia/Karachi",
    "iso:country":"PK",
    "name:und_x_variant":[
        "Wai Zark\u016bn"
    ],
    "wof:name":"Wal Zarkun",
    "wof:placetype":"locality"
},
  "geometry": {"coordinates":[69.01495,30.18696],"type":"Point"}
}