{
  "type": "Feature",
  "properties": {
    "gn:admin1_code":"3.0",
    "gn:asciiname":"Birgah",
    "gn:country_code":"PK",
    "gn:dem":2092,
    "gn:feature_class":"P",
    "gn:feature_code":"PPL",
    "gn:name":"Birgah",
    "gn:population":0,
    "gn:timezone":"Asia/Karachi",
    "iso:country":"PK",
    "name:eng_x_preferred":[
        "Birgah"
    ],
    "wof:name":"Birgah",
    "wof:placetype":"locality"
},
  "geometry": {"coordinates":[71.91074,35.67654],"type":"Point"}
}