{
  "type": "Feature",
  "properties": {
    "gn:admin1_code":"07",
    "gn:asciiname":"Silbu",
    "gn:country_code":"PK",
    "gn:dem":1761,
    "gn:feature_class":"P",
    "gn:feature_code":"PPL",
    "gn:name":"Silbu",
    "gn:population":0,
    "gn:timezone":"Asia/Karachi",
    "iso:country":"PK",
    "wof:name":"Silbu",
    "wof:placetype":"locality"
},
  "geometry": {"coordinates":[74.95429,35.63327],"type":"Point"}
}