{
  "type": "Feature",
  "properties": {
    "gn:admin1_code":"5",
    "gn:asciiname":"Goth Miral Sangi",
    "gn:country_code":"PK",
    "gn:dem":78,
    "gn:feature_class":"P",
    "gn:feature_code":"PPL",
    "gn:name":"Goth Miral Sangi",
    "gn:population":0,
    "gn:timezone":"Asia/Karachi",
    "iso:country":"PK",
    "name:und_x_variant":[
        "Goth M\u012bral"
    ],
    "wof:name":"Goth Miral Sangi",
    "wof:placetype":"locality"
},
  "geometry": {"coordinates":[69.41991,28.28574],"type":"Point"}
}