{
  "type": "Feature",
  "properties": {
    "gn:admin1_code":"4.0",
    "gn:asciiname":"Ghialwala",
    "gn:country_code":"PK",
    "gn:dem":112,
    "gn:feature_class":"P",
    "gn:feature_code":"PPL",
    "gn:name":"Ghialwala",
    "gn:population":0,
    "gn:timezone":"Asia/Karachi",
    "iso:country":"PK",
    "name:und_x_variant":[
        "Gehalpur",
        "Ghiyalpur",
        "Ghialpur",
        "Ghialwala"
    ],
    "wof:name":"Ghialwala",
    "wof:placetype":"locality"
},
  "geometry": {"coordinates":[70.90751999999998,29.75337],"type":"Point"}
}