{
  "type": "Feature",
  "properties": {
    "gn:admin1_code":"3.0",
    "gn:asciiname":"Nagi",
    "gn:country_code":"PK",
    "gn:dem":2011,
    "gn:feature_class":"P",
    "gn:feature_code":"PPL",
    "gn:name":"Nagi",
    "gn:population":0,
    "gn:timezone":"Asia/Karachi",
    "iso:country":"PK",
    "wof:name":"Nagi",
    "wof:placetype":"locality"
},
  "geometry": {"coordinates":[73.27869,34.66515],"type":"Point"}
}