{
  "type": "Feature",
  "properties": {
    "gn:admin1_code":"3.0",
    "gn:asciiname":"Nagi",
    "gn:country_code":"PK",
    "gn:dem":2011,
    "gn:feature_class":"P",
    "gn:feature_code":"PPL",
    "gn:name":"Nagi",
    "gn:population":0,
    "gn:timezone":"Asia/Karachi",
    "iso:country":"PK",
    "name:ceb_x_preferred":[
        "Nagi"
    ],
    "name:fra_x_preferred":[
        "Nagi"
    ],
    "name:ita_x_preferred":[
        "Nagi"
    ],
    "name:jpn_x_preferred":[
        "\u30ca\u30ae"
    ],
    "name:new_x_preferred":[
        "\u0928\u093e\u0917\u0940 \u0917\u093e\u0935\u093f\u0938"
    ],
    "name:pol_x_preferred":[
        "Nagi"
    ],
    "name:rus_x_preferred":[
        "\u041d\u0430\u0433\u0438"
    ],
    "name:swe_x_preferred":[
        "Nagi"
    ],
    "name:tha_x_preferred":[
        "\u0e19\u0e32\u0e07\u0e34"
    ],
    "name:zho_x_preferred":[
        "Nagi"
    ],
    "wof:name":"Nagi",
    "wof:placetype":"locality"
},
  "geometry": {"coordinates":[73.27869,34.66515],"type":"Point"}
}