{
  "type": "Feature",
  "properties": {
    "gn:admin1_code":"2.0",
    "gn:asciiname":"Inzare Kili",
    "gn:country_code":"PK",
    "gn:dem":1969,
    "gn:feature_class":"P",
    "gn:feature_code":"PPL",
    "gn:name":"Inzare Kili",
    "gn:population":0,
    "gn:timezone":"Asia/Karachi",
    "iso:country":"PK",
    "wof:name":"Inzare Kili",
    "wof:placetype":"locality"
},
  "geometry": {"coordinates":[68.54693,30.97017],"type":"Point"}
}