{
  "type": "Feature",
  "properties": {
    "gn:admin1_code":"4",
    "gn:asciiname":"Chah Nawabwala",
    "gn:country_code":"PK",
    "gn:dem":136,
    "gn:feature_class":"P",
    "gn:feature_code":"PPL",
    "gn:name":"Chah Nawabwala",
    "gn:population":0,
    "gn:timezone":"Asia/Karachi",
    "iso:country":"PK",
    "name:und_x_variant":[
        "Jah\u0101npur"
    ],
    "wof:name":"Chah Nawabwala",
    "wof:placetype":"locality"
},
  "geometry": {"coordinates":[72.02514000000002,30.48628],"type":"Point"}
}