{
  "type": "Feature",
  "properties": {
    "gn:admin1_code":"4.0",
    "gn:asciiname":"Chak One Hundred Twenty-one Jhang Branch",
    "gn:country_code":"PK",
    "gn:dem":186,
    "gn:feature_class":"P",
    "gn:feature_code":"PPL",
    "gn:name":"Chak One Hundred Twenty-one Jhang Branch",
    "gn:population":0,
    "gn:timezone":"Asia/Karachi",
    "iso:country":"PK",
    "name:und_x_variant":[
        "Gokh\u016bw\u0101la",
        "Gokhuw\u0101l",
        "Chak One Hundred Twenty-One GB",
        "Chak One Hundred Twenty-one Jhang Branch",
        "Gokhow\u0101la"
    ],
    "wof:name":"Chak One Hundred Twenty-one Jhang Branch",
    "wof:placetype":"neighbourhood"
},
  "geometry": {"coordinates":[73.09984,31.47807],"type":"Point"}
}