{
  "type": "Feature",
  "properties": {
    "gn:admin1_code":"4.0",
    "gn:asciiname":"Basti Chak Chaudhari",
    "gn:country_code":"PK",
    "gn:dem":137,
    "gn:feature_class":"P",
    "gn:feature_code":"PPL",
    "gn:name":"Basti Chak Chaudhari",
    "gn:population":0,
    "gn:timezone":"Asia/Karachi",
    "iso:country":"PK",
    "wof:name":"Basti Chak Chaudhari",
    "wof:placetype":"locality"
},
  "geometry": {"coordinates":[72.40680999999999,29.78654],"type":"Point"}
}