{
  "type": "Feature",
  "properties": {
    "gn:admin1_code":"4",
    "gn:asciiname":"Bhuttewala",
    "gn:country_code":"PK",
    "gn:dem":141,
    "gn:feature_class":"P",
    "gn:feature_code":"PPL",
    "gn:name":"Bhuttewala",
    "gn:population":0,
    "gn:timezone":"Asia/Karachi",
    "iso:country":"PK",
    "name:eng_x_preferred":[
        "Bhuttewala"
    ],
    "wof:name":"Bhuttewala",
    "wof:placetype":"locality"
},
  "geometry": {"coordinates":[70.68850999999999,30.4838],"type":"Point"}
}