{
  "type": "Feature",
  "properties": {
    "gn:admin1_code":"5.0",
    "gn:asciiname":"Goth Karim Dino Khaskheli",
    "gn:country_code":"PK",
    "gn:dem":3,
    "gn:feature_class":"P",
    "gn:feature_code":"PPL",
    "gn:name":"Goth Karim Dino Khaskheli",
    "gn:population":0,
    "gn:timezone":"Asia/Karachi",
    "iso:country":"PK",
    "wof:name":"Goth Karim Dino Khaskheli",
    "wof:placetype":"locality"
},
  "geometry": {"coordinates":[67.48563,24.46299],"type":"Point"}
}