{
  "type": "Feature",
  "properties": {
    "gn:admin1_code":"4.0",
    "gn:asciiname":"Haveli",
    "gn:country_code":"PK",
    "gn:dem":215,
    "gn:feature_class":"P",
    "gn:feature_code":"PPL",
    "gn:name":"Haveli",
    "gn:population":0,
    "gn:timezone":"Asia/Karachi",
    "iso:country":"PK",
    "name:deu_x_preferred":[
        "Haveli"
    ],
    "name:eng_x_preferred":[
        "Haveli"
    ],
    "name:fra_x_preferred":[
        "Havel\u00ee"
    ],
    "name:heb_x_preferred":[
        "\u05d4\u05d5\u05d5\u05d0\u05dc\u05d9"
    ],
    "name:hin_x_preferred":[
        "\u0939\u0935\u0947\u0932\u0940"
    ],
    "name:ita_x_preferred":[
        "Haveli"
    ],
    "name:pnb_x_preferred":[
        "\u062d\u0648\u06cc\u0644\u06cc"
    ],
    "name:pol_x_preferred":[
        "Haweli"
    ],
    "name:por_x_preferred":[
        "Haveli"
    ],
    "name:rus_x_preferred":[
        "\u0425\u0430\u0432\u0435\u043b\u0438"
    ],
    "name:spa_x_preferred":[
        "Havel\u00ed"
    ],
    "name:sqi_x_preferred":[
        "Haveli"
    ],
    "name:und_x_variant":[
        "Haveli\u0101n"
    ],
    "name:urd_x_preferred":[
        "\u062d\u0648\u06cc\u0644\u06cc"
    ],
    "wof:name":"Haveli",
    "wof:placetype":"locality"
},
  "geometry": {"coordinates":[74.54891000000001,31.37769],"type":"Point"}
}