{
  "type": "Feature",
  "properties": {
    "gn:admin1_code":"4.0",
    "gn:asciiname":"Haveli",
    "gn:country_code":"PK",
    "gn:dem":215,
    "gn:feature_class":"P",
    "gn:feature_code":"PPL",
    "gn:name":"Haveli",
    "gn:population":0,
    "gn:timezone":"Asia/Karachi",
    "iso:country":"PK",
    "name:und_x_variant":[
        "Haveli\u0101n"
    ],
    "wof:name":"Haveli",
    "wof:placetype":"locality"
},
  "geometry": {"coordinates":[74.54890999999998,31.37769],"type":"Point"}
}