{
  "type": "Feature",
  "properties": {
    "gn:admin1_code":"2",
    "gn:asciiname":"Band",
    "gn:country_code":"PK",
    "gn:dem":1285,
    "gn:feature_class":"P",
    "gn:feature_code":"PPL",
    "gn:name":"Band",
    "gn:population":0,
    "gn:timezone":"Asia/Karachi",
    "iso:country":"PK",
    "wof:name":"Band",
    "wof:placetype":"locality"
},
  "geometry": {"coordinates":[69.75648000000001,29.96598],"type":"Point"}
}