{
  "type": "Feature",
  "properties": {
    "gn:admin1_code":"5",
    "gn:asciiname":"Dolay Ji Wandh",
    "gn:country_code":"PK",
    "gn:dem":53,
    "gn:feature_class":"P",
    "gn:feature_code":"PPL",
    "gn:name":"Dolay Ji Wandh",
    "gn:population":0,
    "gn:timezone":"Asia/Karachi",
    "iso:country":"PK",
    "name:und_x_variant":[
        "Dulo Ji W\u0101nd",
        "Dulo jo W\u0101nd",
        "Dolay Ji Wandh"
    ],
    "wof:name":"Dolay Ji Wandh",
    "wof:placetype":"locality"
},
  "geometry": {"coordinates":[68.12394,27.70245],"type":"Point"}
}