{
  "type": "Feature",
  "properties": {
    "gn:admin1_code":"2.0",
    "gn:asciiname":"Kili Hazur Bakhsh",
    "gn:country_code":"PK",
    "gn:dem":852,
    "gn:feature_class":"P",
    "gn:feature_code":"PPL",
    "gn:name":"Kili Hazur Bakhsh",
    "gn:population":0,
    "gn:timezone":"Asia/Karachi",
    "iso:country":"PK",
    "wof:name":"Kili Hazur Bakhsh",
    "wof:placetype":"locality"
},
  "geometry": {"coordinates":[64.6905,29.33425],"type":"Point"}
}