{
  "type": "Feature",
  "properties": {
    "gn:admin1_code":"05",
    "gn:asciiname":"Goth Ahmad Khoso",
    "gn:country_code":"PK",
    "gn:dem":9,
    "gn:feature_class":"P",
    "gn:feature_code":"PPL",
    "gn:name":"Goth Ahmad Khoso",
    "gn:population":0,
    "gn:timezone":"Asia/Karachi",
    "iso:country":"PK",
    "name:und_x_variant":[
        "Goth Haidar Kh\u0101n Kosa"
    ],
    "wof:name":"Goth Ahmad Khoso",
    "wof:placetype":"locality"
},
  "geometry": {"coordinates":[67.99659,24.45537],"type":"Point"}
}