{
  "type": "Feature",
  "properties": {
    "gn:admin1_code":"2.0",
    "gn:asciiname":"Zehri Benj",
    "gn:country_code":"PK",
    "gn:dem":1538,
    "gn:feature_class":"P",
    "gn:feature_code":"PPL",
    "gn:name":"Zehri Benj",
    "gn:population":0,
    "gn:timezone":"Asia/Karachi",
    "iso:country":"PK",
    "wof:name":"Zehri Benj",
    "wof:placetype":"locality"
},
  "geometry": {"coordinates":[66.23973000000001,27.91685],"type":"Point"}
}