{
  "type": "Feature",
  "properties": {
    "gn:admin1_code":"5.0",
    "gn:asciiname":"Allabad Halepota",
    "gn:country_code":"PK",
    "gn:dem":56,
    "gn:feature_class":"P",
    "gn:feature_code":"PPL",
    "gn:name":"Allabad Halepota",
    "gn:population":0,
    "gn:timezone":"Asia/Karachi",
    "iso:country":"PK",
    "name:und_x_variant":[
        "Halepota"
    ],
    "wof:name":"Allabad Halepota",
    "wof:placetype":"locality"
},
  "geometry": {"coordinates":[68.62602,27.37173],"type":"Point"}
}