{
  "type": "Feature",
  "properties": {
    "gn:admin1_code":"3.0",
    "gn:asciiname":"Gurada",
    "gn:country_code":"PK",
    "gn:dem":686,
    "gn:feature_class":"P",
    "gn:feature_code":"PPL",
    "gn:name":"Gurada",
    "gn:population":0,
    "gn:timezone":"Asia/Karachi",
    "iso:country":"PK",
    "name:und_x_variant":[
        "Gar\u0101da"
    ],
    "wof:name":"Gurada",
    "wof:placetype":"locality"
},
  "geometry": {"coordinates":[72.66190999999998,34.41698],"type":"Point"}
}