{
  "type": "Feature",
  "properties": {
    "gn:admin1_code":"5",
    "gn:asciiname":"Goth Shah Nawaz Rajput",
    "gn:country_code":"PK",
    "gn:dem":24,
    "gn:feature_class":"P",
    "gn:feature_code":"PPL",
    "gn:name":"Goth Shah Nawaz Rajput",
    "gn:population":0,
    "gn:timezone":"Asia/Karachi",
    "iso:country":"PK",
    "name:und_x_variant":[
        "Sh\u0101h Naw\u0101z Muh\u0101jir"
    ],
    "wof:name":"Goth Shah Nawaz Rajput",
    "wof:placetype":"locality"
},
  "geometry": {"coordinates":[68.71311999999999,25.57273],"type":"Point"}
}