{
  "type": "Feature",
  "properties": {
    "gn:admin1_code":"4.0",
    "gn:asciiname":"Chura Maneke",
    "gn:country_code":"PK",
    "gn:dem":178,
    "gn:feature_class":"P",
    "gn:feature_code":"PPL",
    "gn:name":"Chura Maneke",
    "gn:population":0,
    "gn:timezone":"Asia/Karachi",
    "iso:country":"PK",
    "name:und_x_variant":[
        "Ch\u016bra Lakhwera M\u0101neka"
    ],
    "wof:name":"Chura Maneke",
    "wof:placetype":"locality"
},
  "geometry": {"coordinates":[73.78261999999999,30.42995],"type":"Point"}
}