{
  "type": "Feature",
  "properties": {
    "gn:admin1_code":"2.0",
    "gn:asciiname":"Kili Haji Mim Khan",
    "gn:country_code":"PK",
    "gn:dem":921,
    "gn:feature_class":"P",
    "gn:feature_code":"PPL",
    "gn:name":"Kili Haji Mim Khan",
    "gn:population":0,
    "gn:timezone":"Asia/Karachi",
    "iso:country":"PK",
    "wof:name":"Kili Haji Mim Khan",
    "wof:placetype":"locality"
},
  "geometry": {"coordinates":[64.71599000000001,28.51379],"type":"Point"}
}