{
  "type": "Feature",
  "properties": {
    "gn:admin1_code":"5.0",
    "gn:asciiname":"Jamaluddin Dasti",
    "gn:country_code":"PK",
    "gn:dem":67,
    "gn:feature_class":"P",
    "gn:feature_code":"PPL",
    "gn:name":"Jamaluddin Dasti",
    "gn:population":0,
    "gn:timezone":"Asia/Karachi",
    "iso:country":"PK",
    "name:eng_x_preferred":[
        "Jamaluddin Dasti"
    ],
    "wof:name":"Jamaluddin Dasti",
    "wof:placetype":"locality"
},
  "geometry": {"coordinates":[68.66226999999999,27.96354],"type":"Point"}
}