{
  "type": "Feature",
  "properties": {
    "gn:admin1_code":"4.0",
    "gn:asciiname":"Basti Mahajaran",
    "gn:country_code":"PK",
    "gn:dem":104,
    "gn:feature_class":"P",
    "gn:feature_code":"PPL",
    "gn:name":"Basti Mahajaran",
    "gn:population":0,
    "gn:timezone":"Asia/Karachi",
    "iso:country":"PK",
    "name:und_x_variant":[
        "Basti Malik Mah\u0101jar\u0101n"
    ],
    "wof:name":"Basti Mahajaran",
    "wof:placetype":"locality"
},
  "geometry": {"coordinates":[70.94461,29.43016],"type":"Point"}
}