{
  "type": "Feature",
  "properties": {
    "gn:admin1_code":"3",
    "gn:asciiname":"Koli Dherai",
    "gn:country_code":"PK",
    "gn:dem":361,
    "gn:feature_class":"P",
    "gn:feature_code":"PPL",
    "gn:name":"Koli Dherai",
    "gn:population":0,
    "gn:timezone":"Asia/Karachi",
    "iso:country":"PK",
    "name:eng_x_preferred":[
        "Kodi Dherai"
    ],
    "name:und_x_variant":[
        "Kodi Dheri",
        "Koli Dherai"
    ],
    "wof:name":"Koli Dherai",
    "wof:placetype":"locality"
},
  "geometry": {"coordinates":[72.37295999999998,34.26793],"type":"Point"}
}