{
  "type": "Feature",
  "properties": {
    "gn:admin1_code":"3.0",
    "gn:asciiname":"Jit Kot",
    "gn:country_code":"PK",
    "gn:dem":1411,
    "gn:feature_class":"P",
    "gn:feature_code":"PPL",
    "gn:name":"Jit Kot",
    "gn:population":0,
    "gn:timezone":"Asia/Karachi",
    "iso:country":"PK",
    "name:und_x_variant":[
        "Jitkot"
    ],
    "wof:name":"Jit Kot",
    "wof:placetype":"locality"
},
  "geometry": {"coordinates":[72.00551999999998,35.25383],"type":"Point"}
}