{
  "type": "Feature",
  "properties": {
    "gn:admin1_code":"3.0",
    "gn:asciiname":"Khan Zada Koruna",
    "gn:country_code":"PK",
    "gn:dem":314,
    "gn:feature_class":"P",
    "gn:feature_code":"PPL",
    "gn:name":"Khan Zada Koruna",
    "gn:population":0,
    "gn:timezone":"Asia/Karachi",
    "iso:country":"PK",
    "wof:name":"Khan Zada Koruna",
    "wof:placetype":"locality"
},
  "geometry": {"coordinates":[72.05288,34.22821],"type":"Point"}
}