{
  "type": "Feature",
  "properties": {
    "gn:admin1_code":"03",
    "gn:asciiname":"Patwar Payan",
    "gn:country_code":"PK",
    "gn:dem":329,
    "gn:feature_class":"P",
    "gn:feature_code":"PPL",
    "gn:name":"Patwar Payan",
    "gn:population":0,
    "gn:timezone":"Asia/Karachi",
    "iso:country":"PK",
    "name:und_x_variant":[
        "Patwar Pain",
        "Patwar Payan"
    ],
    "wof:name":"Patwar Payan",
    "wof:placetype":"locality"
},
  "geometry": {"coordinates":[71.49138000000001,34.07203],"type":"Point"}
}