{
  "type": "Feature",
  "properties": {
    "gn:admin1_code":"5.0",
    "gn:asciiname":"Khuda Bakhsh Wahojo",
    "gn:country_code":"PK",
    "gn:dem":50,
    "gn:feature_class":"P",
    "gn:feature_code":"PPL",
    "gn:name":"Khuda Bakhsh Wahojo",
    "gn:population":0,
    "gn:timezone":"Asia/Karachi",
    "iso:country":"PK",
    "wof:name":"Khuda Bakhsh Wahojo",
    "wof:placetype":"locality"
},
  "geometry": {"coordinates":[67.8685,27.42191],"type":"Point"}
}