{
  "type": "Feature",
  "properties": {
    "gn:admin1_code":"5.0",
    "gn:asciiname":"Bhilan jo Goth",
    "gn:country_code":"PK",
    "gn:dem":74,
    "gn:feature_class":"P",
    "gn:feature_code":"PPL",
    "gn:name":"Bhilan jo Goth",
    "gn:population":0,
    "gn:timezone":"Asia/Karachi",
    "iso:country":"PK",
    "name:und_x_variant":[
        "Bh\u012blon ki Got"
    ],
    "wof:name":"Bhilan jo Goth",
    "wof:placetype":"locality"
},
  "geometry": {"coordinates":[70.32101999999999,24.78215],"type":"Point"}
}