{
  "type": "Feature",
  "properties": {
    "gn:admin1_code":"4",
    "gn:asciiname":"Chhinawala",
    "gn:country_code":"PK",
    "gn:dem":165,
    "gn:feature_class":"P",
    "gn:feature_code":"PPL",
    "gn:name":"Chhinawala",
    "gn:population":0,
    "gn:timezone":"Asia/Karachi",
    "iso:country":"PK",
    "name:und_x_variant":[
        "Chh\u012bnaw\u0101la"
    ],
    "wof:name":"Chhinawala",
    "wof:placetype":"locality"
},
  "geometry": {"coordinates":[71.01671,31.4271],"type":"Point"}
}