{
  "type": "Feature",
  "properties": {
    "gn:admin1_code":"3.0",
    "gn:asciiname":"Khatab Kalle",
    "gn:country_code":"PK",
    "gn:dem":300,
    "gn:feature_class":"P",
    "gn:feature_code":"PPL",
    "gn:name":"Khatab Kalle",
    "gn:population":0,
    "gn:timezone":"Asia/Karachi",
    "iso:country":"PK",
    "name:eng_x_preferred":[
        "Khat\u0101b Kor\u016bna"
    ],
    "wof:name":"Khatab Kalle",
    "wof:placetype":"locality"
},
  "geometry": {"coordinates":[71.9944,34.11559],"type":"Point"}
}