{
  "type": "Feature",
  "properties": {
    "gn:admin1_code":"01",
    "gn:asciiname":"Mena Sar",
    "gn:country_code":"PK",
    "gn:dem":1716,
    "gn:feature_class":"P",
    "gn:feature_code":"PPL",
    "gn:name":"Mena Sar",
    "gn:population":0,
    "gn:timezone":"Asia/Karachi",
    "iso:country":"PK",
    "name:eng_x_preferred":[
        "Mena Sar"
    ],
    "name:und_x_variant":[
        "Mena"
    ],
    "wof:name":"Mena Sar",
    "wof:placetype":"locality"
},
  "geometry": {"coordinates":[71.57214,34.61584000000001],"type":"Point"}
}