{
  "type": "Feature",
  "properties": {
    "gn:admin1_code":"5.0",
    "gn:asciiname":"Goth Husain Samo",
    "gn:country_code":"PK",
    "gn:dem":14,
    "gn:feature_class":"P",
    "gn:feature_code":"PPL",
    "gn:name":"Goth Husain Samo",
    "gn:population":0,
    "gn:timezone":"Asia/Karachi",
    "iso:country":"PK",
    "name:und_x_variant":[
        "Goth Hussain Sama"
    ],
    "wof:name":"Goth Husain Samo",
    "wof:placetype":"locality"
},
  "geometry": {"coordinates":[68.34255999999999,24.89022000000001],"type":"Point"}
}