{
  "type": "Feature",
  "properties": {
    "gn:admin1_code":"3.0",
    "gn:asciiname":"Takia Sheikhan",
    "gn:country_code":"PK",
    "gn:dem":1214,
    "gn:feature_class":"P",
    "gn:feature_code":"PPL",
    "gn:name":"Takia Sheikhan",
    "gn:population":0,
    "gn:timezone":"Asia/Karachi",
    "iso:country":"PK",
    "wof:name":"Takia Sheikhan",
    "wof:placetype":"locality"
},
  "geometry": {"coordinates":[73.22150000000001,34.16875],"type":"Point"}
}