{
  "type": "Feature",
  "properties": {
    "gn:admin1_code":"4",
    "gn:asciiname":"Muhammad Yarwala",
    "gn:country_code":"PK",
    "gn:dem":129,
    "gn:feature_class":"P",
    "gn:feature_code":"PPL",
    "gn:name":"Muhammad Yarwala",
    "gn:population":0,
    "gn:timezone":"Asia/Karachi",
    "iso:country":"PK",
    "name:eng_x_preferred":[
        "Muhammad Yarwala"
    ],
    "wof:name":"Muhammad Yarwala",
    "wof:placetype":"locality"
},
  "geometry": {"coordinates":[70.94889000000001,30.17229],"type":"Point"}
}