{
  "type": "Feature",
  "properties": {
    "gn:admin1_code":"4",
    "gn:asciiname":"Rohi Kotavi Ram",
    "gn:country_code":"PK",
    "gn:dem":118,
    "gn:feature_class":"P",
    "gn:feature_code":"PPL",
    "gn:name":"Rohi Kotavi Ram",
    "gn:population":0,
    "gn:timezone":"Asia/Karachi",
    "iso:country":"PK",
    "name:und_x_variant":[
        "W\u0101hi Khota R\u0101m"
    ],
    "wof:name":"Rohi Kotavi Ram",
    "wof:placetype":"locality"
},
  "geometry": {"coordinates":[71.52863000000001,29.85039],"type":"Point"}
}