{
  "type": "Feature",
  "properties": {
    "gn:admin1_code":"5.0",
    "gn:asciiname":"Goth Mari Khu",
    "gn:country_code":"PK",
    "gn:dem":59,
    "gn:feature_class":"P",
    "gn:feature_code":"PPL",
    "gn:name":"Goth Mari Khu",
    "gn:population":0,
    "gn:timezone":"Asia/Karachi",
    "iso:country":"PK",
    "name:und_x_variant":[
        "Mari Khu"
    ],
    "wof:name":"Goth Mari Khu",
    "wof:placetype":"locality"
},
  "geometry": {"coordinates":[67.45094,27.05574],"type":"Point"}
}