{
  "type": "Feature",
  "properties": {
    "gn:admin1_code":"5.0",
    "gn:asciiname":"Ghulam Muhammad Khoso",
    "gn:country_code":"PK",
    "gn:dem":35,
    "gn:feature_class":"P",
    "gn:feature_code":"PPL",
    "gn:name":"Ghulam Muhammad Khoso",
    "gn:population":0,
    "gn:timezone":"Asia/Karachi",
    "iso:country":"PK",
    "wof:name":"Ghulam Muhammad Khoso",
    "wof:placetype":"locality"
},
  "geometry": {"coordinates":[68.30516,26.04773],"type":"Point"}
}