{
  "type": "Feature",
  "properties": {
    "gn:admin1_code":"4.0",
    "gn:asciiname":"Dhok Bhut Mar",
    "gn:country_code":"PK",
    "gn:dem":433,
    "gn:feature_class":"P",
    "gn:feature_code":"PPL",
    "gn:name":"Dhok Bhut Mar",
    "gn:population":0,
    "gn:timezone":"Asia/Karachi",
    "iso:country":"PK",
    "name:und_x_variant":[
        "Mari"
    ],
    "wof:name":"Dhok Bhut Mar",
    "wof:placetype":"locality"
},
  "geometry": {"coordinates":[72.28931,33.56542],"type":"Point"}
}