{
  "type": "Feature",
  "properties": {
    "gn:admin1_code":"7.0",
    "gn:asciiname":"Chongra",
    "gn:country_code":"PK",
    "gn:dem":2641,
    "gn:feature_class":"P",
    "gn:feature_code":"PPL",
    "gn:name":"Chongra",
    "gn:population":0,
    "gn:timezone":"Asia/Karachi",
    "iso:country":"PK",
    "wof:name":"Chongra",
    "wof:placetype":"locality"
},
  "geometry": {"coordinates":[74.84408000000001,35.36282],"type":"Point"}
}