{
  "type": "Feature",
  "properties": {
    "gn:admin1_code":"2.0",
    "gn:asciiname":"Haji Khuda Bukhsh",
    "gn:country_code":"PK",
    "gn:dem":760,
    "gn:feature_class":"P",
    "gn:feature_code":"PPL",
    "gn:name":"Haji Khuda Bukhsh",
    "gn:population":0,
    "gn:timezone":"Asia/Karachi",
    "iso:country":"PK",
    "wof:name":"Haji Khuda Bukhsh",
    "wof:placetype":"locality"
},
  "geometry": {"coordinates":[66.63594000000001,26.39145],"type":"Point"}
}