{
  "type": "Feature",
  "properties": {
    "gn:admin1_code":"01",
    "gn:asciiname":"Pirano Kalle",
    "gn:country_code":"PK",
    "gn:dem":1342,
    "gn:feature_class":"P",
    "gn:feature_code":"PPL",
    "gn:name":"Pirano Kalle",
    "gn:population":0,
    "gn:timezone":"Asia/Karachi",
    "iso:country":"PK",
    "name:und_x_variant":[
        "P\u012br\u0101no Kili"
    ],
    "wof:name":"Pirano Kalle",
    "wof:placetype":"locality"
},
  "geometry": {"coordinates":[69.66148000000001,32.89158],"type":"Point"}
}