{
  "type": "Feature",
  "properties": {
    "gn:admin1_code":"5",
    "gn:asciiname":"Sher Muhammad Khan Mugheri",
    "gn:country_code":"PK",
    "gn:dem":28,
    "gn:feature_class":"P",
    "gn:feature_code":"PPL",
    "gn:name":"Sher Muhammad Khan Mugheri",
    "gn:population":0,
    "gn:timezone":"Asia/Karachi",
    "iso:country":"PK",
    "wof:name":"Sher Muhammad Khan Mugheri",
    "wof:placetype":"locality"
},
  "geometry": {"coordinates":[68.57999000000001,26.1718],"type":"Point"}
}