{
  "type": "Feature",
  "properties": {
    "gn:admin1_code":"04",
    "gn:asciiname":"Chak Twenty-five Gugera Branch",
    "gn:country_code":"PK",
    "gn:dem":185,
    "gn:feature_class":"P",
    "gn:feature_code":"PPL",
    "gn:name":"Chak Twenty-five Gugera Branch",
    "gn:population":0,
    "gn:timezone":"Asia/Karachi",
    "iso:country":"PK",
    "name:und_x_variant":[
        "Maneli",
        "Man\u012bli"
    ],
    "wof:name":"Chak Twenty-five Gugera Branch",
    "wof:placetype":"locality"
},
  "geometry": {"coordinates":[73.30043000000001,31.25453],"type":"Point"}
}