{
  "type": "Feature",
  "properties": {
    "gn:admin1_code":"3",
    "gn:asciiname":"Selai Kandao",
    "gn:country_code":"PK",
    "gn:dem":2240,
    "gn:feature_class":"P",
    "gn:feature_code":"PPL",
    "gn:name":"Selai Kandao",
    "gn:population":0,
    "gn:timezone":"Asia/Karachi",
    "iso:country":"PK",
    "wof:name":"Selai Kandao",
    "wof:placetype":"locality"
},
  "geometry": {"coordinates":[72.19046,34.9804],"type":"Point"}
}