{
  "type": "Feature",
  "properties": {
    "gn:admin1_code":"5",
    "gn:asciiname":"Goth Kingri",
    "gn:country_code":"PK",
    "gn:dem":57,
    "gn:feature_class":"P",
    "gn:feature_code":"PPL",
    "gn:name":"Goth Kingri",
    "gn:population":0,
    "gn:timezone":"Asia/Karachi",
    "iso:country":"PK",
    "name:und_x_variant":[
        "Kingri"
    ],
    "wof:name":"Goth Kingri",
    "wof:placetype":"neighbourhood"
},
  "geometry": {"coordinates":[68.61286,27.58243],"type":"Point"}
}