{
  "type": "Feature",
  "properties": {
    "gn:admin1_code":"2.0",
    "gn:asciiname":"Grishkg Bazar",
    "gn:country_code":"PK",
    "gn:dem":777,
    "gn:feature_class":"P",
    "gn:feature_code":"PPL",
    "gn:name":"Grishkg Bazar",
    "gn:population":0,
    "gn:timezone":"Asia/Karachi",
    "iso:country":"PK",
    "wof:name":"Grishkg Bazar",
    "wof:placetype":"locality"
},
  "geometry": {"coordinates":[62.53933000000001,26.50405],"type":"Point"}
}