{
  "type": "Feature",
  "properties": {
    "gn:admin1_code":"4.0",
    "gn:asciiname":"Muhrianwala",
    "gn:country_code":"PK",
    "gn:dem":1021,
    "gn:feature_class":"P",
    "gn:feature_code":"PPL",
    "gn:name":"Muhrianwala",
    "gn:population":0,
    "gn:timezone":"Asia/Karachi",
    "iso:country":"PK",
    "name:und_x_variant":[
        "Mahauri\u0101nw\u0101la"
    ],
    "wof:name":"Muhrianwala",
    "wof:placetype":"locality"
},
  "geometry": {"coordinates":[71.9616,32.50455],"type":"Point"}
}