{
  "type": "Feature",
  "properties": {
    "gn:admin1_code":"5.0",
    "gn:asciiname":"Abad Khan Khoso",
    "gn:country_code":"PK",
    "gn:dem":29,
    "gn:feature_class":"P",
    "gn:feature_code":"PPL",
    "gn:name":"Abad Khan Khoso",
    "gn:population":0,
    "gn:timezone":"Asia/Karachi",
    "iso:country":"PK",
    "wof:name":"Abad Khan Khoso",
    "wof:placetype":"locality"
},
  "geometry": {"coordinates":[68.19126999999999,25.91857000000001],"type":"Point"}
}