{
  "type": "Feature",
  "properties": {
    "gn:admin1_code":"4",
    "gn:asciiname":"Mastewala",
    "gn:country_code":"PK",
    "gn:dem":186,
    "gn:feature_class":"P",
    "gn:feature_code":"PPL",
    "gn:name":"Mastewala",
    "gn:population":0,
    "gn:timezone":"Asia/Karachi",
    "iso:country":"PK",
    "name:und_x_variant":[
        "Hastew\u0101la Khu"
    ],
    "wof:name":"Mastewala",
    "wof:placetype":"locality"
},
  "geometry": {"coordinates":[72.98947,31.91323],"type":"Point"}
}