{
  "type": "Feature",
  "properties": {
    "gn:admin1_code":"5",
    "gn:asciiname":"Goth Saleh Khaskheli",
    "gn:country_code":"PK",
    "gn:dem":19,
    "gn:feature_class":"P",
    "gn:feature_code":"PPL",
    "gn:name":"Goth Saleh Khaskheli",
    "gn:population":0,
    "gn:timezone":"Asia/Karachi",
    "iso:country":"PK",
    "name:und_x_variant":[
        "S\u0101leh Kh\u0101skheli"
    ],
    "wof:name":"Goth Saleh Khaskheli",
    "wof:placetype":"locality"
},
  "geometry": {"coordinates":[68.99682,25.53047],"type":"Point"}
}