{
  "type": "Feature",
  "properties": {
    "gn:admin1_code":"4",
    "gn:asciiname":"Dhinde Kalan",
    "gn:country_code":"PK",
    "gn:dem":278,
    "gn:feature_class":"P",
    "gn:feature_code":"PPL",
    "gn:name":"Dhinde Kalan",
    "gn:population":0,
    "gn:timezone":"Asia/Karachi",
    "iso:country":"PK",
    "name:und_x_variant":[
        "Ubaria Dhinde"
    ],
    "wof:name":"Dhinde Kalan",
    "wof:placetype":"locality"
},
  "geometry": {"coordinates":[74.23857,32.76641],"type":"Point"}
}