{
  "type": "Feature",
  "properties": {
    "gn:admin1_code":"2.0",
    "gn:asciiname":"Sakhamun",
    "gn:country_code":"PK",
    "gn:dem":2198,
    "gn:feature_class":"P",
    "gn:feature_code":"PPL",
    "gn:name":"Sakhamun",
    "gn:population":0,
    "gn:timezone":"Asia/Karachi",
    "iso:country":"PK",
    "wof:name":"Sakhamun",
    "wof:placetype":"locality"
},
  "geometry": {"coordinates":[66.60808,28.80721],"type":"Point"}
}