{
  "type": "Feature",
  "properties": {
    "gn:admin1_code":"4",
    "gn:asciiname":"Muzafar",
    "gn:country_code":"PK",
    "gn:dem":505,
    "gn:feature_class":"P",
    "gn:feature_code":"PPL",
    "gn:name":"Muzafar",
    "gn:population":0,
    "gn:timezone":"Asia/Karachi",
    "iso:country":"PK",
    "wof:name":"Muzafar",
    "wof:placetype":"locality"
},
  "geometry": {"coordinates":[72.00417,32.67083],"type":"Point"}
}