{
  "type": "Feature",
  "properties": {
    "gn:admin1_code":"5.0",
    "gn:asciiname":"Doctor Sikandar Mandro",
    "gn:country_code":"PK",
    "gn:dem":9,
    "gn:feature_class":"P",
    "gn:feature_code":"PPL",
    "gn:name":"Doctor Sikandar Mandro",
    "gn:population":0,
    "gn:timezone":"Asia/Karachi",
    "iso:country":"PK",
    "wof:name":"Doctor Sikandar Mandro",
    "wof:placetype":"locality"
},
  "geometry": {"coordinates":[68.66589999999999,24.57613],"type":"Point"}
}