{
  "type": "Feature",
  "properties": {
    "gn:admin1_code":"5.0",
    "gn:asciiname":"Bachal Jhaluja",
    "gn:country_code":"PK",
    "gn:dem":29,
    "gn:feature_class":"P",
    "gn:feature_code":"PPL",
    "gn:name":"Bachal Jhaluja",
    "gn:population":0,
    "gn:timezone":"Asia/Karachi",
    "iso:country":"PK",
    "name:und_x_variant":[
        "Bachal Jhalu"
    ],
    "wof:name":"Bachal Jhaluja",
    "wof:placetype":"locality"
},
  "geometry": {"coordinates":[68.6315,26.06215],"type":"Point"}
}