{
  "type": "Feature",
  "properties": {
    "gn:admin1_code":"5.0",
    "gn:asciiname":"Goth Jumo Thaim",
    "gn:country_code":"PK",
    "gn:dem":7,
    "gn:feature_class":"P",
    "gn:feature_code":"PPL",
    "gn:name":"Goth Jumo Thaim",
    "gn:population":0,
    "gn:timezone":"Asia/Karachi",
    "iso:country":"PK",
    "name:und_x_variant":[
        "Goth Jumo Th\u0101im"
    ],
    "wof:name":"Goth Jumo Thaim",
    "wof:placetype":"locality"
},
  "geometry": {"coordinates":[68.32926999999999,24.45434],"type":"Point"}
}