{
  "type": "Feature",
  "properties": {
    "gn:admin1_code":"3.0",
    "gn:asciiname":"Khwaja Vas Kalle",
    "gn:country_code":"PK",
    "gn:dem":347,
    "gn:feature_class":"P",
    "gn:feature_code":"PPL",
    "gn:name":"Khwaja Vas Kalle",
    "gn:population":0,
    "gn:timezone":"Asia/Karachi",
    "iso:country":"PK",
    "name:eng_x_preferred":[
        "Khw\u0101ja B\u0101nda"
    ],
    "wof:name":"Khwaja Vas Kalle",
    "wof:placetype":"locality"
},
  "geometry": {"coordinates":[71.5509,34.23916],"type":"Point"}
}