{
  "type": "Feature",
  "properties": {
    "gn:admin1_code":"3",
    "gn:asciiname":"Dandu Sar",
    "gn:country_code":"PK",
    "gn:dem":2429,
    "gn:feature_class":"P",
    "gn:feature_code":"PPL",
    "gn:name":"Dandu Sar",
    "gn:population":0,
    "gn:timezone":"Asia/Karachi",
    "iso:country":"PK",
    "name:und_x_variant":[
        "Dandosar"
    ],
    "wof:name":"Dandu Sar",
    "wof:placetype":"locality"
},
  "geometry": {"coordinates":[72.84917,34.97765],"type":"Point"}
}