{
  "type": "Feature",
  "properties": {
    "gn:admin1_code":"3.0",
    "gn:asciiname":"Slamir Banda",
    "gn:country_code":"PK",
    "gn:dem":409,
    "gn:feature_class":"P",
    "gn:feature_code":"PPL",
    "gn:name":"Sl\u0101mir B\u0101nda",
    "gn:population":0,
    "gn:timezone":"Asia/Karachi",
    "iso:country":"PK",
    "wof:name":"Slamir Banda",
    "wof:placetype":"locality"
},
  "geometry": {"coordinates":[70.98333000000002,32.86722],"type":"Point"}
}