{
  "type": "Feature",
  "properties": {
    "gn:admin1_code":"3",
    "gn:asciiname":"Banda Kutina",
    "gn:country_code":"PK",
    "gn:dem":344,
    "gn:feature_class":"P",
    "gn:feature_code":"PPL",
    "gn:name":"Banda Kutina",
    "gn:population":0,
    "gn:timezone":"Asia/Karachi",
    "iso:country":"PK",
    "name:und_x_variant":[
        "Kut\u0101ni",
        "B\u0101nda Kut\u0101na",
        "Banda Kutina"
    ],
    "wof:name":"Banda Kutina",
    "wof:placetype":"locality"
},
  "geometry": {"coordinates":[71.05230999999998,32.51314],"type":"Point"}
}