{
  "type": "Feature",
  "properties": {
    "gn:admin1_code":"3.0",
    "gn:asciiname":"Char Chanro Khat",
    "gn:country_code":"PK",
    "gn:dem":322,
    "gn:feature_class":"P",
    "gn:feature_code":"PPL",
    "gn:name":"Char Chanro Khat",
    "gn:population":0,
    "gn:timezone":"Asia/Karachi",
    "iso:country":"PK",
    "wof:name":"Char Chanro Khat",
    "wof:placetype":"locality"
},
  "geometry": {"coordinates":[72.15089999999999,34.11251],"type":"Point"}
}