{
  "type": "Feature",
  "properties": {
    "gn:admin1_code":"4.0",
    "gn:asciiname":"Dhok Bhabar",
    "gn:country_code":"PK",
    "gn:dem":405,
    "gn:feature_class":"P",
    "gn:feature_code":"PPL",
    "gn:name":"Dhok Bhabar",
    "gn:population":0,
    "gn:timezone":"Asia/Karachi",
    "iso:country":"PK",
    "wof:name":"Dhok Bhabar",
    "wof:placetype":"locality"
},
  "geometry": {"coordinates":[72.55946,32.99781],"type":"Point"}
}