{
  "type": "Feature",
  "properties": {
    "gn:admin1_code":"4",
    "gn:asciiname":"Chah Khotewala",
    "gn:country_code":"PK",
    "gn:dem":142,
    "gn:feature_class":"P",
    "gn:feature_code":"PPL",
    "gn:name":"Chah Khotewala",
    "gn:population":0,
    "gn:timezone":"Asia/Karachi",
    "iso:country":"PK",
    "name:und_x_variant":[
        "Ch\u0101h Kothew\u0101la"
    ],
    "wof:name":"Chah Khotewala",
    "wof:placetype":"locality"
},
  "geometry": {"coordinates":[72.09754000000002,30.76267],"type":"Point"}
}