{
  "type": "Feature",
  "properties": {
    "gn:admin1_code":"4.0",
    "gn:asciiname":"Basti Lar",
    "gn:country_code":"PK",
    "gn:dem":89,
    "gn:feature_class":"P",
    "gn:feature_code":"PPL",
    "gn:name":"Basti Lar",
    "gn:population":0,
    "gn:timezone":"Asia/Karachi",
    "iso:country":"PK",
    "name:und_x_variant":[
        "Basti L\u0101r\u0101n"
    ],
    "wof:name":"Basti Lar",
    "wof:placetype":"locality"
},
  "geometry": {"coordinates":[70.68952,28.72837],"type":"Point"}
}