{
  "type": "Feature",
  "properties": {
    "gn:admin1_code":"4",
    "gn:asciiname":"Kauje-de-Basti",
    "gn:country_code":"PK",
    "gn:dem":133,
    "gn:feature_class":"P",
    "gn:feature_code":"PPL",
    "gn:name":"Kauje-de-Basti",
    "gn:population":0,
    "gn:timezone":"Asia/Karachi",
    "iso:country":"PK",
    "name:und_x_variant":[
        "Kauje"
    ],
    "wof:name":"Kauje-de-Basti",
    "wof:placetype":"locality"
},
  "geometry": {"coordinates":[72.23129,29.64183],"type":"Point"}
}