{
  "type": "Feature",
  "properties": {
    "gn:admin1_code":"5",
    "gn:asciiname":"Goth Jaryo Bhambhro",
    "gn:country_code":"PK",
    "gn:dem":20,
    "gn:feature_class":"P",
    "gn:feature_code":"PPL",
    "gn:name":"Goth Jaryo Bhambhro",
    "gn:population":0,
    "gn:timezone":"Asia/Karachi",
    "iso:country":"PK",
    "wof:name":"Goth Jaryo Bhambhro",
    "wof:placetype":"locality"
},
  "geometry": {"coordinates":[68.90278000000001,25.79167],"type":"Point"}
}