{
  "type": "Feature",
  "properties": {
    "gn:admin1_code":"2.0",
    "gn:asciiname":"Kili Arz Muhammad",
    "gn:country_code":"PK",
    "gn:dem":1645,
    "gn:feature_class":"P",
    "gn:feature_code":"PPL",
    "gn:name":"Kili Arz Muhammad",
    "gn:population":0,
    "gn:timezone":"Asia/Karachi",
    "iso:country":"PK",
    "wof:name":"Kili Arz Muhammad",
    "wof:placetype":"locality"
},
  "geometry": {"coordinates":[65.97789,27.89512],"type":"Point"}
}