{
  "type": "Feature",
  "properties": {
    "gn:admin1_code":"2.0",
    "gn:asciiname":"Muhammad Yaqub Lahri",
    "gn:country_code":"PK",
    "gn:dem":1545,
    "gn:feature_class":"P",
    "gn:feature_code":"PPL",
    "gn:name":"Muhammad Yaqub Lahri",
    "gn:population":0,
    "gn:timezone":"Asia/Karachi",
    "iso:country":"PK",
    "name:und_x_variant":[
        "Q\u0101dir Bakhsh"
    ],
    "wof:name":"Muhammad Yaqub Lahri",
    "wof:placetype":"locality"
},
  "geometry": {"coordinates":[66.49224,28.11786],"type":"Point"}
}