{
  "type": "Feature",
  "properties": {
    "gn:admin1_code":"4",
    "gn:asciiname":"Saranwala Dera",
    "gn:country_code":"PK",
    "gn:dem":209,
    "gn:feature_class":"P",
    "gn:feature_code":"PPL",
    "gn:name":"Saranwala Dera",
    "gn:population":0,
    "gn:timezone":"Asia/Karachi",
    "iso:country":"PK",
    "wof:name":"Saranwala Dera",
    "wof:placetype":"locality"
},
  "geometry": {"coordinates":[74.10556,31.75972],"type":"Point"}
}