{
  "type": "Feature",
  "properties": {
    "gn:admin1_code":"4",
    "gn:asciiname":"Chirhoiwala",
    "gn:country_code":"PK",
    "gn:dem":127,
    "gn:feature_class":"P",
    "gn:feature_code":"PPL",
    "gn:name":"Chirhoiwala",
    "gn:population":0,
    "gn:timezone":"Asia/Karachi",
    "iso:country":"PK",
    "name:eng_x_preferred":[
        "Chirho\u012bw\u0101la"
    ],
    "wof:name":"Chirhoiwala",
    "wof:placetype":"locality"
},
  "geometry": {"coordinates":[70.87954999999999,30.19076],"type":"Point"}
}