{
  "type": "Feature",
  "properties": {
    "gn:admin1_code":"2.0",
    "gn:asciiname":"Goth Saleh Muhammad",
    "gn:country_code":"PK",
    "gn:dem":248,
    "gn:feature_class":"P",
    "gn:feature_code":"PPL",
    "gn:name":"Goth Saleh Muhammad",
    "gn:population":0,
    "gn:timezone":"Asia/Karachi",
    "iso:country":"PK",
    "wof:name":"Goth Saleh Muhammad",
    "wof:placetype":"locality"
},
  "geometry": {"coordinates":[67.27758,26.05367],"type":"Point"}
}