{
  "type": "Feature",
  "properties": {
    "gn:admin1_code":"3",
    "gn:asciiname":"Tousa",
    "gn:country_code":"PK",
    "gn:dem":1260,
    "gn:feature_class":"P",
    "gn:feature_code":"PPL",
    "gn:name":"Tousa",
    "gn:population":0,
    "gn:timezone":"Asia/Karachi",
    "iso:country":"PK",
    "name:eng_x_preferred":[
        "Taus"
    ],
    "wof:name":"Tousa",
    "wof:placetype":"locality"
},
  "geometry": {"coordinates":[71.85916,35.13769],"type":"Point"}
}