{
  "type": "Feature",
  "properties": {
    "gn:admin1_code":"2",
    "gn:asciiname":"Sara Melah",
    "gn:country_code":"PK",
    "gn:dem":1258,
    "gn:feature_class":"P",
    "gn:feature_code":"PPL",
    "gn:name":"Sara Melah",
    "gn:population":0,
    "gn:timezone":"Asia/Karachi",
    "iso:country":"PK",
    "name:eng_x_preferred":[
        "Sara Melah"
    ],
    "wof:name":"Sara Melah",
    "wof:placetype":"locality"
},
  "geometry": {"coordinates":[69.81086999999999,31.86098],"type":"Point"}
}