{
  "type": "Feature",
  "properties": {
    "gn:admin1_code":"4.0",
    "gn:asciiname":"Noor-ka-Thatta",
    "gn:country_code":"PK",
    "gn:dem":167,
    "gn:feature_class":"P",
    "gn:feature_code":"PPL",
    "gn:name":"Noor-ka-Thatta",
    "gn:population":0,
    "gn:timezone":"Asia/Karachi",
    "iso:country":"PK",
    "wof:name":"Noor-ka-Thatta",
    "wof:placetype":"locality"
},
  "geometry": {"coordinates":[72.48448,31.61706],"type":"Point"}
}