{
  "type": "Feature",
  "properties": {
    "gn:admin1_code":"2.0",
    "gn:asciiname":"Muhammad Dano Bazar",
    "gn:country_code":"PK",
    "gn:dem":20,
    "gn:feature_class":"P",
    "gn:feature_code":"PPL",
    "gn:name":"Muhammad Dano Bazar",
    "gn:population":0,
    "gn:timezone":"Asia/Karachi",
    "iso:country":"PK",
    "wof:name":"Muhammad Dano Bazar",
    "wof:placetype":"locality"
},
  "geometry": {"coordinates":[61.93015,25.5101],"type":"Point"}
}