{
  "type": "Feature",
  "properties": {
    "gn:admin1_code":"2.0",
    "gn:asciiname":"Kili Rahim Khan",
    "gn:country_code":"PK",
    "gn:dem":1650,
    "gn:feature_class":"P",
    "gn:feature_code":"PPL",
    "gn:name":"Kili Rahim Khan",
    "gn:population":0,
    "gn:timezone":"Asia/Karachi",
    "iso:country":"PK",
    "wof:name":"Kili Rahim Khan",
    "wof:placetype":"locality"
},
  "geometry": {"coordinates":[67.42744,30.18627],"type":"Point"}
}