{
  "type": "Feature",
  "properties": {
    "gn:admin1_code":"3",
    "gn:asciiname":"Yar Ahmad Michan Khel",
    "gn:country_code":"PK",
    "gn:dem":314,
    "gn:feature_class":"P",
    "gn:feature_code":"PPL",
    "gn:name":"Yar Ahmad Michan Khel",
    "gn:population":0,
    "gn:timezone":"Asia/Karachi",
    "iso:country":"PK",
    "wof:name":"Yar Ahmad Michan Khel",
    "wof:placetype":"locality"
},
  "geometry": {"coordinates":[71.00705000000001,32.70962],"type":"Point"}
}