{
  "type": "Feature",
  "properties": {
    "gn:admin1_code":"4",
    "gn:asciiname":"Basti Chandrarh",
    "gn:country_code":"PK",
    "gn:dem":117,
    "gn:feature_class":"P",
    "gn:feature_code":"PPL",
    "gn:name":"Basti Chandrarh",
    "gn:population":0,
    "gn:timezone":"Asia/Karachi",
    "iso:country":"PK",
    "name:und_x_variant":[
        "Chandr\u0101nw\u0101li"
    ],
    "wof:name":"Basti Chandrarh",
    "wof:placetype":"locality"
},
  "geometry": {"coordinates":[70.89352,29.89963],"type":"Point"}
}