{
  "type": "Feature",
  "properties": {
    "gn:admin1_code":"3",
    "gn:asciiname":"Unkar",
    "gn:country_code":"PK",
    "gn:dem":1342,
    "gn:feature_class":"P",
    "gn:feature_code":"PPL",
    "gn:name":"Unkar",
    "gn:population":0,
    "gn:timezone":"Asia/Karachi",
    "iso:country":"PK",
    "name:eng_x_preferred":[
        "Hunk\u0101r"
    ],
    "wof:name":"Unkar",
    "wof:placetype":"locality"
},
  "geometry": {"coordinates":[71.92062,35.14368],"type":"Point"}
}