{
  "type": "Feature",
  "properties": {
    "gn:admin1_code":"3",
    "gn:asciiname":"Darband",
    "gn:country_code":"PK",
    "gn:dem":490,
    "gn:feature_class":"P",
    "gn:feature_code":"PPL",
    "gn:name":"Darband",
    "gn:population":0,
    "gn:timezone":"Asia/Karachi",
    "iso:country":"PK",
    "name:ceb_x_preferred":[
        "Darband"
    ],
    "name:deu_x_preferred":[
        "Darband"
    ],
    "name:fas_x_preferred":[
        "\u062f\u0631\u0628\u0646\u062f"
    ],
    "name:sco_x_preferred":[
        "Darband"
    ],
    "name:swe_x_preferred":[
        "Darband"
    ],
    "wof:name":"Darband",
    "wof:placetype":"locality"
},
  "geometry": {"coordinates":[72.89194000000001,34.00532],"type":"Point"}
}