{
  "type": "Feature",
  "properties": {
    "gn:admin1_code":"4.0",
    "gn:asciiname":"Nawan Kot",
    "gn:country_code":"PK",
    "gn:dem":222,
    "gn:feature_class":"P",
    "gn:feature_code":"PPL",
    "gn:name":"Nawan Kot",
    "gn:population":0,
    "gn:timezone":"Asia/Karachi",
    "iso:country":"PK",
    "wof:name":"Nawan Kot",
    "wof:placetype":"locality"
},
  "geometry": {"coordinates":[74.64961,31.93798],"type":"Point"}
}