{
  "type": "Feature",
  "properties": {
    "gn:admin1_code":"4.0",
    "gn:asciiname":"Lakhanpur",
    "gn:country_code":"PK",
    "gn:dem":249,
    "gn:feature_class":"P",
    "gn:feature_code":"PPL",
    "gn:name":"Lakhanpur",
    "gn:population":0,
    "gn:timezone":"Asia/Karachi",
    "iso:country":"PK",
    "wof:name":"Lakhanpur",
    "wof:placetype":"locality"
},
  "geometry": {"coordinates":[74.57070999999998,32.44424],"type":"Point"}
}