{
  "type": "Feature",
  "properties": {
    "gn:admin1_code":"4.0",
    "gn:asciiname":"Dhok Banjan",
    "gn:country_code":"PK",
    "gn:dem":477,
    "gn:feature_class":"P",
    "gn:feature_code":"PPL",
    "gn:name":"Dhok Banjan",
    "gn:population":0,
    "gn:timezone":"Asia/Karachi",
    "iso:country":"PK",
    "name:und_x_variant":[
        "Banj\u0101n"
    ],
    "wof:name":"Dhok Banjan",
    "wof:placetype":"locality"
},
  "geometry": {"coordinates":[72.75043000000002,33.7302],"type":"Point"}
}