{
  "type": "Feature",
  "properties": {
    "gn:admin1_code":"4.0",
    "gn:asciiname":"Chadawala",
    "gn:country_code":"PK",
    "gn:dem":286,
    "gn:feature_class":"P",
    "gn:feature_code":"PPL",
    "gn:name":"Chadawala",
    "gn:population":0,
    "gn:timezone":"Asia/Karachi",
    "iso:country":"PK",
    "name:und_x_variant":[
        "Charuwala",
        "Chanuw\u0101la",
        "Chadawala"
    ],
    "wof:name":"Chadawala",
    "wof:placetype":"locality"
},
  "geometry": {"coordinates":[73.13695,32.72655],"type":"Point"}
}