{
  "type": "Feature",
  "properties": {
    "gn:admin1_code":"4.0",
    "gn:asciiname":"Tami",
    "gn:country_code":"PK",
    "gn:dem":352,
    "gn:feature_class":"P",
    "gn:feature_code":"PPL",
    "gn:name":"Tami",
    "gn:population":0,
    "gn:timezone":"Asia/Karachi",
    "iso:country":"PK",
    "name:cat_x_preferred":[
        "Tami"
    ],
    "name:ces_x_preferred":[
        "Tami"
    ],
    "name:fra_x_preferred":[
        "Tami"
    ],
    "name:heb_x_preferred":[
        "\u05ea\u05de\"\u05d9"
    ],
    "name:pol_x_preferred":[
        "Tami"
    ],
    "wof:name":"Tami",
    "wof:placetype":"locality"
},
  "geometry": {"coordinates":[73.47769,33.10219],"type":"Point"}
}