{
  "type": "Feature",
  "properties": {
    "gn:admin1_code":"4.0",
    "gn:asciiname":"Azizabad",
    "gn:country_code":"PK",
    "gn:dem":232,
    "gn:feature_class":"P",
    "gn:feature_code":"PPL",
    "gn:name":"Azizabad",
    "gn:population":0,
    "gn:timezone":"Asia/Karachi",
    "iso:country":"PK",
    "name:ckb_x_preferred":[
        "\u0639\u06d5\u0632\u06cc\u0632\u0627\u0648\u0627"
    ],
    "name:eng_x_preferred":[
        "Azizabad"
    ],
    "name:fas_x_preferred":[
        "\u0639\u0632\u06cc\u0632\u0622\u0628\u0627\u062f"
    ],
    "name:urd_x_preferred":[
        "\u0639\u0632\u06cc\u0632 \u0622\u0628\u0627\u062f"
    ],
    "wof:name":"Azizabad",
    "wof:placetype":"locality"
},
  "geometry": {"coordinates":[74.3948,32.25905],"type":"Point"}
}