{
  "type": "Feature",
  "properties": {
    "gn:admin1_code":"4.0",
    "gn:asciiname":"Gorakhpur",
    "gn:country_code":"PK",
    "gn:dem":416,
    "gn:feature_class":"P",
    "gn:feature_code":"PPL",
    "gn:name":"Gorakhpur",
    "gn:population":0,
    "gn:timezone":"Asia/Karachi",
    "iso:country":"PK",
    "name:ben_x_preferred":[
        "\u0997\u09cb\u09b0\u0995\u09cd\u09b7\u09aa\u09c1\u09b0"
    ],
    "name:bih_x_preferred":[
        "\u0917\u094b\u0930\u0916\u092a\u0941\u0930"
    ],
    "name:cat_x_preferred":[
        "Gorakhpur"
    ],
    "name:ces_x_preferred":[
        "G\u00f3rakhpur"
    ],
    "name:deu_x_preferred":[
        "Gorakhpur"
    ],
    "name:epo_x_preferred":[
        "Gorakhpur"
    ],
    "name:fin_x_preferred":[
        "Gorakhpur"
    ],
    "name:fra_x_preferred":[
        "Gorakhpur"
    ],
    "name:heb_x_preferred":[
        "\u05d2\u05d5\u05e8\u05d0\u05e7\u05e4\u05d5\u05e8"
    ],
    "name:hin_x_preferred":[
        "\u0917\u094b\u0930\u0916\u092a\u0941\u0930"
    ],
    "name:hun_x_preferred":[
        "Gorakhpur"
    ],
    "name:ita_x_preferred":[
        "Gorakhpur"
    ],
    "name:jpn_x_preferred":[
        "\u30b4\u30fc\u30e9\u30af\u30d7\u30eb"
    ],
    "name:lit_x_preferred":[
        "Gorakhpuras"
    ],
    "name:mal_x_preferred":[
        "\u0d17\u0d4b\u0d30\u0d16\u0d4d\u0d2a\u0d42\u0d7c"
    ],
    "name:mar_x_preferred":[
        "\u0917\u094b\u0930\u0916\u092a\u0942\u0930"
    ],
    "name:nno_x_preferred":[
        "Gorakhpur"
    ],
    "name:nor_x_preferred":[
        "Gorakhpur"
    ],
    "name:pam_x_preferred":[
        "Gorakhpur"
    ],
    "name:pan_x_preferred":[
        "\u0a17\u0a4b\u0a30\u0a16\u0a2a\u0a41\u0a30"
    ],
    "name:pnb_x_preferred":[
        "\u06af\u0648\u0631\u06a9\u06be\u067e\u0648\u0631"
    ],
    "name:pol_x_preferred":[
        "Gorakhpur"
    ],
    "name:rus_x_preferred":[
        "\u0413\u043e\u0440\u0430\u043a\u0445\u043f\u0443\u0440"
    ],
    "name:san_x_preferred":[
        "\u0917\u094b\u0930\u0916\u092a\u0941\u0930\u092e\u094d"
    ],
    "name:srp_x_preferred":[
        "\u0413\u043e\u0440\u0430\u043a\u043f\u0443\u0440"
    ],
    "name:swe_x_preferred":[
        "Gorakhpur"
    ],
    "name:tam_x_preferred":[
        "\u0b95\u0bcb\u0bb0\u0b95\u0bcd\u0baa\u0bc2\u0bb0\u0bcd"
    ],
    "name:tha_x_preferred":[
        "\u0e42\u0e04\u0e23\u0e32\u0e06\u0e1b\u0e38\u0e23\u0e30"
    ],
    "name:ukr_x_preferred":[
        "\u0413\u043e\u0440\u0430\u043a\u0445\u043f\u0443\u0440"
    ],
    "name:urd_x_preferred":[
        "\u06af\u0648\u0631\u06a9\u06be\u067e\u0648\u0631"
    ],
    "name:uzb_x_preferred":[
        "Gorakhpur"
    ],
    "name:vie_x_preferred":[
        "Gorakhpur"
    ],
    "name:war_x_preferred":[
        "Gorakhpur"
    ],
    "name:zho_x_preferred":[
        "\u6208\u52d2\u514b\u5e03\u723e"
    ],
    "wof:name":"Gorakhpur",
    "wof:placetype":"locality"
},
  "geometry": {"coordinates":[73.03433000000003,33.47503],"type":"Point"}
}