{
  "type": "Feature",
  "properties": {
    "gn:admin1_code":"4.0",
    "gn:asciiname":"Gorakhpur",
    "gn:country_code":"PK",
    "gn:dem":416,
    "gn:feature_class":"P",
    "gn:feature_code":"PPL",
    "gn:name":"Gorakhpur",
    "gn:population":0,
    "gn:timezone":"Asia/Karachi",
    "iso:country":"PK",
    "wof:name":"Gorakhpur",
    "wof:placetype":"locality"
},
  "geometry": {"coordinates":[73.03433000000003,33.47503],"type":"Point"}
}