{
  "type": "Feature",
  "properties": {
    "gn:admin1_code":"6",
    "gn:asciiname":"Dhare",
    "gn:country_code":"PK",
    "gn:dem":1424,
    "gn:feature_class":"P",
    "gn:feature_code":"PPL",
    "gn:name":"Dhare",
    "gn:population":0,
    "gn:timezone":"Asia/Karachi",
    "iso:country":"PK",
    "name:und_x_variant":[
        "Dhari\u0101n"
    ],
    "wof:name":"Dhare",
    "wof:placetype":"locality"
},
  "geometry": {"coordinates":[73.83027,33.93422],"type":"Point"}
}