{
  "type": "Feature",
  "properties": {
    "gn:admin1_code":"6",
    "gn:asciiname":"Sangri",
    "gn:country_code":"PK",
    "gn:dem":1379,
    "gn:feature_class":"P",
    "gn:feature_code":"PPL",
    "gn:name":"Sangri",
    "gn:population":0,
    "gn:timezone":"Asia/Karachi",
    "iso:country":"PK",
    "name:nld_x_preferred":[
        "Sangri"
    ],
    "wof:name":"Sangri",
    "wof:placetype":"locality"
},
  "geometry": {"coordinates":[73.49424,34.48783],"type":"Point"}
}