{
  "type": "Feature",
  "properties": {
    "gn:admin1_code":"3.0",
    "gn:asciiname":"Momin Banda",
    "gn:country_code":"PK",
    "gn:dem":3257,
    "gn:feature_class":"P",
    "gn:feature_code":"PPL",
    "gn:name":"Momin Banda",
    "gn:population":0,
    "gn:timezone":"Asia/Karachi",
    "iso:country":"PK",
    "wof:name":"Momin Banda",
    "wof:placetype":"locality"
},
  "geometry": {"coordinates":[73.08728000000001,34.95649],"type":"Point"}
}