{
  "type": "Feature",
  "properties": {
    "gn:admin1_code":"2.0",
    "gn:asciiname":"Kili Abdul Hakim",
    "gn:country_code":"PK",
    "gn:dem":1224,
    "gn:feature_class":"P",
    "gn:feature_code":"PPL",
    "gn:name":"Kili Abdul Hakim",
    "gn:population":0,
    "gn:timezone":"Asia/Karachi",
    "iso:country":"PK",
    "wof:name":"Kili Abdul Hakim",
    "wof:placetype":"locality"
},
  "geometry": {"coordinates":[66.23729,27.16596],"type":"Point"}
}