{
  "type": "Feature",
  "properties": {
    "gn:admin1_code":"2",
    "gn:asciiname":"Kaina",
    "gn:country_code":"PK",
    "gn:dem":1855,
    "gn:feature_class":"P",
    "gn:feature_code":"PPL",
    "gn:name":"Kaina",
    "gn:population":0,
    "gn:timezone":"Asia/Karachi",
    "iso:country":"PK",
    "name:ceb_x_preferred":[
        "Kaina"
    ],
    "name:deu_x_preferred":[
        "Kaina"
    ],
    "name:eng_x_preferred":[
        "K\u0101nai"
    ],
    "name:swe_x_preferred":[
        "Kaina"
    ],
    "name:und_x_variant":[
        "Kain"
    ],
    "wof:name":"Kaina",
    "wof:placetype":"locality"
},
  "geometry": {"coordinates":[67.14465,30.81964],"type":"Point"}
}