{
  "type": "Feature",
  "properties": {
    "gn:admin1_code":"1.0",
    "gn:asciiname":"Daborai",
    "gn:country_code":"PK",
    "gn:dem":2014,
    "gn:feature_class":"P",
    "gn:feature_code":"PPL",
    "gn:name":"Daborai",
    "gn:population":0,
    "gn:timezone":"Asia/Karachi",
    "iso:country":"PK",
    "name:und_x_variant":[
        "Dab\u016brai"
    ],
    "wof:name":"Daborai",
    "wof:placetype":"locality"
},
  "geometry": {"coordinates":[70.87179999999999,33.78959],"type":"Point"}
}