{
  "type": "Feature",
  "properties": {
    "gn:admin1_code":"4.0",
    "gn:asciiname":"Dhok Bangla",
    "gn:country_code":"PK",
    "gn:dem":500,
    "gn:feature_class":"P",
    "gn:feature_code":"PPL",
    "gn:name":"Dhok Bangla",
    "gn:population":0,
    "gn:timezone":"Asia/Karachi",
    "iso:country":"PK",
    "wof:name":"Dhok Bangla",
    "wof:placetype":"locality"
},
  "geometry": {"coordinates":[73.36814,33.29072],"type":"Point"}
}