{
  "type": "Feature",
  "properties": {
    "gn:admin1_code":"4",
    "gn:asciiname":"Kotli Nawab",
    "gn:country_code":"PK",
    "gn:dem":225,
    "gn:feature_class":"P",
    "gn:feature_code":"PPL",
    "gn:name":"Kotli Nawab",
    "gn:population":0,
    "gn:timezone":"Asia/Karachi",
    "iso:country":"PK",
    "name:und_x_variant":[
        "Kotli Naw\u0101b Sadullah Kh\u0101n"
    ],
    "wof:name":"Kotli Nawab",
    "wof:placetype":"locality"
},
  "geometry": {"coordinates":[74.34161,32.05035],"type":"Point"}
}