{
  "type": "Feature",
  "properties": {
    "gn:admin1_code":"7.0",
    "gn:asciiname":"Manin",
    "gn:country_code":"PK",
    "gn:dem":2984,
    "gn:feature_class":"P",
    "gn:feature_code":"PPL",
    "gn:name":"Manin",
    "gn:population":0,
    "gn:timezone":"Asia/Karachi",
    "iso:country":"PK",
    "name:ceb_x_preferred":[
        "Manin"
    ],
    "name:deu_x_preferred":[
        "Manin"
    ],
    "name:fra_x_preferred":[
        "Manin"
    ],
    "name:glg_x_preferred":[
        "Man\u00edn"
    ],
    "name:ita_x_preferred":[
        "Manin"
    ],
    "name:jpn_x_preferred":[
        "\u30de\u30cb\u30f3"
    ],
    "name:nno_x_preferred":[
        "Manin"
    ],
    "name:rus_x_preferred":[
        "\u041c\u0430\u043d\u0438\u043d"
    ],
    "wof:name":"Manin",
    "wof:placetype":"locality"
},
  "geometry": {"coordinates":[74.01219,35.70838],"type":"Point"}
}