{
  "type": "Feature",
  "properties": {
    "gn:admin1_code":"3",
    "gn:asciiname":"Chaparha",
    "gn:country_code":"PK",
    "gn:dem":2121,
    "gn:feature_class":"P",
    "gn:feature_code":"PPL",
    "gn:name":"Chaparha",
    "gn:population":0,
    "gn:timezone":"Asia/Karachi",
    "iso:country":"PK",
    "name:und_x_variant":[
        "Chaphra"
    ],
    "wof:name":"Chaparha",
    "wof:placetype":"locality"
},
  "geometry": {"coordinates":[73.58253000000001,34.71664000000001],"type":"Point"}
}