{
  "type": "Feature",
  "properties": {
    "gn:admin1_code":"02",
    "gn:asciiname":"Sharan Alizai",
    "gn:country_code":"PK",
    "gn:dem":1258,
    "gn:feature_class":"P",
    "gn:feature_code":"PPL",
    "gn:name":"Sharan Alizai",
    "gn:population":0,
    "gn:timezone":"Asia/Karachi",
    "iso:country":"PK",
    "name:und_x_variant":[
        "Sharan Alezai",
        "Sharan Alizai"
    ],
    "wof:name":"Sharan Alizai",
    "wof:placetype":"locality"
},
  "geometry": {"coordinates":[68.89466,30.26318],"type":"Point"}
}