{
  "type": "Feature",
  "properties": {
    "gn:admin1_code":"01",
    "gn:asciiname":"Barro Kalle",
    "gn:country_code":"PK",
    "gn:dem":882,
    "gn:feature_class":"P",
    "gn:feature_code":"PPL",
    "gn:name":"Barro Kalle",
    "gn:population":0,
    "gn:timezone":"Asia/Karachi",
    "iso:country":"PK",
    "name:eng_x_preferred":[
        "Barro"
    ],
    "wof:name":"Barro Kalle",
    "wof:placetype":"locality"
},
  "geometry": {"coordinates":[71.75158,34.72271],"type":"Point"}
}