{
  "type": "Feature",
  "properties": {
    "gn:admin1_code":"5.0",
    "gn:asciiname":"Miani Shafi",
    "gn:country_code":"PK",
    "gn:dem":22,
    "gn:feature_class":"P",
    "gn:feature_code":"PPL",
    "gn:name":"Miani Shafi",
    "gn:population":0,
    "gn:timezone":"Asia/Karachi",
    "iso:country":"PK",
    "name:eng_x_preferred":[
        "Miani Shafi"
    ],
    "wof:name":"Miani Shafi",
    "wof:placetype":"neighbourhood"
},
  "geometry": {"coordinates":[68.315,25.3818],"type":"Point"}
}