{
  "type": "Feature",
  "properties": {
    "gn:admin1_code":"4",
    "gn:asciiname":"Majhiwali",
    "gn:country_code":"PK",
    "gn:dem":579,
    "gn:feature_class":"P",
    "gn:feature_code":"PPL",
    "gn:name":"Majhiwali",
    "gn:population":0,
    "gn:timezone":"Asia/Karachi",
    "iso:country":"PK",
    "wof:name":"Majhiwali",
    "wof:placetype":"locality"
},
  "geometry": {"coordinates":[72.12905000000001,32.65954],"type":"Point"}
}