{
  "type": "Feature",
  "properties": {
    "gn:admin1_code":"7.0",
    "gn:asciiname":"Turbaling",
    "gn:country_code":"PK",
    "gn:dem":2831,
    "gn:feature_class":"P",
    "gn:feature_code":"PPL",
    "gn:name":"Turbaling",
    "gn:population":0,
    "gn:timezone":"Asia/Karachi",
    "iso:country":"PK",
    "wof:name":"Turbaling",
    "wof:placetype":"locality"
},
  "geometry": {"coordinates":[74.71974,35.50502],"type":"Point"}
}