{
  "type": "Feature",
  "properties": {
    "gn:admin1_code":"7.0",
    "gn:asciiname":"Gologh Muli",
    "gn:country_code":"PK",
    "gn:dem":2996,
    "gn:feature_class":"P",
    "gn:feature_code":"PPL",
    "gn:name":"Gologh Muli",
    "gn:population":0,
    "gn:timezone":"Asia/Karachi",
    "iso:country":"PK",
    "wof:name":"Gologh Muli",
    "wof:placetype":"locality"
},
  "geometry": {"coordinates":[72.82375999999999,36.18079],"type":"Point"}
}