{
  "type": "Feature",
  "properties": {
    "gn:admin1_code":"2.0",
    "gn:asciiname":"Bala Dhaka",
    "gn:country_code":"PK",
    "gn:dem":1214,
    "gn:feature_class":"P",
    "gn:feature_code":"PPL",
    "gn:name":"Bala Dhaka",
    "gn:population":0,
    "gn:timezone":"Asia/Karachi",
    "iso:country":"PK",
    "wof:name":"Bala Dhaka",
    "wof:placetype":"locality"
},
  "geometry": {"coordinates":[69.40430000000001,30.04346],"type":"Point"}
}