{
  "type": "Feature",
  "properties": {
    "gn:admin1_code":"4",
    "gn:asciiname":"Chorakki",
    "gn:country_code":"PK",
    "gn:dem":194,
    "gn:feature_class":"P",
    "gn:feature_code":"PPL",
    "gn:name":"Chorakki",
    "gn:population":0,
    "gn:timezone":"Asia/Karachi",
    "iso:country":"PK",
    "wof:name":"Chorakki",
    "wof:placetype":"locality"
},
  "geometry": {"coordinates":[70.5848,31.01236],"type":"Point"}
}