{
  "type": "Feature",
  "properties": {
    "gn:admin1_code":"4.0",
    "gn:asciiname":"Dhok Gujar",
    "gn:country_code":"PK",
    "gn:dem":450,
    "gn:feature_class":"P",
    "gn:feature_code":"PPL",
    "gn:name":"Dhok Gujar",
    "gn:population":0,
    "gn:timezone":"Asia/Karachi",
    "iso:country":"PK",
    "wof:name":"Dhok Gujar",
    "wof:placetype":"locality"
},
  "geometry": {"coordinates":[72.61261,33.26994000000001],"type":"Point"}
}