{
  "type": "Feature",
  "properties": {
    "gn:admin1_code":"2.0",
    "gn:asciiname":"Laghonai",
    "gn:country_code":"PK",
    "gn:dem":1519,
    "gn:feature_class":"P",
    "gn:feature_code":"PPL",
    "gn:name":"Laghonai",
    "gn:population":0,
    "gn:timezone":"Asia/Karachi",
    "iso:country":"PK",
    "wof:name":"Laghonai",
    "wof:placetype":"locality"
},
  "geometry": {"coordinates":[69.93035,31.29437],"type":"Point"}
}