{
  "type": "Feature",
  "properties": {
    "gn:admin1_code":"5",
    "gn:asciiname":"Muhammad Shah",
    "gn:country_code":"PK",
    "gn:dem":19,
    "gn:feature_class":"P",
    "gn:feature_code":"PPL",
    "gn:name":"Muhammad Shah",
    "gn:population":0,
    "gn:timezone":"Asia/Karachi",
    "iso:country":"PK",
    "name:ara_x_preferred":[
        "\u0646\u0627\u0635\u0631 \u0627\u0644\u062f\u064a\u0646 \u0645\u062d\u0645\u062f \u0634\u0627\u0647"
    ],
    "name:azb_x_preferred":[
        "\u0645\u062d\u0645\u062f \u0634\u0627\u0647 \u0642\u0648\u0631\u06a9\u0627\u0646\u06cc"
    ],
    "name:ben_x_preferred":[
        "\u09ae\u09c1\u09b9\u09be\u09ae\u09cd\u09ae\u09a6 \u09b6\u09be\u09b9"
    ],
    "name:bih_x_preferred":[
        "\u092e\u0941\u0939\u092e\u094d\u092e\u0926 \u0936\u093e\u0939"
    ],
    "name:deu_x_preferred":[
        "Muhammad Shah"
    ],
    "name:epo_x_preferred":[
        "Muhammad \u015caho"
    ],
    "name:fas_x_preferred":[
        "\u0645\u062d\u0645\u062f\u0634\u0627\u0647 \u06af\u0648\u0631\u06a9\u0627\u0646\u06cc"
    ],
    "name:fra_x_preferred":[
        "Muhammad Sh\u00e2h"
    ],
    "name:hin_x_preferred":[
        "\u092e\u0941\u0939\u092e\u094d\u092e\u0926 \u0936\u093e\u0939"
    ],
    "name:ind_x_preferred":[
        "Muhammad Shah"
    ],
    "name:ita_x_preferred":[
        "Muhammad Shah"
    ],
    "name:jpn_x_preferred":[
        "\u30e0\u30cf\u30f3\u30de\u30c9\u30fb\u30b7\u30e3\u30fc"
    ],
    "name:mal_x_preferred":[
        "\u0d2e\u0d41\u0d39\u0d2e\u0d4d\u0d2e\u0d26\u0d4d \u0d37\u0d3e"
    ],
    "name:nld_x_preferred":[
        "Muhammad Shah"
    ],
    "name:pan_x_preferred":[
        "\u0a2e\u0a41\u0a39\u0a70\u0a2e\u0a26 \u0a38\u0a3c\u0a3e\u0a39 \u0a30\u0a70\u0a17\u0a40\u0a32\u0a3e"
    ],
    "name:pnb_x_preferred":[
        "\u0645\u062d\u0645\u062f \u0634\u0627\u06c1 \u0631\u0646\u06af\u06cc\u0644\u0627"
    ],
    "name:rus_x_preferred":[
        "\u041c\u0443\u0445\u0430\u043c\u043c\u0430\u0434 \u0428\u0430\u0445"
    ],
    "name:swe_x_preferred":[
        "Mohammed Nasir"
    ],
    "name:tam_x_preferred":[
        "\u0bae\u0bc1\u0b95\u0bae\u0bcd\u0bae\u0ba4\u0bc1 \u0bb7\u0bbe"
    ],
    "name:tel_x_preferred":[
        "\u0c2e\u0c4a\u0c39\u0c2e\u0c4d\u0c2e\u0c26\u0c4d \u0c37\u0c3e"
    ],
    "name:tur_x_preferred":[
        "Muhammed \u015eah"
    ],
    "name:ukr_x_preferred":[
        "\u041c\u0443\u0445\u0430\u043c\u043c\u0430\u0434 \u0428\u0430\u0445"
    ],
    "name:urd_x_preferred":[
        "\u0645\u062d\u0645\u062f \u0634\u0627\u06c1"
    ],
    "name:uzb_x_preferred":[
        "Muhammad-shoh"
    ],
    "name:war_x_preferred":[
        "Muhammad Shah"
    ],
    "name:zho_x_preferred":[
        "\u7a46\u7f55\u9ed8\u5fb7\u00b7\u6c99"
    ],
    "wof:name":"Muhammad Shah",
    "wof:placetype":"locality"
},
  "geometry": {"coordinates":[68.98468000000001,25.26607000000001],"type":"Point"}
}