{
  "type": "Feature",
  "properties": {
    "gn:admin1_code":"4",
    "gn:asciiname":"Doratta",
    "gn:country_code":"PK",
    "gn:dem":125,
    "gn:feature_class":"P",
    "gn:feature_code":"PPL",
    "gn:name":"Doratta",
    "gn:population":0,
    "gn:timezone":"Asia/Karachi",
    "iso:country":"PK",
    "name:eng_x_preferred":[
        "Doratta"
    ],
    "wof:name":"Doratta",
    "wof:placetype":"locality"
},
  "geometry": {"coordinates":[70.97853000000001,30.20855],"type":"Point"}
}