{
  "type": "Feature",
  "properties": {
    "gn:admin1_code":"2.0",
    "gn:asciiname":"Allah Bakhsh",
    "gn:country_code":"PK",
    "gn:dem":1431,
    "gn:feature_class":"P",
    "gn:feature_code":"PPL",
    "gn:name":"Allah Bakhsh",
    "gn:population":0,
    "gn:timezone":"Asia/Karachi",
    "iso:country":"PK",
    "wof:name":"Allah Bakhsh",
    "wof:placetype":"locality"
},
  "geometry": {"coordinates":[65.54524000000001,27.54365],"type":"Point"}
}