{
  "type": "Feature",
  "properties": {
    "gn:admin1_code":"3",
    "gn:asciiname":"Jozan",
    "gn:country_code":"PK",
    "gn:dem":1796,
    "gn:feature_class":"P",
    "gn:feature_code":"PPL",
    "gn:name":"Jozan",
    "gn:population":0,
    "gn:timezone":"Asia/Karachi",
    "iso:country":"PK",
    "name:eng_x_preferred":[
        "Jozan"
    ],
    "name:und_x_variant":[
        "Jauz\u0101n"
    ],
    "wof:name":"Jozan",
    "wof:placetype":"locality"
},
  "geometry": {"coordinates":[72.605,35.38779],"type":"Point"}
}