{
  "type": "Feature",
  "properties": {
    "gn:admin1_code":"2.0",
    "gn:asciiname":"Kili Siah Reg",
    "gn:country_code":"PK",
    "gn:dem":1001,
    "gn:feature_class":"P",
    "gn:feature_code":"PPL",
    "gn:name":"Kili Siah Reg",
    "gn:population":0,
    "gn:timezone":"Asia/Karachi",
    "iso:country":"PK",
    "wof:name":"Kili Siah Reg",
    "wof:placetype":"locality"
},
  "geometry": {"coordinates":[62.11391999999999,29.14811],"type":"Point"}
}