{
  "type": "Feature",
  "properties": {
    "gn:admin1_code":"4",
    "gn:asciiname":"Basti Gulana",
    "gn:country_code":"PK",
    "gn:dem":111,
    "gn:feature_class":"P",
    "gn:feature_code":"PPL",
    "gn:name":"Basti Gulana",
    "gn:population":0,
    "gn:timezone":"Asia/Karachi",
    "iso:country":"PK",
    "name:und_x_variant":[
        "Basti Gul\u0101",
        "Basti Gul\u0101ni",
        "Basti Gulana"
    ],
    "wof:name":"Basti Gulana",
    "wof:placetype":"locality"
},
  "geometry": {"coordinates":[71.4102,29.20414],"type":"Point"}
}