{
  "type": "Feature",
  "properties": {
    "gn:admin1_code":"3.0",
    "gn:asciiname":"Bhan Baluchan",
    "gn:country_code":"PK",
    "gn:dem":173,
    "gn:feature_class":"P",
    "gn:feature_code":"PPL",
    "gn:name":"Bhan Baluchan",
    "gn:population":0,
    "gn:timezone":"Asia/Karachi",
    "iso:country":"PK",
    "name:und_x_variant":[
        "Bh\u0101n Balochan"
    ],
    "wof:name":"Bhan Baluchan",
    "wof:placetype":"locality"
},
  "geometry": {"coordinates":[71.04819000000001,31.87934000000001],"type":"Point"}
}