{
  "type": "Feature",
  "properties": {
    "gn:admin1_code":"5",
    "gn:asciiname":"Abdul Rehman Brahui",
    "gn:country_code":"PK",
    "gn:dem":48,
    "gn:feature_class":"P",
    "gn:feature_code":"PPL",
    "gn:name":"Abdul Rehman Brahui",
    "gn:population":0,
    "gn:timezone":"Asia/Karachi",
    "iso:country":"PK",
    "name:und_x_variant":[
        "Ghaus Bakhsh Lohr"
    ],
    "wof:name":"Abdul Rehman Brahui",
    "wof:placetype":"locality"
},
  "geometry": {"coordinates":[68.07535,28.10847],"type":"Point"}
}