{
  "type": "Feature",
  "properties": {
    "gn:admin1_code":"5.0",
    "gn:asciiname":"Sakro",
    "gn:country_code":"PK",
    "gn:dem":10,
    "gn:feature_class":"P",
    "gn:feature_code":"PPL",
    "gn:name":"S\u0101kro",
    "gn:population":0,
    "gn:timezone":"Asia/Karachi",
    "iso:country":"PK",
    "wof:name":"Sakro",
    "wof:placetype":"locality"
},
  "geometry": {"coordinates":[67.63333,24.585],"type":"Point"}
}