{
  "type": "Feature",
  "properties": {
    "gn:admin1_code":"4.0",
    "gn:asciiname":"Longpura",
    "gn:country_code":"PK",
    "gn:dem":223,
    "gn:feature_class":"P",
    "gn:feature_code":"PPL",
    "gn:name":"Longpura",
    "gn:population":0,
    "gn:timezone":"Asia/Karachi",
    "iso:country":"PK",
    "name:und_x_variant":[
        "Gang\u016bpura"
    ],
    "wof:name":"Longpura",
    "wof:placetype":"locality"
},
  "geometry": {"coordinates":[74.59726999999999,31.98879],"type":"Point"}
}