{
  "type": "Feature",
  "properties": {
    "gn:admin1_code":"4.0",
    "gn:asciiname":"Basti Tawana",
    "gn:country_code":"PK",
    "gn:dem":167,
    "gn:feature_class":"P",
    "gn:feature_code":"PPL",
    "gn:name":"Basti Tawana",
    "gn:population":0,
    "gn:timezone":"Asia/Karachi",
    "iso:country":"PK",
    "wof:name":"Basti Tawana",
    "wof:placetype":"locality"
},
  "geometry": {"coordinates":[72.58911999999999,31.34457],"type":"Point"}
}