{
  "type": "Feature",
  "properties": {
    "gn:admin1_code":"5",
    "gn:asciiname":"Faqir Muhammad Rahu",
    "gn:country_code":"PK",
    "gn:dem":37,
    "gn:feature_class":"P",
    "gn:feature_code":"PPL",
    "gn:name":"Faqir Muhammad Rahu",
    "gn:population":0,
    "gn:timezone":"Asia/Karachi",
    "iso:country":"PK",
    "name:und_x_variant":[
        "Faq\u012bru Muhammad R\u0101hu",
        "Goth Faq\u012bru R\u0101ho",
        "Faqir Muhammad Rahu"
    ],
    "wof:name":"Faqir Muhammad Rahu",
    "wof:placetype":"locality"
},
  "geometry": {"coordinates":[68.10146999999999,26.35114],"type":"Point"}
}