{
  "type": "Feature",
  "properties": {
    "gn:admin1_code":"01",
    "gn:asciiname":"Inzari",
    "gn:country_code":"PK",
    "gn:dem":988,
    "gn:feature_class":"P",
    "gn:feature_code":"PPL",
    "gn:name":"Inzari",
    "gn:population":0,
    "gn:timezone":"Asia/Karachi",
    "iso:country":"PK",
    "wof:name":"Inzari",
    "wof:placetype":"locality"
},
  "geometry": {"coordinates":[71.3888,34.66879],"type":"Point"}
}