{
  "type": "Feature",
  "properties": {
    "gn:admin1_code":"5",
    "gn:asciiname":"Goth Phtal Khan",
    "gn:country_code":"PK",
    "gn:dem":34,
    "gn:feature_class":"P",
    "gn:feature_code":"PPL",
    "gn:name":"Goth Phtal Khan",
    "gn:population":0,
    "gn:timezone":"Asia/Karachi",
    "iso:country":"PK",
    "name:und_x_variant":[
        "Photal Kh\u0101n"
    ],
    "wof:name":"Goth Phtal Khan",
    "wof:placetype":"locality"
},
  "geometry": {"coordinates":[68.86706,26.38511],"type":"Point"}
}