{
  "type": "Feature",
  "properties": {
    "gn:admin1_code":"6.0",
    "gn:asciiname":"Salios",
    "gn:country_code":"PK",
    "gn:dem":656,
    "gn:feature_class":"P",
    "gn:feature_code":"PPL",
    "gn:name":"Salios",
    "gn:population":0,
    "gn:timezone":"Asia/Karachi",
    "iso:country":"PK",
    "wof:name":"Salios",
    "wof:placetype":"locality"
},
  "geometry": {"coordinates":[73.63304000000002,33.60596],"type":"Point"}
}