{
  "type": "Feature",
  "properties": {
    "gn:admin1_code":"1.0",
    "gn:asciiname":"Irab",
    "gn:country_code":"PK",
    "gn:dem":1080,
    "gn:feature_class":"P",
    "gn:feature_code":"PPL",
    "gn:name":"Irab",
    "gn:population":0,
    "gn:timezone":"Asia/Karachi",
    "iso:country":"PK",
    "wof:name":"Irab",
    "wof:placetype":"locality"
},
  "geometry": {"coordinates":[71.38524,34.81236],"type":"Point"}
}