{
  "type": "Feature",
  "properties": {
    "gn:admin1_code":"4",
    "gn:asciiname":"Chak One Hundred Thirty-one DNB",
    "gn:country_code":"PK",
    "gn:dem":102,
    "gn:feature_class":"P",
    "gn:feature_code":"PPL",
    "gn:name":"Chak One Hundred Thirty-one DNB",
    "gn:population":0,
    "gn:timezone":"Asia/Karachi",
    "iso:country":"PK",
    "name:und_x_variant":[
        "Chak One Hundred Thirty-one",
        "Mir\u0101na",
        "Chak One Hundred Thirty-one DNB"
    ],
    "wof:name":"Chak One Hundred Thirty-one DNB",
    "wof:placetype":"locality"
},
  "geometry": {"coordinates":[71.29914000000002,28.9542],"type":"Point"}
}