{
  "type": "Feature",
  "properties": {
    "gn:admin1_code":"1.0",
    "gn:asciiname":"Shah Nawaz Kalle",
    "gn:country_code":"PK",
    "gn:dem":1403,
    "gn:feature_class":"P",
    "gn:feature_code":"PPL",
    "gn:name":"Shah Nawaz Kalle",
    "gn:population":0,
    "gn:timezone":"Asia/Karachi",
    "iso:country":"PK",
    "wof:name":"Shah Nawaz Kalle",
    "wof:placetype":"locality"
},
  "geometry": {"coordinates":[69.56017,32.27876],"type":"Point"}
}