{
  "type": "Feature",
  "properties": {
    "gn:admin1_code":"4.0",
    "gn:asciiname":"Banda Araiyan",
    "gn:country_code":"PK",
    "gn:dem":213,
    "gn:feature_class":"P",
    "gn:feature_code":"PPL",
    "gn:name":"B\u0101nda Ar\u0101\u012by\u0101n",
    "gn:population":0,
    "gn:timezone":"Asia/Karachi",
    "iso:country":"PK",
    "wof:name":"Banda Araiyan",
    "wof:placetype":"neighbourhood"
},
  "geometry": {"coordinates":[71.56667,32.58333],"type":"Point"}
}