{
  "type": "Feature",
  "properties": {
    "gn:admin1_code":"2.0",
    "gn:asciiname":"Kili Haji Abdul Karim",
    "gn:country_code":"PK",
    "gn:dem":1596,
    "gn:feature_class":"P",
    "gn:feature_code":"PPL",
    "gn:name":"Kili Haji Abdul Karim",
    "gn:population":0,
    "gn:timezone":"Asia/Karachi",
    "iso:country":"PK",
    "wof:name":"Kili Haji Abdul Karim",
    "wof:placetype":"locality"
},
  "geometry": {"coordinates":[67.06359999999999,30.45667000000001],"type":"Point"}
}