{
  "type": "Feature",
  "properties": {
    "gn:admin1_code":"04",
    "gn:asciiname":"Mahiwala",
    "gn:country_code":"PK",
    "gn:dem":206,
    "gn:feature_class":"P",
    "gn:feature_code":"PPL",
    "gn:name":"Mahiwala",
    "gn:population":0,
    "gn:timezone":"Asia/Karachi",
    "iso:country":"PK",
    "wof:name":"Mahiwala",
    "wof:placetype":"locality"
},
  "geometry": {"coordinates":[73.68302,32.00409000000001],"type":"Point"}
}