{
  "type": "Feature",
  "properties": {
    "gn:admin1_code":"2.0",
    "gn:asciiname":"Killi Malik Qadir Bakhsh",
    "gn:country_code":"PK",
    "gn:dem":836,
    "gn:feature_class":"P",
    "gn:feature_code":"PPL",
    "gn:name":"Killi Malik Q\u0101dir Bakhsh",
    "gn:population":0,
    "gn:timezone":"Asia/Karachi",
    "iso:country":"PK",
    "wof:name":"Killi Malik Qadir Bakhsh",
    "wof:placetype":"locality"
},
  "geometry": {"coordinates":[65.26739999999999,28.995],"type":"Point"}
}