{
  "type": "Feature",
  "properties": {
    "gn:admin1_code":"04",
    "gn:asciiname":"Pind Gul Andazan",
    "gn:country_code":"PK",
    "gn:dem":350,
    "gn:feature_class":"P",
    "gn:feature_code":"PPL",
    "gn:name":"Pind Gul Andazan",
    "gn:population":0,
    "gn:timezone":"Asia/Karachi",
    "iso:country":"PK",
    "name:und_x_variant":[
        "Pind Gola Andazan",
        "Pind Goland\u0101z\u0101n Kh\u0101s",
        "Pind Gul Andazan"
    ],
    "wof:name":"Pind Gul Andazan",
    "wof:placetype":"locality"
},
  "geometry": {"coordinates":[73.36521999999999,32.89931],"type":"Point"}
}