{
  "type": "Feature",
  "properties": {
    "gn:admin1_code":"4",
    "gn:asciiname":"Kali Pari",
    "gn:country_code":"PK",
    "gn:dem":470,
    "gn:feature_class":"P",
    "gn:feature_code":"PPL",
    "gn:name":"Kali Pari",
    "gn:population":0,
    "gn:timezone":"Asia/Karachi",
    "iso:country":"PK",
    "name:und_x_variant":[
        "Dhok K\u0101li Pari"
    ],
    "wof:name":"Kali Pari",
    "wof:placetype":"locality"
},
  "geometry": {"coordinates":[73.35771,33.06681],"type":"Point"}
}