{
  "type": "Feature",
  "properties": {
    "gn:admin1_code":"4.0",
    "gn:asciiname":"Ghurbal",
    "gn:country_code":"PK",
    "gn:dem":554,
    "gn:feature_class":"P",
    "gn:feature_code":"PPL",
    "gn:name":"Ghurbal",
    "gn:population":0,
    "gn:timezone":"Asia/Karachi",
    "iso:country":"PK",
    "wof:name":"Ghurbal",
    "wof:placetype":"locality"
},
  "geometry": {"coordinates":[72.84503000000002,33.58509],"type":"Point"}
}