{
  "type": "Feature",
  "properties": {
    "gn:admin1_code":"3.0",
    "gn:asciiname":"Tur Banr",
    "gn:country_code":"PK",
    "gn:dem":2709,
    "gn:feature_class":"P",
    "gn:feature_code":"PPL",
    "gn:name":"Tur Banr",
    "gn:population":0,
    "gn:timezone":"Asia/Karachi",
    "iso:country":"PK",
    "wof:name":"Tur Banr",
    "wof:placetype":"locality"
},
  "geometry": {"coordinates":[73.22979000000002,34.82579],"type":"Point"}
}