{
  "type": "Feature",
  "properties": {
    "gn:admin1_code":"2",
    "gn:asciiname":"Kili Muhammad Salam",
    "gn:country_code":"PK",
    "gn:dem":1980,
    "gn:feature_class":"P",
    "gn:feature_code":"PPL",
    "gn:name":"Kili Muhammad Salam",
    "gn:population":0,
    "gn:timezone":"Asia/Karachi",
    "iso:country":"PK",
    "name:und_x_variant":[
        "Sh\u0101hna"
    ],
    "wof:name":"Kili Muhammad Salam",
    "wof:placetype":"locality"
},
  "geometry": {"coordinates":[66.94186999999999,31.12353],"type":"Point"}
}