{
  "type": "Feature",
  "properties": {
    "gn:admin1_code":"5.0",
    "gn:asciiname":"Shah Banglow Jo Goth",
    "gn:country_code":"PK",
    "gn:dem":55,
    "gn:feature_class":"P",
    "gn:feature_code":"PPL",
    "gn:name":"Shah Banglow Jo Goth",
    "gn:population":0,
    "gn:timezone":"Asia/Karachi",
    "iso:country":"PK",
    "name:und_x_variant":[
        "Sh\u0101h Mehngi"
    ],
    "wof:name":"Shah Banglow Jo Goth",
    "wof:placetype":"locality"
},
  "geometry": {"coordinates":[68.6923,27.4777],"type":"Point"}
}