{
  "type": "Feature",
  "properties": {
    "gn:admin1_code":"5",
    "gn:asciiname":"Raza Muhammad Jakrani",
    "gn:country_code":"PK",
    "gn:dem":67,
    "gn:feature_class":"P",
    "gn:feature_code":"PPL",
    "gn:name":"Raza Muhammad Jakrani",
    "gn:population":0,
    "gn:timezone":"Asia/Karachi",
    "iso:country":"PK",
    "name:und_x_variant":[
        "Raza Muhammad Khosa"
    ],
    "wof:name":"Raza Muhammad Jakrani",
    "wof:placetype":"locality"
},
  "geometry": {"coordinates":[69.06747,28.31867],"type":"Point"}
}