{
  "type": "Feature",
  "properties": {
    "gn:admin1_code":"04",
    "gn:asciiname":"Kureshi",
    "gn:cc2":"PK",
    "gn:country_code":"PK",
    "gn:dem":164,
    "gn:feature_class":"P",
    "gn:feature_code":"PPL",
    "gn:name":"Kureshi",
    "gn:population":0,
    "gn:timezone":"Asia/Karachi",
    "iso:country":"PK",
    "name:und_x_variant":[
        "Qureishi",
        "Kureshi"
    ],
    "wof:name":"Kureshi",
    "wof:placetype":"locality"
},
  "geometry": {"coordinates":[72.21666999999999,31.71667],"type":"Point"}
}