{
  "type": "Feature",
  "properties": {
    "gn:admin1_code":"2",
    "gn:asciiname":"Tand Wani",
    "gn:country_code":"PK",
    "gn:dem":2186,
    "gn:feature_class":"P",
    "gn:feature_code":"PPL",
    "gn:name":"Tand Wani",
    "gn:population":0,
    "gn:timezone":"Asia/Karachi",
    "iso:country":"PK",
    "wof:name":"Tand Wani",
    "wof:placetype":"locality"
},
  "geometry": {"coordinates":[68.00896,30.32884],"type":"Point"}
}