{
  "type": "Feature",
  "properties": {
    "gn:admin1_code":"2.0",
    "gn:asciiname":"Khatkandi",
    "gn:country_code":"PK",
    "gn:dem":2247,
    "gn:feature_class":"P",
    "gn:feature_code":"PPL",
    "gn:name":"Khatkandi",
    "gn:population":0,
    "gn:timezone":"Asia/Karachi",
    "iso:country":"PK",
    "name:eng_x_preferred":[
        "Kats"
    ],
    "wof:name":"Khatkandi",
    "wof:placetype":"locality"
},
  "geometry": {"coordinates":[67.42909,30.80698],"type":"Point"}
}