{
  "type": "Feature",
  "properties": {
    "gn:admin1_code":"2.0",
    "gn:asciiname":"Chunna Sheikh Raza Gul",
    "gn:country_code":"PK",
    "gn:dem":1890,
    "gn:feature_class":"P",
    "gn:feature_code":"PPL",
    "gn:name":"Chunna Sheikh Raza Gul",
    "gn:population":0,
    "gn:timezone":"Asia/Karachi",
    "iso:country":"PK",
    "name:und_x_variant":[
        "Shekh Raza Gul",
        "Chunna Sheikh Raza Gul"
    ],
    "wof:name":"Chunna Sheikh Raza Gul",
    "wof:placetype":"locality"
},
  "geometry": {"coordinates":[69.65188000000001,31.18091],"type":"Point"}
}