{
  "type": "Feature",
  "properties": {
    "gn:admin1_code":"4.0",
    "gn:asciiname":"Habibpur",
    "gn:country_code":"PK",
    "gn:dem":256,
    "gn:feature_class":"P",
    "gn:feature_code":"PPL",
    "gn:name":"Habibpur",
    "gn:population":0,
    "gn:timezone":"Asia/Karachi",
    "iso:country":"PK",
    "name:und_x_variant":[
        "Hub\u012bpur"
    ],
    "wof:name":"Habibpur",
    "wof:placetype":"locality"
},
  "geometry": {"coordinates":[74.82181,32.27247],"type":"Point"}
}