{
  "type": "Feature",
  "properties": {
    "gn:admin1_code":"5",
    "gn:asciiname":"Muhammad Khan Sammun",
    "gn:country_code":"PK",
    "gn:dem":26,
    "gn:feature_class":"P",
    "gn:feature_code":"PPL",
    "gn:name":"Muhammad Khan Sammun",
    "gn:population":0,
    "gn:timezone":"Asia/Karachi",
    "iso:country":"PK",
    "name:eng_x_preferred":[
        "Muhammad Khan Sammun"
    ],
    "wof:name":"Muhammad Khan Sammun",
    "wof:placetype":"locality"
},
  "geometry": {"coordinates":[68.35771,25.53479],"type":"Point"}
}