{
  "type": "Feature",
  "properties": {
    "gn:admin1_code":"3",
    "gn:asciiname":"Gosh Banda",
    "gn:country_code":"PK",
    "gn:dem":1153,
    "gn:feature_class":"P",
    "gn:feature_code":"PPL",
    "gn:name":"Gosh Banda",
    "gn:population":0,
    "gn:timezone":"Asia/Karachi",
    "iso:country":"PK",
    "wof:name":"Gosh Banda",
    "wof:placetype":"locality"
},
  "geometry": {"coordinates":[72.79646,34.77017],"type":"Point"}
}