{
  "type": "Feature",
  "properties": {
    "gn:admin1_code":"2.0",
    "gn:asciiname":"Kili Abdul Majid",
    "gn:country_code":"PK",
    "gn:dem":1301,
    "gn:feature_class":"P",
    "gn:feature_code":"PPL",
    "gn:name":"Kili Abdul Majid",
    "gn:population":0,
    "gn:timezone":"Asia/Karachi",
    "iso:country":"PK",
    "wof:name":"Kili Abdul Majid",
    "wof:placetype":"locality"
},
  "geometry": {"coordinates":[66.48940999999999,27.31473],"type":"Point"}
}