{
  "type": "Feature",
  "properties": {
    "gn:admin1_code":"4.0",
    "gn:asciiname":"Janga",
    "gn:country_code":"PK",
    "gn:dem":543,
    "gn:feature_class":"P",
    "gn:feature_code":"PPL",
    "gn:name":"Janga",
    "gn:population":0,
    "gn:timezone":"Asia/Karachi",
    "iso:country":"PK",
    "wof:name":"Janga",
    "wof:placetype":"locality"
},
  "geometry": {"coordinates":[72.85115999999999,32.86619],"type":"Point"}
}