{
  "type": "Feature",
  "properties": {
    "gn:admin1_code":"4",
    "gn:asciiname":"Thathi Anok Singh",
    "gn:country_code":"PK",
    "gn:dem":211,
    "gn:feature_class":"P",
    "gn:feature_code":"PPL",
    "gn:name":"Thathi Anok Singh",
    "gn:population":0,
    "gn:timezone":"Asia/Karachi",
    "iso:country":"PK",
    "name:und_x_variant":[
        "Thatti"
    ],
    "wof:name":"Thathi Anok Singh",
    "wof:placetype":"locality"
},
  "geometry": {"coordinates":[73.61001,32.23365],"type":"Point"}
}