{
  "type": "Feature",
  "properties": {
    "gn:admin1_code":"4.0",
    "gn:asciiname":"Bhutta Wahan",
    "gn:country_code":"PK",
    "gn:dem":86,
    "gn:feature_class":"P",
    "gn:feature_code":"PPL",
    "gn:name":"Bhutta Wahan",
    "gn:population":0,
    "gn:timezone":"Asia/Karachi",
    "iso:country":"PK",
    "name:und_x_variant":[
        "Bhuta Wahan",
        "Bhutta Wahan"
    ],
    "wof:name":"Bhutta Wahan",
    "wof:placetype":"locality"
},
  "geometry": {"coordinates":[70.10776,28.4646],"type":"Point"}
}