{
  "type": "Feature",
  "properties": {
    "gn:admin1_code":"4.0",
    "gn:asciiname":"Mozo Khoni Kolro",
    "gn:country_code":"PK",
    "gn:dem":142,
    "gn:feature_class":"P",
    "gn:feature_code":"PPL",
    "gn:name":"Mozo Khoni Kolro",
    "gn:population":0,
    "gn:timezone":"Asia/Karachi",
    "iso:country":"PK",
    "wof:name":"Mozo Khoni Kolro",
    "wof:placetype":"locality"
},
  "geometry": {"coordinates":[70.93236999999998,30.72806],"type":"Point"}
}