{
  "type": "Feature",
  "properties": {
    "gn:admin1_code":"4",
    "gn:asciiname":"Mohsan Shahwala",
    "gn:country_code":"PK",
    "gn:dem":118,
    "gn:feature_class":"P",
    "gn:feature_code":"PPL",
    "gn:name":"Mohsan Shahwala",
    "gn:population":0,
    "gn:timezone":"Asia/Karachi",
    "iso:country":"PK",
    "name:und_x_variant":[
        "M\u016bsan Sh\u0101hw\u0101la"
    ],
    "wof:name":"Mohsan Shahwala",
    "wof:placetype":"locality"
},
  "geometry": {"coordinates":[70.72232,30.02164],"type":"Point"}
}