{
  "type": "Feature",
  "properties": {
    "gn:admin1_code":"3",
    "gn:asciiname":"Sharmai",
    "gn:country_code":"PK",
    "gn:dem":1528,
    "gn:feature_class":"P",
    "gn:feature_code":"PPL",
    "gn:name":"Sharmai",
    "gn:population":0,
    "gn:timezone":"Asia/Karachi",
    "iso:country":"PK",
    "name:eng_x_preferred":[
        "Sh\u0101rm\u0101n"
    ],
    "wof:name":"Sharmai",
    "wof:placetype":"locality"
},
  "geometry": {"coordinates":[71.95031,35.19475],"type":"Point"}
}