{
  "type": "Feature",
  "properties": {
    "gn:admin1_code":"3",
    "gn:asciiname":"Baihk Gatti",
    "gn:country_code":"PK",
    "gn:dem":3329,
    "gn:feature_class":"P",
    "gn:feature_code":"PPL",
    "gn:name":"Baihk Gatti",
    "gn:population":0,
    "gn:timezone":"Asia/Karachi",
    "iso:country":"PK",
    "name:und_x_variant":[
        "Gatti"
    ],
    "wof:name":"Baihk Gatti",
    "wof:placetype":"locality"
},
  "geometry": {"coordinates":[73.58471999999998,34.94678],"type":"Point"}
}