{
  "type": "Feature",
  "properties": {
    "gn:admin1_code":"4.0",
    "gn:asciiname":"Hussainpur",
    "gn:country_code":"PK",
    "gn:dem":215,
    "gn:feature_class":"P",
    "gn:feature_code":"PPL",
    "gn:name":"Hussainpur",
    "gn:population":0,
    "gn:timezone":"Asia/Karachi",
    "iso:country":"PK",
    "name:und_x_variant":[
        "Ch\u0101ry\u0101ri"
    ],
    "wof:name":"Hussainpur",
    "wof:placetype":"locality"
},
  "geometry": {"coordinates":[73.79725999999999,32.30976],"type":"Point"}
}