{
  "type": "Feature",
  "properties": {
    "gn:admin1_code":"4",
    "gn:asciiname":"Chak Fifty-one",
    "gn:country_code":"PK",
    "gn:dem":188,
    "gn:feature_class":"P",
    "gn:feature_code":"PPL",
    "gn:name":"Chak Fifty-one",
    "gn:population":0,
    "gn:timezone":"Asia/Karachi",
    "iso:country":"PK",
    "name:und_x_variant":[
        "Siddh\u012bi",
        "Sadhu"
    ],
    "wof:name":"Chak Fifty-one",
    "wof:placetype":"locality"
},
  "geometry": {"coordinates":[73.66117,31.0612],"type":"Point"}
}