{
  "type": "Feature",
  "properties": {
    "gn:admin1_code":"3.0",
    "gn:asciiname":"Banda Hoti",
    "gn:country_code":"PK",
    "gn:dem":696,
    "gn:feature_class":"P",
    "gn:feature_code":"PPL",
    "gn:name":"Banda Hoti",
    "gn:population":0,
    "gn:timezone":"Asia/Karachi",
    "iso:country":"PK",
    "wof:name":"Banda Hoti",
    "wof:placetype":"locality"
},
  "geometry": {"coordinates":[71.14404,33.21853],"type":"Point"}
}