{
  "type": "Feature",
  "properties": {
    "gn:admin1_code":"2.0",
    "gn:asciiname":"Ala Damb",
    "gn:country_code":"PK",
    "gn:dem":1163,
    "gn:feature_class":"P",
    "gn:feature_code":"PPL",
    "gn:name":"Ala Damb",
    "gn:population":0,
    "gn:timezone":"Asia/Karachi",
    "iso:country":"PK",
    "wof:name":"Ala Damb",
    "wof:placetype":"locality"
},
  "geometry": {"coordinates":[66.17147,27.60734],"type":"Point"}
}