{
  "type": "Feature",
  "properties": {
    "gn:admin1_code":"5.0",
    "gn:asciiname":"Bhim",
    "gn:country_code":"PK",
    "gn:dem":17,
    "gn:feature_class":"P",
    "gn:feature_code":"PPL",
    "gn:name":"Bhim",
    "gn:population":0,
    "gn:timezone":"Asia/Karachi",
    "iso:country":"PK",
    "name:eng_x_preferred":[
        "Bhim"
    ],
    "wof:name":"Bhim",
    "wof:placetype":"locality"
},
  "geometry": {"coordinates":[68.39997,25.35413],"type":"Point"}
}