{
  "type": "Feature",
  "properties": {
    "iso:country":"PK",
    "name:bul_x_preferred":[
        "\u0427\u043e\u0440"
    ],
    "name:ceb_x_preferred":[
        "Chor"
    ],
    "name:eng_x_preferred":[
        "Chor"
    ],
    "name:fas_x_preferred":[
        "\u0686\u0648\u0631"
    ],
    "name:jpn_x_preferred":[
        "Chor"
    ],
    "name:mar_x_preferred":[
        "\u0916\u094b\u0916\u0930\u093e\u092a\u093e\u0930"
    ],
    "name:nld_x_preferred":[
        "Chor"
    ],
    "name:unk_x_variant":[
        "Chhor Purano"
    ],
    "name:zho_x_preferred":[
        "\u7126\u723e\uff08\u5df4\u57fa\u65af\u5766\uff09"
    ],
    "qs:gn_country":"PK",
    "qs:gn_fcode":"PPL",
    "qs:gn_pop":16301,
    "qs:name":"Chor",
    "qs:name_adm0":"Pakistan",
    "qs:name_adm1":"Sindh",
    "qs:photos":0,
    "qs:photos_1k":0,
    "qs:photos_9k":0,
    "qs:photos_9r":0,
    "qs:photos_all":0,
    "qs:photos_sr":0,
    "qs:placetype":"Town",
    "qs:pop_sr":"6",
    "qs:woe_adm0":23424922,
    "wd:wordcount":101,
    "wof:name":"Chor",
    "wof:placetype":"locality",
    "wof:population":16301
},
  "geometry": {"coordinates":[69.76667,25.51667],"type":"Point"}
}