{
  "type": "Feature",
  "properties": {
    "gn:admin1_code":"4.0",
    "gn:asciiname":"Gidaranwala",
    "gn:country_code":"PK",
    "gn:dem":110,
    "gn:feature_class":"P",
    "gn:feature_code":"PPL",
    "gn:name":"Gidaranwala",
    "gn:population":0,
    "gn:timezone":"Asia/Karachi",
    "iso:country":"PK",
    "name:und_x_variant":[
        "Basti G\u012bddra"
    ],
    "wof:name":"Gidaranwala",
    "wof:placetype":"locality"
},
  "geometry": {"coordinates":[71.45058,29.54808],"type":"Point"}
}