{
  "type": "Feature",
  "properties": {
    "gn:admin1_code":"3.0",
    "gn:asciiname":"Summan",
    "gn:country_code":"PK",
    "gn:dem":1070,
    "gn:feature_class":"P",
    "gn:feature_code":"PPL",
    "gn:name":"Summan",
    "gn:population":0,
    "gn:timezone":"Asia/Karachi",
    "iso:country":"PK",
    "name:eng_x_preferred":[
        "Summan"
    ],
    "wof:name":"Summan",
    "wof:placetype":"locality"
},
  "geometry": {"coordinates":[73.27063000000003,33.8467],"type":"Point"}
}