{
  "type": "Feature",
  "properties": {
    "gn:admin1_code":"4",
    "gn:asciiname":"Jhok Bahbol",
    "gn:country_code":"PK",
    "gn:dem":179,
    "gn:feature_class":"P",
    "gn:feature_code":"PPL",
    "gn:name":"Jhok Bahbol",
    "gn:population":0,
    "gn:timezone":"Asia/Karachi",
    "iso:country":"PK",
    "wof:name":"Jhok Bahbol",
    "wof:placetype":"locality"
},
  "geometry": {"coordinates":[73.11667,31.06389],"type":"Point"}
}