{
  "type": "Feature",
  "properties": {
    "gn:admin1_code":"02",
    "gn:asciiname":"Mirewari",
    "gn:country_code":"PK",
    "gn:dem":94,
    "gn:feature_class":"P",
    "gn:feature_code":"PPL",
    "gn:name":"Mirewari",
    "gn:population":0,
    "gn:timezone":"Asia/Karachi",
    "iso:country":"PK",
    "name:eng_x_preferred":[
        "M\u012brew\u0101ri Chauki"
    ],
    "name:eng_x_variant":[
        "Merew\u0101ri Chauki"
    ],
    "name:und_x_variant":[
        "Merew\u0101ri Chauki",
        "Mirewari"
    ],
    "wof:name":"Mirewari",
    "wof:placetype":"locality"
},
  "geometry": {"coordinates":[66.8506,25.20997],"type":"Point"}
}