{
  "type": "Feature",
  "properties": {
    "gn:admin1_code":"4.0",
    "gn:asciiname":"Chak Hamid",
    "gn:country_code":"PK",
    "gn:dem":205,
    "gn:feature_class":"P",
    "gn:feature_code":"PPL",
    "gn:name":"Chak Hamid",
    "gn:population":0,
    "gn:timezone":"Asia/Karachi",
    "iso:country":"PK",
    "name:und_x_variant":[
        "Chak Hameed",
        "Chak Hamid"
    ],
    "name:urd_x_preferred":[
        "\u0686\u06a9 \u062d\u0645\u06cc\u062f"
    ],
    "wof:name":"Chak Hamid",
    "wof:placetype":"locality"
},
  "geometry": {"coordinates":[73.20874000000001,32.63747],"type":"Point"}
}