{
  "type": "Feature",
  "properties": {
    "gn:admin1_code":"6.0",
    "gn:asciiname":"Patian",
    "gn:country_code":"PK",
    "gn:dem":719,
    "gn:feature_class":"P",
    "gn:feature_code":"PPL",
    "gn:name":"Patian",
    "gn:population":0,
    "gn:timezone":"Asia/Karachi",
    "iso:country":"PK",
    "name:fas_x_preferred":[
        "\u067e\u062a\u06cc\u0627\u0646"
    ],
    "wof:name":"Patian",
    "wof:placetype":"locality"
},
  "geometry": {"coordinates":[73.64821999999999,33.53085],"type":"Point"}
}