{
  "type": "Feature",
  "properties": {
    "gn:admin1_code":"4.0",
    "gn:asciiname":"Grozan",
    "gn:country_code":"PK",
    "gn:dem":1183,
    "gn:feature_class":"P",
    "gn:feature_code":"PPL",
    "gn:name":"Grozan",
    "gn:population":0,
    "gn:timezone":"Asia/Karachi",
    "iso:country":"PK",
    "name:eng_x_preferred":[
        "Gard\u0101n"
    ],
    "wof:name":"Grozan",
    "wof:placetype":"locality"
},
  "geometry": {"coordinates":[70.09963,30.09121],"type":"Point"}
}