{
  "type": "Feature",
  "properties": {
    "gn:admin1_code":"3",
    "gn:asciiname":"Tokkol",
    "gn:country_code":"PK",
    "gn:dem":1474,
    "gn:feature_class":"P",
    "gn:feature_code":"PPL",
    "gn:name":"Tokkol",
    "gn:population":0,
    "gn:timezone":"Asia/Karachi",
    "iso:country":"PK",
    "name:und_x_variant":[
        "Takul"
    ],
    "wof:name":"Tokkol",
    "wof:placetype":"locality"
},
  "geometry": {"coordinates":[73.44594000000002,34.6619],"type":"Point"}
}