{
  "type": "Feature",
  "properties": {
    "gn:admin1_code":"2",
    "gn:asciiname":"Mandwari",
    "gn:country_code":"PK",
    "gn:dem":101,
    "gn:feature_class":"P",
    "gn:feature_code":"PPL",
    "gn:name":"Mandwari",
    "gn:population":0,
    "gn:timezone":"Asia/Karachi",
    "iso:country":"PK",
    "wof:name":"Mandwari",
    "wof:placetype":"locality"
},
  "geometry": {"coordinates":[67.77049,29.13119],"type":"Point"}
}