{
  "type": "Feature",
  "properties": {
    "gn:admin1_code":"2.0",
    "gn:asciiname":"Dhamb",
    "gn:country_code":"PK",
    "gn:dem":1236,
    "gn:feature_class":"P",
    "gn:feature_code":"PPL",
    "gn:name":"Dhamb",
    "gn:population":0,
    "gn:timezone":"Asia/Karachi",
    "iso:country":"PK",
    "wof:name":"Dhamb",
    "wof:placetype":"locality"
},
  "geometry": {"coordinates":[66.84841999999999,27.79838],"type":"Point"}
}