{
  "type": "Feature",
  "properties": {
    "gn:admin1_code":"3",
    "gn:asciiname":"Chuta",
    "gn:country_code":"PK",
    "gn:dem":2149,
    "gn:feature_class":"P",
    "gn:feature_code":"PPL",
    "gn:name":"Chuta",
    "gn:population":0,
    "gn:timezone":"Asia/Karachi",
    "iso:country":"PK",
    "name:und_x_variant":[
        "Chota"
    ],
    "wof:name":"Chuta",
    "wof:placetype":"locality"
},
  "geometry": {"coordinates":[73.46383,34.69812],"type":"Point"}
}