{
  "type": "Feature",
  "properties": {
    "gn:admin1_code":"3.0",
    "gn:asciiname":"Khatkotai",
    "gn:country_code":"PK",
    "gn:dem":996,
    "gn:feature_class":"P",
    "gn:feature_code":"PPL",
    "gn:name":"Khatkotai",
    "gn:population":0,
    "gn:timezone":"Asia/Karachi",
    "iso:country":"PK",
    "wof:name":"Khatkotai",
    "wof:placetype":"locality"
},
  "geometry": {"coordinates":[72.27701999999999,34.84009],"type":"Point"}
}