{
  "type": "Feature",
  "properties": {
    "gn:admin1_code":"4",
    "gn:asciiname":"Thatha Bhunan",
    "gn:country_code":"PK",
    "gn:dem":204,
    "gn:feature_class":"P",
    "gn:feature_code":"PPL",
    "gn:name":"Thatha Bhunan",
    "gn:population":0,
    "gn:timezone":"Asia/Karachi",
    "iso:country":"PK",
    "name:und_x_variant":[
        "Thatta Bon\u0101n"
    ],
    "wof:name":"Thatha Bhunan",
    "wof:placetype":"locality"
},
  "geometry": {"coordinates":[73.63897,32.00819],"type":"Point"}
}