{
  "type": "Feature",
  "properties": {
    "gn:admin1_code":"4.0",
    "gn:asciiname":"Nabi Shah Bala Colony",
    "gn:country_code":"PK",
    "gn:dem":190,
    "gn:feature_class":"P",
    "gn:feature_code":"PPL",
    "gn:name":"Nabi Shah Bala Colony",
    "gn:population":0,
    "gn:timezone":"Asia/Karachi",
    "iso:country":"PK",
    "wof:name":"Nabi Shah Bala Colony",
    "wof:placetype":"locality"
},
  "geometry": {"coordinates":[72.83065000000001,32.32608],"type":"Point"}
}