{
  "type": "Feature",
  "properties": {
    "gn:admin1_code":"2.0",
    "gn:asciiname":"Kili Mudali",
    "gn:country_code":"PK",
    "gn:dem":1737,
    "gn:feature_class":"P",
    "gn:feature_code":"PPL",
    "gn:name":"Kili Mudali",
    "gn:population":0,
    "gn:timezone":"Asia/Karachi",
    "iso:country":"PK",
    "wof:name":"Kili Mudali",
    "wof:placetype":"locality"
},
  "geometry": {"coordinates":[66.55311999999999,30.68582],"type":"Point"}
}