{
  "type": "Feature",
  "properties": {
    "gn:admin1_code":"5.0",
    "gn:asciiname":"Goth Sobo Khan Mastoi",
    "gn:country_code":"PK",
    "gn:dem":22,
    "gn:feature_class":"P",
    "gn:feature_code":"PPL",
    "gn:name":"Goth Sobo Khan Mastoi",
    "gn:population":0,
    "gn:timezone":"Asia/Karachi",
    "iso:country":"PK",
    "name:und_x_variant":[
        "Goth Taj Muhammad Mastoi"
    ],
    "wof:name":"Goth Sobo Khan Mastoi",
    "wof:placetype":"locality"
},
  "geometry": {"coordinates":[68.86417,25.58625],"type":"Point"}
}