{
  "type": "Feature",
  "properties": {
    "gn:admin1_code":"2.0",
    "gn:asciiname":"Goth Wahid Bakhsh",
    "gn:country_code":"PK",
    "gn:dem":40,
    "gn:feature_class":"P",
    "gn:feature_code":"PPL",
    "gn:name":"Goth Wahid Bakhsh",
    "gn:population":0,
    "gn:timezone":"Asia/Karachi",
    "iso:country":"PK",
    "name:und_x_variant":[
        "Chak 76"
    ],
    "wof:name":"Goth Wahid Bakhsh",
    "wof:placetype":"locality"
},
  "geometry": {"coordinates":[67.67088000000001,28.06377],"type":"Point"}
}