{
  "type": "Feature",
  "properties": {
    "gn:admin1_code":"5",
    "gn:asciiname":"Goth Miandad",
    "gn:country_code":"PK",
    "gn:dem":56,
    "gn:feature_class":"P",
    "gn:feature_code":"PPL",
    "gn:name":"Goth Miandad",
    "gn:population":0,
    "gn:timezone":"Asia/Karachi",
    "iso:country":"PK",
    "name:und_x_variant":[
        "Mi\u0101nd\u0101d Junejo"
    ],
    "wof:name":"Goth Miandad",
    "wof:placetype":"locality"
},
  "geometry": {"coordinates":[68.65541999999999,27.52545],"type":"Point"}
}