{
  "type": "Feature",
  "properties": {
    "gn:admin1_code":"1.0",
    "gn:asciiname":"Fateh Khan Talab",
    "gn:country_code":"PK",
    "gn:dem":524,
    "gn:feature_class":"P",
    "gn:feature_code":"PPL",
    "gn:name":"Fateh Khan Talab",
    "gn:population":0,
    "gn:timezone":"Asia/Karachi",
    "iso:country":"PK",
    "name:und_x_variant":[
        "Fateh Kh\u0101n Talab"
    ],
    "wof:name":"Fateh Khan Talab",
    "wof:placetype":"locality"
},
  "geometry": {"coordinates":[71.63198,33.5763],"type":"Point"}
}