{
  "type": "Feature",
  "properties": {
    "gn:admin1_code":"04",
    "gn:asciiname":"Makhdumpur Pahoran",
    "gn:country_code":"PK",
    "gn:dem":139,
    "gn:feature_class":"P",
    "gn:feature_code":"PPL",
    "gn:name":"Makhdumpur Pahoran",
    "gn:population":0,
    "gn:timezone":"Asia/Karachi",
    "iso:country":"PK",
    "name:und_x_variant":[
        "Makhdumpore",
        "Makhdumpur Pahoran",
        "Makhd\u016bmpur"
    ],
    "wof:name":"Makhdumpur Pahoran",
    "wof:placetype":"locality"
},
  "geometry": {"coordinates":[72.04343,30.45736],"type":"Point"}
}