{
  "type": "Feature",
  "properties": {
    "gn:admin1_code":"3.0",
    "gn:asciiname":"Dherian",
    "gn:country_code":"PK",
    "gn:dem":1150,
    "gn:feature_class":"P",
    "gn:feature_code":"PPL",
    "gn:name":"Dherian",
    "gn:population":0,
    "gn:timezone":"Asia/Karachi",
    "iso:country":"PK",
    "name:eng_x_preferred":[
        "Dheri"
    ],
    "wof:name":"Dherian",
    "wof:placetype":"locality"
},
  "geometry": {"coordinates":[73.24845999999999,33.90766],"type":"Point"}
}