{
  "type": "Feature",
  "properties": {
    "gn:admin1_code":"7.0",
    "gn:asciiname":"Babar Shah Harai",
    "gn:country_code":"PK",
    "gn:dem":3750,
    "gn:feature_class":"P",
    "gn:feature_code":"PPL",
    "gn:name":"Babar Shah Harai",
    "gn:population":0,
    "gn:timezone":"Asia/Karachi",
    "iso:country":"PK",
    "wof:name":"Babar Shah Harai",
    "wof:placetype":"locality"
},
  "geometry": {"coordinates":[73.44563000000002,35.9375],"type":"Point"}
}