{
  "type": "Feature",
  "properties": {
    "gn:admin1_code":"4",
    "gn:asciiname":"Basti Jafar",
    "gn:country_code":"PK",
    "gn:dem":107,
    "gn:feature_class":"P",
    "gn:feature_code":"PPL",
    "gn:name":"Basti Jafar",
    "gn:population":0,
    "gn:timezone":"Asia/Karachi",
    "iso:country":"PK",
    "name:und_x_variant":[
        "J\u0101far"
    ],
    "wof:name":"Basti Jafar",
    "wof:placetype":"locality"
},
  "geometry": {"coordinates":[71.12335999999998,29.43204],"type":"Point"}
}