{
  "type": "Feature",
  "properties": {
    "gn:admin1_code":"8.0",
    "gn:asciiname":"Hon Dhamial",
    "gn:country_code":"PK",
    "gn:dem":488,
    "gn:feature_class":"P",
    "gn:feature_code":"PPL",
    "gn:name":"Hon Dhami\u0101l",
    "gn:population":0,
    "gn:timezone":"Asia/Karachi",
    "iso:country":"PK",
    "name:und_x_variant":[
        "Dhami\u0101l",
        "H\u016bn Dhami\u0101l"
    ],
    "wof:name":"Hon Dhamial",
    "wof:placetype":"locality"
},
  "geometry": {"coordinates":[73.21977,33.54789],"type":"Point"}
}