{
  "type": "Feature",
  "properties": {
    "gn:admin1_code":"4.0",
    "gn:asciiname":"Dhok Laham",
    "gn:country_code":"PK",
    "gn:dem":414,
    "gn:feature_class":"P",
    "gn:feature_code":"PPL",
    "gn:name":"Dhok Laham",
    "gn:population":0,
    "gn:timezone":"Asia/Karachi",
    "iso:country":"PK",
    "wof:name":"Dhok Laham",
    "wof:placetype":"locality"
},
  "geometry": {"coordinates":[72.31197,33.16567],"type":"Point"}
}