{
  "type": "Feature",
  "properties": {
    "gn:admin1_code":"5.0",
    "gn:asciiname":"Rais Hakim Ali Khan Marri",
    "gn:country_code":"PK",
    "gn:dem":22,
    "gn:feature_class":"P",
    "gn:feature_code":"PPL",
    "gn:name":"Rais Hakim Ali Khan Marri",
    "gn:population":0,
    "gn:timezone":"Asia/Karachi",
    "iso:country":"PK",
    "wof:name":"Rais Hakim Ali Khan Marri",
    "wof:placetype":"locality"
},
  "geometry": {"coordinates":[68.89435,26.0722],"type":"Point"}
}