{
  "type": "Feature",
  "properties": {
    "gn:admin1_code":"5",
    "gn:asciiname":"Goth Kalhora",
    "gn:country_code":"PK",
    "gn:dem":46,
    "gn:feature_class":"P",
    "gn:feature_code":"PPL",
    "gn:name":"Goth Kalhora",
    "gn:population":0,
    "gn:timezone":"Asia/Karachi",
    "iso:country":"PK",
    "name:und_x_variant":[
        "Goth Kalhoro"
    ],
    "wof:name":"Goth Kalhora",
    "wof:placetype":"locality"
},
  "geometry": {"coordinates":[68.06909,27.14605],"type":"Point"}
}