{
  "type": "Feature",
  "properties": {
    "gn:admin1_code":"3",
    "gn:asciiname":"Dhanu",
    "gn:country_code":"PK",
    "gn:dem":1746,
    "gn:feature_class":"P",
    "gn:feature_code":"PPL",
    "gn:name":"Dhanu",
    "gn:population":0,
    "gn:timezone":"Asia/Karachi",
    "iso:country":"PK",
    "wof:name":"Dhanu",
    "wof:placetype":"locality"
},
  "geometry": {"coordinates":[73.57389000000001,34.7006],"type":"Point"}
}