{
  "type": "Feature",
  "properties": {
    "gn:admin1_code":"4",
    "gn:asciiname":"Kaneriwala",
    "gn:country_code":"PK",
    "gn:dem":112,
    "gn:feature_class":"P",
    "gn:feature_code":"PPL",
    "gn:name":"Kaner\u012bw\u0101la",
    "gn:population":0,
    "gn:timezone":"Asia/Karachi",
    "iso:country":"PK",
    "wof:name":"Kaneriwala",
    "wof:placetype":"locality"
},
  "geometry": {"coordinates":[71.24583,29.725],"type":"Point"}
}