{
  "type": "Feature",
  "properties": {
    "gn:admin1_code":"2.0",
    "gn:asciiname":"Mazari Kahan",
    "gn:country_code":"PK",
    "gn:dem":114,
    "gn:feature_class":"P",
    "gn:feature_code":"PPL",
    "gn:name":"Mazari Kahan",
    "gn:population":0,
    "gn:timezone":"Asia/Karachi",
    "iso:country":"PK",
    "wof:name":"Mazari Kahan",
    "wof:placetype":"locality"
},
  "geometry": {"coordinates":[62.94888,26.02587],"type":"Point"}
}