{
  "type": "Feature",
  "properties": {
    "gn:admin1_code":"4.0",
    "gn:asciiname":"Maddan",
    "gn:country_code":"PK",
    "gn:dem":255,
    "gn:feature_class":"P",
    "gn:feature_code":"PPL",
    "gn:name":"Maddan",
    "gn:population":0,
    "gn:timezone":"Asia/Karachi",
    "iso:country":"PK",
    "name:est_x_preferred":[
        "Maddan"
    ],
    "name:fra_x_preferred":[
        "Maddan"
    ],
    "name:heb_x_preferred":[
        "\u05de\u05d0\u05d3\u05d0\u05df"
    ],
    "name:ita_x_preferred":[
        "Maddan"
    ],
    "name:nld_x_preferred":[
        "Maddan"
    ],
    "name:nor_x_preferred":[
        "Maddan"
    ],
    "name:rus_x_preferred":[
        "\u041c\u0430\u0434\u0430\u043d"
    ],
    "name:ukr_x_preferred":[
        "\u041c\u0430\u0434\u0430\u043d"
    ],
    "wof:name":"Maddan",
    "wof:placetype":"locality"
},
  "geometry": {"coordinates":[75.12649999999999,32.21749000000001],"type":"Point"}
}