{
  "type": "Feature",
  "properties": {
    "gn:admin1_code":"2.0",
    "gn:asciiname":"Abdul Rahim Gis",
    "gn:country_code":"PK",
    "gn:dem":1411,
    "gn:feature_class":"P",
    "gn:feature_code":"PPL",
    "gn:name":"Abdul Rahim Gis",
    "gn:population":0,
    "gn:timezone":"Asia/Karachi",
    "iso:country":"PK",
    "wof:name":"Abdul Rahim Gis",
    "wof:placetype":"locality"
},
  "geometry": {"coordinates":[63.93198,29.29037000000001],"type":"Point"}
}