{
  "type": "Feature",
  "properties": {
    "gn:admin1_code":"4.0",
    "gn:asciiname":"Masat Dokhli",
    "gn:country_code":"PK",
    "gn:dem":1975,
    "gn:feature_class":"P",
    "gn:feature_code":"PPL",
    "gn:name":"Masat Dokhli",
    "gn:population":0,
    "gn:timezone":"Asia/Karachi",
    "iso:country":"PK",
    "name:eng_x_preferred":[
        "Mas\u0101t Dukhli"
    ],
    "wof:name":"Masat Dokhli",
    "wof:placetype":"locality"
},
  "geometry": {"coordinates":[73.40167,33.9715],"type":"Point"}
}