{
  "type": "Feature",
  "properties": {
    "gn:admin1_code":"2",
    "gn:asciiname":"Abu Said",
    "gn:country_code":"PK",
    "gn:dem":1726,
    "gn:feature_class":"P",
    "gn:feature_code":"PPL",
    "gn:name":"Abu Said",
    "gn:population":0,
    "gn:timezone":"Asia/Karachi",
    "iso:country":"PK",
    "name:eng_x_preferred":[
        "\u0100busidah"
    ],
    "name:und_x_variant":[
        "Bosid",
        "Abu Said"
    ],
    "wof:name":"Abu Said",
    "wof:placetype":"locality"
},
  "geometry": {"coordinates":[67.21137,30.76463],"type":"Point"}
}