{
  "type": "Feature",
  "properties": {
    "gn:admin1_code":"3.0",
    "gn:asciiname":"Kutan Kot",
    "gn:country_code":"PK",
    "gn:dem":320,
    "gn:feature_class":"P",
    "gn:feature_code":"PPL",
    "gn:name":"Kutan Kot",
    "gn:population":0,
    "gn:timezone":"Asia/Karachi",
    "iso:country":"PK",
    "name:und_x_variant":[
        "Kut\u0101n Kot"
    ],
    "wof:name":"Kutan Kot",
    "wof:placetype":"locality"
},
  "geometry": {"coordinates":[70.6935,32.84783],"type":"Point"}
}