{
  "type": "Feature",
  "properties": {
    "gn:admin1_code":"1.0",
    "gn:asciiname":"Muhammad Nao",
    "gn:country_code":"PK",
    "gn:dem":879,
    "gn:feature_class":"P",
    "gn:feature_code":"PPL",
    "gn:name":"Muhammad Nao",
    "gn:population":0,
    "gn:timezone":"Asia/Karachi",
    "iso:country":"PK",
    "wof:name":"Muhammad Nao",
    "wof:placetype":"locality"
},
  "geometry": {"coordinates":[71.29012,34.63766],"type":"Point"}
}