{
  "type": "Feature",
  "properties": {
    "gn:admin1_code":"4.0",
    "gn:asciiname":"Basti Spel",
    "gn:country_code":"PK",
    "gn:dem":93,
    "gn:feature_class":"P",
    "gn:feature_code":"PPL",
    "gn:name":"Basti Spel",
    "gn:population":0,
    "gn:timezone":"Asia/Karachi",
    "iso:country":"PK",
    "name:und_x_variant":[
        "Senpl\u0101n"
    ],
    "wof:name":"Basti Spel",
    "wof:placetype":"locality"
},
  "geometry": {"coordinates":[70.37232,28.99913],"type":"Point"}
}