{
  "type": "Feature",
  "properties": {
    "gn:admin1_code":"4.0",
    "gn:asciiname":"Gaddi Gurha",
    "gn:country_code":"PK",
    "gn:dem":256,
    "gn:feature_class":"P",
    "gn:feature_code":"PPL",
    "gn:name":"Gaddi Gurha",
    "gn:population":0,
    "gn:timezone":"Asia/Karachi",
    "iso:country":"PK",
    "name:und_x_variant":[
        "Gaddi Gohra",
        "Gaddi Gurha"
    ],
    "wof:name":"Gaddi Gurha",
    "wof:placetype":"locality"
},
  "geometry": {"coordinates":[73.7683,32.87286],"type":"Point"}
}