{
  "type": "Feature",
  "properties": {
    "gn:admin1_code":"5.0",
    "gn:asciiname":"Goth Muhammad Umar Girano",
    "gn:country_code":"PK",
    "gn:dem":13,
    "gn:feature_class":"P",
    "gn:feature_code":"PPL",
    "gn:name":"Goth Muhammad Umar Girano",
    "gn:population":0,
    "gn:timezone":"Asia/Karachi",
    "iso:country":"PK",
    "name:und_x_variant":[
        "Goth Bijora",
        "Goth Muhammad Umar Girano"
    ],
    "wof:name":"Goth Muhammad Umar Girano",
    "wof:placetype":"locality"
},
  "geometry": {"coordinates":[67.95435000000001,24.69684],"type":"Point"}
}