{
  "type": "Feature",
  "properties": {
    "gn:admin1_code":"4.0",
    "gn:asciiname":"Waryanwala",
    "gn:country_code":"PK",
    "gn:dem":180,
    "gn:feature_class":"P",
    "gn:feature_code":"PPL",
    "gn:name":"Waryanwala",
    "gn:population":0,
    "gn:timezone":"Asia/Karachi",
    "iso:country":"PK",
    "name:und_x_variant":[
        "Waryamwala"
    ],
    "wof:name":"Waryanwala",
    "wof:placetype":"locality"
},
  "geometry": {"coordinates":[72.43649000000001,32.34335],"type":"Point"}
}