{
  "type": "Feature",
  "properties": {
    "gn:admin1_code":"4",
    "gn:asciiname":"Gamb Khurd",
    "gn:country_code":"PK",
    "gn:dem":185,
    "gn:feature_class":"P",
    "gn:feature_code":"PPL",
    "gn:name":"Gamb Khurd",
    "gn:population":0,
    "gn:timezone":"Asia/Karachi",
    "iso:country":"PK",
    "name:und_x_variant":[
        "Gamb"
    ],
    "wof:name":"Gamb Khurd",
    "wof:placetype":"locality"
},
  "geometry": {"coordinates":[74.04482,30.90508],"type":"Point"}
}