{
  "type": "Feature",
  "properties": {
    "gn:admin1_code":"2.0",
    "gn:asciiname":"Murid Chah",
    "gn:country_code":"PK",
    "gn:dem":871,
    "gn:feature_class":"P",
    "gn:feature_code":"PPL",
    "gn:name":"Murid Chah",
    "gn:population":0,
    "gn:timezone":"Asia/Karachi",
    "iso:country":"PK",
    "wof:name":"Murid Chah",
    "wof:placetype":"locality"
},
  "geometry": {"coordinates":[63.83496,26.8817],"type":"Point"}
}