{
  "type": "Feature",
  "properties": {
    "gn:admin1_code":"4",
    "gn:asciiname":"Makorianwala",
    "gn:country_code":"PK",
    "gn:dem":143,
    "gn:feature_class":"P",
    "gn:feature_code":"PPL",
    "gn:name":"Makorianwala",
    "gn:population":0,
    "gn:timezone":"Asia/Karachi",
    "iso:country":"PK",
    "wof:name":"Makorianwala",
    "wof:placetype":"locality"
},
  "geometry": {"coordinates":[71.88478000000001,30.90144],"type":"Point"}
}