{
  "type": "Feature",
  "properties": {
    "gn:admin1_code":"1.0",
    "gn:asciiname":"Ahd Koruna",
    "gn:country_code":"PK",
    "gn:dem":832,
    "gn:feature_class":"P",
    "gn:feature_code":"PPL",
    "gn:name":"Ahd Koruna",
    "gn:population":0,
    "gn:timezone":"Asia/Karachi",
    "iso:country":"PK",
    "name:fas_x_preferred":[
        "\u0627\u062d\u062f \u06a9\u0631\u0648\u0646\u0627"
    ],
    "name:und_x_variant":[
        "Ahad Kor\u016bna",
        "Ahd Koruna"
    ],
    "name:urd_x_preferred":[
        "\u0627\u062d\u062f \u06a9\u0631\u0648\u0646\u0627"
    ],
    "wof:name":"Ahd Koruna",
    "wof:placetype":"locality"
},
  "geometry": {"coordinates":[71.2484,34.38372],"type":"Point"}
}