{
  "type": "Feature",
  "properties": {
    "gn:admin1_code":"3.0",
    "gn:asciiname":"Badreri",
    "gn:country_code":"PK",
    "gn:dem":1515,
    "gn:feature_class":"P",
    "gn:feature_code":"PPL",
    "gn:name":"Badreri",
    "gn:population":0,
    "gn:timezone":"Asia/Karachi",
    "iso:country":"PK",
    "name:eng_x_preferred":[
        "Bhadner"
    ],
    "wof:name":"Badreri",
    "wof:placetype":"locality"
},
  "geometry": {"coordinates":[73.34295999999998,33.96472],"type":"Point"}
}