{
  "type": "Feature",
  "properties": {
    "gn:admin1_code":"5",
    "gn:asciiname":"Sulaiman Zaur",
    "gn:country_code":"PK",
    "gn:dem":16,
    "gn:feature_class":"P",
    "gn:feature_code":"PPL",
    "gn:name":"Sulaiman Zaur",
    "gn:population":0,
    "gn:timezone":"Asia/Karachi",
    "iso:country":"PK",
    "wof:name":"Sulaiman Zaur",
    "wof:placetype":"locality"
},
  "geometry": {"coordinates":[68.54087,25.02151],"type":"Point"}
}