{
  "type": "Feature",
  "properties": {
    "gn:admin1_code":"4",
    "gn:asciiname":"Mohra Kalia",
    "gn:country_code":"PK",
    "gn:dem":510,
    "gn:feature_class":"P",
    "gn:feature_code":"PPL",
    "gn:name":"Mohra Kalia",
    "gn:population":0,
    "gn:timezone":"Asia/Karachi",
    "iso:country":"PK",
    "name:und_x_variant":[
        "Mohra Kami\u0101l"
    ],
    "wof:name":"Mohra Kalia",
    "wof:placetype":"locality"
},
  "geometry": {"coordinates":[73.32597,33.09762],"type":"Point"}
}