{
  "type": "Feature",
  "properties": {
    "gn:admin1_code":"4",
    "gn:asciiname":"Basti Kalewali",
    "gn:country_code":"PK",
    "gn:dem":82,
    "gn:feature_class":"P",
    "gn:feature_code":"PPL",
    "gn:name":"Basti Kalewali",
    "gn:population":0,
    "gn:timezone":"Asia/Karachi",
    "iso:country":"PK",
    "name:und_x_variant":[
        "K\u0101lew\u0101li"
    ],
    "wof:name":"Basti Kalewali",
    "wof:placetype":"locality"
},
  "geometry": {"coordinates":[69.84716999999999,28.38092],"type":"Point"}
}