{
  "type": "Feature",
  "properties": {
    "gn:admin1_code":"04",
    "gn:asciiname":"Makial",
    "gn:country_code":"PK",
    "gn:dem":442,
    "gn:feature_class":"P",
    "gn:feature_code":"PPL",
    "gn:name":"Makial",
    "gn:population":0,
    "gn:timezone":"Asia/Karachi",
    "iso:country":"PK",
    "wof:name":"Makial",
    "wof:placetype":"locality"
},
  "geometry": {"coordinates":[72.42149000000001,33.27952],"type":"Point"}
}