{
  "type": "Feature",
  "properties": {
    "gn:admin1_code":"4.0",
    "gn:asciiname":"Dhok Chhuai",
    "gn:country_code":"PK",
    "gn:dem":295,
    "gn:feature_class":"P",
    "gn:feature_code":"PPL",
    "gn:name":"Dhok Chhuai",
    "gn:population":0,
    "gn:timezone":"Asia/Karachi",
    "iso:country":"PK",
    "wof:name":"Dhok Chhuai",
    "wof:placetype":"locality"
},
  "geometry": {"coordinates":[71.87666999999998,33.09806],"type":"Point"}
}