{
  "type": "Feature",
  "properties": {
    "gn:admin1_code":"3.0",
    "gn:asciiname":"Gangu",
    "gn:country_code":"PK",
    "gn:dem":319,
    "gn:feature_class":"P",
    "gn:feature_code":"PPL",
    "gn:name":"Gangu",
    "gn:population":0,
    "gn:timezone":"Asia/Karachi",
    "iso:country":"PK",
    "name:eng_x_preferred":[
        "G\u0101ngu"
    ],
    "wof:name":"Gangu",
    "wof:placetype":"locality"
},
  "geometry": {"coordinates":[71.68921,34.22078],"type":"Point"}
}