{
  "type": "Feature",
  "properties": {
    "gn:admin1_code":"4",
    "gn:asciiname":"Qila Nanda Singh",
    "gn:country_code":"PK",
    "gn:dem":185,
    "gn:feature_class":"P",
    "gn:feature_code":"PPL",
    "gn:name":"Qila Nanda Singh",
    "gn:population":0,
    "gn:timezone":"Asia/Karachi",
    "iso:country":"PK",
    "wof:name":"Qila Nanda Singh",
    "wof:placetype":"locality"
},
  "geometry": {"coordinates":[73.68333,31.15694],"type":"Point"}
}