{
  "type": "Feature",
  "properties": {
    "gn:admin1_code":"3",
    "gn:asciiname":"Kajo",
    "gn:country_code":"PK",
    "gn:dem":985,
    "gn:feature_class":"P",
    "gn:feature_code":"PPL",
    "gn:name":"Kajo",
    "gn:population":0,
    "gn:timezone":"Asia/Karachi",
    "iso:country":"PK",
    "name:und_x_variant":[
        "Kaju",
        "Kajo"
    ],
    "wof:name":"Kajo",
    "wof:placetype":"locality"
},
  "geometry": {"coordinates":[73.13504,34.2949],"type":"Point"}
}