{
  "type": "Feature",
  "properties": {
    "gn:admin1_code":"3",
    "gn:asciiname":"Baddher",
    "gn:country_code":"PK",
    "gn:dem":2423,
    "gn:feature_class":"P",
    "gn:feature_code":"PPL",
    "gn:name":"Baddher",
    "gn:population":0,
    "gn:timezone":"Asia/Karachi",
    "iso:country":"PK",
    "name:eng_x_preferred":[
        "Baddher"
    ],
    "name:und_x_variant":[
        "Badder"
    ],
    "wof:name":"Baddher",
    "wof:placetype":"locality"
},
  "geometry": {"coordinates":[72.5052,35.22961],"type":"Point"}
}