{
  "type": "Feature",
  "properties": {
    "gn:admin1_code":"5.0",
    "gn:asciiname":"Karkasar",
    "gn:country_code":"PK",
    "gn:dem":29,
    "gn:feature_class":"P",
    "gn:feature_code":"PPL",
    "gn:name":"Karkasar",
    "gn:population":0,
    "gn:timezone":"Asia/Karachi",
    "iso:country":"PK",
    "name:ceb_x_preferred":[
        "Karkas\u0101r"
    ],
    "name:fas_x_preferred":[
        "\u06a9\u0631\u06a9\u0633\u0627\u0631"
    ],
    "name:swe_x_preferred":[
        "Karkas\u0101r"
    ],
    "wof:name":"Karkasar",
    "wof:placetype":"locality"
},
  "geometry": {"coordinates":[69.74658000000001,24.50716],"type":"Point"}
}