{
  "type": "Feature",
  "properties": {
    "gn:admin1_code":"2",
    "gn:asciiname":"Goth Sajan Khan",
    "gn:country_code":"PK",
    "gn:dem":51,
    "gn:feature_class":"P",
    "gn:feature_code":"PPL",
    "gn:name":"Goth Sajan Khan",
    "gn:population":0,
    "gn:timezone":"Asia/Karachi",
    "iso:country":"PK",
    "name:und_x_variant":[
        "Goth Sewa Kh\u0101n",
        "Sewa Kh\u0101n",
        "Goth Sajan Khan"
    ],
    "wof:name":"Goth Sajan Khan",
    "wof:placetype":"locality"
},
  "geometry": {"coordinates":[67.77891,28.0768],"type":"Point"}
}