{
  "type": "Feature",
  "properties": {
    "gn:admin1_code":"4",
    "gn:asciiname":"Pathoriwala",
    "gn:country_code":"PK",
    "gn:dem":163,
    "gn:feature_class":"P",
    "gn:feature_code":"PPL",
    "gn:name":"Pathoriwala",
    "gn:population":0,
    "gn:timezone":"Asia/Karachi",
    "iso:country":"PK",
    "wof:name":"Pathoriwala",
    "wof:placetype":"locality"
},
  "geometry": {"coordinates":[71.15867,31.43298],"type":"Point"}
}