{
  "type": "Feature",
  "properties": {
    "gn:admin1_code":"4",
    "gn:asciiname":"Chak Five Hundred Eight",
    "gn:country_code":"PK",
    "gn:dem":163,
    "gn:feature_class":"P",
    "gn:feature_code":"PPL",
    "gn:name":"Chak Five Hundred Eight",
    "gn:population":0,
    "gn:timezone":"Asia/Karachi",
    "iso:country":"PK",
    "name:und_x_variant":[
        "Th\u012bkr\u012bw\u0101la",
        "Thikri\u0101nw\u0101la"
    ],
    "wof:name":"Chak Five Hundred Eight",
    "wof:placetype":"locality"
},
  "geometry": {"coordinates":[72.74775,30.84013],"type":"Point"}
}