{
  "type": "Feature",
  "properties": {
    "gn:admin1_code":"5.0",
    "gn:asciiname":"Mir Muhammad Sumro",
    "gn:country_code":"PK",
    "gn:dem":9,
    "gn:feature_class":"P",
    "gn:feature_code":"PPL",
    "gn:name":"Mir Muhammad Sumro",
    "gn:population":0,
    "gn:timezone":"Asia/Karachi",
    "iso:country":"PK",
    "name:eng_x_preferred":[
        "Mir Muhammad Sumro"
    ],
    "wof:name":"Mir Muhammad Sumro",
    "wof:placetype":"locality"
},
  "geometry": {"coordinates":[68.09416,24.59862],"type":"Point"}
}