{
  "type": "Feature",
  "properties": {
    "gn:admin1_code":"5",
    "gn:asciiname":"Goth Rais Mubarak",
    "gn:country_code":"PK",
    "gn:dem":67,
    "gn:feature_class":"P",
    "gn:feature_code":"PPL",
    "gn:name":"Goth Rais Mubarak",
    "gn:population":0,
    "gn:timezone":"Asia/Karachi",
    "iso:country":"PK",
    "name:und_x_variant":[
        "Goth Ra\u012bs Mub\u0101rik"
    ],
    "wof:name":"Goth Rais Mubarak",
    "wof:placetype":"locality"
},
  "geometry": {"coordinates":[69.1006,28.20523],"type":"Point"}
}