{
  "type": "Feature",
  "properties": {
    "gn:admin1_code":"3.0",
    "gn:asciiname":"Sabai",
    "gn:country_code":"PK",
    "gn:dem":1660,
    "gn:feature_class":"P",
    "gn:feature_code":"PPL",
    "gn:name":"Sabai",
    "gn:population":0,
    "gn:timezone":"Asia/Karachi",
    "iso:country":"PK",
    "wof:name":"Sabai",
    "wof:placetype":"locality"
},
  "geometry": {"coordinates":[72.84435000000001,34.53148],"type":"Point"}
}