{
  "type": "Feature",
  "properties": {
    "gn:admin1_code":"01",
    "gn:asciiname":"Gulpir",
    "gn:country_code":"PK",
    "gn:dem":673,
    "gn:feature_class":"P",
    "gn:feature_code":"PPL",
    "gn:name":"Gulpir",
    "gn:population":0,
    "gn:timezone":"Asia/Karachi",
    "iso:country":"PK",
    "wof:name":"Gulpir",
    "wof:placetype":"locality"
},
  "geometry": {"coordinates":[70.51925,33.26258],"type":"Point"}
}