{
  "type": "Feature",
  "properties": {
    "gn:admin1_code":"4.0",
    "gn:asciiname":"Mallah",
    "gn:country_code":"PK",
    "gn:dem":285,
    "gn:feature_class":"P",
    "gn:feature_code":"PPL",
    "gn:name":"Mallah",
    "gn:population":0,
    "gn:timezone":"Asia/Karachi",
    "iso:country":"PK",
    "wof:name":"Mallah",
    "wof:placetype":"locality"
},
  "geometry": {"coordinates":[74.96016999999998,32.41344],"type":"Point"}
}