{
  "type": "Feature",
  "properties": {
    "gn:admin1_code":"5",
    "gn:asciiname":"Shadi Khan Almani",
    "gn:country_code":"PK",
    "gn:dem":47,
    "gn:feature_class":"P",
    "gn:feature_code":"PPL",
    "gn:name":"Shadi Khan Almani",
    "gn:population":0,
    "gn:timezone":"Asia/Karachi",
    "iso:country":"PK",
    "name:und_x_variant":[
        "Alm\u0101ni"
    ],
    "wof:name":"Shadi Khan Almani",
    "wof:placetype":"locality"
},
  "geometry": {"coordinates":[68.0857,26.9917],"type":"Point"}
}