{
  "type": "Feature",
  "properties": {
    "gn:admin1_code":"2",
    "gn:asciiname":"Loe Shin Magh",
    "gn:country_code":"PK",
    "gn:dem":2522,
    "gn:feature_class":"P",
    "gn:feature_code":"PPL",
    "gn:name":"Loe Shin Magh",
    "gn:population":0,
    "gn:timezone":"Asia/Karachi",
    "iso:country":"PK",
    "name:und_x_variant":[
        "Loe Sh\u012bn Maghzai",
        "Loe Shin Magh"
    ],
    "wof:name":"Loe Shin Magh",
    "wof:placetype":"locality"
},
  "geometry": {"coordinates":[67.03863,30.35362000000001],"type":"Point"}
}