{
  "type": "Feature",
  "properties": {
    "gn:admin1_code":"2.0",
    "gn:asciiname":"Hayatabad",
    "gn:country_code":"PK",
    "gn:dem":1472,
    "gn:feature_class":"P",
    "gn:feature_code":"PPL",
    "gn:name":"Hayatabad",
    "gn:population":0,
    "gn:timezone":"Asia/Karachi",
    "iso:country":"PK",
    "wof:name":"Hayatabad",
    "wof:placetype":"locality"
},
  "geometry": {"coordinates":[66.49014,30.07291],"type":"Point"}
}