{
  "type": "Feature",
  "properties": {
    "gn:admin1_code":"3.0",
    "gn:asciiname":"Shamnimos",
    "gn:country_code":"PK",
    "gn:dem":1943,
    "gn:feature_class":"P",
    "gn:feature_code":"PPL",
    "gn:name":"Shamnimos",
    "gn:population":0,
    "gn:timezone":"Asia/Karachi",
    "iso:country":"PK",
    "wof:name":"Shamnimos",
    "wof:placetype":"locality"
},
  "geometry": {"coordinates":[73.62834000000002,35.44944],"type":"Point"}
}