{
  "type": "Feature",
  "properties": {
    "gn:admin1_code":"2.0",
    "gn:asciiname":"Isa Khan Kili",
    "gn:country_code":"PK",
    "gn:dem":1591,
    "gn:feature_class":"P",
    "gn:feature_code":"PPL",
    "gn:name":"Isa Khan Kili",
    "gn:population":0,
    "gn:timezone":"Asia/Karachi",
    "iso:country":"PK",
    "wof:name":"Isa Khan Kili",
    "wof:placetype":"locality"
},
  "geometry": {"coordinates":[69.73416999999999,31.68861],"type":"Point"}
}