{
  "type": "Feature",
  "properties": {
    "gn:admin1_code":"4.0",
    "gn:asciiname":"Chak Sabz",
    "gn:country_code":"PK",
    "gn:dem":423,
    "gn:feature_class":"P",
    "gn:feature_code":"PPL",
    "gn:name":"Chak Sabz",
    "gn:population":0,
    "gn:timezone":"Asia/Karachi",
    "iso:country":"PK",
    "wof:name":"Chak Sabz",
    "wof:placetype":"locality"
},
  "geometry": {"coordinates":[73.00923,33.29927],"type":"Point"}
}