{
  "type": "Feature",
  "properties": {
    "gn:admin1_code":"3.0",
    "gn:asciiname":"Darya Khel",
    "gn:country_code":"PK",
    "gn:dem":983,
    "gn:feature_class":"P",
    "gn:feature_code":"PPL",
    "gn:name":"Darya Khel",
    "gn:population":0,
    "gn:timezone":"Asia/Karachi",
    "iso:country":"PK",
    "wof:name":"Darya Khel",
    "wof:placetype":"locality"
},
  "geometry": {"coordinates":[71.29442,33.10971],"type":"Point"}
}