{
  "type": "Feature",
  "properties": {
    "gn:admin1_code":"3.0",
    "gn:asciiname":"Garhi Saidabad",
    "gn:country_code":"PK",
    "gn:dem":301,
    "gn:feature_class":"P",
    "gn:feature_code":"PPL",
    "gn:name":"Garhi Saidabad",
    "gn:population":0,
    "gn:timezone":"Asia/Karachi",
    "iso:country":"PK",
    "name:eng_x_preferred":[
        "Muzaffar Kh\u0101n Garhi"
    ],
    "wof:name":"Garhi Saidabad",
    "wof:placetype":"locality"
},
  "geometry": {"coordinates":[71.66989000000002,34.04104],"type":"Point"}
}