{
  "type": "Feature",
  "properties": {
    "gn:admin1_code":"5",
    "gn:asciiname":"Goth Samano",
    "gn:country_code":"PK",
    "gn:dem":69,
    "gn:feature_class":"P",
    "gn:feature_code":"PPL",
    "gn:name":"Goth Samano",
    "gn:population":0,
    "gn:timezone":"Asia/Karachi",
    "iso:country":"PK",
    "name:und_x_variant":[
        "Sam\u0101no"
    ],
    "wof:name":"Goth Samano",
    "wof:placetype":"locality"
},
  "geometry": {"coordinates":[68.80053000000001,27.82874],"type":"Point"}
}