{
  "type": "Feature",
  "properties": {
    "gn:admin1_code":"4.0",
    "gn:asciiname":"Munshi Uthar",
    "gn:country_code":"PK",
    "gn:dem":164,
    "gn:feature_class":"P",
    "gn:feature_code":"PPL",
    "gn:name":"Munshi Uthar",
    "gn:population":0,
    "gn:timezone":"Asia/Karachi",
    "iso:country":"PK",
    "wof:name":"Munshi Uthar",
    "wof:placetype":"locality"
},
  "geometry": {"coordinates":[73.46531,30.14671],"type":"Point"}
}