{
  "type": "Feature",
  "properties": {
    "gn:admin1_code":"4",
    "gn:asciiname":"Dhab Ghumanwala",
    "gn:country_code":"PK",
    "gn:dem":174,
    "gn:feature_class":"P",
    "gn:feature_code":"PPL",
    "gn:name":"Dhab Ghumanwala",
    "gn:population":0,
    "gn:timezone":"Asia/Karachi",
    "iso:country":"PK",
    "name:und_x_variant":[
        "Dh\u0101bw\u0101la"
    ],
    "wof:name":"Dhab Ghumanwala",
    "wof:placetype":"locality"
},
  "geometry": {"coordinates":[73.9199,30.26839],"type":"Point"}
}