{
  "type": "Feature",
  "properties": {
    "gn:admin1_code":"4",
    "gn:asciiname":"Kotli Loiyan",
    "gn:country_code":"PK",
    "gn:dem":253,
    "gn:feature_class":"P",
    "gn:feature_code":"PPL",
    "gn:name":"Kotli Loiyan",
    "gn:population":0,
    "gn:timezone":"Asia/Karachi",
    "iso:country":"PK",
    "name:und_x_variant":[
        "Kotli Ri\u0101nda"
    ],
    "wof:name":"Kotli Loiyan",
    "wof:placetype":"locality"
},
  "geometry": {"coordinates":[74.60342,32.4671],"type":"Point"}
}