{
  "type": "Feature",
  "properties": {
    "gn:admin1_code":"4",
    "gn:asciiname":"Tibba Pathananwala",
    "gn:country_code":"PK",
    "gn:dem":149,
    "gn:feature_class":"P",
    "gn:feature_code":"PPL",
    "gn:name":"Tibba Pathananwala",
    "gn:population":0,
    "gn:timezone":"Asia/Karachi",
    "iso:country":"PK",
    "name:und_x_variant":[
        "Tibba Mochi\u0101nw\u0101la"
    ],
    "wof:name":"Tibba Pathananwala",
    "wof:placetype":"locality"
},
  "geometry": {"coordinates":[70.94194,31.06941],"type":"Point"}
}