{
  "type": "Feature",
  "properties": {
    "gn:admin1_code":"4",
    "gn:asciiname":"Tibbiwala",
    "gn:country_code":"PK",
    "gn:dem":151,
    "gn:feature_class":"P",
    "gn:feature_code":"PPL",
    "gn:name":"Tibbiwala",
    "gn:population":0,
    "gn:timezone":"Asia/Karachi",
    "iso:country":"PK",
    "name:und_x_variant":[
        "Tibbaw\u0101la"
    ],
    "wof:name":"Tibbiwala",
    "wof:placetype":"locality"
},
  "geometry": {"coordinates":[72.18127,31.13948],"type":"Point"}
}