{
  "type": "Feature",
  "properties": {
    "gn:admin1_code":"6",
    "gn:asciiname":"Chikhri",
    "gn:country_code":"PK",
    "gn:dem":1962,
    "gn:feature_class":"P",
    "gn:feature_code":"PPL",
    "gn:name":"Chikhri",
    "gn:population":0,
    "gn:timezone":"Asia/Karachi",
    "iso:country":"PK",
    "name:und_x_variant":[
        "Chiari",
        "Chikri"
    ],
    "wof:name":"Chikhri",
    "wof:placetype":"locality"
},
  "geometry": {"coordinates":[74.08315999999998,33.92612],"type":"Point"}
}