{
  "type": "Feature",
  "properties": {
    "gn:admin1_code":"4",
    "gn:asciiname":"Merewali",
    "gn:country_code":"PK",
    "gn:dem":865,
    "gn:feature_class":"P",
    "gn:feature_code":"PPL",
    "gn:name":"Merewali",
    "gn:population":0,
    "gn:timezone":"Asia/Karachi",
    "iso:country":"PK",
    "wof:name":"Merewali",
    "wof:placetype":"locality"
},
  "geometry": {"coordinates":[72.1375,32.62083],"type":"Point"}
}