{
  "type": "Feature",
  "properties": {
    "gn:admin1_code":"02",
    "gn:asciiname":"Goth Shaikh Mangia",
    "gn:country_code":"PK",
    "gn:dem":118,
    "gn:feature_class":"P",
    "gn:feature_code":"PPL",
    "gn:name":"Goth Shaikh Mangia",
    "gn:population":0,
    "gn:timezone":"Asia/Karachi",
    "iso:country":"PK",
    "wof:name":"Goth Shaikh Mangia",
    "wof:placetype":"locality"
},
  "geometry": {"coordinates":[66.30619,26.29392],"type":"Point"}
}