{
  "type": "Feature",
  "properties": {
    "gn:admin1_code":"6.0",
    "gn:asciiname":"Kunal",
    "gn:country_code":"PK",
    "gn:dem":670,
    "gn:feature_class":"P",
    "gn:feature_code":"PPL",
    "gn:name":"Kunal",
    "gn:population":0,
    "gn:timezone":"Asia/Karachi",
    "iso:country":"PK",
    "wof:name":"Kunal",
    "wof:placetype":"locality"
},
  "geometry": {"coordinates":[73.56116,33.9327],"type":"Point"}
}