{
  "type": "Feature",
  "properties": {
    "gn:admin1_code":"3",
    "gn:asciiname":"Thandi Behni",
    "gn:country_code":"PK",
    "gn:dem":820,
    "gn:feature_class":"P",
    "gn:feature_code":"PPL",
    "gn:name":"Thandi Behni",
    "gn:population":0,
    "gn:timezone":"Asia/Karachi",
    "iso:country":"PK",
    "name:und_x_variant":[
        "Thandi Baihni"
    ],
    "wof:name":"Thandi Behni",
    "wof:placetype":"locality"
},
  "geometry": {"coordinates":[73.05885000000001,34.32549],"type":"Point"}
}