{
  "type": "Feature",
  "properties": {
    "gn:admin1_code":"4.0",
    "gn:asciiname":"Chak Atma Ram",
    "gn:country_code":"PK",
    "gn:dem":273,
    "gn:feature_class":"P",
    "gn:feature_code":"PPL",
    "gn:name":"Chak Atma Ram",
    "gn:population":0,
    "gn:timezone":"Asia/Karachi",
    "iso:country":"PK",
    "name:und_x_variant":[
        "Chak Atma"
    ],
    "wof:name":"Chak Atma Ram",
    "wof:placetype":"locality"
},
  "geometry": {"coordinates":[74.83800000000002,32.45402],"type":"Point"}
}