{
  "type": "Feature",
  "properties": {
    "gn:admin1_code":"5",
    "gn:asciiname":"Goth Haji Adam Mashuri",
    "gn:country_code":"PK",
    "gn:dem":51,
    "gn:feature_class":"P",
    "gn:feature_code":"PPL",
    "gn:name":"Goth Haji Adam Mashuri",
    "gn:population":0,
    "gn:timezone":"Asia/Karachi",
    "iso:country":"PK",
    "name:und_x_variant":[
        "H\u0101ji \u0100dam Mash\u016bri"
    ],
    "wof:name":"Goth Haji Adam Mashuri",
    "wof:placetype":"locality"
},
  "geometry": {"coordinates":[68.12411999999999,27.45111],"type":"Point"}
}