{
  "type": "Feature",
  "properties": {
    "gn:admin1_code":"3.0",
    "gn:asciiname":"Utlair Banda",
    "gn:country_code":"PK",
    "gn:dem":888,
    "gn:feature_class":"P",
    "gn:feature_code":"PPL",
    "gn:name":"Utlair Banda",
    "gn:population":0,
    "gn:timezone":"Asia/Karachi",
    "iso:country":"PK",
    "wof:name":"Utlair Banda",
    "wof:placetype":"locality"
},
  "geometry": {"coordinates":[72.80745,34.60544],"type":"Point"}
}