{
  "type": "Feature",
  "properties": {
    "gn:admin1_code":"5.0",
    "gn:asciiname":"Musafir Brahui",
    "gn:country_code":"PK",
    "gn:dem":29,
    "gn:feature_class":"P",
    "gn:feature_code":"PPL",
    "gn:name":"Musafir Brahui",
    "gn:population":0,
    "gn:timezone":"Asia/Karachi",
    "iso:country":"PK",
    "name:und_x_variant":[
        "Musafir Br\u0101hui"
    ],
    "wof:name":"Musafir Brahui",
    "wof:placetype":"locality"
},
  "geometry": {"coordinates":[68.45656,26.04605],"type":"Point"}
}