{
  "type": "Feature",
  "properties": {
    "gn:admin1_code":"04",
    "gn:asciiname":"Chak Two Hundred Seventy-five Gogera Branch",
    "gn:country_code":"PK",
    "gn:dem":184,
    "gn:feature_class":"P",
    "gn:feature_code":"PPL",
    "gn:name":"Chak Two Hundred Seventy-five Gogera Branch",
    "gn:population":0,
    "gn:timezone":"Asia/Karachi",
    "iso:country":"PK",
    "name:und_x_variant":[
        "Madwana",
        "Mado\u0101na",
        "Chak Two Hundred Seventy-five Gogera Branch"
    ],
    "wof:name":"Chak Two Hundred Seventy-five Gogera Branch",
    "wof:placetype":"locality"
},
  "geometry": {"coordinates":[73.31803000000002,31.15296],"type":"Point"}
}