{
  "type": "Feature",
  "properties": {
    "gn:admin1_code":"02",
    "gn:asciiname":"Chatti-i-Chah",
    "gn:country_code":"PK",
    "gn:dem":71,
    "gn:feature_class":"P",
    "gn:feature_code":"PPL",
    "gn:name":"Chatti-i-Chah",
    "gn:population":0,
    "gn:timezone":"Asia/Karachi",
    "iso:country":"PK",
    "wof:name":"Chatti-i-Chah",
    "wof:placetype":"locality"
},
  "geometry": {"coordinates":[63.32222,25.48889],"type":"Point"}
}