{
  "type": "Feature",
  "properties": {
    "gn:admin1_code":"5",
    "gn:asciiname":"Haji Dur Muhammad Rind",
    "gn:country_code":"PK",
    "gn:dem":39,
    "gn:feature_class":"P",
    "gn:feature_code":"PPL",
    "gn:name":"Haji Dur Muhammad Rind",
    "gn:population":0,
    "gn:timezone":"Asia/Karachi",
    "iso:country":"PK",
    "name:und_x_variant":[
        "Wali Muhammad Kh\u0101n Rind"
    ],
    "wof:name":"Haji Dur Muhammad Rind",
    "wof:placetype":"locality"
},
  "geometry": {"coordinates":[68.12979,26.48813],"type":"Point"}
}