{
  "type": "Feature",
  "properties": {
    "gn:admin1_code":"04",
    "gn:asciiname":"Sohawa",
    "gn:country_code":"PK",
    "gn:dem":494,
    "gn:feature_class":"P",
    "gn:feature_code":"PPL",
    "gn:name":"Sohawa",
    "gn:population":0,
    "gn:timezone":"Asia/Karachi",
    "iso:country":"PK",
    "name:fas_x_preferred":[
        "\u0633\u0648\u0647\u0627\u0648\u0647"
    ],
    "name:fra_x_preferred":[
        "Sohawa"
    ],
    "name:pnb_x_preferred":[
        "\u0633\u0648\u06c1\u0627\u0648\u06c1"
    ],
    "name:urd_x_preferred":[
        "\u0633\u0648\u06c1\u0627\u0648\u06c1"
    ],
    "wof:name":"Sohawa",
    "wof:placetype":"locality"
},
  "geometry": {"coordinates":[72.99919,32.84227],"type":"Point"}
}