{
  "type": "Feature",
  "properties": {
    "gn:admin1_code":"01",
    "gn:asciiname":"Hathi Khel",
    "gn:country_code":"PK",
    "gn:dem":1928,
    "gn:feature_class":"P",
    "gn:feature_code":"PPL",
    "gn:name":"Hathi Khel",
    "gn:population":0,
    "gn:timezone":"Asia/Karachi",
    "iso:country":"PK",
    "wof:name":"Hathi Khel",
    "wof:placetype":"locality"
},
  "geometry": {"coordinates":[69.63424999999999,32.48024],"type":"Point"}
}