{
  "type": "Feature",
  "properties": {
    "gn:admin1_code":"5.0",
    "gn:asciiname":"Goth Mewo Khan Mangrio",
    "gn:country_code":"PK",
    "gn:dem":50,
    "gn:feature_class":"P",
    "gn:feature_code":"PPL",
    "gn:name":"Goth Mewo Khan Mangrio",
    "gn:population":0,
    "gn:timezone":"Asia/Karachi",
    "iso:country":"PK",
    "wof:name":"Goth Mewo Khan Mangrio",
    "wof:placetype":"locality"
},
  "geometry": {"coordinates":[68.4808,27.04571],"type":"Point"}
}