{
  "type": "Feature",
  "properties": {
    "gn:admin1_code":"01",
    "gn:asciiname":"Sangra",
    "gn:country_code":"PK",
    "gn:dem":730,
    "gn:feature_class":"P",
    "gn:feature_code":"PPL",
    "gn:name":"Sangra",
    "gn:population":0,
    "gn:timezone":"Asia/Karachi",
    "iso:country":"PK",
    "name:und_x_variant":[
        "Kola"
    ],
    "wof:name":"Sangra",
    "wof:placetype":"locality"
},
  "geometry": {"coordinates":[71.46346,34.59988],"type":"Point"}
}