{
  "type": "Feature",
  "properties": {
    "gn:admin1_code":"5.0",
    "gn:asciiname":"Sher Muhammad Brahui",
    "gn:country_code":"PK",
    "gn:dem":54,
    "gn:feature_class":"P",
    "gn:feature_code":"PPL",
    "gn:name":"Sher Muhammad Brahui",
    "gn:population":0,
    "gn:timezone":"Asia/Karachi",
    "iso:country":"PK",
    "wof:name":"Sher Muhammad Brahui",
    "wof:placetype":"locality"
},
  "geometry": {"coordinates":[68.23850999999999,28.06205],"type":"Point"}
}