{
  "type": "Feature",
  "properties": {
    "gn:admin1_code":"4",
    "gn:asciiname":"Sadiawalai",
    "gn:country_code":"PK",
    "gn:dem":126,
    "gn:feature_class":"P",
    "gn:feature_code":"PPL",
    "gn:name":"Sad\u012baw\u0101la\u012b",
    "gn:population":0,
    "gn:timezone":"Asia/Karachi",
    "iso:country":"PK",
    "wof:name":"Sadiawalai",
    "wof:placetype":"locality"
},
  "geometry": {"coordinates":[71.03749999999999,30.35833],"type":"Point"}
}