{
  "type": "Feature",
  "properties": {
    "gn:admin1_code":"4.0",
    "gn:asciiname":"Banda Sabuwal",
    "gn:country_code":"PK",
    "gn:dem":280,
    "gn:feature_class":"P",
    "gn:feature_code":"PPL",
    "gn:name":"B\u0101nda S\u0101b\u016bw\u0101l",
    "gn:population":0,
    "gn:timezone":"Asia/Karachi",
    "iso:country":"PK",
    "wof:name":"Banda Sabuwal",
    "wof:placetype":"locality"
},
  "geometry": {"coordinates":[71.23333000000002,32.88333],"type":"Point"}
}