{
  "type": "Feature",
  "properties": {
    "gn:admin1_code":"4",
    "gn:asciiname":"Hamidpur",
    "gn:country_code":"PK",
    "gn:dem":226,
    "gn:feature_class":"P",
    "gn:feature_code":"PPL",
    "gn:name":"Hamidpur",
    "gn:population":0,
    "gn:timezone":"Asia/Karachi",
    "iso:country":"PK",
    "wof:name":"Hamidpur",
    "wof:placetype":"locality"
},
  "geometry": {"coordinates":[74.55846,32.02334],"type":"Point"}
}