{
  "type": "Feature",
  "properties": {
    "gn:admin1_code":"02",
    "gn:asciiname":"Retak Chah",
    "gn:country_code":"PK",
    "gn:dem":1388,
    "gn:feature_class":"P",
    "gn:feature_code":"PPL",
    "gn:name":"Retak Chah",
    "gn:population":0,
    "gn:timezone":"Asia/Karachi",
    "iso:country":"PK",
    "wof:name":"Retak Chah",
    "wof:placetype":"locality"
},
  "geometry": {"coordinates":[63.95,29.28333],"type":"Point"}
}