{
  "type": "Feature",
  "properties": {
    "gn:admin1_code":"4.0",
    "gn:asciiname":"Rathanwala",
    "gn:country_code":"PK",
    "gn:dem":181,
    "gn:feature_class":"P",
    "gn:feature_code":"PPL",
    "gn:name":"Rathanwala",
    "gn:population":0,
    "gn:timezone":"Asia/Karachi",
    "iso:country":"PK",
    "name:und_x_variant":[
        "Rathnanw\u0101la"
    ],
    "wof:name":"Rathanwala",
    "wof:placetype":"locality"
},
  "geometry": {"coordinates":[72.96056999999998,31.69019],"type":"Point"}
}