{
  "type": "Feature",
  "properties": {
    "gn:admin1_code":"4",
    "gn:asciiname":"Bhaini Beleywali",
    "gn:country_code":"PK",
    "gn:dem":144,
    "gn:feature_class":"P",
    "gn:feature_code":"PPL",
    "gn:name":"Bhaini Beleywali",
    "gn:population":0,
    "gn:timezone":"Asia/Karachi",
    "iso:country":"PK",
    "wof:name":"Bhaini Beleywali",
    "wof:placetype":"locality"
},
  "geometry": {"coordinates":[72.32222,30.31528],"type":"Point"}
}