{
  "type": "Feature",
  "properties": {
    "gn:country":"PK",
    "gn:fcode":"PPL",
    "gn:population":40083,
    "iso:country":"PK",
    "name:ben_x_preferred":[
        "\u0996\u09c8\u09b0\u09aa\u09c1\u09b0"
    ],
    "name:cat_x_preferred":[
        "Khairpur"
    ],
    "name:ceb_x_preferred":[
        "Khairpur"
    ],
    "name:deu_x_preferred":[
        "Khairpur"
    ],
    "name:eng_x_preferred":[
        "Khairpur"
    ],
    "name:fas_x_preferred":[
        "\u062e\u06cc\u0631\u067e\u0648\u0631"
    ],
    "name:fra_x_preferred":[
        "Khayrpur"
    ],
    "name:glg_x_preferred":[
        "Khairpur"
    ],
    "name:hin_x_preferred":[
        "\u0916\u0948\u0930\u092a\u0941\u0930"
    ],
    "name:ita_x_preferred":[
        "Khairpur"
    ],
    "name:jpn_x_preferred":[
        "\u30ab\u30a4\u30d7\u30fc\u30eb"
    ],
    "name:lit_x_preferred":[
        "Chairp\u016bras"
    ],
    "name:nld_x_preferred":[
        "Khairpur"
    ],
    "name:pnb_x_preferred":[
        "\u062e\u06cc\u0631\u067e\u0648\u0631"
    ],
    "name:pol_x_preferred":[
        "Khairpur"
    ],
    "name:pus_x_preferred":[
        "\u062e\u064a\u0631\u067e\u0648\u0631"
    ],
    "name:rus_x_preferred":[
        "\u0425\u0430\u0439\u0440\u043f\u0443\u0440\u0430"
    ],
    "name:rus_x_variant":[
        "\u0425\u0430\u0439\u0440\u043f\u0443\u0440"
    ],
    "name:snd_x_preferred":[
        "\u062e\u064a\u0631\u067e\u0648\u0631"
    ],
    "name:spa_x_preferred":[
        "Khairpur"
    ],
    "name:srp_x_preferred":[
        "\u0425\u0430\u0458\u0440\u043f\u0443\u0440"
    ],
    "name:swe_x_preferred":[
        "Khairpur"
    ],
    "name:und_x_variant":[
        "Khairpur Daherki"
    ],
    "name:urd_x_preferred":[
        "\u062e\u06cc\u0631\u067e\u0648\u0631"
    ],
    "name:war_x_preferred":[
        "Khairpur"
    ],
    "name:zho_x_preferred":[
        "\u6d77\u723e\u5e03\u723e"
    ],
    "qs:name":"Khairpur",
    "qs:photos_9r":0,
    "qs:photos_sr":0,
    "qs:pop_sr":"7",
    "wd:wordcount":426,
    "wof:name":"Khairpur",
    "wof:placetype":"locality",
    "wof:population":40083
},
  "geometry": {"coordinates":[69.70076,28.06526],"type":"Point"}
}