{
  "type": "Feature",
  "properties": {
    "gn:country":"PK",
    "gn:fcode":"PPL",
    "gn:pop":40083,
    "iso:country":"PK",
    "name:rus_x_preferred":[
        "\u0425\u0430\u0439\u0440\u043f\u0443\u0440\u0430"
    ],
    "name:unk_x_variant":[
        "Khairpur Daherki"
    ],
    "qs:name":"Khairpur",
    "qs:photos_9r":0,
    "qs:photos_sr":0,
    "qs:pop_sr":"7",
    "wd:wordcount":426,
    "wof:name":"Khairpur",
    "wof:placetype":"locality",
    "wof:population":40083
},
  "geometry": {"coordinates":[69.70076,28.06526],"type":"Point"}
}