{
  "type": "Feature",
  "properties": {
    "gn:admin1_code":"5",
    "gn:asciiname":"Goth Mir Ibrahim",
    "gn:country_code":"PK",
    "gn:dem":23,
    "gn:feature_class":"P",
    "gn:feature_code":"PPL",
    "gn:name":"Goth Mir Ibrahim",
    "gn:population":0,
    "gn:timezone":"Asia/Karachi",
    "iso:country":"PK",
    "name:und_x_variant":[
        "M\u012br Ibr\u0101h\u012bm"
    ],
    "wof:name":"Goth Mir Ibrahim",
    "wof:placetype":"locality"
},
  "geometry": {"coordinates":[68.54550999999999,25.61261],"type":"Point"}
}