{
  "type": "Feature",
  "properties": {
    "gn:admin1_code":"6",
    "gn:asciiname":"Akhori",
    "gn:country_code":"PK",
    "gn:dem":1586,
    "gn:feature_class":"P",
    "gn:feature_code":"PPL",
    "gn:name":"Akhori",
    "gn:population":0,
    "gn:timezone":"Asia/Karachi",
    "iso:country":"PK",
    "name:und_x_variant":[
        "Akhari"
    ],
    "wof:name":"Akhori",
    "wof:placetype":"locality"
},
  "geometry": {"coordinates":[74.15156,33.91862],"type":"Point"}
}