{
  "type": "Feature",
  "properties": {
    "gn:admin1_code":"6.0",
    "gn:asciiname":"Chak Qazi",
    "gn:country_code":"PK",
    "gn:dem":260,
    "gn:feature_class":"P",
    "gn:feature_code":"PPL",
    "gn:name":"Chak Qazi",
    "gn:population":0,
    "gn:timezone":"Asia/Karachi",
    "iso:country":"PK",
    "name:und_x_variant":[
        "Chak Q\u0101zi"
    ],
    "wof:name":"Chak Qazi",
    "wof:placetype":"locality"
},
  "geometry": {"coordinates":[73.67544000000002,33.05041],"type":"Point"}
}