{
  "type": "Feature",
  "properties": {
    "gn:admin1_code":"5.0",
    "gn:asciiname":"Ali Nawaz Zardari",
    "gn:country_code":"PK",
    "gn:dem":34,
    "gn:feature_class":"P",
    "gn:feature_code":"PPL",
    "gn:name":"Ali Nawaz Zardari",
    "gn:population":0,
    "gn:timezone":"Asia/Karachi",
    "iso:country":"PK",
    "wof:name":"Ali Nawaz Zardari",
    "wof:placetype":"locality"
},
  "geometry": {"coordinates":[68.32725000000001,26.22694000000001],"type":"Point"}
}