{
  "type": "Feature",
  "properties": {
    "gn:admin1_code":"4.0",
    "gn:asciiname":"Phatli",
    "gn:country_code":"PK",
    "gn:dem":1607,
    "gn:feature_class":"P",
    "gn:feature_code":"PPL",
    "gn:name":"Phatli",
    "gn:population":0,
    "gn:timezone":"Asia/Karachi",
    "iso:country":"PK",
    "name:eng_x_preferred":[
        "Pithli"
    ],
    "wof:name":"Phatli",
    "wof:placetype":"locality"
},
  "geometry": {"coordinates":[73.34649,33.90300999999999],"type":"Point"}
}