{
  "type": "Feature",
  "properties": {
    "gn:admin1_code":"4",
    "gn:asciiname":"Mansowala",
    "gn:country_code":"PK",
    "gn:dem":188,
    "gn:feature_class":"P",
    "gn:feature_code":"PPL",
    "gn:name":"Mansowala",
    "gn:population":0,
    "gn:timezone":"Asia/Karachi",
    "iso:country":"PK",
    "name:und_x_variant":[
        "Mansuw\u0101la"
    ],
    "wof:name":"Mansowala",
    "wof:placetype":"locality"
},
  "geometry": {"coordinates":[74.20992,30.78741],"type":"Point"}
}