{
  "type": "Feature",
  "properties": {
    "gn:admin1_code":"7.0",
    "gn:asciiname":"Mashi",
    "gn:country_code":"PK",
    "gn:dem":1776,
    "gn:feature_class":"P",
    "gn:feature_code":"PPL",
    "gn:name":"Mashi",
    "gn:population":0,
    "gn:timezone":"Asia/Karachi",
    "iso:country":"PK",
    "name:und_x_variant":[
        "M\u0101shai"
    ],
    "wof:name":"Mashi",
    "wof:placetype":"locality"
},
  "geometry": {"coordinates":[74.01791,35.37154],"type":"Point"}
}