{
  "type": "Feature",
  "properties": {
    "gn:admin1_code":"3.0",
    "gn:asciiname":"Karwali",
    "gn:country_code":"PK",
    "gn:dem":979,
    "gn:feature_class":"P",
    "gn:feature_code":"PPL",
    "gn:name":"Karwali",
    "gn:population":0,
    "gn:timezone":"Asia/Karachi",
    "iso:country":"PK",
    "name:eng_x_preferred":[
        "Karwali"
    ],
    "wof:name":"Karwali",
    "wof:placetype":"locality"
},
  "geometry": {"coordinates":[73.01281999999998,33.77827],"type":"Point"}
}