{
  "type": "Feature",
  "properties": {
    "gn:admin1_code":"2.0",
    "gn:asciiname":"Shorag Gaz",
    "gn:country_code":"PK",
    "gn:dem":1131,
    "gn:feature_class":"P",
    "gn:feature_code":"PPL",
    "gn:name":"Shorag Gaz",
    "gn:population":0,
    "gn:timezone":"Asia/Karachi",
    "iso:country":"PK",
    "wof:name":"Shorag Gaz",
    "wof:placetype":"locality"
},
  "geometry": {"coordinates":[63.54022,29.2154],"type":"Point"}
}