{
  "type": "Feature",
  "properties": {
    "gn:admin1_code":"4.0",
    "gn:asciiname":"Bala Chani di Basti",
    "gn:country_code":"PK",
    "gn:dem":87,
    "gn:feature_class":"P",
    "gn:feature_code":"PPL",
    "gn:name":"Bala Chani di Basti",
    "gn:population":0,
    "gn:timezone":"Asia/Karachi",
    "iso:country":"PK",
    "name:und_x_variant":[
        "Basti Sarg\u0101ni"
    ],
    "wof:name":"Bala Chani di Basti",
    "wof:placetype":"locality"
},
  "geometry": {"coordinates":[70.10424,28.82213],"type":"Point"}
}