{
  "type": "Feature",
  "properties": {
    "gn:admin1_code":"2.0",
    "gn:asciiname":"Ozhan",
    "gn:country_code":"PK",
    "gn:dem":1713,
    "gn:feature_class":"P",
    "gn:feature_code":"PPL",
    "gn:name":"Ozhan",
    "gn:population":0,
    "gn:timezone":"Asia/Karachi",
    "iso:country":"PK",
    "wof:name":"Ozhan",
    "wof:placetype":"locality"
},
  "geometry": {"coordinates":[69.79396,31.51913],"type":"Point"}
}