{
  "type": "Feature",
  "properties": {
    "gn:admin1_code":"1.0",
    "gn:asciiname":"Kanre Kuna",
    "gn:country_code":"PK",
    "gn:dem":1174,
    "gn:feature_class":"P",
    "gn:feature_code":"PPL",
    "gn:name":"Kanre Kuna",
    "gn:population":0,
    "gn:timezone":"Asia/Karachi",
    "iso:country":"PK",
    "name:und_x_variant":[
        "K\u0101nre Kuna"
    ],
    "wof:name":"Kanre Kuna",
    "wof:placetype":"locality"
},
  "geometry": {"coordinates":[70.91143000000002,33.6082],"type":"Point"}
}