{
  "type": "Feature",
  "properties": {
    "gn:admin1_code":"4",
    "gn:asciiname":"Gasora",
    "gn:country_code":"PK",
    "gn:dem":163,
    "gn:feature_class":"P",
    "gn:feature_code":"PPL",
    "gn:name":"Gasora",
    "gn:population":0,
    "gn:timezone":"Asia/Karachi",
    "iso:country":"PK",
    "name:und_x_variant":[
        "Basti Gasora",
        "Gasora"
    ],
    "wof:name":"Gasora",
    "wof:placetype":"locality"
},
  "geometry": {"coordinates":[70.96271999999998,31.50079],"type":"Point"}
}