{
  "type": "Feature",
  "properties": {
    "gn:admin1_code":"04",
    "gn:asciiname":"Chak Three Hundred Fifty-three",
    "gn:country_code":"PK",
    "gn:dem":171,
    "gn:feature_class":"P",
    "gn:feature_code":"PPL",
    "gn:name":"Chak Three Hundred Fifty-three",
    "gn:population":0,
    "gn:timezone":"Asia/Karachi",
    "iso:country":"PK",
    "name:und_x_variant":[
        "Mehdiabad",
        "Mehdi",
        "Chak Number Three Hundred Fifty-Three",
        "Chak Three Hundred Fifty-three",
        "Mehri"
    ],
    "wof:name":"Chak Three Hundred Fifty-three",
    "wof:placetype":"locality"
},
  "geometry": {"coordinates":[72.63224,31.20737],"type":"Point"}
}