{
  "type": "Feature",
  "properties": {
    "gn:admin1_code":"4.0",
    "gn:asciiname":"Dhok Maira",
    "gn:country_code":"PK",
    "gn:dem":488,
    "gn:feature_class":"P",
    "gn:feature_code":"PPL",
    "gn:name":"Dhok Maira",
    "gn:population":0,
    "gn:timezone":"Asia/Karachi",
    "iso:country":"PK",
    "wof:name":"Dhok Maira",
    "wof:placetype":"locality"
},
  "geometry": {"coordinates":[73.03985,33.54056],"type":"Point"}
}