{
  "type": "Feature",
  "properties": {
    "gn:admin1_code":"4",
    "gn:asciiname":"Hansewala",
    "gn:country_code":"PK",
    "gn:dem":123,
    "gn:feature_class":"P",
    "gn:feature_code":"PPL",
    "gn:name":"Hansewala",
    "gn:population":0,
    "gn:timezone":"Asia/Karachi",
    "iso:country":"PK",
    "name:und_x_variant":[
        "H\u0101nsi\u0101nw\u0101la"
    ],
    "wof:name":"Hansewala",
    "wof:placetype":"locality"
},
  "geometry": {"coordinates":[71.88245000000001,29.71981],"type":"Point"}
}