{
  "type": "Feature",
  "properties": {
    "gn:admin1_code":"4",
    "gn:asciiname":"Masuwala",
    "gn:country_code":"PK",
    "gn:dem":135,
    "gn:feature_class":"P",
    "gn:feature_code":"PPL",
    "gn:name":"Masuwala",
    "gn:population":0,
    "gn:timezone":"Asia/Karachi",
    "iso:country":"PK",
    "name:und_x_variant":[
        "Mass\u016bw\u0101la"
    ],
    "wof:name":"Masuwala",
    "wof:placetype":"locality"
},
  "geometry": {"coordinates":[71.17215,30.51264],"type":"Point"}
}