{
  "type": "Feature",
  "properties": {
    "gn:admin1_code":"6",
    "gn:asciiname":"Bindian",
    "gn:country_code":"PK",
    "gn:dem":811,
    "gn:feature_class":"P",
    "gn:feature_code":"PPL",
    "gn:name":"Bindian",
    "gn:population":0,
    "gn:timezone":"Asia/Karachi",
    "iso:country":"PK",
    "wof:name":"Bindian",
    "wof:placetype":"locality"
},
  "geometry": {"coordinates":[74.06809,33.34049],"type":"Point"}
}