{
  "type": "Feature",
  "properties": {
    "gn:admin1_code":"5",
    "gn:asciiname":"Bhanbhra",
    "gn:country_code":"PK",
    "gn:dem":44,
    "gn:feature_class":"P",
    "gn:feature_code":"PPL",
    "gn:name":"Bhanbhra",
    "gn:population":0,
    "gn:timezone":"Asia/Karachi",
    "iso:country":"PK",
    "name:und_x_variant":[
        "Bhanbhro"
    ],
    "wof:name":"Bhanbhra",
    "wof:placetype":"locality"
},
  "geometry": {"coordinates":[68.13613000000001,26.89196],"type":"Point"}
}