{
  "type": "Feature",
  "properties": {
    "gn:admin1_code":"4",
    "gn:asciiname":"Kirarwala",
    "gn:country_code":"PK",
    "gn:dem":124,
    "gn:feature_class":"P",
    "gn:feature_code":"PPL",
    "gn:name":"Kirarwala",
    "gn:population":0,
    "gn:timezone":"Asia/Karachi",
    "iso:country":"PK",
    "name:eng_x_preferred":[
        "Kirarwala"
    ],
    "wof:name":"Kirarwala",
    "wof:placetype":"locality"
},
  "geometry": {"coordinates":[70.99361,30.13895],"type":"Point"}
}