{
  "type": "Feature",
  "properties": {
    "gn:admin1_code":"3",
    "gn:asciiname":"Takhtaband",
    "gn:country_code":"PK",
    "gn:dem":1996,
    "gn:feature_class":"P",
    "gn:feature_code":"PPL",
    "gn:name":"Takhtaband",
    "gn:population":0,
    "gn:timezone":"Asia/Karachi",
    "iso:country":"PK",
    "wof:name":"Takhtaband",
    "wof:placetype":"locality"
},
  "geometry": {"coordinates":[72.56598000000002,35.18344],"type":"Point"}
}