{
  "type": "Feature",
  "properties": {
    "gn:admin1_code":"3.0",
    "gn:asciiname":"Banda Jangli Khel",
    "gn:country_code":"PK",
    "gn:dem":381,
    "gn:feature_class":"P",
    "gn:feature_code":"PPL",
    "gn:name":"Banda Jangli Khel",
    "gn:population":0,
    "gn:timezone":"Asia/Karachi",
    "iso:country":"PK",
    "name:und_x_variant":[
        "B\u0101nda Jangi Kh\u0101n",
        "Banda Jangli Khel"
    ],
    "wof:name":"Banda Jangli Khel",
    "wof:placetype":"locality"
},
  "geometry": {"coordinates":[70.94665999999999,32.88102],"type":"Point"}
}