{
  "type": "Feature",
  "properties": {
    "gn:admin1_code":"2.0",
    "gn:asciiname":"Mir Mohtaj",
    "gn:country_code":"PK",
    "gn:dem":511,
    "gn:feature_class":"P",
    "gn:feature_code":"PPL",
    "gn:name":"Mir Mohtaj",
    "gn:population":0,
    "gn:timezone":"Asia/Karachi",
    "iso:country":"PK",
    "wof:name":"Mir Mohtaj",
    "wof:placetype":"locality"
},
  "geometry": {"coordinates":[63.28619000000001,28.06942],"type":"Point"}
}