{
  "type": "Feature",
  "properties": {
    "gn:admin1_code":"4.0",
    "gn:asciiname":"Bagian",
    "gn:country_code":"PK",
    "gn:dem":187,
    "gn:feature_class":"P",
    "gn:feature_code":"PPL",
    "gn:name":"Bagian",
    "gn:population":0,
    "gn:timezone":"Asia/Karachi",
    "iso:country":"PK",
    "name:und_x_variant":[
        "Bagr\u0101n"
    ],
    "wof:name":"Bagian",
    "wof:placetype":"locality"
},
  "geometry": {"coordinates":[72.56993,32.42537],"type":"Point"}
}