{
  "type": "Feature",
  "properties": {
    "gn:admin1_code":"5.0",
    "gn:asciiname":"Mir Hamidullah Buledi",
    "gn:country_code":"PK",
    "gn:dem":56,
    "gn:feature_class":"P",
    "gn:feature_code":"PPL",
    "gn:name":"Mir Hamidullah Buledi",
    "gn:population":0,
    "gn:timezone":"Asia/Karachi",
    "iso:country":"PK",
    "wof:name":"Mir Hamidullah Buledi",
    "wof:placetype":"locality"
},
  "geometry": {"coordinates":[68.09536999999999,28.14569],"type":"Point"}
}