{
  "type": "Feature",
  "properties": {
    "gn:admin1_code":"5.0",
    "gn:asciiname":"Napran",
    "gn:country_code":"PK",
    "gn:dem":63,
    "gn:feature_class":"P",
    "gn:feature_code":"PPL",
    "gn:name":"Napran",
    "gn:population":0,
    "gn:timezone":"Asia/Karachi",
    "iso:country":"PK",
    "wof:name":"Napran",
    "wof:placetype":"locality"
},
  "geometry": {"coordinates":[69.07143000000001,27.62223],"type":"Point"}
}