{
  "type": "Feature",
  "properties": {
    "gn:admin1_code":"5.0",
    "gn:asciiname":"Goth Zangeja",
    "gn:country_code":"PK",
    "gn:dem":54,
    "gn:feature_class":"P",
    "gn:feature_code":"PPL",
    "gn:name":"Goth Zangeja",
    "gn:population":0,
    "gn:timezone":"Asia/Karachi",
    "iso:country":"PK",
    "name:und_x_variant":[
        "Zangeja",
        "Juneja",
        "Goth Zangeja"
    ],
    "wof:name":"Goth Zangeja",
    "wof:placetype":"locality"
},
  "geometry": {"coordinates":[68.26842000000001,27.77047],"type":"Point"}
}