{
  "type": "Feature",
  "properties": {
    "gn:admin1_code":"7.0",
    "gn:asciiname":"Balti Khar",
    "gn:country_code":"PK",
    "gn:dem":3194,
    "gn:feature_class":"P",
    "gn:feature_code":"PPL",
    "gn:name":"Balti Khar",
    "gn:population":0,
    "gn:timezone":"Asia/Karachi",
    "iso:country":"PK",
    "name:und_x_variant":[
        "Balthi Khar"
    ],
    "wof:name":"Balti Khar",
    "wof:placetype":"locality"
},
  "geometry": {"coordinates":[75.84205,35.10897],"type":"Point"}
}