{
  "type": "Feature",
  "properties": {
    "gn:admin1_code":"4",
    "gn:asciiname":"Kach Piran",
    "gn:country_code":"PK",
    "gn:dem":109,
    "gn:feature_class":"P",
    "gn:feature_code":"PPL",
    "gn:name":"Kach Piran",
    "gn:population":0,
    "gn:timezone":"Asia/Karachi",
    "iso:country":"PK",
    "name:und_x_variant":[
        "Kech P\u012bran"
    ],
    "wof:name":"Kach Piran",
    "wof:placetype":"locality"
},
  "geometry": {"coordinates":[71.09949,29.49442],"type":"Point"}
}