{
  "type": "Feature",
  "properties": {
    "gn:admin1_code":"04",
    "gn:asciiname":"Seowal",
    "gn:country_code":"PK",
    "gn:dem":259,
    "gn:feature_class":"P",
    "gn:feature_code":"PPL",
    "gn:name":"Seowal",
    "gn:population":0,
    "gn:timezone":"Asia/Karachi",
    "iso:country":"PK",
    "name:fas_x_preferred":[
        "\u0633\u0626\u0648\u0648\u0627\u0644"
    ],
    "name:pan_x_preferred":[
        "\u0a38\u0a40\u0a13\u0a35\u0a3e\u0a32"
    ],
    "wof:name":"Seowal",
    "wof:placetype":"locality"
},
  "geometry": {"coordinates":[74.78115,32.31983],"type":"Point"}
}