{
  "type": "Feature",
  "properties": {
    "gn:admin1_code":"4",
    "gn:asciiname":"Goth Tindo Tarkhan",
    "gn:country_code":"PK",
    "gn:dem":78,
    "gn:feature_class":"P",
    "gn:feature_code":"PPL",
    "gn:name":"Goth Tindo Tarkhan",
    "gn:population":0,
    "gn:timezone":"Asia/Karachi",
    "iso:country":"PK",
    "wof:name":"Goth Tindo Tarkhan",
    "wof:placetype":"locality"
},
  "geometry": {"coordinates":[69.69258000000001,28.46811],"type":"Point"}
}