{
  "type": "Feature",
  "properties": {
    "gn:admin1_code":"5",
    "gn:asciiname":"Goth Murid Rind",
    "gn:country_code":"PK",
    "gn:dem":24,
    "gn:feature_class":"P",
    "gn:feature_code":"PPL",
    "gn:name":"Goth Murid Rind",
    "gn:population":0,
    "gn:timezone":"Asia/Karachi",
    "iso:country":"PK",
    "name:und_x_variant":[
        "Mur\u012bd Rind"
    ],
    "wof:name":"Goth Murid Rind",
    "wof:placetype":"locality"
},
  "geometry": {"coordinates":[68.83954,25.71958],"type":"Point"}
}