{
  "type": "Feature",
  "properties": {
    "gn:admin1_code":"4",
    "gn:asciiname":"Dhok Mattian",
    "gn:country_code":"PK",
    "gn:dem":346,
    "gn:feature_class":"P",
    "gn:feature_code":"PPL",
    "gn:name":"Dhok Mattian",
    "gn:population":0,
    "gn:timezone":"Asia/Karachi",
    "iso:country":"PK",
    "name:und_x_variant":[
        "Dhok Maitan"
    ],
    "wof:name":"Dhok Mattian",
    "wof:placetype":"locality"
},
  "geometry": {"coordinates":[73.37251999999999,32.95185],"type":"Point"}
}