{
  "type": "Feature",
  "properties": {
    "gn:admin1_code":"7.0",
    "gn:asciiname":"Hurkus",
    "gn:country_code":"PK",
    "gn:dem":2466,
    "gn:feature_class":"P",
    "gn:feature_code":"PPL",
    "gn:name":"Hurkus",
    "gn:population":0,
    "gn:timezone":"Asia/Karachi",
    "iso:country":"PK",
    "wof:name":"Hurkus",
    "wof:placetype":"locality"
},
  "geometry": {"coordinates":[74.46368000000002,35.77622],"type":"Point"}
}