{
  "type": "Feature",
  "properties": {
    "gn:admin1_code":"03",
    "gn:asciiname":"Gulzari Khel",
    "gn:country_code":"PK",
    "gn:dem":382,
    "gn:feature_class":"P",
    "gn:feature_code":"PPL",
    "gn:name":"Gulzari Khel",
    "gn:population":0,
    "gn:timezone":"Asia/Karachi",
    "iso:country":"PK",
    "name:und_x_variant":[
        "Gulzari"
    ],
    "wof:name":"Gulzari Khel",
    "wof:placetype":"locality"
},
  "geometry": {"coordinates":[70.52878,32.61312],"type":"Point"}
}