{
  "type": "Feature",
  "properties": {
    "gn:admin1_code":"4.0",
    "gn:asciiname":"Barazai",
    "gn:country_code":"PK",
    "gn:dem":331,
    "gn:feature_class":"P",
    "gn:feature_code":"PPL",
    "gn:name":"Barazai",
    "gn:population":0,
    "gn:timezone":"Asia/Karachi",
    "iso:country":"PK",
    "name:fas_x_preferred":[
        "\u0628\u0631\u0627\u0632\u0627\u06cc"
    ],
    "name:pnb_x_preferred":[
        "\u0628\u0627\u0691\u0627\u0632\u0626\u06cc"
    ],
    "wof:name":"Barazai",
    "wof:placetype":"locality"
},
  "geometry": {"coordinates":[72.54245999999998,33.91887],"type":"Point"}
}