{
  "type": "Feature",
  "properties": {
    "gn:admin1_code":"3.0",
    "gn:asciiname":"Badu",
    "gn:country_code":"PK",
    "gn:dem":604,
    "gn:feature_class":"P",
    "gn:feature_code":"PPL",
    "gn:name":"Badu",
    "gn:population":0,
    "gn:timezone":"Asia/Karachi",
    "iso:country":"PK",
    "name:und_x_variant":[
        "B\u0101dho"
    ],
    "wof:name":"Badu",
    "wof:placetype":"locality"
},
  "geometry": {"coordinates":[72.82737,34.05475],"type":"Point"}
}