{
  "type": "Feature",
  "properties": {
    "gn:admin1_code":"4.0",
    "gn:asciiname":"Basti Khan Mand",
    "gn:country_code":"PK",
    "gn:dem":95,
    "gn:feature_class":"P",
    "gn:feature_code":"PPL",
    "gn:name":"Basti Khan Mand",
    "gn:population":0,
    "gn:timezone":"Asia/Karachi",
    "iso:country":"PK",
    "wof:name":"Basti Khan Mand",
    "wof:placetype":"locality"
},
  "geometry": {"coordinates":[70.66438000000002,29.14376],"type":"Point"}
}