{
  "type": "Feature",
  "properties": {
    "gn:admin1_code":"4",
    "gn:asciiname":"Kotla Ran",
    "gn:country_code":"PK",
    "gn:dem":95,
    "gn:feature_class":"P",
    "gn:feature_code":"PPL",
    "gn:name":"Kotla Ran",
    "gn:population":0,
    "gn:timezone":"Asia/Karachi",
    "iso:country":"PK",
    "name:und_x_variant":[
        "Kotla R\u0101j Wal\u012bhan"
    ],
    "wof:name":"Kotla Ran",
    "wof:placetype":"locality"
},
  "geometry": {"coordinates":[70.83251,28.86404000000001],"type":"Point"}
}