{
  "type": "Feature",
  "properties": {
    "gn:admin1_code":"4.0",
    "gn:asciiname":"Mud Mithwan",
    "gn:country_code":"PK",
    "gn:dem":318,
    "gn:feature_class":"P",
    "gn:feature_code":"PPL",
    "gn:name":"Mud Mithwan",
    "gn:population":0,
    "gn:timezone":"Asia/Karachi",
    "iso:country":"PK",
    "wof:name":"Mud Mithwan",
    "wof:placetype":"locality"
},
  "geometry": {"coordinates":[70.40876,31.06172],"type":"Point"}
}