{
  "type": "Feature",
  "properties": {
    "gn:admin1_code":"3.0",
    "gn:asciiname":"Aloch",
    "gn:country_code":"PK",
    "gn:dem":1068,
    "gn:feature_class":"P",
    "gn:feature_code":"PPL",
    "gn:name":"Aloch",
    "gn:population":0,
    "gn:timezone":"Asia/Karachi",
    "iso:country":"PK",
    "wof:name":"Aloch",
    "wof:placetype":"locality"
},
  "geometry": {"coordinates":[72.68424,34.73911],"type":"Point"}
}