{
  "type": "Feature",
  "properties": {
    "gn:admin1_code":"3.0",
    "gn:asciiname":"Aloch",
    "gn:country_code":"PK",
    "gn:dem":1068,
    "gn:feature_class":"P",
    "gn:feature_code":"PPL",
    "gn:name":"Aloch",
    "gn:population":0,
    "gn:timezone":"Asia/Karachi",
    "iso:country":"PK",
    "name:fas_x_preferred":[
        "\u0627\u0644\u0627\u0686"
    ],
    "name:urd_x_preferred":[
        "\u0622\u0644\u0648\u0686"
    ],
    "wof:name":"Aloch",
    "wof:placetype":"locality"
},
  "geometry": {"coordinates":[72.68424,34.73911],"type":"Point"}
}