{
  "type": "Feature",
  "properties": {
    "gn:admin1_code":"04",
    "gn:asciiname":"Tegh Bahadurpur",
    "gn:cc2":"PK",
    "gn:country_code":"PK",
    "gn:dem":168,
    "gn:feature_class":"P",
    "gn:feature_code":"PPL",
    "gn:name":"Tegh Bah\u0101durpur",
    "gn:population":0,
    "gn:timezone":"Asia/Karachi",
    "iso:country":"PK",
    "name:und_x_variant":[
        "Tegh Bah\u0101darpur",
        "Tegh Bah\u0101durpur"
    ],
    "wof:name":"Tegh Bahadurpur",
    "wof:placetype":"locality"
},
  "geometry": {"coordinates":[72.66667,31.21667],"type":"Point"}
}