{
  "type": "Feature",
  "properties": {
    "gn:admin1_code":"1.0",
    "gn:asciiname":"Chadnar Kalle",
    "gn:country_code":"PK",
    "gn:dem":413,
    "gn:feature_class":"P",
    "gn:feature_code":"PPL",
    "gn:name":"Chadnar Kalle",
    "gn:population":0,
    "gn:timezone":"Asia/Karachi",
    "iso:country":"PK",
    "name:und_x_variant":[
        "Umr\u0101n Kili",
        "Chandan Kili",
        "Chadnar Kalle"
    ],
    "wof:name":"Chadnar Kalle",
    "wof:placetype":"locality"
},
  "geometry": {"coordinates":[70.41557,32.46669],"type":"Point"}
}