{
  "type": "Feature",
  "properties": {
    "gn:admin1_code":"4",
    "gn:asciiname":"Basti Shaikh Sulaiman",
    "gn:country_code":"PK",
    "gn:dem":78,
    "gn:feature_class":"P",
    "gn:feature_code":"PPL",
    "gn:name":"Basti Shaikh Sulaiman",
    "gn:population":0,
    "gn:timezone":"Asia/Karachi",
    "iso:country":"PK",
    "name:und_x_variant":[
        "Shaikh"
    ],
    "wof:name":"Basti Shaikh Sulaiman",
    "wof:placetype":"locality"
},
  "geometry": {"coordinates":[69.99006999999999,28.33865],"type":"Point"}
}