{
  "type": "Feature",
  "properties": {
    "gn:admin1_code":"5",
    "gn:asciiname":"Nawab Muhammad Husain Khan",
    "gn:country_code":"PK",
    "gn:dem":18,
    "gn:feature_class":"P",
    "gn:feature_code":"PPL",
    "gn:name":"Naw\u0101b Muhammad Husain Kh\u0101n",
    "gn:population":0,
    "gn:timezone":"Asia/Karachi",
    "iso:country":"PK",
    "wof:name":"Nawab Muhammad Husain Khan",
    "wof:placetype":"locality"
},
  "geometry": {"coordinates":[68.68472,25.2125],"type":"Point"}
}