{
  "type": "Feature",
  "properties": {
    "gn:admin1_code":"2.0",
    "gn:asciiname":"Tutiani",
    "gn:country_code":"PK",
    "gn:dem":1559,
    "gn:feature_class":"P",
    "gn:feature_code":"PPL",
    "gn:name":"Tutiani",
    "gn:population":0,
    "gn:timezone":"Asia/Karachi",
    "iso:country":"PK",
    "wof:name":"Tutiani",
    "wof:placetype":"locality"
},
  "geometry": {"coordinates":[69.67746,30.17775],"type":"Point"}
}