{
  "type": "Feature",
  "properties": {
    "gn:admin1_code":"6",
    "gn:asciiname":"Chinat",
    "gn:country_code":"PK",
    "gn:dem":2907,
    "gn:feature_class":"P",
    "gn:feature_code":"PPL",
    "gn:name":"Chinat",
    "gn:population":0,
    "gn:timezone":"Asia/Karachi",
    "iso:country":"PK",
    "name:und_x_variant":[
        "Chanat",
        "Chin\u0101t"
    ],
    "wof:name":"Chinat",
    "wof:placetype":"locality"
},
  "geometry": {"coordinates":[74.08113,34.74119],"type":"Point"}
}