{
  "type": "Feature",
  "properties": {
    "gn:admin1_code":"4.0",
    "gn:asciiname":"Chak Two Hundred Nineteen Rakh Branch",
    "gn:country_code":"PK",
    "gn:dem":181,
    "gn:feature_class":"P",
    "gn:feature_code":"PPL",
    "gn:name":"Chak Two Hundred Nineteen Rakh Branch",
    "gn:population":0,
    "gn:timezone":"Asia/Karachi",
    "iso:country":"PK",
    "name:und_x_variant":[
        "Malwidanw\u0101la",
        "Chak Two Hundred Nineteen RB",
        "Chak Two Hundred Nineteen Rakh Branch",
        "Malwi\u0101nw\u0101la"
    ],
    "wof:name":"Chak Two Hundred Nineteen Rakh Branch",
    "wof:placetype":"locality"
},
  "geometry": {"coordinates":[73.01109,31.41524],"type":"Point"}
}