{
  "type": "Feature",
  "properties": {
    "gn:admin1_code":"2",
    "gn:asciiname":"Sanglun",
    "gn:country_code":"PK",
    "gn:dem":2129,
    "gn:feature_class":"P",
    "gn:feature_code":"PPL",
    "gn:name":"Sanglun",
    "gn:population":0,
    "gn:timezone":"Asia/Karachi",
    "iso:country":"PK",
    "name:rus_x_preferred":[
        "\u0421\u0430\u043d\u0433\u043b\u0443\u043d"
    ],
    "wof:name":"Sanglun",
    "wof:placetype":"locality"
},
  "geometry": {"coordinates":[67.39224,31.20229],"type":"Point"}
}