{
  "type": "Feature",
  "properties": {
    "gn:admin1_code":"5.0",
    "gn:asciiname":"Rais Umar Khan Sumro",
    "gn:country_code":"PK",
    "gn:dem":5,
    "gn:feature_class":"P",
    "gn:feature_code":"PPL",
    "gn:name":"Rais Umar Khan Sumro",
    "gn:population":0,
    "gn:timezone":"Asia/Karachi",
    "iso:country":"PK",
    "name:und_x_variant":[
        "Ra\u012bs Umar Kh\u0101n S\u016bmro"
    ],
    "wof:name":"Rais Umar Khan Sumro",
    "wof:placetype":"locality"
},
  "geometry": {"coordinates":[68.09050000000001,24.2768],"type":"Point"}
}