{
  "type": "Feature",
  "properties": {
    "gn:admin1_code":"4.0",
    "gn:asciiname":"Jhok Mangur",
    "gn:country_code":"PK",
    "gn:dem":179,
    "gn:feature_class":"P",
    "gn:feature_code":"PPL",
    "gn:name":"Jhok Mangur",
    "gn:population":0,
    "gn:timezone":"Asia/Karachi",
    "iso:country":"PK",
    "name:und_x_variant":[
        "Jhok Manghur"
    ],
    "wof:name":"Jhok Mangur",
    "wof:placetype":"locality"
},
  "geometry": {"coordinates":[72.35426,32.27439],"type":"Point"}
}