{
  "type": "Feature",
  "properties": {
    "gn:admin1_code":"5",
    "gn:asciiname":"Dubi",
    "gn:country_code":"PK",
    "gn:dem":47,
    "gn:feature_class":"P",
    "gn:feature_code":"PPL",
    "gn:name":"Dubi",
    "gn:population":0,
    "gn:timezone":"Asia/Karachi",
    "iso:country":"PK",
    "name:und_x_variant":[
        "Dabi"
    ],
    "wof:name":"Dubi",
    "wof:placetype":"locality"
},
  "geometry": {"coordinates":[67.88245999999999,26.98245],"type":"Point"}
}