{
  "type": "Feature",
  "properties": {
    "gn:admin1_code":"4.0",
    "gn:asciiname":"Chak Ghullah",
    "gn:country_code":"PK",
    "gn:dem":191,
    "gn:elevation":"90.0",
    "gn:feature_class":"P",
    "gn:feature_code":"PPLF",
    "gn:name":"Chak Ghullah",
    "gn:population":0,
    "gn:timezone":"Asia/Karachi",
    "iso:country":"PK",
    "wof:name":"Chak Ghullah",
    "wof:placetype":"locality"
},
  "geometry": {"coordinates":[73.26047,31.90205],"type":"Point"}
}