{
  "type": "Feature",
  "properties": {
    "gn:admin1_code":"03",
    "gn:asciiname":"Nahki Daudazai",
    "gn:country_code":"PK",
    "gn:dem":307,
    "gn:feature_class":"P",
    "gn:feature_code":"PPL",
    "gn:name":"Nahki Daudazai",
    "gn:population":0,
    "gn:timezone":"Asia/Karachi",
    "iso:country":"PK",
    "name:eng_x_preferred":[
        "Nahkai"
    ],
    "name:und_x_variant":[
        "Nahakki",
        "Nahaqi",
        "Nahki Daudazai"
    ],
    "wof:name":"Nahki Daudazai",
    "wof:placetype":"locality"
},
  "geometry": {"coordinates":[71.61506999999997,34.10303],"type":"Point"}
}