{
  "type": "Feature",
  "properties": {
    "gn:admin1_code":"5.0",
    "gn:asciiname":"Haji Khair Muhammad Laghari",
    "gn:country_code":"PK",
    "gn:dem":70,
    "gn:feature_class":"P",
    "gn:feature_code":"PPL",
    "gn:name":"Haji Khair Muhammad Laghari",
    "gn:population":0,
    "gn:timezone":"Asia/Karachi",
    "iso:country":"PK",
    "wof:name":"Haji Khair Muhammad Laghari",
    "wof:placetype":"locality"
},
  "geometry": {"coordinates":[69.74382,27.96996],"type":"Point"}
}