{
  "type": "Feature",
  "properties": {
    "gn:admin1_code":"4",
    "gn:asciiname":"Chak One Hundred Fifteen Jhang Branch",
    "gn:country_code":"PK",
    "gn:dem":187,
    "gn:feature_class":"P",
    "gn:feature_code":"PPL",
    "gn:name":"Chak One Hundred Fifteen Jhang Branch",
    "gn:population":0,
    "gn:timezone":"Asia/Karachi",
    "iso:country":"PK",
    "name:und_x_variant":[
        "Chak One Hundred Fifteen",
        "Di\u0101lgarh",
        "Chak One Hundred Fifteen Jhang Branch"
    ],
    "wof:name":"Chak One Hundred Fifteen Jhang Branch",
    "wof:placetype":"locality"
},
  "geometry": {"coordinates":[73.11239999999999,31.55723],"type":"Point"}
}