{
  "type": "Feature",
  "properties": {
    "gn:admin1_code":"4.0",
    "gn:asciiname":"Chak Islamabad",
    "gn:country_code":"PK",
    "gn:dem":191,
    "gn:feature_class":"P",
    "gn:feature_code":"PPL",
    "gn:name":"Chak Islamabad",
    "gn:population":0,
    "gn:timezone":"Asia/Karachi",
    "iso:country":"PK",
    "name:und_x_variant":[
        "Islamabad",
        "Chak Islamabad"
    ],
    "wof:name":"Chak Islamabad",
    "wof:placetype":"locality"
},
  "geometry": {"coordinates":[71.91888,32.27137],"type":"Point"}
}