{
  "type": "Feature",
  "properties": {
    "gn:admin1_code":"2.0",
    "gn:asciiname":"Kili Katir",
    "gn:country_code":"PK",
    "gn:dem":1556,
    "gn:feature_class":"P",
    "gn:feature_code":"PPL",
    "gn:name":"Kili Katir",
    "gn:population":0,
    "gn:timezone":"Asia/Karachi",
    "iso:country":"PK",
    "name:und_x_variant":[
        "Kati",
        "Katir",
        "Kili Katir"
    ],
    "wof:name":"Kili Katir",
    "wof:placetype":"locality"
},
  "geometry": {"coordinates":[66.92169,30.34196],"type":"Point"}
}