{
  "type": "Feature",
  "properties": {
    "gn:admin1_code":"4.0",
    "gn:asciiname":"Jalilpur",
    "gn:country_code":"PK",
    "gn:dem":234,
    "gn:feature_class":"P",
    "gn:feature_code":"PPL",
    "gn:name":"Jalilpur",
    "gn:population":0,
    "gn:timezone":"Asia/Karachi",
    "iso:country":"PK",
    "name:und_x_variant":[
        "Chak Jalilpur",
        "Jalilpur"
    ],
    "wof:name":"Jalilpur",
    "wof:placetype":"locality"
},
  "geometry": {"coordinates":[73.72131999999998,32.87807],"type":"Point"}
}