{
  "type": "Feature",
  "properties": {
    "gn:admin1_code":"3.0",
    "gn:asciiname":"Ghazgai Dharai",
    "gn:country_code":"PK",
    "gn:dem":339,
    "gn:feature_class":"P",
    "gn:feature_code":"PPL",
    "gn:name":"Ghazgai Dharai",
    "gn:population":0,
    "gn:timezone":"Asia/Karachi",
    "iso:country":"PK",
    "name:eng_x_preferred":[
        "Sp\u012bnw\u0101ri"
    ],
    "wof:name":"Ghazgai Dharai",
    "wof:placetype":"locality"
},
  "geometry": {"coordinates":[71.78959,34.252],"type":"Point"}
}