{
  "type": "Feature",
  "properties": {
    "gn:admin1_code":"2.0",
    "gn:asciiname":"Kili Sulaiman Zai",
    "gn:country_code":"PK",
    "gn:dem":1740,
    "gn:feature_class":"P",
    "gn:feature_code":"PPL",
    "gn:name":"Kili Sulaiman Zai",
    "gn:population":0,
    "gn:timezone":"Asia/Karachi",
    "iso:country":"PK",
    "name:und_x_variant":[
        "Toi Kili",
        "Kili Sulaiman Zai"
    ],
    "wof:name":"Kili Sulaiman Zai",
    "wof:placetype":"locality"
},
  "geometry": {"coordinates":[69.538,31.11334],"type":"Point"}
}