{
  "type": "Feature",
  "properties": {
    "gn:admin1_code":"5",
    "gn:asciiname":"Goth Khair Muhammad",
    "gn:country_code":"PK",
    "gn:dem":65,
    "gn:feature_class":"P",
    "gn:feature_code":"PPL",
    "gn:name":"Goth Khair Muhammad",
    "gn:population":0,
    "gn:timezone":"Asia/Karachi",
    "iso:country":"PK",
    "name:und_x_variant":[
        "Goth Khali Muhammad"
    ],
    "wof:name":"Goth Khair Muhammad",
    "wof:placetype":"locality"
},
  "geometry": {"coordinates":[69.15139000000001,28.16944],"type":"Point"}
}