{
  "type": "Feature",
  "properties": {
    "gn:admin1_code":"5",
    "gn:asciiname":"Goth Naban Narejo",
    "gn:country_code":"PK",
    "gn:dem":20,
    "gn:feature_class":"P",
    "gn:feature_code":"PPL",
    "gn:name":"Goth Naban Narejo",
    "gn:population":0,
    "gn:timezone":"Asia/Karachi",
    "iso:country":"PK",
    "name:und_x_variant":[
        "Goth Nabban N\u0101r\u012bja"
    ],
    "wof:name":"Goth Naban Narejo",
    "wof:placetype":"locality"
},
  "geometry": {"coordinates":[68.98029,25.78597],"type":"Point"}
}