{
  "type": "Feature",
  "properties": {
    "gn:admin1_code":"4.0",
    "gn:asciiname":"Jarpal",
    "gn:country_code":"PK",
    "gn:dem":277,
    "gn:feature_class":"P",
    "gn:feature_code":"PPL",
    "gn:name":"Jarpal",
    "gn:population":0,
    "gn:timezone":"Asia/Karachi",
    "iso:country":"PK",
    "wof:name":"Jarpal",
    "wof:placetype":"locality"
},
  "geometry": {"coordinates":[74.98819,32.35439],"type":"Point"}
}