{
  "type": "Feature",
  "properties": {
    "gn:admin1_code":"5.0",
    "gn:asciiname":"Goth Fatehpur",
    "gn:country_code":"PK",
    "gn:dem":55,
    "gn:feature_class":"P",
    "gn:feature_code":"PPL",
    "gn:name":"Goth Fatehpur",
    "gn:population":0,
    "gn:timezone":"Asia/Karachi",
    "iso:country":"PK",
    "name:und_x_variant":[
        "Fatehpur"
    ],
    "wof:name":"Goth Fatehpur",
    "wof:placetype":"locality"
},
  "geometry": {"coordinates":[68.59505,27.39278],"type":"Point"}
}