{
  "type": "Feature",
  "properties": {
    "gn:admin1_code":"4.0",
    "gn:asciiname":"Behlula",
    "gn:country_code":"PK",
    "gn:dem":233,
    "gn:feature_class":"P",
    "gn:feature_code":"PPL",
    "gn:name":"Behlula",
    "gn:population":0,
    "gn:timezone":"Asia/Karachi",
    "iso:country":"PK",
    "name:und_x_variant":[
        "Bhalolah",
        "Bahlola",
        "Behlula"
    ],
    "wof:name":"Behlula",
    "wof:placetype":"locality"
},
  "geometry": {"coordinates":[73.65233000000001,32.94638],"type":"Point"}
}