{
  "type": "Feature",
  "properties": {
    "gn:admin1_code":"1.0",
    "gn:asciiname":"Hassu Khel",
    "gn:country_code":"PK",
    "gn:dem":673,
    "gn:feature_class":"P",
    "gn:feature_code":"PPL",
    "gn:name":"Hassu Khel",
    "gn:population":0,
    "gn:timezone":"Asia/Karachi",
    "iso:country":"PK",
    "wof:name":"Hassu Khel",
    "wof:placetype":"locality"
},
  "geometry": {"coordinates":[70.26719,32.9538],"type":"Point"}
}