{
  "type": "Feature",
  "properties": {
    "gn:admin1_code":"03",
    "gn:asciiname":"Nasapai",
    "gn:country_code":"PK",
    "gn:dem":1192,
    "gn:feature_class":"P",
    "gn:feature_code":"PPL",
    "gn:name":"Nasapai",
    "gn:population":0,
    "gn:timezone":"Asia/Karachi",
    "iso:country":"PK",
    "name:eng_x_preferred":[
        "Nas\u0101pai"
    ],
    "wof:name":"Nasapai",
    "wof:placetype":"locality"
},
  "geometry": {"coordinates":[71.75249000000002,34.95589],"type":"Point"}
}