{
  "type": "Feature",
  "properties": {
    "gn:admin1_code":"4",
    "gn:asciiname":"Basti Sialanwali",
    "gn:country_code":"PK",
    "gn:dem":110,
    "gn:feature_class":"P",
    "gn:feature_code":"PPL",
    "gn:name":"Basti Sialanwali",
    "gn:population":0,
    "gn:timezone":"Asia/Karachi",
    "iso:country":"PK",
    "name:und_x_variant":[
        "Basti Si\u0101l\u0101n",
        "Basti Si\u0101i\u0101n",
        "Basti Sialanwali"
    ],
    "wof:name":"Basti Sialanwali",
    "wof:placetype":"locality"
},
  "geometry": {"coordinates":[71.41755999999999,29.27841],"type":"Point"}
}