{
  "type": "Feature",
  "properties": {
    "gn:admin1_code":"4.0",
    "gn:asciiname":"Abaid Ali Khel",
    "gn:country_code":"PK",
    "gn:dem":256,
    "gn:feature_class":"P",
    "gn:feature_code":"PPL",
    "gn:name":"Abaid Ali Khel",
    "gn:population":0,
    "gn:timezone":"Asia/Karachi",
    "iso:country":"PK",
    "wof:name":"Abaid Ali Khel",
    "wof:placetype":"locality"
},
  "geometry": {"coordinates":[71.33329999999999,32.92442],"type":"Point"}
}