{
  "type": "Feature",
  "properties": {
    "gn:admin1_code":"2.0",
    "gn:asciiname":"Dasht",
    "gn:cc2":"PK",
    "gn:country_code":"PK",
    "gn:dem":1771,
    "gn:feature_class":"P",
    "gn:feature_code":"PPL",
    "gn:name":"Dasht",
    "gn:population":0,
    "gn:timezone":"Asia/Karachi",
    "iso:country":"PK",
    "name:ceb_x_preferred":[
        "Dasht"
    ],
    "name:fas_x_preferred":[
        "\u062f\u0634\u062a\u06cc"
    ],
    "name:ita_x_preferred":[
        "Dasht"
    ],
    "name:sco_x_preferred":[
        "Dasht"
    ],
    "name:swe_x_preferred":[
        "Dasht"
    ],
    "name:und_x_variant":[
        "Dasht Levy Post",
        "Dasht"
    ],
    "name:vie_x_preferred":[
        "Dasht"
    ],
    "wof:name":"Dasht",
    "wof:placetype":"locality"
},
  "geometry": {"coordinates":[67.09999999999999,29.91667],"type":"Point"}
}