{
  "type": "Feature",
  "properties": {
    "gn:admin1_code":"4.0",
    "gn:asciiname":"Chitala",
    "gn:country_code":"PK",
    "gn:dem":851,
    "gn:feature_class":"P",
    "gn:feature_code":"PPL",
    "gn:name":"Chitala",
    "gn:population":0,
    "gn:timezone":"Asia/Karachi",
    "iso:country":"PK",
    "name:ben_x_preferred":[
        "\u099a\u09bf\u09a4\u09b2"
    ],
    "name:ceb_x_preferred":[
        "Chitala"
    ],
    "name:fas_x_preferred":[
        "\u067e\u0634\u062a\u200c\u067e\u0631\u0647\u200c\u0627\u06cc\u200c\u0647\u0627\u06cc \u0622\u0633\u06cc\u0627\u06cc\u06cc"
    ],
    "name:fra_x_preferred":[
        "Chitala"
    ],
    "name:hun_x_preferred":[
        "Chitala"
    ],
    "name:ita_x_preferred":[
        "Chitala"
    ],
    "name:msa_x_preferred":[
        "Ikan Belida"
    ],
    "name:nld_x_preferred":[
        "Chitala"
    ],
    "name:pol_x_preferred":[
        "Chitala"
    ],
    "name:por_x_preferred":[
        "Chitala"
    ],
    "name:spa_x_preferred":[
        "Chitala"
    ],
    "name:swe_x_preferred":[
        "Chitala"
    ],
    "name:tha_x_preferred":[
        "\u0e1b\u0e25\u0e32\u0e15\u0e2d\u0e07"
    ],
    "name:war_x_preferred":[
        "Chitala"
    ],
    "wof:name":"Chitala",
    "wof:placetype":"locality"
},
  "geometry": {"coordinates":[72.12146,32.60978],"type":"Point"}
}