{
  "type": "Feature",
  "properties": {
    "gn:admin1_code":"4.0",
    "gn:asciiname":"Chitala",
    "gn:country_code":"PK",
    "gn:dem":851,
    "gn:feature_class":"P",
    "gn:feature_code":"PPL",
    "gn:name":"Chitala",
    "gn:population":0,
    "gn:timezone":"Asia/Karachi",
    "iso:country":"PK",
    "wof:name":"Chitala",
    "wof:placetype":"locality"
},
  "geometry": {"coordinates":[72.12146,32.60978],"type":"Point"}
}