{
  "type": "Feature",
  "properties": {
    "gn:admin1_code":"4.0",
    "gn:asciiname":"Allahdad di Bhaini",
    "gn:country_code":"PK",
    "gn:dem":148,
    "gn:feature_class":"P",
    "gn:feature_code":"PPL",
    "gn:name":"Allahdad di Bhaini",
    "gn:population":0,
    "gn:timezone":"Asia/Karachi",
    "iso:country":"PK",
    "wof:name":"Allahdad di Bhaini",
    "wof:placetype":"locality"
},
  "geometry": {"coordinates":[72.89771,29.98378],"type":"Point"}
}