{
  "type": "Feature",
  "properties": {
    "gn:admin1_code":"5.0",
    "gn:asciiname":"Muhammad Zarif Khan Jakhrani",
    "gn:country_code":"PK",
    "gn:dem":56,
    "gn:feature_class":"P",
    "gn:feature_code":"PPL",
    "gn:name":"Muhammad Zarif Khan Jakhrani",
    "gn:population":0,
    "gn:timezone":"Asia/Karachi",
    "iso:country":"PK",
    "wof:name":"Muhammad Zarif Khan Jakhrani",
    "wof:placetype":"locality"
},
  "geometry": {"coordinates":[68.29881,27.96861],"type":"Point"}
}