{
  "type": "Feature",
  "properties": {
    "gn:admin1_code":"4.0",
    "gn:asciiname":"Jinda Wali Dhok",
    "gn:country_code":"PK",
    "gn:dem":349,
    "gn:feature_class":"P",
    "gn:feature_code":"PPL",
    "gn:name":"Jinda Wali Dhok",
    "gn:population":0,
    "gn:timezone":"Asia/Karachi",
    "iso:country":"PK",
    "name:und_x_variant":[
        "Janderw\u0101li Dhok"
    ],
    "wof:name":"Jinda Wali Dhok",
    "wof:placetype":"locality"
},
  "geometry": {"coordinates":[71.80801,33.34883],"type":"Point"}
}