{
  "type": "Feature",
  "properties": {
    "gn:admin1_code":"5",
    "gn:asciiname":"Goth Jangi Khan",
    "gn:country_code":"PK",
    "gn:dem":54,
    "gn:feature_class":"P",
    "gn:feature_code":"PPL",
    "gn:name":"Goth Jangi Khan",
    "gn:population":0,
    "gn:timezone":"Asia/Karachi",
    "iso:country":"PK",
    "name:und_x_variant":[
        "Jangi Kh\u0101n"
    ],
    "wof:name":"Goth Jangi Khan",
    "wof:placetype":"locality"
},
  "geometry": {"coordinates":[68.11564,27.92989],"type":"Point"}
}