{
  "type": "Feature",
  "properties": {
    "gn:admin1_code":"5.0",
    "gn:asciiname":"Saleh Khan Mazari",
    "gn:country_code":"PK",
    "gn:dem":77,
    "gn:feature_class":"P",
    "gn:feature_code":"PPL",
    "gn:name":"Saleh Khan Mazari",
    "gn:population":0,
    "gn:timezone":"Asia/Karachi",
    "iso:country":"PK",
    "wof:name":"Saleh Khan Mazari",
    "wof:placetype":"locality"
},
  "geometry": {"coordinates":[69.52889999999999,28.42381],"type":"Point"}
}