{
  "type": "Feature",
  "properties": {
    "gn:admin1_code":"2.0",
    "gn:asciiname":"Chah Sar",
    "gn:country_code":"PK",
    "gn:dem":134,
    "gn:feature_class":"P",
    "gn:feature_code":"PPL",
    "gn:name":"Chah Sar",
    "gn:population":0,
    "gn:timezone":"Asia/Karachi",
    "iso:country":"PK",
    "wof:name":"Chah Sar",
    "wof:placetype":"locality"
},
  "geometry": {"coordinates":[63.0313,26.0048],"type":"Point"}
}