{
  "type": "Feature",
  "properties": {
    "gn:admin1_code":"03",
    "gn:asciiname":"Sikandar Shamali",
    "gn:country_code":"PK",
    "gn:dem":198,
    "gn:feature_class":"P",
    "gn:feature_code":"PPL",
    "gn:name":"Sikandar Shamali",
    "gn:population":0,
    "gn:timezone":"Asia/Karachi",
    "iso:country":"PK",
    "name:und_x_variant":[
        "Sikandar Shumali",
        "Sik\u0101ndar",
        "Sikandar Shamali"
    ],
    "wof:name":"Sikandar Shamali",
    "wof:placetype":"locality"
},
  "geometry": {"coordinates":[70.62668000000002,31.89328],"type":"Point"}
}