{
  "type": "Feature",
  "properties": {
    "gn:admin1_code":"4",
    "gn:asciiname":"Goth Lashkar",
    "gn:country_code":"PK",
    "gn:dem":121,
    "gn:feature_class":"P",
    "gn:feature_code":"PPL",
    "gn:name":"Goth Lashkar",
    "gn:population":0,
    "gn:timezone":"Asia/Karachi",
    "iso:country":"PK",
    "name:eng_x_preferred":[
        "Goth Lashkar"
    ],
    "wof:name":"Goth Lashkar",
    "wof:placetype":"neighbourhood"
},
  "geometry": {"coordinates":[71.73196,29.41362],"type":"Point"}
}