{
  "type": "Feature",
  "properties": {
    "gn:admin1_code":"3.0",
    "gn:asciiname":"Zargar Mama Khel",
    "gn:country_code":"PK",
    "gn:dem":349,
    "gn:feature_class":"P",
    "gn:feature_code":"PPL",
    "gn:name":"Zargar Mama Khel",
    "gn:population":0,
    "gn:timezone":"Asia/Karachi",
    "iso:country":"PK",
    "name:und_x_variant":[
        "Zargar Khel",
        "Zargar Mama Khel"
    ],
    "wof:name":"Zargar Mama Khel",
    "wof:placetype":"locality"
},
  "geometry": {"coordinates":[70.60587,32.90717],"type":"Point"}
}