{
  "type": "Feature",
  "properties": {
    "gn:admin1_code":"3.0",
    "gn:asciiname":"Dherai Kalle",
    "gn:country_code":"PK",
    "gn:dem":1117,
    "gn:feature_class":"P",
    "gn:feature_code":"PPL",
    "gn:name":"Dherai Kalle",
    "gn:population":0,
    "gn:timezone":"Asia/Karachi",
    "iso:country":"PK",
    "wof:name":"Dherai Kalle",
    "wof:placetype":"locality"
},
  "geometry": {"coordinates":[71.80662,34.95842],"type":"Point"}
}