{
  "type": "Feature",
  "properties": {
    "gn:admin1_code":"2.0",
    "gn:asciiname":"Janai",
    "gn:country_code":"PK",
    "gn:dem":50,
    "gn:feature_class":"P",
    "gn:feature_code":"PPL",
    "gn:name":"Janai",
    "gn:population":0,
    "gn:timezone":"Asia/Karachi",
    "iso:country":"PK",
    "name:und_x_variant":[
        "J\u0101n\u0101n"
    ],
    "wof:name":"Janai",
    "wof:placetype":"locality"
},
  "geometry": {"coordinates":[67.83501,27.99809],"type":"Point"}
}