{
  "type": "Feature",
  "properties": {
    "gn:admin1_code":"6",
    "gn:asciiname":"Saddan",
    "gn:country_code":"PK",
    "gn:dem":1435,
    "gn:feature_class":"P",
    "gn:feature_code":"PPL",
    "gn:name":"Saddan",
    "gn:population":0,
    "gn:timezone":"Asia/Karachi",
    "iso:country":"PK",
    "name:und_x_variant":[
        "Saiyid\u0101n"
    ],
    "wof:name":"Saddan",
    "wof:placetype":"locality"
},
  "geometry": {"coordinates":[73.50126999999998,34.42610999999999],"type":"Point"}
}