{
  "type": "Feature",
  "properties": {
    "gn:admin1_code":"3.0",
    "gn:asciiname":"Kotka Adamzai",
    "gn:country_code":"PK",
    "gn:dem":325,
    "gn:feature_class":"P",
    "gn:feature_code":"PPL",
    "gn:name":"Kotka Adamzai",
    "gn:population":0,
    "gn:timezone":"Asia/Karachi",
    "iso:country":"PK",
    "wof:name":"Kotka Adamzai",
    "wof:placetype":"locality"
},
  "geometry": {"coordinates":[70.63488000000002,32.57729],"type":"Point"}
}