{
  "type": "Feature",
  "properties": {
    "gn:admin1_code":"3",
    "gn:asciiname":"Zaodin Barai",
    "gn:country_code":"PK",
    "gn:dem":1088,
    "gn:feature_class":"P",
    "gn:feature_code":"PPL",
    "gn:name":"Zaodin Barai",
    "gn:population":0,
    "gn:timezone":"Asia/Karachi",
    "iso:country":"PK",
    "wof:name":"Zaodin Barai",
    "wof:placetype":"locality"
},
  "geometry": {"coordinates":[72.01418000000002,34.9463],"type":"Point"}
}