{
  "type": "Feature",
  "properties": {
    "gn:admin1_code":"3.0",
    "gn:asciiname":"Amir Akbar Shah",
    "gn:country_code":"PK",
    "gn:dem":441,
    "gn:feature_class":"P",
    "gn:feature_code":"PPL",
    "gn:name":"Amir Akbar Shah",
    "gn:population":0,
    "gn:timezone":"Asia/Karachi",
    "iso:country":"PK",
    "name:eng_x_preferred":[
        "M\u012br Akbar Sh\u0101h"
    ],
    "wof:name":"Amir Akbar Shah",
    "wof:placetype":"locality"
},
  "geometry": {"coordinates":[71.83894000000002,34.45084],"type":"Point"}
}