{
  "type": "Feature",
  "properties": {
    "gn:admin1_code":"1.0",
    "gn:asciiname":"Spo Banda",
    "gn:country_code":"PK",
    "gn:dem":803,
    "gn:feature_class":"P",
    "gn:feature_code":"PPL",
    "gn:name":"Spo Banda",
    "gn:population":0,
    "gn:timezone":"Asia/Karachi",
    "iso:country":"PK",
    "wof:name":"Spo Banda",
    "wof:placetype":"locality"
},
  "geometry": {"coordinates":[71.57231999999998,34.50397],"type":"Point"}
}