{
  "type": "Feature",
  "properties": {
    "gn:admin1_code":"03",
    "gn:asciiname":"Thalikot",
    "gn:country_code":"PK",
    "gn:dem":507,
    "gn:feature_class":"P",
    "gn:feature_code":"PPL",
    "gn:name":"Thalikot",
    "gn:population":0,
    "gn:timezone":"Asia/Karachi",
    "iso:country":"PK",
    "wof:name":"Thalikot",
    "wof:placetype":"locality"
},
  "geometry": {"coordinates":[72.65816,33.93869],"type":"Point"}
}