{
  "type": "Feature",
  "properties": {
    "gn:admin1_code":"3.0",
    "gn:asciiname":"Gumbat",
    "gn:country_code":"PK",
    "gn:dem":1708,
    "gn:feature_class":"P",
    "gn:feature_code":"PPL",
    "gn:name":"Gumbat",
    "gn:population":0,
    "gn:timezone":"Asia/Karachi",
    "iso:country":"PK",
    "name:eng_x_preferred":[
        "Gumbad"
    ],
    "name:und_x_variant":[
        "Gumbadat"
    ],
    "wof:name":"Gumbat",
    "wof:placetype":"locality"
},
  "geometry": {"coordinates":[71.86780999999998,35.01307],"type":"Point"}
}