{
  "type": "Feature",
  "properties": {
    "gn:admin1_code":"04",
    "gn:asciiname":"Saliana",
    "gn:country_code":"PK",
    "gn:dem":157,
    "gn:feature_class":"P",
    "gn:feature_code":"PPL",
    "gn:name":"Saliana",
    "gn:population":0,
    "gn:timezone":"Asia/Karachi",
    "iso:country":"PK",
    "wof:name":"Saliana",
    "wof:placetype":"locality"
},
  "geometry": {"coordinates":[72.13761,31.34972],"type":"Point"}
}