{
  "type": "Feature",
  "properties": {
    "gn:admin1_code":"04",
    "gn:asciiname":"Saliana",
    "gn:country_code":"PK",
    "gn:dem":157,
    "gn:feature_class":"P",
    "gn:feature_code":"PPL",
    "gn:name":"Saliana",
    "gn:population":0,
    "gn:timezone":"Asia/Karachi",
    "iso:country":"PK",
    "name:ceb_x_preferred":[
        "Saliana"
    ],
    "name:nor_x_preferred":[
        "Saliana"
    ],
    "name:swe_x_preferred":[
        "Saliana"
    ],
    "name:vie_x_preferred":[
        "Saliana"
    ],
    "name:war_x_preferred":[
        "Saliana"
    ],
    "name:zho_x_preferred":[
        "\u980c\u5f04\u8776\u5c6c"
    ],
    "wof:name":"Saliana",
    "wof:placetype":"locality"
},
  "geometry": {"coordinates":[72.13761,31.34972],"type":"Point"}
}