{
  "type": "Feature",
  "properties": {
    "gn:admin1_code":"5.0",
    "gn:asciiname":"Rahu",
    "gn:country_code":"PK",
    "gn:dem":8,
    "gn:feature_class":"P",
    "gn:feature_code":"PPL",
    "gn:name":"Rahu",
    "gn:population":0,
    "gn:timezone":"Asia/Karachi",
    "iso:country":"PK",
    "name:ben_x_preferred":[
        "\u09b0\u09be\u09b9\u09c1"
    ],
    "name:deu_x_preferred":[
        "Rahu"
    ],
    "name:est_x_preferred":[
        "R\u0101hu"
    ],
    "name:fra_x_preferred":[
        "R\u00e2hu"
    ],
    "name:hin_x_preferred":[
        "\u0930\u093e\u0939\u0941"
    ],
    "name:ind_x_preferred":[
        "Rahu"
    ],
    "name:jpn_x_preferred":[
        "\u30e9\u30fc\u30d5"
    ],
    "name:kan_x_preferred":[
        "\u0cb0\u0cbe\u0cb9\u0cc1"
    ],
    "name:khm_x_preferred":[
        "\u179a\u17b6\u17a0\u17bb"
    ],
    "name:mon_x_preferred":[
        "\u0420\u0430\u0445"
    ],
    "name:mya_x_preferred":[
        "\u101b\u102c\u101f\u102f"
    ],
    "name:nor_x_preferred":[
        "Rahu"
    ],
    "name:pan_x_preferred":[
        "\u0a30\u0a3e\u0a39\u0a42"
    ],
    "name:pol_x_preferred":[
        "Rahu"
    ],
    "name:por_x_preferred":[
        "Rahu"
    ],
    "name:rus_x_preferred":[
        "\u0420\u0430\u0445\u0443"
    ],
    "name:san_x_preferred":[
        "\u0930\u093e\u0939\u0941\u0903"
    ],
    "name:slv_x_preferred":[
        "Rahu"
    ],
    "name:spa_x_preferred":[
        "Raju"
    ],
    "name:tam_x_preferred":[
        "\u0b87\u0bb0\u0bbe\u0b95\u0bc1"
    ],
    "name:tha_x_preferred":[
        "\u0e1e\u0e23\u0e30\u0e23\u0e32\u0e2b\u0e39"
    ],
    "name:tur_x_preferred":[
        "Rahu"
    ],
    "name:ukr_x_preferred":[
        "\u0420\u0430\u0445\u0443"
    ],
    "name:vie_x_preferred":[
        "La H\u1ea7u"
    ],
    "wof:name":"Rahu",
    "wof:placetype":"locality"
},
  "geometry": {"coordinates":[68.58006,24.74595],"type":"Point"}
}