{
  "type": "Feature",
  "properties": {
    "gn:admin1_code":"03",
    "gn:asciiname":"Shahbra",
    "gn:country_code":"PK",
    "gn:dem":296,
    "gn:feature_class":"P",
    "gn:feature_code":"PPL",
    "gn:name":"Shahbra",
    "gn:population":0,
    "gn:timezone":"Asia/Karachi",
    "iso:country":"PK",
    "name:eng_x_preferred":[
        "Dheri Sh\u0101h B\u0101ra"
    ],
    "wof:name":"Shahbra",
    "wof:placetype":"locality"
},
  "geometry": {"coordinates":[71.72185999999998,34.10351],"type":"Point"}
}