{
  "type": "Feature",
  "properties": {
    "gn:admin1_code":"6",
    "gn:asciiname":"Chhel",
    "gn:country_code":"PK",
    "gn:dem":437,
    "gn:feature_class":"P",
    "gn:feature_code":"PPL",
    "gn:name":"Chhel",
    "gn:population":0,
    "gn:timezone":"Asia/Karachi",
    "iso:country":"PK",
    "name:und_x_variant":[
        "Chhei",
        "Chhel"
    ],
    "wof:name":"Chhel",
    "wof:placetype":"locality"
},
  "geometry": {"coordinates":[74.19627,32.99487],"type":"Point"}
}