{
  "type": "Feature",
  "properties": {
    "gn:admin1_code":"4.0",
    "gn:asciiname":"Basti Gul Muhammad Lar",
    "gn:country_code":"PK",
    "gn:dem":89,
    "gn:feature_class":"P",
    "gn:feature_code":"PPL",
    "gn:name":"Basti Gul Muhammad L\u0101r",
    "gn:population":0,
    "gn:timezone":"Asia/Karachi",
    "iso:country":"PK",
    "wof:name":"Basti Gul Muhammad Lar",
    "wof:placetype":"locality"
},
  "geometry": {"coordinates":[70.59583000000001,28.74306],"type":"Point"}
}