{
  "type": "Feature",
  "properties": {
    "gn:admin1_code":"4.0",
    "gn:asciiname":"Kolian Par",
    "gn:country_code":"PK",
    "gn:dem":504,
    "gn:feature_class":"P",
    "gn:feature_code":"PPL",
    "gn:name":"Kolian Par",
    "gn:population":0,
    "gn:timezone":"Asia/Karachi",
    "iso:country":"PK",
    "wof:name":"Kolian Par",
    "wof:placetype":"locality"
},
  "geometry": {"coordinates":[72.94875999999999,33.49487],"type":"Point"}
}