{
  "type": "Feature",
  "properties": {
    "gn:admin1_code":"5",
    "gn:asciiname":"Goth Chaudhry Sultan",
    "gn:country_code":"PK",
    "gn:dem":14,
    "gn:feature_class":"P",
    "gn:feature_code":"PPL",
    "gn:name":"Goth Chaudhry Sultan",
    "gn:population":0,
    "gn:timezone":"Asia/Karachi",
    "iso:country":"PK",
    "name:und_x_variant":[
        "Goth M\u012br Kh\u0101n Muhammad",
        "Goth Choudhari Sultan"
    ],
    "wof:name":"Goth Chaudhry Sultan",
    "wof:placetype":"locality"
},
  "geometry": {"coordinates":[69.13059,25.33641],"type":"Point"}
}