{
  "type": "Feature",
  "properties": {
    "gn:admin1_code":"3.0",
    "gn:asciiname":"Dalhorai",
    "gn:country_code":"PK",
    "gn:dem":1386,
    "gn:feature_class":"P",
    "gn:feature_code":"PPL",
    "gn:name":"Dalhorai",
    "gn:population":0,
    "gn:timezone":"Asia/Karachi",
    "iso:country":"PK",
    "wof:name":"Dalhorai",
    "wof:placetype":"locality"
},
  "geometry": {"coordinates":[72.99935000000001,34.55974000000001],"type":"Point"}
}