{
  "type": "Feature",
  "properties": {
    "iso:country":"PK",
    "qs:gn_pop":0,
    "qs:name":"Sewan Sharif",
    "qs:name_adm0":"Pakistan",
    "qs:name_adm1":"Sindh",
    "qs:photos":157,
    "qs:photos_1k":32,
    "qs:photos_9k":1,
    "qs:photos_9r":4,
    "qs:photos_all":157,
    "qs:photos_sr":4,
    "qs:placetype":"Town",
    "qs:pop_sr":"0",
    "qs:woe_adm0":23424922,
    "wof:name":"Sewan Sharif",
    "wof:placetype":"locality"
},
  "geometry": {"coordinates":[67.851562,26.427923],"type":"Point"}
}