{
  "type": "Feature",
  "properties": {
    "gn:admin1_code":"3",
    "gn:asciiname":"Dilakal Kas",
    "gn:country_code":"PK",
    "gn:dem":1458,
    "gn:feature_class":"P",
    "gn:feature_code":"PPL",
    "gn:name":"Dilakal Kas",
    "gn:population":0,
    "gn:timezone":"Asia/Karachi",
    "iso:country":"PK",
    "name:eng_x_preferred":[
        "D\u012blakal"
    ],
    "wof:name":"Dilakal Kas",
    "wof:placetype":"locality"
},
  "geometry": {"coordinates":[71.77811,35.09545],"type":"Point"}
}