{
  "type": "Feature",
  "properties": {
    "gn:admin1_code":"6.0",
    "gn:asciiname":"Makhwalan",
    "gn:country_code":"PK",
    "gn:dem":1774,
    "gn:feature_class":"P",
    "gn:feature_code":"PPL",
    "gn:name":"Makhwalan",
    "gn:population":0,
    "gn:timezone":"Asia/Karachi",
    "iso:country":"PK",
    "name:und_x_variant":[
        "Poth Makw\u0101l\u0101n"
    ],
    "wof:name":"Makhwalan",
    "wof:placetype":"locality"
},
  "geometry": {"coordinates":[73.73895999999998,33.87049],"type":"Point"}
}