{
  "type": "Feature",
  "properties": {
    "gn:admin1_code":"2.0",
    "gn:asciiname":"Badal Palal",
    "gn:country_code":"PK",
    "gn:dem":50,
    "gn:feature_class":"P",
    "gn:feature_code":"PPL",
    "gn:name":"Badal Palal",
    "gn:population":0,
    "gn:timezone":"Asia/Karachi",
    "iso:country":"PK",
    "name:und_x_variant":[
        "B\u0101dal Pal\u0101i"
    ],
    "wof:name":"Badal Palal",
    "wof:placetype":"locality"
},
  "geometry": {"coordinates":[67.79128,27.98727],"type":"Point"}
}