{
  "type": "Feature",
  "properties": {
    "gn:admin1_code":"3.0",
    "gn:asciiname":"Badin Payan",
    "gn:country_code":"PK",
    "gn:dem":302,
    "gn:feature_class":"P",
    "gn:feature_code":"PPL",
    "gn:name":"Badin Payan",
    "gn:population":0,
    "gn:timezone":"Asia/Karachi",
    "iso:country":"PK",
    "wof:name":"Badin Payan",
    "wof:placetype":"locality"
},
  "geometry": {"coordinates":[71.63464,34.1198],"type":"Point"}
}