{
  "type": "Feature",
  "properties": {
    "gn:admin1_code":"3",
    "gn:asciiname":"Durah",
    "gn:country_code":"PK",
    "gn:dem":861,
    "gn:feature_class":"P",
    "gn:feature_code":"PPL",
    "gn:name":"Durah",
    "gn:population":0,
    "gn:timezone":"Asia/Karachi",
    "iso:country":"PK",
    "name:und_x_variant":[
        "Dor\u0101h"
    ],
    "wof:name":"Durah",
    "wof:placetype":"locality"
},
  "geometry": {"coordinates":[72.79926999999998,34.0735],"type":"Point"}
}