{
  "type": "Feature",
  "properties": {
    "gn:admin1_code":"05",
    "gn:asciiname":"Saleh Muhammad Ganber",
    "gn:country_code":"PK",
    "gn:dem":0,
    "gn:feature_class":"P",
    "gn:feature_code":"PPL",
    "gn:name":"Saleh Muhammad Ganber",
    "gn:population":0,
    "gn:timezone":"Asia/Karachi",
    "iso:country":"PK",
    "wof:name":"Saleh Muhammad Ganber",
    "wof:placetype":"locality"
},
  "geometry": {"coordinates":[67.52724000000001,24.07703],"type":"Point"}
}