{
  "type": "Feature",
  "properties": {
    "gn:admin1_code":"2.0",
    "gn:asciiname":"Alabad",
    "gn:country_code":"PK",
    "gn:dem":1598,
    "gn:feature_class":"P",
    "gn:feature_code":"PPL",
    "gn:name":"Alabad",
    "gn:population":0,
    "gn:timezone":"Asia/Karachi",
    "iso:country":"PK",
    "wof:name":"Alabad",
    "wof:placetype":"locality"
},
  "geometry": {"coordinates":[66.05739,28.205],"type":"Point"}
}