{
  "type": "Feature",
  "properties": {
    "gn:admin1_code":"03",
    "gn:asciiname":"Wardaga",
    "gn:country_code":"PK",
    "gn:dem":319,
    "gn:feature_class":"P",
    "gn:feature_code":"PPL",
    "gn:name":"Wardaga",
    "gn:population":0,
    "gn:timezone":"Asia/Karachi",
    "iso:country":"PK",
    "name:eng_x_preferred":[
        "Wardga"
    ],
    "wof:name":"Wardaga",
    "wof:placetype":"locality"
},
  "geometry": {"coordinates":[71.84756,34.19015],"type":"Point"}
}