{
  "type": "Feature",
  "properties": {
    "gn:admin1_code":"2.0",
    "gn:asciiname":"Diwan Shah",
    "gn:country_code":"PK",
    "gn:dem":262,
    "gn:feature_class":"P",
    "gn:feature_code":"PPL",
    "gn:name":"Diwan Shah",
    "gn:population":0,
    "gn:timezone":"Asia/Karachi",
    "iso:country":"PK",
    "name:und_x_variant":[
        "Diwana Thana",
        "Diw\u0101na",
        "Diwan Shah"
    ],
    "wof:name":"Diwan Shah",
    "wof:placetype":"locality"
},
  "geometry": {"coordinates":[67.29177,26.07513],"type":"Point"}
}