{
  "type": "Feature",
  "properties": {
    "gn:admin1_code":"2.0",
    "gn:asciiname":"Tahdem Bazar Deh",
    "gn:country_code":"PK",
    "gn:dem":940,
    "gn:feature_class":"P",
    "gn:feature_code":"PPL",
    "gn:name":"Tahdem Bazar Deh",
    "gn:population":0,
    "gn:timezone":"Asia/Karachi",
    "iso:country":"PK",
    "wof:name":"Tahdem Bazar Deh",
    "wof:placetype":"locality"
},
  "geometry": {"coordinates":[63.05226,26.58127],"type":"Point"}
}