{
  "type": "Feature",
  "properties": {
    "gn:admin1_code":"05",
    "gn:asciiname":"Jumma Dablo",
    "gn:country_code":"PK",
    "gn:dem":2,
    "gn:feature_class":"P",
    "gn:feature_code":"PPL",
    "gn:name":"Jumma Dablo",
    "gn:population":0,
    "gn:timezone":"Asia/Karachi",
    "iso:country":"PK",
    "wof:name":"Jumma Dablo",
    "wof:placetype":"locality"
},
  "geometry": {"coordinates":[67.34999999999999,24.20694],"type":"Point"}
}