{
  "type": "Feature",
  "properties": {
    "gn:admin1_code":"4",
    "gn:asciiname":"Chak Twenty-three Dullewala Branch",
    "gn:country_code":"PK",
    "gn:dem":198,
    "gn:feature_class":"P",
    "gn:feature_code":"PPL",
    "gn:name":"Chak Twenty-three Dullewala Branch",
    "gn:population":0,
    "gn:timezone":"Asia/Karachi",
    "iso:country":"PK",
    "name:und_x_variant":[
        "Chak Twenty-three DB"
    ],
    "wof:name":"Chak Twenty-three Dullewala Branch",
    "wof:placetype":"locality"
},
  "geometry": {"coordinates":[71.63526999999998,32.33000999999999],"type":"Point"}
}