{
  "type": "Feature",
  "properties": {
    "gn:admin1_code":"03",
    "gn:asciiname":"Phuhar",
    "gn:country_code":"PK",
    "gn:dem":546,
    "gn:feature_class":"P",
    "gn:feature_code":"PPL",
    "gn:name":"Phuhar",
    "gn:population":0,
    "gn:timezone":"Asia/Karachi",
    "iso:country":"PK",
    "name:und_x_variant":[
        "Pohar",
        "Phuh\u0101r",
        "Phuhar"
    ],
    "wof:name":"Phuhar",
    "wof:placetype":"locality"
},
  "geometry": {"coordinates":[72.9781,34.18305],"type":"Point"}
}