{
  "type": "Feature",
  "properties": {
    "gn:admin1_code":"2.0",
    "gn:asciiname":"Landi",
    "gn:country_code":"PK",
    "gn:dem":743,
    "gn:feature_class":"P",
    "gn:feature_code":"PPL",
    "gn:name":"Landi",
    "gn:population":0,
    "gn:timezone":"Asia/Karachi",
    "iso:country":"PK",
    "name:ceb_x_preferred":[
        "Landi"
    ],
    "name:deu_x_preferred":[
        "Landi"
    ],
    "name:eng_x_preferred":[
        "Landi"
    ],
    "name:fra_x_preferred":[
        "Landi"
    ],
    "name:ita_x_preferred":[
        "Landi"
    ],
    "name:pol_x_preferred":[
        "Landi"
    ],
    "name:por_x_preferred":[
        "Landi"
    ],
    "name:spa_x_preferred":[
        "Landi"
    ],
    "name:swe_x_preferred":[
        "Landi"
    ],
    "name:urd_x_preferred":[
        "\u0644\u0646\u0688\u06cc"
    ],
    "wof:name":"Landi",
    "wof:placetype":"locality"
},
  "geometry": {"coordinates":[70.1943,31.14192],"type":"Point"}
}