{
  "type": "Feature",
  "properties": {
    "gn:admin1_code":"3.0",
    "gn:asciiname":"Ghanran",
    "gn:country_code":"PK",
    "gn:dem":1386,
    "gn:feature_class":"P",
    "gn:feature_code":"PPL",
    "gn:name":"Ghanran",
    "gn:population":0,
    "gn:timezone":"Asia/Karachi",
    "iso:country":"PK",
    "wof:name":"Ghanran",
    "wof:placetype":"locality"
},
  "geometry": {"coordinates":[72.9914,34.55698],"type":"Point"}
}