{
  "type": "Feature",
  "properties": {
    "gn:admin1_code":"5",
    "gn:asciiname":"Umid Ali Khoso",
    "gn:country_code":"PK",
    "gn:dem":20,
    "gn:feature_class":"P",
    "gn:feature_code":"PPL",
    "gn:name":"Umid Ali Khoso",
    "gn:population":0,
    "gn:timezone":"Asia/Karachi",
    "iso:country":"PK",
    "name:und_x_variant":[
        "Umed Ali Khoso"
    ],
    "wof:name":"Umid Ali Khoso",
    "wof:placetype":"locality"
},
  "geometry": {"coordinates":[68.52185,25.30036],"type":"Point"}
}