{
  "type": "Feature",
  "properties": {
    "gn:admin1_code":"4.0",
    "gn:asciiname":"Sobhe Khan",
    "gn:country_code":"PK",
    "gn:dem":122,
    "gn:feature_class":"P",
    "gn:feature_code":"PPL",
    "gn:name":"Sobhe Khan",
    "gn:population":0,
    "gn:timezone":"Asia/Karachi",
    "iso:country":"PK",
    "name:eng_x_preferred":[
        "Sobhe Khan"
    ],
    "wof:name":"Sobhe Khan",
    "wof:placetype":"locality"
},
  "geometry": {"coordinates":[71.89893000000002,29.73955],"type":"Point"}
}