{
  "type": "Feature",
  "properties": {
    "gn:admin1_code":"4.0",
    "gn:asciiname":"Chak Four Hundred Six Thal Development Authority",
    "gn:country_code":"PK",
    "gn:dem":144,
    "gn:feature_class":"P",
    "gn:feature_code":"PPL",
    "gn:name":"Chak Four Hundred Six Thal Development Authority",
    "gn:population":0,
    "gn:timezone":"Asia/Karachi",
    "iso:country":"PK",
    "name:und_x_variant":[
        "Chak Four Hundred Six TDA"
    ],
    "wof:name":"Chak Four Hundred Six Thal Development Authority",
    "wof:placetype":"locality"
},
  "geometry": {"coordinates":[71.39236,30.89408],"type":"Point"}
}