{
  "type": "Feature",
  "properties": {
    "gn:admin1_code":"4",
    "gn:asciiname":"Basti Khalilani",
    "gn:country_code":"PK",
    "gn:dem":121,
    "gn:feature_class":"P",
    "gn:feature_code":"PPL",
    "gn:name":"Basti Khalilani",
    "gn:population":0,
    "gn:timezone":"Asia/Karachi",
    "iso:country":"PK",
    "name:und_x_variant":[
        "Mad Khalel\u0101n"
    ],
    "wof:name":"Basti Khalilani",
    "wof:placetype":"locality"
},
  "geometry": {"coordinates":[70.30833,29.46944],"type":"Point"}
}