{
  "type": "Feature",
  "properties": {
    "gn:admin1_code":"4",
    "gn:asciiname":"Bhutianwala",
    "gn:country_code":"PK",
    "gn:dem":189,
    "gn:feature_class":"P",
    "gn:feature_code":"PPL",
    "gn:name":"Bhutianwala",
    "gn:population":0,
    "gn:timezone":"Asia/Karachi",
    "iso:country":"PK",
    "name:und_x_variant":[
        "Bhattiy\u0101n",
        "Bhutianwala"
    ],
    "wof:name":"Bhutianwala",
    "wof:placetype":"locality"
},
  "geometry": {"coordinates":[72.21890999999999,32.36866],"type":"Point"}
}