{
  "type": "Feature",
  "properties": {
    "gn:admin1_code":"4",
    "gn:asciiname":"Pir Makhdum Jahanian",
    "gn:country_code":"PK",
    "gn:dem":640,
    "gn:feature_class":"P",
    "gn:feature_code":"PPL",
    "gn:name":"Pir Makhdum Jahanian",
    "gn:population":0,
    "gn:timezone":"Asia/Karachi",
    "iso:country":"PK",
    "wof:name":"Pir Makhdum Jahanian",
    "wof:placetype":"locality"
},
  "geometry": {"coordinates":[73.00912,32.75515],"type":"Point"}
}