{
  "type": "Feature",
  "properties": {
    "gn:admin1_code":"5.0",
    "gn:asciiname":"Goth Chaudhari Zahid",
    "gn:country_code":"PK",
    "gn:dem":16,
    "gn:feature_class":"P",
    "gn:feature_code":"PPL",
    "gn:name":"Goth Chaudhari Zahid",
    "gn:population":0,
    "gn:timezone":"Asia/Karachi",
    "iso:country":"PK",
    "wof:name":"Goth Chaudhari Zahid",
    "wof:placetype":"locality"
},
  "geometry": {"coordinates":[68.53868,25.15927000000001],"type":"Point"}
}