{
  "type": "Feature",
  "properties": {
    "gn:admin1_code":"3.0",
    "gn:asciiname":"Patikar",
    "gn:country_code":"PK",
    "gn:dem":3442,
    "gn:feature_class":"P",
    "gn:feature_code":"PPL",
    "gn:name":"Patikar",
    "gn:population":0,
    "gn:timezone":"Asia/Karachi",
    "iso:country":"PK",
    "wof:name":"Patikar",
    "wof:placetype":"locality"
},
  "geometry": {"coordinates":[72.68040999999999,35.04085],"type":"Point"}
}