{
  "type": "Feature",
  "properties": {
    "gn:admin1_code":"4",
    "gn:asciiname":"Hattar",
    "gn:country_code":"PK",
    "gn:dem":247,
    "gn:feature_class":"P",
    "gn:feature_code":"PPL",
    "gn:name":"Hattar",
    "gn:population":0,
    "gn:timezone":"Asia/Karachi",
    "iso:country":"PK",
    "name:deu_x_preferred":[
        "Hattar"
    ],
    "name:swe_x_preferred":[
        "Hattar"
    ],
    "wof:name":"Hattar",
    "wof:placetype":"locality"
},
  "geometry": {"coordinates":[74.36111,32.63889],"type":"Point"}
}