{
  "type": "Feature",
  "properties": {
    "gn:admin1_code":"5",
    "gn:asciiname":"Ali Murad Nunari",
    "gn:country_code":"PK",
    "gn:dem":66,
    "gn:feature_class":"P",
    "gn:feature_code":"PPL",
    "gn:name":"Ali Murad Nunari",
    "gn:population":0,
    "gn:timezone":"Asia/Karachi",
    "iso:country":"PK",
    "name:und_x_variant":[
        "Ali Mur\u0101d Kh\u0101n Lash\u0101ri"
    ],
    "wof:name":"Ali Murad Nunari",
    "wof:placetype":"locality"
},
  "geometry": {"coordinates":[68.86245,28.22876],"type":"Point"}
}