{
  "type": "Feature",
  "properties": {
    "gn:admin1_code":"4.0",
    "gn:asciiname":"Chak Twenty-eight Dullewala Branch",
    "gn:country_code":"PK",
    "gn:dem":198,
    "gn:feature_class":"P",
    "gn:feature_code":"PPL",
    "gn:name":"Chak Twenty-eight Dullewala Branch",
    "gn:population":0,
    "gn:timezone":"Asia/Karachi",
    "iso:country":"PK",
    "name:und_x_variant":[
        "Chak Twenty eight DB"
    ],
    "wof:name":"Chak Twenty-eight Dullewala Branch",
    "wof:placetype":"locality"
},
  "geometry": {"coordinates":[71.68985000000001,32.31169000000001],"type":"Point"}
}