{
  "type": "Feature",
  "properties": {
    "gn:admin1_code":"5",
    "gn:asciiname":"Haji Khan Khosa",
    "gn:country_code":"PK",
    "gn:dem":50,
    "gn:feature_class":"P",
    "gn:feature_code":"PPL",
    "gn:name":"Haji Khan Khosa",
    "gn:population":0,
    "gn:timezone":"Asia/Karachi",
    "iso:country":"PK",
    "name:und_x_variant":[
        "Muhammad S\u0101lah"
    ],
    "wof:name":"Haji Khan Khosa",
    "wof:placetype":"locality"
},
  "geometry": {"coordinates":[68.19476,28.16136],"type":"Point"}
}