{
  "type": "Feature",
  "properties": {
    "gn:admin1_code":"1.0",
    "gn:asciiname":"Oucham Kala",
    "gn:country_code":"PK",
    "gn:dem":2286,
    "gn:feature_class":"P",
    "gn:feature_code":"PPL",
    "gn:name":"Oucham Kala",
    "gn:population":0,
    "gn:timezone":"Asia/Karachi",
    "iso:country":"PK",
    "wof:name":"Oucham Kala",
    "wof:placetype":"locality"
},
  "geometry": {"coordinates":[69.62772,32.70493],"type":"Point"}
}