{
  "type": "Feature",
  "properties": {
    "gn:admin1_code":"3.0",
    "gn:asciiname":"Thatha Paya",
    "gn:country_code":"PK",
    "gn:dem":1923,
    "gn:feature_class":"P",
    "gn:feature_code":"PPL",
    "gn:name":"Thatha Paya",
    "gn:population":0,
    "gn:timezone":"Asia/Karachi",
    "iso:country":"PK",
    "wof:name":"Thatha Paya",
    "wof:placetype":"locality"
},
  "geometry": {"coordinates":[73.44789,34.59426],"type":"Point"}
}