{
  "type": "Feature",
  "properties": {
    "gn:admin1_code":"2.0",
    "gn:asciiname":"Zargar Kaul",
    "gn:country_code":"PK",
    "gn:dem":1829,
    "gn:feature_class":"P",
    "gn:feature_code":"PPL",
    "gn:name":"Zargar Kaul",
    "gn:population":0,
    "gn:timezone":"Asia/Karachi",
    "iso:country":"PK",
    "wof:name":"Zargar Kaul",
    "wof:placetype":"locality"
},
  "geometry": {"coordinates":[66.82637,30.80103],"type":"Point"}
}