{
  "type": "Feature",
  "properties": {
    "gn:admin1_code":"4.0",
    "gn:asciiname":"Jawnara",
    "gn:country_code":"PK",
    "gn:dem":1259,
    "gn:feature_class":"P",
    "gn:feature_code":"PPL",
    "gn:name":"Jawnara",
    "gn:population":0,
    "gn:timezone":"Asia/Karachi",
    "iso:country":"PK",
    "name:eng_x_preferred":[
        "Jawnara"
    ],
    "wof:name":"Jawnara",
    "wof:placetype":"locality"
},
  "geometry": {"coordinates":[73.39361,33.83402],"type":"Point"}
}