{
  "type": "Feature",
  "properties": {
    "gn:admin1_code":"3",
    "gn:asciiname":"Sangor",
    "gn:country_code":"PK",
    "gn:dem":1983,
    "gn:feature_class":"P",
    "gn:feature_code":"PPL",
    "gn:name":"Sangor",
    "gn:population":0,
    "gn:timezone":"Asia/Karachi",
    "iso:country":"PK",
    "wof:name":"Sangor",
    "wof:placetype":"locality"
},
  "geometry": {"coordinates":[72.68409,34.80884],"type":"Point"}
}