{
  "type": "Feature",
  "properties": {
    "gn:admin1_code":"5.0",
    "gn:asciiname":"Umrani",
    "gn:country_code":"PK",
    "gn:dem":44,
    "gn:feature_class":"P",
    "gn:feature_code":"PPL",
    "gn:name":"Umrani",
    "gn:population":0,
    "gn:timezone":"Asia/Karachi",
    "iso:country":"PK",
    "name:fra_x_preferred":[
        "Umrani"
    ],
    "wof:name":"Umrani",
    "wof:placetype":"locality"
},
  "geometry": {"coordinates":[67.77931,27.67296],"type":"Point"}
}