{
  "type": "Feature",
  "properties": {
    "gn:admin1_code":"03",
    "gn:asciiname":"Kamalizarah Khel",
    "gn:country_code":"PK",
    "gn:dem":994,
    "gn:feature_class":"P",
    "gn:feature_code":"PPL",
    "gn:name":"Kamalizarah Khel",
    "gn:population":0,
    "gn:timezone":"Asia/Karachi",
    "iso:country":"PK",
    "name:und_x_variant":[
        "Zara Khel Kamali"
    ],
    "wof:name":"Kamalizarah Khel",
    "wof:placetype":"locality"
},
  "geometry": {"coordinates":[71.286,33.1042],"type":"Point"}
}