{
  "type": "Feature",
  "properties": {
    "gn:admin1_code":"2",
    "gn:asciiname":"Basti Rehman Shah",
    "gn:country_code":"PK",
    "gn:dem":981,
    "gn:feature_class":"P",
    "gn:feature_code":"PPL",
    "gn:name":"Basti Rehman Shah",
    "gn:population":0,
    "gn:timezone":"Asia/Karachi",
    "iso:country":"PK",
    "name:und_x_variant":[
        "Rahm\u0101n Sh\u0101h"
    ],
    "wof:name":"Basti Rehman Shah",
    "wof:placetype":"locality"
},
  "geometry": {"coordinates":[69.37174,29.75548],"type":"Point"}
}