{
  "type": "Feature",
  "properties": {
    "gn:admin1_code":"5",
    "gn:asciiname":"Goth Haji Shahid",
    "gn:country_code":"PK",
    "gn:dem":13,
    "gn:feature_class":"P",
    "gn:feature_code":"PPL",
    "gn:name":"Goth Haji Shahid",
    "gn:population":0,
    "gn:timezone":"Asia/Karachi",
    "iso:country":"PK",
    "name:und_x_variant":[
        "Goth H\u0101ji Sh\u0101hd\u0101d Kh\u0101n Nud\u0101ni"
    ],
    "wof:name":"Goth Haji Shahid",
    "wof:placetype":"locality"
},
  "geometry": {"coordinates":[69.20429,25.26334],"type":"Point"}
}