{
  "type": "Feature",
  "properties": {
    "gn:admin1_code":"2.0",
    "gn:asciiname":"Kili Shadlan",
    "gn:country_code":"PK",
    "gn:dem":595,
    "gn:feature_class":"P",
    "gn:feature_code":"PPL",
    "gn:name":"Kili Shadlan",
    "gn:population":0,
    "gn:timezone":"Asia/Karachi",
    "iso:country":"PK",
    "wof:name":"Kili Shadlan",
    "wof:placetype":"locality"
},
  "geometry": {"coordinates":[64.47084,28.1239],"type":"Point"}
}