{
  "type": "Feature",
  "properties": {
    "gn:admin1_code":"3.0",
    "gn:asciiname":"Sahan Gali",
    "gn:country_code":"PK",
    "gn:dem":2139,
    "gn:feature_class":"P",
    "gn:feature_code":"PPL",
    "gn:name":"Sahan Gali",
    "gn:population":0,
    "gn:timezone":"Asia/Karachi",
    "iso:country":"PK",
    "wof:name":"Sahan Gali",
    "wof:placetype":"locality"
},
  "geometry": {"coordinates":[73.35726,34.05141],"type":"Point"}
}