{
  "type": "Feature",
  "properties": {
    "gn:admin1_code":"5",
    "gn:asciiname":"Rajibah",
    "gn:country_code":"PK",
    "gn:dem":38,
    "gn:feature_class":"P",
    "gn:feature_code":"PPL",
    "gn:name":"Rajibah",
    "gn:population":0,
    "gn:timezone":"Asia/Karachi",
    "iso:country":"PK",
    "name:und_x_variant":[
        "R\u0101jab"
    ],
    "wof:name":"Rajibah",
    "wof:placetype":"locality"
},
  "geometry": {"coordinates":[69.66152,24.87016],"type":"Point"}
}