{
  "type": "Feature",
  "properties": {
    "gn:admin1_code":"3.0",
    "gn:asciiname":"Mian Kalle",
    "gn:country_code":"PK",
    "gn:dem":1083,
    "gn:feature_class":"P",
    "gn:feature_code":"PPL",
    "gn:name":"Mian Kalle",
    "gn:population":0,
    "gn:timezone":"Asia/Karachi",
    "iso:country":"PK",
    "name:und_x_variant":[
        "Kar\u0101kar Kandao",
        "Karakar",
        "Kar\u0101kar B\u0101nda",
        "Mian Kalle"
    ],
    "wof:name":"Mian Kalle",
    "wof:placetype":"locality"
},
  "geometry": {"coordinates":[72.28194000000001,34.61678],"type":"Point"}
}