{
  "type": "Feature",
  "properties": {
    "gn:admin1_code":"2",
    "gn:asciiname":"Kot Lashari",
    "gn:country_code":"PK",
    "gn:dem":60,
    "gn:feature_class":"P",
    "gn:feature_code":"PPL",
    "gn:name":"Kot Lashari",
    "gn:population":0,
    "gn:timezone":"Asia/Karachi",
    "iso:country":"PK",
    "wof:name":"Kot Lashari",
    "wof:placetype":"locality"
},
  "geometry": {"coordinates":[68.70837,28.47821],"type":"Point"}
}