{
  "type": "Feature",
  "properties": {
    "gn:admin1_code":"4.0",
    "gn:asciiname":"Amlike Sohag",
    "gn:country_code":"PK",
    "gn:dem":178,
    "gn:feature_class":"P",
    "gn:feature_code":"PPL",
    "gn:name":"Amlike Sohag",
    "gn:population":0,
    "gn:timezone":"Asia/Karachi",
    "iso:country":"PK",
    "name:und_x_variant":[
        "Amleke Sohag",
        "Amlike Sohag"
    ],
    "wof:name":"Amlike Sohag",
    "wof:placetype":"locality"
},
  "geometry": {"coordinates":[73.78022,30.5125],"type":"Point"}
}