{
  "type": "Feature",
  "properties": {
    "gn:admin1_code":"4",
    "gn:asciiname":"Pakhowal",
    "gn:country_code":"PK",
    "gn:dem":237,
    "gn:feature_class":"P",
    "gn:feature_code":"PPL",
    "gn:name":"Pakhowal",
    "gn:population":0,
    "gn:timezone":"Asia/Karachi",
    "iso:country":"PK",
    "name:und_x_variant":[
        "Pakhaw\u0101l"
    ],
    "wof:name":"Pakhowal",
    "wof:placetype":"locality"
},
  "geometry": {"coordinates":[74.05998000000002,32.62194],"type":"Point"}
}