{
  "type": "Feature",
  "properties": {
    "gn:admin1_code":"03",
    "gn:asciiname":"Mandhar",
    "gn:country_code":"PK",
    "gn:dem":1120,
    "gn:feature_class":"P",
    "gn:feature_code":"PPL",
    "gn:name":"Mandhar",
    "gn:population":0,
    "gn:timezone":"Asia/Karachi",
    "iso:country":"PK",
    "name:und_x_variant":[
        "Mundh\u0101r"
    ],
    "wof:name":"Mandhar",
    "wof:placetype":"locality"
},
  "geometry": {"coordinates":[73.30356,34.38549],"type":"Point"}
}