{
  "type": "Feature",
  "properties": {
    "gn:admin1_code":"7.0",
    "gn:asciiname":"Murtswa",
    "gn:country_code":"PK",
    "gn:dem":3023,
    "gn:feature_class":"P",
    "gn:feature_code":"PPL",
    "gn:name":"Murtswa",
    "gn:population":0,
    "gn:timezone":"Asia/Karachi",
    "iso:country":"PK",
    "wof:name":"Murtswa",
    "wof:placetype":"locality"
},
  "geometry": {"coordinates":[75.42803000000001,35.85252],"type":"Point"}
}