{
  "type": "Feature",
  "properties": {
    "gn:admin1_code":"5",
    "gn:asciiname":"Abdul Rahim Lakhero",
    "gn:country_code":"PK",
    "gn:dem":44,
    "gn:feature_class":"P",
    "gn:feature_code":"PPL",
    "gn:name":"Abdul Rahim Lakhero",
    "gn:population":0,
    "gn:timezone":"Asia/Karachi",
    "iso:country":"PK",
    "name:und_x_variant":[
        "Lakhar"
    ],
    "wof:name":"Abdul Rahim Lakhero",
    "wof:placetype":"locality"
},
  "geometry": {"coordinates":[68.17955000000001,26.92644],"type":"Point"}
}