{
  "type": "Feature",
  "properties": {
    "gn:admin1_code":"3",
    "gn:asciiname":"Chhur Sharif",
    "gn:country_code":"PK",
    "gn:dem":516,
    "gn:feature_class":"P",
    "gn:feature_code":"PPL",
    "gn:name":"Chhur Sharif",
    "gn:population":0,
    "gn:timezone":"Asia/Karachi",
    "iso:country":"PK",
    "name:und_x_variant":[
        "Chhor"
    ],
    "wof:name":"Chhur Sharif",
    "wof:placetype":"locality"
},
  "geometry": {"coordinates":[72.91979000000001,34.00594],"type":"Point"}
}