{
  "type": "Feature",
  "properties": {
    "gn:admin1_code":"2.0",
    "gn:asciiname":"Kili Zawa",
    "gn:country_code":"PK",
    "gn:dem":2030,
    "gn:feature_class":"P",
    "gn:feature_code":"PPL",
    "gn:name":"Kili Zawa",
    "gn:population":0,
    "gn:timezone":"Asia/Karachi",
    "iso:country":"PK",
    "wof:name":"Kili Zawa",
    "wof:placetype":"locality"
},
  "geometry": {"coordinates":[67.54899,30.46086],"type":"Point"}
}