{
  "type": "Feature",
  "properties": {
    "gn:admin1_code":"5.0",
    "gn:asciiname":"Goth Ghotana",
    "gn:country_code":"PK",
    "gn:dem":29,
    "gn:feature_class":"P",
    "gn:feature_code":"PPL",
    "gn:name":"Goth Ghotana",
    "gn:population":0,
    "gn:timezone":"Asia/Karachi",
    "iso:country":"PK",
    "name:eng_x_preferred":[
        "Ghot\u0101na"
    ],
    "wof:name":"Goth Ghotana",
    "wof:placetype":"locality"
},
  "geometry": {"coordinates":[68.41215,25.74719],"type":"Point"}
}