{
  "type": "Feature",
  "properties": {
    "gn:admin1_code":"1.0",
    "gn:asciiname":"Talai",
    "gn:country_code":"PK",
    "gn:dem":1948,
    "gn:feature_class":"P",
    "gn:feature_code":"PPL",
    "gn:name":"Talai",
    "gn:population":0,
    "gn:timezone":"Asia/Karachi",
    "iso:country":"PK",
    "name:ben_x_preferred":[
        "\u09a4\u09be\u09b2\u09be\u0987"
    ],
    "name:bpy_x_preferred":[
        "\u09a4\u09be\u09b2\u09be\u0987"
    ],
    "name:ita_x_preferred":[
        "Talai"
    ],
    "name:msa_x_preferred":[
        "Talai"
    ],
    "name:nld_x_preferred":[
        "Talai"
    ],
    "name:por_x_preferred":[
        "Talai"
    ],
    "name:tam_x_preferred":[
        "\u0ba4\u0bb2\u0bbe\u0baf\u0bcd"
    ],
    "name:und_x_variant":[
        "Talat"
    ],
    "name:vie_x_preferred":[
        "Talai"
    ],
    "wof:name":"Talai",
    "wof:placetype":"locality"
},
  "geometry": {"coordinates":[70.80251,33.72006],"type":"Point"}
}