{
  "type": "Feature",
  "properties": {
    "gn:admin1_code":"01",
    "gn:asciiname":"Rashakai",
    "gn:country_code":"PK",
    "gn:dem":951,
    "gn:feature_class":"P",
    "gn:feature_code":"PPL",
    "gn:name":"Rashakai",
    "gn:population":0,
    "gn:timezone":"Asia/Karachi",
    "iso:country":"PK",
    "wof:name":"Rashakai",
    "wof:placetype":"locality"
},
  "geometry": {"coordinates":[71.41072,34.70682],"type":"Point"}
}