{
  "type": "Feature",
  "properties": {
    "gn:admin1_code":"3",
    "gn:asciiname":"Dosam",
    "gn:country_code":"PK",
    "gn:dem":1804,
    "gn:feature_class":"P",
    "gn:feature_code":"PPL",
    "gn:name":"Dosam",
    "gn:population":0,
    "gn:timezone":"Asia/Karachi",
    "iso:country":"PK",
    "wof:name":"Dosam",
    "wof:placetype":"locality"
},
  "geometry": {"coordinates":[73.13632,34.63693],"type":"Point"}
}