{
  "type": "Feature",
  "properties": {
    "gn:admin1_code":"02",
    "gn:asciiname":"Torak Kili",
    "gn:country_code":"PK",
    "gn:dem":1479,
    "gn:feature_class":"P",
    "gn:feature_code":"PPL",
    "gn:name":"Torak Kili",
    "gn:population":0,
    "gn:timezone":"Asia/Karachi",
    "iso:country":"PK",
    "wof:name":"Torak Kili",
    "wof:placetype":"locality"
},
  "geometry": {"coordinates":[68.947,30.8938],"type":"Point"}
}