{
  "type": "Feature",
  "properties": {
    "gn:admin1_code":"4",
    "gn:asciiname":"Ghilken",
    "gn:country_code":"PK",
    "gn:dem":167,
    "gn:feature_class":"P",
    "gn:feature_code":"PPL",
    "gn:name":"Ghilken",
    "gn:population":0,
    "gn:timezone":"Asia/Karachi",
    "iso:country":"PK",
    "name:und_x_variant":[
        "Gilkin",
        "Ghilkin",
        "Ghilken"
    ],
    "wof:name":"Ghilken",
    "wof:placetype":"locality"
},
  "geometry": {"coordinates":[71.00121,31.70279],"type":"Point"}
}