{
  "type": "Feature",
  "properties": {
    "gn:admin1_code":"5",
    "gn:asciiname":"Goth Idan Khan Jalani",
    "gn:country_code":"PK",
    "gn:dem":37,
    "gn:feature_class":"P",
    "gn:feature_code":"PPL",
    "gn:name":"Goth Idan Khan Jalani",
    "gn:population":0,
    "gn:timezone":"Asia/Karachi",
    "iso:country":"PK",
    "wof:name":"Goth Idan Khan Jalani",
    "wof:placetype":"locality"
},
  "geometry": {"coordinates":[68.20864,26.33899000000001],"type":"Point"}
}