{
  "type": "Feature",
  "properties": {
    "gn:admin1_code":"02",
    "gn:asciiname":"Reg Burida",
    "gn:cc2":"PK",
    "gn:country_code":"PK",
    "gn:dem":535,
    "gn:feature_class":"P",
    "gn:feature_code":"PPL",
    "gn:name":"Reg Bur\u012bda",
    "gn:population":0,
    "gn:timezone":"Asia/Karachi",
    "iso:country":"PK",
    "name:und_x_variant":[
        "Rag Bur\u012bda",
        "R\u012bg Bur\u012bda",
        "Reg Bur\u012bda"
    ],
    "wof:name":"Reg Burida",
    "wof:placetype":"locality"
},
  "geometry": {"coordinates":[63.60111,27.86306],"type":"Point"}
}