{
  "type": "Feature",
  "properties": {
    "gn:admin1_code":"3.0",
    "gn:asciiname":"Gulbaz Dahqan",
    "gn:country_code":"PK",
    "gn:dem":281,
    "gn:feature_class":"P",
    "gn:feature_code":"PPL",
    "gn:name":"Gulbaz Dahqan",
    "gn:population":0,
    "gn:timezone":"Asia/Karachi",
    "iso:country":"PK",
    "name:und_x_variant":[
        "Gulbaz Dehkan",
        "Gul B\u0101z Dekh\u0101n",
        "Gulbaz Dahqan"
    ],
    "wof:name":"Gulbaz Dahqan",
    "wof:placetype":"locality"
},
  "geometry": {"coordinates":[70.7724,32.59762],"type":"Point"}
}