{
  "type": "Feature",
  "properties": {
    "gn:admin1_code":"2.0",
    "gn:asciiname":"Ahmad Chah",
    "gn:country_code":"PK",
    "gn:dem":610,
    "gn:feature_class":"P",
    "gn:feature_code":"PPL",
    "gn:name":"Ahmad Chah",
    "gn:population":0,
    "gn:timezone":"Asia/Karachi",
    "iso:country":"PK",
    "wof:name":"Ahmad Chah",
    "wof:placetype":"locality"
},
  "geometry": {"coordinates":[64.75480999999999,28.06727],"type":"Point"}
}