{
  "type": "Feature",
  "properties": {
    "gn:admin1_code":"4.0",
    "gn:asciiname":"Shera Dhonwala",
    "gn:country_code":"PK",
    "gn:dem":188,
    "gn:feature_class":"P",
    "gn:feature_code":"PPL",
    "gn:name":"Shera Dhonwala",
    "gn:population":0,
    "gn:timezone":"Asia/Karachi",
    "iso:country":"PK",
    "wof:name":"Shera Dhonwala",
    "wof:placetype":"locality"
},
  "geometry": {"coordinates":[71.94625000000001,31.89054],"type":"Point"}
}