{
  "type": "Feature",
  "properties": {
    "gn:admin1_code":"5.0",
    "gn:asciiname":"Saiyid Jahan Shah",
    "gn:country_code":"PK",
    "gn:dem":54,
    "gn:feature_class":"P",
    "gn:feature_code":"PPL",
    "gn:name":"Saiyid Jahan Shah",
    "gn:population":0,
    "gn:timezone":"Asia/Karachi",
    "iso:country":"PK",
    "name:und_x_variant":[
        "Saiyid Jah\u0101n Sh\u0101h",
        "Jah\u0101n Sh\u0101h",
        "Saiyid Jahan Shah"
    ],
    "wof:name":"Saiyid Jahan Shah",
    "wof:placetype":"locality"
},
  "geometry": {"coordinates":[68.24168,28.16209000000001],"type":"Point"}
}