{
  "type": "Feature",
  "properties": {
    "gn:admin1_code":"04",
    "gn:asciiname":"Rajo",
    "gn:country_code":"PK",
    "gn:dem":216,
    "gn:feature_class":"P",
    "gn:feature_code":"PPL",
    "gn:name":"Rajo",
    "gn:population":0,
    "gn:timezone":"Asia/Karachi",
    "iso:country":"PK",
    "name:und_x_variant":[
        "Rajoah",
        "Rajoa",
        "Rajo"
    ],
    "wof:name":"Rajo",
    "wof:placetype":"locality"
},
  "geometry": {"coordinates":[73.70952,32.51486],"type":"Point"}
}