{
  "type": "Feature",
  "properties": {
    "gn:admin1_code":"3.0",
    "gn:asciiname":"Shishi",
    "gn:country_code":"PK",
    "gn:dem":1406,
    "gn:feature_class":"P",
    "gn:feature_code":"PPL",
    "gn:name":"Shishi",
    "gn:population":0,
    "gn:timezone":"Asia/Karachi",
    "iso:country":"PK",
    "name:ceb_x_preferred":[
        "Shishi"
    ],
    "name:cym_x_preferred":[
        "Shishi"
    ],
    "name:deu_x_preferred":[
        "Shishi"
    ],
    "name:nor_x_preferred":[
        "Shishi"
    ],
    "name:swe_x_preferred":[
        "Shishi"
    ],
    "wof:name":"Shishi",
    "wof:placetype":"locality"
},
  "geometry": {"coordinates":[71.83581,35.59812],"type":"Point"}
}