{
  "type": "Feature",
  "properties": {
    "gn:admin1_code":"1.0",
    "gn:asciiname":"Nowe Kalle",
    "gn:country_code":"PK",
    "gn:dem":857,
    "gn:feature_class":"P",
    "gn:feature_code":"PPL",
    "gn:name":"Nowe Kalle",
    "gn:population":0,
    "gn:timezone":"Asia/Karachi",
    "iso:country":"PK",
    "name:und_x_variant":[
        "N\u0101i Kach"
    ],
    "wof:name":"Nowe Kalle",
    "wof:placetype":"locality"
},
  "geometry": {"coordinates":[70.06293000000001,32.38782],"type":"Point"}
}