{
  "type": "Feature",
  "properties": {
    "gn:admin1_code":"7.0",
    "gn:asciiname":"Darvi Baihk",
    "gn:country_code":"PK",
    "gn:dem":3488,
    "gn:feature_class":"P",
    "gn:feature_code":"PPL",
    "gn:name":"Darvi Baihk",
    "gn:population":0,
    "gn:timezone":"Asia/Karachi",
    "iso:country":"PK",
    "wof:name":"Darvi Baihk",
    "wof:placetype":"locality"
},
  "geometry": {"coordinates":[75.6626,35.1768],"type":"Point"}
}