{
  "type": "Feature",
  "properties": {
    "gn:admin1_code":"5.0",
    "gn:asciiname":"Rahiro",
    "gn:country_code":"PK",
    "gn:dem":50,
    "gn:feature_class":"P",
    "gn:feature_code":"PPL",
    "gn:name":"Rahiro",
    "gn:population":0,
    "gn:timezone":"Asia/Karachi",
    "iso:country":"PK",
    "name:und_x_variant":[
        "Rohir\u0101ri"
    ],
    "wof:name":"Rahiro",
    "wof:placetype":"locality"
},
  "geometry": {"coordinates":[70.72716,24.69866],"type":"Point"}
}