{
  "type": "Feature",
  "properties": {
    "gn:admin1_code":"4.0",
    "gn:asciiname":"Gaggan",
    "gn:country_code":"PK",
    "gn:dem":500,
    "gn:feature_class":"P",
    "gn:feature_code":"PPL",
    "gn:name":"Gaggan",
    "gn:population":0,
    "gn:timezone":"Asia/Karachi",
    "iso:country":"PK",
    "name:und_x_variant":[
        "Gagan",
        "Gaggan"
    ],
    "wof:name":"Gaggan",
    "wof:placetype":"locality"
},
  "geometry": {"coordinates":[72.49061999999998,33.53305],"type":"Point"}
}