{
  "type": "Feature",
  "properties": {
    "gn:admin1_code":"3",
    "gn:asciiname":"Daboi",
    "gn:country_code":"PK",
    "gn:dem":721,
    "gn:feature_class":"P",
    "gn:feature_code":"PPL",
    "gn:name":"Daboi",
    "gn:population":0,
    "gn:timezone":"Asia/Karachi",
    "iso:country":"PK",
    "name:und_x_variant":[
        "Dabhuli"
    ],
    "wof:name":"Daboi",
    "wof:placetype":"locality"
},
  "geometry": {"coordinates":[72.87772,34.37719],"type":"Point"}
}