{
  "type": "Feature",
  "properties": {
    "gn:admin1_code":"4.0",
    "gn:asciiname":"Lassan",
    "gn:country_code":"PK",
    "gn:dem":798,
    "gn:feature_class":"P",
    "gn:feature_code":"PPL",
    "gn:name":"Lassan",
    "gn:population":0,
    "gn:timezone":"Asia/Karachi",
    "iso:country":"PK",
    "wof:name":"Lassan",
    "wof:placetype":"locality"
},
  "geometry": {"coordinates":[73.24293,33.81185],"type":"Point"}
}