{
  "type": "Feature",
  "properties": {
    "gn:admin1_code":"01",
    "gn:asciiname":"Sholam",
    "gn:country_code":"PK",
    "gn:dem":1651,
    "gn:feature_class":"P",
    "gn:feature_code":"PPL",
    "gn:name":"Sholam",
    "gn:population":0,
    "gn:timezone":"Asia/Karachi",
    "iso:country":"PK",
    "wof:name":"Sholam",
    "wof:placetype":"locality"
},
  "geometry": {"coordinates":[69.47861,32.36278],"type":"Point"}
}