{
  "type": "Feature",
  "properties": {
    "gn:admin1_code":"2.0",
    "gn:asciiname":"Badell Kili",
    "gn:country_code":"PK",
    "gn:dem":854,
    "gn:feature_class":"P",
    "gn:feature_code":"PPL",
    "gn:name":"Badell Kili",
    "gn:population":0,
    "gn:timezone":"Asia/Karachi",
    "iso:country":"PK",
    "name:eng_x_preferred":[
        "Badail Kili"
    ],
    "wof:name":"Badell Kili",
    "wof:placetype":"locality"
},
  "geometry": {"coordinates":[67.36049,29.84431],"type":"Point"}
}