{
  "type": "Feature",
  "properties": {
    "gn:admin1_code":"4.0",
    "gn:asciiname":"Chak Six Hundred Fourteen",
    "gn:country_code":"PK",
    "gn:dem":173,
    "gn:feature_class":"P",
    "gn:feature_code":"PPL",
    "gn:name":"Chak Six Hundred Fourteen",
    "gn:population":0,
    "gn:timezone":"Asia/Karachi",
    "iso:country":"PK",
    "name:und_x_variant":[
        "Baig"
    ],
    "wof:name":"Chak Six Hundred Fourteen",
    "wof:placetype":"locality"
},
  "geometry": {"coordinates":[73.04439000000001,30.88295],"type":"Point"}
}