{
  "type": "Feature",
  "properties": {
    "gn:admin1_code":"4",
    "gn:asciiname":"Vallawala",
    "gn:country_code":"PK",
    "gn:dem":144,
    "gn:feature_class":"P",
    "gn:feature_code":"PPL",
    "gn:name":"Vallaw\u0101la",
    "gn:population":0,
    "gn:timezone":"Asia/Karachi",
    "iso:country":"PK",
    "wof:name":"Vallawala",
    "wof:placetype":"locality"
},
  "geometry": {"coordinates":[71.04583000000002,30.84167],"type":"Point"}
}