{
  "type": "Feature",
  "properties": {
    "gn:admin1_code":"4.0",
    "gn:asciiname":"Dera Mahianwala",
    "gn:country_code":"PK",
    "gn:dem":192,
    "gn:feature_class":"P",
    "gn:feature_code":"PPL",
    "gn:name":"Dera Mahianwala",
    "gn:population":0,
    "gn:timezone":"Asia/Karachi",
    "iso:country":"PK",
    "name:und_x_variant":[
        "Dera Amhi\u0101nw\u0101la"
    ],
    "wof:name":"Dera Mahianwala",
    "wof:placetype":"locality"
},
  "geometry": {"coordinates":[71.87564999999999,32.25815],"type":"Point"}
}