{
  "type": "Feature",
  "properties": {
    "gn:admin1_code":"4.0",
    "gn:asciiname":"Tarka Khelanwala",
    "gn:country_code":"PK",
    "gn:dem":267,
    "gn:feature_class":"P",
    "gn:feature_code":"PPL",
    "gn:name":"Tarka Khelanwala",
    "gn:population":0,
    "gn:timezone":"Asia/Karachi",
    "iso:country":"PK",
    "name:und_x_variant":[
        "Tarya Khel\u0101nw\u0101la",
        "Turab\u0101z Khel\u0101nw\u0101la",
        "Tarka Khelanwala"
    ],
    "wof:name":"Tarka Khelanwala",
    "wof:placetype":"locality"
},
  "geometry": {"coordinates":[71.74311999999998,32.61171],"type":"Point"}
}