{
  "type": "Feature",
  "properties": {
    "gn:admin1_code":"3.0",
    "gn:asciiname":"Naro",
    "gn:country_code":"PK",
    "gn:dem":1593,
    "gn:feature_class":"P",
    "gn:feature_code":"PPL",
    "gn:name":"Naro",
    "gn:population":0,
    "gn:timezone":"Asia/Karachi",
    "iso:country":"PK",
    "wof:name":"Naro",
    "wof:placetype":"locality"
},
  "geometry": {"coordinates":[73.11764000000002,35.46773],"type":"Point"}
}