{
  "type": "Feature",
  "properties": {
    "gn:admin1_code":"4",
    "gn:asciiname":"Thatta Dahr",
    "gn:country_code":"PK",
    "gn:dem":175,
    "gn:feature_class":"P",
    "gn:feature_code":"PPL",
    "gn:name":"Thatta Dahr",
    "gn:population":0,
    "gn:timezone":"Asia/Karachi",
    "iso:country":"PK",
    "name:und_x_variant":[
        "D\u0101war"
    ],
    "wof:name":"Thatta Dahr",
    "wof:placetype":"locality"
},
  "geometry": {"coordinates":[72.75148,31.71351],"type":"Point"}
}