{
  "type": "Feature",
  "properties": {
    "gn:admin1_code":"5.0",
    "gn:asciiname":"Goth Ahmad Saman",
    "gn:country_code":"PK",
    "gn:dem":17,
    "gn:feature_class":"P",
    "gn:feature_code":"PPL",
    "gn:name":"Goth Ahmad Saman",
    "gn:population":0,
    "gn:timezone":"Asia/Karachi",
    "iso:country":"PK",
    "name:und_x_variant":[
        "Goth Ahmad Sama"
    ],
    "wof:name":"Goth Ahmad Saman",
    "wof:placetype":"locality"
},
  "geometry": {"coordinates":[68.33821999999999,24.90591],"type":"Point"}
}