{
  "type": "Feature",
  "properties": {
    "gn:admin1_code":"5",
    "gn:asciiname":"Goth Faqir Muhammad Khokhar",
    "gn:country_code":"PK",
    "gn:dem":41,
    "gn:feature_class":"P",
    "gn:feature_code":"PPL",
    "gn:name":"Goth Faqir Muhammad Khokhar",
    "gn:population":0,
    "gn:timezone":"Asia/Karachi",
    "iso:country":"PK",
    "name:und_x_variant":[
        "Goth Khokhar"
    ],
    "wof:name":"Goth Faqir Muhammad Khokhar",
    "wof:placetype":"locality"
},
  "geometry": {"coordinates":[67.77594000000001,27.07871],"type":"Point"}
}