{
  "type": "Feature",
  "properties": {
    "gn:admin1_code":"04",
    "gn:asciiname":"Raju Pindi",
    "gn:country_code":"PK",
    "gn:dem":256,
    "gn:feature_class":"P",
    "gn:feature_code":"PPL",
    "gn:name":"Raju Pindi",
    "gn:population":0,
    "gn:timezone":"Asia/Karachi",
    "iso:country":"PK",
    "name:und_x_variant":[
        "R\u0101jo Pindi"
    ],
    "wof:name":"Raju Pindi",
    "wof:placetype":"locality"
},
  "geometry": {"coordinates":[73.56625,32.98357],"type":"Point"}
}