{
  "type": "Feature",
  "properties": {
    "gn:admin1_code":"3.0",
    "gn:asciiname":"Jamshaid Khan Kalle",
    "gn:country_code":"PK",
    "gn:dem":342,
    "gn:feature_class":"P",
    "gn:feature_code":"PPL",
    "gn:name":"Jamshaid Khan Kalle",
    "gn:population":0,
    "gn:timezone":"Asia/Karachi",
    "iso:country":"PK",
    "wof:name":"Jamshaid Khan Kalle",
    "wof:placetype":"locality"
},
  "geometry": {"coordinates":[71.92859,34.26765],"type":"Point"}
}