{
  "type": "Feature",
  "properties": {
    "gn:admin1_code":"3.0",
    "gn:asciiname":"Taikonra",
    "gn:country_code":"PK",
    "gn:dem":592,
    "gn:feature_class":"P",
    "gn:feature_code":"PPL",
    "gn:name":"Taikonra",
    "gn:population":0,
    "gn:timezone":"Asia/Karachi",
    "iso:country":"PK",
    "wof:name":"Taikonra",
    "wof:placetype":"locality"
},
  "geometry": {"coordinates":[70.89144,33.1627],"type":"Point"}
}