{
  "type": "Feature",
  "properties": {
    "gn:admin1_code":"2.0",
    "gn:asciiname":"Barkasaza",
    "gn:country_code":"PK",
    "gn:dem":2214,
    "gn:elevation":"2221.0",
    "gn:feature_class":"P",
    "gn:feature_code":"PPL",
    "gn:name":"Barkasaza",
    "gn:population":0,
    "gn:timezone":"Asia/Karachi",
    "iso:country":"PK",
    "name:und_x_variant":[
        "Baraksi\u0101za"
    ],
    "wof:name":"Barkasaza",
    "wof:placetype":"locality"
},
  "geometry": {"coordinates":[68.18115,31.05702],"type":"Point"}
}