{
  "type": "Feature",
  "properties": {
    "gn:admin1_code":"4.0",
    "gn:asciiname":"Tobewala Azam Khan Gopang",
    "gn:country_code":"PK",
    "gn:dem":98,
    "gn:feature_class":"P",
    "gn:feature_code":"PPL",
    "gn:name":"Tobew\u0101la Az\u0101m Kh\u0101n Gop\u0101ng",
    "gn:population":0,
    "gn:timezone":"Asia/Karachi",
    "iso:country":"PK",
    "wof:name":"Tobewala Azam Khan Gopang",
    "wof:placetype":"locality"
},
  "geometry": {"coordinates":[70.53445000000001,29.21675],"type":"Point"}
}