{
  "type": "Feature",
  "properties": {
    "gn:admin1_code":"4.0",
    "gn:asciiname":"Chah Hadyatwala",
    "gn:country_code":"PK",
    "gn:dem":157,
    "gn:feature_class":"P",
    "gn:feature_code":"PPL",
    "gn:name":"Chah Hadyatwala",
    "gn:population":0,
    "gn:timezone":"Asia/Karachi",
    "iso:country":"PK",
    "name:und_x_variant":[
        "Ch\u0101h Hid\u0101yaw\u0101la",
        "Ch\u0101h Hid\u0101yatw\u0101la",
        "Chah Hadyatwala"
    ],
    "wof:name":"Chah Hadyatwala",
    "wof:placetype":"locality"
},
  "geometry": {"coordinates":[72.34786,31.43271],"type":"Point"}
}