{
  "type": "Feature",
  "properties": {
    "gn:admin1_code":"3.0",
    "gn:asciiname":"Adizai",
    "gn:country_code":"PK",
    "gn:dem":311,
    "gn:feature_class":"P",
    "gn:feature_code":"PPL",
    "gn:name":"Adizai",
    "gn:population":0,
    "gn:timezone":"Asia/Karachi",
    "iso:country":"PK",
    "wof:name":"Adizai",
    "wof:placetype":"locality"
},
  "geometry": {"coordinates":[71.59591999999998,34.1615],"type":"Point"}
}