{
  "type": "Feature",
  "properties": {
    "gn:admin1_code":"2.0",
    "gn:asciiname":"Kili Sardar Khan",
    "gn:country_code":"PK",
    "gn:dem":1932,
    "gn:feature_class":"P",
    "gn:feature_code":"PPL",
    "gn:name":"Kili Sardar Khan",
    "gn:population":0,
    "gn:timezone":"Asia/Karachi",
    "iso:country":"PK",
    "wof:name":"Kili Sardar Khan",
    "wof:placetype":"locality"
},
  "geometry": {"coordinates":[68.4151,31.33999],"type":"Point"}
}