{
  "type": "Feature",
  "properties": {
    "gn:admin1_code":"5.0",
    "gn:asciiname":"Chaudary Abdus Sattar",
    "gn:country_code":"PK",
    "gn:dem":61,
    "gn:feature_class":"P",
    "gn:feature_code":"PPL",
    "gn:name":"Chaudary Abdus Sattar",
    "gn:population":0,
    "gn:timezone":"Asia/Karachi",
    "iso:country":"PK",
    "wof:name":"Chaudary Abdus Sattar",
    "wof:placetype":"locality"
},
  "geometry": {"coordinates":[69.16840999999999,27.69552],"type":"Point"}
}