{
  "type": "Feature",
  "properties": {
    "gn:admin1_code":"3",
    "gn:asciiname":"Zada Doga",
    "gn:country_code":"PK",
    "gn:dem":1102,
    "gn:feature_class":"P",
    "gn:feature_code":"PPL",
    "gn:name":"Zada Doga",
    "gn:population":0,
    "gn:timezone":"Asia/Karachi",
    "iso:country":"PK",
    "name:und_x_variant":[
        "Z\u0101da Doga"
    ],
    "wof:name":"Zada Doga",
    "wof:placetype":"locality"
},
  "geometry": {"coordinates":[72.9618,34.31214],"type":"Point"}
}