{
  "type": "Feature",
  "properties": {
    "gn:admin1_code":"2.0",
    "gn:asciiname":"Gola Ram",
    "gn:country_code":"PK",
    "gn:dem":1086,
    "gn:feature_class":"P",
    "gn:feature_code":"PPL",
    "gn:name":"Gola Ram",
    "gn:population":0,
    "gn:timezone":"Asia/Karachi",
    "iso:country":"PK",
    "wof:name":"Gola Ram",
    "wof:placetype":"locality"
},
  "geometry": {"coordinates":[63.92124,29.09456],"type":"Point"}
}