{
  "type": "Feature",
  "properties": {
    "gn:admin1_code":"4.0",
    "gn:asciiname":"Shaukatabad",
    "gn:country_code":"PK",
    "gn:dem":877,
    "gn:feature_class":"P",
    "gn:feature_code":"PPL",
    "gn:name":"Shaukatabad",
    "gn:population":0,
    "gn:timezone":"Asia/Karachi",
    "iso:country":"PK",
    "wof:name":"Shaukatabad",
    "wof:placetype":"locality"
},
  "geometry": {"coordinates":[73.12949,34.45308],"type":"Point"}
}