{
  "type": "Feature",
  "properties": {
    "gn:admin1_code":"5",
    "gn:asciiname":"Goth Shadi Bahar",
    "gn:country_code":"PK",
    "gn:dem":16,
    "gn:feature_class":"P",
    "gn:feature_code":"PPL",
    "gn:name":"Goth Shadi Bahar",
    "gn:population":0,
    "gn:timezone":"Asia/Karachi",
    "iso:country":"PK",
    "name:und_x_variant":[
        "Sh\u0101di Bahar"
    ],
    "wof:name":"Goth Shadi Bahar",
    "wof:placetype":"locality"
},
  "geometry": {"coordinates":[68.54134999999999,25.04643],"type":"Point"}
}