{
  "type": "Feature",
  "properties": {
    "gn:admin1_code":"4.0",
    "gn:asciiname":"Chak Muslim",
    "gn:country_code":"PK",
    "gn:dem":540,
    "gn:feature_class":"P",
    "gn:feature_code":"PPL",
    "gn:name":"Chak Muslim",
    "gn:population":0,
    "gn:timezone":"Asia/Karachi",
    "iso:country":"PK",
    "name:und_x_variant":[
        "Chak Brahman\u0101n"
    ],
    "wof:name":"Chak Muslim",
    "wof:placetype":"locality"
},
  "geometry": {"coordinates":[73.18770000000001,33.26124],"type":"Point"}
}