{
  "type": "Feature",
  "properties": {
    "gn:admin1_code":"04",
    "gn:asciiname":"Nurjwala",
    "gn:country_code":"PK",
    "gn:dem":196,
    "gn:feature_class":"P",
    "gn:feature_code":"PPL",
    "gn:name":"Nurjwala",
    "gn:population":0,
    "gn:timezone":"Asia/Karachi",
    "iso:country":"PK",
    "name:und_x_variant":[
        "N\u016br\u012bw\u0101la"
    ],
    "wof:name":"Nurjwala",
    "wof:placetype":"locality"
},
  "geometry": {"coordinates":[74.42963,30.98729],"type":"Point"}
}