{
  "type": "Feature",
  "properties": {
    "gn:admin1_code":"4.0",
    "gn:asciiname":"Jinnah Colony",
    "gn:country_code":"PK",
    "gn:dem":253,
    "gn:feature_class":"P",
    "gn:feature_code":"PPL",
    "gn:name":"Jinnah Colony",
    "gn:population":0,
    "gn:timezone":"Asia/Karachi",
    "iso:country":"PK",
    "wof:name":"Jinnah Colony",
    "wof:placetype":"locality"
},
  "geometry": {"coordinates":[74.24476999999997,32.66737],"type":"Point"}
}