{
  "type": "Feature",
  "properties": {
    "gn:admin1_code":"02",
    "gn:asciiname":"Salarzai",
    "gn:country_code":"PK",
    "gn:dem":1735,
    "gn:feature_class":"P",
    "gn:feature_code":"PPL",
    "gn:name":"Salarzai",
    "gn:population":0,
    "gn:timezone":"Asia/Karachi",
    "iso:country":"PK",
    "wof:name":"Salarzai",
    "wof:placetype":"locality"
},
  "geometry": {"coordinates":[66.51584,29.48984],"type":"Point"}
}