{
  "type": "Feature",
  "properties": {
    "gn:admin1_code":"5.0",
    "gn:asciiname":"Amir Bakhsh Wasan",
    "gn:country_code":"PK",
    "gn:dem":38,
    "gn:feature_class":"P",
    "gn:feature_code":"PPL",
    "gn:name":"Amir Bakhsh Wasan",
    "gn:population":0,
    "gn:timezone":"Asia/Karachi",
    "iso:country":"PK",
    "wof:name":"Amir Bakhsh Wasan",
    "wof:placetype":"locality"
},
  "geometry": {"coordinates":[68.32670999999999,26.47675],"type":"Point"}
}