{
  "type": "Feature",
  "properties": {
    "gn:admin1_code":"4.0",
    "gn:asciiname":"Kutehri",
    "gn:country_code":"PK",
    "gn:dem":1848,
    "gn:feature_class":"P",
    "gn:feature_code":"PPL",
    "gn:name":"Kutehri",
    "gn:population":0,
    "gn:timezone":"Asia/Karachi",
    "iso:country":"PK",
    "name:eng_x_preferred":[
        "Kotuhri"
    ],
    "wof:name":"Kutehri",
    "wof:placetype":"locality"
},
  "geometry": {"coordinates":[73.47062,33.8644],"type":"Point"}
}