{
  "type": "Feature",
  "properties": {
    "gn:admin1_code":"4",
    "gn:asciiname":"Roshidi",
    "gn:country_code":"PK",
    "gn:dem":176,
    "gn:feature_class":"P",
    "gn:feature_code":"PPL",
    "gn:name":"Roshidi",
    "gn:population":0,
    "gn:timezone":"Asia/Karachi",
    "iso:country":"PK",
    "name:und_x_variant":[
        "Rash\u012bdi"
    ],
    "wof:name":"Roshidi",
    "wof:placetype":"locality"
},
  "geometry": {"coordinates":[72.62698,31.74117],"type":"Point"}
}