{
  "type": "Feature",
  "properties": {
    "gn:admin1_code":"1.0",
    "gn:asciiname":"Muhammad Khel",
    "gn:country_code":"PK",
    "gn:dem":615,
    "gn:feature_class":"P",
    "gn:feature_code":"PPL",
    "gn:name":"Muhammad Khel",
    "gn:population":0,
    "gn:timezone":"Asia/Karachi",
    "iso:country":"PK",
    "name:urd_x_preferred":[
        "\u0645\u062d\u0645\u062f \u062e\u06cc\u0644"
    ],
    "wof:name":"Muhammad Khel",
    "wof:placetype":"locality"
},
  "geometry": {"coordinates":[70.49904000000002,33.20792],"type":"Point"}
}