{
  "type": "Feature",
  "properties": {
    "gn:admin1_code":"2",
    "gn:asciiname":"Kachhi Alizai",
    "gn:country_code":"PK",
    "gn:dem":1230,
    "gn:feature_class":"P",
    "gn:feature_code":"PPL",
    "gn:name":"Kachhi Alizai",
    "gn:population":0,
    "gn:timezone":"Asia/Karachi",
    "iso:country":"PK",
    "wof:name":"Kachhi Alizai",
    "wof:placetype":"locality"
},
  "geometry": {"coordinates":[68.90621999999999,30.39192],"type":"Point"}
}