{
  "type": "Feature",
  "properties": {
    "gn:admin1_code":"4.0",
    "gn:asciiname":"Jandala",
    "gn:country_code":"PK",
    "gn:dem":808,
    "gn:feature_class":"P",
    "gn:feature_code":"PPL",
    "gn:name":"Jandala",
    "gn:population":0,
    "gn:timezone":"Asia/Karachi",
    "iso:country":"PK",
    "wof:name":"Jandala",
    "wof:placetype":"locality"
},
  "geometry": {"coordinates":[73.42801999999998,33.70194],"type":"Point"}
}