{
  "type": "Feature",
  "properties": {
    "gn:admin1_code":"4",
    "gn:asciiname":"Mohra Chaudrian",
    "gn:country_code":"PK",
    "gn:dem":543,
    "gn:feature_class":"P",
    "gn:feature_code":"PPL",
    "gn:name":"Mohra Chaudrian",
    "gn:population":0,
    "gn:timezone":"Asia/Karachi",
    "iso:country":"PK",
    "name:und_x_variant":[
        "Mohra Chaudhri\u0101n"
    ],
    "wof:name":"Mohra Chaudrian",
    "wof:placetype":"locality"
},
  "geometry": {"coordinates":[73.17654,33.21236],"type":"Point"}
}