{
  "type": "Feature",
  "properties": {
    "gn:admin1_code":"3",
    "gn:asciiname":"Bar Laikot",
    "gn:country_code":"PK",
    "gn:dem":2042,
    "gn:feature_class":"P",
    "gn:feature_code":"PPL",
    "gn:name":"Bar Laikot",
    "gn:population":0,
    "gn:timezone":"Asia/Karachi",
    "iso:country":"PK",
    "name:und_x_variant":[
        "L\u0101ikot",
        "Bar Laikot"
    ],
    "wof:name":"Bar Laikot",
    "wof:placetype":"locality"
},
  "geometry": {"coordinates":[72.6003,35.39374],"type":"Point"}
}