{
  "type": "Feature",
  "properties": {
    "gn:admin1_code":"3.0",
    "gn:asciiname":"Baraian Dur",
    "gn:country_code":"PK",
    "gn:dem":2853,
    "gn:feature_class":"P",
    "gn:feature_code":"PPL",
    "gn:name":"Baraian Dur",
    "gn:population":0,
    "gn:timezone":"Asia/Karachi",
    "iso:country":"PK",
    "wof:name":"Baraian Dur",
    "wof:placetype":"locality"
},
  "geometry": {"coordinates":[72.28180999999999,36.33344],"type":"Point"}
}