{
  "type": "Feature",
  "properties": {
    "gn:admin1_code":"1.0",
    "gn:asciiname":"Khunekai",
    "gn:country_code":"PK",
    "gn:dem":2044,
    "gn:feature_class":"P",
    "gn:feature_code":"PPL",
    "gn:name":"Khunekai",
    "gn:population":0,
    "gn:timezone":"Asia/Karachi",
    "iso:country":"PK",
    "name:und_x_variant":[
        "Khunekal",
        "Khunekai"
    ],
    "wof:name":"Khunekai",
    "wof:placetype":"locality"
},
  "geometry": {"coordinates":[70.14831,33.93527],"type":"Point"}
}