{
  "type": "Feature",
  "properties": {
    "gn:admin1_code":"4.0",
    "gn:asciiname":"Basti Bechrar",
    "gn:country_code":"PK",
    "gn:dem":93,
    "gn:feature_class":"P",
    "gn:feature_code":"PPL",
    "gn:name":"Basti Bechrar",
    "gn:population":0,
    "gn:timezone":"Asia/Karachi",
    "iso:country":"PK",
    "name:urd_x_preferred":[
        "Basti Bacha Ar\u0101\u012bn"
    ],
    "wof:name":"Basti Bechrar",
    "wof:placetype":"locality"
},
  "geometry": {"coordinates":[70.58440999999998,28.77411],"type":"Point"}
}