{
  "type": "Feature",
  "properties": {
    "gn:admin1_code":"3",
    "gn:asciiname":"Zor Chel",
    "gn:country_code":"PK",
    "gn:dem":1795,
    "gn:feature_class":"P",
    "gn:feature_code":"PPL",
    "gn:name":"Zor Chel",
    "gn:population":0,
    "gn:timezone":"Asia/Karachi",
    "iso:country":"PK",
    "wof:name":"Zor Chel",
    "wof:placetype":"locality"
},
  "geometry": {"coordinates":[72.58880000000001,35.13932],"type":"Point"}
}