{
  "type": "Feature",
  "properties": {
    "gn:admin1_code":"5.0",
    "gn:asciiname":"Goth Faiz Muhammad Mahasar",
    "gn:country_code":"PK",
    "gn:dem":56,
    "gn:feature_class":"P",
    "gn:feature_code":"PPL",
    "gn:name":"Goth Faiz Muhammad Mahasar",
    "gn:population":0,
    "gn:timezone":"Asia/Karachi",
    "iso:country":"PK",
    "name:und_x_variant":[
        "Mahar"
    ],
    "wof:name":"Goth Faiz Muhammad Mahasar",
    "wof:placetype":"locality"
},
  "geometry": {"coordinates":[68.56269,27.36279],"type":"Point"}
}