{
  "type": "Feature",
  "properties": {
    "gn:admin1_code":"7.0",
    "gn:asciiname":"Sosai",
    "gn:country_code":"PK",
    "gn:dem":2495,
    "gn:feature_class":"P",
    "gn:feature_code":"PPL",
    "gn:name":"Sosai",
    "gn:population":0,
    "gn:timezone":"Asia/Karachi",
    "iso:country":"PK",
    "name:pol_x_preferred":[
        "S\u014dsai"
    ],
    "name:rus_x_preferred":[
        "\u0421\u043e\u0441\u0430\u0439"
    ],
    "name:spa_x_preferred":[
        "S\u014dsai"
    ],
    "name:ukr_x_preferred":[
        "\u0421\u043e\u0441\u0430\u0439"
    ],
    "name:und_x_variant":[
        "Sosal"
    ],
    "wof:name":"Sosai",
    "wof:placetype":"locality"
},
  "geometry": {"coordinates":[73.13118,36.16046],"type":"Point"}
}