{
  "type": "Feature",
  "properties": {
    "gn:admin1_code":"5.0",
    "gn:asciiname":"Goth Jumman Gado",
    "gn:country_code":"PK",
    "gn:dem":1,
    "gn:feature_class":"P",
    "gn:feature_code":"PPL",
    "gn:name":"Goth Jumman Gado",
    "gn:population":0,
    "gn:timezone":"Asia/Karachi",
    "iso:country":"PK",
    "wof:name":"Goth Jumman Gado",
    "wof:placetype":"locality"
},
  "geometry": {"coordinates":[67.60122,24.02542],"type":"Point"}
}