{
  "type": "Feature",
  "properties": {
    "gn:admin1_code":"6.0",
    "gn:asciiname":"Walayatabad",
    "gn:country_code":"PK",
    "gn:dem":433,
    "gn:feature_class":"P",
    "gn:feature_code":"PPL",
    "gn:name":"Walayatabad",
    "gn:population":0,
    "gn:timezone":"Asia/Karachi",
    "iso:country":"PK",
    "wof:name":"Walayatabad",
    "wof:placetype":"locality"
},
  "geometry": {"coordinates":[73.53811999999998,33.37072],"type":"Point"}
}