{
  "type": "Feature",
  "properties": {
    "gn:admin1_code":"5.0",
    "gn:asciiname":"Goth Abdul Karim Sommo",
    "gn:country_code":"PK",
    "gn:dem":22,
    "gn:feature_class":"P",
    "gn:feature_code":"PPL",
    "gn:name":"Goth Abdul Karim Sommo",
    "gn:population":0,
    "gn:timezone":"Asia/Karachi",
    "iso:country":"PK",
    "wof:name":"Goth Abdul Karim Sommo",
    "wof:placetype":"neighbourhood"
},
  "geometry": {"coordinates":[68.32612,25.44422],"type":"Point"}
}