{
  "type": "Feature",
  "properties": {
    "gn:admin1_code":"4",
    "gn:asciiname":"Chak Nineteen Western Bank",
    "gn:country_code":"PK",
    "gn:dem":143,
    "gn:feature_class":"P",
    "gn:feature_code":"PPL",
    "gn:name":"Chak Nineteen Western Bank",
    "gn:population":0,
    "gn:timezone":"Asia/Karachi",
    "iso:country":"PK",
    "name:und_x_variant":[
        "Chak Nineteen-Eight L"
    ],
    "wof:name":"Chak Nineteen Western Bank",
    "wof:placetype":"locality"
},
  "geometry": {"coordinates":[72.47081999999997,30.05972],"type":"Point"}
}