{
  "type": "Feature",
  "properties": {
    "gn:admin1_code":"4.0",
    "gn:asciiname":"Bahmankot",
    "gn:country_code":"PK",
    "gn:dem":773,
    "gn:feature_class":"P",
    "gn:feature_code":"PPL",
    "gn:name":"Bahmankot",
    "gn:population":0,
    "gn:timezone":"Asia/Karachi",
    "iso:country":"PK",
    "wof:name":"Bahmankot",
    "wof:placetype":"locality"
},
  "geometry": {"coordinates":[73.56067,33.80625999999999],"type":"Point"}
}