{
  "type": "Feature",
  "properties": {
    "gn:admin1_code":"3.0",
    "gn:asciiname":"Lal Saiyid Koruna",
    "gn:country_code":"PK",
    "gn:dem":374,
    "gn:feature_class":"P",
    "gn:feature_code":"PPL",
    "gn:name":"Lal Saiyid Koruna",
    "gn:population":0,
    "gn:timezone":"Asia/Karachi",
    "iso:country":"PK",
    "name:eng_x_preferred":[
        "Lal Saiyid Koruna"
    ],
    "wof:name":"Lal Saiyid Koruna",
    "wof:placetype":"locality"
},
  "geometry": {"coordinates":[71.79091,34.31421],"type":"Point"}
}