{
  "type": "Feature",
  "properties": {
    "gn:admin1_code":"5",
    "gn:asciiname":"Goth Jan Muhammad Nizamani",
    "gn:country_code":"PK",
    "gn:dem":16,
    "gn:feature_class":"P",
    "gn:feature_code":"PPL",
    "gn:name":"Goth Jan Muhammad Nizamani",
    "gn:population":0,
    "gn:timezone":"Asia/Karachi",
    "iso:country":"PK",
    "name:und_x_variant":[
        "Goth Gul Hassan Niz\u0101mani",
        "Muhammad Rah\u012bm Nid\u0101m\u0101ni Goth",
        "Goth Jan Muhammad Nizamani",
        "Goth Nid\u0101m\u0101ni",
        "Goth J\u0101n Muhammad Niz\u0101m\u0101ni"
    ],
    "wof:name":"Goth Jan Muhammad Nizamani",
    "wof:placetype":"locality"
},
  "geometry": {"coordinates":[68.86579,25.05018],"type":"Point"}
}