{
  "type": "Feature",
  "properties": {
    "gn:admin1_code":"4",
    "gn:asciiname":"Hussainpur",
    "gn:country_code":"PK",
    "gn:dem":224,
    "gn:feature_class":"P",
    "gn:feature_code":"PPL",
    "gn:name":"Hussainpur",
    "gn:population":0,
    "gn:timezone":"Asia/Karachi",
    "iso:country":"PK",
    "name:ben_x_preferred":[
        "\u09b9\u09c1\u09b8\u09c7\u0987\u09a8\u09aa\u09c1\u09b0"
    ],
    "name:bpy_x_preferred":[
        "\u09b9\u09c1\u09b8\u09c7\u0987\u09a8\u09aa\u09c1\u09b0"
    ],
    "name:ita_x_preferred":[
        "Hussainpur"
    ],
    "name:msa_x_preferred":[
        "Hussainpur"
    ],
    "name:new_x_preferred":[
        "\u0939\u0941\u0938\u094d\u0938\u0948\u0928\u092a\u0941\u0930"
    ],
    "name:nld_x_preferred":[
        "Hussainpur"
    ],
    "name:por_x_preferred":[
        "Hussainpur"
    ],
    "name:und_x_variant":[
        "Husainpur"
    ],
    "name:vie_x_preferred":[
        "Hussainpur"
    ],
    "name:zho_x_preferred":[
        "\u80e1\u8d5b\u6069\u666e\u5c14"
    ],
    "wof:name":"Hussainpur",
    "wof:placetype":"locality"
},
  "geometry": {"coordinates":[74.45143,32.12077],"type":"Point"}
}