{
  "type": "Feature",
  "properties": {
    "gn:admin1_code":"4",
    "gn:asciiname":"Hussainpur",
    "gn:country_code":"PK",
    "gn:dem":224,
    "gn:feature_class":"P",
    "gn:feature_code":"PPL",
    "gn:name":"Hussainpur",
    "gn:population":0,
    "gn:timezone":"Asia/Karachi",
    "iso:country":"PK",
    "name:und_x_variant":[
        "Husainpur"
    ],
    "wof:name":"Hussainpur",
    "wof:placetype":"locality"
},
  "geometry": {"coordinates":[74.45143,32.12077],"type":"Point"}
}