{
  "type": "Feature",
  "properties": {
    "gn:admin1_code":"5.0",
    "gn:asciiname":"Quarter Gard",
    "gn:country_code":"PK",
    "gn:dem":34,
    "gn:feature_class":"P",
    "gn:feature_code":"PPL",
    "gn:name":"Quarter Gard",
    "gn:population":0,
    "gn:timezone":"Asia/Karachi",
    "iso:country":"PK",
    "name:eng_x_preferred":[
        "Quarter Gard"
    ],
    "wof:name":"Quarter Gard",
    "wof:placetype":"locality"
},
  "geometry": {"coordinates":[68.37748000000001,25.35219],"type":"Point"}
}