{
  "type": "Feature",
  "properties": {
    "gn:admin1_code":"7.0",
    "gn:asciiname":"Top Baihk",
    "gn:country_code":"PK",
    "gn:dem":3511,
    "gn:feature_class":"P",
    "gn:feature_code":"PPL",
    "gn:name":"Top Baihk",
    "gn:population":0,
    "gn:timezone":"Asia/Karachi",
    "iso:country":"PK",
    "wof:name":"Top Baihk",
    "wof:placetype":"locality"
},
  "geometry": {"coordinates":[74.63835,35.19612],"type":"Point"}
}