{
  "type": "Feature",
  "properties": {
    "gn:admin1_code":"4",
    "gn:asciiname":"Basti Qureshi",
    "gn:country_code":"PK",
    "gn:dem":109,
    "gn:feature_class":"P",
    "gn:feature_code":"PPL",
    "gn:name":"Basti Qureshi",
    "gn:population":0,
    "gn:timezone":"Asia/Karachi",
    "iso:country":"PK",
    "name:und_x_variant":[
        "Basti Quraishi"
    ],
    "wof:name":"Basti Qureshi",
    "wof:placetype":"locality"
},
  "geometry": {"coordinates":[71.23595999999998,29.60787],"type":"Point"}
}