{
  "type": "Feature",
  "properties": {
    "gn:admin1_code":"4.0",
    "gn:asciiname":"Chah Dorattawala",
    "gn:country_code":"PK",
    "gn:dem":126,
    "gn:feature_class":"P",
    "gn:feature_code":"PPL",
    "gn:name":"Chah Dorattawala",
    "gn:population":0,
    "gn:timezone":"Asia/Karachi",
    "iso:country":"PK",
    "name:eng_x_preferred":[
        "Chah Dorattawala"
    ],
    "wof:name":"Chah Dorattawala",
    "wof:placetype":"locality"
},
  "geometry": {"coordinates":[70.71048,30.18076],"type":"Point"}
}