{
  "type": "Feature",
  "properties": {
    "gn:admin1_code":"04",
    "gn:asciiname":"Chak Nandna",
    "gn:country_code":"PK",
    "gn:dem":292,
    "gn:feature_class":"P",
    "gn:feature_code":"PPL",
    "gn:name":"Chak Nandna",
    "gn:population":0,
    "gn:timezone":"Asia/Karachi",
    "iso:country":"PK",
    "name:und_x_variant":[
        "Naundna",
        "N\u0101ndna",
        "Chak Nandna"
    ],
    "wof:name":"Chak Nandna",
    "wof:placetype":"locality"
},
  "geometry": {"coordinates":[73.96349000000002,32.92706],"type":"Point"}
}