{
  "type": "Feature",
  "properties": {
    "gn:admin1_code":"3",
    "gn:asciiname":"Belagai",
    "gn:country_code":"PK",
    "gn:dem":1984,
    "gn:feature_class":"P",
    "gn:feature_code":"PPL",
    "gn:name":"Belagai",
    "gn:population":0,
    "gn:timezone":"Asia/Karachi",
    "iso:country":"PK",
    "wof:name":"Belagai",
    "wof:placetype":"locality"
},
  "geometry": {"coordinates":[71.90415,35.60901],"type":"Point"}
}