{
  "type": "Feature",
  "properties": {
    "gn:admin1_code":"5.0",
    "gn:asciiname":"Saiyid Nahal Shah",
    "gn:country_code":"PK",
    "gn:dem":80,
    "gn:feature_class":"P",
    "gn:feature_code":"PPL",
    "gn:name":"Saiyid Nahal Shah",
    "gn:population":0,
    "gn:timezone":"Asia/Karachi",
    "iso:country":"PK",
    "wof:name":"Saiyid Nahal Shah",
    "wof:placetype":"locality"
},
  "geometry": {"coordinates":[69.71963000000001,28.3945],"type":"Point"}
}