{
  "type": "Feature",
  "properties": {
    "gn:admin1_code":"04",
    "gn:asciiname":"Saidpur",
    "gn:country_code":"PK",
    "gn:dem":472,
    "gn:feature_class":"P",
    "gn:feature_code":"PPL",
    "gn:name":"Saidpur",
    "gn:population":0,
    "gn:timezone":"Asia/Karachi",
    "iso:country":"PK",
    "name:und_x_variant":[
        "Saiyidpur"
    ],
    "wof:name":"Saidpur",
    "wof:placetype":"locality"
},
  "geometry": {"coordinates":[73.05183000000002,32.86364],"type":"Point"}
}