{
  "type": "Feature",
  "properties": {
    "gn:admin1_code":"5.0",
    "gn:asciiname":"Goth Allu Baran",
    "gn:country_code":"PK",
    "gn:dem":8,
    "gn:feature_class":"P",
    "gn:feature_code":"PPL",
    "gn:name":"Goth Allu Baran",
    "gn:population":0,
    "gn:timezone":"Asia/Karachi",
    "iso:country":"PK",
    "name:eng_x_preferred":[
        "Goth Allu Baran"
    ],
    "wof:name":"Goth Allu Baran",
    "wof:placetype":"locality"
},
  "geometry": {"coordinates":[68.15661,24.59214],"type":"Point"}
}