{
  "type": "Feature",
  "properties": {
    "gn:admin1_code":"5.0",
    "gn:asciiname":"Bhutti Lashkar Khan",
    "gn:country_code":"PK",
    "gn:dem":44,
    "gn:feature_class":"P",
    "gn:feature_code":"PPL",
    "gn:name":"Bhutti Lashkar Khan",
    "gn:population":0,
    "gn:timezone":"Asia/Karachi",
    "iso:country":"PK",
    "name:und_x_variant":[
        "Lashkar Kh\u0101n Panni"
    ],
    "wof:name":"Bhutti Lashkar Khan",
    "wof:placetype":"locality"
},
  "geometry": {"coordinates":[67.75674000000001,27.57791],"type":"Point"}
}