{
  "type": "Feature",
  "properties": {
    "gn:admin1_code":"4.0",
    "gn:asciiname":"Dhok Ghulam Khan",
    "gn:country_code":"PK",
    "gn:dem":343,
    "gn:feature_class":"P",
    "gn:feature_code":"PPL",
    "gn:name":"Dhok Ghulam Khan",
    "gn:population":0,
    "gn:timezone":"Asia/Karachi",
    "iso:country":"PK",
    "name:und_x_variant":[
        "Dhok Ghulan Kh\u0101n"
    ],
    "wof:name":"Dhok Ghulam Khan",
    "wof:placetype":"neighbourhood"
},
  "geometry": {"coordinates":[72.34757,33.75773],"type":"Point"}
}