{
  "type": "Feature",
  "properties": {
    "gn:admin1_code":"3.0",
    "gn:asciiname":"Wasi Khel Kalle",
    "gn:country_code":"PK",
    "gn:dem":327,
    "gn:feature_class":"P",
    "gn:feature_code":"PPL",
    "gn:name":"Wasi Khel Kalle",
    "gn:population":0,
    "gn:timezone":"Asia/Karachi",
    "iso:country":"PK",
    "wof:name":"Wasi Khel Kalle",
    "wof:placetype":"locality"
},
  "geometry": {"coordinates":[70.4555,32.46255],"type":"Point"}
}