{
  "type": "Feature",
  "properties": {
    "gn:admin1_code":"4.0",
    "gn:asciiname":"Khokranwala",
    "gn:country_code":"PK",
    "gn:dem":198,
    "gn:feature_class":"P",
    "gn:feature_code":"PPL",
    "gn:name":"Khokranwala",
    "gn:population":0,
    "gn:timezone":"Asia/Karachi",
    "iso:country":"PK",
    "wof:name":"Khokranwala",
    "wof:placetype":"locality"
},
  "geometry": {"coordinates":[71.46488000000002,32.23953],"type":"Point"}
}