{
  "type": "Feature",
  "properties": {
    "gn:admin1_code":"04",
    "gn:asciiname":"Pumali",
    "gn:country_code":"PK",
    "gn:dem":297,
    "gn:feature_class":"P",
    "gn:feature_code":"PPL",
    "gn:name":"Pumali",
    "gn:population":0,
    "gn:timezone":"Asia/Karachi",
    "iso:country":"PK",
    "name:und_x_variant":[
        "Pormali",
        "Prumali",
        "Pumali"
    ],
    "wof:name":"Pumali",
    "wof:placetype":"locality"
},
  "geometry": {"coordinates":[72.35783000000001,33.92202],"type":"Point"}
}