{
  "type": "Feature",
  "properties": {
    "gn:admin1_code":"2.0",
    "gn:asciiname":"Mozo Sanaullah",
    "gn:country_code":"PK",
    "gn:dem":939,
    "gn:feature_class":"P",
    "gn:feature_code":"PPL",
    "gn:name":"Mozo Sanaullah",
    "gn:population":0,
    "gn:timezone":"Asia/Karachi",
    "iso:country":"PK",
    "wof:name":"Mozo Sanaullah",
    "wof:placetype":"locality"
},
  "geometry": {"coordinates":[67.02375000000001,27.7683],"type":"Point"}
}