{
  "type": "Feature",
  "properties": {
    "gn:admin1_code":"4",
    "gn:asciiname":"Kotli Chhambwali",
    "gn:country_code":"PK",
    "gn:dem":234,
    "gn:feature_class":"P",
    "gn:feature_code":"PPL",
    "gn:name":"Kotli Chhambwali",
    "gn:population":0,
    "gn:timezone":"Asia/Karachi",
    "iso:country":"PK",
    "name:und_x_variant":[
        "Kotli Chhamb"
    ],
    "wof:name":"Kotli Chhambwali",
    "wof:placetype":"locality"
},
  "geometry": {"coordinates":[74.39549,32.32513],"type":"Point"}
}