{
  "type": "Feature",
  "properties": {
    "gn:admin1_code":"3",
    "gn:asciiname":"Mohri",
    "gn:country_code":"PK",
    "gn:dem":696,
    "gn:feature_class":"P",
    "gn:feature_code":"PPL",
    "gn:name":"Mohri",
    "gn:population":0,
    "gn:timezone":"Asia/Karachi",
    "iso:country":"PK",
    "wof:name":"Mohri",
    "wof:placetype":"locality"
},
  "geometry": {"coordinates":[73.04026,34.00169],"type":"Point"}
}