{
  "type": "Feature",
  "properties": {
    "gn:admin1_code":"4",
    "gn:asciiname":"Kakrawala",
    "gn:country_code":"PK",
    "gn:dem":195,
    "gn:feature_class":"P",
    "gn:feature_code":"PPL",
    "gn:name":"Kakr\u0101w\u0101la",
    "gn:population":0,
    "gn:timezone":"Asia/Karachi",
    "iso:country":"PK",
    "wof:name":"Kakrawala",
    "wof:placetype":"locality"
},
  "geometry": {"coordinates":[71.69167,32.05972],"type":"Point"}
}