{
  "type": "Feature",
  "properties": {
    "gn:admin1_code":"1.0",
    "gn:asciiname":"Kumbar",
    "gn:country_code":"PK",
    "gn:dem":2511,
    "gn:feature_class":"P",
    "gn:feature_code":"PPLL",
    "gn:name":"Kumbar",
    "gn:population":0,
    "gn:timezone":"Asia/Karachi",
    "iso:country":"PK",
    "wof:name":"Kumbar",
    "wof:placetype":"locality"
},
  "geometry": {"coordinates":[69.42746,32.56676],"type":"Point"}
}