{
  "type": "Feature",
  "properties": {
    "gn:admin1_code":"6",
    "gn:asciiname":"Changan",
    "gn:country_code":"PK",
    "gn:dem":2067,
    "gn:feature_class":"P",
    "gn:feature_code":"PPL",
    "gn:name":"Changan",
    "gn:population":0,
    "gn:timezone":"Asia/Karachi",
    "iso:country":"PK",
    "wof:name":"Changan",
    "wof:placetype":"locality"
},
  "geometry": {"coordinates":[74.07556,34.71934],"type":"Point"}
}