{
  "type": "Feature",
  "properties": {
    "gn:admin1_code":"4",
    "gn:asciiname":"Chak One Hundred Thirty-five",
    "gn:country_code":"PK",
    "gn:dem":191,
    "gn:feature_class":"P",
    "gn:feature_code":"PPL",
    "gn:name":"Chak One Hundred Thirty-five",
    "gn:population":0,
    "gn:timezone":"Asia/Karachi",
    "iso:country":"PK",
    "name:und_x_variant":[
        "Kandan Si\u0101n",
        "Kanansi\u0101n"
    ],
    "wof:name":"Chak One Hundred Thirty-five",
    "wof:placetype":"locality"
},
  "geometry": {"coordinates":[73.20851,31.70821],"type":"Point"}
}