{
  "type": "Feature",
  "properties": {
    "gn:admin1_code":"6.0",
    "gn:asciiname":"Jhala",
    "gn:country_code":"PK",
    "gn:dem":957,
    "gn:feature_class":"P",
    "gn:feature_code":"PPL",
    "gn:name":"Jhala",
    "gn:population":0,
    "gn:timezone":"Asia/Karachi",
    "iso:country":"PK",
    "name:nld_x_preferred":[
        "Jhala"
    ],
    "name:spa_x_preferred":[
        "Jhala"
    ],
    "wof:name":"Jhala",
    "wof:placetype":"locality"
},
  "geometry": {"coordinates":[73.57498000000002,33.92733],"type":"Point"}
}