{
  "type": "Feature",
  "properties": {
    "gn:admin1_code":"3.0",
    "gn:asciiname":"Khanjare",
    "gn:country_code":"PK",
    "gn:dem":416,
    "gn:feature_class":"P",
    "gn:feature_code":"PPL",
    "gn:name":"Khanjare",
    "gn:population":0,
    "gn:timezone":"Asia/Karachi",
    "iso:country":"PK",
    "name:eng_x_preferred":[
        "Kh\u0101ni\u0101ri"
    ],
    "name:und_x_variant":[
        "Khanj\u0101ri",
        "Khanjare"
    ],
    "wof:name":"Khanjare",
    "wof:placetype":"locality"
},
  "geometry": {"coordinates":[71.72816,34.37384],"type":"Point"}
}