{
  "type": "Feature",
  "properties": {
    "gn:admin1_code":"3",
    "gn:asciiname":"Tandara Kalan",
    "gn:country_code":"PK",
    "gn:dem":740,
    "gn:feature_class":"P",
    "gn:feature_code":"PPL",
    "gn:name":"Tandara Kalan",
    "gn:population":0,
    "gn:timezone":"Asia/Karachi",
    "iso:country":"PK",
    "name:und_x_variant":[
        "Dhand\u0101ra Kal\u0101n"
    ],
    "wof:name":"Tandara Kalan",
    "wof:placetype":"locality"
},
  "geometry": {"coordinates":[73.04594,34.19307],"type":"Point"}
}