{
  "type": "Feature",
  "properties": {
    "gn:admin1_code":"2",
    "gn:asciiname":"Goth Allahyar Khan",
    "gn:country_code":"PK",
    "gn:dem":121,
    "gn:feature_class":"P",
    "gn:feature_code":"PPL",
    "gn:name":"Goth Allahyar Khan",
    "gn:population":0,
    "gn:timezone":"Asia/Karachi",
    "iso:country":"PK",
    "name:und_x_variant":[
        "Goth All\u0101y\u0101r Kh\u0101n"
    ],
    "wof:name":"Goth Allahyar Khan",
    "wof:placetype":"locality"
},
  "geometry": {"coordinates":[67.81089,29.36211],"type":"Point"}
}