{
  "type": "Feature",
  "properties": {
    "gn:admin1_code":"2.0",
    "gn:asciiname":"Haji Rustum",
    "gn:country_code":"PK",
    "gn:dem":666,
    "gn:feature_class":"P",
    "gn:feature_code":"PPL",
    "gn:name":"Haji Rustum",
    "gn:population":0,
    "gn:timezone":"Asia/Karachi",
    "iso:country":"PK",
    "wof:name":"Haji Rustum",
    "wof:placetype":"locality"
},
  "geometry": {"coordinates":[65.16618000000001,28.33021],"type":"Point"}
}