{
  "type": "Feature",
  "properties": {
    "gn:admin1_code":"3.0",
    "gn:asciiname":"Mehrdil",
    "gn:country_code":"PK",
    "gn:dem":307,
    "gn:feature_class":"P",
    "gn:feature_code":"PPL",
    "gn:name":"Mehrdil",
    "gn:population":0,
    "gn:timezone":"Asia/Karachi",
    "iso:country":"PK",
    "wof:name":"Mehrdil",
    "wof:placetype":"locality"
},
  "geometry": {"coordinates":[70.75194,32.83167],"type":"Point"}
}