{
  "type": "Feature",
  "properties": {
    "gn:admin1_code":"3",
    "gn:asciiname":"Mundi Maira",
    "gn:country_code":"PK",
    "gn:dem":721,
    "gn:feature_class":"P",
    "gn:feature_code":"PPL",
    "gn:name":"Mundi Maira",
    "gn:population":0,
    "gn:timezone":"Asia/Karachi",
    "iso:country":"PK",
    "name:und_x_variant":[
        "Mundi Mali\u0101ra"
    ],
    "wof:name":"Mundi Maira",
    "wof:placetype":"locality"
},
  "geometry": {"coordinates":[72.97674000000001,34.28052],"type":"Point"}
}