{
  "type": "Feature",
  "properties": {
    "gn:admin1_code":"5.0",
    "gn:asciiname":"Jhan Kar jo Tar",
    "gn:country_code":"PK",
    "gn:dem":24,
    "gn:feature_class":"P",
    "gn:feature_code":"PPL",
    "gn:name":"Jhan Kar jo Tar",
    "gn:population":0,
    "gn:timezone":"Asia/Karachi",
    "iso:country":"PK",
    "wof:name":"Jhan Kar jo Tar",
    "wof:placetype":"locality"
},
  "geometry": {"coordinates":[69.66764999999999,24.44152],"type":"Point"}
}