{
  "type": "Feature",
  "properties": {
    "gn:admin1_code":"4",
    "gn:asciiname":"Qila Mian Singh",
    "gn:country_code":"PK",
    "gn:dem":200,
    "gn:feature_class":"P",
    "gn:feature_code":"PPL",
    "gn:name":"Qila Mian Singh",
    "gn:population":0,
    "gn:timezone":"Asia/Karachi",
    "iso:country":"PK",
    "wof:name":"Qila Mian Singh",
    "wof:placetype":"locality"
},
  "geometry": {"coordinates":[73.92274999999999,31.36589],"type":"Point"}
}