{
  "type": "Feature",
  "properties": {
    "gn:admin1_code":"2.0",
    "gn:asciiname":"Ahmad Wal",
    "gn:country_code":"PK",
    "gn:dem":904,
    "gn:feature_class":"P",
    "gn:feature_code":"PPL",
    "gn:name":"Ahmad Wal",
    "gn:population":0,
    "gn:timezone":"Asia/Karachi",
    "iso:country":"PK",
    "name:und_x_variant":[
        "Ahmedwal Killi",
        "Ahmad Wal"
    ],
    "wof:name":"Ahmad Wal",
    "wof:placetype":"locality"
},
  "geometry": {"coordinates":[65.93635,29.42217],"type":"Point"}
}