{
  "type": "Feature",
  "properties": {
    "gn:admin1_code":"4",
    "gn:asciiname":"Lodhranwala",
    "gn:country_code":"PK",
    "gn:dem":146,
    "gn:feature_class":"P",
    "gn:feature_code":"PPL",
    "gn:name":"Lodhranwala",
    "gn:population":0,
    "gn:timezone":"Asia/Karachi",
    "iso:country":"PK",
    "name:und_x_variant":[
        "Ladhr\u0101nw\u0101la"
    ],
    "wof:name":"Lodhranwala",
    "wof:placetype":"locality"
},
  "geometry": {"coordinates":[71.50010999999998,30.97143],"type":"Point"}
}