{
  "type": "Feature",
  "properties": {
    "gn:admin1_code":"7.0",
    "gn:asciiname":"Dih",
    "gn:country_code":"PK",
    "gn:dem":5031,
    "gn:feature_class":"P",
    "gn:feature_code":"PPL",
    "gn:name":"Dih",
    "gn:population":0,
    "gn:timezone":"Asia/Karachi",
    "iso:country":"PK",
    "wof:name":"Dih",
    "wof:placetype":"locality"
},
  "geometry": {"coordinates":[75.25855,36.64877],"type":"Point"}
}