{
  "type": "Feature",
  "properties": {
    "gn:admin1_code":"3",
    "gn:asciiname":"Chhambar",
    "gn:country_code":"PK",
    "gn:dem":2253,
    "gn:feature_class":"P",
    "gn:feature_code":"PPL",
    "gn:name":"Chhambar",
    "gn:population":0,
    "gn:timezone":"Asia/Karachi",
    "iso:country":"PK",
    "name:und_x_variant":[
        "Chahmra"
    ],
    "wof:name":"Chhambar",
    "wof:placetype":"locality"
},
  "geometry": {"coordinates":[73.37738,34.63848],"type":"Point"}
}