{
  "type": "Feature",
  "properties": {
    "gn:admin1_code":"7",
    "gn:asciiname":"Umbulung",
    "gn:country_code":"PK",
    "gn:dem":3805,
    "gn:feature_class":"P",
    "gn:feature_code":"PPL",
    "gn:name":"Umbulung",
    "gn:population":0,
    "gn:timezone":"Asia/Karachi",
    "iso:country":"PK",
    "wof:name":"Umbulung",
    "wof:placetype":"locality"
},
  "geometry": {"coordinates":[76.17107,34.66501],"type":"Point"}
}