{
  "type": "Feature",
  "properties": {
    "gn:admin1_code":"4",
    "gn:asciiname":"Dabli Ranjha Khan",
    "gn:country_code":"PK",
    "gn:dem":141,
    "gn:feature_class":"P",
    "gn:feature_code":"PPL",
    "gn:name":"Dabli Ranjha Khan",
    "gn:population":0,
    "gn:timezone":"Asia/Karachi",
    "iso:country":"PK",
    "name:und_x_variant":[
        "Dabli R\u0101njhe Kh\u0101n"
    ],
    "wof:name":"Dabli Ranjha Khan",
    "wof:placetype":"locality"
},
  "geometry": {"coordinates":[70.88081,30.72629],"type":"Point"}
}