{
  "type": "Feature",
  "properties": {
    "gn:admin1_code":"2.0",
    "gn:asciiname":"Raziq Khan Umrani",
    "gn:country_code":"PK",
    "gn:dem":66,
    "gn:feature_class":"P",
    "gn:feature_code":"PPL",
    "gn:name":"Raziq Khan Umrani",
    "gn:population":0,
    "gn:timezone":"Asia/Karachi",
    "iso:country":"PK",
    "wof:name":"Raziq Khan Umrani",
    "wof:placetype":"locality"
},
  "geometry": {"coordinates":[68.35921999999999,28.5146],"type":"Point"}
}