{
  "type": "Feature",
  "properties": {
    "gn:admin1_code":"04",
    "gn:asciiname":"Targa",
    "gn:country_code":"PK",
    "gn:dem":208,
    "gn:feature_class":"P",
    "gn:feature_code":"PPL",
    "gn:name":"Targa",
    "gn:population":0,
    "gn:timezone":"Asia/Karachi",
    "iso:country":"PK",
    "name:cat_x_preferred":[
        "Targa"
    ],
    "name:ceb_x_preferred":[
        "Targa"
    ],
    "name:ces_x_preferred":[
        "Targa"
    ],
    "name:deu_x_preferred":[
        "Targa"
    ],
    "name:fra_x_preferred":[
        "Targa"
    ],
    "name:ita_x_preferred":[
        "Targa"
    ],
    "name:nld_x_preferred":[
        "Targa"
    ],
    "name:swe_x_preferred":[
        "Targa"
    ],
    "wof:name":"Targa",
    "wof:placetype":"locality"
},
  "geometry": {"coordinates":[74.51666999999998,31.16667],"type":"Point"}
}