{
  "type": "Feature",
  "properties": {
    "gn:admin1_code":"5.0",
    "gn:asciiname":"Ahori",
    "gn:country_code":"PK",
    "gn:dem":43,
    "gn:feature_class":"P",
    "gn:feature_code":"PPL",
    "gn:name":"Ahori",
    "gn:population":0,
    "gn:timezone":"Asia/Karachi",
    "iso:country":"PK",
    "name:und_x_variant":[
        "\u0100hori"
    ],
    "wof:name":"Ahori",
    "wof:placetype":"locality"
},
  "geometry": {"coordinates":[67.64029000000001,27.02084],"type":"Point"}
}