{
  "type": "Feature",
  "properties": {
    "gn:admin1_code":"4",
    "gn:asciiname":"Diali",
    "gn:country_code":"PK",
    "gn:dem":513,
    "gn:feature_class":"P",
    "gn:feature_code":"PPL",
    "gn:name":"Diali",
    "gn:population":0,
    "gn:timezone":"Asia/Karachi",
    "iso:country":"PK",
    "wof:name":"Diali",
    "wof:placetype":"locality"
},
  "geometry": {"coordinates":[73.33069999999999,33.08844000000001],"type":"Point"}
}