{
  "type": "Feature",
  "properties": {
    "gn:admin1_code":"4",
    "gn:asciiname":"Chah Musawala",
    "gn:country_code":"PK",
    "gn:dem":86,
    "gn:feature_class":"P",
    "gn:feature_code":"PPL",
    "gn:name":"Chah Musawala",
    "gn:population":0,
    "gn:timezone":"Asia/Karachi",
    "iso:country":"PK",
    "name:und_x_variant":[
        "M\u016bsaw\u0101la Khu"
    ],
    "wof:name":"Chah Musawala",
    "wof:placetype":"locality"
},
  "geometry": {"coordinates":[70.57857,28.50722],"type":"Point"}
}