{
  "type": "Feature",
  "properties": {
    "gn:admin1_code":"3",
    "gn:asciiname":"Sarmato",
    "gn:country_code":"PK",
    "gn:dem":1810,
    "gn:feature_class":"P",
    "gn:feature_code":"PPL",
    "gn:name":"Sarmato",
    "gn:population":0,
    "gn:timezone":"Asia/Karachi",
    "iso:country":"PK",
    "name:eng_x_preferred":[
        "Sarmato"
    ],
    "wof:name":"Sarmato",
    "wof:placetype":"locality"
},
  "geometry": {"coordinates":[71.9573,35.24668],"type":"Point"}
}