{
  "type": "Feature",
  "properties": {
    "gn:admin1_code":"3",
    "gn:asciiname":"Sarmato",
    "gn:country_code":"PK",
    "gn:dem":1810,
    "gn:feature_class":"P",
    "gn:feature_code":"PPL",
    "gn:name":"Sarmato",
    "gn:population":0,
    "gn:timezone":"Asia/Karachi",
    "iso:country":"PK",
    "name:ara_x_preferred":[
        "\u0633\u0627\u0631\u0645\u0627\u062a\u0648"
    ],
    "name:azb_x_preferred":[
        "\u0633\u0627\u0631\u0645\u0627\u062a\u0648"
    ],
    "name:bul_x_preferred":[
        "\u0421\u0430\u0440\u043c\u0430\u0442\u043e"
    ],
    "name:ceb_x_preferred":[
        "Sarmato"
    ],
    "name:deu_x_preferred":[
        "Sarmato"
    ],
    "name:eml_x_preferred":[
        "S\u00e4rmat"
    ],
    "name:eng_x_preferred":[
        "Sarmato"
    ],
    "name:epo_x_preferred":[
        "Sarmato"
    ],
    "name:eus_x_preferred":[
        "Sarmato"
    ],
    "name:fas_x_preferred":[
        "\u0633\u0627\u0631\u0645\u0627\u062a\u0648"
    ],
    "name:fra_x_preferred":[
        "Sarmato"
    ],
    "name:hun_x_preferred":[
        "Sarmato"
    ],
    "name:hye_x_preferred":[
        "\u054d\u0561\u0580\u0574\u0561\u057f\u0578"
    ],
    "name:ina_x_preferred":[
        "Sarmato"
    ],
    "name:ita_x_preferred":[
        "Sarmato"
    ],
    "name:jpn_x_preferred":[
        "\u30b5\u30eb\u30de\u30c8"
    ],
    "name:kaz_x_preferred":[
        "\u0421\u0430\u0440\u043c\u0430\u0442\u043e"
    ],
    "name:kik_x_preferred":[
        "Sarmato"
    ],
    "name:lat_x_preferred":[
        "Curtis Sarmadas"
    ],
    "name:lmo_x_preferred":[
        "Sarmat"
    ],
    "name:msa_x_preferred":[
        "Sarmato"
    ],
    "name:nap_x_preferred":[
        "Sarmato"
    ],
    "name:nld_x_preferred":[
        "Sarmato"
    ],
    "name:pms_x_preferred":[
        "Sarmato"
    ],
    "name:pol_x_preferred":[
        "Sarmato"
    ],
    "name:por_x_preferred":[
        "Sarmato"
    ],
    "name:ron_x_preferred":[
        "Sarmato"
    ],
    "name:rus_x_preferred":[
        "\u0421\u0430\u0440\u043c\u0430\u0442\u043e"
    ],
    "name:spa_x_preferred":[
        "Sarmato"
    ],
    "name:srp_x_preferred":[
        "\u0421\u0430\u0440\u043c\u0430\u0442\u043e"
    ],
    "name:tur_x_preferred":[
        "Sarmato"
    ],
    "name:ukr_x_preferred":[
        "\u0421\u0430\u0440\u043c\u0430\u0442\u043e"
    ],
    "name:uzb_x_preferred":[
        "Sarmato"
    ],
    "name:vol_x_preferred":[
        "Sarmato"
    ],
    "name:war_x_preferred":[
        "Sarmato"
    ],
    "name:zho_x_preferred":[
        "\u8428\u5c14\u9a6c\u6258"
    ],
    "wof:name":"Sarmato",
    "wof:placetype":"locality"
},
  "geometry": {"coordinates":[71.9573,35.24668],"type":"Point"}
}