{
  "type": "Feature",
  "properties": {
    "gn:admin1_code":"4.0",
    "gn:asciiname":"Bahadurwala Khu",
    "gn:country_code":"PK",
    "gn:dem":136,
    "gn:feature_class":"P",
    "gn:feature_code":"PPL",
    "gn:name":"Bahadurwala Khu",
    "gn:population":0,
    "gn:timezone":"Asia/Karachi",
    "iso:country":"PK",
    "name:und_x_variant":[
        "Pattal Munda"
    ],
    "wof:name":"Bahadurwala Khu",
    "wof:placetype":"locality"
},
  "geometry": {"coordinates":[71.35596,30.60279],"type":"Point"}
}