{
  "type": "Feature",
  "properties": {
    "gn:admin1_code":"5",
    "gn:asciiname":"Goth Long Faqir",
    "gn:country_code":"PK",
    "gn:dem":50,
    "gn:feature_class":"P",
    "gn:feature_code":"PPL",
    "gn:name":"Goth Long Faqir",
    "gn:population":0,
    "gn:timezone":"Asia/Karachi",
    "iso:country":"PK",
    "name:und_x_variant":[
        "Jumman Halepota"
    ],
    "wof:name":"Goth Long Faqir",
    "wof:placetype":"locality"
},
  "geometry": {"coordinates":[68.83891,27.46731],"type":"Point"}
}