{
  "type": "Feature",
  "properties": {
    "gn:admin1_code":"01",
    "gn:asciiname":"Jani Khel",
    "gn:country_code":"PK",
    "gn:dem":2216,
    "gn:feature_class":"P",
    "gn:feature_code":"PPL",
    "gn:name":"Jani Khel",
    "gn:population":0,
    "gn:timezone":"Asia/Karachi",
    "iso:country":"PK",
    "wof:name":"Jani Khel",
    "wof:placetype":"locality"
},
  "geometry": {"coordinates":[69.59392,32.71773],"type":"Point"}
}