{
  "type": "Feature",
  "properties": {
    "gn:admin1_code":"3.0",
    "gn:asciiname":"Sipri",
    "gn:country_code":"PK",
    "gn:dem":913,
    "gn:feature_class":"P",
    "gn:feature_code":"PPL",
    "gn:name":"Sipri",
    "gn:population":0,
    "gn:timezone":"Asia/Karachi",
    "iso:country":"PK",
    "name:und_x_variant":[
        "Chapri"
    ],
    "wof:name":"Sipri",
    "wof:placetype":"locality"
},
  "geometry": {"coordinates":[71.39119000000002,33.14605],"type":"Point"}
}