{
  "type": "Feature",
  "properties": {
    "gn:admin1_code":"5.0",
    "gn:asciiname":"Goth Siraj Punjabi",
    "gn:country_code":"PK",
    "gn:dem":52,
    "gn:feature_class":"P",
    "gn:feature_code":"PPL",
    "gn:name":"Goth Siraj Punjabi",
    "gn:population":0,
    "gn:timezone":"Asia/Karachi",
    "iso:country":"PK",
    "name:und_x_variant":[
        "Goth Muhammad S\u0101leh Brah\u016bi"
    ],
    "wof:name":"Goth Siraj Punjabi",
    "wof:placetype":"locality"
},
  "geometry": {"coordinates":[68.05596,27.80782],"type":"Point"}
}