{
  "type": "Feature",
  "properties": {
    "gn:admin1_code":"2.0",
    "gn:asciiname":"Zharanz Khwar Kili",
    "gn:country_code":"PK",
    "gn:dem":1790,
    "gn:feature_class":"P",
    "gn:feature_code":"PPL",
    "gn:name":"Zharanz Khwar Kili",
    "gn:population":0,
    "gn:timezone":"Asia/Karachi",
    "iso:country":"PK",
    "name:und_x_variant":[
        "Yaranz Khwar Kili"
    ],
    "wof:name":"Zharanz Khwar Kili",
    "wof:placetype":"locality"
},
  "geometry": {"coordinates":[69.35001,30.83094],"type":"Point"}
}