{
  "type": "Feature",
  "properties": {
    "gn:admin1_code":"8.0",
    "gn:asciiname":"Mal",
    "gn:country_code":"PK",
    "gn:dem":528,
    "gn:feature_class":"P",
    "gn:feature_code":"PPL",
    "gn:name":"Mal",
    "gn:population":0,
    "gn:timezone":"Asia/Karachi",
    "iso:country":"PK",
    "wof:name":"Mal",
    "wof:placetype":"locality"
},
  "geometry": {"coordinates":[73.21847,33.70107],"type":"Point"}
}