{
  "type": "Feature",
  "properties": {
    "gn:admin1_code":"3.0",
    "gn:asciiname":"Bhati",
    "gn:country_code":"PK",
    "gn:dem":820,
    "gn:feature_class":"P",
    "gn:feature_code":"PPL",
    "gn:name":"Bhati",
    "gn:population":0,
    "gn:timezone":"Asia/Karachi",
    "iso:country":"PK",
    "name:eng_x_preferred":[
        "Bhati"
    ],
    "wof:name":"Bhati",
    "wof:placetype":"locality"
},
  "geometry": {"coordinates":[73.10649000000002,33.8761],"type":"Point"}
}