{
  "type": "Feature",
  "properties": {
    "gn:admin1_code":"3.0",
    "gn:asciiname":"Bala Garhi",
    "gn:country_code":"PK",
    "gn:dem":311,
    "gn:feature_class":"P",
    "gn:feature_code":"PPL",
    "gn:name":"Bala Garhi",
    "gn:population":0,
    "gn:timezone":"Asia/Karachi",
    "iso:country":"PK",
    "name:eng_x_preferred":[
        "B\u0101l\u0101garhi"
    ],
    "name:urd_x_preferred":[
        "\u0628\u0627\u0644\u0627 \u06af\u0691\u06be\u06cc"
    ],
    "wof:name":"Bala Garhi",
    "wof:placetype":"locality"
},
  "geometry": {"coordinates":[72.15069,34.22765],"type":"Point"}
}