{
  "type": "Feature",
  "properties": {
    "gn:admin1_code":"4",
    "gn:asciiname":"Chah Khadamwala",
    "gn:country_code":"PK",
    "gn:dem":133,
    "gn:feature_class":"P",
    "gn:feature_code":"PPL",
    "gn:name":"Chah Khadamwala",
    "gn:population":0,
    "gn:timezone":"Asia/Karachi",
    "iso:country":"PK",
    "name:und_x_variant":[
        "Buiw\u0101la"
    ],
    "wof:name":"Chah Khadamwala",
    "wof:placetype":"locality"
},
  "geometry": {"coordinates":[71.28386999999999,30.50955],"type":"Point"}
}