{
  "type": "Feature",
  "properties": {
    "gn:admin1_code":"4.0",
    "gn:asciiname":"Dhingar",
    "gn:country_code":"PK",
    "gn:dem":250,
    "gn:feature_class":"P",
    "gn:feature_code":"PPL",
    "gn:name":"Dhingar",
    "gn:population":0,
    "gn:timezone":"Asia/Karachi",
    "iso:country":"PK",
    "name:und_x_variant":[
        "Dhinger",
        "Dhingar"
    ],
    "wof:name":"Dhingar",
    "wof:placetype":"locality"
},
  "geometry": {"coordinates":[75.13987,32.1429],"type":"Point"}
}