{
  "type": "Feature",
  "properties": {
    "gn:admin1_code":"7.0",
    "gn:asciiname":"Minkial Baihk",
    "gn:country_code":"PK",
    "gn:dem":3667,
    "gn:feature_class":"P",
    "gn:feature_code":"PPL",
    "gn:name":"Minkial Baihk",
    "gn:population":0,
    "gn:timezone":"Asia/Karachi",
    "iso:country":"PK",
    "wof:name":"Minkial Baihk",
    "wof:placetype":"locality"
},
  "geometry": {"coordinates":[74.88535999999998,35.29685999999999],"type":"Point"}
}