{
  "type": "Feature",
  "properties": {
    "gn:admin1_code":"4.0",
    "gn:asciiname":"Kakar Kalan",
    "gn:country_code":"PK",
    "gn:dem":170,
    "gn:feature_class":"P",
    "gn:feature_code":"PPL",
    "gn:name":"Kakar Kalan",
    "gn:population":0,
    "gn:timezone":"Asia/Karachi",
    "iso:country":"PK",
    "name:und_x_variant":[
        "Kakkar Kal\u0101n"
    ],
    "wof:name":"Kakar Kalan",
    "wof:placetype":"locality"
},
  "geometry": {"coordinates":[72.78333000000001,31.15],"type":"Point"}
}