{
  "type": "Feature",
  "properties": {
    "gn:admin1_code":"2.0",
    "gn:asciiname":"Pat Kohna",
    "gn:country_code":"PK",
    "gn:dem":86,
    "gn:feature_class":"P",
    "gn:feature_code":"PPL",
    "gn:name":"Pat Kohna",
    "gn:population":0,
    "gn:timezone":"Asia/Karachi",
    "iso:country":"PK",
    "name:und_x_variant":[
        "Manju Kohna"
    ],
    "wof:name":"Pat Kohna",
    "wof:placetype":"locality"
},
  "geometry": {"coordinates":[67.92766999999999,28.85306],"type":"Point"}
}