{
  "type": "Feature",
  "properties": {
    "gn:admin1_code":"6.0",
    "gn:asciiname":"Dulur",
    "gn:country_code":"PK",
    "gn:dem":1316,
    "gn:feature_class":"P",
    "gn:feature_code":"PPL",
    "gn:name":"Dulur",
    "gn:population":0,
    "gn:timezone":"Asia/Karachi",
    "iso:country":"PK",
    "wof:name":"Dulur",
    "wof:placetype":"locality"
},
  "geometry": {"coordinates":[73.84788,34.55148],"type":"Point"}
}