{
  "type": "Feature",
  "properties": {
    "gn:admin1_code":"2.0",
    "gn:asciiname":"Faqirzai",
    "gn:country_code":"PK",
    "gn:dem":697,
    "gn:feature_class":"P",
    "gn:feature_code":"PPL",
    "gn:name":"Faqirzai",
    "gn:population":0,
    "gn:timezone":"Asia/Karachi",
    "iso:country":"PK",
    "wof:name":"Faqirzai",
    "wof:placetype":"locality"
},
  "geometry": {"coordinates":[65.24732,28.53141],"type":"Point"}
}