{
  "type": "Feature",
  "properties": {
    "gn:admin1_code":"1.0",
    "gn:asciiname":"Sara Khwa",
    "gn:country_code":"PK",
    "gn:dem":2075,
    "gn:feature_class":"P",
    "gn:feature_code":"PPL",
    "gn:name":"Sara Khwa",
    "gn:population":0,
    "gn:timezone":"Asia/Karachi",
    "iso:country":"PK",
    "wof:name":"Sara Khwa",
    "wof:placetype":"locality"
},
  "geometry": {"coordinates":[70.41486999999999,33.85217],"type":"Point"}
}