{
  "type": "Feature",
  "properties": {
    "gn:admin1_code":"01",
    "gn:asciiname":"Musa Khan Kili",
    "gn:country_code":"PK",
    "gn:dem":1451,
    "gn:feature_class":"P",
    "gn:feature_code":"PPL",
    "gn:name":"Musa Khan Kili",
    "gn:population":0,
    "gn:timezone":"Asia/Karachi",
    "iso:country":"PK",
    "name:und_x_variant":[
        "Musa Khan Kali",
        "Musa Khan Kili",
        "Musa Khan Kila"
    ],
    "wof:name":"Musa Khan Kili",
    "wof:placetype":"locality"
},
  "geometry": {"coordinates":[70.11041999999999,33.8283],"type":"Point"}
}