{
  "type": "Feature",
  "properties": {
    "gn:admin1_code":"3",
    "gn:asciiname":"Chamtar",
    "gn:country_code":"PK",
    "gn:dem":982,
    "gn:feature_class":"P",
    "gn:feature_code":"PPL",
    "gn:name":"Chamtar",
    "gn:population":0,
    "gn:timezone":"Asia/Karachi",
    "iso:country":"PK",
    "name:eng_x_preferred":[
        "Chatara"
    ],
    "name:fas_x_preferred":[
        "\u0686\u0645\u062a\u0631"
    ],
    "name:urd_x_preferred":[
        "\u0686\u0645\u062a\u0631"
    ],
    "wof:name":"Chamtar",
    "wof:placetype":"locality"
},
  "geometry": {"coordinates":[72.44733000000002,34.29855999999999],"type":"Point"}
}