{
  "type": "Feature",
  "properties": {
    "gn:admin1_code":"3.0",
    "gn:asciiname":"Banja Kara",
    "gn:country_code":"PK",
    "gn:dem":1848,
    "gn:feature_class":"P",
    "gn:feature_code":"PPL",
    "gn:name":"Banja Kara",
    "gn:population":0,
    "gn:timezone":"Asia/Karachi",
    "iso:country":"PK",
    "wof:name":"Banja Kara",
    "wof:placetype":"locality"
},
  "geometry": {"coordinates":[73.10129000000001,34.86076],"type":"Point"}
}