{
  "type": "Feature",
  "properties": {
    "gn:admin1_code":"4",
    "gn:asciiname":"Basti Arain",
    "gn:country_code":"PK",
    "gn:dem":102,
    "gn:feature_class":"P",
    "gn:feature_code":"PPL",
    "gn:name":"Basti Arain",
    "gn:population":0,
    "gn:timezone":"Asia/Karachi",
    "iso:country":"PK",
    "wof:name":"Basti Arain",
    "wof:placetype":"locality"
},
  "geometry": {"coordinates":[71.08525,29.32002],"type":"Point"}
}