{
  "type": "Feature",
  "properties": {
    "gn:admin1_code":"3.0",
    "gn:asciiname":"Sher Khan Koruna",
    "gn:country_code":"PK",
    "gn:dem":789,
    "gn:feature_class":"P",
    "gn:feature_code":"PPL",
    "gn:name":"Sher Khan Koruna",
    "gn:population":0,
    "gn:timezone":"Asia/Karachi",
    "iso:country":"PK",
    "wof:name":"Sher Khan Koruna",
    "wof:placetype":"locality"
},
  "geometry": {"coordinates":[71.28971999999997,33.16099000000001],"type":"Point"}
}