{
  "type": "Feature",
  "properties": {
    "gn:admin1_code":"5.0",
    "gn:asciiname":"Goth Arbab Allah Dino",
    "gn:country_code":"PK",
    "gn:dem":10,
    "gn:feature_class":"P",
    "gn:feature_code":"PPL",
    "gn:name":"Goth Arbab Allah Dino",
    "gn:population":0,
    "gn:timezone":"Asia/Karachi",
    "iso:country":"PK",
    "wof:name":"Goth Arbab Allah Dino",
    "wof:placetype":"locality"
},
  "geometry": {"coordinates":[69.05904,24.60926],"type":"Point"}
}