{
  "type": "Feature",
  "properties": {
    "gn:admin1_code":"4.0",
    "gn:asciiname":"Chak Two Hundred Forty Rakh Branch",
    "gn:country_code":"PK",
    "gn:dem":184,
    "gn:feature_class":"P",
    "gn:feature_code":"PPL",
    "gn:name":"Chak Two Hundred Forty Rakh Branch",
    "gn:population":0,
    "gn:timezone":"Asia/Karachi",
    "iso:country":"PK",
    "name:und_x_variant":[
        "Chaddar",
        "Chak Two Hundred Forty RB",
        "Chak Two Hundred Forty Rakh Branch",
        "Chidhor"
    ],
    "wof:name":"Chak Two Hundred Forty Rakh Branch",
    "wof:placetype":"locality"
},
  "geometry": {"coordinates":[73.18777,31.34148],"type":"Point"}
}