{
  "type": "Feature",
  "properties": {
    "gn:admin1_code":"4",
    "gn:asciiname":"Nahrke",
    "gn:country_code":"PK",
    "gn:dem":230,
    "gn:feature_class":"P",
    "gn:feature_code":"PPL",
    "gn:name":"Nahrke",
    "gn:population":0,
    "gn:timezone":"Asia/Karachi",
    "iso:country":"PK",
    "name:und_x_variant":[
        "N\u0101harke"
    ],
    "wof:name":"Nahrke",
    "wof:placetype":"locality"
},
  "geometry": {"coordinates":[74.18316,32.50108],"type":"Point"}
}