{
  "type": "Feature",
  "properties": {
    "gn:admin1_code":"4",
    "gn:asciiname":"Gahanwori",
    "gn:country_code":"PK",
    "gn:dem":234,
    "gn:feature_class":"P",
    "gn:feature_code":"PPL",
    "gn:name":"Gahanwori",
    "gn:population":0,
    "gn:timezone":"Asia/Karachi",
    "iso:country":"PK",
    "name:eng_x_preferred":[
        "Basti Kappuhani"
    ],
    "name:und_x_variant":[
        "Basti Kippuh\u0101ni"
    ],
    "wof:name":"Gahanwori",
    "wof:placetype":"locality"
},
  "geometry": {"coordinates":[70.36908000000003,29.95725],"type":"Point"}
}