{
  "type": "Feature",
  "properties": {
    "gn:admin1_code":"1.0",
    "gn:asciiname":"Bar Garkai",
    "gn:country_code":"PK",
    "gn:dem":1299,
    "gn:feature_class":"P",
    "gn:feature_code":"PPL",
    "gn:name":"Bar Garkai",
    "gn:population":0,
    "gn:timezone":"Asia/Karachi",
    "iso:country":"PK",
    "name:und_x_variant":[
        "Nara Kharkai",
        "Bar Gatkai"
    ],
    "wof:name":"Bar Garkai",
    "wof:placetype":"locality"
},
  "geometry": {"coordinates":[71.40689999999999,34.87994],"type":"Point"}
}