{
  "type": "Feature",
  "properties": {
    "gn:admin1_code":"3.0",
    "gn:asciiname":"Shahrat",
    "gn:country_code":"PK",
    "gn:dem":3751,
    "gn:feature_class":"P",
    "gn:feature_code":"PPL",
    "gn:name":"Shahrat",
    "gn:population":0,
    "gn:timezone":"Asia/Karachi",
    "iso:country":"PK",
    "wof:name":"Shahrat",
    "wof:placetype":"locality"
},
  "geometry": {"coordinates":[71.63630000000001,36.12047000000001],"type":"Point"}
}