{
  "type": "Feature",
  "properties": {
    "gn:admin1_code":"5",
    "gn:asciiname":"Bagh Lahbar Jat",
    "gn:country_code":"PK",
    "gn:dem":49,
    "gn:feature_class":"P",
    "gn:feature_code":"PPL",
    "gn:name":"Bagh Lahbar Jat",
    "gn:population":0,
    "gn:timezone":"Asia/Karachi",
    "iso:country":"PK",
    "name:und_x_variant":[
        "Jat"
    ],
    "wof:name":"Bagh Lahbar Jat",
    "wof:placetype":"locality"
},
  "geometry": {"coordinates":[67.99175,27.38557],"type":"Point"}
}