{
  "type": "Feature",
  "properties": {
    "gn:admin1_code":"6",
    "gn:asciiname":"Mohra Seri",
    "gn:country_code":"PK",
    "gn:dem":1374,
    "gn:feature_class":"P",
    "gn:feature_code":"PPL",
    "gn:name":"Mohra Seri",
    "gn:population":0,
    "gn:timezone":"Asia/Karachi",
    "iso:country":"PK",
    "wof:name":"Mohra Seri",
    "wof:placetype":"locality"
},
  "geometry": {"coordinates":[74.09493000000001,33.46306],"type":"Point"}
}