{
  "type": "Feature",
  "properties": {
    "gn:admin1_code":"6",
    "gn:asciiname":"Doba",
    "gn:country_code":"PK",
    "gn:dem":2863,
    "gn:feature_class":"P",
    "gn:feature_code":"PPL",
    "gn:name":"Doba",
    "gn:population":0,
    "gn:timezone":"Asia/Karachi",
    "iso:country":"PK",
    "name:und_x_variant":[
        "Duna"
    ],
    "wof:name":"Doba",
    "wof:placetype":"locality"
},
  "geometry": {"coordinates":[74.20272,33.98001],"type":"Point"}
}