{
  "type": "Feature",
  "properties": {
    "gn:admin1_code":"3",
    "gn:asciiname":"Tikai",
    "gn:country_code":"PK",
    "gn:dem":3125,
    "gn:feature_class":"P",
    "gn:feature_code":"PPL",
    "gn:name":"Tikai",
    "gn:population":0,
    "gn:timezone":"Asia/Karachi",
    "iso:country":"PK",
    "wof:name":"Tikai",
    "wof:placetype":"locality"
},
  "geometry": {"coordinates":[72.70139,35.35694],"type":"Point"}
}