{
  "type": "Feature",
  "properties": {
    "gn:admin1_code":"4.0",
    "gn:asciiname":"Santini Dheri",
    "gn:country_code":"PK",
    "gn:dem":316,
    "gn:feature_class":"P",
    "gn:feature_code":"PPL",
    "gn:name":"Santini Dheri",
    "gn:population":0,
    "gn:timezone":"Asia/Karachi",
    "iso:country":"PK",
    "wof:name":"Santini Dheri",
    "wof:placetype":"locality"
},
  "geometry": {"coordinates":[72.52914,33.97172],"type":"Point"}
}