{
  "type": "Feature",
  "properties": {
    "gn:admin1_code":"4",
    "gn:asciiname":"Chak Four Hundred Eighty-one Gugera Branch",
    "gn:country_code":"PK",
    "gn:dem":170,
    "gn:feature_class":"P",
    "gn:feature_code":"PPL",
    "gn:name":"Chak Four Hundred Eighty-one Gugera Branch",
    "gn:population":0,
    "gn:timezone":"Asia/Karachi",
    "iso:country":"PK",
    "name:und_x_variant":[
        "Chak Four Hundred Eighty-one"
    ],
    "wof:name":"Chak Four Hundred Eighty-one Gugera Branch",
    "wof:placetype":"locality"
},
  "geometry": {"coordinates":[72.90289,30.95626],"type":"Point"}
}