{
  "type": "Feature",
  "properties": {
    "gn:admin1_code":"4",
    "gn:asciiname":"Bhattiwala",
    "gn:country_code":"PK",
    "gn:dem":134,
    "gn:feature_class":"P",
    "gn:feature_code":"PPL",
    "gn:name":"Bhattiwala",
    "gn:population":0,
    "gn:timezone":"Asia/Karachi",
    "iso:country":"PK",
    "name:eng_x_preferred":[
        "Bhatt\u012bw\u0101la"
    ],
    "wof:name":"Bhattiwala",
    "wof:placetype":"locality"
},
  "geometry": {"coordinates":[70.73528,30.48639],"type":"Point"}
}