{
  "type": "Feature",
  "properties": {
    "gn:admin1_code":"1.0",
    "gn:asciiname":"Bara Darra",
    "gn:country_code":"PK",
    "gn:dem":1956,
    "gn:feature_class":"P",
    "gn:feature_code":"PPL",
    "gn:name":"Bara Darra",
    "gn:population":0,
    "gn:timezone":"Asia/Karachi",
    "iso:country":"PK",
    "wof:name":"Bara Darra",
    "wof:placetype":"locality"
},
  "geometry": {"coordinates":[70.13701,33.93389000000001],"type":"Point"}
}