{
  "type": "Feature",
  "properties": {
    "gn:admin1_code":"4",
    "gn:asciiname":"Chak Ten",
    "gn:country_code":"PK",
    "gn:dem":189,
    "gn:feature_class":"P",
    "gn:feature_code":"PPL",
    "gn:name":"Chak Ten",
    "gn:population":0,
    "gn:timezone":"Asia/Karachi",
    "iso:country":"PK",
    "name:und_x_variant":[
        "B\u016blegarhi",
        "Bhol\u0101garhi"
    ],
    "wof:name":"Chak Ten",
    "wof:placetype":"locality"
},
  "geometry": {"coordinates":[73.80081,30.93173],"type":"Point"}
}