{
  "type": "Feature",
  "properties": {
    "gn:admin1_code":"6",
    "gn:asciiname":"Kandiawaladanna",
    "gn:country_code":"PK",
    "gn:dem":3063,
    "gn:feature_class":"P",
    "gn:feature_code":"PPL",
    "gn:name":"Kandiawaladanna",
    "gn:population":0,
    "gn:timezone":"Asia/Karachi",
    "iso:country":"PK",
    "wof:name":"Kandiawaladanna",
    "wof:placetype":"locality"
},
  "geometry": {"coordinates":[73.44575,34.53648],"type":"Point"}
}