{
  "type": "Feature",
  "properties": {
    "gn:admin1_code":"3.0",
    "gn:asciiname":"Banda Mulla Khan",
    "gn:country_code":"PK",
    "gn:dem":296,
    "gn:feature_class":"P",
    "gn:feature_code":"PPL",
    "gn:name":"Banda Mulla Khan",
    "gn:population":0,
    "gn:timezone":"Asia/Karachi",
    "iso:country":"PK",
    "name:eng_x_preferred":[
        "B\u0101nda Mall\u0101h\u0101n"
    ],
    "name:und_x_variant":[
        "Banda Malahan",
        "Banda Mulla Khan"
    ],
    "wof:name":"Banda Mulla Khan",
    "wof:placetype":"locality"
},
  "geometry": {"coordinates":[71.75735,34.07169],"type":"Point"}
}