{
  "type": "Feature",
  "properties": {
    "gn:admin1_code":"5.0",
    "gn:asciiname":"Saiyid Daman Ali Shah",
    "gn:country_code":"PK",
    "gn:dem":63,
    "gn:feature_class":"P",
    "gn:feature_code":"PPL",
    "gn:name":"Saiyid Daman Ali Shah",
    "gn:population":0,
    "gn:timezone":"Asia/Karachi",
    "iso:country":"PK",
    "name:und_x_variant":[
        "Saiyld D\u0101man Ali Sh\u0101n"
    ],
    "wof:name":"Saiyid Daman Ali Shah",
    "wof:placetype":"locality"
},
  "geometry": {"coordinates":[68.76801999999999,28.25044],"type":"Point"}
}