{
  "type": "Feature",
  "properties": {
    "gn:admin1_code":"5",
    "gn:asciiname":"Ziarat",
    "gn:country_code":"PK",
    "gn:dem":16,
    "gn:feature_class":"P",
    "gn:feature_code":"PPL",
    "gn:name":"Zi\u0101rat",
    "gn:population":0,
    "gn:timezone":"Asia/Karachi",
    "iso:country":"PK",
    "wof:name":"Ziarat",
    "wof:placetype":"locality"
},
  "geometry": {"coordinates":[68.83750000000001,25.05139],"type":"Point"}
}