{
  "type": "Feature",
  "properties": {
    "gn:admin1_code":"02",
    "gn:asciiname":"Zhar Karez",
    "gn:country_code":"PK",
    "gn:dem":1546,
    "gn:feature_class":"P",
    "gn:feature_code":"PPL",
    "gn:name":"Zhar Karez",
    "gn:population":0,
    "gn:timezone":"Asia/Karachi",
    "iso:country":"PK",
    "name:und_x_variant":[
        "Zar Karaz",
        "Zhar Karez"
    ],
    "wof:name":"Zhar Karez",
    "wof:placetype":"locality"
},
  "geometry": {"coordinates":[68.51097,30.43926],"type":"Point"}
}