{
  "type": "Feature",
  "properties": {
    "gn:admin1_code":"4",
    "gn:asciiname":"Maira",
    "gn:country_code":"PK",
    "gn:dem":347,
    "gn:feature_class":"P",
    "gn:feature_code":"PPL",
    "gn:name":"Maira",
    "gn:population":0,
    "gn:timezone":"Asia/Karachi",
    "iso:country":"PK",
    "wof:name":"Maira",
    "wof:placetype":"locality"
},
  "geometry": {"coordinates":[73.92166999999998,32.88596],"type":"Point"}
}