{
  "type": "Feature",
  "properties": {
    "gn:admin1_code":"4.0",
    "gn:asciiname":"Chak Three Hundred Thirty-three Hakra Right",
    "gn:country_code":"PK",
    "gn:dem":134,
    "gn:feature_class":"P",
    "gn:feature_code":"PPL",
    "gn:name":"Chak Three Hundred Thirty-three Hakra Right",
    "gn:population":0,
    "gn:timezone":"Asia/Karachi",
    "iso:country":"PK",
    "wof:name":"Chak Three Hundred Thirty-three Hakra Right",
    "wof:placetype":"locality"
},
  "geometry": {"coordinates":[72.35961999999998,29.11532],"type":"Point"}
}