{
  "type": "Feature",
  "properties": {
    "gn:admin1_code":"6",
    "gn:asciiname":"Halal",
    "gn:country_code":"PK",
    "gn:dem":1500,
    "gn:feature_class":"P",
    "gn:feature_code":"PPL",
    "gn:name":"Halal",
    "gn:population":0,
    "gn:timezone":"Asia/Karachi",
    "iso:country":"PK",
    "wof:name":"Halal",
    "wof:placetype":"locality"
},
  "geometry": {"coordinates":[73.63382,34.1225],"type":"Point"}
}