{
  "type": "Feature",
  "properties": {
    "gn:admin1_code":"2.0",
    "gn:asciiname":"Walla",
    "gn:country_code":"PK",
    "gn:dem":2114,
    "gn:feature_class":"P",
    "gn:feature_code":"PPL",
    "gn:name":"Walla",
    "gn:population":0,
    "gn:timezone":"Asia/Karachi",
    "iso:country":"PK",
    "name:eng_x_preferred":[
        "Walha"
    ],
    "wof:name":"Walla",
    "wof:placetype":"locality"
},
  "geometry": {"coordinates":[67.40937,30.79843],"type":"Point"}
}