{
  "type": "Feature",
  "properties": {
    "gn:admin1_code":"4",
    "gn:asciiname":"Chak Two Hundred Fifty-seven",
    "gn:country_code":"PK",
    "gn:dem":148,
    "gn:feature_class":"P",
    "gn:feature_code":"PPL",
    "gn:name":"Chak Two Hundred Fifty-seven",
    "gn:population":0,
    "gn:timezone":"Asia/Karachi",
    "iso:country":"PK",
    "name:und_x_variant":[
        "Chak Two Hundred Fifty-Seven A"
    ],
    "wof:name":"Chak Two Hundred Fifty-seven",
    "wof:placetype":"locality"
},
  "geometry": {"coordinates":[71.17189999999999,30.94573],"type":"Point"}
}