{
  "type": "Feature",
  "properties": {
    "gn:admin1_code":"4.0",
    "gn:asciiname":"Mujhamlawala Khu",
    "gn:country_code":"PK",
    "gn:dem":173,
    "gn:feature_class":"P",
    "gn:feature_code":"PPL",
    "gn:name":"Mujhamlawala Khu",
    "gn:population":0,
    "gn:timezone":"Asia/Karachi",
    "iso:country":"PK",
    "wof:name":"Mujhamlawala Khu",
    "wof:placetype":"locality"
},
  "geometry": {"coordinates":[73.76361999999997,30.40938],"type":"Point"}
}