{
  "type": "Feature",
  "properties": {
    "gn:admin1_code":"4.0",
    "gn:asciiname":"Chhatanwala",
    "gn:country_code":"PK",
    "gn:dem":226,
    "gn:feature_class":"P",
    "gn:feature_code":"PPL",
    "gn:name":"Chhatanwala",
    "gn:population":0,
    "gn:timezone":"Asia/Karachi",
    "iso:country":"PK",
    "wof:name":"Chhatanwala",
    "wof:placetype":"locality"
},
  "geometry": {"coordinates":[73.9143,32.53744],"type":"Point"}
}