{
  "type": "Feature",
  "properties": {
    "gn:admin1_code":"5",
    "gn:asciiname":"Muhammad Amin Joya",
    "gn:country_code":"PK",
    "gn:dem":43,
    "gn:feature_class":"P",
    "gn:feature_code":"PPL",
    "gn:name":"Muhammad Amin Joya",
    "gn:population":0,
    "gn:timezone":"Asia/Karachi",
    "iso:country":"PK",
    "name:und_x_variant":[
        "Imam Sh\u0101h",
        "Muhammad Amin Ja\u016bia",
        "Muhammad Amin Joya"
    ],
    "wof:name":"Muhammad Amin Joya",
    "wof:placetype":"locality"
},
  "geometry": {"coordinates":[68.15168,26.68708],"type":"Point"}
}