{
  "type": "Feature",
  "properties": {
    "gn:admin1_code":"4",
    "gn:asciiname":"Sandi",
    "gn:country_code":"PK",
    "gn:dem":187,
    "gn:feature_class":"P",
    "gn:feature_code":"PPL",
    "gn:name":"Sandi",
    "gn:population":0,
    "gn:timezone":"Asia/Karachi",
    "iso:country":"PK",
    "name:ceb_x_preferred":[
        "Sandi"
    ],
    "name:ind_x_preferred":[
        "Sandi"
    ],
    "name:nld_x_preferred":[
        "Sandi"
    ],
    "name:swe_x_preferred":[
        "Sandi"
    ],
    "wof:name":"Sandi",
    "wof:placetype":"locality"
},
  "geometry": {"coordinates":[71.17825999999999,32.0088],"type":"Point"}
}