{
  "type": "Feature",
  "properties": {
    "gn:admin1_code":"3.0",
    "gn:asciiname":"Sunaru Goshti",
    "gn:country_code":"PK",
    "gn:dem":3685,
    "gn:feature_class":"P",
    "gn:feature_code":"PPL",
    "gn:name":"Sunaru Goshti",
    "gn:population":0,
    "gn:timezone":"Asia/Karachi",
    "iso:country":"PK",
    "wof:name":"Sunaru Goshti",
    "wof:placetype":"locality"
},
  "geometry": {"coordinates":[71.29701,36.08736],"type":"Point"}
}