{
  "type": "Feature",
  "properties": {
    "gn:admin1_code":"4",
    "gn:asciiname":"Usman",
    "gn:country_code":"PK",
    "gn:dem":207,
    "gn:feature_class":"P",
    "gn:feature_code":"PPL",
    "gn:name":"Usman",
    "gn:population":0,
    "gn:timezone":"Asia/Karachi",
    "iso:country":"PK",
    "name:bel_x_preferred":[
        "\u0423\u0441\u043c\u0430\u043d\u044c"
    ],
    "name:ben_x_preferred":[
        "\u0989\u09b8\u09ae\u09be\u09a8"
    ],
    "name:ceb_x_preferred":[
        "Usman"
    ],
    "name:deu_x_preferred":[
        "Usman"
    ],
    "name:ron_x_preferred":[
        "Usman"
    ],
    "name:rus_x_preferred":[
        "\u0423\u0441\u043c\u0430\u043d\u044c"
    ],
    "name:ukr_x_preferred":[
        "\u0423\u0441\u043c\u0430\u043d\u044c"
    ],
    "wof:name":"Usman",
    "wof:placetype":"locality"
},
  "geometry": {"coordinates":[73.14166999999998,32.60278],"type":"Point"}
}