{
  "type": "Feature",
  "properties": {
    "gn:admin1_code":"2.0",
    "gn:asciiname":"Ali Khanzai Kili",
    "gn:country_code":"PK",
    "gn:dem":1432,
    "gn:feature_class":"P",
    "gn:feature_code":"PPL",
    "gn:name":"Ali Khanzai Kili",
    "gn:population":0,
    "gn:timezone":"Asia/Karachi",
    "iso:country":"PK",
    "name:und_x_variant":[
        "Alikhanzai",
        "Ali Khanzai Kili"
    ],
    "wof:name":"Ali Khanzai Kili",
    "wof:placetype":"locality"
},
  "geometry": {"coordinates":[69.38226999999999,31.26108],"type":"Point"}
}