{
  "type": "Feature",
  "properties": {
    "gn:admin1_code":"6",
    "gn:asciiname":"Gali",
    "gn:country_code":"PK",
    "gn:dem":2440,
    "gn:feature_class":"P",
    "gn:feature_code":"PPL",
    "gn:name":"Gali",
    "gn:population":0,
    "gn:timezone":"Asia/Karachi",
    "iso:country":"PK",
    "name:ceb_x_preferred":[
        "Gali"
    ],
    "name:heb_x_preferred":[
        "\u05d2\u05d0\u05dc\u05d9"
    ],
    "name:kat_x_preferred":[
        "\u10d2\u10d0\u10da\u10d8"
    ],
    "name:nld_x_preferred":[
        "Gali"
    ],
    "name:sco_x_preferred":[
        "Gali"
    ],
    "name:swe_x_preferred":[
        "Gali"
    ],
    "wof:name":"Gali",
    "wof:placetype":"locality"
},
  "geometry": {"coordinates":[73.75369000000001,34.22571],"type":"Point"}
}