{
  "type": "Feature",
  "properties": {
    "gn:admin1_code":"6.0",
    "gn:asciiname":"Mandhal",
    "gn:country_code":"PK",
    "gn:dem":527,
    "gn:feature_class":"P",
    "gn:feature_code":"PPL",
    "gn:name":"Mandhal",
    "gn:population":0,
    "gn:timezone":"Asia/Karachi",
    "iso:country":"PK",
    "name:und_x_variant":[
        "Mad\u0101l"
    ],
    "wof:name":"Mandhal",
    "wof:placetype":"locality"
},
  "geometry": {"coordinates":[73.53544000000002,33.29089],"type":"Point"}
}