{
  "type": "Feature",
  "properties": {
    "gn:admin1_code":"2.0",
    "gn:asciiname":"Malik Sheikh Kili",
    "gn:country_code":"PK",
    "gn:dem":988,
    "gn:feature_class":"P",
    "gn:feature_code":"PPL",
    "gn:name":"Malik Sheikh Kili",
    "gn:population":0,
    "gn:timezone":"Asia/Karachi",
    "iso:country":"PK",
    "wof:name":"Malik Sheikh Kili",
    "wof:placetype":"locality"
},
  "geometry": {"coordinates":[69.47575999999999,31.93215],"type":"Point"}
}