{
  "type": "Feature",
  "properties": {
    "gn:admin1_code":"4.0",
    "gn:asciiname":"Makuwala",
    "gn:country_code":"PK",
    "gn:dem":211,
    "gn:feature_class":"P",
    "gn:feature_code":"PPL",
    "gn:name":"Makuwala",
    "gn:population":0,
    "gn:timezone":"Asia/Karachi",
    "iso:country":"PK",
    "name:und_x_variant":[
        "Makhanw\u0101la Khu"
    ],
    "wof:name":"Makuwala",
    "wof:placetype":"locality"
},
  "geometry": {"coordinates":[74.41436,31.7937],"type":"Point"}
}