{
  "type": "Feature",
  "properties": {
    "gn:admin1_code":"01",
    "gn:asciiname":"Pao",
    "gn:country_code":"PK",
    "gn:dem":818,
    "gn:feature_class":"P",
    "gn:feature_code":"PPL",
    "gn:name":"Pao",
    "gn:population":0,
    "gn:timezone":"Asia/Karachi",
    "iso:country":"PK",
    "name:ceb_x_preferred":[
        "Pao"
    ],
    "name:deu_x_preferred":[
        "Pao"
    ],
    "name:spa_x_preferred":[
        "Pao"
    ],
    "name:swe_x_preferred":[
        "Pao"
    ],
    "wof:name":"Pao",
    "wof:placetype":"locality"
},
  "geometry": {"coordinates":[71.74789,34.78185],"type":"Point"}
}