{
  "type": "Feature",
  "properties": {
    "gn:admin1_code":"5",
    "gn:asciiname":"Goth Amir Muhammad",
    "gn:country_code":"PK",
    "gn:dem":68,
    "gn:feature_class":"P",
    "gn:feature_code":"PPL",
    "gn:name":"Goth Amir Muhammad",
    "gn:population":0,
    "gn:timezone":"Asia/Karachi",
    "iso:country":"PK",
    "name:und_x_variant":[
        "Goth M\u012br Muhammad"
    ],
    "wof:name":"Goth Amir Muhammad",
    "wof:placetype":"locality"
},
  "geometry": {"coordinates":[68.82491999999999,28.06517],"type":"Point"}
}