{
  "type": "Feature",
  "properties": {
    "gn:admin1_code":"2.0",
    "gn:asciiname":"Saifullah Kili",
    "gn:country_code":"PK",
    "gn:dem":1466,
    "gn:feature_class":"P",
    "gn:feature_code":"PPL",
    "gn:name":"Saifullah Kili",
    "gn:population":0,
    "gn:timezone":"Asia/Karachi",
    "iso:country":"PK",
    "wof:name":"Saifullah Kili",
    "wof:placetype":"locality"
},
  "geometry": {"coordinates":[69.07771,30.88593],"type":"Point"}
}