{
  "type": "Feature",
  "properties": {
    "gn:admin1_code":"4",
    "gn:asciiname":"Massuwala",
    "gn:country_code":"PK",
    "gn:dem":121,
    "gn:feature_class":"P",
    "gn:feature_code":"PPL",
    "gn:name":"Massuwala",
    "gn:population":0,
    "gn:timezone":"Asia/Karachi",
    "iso:country":"PK",
    "wof:name":"Massuwala",
    "wof:placetype":"locality"
},
  "geometry": {"coordinates":[71.05049,30.05588],"type":"Point"}
}