{
  "type": "Feature",
  "properties": {
    "gn:admin1_code":"4",
    "gn:asciiname":"Chak Mauj Rae",
    "gn:country_code":"PK",
    "gn:dem":170,
    "gn:feature_class":"P",
    "gn:feature_code":"PPL",
    "gn:name":"Chak Mauj Rae",
    "gn:population":0,
    "gn:timezone":"Asia/Karachi",
    "iso:country":"PK",
    "name:und_x_variant":[
        "Chak Mauj R\u0101i"
    ],
    "wof:name":"Chak Mauj Rae",
    "wof:placetype":"locality"
},
  "geometry": {"coordinates":[73.69939000000002,30.41428],"type":"Point"}
}