{
  "type": "Feature",
  "properties": {
    "gn:admin1_code":"2.0",
    "gn:asciiname":"Chhib wari",
    "gn:country_code":"PK",
    "gn:dem":40,
    "gn:feature_class":"P",
    "gn:feature_code":"PPL",
    "gn:name":"Chhib wari",
    "gn:population":0,
    "gn:timezone":"Asia/Karachi",
    "iso:country":"PK",
    "wof:name":"Chhib wari",
    "wof:placetype":"locality"
},
  "geometry": {"coordinates":[62.74311,25.55482],"type":"Point"}
}