{
  "type": "Feature",
  "properties": {
    "gn:admin1_code":"3.0",
    "gn:asciiname":"Chitta Katha",
    "gn:country_code":"PK",
    "gn:dem":2457,
    "gn:feature_class":"P",
    "gn:feature_code":"PPL",
    "gn:name":"Chitta Katha",
    "gn:population":0,
    "gn:timezone":"Asia/Karachi",
    "iso:country":"PK",
    "wof:name":"Chitta Katha",
    "wof:placetype":"locality"
},
  "geometry": {"coordinates":[73.60781999999998,34.86646],"type":"Point"}
}