{
  "type": "Feature",
  "properties": {
    "gn:admin1_code":"3",
    "gn:asciiname":"Takanr",
    "gn:country_code":"PK",
    "gn:dem":1834,
    "gn:feature_class":"P",
    "gn:feature_code":"PPL",
    "gn:name":"Takanr",
    "gn:population":0,
    "gn:timezone":"Asia/Karachi",
    "iso:country":"PK",
    "name:und_x_variant":[
        "T\u0101kan",
        "T\u0101kani",
        "Takanr"
    ],
    "wof:name":"Takanr",
    "wof:placetype":"locality"
},
  "geometry": {"coordinates":[72.51886999999998,35.1866],"type":"Point"}
}