{
  "type": "Feature",
  "properties": {
    "gn:admin1_code":"2.0",
    "gn:asciiname":"Kili Pasand Khan",
    "gn:country_code":"PK",
    "gn:dem":1259,
    "gn:feature_class":"P",
    "gn:feature_code":"PPL",
    "gn:name":"Kili Pasand Khan",
    "gn:population":0,
    "gn:timezone":"Asia/Karachi",
    "iso:country":"PK",
    "wof:name":"Kili Pasand Khan",
    "wof:placetype":"locality"
},
  "geometry": {"coordinates":[66.2851,27.43534],"type":"Point"}
}