{
  "type": "Feature",
  "properties": {
    "gn:admin1_code":"2.0",
    "gn:asciiname":"Oshta",
    "gn:country_code":"PK",
    "gn:dem":1365,
    "gn:feature_class":"P",
    "gn:feature_code":"PPL",
    "gn:name":"Oshta",
    "gn:population":0,
    "gn:timezone":"Asia/Karachi",
    "iso:country":"PK",
    "wof:name":"Oshta",
    "wof:placetype":"locality"
},
  "geometry": {"coordinates":[68.70959999999999,30.31835],"type":"Point"}
}