{
  "type": "Feature",
  "properties": {
    "gn:admin1_code":"01",
    "gn:asciiname":"Mullah Hamzullah",
    "gn:country_code":"PK",
    "gn:dem":2427,
    "gn:feature_class":"P",
    "gn:feature_code":"PPL",
    "gn:name":"Mullah Hamzullah",
    "gn:population":0,
    "gn:timezone":"Asia/Karachi",
    "iso:country":"PK",
    "name:und_x_variant":[
        "Mulla Hamzull\u0101h"
    ],
    "wof:name":"Mullah Hamzullah",
    "wof:placetype":"locality"
},
  "geometry": {"coordinates":[69.59834000000001,32.55571],"type":"Point"}
}