{
  "type": "Feature",
  "properties": {
    "gn:admin1_code":"4",
    "gn:asciiname":"Basti Shakurwala",
    "gn:country_code":"PK",
    "gn:dem":127,
    "gn:feature_class":"P",
    "gn:feature_code":"PPL",
    "gn:name":"Basti Shakurwala",
    "gn:population":0,
    "gn:timezone":"Asia/Karachi",
    "iso:country":"PK",
    "name:und_x_variant":[
        "Shak\u016brw\u0101la"
    ],
    "wof:name":"Basti Shakurwala",
    "wof:placetype":"locality"
},
  "geometry": {"coordinates":[72.08495000000001,29.59538],"type":"Point"}
}