{
  "type": "Feature",
  "properties": {
    "gn:admin1_code":"4",
    "gn:asciiname":"Chak Thirteen SP",
    "gn:country_code":"PK",
    "gn:dem":168,
    "gn:feature_class":"P",
    "gn:feature_code":"PPL",
    "gn:name":"Chak Thirteen SP",
    "gn:population":0,
    "gn:timezone":"Asia/Karachi",
    "iso:country":"PK",
    "name:und_x_variant":[
        "Baloch\u0101nw\u0101la",
        "Baluch\u0101nw\u0101la"
    ],
    "wof:name":"Chak Thirteen SP",
    "wof:placetype":"locality"
},
  "geometry": {"coordinates":[73.43548,30.39127],"type":"Point"}
}