{
  "type": "Feature",
  "properties": {
    "gn:admin1_code":"3.0",
    "gn:asciiname":"Khan Khel",
    "gn:country_code":"PK",
    "gn:dem":337,
    "gn:feature_class":"P",
    "gn:feature_code":"PPL",
    "gn:name":"Khan Khel",
    "gn:population":0,
    "gn:timezone":"Asia/Karachi",
    "iso:country":"PK",
    "wof:name":"Khan Khel",
    "wof:placetype":"locality"
},
  "geometry": {"coordinates":[70.55513000000001,32.84839],"type":"Point"}
}