{
  "type": "Feature",
  "properties": {
    "gn:admin1_code":"4",
    "gn:asciiname":"Chandrinwala",
    "gn:country_code":"PK",
    "gn:dem":119,
    "gn:feature_class":"P",
    "gn:feature_code":"PPL",
    "gn:name":"Chandrinwala",
    "gn:population":0,
    "gn:timezone":"Asia/Karachi",
    "iso:country":"PK",
    "name:eng_x_preferred":[
        "Chandrenw\u0101li"
    ],
    "wof:name":"Chandrinwala",
    "wof:placetype":"locality"
},
  "geometry": {"coordinates":[70.9584,30.01535],"type":"Point"}
}