{
  "type": "Feature",
  "properties": {
    "gn:admin1_code":"4",
    "gn:asciiname":"Chak Eleven North Branch",
    "gn:country_code":"PK",
    "gn:dem":196,
    "gn:feature_class":"P",
    "gn:feature_code":"PPL",
    "gn:name":"Chak Eleven North Branch",
    "gn:population":0,
    "gn:timezone":"Asia/Karachi",
    "iso:country":"PK",
    "name:und_x_variant":[
        "Chak Eleven NB",
        "Chak Eleven Shumali",
        "Chak 11 NB",
        "Chak Eleven North Branch"
    ],
    "wof:name":"Chak Eleven North Branch",
    "wof:placetype":"locality"
},
  "geometry": {"coordinates":[72.88234,32.25472],"type":"Point"}
}