{
  "type": "Feature",
  "properties": {
    "gn:admin1_code":"4.0",
    "gn:asciiname":"Khabbeke",
    "gn:country_code":"PK",
    "gn:dem":224,
    "gn:feature_class":"P",
    "gn:feature_code":"PPL",
    "gn:name":"Khabbeke",
    "gn:population":0,
    "gn:timezone":"Asia/Karachi",
    "iso:country":"PK",
    "name:und_x_variant":[
        "Khhabeke",
        "Khabbeke"
    ],
    "wof:name":"Khabbeke",
    "wof:placetype":"locality"
},
  "geometry": {"coordinates":[74.05404,32.09908],"type":"Point"}
}