{
  "type": "Feature",
  "properties": {
    "gn:admin1_code":"3.0",
    "gn:asciiname":"Pochial",
    "gn:country_code":"PK",
    "gn:dem":1224,
    "gn:feature_class":"P",
    "gn:feature_code":"PPL",
    "gn:name":"Pochial",
    "gn:population":0,
    "gn:timezone":"Asia/Karachi",
    "iso:country":"PK",
    "wof:name":"Pochial",
    "wof:placetype":"locality"
},
  "geometry": {"coordinates":[72.91682,34.45691],"type":"Point"}
}