{
  "type": "Feature",
  "properties": {
    "gn:admin1_code":"3",
    "gn:asciiname":"Khunar Dheri",
    "gn:country_code":"PK",
    "gn:dem":337,
    "gn:feature_class":"P",
    "gn:feature_code":"PPL",
    "gn:name":"Khunar Dheri",
    "gn:population":0,
    "gn:timezone":"Asia/Karachi",
    "iso:country":"PK",
    "name:eng_x_preferred":[
        "Khuneb Dheri"
    ],
    "wof:name":"Khunar Dheri",
    "wof:placetype":"locality"
},
  "geometry": {"coordinates":[72.45038000000002,34.12959],"type":"Point"}
}