{
  "type": "Feature",
  "properties": {
    "gn:admin1_code":"3.0",
    "gn:asciiname":"Esar Paghaini",
    "gn:country_code":"PK",
    "gn:dem":3240,
    "gn:feature_class":"P",
    "gn:feature_code":"PPL",
    "gn:name":"Esar Paghaini",
    "gn:population":0,
    "gn:timezone":"Asia/Karachi",
    "iso:country":"PK",
    "wof:name":"Esar Paghaini",
    "wof:placetype":"locality"
},
  "geometry": {"coordinates":[72.30853,36.42005],"type":"Point"}
}