{
  "type": "Feature",
  "properties": {
    "gn:admin1_code":"2.0",
    "gn:asciiname":"Goth Pathan",
    "gn:country_code":"PK",
    "gn:dem":49,
    "gn:feature_class":"P",
    "gn:feature_code":"PPL",
    "gn:name":"Goth Pathan",
    "gn:population":0,
    "gn:timezone":"Asia/Karachi",
    "iso:country":"PK",
    "wof:name":"Goth Pathan",
    "wof:placetype":"locality"
},
  "geometry": {"coordinates":[66.27681,25.91982],"type":"Point"}
}