{
  "type": "Feature",
  "properties": {
    "gn:admin1_code":"6.0",
    "gn:asciiname":"Palina",
    "gn:country_code":"PK",
    "gn:dem":541,
    "gn:feature_class":"P",
    "gn:feature_code":"PPL",
    "gn:name":"Palina",
    "gn:population":0,
    "gn:timezone":"Asia/Karachi",
    "iso:country":"PK",
    "name:und_x_variant":[
        "Patina"
    ],
    "wof:name":"Palina",
    "wof:placetype":"locality"
},
  "geometry": {"coordinates":[73.51088,33.28208],"type":"Point"}
}