{
  "type": "Feature",
  "properties": {
    "gn:admin1_code":"6",
    "gn:asciiname":"Gali Danna",
    "gn:country_code":"PK",
    "gn:dem":2551,
    "gn:feature_class":"P",
    "gn:feature_code":"PPL",
    "gn:name":"Gali Danna",
    "gn:population":0,
    "gn:timezone":"Asia/Karachi",
    "iso:country":"PK",
    "wof:name":"Gali Danna",
    "wof:placetype":"locality"
},
  "geometry": {"coordinates":[73.86668,34.02657],"type":"Point"}
}