{
  "type": "Feature",
  "properties": {
    "gn:admin1_code":"7.0",
    "gn:asciiname":"Der Barkul",
    "gn:country_code":"PK",
    "gn:dem":2917,
    "gn:feature_class":"P",
    "gn:feature_code":"PPL",
    "gn:name":"Der Barkul",
    "gn:population":0,
    "gn:timezone":"Asia/Karachi",
    "iso:country":"PK",
    "name:und_x_variant":[
        "Der Barkulti"
    ],
    "wof:name":"Der Barkul",
    "wof:placetype":"locality"
},
  "geometry": {"coordinates":[72.89534999999999,36.16584],"type":"Point"}
}