{
  "type": "Feature",
  "properties": {
    "gn:admin1_code":"2.0",
    "gn:asciiname":"Kili Fooj Ali",
    "gn:country_code":"PK",
    "gn:dem":1279,
    "gn:feature_class":"P",
    "gn:feature_code":"PPL",
    "gn:name":"Kili Fooj Ali",
    "gn:population":0,
    "gn:timezone":"Asia/Karachi",
    "iso:country":"PK",
    "wof:name":"Kili Fooj Ali",
    "wof:placetype":"locality"
},
  "geometry": {"coordinates":[66.14256,29.66437],"type":"Point"}
}