{
  "type": "Feature",
  "properties": {
    "gn:admin1_code":"08",
    "gn:asciiname":"Sudar",
    "gn:country_code":"PK",
    "gn:dem":503,
    "gn:feature_class":"P",
    "gn:feature_code":"PPL",
    "gn:name":"Sudar",
    "gn:population":0,
    "gn:timezone":"Asia/Karachi",
    "iso:country":"PK",
    "name:srp_x_preferred":[
        "\u0421\u0443\u0434\u0430\u0440"
    ],
    "name:und_x_variant":[
        "Suhd\u0101r"
    ],
    "wof:name":"Sudar",
    "wof:placetype":"neighbourhood"
},
  "geometry": {"coordinates":[73.15067999999999,33.62822],"type":"Point"}
}