{
  "type": "Feature",
  "properties": {
    "gn:admin1_code":"4",
    "gn:asciiname":"Khu Jogiwala",
    "gn:country_code":"PK",
    "gn:dem":129,
    "gn:feature_class":"P",
    "gn:feature_code":"PPL",
    "gn:name":"Khu Jogiwala",
    "gn:population":0,
    "gn:timezone":"Asia/Karachi",
    "iso:country":"PK",
    "name:eng_x_preferred":[
        "Jog\u012bw\u0101la"
    ],
    "wof:name":"Khu Jogiwala",
    "wof:placetype":"locality"
},
  "geometry": {"coordinates":[70.70676999999998,30.33602],"type":"Point"}
}