{
  "type": "Feature",
  "properties": {
    "gn:admin1_code":"2.0",
    "gn:asciiname":"Bonin",
    "gn:country_code":"PK",
    "gn:dem":354,
    "gn:feature_class":"P",
    "gn:feature_code":"PPL",
    "gn:name":"Bonin",
    "gn:population":0,
    "gn:timezone":"Asia/Karachi",
    "iso:country":"PK",
    "wof:name":"Bonin",
    "wof:placetype":"locality"
},
  "geometry": {"coordinates":[62.29428000000001,26.22418],"type":"Point"}
}