{
  "type": "Feature",
  "properties": {
    "gn:admin1_code":"04",
    "gn:asciiname":"Pind Malhu",
    "gn:country_code":"PK",
    "gn:dem":367,
    "gn:feature_class":"P",
    "gn:feature_code":"PPL",
    "gn:name":"Pind Malhu",
    "gn:population":0,
    "gn:timezone":"Asia/Karachi",
    "iso:country":"PK",
    "wof:name":"Pind Malhu",
    "wof:placetype":"locality"
},
  "geometry": {"coordinates":[72.84546,33.34425],"type":"Point"}
}