{
  "type": "Feature",
  "properties": {
    "gn:admin1_code":"07",
    "gn:asciiname":"Um Hatun",
    "gn:country_code":"PK",
    "gn:dem":2012,
    "gn:feature_class":"P",
    "gn:feature_code":"PPL",
    "gn:name":"Um Hatun",
    "gn:population":0,
    "gn:timezone":"Asia/Karachi",
    "iso:country":"PK",
    "wof:name":"Um Hatun",
    "wof:placetype":"locality"
},
  "geometry": {"coordinates":[73.76635999999998,36.27348],"type":"Point"}
}