{
  "type": "Feature",
  "properties": {
    "gn:admin1_code":"3",
    "gn:asciiname":"Mandrochh Khurd",
    "gn:country_code":"PK",
    "gn:dem":1303,
    "gn:feature_class":"P",
    "gn:feature_code":"PPL",
    "gn:name":"Mandrochh Khurd",
    "gn:population":0,
    "gn:timezone":"Asia/Karachi",
    "iso:country":"PK",
    "name:und_x_variant":[
        "Mandrochh Khura"
    ],
    "wof:name":"Mandrochh Khurd",
    "wof:placetype":"locality"
},
  "geometry": {"coordinates":[73.26255,34.18227],"type":"Point"}
}