{
  "type": "Feature",
  "properties": {
    "gn:admin1_code":"5",
    "gn:asciiname":"Khamiso Talpur",
    "gn:country_code":"PK",
    "gn:dem":22,
    "gn:feature_class":"P",
    "gn:feature_code":"PPL",
    "gn:name":"Khamiso Talpur",
    "gn:population":0,
    "gn:timezone":"Asia/Karachi",
    "iso:country":"PK",
    "wof:name":"Khamiso Talpur",
    "wof:placetype":"locality"
},
  "geometry": {"coordinates":[68.66249999999999,25.49444],"type":"Point"}
}