{
  "type": "Feature",
  "properties": {
    "gn:admin1_code":"3",
    "gn:asciiname":"Luqman Dheri",
    "gn:country_code":"PK",
    "gn:dem":367,
    "gn:feature_class":"P",
    "gn:feature_code":"PPL",
    "gn:name":"Luqman Dheri",
    "gn:population":0,
    "gn:timezone":"Asia/Karachi",
    "iso:country":"PK",
    "name:eng_x_preferred":[
        "Luqman Dheri"
    ],
    "wof:name":"Luqman Dheri",
    "wof:placetype":"locality"
},
  "geometry": {"coordinates":[72.41453,34.1568],"type":"Point"}
}