{
  "type": "Feature",
  "properties": {
    "gn:admin1_code":"2",
    "gn:asciiname":"Alai",
    "gn:country_code":"PK",
    "gn:dem":2206,
    "gn:feature_class":"P",
    "gn:feature_code":"PPL",
    "gn:name":"Alai",
    "gn:population":0,
    "gn:timezone":"Asia/Karachi",
    "iso:country":"PK",
    "name:eng_x_preferred":[
        "Alai"
    ],
    "wof:name":"Alai",
    "wof:placetype":"locality"
},
  "geometry": {"coordinates":[67.30353000000001,30.8978],"type":"Point"}
}