{
  "type": "Feature",
  "properties": {
    "gn:admin1_code":"5",
    "gn:asciiname":"Goth Ghulam Shah Laghari",
    "gn:country_code":"PK",
    "gn:dem":17,
    "gn:feature_class":"P",
    "gn:feature_code":"PPL",
    "gn:name":"Goth Ghulam Shah Laghari",
    "gn:population":0,
    "gn:timezone":"Asia/Karachi",
    "iso:country":"PK",
    "name:und_x_variant":[
        "Ghul\u0101m Sh\u0101h Lagh\u0101ri Goth"
    ],
    "wof:name":"Goth Ghulam Shah Laghari",
    "wof:placetype":"locality"
},
  "geometry": {"coordinates":[68.83596,25.15487000000001],"type":"Point"}
}