{
  "type": "Feature",
  "properties": {
    "gn:admin1_code":"1.0",
    "gn:asciiname":"Jangi Sher Ali Khan Kale",
    "gn:country_code":"PK",
    "gn:dem":2424,
    "gn:feature_class":"P",
    "gn:feature_code":"PPL",
    "gn:name":"Jangi Sher Ali Khan Kale",
    "gn:population":0,
    "gn:timezone":"Asia/Karachi",
    "iso:country":"PK",
    "wof:name":"Jangi Sher Ali Khan Kale",
    "wof:placetype":"locality"
},
  "geometry": {"coordinates":[69.64782,32.64561],"type":"Point"}
}