{
  "type": "Feature",
  "properties": {
    "gn:admin1_code":"3",
    "gn:asciiname":"Jabagai",
    "gn:country_code":"PK",
    "gn:dem":600,
    "gn:feature_class":"P",
    "gn:feature_code":"PPL",
    "gn:name":"Jabagai",
    "gn:population":0,
    "gn:timezone":"Asia/Karachi",
    "iso:country":"PK",
    "wof:name":"Jabagai",
    "wof:placetype":"locality"
},
  "geometry": {"coordinates":[72.94286,34.86339],"type":"Point"}
}