{
  "type": "Feature",
  "properties": {
    "gn:admin1_code":"4",
    "gn:asciiname":"Saida Brahm",
    "gn:country_code":"PK",
    "gn:dem":249,
    "gn:feature_class":"P",
    "gn:feature_code":"PPL",
    "gn:name":"Saida Brahm",
    "gn:population":0,
    "gn:timezone":"Asia/Karachi",
    "iso:country":"PK",
    "name:und_x_variant":[
        "Saiyid Ibr\u0101h\u012bm"
    ],
    "wof:name":"Saida Brahm",
    "wof:placetype":"locality"
},
  "geometry": {"coordinates":[73.92929000000002,32.69161],"type":"Point"}
}