{
  "type": "Feature",
  "properties": {
    "gn:admin1_code":"3",
    "gn:asciiname":"Lundai",
    "gn:country_code":"PK",
    "gn:dem":3000,
    "gn:feature_class":"P",
    "gn:feature_code":"PPL",
    "gn:name":"Lundai",
    "gn:population":0,
    "gn:timezone":"Asia/Karachi",
    "iso:country":"PK",
    "wof:name":"Lundai",
    "wof:placetype":"locality"
},
  "geometry": {"coordinates":[73.07383,34.95132],"type":"Point"}
}