{
  "type": "Feature",
  "properties": {
    "gn:admin1_code":"2.0",
    "gn:asciiname":"Dumb Bazar",
    "gn:country_code":"PK",
    "gn:dem":15,
    "gn:feature_class":"P",
    "gn:feature_code":"PPL",
    "gn:name":"Dumb Bazar",
    "gn:population":0,
    "gn:timezone":"Asia/Karachi",
    "iso:country":"PK",
    "name:und_x_variant":[
        "Dumb"
    ],
    "wof:name":"Dumb Bazar",
    "wof:placetype":"locality"
},
  "geometry": {"coordinates":[61.87868,25.43934],"type":"Point"}
}