{
  "type": "Feature",
  "properties": {
    "gn:admin1_code":"4",
    "gn:asciiname":"Chinjrianwala",
    "gn:country_code":"PK",
    "gn:dem":167,
    "gn:feature_class":"P",
    "gn:feature_code":"PPL",
    "gn:name":"Chinjrianwala",
    "gn:population":0,
    "gn:timezone":"Asia/Karachi",
    "iso:country":"PK",
    "name:und_x_variant":[
        "Chujranw\u0101la"
    ],
    "wof:name":"Chinjrianwala",
    "wof:placetype":"locality"
},
  "geometry": {"coordinates":[71.04661999999998,31.54617],"type":"Point"}
}