{
  "type": "Feature",
  "properties": {
    "gn:admin1_code":"03",
    "gn:asciiname":"Qadri Banda",
    "gn:country_code":"PK",
    "gn:dem":918,
    "gn:feature_class":"P",
    "gn:feature_code":"PPL",
    "gn:name":"Qadri Banda",
    "gn:population":0,
    "gn:timezone":"Asia/Karachi",
    "iso:country":"PK",
    "name:und_x_variant":[
        "Mianji Khel"
    ],
    "wof:name":"Qadri Banda",
    "wof:placetype":"locality"
},
  "geometry": {"coordinates":[70.73869000000001,33.32301],"type":"Point"}
}