{
  "type": "Feature",
  "properties": {
    "gn:admin1_code":"4",
    "gn:asciiname":"Ram Sohan",
    "gn:country_code":"PK",
    "gn:dem":140,
    "gn:feature_class":"P",
    "gn:feature_code":"PPL",
    "gn:name":"Ram Sohan",
    "gn:population":0,
    "gn:timezone":"Asia/Karachi",
    "iso:country":"PK",
    "name:und_x_variant":[
        "R\u0101m S\u0101wanw\u0101la"
    ],
    "wof:name":"Ram Sohan",
    "wof:placetype":"locality"
},
  "geometry": {"coordinates":[72.25541,30.12176],"type":"Point"}
}