{
  "type": "Feature",
  "properties": {
    "gn:admin1_code":"5",
    "gn:asciiname":"Goth Nawab Khan",
    "gn:country_code":"PK",
    "gn:dem":22,
    "gn:feature_class":"P",
    "gn:feature_code":"PPL",
    "gn:name":"Goth Nawab Khan",
    "gn:population":0,
    "gn:timezone":"Asia/Karachi",
    "iso:country":"PK",
    "name:und_x_variant":[
        "Goth Naw\u0101b Khan",
        "Goth Sobho Mastoi",
        "Goth Nawab Khan"
    ],
    "wof:name":"Goth Nawab Khan",
    "wof:placetype":"locality"
},
  "geometry": {"coordinates":[68.84836,25.58646],"type":"Point"}
}