{
  "type": "Feature",
  "properties": {
    "gn:admin1_code":"01",
    "gn:asciiname":"Dag",
    "gn:country_code":"PK",
    "gn:dem":892,
    "gn:feature_class":"P",
    "gn:feature_code":"PPL",
    "gn:name":"Dag",
    "gn:population":0,
    "gn:timezone":"Asia/Karachi",
    "iso:country":"PK",
    "wof:name":"Dag",
    "wof:placetype":"locality"
},
  "geometry": {"coordinates":[71.69729,34.74187],"type":"Point"}
}