{
  "type": "Feature",
  "properties": {
    "gn:admin1_code":"3",
    "gn:asciiname":"Ghabasanai",
    "gn:country_code":"PK",
    "gn:dem":1132,
    "gn:feature_class":"P",
    "gn:feature_code":"PPL",
    "gn:name":"Ghabasanai",
    "gn:population":0,
    "gn:timezone":"Asia/Karachi",
    "iso:country":"PK",
    "name:und_x_variant":[
        "G\u0101b\u0101sanrai",
        "Ghabasanai"
    ],
    "wof:name":"Ghabasanai",
    "wof:placetype":"locality"
},
  "geometry": {"coordinates":[72.71259000000001,34.26097],"type":"Point"}
}