{
  "type": "Feature",
  "properties": {
    "gn:admin1_code":"3",
    "gn:asciiname":"Karka Saiyidan",
    "gn:country_code":"PK",
    "gn:dem":891,
    "gn:feature_class":"P",
    "gn:feature_code":"PPL",
    "gn:name":"Karka Saiyidan",
    "gn:population":0,
    "gn:timezone":"Asia/Karachi",
    "iso:country":"PK",
    "name:und_x_variant":[
        "Karka"
    ],
    "wof:name":"Karka Saiyidan",
    "wof:placetype":"locality"
},
  "geometry": {"coordinates":[73.08655,34.33347],"type":"Point"}
}