{
  "type": "Feature",
  "properties": {
    "gn:admin1_code":"5.0",
    "gn:asciiname":"Adani Jat",
    "gn:country_code":"PK",
    "gn:dem":11,
    "gn:feature_class":"P",
    "gn:feature_code":"PPL",
    "gn:name":"Adani Jat",
    "gn:population":0,
    "gn:timezone":"Asia/Karachi",
    "iso:country":"PK",
    "name:eng_x_preferred":[
        "\u0100dam Jat"
    ],
    "wof:name":"Adani Jat",
    "wof:placetype":"locality"
},
  "geometry": {"coordinates":[68.39672,24.66761],"type":"Point"}
}