{
  "type": "Feature",
  "properties": {
    "gn:admin1_code":"4.0",
    "gn:asciiname":"Sher Baz",
    "gn:country_code":"PK",
    "gn:dem":834,
    "gn:feature_class":"P",
    "gn:feature_code":"PPL",
    "gn:name":"Sher Baz",
    "gn:population":0,
    "gn:timezone":"Asia/Karachi",
    "iso:country":"PK",
    "wof:name":"Sher Baz",
    "wof:placetype":"locality"
},
  "geometry": {"coordinates":[72.25293000000001,32.64619],"type":"Point"}
}