{
  "type": "Feature",
  "properties": {
    "gn:admin1_code":"2.0",
    "gn:asciiname":"Kili Muhammad Khan",
    "gn:country_code":"PK",
    "gn:dem":1207,
    "gn:feature_class":"P",
    "gn:feature_code":"PPL",
    "gn:name":"Kili Muhammad Khan",
    "gn:population":0,
    "gn:timezone":"Asia/Karachi",
    "iso:country":"PK",
    "wof:name":"Kili Muhammad Khan",
    "wof:placetype":"locality"
},
  "geometry": {"coordinates":[65.82101999999999,29.13811],"type":"Point"}
}