{
  "type": "Feature",
  "properties": {
    "gn:admin1_code":"4.0",
    "gn:asciiname":"Olakh Hithar",
    "gn:country_code":"PK",
    "gn:dem":196,
    "gn:feature_class":"P",
    "gn:feature_code":"PPL",
    "gn:name":"Olakh Hithar",
    "gn:population":0,
    "gn:timezone":"Asia/Karachi",
    "iso:country":"PK",
    "name:und_x_variant":[
        "Aulakh Hithhar",
        "Aulakh Hith\u0101l",
        "Aulakh Hith\u0101r",
        "Olakh Hithar"
    ],
    "wof:name":"Olakh Hithar",
    "wof:placetype":"locality"
},
  "geometry": {"coordinates":[74.24659,31.05451],"type":"Point"}
}