{
  "type": "Feature",
  "properties": {
    "gn:admin1_code":"01",
    "gn:asciiname":"Haji Tangai",
    "gn:country_code":"PK",
    "gn:dem":808,
    "gn:feature_class":"P",
    "gn:feature_code":"PPL",
    "gn:name":"Haji Tangai",
    "gn:population":0,
    "gn:timezone":"Asia/Karachi",
    "iso:country":"PK",
    "wof:name":"Haji Tangai",
    "wof:placetype":"locality"
},
  "geometry": {"coordinates":[71.73690999999999,34.74372],"type":"Point"}
}