{
  "type": "Feature",
  "properties": {
    "gn:admin1_code":"5",
    "gn:asciiname":"Gullan Khan Chachar",
    "gn:country_code":"PK",
    "gn:dem":69,
    "gn:feature_class":"P",
    "gn:feature_code":"PPL",
    "gn:name":"Gullan Khan Chachar",
    "gn:population":0,
    "gn:timezone":"Asia/Karachi",
    "iso:country":"PK",
    "wof:name":"Gullan Khan Chachar",
    "wof:placetype":"locality"
},
  "geometry": {"coordinates":[69.23056,28.13889],"type":"Point"}
}