{
  "type": "Feature",
  "properties": {
    "gn:admin1_code":"4.0",
    "gn:asciiname":"Ghoman",
    "gn:country_code":"PK",
    "gn:dem":216,
    "gn:feature_class":"P",
    "gn:feature_code":"PPL",
    "gn:name":"Ghoman",
    "gn:population":0,
    "gn:timezone":"Asia/Karachi",
    "iso:country":"PK",
    "name:und_x_variant":[
        "Tibbi Ghom\u0101n"
    ],
    "wof:name":"Ghoman",
    "wof:placetype":"locality"
},
  "geometry": {"coordinates":[74.17310999999999,31.90657],"type":"Point"}
}