{
  "type": "Feature",
  "properties": {
    "gn:admin1_code":"3.0",
    "gn:asciiname":"Makhmad Alam",
    "gn:country_code":"PK",
    "gn:dem":414,
    "gn:feature_class":"P",
    "gn:feature_code":"PPL",
    "gn:name":"Makhmad Alam",
    "gn:population":0,
    "gn:timezone":"Asia/Karachi",
    "iso:country":"PK",
    "wof:name":"Makhmad Alam",
    "wof:placetype":"locality"
},
  "geometry": {"coordinates":[70.53374000000002,33.00867],"type":"Point"}
}