{
  "type": "Feature",
  "properties": {
    "gn:admin1_code":"5.0",
    "gn:asciiname":"Bukhsh Ali Marri",
    "gn:country_code":"PK",
    "gn:dem":12,
    "gn:feature_class":"P",
    "gn:feature_code":"PPL",
    "gn:name":"Bukhsh Ali Marri",
    "gn:population":0,
    "gn:timezone":"Asia/Karachi",
    "iso:country":"PK",
    "wof:name":"Bukhsh Ali Marri",
    "wof:placetype":"locality"
},
  "geometry": {"coordinates":[68.45411,24.72853],"type":"Point"}
}