{
  "type": "Feature",
  "properties": {
    "gn:admin1_code":"4",
    "gn:asciiname":"Magha",
    "gn:country_code":"PK",
    "gn:dem":142,
    "gn:feature_class":"P",
    "gn:feature_code":"PPL",
    "gn:name":"Magha",
    "gn:population":0,
    "gn:timezone":"Asia/Karachi",
    "iso:country":"PK",
    "name:rus_x_preferred":[
        "\u041c\u0430\u0433\u0445\u0430"
    ],
    "name:und_x_variant":[
        "Magha Hir\u0101j"
    ],
    "wof:name":"Magha",
    "wof:placetype":"locality"
},
  "geometry": {"coordinates":[72.23151,30.54707],"type":"Point"}
}