{
  "type": "Feature",
  "properties": {
    "gn:admin1_code":"5.0",
    "gn:asciiname":"Goth Kalati Banglani",
    "gn:country_code":"PK",
    "gn:dem":62,
    "gn:feature_class":"P",
    "gn:feature_code":"PPL",
    "gn:name":"Goth Kalati Banglani",
    "gn:population":0,
    "gn:timezone":"Asia/Karachi",
    "iso:country":"PK",
    "name:und_x_variant":[
        "Kalati Bangl\u0101ni"
    ],
    "wof:name":"Goth Kalati Banglani",
    "wof:placetype":"locality"
},
  "geometry": {"coordinates":[68.84172,28.2796],"type":"Point"}
}