{
  "type": "Feature",
  "properties": {
    "gn:admin1_code":"4",
    "gn:asciiname":"Jattoiwala",
    "gn:country_code":"PK",
    "gn:dem":172,
    "gn:feature_class":"P",
    "gn:feature_code":"PPL",
    "gn:name":"Jattoiwala",
    "gn:population":0,
    "gn:timezone":"Asia/Karachi",
    "iso:country":"PK",
    "name:und_x_variant":[
        "J\u0101tui"
    ],
    "wof:name":"Jattoiwala",
    "wof:placetype":"locality"
},
  "geometry": {"coordinates":[72.01257,31.5625],"type":"Point"}
}