{
  "type": "Feature",
  "properties": {
    "gn:admin1_code":"2.0",
    "gn:asciiname":"Sher Muhammad Bugti",
    "gn:country_code":"PK",
    "gn:dem":1040,
    "gn:feature_class":"P",
    "gn:feature_code":"PPL",
    "gn:name":"Sher Muhammad Bugti",
    "gn:population":0,
    "gn:timezone":"Asia/Karachi",
    "iso:country":"PK",
    "wof:name":"Sher Muhammad Bugti",
    "wof:placetype":"locality"
},
  "geometry": {"coordinates":[69.75623,29.78597],"type":"Point"}
}