{
  "type": "Feature",
  "properties": {
    "gn:admin1_code":"4.0",
    "gn:asciiname":"Sadr Bala Bhaini",
    "gn:country_code":"PK",
    "gn:dem":181,
    "gn:feature_class":"P",
    "gn:feature_code":"PPL",
    "gn:name":"Sadr Bala Bhaini",
    "gn:population":0,
    "gn:timezone":"Asia/Karachi",
    "iso:country":"PK",
    "wof:name":"Sadr Bala Bhaini",
    "wof:placetype":"locality"
},
  "geometry": {"coordinates":[74.08589000000001,30.60425],"type":"Point"}
}