{
  "type": "Feature",
  "properties": {
    "gn:admin1_code":"3",
    "gn:asciiname":"Nalkot",
    "gn:country_code":"PK",
    "gn:dem":2047,
    "gn:feature_class":"P",
    "gn:feature_code":"PPL",
    "gn:name":"Nalkot",
    "gn:population":0,
    "gn:timezone":"Asia/Karachi",
    "iso:country":"PK",
    "wof:name":"Nalkot",
    "wof:placetype":"locality"
},
  "geometry": {"coordinates":[72.61978000000001,35.13365],"type":"Point"}
}