{
  "type": "Feature",
  "properties": {
    "gn:admin1_code":"4",
    "gn:asciiname":"Pahianwala",
    "gn:country_code":"PK",
    "gn:dem":168,
    "gn:feature_class":"P",
    "gn:feature_code":"PPL",
    "gn:name":"Pahianwala",
    "gn:population":0,
    "gn:timezone":"Asia/Karachi",
    "iso:country":"PK",
    "wof:name":"Pahianwala",
    "wof:placetype":"locality"
},
  "geometry": {"coordinates":[71.62100000000002,31.47865],"type":"Point"}
}