{
  "type": "Feature",
  "properties": {
    "gn:admin1_code":"2.0",
    "gn:asciiname":"Goth Achar Shaikh",
    "gn:country_code":"PK",
    "gn:dem":37,
    "gn:feature_class":"P",
    "gn:feature_code":"PPL",
    "gn:name":"Goth Achar Shaikh",
    "gn:population":0,
    "gn:timezone":"Asia/Karachi",
    "iso:country":"PK",
    "wof:name":"Goth Achar Shaikh",
    "wof:placetype":"locality"
},
  "geometry": {"coordinates":[66.91601999999999,25.05399],"type":"Point"}
}