{
  "type": "Feature",
  "properties": {
    "gn:admin1_code":"04",
    "gn:asciiname":"Chak Three Hundred Thirteen Gugera Branch",
    "gn:country_code":"PK",
    "gn:dem":146,
    "gn:feature_class":"P",
    "gn:feature_code":"PPL",
    "gn:name":"Chak Three Hundred Thirteen Gugera Branch",
    "gn:population":0,
    "gn:timezone":"Asia/Karachi",
    "iso:country":"PK",
    "name:und_x_variant":[
        "Piripur",
        "Chak Three Hundred Thirteen GB",
        "Pirepur",
        "Chak Three Hundred Thirteen Gugera Branch"
    ],
    "wof:name":"Chak Three Hundred Thirteen Gugera Branch",
    "wof:placetype":"locality"
},
  "geometry": {"coordinates":[72.27611,30.83257],"type":"Point"}
}