{
  "type": "Feature",
  "properties": {
    "gn:admin1_code":"4.0",
    "gn:asciiname":"Dera Muhammad Siddique",
    "gn:country_code":"PK",
    "gn:dem":86,
    "gn:feature_class":"P",
    "gn:feature_code":"PPL",
    "gn:name":"Dera Muhammad Siddique",
    "gn:population":0,
    "gn:timezone":"Asia/Karachi",
    "iso:country":"PK",
    "name:und_x_variant":[
        "Dera Gul\u0101b Kh\u0101n"
    ],
    "wof:name":"Dera Muhammad Siddique",
    "wof:placetype":"locality"
},
  "geometry": {"coordinates":[69.98009,28.75706],"type":"Point"}
}