{
  "type": "Feature",
  "properties": {
    "gn:admin1_code":"5.0",
    "gn:asciiname":"Gul Muhammad Rind Jo Tar",
    "gn:country_code":"PK",
    "gn:dem":102,
    "gn:feature_class":"P",
    "gn:feature_code":"PPL",
    "gn:name":"Gul Muhammad Rind Jo Tar",
    "gn:population":0,
    "gn:timezone":"Asia/Karachi",
    "iso:country":"PK",
    "name:und_x_variant":[
        "Gul Muhammad jo Tar"
    ],
    "wof:name":"Gul Muhammad Rind Jo Tar",
    "wof:placetype":"locality"
},
  "geometry": {"coordinates":[70.67654,25.00105],"type":"Point"}
}