{
  "type": "Feature",
  "properties": {
    "gn:admin1_code":"5",
    "gn:asciiname":"Goth Dhoro Jee",
    "gn:country_code":"PK",
    "gn:dem":30,
    "gn:feature_class":"P",
    "gn:feature_code":"PPL",
    "gn:name":"Goth Dhoro Jee",
    "gn:population":0,
    "gn:timezone":"Asia/Karachi",
    "iso:country":"PK",
    "name:und_x_variant":[
        "Goth J\u0101n Muhammad"
    ],
    "wof:name":"Goth Dhoro Jee",
    "wof:placetype":"locality"
},
  "geometry": {"coordinates":[68.58821,25.76174],"type":"Point"}
}