{
  "type": "Feature",
  "properties": {
    "gn:admin1_code":"1.0",
    "gn:asciiname":"Nawe Gorey",
    "gn:country_code":"PK",
    "gn:dem":654,
    "gn:feature_class":"P",
    "gn:feature_code":"PPL",
    "gn:name":"Nawe Gorey",
    "gn:population":0,
    "gn:timezone":"Asia/Karachi",
    "iso:country":"PK",
    "wof:name":"Nawe Gorey",
    "wof:placetype":"locality"
},
  "geometry": {"coordinates":[71.31395999999999,33.81746],"type":"Point"}
}