{
  "type": "Feature",
  "properties": {
    "gn:admin1_code":"5.0",
    "gn:asciiname":"Goth Mobarak Shar",
    "gn:country_code":"PK",
    "gn:dem":69,
    "gn:feature_class":"P",
    "gn:feature_code":"PPL",
    "gn:name":"Goth Mobarak Shar",
    "gn:population":0,
    "gn:timezone":"Asia/Karachi",
    "iso:country":"PK",
    "wof:name":"Goth Mobarak Shar",
    "wof:placetype":"locality"
},
  "geometry": {"coordinates":[68.79985000000001,27.86585],"type":"Point"}
}