{
  "type": "Feature",
  "properties": {
    "gn:admin1_code":"2.0",
    "gn:asciiname":"Khushhal Kaul",
    "gn:country_code":"PK",
    "gn:dem":1716,
    "gn:feature_class":"P",
    "gn:feature_code":"PPL",
    "gn:name":"Khushhal Kaul",
    "gn:population":0,
    "gn:timezone":"Asia/Karachi",
    "iso:country":"PK",
    "name:und_x_variant":[
        "Kushang",
        "Khushang",
        "Khushhal Kaul"
    ],
    "wof:name":"Khushhal Kaul",
    "wof:placetype":"locality"
},
  "geometry": {"coordinates":[66.77977,30.79179],"type":"Point"}
}