{
  "type": "Feature",
  "properties": {
    "gn:admin1_code":"4.0",
    "gn:asciiname":"Kali Chohi",
    "gn:country_code":"PK",
    "gn:dem":497,
    "gn:feature_class":"P",
    "gn:feature_code":"PPL",
    "gn:name":"Kali Chohi",
    "gn:population":0,
    "gn:timezone":"Asia/Karachi",
    "iso:country":"PK",
    "wof:name":"Kali Chohi",
    "wof:placetype":"locality"
},
  "geometry": {"coordinates":[72.42369000000002,33.6226],"type":"Point"}
}