{
  "type": "Feature",
  "properties": {
    "gn:admin1_code":"2.0",
    "gn:asciiname":"Shabbirabad",
    "gn:country_code":"PK",
    "gn:dem":1452,
    "gn:feature_class":"P",
    "gn:feature_code":"PPL",
    "gn:name":"Shabbirabad",
    "gn:population":0,
    "gn:timezone":"Asia/Karachi",
    "iso:country":"PK",
    "name:eng_x_preferred":[
        "Shabbirabad"
    ],
    "name:urd_x_preferred":[
        "\u0634\u0628\u06cc\u0631 \u0622\u0628\u0627\u062f"
    ],
    "wof:name":"Shabbirabad",
    "wof:placetype":"locality"
},
  "geometry": {"coordinates":[69.21298,31.02603],"type":"Point"}
}