{
  "type": "Feature",
  "properties": {
    "gn:admin1_code":"3.0",
    "gn:asciiname":"Kiali",
    "gn:country_code":"PK",
    "gn:dem":1347,
    "gn:feature_class":"P",
    "gn:feature_code":"PPL",
    "gn:name":"Kiali",
    "gn:population":0,
    "gn:timezone":"Asia/Karachi",
    "iso:country":"PK",
    "name:eng_x_preferred":[
        "Ki\u0101ti"
    ],
    "wof:name":"Kiali",
    "wof:placetype":"locality"
},
  "geometry": {"coordinates":[73.43103000000001,33.96426],"type":"Point"}
}