{
  "type": "Feature",
  "properties": {
    "gn:admin1_code":"4",
    "gn:asciiname":"Basti Rasidpur",
    "gn:country_code":"PK",
    "gn:dem":161,
    "gn:feature_class":"P",
    "gn:feature_code":"PPL",
    "gn:name":"Basti Rasidpur",
    "gn:population":0,
    "gn:timezone":"Asia/Karachi",
    "iso:country":"PK",
    "name:und_x_variant":[
        "Rash\u012bdpur",
        "Ras\u012bdpur",
        "Basti Rasidpur"
    ],
    "wof:name":"Basti Rasidpur",
    "wof:placetype":"locality"
},
  "geometry": {"coordinates":[70.96195,31.41398],"type":"Point"}
}