{
  "type": "Feature",
  "properties": {
    "gn:admin1_code":"5",
    "gn:asciiname":"Goth Khaskheli",
    "gn:country_code":"PK",
    "gn:dem":19,
    "gn:feature_class":"P",
    "gn:feature_code":"PPL",
    "gn:name":"Goth Khaskheli",
    "gn:population":0,
    "gn:timezone":"Asia/Karachi",
    "iso:country":"PK",
    "name:eng_x_preferred":[
        "Kh\u0101skheli"
    ],
    "wof:name":"Goth Khaskheli",
    "wof:placetype":"locality"
},
  "geometry": {"coordinates":[68.4576,25.17389],"type":"Point"}
}