{
  "type": "Feature",
  "properties": {
    "gn:admin1_code":"4.0",
    "gn:asciiname":"Nanu Dogar",
    "gn:country_code":"PK",
    "gn:dem":202,
    "gn:feature_class":"P",
    "gn:feature_code":"PPL",
    "gn:name":"Nanu Dogar",
    "gn:population":0,
    "gn:timezone":"Asia/Karachi",
    "iso:country":"PK",
    "name:und_x_variant":[
        "N\u0101no Dogar"
    ],
    "wof:name":"Nanu Dogar",
    "wof:placetype":"locality"
},
  "geometry": {"coordinates":[74.06314,31.35851],"type":"Point"}
}