{
  "type": "Feature",
  "properties": {
    "gn:admin1_code":"5.0",
    "gn:asciiname":"Charhiar",
    "gn:country_code":"PK",
    "gn:dem":92,
    "gn:feature_class":"P",
    "gn:feature_code":"PPL",
    "gn:name":"Charhiar",
    "gn:population":0,
    "gn:timezone":"Asia/Karachi",
    "iso:country":"PK",
    "wof:name":"Charhiar",
    "wof:placetype":"locality"
},
  "geometry": {"coordinates":[70.29298,25.31043],"type":"Point"}
}