{
  "type": "Feature",
  "properties": {
    "gn:admin1_code":"2",
    "gn:asciiname":"Awagera Kili",
    "gn:country_code":"PK",
    "gn:dem":2113,
    "gn:feature_class":"P",
    "gn:feature_code":"PPL",
    "gn:name":"Awagera Kili",
    "gn:population":0,
    "gn:timezone":"Asia/Karachi",
    "iso:country":"PK",
    "name:rus_x_preferred":[
        "\u0420\u0430\u0441\u0443\u043b-\u0427\u0430\u0443\u0433\u0430\u0439"
    ],
    "name:und_x_variant":[
        "Rasul-Chaugay",
        "Ras\u016bl Chaugai",
        "Awagera Kili"
    ],
    "wof:name":"Awagera Kili",
    "wof:placetype":"locality"
},
  "geometry": {"coordinates":[67.43374,31.21632],"type":"Point"}
}