{
  "type": "Feature",
  "properties": {
    "gn:admin1_code":"6",
    "gn:asciiname":"Sahra",
    "gn:country_code":"PK",
    "gn:dem":2274,
    "gn:feature_class":"P",
    "gn:feature_code":"PPL",
    "gn:name":"Sahra",
    "gn:population":0,
    "gn:timezone":"Asia/Karachi",
    "iso:country":"PK",
    "name:ara_x_preferred":[
        "\u0635\u062d\u0631\u0627\u0621"
    ],
    "name:fin_x_preferred":[
        "Sahra"
    ],
    "name:ita_x_preferred":[
        "Sahra"
    ],
    "name:pol_x_preferred":[
        "Sahra"
    ],
    "name:por_x_preferred":[
        "Sahra"
    ],
    "name:und_x_variant":[
        "S\u0101ra"
    ],
    "wof:name":"Sahra",
    "wof:placetype":"locality"
},
  "geometry": {"coordinates":[74.01461,33.91819],"type":"Point"}
}