{
  "type": "Feature",
  "properties": {
    "gn:admin1_code":"2.0",
    "gn:asciiname":"Goth Maulai",
    "gn:country_code":"PK",
    "gn:dem":47,
    "gn:feature_class":"P",
    "gn:feature_code":"PPL",
    "gn:name":"Goth Maulai",
    "gn:population":0,
    "gn:timezone":"Asia/Karachi",
    "iso:country":"PK",
    "name:und_x_variant":[
        "Goth Moujai"
    ],
    "wof:name":"Goth Maulai",
    "wof:placetype":"locality"
},
  "geometry": {"coordinates":[67.74191999999999,28.39691],"type":"Point"}
}