{
  "type": "Feature",
  "properties": {
    "gn:admin1_code":"2",
    "gn:asciiname":"Baba Kili",
    "gn:country_code":"PK",
    "gn:dem":1611,
    "gn:feature_class":"P",
    "gn:feature_code":"PPL",
    "gn:name":"Baba Kili",
    "gn:population":0,
    "gn:timezone":"Asia/Karachi",
    "iso:country":"PK",
    "name:und_x_variant":[
        "B\u0101bu Kili"
    ],
    "wof:name":"Baba Kili",
    "wof:placetype":"locality"
},
  "geometry": {"coordinates":[69.11539,30.74793],"type":"Point"}
}