{
  "type": "Feature",
  "properties": {
    "gn:admin1_code":"4.0",
    "gn:asciiname":"Chah Barokanwala",
    "gn:country_code":"PK",
    "gn:dem":197,
    "gn:feature_class":"P",
    "gn:feature_code":"PPL",
    "gn:name":"Chah Barokanwala",
    "gn:population":0,
    "gn:timezone":"Asia/Karachi",
    "iso:country":"PK",
    "name:und_x_variant":[
        "Ch\u0101h Bharok\u0101nw\u0101la"
    ],
    "wof:name":"Chah Barokanwala",
    "wof:placetype":"locality"
},
  "geometry": {"coordinates":[71.71245999999999,32.25117],"type":"Point"}
}