{
  "type": "Feature",
  "properties": {
    "gn:admin1_code":"1.0",
    "gn:asciiname":"Sra Manza",
    "gn:country_code":"PK",
    "gn:dem":1918,
    "gn:feature_class":"P",
    "gn:feature_code":"PPL",
    "gn:name":"Sra Manza",
    "gn:population":0,
    "gn:timezone":"Asia/Karachi",
    "iso:country":"PK",
    "wof:name":"Sra Manza",
    "wof:placetype":"locality"
},
  "geometry": {"coordinates":[69.59738,33.02403],"type":"Point"}
}