{
  "type": "Feature",
  "properties": {
    "gn:admin1_code":"4.0",
    "gn:asciiname":"Dhola",
    "gn:country_code":"PK",
    "gn:dem":162,
    "gn:feature_class":"P",
    "gn:feature_code":"PPL",
    "gn:name":"Dhola",
    "gn:population":0,
    "gn:timezone":"Asia/Karachi",
    "iso:country":"PK",
    "name:ceb_x_preferred":[
        "Dhola"
    ],
    "name:swe_x_preferred":[
        "Dhola"
    ],
    "wof:name":"Dhola",
    "wof:placetype":"locality"
},
  "geometry": {"coordinates":[73.23392,30.46036],"type":"Point"}
}