{
  "type": "Feature",
  "properties": {
    "gn:admin1_code":"3.0",
    "gn:asciiname":"Bazi Khel",
    "gn:country_code":"PK",
    "gn:dem":410,
    "gn:feature_class":"P",
    "gn:feature_code":"PPL",
    "gn:name":"Bazi Khel",
    "gn:population":0,
    "gn:timezone":"Asia/Karachi",
    "iso:country":"PK",
    "name:und_x_variant":[
        "Kotkai Bozi Khel"
    ],
    "wof:name":"Bazi Khel",
    "wof:placetype":"locality"
},
  "geometry": {"coordinates":[70.55644000000002,33.00510999999999],"type":"Point"}
}