{
  "type": "Feature",
  "properties": {
    "gn:admin1_code":"4",
    "gn:asciiname":"Munehiwala",
    "gn:country_code":"PK",
    "gn:dem":122,
    "gn:feature_class":"P",
    "gn:feature_code":"PPL",
    "gn:name":"Munehiwala",
    "gn:population":0,
    "gn:timezone":"Asia/Karachi",
    "iso:country":"PK",
    "name:und_x_variant":[
        "Munsh\u012bw\u0101la"
    ],
    "wof:name":"Munehiwala",
    "wof:placetype":"locality"
},
  "geometry": {"coordinates":[71.39673000000001,30.15286],"type":"Point"}
}