{
  "type": "Feature",
  "properties": {
    "gn:admin1_code":"5",
    "gn:asciiname":"Deh Three Hundred Sixty-nine",
    "gn:country_code":"PK",
    "gn:dem":6,
    "gn:feature_class":"P",
    "gn:feature_code":"PPL",
    "gn:name":"Deh Three Hundred Sixty-nine",
    "gn:population":0,
    "gn:timezone":"Asia/Karachi",
    "iso:country":"PK",
    "wof:name":"Deh Three Hundred Sixty-nine",
    "wof:placetype":"locality"
},
  "geometry": {"coordinates":[69.34553000000001,24.99124],"type":"Point"}
}