{
  "type": "Feature",
  "properties": {
    "gn:admin1_code":"05",
    "gn:asciiname":"Makhi",
    "gn:country_code":"PK",
    "gn:dem":42,
    "gn:feature_class":"P",
    "gn:feature_code":"PPL",
    "gn:name":"Makhi",
    "gn:population":0,
    "gn:timezone":"Asia/Karachi",
    "iso:country":"PK",
    "name:ell_x_preferred":[
        "\u039c\u03ac\u03c7\u03b7"
    ],
    "wof:name":"Makhi",
    "wof:placetype":"locality"
},
  "geometry": {"coordinates":[67.53333000000001,27.03333],"type":"Point"}
}