{
  "type": "Feature",
  "properties": {
    "gn:admin1_code":"4.0",
    "gn:asciiname":"Chak Three -One Right A",
    "gn:country_code":"PK",
    "gn:dem":185,
    "gn:feature_class":"P",
    "gn:feature_code":"PPL",
    "gn:name":"Chak Three -One Right A",
    "gn:population":0,
    "gn:timezone":"Asia/Karachi",
    "iso:country":"PK",
    "wof:name":"Chak Three -One Right A",
    "wof:placetype":"locality"
},
  "geometry": {"coordinates":[73.60378,30.93852],"type":"Point"}
}