{
  "type": "Feature",
  "properties": {
    "gn:admin1_code":"4.0",
    "gn:asciiname":"Basti Pathanwali",
    "gn:country_code":"PK",
    "gn:dem":147,
    "gn:feature_class":"P",
    "gn:feature_code":"PPL",
    "gn:name":"Basti Pathanwali",
    "gn:population":0,
    "gn:timezone":"Asia/Karachi",
    "iso:country":"PK",
    "name:und_x_variant":[
        "Dar\u0101j",
        "Dir\u0101j",
        "Basti Pathanwali",
        "Pathanw\u0101la"
    ],
    "wof:name":"Basti Pathanwali",
    "wof:placetype":"locality"
},
  "geometry": {"coordinates":[72.18330999999998,31.17181],"type":"Point"}
}