{
  "type": "Feature",
  "properties": {
    "gn:admin1_code":"4",
    "gn:asciiname":"Basti Rajewala",
    "gn:country_code":"PK",
    "gn:dem":151,
    "gn:feature_class":"P",
    "gn:feature_code":"PPL",
    "gn:name":"Basti Rajewala",
    "gn:population":0,
    "gn:timezone":"Asia/Karachi",
    "iso:country":"PK",
    "name:und_x_variant":[
        "Rajjew\u0101la"
    ],
    "wof:name":"Basti Rajewala",
    "wof:placetype":"locality"
},
  "geometry": {"coordinates":[72.07799,31.10049],"type":"Point"}
}