{
  "type": "Feature",
  "properties": {
    "gn:admin1_code":"03",
    "gn:asciiname":"Panj Pir",
    "gn:country_code":"PK",
    "gn:dem":327,
    "gn:feature_class":"P",
    "gn:feature_code":"PPL",
    "gn:name":"Panj Pir",
    "gn:population":0,
    "gn:timezone":"Asia/Karachi",
    "iso:country":"PK",
    "name:eng_x_preferred":[
        "Panj Pir"
    ],
    "wof:name":"Panj Pir",
    "wof:placetype":"locality"
},
  "geometry": {"coordinates":[72.48078000000002,34.08841],"type":"Point"}
}