{
  "type": "Feature",
  "properties": {
    "gn:admin1_code":"4",
    "gn:asciiname":"Pipalwala Khu",
    "gn:country_code":"PK",
    "gn:dem":135,
    "gn:feature_class":"P",
    "gn:feature_code":"PPL",
    "gn:name":"Pipalwala Khu",
    "gn:population":0,
    "gn:timezone":"Asia/Karachi",
    "iso:country":"PK",
    "name:und_x_variant":[
        "Pipalw\u0101la Kh\u016bh"
    ],
    "wof:name":"Pipalwala Khu",
    "wof:placetype":"locality"
},
  "geometry": {"coordinates":[72.36181999999999,29.70474],"type":"Point"}
}