{
  "type": "Feature",
  "properties": {
    "gn:admin1_code":"3.0",
    "gn:asciiname":"Sumbal",
    "gn:country_code":"PK",
    "gn:dem":1323,
    "gn:feature_class":"P",
    "gn:feature_code":"PPL",
    "gn:name":"Sumbal",
    "gn:population":0,
    "gn:timezone":"Asia/Karachi",
    "iso:country":"PK",
    "name:eng_x_preferred":[
        "Sumbal Dh\u0101ra"
    ],
    "wof:name":"Sumbal",
    "wof:placetype":"locality"
},
  "geometry": {"coordinates":[73.27299000000002,33.97282],"type":"Point"}
}