{
  "type": "Feature",
  "properties": {
    "gn:admin1_code":"3",
    "gn:asciiname":"Saidabad",
    "gn:country_code":"PK",
    "gn:dem":395,
    "gn:feature_class":"P",
    "gn:feature_code":"PPL",
    "gn:name":"Saidabad",
    "gn:population":0,
    "gn:timezone":"Asia/Karachi",
    "iso:country":"PK",
    "name:fas_x_preferred":[
        "\u0633\u0639\u06cc\u062f\u0622\u0628\u0627\u062f"
    ],
    "name:und_x_variant":[
        "Mi\u0101ng\u0101no Khandare"
    ],
    "name:urd_x_preferred":[
        "\u0633\u0639\u06cc\u062f \u0622\u0628\u0627\u062f"
    ],
    "wof:name":"Saidabad",
    "wof:placetype":"locality"
},
  "geometry": {"coordinates":[72.62054999999999,34.1367],"type":"Point"}
}