{
  "type": "Feature",
  "properties": {
    "gn:admin1_code":"4.0",
    "gn:asciiname":"Basti Panwar",
    "gn:country_code":"PK",
    "gn:dem":90,
    "gn:feature_class":"P",
    "gn:feature_code":"PPL",
    "gn:name":"Basti Panwar",
    "gn:population":0,
    "gn:timezone":"Asia/Karachi",
    "iso:country":"PK",
    "name:urd_x_preferred":[
        "Basti Panwar"
    ],
    "wof:name":"Basti Panwar",
    "wof:placetype":"locality"
},
  "geometry": {"coordinates":[70.56652,28.85168],"type":"Point"}
}