{
  "type": "Feature",
  "properties": {
    "gn:admin1_code":"4.0",
    "gn:asciiname":"Gohra Khan Zinkani",
    "gn:country_code":"PK",
    "gn:dem":83,
    "gn:feature_class":"P",
    "gn:feature_code":"PPL",
    "gn:name":"Gohra Khan Zinkani",
    "gn:population":0,
    "gn:timezone":"Asia/Karachi",
    "iso:country":"PK",
    "name:und_x_variant":[
        "Zimk\u0101ni"
    ],
    "wof:name":"Gohra Khan Zinkani",
    "wof:placetype":"locality"
},
  "geometry": {"coordinates":[70.03126,28.75984],"type":"Point"}
}