{
  "type": "Feature",
  "properties": {
    "gn:admin1_code":"4",
    "gn:asciiname":"Sakhi",
    "gn:country_code":"PK",
    "gn:dem":120,
    "gn:feature_class":"P",
    "gn:feature_code":"PPL",
    "gn:name":"Sakhi",
    "gn:population":0,
    "gn:timezone":"Asia/Karachi",
    "iso:country":"PK",
    "name:cat_x_preferred":[
        "Sakhi"
    ],
    "name:hin_x_preferred":[
        "\u0938\u0916\u0940 \u0938\u0902\u092a\u094d\u0930\u0926\u093e\u092f"
    ],
    "wof:name":"Sakhi",
    "wof:placetype":"locality"
},
  "geometry": {"coordinates":[70.52167,29.91944],"type":"Point"}
}