{
  "type": "Feature",
  "properties": {
    "gn:admin1_code":"05",
    "gn:asciiname":"Tando Masti Khan",
    "gn:country_code":"PK",
    "gn:dem":58,
    "gn:feature_class":"P",
    "gn:feature_code":"PPL",
    "gn:name":"Tando Masti Khan",
    "gn:population":0,
    "gn:timezone":"Asia/Karachi",
    "iso:country":"PK",
    "name:und_x_variant":[
        "Tando Masti",
        "Tando Masti Khan"
    ],
    "wof:name":"Tando Masti Khan",
    "wof:placetype":"locality"
},
  "geometry": {"coordinates":[68.64383000000001,27.44006],"type":"Point"}
}