{
  "type": "Feature",
  "properties": {
    "gn:admin1_code":"3.0",
    "gn:asciiname":"Jaswal",
    "gn:country_code":"PK",
    "gn:dem":1093,
    "gn:feature_class":"P",
    "gn:feature_code":"PPL",
    "gn:name":"Jaswal",
    "gn:population":0,
    "gn:timezone":"Asia/Karachi",
    "iso:country":"PK",
    "name:und_x_variant":[
        "Paswal"
    ],
    "wof:name":"Jaswal",
    "wof:placetype":"locality"
},
  "geometry": {"coordinates":[73.26926,34.10869],"type":"Point"}
}