{
  "type": "Feature",
  "properties": {
    "gn:admin1_code":"3",
    "gn:asciiname":"Kaner",
    "gn:country_code":"PK",
    "gn:dem":728,
    "gn:feature_class":"P",
    "gn:feature_code":"PPL",
    "gn:name":"Kaner",
    "gn:population":0,
    "gn:timezone":"Asia/Karachi",
    "iso:country":"PK",
    "name:und_x_variant":[
        "Kanir"
    ],
    "wof:name":"Kaner",
    "wof:placetype":"locality"
},
  "geometry": {"coordinates":[72.83499,34.31321],"type":"Point"}
}