{
  "type": "Feature",
  "properties": {
    "gn:admin1_code":"1.0",
    "gn:asciiname":"Gidar Kalle",
    "gn:country_code":"PK",
    "gn:dem":1093,
    "gn:feature_class":"P",
    "gn:feature_code":"PPL",
    "gn:name":"Gidar Kalle",
    "gn:population":0,
    "gn:timezone":"Asia/Karachi",
    "iso:country":"PK",
    "name:und_x_variant":[
        "Gaodara",
        "Gidara",
        "Gidar Kalle"
    ],
    "wof:name":"Gidar Kalle",
    "wof:placetype":"locality"
},
  "geometry": {"coordinates":[70.30378,33.63195],"type":"Point"}
}