{
  "type": "Feature",
  "properties": {
    "gn:admin1_code":"5.0",
    "gn:asciiname":"Muhammad Amin Jhanjhi",
    "gn:country_code":"PK",
    "gn:dem":117,
    "gn:feature_class":"P",
    "gn:feature_code":"PPL",
    "gn:name":"Muhammad Amin Jhanjhi",
    "gn:population":0,
    "gn:timezone":"Asia/Karachi",
    "iso:country":"PK",
    "wof:name":"Muhammad Amin Jhanjhi",
    "wof:placetype":"locality"
},
  "geometry": {"coordinates":[70.61735999999998,24.94903],"type":"Point"}
}