{
  "type": "Feature",
  "properties": {
    "gn:admin1_code":"4.0",
    "gn:asciiname":"Dhok Khaki",
    "gn:country_code":"PK",
    "gn:dem":473,
    "gn:feature_class":"P",
    "gn:feature_code":"PPL",
    "gn:name":"Dhok Khaki",
    "gn:population":0,
    "gn:timezone":"Asia/Karachi",
    "iso:country":"PK",
    "wof:name":"Dhok Khaki",
    "wof:placetype":"locality"
},
  "geometry": {"coordinates":[72.37090000000001,33.59163],"type":"Point"}
}