{
  "type": "Feature",
  "properties": {
    "gn:admin1_code":"3.0",
    "gn:asciiname":"Sardarabad",
    "gn:country_code":"PK",
    "gn:dem":305,
    "gn:feature_class":"P",
    "gn:feature_code":"PPL",
    "gn:name":"Sardarabad",
    "gn:population":0,
    "gn:timezone":"Asia/Karachi",
    "iso:country":"PK",
    "name:aze_x_preferred":[
        "S\u0259rdarabad"
    ],
    "name:eng_x_preferred":[
        "Pasham Kor\u016bna"
    ],
    "name:fas_x_preferred":[
        "\u0633\u0631\u062f\u0627\u0631\u0622\u0628\u0627\u062f"
    ],
    "name:ita_x_preferred":[
        "Sardarabad"
    ],
    "wof:name":"Sardarabad",
    "wof:placetype":"locality"
},
  "geometry": {"coordinates":[71.80781999999998,34.17155],"type":"Point"}
}