{
  "type": "Feature",
  "properties": {
    "gn:admin1_code":"03",
    "gn:asciiname":"Mithi",
    "gn:country_code":"PK",
    "gn:dem":192,
    "gn:feature_class":"P",
    "gn:feature_code":"PPL",
    "gn:name":"Mithi",
    "gn:population":0,
    "gn:timezone":"Asia/Karachi",
    "iso:country":"PK",
    "name:ceb_x_preferred":[
        "Mithi"
    ],
    "name:fas_x_preferred":[
        "\u0645\u062a\u0647\u06cc"
    ],
    "name:hin_x_preferred":[
        "\u092e\u0920\u0940"
    ],
    "name:pan_x_preferred":[
        "\u0a2e\u0a40\u0a20\u0a40"
    ],
    "name:pnb_x_preferred":[
        "\u0645\u0679\u06be\u06cc"
    ],
    "name:rus_x_preferred":[
        "\u041c\u0438\u0442\u0445\u0438"
    ],
    "name:snd_x_preferred":[
        "\u0645\u067a\u064a"
    ],
    "name:swe_x_preferred":[
        "Mithi"
    ],
    "name:tam_x_preferred":[
        "\u0bae\u0bbf\u0ba4\u0bcd\u0ba4\u0bbf"
    ],
    "name:und_x_variant":[
        "Mitthi"
    ],
    "name:urd_x_preferred":[
        "\u0645\u0679\u06be\u06cc"
    ],
    "wof:name":"Mithi",
    "wof:placetype":"locality"
},
  "geometry": {"coordinates":[70.67968,31.73881],"type":"Point"}
}