{
  "type": "Feature",
  "properties": {
    "gn:admin1_code":"03",
    "gn:asciiname":"Mithi",
    "gn:country_code":"PK",
    "gn:dem":192,
    "gn:feature_class":"P",
    "gn:feature_code":"PPL",
    "gn:name":"Mithi",
    "gn:population":0,
    "gn:timezone":"Asia/Karachi",
    "iso:country":"PK",
    "name:und_x_variant":[
        "Mitthi"
    ],
    "wof:name":"Mithi",
    "wof:placetype":"locality"
},
  "geometry": {"coordinates":[70.67968,31.73881],"type":"Point"}
}