{
  "type": "Feature",
  "properties": {
    "gn:admin1_code":"5.0",
    "gn:asciiname":"Goth Ali Muhammad Jokhro",
    "gn:country_code":"PK",
    "gn:dem":27,
    "gn:feature_class":"P",
    "gn:feature_code":"PPL",
    "gn:name":"Goth Ali Muhammad Jokhro",
    "gn:population":0,
    "gn:timezone":"Asia/Karachi",
    "iso:country":"PK",
    "name:und_x_variant":[
        "Ali Muhammad Jokhio",
        "Goth Ali Muhammad Jokhio",
        "Goth Ali Muhammad Jokhro"
    ],
    "wof:name":"Goth Ali Muhammad Jokhro",
    "wof:placetype":"locality"
},
  "geometry": {"coordinates":[67.61138000000001,24.79174],"type":"Point"}
}