{
  "type": "Feature",
  "properties": {
    "gn:admin1_code":"5.0",
    "gn:asciiname":"Goth Umid Ali Khan Junejo",
    "gn:country_code":"PK",
    "gn:dem":49,
    "gn:feature_class":"P",
    "gn:feature_code":"PPL",
    "gn:name":"Goth Umid Ali Khan Junejo",
    "gn:population":0,
    "gn:timezone":"Asia/Karachi",
    "iso:country":"PK",
    "name:und_x_variant":[
        "Lemo Kh\u0101n Junejo"
    ],
    "wof:name":"Goth Umid Ali Khan Junejo",
    "wof:placetype":"locality"
},
  "geometry": {"coordinates":[67.9654,27.98721],"type":"Point"}
}