{
  "type": "Feature",
  "properties": {
    "gn:admin1_code":"2.0",
    "gn:asciiname":"Azam Shah Murad",
    "gn:country_code":"PK",
    "gn:dem":1854,
    "gn:feature_class":"P",
    "gn:feature_code":"PPL",
    "gn:name":"Azam Shah Murad",
    "gn:population":0,
    "gn:timezone":"Asia/Karachi",
    "iso:country":"PK",
    "wof:name":"Azam Shah Murad",
    "wof:placetype":"locality"
},
  "geometry": {"coordinates":[67.68329,30.83111],"type":"Point"}
}