{
  "type": "Feature",
  "properties": {
    "gn:admin1_code":"4.0",
    "gn:asciiname":"Parera",
    "gn:country_code":"PK",
    "gn:dem":270,
    "gn:feature_class":"P",
    "gn:feature_code":"PPL",
    "gn:name":"Parera",
    "gn:population":0,
    "gn:timezone":"Asia/Karachi",
    "iso:country":"PK",
    "name:und_x_variant":[
        "Bori"
    ],
    "wof:name":"Parera",
    "wof:placetype":"locality"
},
  "geometry": {"coordinates":[74.99954,32.31775],"type":"Point"}
}