{
  "type": "Feature",
  "properties": {
    "gn:admin1_code":"01",
    "gn:asciiname":"Ghulbandai",
    "gn:country_code":"PK",
    "gn:dem":905,
    "gn:feature_class":"P",
    "gn:feature_code":"PPL",
    "gn:name":"Ghulbandai",
    "gn:population":0,
    "gn:timezone":"Asia/Karachi",
    "iso:country":"PK",
    "name:eng_x_preferred":[
        "Ghulbandai"
    ],
    "wof:name":"Ghulbandai",
    "wof:placetype":"locality"
},
  "geometry": {"coordinates":[71.57658000000001,34.72482],"type":"Point"}
}