{
  "type": "Feature",
  "properties": {
    "gn:admin1_code":"5",
    "gn:asciiname":"Goth Lal Bakhsh Makrani",
    "gn:country_code":"PK",
    "gn:dem":26,
    "gn:feature_class":"P",
    "gn:feature_code":"PPL",
    "gn:name":"Goth Lal Bakhsh Makrani",
    "gn:population":0,
    "gn:timezone":"Asia/Karachi",
    "iso:country":"PK",
    "name:und_x_variant":[
        "L\u0101l Bakhsh Makr\u0101ni"
    ],
    "wof:name":"Goth Lal Bakhsh Makrani",
    "wof:placetype":"locality"
},
  "geometry": {"coordinates":[68.64619999999999,25.84805],"type":"Point"}
}