{
  "type": "Feature",
  "properties": {
    "gn:admin1_code":"5",
    "gn:asciiname":"Goth Muhammad Akram Punjabi",
    "gn:country_code":"PK",
    "gn:dem":12,
    "gn:feature_class":"P",
    "gn:feature_code":"PPL",
    "gn:name":"Goth Muhammad Akram Punjabi",
    "gn:population":0,
    "gn:timezone":"Asia/Karachi",
    "iso:country":"PK",
    "name:und_x_variant":[
        "Goth S\u0101leh Muhammad"
    ],
    "wof:name":"Goth Muhammad Akram Punjabi",
    "wof:placetype":"locality"
},
  "geometry": {"coordinates":[69.10120000000001,25.03669],"type":"Point"}
}