{
  "type": "Feature",
  "properties": {
    "gn:admin1_code":"1.0",
    "gn:asciiname":"Sandu",
    "gn:country_code":"PK",
    "gn:dem":1892,
    "gn:feature_class":"P",
    "gn:feature_code":"PPL",
    "gn:name":"Sandu",
    "gn:population":0,
    "gn:timezone":"Asia/Karachi",
    "iso:country":"PK",
    "name:ceb_x_preferred":[
        "Sandu"
    ],
    "name:deu_x_preferred":[
        "Sandu"
    ],
    "name:fra_x_preferred":[
        "Sandu"
    ],
    "name:ita_x_preferred":[
        "Sandu"
    ],
    "name:pol_x_preferred":[
        "Sandu"
    ],
    "name:por_x_preferred":[
        "Sandu"
    ],
    "name:ron_x_preferred":[
        "Sandu"
    ],
    "name:rus_x_preferred":[
        "\u0421\u0430\u043d\u0434\u0443"
    ],
    "name:swe_x_preferred":[
        "Sandu"
    ],
    "name:ukr_x_preferred":[
        "\u0421\u0430\u043d\u0434\u0443"
    ],
    "wof:name":"Sandu",
    "wof:placetype":"locality"
},
  "geometry": {"coordinates":[70.54595,33.65246],"type":"Point"}
}