{
  "type": "Feature",
  "properties": {
    "gn:admin1_code":"4.0",
    "gn:asciiname":"Balawal",
    "gn:country_code":"PK",
    "gn:dem":387,
    "gn:feature_class":"P",
    "gn:feature_code":"PPL",
    "gn:name":"Balawal",
    "gn:population":0,
    "gn:timezone":"Asia/Karachi",
    "iso:country":"PK",
    "name:und_x_variant":[
        "Bal\u0101wal"
    ],
    "wof:name":"Balawal",
    "wof:placetype":"locality"
},
  "geometry": {"coordinates":[72.70376,33.29022],"type":"Point"}
}