{
  "type": "Feature",
  "properties": {
    "gn:admin1_code":"4.0",
    "gn:asciiname":"Bawre Nau",
    "gn:country_code":"PK",
    "gn:dem":205,
    "gn:feature_class":"P",
    "gn:feature_code":"PPL",
    "gn:name":"Bawre Nau",
    "gn:population":0,
    "gn:timezone":"Asia/Karachi",
    "iso:country":"PK",
    "name:und_x_variant":[
        "B\u0101ware Nau"
    ],
    "wof:name":"Bawre Nau",
    "wof:placetype":"locality"
},
  "geometry": {"coordinates":[73.6194,32.12001],"type":"Point"}
}