{
  "type": "Feature",
  "properties": {
    "gn:admin1_code":"4",
    "gn:asciiname":"Chak Two Hundred Nineteen Western Bar",
    "gn:country_code":"PK",
    "gn:dem":128,
    "gn:feature_class":"P",
    "gn:feature_code":"PPL",
    "gn:name":"Chak Two Hundred Nineteen Western Bar",
    "gn:population":0,
    "gn:timezone":"Asia/Karachi",
    "iso:country":"PK",
    "name:und_x_variant":[
        "Chak Two Hundred Nineteen WB"
    ],
    "wof:name":"Chak Two Hundred Nineteen Western Bar",
    "wof:placetype":"locality"
},
  "geometry": {"coordinates":[71.90191999999998,29.83725],"type":"Point"}
}