{
  "type": "Feature",
  "properties": {
    "gn:admin1_code":"7.0",
    "gn:asciiname":"Das",
    "gn:country_code":"PK",
    "gn:dem":3189,
    "gn:feature_class":"P",
    "gn:feature_code":"PPL",
    "gn:name":"Das",
    "gn:population":0,
    "gn:timezone":"Asia/Karachi",
    "iso:country":"PK",
    "name:ceb_x_preferred":[
        "Das"
    ],
    "name:dan_x_preferred":[
        "Das"
    ],
    "name:deu_x_preferred":[
        "Das"
    ],
    "name:fra_x_preferred":[
        "Das"
    ],
    "name:lmo_x_preferred":[
        "Das"
    ],
    "name:nld_x_preferred":[
        "Das"
    ],
    "name:ron_x_preferred":[
        "Das"
    ],
    "name:rus_x_preferred":[
        "\u0414\u0430\u0441"
    ],
    "name:spa_x_preferred":[
        "DAS"
    ],
    "name:swe_x_preferred":[
        "Das"
    ],
    "name:ukr_x_preferred":[
        "\u0414\u0430\u0441"
    ],
    "wof:name":"Das",
    "wof:placetype":"locality"
},
  "geometry": {"coordinates":[74.3955,35.69015],"type":"Point"}
}