{
  "type": "Feature",
  "properties": {
    "gn:admin1_code":"2.0",
    "gn:asciiname":"Kili Miran",
    "gn:country_code":"PK",
    "gn:dem":1590,
    "gn:feature_class":"P",
    "gn:feature_code":"PPL",
    "gn:name":"Kili Miran",
    "gn:population":0,
    "gn:timezone":"Asia/Karachi",
    "iso:country":"PK",
    "name:und_x_variant":[
        "Kili Mir Hasan"
    ],
    "wof:name":"Kili Miran",
    "wof:placetype":"locality"
},
  "geometry": {"coordinates":[66.7392,29.94431],"type":"Point"}
}