{
  "type": "Feature",
  "properties": {
    "gn:admin1_code":"5.0",
    "gn:asciiname":"Benayo",
    "gn:country_code":"PK",
    "gn:dem":118,
    "gn:feature_class":"P",
    "gn:feature_code":"PPL",
    "gn:name":"Benayo",
    "gn:population":0,
    "gn:timezone":"Asia/Karachi",
    "iso:country":"PK",
    "wof:name":"Benayo",
    "wof:placetype":"locality"
},
  "geometry": {"coordinates":[70.46684999999999,25.43554],"type":"Point"}
}