{
  "type": "Feature",
  "properties": {
    "gn:admin1_code":"4.0",
    "gn:asciiname":"Basti Farid Bakhsh Langah",
    "gn:country_code":"PK",
    "gn:dem":99,
    "gn:feature_class":"P",
    "gn:feature_code":"PPL",
    "gn:name":"Basti Farid Bakhsh Langah",
    "gn:population":0,
    "gn:timezone":"Asia/Karachi",
    "iso:country":"PK",
    "name:und_x_variant":[
        "Langhaw\u0101la Khu"
    ],
    "wof:name":"Basti Farid Bakhsh Langah",
    "wof:placetype":"locality"
},
  "geometry": {"coordinates":[70.38176,29.23244],"type":"Point"}
}