{
  "type": "Feature",
  "properties": {
    "gn:admin1_code":"2.0",
    "gn:asciiname":"Kili Mulla Fateh Khan",
    "gn:country_code":"PK",
    "gn:dem":2022,
    "gn:feature_class":"P",
    "gn:feature_code":"PPL",
    "gn:name":"Kili Mulla Fateh Khan",
    "gn:population":0,
    "gn:timezone":"Asia/Karachi",
    "iso:country":"PK",
    "wof:name":"Kili Mulla Fateh Khan",
    "wof:placetype":"locality"
},
  "geometry": {"coordinates":[68.86612,31.37273],"type":"Point"}
}