{
  "type": "Feature",
  "properties": {
    "gn:admin1_code":"4",
    "gn:asciiname":"Dera Qadirpur",
    "gn:country_code":"PK",
    "gn:dem":150,
    "gn:feature_class":"P",
    "gn:feature_code":"PPL",
    "gn:name":"Dera Qadirpur",
    "gn:population":0,
    "gn:timezone":"Asia/Karachi",
    "iso:country":"PK",
    "name:und_x_variant":[
        "Qad\u012brpur"
    ],
    "wof:name":"Dera Qadirpur",
    "wof:placetype":"locality"
},
  "geometry": {"coordinates":[72.17364000000001,31.24383],"type":"Point"}
}