{
  "type": "Feature",
  "properties": {
    "gn:admin1_code":"02",
    "gn:asciiname":"Nokhbur Kalat",
    "gn:country_code":"PK",
    "gn:dem":32,
    "gn:feature_class":"P",
    "gn:feature_code":"PPL",
    "gn:name":"Nokhbur Kalat",
    "gn:population":0,
    "gn:timezone":"Asia/Karachi",
    "iso:country":"PK",
    "name:und_x_variant":[
        "Nokhb\u016br",
        "Nokhbur Kalat"
    ],
    "wof:name":"Nokhbur Kalat",
    "wof:placetype":"locality"
},
  "geometry": {"coordinates":[63.03247,25.48855],"type":"Point"}
}