{
  "type": "Feature",
  "properties": {
    "gn:admin1_code":"8.0",
    "gn:asciiname":"Badhalan",
    "gn:country_code":"PK",
    "gn:dem":596,
    "gn:feature_class":"P",
    "gn:feature_code":"PPL",
    "gn:name":"Badhalan",
    "gn:population":0,
    "gn:timezone":"Asia/Karachi",
    "iso:country":"PK",
    "wof:name":"Badhalan",
    "wof:placetype":"locality"
},
  "geometry": {"coordinates":[73.29589,33.66434],"type":"Point"}
}