{
  "type": "Feature",
  "properties": {
    "gn:admin1_code":"5.0",
    "gn:asciiname":"Pilro jo Goth",
    "gn:country_code":"PK",
    "gn:dem":42,
    "gn:feature_class":"P",
    "gn:feature_code":"PPL",
    "gn:name":"Pilro jo Goth",
    "gn:population":0,
    "gn:timezone":"Asia/Karachi",
    "iso:country":"PK",
    "name:und_x_variant":[
        "P\u012blro"
    ],
    "wof:name":"Pilro jo Goth",
    "wof:placetype":"locality"
},
  "geometry": {"coordinates":[70.26893000000001,24.55999],"type":"Point"}
}