{
  "type": "Feature",
  "properties": {
    "gn:admin1_code":"3",
    "gn:asciiname":"Boli",
    "gn:country_code":"PK",
    "gn:dem":951,
    "gn:feature_class":"P",
    "gn:feature_code":"PPL",
    "gn:name":"Boli",
    "gn:population":0,
    "gn:timezone":"Asia/Karachi",
    "iso:country":"PK",
    "name:bar_x_preferred":[
        "Boli"
    ],
    "name:ceb_x_preferred":[
        "Boli"
    ],
    "name:deu_x_preferred":[
        "Boli"
    ],
    "name:fin_x_preferred":[
        "Boli"
    ],
    "name:fra_x_preferred":[
        "Boli"
    ],
    "name:rus_x_preferred":[
        "\u0411\u043e\u043b\u0438"
    ],
    "name:spa_x_preferred":[
        "Boli"
    ],
    "name:srp_x_preferred":[
        "\u0411\u043e\u043b\u0438"
    ],
    "name:swe_x_preferred":[
        "Boli"
    ],
    "name:ukr_x_preferred":[
        "\u0411\u043e\u043b\u0456"
    ],
    "name:und_x_variant":[
        "Bauli"
    ],
    "wof:name":"Boli",
    "wof:placetype":"locality"
},
  "geometry": {"coordinates":[73.34694,34.51684],"type":"Point"}
}