{
  "type": "Feature",
  "properties": {
    "gn:admin1_code":"3",
    "gn:asciiname":"Boli",
    "gn:country_code":"PK",
    "gn:dem":951,
    "gn:feature_class":"P",
    "gn:feature_code":"PPL",
    "gn:name":"Boli",
    "gn:population":0,
    "gn:timezone":"Asia/Karachi",
    "iso:country":"PK",
    "name:und_x_variant":[
        "Bauli"
    ],
    "wof:name":"Boli",
    "wof:placetype":"locality"
},
  "geometry": {"coordinates":[73.34694,34.51684],"type":"Point"}
}