{
  "type": "Feature",
  "properties": {
    "gn:admin1_code":"4.0",
    "gn:asciiname":"Hussain Bholi ka Dera",
    "gn:country_code":"PK",
    "gn:dem":212,
    "gn:feature_class":"P",
    "gn:feature_code":"PPL",
    "gn:name":"Hussain Bholi ka Dera",
    "gn:population":0,
    "gn:timezone":"Asia/Karachi",
    "iso:country":"PK",
    "wof:name":"Hussain Bholi ka Dera",
    "wof:placetype":"locality"
},
  "geometry": {"coordinates":[73.38809999999999,32.42527],"type":"Point"}
}