{
  "type": "Feature",
  "properties": {
    "gn:admin1_code":"5",
    "gn:asciiname":"Nur Muhammad Paryar",
    "gn:country_code":"PK",
    "gn:dem":20,
    "gn:feature_class":"P",
    "gn:feature_code":"PPL",
    "gn:name":"Nur Muhammad Paryar",
    "gn:population":0,
    "gn:timezone":"Asia/Karachi",
    "iso:country":"PK",
    "name:eng_x_preferred":[
        "Nur Muhammad Paryar"
    ],
    "wof:name":"Nur Muhammad Paryar",
    "wof:placetype":"locality"
},
  "geometry": {"coordinates":[68.42381999999999,25.3609],"type":"Point"}
}