{
  "type": "Feature",
  "properties": {
    "gn:admin1_code":"3.0",
    "gn:asciiname":"Mir Ahmed Khan Garhi",
    "gn:country_code":"PK",
    "gn:dem":565,
    "gn:feature_class":"P",
    "gn:feature_code":"PPL",
    "gn:name":"Mir Ahmed Khan Garhi",
    "gn:population":0,
    "gn:timezone":"Asia/Karachi",
    "iso:country":"PK",
    "name:und_x_variant":[
        "M\u012br Ahmad Khan Garhi"
    ],
    "wof:name":"Mir Ahmed Khan Garhi",
    "wof:placetype":"locality"
},
  "geometry": {"coordinates":[71.54257,33.73706],"type":"Point"}
}