{
  "type": "Feature",
  "properties": {
    "gn:admin1_code":"5",
    "gn:asciiname":"Goth Masti Khan Kalro",
    "gn:country_code":"PK",
    "gn:dem":19,
    "gn:feature_class":"P",
    "gn:feature_code":"PPL",
    "gn:name":"Goth Masti Khan Kalro",
    "gn:population":0,
    "gn:timezone":"Asia/Karachi",
    "iso:country":"PK",
    "wof:name":"Goth Masti Khan Kalro",
    "wof:placetype":"locality"
},
  "geometry": {"coordinates":[68.75633000000001,25.44036],"type":"Point"}
}