{
  "type": "Feature",
  "properties": {
    "gn:admin1_code":"5.0",
    "gn:asciiname":"Siddiq Mallah",
    "gn:country_code":"PK",
    "gn:dem":8,
    "gn:feature_class":"P",
    "gn:feature_code":"PPL",
    "gn:name":"Siddiq Mallah",
    "gn:population":0,
    "gn:timezone":"Asia/Karachi",
    "iso:country":"PK",
    "name:und_x_variant":[
        "Muhammad Mandro"
    ],
    "wof:name":"Siddiq Mallah",
    "wof:placetype":"locality"
},
  "geometry": {"coordinates":[68.78384,24.53435],"type":"Point"}
}