{
  "type": "Feature",
  "properties": {
    "gn:admin1_code":"6",
    "gn:asciiname":"Doba",
    "gn:country_code":"PK",
    "gn:dem":1822,
    "gn:feature_class":"P",
    "gn:feature_code":"PPL",
    "gn:name":"Doba",
    "gn:population":0,
    "gn:timezone":"Asia/Karachi",
    "iso:country":"PK",
    "wof:name":"Doba",
    "wof:placetype":"locality"
},
  "geometry": {"coordinates":[73.56990999999999,34.54281],"type":"Point"}
}