{
  "type": "Feature",
  "properties": {
    "gn:admin1_code":"4",
    "gn:asciiname":"Basti Jhok Naich",
    "gn:country_code":"PK",
    "gn:dem":96,
    "gn:feature_class":"P",
    "gn:feature_code":"PPL",
    "gn:name":"Basti Jhok Naich",
    "gn:population":0,
    "gn:timezone":"Asia/Karachi",
    "iso:country":"PK",
    "name:und_x_variant":[
        "Basti Muhammad N\u0101ich"
    ],
    "wof:name":"Basti Jhok Naich",
    "wof:placetype":"locality"
},
  "geometry": {"coordinates":[70.96814000000001,29.1106],"type":"Point"}
}