{
  "type": "Feature",
  "properties": {
    "gn:admin1_code":"4",
    "gn:asciiname":"Kakik",
    "gn:country_code":"PK",
    "gn:dem":97,
    "gn:feature_class":"P",
    "gn:feature_code":"PPL",
    "gn:name":"Kakik",
    "gn:population":0,
    "gn:timezone":"Asia/Karachi",
    "iso:country":"PK",
    "wof:name":"Kakik",
    "wof:placetype":"locality"
},
  "geometry": {"coordinates":[71.03333000000001,29.19583],"type":"Point"}
}