{
  "type": "Feature",
  "properties": {
    "gn:admin1_code":"4.0",
    "gn:asciiname":"Dandi Kalial",
    "gn:country_code":"PK",
    "gn:dem":259,
    "gn:feature_class":"P",
    "gn:feature_code":"PPL",
    "gn:name":"Dandi Kalial",
    "gn:population":0,
    "gn:timezone":"Asia/Karachi",
    "iso:country":"PK",
    "wof:name":"Dandi Kalial",
    "wof:placetype":"locality"
},
  "geometry": {"coordinates":[73.85491999999998,32.91599],"type":"Point"}
}