{
  "type": "Feature",
  "properties": {
    "gn:admin1_code":"4",
    "gn:asciiname":"Chak Two Hundred Seventy-eight A",
    "gn:country_code":"PK",
    "gn:dem":149,
    "gn:feature_class":"P",
    "gn:feature_code":"PPL",
    "gn:name":"Chak Two Hundred Seventy-eight A",
    "gn:population":0,
    "gn:timezone":"Asia/Karachi",
    "iso:country":"PK",
    "name:und_x_variant":[
        "Chak Two Hundred Seventy-Eight"
    ],
    "wof:name":"Chak Two Hundred Seventy-eight A",
    "wof:placetype":"locality"
},
  "geometry": {"coordinates":[71.13235999999998,30.95075],"type":"Point"}
}