{
  "type": "Feature",
  "properties": {
    "gn:admin1_code":"5.0",
    "gn:asciiname":"Goth Abdul Rehman Dal",
    "gn:country_code":"PK",
    "gn:dem":41,
    "gn:feature_class":"P",
    "gn:feature_code":"PPL",
    "gn:name":"Goth Abdul Rehman Dal",
    "gn:population":0,
    "gn:timezone":"Asia/Karachi",
    "iso:country":"PK",
    "wof:name":"Goth Abdul Rehman Dal",
    "wof:placetype":"locality"
},
  "geometry": {"coordinates":[67.95573,26.64872],"type":"Point"}
}