{
  "type": "Feature",
  "properties": {
    "gn:admin1_code":"4.0",
    "gn:asciiname":"Gohri",
    "gn:country_code":"PK",
    "gn:dem":212,
    "gn:feature_class":"P",
    "gn:feature_code":"PPL",
    "gn:name":"Gohri",
    "gn:population":0,
    "gn:timezone":"Asia/Karachi",
    "iso:country":"PK",
    "name:und_x_variant":[
        "Gohari",
        "Gohri"
    ],
    "wof:name":"Gohri",
    "wof:placetype":"locality"
},
  "geometry": {"coordinates":[73.30489,32.45238],"type":"Point"}
}