{
  "type": "Feature",
  "properties": {
    "gn:admin1_code":"2.0",
    "gn:asciiname":"Shahdad Chat",
    "gn:country_code":"PK",
    "gn:dem":241,
    "gn:feature_class":"P",
    "gn:feature_code":"PPL",
    "gn:name":"Shahdad Chat",
    "gn:population":0,
    "gn:timezone":"Asia/Karachi",
    "iso:country":"PK",
    "wof:name":"Shahdad Chat",
    "wof:placetype":"locality"
},
  "geometry": {"coordinates":[61.94693,26.15472],"type":"Point"}
}