{
  "type": "Feature",
  "properties": {
    "gn:admin1_code":"4.0",
    "gn:asciiname":"Darganiwala",
    "gn:country_code":"PK",
    "gn:dem":145,
    "gn:feature_class":"P",
    "gn:feature_code":"PPL",
    "gn:name":"Darganiwala",
    "gn:population":0,
    "gn:timezone":"Asia/Karachi",
    "iso:country":"PK",
    "name:eng_x_preferred":[
        "Darganiwala"
    ],
    "wof:name":"Darganiwala",
    "wof:placetype":"locality"
},
  "geometry": {"coordinates":[70.90213,30.89401],"type":"Point"}
}