{
  "type": "Feature",
  "properties": {
    "gn:admin1_code":"7.0",
    "gn:asciiname":"Mallawa",
    "gn:country_code":"PK",
    "gn:dem":3263,
    "gn:feature_class":"P",
    "gn:feature_code":"PPL",
    "gn:name":"Mallawa",
    "gn:population":0,
    "gn:timezone":"Asia/Karachi",
    "iso:country":"PK",
    "wof:name":"Mallawa",
    "wof:placetype":"locality"
},
  "geometry": {"coordinates":[75.84416,35.10687],"type":"Point"}
}