{
  "type": "Feature",
  "properties": {
    "gn:admin1_code":"4.0",
    "gn:asciiname":"Haleliwala",
    "gn:country_code":"PK",
    "gn:dem":107,
    "gn:feature_class":"P",
    "gn:feature_code":"PPL",
    "gn:name":"Haleliwala",
    "gn:population":0,
    "gn:timezone":"Asia/Karachi",
    "iso:country":"PK",
    "name:und_x_variant":[
        "Haleli",
        "Jangal",
        "Haleliwala"
    ],
    "wof:name":"Haleliwala",
    "wof:placetype":"locality"
},
  "geometry": {"coordinates":[70.87026999999998,29.551],"type":"Point"}
}