{
  "type": "Feature",
  "properties": {
    "gn:admin1_code":"4",
    "gn:asciiname":"Ara Akbar",
    "gn:country_code":"PK",
    "gn:dem":128,
    "gn:feature_class":"P",
    "gn:feature_code":"PPL",
    "gn:name":"Ara Akbar",
    "gn:population":0,
    "gn:timezone":"Asia/Karachi",
    "iso:country":"PK",
    "name:eng_x_preferred":[
        "\u0100ra Akbar Sh\u0101h"
    ],
    "name:eng_x_variant":[
        "\u0100ri Akbar Sh\u0101h"
    ],
    "name:und_x_variant":[
        "Ara Akbar Sh\u0101h"
    ],
    "wof:name":"Ara Akbar",
    "wof:placetype":"locality"
},
  "geometry": {"coordinates":[70.94192,30.24131],"type":"Point"}
}