{
  "type": "Feature",
  "properties": {
    "gn:admin1_code":"2.0",
    "gn:asciiname":"Kasha Kili",
    "gn:country_code":"PK",
    "gn:dem":2080,
    "gn:feature_class":"P",
    "gn:feature_code":"PPL",
    "gn:name":"Kasha Kili",
    "gn:population":0,
    "gn:timezone":"Asia/Karachi",
    "iso:country":"PK",
    "wof:name":"Kasha Kili",
    "wof:placetype":"locality"
},
  "geometry": {"coordinates":[68.97967,31.15292],"type":"Point"}
}