{
  "type": "Feature",
  "properties": {
    "gn:admin1_code":"2.0",
    "gn:asciiname":"Goethan Kili",
    "gn:country_code":"PK",
    "gn:dem":1462,
    "gn:feature_class":"P",
    "gn:feature_code":"PPL",
    "gn:name":"Goethan Kili",
    "gn:population":0,
    "gn:timezone":"Asia/Karachi",
    "iso:country":"PK",
    "name:und_x_variant":[
        "Goeth\u0101n Kili"
    ],
    "wof:name":"Goethan Kili",
    "wof:placetype":"locality"
},
  "geometry": {"coordinates":[69.98296999999999,31.06592],"type":"Point"}
}