{
  "type": "Feature",
  "properties": {
    "gn:admin1_code":"05",
    "gn:asciiname":"Goth Kando Khaskheli",
    "gn:country_code":"PK",
    "gn:dem":32,
    "gn:feature_class":"P",
    "gn:feature_code":"PPL",
    "gn:name":"Goth Kando Khaskheli",
    "gn:population":0,
    "gn:timezone":"Asia/Karachi",
    "iso:country":"PK",
    "name:und_x_variant":[
        "Mir Ewaz"
    ],
    "wof:name":"Goth Kando Khaskheli",
    "wof:placetype":"locality"
},
  "geometry": {"coordinates":[68.19705,26.22377],"type":"Point"}
}