{
  "type": "Feature",
  "properties": {
    "gn:admin1_code":"6",
    "gn:asciiname":"Gura",
    "gn:country_code":"PK",
    "gn:dem":670,
    "gn:feature_class":"P",
    "gn:feature_code":"PPL",
    "gn:name":"Gura",
    "gn:population":0,
    "gn:timezone":"Asia/Karachi",
    "iso:country":"PK",
    "wof:name":"Gura",
    "wof:placetype":"locality"
},
  "geometry": {"coordinates":[74.07575,33.11557],"type":"Point"}
}