{
  "type": "Feature",
  "properties": {
    "gn:admin1_code":"01",
    "gn:asciiname":"Sheikhan",
    "gn:country_code":"PK",
    "gn:dem":848,
    "gn:feature_class":"P",
    "gn:feature_code":"PPL",
    "gn:name":"Sheikhan",
    "gn:population":0,
    "gn:timezone":"Asia/Karachi",
    "iso:country":"PK",
    "name:eng_x_preferred":[
        "Gul Pal\u0101i"
    ],
    "name:fas_x_preferred":[
        "\u0634\u06cc\u062e\u0646"
    ],
    "name:und_x_variant":[
        "Gul Qal\u0101i",
        "Sheikhan"
    ],
    "name:urd_x_preferred":[
        "\u0634\u06cc\u062e\u0646"
    ],
    "wof:name":"Sheikhan",
    "wof:placetype":"locality"
},
  "geometry": {"coordinates":[71.51028000000002,34.59397],"type":"Point"}
}