{
  "type": "Feature",
  "properties": {
    "gn:admin1_code":"4.0",
    "gn:asciiname":"Gazwala",
    "gn:country_code":"PK",
    "gn:dem":596,
    "gn:feature_class":"P",
    "gn:feature_code":"PPL",
    "gn:name":"Gazwala",
    "gn:population":0,
    "gn:timezone":"Asia/Karachi",
    "iso:country":"PK",
    "wof:name":"Gazwala",
    "wof:placetype":"locality"
},
  "geometry": {"coordinates":[70.29798000000001,31.07646],"type":"Point"}
}