{
  "type": "Feature",
  "properties": {
    "gn:admin1_code":"01",
    "gn:asciiname":"Darbalai",
    "gn:country_code":"PK",
    "gn:dem":1647,
    "gn:feature_class":"P",
    "gn:feature_code":"PPL",
    "gn:name":"Darbalai",
    "gn:population":0,
    "gn:timezone":"Asia/Karachi",
    "iso:country":"PK",
    "name:und_x_variant":[
        "Drublai",
        "Drablai"
    ],
    "wof:name":"Darbalai",
    "wof:placetype":"locality"
},
  "geometry": {"coordinates":[69.63473,32.99743],"type":"Point"}
}