{
  "type": "Feature",
  "properties": {
    "gn:admin1_code":"2.0",
    "gn:asciiname":"Goth Haji Ghou Bay",
    "gn:country_code":"PK",
    "gn:dem":29,
    "gn:feature_class":"P",
    "gn:feature_code":"PPL",
    "gn:name":"Goth Haji Ghou Bay",
    "gn:population":0,
    "gn:timezone":"Asia/Karachi",
    "iso:country":"PK",
    "name:eng_x_preferred":[
        "Goth Y\u016bsuf"
    ],
    "name:eng_x_variant":[
        "Goth Y\u016bsof"
    ],
    "name:und_x_variant":[
        "Goth Haji Ghou Bay"
    ],
    "wof:name":"Goth Haji Ghou Bay",
    "wof:placetype":"locality"
},
  "geometry": {"coordinates":[66.90514,25.03103],"type":"Point"}
}