{
  "type": "Feature",
  "properties": {
    "gn:admin1_code":"4.0",
    "gn:asciiname":"Zamirabad",
    "gn:country_code":"PK",
    "gn:dem":193,
    "gn:feature_class":"P",
    "gn:feature_code":"PPL",
    "gn:name":"Zamirabad",
    "gn:population":0,
    "gn:timezone":"Asia/Karachi",
    "iso:country":"PK",
    "name:und_x_variant":[
        "Victoria Farm"
    ],
    "wof:name":"Zamirabad",
    "wof:placetype":"locality"
},
  "geometry": {"coordinates":[73.79366,30.90655],"type":"Point"}
}