{
  "type": "Feature",
  "properties": {
    "gn:admin1_code":"2.0",
    "gn:asciiname":"Joi",
    "gn:country_code":"PK",
    "gn:dem":746,
    "gn:feature_class":"P",
    "gn:feature_code":"PPL",
    "gn:name":"Joi",
    "gn:population":0,
    "gn:timezone":"Asia/Karachi",
    "iso:country":"PK",
    "name:ceb_x_preferred":[
        "Joi"
    ],
    "name:jpn_x_preferred":[
        "Joi"
    ],
    "name:swe_x_preferred":[
        "Joi"
    ],
    "wof:name":"Joi",
    "wof:placetype":"locality"
},
  "geometry": {"coordinates":[63.26595,26.467],"type":"Point"}
}