{
  "type": "Feature",
  "properties": {
    "gn:admin1_code":"4",
    "gn:asciiname":"Nahinwala",
    "gn:country_code":"PK",
    "gn:dem":113,
    "gn:feature_class":"P",
    "gn:feature_code":"PPL",
    "gn:name":"Nahinwala",
    "gn:population":0,
    "gn:timezone":"Asia/Karachi",
    "iso:country":"PK",
    "name:und_x_variant":[
        "Nahimw\u0101la",
        "Nahinw\u0101la",
        "Nahinwala"
    ],
    "wof:name":"Nahinwala",
    "wof:placetype":"locality"
},
  "geometry": {"coordinates":[71.13118,29.81239],"type":"Point"}
}