{
  "type": "Feature",
  "properties": {
    "gn:admin1_code":"4.0",
    "gn:asciiname":"Chak Nintey-nine M",
    "gn:country_code":"PK",
    "gn:dem":114,
    "gn:feature_class":"P",
    "gn:feature_code":"PPL",
    "gn:name":"Chak Nintey-nine M",
    "gn:population":0,
    "gn:timezone":"Asia/Karachi",
    "iso:country":"PK",
    "name:eng_x_preferred":[
        "Chak Nintey-nine M"
    ],
    "wof:name":"Chak Nintey-nine M",
    "wof:placetype":"locality"
},
  "geometry": {"coordinates":[71.60111999999999,29.49158],"type":"Point"}
}