{
  "type": "Feature",
  "properties": {
    "gn:admin1_code":"5.0",
    "gn:asciiname":"Narhoro",
    "gn:country_code":"PK",
    "gn:dem":14,
    "gn:feature_class":"P",
    "gn:feature_code":"PPL",
    "gn:name":"Narhoro",
    "gn:population":0,
    "gn:timezone":"Asia/Karachi",
    "iso:country":"PK",
    "name:und_x_variant":[
        "Nurhoro"
    ],
    "wof:name":"Narhoro",
    "wof:placetype":"locality"
},
  "geometry": {"coordinates":[69.73947,24.38033],"type":"Point"}
}