{
  "type": "Feature",
  "properties": {
    "gn:admin1_code":"5",
    "gn:asciiname":"Goth Abdul Hakim Dars",
    "gn:country_code":"PK",
    "gn:dem":20,
    "gn:feature_class":"P",
    "gn:feature_code":"PPL",
    "gn:name":"Goth Abdul Hakim Dars",
    "gn:population":0,
    "gn:timezone":"Asia/Karachi",
    "iso:country":"PK",
    "name:und_x_variant":[
        "Goth Muhammad Ali Dars"
    ],
    "wof:name":"Goth Abdul Hakim Dars",
    "wof:placetype":"locality"
},
  "geometry": {"coordinates":[68.84921999999999,25.54361],"type":"Point"}
}