{
  "type": "Feature",
  "properties": {
    "gn:admin1_code":"5",
    "gn:asciiname":"Mehrab Hillio",
    "gn:country_code":"PK",
    "gn:dem":42,
    "gn:feature_class":"P",
    "gn:feature_code":"PPL",
    "gn:name":"Mehrab Hillio",
    "gn:population":0,
    "gn:timezone":"Asia/Karachi",
    "iso:country":"PK",
    "name:und_x_variant":[
        "Mehr\u0101b Hilio"
    ],
    "wof:name":"Mehrab Hillio",
    "wof:placetype":"locality"
},
  "geometry": {"coordinates":[68.01993,26.70215],"type":"Point"}
}