{
  "type": "Feature",
  "properties": {
    "gn:admin1_code":"3.0",
    "gn:asciiname":"Zota Khan Banda",
    "gn:country_code":"PK",
    "gn:dem":3314,
    "gn:feature_class":"P",
    "gn:feature_code":"PPL",
    "gn:name":"Zota Khan Banda",
    "gn:population":0,
    "gn:timezone":"Asia/Karachi",
    "iso:country":"PK",
    "wof:name":"Zota Khan Banda",
    "wof:placetype":"locality"
},
  "geometry": {"coordinates":[71.88919,35.3818],"type":"Point"}
}