{
  "type": "Feature",
  "properties": {
    "gn:admin1_code":"4",
    "gn:asciiname":"Basti Rahim Bakhsh",
    "gn:country_code":"PK",
    "gn:dem":81,
    "gn:feature_class":"P",
    "gn:feature_code":"PPL",
    "gn:name":"Basti Rahim Bakhsh",
    "gn:population":0,
    "gn:timezone":"Asia/Karachi",
    "iso:country":"PK",
    "wof:name":"Basti Rahim Bakhsh",
    "wof:placetype":"locality"
},
  "geometry": {"coordinates":[69.89003000000001,28.47735],"type":"Point"}
}