{
  "type": "Feature",
  "properties": {
    "gn:admin1_code":"5.0",
    "gn:asciiname":"Goth Rahim Bukhsh Rind",
    "gn:country_code":"PK",
    "gn:dem":13,
    "gn:feature_class":"P",
    "gn:feature_code":"PPL",
    "gn:name":"Goth Rahim Bukhsh Rind",
    "gn:population":0,
    "gn:timezone":"Asia/Karachi",
    "iso:country":"PK",
    "name:und_x_variant":[
        "Goth Rah\u012bm Bakhsh Rind"
    ],
    "wof:name":"Goth Rahim Bukhsh Rind",
    "wof:placetype":"locality"
},
  "geometry": {"coordinates":[68.34435999999999,24.8594],"type":"Point"}
}