{
  "type": "Feature",
  "properties": {
    "gn:admin1_code":"5",
    "gn:asciiname":"Goth Abdul Rahman",
    "gn:country_code":"PK",
    "gn:dem":9,
    "gn:feature_class":"P",
    "gn:feature_code":"PPL",
    "gn:name":"Goth Abdul Rahman",
    "gn:population":0,
    "gn:timezone":"Asia/Karachi",
    "iso:country":"PK",
    "name:und_x_variant":[
        "Abdur Rahm\u0101n Number One"
    ],
    "wof:name":"Goth Abdul Rahman",
    "wof:placetype":"locality"
},
  "geometry": {"coordinates":[69.56073000000001,25.10232],"type":"Point"}
}