{
  "type": "Feature",
  "properties": {
    "gn:admin1_code":"2.0",
    "gn:asciiname":"Shin Wam",
    "gn:country_code":"PK",
    "gn:dem":2135,
    "gn:feature_class":"P",
    "gn:feature_code":"PPL",
    "gn:name":"Shin Wam",
    "gn:population":0,
    "gn:timezone":"Asia/Karachi",
    "iso:country":"PK",
    "name:eng_x_preferred":[
        "Shin Wam"
    ],
    "name:und_x_variant":[
        "H\u0101ji Sard\u0101r"
    ],
    "wof:name":"Shin Wam",
    "wof:placetype":"locality"
},
  "geometry": {"coordinates":[67.16724000000001,30.9054],"type":"Point"}
}