{
  "type": "Feature",
  "properties": {
    "gn:admin1_code":"2",
    "gn:asciiname":"Ahad Ali",
    "gn:country_code":"PK",
    "gn:dem":1775,
    "gn:feature_class":"P",
    "gn:feature_code":"PPL",
    "gn:name":"Ahad Ali",
    "gn:population":0,
    "gn:timezone":"Asia/Karachi",
    "iso:country":"PK",
    "wof:name":"Ahad Ali",
    "wof:placetype":"locality"
},
  "geometry": {"coordinates":[67.00424,29.83334],"type":"Point"}
}