{
  "type": "Feature",
  "properties": {
    "gn:admin1_code":"03",
    "gn:asciiname":"Thathi",
    "gn:country_code":"PK",
    "gn:dem":1341,
    "gn:feature_class":"P",
    "gn:feature_code":"PPL",
    "gn:name":"Thathi",
    "gn:population":0,
    "gn:timezone":"Asia/Karachi",
    "iso:country":"PK",
    "name:fas_x_preferred":[
        "\u062a\u0647\u062a\u06cc"
    ],
    "name:pnb_x_preferred":[
        "\u0679\u06be\u0679\u06be\u06cc"
    ],
    "name:urd_x_preferred":[
        "\u0679\u06be\u0679\u06cc"
    ],
    "wof:name":"Thathi",
    "wof:placetype":"locality"
},
  "geometry": {"coordinates":[73.12236999999998,34.20967],"type":"Point"}
}