{
  "type": "Feature",
  "properties": {
    "gn:admin1_code":"5",
    "gn:asciiname":"Goth Wadal Shah",
    "gn:country_code":"PK",
    "gn:dem":28,
    "gn:feature_class":"P",
    "gn:feature_code":"PPL",
    "gn:name":"Goth Wadal Shah",
    "gn:population":0,
    "gn:timezone":"Asia/Karachi",
    "iso:country":"PK",
    "name:eng_x_preferred":[
        "Bachal Unar"
    ],
    "wof:name":"Goth Wadal Shah",
    "wof:placetype":"locality"
},
  "geometry": {"coordinates":[68.44653000000001,25.96181],"type":"Point"}
}