{
  "type": "Feature",
  "properties": {
    "gn:admin1_code":"4.0",
    "gn:asciiname":"Pakki Pul",
    "gn:country_code":"PK",
    "gn:dem":110,
    "gn:feature_class":"P",
    "gn:feature_code":"PPL",
    "gn:name":"Pakki Pul",
    "gn:population":0,
    "gn:timezone":"Asia/Karachi",
    "iso:country":"PK",
    "name:und_x_variant":[
        "Shorkot"
    ],
    "wof:name":"Pakki Pul",
    "wof:placetype":"locality"
},
  "geometry": {"coordinates":[71.25834,29.67376],"type":"Point"}
}