{
  "type": "Feature",
  "properties": {
    "gn:admin1_code":"4",
    "gn:asciiname":"Jhangiwali",
    "gn:country_code":"PK",
    "gn:dem":121,
    "gn:feature_class":"P",
    "gn:feature_code":"PPL",
    "gn:name":"Jhangiwali",
    "gn:population":0,
    "gn:timezone":"Asia/Karachi",
    "iso:country":"PK",
    "name:eng_x_preferred":[
        "Jind W\u0101dew\u0101li"
    ],
    "wof:name":"Jhangiwali",
    "wof:placetype":"locality"
},
  "geometry": {"coordinates":[71.76363000000001,29.42592],"type":"Point"}
}