{
  "type": "Feature",
  "properties": {
    "gn:admin1_code":"2.0",
    "gn:asciiname":"Lal Muhammad",
    "gn:country_code":"PK",
    "gn:dem":1454,
    "gn:feature_class":"P",
    "gn:feature_code":"PPL",
    "gn:name":"Lal Muhammad",
    "gn:population":0,
    "gn:timezone":"Asia/Karachi",
    "iso:country":"PK",
    "wof:name":"Lal Muhammad",
    "wof:placetype":"locality"
},
  "geometry": {"coordinates":[66.42639,28.01565],"type":"Point"}
}