{
  "type": "Feature",
  "properties": {
    "gn:admin1_code":"3.0",
    "gn:asciiname":"Muhabhati Kalle",
    "gn:country_code":"PK",
    "gn:dem":400,
    "gn:feature_class":"P",
    "gn:feature_code":"PPL",
    "gn:name":"Muhabhati Kalle",
    "gn:population":0,
    "gn:timezone":"Asia/Karachi",
    "iso:country":"PK",
    "wof:name":"Muhabhati Kalle",
    "wof:placetype":"locality"
},
  "geometry": {"coordinates":[70.92841999999997,33.00622],"type":"Point"}
}