{
  "type": "Feature",
  "properties": {
    "gn:admin1_code":"04",
    "gn:asciiname":"Chak Ninety-one -Twelve Left",
    "gn:country_code":"PK",
    "gn:dem":150,
    "gn:feature_class":"P",
    "gn:feature_code":"PPL",
    "gn:name":"Chak Ninety-one -Twelve Left",
    "gn:population":0,
    "gn:timezone":"Asia/Karachi",
    "iso:country":"PK",
    "name:und_x_variant":[
        "Saj\u0101walnagar",
        "Sajaw\u0101lnagar"
    ],
    "wof:name":"Chak Ninety-one -Twelve Left",
    "wof:placetype":"locality"
},
  "geometry": {"coordinates":[72.52275999999998,30.32014],"type":"Point"}
}