{
  "type": "Feature",
  "properties": {
    "gn:admin1_code":"5.0",
    "gn:asciiname":"Alihari",
    "gn:country_code":"PK",
    "gn:dem":32,
    "gn:feature_class":"P",
    "gn:feature_code":"PPL",
    "gn:name":"Alihari",
    "gn:population":0,
    "gn:timezone":"Asia/Karachi",
    "iso:country":"PK",
    "name:und_x_variant":[
        "Al\u012bh\u0101ri"
    ],
    "wof:name":"Alihari",
    "wof:placetype":"locality"
},
  "geometry": {"coordinates":[70.47318,24.50949],"type":"Point"}
}