{
  "type": "Feature",
  "properties": {
    "gn:admin1_code":"03",
    "gn:asciiname":"Kirri Shah Alam",
    "gn:country_code":"PK",
    "gn:dem":263,
    "gn:feature_class":"P",
    "gn:feature_code":"PPL",
    "gn:name":"Kirri Shah Alam",
    "gn:population":0,
    "gn:timezone":"Asia/Karachi",
    "iso:country":"PK",
    "name:und_x_variant":[
        "Sh\u0101h \u0100lam"
    ],
    "wof:name":"Kirri Shah Alam",
    "wof:placetype":"locality"
},
  "geometry": {"coordinates":[70.42328000000001,32.25464],"type":"Point"}
}