{
  "type": "Feature",
  "properties": {
    "gn:admin1_code":"2.0",
    "gn:asciiname":"Kili Malik Bahar",
    "gn:country_code":"PK",
    "gn:dem":1933,
    "gn:feature_class":"P",
    "gn:feature_code":"PPL",
    "gn:name":"Kili Malik Bahar",
    "gn:population":0,
    "gn:timezone":"Asia/Karachi",
    "iso:country":"PK",
    "wof:name":"Kili Malik Bahar",
    "wof:placetype":"locality"
},
  "geometry": {"coordinates":[67.13146999999999,30.03338],"type":"Point"}
}