{
  "type": "Feature",
  "properties": {
    "gn:admin1_code":"4.0",
    "gn:asciiname":"Basti Chatul",
    "gn:country_code":"PK",
    "gn:dem":134,
    "gn:feature_class":"P",
    "gn:feature_code":"PPL",
    "gn:name":"Basti Chatul",
    "gn:population":0,
    "gn:timezone":"Asia/Karachi",
    "iso:country":"PK",
    "name:und_x_variant":[
        "Chat\u016bl"
    ],
    "wof:name":"Basti Chatul",
    "wof:placetype":"locality"
},
  "geometry": {"coordinates":[70.23905999999999,29.50851],"type":"Point"}
}