{
  "type": "Feature",
  "properties": {
    "gn:admin1_code":"4",
    "gn:asciiname":"Naurangwala",
    "gn:country_code":"PK",
    "gn:dem":121,
    "gn:feature_class":"P",
    "gn:feature_code":"PPL",
    "gn:name":"Naurangwala",
    "gn:population":0,
    "gn:timezone":"Asia/Karachi",
    "iso:country":"PK",
    "name:eng_x_preferred":[
        "Naurangwala"
    ],
    "name:und_x_variant":[
        "Naurang\u0101b\u0101d"
    ],
    "wof:name":"Naurangwala",
    "wof:placetype":"locality"
},
  "geometry": {"coordinates":[70.73155,30.10468],"type":"Point"}
}