{
  "type": "Feature",
  "properties": {
    "gn:admin1_code":"2.0",
    "gn:asciiname":"Nagar Bazar",
    "gn:country_code":"PK",
    "gn:dem":41,
    "gn:feature_class":"P",
    "gn:feature_code":"PPL",
    "gn:name":"Nagar Bazar",
    "gn:population":0,
    "gn:timezone":"Asia/Karachi",
    "iso:country":"PK",
    "name:und_x_variant":[
        "Hor",
        "Nagar Bazar"
    ],
    "wof:name":"Nagar Bazar",
    "wof:placetype":"locality"
},
  "geometry": {"coordinates":[62.24343,25.6119],"type":"Point"}
}