{
  "type": "Feature",
  "properties": {
    "gn:admin1_code":"5.0",
    "gn:asciiname":"Dewan Ram Chand",
    "gn:country_code":"PK",
    "gn:dem":31,
    "gn:feature_class":"P",
    "gn:feature_code":"PPL",
    "gn:name":"Dewan Ram Chand",
    "gn:population":0,
    "gn:timezone":"Asia/Karachi",
    "iso:country":"PK",
    "wof:name":"Dewan Ram Chand",
    "wof:placetype":"locality"
},
  "geometry": {"coordinates":[68.41755999999999,26.29214],"type":"Point"}
}