{
  "type": "Feature",
  "properties": {
    "gn:admin1_code":"4.0",
    "gn:asciiname":"Lambwala",
    "gn:country_code":"PK",
    "gn:dem":413,
    "gn:feature_class":"P",
    "gn:feature_code":"PPL",
    "gn:name":"Lambwala",
    "gn:population":0,
    "gn:timezone":"Asia/Karachi",
    "iso:country":"PK",
    "name:und_x_variant":[
        "Lamb\u012bw\u0101la Dhok",
        "Dhok Namw\u0101la",
        "Lambwala"
    ],
    "wof:name":"Lambwala",
    "wof:placetype":"locality"
},
  "geometry": {"coordinates":[72.378,33.09426],"type":"Point"}
}