{
  "type": "Feature",
  "properties": {
    "gn:admin1_code":"04",
    "gn:asciiname":"Sher Rai Sadulla",
    "gn:country_code":"PK",
    "gn:dem":460,
    "gn:feature_class":"P",
    "gn:feature_code":"PPL",
    "gn:name":"Sher Rai Sadulla",
    "gn:population":0,
    "gn:timezone":"Asia/Karachi",
    "iso:country":"PK",
    "name:und_x_variant":[
        "Shahr Rai Saadullah",
        "Shahr R\u0101i S\u0101dull\u0101h",
        "Sher Rai Sadulla"
    ],
    "wof:name":"Sher Rai Sadulla",
    "wof:placetype":"locality"
},
  "geometry": {"coordinates":[72.58955,33.48591],"type":"Point"}
}