{
  "type": "Feature",
  "properties": {
    "gn:admin1_code":"4.0",
    "gn:asciiname":"Dhok Atar Khan",
    "gn:country_code":"PK",
    "gn:dem":379,
    "gn:feature_class":"P",
    "gn:feature_code":"PPL",
    "gn:name":"Dhok Atar Khan",
    "gn:population":0,
    "gn:timezone":"Asia/Karachi",
    "iso:country":"PK",
    "name:und_x_variant":[
        "Dhok Fateh Kh\u0101n Hams\u0101l"
    ],
    "wof:name":"Dhok Atar Khan",
    "wof:placetype":"locality"
},
  "geometry": {"coordinates":[71.87567,32.69927],"type":"Point"}
}