{
  "type": "Feature",
  "properties": {
    "gn:admin1_code":"3.0",
    "gn:asciiname":"Ariyan Kalle",
    "gn:country_code":"PK",
    "gn:dem":340,
    "gn:feature_class":"P",
    "gn:feature_code":"PPL",
    "gn:name":"Ariyan Kalle",
    "gn:population":0,
    "gn:timezone":"Asia/Karachi",
    "iso:country":"PK",
    "wof:name":"Ariyan Kalle",
    "wof:placetype":"locality"
},
  "geometry": {"coordinates":[72.20939,34.10013],"type":"Point"}
}