{
  "type": "Feature",
  "properties": {
    "gn:admin1_code":"6.0",
    "gn:asciiname":"Dohgaban",
    "gn:country_code":"PK",
    "gn:dem":2241,
    "gn:feature_class":"P",
    "gn:feature_code":"PPL",
    "gn:name":"Dohgaban",
    "gn:population":0,
    "gn:timezone":"Asia/Karachi",
    "iso:country":"PK",
    "wof:name":"Dohgaban",
    "wof:placetype":"locality"
},
  "geometry": {"coordinates":[73.98911,34.75366],"type":"Point"}
}