{
  "type": "Feature",
  "properties": {
    "gn:admin1_code":"5.0",
    "gn:asciiname":"Goth Photo Khan Sumro",
    "gn:country_code":"PK",
    "gn:dem":48,
    "gn:feature_class":"P",
    "gn:feature_code":"PPL",
    "gn:name":"Goth Photo Khan Sumro",
    "gn:population":0,
    "gn:timezone":"Asia/Karachi",
    "iso:country":"PK",
    "name:und_x_variant":[
        "Goth Photo Kh\u0101n S\u016bmra"
    ],
    "wof:name":"Goth Photo Khan Sumro",
    "wof:placetype":"locality"
},
  "geometry": {"coordinates":[68.28231,26.94625],"type":"Point"}
}