{
  "type": "Feature",
  "properties": {
    "gn:admin1_code":"1.0",
    "gn:asciiname":"Janal Khel",
    "gn:country_code":"PK",
    "gn:dem":1005,
    "gn:feature_class":"P",
    "gn:feature_code":"PPL",
    "gn:name":"Janal Khel",
    "gn:population":0,
    "gn:timezone":"Asia/Karachi",
    "iso:country":"PK",
    "name:und_x_variant":[
        "J\u0101nal Khel"
    ],
    "wof:name":"Janal Khel",
    "wof:placetype":"locality"
},
  "geometry": {"coordinates":[71.64768000000002,33.68202],"type":"Point"}
}