{
  "type": "Feature",
  "properties": {
    "gn:admin1_code":"2",
    "gn:asciiname":"Salas Tangi",
    "gn:country_code":"PK",
    "gn:dem":1180,
    "gn:feature_class":"P",
    "gn:feature_code":"PPL",
    "gn:name":"Salas Tangi",
    "gn:population":0,
    "gn:timezone":"Asia/Karachi",
    "iso:country":"PK",
    "wof:name":"Salas Tangi",
    "wof:placetype":"locality"
},
  "geometry": {"coordinates":[67.72846,30.17406],"type":"Point"}
}