{
  "type": "Feature",
  "properties": {
    "gn:admin1_code":"3.0",
    "gn:asciiname":"Nillan Bhotu",
    "gn:country_code":"PK",
    "gn:dem":1023,
    "gn:feature_class":"P",
    "gn:feature_code":"PPL",
    "gn:name":"Nillan Bhotu",
    "gn:population":0,
    "gn:timezone":"Asia/Karachi",
    "iso:country":"PK",
    "name:eng_x_preferred":[
        "Nil\u0101n Bhotu"
    ],
    "name:urd_x_preferred":[
        "\u0646\u06cc\u0644\u0627\u06ba \u0628\u06be\u0648\u062a\u0648"
    ],
    "wof:name":"Nillan Bhotu",
    "wof:placetype":"locality"
},
  "geometry": {"coordinates":[73.18819999999999,33.83119],"type":"Point"}
}