{
  "type": "Feature",
  "properties": {
    "gn:admin1_code":"04",
    "gn:asciiname":"Machranwala",
    "gn:country_code":"PK",
    "gn:dem":218,
    "gn:feature_class":"P",
    "gn:feature_code":"PPL",
    "gn:name":"Machranwala",
    "gn:population":0,
    "gn:timezone":"Asia/Karachi",
    "iso:country":"PK",
    "name:und_x_variant":[
        "Machr\u0101nw\u0101li"
    ],
    "wof:name":"Machranwala",
    "wof:placetype":"locality"
},
  "geometry": {"coordinates":[73.95142,32.13093],"type":"Point"}
}