{
  "type": "Feature",
  "properties": {
    "gn:admin1_code":"4",
    "gn:asciiname":"Miro Bhadiar",
    "gn:country_code":"PK",
    "gn:dem":233,
    "gn:feature_class":"P",
    "gn:feature_code":"PPL",
    "gn:name":"Miro Bhadiar",
    "gn:population":0,
    "gn:timezone":"Asia/Karachi",
    "iso:country":"PK",
    "name:und_x_variant":[
        "Bhadi\u0101r"
    ],
    "wof:name":"Miro Bhadiar",
    "wof:placetype":"locality"
},
  "geometry": {"coordinates":[74.63500000000001,32.13249],"type":"Point"}
}