{
  "type": "Feature",
  "properties": {
    "gn:admin1_code":"2",
    "gn:asciiname":"Salehzai",
    "gn:country_code":"PK",
    "gn:dem":2073,
    "gn:feature_class":"P",
    "gn:feature_code":"PPL",
    "gn:name":"Salehzai",
    "gn:population":0,
    "gn:timezone":"Asia/Karachi",
    "iso:country":"PK",
    "wof:name":"Salehzai",
    "wof:placetype":"locality"
},
  "geometry": {"coordinates":[66.75,31.04528],"type":"Point"}
}