{
  "type": "Feature",
  "properties": {
    "gn:admin1_code":"01",
    "gn:asciiname":"Jor",
    "gn:country_code":"PK",
    "gn:dem":931,
    "gn:feature_class":"P",
    "gn:feature_code":"PPL",
    "gn:name":"Jor",
    "gn:population":0,
    "gn:timezone":"Asia/Karachi",
    "iso:country":"PK",
    "name:ceb_x_preferred":[
        "Jor"
    ],
    "name:eng_x_preferred":[
        "Jowar"
    ],
    "name:swe_x_preferred":[
        "Jor"
    ],
    "name:und_x_variant":[
        "Johar"
    ],
    "wof:name":"Jor",
    "wof:placetype":"locality"
},
  "geometry": {"coordinates":[71.65846999999999,34.56319000000001],"type":"Point"}
}