{
  "type": "Feature",
  "properties": {
    "gn:admin1_code":"6",
    "gn:asciiname":"Bearan",
    "gn:country_code":"PK",
    "gn:dem":2087,
    "gn:feature_class":"P",
    "gn:feature_code":"PPL",
    "gn:name":"Bearan",
    "gn:population":0,
    "gn:timezone":"Asia/Karachi",
    "iso:country":"PK",
    "name:und_x_variant":[
        "Beran",
        "Bearan"
    ],
    "wof:name":"Bearan",
    "wof:placetype":"locality"
},
  "geometry": {"coordinates":[74.08889000000001,34.02083],"type":"Point"}
}