{
  "type": "Feature",
  "properties": {
    "gn:admin1_code":"3",
    "gn:asciiname":"Khadarzo Patai",
    "gn:country_code":"PK",
    "gn:dem":1479,
    "gn:feature_class":"P",
    "gn:feature_code":"PPL",
    "gn:name":"Khadarzo Patai",
    "gn:population":0,
    "gn:timezone":"Asia/Karachi",
    "iso:country":"PK",
    "wof:name":"Khadarzo Patai",
    "wof:placetype":"locality"
},
  "geometry": {"coordinates":[72.52903000000001,34.84337],"type":"Point"}
}