{
  "type": "Feature",
  "properties": {
    "gn:admin1_code":"4.0",
    "gn:asciiname":"Bangial",
    "gn:country_code":"PK",
    "gn:dem":292,
    "gn:feature_class":"P",
    "gn:feature_code":"PPL",
    "gn:name":"Bangial",
    "gn:population":0,
    "gn:timezone":"Asia/Karachi",
    "iso:country":"PK",
    "wof:name":"Bangial",
    "wof:placetype":"locality"
},
  "geometry": {"coordinates":[73.4669,32.91157],"type":"Point"}
}