{
  "type": "Feature",
  "properties": {
    "gn:admin1_code":"4.0",
    "gn:asciiname":"Shergarh",
    "gn:country_code":"PK",
    "gn:dem":83,
    "gn:feature_class":"P",
    "gn:feature_code":"PPL",
    "gn:name":"Shergarh",
    "gn:population":0,
    "gn:timezone":"Asia/Karachi",
    "iso:country":"PK",
    "name:ceb_x_preferred":[
        "Shergarh"
    ],
    "name:pol_x_preferred":[
        "Shergarh"
    ],
    "name:swe_x_preferred":[
        "Shergarh"
    ],
    "wof:name":"Shergarh",
    "wof:placetype":"locality"
},
  "geometry": {"coordinates":[70.5522,28.47893],"type":"Point"}
}