{
  "type": "Feature",
  "properties": {
    "gn:admin1_code":"3.0",
    "gn:asciiname":"Khalfanan Dur",
    "gn:country_code":"PK",
    "gn:dem":2435,
    "gn:feature_class":"P",
    "gn:feature_code":"PPL",
    "gn:name":"Khalfanan Dur",
    "gn:population":0,
    "gn:timezone":"Asia/Karachi",
    "iso:country":"PK",
    "wof:name":"Khalfanan Dur",
    "wof:placetype":"locality"
},
  "geometry": {"coordinates":[72.43428,36.48315],"type":"Point"}
}