{
  "type": "Feature",
  "properties": {
    "gn:admin1_code":"4.0",
    "gn:asciiname":"Shahwala",
    "gn:country_code":"PK",
    "gn:dem":137,
    "gn:feature_class":"P",
    "gn:feature_code":"PPL",
    "gn:name":"Shahwala",
    "gn:population":0,
    "gn:timezone":"Asia/Karachi",
    "iso:country":"PK",
    "wof:name":"Shahwala",
    "wof:placetype":"locality"
},
  "geometry": {"coordinates":[72.05269,30.46624000000001],"type":"Point"}
}