{
  "type": "Feature",
  "properties": {
    "gn:admin1_code":"5",
    "gn:asciiname":"Goth Sajan Sangi",
    "gn:country_code":"PK",
    "gn:dem":57,
    "gn:feature_class":"P",
    "gn:feature_code":"PPL",
    "gn:name":"Goth Sajan Sangi",
    "gn:population":0,
    "gn:timezone":"Asia/Karachi",
    "iso:country":"PK",
    "name:und_x_variant":[
        "Sajan S\u0101ngi"
    ],
    "wof:name":"Goth Sajan Sangi",
    "wof:placetype":"locality"
},
  "geometry": {"coordinates":[68.21911999999999,27.61815],"type":"Point"}
}