{
  "type": "Feature",
  "properties": {
    "gn:admin1_code":"4.0",
    "gn:asciiname":"Bhuchh",
    "gn:country_code":"PK",
    "gn:dem":282,
    "gn:feature_class":"P",
    "gn:feature_code":"PPL",
    "gn:name":"Bhuchh",
    "gn:population":0,
    "gn:timezone":"Asia/Karachi",
    "iso:country":"PK",
    "name:und_x_variant":[
        "Buchh",
        "Bh\u016bchh",
        "Bhuchh"
    ],
    "wof:name":"Bhuchh",
    "wof:placetype":"locality"
},
  "geometry": {"coordinates":[74.1776,32.77433],"type":"Point"}
}