{
  "type": "Feature",
  "properties": {
    "gn:admin1_code":"3",
    "gn:asciiname":"Banjot",
    "gn:country_code":"PK",
    "gn:dem":1285,
    "gn:feature_class":"P",
    "gn:feature_code":"PPL",
    "gn:name":"Banjot",
    "gn:population":0,
    "gn:timezone":"Asia/Karachi",
    "iso:country":"PK",
    "wof:name":"Banjot",
    "wof:placetype":"locality"
},
  "geometry": {"coordinates":[72.47207,34.77064],"type":"Point"}
}