{
  "type": "Feature",
  "properties": {
    "gn:admin1_code":"4.0",
    "gn:asciiname":"Thukarke",
    "gn:country_code":"PK",
    "gn:dem":175,
    "gn:feature_class":"P",
    "gn:feature_code":"PPL",
    "gn:name":"Thukarke",
    "gn:population":0,
    "gn:timezone":"Asia/Karachi",
    "iso:country":"PK",
    "name:und_x_variant":[
        "Seven D"
    ],
    "wof:name":"Thukarke",
    "wof:placetype":"locality"
},
  "geometry": {"coordinates":[73.75411,30.62861],"type":"Point"}
}