{
  "type": "Feature",
  "properties": {
    "gn:admin1_code":"4",
    "gn:asciiname":"Shorewala",
    "gn:country_code":"PK",
    "gn:dem":136,
    "gn:feature_class":"P",
    "gn:feature_code":"PPL",
    "gn:name":"Shorew\u0101la",
    "gn:population":0,
    "gn:timezone":"Asia/Karachi",
    "iso:country":"PK",
    "wof:name":"Shorewala",
    "wof:placetype":"locality"
},
  "geometry": {"coordinates":[71.22499999999999,30.45833],"type":"Point"}
}