{
  "type": "Feature",
  "properties": {
    "gn:admin1_code":"5",
    "gn:asciiname":"Ali Khan jo Goth",
    "gn:country_code":"PK",
    "gn:dem":71,
    "gn:feature_class":"P",
    "gn:feature_code":"PPL",
    "gn:name":"Ali Khan jo Goth",
    "gn:population":0,
    "gn:timezone":"Asia/Karachi",
    "iso:country":"PK",
    "wof:name":"Ali Khan jo Goth",
    "wof:placetype":"locality"
},
  "geometry": {"coordinates":[69.24528000000001,26.58807],"type":"Point"}
}