{
  "type": "Feature",
  "properties": {
    "gn:admin1_code":"4",
    "gn:asciiname":"Sodhi Bala",
    "gn:country_code":"PK",
    "gn:dem":815,
    "gn:feature_class":"P",
    "gn:feature_code":"PPL",
    "gn:name":"Sodhi Bala",
    "gn:population":0,
    "gn:timezone":"Asia/Karachi",
    "iso:country":"PK",
    "name:urd_x_preferred":[
        "\u0633\u0648\u0688\u06be\u06cc \u0628\u0627\u0644\u0627"
    ],
    "wof:name":"Sodhi Bala",
    "wof:placetype":"locality"
},
  "geometry": {"coordinates":[72.15841,32.48875],"type":"Point"}
}