{
  "type": "Feature",
  "properties": {
    "gn:admin1_code":"4",
    "gn:asciiname":"Sodhi Bala",
    "gn:country_code":"PK",
    "gn:dem":815,
    "gn:feature_class":"P",
    "gn:feature_code":"PPL",
    "gn:name":"Sodhi Bala",
    "gn:population":0,
    "gn:timezone":"Asia/Karachi",
    "iso:country":"PK",
    "wof:name":"Sodhi Bala",
    "wof:placetype":"locality"
},
  "geometry": {"coordinates":[72.15841,32.48875],"type":"Point"}
}