{
  "type": "Feature",
  "properties": {
    "gn:admin1_code":"4.0",
    "gn:asciiname":"Dahira",
    "gn:country_code":"PK",
    "gn:dem":294,
    "gn:feature_class":"P",
    "gn:feature_code":"PPL",
    "gn:name":"Dahira",
    "gn:population":0,
    "gn:timezone":"Asia/Karachi",
    "iso:country":"PK",
    "name:und_x_variant":[
        "Dailhra",
        "Dehlra",
        "Dahira"
    ],
    "wof:name":"Dahira",
    "wof:placetype":"locality"
},
  "geometry": {"coordinates":[75.09468000000003,32.38806],"type":"Point"}
}