{
  "type": "Feature",
  "properties": {
    "gn:admin1_code":"2.0",
    "gn:asciiname":"Phuleji",
    "gn:country_code":"PK",
    "gn:dem":117,
    "gn:feature_class":"P",
    "gn:feature_code":"PPL",
    "gn:name":"Phuleji",
    "gn:population":0,
    "gn:timezone":"Asia/Karachi",
    "iso:country":"PK",
    "name:und_x_variant":[
        "Goth Phuleji"
    ],
    "wof:name":"Phuleji",
    "wof:placetype":"locality"
},
  "geometry": {"coordinates":[68.10569,29.17917000000001],"type":"Point"}
}