{
  "type": "Feature",
  "properties": {
    "gn:admin1_code":"4.0",
    "gn:asciiname":"Chak Six Hundred Fifty Thal Development Authority",
    "gn:country_code":"PK",
    "gn:dem":138,
    "gn:feature_class":"P",
    "gn:feature_code":"PPL",
    "gn:name":"Chak Six Hundred Fifty Thal Development Authority",
    "gn:population":0,
    "gn:timezone":"Asia/Karachi",
    "iso:country":"PK",
    "name:und_x_variant":[
        "Chak Six Hundred Fifty TDA",
        "Chak 650 TDA"
    ],
    "wof:name":"Chak Six Hundred Fifty Thal Development Authority",
    "wof:placetype":"locality"
},
  "geometry": {"coordinates":[71.33020999999999,30.64026],"type":"Point"}
}