{
  "type": "Feature",
  "properties": {
    "gn:admin1_code":"4.0",
    "gn:asciiname":"Chak Fourty-five Eastern Bar",
    "gn:country_code":"PK",
    "gn:dem":155,
    "gn:feature_class":"P",
    "gn:feature_code":"PPL",
    "gn:name":"Chak Fourty-five Eastern Bar",
    "gn:population":0,
    "gn:timezone":"Asia/Karachi",
    "iso:country":"PK",
    "wof:name":"Chak Fourty-five Eastern Bar",
    "wof:placetype":"locality"
},
  "geometry": {"coordinates":[73.05020999999998,30.2172],"type":"Point"}
}