{
  "type": "Feature",
  "properties": {
    "gn:admin1_code":"3.0",
    "gn:asciiname":"Shoharan Bala",
    "gn:country_code":"PK",
    "gn:dem":3171,
    "gn:feature_class":"P",
    "gn:feature_code":"PPL",
    "gn:name":"Shoharan Bala",
    "gn:population":0,
    "gn:timezone":"Asia/Karachi",
    "iso:country":"PK",
    "wof:name":"Shoharan Bala",
    "wof:placetype":"locality"
},
  "geometry": {"coordinates":[73.63268000000002,34.68183],"type":"Point"}
}