{
  "type": "Feature",
  "properties": {
    "gn:admin1_code":"5",
    "gn:asciiname":"Goth Qazi Ali Dad",
    "gn:country_code":"PK",
    "gn:dem":53,
    "gn:feature_class":"P",
    "gn:feature_code":"PPL",
    "gn:name":"Goth Qazi Ali Dad",
    "gn:population":0,
    "gn:timezone":"Asia/Karachi",
    "iso:country":"PK",
    "name:und_x_variant":[
        "Q\u0101zi All\u0101hd\u0101d"
    ],
    "wof:name":"Goth Qazi Ali Dad",
    "wof:placetype":"locality"
},
  "geometry": {"coordinates":[68.32096999999999,27.26605],"type":"Point"}
}