{
  "type": "Feature",
  "properties": {
    "gn:admin1_code":"4.0",
    "gn:asciiname":"Chak Sixty-one -Ten Right Colony",
    "gn:country_code":"PK",
    "gn:dem":139,
    "gn:feature_class":"P",
    "gn:feature_code":"PPL",
    "gn:name":"Chak Sixty-one -Ten Right Colony",
    "gn:population":0,
    "gn:timezone":"Asia/Karachi",
    "iso:country":"PK",
    "wof:name":"Chak Sixty-one -Ten Right Colony",
    "wof:placetype":"locality"
},
  "geometry": {"coordinates":[71.99901,30.14458],"type":"Point"}
}