{
  "type": "Feature",
  "properties": {
    "gn:admin1_code":"5.0",
    "gn:asciiname":"Samanbewari Khui",
    "gn:country_code":"PK",
    "gn:dem":45,
    "gn:feature_class":"P",
    "gn:feature_code":"PPL",
    "gn:name":"Samanbewari Khui",
    "gn:population":0,
    "gn:timezone":"Asia/Karachi",
    "iso:country":"PK",
    "name:und_x_variant":[
        "Sam\u0101nbew\u0101ri Kh\u016bi"
    ],
    "wof:name":"Samanbewari Khui",
    "wof:placetype":"locality"
},
  "geometry": {"coordinates":[69.86112,26.01856],"type":"Point"}
}