{
  "type": "Feature",
  "properties": {
    "gn:admin1_code":"1.0",
    "gn:asciiname":"Singar",
    "gn:country_code":"PK",
    "gn:dem":745,
    "gn:feature_class":"P",
    "gn:feature_code":"PPL",
    "gn:name":"Singar",
    "gn:population":0,
    "gn:timezone":"Asia/Karachi",
    "iso:country":"PK",
    "wof:name":"Singar",
    "wof:placetype":"locality"
},
  "geometry": {"coordinates":[70.17440000000001,32.9851],"type":"Point"}
}