{
  "type": "Feature",
  "properties": {
    "gn:admin1_code":"5",
    "gn:asciiname":"Goth Khamiso Hulio",
    "gn:country_code":"PK",
    "gn:dem":51,
    "gn:feature_class":"P",
    "gn:feature_code":"PPL",
    "gn:name":"Goth Khamiso Hulio",
    "gn:population":0,
    "gn:timezone":"Asia/Karachi",
    "iso:country":"PK",
    "name:und_x_variant":[
        "Khamiso Hulia"
    ],
    "wof:name":"Goth Khamiso Hulio",
    "wof:placetype":"locality"
},
  "geometry": {"coordinates":[68.16014,27.37461],"type":"Point"}
}