{
  "type": "Feature",
  "properties": {
    "gn:admin1_code":"04",
    "gn:asciiname":"Manurian",
    "gn:country_code":"PK",
    "gn:dem":189,
    "gn:feature_class":"P",
    "gn:feature_code":"PPL",
    "gn:name":"Manurian",
    "gn:population":0,
    "gn:timezone":"Asia/Karachi",
    "iso:country":"PK",
    "name:und_x_variant":[
        "Man\u016bri"
    ],
    "wof:name":"Manurian",
    "wof:placetype":"locality"
},
  "geometry": {"coordinates":[74.15529000000002,30.75036],"type":"Point"}
}