{
  "type": "Feature",
  "properties": {
    "gn:admin1_code":"2",
    "gn:asciiname":"Gardi",
    "gn:country_code":"PK",
    "gn:dem":2638,
    "gn:feature_class":"P",
    "gn:feature_code":"PPL",
    "gn:name":"Gardi",
    "gn:population":0,
    "gn:timezone":"Asia/Karachi",
    "iso:country":"PK",
    "name:eng_x_preferred":[
        "Girdai"
    ],
    "wof:name":"Gardi",
    "wof:placetype":"locality"
},
  "geometry": {"coordinates":[67.49961999999999,30.85318],"type":"Point"}
}