{
  "type": "Feature",
  "properties": {
    "gn:admin1_code":"1.0",
    "gn:asciiname":"Shahi Tangai",
    "gn:country_code":"PK",
    "gn:dem":1301,
    "gn:feature_class":"P",
    "gn:feature_code":"PPL",
    "gn:name":"Shahi Tangai",
    "gn:population":0,
    "gn:timezone":"Asia/Karachi",
    "iso:country":"PK",
    "name:und_x_variant":[
        "Shahi Tangi"
    ],
    "wof:name":"Shahi Tangai",
    "wof:placetype":"locality"
},
  "geometry": {"coordinates":[71.44184,34.85659],"type":"Point"}
}