{
  "type": "Feature",
  "properties": {
    "gn:admin1_code":"4.0",
    "gn:asciiname":"Khanjar Dhok",
    "gn:country_code":"PK",
    "gn:dem":406,
    "gn:feature_class":"P",
    "gn:feature_code":"PPL",
    "gn:name":"Khanjar Dhok",
    "gn:population":0,
    "gn:timezone":"Asia/Karachi",
    "iso:country":"PK",
    "wof:name":"Khanjar Dhok",
    "wof:placetype":"locality"
},
  "geometry": {"coordinates":[71.83889000000001,33.18444],"type":"Point"}
}