{
  "type": "Feature",
  "properties": {
    "gn:admin1_code":"4.0",
    "gn:asciiname":"Mohra Yaru",
    "gn:country_code":"PK",
    "gn:dem":503,
    "gn:feature_class":"P",
    "gn:feature_code":"PPL",
    "gn:name":"Mohra Yaru",
    "gn:population":0,
    "gn:timezone":"Asia/Karachi",
    "iso:country":"PK",
    "wof:name":"Mohra Yaru",
    "wof:placetype":"locality"
},
  "geometry": {"coordinates":[73.13531999999999,33.36277],"type":"Point"}
}