{
  "type": "Feature",
  "properties": {
    "gn:admin1_code":"3",
    "gn:asciiname":"Parmand",
    "gn:country_code":"PK",
    "gn:dem":687,
    "gn:feature_class":"P",
    "gn:feature_code":"PPL",
    "gn:name":"Parmand",
    "gn:population":0,
    "gn:timezone":"Asia/Karachi",
    "iso:country":"PK",
    "wof:name":"Parmand",
    "wof:placetype":"locality"
},
  "geometry": {"coordinates":[72.54933,34.45283],"type":"Point"}
}