{
  "type": "Feature",
  "properties": {
    "gn:admin1_code":"1",
    "gn:asciiname":"Kam Narakai",
    "gn:country_code":"PK",
    "gn:dem":1817,
    "gn:feature_class":"P",
    "gn:feature_code":"PPL",
    "gn:name":"Kam Narakai",
    "gn:population":0,
    "gn:timezone":"Asia/Karachi",
    "iso:country":"PK",
    "wof:name":"Kam Narakai",
    "wof:placetype":"locality"
},
  "geometry": {"coordinates":[69.81474,32.63126],"type":"Point"}
}