{
  "type": "Feature",
  "properties": {
    "gn:admin1_code":"3.0",
    "gn:asciiname":"Ispsht",
    "gn:country_code":"PK",
    "gn:dem":3763,
    "gn:feature_class":"P",
    "gn:feature_code":"PPL",
    "gn:name":"Ispsht",
    "gn:population":0,
    "gn:timezone":"Asia/Karachi",
    "iso:country":"PK",
    "name:und_x_variant":[
        "Shpasht"
    ],
    "wof:name":"Ispsht",
    "wof:placetype":"locality"
},
  "geometry": {"coordinates":[71.54464,36.12779000000001],"type":"Point"}
}