{
  "type": "Feature",
  "properties": {
    "gn:admin1_code":"4.0",
    "gn:asciiname":"Sarai",
    "gn:country_code":"PK",
    "gn:dem":220,
    "gn:feature_class":"P",
    "gn:feature_code":"PPL",
    "gn:name":"Sarai",
    "gn:population":0,
    "gn:timezone":"Asia/Karachi",
    "iso:country":"PK",
    "name:cat_x_preferred":[
        "Sarai"
    ],
    "name:ceb_x_preferred":[
        "Sarai"
    ],
    "name:deu_x_preferred":[
        "Sarai"
    ],
    "name:fra_x_preferred":[
        "Sarai"
    ],
    "name:ind_x_preferred":[
        "Sarai"
    ],
    "name:jpn_x_preferred":[
        "\u30b5\u30e9\u30a4"
    ],
    "name:nld_x_preferred":[
        "Sarai"
    ],
    "name:swe_x_preferred":[
        "Sarai"
    ],
    "name:tgl_x_preferred":[
        "Sarai"
    ],
    "name:und_x_variant":[
        "Sar\u0101n"
    ],
    "wof:name":"Sarai",
    "wof:placetype":"locality"
},
  "geometry": {"coordinates":[74.49935000000001,31.85706],"type":"Point"}
}