{
  "type": "Feature",
  "properties": {
    "gn:admin1_code":"5.0",
    "gn:asciiname":"Goth Jan Muhammad Khushk",
    "gn:country_code":"PK",
    "gn:dem":44,
    "gn:feature_class":"P",
    "gn:feature_code":"PPL",
    "gn:name":"Goth Jan Muhammad Khushk",
    "gn:population":0,
    "gn:timezone":"Asia/Karachi",
    "iso:country":"PK",
    "wof:name":"Goth Jan Muhammad Khushk",
    "wof:placetype":"locality"
},
  "geometry": {"coordinates":[67.80897,26.78211],"type":"Point"}
}