{
  "type": "Feature",
  "properties": {
    "gn:admin1_code":"4.0",
    "gn:asciiname":"Kala Dhora",
    "gn:country_code":"PK",
    "gn:dem":86,
    "gn:feature_class":"P",
    "gn:feature_code":"PPL",
    "gn:name":"Kala Dhora",
    "gn:population":0,
    "gn:timezone":"Asia/Karachi",
    "iso:country":"PK",
    "name:und_x_variant":[
        "Chak K\u0101la Dhora"
    ],
    "wof:name":"Kala Dhora",
    "wof:placetype":"locality"
},
  "geometry": {"coordinates":[70.33279,28.55382],"type":"Point"}
}