{
  "type": "Feature",
  "properties": {
    "gn:admin1_code":"03",
    "gn:asciiname":"Gandere",
    "gn:country_code":"PK",
    "gn:dem":952,
    "gn:feature_class":"P",
    "gn:feature_code":"PPL",
    "gn:name":"Gandere",
    "gn:population":0,
    "gn:timezone":"Asia/Karachi",
    "iso:country":"PK",
    "name:eng_x_preferred":[
        "Ganderai"
    ],
    "wof:name":"Gandere",
    "wof:placetype":"locality"
},
  "geometry": {"coordinates":[71.66094,34.92157],"type":"Point"}
}