{
  "type": "Feature",
  "properties": {
    "gn:admin1_code":"04",
    "gn:asciiname":"Qabula",
    "gn:country_code":"PK",
    "gn:dem":155,
    "gn:feature_class":"P",
    "gn:feature_code":"PPL",
    "gn:name":"Qabula",
    "gn:population":0,
    "gn:timezone":"Asia/Karachi",
    "iso:country":"PK",
    "name:und_x_variant":[
        "Qabala",
        "Qabula"
    ],
    "wof:name":"Qabula",
    "wof:placetype":"locality"
},
  "geometry": {"coordinates":[73.0651,30.17784],"type":"Point"}
}