{
  "type": "Feature",
  "properties": {
    "gn:admin1_code":"5.0",
    "gn:asciiname":"Goth Dir Muhammad Marri",
    "gn:country_code":"PK",
    "gn:dem":43,
    "gn:feature_class":"P",
    "gn:feature_code":"PPL",
    "gn:name":"Goth Dir Muhammad Marri",
    "gn:population":0,
    "gn:timezone":"Asia/Karachi",
    "iso:country":"PK",
    "name:und_x_variant":[
        "R\u0101\u012bs Ras\u016bl Bakhsh"
    ],
    "wof:name":"Goth Dir Muhammad Marri",
    "wof:placetype":"locality"
},
  "geometry": {"coordinates":[68.32565,26.70311],"type":"Point"}
}