{
  "type": "Feature",
  "properties": {
    "gn:admin1_code":"4.0",
    "gn:asciiname":"Khangan Shimali",
    "gn:country_code":"PK",
    "gn:dem":118,
    "gn:feature_class":"P",
    "gn:feature_code":"PPL",
    "gn:name":"Khangan Shimali",
    "gn:population":0,
    "gn:timezone":"Asia/Karachi",
    "iso:country":"PK",
    "name:und_x_variant":[
        "Khhanghan Shumali",
        "Khangan Shimali"
    ],
    "wof:name":"Khangan Shimali",
    "wof:placetype":"locality"
},
  "geometry": {"coordinates":[71.25698,30.15309],"type":"Point"}
}