{
  "type": "Feature",
  "properties": {
    "gn:admin1_code":"4",
    "gn:asciiname":"Kund Rehm Shah",
    "gn:country_code":"PK",
    "gn:dem":186,
    "gn:feature_class":"P",
    "gn:feature_code":"PPL",
    "gn:name":"Kund Rehm Shah",
    "gn:population":0,
    "gn:timezone":"Asia/Karachi",
    "iso:country":"PK",
    "name:und_x_variant":[
        "Kund Raham Sh\u0101h"
    ],
    "wof:name":"Kund Rehm Shah",
    "wof:placetype":"locality"
},
  "geometry": {"coordinates":[73.55020999999998,31.13165],"type":"Point"}
}