{
  "type": "Feature",
  "properties": {
    "gn:admin1_code":"2.0",
    "gn:asciiname":"Apozai Kili",
    "gn:country_code":"PK",
    "gn:dem":1376,
    "gn:feature_class":"P",
    "gn:feature_code":"PPL",
    "gn:name":"Apozai Kili",
    "gn:population":0,
    "gn:timezone":"Asia/Karachi",
    "iso:country":"PK",
    "wof:name":"Apozai Kili",
    "wof:placetype":"locality"
},
  "geometry": {"coordinates":[69.42227,31.33983],"type":"Point"}
}