{
  "type": "Feature",
  "properties": {
    "gn:admin1_code":"3.0",
    "gn:asciiname":"Mada Khef",
    "gn:country_code":"PK",
    "gn:dem":359,
    "gn:feature_class":"P",
    "gn:feature_code":"PPL",
    "gn:name":"Mada Khef",
    "gn:population":0,
    "gn:timezone":"Asia/Karachi",
    "iso:country":"PK",
    "name:und_x_variant":[
        "Hawed"
    ],
    "wof:name":"Mada Khef",
    "wof:placetype":"locality"
},
  "geometry": {"coordinates":[70.59739,32.94406],"type":"Point"}
}