{
  "type": "Feature",
  "properties": {
    "gn:admin1_code":"2.0",
    "gn:asciiname":"Kili Lameran",
    "gn:country_code":"PK",
    "gn:dem":1556,
    "gn:feature_class":"P",
    "gn:feature_code":"PPL",
    "gn:name":"Kili Lameran",
    "gn:population":0,
    "gn:timezone":"Asia/Karachi",
    "iso:country":"PK",
    "name:eng_x_preferred":[
        "Kili Lameran"
    ],
    "wof:name":"Kili Lameran",
    "wof:placetype":"locality"
},
  "geometry": {"coordinates":[67.00221999999999,30.57361],"type":"Point"}
}