{
  "type": "Feature",
  "properties": {
    "gn:admin1_code":"04",
    "gn:asciiname":"Marara",
    "gn:country_code":"PK",
    "gn:dem":276,
    "gn:feature_class":"P",
    "gn:feature_code":"PPL",
    "gn:name":"Marara",
    "gn:population":0,
    "gn:timezone":"Asia/Karachi",
    "iso:country":"PK",
    "wof:name":"Marara",
    "wof:placetype":"locality"
},
  "geometry": {"coordinates":[74.94266,32.35942],"type":"Point"}
}