{
  "type": "Feature",
  "properties": {
    "gn:admin1_code":"2.0",
    "gn:asciiname":"Haji Akhtar Muhammad Kili",
    "gn:country_code":"PK",
    "gn:dem":1248,
    "gn:feature_class":"P",
    "gn:feature_code":"PPL",
    "gn:name":"Haji Akhtar Muhammad Kili",
    "gn:population":0,
    "gn:timezone":"Asia/Karachi",
    "iso:country":"PK",
    "wof:name":"Haji Akhtar Muhammad Kili",
    "wof:placetype":"locality"
},
  "geometry": {"coordinates":[66.38831999999999,30.89362],"type":"Point"}
}