{
  "type": "Feature",
  "properties": {
    "gn:admin1_code":"4",
    "gn:asciiname":"Nurwala",
    "gn:country_code":"PK",
    "gn:dem":109,
    "gn:feature_class":"P",
    "gn:feature_code":"PPL",
    "gn:name":"Nurwala",
    "gn:population":0,
    "gn:timezone":"Asia/Karachi",
    "iso:country":"PK",
    "name:und_x_variant":[
        "Noww\u0101la",
        "Nurwala"
    ],
    "wof:name":"Nurwala",
    "wof:placetype":"locality"
},
  "geometry": {"coordinates":[71.24556,29.44798],"type":"Point"}
}