{
  "type": "Feature",
  "properties": {
    "gn:admin1_code":"4",
    "gn:asciiname":"Madhranwala",
    "gn:country_code":"PK",
    "gn:dem":232,
    "gn:feature_class":"P",
    "gn:feature_code":"PPL",
    "gn:name":"Madhranwala",
    "gn:population":0,
    "gn:timezone":"Asia/Karachi",
    "iso:country":"PK",
    "name:und_x_variant":[
        "Mandar\u0101nw\u0101la"
    ],
    "wof:name":"Madhranwala",
    "wof:placetype":"locality"
},
  "geometry": {"coordinates":[74.46623000000002,32.14307],"type":"Point"}
}