{
  "type": "Feature",
  "properties": {
    "gn:admin1_code":"2",
    "gn:asciiname":"Harboi",
    "gn:country_code":"PK",
    "gn:dem":2794,
    "gn:feature_class":"P",
    "gn:feature_code":"PPL",
    "gn:name":"Harboi",
    "gn:population":0,
    "gn:timezone":"Asia/Karachi",
    "iso:country":"PK",
    "name:ceb_x_preferred":[
        "Harboi"
    ],
    "wof:name":"Harboi",
    "wof:placetype":"locality"
},
  "geometry": {"coordinates":[66.76040999999999,28.97912],"type":"Point"}
}