{
  "type": "Feature",
  "properties": {
    "gn:admin1_code":"2.0",
    "gn:asciiname":"Haji Agha Gul",
    "gn:country_code":"PK",
    "gn:dem":1951,
    "gn:feature_class":"P",
    "gn:feature_code":"PPL",
    "gn:name":"Haji Agha Gul",
    "gn:population":0,
    "gn:timezone":"Asia/Karachi",
    "iso:country":"PK",
    "wof:name":"Haji Agha Gul",
    "wof:placetype":"locality"
},
  "geometry": {"coordinates":[66.90129,31.26771],"type":"Point"}
}