{
  "type": "Feature",
  "properties": {
    "gn:admin1_code":"2.0",
    "gn:asciiname":"Muhammad Musa",
    "gn:country_code":"PK",
    "gn:dem":691,
    "gn:feature_class":"P",
    "gn:feature_code":"PPL",
    "gn:name":"Muhammad Musa",
    "gn:population":0,
    "gn:timezone":"Asia/Karachi",
    "iso:country":"PK",
    "name:ben_x_preferred":[
        "\u09ae\u09c1\u09b9\u09be\u09ae\u09cd\u09ae\u09a6 \u09ae\u09c1\u09b8\u09be \u0996\u09be\u09a8"
    ],
    "name:fas_x_preferred":[
        "\u0645\u0648\u0633\u06cc \u062e\u0627\u0646 \u0647\u0632\u0627\u0631\u0647"
    ],
    "name:fra_x_preferred":[
        "Muhammad Musa"
    ],
    "name:hin_x_preferred":[
        "\u091c\u0928\u0930\u0932 \u092e\u094b\u0939\u092e\u094d\u092e\u0926 \u092e\u0942\u0938\u093e \u0916\u093e\u0928"
    ],
    "name:pan_x_preferred":[
        "\u0a2e\u0a41\u0a39\u0a70\u0a2e\u0a26 \u0a2e\u0a42\u0a38\u0a3e"
    ],
    "name:pnb_x_preferred":[
        "\u062c\u0646\u0631\u0644 \u0645\u0648\u0633\u06cc \u062e\u0627\u0646"
    ],
    "name:pus_x_preferred":[
        "\u0645\u0648\u0633\u06cc \u062e\u0627\u0646"
    ],
    "name:rus_x_preferred":[
        "\u041c\u0443\u0441\u0430"
    ],
    "name:slv_x_preferred":[
        "Musa Kan Hazara"
    ],
    "name:urd_x_preferred":[
        "\u0645\u0648\u0633\u06cc \u062e\u0627\u0646"
    ],
    "wof:name":"Muhammad Musa",
    "wof:placetype":"locality"
},
  "geometry": {"coordinates":[63.6229,26.42161],"type":"Point"}
}