{
  "type": "Feature",
  "properties": {
    "gn:admin1_code":"5",
    "gn:asciiname":"Sheikh Marri",
    "gn:country_code":"PK",
    "gn:dem":24,
    "gn:feature_class":"P",
    "gn:feature_code":"PPL",
    "gn:name":"Sheikh Marri",
    "gn:population":0,
    "gn:timezone":"Asia/Karachi",
    "iso:country":"PK",
    "name:und_x_variant":[
        "Goth Sh\u0101hik Marri"
    ],
    "wof:name":"Sheikh Marri",
    "wof:placetype":"locality"
},
  "geometry": {"coordinates":[68.69081,25.74154],"type":"Point"}
}