{
  "type": "Feature",
  "properties": {
    "gn:admin1_code":"2.0",
    "gn:asciiname":"Maidan Sasol",
    "gn:country_code":"PK",
    "gn:dem":1021,
    "gn:feature_class":"P",
    "gn:feature_code":"PPL",
    "gn:name":"Maidan Sasol",
    "gn:population":0,
    "gn:timezone":"Asia/Karachi",
    "iso:country":"PK",
    "wof:name":"Maidan Sasol",
    "wof:placetype":"locality"
},
  "geometry": {"coordinates":[65.71038,28.96093],"type":"Point"}
}