{
  "type": "Feature",
  "properties": {
    "gn:admin1_code":"2.0",
    "gn:asciiname":"Shin Wam",
    "gn:country_code":"PK",
    "gn:dem":669,
    "gn:feature_class":"P",
    "gn:feature_code":"PPL",
    "gn:name":"Shin Wam",
    "gn:population":0,
    "gn:timezone":"Asia/Karachi",
    "iso:country":"PK",
    "wof:name":"Shin Wam",
    "wof:placetype":"locality"
},
  "geometry": {"coordinates":[70.16339000000001,31.35174],"type":"Point"}
}