{
  "type": "Feature",
  "properties": {
    "gn:admin1_code":"5.0",
    "gn:asciiname":"Hafiz Baloch Goth",
    "gn:country_code":"PK",
    "gn:dem":61,
    "gn:feature_class":"P",
    "gn:feature_code":"PPL",
    "gn:name":"Hafiz Baloch Goth",
    "gn:population":0,
    "gn:timezone":"Asia/Karachi",
    "iso:country":"PK",
    "name:eng_x_preferred":[
        "Hafiz Baloch Goth"
    ],
    "wof:name":"Hafiz Baloch Goth",
    "wof:placetype":"locality"
},
  "geometry": {"coordinates":[68.58877,27.83545],"type":"Point"}
}