{
  "type": "Feature",
  "properties": {
    "gn:admin1_code":"5",
    "gn:asciiname":"Goth Mubarak Pali",
    "gn:country_code":"PK",
    "gn:dem":13,
    "gn:feature_class":"P",
    "gn:feature_code":"PPL",
    "gn:name":"Goth Mubarak Pali",
    "gn:population":0,
    "gn:timezone":"Asia/Karachi",
    "iso:country":"PK",
    "name:und_x_variant":[
        "Mub\u0101rak Pali"
    ],
    "wof:name":"Goth Mubarak Pali",
    "wof:placetype":"locality"
},
  "geometry": {"coordinates":[69.55414,25.48838],"type":"Point"}
}