{
  "type": "Feature",
  "properties": {
    "gn:admin1_code":"6",
    "gn:asciiname":"Dheri Rampur",
    "gn:country_code":"PK",
    "gn:dem":378,
    "gn:feature_class":"P",
    "gn:feature_code":"PPL",
    "gn:name":"Dheri Rampur",
    "gn:population":0,
    "gn:timezone":"Asia/Karachi",
    "iso:country":"PK",
    "name:und_x_variant":[
        "Dhri R\u0101mpur"
    ],
    "wof:name":"Dheri Rampur",
    "wof:placetype":"locality"
},
  "geometry": {"coordinates":[73.76445,33.26175],"type":"Point"}
}