{
  "type": "Feature",
  "properties": {
    "gn:admin1_code":"3.0",
    "gn:asciiname":"Karkinosam Talao",
    "gn:country_code":"PK",
    "gn:dem":446,
    "gn:feature_class":"P",
    "gn:feature_code":"PPL",
    "gn:name":"Karkinosam Talao",
    "gn:population":0,
    "gn:timezone":"Asia/Karachi",
    "iso:country":"PK",
    "wof:name":"Karkinosam Talao",
    "wof:placetype":"locality"
},
  "geometry": {"coordinates":[71.63565,33.54133],"type":"Point"}
}