{
  "type": "Feature",
  "properties": {
    "gn:admin1_code":"6",
    "gn:asciiname":"Mohri Baihk",
    "gn:country_code":"PK",
    "gn:dem":3134,
    "gn:feature_class":"P",
    "gn:feature_code":"PPL",
    "gn:name":"Mohri Baihk",
    "gn:population":0,
    "gn:timezone":"Asia/Karachi",
    "iso:country":"PK",
    "name:und_x_variant":[
        "Mori Baihk"
    ],
    "wof:name":"Mohri Baihk",
    "wof:placetype":"locality"
},
  "geometry": {"coordinates":[73.84000999999998,34.70761],"type":"Point"}
}