{
  "type": "Feature",
  "properties": {
    "gn:admin1_code":"01",
    "gn:asciiname":"Mazid Khel",
    "gn:country_code":"PK",
    "gn:dem":772,
    "gn:feature_class":"P",
    "gn:feature_code":"PPL",
    "gn:name":"Mazid Khel",
    "gn:population":0,
    "gn:timezone":"Asia/Karachi",
    "iso:country":"PK",
    "wof:name":"Mazid Khel",
    "wof:placetype":"locality"
},
  "geometry": {"coordinates":[71.47293000000001,34.38019],"type":"Point"}
}