{
  "type": "Feature",
  "properties": {
    "gn:admin1_code":"2.0",
    "gn:asciiname":"Goth Chukhi Haji Ghulam Nabi Magsi",
    "gn:country_code":"PK",
    "gn:dem":48,
    "gn:feature_class":"P",
    "gn:feature_code":"PPL",
    "gn:name":"Goth Chukhi Haji Ghulam Nabi Magsi",
    "gn:population":0,
    "gn:timezone":"Asia/Karachi",
    "iso:country":"PK",
    "wof:name":"Goth Chukhi Haji Ghulam Nabi Magsi",
    "wof:placetype":"locality"
},
  "geometry": {"coordinates":[67.6262,27.92217],"type":"Point"}
}