{
  "type": "Feature",
  "properties": {
    "gn:admin1_code":"5",
    "gn:asciiname":"Dagano Buzdar",
    "gn:country_code":"PK",
    "gn:dem":24,
    "gn:feature_class":"P",
    "gn:feature_code":"PPL",
    "gn:name":"Dagano Buzdar",
    "gn:population":0,
    "gn:timezone":"Asia/Karachi",
    "iso:country":"PK",
    "name:und_x_variant":[
        "Dag\u0101na Buzd\u0101r"
    ],
    "wof:name":"Dagano Buzdar",
    "wof:placetype":"locality"
},
  "geometry": {"coordinates":[68.65524000000001,25.42494],"type":"Point"}
}