{
  "type": "Feature",
  "properties": {
    "gn:admin1_code":"5",
    "gn:asciiname":"Goth Ismail Kaloi",
    "gn:country_code":"PK",
    "gn:dem":10,
    "gn:feature_class":"P",
    "gn:feature_code":"PPL",
    "gn:name":"Goth Ismail Kaloi",
    "gn:population":0,
    "gn:timezone":"Asia/Karachi",
    "iso:country":"PK",
    "name:und_x_variant":[
        "Ali Ahmad Chaudhry"
    ],
    "wof:name":"Goth Ismail Kaloi",
    "wof:placetype":"locality"
},
  "geometry": {"coordinates":[69.18228000000001,25.10244],"type":"Point"}
}