{
  "type": "Feature",
  "properties": {
    "gn:admin1_code":"4.0",
    "gn:asciiname":"Matha",
    "gn:country_code":"PK",
    "gn:dem":184,
    "gn:feature_class":"P",
    "gn:feature_code":"PPL",
    "gn:name":"Matha",
    "gn:population":0,
    "gn:timezone":"Asia/Karachi",
    "iso:country":"PK",
    "name:pol_x_preferred":[
        "Matha"
    ],
    "name:rus_x_preferred":[
        "\u041c\u0430\u0442\u0445\u0430"
    ],
    "name:sqi_x_preferred":[
        "Matha"
    ],
    "name:tam_x_preferred":[
        "\u0bae\u0b9f\u0bae\u0bcd"
    ],
    "name:ukr_x_preferred":[
        "\u041c\u0430\u0442\u0445\u0430"
    ],
    "wof:name":"Matha",
    "wof:placetype":"locality"
},
  "geometry": {"coordinates":[71.30915,32.24537],"type":"Point"}
}