{
  "type": "Feature",
  "properties": {
    "gn:admin1_code":"5",
    "gn:asciiname":"Goth Hasul",
    "gn:country_code":"PK",
    "gn:dem":70,
    "gn:feature_class":"P",
    "gn:feature_code":"PPL",
    "gn:name":"Goth Hasul",
    "gn:population":0,
    "gn:timezone":"Asia/Karachi",
    "iso:country":"PK",
    "wof:name":"Goth Hasul",
    "wof:placetype":"locality"
},
  "geometry": {"coordinates":[67.41032,26.88965],"type":"Point"}
}