{
  "type": "Feature",
  "properties": {
    "gn:admin1_code":"4.0",
    "gn:asciiname":"Basti Muradwala",
    "gn:country_code":"PK",
    "gn:dem":101,
    "gn:feature_class":"P",
    "gn:feature_code":"PPL",
    "gn:name":"Basti Muradwala",
    "gn:population":0,
    "gn:timezone":"Asia/Karachi",
    "iso:country":"PK",
    "name:und_x_variant":[
        "Muradw\u0101la"
    ],
    "wof:name":"Basti Muradwala",
    "wof:placetype":"locality"
},
  "geometry": {"coordinates":[71.16746999999999,29.27124],"type":"Point"}
}