{
  "type": "Feature",
  "properties": {
    "gn:admin1_code":"5.0",
    "gn:asciiname":"Wajahat Solongi",
    "gn:country_code":"PK",
    "gn:dem":27,
    "gn:feature_class":"P",
    "gn:feature_code":"PPL",
    "gn:name":"Wajahat Solongi",
    "gn:population":0,
    "gn:timezone":"Asia/Karachi",
    "iso:country":"PK",
    "wof:name":"Wajahat Solongi",
    "wof:placetype":"locality"
},
  "geometry": {"coordinates":[68.65564999999999,26.10113],"type":"Point"}
}