{
  "type": "Feature",
  "properties": {
    "gn:admin1_code":"04",
    "gn:asciiname":"Chaka Six Hundred Thirteen",
    "gn:country_code":"PK",
    "gn:dem":174,
    "gn:feature_class":"P",
    "gn:feature_code":"PPL",
    "gn:name":"Chaka Six Hundred Thirteen",
    "gn:population":0,
    "gn:timezone":"Asia/Karachi",
    "iso:country":"PK",
    "name:und_x_variant":[
        "Kot Sam\u0101il",
        "Kot Saman"
    ],
    "wof:name":"Chaka Six Hundred Thirteen",
    "wof:placetype":"locality"
},
  "geometry": {"coordinates":[73.06390999999998,30.88352],"type":"Point"}
}