{
  "type": "Feature",
  "properties": {
    "gn:admin1_code":"1.0",
    "gn:asciiname":"Tandai",
    "gn:country_code":"PK",
    "gn:dem":527,
    "gn:feature_class":"P",
    "gn:feature_code":"PPL",
    "gn:name":"Tandai",
    "gn:population":0,
    "gn:timezone":"Asia/Karachi",
    "iso:country":"PK",
    "name:bar_x_preferred":[
        "Tandai"
    ],
    "name:deu_x_preferred":[
        "Tandai"
    ],
    "name:fas_x_preferred":[
        "\u062a\u0627\u0646\u062f\u0627\u06cc"
    ],
    "name:fra_x_preferred":[
        "Tandai"
    ],
    "name:kor_x_preferred":[
        "\ub2e8\ub2e4\uc774"
    ],
    "name:por_x_preferred":[
        "Tandai"
    ],
    "wof:name":"Tandai",
    "wof:placetype":"locality"
},
  "geometry": {"coordinates":[71.49035000000001,33.8105],"type":"Point"}
}