{
  "type": "Feature",
  "properties": {
    "gn:admin1_code":"02",
    "gn:asciiname":"Mand-i-Haji",
    "gn:country_code":"PK",
    "gn:dem":1752,
    "gn:feature_class":"P",
    "gn:feature_code":"PPL",
    "gn:name":"Mand-i-Haji",
    "gn:population":0,
    "gn:timezone":"Asia/Karachi",
    "iso:country":"PK",
    "name:und_x_variant":[
        "Mand Haji",
        "Mand-i-Haji"
    ],
    "wof:name":"Mand-i-Haji",
    "wof:placetype":"locality"
},
  "geometry": {"coordinates":[66.62439000000001,29.38322],"type":"Point"}
}