{
  "type": "Feature",
  "properties": {
    "gn:admin1_code":"3.0",
    "gn:asciiname":"Datai",
    "gn:country_code":"PK",
    "gn:dem":1155,
    "gn:feature_class":"P",
    "gn:feature_code":"PPL",
    "gn:name":"Datai",
    "gn:population":0,
    "gn:timezone":"Asia/Karachi",
    "iso:country":"PK",
    "wof:name":"Datai",
    "wof:placetype":"locality"
},
  "geometry": {"coordinates":[71.62876999999997,34.87487],"type":"Point"}
}