{
  "type": "Feature",
  "properties": {
    "gn:admin1_code":"1.0",
    "gn:asciiname":"Shadmeer Kalle",
    "gn:country_code":"PK",
    "gn:dem":1606,
    "gn:feature_class":"P",
    "gn:feature_code":"PPL",
    "gn:name":"Shadmeer Kalle",
    "gn:population":0,
    "gn:timezone":"Asia/Karachi",
    "iso:country":"PK",
    "wof:name":"Shadmeer Kalle",
    "wof:placetype":"locality"
},
  "geometry": {"coordinates":[69.29431,32.21529],"type":"Point"}
}