{
  "type": "Feature",
  "properties": {
    "gn:admin1_code":"2.0",
    "gn:asciiname":"Khaprezai Kili",
    "gn:country_code":"PK",
    "gn:dem":1211,
    "gn:feature_class":"P",
    "gn:feature_code":"PPL",
    "gn:name":"Khaprezai Kili",
    "gn:population":0,
    "gn:timezone":"Asia/Karachi",
    "iso:country":"PK",
    "name:und_x_variant":[
        "Khaprezai",
        "Khaprezai Kili"
    ],
    "wof:name":"Khaprezai Kili",
    "wof:placetype":"locality"
},
  "geometry": {"coordinates":[67.66974999999999,30.20238],"type":"Point"}
}