{
  "type": "Feature",
  "properties": {
    "gn:admin1_code":"6.0",
    "gn:asciiname":"Simari",
    "gn:country_code":"PK",
    "gn:dem":1700,
    "gn:feature_class":"P",
    "gn:feature_code":"PPL",
    "gn:name":"Simari",
    "gn:population":0,
    "gn:timezone":"Asia/Karachi",
    "iso:country":"PK",
    "wof:name":"Simari",
    "wof:placetype":"locality"
},
  "geometry": {"coordinates":[73.79134999999999,34.43199],"type":"Point"}
}