{
  "type": "Feature",
  "properties": {
    "gn:admin1_code":"5",
    "gn:asciiname":"Goth Khabar Mulana",
    "gn:country_code":"PK",
    "gn:dem":25,
    "gn:feature_class":"P",
    "gn:feature_code":"PPL",
    "gn:name":"Goth Khabar Mulana",
    "gn:population":0,
    "gn:timezone":"Asia/Karachi",
    "iso:country":"PK",
    "name:eng_x_preferred":[
        "Khabbar Muli\u0101n"
    ],
    "wof:name":"Goth Khabar Mulana",
    "wof:placetype":"locality"
},
  "geometry": {"coordinates":[68.4594,25.50804],"type":"Point"}
}