{
  "type": "Feature",
  "properties": {
    "gn:admin1_code":"3.0",
    "gn:asciiname":"Mahmudabad",
    "gn:country_code":"PK",
    "gn:dem":334,
    "gn:feature_class":"P",
    "gn:feature_code":"PPL",
    "gn:name":"Mahmudabad",
    "gn:population":0,
    "gn:timezone":"Asia/Karachi",
    "iso:country":"PK",
    "name:eng_x_preferred":[
        "Mahmudabad"
    ],
    "wof:name":"Mahmudabad",
    "wof:placetype":"locality"
},
  "geometry": {"coordinates":[72.45947,34.09755],"type":"Point"}
}