{
  "type": "Feature",
  "properties": {
    "gn:admin1_code":"3.0",
    "gn:asciiname":"Kawari",
    "gn:country_code":"PK",
    "gn:dem":862,
    "gn:feature_class":"P",
    "gn:feature_code":"PPL",
    "gn:name":"Kawari",
    "gn:population":0,
    "gn:timezone":"Asia/Karachi",
    "iso:country":"PK",
    "wof:name":"Kawari",
    "wof:placetype":"locality"
},
  "geometry": {"coordinates":[71.97416,33.84899],"type":"Point"}
}