{
  "type": "Feature",
  "properties": {
    "gn:admin1_code":"4",
    "gn:asciiname":"Chak One Hundred Eighty-one",
    "gn:country_code":"PK",
    "gn:dem":163,
    "gn:feature_class":"P",
    "gn:feature_code":"PPL",
    "gn:name":"Chak One Hundred Eighty-one",
    "gn:population":0,
    "gn:timezone":"Asia/Karachi",
    "iso:country":"PK",
    "name:eng_x_preferred":[
        "Chak One Hundred Eighty-one"
    ],
    "name:und_x_variant":[
        "Mochiw\u0101la"
    ],
    "wof:name":"Chak One Hundred Eighty-one",
    "wof:placetype":"locality"
},
  "geometry": {"coordinates":[72.57563,31.31862000000001],"type":"Point"}
}