{
  "type": "Feature",
  "properties": {
    "gn:admin1_code":"2.0",
    "gn:asciiname":"Kili Haji Kamal Khan",
    "gn:country_code":"PK",
    "gn:dem":1720,
    "gn:feature_class":"P",
    "gn:feature_code":"PPL",
    "gn:name":"Kili Haji Kamal Khan",
    "gn:population":0,
    "gn:timezone":"Asia/Karachi",
    "iso:country":"PK",
    "wof:name":"Kili Haji Kamal Khan",
    "wof:placetype":"locality"
},
  "geometry": {"coordinates":[66.96852,30.08068],"type":"Point"}
}