{
  "type": "Feature",
  "properties": {
    "gn:admin1_code":"2.0",
    "gn:asciiname":"Jatak",
    "gn:country_code":"PK",
    "gn:dem":1658,
    "gn:feature_class":"P",
    "gn:feature_code":"PPL",
    "gn:name":"Jatak",
    "gn:population":0,
    "gn:timezone":"Asia/Karachi",
    "iso:country":"PK",
    "name:und_x_variant":[
        "Jetak"
    ],
    "wof:name":"Jatak",
    "wof:placetype":"locality"
},
  "geometry": {"coordinates":[66.3006,28.18938],"type":"Point"}
}