{
  "type": "Feature",
  "properties": {
    "gn:admin1_code":"2.0",
    "gn:asciiname":"Haji Dad Muhammad Hajwani",
    "gn:country_code":"PK",
    "gn:dem":63,
    "gn:feature_class":"P",
    "gn:feature_code":"PPL",
    "gn:name":"Haji Dad Muhammad Hajwani",
    "gn:population":0,
    "gn:timezone":"Asia/Karachi",
    "iso:country":"PK",
    "wof:name":"Haji Dad Muhammad Hajwani",
    "wof:placetype":"locality"
},
  "geometry": {"coordinates":[68.21408000000001,28.46975],"type":"Point"}
}