{
  "type": "Feature",
  "properties": {
    "gn:admin1_code":"4",
    "gn:asciiname":"Basti Mad",
    "gn:country_code":"PK",
    "gn:dem":123,
    "gn:feature_class":"P",
    "gn:feature_code":"PPL",
    "gn:name":"Basti Mad",
    "gn:population":0,
    "gn:timezone":"Asia/Karachi",
    "iso:country":"PK",
    "name:und_x_variant":[
        "Mad"
    ],
    "wof:name":"Basti Mad",
    "wof:placetype":"locality"
},
  "geometry": {"coordinates":[71.98614999999999,29.55255],"type":"Point"}
}