{
  "type": "Feature",
  "properties": {
    "gn:admin1_code":"4",
    "gn:asciiname":"Chak Thirteen Jhang Branch",
    "gn:country_code":"PK",
    "gn:dem":192,
    "gn:feature_class":"P",
    "gn:feature_code":"PPL",
    "gn:name":"Chak Thirteen Jhang Branch",
    "gn:population":0,
    "gn:timezone":"Asia/Karachi",
    "iso:country":"PK",
    "name:und_x_variant":[
        "Chak Thirteen",
        "S\u0101r\u016bw\u0101la",
        "Chak Thirteen Jhang Branch",
        "S\u0101rw\u0101la"
    ],
    "wof:name":"Chak Thirteen Jhang Branch",
    "wof:placetype":"locality"
},
  "geometry": {"coordinates":[73.11140999999998,31.72601],"type":"Point"}
}