{
  "type": "Feature",
  "properties": {
    "gn:admin1_code":"4",
    "gn:asciiname":"Ramke",
    "gn:country_code":"PK",
    "gn:dem":254,
    "gn:feature_class":"P",
    "gn:feature_code":"PPL",
    "gn:name":"Ramke",
    "gn:population":0,
    "gn:timezone":"Asia/Karachi",
    "iso:country":"PK",
    "wof:name":"Ramke",
    "wof:placetype":"locality"
},
  "geometry": {"coordinates":[74.27396999999998,32.64847],"type":"Point"}
}