{
  "type": "Feature",
  "properties": {
    "gn:admin1_code":"3",
    "gn:asciiname":"Motehianandeh",
    "gn:country_code":"PK",
    "gn:dem":1531,
    "gn:feature_class":"P",
    "gn:feature_code":"PPL",
    "gn:name":"Motehianandeh",
    "gn:population":0,
    "gn:timezone":"Asia/Karachi",
    "iso:country":"PK",
    "name:eng_x_preferred":[
        "Motehianandeh"
    ],
    "wof:name":"Motehianandeh",
    "wof:placetype":"locality"
},
  "geometry": {"coordinates":[71.79366,35.8642],"type":"Point"}
}