{
  "type": "Feature",
  "properties": {
    "gn:admin1_code":"4",
    "gn:asciiname":"Nikka Sadwal",
    "gn:country_code":"PK",
    "gn:dem":297,
    "gn:feature_class":"P",
    "gn:feature_code":"PPL",
    "gn:name":"Nikka Sadwal",
    "gn:population":0,
    "gn:timezone":"Asia/Karachi",
    "iso:country":"PK",
    "name:und_x_variant":[
        "Nikka Saaw\u0101l"
    ],
    "wof:name":"Nikka Sadwal",
    "wof:placetype":"locality"
},
  "geometry": {"coordinates":[74.09845,32.8431],"type":"Point"}
}