{
  "type": "Feature",
  "properties": {
    "gn:admin1_code":"5.0",
    "gn:asciiname":"Mankahu",
    "gn:country_code":"PK",
    "gn:dem":75,
    "gn:feature_class":"P",
    "gn:feature_code":"PPL",
    "gn:name":"Mankahu",
    "gn:population":0,
    "gn:timezone":"Asia/Karachi",
    "iso:country":"PK",
    "wof:name":"Mankahu",
    "wof:placetype":"locality"
},
  "geometry": {"coordinates":[69.99803,26.07752],"type":"Point"}
}