{
  "type": "Feature",
  "properties": {
    "gn:admin1_code":"4",
    "gn:asciiname":"Basti Balhora",
    "gn:country_code":"PK",
    "gn:dem":101,
    "gn:feature_class":"P",
    "gn:feature_code":"PPL",
    "gn:name":"Basti Balhora",
    "gn:population":0,
    "gn:timezone":"Asia/Karachi",
    "iso:country":"PK",
    "wof:name":"Basti Balhora",
    "wof:placetype":"locality"
},
  "geometry": {"coordinates":[70.58941999999998,29.37791],"type":"Point"}
}