{
  "type": "Feature",
  "properties": {
    "gn:admin1_code":"4.0",
    "gn:asciiname":"Khanwala",
    "gn:country_code":"PK",
    "gn:dem":108,
    "gn:feature_class":"P",
    "gn:feature_code":"PPL",
    "gn:name":"Khanwala",
    "gn:population":0,
    "gn:timezone":"Asia/Karachi",
    "iso:country":"PK",
    "name:und_x_variant":[
        "Bhakkiw\u0101la"
    ],
    "wof:name":"Khanwala",
    "wof:placetype":"locality"
},
  "geometry": {"coordinates":[70.61256999999998,29.64972],"type":"Point"}
}