{
  "type": "Feature",
  "properties": {
    "gn:admin1_code":"4.0",
    "gn:asciiname":"Basti Kanewali Sharqi",
    "gn:country_code":"PK",
    "gn:dem":157,
    "gn:feature_class":"P",
    "gn:feature_code":"PPL",
    "gn:name":"Basti Kanewali Sharqi",
    "gn:population":0,
    "gn:timezone":"Asia/Karachi",
    "iso:country":"PK",
    "wof:name":"Basti Kanewali Sharqi",
    "wof:placetype":"locality"
},
  "geometry": {"coordinates":[70.72988000000002,31.27583],"type":"Point"}
}