{
  "type": "Feature",
  "properties": {
    "gn:admin1_code":"5.0",
    "gn:asciiname":"Jamshoro",
    "gn:country_code":"PK",
    "gn:dem":27,
    "gn:feature_class":"P",
    "gn:feature_code":"PPLA2",
    "gn:name":"Jamshoro",
    "gn:population":0,
    "gn:timezone":"Asia/Karachi",
    "iso:country":"PK",
    "name:eng_x_preferred":[
        "J\u0101m Shoro"
    ],
    "name:eng_x_variant":[
        "Jamshoro"
    ],
    "name:und_x_variant":[
        "Jamsboro",
        "Jamshore",
        "Jams Shoro"
    ],
    "wof:name":"Jamshoro",
    "wof:placetype":"locality"
},
  "geometry": {"coordinates":[68.28017,25.43608],"type":"Point"}
}