{
  "type": "Feature",
  "properties": {
    "gn:admin1_code":"5.0",
    "gn:asciiname":"Jamshoro",
    "gn:country_code":"PK",
    "gn:dem":27,
    "gn:feature_class":"P",
    "gn:feature_code":"PPLA2",
    "gn:name":"Jamshoro",
    "gn:population":0,
    "gn:timezone":"Asia/Karachi",
    "iso:country":"PK",
    "name:ceb_x_preferred":[
        "Jamshoro"
    ],
    "name:eng_x_preferred":[
        "J\u0101m Shoro"
    ],
    "name:eng_x_variant":[
        "Jamshoro"
    ],
    "name:epo_x_preferred":[
        "Jam\u015doro"
    ],
    "name:fas_x_preferred":[
        "\u062c\u0627\u0645\u0634\u0648\u0631\u0648"
    ],
    "name:fra_x_preferred":[
        "Jamshoro"
    ],
    "name:hin_x_preferred":[
        "\u091c\u092e\u0936\u094b\u0930\u094b"
    ],
    "name:pnb_x_preferred":[
        "\u062c\u0627\u0645\u0634\u0648\u0631\u0648"
    ],
    "name:rus_x_preferred":[
        "\u0414\u0436\u0430\u043c\u0448\u043e\u0440\u043e"
    ],
    "name:snd_x_preferred":[
        "\u0684\u0627\u0645\u0634\u0648\u0631\u0648"
    ],
    "name:swe_x_preferred":[
        "Jamshoro"
    ],
    "name:und_x_variant":[
        "Jamsboro",
        "Jamshore",
        "Jams Shoro"
    ],
    "name:urd_x_preferred":[
        "\u062c\u0627\u0645\u0634\u0648\u0631\u0648"
    ],
    "wof:name":"Jamshoro",
    "wof:placetype":"locality"
},
  "geometry": {"coordinates":[68.28017,25.43608],"type":"Point"}
}