{
  "type": "Feature",
  "properties": {
    "gn:admin1_code":"4.0",
    "gn:asciiname":"Passianwala",
    "gn:country_code":"PK",
    "gn:dem":221,
    "gn:feature_class":"P",
    "gn:feature_code":"PPL",
    "gn:name":"Passianwala",
    "gn:population":0,
    "gn:timezone":"Asia/Karachi",
    "iso:country":"PK",
    "name:und_x_variant":[
        "Passi\u0101nw\u0101li"
    ],
    "wof:name":"Passianwala",
    "wof:placetype":"locality"
},
  "geometry": {"coordinates":[74.58388000000002,31.88956],"type":"Point"}
}