{
  "type": "Feature",
  "properties": {
    "gn:admin1_code":"3",
    "gn:asciiname":"Bandi Maira",
    "gn:country_code":"PK",
    "gn:dem":1790,
    "gn:feature_class":"P",
    "gn:feature_code":"PPL",
    "gn:name":"Bandi Maira",
    "gn:population":0,
    "gn:timezone":"Asia/Karachi",
    "iso:country":"PK",
    "name:und_x_variant":[
        "B\u0101ndi"
    ],
    "wof:name":"Bandi Maira",
    "wof:placetype":"locality"
},
  "geometry": {"coordinates":[73.32167,34.12233],"type":"Point"}
}