{
  "type": "Feature",
  "properties": {
    "gn:admin1_code":"4.0",
    "gn:asciiname":"Dhos Muhammad Din",
    "gn:country_code":"PK",
    "gn:dem":184,
    "gn:feature_class":"P",
    "gn:feature_code":"PPL",
    "gn:name":"Dhos Muhammad Din",
    "gn:population":0,
    "gn:timezone":"Asia/Karachi",
    "iso:country":"PK",
    "name:und_x_variant":[
        "Dhos"
    ],
    "wof:name":"Dhos Muhammad Din",
    "wof:placetype":"locality"
},
  "geometry": {"coordinates":[73.96207,30.92516],"type":"Point"}
}