{
  "type": "Feature",
  "properties": {
    "gn:admin1_code":"6",
    "gn:asciiname":"Pithorani",
    "gn:country_code":"PK",
    "gn:dem":358,
    "gn:feature_class":"P",
    "gn:feature_code":"PPL",
    "gn:name":"Pithorani",
    "gn:population":0,
    "gn:timezone":"Asia/Karachi",
    "iso:country":"PK",
    "name:und_x_variant":[
        "Pitthorani"
    ],
    "wof:name":"Pithorani",
    "wof:placetype":"locality"
},
  "geometry": {"coordinates":[74.16088000000001,32.93897],"type":"Point"}
}