{
  "type": "Feature",
  "properties": {
    "gn:admin1_code":"7.0",
    "gn:asciiname":"Achash",
    "gn:country_code":"PK",
    "gn:dem":1606,
    "gn:feature_class":"P",
    "gn:feature_code":"PPL",
    "gn:name":"Achash",
    "gn:population":0,
    "gn:timezone":"Asia/Karachi",
    "iso:country":"PK",
    "wof:name":"Achash",
    "wof:placetype":"locality"
},
  "geometry": {"coordinates":[74.28907,36.09234],"type":"Point"}
}