{
  "type": "Feature",
  "properties": {
    "gn:admin1_code":"4",
    "gn:asciiname":"Dur Kot",
    "gn:country_code":"PK",
    "gn:dem":138,
    "gn:feature_class":"P",
    "gn:feature_code":"PPL",
    "gn:name":"Dur Kot",
    "gn:population":0,
    "gn:timezone":"Asia/Karachi",
    "iso:country":"PK",
    "name:und_x_variant":[
        "Dhur Kot"
    ],
    "wof:name":"Dur Kot",
    "wof:placetype":"locality"
},
  "geometry": {"coordinates":[72.0089,30.82958],"type":"Point"}
}