{
  "type": "Feature",
  "properties": {
    "gn:admin1_code":"5",
    "gn:asciiname":"Fakharuddin Khosa",
    "gn:country_code":"PK",
    "gn:dem":59,
    "gn:feature_class":"P",
    "gn:feature_code":"PPL",
    "gn:name":"Fakharuddin Khosa",
    "gn:population":0,
    "gn:timezone":"Asia/Karachi",
    "iso:country":"PK",
    "name:und_x_variant":[
        "Jamal Khosa"
    ],
    "wof:name":"Fakharuddin Khosa",
    "wof:placetype":"locality"
},
  "geometry": {"coordinates":[68.41546,28.1381],"type":"Point"}
}