{
  "type": "Feature",
  "properties": {
    "gn:admin1_code":"4.0",
    "gn:asciiname":"Basti Chandian",
    "gn:country_code":"PK",
    "gn:dem":92,
    "gn:feature_class":"P",
    "gn:feature_code":"PPL",
    "gn:name":"Basti Chandian",
    "gn:population":0,
    "gn:timezone":"Asia/Karachi",
    "iso:country":"PK",
    "name:und_x_variant":[
        "Basti Ch\u0101ndi\u0101nw\u0101li"
    ],
    "wof:name":"Basti Chandian",
    "wof:placetype":"locality"
},
  "geometry": {"coordinates":[70.60708000000002,28.69861],"type":"Point"}
}