{
  "type": "Feature",
  "properties": {
    "gn:admin1_code":"3.0",
    "gn:asciiname":"Mira Khel Kallle",
    "gn:country_code":"PK",
    "gn:dem":542,
    "gn:feature_class":"P",
    "gn:feature_code":"PPL",
    "gn:name":"Mira Khel Kallle",
    "gn:population":0,
    "gn:timezone":"Asia/Karachi",
    "iso:country":"PK",
    "wof:name":"Mira Khel Kallle",
    "wof:placetype":"locality"
},
  "geometry": {"coordinates":[71.62013,33.17147],"type":"Point"}
}