{
  "type": "Feature",
  "properties": {
    "gn:admin1_code":"4",
    "gn:asciiname":"Chak Three -Fourteen Left",
    "gn:country_code":"PK",
    "gn:dem":155,
    "gn:feature_class":"P",
    "gn:feature_code":"PPL",
    "gn:name":"Chak Three -Fourteen Left",
    "gn:population":0,
    "gn:timezone":"Asia/Karachi",
    "iso:country":"PK",
    "name:und_x_variant":[
        "Chak Three-Fourteen L",
        "Nurpur"
    ],
    "wof:name":"Chak Three -Fourteen Left",
    "wof:placetype":"locality"
},
  "geometry": {"coordinates":[72.50794999999999,30.50555],"type":"Point"}
}