{
  "type": "Feature",
  "properties": {
    "gn:admin1_code":"3",
    "gn:asciiname":"Mandao",
    "gn:country_code":"PK",
    "gn:dem":1130,
    "gn:feature_class":"P",
    "gn:feature_code":"PPL",
    "gn:name":"Mandao",
    "gn:population":0,
    "gn:timezone":"Asia/Karachi",
    "iso:country":"PK",
    "name:und_x_variant":[
        "Mando"
    ],
    "wof:name":"Mandao",
    "wof:placetype":"locality"
},
  "geometry": {"coordinates":[72.72913,34.38447],"type":"Point"}
}