{
  "type": "Feature",
  "properties": {
    "gn:admin1_code":"3.0",
    "gn:asciiname":"Kharoi Payan",
    "gn:country_code":"PK",
    "gn:dem":2203,
    "gn:feature_class":"P",
    "gn:feature_code":"PPL",
    "gn:name":"Kharoi Payan",
    "gn:population":0,
    "gn:timezone":"Asia/Karachi",
    "iso:country":"PK",
    "wof:name":"Kharoi Payan",
    "wof:placetype":"locality"
},
  "geometry": {"coordinates":[71.89573,35.24963],"type":"Point"}
}