{
  "type": "Feature",
  "properties": {
    "gn:admin1_code":"2.0",
    "gn:asciiname":"Dilshad Zai",
    "gn:country_code":"PK",
    "gn:dem":2201,
    "gn:feature_class":"P",
    "gn:feature_code":"PPL",
    "gn:name":"Dilshad Zai",
    "gn:population":0,
    "gn:timezone":"Asia/Karachi",
    "iso:country":"PK",
    "wof:name":"Dilshad Zai",
    "wof:placetype":"locality"
},
  "geometry": {"coordinates":[66.61752,28.77703],"type":"Point"}
}