{
  "type": "Feature",
  "properties": {
    "gn:admin1_code":"6",
    "gn:asciiname":"Senth",
    "gn:country_code":"PK",
    "gn:dem":2421,
    "gn:feature_class":"P",
    "gn:feature_code":"PPL",
    "gn:name":"Senth",
    "gn:population":0,
    "gn:timezone":"Asia/Karachi",
    "iso:country":"PK",
    "name:und_x_variant":[
        "Sainsh"
    ],
    "wof:name":"Senth",
    "wof:placetype":"locality"
},
  "geometry": {"coordinates":[73.61963,34.35975999999999],"type":"Point"}
}