{
  "type": "Feature",
  "properties": {
    "gn:admin1_code":"3.0",
    "gn:asciiname":"Viranz",
    "gn:country_code":"PK",
    "gn:dem":3053,
    "gn:feature_class":"P",
    "gn:feature_code":"PPL",
    "gn:name":"Viranz",
    "gn:population":0,
    "gn:timezone":"Asia/Karachi",
    "iso:country":"PK",
    "wof:name":"Viranz",
    "wof:placetype":"locality"
},
  "geometry": {"coordinates":[72.94670000000001,36.75093],"type":"Point"}
}