{
  "type": "Feature",
  "properties": {
    "gn:admin1_code":"4",
    "gn:asciiname":"Basti Langah",
    "gn:country_code":"PK",
    "gn:dem":102,
    "gn:feature_class":"P",
    "gn:feature_code":"PPL",
    "gn:name":"Basti Langah",
    "gn:population":0,
    "gn:timezone":"Asia/Karachi",
    "iso:country":"PK",
    "name:und_x_variant":[
        "Harw\u0101la",
        "Lang\u0101h"
    ],
    "wof:name":"Basti Langah",
    "wof:placetype":"locality"
},
  "geometry": {"coordinates":[70.73786,29.34397],"type":"Point"}
}