{
  "type": "Feature",
  "properties": {
    "gn:admin1_code":"1.0",
    "gn:asciiname":"Ghoz Garhi",
    "gn:country_code":"PK",
    "gn:dem":1743,
    "gn:feature_class":"P",
    "gn:feature_code":"PPL",
    "gn:name":"Ghoz Garhi",
    "gn:population":0,
    "gn:timezone":"Asia/Karachi",
    "iso:country":"PK",
    "name:und_x_variant":[
        "Ghozgarhy"
    ],
    "wof:name":"Ghoz Garhi",
    "wof:placetype":"locality"
},
  "geometry": {"coordinates":[70.00681999999999,33.78084],"type":"Point"}
}