{
  "type": "Feature",
  "properties": {
    "gn:admin1_code":"2.0",
    "gn:asciiname":"Goth Haji Kabru",
    "gn:country_code":"PK",
    "gn:dem":51,
    "gn:feature_class":"P",
    "gn:feature_code":"PPL",
    "gn:name":"Goth Haji Kabru",
    "gn:population":0,
    "gn:timezone":"Asia/Karachi",
    "iso:country":"PK",
    "name:eng_x_preferred":[
        "Goth Haji Kabru"
    ],
    "wof:name":"Goth Haji Kabru",
    "wof:placetype":"locality"
},
  "geometry": {"coordinates":[66.75355999999999,25.22165],"type":"Point"}
}