{
  "type": "Feature",
  "properties": {
    "gn:admin1_code":"5.0",
    "gn:asciiname":"Sahab Khan Bahrani",
    "gn:country_code":"PK",
    "gn:dem":38,
    "gn:feature_class":"P",
    "gn:feature_code":"PPL",
    "gn:name":"Sahab Khan Bahrani",
    "gn:population":0,
    "gn:timezone":"Asia/Karachi",
    "iso:country":"PK",
    "wof:name":"Sahab Khan Bahrani",
    "wof:placetype":"locality"
},
  "geometry": {"coordinates":[68.31909,26.27513],"type":"Point"}
}