{
  "type": "Feature",
  "properties": {
    "gn:admin1_code":"5.0",
    "gn:asciiname":"Goth Piaro Khan Shar",
    "gn:country_code":"PK",
    "gn:dem":46,
    "gn:feature_class":"P",
    "gn:feature_code":"PPL",
    "gn:name":"Goth Piaro Khan Shar",
    "gn:population":0,
    "gn:timezone":"Asia/Karachi",
    "iso:country":"PK",
    "name:und_x_variant":[
        "H\u0101ji P\u012br Muhammad R\u0101jpar"
    ],
    "wof:name":"Goth Piaro Khan Shar",
    "wof:placetype":"locality"
},
  "geometry": {"coordinates":[68.32886999999999,26.73767],"type":"Point"}
}