{
  "type": "Feature",
  "properties": {
    "gn:admin1_code":"7.0",
    "gn:asciiname":"Hlabpat",
    "gn:country_code":"PK",
    "gn:dem":2346,
    "gn:feature_class":"P",
    "gn:feature_code":"PPL",
    "gn:name":"Hlabpat",
    "gn:population":0,
    "gn:timezone":"Asia/Karachi",
    "iso:country":"PK",
    "wof:name":"Hlabpat",
    "wof:placetype":"locality"
},
  "geometry": {"coordinates":[75.14785000000001,35.59531],"type":"Point"}
}