{
  "type": "Feature",
  "properties": {
    "gn:admin1_code":"4",
    "gn:asciiname":"Chak One Hundred Fifty-three Rakh Branch",
    "gn:country_code":"PK",
    "gn:dem":193,
    "gn:feature_class":"P",
    "gn:feature_code":"PPL",
    "gn:name":"Chak One Hundred Fifty-three Rakh Branch",
    "gn:population":0,
    "gn:timezone":"Asia/Karachi",
    "iso:country":"PK",
    "name:und_x_variant":[
        "Chak One Hundred Fifty-Three",
        "Daska",
        "Chak One Hundred Fifty-three Rakh Branch"
    ],
    "wof:name":"Chak One Hundred Fifty-three Rakh Branch",
    "wof:placetype":"locality"
},
  "geometry": {"coordinates":[73.23385,31.62168],"type":"Point"}
}