{
  "type": "Feature",
  "properties": {
    "gn:admin1_code":"6",
    "gn:asciiname":"Malni",
    "gn:country_code":"PK",
    "gn:dem":856,
    "gn:feature_class":"P",
    "gn:feature_code":"PPL",
    "gn:name":"Malni",
    "gn:population":0,
    "gn:timezone":"Asia/Karachi",
    "iso:country":"PK",
    "wof:name":"Malni",
    "wof:placetype":"locality"
},
  "geometry": {"coordinates":[74.23704000000002,33.0284],"type":"Point"}
}