{
  "type": "Feature",
  "properties": {
    "gn:admin1_code":"6",
    "gn:asciiname":"Malni",
    "gn:country_code":"PK",
    "gn:dem":856,
    "gn:feature_class":"P",
    "gn:feature_code":"PPL",
    "gn:name":"Malni",
    "gn:population":0,
    "gn:timezone":"Asia/Karachi",
    "iso:country":"PK",
    "name:bos_x_preferred":[
        "Malni"
    ],
    "name:hrv_x_preferred":[
        "Malni"
    ],
    "name:nld_x_preferred":[
        "Malni"
    ],
    "name:pol_x_preferred":[
        "Malni"
    ],
    "name:ron_x_preferred":[
        "Malni"
    ],
    "name:slv_x_preferred":[
        "Malni"
    ],
    "name:ukr_x_preferred":[
        "\u041c\u0430\u043b\u043d\u0456"
    ],
    "wof:name":"Malni",
    "wof:placetype":"locality"
},
  "geometry": {"coordinates":[74.23704000000002,33.0284],"type":"Point"}
}