{
  "type": "Feature",
  "properties": {
    "gn:admin1_code":"2.0",
    "gn:asciiname":"Shah Jahan Kili",
    "gn:country_code":"PK",
    "gn:dem":1544,
    "gn:feature_class":"P",
    "gn:feature_code":"PPL",
    "gn:name":"Shah Jahan Kili",
    "gn:population":0,
    "gn:timezone":"Asia/Karachi",
    "iso:country":"PK",
    "wof:name":"Shah Jahan Kili",
    "wof:placetype":"locality"
},
  "geometry": {"coordinates":[66.96298,30.38702],"type":"Point"}
}