{
  "type": "Feature",
  "properties": {
    "gn:admin1_code":"04",
    "gn:asciiname":"Uch Gul Imam",
    "gn:country_code":"PK",
    "gn:dem":154,
    "gn:feature_class":"P",
    "gn:feature_code":"PPL",
    "gn:name":"Uch Gul Imam",
    "gn:population":0,
    "gn:timezone":"Asia/Karachi",
    "iso:country":"PK",
    "name:und_x_variant":[
        "Uch"
    ],
    "wof:name":"Uch Gul Imam",
    "wof:placetype":"locality"
},
  "geometry": {"coordinates":[71.97509000000002,31.13201],"type":"Point"}
}