{
  "type": "Feature",
  "properties": {
    "gn:admin1_code":"3",
    "gn:asciiname":"Jastar",
    "gn:country_code":"PK",
    "gn:dem":1930,
    "gn:feature_class":"P",
    "gn:feature_code":"PPL",
    "gn:name":"Jastar",
    "gn:population":0,
    "gn:timezone":"Asia/Karachi",
    "iso:country":"PK",
    "name:und_x_variant":[
        "Jasta"
    ],
    "wof:name":"Jastar",
    "wof:placetype":"locality"
},
  "geometry": {"coordinates":[73.36178000000002,34.10727],"type":"Point"}
}