{
  "type": "Feature",
  "properties": {
    "gn:admin1_code":"3",
    "gn:asciiname":"Kuthera",
    "gn:country_code":"PK",
    "gn:dem":908,
    "gn:feature_class":"P",
    "gn:feature_code":"PPL",
    "gn:name":"Kuthera",
    "gn:population":0,
    "gn:timezone":"Asia/Karachi",
    "iso:country":"PK",
    "wof:name":"Kuthera",
    "wof:placetype":"locality"
},
  "geometry": {"coordinates":[73.01543000000002,34.17747],"type":"Point"}
}