{
  "type": "Feature",
  "properties": {
    "gn:admin1_code":"4",
    "gn:asciiname":"Chak One Hundred Two",
    "gn:country_code":"PK",
    "gn:dem":134,
    "gn:feature_class":"P",
    "gn:feature_code":"PPL",
    "gn:name":"Chak One Hundred Two",
    "gn:population":0,
    "gn:timezone":"Asia/Karachi",
    "iso:country":"PK",
    "name:und_x_variant":[
        "Zafar\u0101b\u0101d"
    ],
    "wof:name":"Chak One Hundred Two",
    "wof:placetype":"locality"
},
  "geometry": {"coordinates":[71.91531999999999,30.08578],"type":"Point"}
}