{
  "type": "Feature",
  "properties": {
    "gn:admin1_code":"4",
    "gn:asciiname":"Ghaffarpur",
    "gn:country_code":"PK",
    "gn:dem":151,
    "gn:feature_class":"P",
    "gn:feature_code":"PPL",
    "gn:name":"Ghaff\u0101rpur",
    "gn:population":0,
    "gn:timezone":"Asia/Karachi",
    "iso:country":"PK",
    "wof:name":"Ghaffarpur",
    "wof:placetype":"locality"
},
  "geometry": {"coordinates":[72.84721999999999,30.21944],"type":"Point"}
}