{
  "type": "Feature",
  "properties": {
    "gn:admin1_code":"4",
    "gn:asciiname":"Chak Eighty-three Ten Right",
    "gn:country_code":"PK",
    "gn:dem":142,
    "gn:feature_class":"P",
    "gn:feature_code":"PPL",
    "gn:name":"Chak Eighty-three Ten Right",
    "gn:population":0,
    "gn:timezone":"Asia/Karachi",
    "iso:country":"PK",
    "name:und_x_variant":[
        "Chak Eighty-Three"
    ],
    "wof:name":"Chak Eighty-three Ten Right",
    "wof:placetype":"locality"
},
  "geometry": {"coordinates":[71.99876999999999,30.30758],"type":"Point"}
}