{
  "type": "Feature",
  "properties": {
    "gn:admin1_code":"2.0",
    "gn:asciiname":"Wali",
    "gn:country_code":"PK",
    "gn:dem":1978,
    "gn:feature_class":"P",
    "gn:feature_code":"PPL",
    "gn:name":"Wali",
    "gn:population":0,
    "gn:timezone":"Asia/Karachi",
    "iso:country":"PK",
    "wof:name":"Wali",
    "wof:placetype":"locality"
},
  "geometry": {"coordinates":[69.93924,31.48596],"type":"Point"}
}