{
  "type": "Feature",
  "properties": {
    "gn:admin1_code":"5",
    "gn:asciiname":"Jafar Sotairo",
    "gn:country_code":"PK",
    "gn:dem":49,
    "gn:feature_class":"P",
    "gn:feature_code":"PPL",
    "gn:name":"Jafar Sotairo",
    "gn:population":0,
    "gn:timezone":"Asia/Karachi",
    "iso:country":"PK",
    "name:und_x_variant":[
        "Goth Jafar Unar"
    ],
    "wof:name":"Jafar Sotairo",
    "wof:placetype":"locality"
},
  "geometry": {"coordinates":[68.52228000000001,27.05367],"type":"Point"}
}