{
  "type": "Feature",
  "properties": {
    "gn:admin1_code":"2.0",
    "gn:asciiname":"Bado Kushta",
    "gn:country_code":"PK",
    "gn:dem":1604,
    "gn:feature_class":"P",
    "gn:feature_code":"PPL",
    "gn:name":"Bado Kushta",
    "gn:population":0,
    "gn:timezone":"Asia/Karachi",
    "iso:country":"PK",
    "name:und_x_variant":[
        "Kucha Bado Kuahta"
    ],
    "wof:name":"Bado Kushta",
    "wof:placetype":"locality"
},
  "geometry": {"coordinates":[66.45195,28.33762],"type":"Point"}
}