{
  "type": "Feature",
  "properties": {
    "gn:admin1_code":"3.0",
    "gn:asciiname":"Durial",
    "gn:country_code":"PK",
    "gn:dem":395,
    "gn:feature_class":"P",
    "gn:feature_code":"PPL",
    "gn:name":"Durial",
    "gn:population":0,
    "gn:timezone":"Asia/Karachi",
    "iso:country":"PK",
    "wof:name":"Durial",
    "wof:placetype":"locality"
},
  "geometry": {"coordinates":[72.03409000000001,34.38747],"type":"Point"}
}