{
  "type": "Feature",
  "properties": {
    "gn:admin1_code":"5",
    "gn:asciiname":"Goth Chhorun",
    "gn:country_code":"PK",
    "gn:dem":16,
    "gn:feature_class":"P",
    "gn:feature_code":"PPL",
    "gn:name":"Goth Chhorun",
    "gn:population":0,
    "gn:timezone":"Asia/Karachi",
    "iso:country":"PK",
    "name:eng_x_preferred":[
        "Goth Chhorun"
    ],
    "wof:name":"Goth Chhorun",
    "wof:placetype":"locality"
},
  "geometry": {"coordinates":[68.30122,25.00719],"type":"Point"}
}