{
  "type": "Feature",
  "properties": {
    "gn:admin1_code":"4",
    "gn:asciiname":"Dhok Banth",
    "gn:country_code":"PK",
    "gn:dem":425,
    "gn:feature_class":"P",
    "gn:feature_code":"PPL",
    "gn:name":"Dhok Banth",
    "gn:population":0,
    "gn:timezone":"Asia/Karachi",
    "iso:country":"PK",
    "name:und_x_variant":[
        "Dhok Bant"
    ],
    "wof:name":"Dhok Banth",
    "wof:placetype":"locality"
},
  "geometry": {"coordinates":[73.23294,32.86004000000001],"type":"Point"}
}