{
  "type": "Feature",
  "properties": {
    "gn:admin1_code":"4.0",
    "gn:asciiname":"Chak One Hundred Seven NP",
    "gn:country_code":"PK",
    "gn:dem":92,
    "gn:feature_class":"P",
    "gn:feature_code":"PPL",
    "gn:name":"Chak One Hundred Seven NP",
    "gn:population":0,
    "gn:timezone":"Asia/Karachi",
    "iso:country":"PK",
    "name:urd_x_preferred":[
        "Chak One Hundred - seven"
    ],
    "wof:name":"Chak One Hundred Seven NP",
    "wof:placetype":"locality"
},
  "geometry": {"coordinates":[70.70076999999998,28.79257],"type":"Point"}
}