{
  "type": "Feature",
  "properties": {
    "gn:admin1_code":"4",
    "gn:asciiname":"Naqshi",
    "gn:country_code":"PK",
    "gn:dem":200,
    "gn:feature_class":"P",
    "gn:feature_code":"PPL",
    "gn:name":"Naqshi",
    "gn:population":0,
    "gn:timezone":"Asia/Karachi",
    "iso:country":"PK",
    "name:und_x_variant":[
        "Nakshi"
    ],
    "wof:name":"Naqshi",
    "wof:placetype":"locality"
},
  "geometry": {"coordinates":[73.05710000000001,32.49728],"type":"Point"}
}