{
  "type": "Feature",
  "properties": {
    "gn:admin1_code":"02",
    "gn:asciiname":"Miski",
    "gn:country_code":"PK",
    "gn:dem":28,
    "gn:feature_class":"P",
    "gn:feature_code":"PPL",
    "gn:name":"Miski",
    "gn:population":0,
    "gn:timezone":"Asia/Karachi",
    "iso:country":"PK",
    "name:fas_x_preferred":[
        "\u0645\u0633\u06a9\u06cc"
    ],
    "wof:name":"Miski",
    "wof:placetype":"locality"
},
  "geometry": {"coordinates":[63.53278,25.40028],"type":"Point"}
}