{
  "type": "Feature",
  "properties": {
    "gn:admin1_code":"2.0",
    "gn:asciiname":"Garang Kili",
    "gn:country_code":"PK",
    "gn:dem":1314,
    "gn:feature_class":"P",
    "gn:feature_code":"PPL",
    "gn:name":"Garang Kili",
    "gn:population":0,
    "gn:timezone":"Asia/Karachi",
    "iso:country":"PK",
    "wof:name":"Garang Kili",
    "wof:placetype":"locality"
},
  "geometry": {"coordinates":[69.99729000000001,31.43622],"type":"Point"}
}