{
  "type": "Feature",
  "properties": {
    "gn:admin1_code":"3",
    "gn:asciiname":"Mahavelian",
    "gn:country_code":"PK",
    "gn:dem":1265,
    "gn:feature_class":"P",
    "gn:feature_code":"PPL",
    "gn:name":"Mahavelian",
    "gn:population":0,
    "gn:timezone":"Asia/Karachi",
    "iso:country":"PK",
    "wof:name":"Mahavelian",
    "wof:placetype":"locality"
},
  "geometry": {"coordinates":[73.19985,34.25527],"type":"Point"}
}