{
  "type": "Feature",
  "properties": {
    "gn:admin1_code":"4.0",
    "gn:asciiname":"Dhok Ghazian",
    "gn:country_code":"PK",
    "gn:dem":470,
    "gn:feature_class":"P",
    "gn:feature_code":"PPL",
    "gn:name":"Dhok Ghazian",
    "gn:population":0,
    "gn:timezone":"Asia/Karachi",
    "iso:country":"PK",
    "name:eng_x_preferred":[
        "Dhok Gh\u0101zi"
    ],
    "wof:name":"Dhok Ghazian",
    "wof:placetype":"locality"
},
  "geometry": {"coordinates":[72.99614,33.24318],"type":"Point"}
}