{
  "type": "Feature",
  "properties": {
    "gn:admin1_code":"4",
    "gn:asciiname":"Basti Musani",
    "gn:country_code":"PK",
    "gn:dem":88,
    "gn:feature_class":"P",
    "gn:feature_code":"PPL",
    "gn:name":"Basti Musani",
    "gn:population":0,
    "gn:timezone":"Asia/Karachi",
    "iso:country":"PK",
    "name:und_x_variant":[
        "Basti Mas\u0101ni\u0101n"
    ],
    "wof:name":"Basti Musani",
    "wof:placetype":"locality"
},
  "geometry": {"coordinates":[70.62153000000001,28.60688],"type":"Point"}
}