{
  "type": "Feature",
  "properties": {
    "gn:admin1_code":"4",
    "gn:asciiname":"Chak Six Hundred Fifty-five -Six",
    "gn:country_code":"PK",
    "gn:dem":199,
    "gn:feature_class":"P",
    "gn:feature_code":"PPL",
    "gn:name":"Chak Six Hundred Fifty-five -Six",
    "gn:population":0,
    "gn:timezone":"Asia/Karachi",
    "iso:country":"PK",
    "name:und_x_variant":[
        "Chak Six"
    ],
    "wof:name":"Chak Six Hundred Fifty-five -Six",
    "wof:placetype":"locality"
},
  "geometry": {"coordinates":[73.55009,31.43453],"type":"Point"}
}