{
  "type": "Feature",
  "properties": {
    "gn:admin1_code":"4",
    "gn:asciiname":"Qadar Bakhshwala",
    "gn:country_code":"PK",
    "gn:dem":141,
    "gn:feature_class":"P",
    "gn:feature_code":"PPL",
    "gn:name":"Qadar Bakhshwala",
    "gn:population":0,
    "gn:timezone":"Asia/Karachi",
    "iso:country":"PK",
    "wof:name":"Qadar Bakhshwala",
    "wof:placetype":"locality"
},
  "geometry": {"coordinates":[71.10265,30.68829],"type":"Point"}
}