{
  "type": "Feature",
  "properties": {
    "gn:admin1_code":"04",
    "gn:asciiname":"Kaltea",
    "gn:country_code":"PK",
    "gn:dem":899,
    "gn:feature_class":"P",
    "gn:feature_code":"PPL",
    "gn:name":"Kaltea",
    "gn:population":0,
    "gn:timezone":"Asia/Karachi",
    "iso:country":"PK",
    "name:und_x_variant":[
        "Kulteha",
        "Kultea",
        "Kaltea"
    ],
    "wof:name":"Kaltea",
    "wof:placetype":"locality"
},
  "geometry": {"coordinates":[73.55745,33.63736],"type":"Point"}
}