{
  "type": "Feature",
  "properties": {
    "gn:admin1_code":"2.0",
    "gn:asciiname":"Hazoor Bakhsh Gis",
    "gn:country_code":"PK",
    "gn:dem":1430,
    "gn:feature_class":"P",
    "gn:feature_code":"PPL",
    "gn:name":"Hazoor Bakhsh Gis",
    "gn:population":0,
    "gn:timezone":"Asia/Karachi",
    "iso:country":"PK",
    "wof:name":"Hazoor Bakhsh Gis",
    "wof:placetype":"locality"
},
  "geometry": {"coordinates":[63.92131,29.28924],"type":"Point"}
}