{
  "type": "Feature",
  "properties": {
    "gn:admin1_code":"2.0",
    "gn:asciiname":"Colo Kano",
    "gn:country_code":"PK",
    "gn:dem":2294,
    "gn:feature_class":"P",
    "gn:feature_code":"PPL",
    "gn:name":"Colo Kano",
    "gn:population":0,
    "gn:timezone":"Asia/Karachi",
    "iso:country":"PK",
    "name:und_x_variant":[
        "Kano"
    ],
    "wof:name":"Colo Kano",
    "wof:placetype":"locality"
},
  "geometry": {"coordinates":[67.64029000000001,30.50335],"type":"Point"}
}