{
  "type": "Feature",
  "properties": {
    "gn:admin1_code":"2.0",
    "gn:asciiname":"Gargoji",
    "gn:country_code":"PK",
    "gn:dem":947,
    "gn:feature_class":"P",
    "gn:feature_code":"PPL",
    "gn:name":"Gargoji",
    "gn:population":0,
    "gn:timezone":"Asia/Karachi",
    "iso:country":"PK",
    "wof:name":"Gargoji",
    "wof:placetype":"locality"
},
  "geometry": {"coordinates":[70.17085,30.80404],"type":"Point"}
}