{
  "type": "Feature",
  "properties": {
    "gn:admin1_code":"4.0",
    "gn:asciiname":"Rohri",
    "gn:country_code":"PK",
    "gn:dem":247,
    "gn:feature_class":"P",
    "gn:feature_code":"PPL",
    "gn:name":"Rohri",
    "gn:population":0,
    "gn:timezone":"Asia/Karachi",
    "iso:country":"PK",
    "name:ceb_x_preferred":[
        "Rohri"
    ],
    "name:eng_x_preferred":[
        "Rohri"
    ],
    "name:fas_x_preferred":[
        "\u0631\u0648\u0647\u0631\u06cc"
    ],
    "name:fra_x_preferred":[
        "Rohri"
    ],
    "name:hin_x_preferred":[
        "\u0930\u094b\u0939\u0921\u093c\u0940"
    ],
    "name:snd_x_preferred":[
        "\u0631\u0648\u0647\u0699\u064a"
    ],
    "name:spa_x_preferred":[
        "Rohri"
    ],
    "name:tgl_x_preferred":[
        "Rohri"
    ],
    "name:und_x_variant":[
        "L\u0101khi Bher"
    ],
    "name:urd_x_preferred":[
        "\u0631\u0648\u06c1\u0691\u06cc"
    ],
    "wof:name":"Rohri",
    "wof:placetype":"locality"
},
  "geometry": {"coordinates":[70.41651,31.17255],"type":"Point"}
}