{
  "type": "Feature",
  "properties": {
    "gn:admin1_code":"6",
    "gn:asciiname":"Banatian",
    "gn:country_code":"PK",
    "gn:dem":963,
    "gn:feature_class":"P",
    "gn:feature_code":"PPL",
    "gn:name":"Banatian",
    "gn:population":0,
    "gn:timezone":"Asia/Kolkata",
    "iso:country":"PK",
    "wof:name":"Banatian",
    "wof:placetype":"locality"
},
  "geometry": {"coordinates":[74.0663,33.15785],"type":"Point"}
}