{
  "type": "Feature",
  "properties": {
    "gn:admin1_code":"4",
    "gn:asciiname":"Chak Sada",
    "gn:country_code":"PK",
    "gn:dem":224,
    "gn:feature_class":"P",
    "gn:feature_code":"PPL",
    "gn:name":"Chak Sada",
    "gn:population":0,
    "gn:timezone":"Asia/Karachi",
    "iso:country":"PK",
    "wof:name":"Chak Sada",
    "wof:placetype":"locality"
},
  "geometry": {"coordinates":[74.04826,32.24466],"type":"Point"}
}