{
  "type": "Feature",
  "properties": {
    "gn:admin1_code":"04",
    "gn:asciiname":"Ziarat",
    "gn:country_code":"PK",
    "gn:dem":289,
    "gn:feature_class":"P",
    "gn:feature_code":"PPL",
    "gn:name":"Ziarat",
    "gn:population":0,
    "gn:timezone":"Asia/Karachi",
    "iso:country":"PK",
    "wof:name":"Ziarat",
    "wof:placetype":"locality"
},
  "geometry": {"coordinates":[71.89805,33.42382],"type":"Point"}
}