{
  "type": "Feature",
  "properties": {
    "gn:admin1_code":"5",
    "gn:asciiname":"Gul Muhammad Baloch",
    "gn:country_code":"PK",
    "gn:dem":21,
    "gn:feature_class":"P",
    "gn:feature_code":"PPL",
    "gn:name":"Gul Muhammad Baloch",
    "gn:population":0,
    "gn:timezone":"Asia/Karachi",
    "iso:country":"PK",
    "name:eng_x_preferred":[
        "Gul Muhammad Baloch"
    ],
    "wof:name":"Gul Muhammad Baloch",
    "wof:placetype":"locality"
},
  "geometry": {"coordinates":[68.43257,25.4045],"type":"Point"}
}