{
  "type": "Feature",
  "properties": {
    "gn:admin1_code":"4",
    "gn:asciiname":"Chak Two Hundred Sixty-seven Thal Development Authority",
    "gn:country_code":"PK",
    "gn:dem":153,
    "gn:feature_class":"P",
    "gn:feature_code":"PPL",
    "gn:name":"Chak Two Hundred Sixty-seven Thal Development Authority",
    "gn:population":0,
    "gn:timezone":"Asia/Karachi",
    "iso:country":"PK",
    "name:und_x_variant":[
        "Chak 267 TDA",
        "Chak Two Hundred Sixty-Seven TDA",
        "Chak Two Hundred Sixty-seven Thal Development Authority"
    ],
    "wof:name":"Chak Two Hundred Sixty-seven Thal Development Authority",
    "wof:placetype":"locality"
},
  "geometry": {"coordinates":[71.14641,31.09533],"type":"Point"}
}