{
  "type": "Feature",
  "properties": {
    "gn:admin1_code":"5.0",
    "gn:asciiname":"Goth Allah Bakhsh",
    "gn:country_code":"PK",
    "gn:dem":24,
    "gn:feature_class":"P",
    "gn:feature_code":"PPL",
    "gn:name":"Goth Allah Bakhsh",
    "gn:population":0,
    "gn:timezone":"Asia/Karachi",
    "iso:country":"PK",
    "name:eng_x_preferred":[
        "Goth Ali Bakhsh"
    ],
    "wof:name":"Goth Allah Bakhsh",
    "wof:placetype":"locality"
},
  "geometry": {"coordinates":[68.35365999999999,25.27921],"type":"Point"}
}