{
  "type": "Feature",
  "properties": {
    "gn:admin1_code":"4",
    "gn:asciiname":"Moshewala",
    "gn:country_code":"PK",
    "gn:dem":141,
    "gn:feature_class":"P",
    "gn:feature_code":"PPL",
    "gn:name":"Moshewala",
    "gn:population":0,
    "gn:timezone":"Asia/Karachi",
    "iso:country":"PK",
    "name:und_x_variant":[
        "Musew\u0101la"
    ],
    "wof:name":"Moshewala",
    "wof:placetype":"locality"
},
  "geometry": {"coordinates":[70.71723,30.56027000000001],"type":"Point"}
}