{
  "type": "Feature",
  "properties": {
    "gn:admin1_code":"3.0",
    "gn:asciiname":"Barlan",
    "gn:country_code":"PK",
    "gn:dem":394,
    "gn:feature_class":"P",
    "gn:feature_code":"PPL",
    "gn:name":"Barlan",
    "gn:population":0,
    "gn:timezone":"Asia/Karachi",
    "iso:country":"PK",
    "name:eng_x_preferred":[
        "Sw\u0101tu Kalle"
    ],
    "wof:name":"Barlan",
    "wof:placetype":"locality"
},
  "geometry": {"coordinates":[71.6602,34.3493],"type":"Point"}
}