{
  "type": "Feature",
  "properties": {
    "gn:admin1_code":"2.0",
    "gn:asciiname":"Nargasi Kili",
    "gn:country_code":"PK",
    "gn:dem":1420,
    "gn:feature_class":"P",
    "gn:feature_code":"PPL",
    "gn:name":"Nargasi Kili",
    "gn:population":0,
    "gn:timezone":"Asia/Karachi",
    "iso:country":"PK",
    "wof:name":"Nargasi Kili",
    "wof:placetype":"locality"
},
  "geometry": {"coordinates":[69.60374,30.35863],"type":"Point"}
}