{
  "type": "Feature",
  "properties": {
    "gn:admin1_code":"04",
    "gn:asciiname":"Muhammad Shah",
    "gn:country_code":"PK",
    "gn:dem":138,
    "gn:feature_class":"P",
    "gn:feature_code":"PPL",
    "gn:name":"Muhammad Shah",
    "gn:population":0,
    "gn:timezone":"Asia/Karachi",
    "iso:country":"PK",
    "wof:name":"Muhammad Shah",
    "wof:placetype":"locality"
},
  "geometry": {"coordinates":[72.26748000000001,29.91621],"type":"Point"}
}