{
  "type": "Feature",
  "properties": {
    "gn:admin1_code":"4",
    "gn:asciiname":"Naruke Par",
    "gn:country_code":"PK",
    "gn:dem":195,
    "gn:feature_class":"P",
    "gn:feature_code":"PPL",
    "gn:name":"Naruke Par",
    "gn:population":0,
    "gn:timezone":"Asia/Karachi",
    "iso:country":"PK",
    "name:und_x_variant":[
        "N\u0101ru ke P\u0101r"
    ],
    "wof:name":"Naruke Par",
    "wof:placetype":"locality"
},
  "geometry": {"coordinates":[73.76984,31.24337],"type":"Point"}
}