{
  "type": "Feature",
  "properties": {
    "gn:admin1_code":"1.0",
    "gn:asciiname":"Bura",
    "gn:country_code":"PK",
    "gn:dem":1842,
    "gn:feature_class":"P",
    "gn:feature_code":"PPL",
    "gn:name":"Bura",
    "gn:population":0,
    "gn:timezone":"Asia/Karachi",
    "iso:country":"PK",
    "wof:name":"Bura",
    "wof:placetype":"locality"
},
  "geometry": {"coordinates":[70.86924999999999,33.86483],"type":"Point"}
}