{
  "type": "Feature",
  "properties": {
    "gn:admin1_code":"3.0",
    "gn:asciiname":"Dunisari Shal",
    "gn:country_code":"PK",
    "gn:dem":2682,
    "gn:feature_class":"P",
    "gn:feature_code":"PPL",
    "gn:name":"Dunisari Shal",
    "gn:population":0,
    "gn:timezone":"Asia/Karachi",
    "iso:country":"PK",
    "name:eng_x_preferred":[
        "D\u016bn\u012bsari Sh\u0101l"
    ],
    "wof:name":"Dunisari Shal",
    "wof:placetype":"locality"
},
  "geometry": {"coordinates":[71.83779,35.75189],"type":"Point"}
}