{
  "type": "Feature",
  "properties": {
    "gn:admin1_code":"3",
    "gn:asciiname":"Tundi Dheri",
    "gn:country_code":"PK",
    "gn:dem":1086,
    "gn:feature_class":"P",
    "gn:feature_code":"PPL",
    "gn:name":"Tundi Dheri",
    "gn:population":0,
    "gn:timezone":"Asia/Karachi",
    "iso:country":"PK",
    "wof:name":"Tundi Dheri",
    "wof:placetype":"locality"
},
  "geometry": {"coordinates":[73.24866999999998,34.10657],"type":"Point"}
}