{
  "type": "Feature",
  "properties": {
    "gn:admin1_code":"5.0",
    "gn:asciiname":"Rahim Bakhsh Shar",
    "gn:country_code":"PK",
    "gn:dem":73,
    "gn:feature_class":"P",
    "gn:feature_code":"PPL",
    "gn:name":"Rahim Bakhsh Shar",
    "gn:population":0,
    "gn:timezone":"Asia/Karachi",
    "iso:country":"PK",
    "wof:name":"Rahim Bakhsh Shar",
    "wof:placetype":"locality"
},
  "geometry": {"coordinates":[69.70090999999999,28.15457],"type":"Point"}
}