{
  "type": "Feature",
  "properties": {
    "gn:admin1_code":"5.0",
    "gn:asciiname":"Pinnu Baran",
    "gn:country_code":"PK",
    "gn:dem":8,
    "gn:feature_class":"P",
    "gn:feature_code":"PPL",
    "gn:name":"Pinnu Baran",
    "gn:population":0,
    "gn:timezone":"Asia/Karachi",
    "iso:country":"PK",
    "name:eng_x_preferred":[
        "Pinnu Baran"
    ],
    "wof:name":"Pinnu Baran",
    "wof:placetype":"locality"
},
  "geometry": {"coordinates":[68.13112,24.59504],"type":"Point"}
}