{
  "type": "Feature",
  "properties": {
    "gn:admin1_code":"3",
    "gn:asciiname":"Malalai",
    "gn:country_code":"PK",
    "gn:dem":1277,
    "gn:feature_class":"P",
    "gn:feature_code":"PPL",
    "gn:name":"Malalai",
    "gn:population":0,
    "gn:timezone":"Asia/Karachi",
    "iso:country":"PK",
    "wof:name":"Malalai",
    "wof:placetype":"locality"
},
  "geometry": {"coordinates":[72.46651,34.76845],"type":"Point"}
}