{
  "type": "Feature",
  "properties": {
    "gn:admin1_code":"4.0",
    "gn:asciiname":"Khan Garli",
    "gn:country_code":"PK",
    "gn:dem":266,
    "gn:feature_class":"P",
    "gn:feature_code":"PPL",
    "gn:name":"Khan Garli",
    "gn:population":0,
    "gn:timezone":"Asia/Karachi",
    "iso:country":"PK",
    "wof:name":"Khan Garli",
    "wof:placetype":"locality"
},
  "geometry": {"coordinates":[74.80107,32.41449],"type":"Point"}
}