{
  "type": "Feature",
  "properties": {
    "gn:admin1_code":"4.0",
    "gn:asciiname":"Basti Baqirpur",
    "gn:country_code":"PK",
    "gn:dem":137,
    "gn:feature_class":"P",
    "gn:feature_code":"PPL",
    "gn:name":"Basti Baqirpur",
    "gn:population":0,
    "gn:timezone":"Asia/Karachi",
    "iso:country":"PK",
    "name:und_x_variant":[
        "B\u0101qirpur"
    ],
    "wof:name":"Basti Baqirpur",
    "wof:placetype":"locality"
},
  "geometry": {"coordinates":[71.88965,30.56585],"type":"Point"}
}