{
  "type": "Feature",
  "properties": {
    "gn:admin1_code":"5.0",
    "gn:asciiname":"Goth Hassan Shah",
    "gn:country_code":"PK",
    "gn:dem":4,
    "gn:feature_class":"P",
    "gn:feature_code":"PPL",
    "gn:name":"Goth Hassan Shah",
    "gn:population":0,
    "gn:timezone":"Asia/Karachi",
    "iso:country":"PK",
    "name:und_x_variant":[
        "Goth Ras\u016bl Sh\u0101h"
    ],
    "wof:name":"Goth Hassan Shah",
    "wof:placetype":"locality"
},
  "geometry": {"coordinates":[68.14269,24.1928],"type":"Point"}
}