{
  "type": "Feature",
  "properties": {
    "gn:admin1_code":"2",
    "gn:asciiname":"Wazilun China",
    "gn:country_code":"PK",
    "gn:dem":1769,
    "gn:feature_class":"P",
    "gn:feature_code":"PPL",
    "gn:name":"Wazilun China",
    "gn:population":0,
    "gn:timezone":"Asia/Karachi",
    "iso:country":"PK",
    "name:und_x_variant":[
        "Wazilun Ch\u012bna"
    ],
    "wof:name":"Wazilun China",
    "wof:placetype":"locality"
},
  "geometry": {"coordinates":[68.21911,30.22939],"type":"Point"}
}