{
  "type": "Feature",
  "properties": {
    "gn:admin1_code":"4.0",
    "gn:asciiname":"Kikranwala",
    "gn:country_code":"PK",
    "gn:dem":110,
    "gn:feature_class":"P",
    "gn:feature_code":"PPL",
    "gn:name":"Kikranwala",
    "gn:population":0,
    "gn:timezone":"Asia/Karachi",
    "iso:country":"PK",
    "name:und_x_variant":[
        "Garangw\u0101la"
    ],
    "wof:name":"Kikranwala",
    "wof:placetype":"locality"
},
  "geometry": {"coordinates":[71.28748,29.68532],"type":"Point"}
}