{
  "type": "Feature",
  "properties": {
    "gn:admin1_code":"3.0",
    "gn:asciiname":"Topak Kas",
    "gn:country_code":"PK",
    "gn:dem":413,
    "gn:feature_class":"P",
    "gn:feature_code":"PPL",
    "gn:name":"Topak Kas",
    "gn:population":0,
    "gn:timezone":"Asia/Karachi",
    "iso:country":"PK",
    "wof:name":"Topak Kas",
    "wof:placetype":"locality"
},
  "geometry": {"coordinates":[70.51289,33.01435],"type":"Point"}
}