{
  "type": "Feature",
  "properties": {
    "gn:admin1_code":"4.0",
    "gn:asciiname":"Nakka",
    "gn:country_code":"PK",
    "gn:dem":600,
    "gn:feature_class":"P",
    "gn:feature_code":"PPL",
    "gn:name":"Nakka",
    "gn:population":0,
    "gn:timezone":"Asia/Karachi",
    "iso:country":"PK",
    "wof:name":"Nakka",
    "wof:placetype":"locality"
},
  "geometry": {"coordinates":[72.29455,32.78623],"type":"Point"}
}