{
  "type": "Feature",
  "properties": {
    "gn:admin1_code":"3",
    "gn:asciiname":"Gorei",
    "gn:country_code":"PK",
    "gn:dem":1926,
    "gn:feature_class":"P",
    "gn:feature_code":"PPL",
    "gn:name":"Gorei",
    "gn:population":0,
    "gn:timezone":"Asia/Karachi",
    "iso:country":"PK",
    "name:eng_x_preferred":[
        "Gorei"
    ],
    "name:und_x_variant":[
        "Gorail"
    ],
    "wof:name":"Gorei",
    "wof:placetype":"locality"
},
  "geometry": {"coordinates":[72.60205999999999,35.41719000000001],"type":"Point"}
}