{
  "type": "Feature",
  "properties": {
    "gn:admin1_code":"01",
    "gn:asciiname":"Gandoai",
    "gn:country_code":"PK",
    "gn:dem":2322,
    "gn:feature_class":"P",
    "gn:feature_code":"PPL",
    "gn:name":"Gandoai",
    "gn:population":0,
    "gn:timezone":"Asia/Karachi",
    "iso:country":"PK",
    "name:und_x_variant":[
        "Kandawai"
    ],
    "wof:name":"Gandoai",
    "wof:placetype":"locality"
},
  "geometry": {"coordinates":[70.5971,33.81767],"type":"Point"}
}