{
  "type": "Feature",
  "properties": {
    "gn:admin1_code":"4.0",
    "gn:asciiname":"Basti Mian Ghulamu Lar",
    "gn:country_code":"PK",
    "gn:dem":86,
    "gn:feature_class":"P",
    "gn:feature_code":"PPL",
    "gn:name":"Basti Mian Ghulamu Lar",
    "gn:population":0,
    "gn:timezone":"Asia/Karachi",
    "iso:country":"PK",
    "wof:name":"Basti Mian Ghulamu Lar",
    "wof:placetype":"locality"
},
  "geometry": {"coordinates":[70.6258,28.54749],"type":"Point"}
}