{
  "type": "Feature",
  "properties": {
    "gn:admin1_code":"4.0",
    "gn:asciiname":"Kanjlanwala",
    "gn:country_code":"PK",
    "gn:dem":197,
    "gn:feature_class":"P",
    "gn:feature_code":"PPL",
    "gn:name":"Kanjlanwala",
    "gn:population":0,
    "gn:timezone":"Asia/Karachi",
    "iso:country":"PK",
    "name:und_x_variant":[
        "K\u0101ni\u0101l\u0101nw\u0101la"
    ],
    "wof:name":"Kanjlanwala",
    "wof:placetype":"locality"
},
  "geometry": {"coordinates":[71.5526,32.25612],"type":"Point"}
}