{
  "type": "Feature",
  "properties": {
    "gn:admin1_code":"3",
    "gn:asciiname":"Charai",
    "gn:country_code":"PK",
    "gn:dem":2157,
    "gn:feature_class":"P",
    "gn:feature_code":"PPL",
    "gn:name":"Charai",
    "gn:population":0,
    "gn:timezone":"Asia/Karachi",
    "iso:country":"PK",
    "wof:name":"Charai",
    "wof:placetype":"locality"
},
  "geometry": {"coordinates":[72.51850999999998,34.73982],"type":"Point"}
}