{
  "type": "Feature",
  "properties": {
    "gn:admin1_code":"3.0",
    "gn:asciiname":"Deong Baihk",
    "gn:country_code":"PK",
    "gn:dem":3962,
    "gn:feature_class":"P",
    "gn:feature_code":"PPL",
    "gn:name":"Deong Baihk",
    "gn:population":0,
    "gn:timezone":"Asia/Karachi",
    "iso:country":"PK",
    "wof:name":"Deong Baihk",
    "wof:placetype":"locality"
},
  "geometry": {"coordinates":[73.82096,35.21494000000001],"type":"Point"}
}