{
  "type": "Feature",
  "properties": {
    "gn:admin1_code":"3",
    "gn:asciiname":"Richh Bela",
    "gn:country_code":"PK",
    "gn:dem":3063,
    "gn:feature_class":"P",
    "gn:feature_code":"PPL",
    "gn:name":"Richh Bela",
    "gn:population":0,
    "gn:timezone":"Asia/Karachi",
    "iso:country":"PK",
    "name:und_x_variant":[
        "Richhbela"
    ],
    "wof:name":"Richh Bela",
    "wof:placetype":"locality"
},
  "geometry": {"coordinates":[73.64971,34.80419000000001],"type":"Point"}
}