{
  "type": "Feature",
  "properties": {
    "gn:admin1_code":"5.0",
    "gn:asciiname":"Goth Korewari",
    "gn:country_code":"PK",
    "gn:dem":71,
    "gn:feature_class":"P",
    "gn:feature_code":"PPL",
    "gn:name":"Goth Korewari",
    "gn:population":0,
    "gn:timezone":"Asia/Karachi",
    "iso:country":"PK",
    "wof:name":"Goth Korewari",
    "wof:placetype":"locality"
},
  "geometry": {"coordinates":[69.60516,27.99786],"type":"Point"}
}