{
  "type": "Feature",
  "properties": {
    "gn:admin1_code":"4.0",
    "gn:asciiname":"Bandoke Chhota",
    "gn:country_code":"PK",
    "gn:dem":205,
    "gn:feature_class":"P",
    "gn:feature_code":"PPL",
    "gn:name":"Bandoke Chhota",
    "gn:population":0,
    "gn:timezone":"Asia/Karachi",
    "iso:country":"PK",
    "name:und_x_variant":[
        "Bandoke Chhola"
    ],
    "wof:name":"Bandoke Chhota",
    "wof:placetype":"locality"
},
  "geometry": {"coordinates":[73.83107,31.77557],"type":"Point"}
}