{
  "type": "Feature",
  "properties": {
    "gn:admin1_code":"2.0",
    "gn:asciiname":"Shangai Alizai",
    "gn:country_code":"PK",
    "gn:dem":2406,
    "gn:feature_class":"P",
    "gn:feature_code":"PPL",
    "gn:name":"Shangai Alizai",
    "gn:population":0,
    "gn:timezone":"Asia/Karachi",
    "iso:country":"PK",
    "name:eng_x_preferred":[
        "Shangai Alizai"
    ],
    "wof:name":"Shangai Alizai",
    "wof:placetype":"locality"
},
  "geometry": {"coordinates":[67.14509,30.96709],"type":"Point"}
}