{
  "type": "Feature",
  "properties": {
    "gn:admin1_code":"04",
    "gn:asciiname":"Pindi Dhodhal",
    "gn:country_code":"PK",
    "gn:dem":199,
    "gn:feature_class":"P",
    "gn:feature_code":"PPL",
    "gn:name":"Pindi Dhodhal",
    "gn:population":0,
    "gn:timezone":"Asia/Karachi",
    "iso:country":"PK",
    "name:und_x_variant":[
        "Pindi Dhudal",
        "Pindi Dhodhal"
    ],
    "wof:name":"Pindi Dhodhal",
    "wof:placetype":"locality"
},
  "geometry": {"coordinates":[73.41223000000002,32.08376],"type":"Point"}
}