{
  "type": "Feature",
  "properties": {
    "gn:admin1_code":"5",
    "gn:asciiname":"Piaro Khan",
    "gn:country_code":"PK",
    "gn:dem":53,
    "gn:feature_class":"P",
    "gn:feature_code":"PPL",
    "gn:name":"Piaro Khan",
    "gn:population":0,
    "gn:timezone":"Asia/Karachi",
    "iso:country":"PK",
    "name:und_x_variant":[
        "Wal\u0101ri San\u0101ri"
    ],
    "wof:name":"Piaro Khan",
    "wof:placetype":"locality"
},
  "geometry": {"coordinates":[68.15264000000001,28.115],"type":"Point"}
}