{
  "type": "Feature",
  "properties": {
    "gn:admin1_code":"01",
    "gn:asciiname":"Shinali",
    "gn:country_code":"PK",
    "gn:dem":1935,
    "gn:feature_class":"P",
    "gn:feature_code":"PPL",
    "gn:name":"Shinali",
    "gn:population":0,
    "gn:timezone":"Asia/Karachi",
    "iso:country":"PK",
    "name:und_x_variant":[
        "Shinalai"
    ],
    "wof:name":"Shinali",
    "wof:placetype":"locality"
},
  "geometry": {"coordinates":[70.56794000000002,33.75754000000001],"type":"Point"}
}