{
  "type": "Feature",
  "properties": {
    "gn:admin1_code":"3.0",
    "gn:asciiname":"Buledana Dheri",
    "gn:country_code":"PK",
    "gn:dem":406,
    "gn:feature_class":"P",
    "gn:feature_code":"PPL",
    "gn:name":"Buledana Dheri",
    "gn:population":0,
    "gn:timezone":"Asia/Karachi",
    "iso:country":"PK",
    "name:und_x_variant":[
        "Buled\u0101na Dheri"
    ],
    "wof:name":"Buledana Dheri",
    "wof:placetype":"locality"
},
  "geometry": {"coordinates":[71.60073,33.86554],"type":"Point"}
}