{
  "type": "Feature",
  "properties": {
    "gn:admin1_code":"4.0",
    "gn:asciiname":"Ban",
    "gn:country_code":"PK",
    "gn:dem":205,
    "gn:feature_class":"P",
    "gn:feature_code":"PPL",
    "gn:name":"Ban",
    "gn:population":0,
    "gn:timezone":"Asia/Karachi",
    "iso:country":"PK",
    "name:bos_x_preferred":[
        "Ban"
    ],
    "name:bul_x_preferred":[
        "\u0411\u0430\u043d"
    ],
    "name:cat_x_preferred":[
        "Ban"
    ],
    "name:ceb_x_preferred":[
        "Ban"
    ],
    "name:ces_x_preferred":[
        "Ban"
    ],
    "name:deu_x_preferred":[
        "Ban"
    ],
    "name:fas_x_preferred":[
        "\u0628\u0627\u0646"
    ],
    "name:fra_x_preferred":[
        "Ban"
    ],
    "name:fry_x_preferred":[
        "Ban"
    ],
    "name:heb_x_preferred":[
        "\u05d1\u05d0\u05df"
    ],
    "name:hrv_x_preferred":[
        "Ban"
    ],
    "name:hun_x_preferred":[
        "Ban"
    ],
    "name:ind_x_preferred":[
        "Ban"
    ],
    "name:lim_x_preferred":[
        "Ban"
    ],
    "name:nld_x_preferred":[
        "Ban"
    ],
    "name:pol_x_preferred":[
        "Ban"
    ],
    "name:por_x_preferred":[
        "Ban"
    ],
    "name:ron_x_preferred":[
        "Ban"
    ],
    "name:rus_x_preferred":[
        "\u0411\u0430\u043d"
    ],
    "name:slk_x_preferred":[
        "Ban"
    ],
    "name:slv_x_preferred":[
        "Ban"
    ],
    "name:srp_x_preferred":[
        "\u0411\u0430\u043d"
    ],
    "name:swe_x_preferred":[
        "Ban"
    ],
    "name:ukr_x_preferred":[
        "\u0411\u0430\u043d"
    ],
    "name:vie_x_preferred":[
        "Ban"
    ],
    "name:zho_x_preferred":[
        "Ban"
    ],
    "wof:name":"Ban",
    "wof:placetype":"locality"
},
  "geometry": {"coordinates":[73.65839,31.89924],"type":"Point"}
}