{
  "type": "Feature",
  "properties": {
    "gn:admin1_code":"3.0",
    "gn:asciiname":"Sheikhai Banda",
    "gn:country_code":"PK",
    "gn:dem":453,
    "gn:feature_class":"P",
    "gn:feature_code":"PPL",
    "gn:name":"Sheikhai Banda",
    "gn:population":0,
    "gn:timezone":"Asia/Karachi",
    "iso:country":"PK",
    "name:und_x_variant":[
        "Shaikhi B\u0101nda"
    ],
    "wof:name":"Sheikhai Banda",
    "wof:placetype":"locality"
},
  "geometry": {"coordinates":[71.9015,33.91988],"type":"Point"}
}