{
  "type": "Feature",
  "properties": {
    "gn:admin1_code":"2.0",
    "gn:asciiname":"Harun Khan",
    "gn:country_code":"PK",
    "gn:dem":56,
    "gn:feature_class":"P",
    "gn:feature_code":"PPL",
    "gn:name":"Harun Khan",
    "gn:population":0,
    "gn:timezone":"Asia/Karachi",
    "iso:country":"PK",
    "wof:name":"Harun Khan",
    "wof:placetype":"locality"
},
  "geometry": {"coordinates":[68.52771,28.54389],"type":"Point"}
}