{
  "type": "Feature",
  "properties": {
    "gn:admin1_code":"4.0",
    "gn:asciiname":"Laugwani",
    "gn:country_code":"PK",
    "gn:dem":182,
    "gn:feature_class":"P",
    "gn:feature_code":"PPL",
    "gn:name":"Laugwani",
    "gn:population":0,
    "gn:timezone":"Asia/Karachi",
    "iso:country":"PK",
    "name:und_x_variant":[
        "Lanjw\u0101ni"
    ],
    "wof:name":"Laugwani",
    "wof:placetype":"locality"
},
  "geometry": {"coordinates":[70.25849000000001,29.74612],"type":"Point"}
}