{
  "type": "Feature",
  "properties": {
    "gn:admin1_code":"4",
    "gn:asciiname":"Malik Ghulam Qasim",
    "gn:country_code":"PK",
    "gn:dem":98,
    "gn:feature_class":"P",
    "gn:feature_code":"PPL",
    "gn:name":"Malik Ghulam Qasim",
    "gn:population":0,
    "gn:timezone":"Asia/Karachi",
    "iso:country":"PK",
    "name:und_x_variant":[
        "Malik Gh\u016bl\u0101m Q\u0101s\u012bm Indr\u0101h",
        "Basti Indr\u0101h",
        "Malik Ghulam Qasim"
    ],
    "wof:name":"Malik Ghulam Qasim",
    "wof:placetype":"locality"
},
  "geometry": {"coordinates":[70.74134000000002,29.12572],"type":"Point"}
}