{
  "type": "Feature",
  "properties": {
    "gn:admin1_code":"03",
    "gn:asciiname":"Warasta",
    "gn:country_code":"PK",
    "gn:dem":867,
    "gn:feature_class":"P",
    "gn:feature_code":"PPL",
    "gn:name":"Warasta",
    "gn:population":0,
    "gn:timezone":"Asia/Karachi",
    "iso:country":"PK",
    "name:und_x_variant":[
        "Wrasta",
        "Warasta"
    ],
    "wof:name":"Warasta",
    "wof:placetype":"locality"
},
  "geometry": {"coordinates":[71.02061999999999,33.50944],"type":"Point"}
}