{
  "type": "Feature",
  "properties": {
    "gn:admin1_code":"2.0",
    "gn:asciiname":"Bhadin Bazar",
    "gn:country_code":"PK",
    "gn:dem":961,
    "gn:feature_class":"P",
    "gn:feature_code":"PPL",
    "gn:name":"Bhadin Bazar",
    "gn:population":0,
    "gn:timezone":"Asia/Karachi",
    "iso:country":"PK",
    "wof:name":"Bhadin Bazar",
    "wof:placetype":"locality"
},
  "geometry": {"coordinates":[63.19872,26.69921],"type":"Point"}
}