{
  "type": "Feature",
  "properties": {
    "gn:admin1_code":"2.0",
    "gn:asciiname":"Gadi Saleh Muhammad",
    "gn:country_code":"PK",
    "gn:dem":108,
    "gn:feature_class":"P",
    "gn:feature_code":"PPL",
    "gn:name":"Gadi Saleh Muhammad",
    "gn:population":0,
    "gn:timezone":"Asia/Karachi",
    "iso:country":"PK",
    "wof:name":"Gadi Saleh Muhammad",
    "wof:placetype":"locality"
},
  "geometry": {"coordinates":[67.76283000000001,29.21844],"type":"Point"}
}