{
  "type": "Feature",
  "properties": {
    "gn:admin1_code":"04",
    "gn:asciiname":"Chak Ninety-six Western Branch",
    "gn:country_code":"PK",
    "gn:dem":130,
    "gn:feature_class":"P",
    "gn:feature_code":"PPL",
    "gn:name":"Chak Ninety-six Western Branch",
    "gn:population":0,
    "gn:timezone":"Asia/Karachi",
    "iso:country":"PK",
    "name:und_x_variant":[
        "Sher\u0101n Sher"
    ],
    "wof:name":"Chak Ninety-six Western Branch",
    "wof:placetype":"locality"
},
  "geometry": {"coordinates":[72.06658,30.03079],"type":"Point"}
}