{
  "type": "Feature",
  "properties": {
    "gn:admin1_code":"4",
    "gn:asciiname":"Pawalyan",
    "gn:country_code":"PK",
    "gn:dem":262,
    "gn:feature_class":"P",
    "gn:feature_code":"PPL",
    "gn:name":"Pawalyan",
    "gn:population":0,
    "gn:timezone":"Asia/Karachi",
    "iso:country":"PK",
    "wof:name":"Pawalyan",
    "wof:placetype":"locality"
},
  "geometry": {"coordinates":[72.06667,32.39944000000001],"type":"Point"}
}