{
  "type": "Feature",
  "properties": {
    "gn:admin1_code":"2.0",
    "gn:asciiname":"Tleri Shabozai",
    "gn:country_code":"PK",
    "gn:dem":1898,
    "gn:feature_class":"P",
    "gn:feature_code":"PPL",
    "gn:name":"Tleri Shabozai",
    "gn:population":0,
    "gn:timezone":"Asia/Karachi",
    "iso:country":"PK",
    "name:eng_x_preferred":[
        "Sh\u0101buzai"
    ],
    "wof:name":"Tleri Shabozai",
    "wof:placetype":"locality"
},
  "geometry": {"coordinates":[67.08688000000001,30.83325],"type":"Point"}
}