{
  "type": "Feature",
  "properties": {
    "gn:admin1_code":"4",
    "gn:asciiname":"Thatta Kandhiwala",
    "gn:country_code":"PK",
    "gn:dem":213,
    "gn:feature_class":"P",
    "gn:feature_code":"PPL",
    "gn:name":"Thatta Kandhiwala",
    "gn:population":0,
    "gn:timezone":"Asia/Karachi",
    "iso:country":"PK",
    "name:und_x_variant":[
        "Kand\u0101nw\u0101la"
    ],
    "wof:name":"Thatta Kandhiwala",
    "wof:placetype":"locality"
},
  "geometry": {"coordinates":[73.76222,32.39043],"type":"Point"}
}