{
  "type": "Feature",
  "properties": {
    "gn:admin1_code":"4",
    "gn:asciiname":"Maukot",
    "gn:country_code":"PK",
    "gn:dem":214,
    "gn:feature_class":"P",
    "gn:feature_code":"PPL",
    "gn:name":"Maukot",
    "gn:population":0,
    "gn:timezone":"Asia/Karachi",
    "iso:country":"PK",
    "wof:name":"Maukot",
    "wof:placetype":"locality"
},
  "geometry": {"coordinates":[73.81944,32.26111],"type":"Point"}
}