{
  "type": "Feature",
  "properties": {
    "gn:admin1_code":"4",
    "gn:asciiname":"Hota Naiyanwala",
    "gn:country_code":"PK",
    "gn:dem":172,
    "gn:feature_class":"P",
    "gn:feature_code":"PPL",
    "gn:name":"Hota Naiyanwala",
    "gn:population":0,
    "gn:timezone":"Asia/Karachi",
    "iso:country":"PK",
    "name:und_x_variant":[
        "Hota Naenw\u0101la"
    ],
    "wof:name":"Hota Naiyanwala",
    "wof:placetype":"locality"
},
  "geometry": {"coordinates":[71.17846,31.65377],"type":"Point"}
}