{
  "type": "Feature",
  "properties": {
    "gn:admin1_code":"3.0",
    "gn:asciiname":"Ghando",
    "gn:country_code":"PK",
    "gn:dem":430,
    "gn:feature_class":"P",
    "gn:feature_code":"PPL",
    "gn:name":"Ghando",
    "gn:population":0,
    "gn:timezone":"Asia/Karachi",
    "iso:country":"PK",
    "name:eng_x_preferred":[
        "Ghando"
    ],
    "wof:name":"Ghando",
    "wof:placetype":"locality"
},
  "geometry": {"coordinates":[72.10244,34.40213],"type":"Point"}
}