{
  "type": "Feature",
  "properties": {
    "gn:admin1_code":"5",
    "gn:asciiname":"Goth Tagial Khan Sandilo",
    "gn:country_code":"PK",
    "gn:dem":55,
    "gn:feature_class":"P",
    "gn:feature_code":"PPL",
    "gn:name":"Goth Tagial Khan Sandilo",
    "gn:population":0,
    "gn:timezone":"Asia/Karachi",
    "iso:country":"PK",
    "name:und_x_variant":[
        "Sandela"
    ],
    "wof:name":"Goth Tagial Khan Sandilo",
    "wof:placetype":"locality"
},
  "geometry": {"coordinates":[68.53881,27.55079000000001],"type":"Point"}
}