{
  "type": "Feature",
  "properties": {
    "gn:admin1_code":"2.0",
    "gn:asciiname":"Somari",
    "gn:country_code":"PK",
    "gn:dem":23,
    "gn:feature_class":"P",
    "gn:feature_code":"PPL",
    "gn:name":"Somari",
    "gn:population":0,
    "gn:timezone":"Asia/Karachi",
    "iso:country":"PK",
    "name:ita_x_preferred":[
        "Somari"
    ],
    "name:kor_x_preferred":[
        "\uc18c\ub9c8\ub9ac"
    ],
    "name:por_x_preferred":[
        "Somari"
    ],
    "name:spa_x_preferred":[
        "Somari"
    ],
    "name:und_x_variant":[
        "S\u016bm\u0101rni"
    ],
    "wof:name":"Somari",
    "wof:placetype":"locality"
},
  "geometry": {"coordinates":[62.9428,25.46151],"type":"Point"}
}