{
  "type": "Feature",
  "properties": {
    "gn:admin1_code":"7.0",
    "gn:asciiname":"Shunu",
    "gn:country_code":"PK",
    "gn:dem":3006,
    "gn:feature_class":"P",
    "gn:feature_code":"PPL",
    "gn:name":"Shunu",
    "gn:population":0,
    "gn:timezone":"Asia/Karachi",
    "iso:country":"PK",
    "wof:name":"Shunu",
    "wof:placetype":"locality"
},
  "geometry": {"coordinates":[75.01863,35.69848],"type":"Point"}
}