{
  "type": "Feature",
  "properties": {
    "gn:admin1_code":"6",
    "gn:asciiname":"Bhartan",
    "gn:country_code":"PK",
    "gn:dem":2847,
    "gn:feature_class":"P",
    "gn:feature_code":"PPL",
    "gn:name":"Bhartan",
    "gn:population":0,
    "gn:timezone":"Asia/Karachi",
    "iso:country":"PK",
    "name:und_x_variant":[
        "Bharth\u0101n"
    ],
    "wof:name":"Bhartan",
    "wof:placetype":"locality"
},
  "geometry": {"coordinates":[73.62303,34.36988],"type":"Point"}
}