{
  "type": "Feature",
  "properties": {
    "gn:admin1_code":"4.0",
    "gn:asciiname":"Dera Mera",
    "gn:country_code":"PK",
    "gn:dem":215,
    "gn:feature_class":"P",
    "gn:feature_code":"PPL",
    "gn:name":"Dera Mera",
    "gn:population":0,
    "gn:timezone":"Asia/Karachi",
    "iso:country":"PK",
    "name:und_x_variant":[
        "Mira"
    ],
    "wof:name":"Dera Mera",
    "wof:placetype":"locality"
},
  "geometry": {"coordinates":[72.31845,32.45779],"type":"Point"}
}