{
  "type": "Feature",
  "properties": {
    "gn:admin1_code":"1.0",
    "gn:asciiname":"Warrukai Surdag",
    "gn:country_code":"PK",
    "gn:dem":730,
    "gn:feature_class":"P",
    "gn:feature_code":"PPL",
    "gn:name":"Warrukai Surdag",
    "gn:population":0,
    "gn:timezone":"Asia/Karachi",
    "iso:country":"PK",
    "wof:name":"Warrukai Surdag",
    "wof:placetype":"locality"
},
  "geometry": {"coordinates":[71.33723000000001,34.5937],"type":"Point"}
}