{
  "type": "Feature",
  "properties": {
    "gn:admin1_code":"7.0",
    "gn:asciiname":"Dirkul",
    "gn:country_code":"PK",
    "gn:dem":1732,
    "gn:feature_class":"P",
    "gn:feature_code":"PPL",
    "gn:name":"Dirkul",
    "gn:population":0,
    "gn:timezone":"Asia/Karachi",
    "iso:country":"PK",
    "name:und_x_variant":[
        "Dirkil"
    ],
    "wof:name":"Dirkul",
    "wof:placetype":"locality"
},
  "geometry": {"coordinates":[74.52814000000002,35.51469],"type":"Point"}
}