{
  "type": "Feature",
  "properties": {
    "gn:admin1_code":"5",
    "gn:asciiname":"Arz Muhammad Tagar",
    "gn:country_code":"PK",
    "gn:dem":43,
    "gn:feature_class":"P",
    "gn:feature_code":"PPL",
    "gn:name":"Arz Muhammad Tagar",
    "gn:population":0,
    "gn:timezone":"Asia/Karachi",
    "iso:country":"PK",
    "name:und_x_variant":[
        "Arz Taggar"
    ],
    "wof:name":"Arz Muhammad Tagar",
    "wof:placetype":"locality"
},
  "geometry": {"coordinates":[68.0924,26.88107],"type":"Point"}
}