{
  "type": "Feature",
  "properties": {
    "gn:admin1_code":"4.0",
    "gn:asciiname":"Water And Power Development Authority Colony",
    "gn:country_code":"PK",
    "gn:dem":282,
    "gn:feature_class":"P",
    "gn:feature_code":"PPL",
    "gn:name":"Water And Power Development Authority Colony",
    "gn:population":0,
    "gn:timezone":"Asia/Karachi",
    "iso:country":"PK",
    "name:und_x_variant":[
        "Bani \u0100fgh\u0101nan"
    ],
    "wof:name":"Water And Power Development Authority Colony",
    "wof:placetype":"locality"
},
  "geometry": {"coordinates":[71.70653,32.98484000000001],"type":"Point"}
}