{
  "type": "Feature",
  "properties": {
    "gn:admin1_code":"6",
    "gn:asciiname":"Moil",
    "gn:country_code":"PK",
    "gn:dem":298,
    "gn:feature_class":"P",
    "gn:feature_code":"PPL",
    "gn:name":"Moil",
    "gn:population":0,
    "gn:timezone":"Asia/Karachi",
    "iso:country":"PK",
    "name:und_x_variant":[
        "Moel"
    ],
    "wof:name":"Moil",
    "wof:placetype":"locality"
},
  "geometry": {"coordinates":[74.34849,32.84033],"type":"Point"}
}