{
  "type": "Feature",
  "properties": {
    "gn:admin1_code":"4.0",
    "gn:asciiname":"Basti Chhuttani",
    "gn:country_code":"PK",
    "gn:dem":88,
    "gn:feature_class":"P",
    "gn:feature_code":"PPL",
    "gn:name":"Basti Chhuttani",
    "gn:population":0,
    "gn:timezone":"Asia/Karachi",
    "iso:country":"PK",
    "name:und_x_variant":[
        "Chhuttanw\u0101la"
    ],
    "wof:name":"Basti Chhuttani",
    "wof:placetype":"locality"
},
  "geometry": {"coordinates":[70.29029,28.9919],"type":"Point"}
}