{
  "type": "Feature",
  "properties": {
    "gn:admin1_code":"3.0",
    "gn:asciiname":"Pashatai",
    "gn:country_code":"PK",
    "gn:dem":845,
    "gn:feature_class":"P",
    "gn:feature_code":"PPL",
    "gn:name":"Pashatai",
    "gn:population":0,
    "gn:timezone":"Asia/Karachi",
    "iso:country":"PK",
    "name:eng_x_preferred":[
        "Pashatai"
    ],
    "wof:name":"Pashatai",
    "wof:placetype":"locality"
},
  "geometry": {"coordinates":[71.70074,34.83694000000001],"type":"Point"}
}