{
  "type": "Feature",
  "properties": {
    "gn:admin1_code":"3.0",
    "gn:asciiname":"Gadang Dara",
    "gn:country_code":"PK",
    "gn:dem":533,
    "gn:feature_class":"P",
    "gn:feature_code":"PPL",
    "gn:name":"Gadang Dara",
    "gn:population":0,
    "gn:timezone":"Asia/Karachi",
    "iso:country":"PK",
    "wof:name":"Gadang Dara",
    "wof:placetype":"locality"
},
  "geometry": {"coordinates":[71.96823000000001,34.53917],"type":"Point"}
}