{
  "type": "Feature",
  "properties": {
    "gn:admin1_code":"4.0",
    "gn:asciiname":"Chak One Hundred Sixty-six Panjnad",
    "gn:country_code":"PK",
    "gn:dem":78,
    "gn:feature_class":"P",
    "gn:feature_code":"PPL",
    "gn:name":"Chak One Hundred Sixty-six Panjnad",
    "gn:population":0,
    "gn:timezone":"Asia/Karachi",
    "iso:country":"PK",
    "name:und_x_variant":[
        "Chak One Hundred Sixty-six P"
    ],
    "wof:name":"Chak One Hundred Sixty-six Panjnad",
    "wof:placetype":"neighbourhood"
},
  "geometry": {"coordinates":[70.14543,28.30844],"type":"Point"}
}