{
  "type": "Feature",
  "properties": {
    "gn:admin1_code":"6",
    "gn:asciiname":"Jakri Baihk",
    "gn:country_code":"PK",
    "gn:dem":3158,
    "gn:feature_class":"P",
    "gn:feature_code":"PPL",
    "gn:name":"Jakri Baihk",
    "gn:population":0,
    "gn:timezone":"Asia/Karachi",
    "iso:country":"PK",
    "name:und_x_variant":[
        "Jhakri Baihk"
    ],
    "wof:name":"Jakri Baihk",
    "wof:placetype":"locality"
},
  "geometry": {"coordinates":[73.85259000000001,34.70754],"type":"Point"}
}