{
  "type": "Feature",
  "properties": {
    "gn:admin1_code":"3",
    "gn:asciiname":"Jabang",
    "gn:country_code":"PK",
    "gn:dem":1690,
    "gn:feature_class":"P",
    "gn:feature_code":"PPL",
    "gn:name":"Jabang",
    "gn:population":0,
    "gn:timezone":"Asia/Karachi",
    "iso:country":"PK",
    "wof:name":"Jabang",
    "wof:placetype":"locality"
},
  "geometry": {"coordinates":[73.19889999999999,34.56361],"type":"Point"}
}