{
  "type": "Feature",
  "properties": {
    "gn:admin1_code":"4.0",
    "gn:asciiname":"Bakkharbar",
    "gn:country_code":"PK",
    "gn:dem":190,
    "gn:feature_class":"P",
    "gn:feature_code":"PPL",
    "gn:name":"Bakkharbar",
    "gn:population":0,
    "gn:timezone":"Asia/Karachi",
    "iso:country":"PK",
    "name:und_x_variant":[
        "Bakkhar"
    ],
    "wof:name":"Bakkharbar",
    "wof:placetype":"locality"
},
  "geometry": {"coordinates":[72.49321999999999,32.3104],"type":"Point"}
}