{
  "type": "Feature",
  "properties": {
    "gn:admin1_code":"5.0",
    "gn:asciiname":"Goth Malang Khan Brohi",
    "gn:country_code":"PK",
    "gn:dem":51,
    "gn:feature_class":"P",
    "gn:feature_code":"PPL",
    "gn:name":"Goth Malang Khan Brohi",
    "gn:population":0,
    "gn:timezone":"Asia/Karachi",
    "iso:country":"PK",
    "name:und_x_variant":[
        "Goth Malang Kh\u0101n Brah\u016bi"
    ],
    "wof:name":"Goth Malang Khan Brohi",
    "wof:placetype":"locality"
},
  "geometry": {"coordinates":[68.072,27.37671],"type":"Point"}
}