{
  "type": "Feature",
  "properties": {
    "gn:admin1_code":"3.0",
    "gn:asciiname":"Darband",
    "gn:country_code":"PK",
    "gn:dem":920,
    "gn:feature_class":"P",
    "gn:feature_code":"PPL",
    "gn:name":"Darband",
    "gn:population":0,
    "gn:timezone":"Asia/Karachi",
    "iso:country":"PK",
    "wof:name":"Darband",
    "wof:placetype":"locality"
},
  "geometry": {"coordinates":[70.98833,33.51553],"type":"Point"}
}