{
  "type": "Feature",
  "properties": {
    "gn:admin1_code":"03",
    "gn:asciiname":"Mansurgarh",
    "gn:country_code":"PK",
    "gn:dem":624,
    "gn:feature_class":"P",
    "gn:feature_code":"PPL",
    "gn:name":"Mansurgarh",
    "gn:population":0,
    "gn:timezone":"Asia/Karachi",
    "iso:country":"PK",
    "wof:name":"Mansurgarh",
    "wof:placetype":"locality"
},
  "geometry": {"coordinates":[71.22494,33.32346],"type":"Point"}
}