{
  "type": "Feature",
  "properties": {
    "gn:admin1_code":"5.0",
    "gn:asciiname":"Goth Hut Brahui",
    "gn:country_code":"PK",
    "gn:dem":28,
    "gn:feature_class":"P",
    "gn:feature_code":"PPL",
    "gn:name":"Goth Hut Brahui",
    "gn:population":0,
    "gn:timezone":"Asia/Karachi",
    "iso:country":"PK",
    "wof:name":"Goth Hut Brahui",
    "wof:placetype":"locality"
},
  "geometry": {"coordinates":[68.57853,25.96326],"type":"Point"}
}