{
  "type": "Feature",
  "properties": {
    "gn:admin1_code":"7.0",
    "gn:asciiname":"Chomai",
    "gn:country_code":"PK",
    "gn:dem":3997,
    "gn:feature_class":"P",
    "gn:feature_code":"PPL",
    "gn:name":"Chomai",
    "gn:population":0,
    "gn:timezone":"Asia/Karachi",
    "iso:country":"PK",
    "wof:name":"Chomai",
    "wof:placetype":"locality"
},
  "geometry": {"coordinates":[73.94819,35.21367],"type":"Point"}
}