{
  "type": "Feature",
  "properties": {
    "gn:admin1_code":"04",
    "gn:asciiname":"Kotla Hussain Jamra",
    "gn:country_code":"PK",
    "gn:dem":90,
    "gn:feature_class":"P",
    "gn:feature_code":"PPL",
    "gn:name":"Kotla Hussain Jamra",
    "gn:population":0,
    "gn:timezone":"Asia/Karachi",
    "iso:country":"PK",
    "name:und_x_variant":[
        "Kotla Husain"
    ],
    "wof:name":"Kotla Hussain Jamra",
    "wof:placetype":"locality"
},
  "geometry": {"coordinates":[70.36187,28.9493],"type":"Point"}
}