{
  "type": "Feature",
  "properties": {
    "gn:admin1_code":"4.0",
    "gn:asciiname":"Chak Forty-two -Three Right",
    "gn:country_code":"PK",
    "gn:dem":178,
    "gn:feature_class":"P",
    "gn:feature_code":"PPL",
    "gn:name":"Chak Forty-two -Three Right",
    "gn:population":0,
    "gn:timezone":"Asia/Karachi",
    "iso:country":"PK",
    "name:und_x_variant":[
        "Manali\u0101n"
    ],
    "wof:name":"Chak Forty-two -Three Right",
    "wof:placetype":"locality"
},
  "geometry": {"coordinates":[73.37128,30.78306],"type":"Point"}
}