{
  "type": "Feature",
  "properties": {
    "gn:admin1_code":"3.0",
    "gn:asciiname":"Yaghi Moskan",
    "gn:country_code":"PK",
    "gn:dem":440,
    "gn:feature_class":"P",
    "gn:feature_code":"PPL",
    "gn:name":"Yaghi Moskan",
    "gn:population":0,
    "gn:timezone":"Asia/Karachi",
    "iso:country":"PK",
    "name:und_x_variant":[
        "Maskan",
        "Yaghi Moskan"
    ],
    "wof:name":"Yaghi Moskan",
    "wof:placetype":"locality"
},
  "geometry": {"coordinates":[70.98571,32.96992],"type":"Point"}
}