{
  "type": "Feature",
  "properties": {
    "gn:admin1_code":"3.0",
    "gn:asciiname":"Kandar",
    "gn:country_code":"PK",
    "gn:dem":388,
    "gn:feature_class":"P",
    "gn:feature_code":"PPL",
    "gn:name":"Kandar",
    "gn:population":0,
    "gn:timezone":"Asia/Karachi",
    "iso:country":"PK",
    "wof:name":"Kandar",
    "wof:placetype":"locality"
},
  "geometry": {"coordinates":[71.83559,33.5466],"type":"Point"}
}