{
  "type": "Feature",
  "properties": {
    "gn:admin1_code":"5.0",
    "gn:asciiname":"Kamal Khan Chang",
    "gn:country_code":"PK",
    "gn:dem":10,
    "gn:feature_class":"P",
    "gn:feature_code":"PPL",
    "gn:name":"Kamal Khan Chang",
    "gn:population":0,
    "gn:timezone":"Asia/Karachi",
    "iso:country":"PK",
    "wof:name":"Kamal Khan Chang",
    "wof:placetype":"locality"
},
  "geometry": {"coordinates":[68.78093,24.61285],"type":"Point"}
}