{
  "type": "Feature",
  "properties": {
    "gn:admin1_code":"05",
    "gn:asciiname":"Mithri Jat",
    "gn:country_code":"PK",
    "gn:dem":58,
    "gn:feature_class":"P",
    "gn:feature_code":"PPL",
    "gn:name":"Mithri Jat",
    "gn:population":0,
    "gn:timezone":"Asia/Karachi",
    "iso:country":"PK",
    "name:und_x_variant":[
        "Mithri",
        "Mithri Jat"
    ],
    "wof:name":"Mithri Jat",
    "wof:placetype":"locality"
},
  "geometry": {"coordinates":[68.73737,27.40821],"type":"Point"}
}