{
  "type": "Feature",
  "properties": {
    "gn:admin1_code":"4",
    "gn:asciiname":"Sarawala",
    "gn:country_code":"PK",
    "gn:dem":144,
    "gn:feature_class":"P",
    "gn:feature_code":"PPL",
    "gn:name":"Sarawala",
    "gn:population":0,
    "gn:timezone":"Asia/Karachi",
    "iso:country":"PK",
    "name:und_x_variant":[
        "Chak Four Hundred Eighty-five Eastern Bar"
    ],
    "wof:name":"Sarawala",
    "wof:placetype":"locality"
},
  "geometry": {"coordinates":[72.60064,30.05053],"type":"Point"}
}