{
  "type": "Feature",
  "properties": {
    "gn:admin1_code":"2.0",
    "gn:asciiname":"Shahr Shaikh",
    "gn:country_code":"PK",
    "gn:dem":1076,
    "gn:feature_class":"P",
    "gn:feature_code":"PPL",
    "gn:name":"Shahr Shaikh",
    "gn:population":0,
    "gn:timezone":"Asia/Karachi",
    "iso:country":"PK",
    "wof:name":"Shahr Shaikh",
    "wof:placetype":"locality"
},
  "geometry": {"coordinates":[66.82029,27.69923],"type":"Point"}
}