{
  "type": "Feature",
  "properties": {
    "gn:admin1_code":"6.0",
    "gn:asciiname":"Khai",
    "gn:country_code":"PK",
    "gn:dem":810,
    "gn:feature_class":"P",
    "gn:feature_code":"PPL",
    "gn:name":"Khai",
    "gn:population":0,
    "gn:timezone":"Asia/Karachi",
    "iso:country":"PK",
    "wof:name":"Khai",
    "wof:placetype":"locality"
},
  "geometry": {"coordinates":[73.63431,33.97339],"type":"Point"}
}