{
  "type": "Feature",
  "properties": {
    "gn:admin1_code":"4",
    "gn:asciiname":"Chak Five Hundred Five",
    "gn:country_code":"PK",
    "gn:dem":147,
    "gn:feature_class":"P",
    "gn:feature_code":"PPL",
    "gn:name":"Chak Five Hundred Five",
    "gn:population":0,
    "gn:timezone":"Asia/Karachi",
    "iso:country":"PK",
    "wof:name":"Chak Five Hundred Five",
    "wof:placetype":"locality"
},
  "geometry": {"coordinates":[72.25139,30.89444],"type":"Point"}
}