{
  "type": "Feature",
  "properties": {
    "gn:admin1_code":"3",
    "gn:asciiname":"Shamsher",
    "gn:country_code":"PK",
    "gn:dem":2152,
    "gn:feature_class":"P",
    "gn:feature_code":"PPL",
    "gn:name":"Shamsher",
    "gn:population":0,
    "gn:timezone":"Asia/Karachi",
    "iso:country":"PK",
    "wof:name":"Shamsher",
    "wof:placetype":"locality"
},
  "geometry": {"coordinates":[73.16381,34.88777],"type":"Point"}
}