{
  "type": "Feature",
  "properties": {
    "gn:admin1_code":"2.0",
    "gn:asciiname":"Mugai Bargai",
    "gn:country_code":"PK",
    "gn:dem":2282,
    "gn:feature_class":"P",
    "gn:feature_code":"PPL",
    "gn:name":"Mugai Bargai",
    "gn:population":0,
    "gn:timezone":"Asia/Karachi",
    "iso:country":"PK",
    "name:eng_x_preferred":[
        "Mugai Bargai"
    ],
    "wof:name":"Mugai Bargai",
    "wof:placetype":"locality"
},
  "geometry": {"coordinates":[67.44818000000001,30.59796],"type":"Point"}
}