{
  "type": "Feature",
  "properties": {
    "gn:admin1_code":"7.0",
    "gn:asciiname":"Naltar",
    "gn:country_code":"PK",
    "gn:dem":4625,
    "gn:feature_class":"P",
    "gn:feature_code":"PPL",
    "gn:name":"Naltar",
    "gn:population":0,
    "gn:timezone":"Asia/Karachi",
    "iso:country":"PK",
    "wof:name":"Naltar",
    "wof:placetype":"locality"
},
  "geometry": {"coordinates":[74.03045999999998,36.32426],"type":"Point"}
}