{
  "type": "Feature",
  "properties": {
    "gn:admin1_code":"2.0",
    "gn:asciiname":"Kandi",
    "gn:country_code":"PK",
    "gn:dem":45,
    "gn:feature_class":"P",
    "gn:feature_code":"PPL",
    "gn:name":"Kandi",
    "gn:population":0,
    "gn:timezone":"Asia/Karachi",
    "iso:country":"PK",
    "name:ceb_x_preferred":[
        "Kandi"
    ],
    "name:deu_x_preferred":[
        "Kandi"
    ],
    "name:fin_x_preferred":[
        "Kandi"
    ],
    "name:fra_x_preferred":[
        "Kandi"
    ],
    "name:hun_x_preferred":[
        "Kandi"
    ],
    "name:swe_x_preferred":[
        "Kandi"
    ],
    "wof:name":"Kandi",
    "wof:placetype":"locality"
},
  "geometry": {"coordinates":[66.515,25.97667],"type":"Point"}
}