{
  "type": "Feature",
  "properties": {
    "gn:admin1_code":"5",
    "gn:asciiname":"Sher Khan",
    "gn:country_code":"PK",
    "gn:dem":58,
    "gn:feature_class":"P",
    "gn:feature_code":"PPL",
    "gn:name":"Sher Khan",
    "gn:population":0,
    "gn:timezone":"Asia/Karachi",
    "iso:country":"PK",
    "wof:name":"Sher Khan",
    "wof:placetype":"locality"
},
  "geometry": {"coordinates":[68.82318000000001,27.4592],"type":"Point"}
}