{
  "type": "Feature",
  "properties": {
    "gn:admin1_code":"3.0",
    "gn:asciiname":"Nakoi",
    "gn:country_code":"PK",
    "gn:dem":1585,
    "gn:feature_class":"P",
    "gn:feature_code":"PPL",
    "gn:name":"Nakoi",
    "gn:population":0,
    "gn:timezone":"Asia/Karachi",
    "iso:country":"PK",
    "wof:name":"Nakoi",
    "wof:placetype":"locality"
},
  "geometry": {"coordinates":[72.92294,35.48390999999999],"type":"Point"}
}