{
  "type": "Feature",
  "properties": {
    "gn:admin1_code":"2.0",
    "gn:asciiname":"Kili Hassan",
    "gn:country_code":"PK",
    "gn:dem":1424,
    "gn:feature_class":"P",
    "gn:feature_code":"PPL",
    "gn:name":"Kili Hassan",
    "gn:population":0,
    "gn:timezone":"Asia/Karachi",
    "iso:country":"PK",
    "wof:name":"Kili Hassan",
    "wof:placetype":"locality"
},
  "geometry": {"coordinates":[66.57629,27.21426],"type":"Point"}
}