{
  "type": "Feature",
  "properties": {
    "gn:admin1_code":"6",
    "gn:asciiname":"Budhal",
    "gn:country_code":"PK",
    "gn:dem":1748,
    "gn:feature_class":"P",
    "gn:feature_code":"PPL",
    "gn:name":"Budhal",
    "gn:population":0,
    "gn:timezone":"Asia/Karachi",
    "iso:country":"PK",
    "name:und_x_variant":[
        "Badhaf",
        "Badh\u0101l"
    ],
    "wof:name":"Budhal",
    "wof:placetype":"locality"
},
  "geometry": {"coordinates":[74.00678000000001,33.88959000000001],"type":"Point"}
}