{
  "type": "Feature",
  "properties": {
    "gn:admin1_code":"4.0",
    "gn:asciiname":"Chak Fifty-five",
    "gn:country_code":"PK",
    "gn:dem":185,
    "gn:feature_class":"P",
    "gn:feature_code":"PPL",
    "gn:name":"Chak Fifty-five",
    "gn:population":0,
    "gn:timezone":"Asia/Karachi",
    "iso:country":"PK",
    "name:und_x_variant":[
        "Baba Bukala",
        "Chak Fifty-five",
        "B\u0101ba Bak\u0101la"
    ],
    "wof:name":"Chak Fifty-five",
    "wof:placetype":"locality"
},
  "geometry": {"coordinates":[72.94835999999999,31.50425],"type":"Point"}
}