{
  "type": "Feature",
  "properties": {
    "gn:admin1_code":"5",
    "gn:asciiname":"Goth Ghulam Ali Nurpur",
    "gn:country_code":"PK",
    "gn:dem":15,
    "gn:feature_class":"P",
    "gn:feature_code":"PPL",
    "gn:name":"Goth Ghul\u0101m Ali N\u016brpur",
    "gn:population":0,
    "gn:timezone":"Asia/Karachi",
    "iso:country":"PK",
    "wof:name":"Goth Ghulam Ali Nurpur",
    "wof:placetype":"locality"
},
  "geometry": {"coordinates":[68.96666999999999,25.18472],"type":"Point"}
}