{
  "type": "Feature",
  "properties": {
    "gn:admin1_code":"4.0",
    "gn:asciiname":"Khalabat",
    "gn:country_code":"PK",
    "gn:dem":1783,
    "gn:feature_class":"P",
    "gn:feature_code":"PPL",
    "gn:name":"Khalabat",
    "gn:population":0,
    "gn:timezone":"Asia/Karachi",
    "iso:country":"PK",
    "name:eng_x_preferred":[
        "Khalabat"
    ],
    "wof:name":"Khalabat",
    "wof:placetype":"locality"
},
  "geometry": {"coordinates":[73.47565999999998,33.8284],"type":"Point"}
}