{
  "type": "Feature",
  "properties": {
    "gn:admin1_code":"4.0",
    "gn:asciiname":"Din",
    "gn:country_code":"PK",
    "gn:dem":160,
    "gn:feature_class":"P",
    "gn:feature_code":"PPL",
    "gn:name":"Din",
    "gn:population":0,
    "gn:timezone":"Asia/Karachi",
    "iso:country":"PK",
    "name:ara_x_preferred":[
        "\u062f\u064a\u0646"
    ],
    "name:cat_x_preferred":[
        "Din"
    ],
    "name:dan_x_preferred":[
        "Din"
    ],
    "name:deu_x_preferred":[
        "Din"
    ],
    "name:est_x_preferred":[
        "DIN"
    ],
    "name:lav_x_preferred":[
        "Dins"
    ],
    "name:nor_x_preferred":[
        "Din"
    ],
    "name:spa_x_preferred":[
        "Din"
    ],
    "wof:name":"Din",
    "wof:placetype":"locality"
},
  "geometry": {"coordinates":[73.20823,29.6519],"type":"Point"}
}