{
  "type": "Feature",
  "properties": {
    "gn:admin1_code":"5.0",
    "gn:asciiname":"Rabbu Jat",
    "gn:country_code":"PK",
    "gn:dem":7,
    "gn:feature_class":"P",
    "gn:feature_code":"PPL",
    "gn:name":"Rabbu Jat",
    "gn:population":0,
    "gn:timezone":"Asia/Karachi",
    "iso:country":"PK",
    "name:eng_x_preferred":[
        "Rabbu Jat"
    ],
    "wof:name":"Rabbu Jat",
    "wof:placetype":"locality"
},
  "geometry": {"coordinates":[68.29177,24.50808],"type":"Point"}
}