{
  "type": "Feature",
  "properties": {
    "gn:admin1_code":"5",
    "gn:asciiname":"Goth Khan Muhammad",
    "gn:country_code":"PK",
    "gn:dem":62,
    "gn:feature_class":"P",
    "gn:feature_code":"PPL",
    "gn:name":"Goth Khan Muhammad",
    "gn:population":0,
    "gn:timezone":"Asia/Karachi",
    "iso:country":"PK",
    "name:und_x_variant":[
        "Kh\u0101n Muhammad"
    ],
    "wof:name":"Goth Khan Muhammad",
    "wof:placetype":"locality"
},
  "geometry": {"coordinates":[68.51164,28.12332],"type":"Point"}
}