{
  "type": "Feature",
  "properties": {
    "gn:admin1_code":"3",
    "gn:asciiname":"Kalanda",
    "gn:country_code":"PK",
    "gn:dem":1533,
    "gn:feature_class":"P",
    "gn:feature_code":"PPL",
    "gn:name":"Kalanda",
    "gn:population":0,
    "gn:timezone":"Asia/Karachi",
    "iso:country":"PK",
    "wof:name":"Kalanda",
    "wof:placetype":"locality"
},
  "geometry": {"coordinates":[73.24103000000002,34.00044],"type":"Point"}
}