{
  "type": "Feature",
  "properties": {
    "gn:admin1_code":"5.0",
    "gn:asciiname":"Goth Saiyidan Jo",
    "gn:country_code":"PK",
    "gn:dem":65,
    "gn:feature_class":"P",
    "gn:feature_code":"PPL",
    "gn:name":"Goth Saiyidan Jo",
    "gn:population":0,
    "gn:timezone":"Asia/Karachi",
    "iso:country":"PK",
    "wof:name":"Goth Saiyidan Jo",
    "wof:placetype":"locality"
},
  "geometry": {"coordinates":[68.77016999999999,27.84637],"type":"Point"}
}