{
  "type": "Feature",
  "properties": {
    "gn:admin1_code":"7.0",
    "gn:asciiname":"Dodarabo Baihk",
    "gn:country_code":"PK",
    "gn:dem":3179,
    "gn:feature_class":"P",
    "gn:feature_code":"PPL",
    "gn:name":"Dodarabo Baihk",
    "gn:population":0,
    "gn:timezone":"Asia/Karachi",
    "iso:country":"PK",
    "wof:name":"Dodarabo Baihk",
    "wof:placetype":"locality"
},
  "geometry": {"coordinates":[74.88401,35.05924],"type":"Point"}
}