{
  "type": "Feature",
  "properties": {
    "gn:admin1_code":"1",
    "gn:asciiname":"Mulla Darra",
    "gn:country_code":"PK",
    "gn:dem":1640,
    "gn:feature_class":"P",
    "gn:feature_code":"PPL",
    "gn:name":"Mulla Darra",
    "gn:population":0,
    "gn:timezone":"Asia/Karachi",
    "iso:country":"PK",
    "wof:name":"Mulla Darra",
    "wof:placetype":"locality"
},
  "geometry": {"coordinates":[71.02224,33.81695],"type":"Point"}
}