{
  "type": "Feature",
  "properties": {
    "gn:admin1_code":"5",
    "gn:asciiname":"Goth Aga Panhwar",
    "gn:country_code":"PK",
    "gn:dem":17,
    "gn:feature_class":"P",
    "gn:feature_code":"PPL",
    "gn:name":"Goth Aga Panhwar",
    "gn:population":0,
    "gn:timezone":"Asia/Karachi",
    "iso:country":"PK",
    "name:und_x_variant":[
        "Goth Agu Panwhar"
    ],
    "wof:name":"Goth Aga Panhwar",
    "wof:placetype":"locality"
},
  "geometry": {"coordinates":[68.99226,25.59454],"type":"Point"}
}