{
  "type": "Feature",
  "properties": {
    "gn:admin1_code":"4",
    "gn:asciiname":"Ramzanwala",
    "gn:country_code":"PK",
    "gn:dem":150,
    "gn:feature_class":"P",
    "gn:feature_code":"PPL",
    "gn:name":"Ramz\u0101nw\u0101la",
    "gn:population":0,
    "gn:timezone":"Asia/Karachi",
    "iso:country":"PK",
    "wof:name":"Ramzanwala",
    "wof:placetype":"locality"
},
  "geometry": {"coordinates":[71.18056,31.04722000000001],"type":"Point"}
}