{
  "type": "Feature",
  "properties": {
    "gn:admin1_code":"05",
    "gn:asciiname":"Virawah",
    "gn:country_code":"PK",
    "gn:dem":24,
    "gn:feature_class":"P",
    "gn:feature_code":"PPL",
    "gn:name":"Virawah",
    "gn:population":0,
    "gn:timezone":"Asia/Karachi",
    "iso:country":"PK",
    "name:und_x_variant":[
        "Wirawah",
        "Vir\u0101wah",
        "Virawah"
    ],
    "wof:name":"Virawah",
    "wof:placetype":"locality"
},
  "geometry": {"coordinates":[70.77783000000002,24.52217000000001],"type":"Point"}
}