{
  "type": "Feature",
  "properties": {
    "gn:admin1_code":"4.0",
    "gn:asciiname":"Chah Jutianwala",
    "gn:country_code":"PK",
    "gn:dem":143,
    "gn:feature_class":"P",
    "gn:feature_code":"PPL",
    "gn:name":"Chah Jutianwala",
    "gn:population":0,
    "gn:timezone":"Asia/Karachi",
    "iso:country":"PK",
    "name:und_x_variant":[
        "Gow\u0101ns\u0101nw\u0101la"
    ],
    "wof:name":"Chah Jutianwala",
    "wof:placetype":"locality"
},
  "geometry": {"coordinates":[72.14527,30.79711],"type":"Point"}
}