{
  "type": "Feature",
  "properties": {
    "gn:admin1_code":"5",
    "gn:asciiname":"Nir Waro",
    "gn:country_code":"PK",
    "gn:dem":51,
    "gn:feature_class":"P",
    "gn:feature_code":"PPL",
    "gn:name":"Nir Waro",
    "gn:population":0,
    "gn:timezone":"Asia/Karachi",
    "iso:country":"PK",
    "name:und_x_variant":[
        "Nirwaro",
        "Narwaro",
        "Nir Waro"
    ],
    "wof:name":"Nir Waro",
    "wof:placetype":"locality"
},
  "geometry": {"coordinates":[68.50296,27.09874000000001],"type":"Point"}
}