{
  "type": "Feature",
  "properties": {
    "gn:admin1_code":"2.0",
    "gn:asciiname":"Goth Essa",
    "gn:country_code":"PK",
    "gn:dem":1023,
    "gn:feature_class":"P",
    "gn:feature_code":"PPL",
    "gn:name":"Goth Essa",
    "gn:population":0,
    "gn:timezone":"Asia/Karachi",
    "iso:country":"PK",
    "wof:name":"Goth Essa",
    "wof:placetype":"locality"
},
  "geometry": {"coordinates":[64.6314,26.57638],"type":"Point"}
}