{
  "type": "Feature",
  "properties": {
    "gn:admin1_code":"6.0",
    "gn:asciiname":"Nura Tekri",
    "gn:country_code":"PK",
    "gn:dem":735,
    "gn:feature_class":"P",
    "gn:feature_code":"PPL",
    "gn:name":"Nura Tekri",
    "gn:population":0,
    "gn:timezone":"Asia/Karachi",
    "iso:country":"PK",
    "wof:name":"Nura Tekri",
    "wof:placetype":"locality"
},
  "geometry": {"coordinates":[74.01071999999998,33.21056],"type":"Point"}
}