{
  "type": "Feature",
  "properties": {
    "gn:admin1_code":"05",
    "gn:asciiname":"Gul Muhammad Jalbani",
    "gn:country_code":"PK",
    "gn:dem":4,
    "gn:feature_class":"P",
    "gn:feature_code":"PPL",
    "gn:name":"Gul Muhammad Jalbani",
    "gn:population":0,
    "gn:timezone":"Asia/Karachi",
    "iso:country":"PK",
    "wof:name":"Gul Muhammad Jalbani",
    "wof:placetype":"locality"
},
  "geometry": {"coordinates":[67.96583000000001,24.25812],"type":"Point"}
}