{
  "type": "Feature",
  "properties": {
    "gn:admin1_code":"4.0",
    "gn:asciiname":"Dhok Patwariwali",
    "gn:country_code":"PK",
    "gn:dem":527,
    "gn:feature_class":"P",
    "gn:feature_code":"PPL",
    "gn:name":"Dhok Patwariwali",
    "gn:population":0,
    "gn:timezone":"Asia/Karachi",
    "iso:country":"PK",
    "wof:name":"Dhok Patwariwali",
    "wof:placetype":"locality"
},
  "geometry": {"coordinates":[72.37663000000001,32.86299],"type":"Point"}
}