{
  "type": "Feature",
  "properties": {
    "gn:admin1_code":"3",
    "gn:asciiname":"Kaneri",
    "gn:country_code":"PK",
    "gn:dem":574,
    "gn:feature_class":"P",
    "gn:feature_code":"PPL",
    "gn:name":"Kaneri",
    "gn:population":0,
    "gn:timezone":"Asia/Karachi",
    "iso:country":"PK",
    "wof:name":"Kaneri",
    "wof:placetype":"locality"
},
  "geometry": {"coordinates":[72.812,34.28071],"type":"Point"}
}