{
  "type": "Feature",
  "properties": {
    "gn:admin1_code":"4.0",
    "gn:asciiname":"Dhaulka",
    "gn:country_code":"PK",
    "gn:dem":163,
    "gn:feature_class":"P",
    "gn:feature_code":"PPL",
    "gn:name":"Dhaulka",
    "gn:population":0,
    "gn:timezone":"Asia/Karachi",
    "iso:country":"PK",
    "name:und_x_variant":[
        "Dholka",
        "Dnaulka",
        "Dhaulka"
    ],
    "wof:name":"Dhaulka",
    "wof:placetype":"locality"
},
  "geometry": {"coordinates":[72.25636,31.68118],"type":"Point"}
}