{
  "type": "Feature",
  "properties": {
    "gn:admin1_code":"6",
    "gn:asciiname":"Mansar",
    "gn:country_code":"PK",
    "gn:dem":2536,
    "gn:feature_class":"P",
    "gn:feature_code":"PPL",
    "gn:name":"Mansar",
    "gn:population":0,
    "gn:timezone":"Asia/Karachi",
    "iso:country":"PK",
    "name:ceb_x_preferred":[
        "Mansar"
    ],
    "name:swe_x_preferred":[
        "Mansar"
    ],
    "name:und_x_variant":[
        "Mensar"
    ],
    "wof:name":"Mansar",
    "wof:placetype":"locality"
},
  "geometry": {"coordinates":[74.13757,33.94515],"type":"Point"}
}