{
  "type": "Feature",
  "properties": {
    "gn:admin1_code":"3",
    "gn:asciiname":"Ranja",
    "gn:country_code":"PK",
    "gn:dem":1506,
    "gn:feature_class":"P",
    "gn:feature_code":"PPL",
    "gn:name":"Ranja",
    "gn:population":0,
    "gn:timezone":"Asia/Karachi",
    "iso:country":"PK",
    "wof:name":"Ranja",
    "wof:placetype":"locality"
},
  "geometry": {"coordinates":[73.06388000000003,34.56737],"type":"Point"}
}