{
  "type": "Feature",
  "properties": {
    "gn:admin1_code":"5",
    "gn:asciiname":"Goth Mirbahar",
    "gn:country_code":"PK",
    "gn:dem":17,
    "gn:feature_class":"P",
    "gn:feature_code":"PPL",
    "gn:name":"Goth Mirbahar",
    "gn:population":0,
    "gn:timezone":"Asia/Karachi",
    "iso:country":"PK",
    "name:und_x_variant":[
        "Hal\u0101je"
    ],
    "wof:name":"Goth Mirbahar",
    "wof:placetype":"locality"
},
  "geometry": {"coordinates":[68.62559,25.01943],"type":"Point"}
}