{
  "type": "Feature",
  "properties": {
    "gn:admin1_code":"3.0",
    "gn:asciiname":"Khelan",
    "gn:country_code":"PK",
    "gn:dem":2092,
    "gn:feature_class":"P",
    "gn:feature_code":"PPL",
    "gn:name":"Khelan",
    "gn:population":0,
    "gn:timezone":"Asia/Karachi",
    "iso:country":"PK",
    "name:eng_x_preferred":[
        "Khelan"
    ],
    "wof:name":"Khelan",
    "wof:placetype":"locality"
},
  "geometry": {"coordinates":[72.24438000000001,35.48854],"type":"Point"}
}