{
  "type": "Feature",
  "properties": {
    "gn:admin1_code":"2.0",
    "gn:asciiname":"Kili Allah Bakhsh",
    "gn:country_code":"PK",
    "gn:dem":1124,
    "gn:feature_class":"P",
    "gn:feature_code":"PPL",
    "gn:name":"Kili Allah Bakhsh",
    "gn:population":0,
    "gn:timezone":"Asia/Karachi",
    "iso:country":"PK",
    "wof:name":"Kili Allah Bakhsh",
    "wof:placetype":"locality"
},
  "geometry": {"coordinates":[66.79259,27.75558],"type":"Point"}
}