{
  "type": "Feature",
  "properties": {
    "gn:admin1_code":"4.0",
    "gn:asciiname":"Ghazni Ghorkiwala",
    "gn:country_code":"PK",
    "gn:dem":251,
    "gn:feature_class":"P",
    "gn:feature_code":"PPL",
    "gn:name":"Ghazni Ghorkiwala",
    "gn:population":0,
    "gn:timezone":"Asia/Karachi",
    "iso:country":"PK",
    "wof:name":"Ghazni Ghorkiwala",
    "wof:placetype":"locality"
},
  "geometry": {"coordinates":[71.70588000000002,32.60358],"type":"Point"}
}