{
  "type": "Feature",
  "properties": {
    "gn:admin1_code":"3",
    "gn:asciiname":"Banda",
    "gn:country_code":"PK",
    "gn:dem":808,
    "gn:feature_class":"P",
    "gn:feature_code":"PPL",
    "gn:name":"Banda",
    "gn:population":0,
    "gn:timezone":"Asia/Karachi",
    "iso:country":"PK",
    "name:eng_x_preferred":[
        "Banda"
    ],
    "wof:name":"Banda",
    "wof:placetype":"locality"
},
  "geometry": {"coordinates":[72.37617,34.44288],"type":"Point"}
}