{
  "type": "Feature",
  "properties": {
    "gn:admin1_code":"1.0",
    "gn:asciiname":"Hiro Mela",
    "gn:country_code":"PK",
    "gn:dem":1076,
    "gn:feature_class":"P",
    "gn:feature_code":"PPL",
    "gn:name":"Hiro Mela",
    "gn:population":0,
    "gn:timezone":"Asia/Karachi",
    "iso:country":"PK",
    "wof:name":"Hiro Mela",
    "wof:placetype":"locality"
},
  "geometry": {"coordinates":[71.17605999999998,33.95038],"type":"Point"}
}