{
  "type": "Feature",
  "properties": {
    "gn:admin1_code":"4",
    "gn:asciiname":"Zaur",
    "gn:country_code":"PK",
    "gn:dem":148,
    "gn:feature_class":"P",
    "gn:feature_code":"PPL",
    "gn:name":"Zaur",
    "gn:population":0,
    "gn:timezone":"Asia/Karachi",
    "iso:country":"PK",
    "name:aze_x_preferred":[
        "Zaur"
    ],
    "name:por_x_preferred":[
        "Zaur"
    ],
    "wof:name":"Zaur",
    "wof:placetype":"locality"
},
  "geometry": {"coordinates":[70.69618,30.94542],"type":"Point"}
}