{
  "type": "Feature",
  "properties": {
    "gn:admin1_code":"5.0",
    "gn:asciiname":"Sawan",
    "gn:country_code":"PK",
    "gn:dem":6,
    "gn:feature_class":"P",
    "gn:feature_code":"PPL",
    "gn:name":"S\u0101wan",
    "gn:population":0,
    "gn:timezone":"Asia/Karachi",
    "iso:country":"PK",
    "name:ara_x_preferred":[
        "\u0633\u0627\u0648\u0627\u0646"
    ],
    "name:mal_x_preferred":[
        "\u0d38\u0d3e\u0d35\u0d7b"
    ],
    "name:pan_x_preferred":[
        "\u0a38\u0a3e\u0a35\u0a23"
    ],
    "name:tam_x_preferred":[
        "\u0b9a\u0bbe\u0bb5\u0ba9\u0bcd"
    ],
    "name:und_x_variant":[
        "S\u0101wan"
    ],
    "name:urd_x_preferred":[
        "\u0633\u0627\u0648\u0646"
    ],
    "wof:name":"Sawan",
    "wof:placetype":"locality"
},
  "geometry": {"coordinates":[67.62,24.5525],"type":"Point"}
}