{
  "type": "Feature",
  "properties": {
    "gn:admin1_code":"2.0",
    "gn:asciiname":"Tor Raghe",
    "gn:country_code":"PK",
    "gn:dem":1785,
    "gn:feature_class":"P",
    "gn:feature_code":"PPL",
    "gn:name":"Tor Raghe",
    "gn:population":0,
    "gn:timezone":"Asia/Karachi",
    "iso:country":"PK",
    "wof:name":"Tor Raghe",
    "wof:placetype":"locality"
},
  "geometry": {"coordinates":[69.54307,31.17226],"type":"Point"}
}