{
  "type": "Feature",
  "properties": {
    "gn:admin1_code":"4",
    "gn:asciiname":"Chak Twenty-two-Eight Right",
    "gn:country_code":"PK",
    "gn:dem":147,
    "gn:feature_class":"P",
    "gn:feature_code":"PPL",
    "gn:name":"Chak Twenty-two-Eight Right",
    "gn:population":0,
    "gn:timezone":"Asia/Karachi",
    "iso:country":"PK",
    "name:und_x_variant":[
        "Chak Twenty-two-Eight R"
    ],
    "wof:name":"Chak Twenty-two-Eight Right",
    "wof:placetype":"locality"
},
  "geometry": {"coordinates":[72.28628,30.50684],"type":"Point"}
}