{
  "type": "Feature",
  "properties": {
    "gn:admin1_code":"01",
    "gn:asciiname":"Mana",
    "gn:country_code":"PK",
    "gn:dem":1657,
    "gn:feature_class":"P",
    "gn:feature_code":"PPL",
    "gn:name":"Mana",
    "gn:population":0,
    "gn:timezone":"Asia/Karachi",
    "iso:country":"PK",
    "wof:name":"Mana",
    "wof:placetype":"locality"
},
  "geometry": {"coordinates":[70.18186,33.88691],"type":"Point"}
}