{
  "type": "Feature",
  "properties": {
    "gn:admin1_code":"4.0",
    "gn:asciiname":"Bakhra Sharif",
    "gn:country_code":"PK",
    "gn:dem":189,
    "gn:feature_class":"P",
    "gn:feature_code":"PPL",
    "gn:name":"Bakhra Sharif",
    "gn:population":0,
    "gn:timezone":"Asia/Karachi",
    "iso:country":"PK",
    "name:und_x_variant":[
        "Rakh Bhakra",
        "Bhakhra",
        "Bakhra Sharif"
    ],
    "wof:name":"Bakhra Sharif",
    "wof:placetype":"locality"
},
  "geometry": {"coordinates":[71.35854,32.42286],"type":"Point"}
}