{
  "type": "Feature",
  "properties": {
    "gn:admin1_code":"4",
    "gn:asciiname":"Chak Eighty-eight Desert Branch",
    "gn:country_code":"PK",
    "gn:dem":121,
    "gn:feature_class":"P",
    "gn:feature_code":"PPL",
    "gn:name":"Chak Eighty-eight Desert Branch",
    "gn:population":0,
    "gn:timezone":"Asia/Karachi",
    "iso:country":"PK",
    "name:und_x_variant":[
        "Chak Eighty-eight D B"
    ],
    "wof:name":"Chak Eighty-eight Desert Branch",
    "wof:placetype":"locality"
},
  "geometry": {"coordinates":[71.79476,29.11845],"type":"Point"}
}