{
  "type": "Feature",
  "properties": {
    "gn:admin1_code":"3.0",
    "gn:asciiname":"Musgai Cham",
    "gn:country_code":"PK",
    "gn:dem":1866,
    "gn:feature_class":"P",
    "gn:feature_code":"PPL",
    "gn:name":"Musgai Cham",
    "gn:population":0,
    "gn:timezone":"Asia/Karachi",
    "iso:country":"PK",
    "wof:name":"Musgai Cham",
    "wof:placetype":"locality"
},
  "geometry": {"coordinates":[72.5157,35.16909],"type":"Point"}
}