{
  "type": "Feature",
  "properties": {
    "gn:admin1_code":"2.0",
    "gn:asciiname":"Kili Malik Ghulam Muhammad",
    "gn:country_code":"PK",
    "gn:dem":1663,
    "gn:feature_class":"P",
    "gn:feature_code":"PPL",
    "gn:name":"Kili Malik Ghulam Muhammad",
    "gn:population":0,
    "gn:timezone":"Asia/Karachi",
    "iso:country":"PK",
    "name:und_x_variant":[
        "Aurang Kili",
        "Kili Malik Ghul\u0101m Muhammad",
        "Kili Malik Ghulam Muhammad"
    ],
    "wof:name":"Kili Malik Ghulam Muhammad",
    "wof:placetype":"locality"
},
  "geometry": {"coordinates":[66.51300999999999,30.83989],"type":"Point"}
}