{
  "type": "Feature",
  "properties": {
    "gn:admin1_code":"02",
    "gn:asciiname":"Ser Dangi",
    "gn:country_code":"PK",
    "gn:dem":1066,
    "gn:feature_class":"P",
    "gn:feature_code":"PPL",
    "gn:name":"Ser Dangi",
    "gn:population":0,
    "gn:timezone":"Asia/Karachi",
    "iso:country":"PK",
    "wof:name":"Ser Dangi",
    "wof:placetype":"locality"
},
  "geometry": {"coordinates":[63.57003,29.13834],"type":"Point"}
}