{
  "type": "Feature",
  "properties": {
    "gn:admin1_code":"4",
    "gn:asciiname":"Khu Mariwala",
    "gn:country_code":"PK",
    "gn:dem":130,
    "gn:feature_class":"P",
    "gn:feature_code":"PPL",
    "gn:name":"Khu Mariwala",
    "gn:population":0,
    "gn:timezone":"Asia/Karachi",
    "iso:country":"PK",
    "name:eng_x_preferred":[
        "M\u0101r\u012bw\u0101la"
    ],
    "wof:name":"Khu Mariwala",
    "wof:placetype":"locality"
},
  "geometry": {"coordinates":[70.69880999999999,30.32688],"type":"Point"}
}