{
  "type": "Feature",
  "properties": {
    "gn:admin1_code":"4",
    "gn:asciiname":"Chak Forty-one Desert Branch Gharbi",
    "gn:country_code":"PK",
    "gn:dem":118,
    "gn:feature_class":"P",
    "gn:feature_code":"PPL",
    "gn:name":"Chak Forty-one Desert Branch Gharbi",
    "gn:population":0,
    "gn:timezone":"Asia/Karachi",
    "iso:country":"PK",
    "name:und_x_variant":[
        "Chak Forty-one D B Gharbi"
    ],
    "wof:name":"Chak Forty-one Desert Branch Gharbi",
    "wof:placetype":"locality"
},
  "geometry": {"coordinates":[71.75793,29.24365],"type":"Point"}
}