{
  "type": "Feature",
  "properties": {
    "gn:admin1_code":"6.0",
    "gn:asciiname":"Thamla",
    "gn:country_code":"PK",
    "gn:dem":689,
    "gn:feature_class":"P",
    "gn:feature_code":"PPL",
    "gn:name":"Thamla",
    "gn:population":0,
    "gn:timezone":"Asia/Karachi",
    "iso:country":"PK",
    "wof:name":"Thamla",
    "wof:placetype":"locality"
},
  "geometry": {"coordinates":[73.72963,33.56356],"type":"Point"}
}