{
  "type": "Feature",
  "properties": {
    "gn:admin1_code":"4",
    "gn:asciiname":"Nur Sial",
    "gn:country_code":"PK",
    "gn:dem":127,
    "gn:feature_class":"P",
    "gn:feature_code":"PPL",
    "gn:name":"Nur Sial",
    "gn:population":0,
    "gn:timezone":"Asia/Karachi",
    "iso:country":"PK",
    "wof:name":"Nur Sial",
    "wof:placetype":"locality"
},
  "geometry": {"coordinates":[72.19450000000001,29.5713],"type":"Point"}
}