{
  "type": "Feature",
  "properties": {
    "gn:admin1_code":"4",
    "gn:asciiname":"Kachhelanwala",
    "gn:country_code":"PK",
    "gn:dem":189,
    "gn:feature_class":"P",
    "gn:feature_code":"PPL",
    "gn:name":"Kachhelanwala",
    "gn:population":0,
    "gn:timezone":"Asia/Karachi",
    "iso:country":"PK",
    "name:und_x_variant":[
        "Kachheli\u0101nw\u0101la"
    ],
    "wof:name":"Kachhelanwala",
    "wof:placetype":"locality"
},
  "geometry": {"coordinates":[71.69519,31.96656],"type":"Point"}
}