{
  "type": "Feature",
  "properties": {
    "gn:admin1_code":"1.0",
    "gn:asciiname":"Maddar Khel",
    "gn:country_code":"PK",
    "gn:dem":1527,
    "gn:feature_class":"P",
    "gn:feature_code":"PPL",
    "gn:name":"Maddar Khel",
    "gn:population":0,
    "gn:timezone":"Asia/Karachi",
    "iso:country":"PK",
    "name:und_x_variant":[
        "Mad\u0101r Khel"
    ],
    "wof:name":"Maddar Khel",
    "wof:placetype":"locality"
},
  "geometry": {"coordinates":[70.7878,33.87886],"type":"Point"}
}