{
  "type": "Feature",
  "properties": {
    "gn:admin1_code":"3.0",
    "gn:asciiname":"Landai",
    "gn:country_code":"PK",
    "gn:dem":1559,
    "gn:feature_class":"P",
    "gn:feature_code":"PPL",
    "gn:name":"Landai",
    "gn:population":0,
    "gn:timezone":"Asia/Karachi",
    "iso:country":"PK",
    "wof:name":"Landai",
    "wof:placetype":"locality"
},
  "geometry": {"coordinates":[72.95329,34.69067],"type":"Point"}
}