{
  "type": "Feature",
  "properties": {
    "gn:admin1_code":"7.0",
    "gn:asciiname":"Murat Baihk",
    "gn:country_code":"PK",
    "gn:dem":3440,
    "gn:feature_class":"P",
    "gn:feature_code":"PPL",
    "gn:name":"Murat Baihk",
    "gn:population":0,
    "gn:timezone":"Asia/Karachi",
    "iso:country":"PK",
    "wof:name":"Murat Baihk",
    "wof:placetype":"locality"
},
  "geometry": {"coordinates":[74.28491,35.16028],"type":"Point"}
}