{
  "type": "Feature",
  "properties": {
    "gn:admin1_code":"4.0",
    "gn:asciiname":"Dhab Pari",
    "gn:country_code":"PK",
    "gn:dem":544,
    "gn:feature_class":"P",
    "gn:feature_code":"PPL",
    "gn:name":"Dhab Pari",
    "gn:population":0,
    "gn:timezone":"Asia/Karachi",
    "iso:country":"PK",
    "name:eng_x_preferred":[
        "Dh\u0101b Pariw\u0101li"
    ],
    "name:fas_x_preferred":[
        "\u062f\u0647\u0627\u0628 \u067e\u0631\u06cc"
    ],
    "name:urd_x_preferred":[
        "\u0688\u06be\u0627\u0628 \u067e\u0691\u06cc"
    ],
    "wof:name":"Dhab Pari",
    "wof:placetype":"locality"
},
  "geometry": {"coordinates":[72.89461999999997,33.00247],"type":"Point"}
}