{
  "type": "Feature",
  "properties": {
    "gn:admin1_code":"2.0",
    "gn:asciiname":"Posti Number One",
    "gn:country_code":"PK",
    "gn:dem":1195,
    "gn:feature_class":"P",
    "gn:feature_code":"PPL",
    "gn:name":"Posti Number One",
    "gn:population":0,
    "gn:timezone":"Asia/Karachi",
    "iso:country":"PK",
    "wof:name":"Posti Number One",
    "wof:placetype":"locality"
},
  "geometry": {"coordinates":[64.26271,29.24096],"type":"Point"}
}