{
  "type": "Feature",
  "properties": {
    "gn:admin1_code":"4.0",
    "gn:asciiname":"Tutnian",
    "gn:country_code":"PK",
    "gn:dem":476,
    "gn:feature_class":"P",
    "gn:feature_code":"PPL",
    "gn:name":"Tutnian",
    "gn:population":0,
    "gn:timezone":"Asia/Karachi",
    "iso:country":"PK",
    "name:und_x_variant":[
        "Tutni\u0101n"
    ],
    "wof:name":"Tutnian",
    "wof:placetype":"locality"
},
  "geometry": {"coordinates":[72.81101,33.79065],"type":"Point"}
}