{
  "type": "Feature",
  "properties": {
    "gn:admin1_code":"4.0",
    "gn:asciiname":"Chak Four Hundred Twenty-two Jhang Branch",
    "gn:country_code":"PK",
    "gn:dem":169,
    "gn:feature_class":"P",
    "gn:feature_code":"PPL",
    "gn:name":"Chak Four Hundred Twenty-two Jhang Branch",
    "gn:population":0,
    "gn:timezone":"Asia/Karachi",
    "iso:country":"PK",
    "name:und_x_variant":[
        "Barlatonpur",
        "Burltonpur",
        "Chak Number Four Hundred Twenty-Two",
        "Chak Four Hundred Twenty-two Jhang Branch",
        "Ad\u0101n Khurd"
    ],
    "wof:name":"Chak Four Hundred Twenty-two Jhang Branch",
    "wof:placetype":"locality"
},
  "geometry": {"coordinates":[72.61544000000001,31.22335],"type":"Point"}
}