{
  "type": "Feature",
  "properties": {
    "gn:admin1_code":"1.0",
    "gn:asciiname":"Patao Kalle",
    "gn:country_code":"PK",
    "gn:dem":1451,
    "gn:feature_class":"P",
    "gn:feature_code":"PPL",
    "gn:name":"Patao Kalle",
    "gn:population":0,
    "gn:timezone":"Asia/Karachi",
    "iso:country":"PK",
    "name:und_x_variant":[
        "Pitao Kili"
    ],
    "wof:name":"Patao Kalle",
    "wof:placetype":"locality"
},
  "geometry": {"coordinates":[70.82969,33.58109],"type":"Point"}
}