{
  "type": "Feature",
  "properties": {
    "gn:admin1_code":"4.0",
    "gn:asciiname":"Tibba Rehmat",
    "gn:country_code":"PK",
    "gn:dem":208,
    "gn:feature_class":"P",
    "gn:feature_code":"PPL",
    "gn:name":"Tibba Rehmat",
    "gn:population":0,
    "gn:timezone":"Asia/Karachi",
    "iso:country":"PK",
    "name:und_x_variant":[
        "Kall\u0101h"
    ],
    "wof:name":"Tibba Rehmat",
    "wof:placetype":"locality"
},
  "geometry": {"coordinates":[74.11775,31.664],"type":"Point"}
}