{
  "type": "Feature",
  "properties": {
    "gn:admin1_code":"5",
    "gn:asciiname":"Bachal Shah",
    "gn:country_code":"PK",
    "gn:dem":36,
    "gn:feature_class":"P",
    "gn:feature_code":"PPL",
    "gn:name":"Bachal Shah",
    "gn:population":0,
    "gn:timezone":"Asia/Karachi",
    "iso:country":"PK",
    "wof:name":"Bachal Shah",
    "wof:placetype":"locality"
},
  "geometry": {"coordinates":[68.12120999999999,26.15355],"type":"Point"}
}