{
  "type": "Feature",
  "properties": {
    "gn:admin1_code":"4.0",
    "gn:asciiname":"Jhalar Dina Tulla",
    "gn:country_code":"PK",
    "gn:dem":154,
    "gn:feature_class":"P",
    "gn:feature_code":"PPL",
    "gn:name":"Jhalar Dina Tulla",
    "gn:population":0,
    "gn:timezone":"Asia/Karachi",
    "iso:country":"PK",
    "name:und_x_variant":[
        "Jhal\u0101r D\u012bna Tula"
    ],
    "wof:name":"Jhalar Dina Tulla",
    "wof:placetype":"locality"
},
  "geometry": {"coordinates":[72.58333,30.56667],"type":"Point"}
}