{
  "type": "Feature",
  "properties": {
    "gn:admin1_code":"5.0",
    "gn:asciiname":"Ladhe ji Veri",
    "gn:country_code":"PK",
    "gn:dem":66,
    "gn:feature_class":"P",
    "gn:feature_code":"PPL",
    "gn:name":"Ladhe ji Veri",
    "gn:population":0,
    "gn:timezone":"Asia/Karachi",
    "iso:country":"PK",
    "wof:name":"Ladhe ji Veri",
    "wof:placetype":"locality"
},
  "geometry": {"coordinates":[70.72669,24.77843],"type":"Point"}
}