{
  "type": "Feature",
  "properties": {
    "gn:admin1_code":"1.0",
    "gn:asciiname":"Kozina",
    "gn:country_code":"PK",
    "gn:dem":1842,
    "gn:feature_class":"P",
    "gn:feature_code":"PPL",
    "gn:name":"Kozina",
    "gn:population":0,
    "gn:timezone":"Asia/Karachi",
    "iso:country":"PK",
    "name:und_x_variant":[
        "Korz\u012bna"
    ],
    "wof:name":"Kozina",
    "wof:placetype":"locality"
},
  "geometry": {"coordinates":[70.74663000000002,33.77891],"type":"Point"}
}