{
  "type": "Feature",
  "properties": {
    "gn:admin1_code":"1.0",
    "gn:asciiname":"Kozina",
    "gn:country_code":"PK",
    "gn:dem":1842,
    "gn:feature_class":"P",
    "gn:feature_code":"PPL",
    "gn:name":"Kozina",
    "gn:population":0,
    "gn:timezone":"Asia/Karachi",
    "iso:country":"PK",
    "name:bos_x_preferred":[
        "Kozina"
    ],
    "name:ceb_x_preferred":[
        "Kozina"
    ],
    "name:ita_x_preferred":[
        "Cosina"
    ],
    "name:nld_x_preferred":[
        "Kozina"
    ],
    "name:pol_x_preferred":[
        "Kozina"
    ],
    "name:ron_x_preferred":[
        "Kozina"
    ],
    "name:slv_x_preferred":[
        "Kozina"
    ],
    "name:srp_x_preferred":[
        "\u041a\u043e\u0437\u0438\u043d\u0430"
    ],
    "name:ukr_x_preferred":[
        "\u041a\u043e\u0437\u0456\u043d\u0430"
    ],
    "name:und_x_variant":[
        "Korz\u012bna"
    ],
    "wof:name":"Kozina",
    "wof:placetype":"locality"
},
  "geometry": {"coordinates":[70.74663000000002,33.77891],"type":"Point"}
}