{
  "type": "Feature",
  "properties": {
    "gn:admin1_code":"4",
    "gn:asciiname":"Subalpur",
    "gn:country_code":"PK",
    "gn:dem":244,
    "gn:feature_class":"P",
    "gn:feature_code":"PPL",
    "gn:name":"Subalpur",
    "gn:population":0,
    "gn:timezone":"Asia/Karachi",
    "iso:country":"PK",
    "name:und_x_variant":[
        "Saulpur"
    ],
    "wof:name":"Subalpur",
    "wof:placetype":"locality"
},
  "geometry": {"coordinates":[74.67979,32.29609],"type":"Point"}
}