{
  "type": "Feature",
  "properties": {
    "gn:admin1_code":"4.0",
    "gn:asciiname":"Dhok Baba Muhammad Bukhsh",
    "gn:country_code":"PK",
    "gn:dem":474,
    "gn:feature_class":"P",
    "gn:feature_code":"PPL",
    "gn:name":"Dhok Baba Muhammad Bukhsh",
    "gn:population":0,
    "gn:timezone":"Asia/Karachi",
    "iso:country":"PK",
    "wof:name":"Dhok Baba Muhammad Bukhsh",
    "wof:placetype":"locality"
},
  "geometry": {"coordinates":[73.43499,33.33408],"type":"Point"}
}