{
  "type": "Feature",
  "properties": {
    "gn:admin1_code":"4.0",
    "gn:asciiname":"Mari Mian Sahib",
    "gn:country_code":"PK",
    "gn:dem":152,
    "gn:feature_class":"P",
    "gn:feature_code":"PPL",
    "gn:name":"Mari Mian Sahib",
    "gn:population":0,
    "gn:timezone":"Asia/Karachi",
    "iso:country":"PK",
    "wof:name":"Mari Mian Sahib",
    "wof:placetype":"locality"
},
  "geometry": {"coordinates":[73.17933000000002,30.0623],"type":"Point"}
}