{
  "type": "Feature",
  "properties": {
    "gn:admin1_code":"4",
    "gn:asciiname":"Chak One Hundred Twenty - Ten Right",
    "gn:country_code":"PK",
    "gn:dem":126,
    "gn:feature_class":"P",
    "gn:feature_code":"PPL",
    "gn:name":"Chak One Hundred Twenty - Ten Right",
    "gn:population":0,
    "gn:timezone":"Asia/Karachi",
    "iso:country":"PK",
    "name:und_x_variant":[
        "Chak One Hundred Twenty Ten R",
        "Chak One Hundred Twenty",
        "Chak One Hundred Twenty - Ten Right"
    ],
    "wof:name":"Chak One Hundred Twenty - Ten Right",
    "wof:placetype":"locality"
},
  "geometry": {"coordinates":[71.71624,29.93324],"type":"Point"}
}