{
  "type": "Feature",
  "properties": {
    "gn:admin1_code":"4.0",
    "gn:asciiname":"Chiari Dulal",
    "gn:country_code":"PK",
    "gn:dem":523,
    "gn:feature_class":"P",
    "gn:feature_code":"PPL",
    "gn:name":"Chiari Dulal",
    "gn:population":0,
    "gn:timezone":"Asia/Karachi",
    "iso:country":"PK",
    "name:und_x_variant":[
        "Hachari Dolal",
        "Hachi\u0101ri Dul\u0101l",
        "Chiari Dulal"
    ],
    "wof:name":"Chiari Dulal",
    "wof:placetype":"locality"
},
  "geometry": {"coordinates":[73.26358,33.29765],"type":"Point"}
}