{
  "type": "Feature",
  "properties": {
    "gn:admin1_code":"4.0",
    "gn:asciiname":"Dharangah",
    "gn:country_code":"PK",
    "gn:dem":176,
    "gn:feature_class":"P",
    "gn:feature_code":"PPL",
    "gn:name":"Dharangah",
    "gn:population":0,
    "gn:timezone":"Asia/Karachi",
    "iso:country":"PK",
    "name:und_x_variant":[
        "Dharanga",
        "Mahm\u016bd Kot"
    ],
    "wof:name":"Dharangah",
    "wof:placetype":"locality"
},
  "geometry": {"coordinates":[73.83454999999999,30.4157],"type":"Point"}
}