{
  "type": "Feature",
  "properties": {
    "gn:admin1_code":"4.0",
    "gn:asciiname":"Ziarat Chokra",
    "gn:country_code":"PK",
    "gn:dem":846,
    "gn:feature_class":"P",
    "gn:feature_code":"PPL",
    "gn:name":"Ziarat Chokra",
    "gn:population":0,
    "gn:timezone":"Asia/Karachi",
    "iso:country":"PK",
    "wof:name":"Ziarat Chokra",
    "wof:placetype":"locality"
},
  "geometry": {"coordinates":[73.52041,33.63657],"type":"Point"}
}