{
  "type": "Feature",
  "properties": {
    "gn:admin1_code":"2.0",
    "gn:asciiname":"Gurandi",
    "gn:country_code":"PK",
    "gn:dem":1652,
    "gn:feature_class":"P",
    "gn:feature_code":"PPL",
    "gn:name":"Gurandi",
    "gn:population":0,
    "gn:timezone":"Asia/Karachi",
    "iso:country":"PK",
    "wof:name":"Gurandi",
    "wof:placetype":"locality"
},
  "geometry": {"coordinates":[66.01271,28.11964],"type":"Point"}
}