{
  "type": "Feature",
  "properties": {
    "gn:admin1_code":"1",
    "gn:asciiname":"Tamre Oba",
    "gn:country_code":"PK",
    "gn:dem":1614,
    "gn:feature_class":"P",
    "gn:feature_code":"PPL",
    "gn:name":"Tamre Oba",
    "gn:population":0,
    "gn:timezone":"Asia/Karachi",
    "iso:country":"PK",
    "wof:name":"Tamre Oba",
    "wof:placetype":"locality"
},
  "geometry": {"coordinates":[69.93935,32.83267],"type":"Point"}
}