{
  "type": "Feature",
  "properties": {
    "gn:admin1_code":"3.0",
    "gn:asciiname":"Tor Kakki",
    "gn:country_code":"PK",
    "gn:dem":323,
    "gn:feature_class":"P",
    "gn:feature_code":"PPL",
    "gn:name":"Tor Kakki",
    "gn:population":0,
    "gn:timezone":"Asia/Karachi",
    "iso:country":"PK",
    "name:und_x_variant":[
        "Torkaki"
    ],
    "wof:name":"Tor Kakki",
    "wof:placetype":"locality"
},
  "geometry": {"coordinates":[70.68394000000001,32.85368],"type":"Point"}
}