{
  "type": "Feature",
  "properties": {
    "gn:admin1_code":"2.0",
    "gn:asciiname":"Goni",
    "gn:country_code":"PK",
    "gn:dem":1246,
    "gn:feature_class":"P",
    "gn:feature_code":"PPL",
    "gn:name":"Goni",
    "gn:population":0,
    "gn:timezone":"Asia/Karachi",
    "iso:country":"PK",
    "wof:name":"Goni",
    "wof:placetype":"locality"
},
  "geometry": {"coordinates":[65.91093000000001,27.47024],"type":"Point"}
}