{
  "type": "Feature",
  "properties": {
    "gn:admin1_code":"3.0",
    "gn:asciiname":"Tajko",
    "gn:country_code":"PK",
    "gn:dem":400,
    "gn:feature_class":"P",
    "gn:feature_code":"PPL",
    "gn:name":"Tajko",
    "gn:population":0,
    "gn:timezone":"Asia/Karachi",
    "iso:country":"PK",
    "name:eng_x_preferred":[
        "Tajko"
    ],
    "wof:name":"Tajko",
    "wof:placetype":"locality"
},
  "geometry": {"coordinates":[72.28124,34.37068],"type":"Point"}
}