{
  "type": "Feature",
  "properties": {
    "gn:admin1_code":"1.0",
    "gn:asciiname":"Jarabi",
    "gn:country_code":"PK",
    "gn:dem":628,
    "gn:feature_class":"P",
    "gn:feature_code":"PPL",
    "gn:name":"Jarabi",
    "gn:population":0,
    "gn:timezone":"Asia/Karachi",
    "iso:country":"PK",
    "wof:name":"Jarabi",
    "wof:placetype":"locality"
},
  "geometry": {"coordinates":[71.75622,33.6518],"type":"Point"}
}