{
  "type": "Feature",
  "properties": {
    "gn:admin1_code":"4.0",
    "gn:asciiname":"Chak Two Hundred Seventy-one Thal Development Authority",
    "gn:country_code":"PK",
    "gn:dem":151,
    "gn:feature_class":"P",
    "gn:feature_code":"PPL",
    "gn:name":"Chak Two Hundred Seventy-one Thal Development Authority",
    "gn:population":0,
    "gn:timezone":"Asia/Karachi",
    "iso:country":"PK",
    "name:und_x_variant":[
        "Chak 271 TDA",
        "Chak Two Hundred Seventy-One TDA",
        "Chak Two Hundred Seventy-one Thal Development Authority"
    ],
    "wof:name":"Chak Two Hundred Seventy-one Thal Development Authority",
    "wof:placetype":"locality"
},
  "geometry": {"coordinates":[71.08976,31.07283],"type":"Point"}
}