{
  "type": "Feature",
  "properties": {
    "gn:admin1_code":"2.0",
    "gn:asciiname":"Kili Sheyan",
    "gn:country_code":"PK",
    "gn:dem":706,
    "gn:feature_class":"P",
    "gn:feature_code":"PPL",
    "gn:name":"Kili Sheyan",
    "gn:population":0,
    "gn:timezone":"Asia/Karachi",
    "iso:country":"PK",
    "name:und_x_variant":[
        "Nauroz\u0101b\u0101d"
    ],
    "wof:name":"Kili Sheyan",
    "wof:placetype":"locality"
},
  "geometry": {"coordinates":[65.48295999999999,28.5297],"type":"Point"}
}