{
  "type": "Feature",
  "properties": {
    "gn:admin1_code":"04",
    "gn:asciiname":"Tarechri",
    "gn:country_code":"PK",
    "gn:dem":85,
    "gn:feature_class":"P",
    "gn:feature_code":"PPL",
    "gn:name":"Tarechri",
    "gn:population":0,
    "gn:timezone":"Asia/Karachi",
    "iso:country":"PK",
    "name:und_x_variant":[
        "Trechari",
        "Tarechri"
    ],
    "wof:name":"Tarechri",
    "wof:placetype":"locality"
},
  "geometry": {"coordinates":[70.3447,28.2885],"type":"Point"}
}