{
  "type": "Feature",
  "properties": {
    "gn:admin1_code":"7.0",
    "gn:asciiname":"Chogho Gond Bulghar",
    "gn:country_code":"PK",
    "gn:dem":2477,
    "gn:feature_class":"P",
    "gn:feature_code":"PPL",
    "gn:name":"Chogho Gond Bulghar",
    "gn:population":0,
    "gn:timezone":"Asia/Karachi",
    "iso:country":"PK",
    "wof:name":"Chogho Gond Bulghar",
    "wof:placetype":"locality"
},
  "geometry": {"coordinates":[76.18325,35.23614],"type":"Point"}
}