{
  "type": "Feature",
  "properties": {
    "gn:admin1_code":"5",
    "gn:asciiname":"Rabrakhio Rajpar",
    "gn:country_code":"PK",
    "gn:dem":65,
    "gn:feature_class":"P",
    "gn:feature_code":"PPL",
    "gn:name":"Rabrakhio Rajpar",
    "gn:population":0,
    "gn:timezone":"Asia/Karachi",
    "iso:country":"PK",
    "wof:name":"Rabrakhio Rajpar",
    "wof:placetype":"locality"
},
  "geometry": {"coordinates":[68.91379999999999,26.80336],"type":"Point"}
}