{
  "type": "Feature",
  "properties": {
    "gn:admin1_code":"5.0",
    "gn:asciiname":"Goth Alma",
    "gn:country_code":"PK",
    "gn:dem":13,
    "gn:feature_class":"P",
    "gn:feature_code":"PPL",
    "gn:name":"Goth Alma",
    "gn:population":0,
    "gn:timezone":"Asia/Karachi",
    "iso:country":"PK",
    "name:und_x_variant":[
        "Goth H\u0101ji Abdull\u0101h K\u0101ndhro"
    ],
    "wof:name":"Goth Alma",
    "wof:placetype":"locality"
},
  "geometry": {"coordinates":[68.19849000000001,24.78151],"type":"Point"}
}