{
  "type": "Feature",
  "properties": {
    "gn:admin1_code":"4",
    "gn:asciiname":"Chak One Hundred Thirty-eight Gugera Branch",
    "gn:country_code":"PK",
    "gn:dem":174,
    "gn:feature_class":"P",
    "gn:feature_code":"PPL",
    "gn:name":"Chak One Hundred Thirty-eight Gugera Branch",
    "gn:population":0,
    "gn:timezone":"Asia/Karachi",
    "iso:country":"PK",
    "name:und_x_variant":[
        "Rashi\u0101na",
        "Rasi\u0101na"
    ],
    "wof:name":"Chak One Hundred Thirty-eight Gugera Branch",
    "wof:placetype":"locality"
},
  "geometry": {"coordinates":[72.90798000000002,31.10378],"type":"Point"}
}