{
  "type": "Feature",
  "properties": {
    "gn:admin1_code":"2.0",
    "gn:asciiname":"Goth Muhammad Alam Hatehani",
    "gn:country_code":"PK",
    "gn:dem":68,
    "gn:feature_class":"P",
    "gn:feature_code":"PPL",
    "gn:name":"Goth Muhammad Alam Hatehani",
    "gn:population":0,
    "gn:timezone":"Asia/Karachi",
    "iso:country":"PK",
    "name:und_x_variant":[
        "Goth Muhammad \u0100lam"
    ],
    "wof:name":"Goth Muhammad Alam Hatehani",
    "wof:placetype":"locality"
},
  "geometry": {"coordinates":[67.98506,28.40194],"type":"Point"}
}