{
  "type": "Feature",
  "properties": {
    "gn:admin1_code":"3",
    "gn:asciiname":"Shalki",
    "gn:country_code":"PK",
    "gn:dem":815,
    "gn:feature_class":"P",
    "gn:feature_code":"PPL",
    "gn:name":"Shalki",
    "gn:population":0,
    "gn:timezone":"Asia/Karachi",
    "iso:country":"PK",
    "name:und_x_variant":[
        "Tarakki"
    ],
    "wof:name":"Shalki",
    "wof:placetype":"locality"
},
  "geometry": {"coordinates":[73.09756999999998,34.30738],"type":"Point"}
}