{
  "type": "Feature",
  "properties": {
    "gn:admin1_code":"3.0",
    "gn:asciiname":"Drosh",
    "gn:country_code":"PK",
    "gn:dem":1339,
    "gn:feature_class":"P",
    "gn:feature_code":"PPL",
    "gn:name":"Drosh",
    "gn:population":0,
    "gn:timezone":"Asia/Karachi",
    "iso:country":"PK",
    "name:eng_x_preferred":[
        "Drosh"
    ],
    "name:fas_x_preferred":[
        "\u062a\u062d\u0635\u06cc\u0644 \u062f\u0631\u0648\u0634"
    ],
    "name:und_x_variant":[
        "Kila Drosh"
    ],
    "name:urd_x_preferred":[
        "\u062f\u0652\u0631\u0648\u0634"
    ],
    "name:urd_x_variant":[
        "\u062a\u062d\u0635\u06cc\u0644 \u062f\u0631\u0648\u0634"
    ],
    "wof:name":"Drosh",
    "wof:placetype":"locality"
},
  "geometry": {"coordinates":[71.79604,35.56036],"type":"Point"}
}