{
  "type": "Feature",
  "properties": {
    "gn:admin1_code":"3.0",
    "gn:asciiname":"Mian Garhi",
    "gn:country_code":"PK",
    "gn:dem":569,
    "gn:feature_class":"P",
    "gn:feature_code":"PPL",
    "gn:name":"Mian Garhi",
    "gn:population":0,
    "gn:timezone":"Asia/Karachi",
    "iso:country":"PK",
    "name:und_x_variant":[
        "Mi\u0101n Garhi"
    ],
    "wof:name":"Mian Garhi",
    "wof:placetype":"locality"
},
  "geometry": {"coordinates":[71.36678000000001,33.61037],"type":"Point"}
}