{
  "type": "Feature",
  "properties": {
    "gn:admin1_code":"7.0",
    "gn:asciiname":"Ghalu Khor",
    "gn:country_code":"PK",
    "gn:dem":2336,
    "gn:feature_class":"P",
    "gn:feature_code":"PPL",
    "gn:name":"Ghalu Khor",
    "gn:population":0,
    "gn:timezone":"Asia/Karachi",
    "iso:country":"PK",
    "wof:name":"Ghalu Khor",
    "wof:placetype":"locality"
},
  "geometry": {"coordinates":[76.02828000000002,35.18349],"type":"Point"}
}