{
  "type": "Feature",
  "properties": {
    "gn:admin1_code":"6",
    "gn:asciiname":"Khajurla",
    "gn:country_code":"PK",
    "gn:dem":949,
    "gn:feature_class":"P",
    "gn:feature_code":"PPL",
    "gn:name":"Khajurla",
    "gn:population":0,
    "gn:timezone":"Asia/Karachi",
    "iso:country":"PK",
    "name:und_x_variant":[
        "Khaj\u016brla",
        "Khojuila"
    ],
    "wof:name":"Khajurla",
    "wof:placetype":"locality"
},
  "geometry": {"coordinates":[73.99951999999998,33.36046],"type":"Point"}
}