{
  "type": "Feature",
  "properties": {
    "gn:admin1_code":"3.0",
    "gn:asciiname":"Khan Bahadur Gazi",
    "gn:country_code":"PK",
    "gn:dem":331,
    "gn:feature_class":"P",
    "gn:feature_code":"PPL",
    "gn:name":"Khan Bahadur Gazi",
    "gn:population":0,
    "gn:timezone":"Asia/Karachi",
    "iso:country":"PK",
    "name:und_x_variant":[
        "Isperka",
        "Khan Bahadur Gazi"
    ],
    "wof:name":"Khan Bahadur Gazi",
    "wof:placetype":"locality"
},
  "geometry": {"coordinates":[70.72985,32.96644000000001],"type":"Point"}
}