{
  "type": "Feature",
  "properties": {
    "gn:admin1_code":"4",
    "gn:asciiname":"Bagariil",
    "gn:country_code":"PK",
    "gn:dem":237,
    "gn:feature_class":"P",
    "gn:feature_code":"PPL",
    "gn:name":"Bagariil",
    "gn:population":0,
    "gn:timezone":"Asia/Karachi",
    "iso:country":"PK",
    "name:und_x_variant":[
        "Bogargil"
    ],
    "wof:name":"Bagariil",
    "wof:placetype":"locality"
},
  "geometry": {"coordinates":[74.61324999999999,32.24197],"type":"Point"}
}