{
  "type": "Feature",
  "properties": {
    "gn:admin1_code":"4.0",
    "gn:asciiname":"Kotoana",
    "gn:country_code":"PK",
    "gn:dem":203,
    "gn:feature_class":"P",
    "gn:feature_code":"PPL",
    "gn:name":"Kotoana",
    "gn:population":0,
    "gn:timezone":"Asia/Karachi",
    "iso:country":"PK",
    "name:und_x_variant":[
        "Kotu\u0101na"
    ],
    "wof:name":"Kotoana",
    "wof:placetype":"locality"
},
  "geometry": {"coordinates":[73.52249,31.88883],"type":"Point"}
}