{
  "type": "Feature",
  "properties": {
    "gn:admin1_code":"7.0",
    "gn:asciiname":"Chauki Jut",
    "gn:country_code":"PK",
    "gn:dem":2192,
    "gn:feature_class":"P",
    "gn:feature_code":"PPL",
    "gn:name":"Chauki Jut",
    "gn:population":0,
    "gn:timezone":"Asia/Karachi",
    "iso:country":"PK",
    "wof:name":"Chauki Jut",
    "wof:placetype":"locality"
},
  "geometry": {"coordinates":[74.3674,35.4653],"type":"Point"}
}