{
  "type": "Feature",
  "properties": {
    "gn:admin1_code":"4",
    "gn:asciiname":"Thathar",
    "gn:country_code":"PK",
    "gn:dem":736,
    "gn:feature_class":"P",
    "gn:feature_code":"PPL",
    "gn:name":"Thathar",
    "gn:population":0,
    "gn:timezone":"Asia/Karachi",
    "iso:country":"PK",
    "name:und_x_variant":[
        "Thathour",
        "Thathar"
    ],
    "wof:name":"Thathar",
    "wof:placetype":"locality"
},
  "geometry": {"coordinates":[72.12954999999999,32.42705],"type":"Point"}
}