{
  "type": "Feature",
  "properties": {
    "gn:admin1_code":"4.0",
    "gn:asciiname":"Chhapper",
    "gn:country_code":"PK",
    "gn:dem":467,
    "gn:feature_class":"P",
    "gn:feature_code":"PPL",
    "gn:name":"Chhapper",
    "gn:population":0,
    "gn:timezone":"Asia/Karachi",
    "iso:country":"PK",
    "name:und_x_variant":[
        "Gahia Chhappar"
    ],
    "wof:name":"Chhapper",
    "wof:placetype":"locality"
},
  "geometry": {"coordinates":[72.9859,33.25453],"type":"Point"}
}