{
  "type": "Feature",
  "properties": {
    "gn:admin1_code":"4",
    "gn:asciiname":"Chak One Hundred Twenty-seven -Fifteen Left",
    "gn:country_code":"PK",
    "gn:dem":155,
    "gn:feature_class":"P",
    "gn:feature_code":"PPL",
    "gn:name":"Chak One Hundred Twenty-seven -Fifteen Left",
    "gn:population":0,
    "gn:timezone":"Asia/Karachi",
    "iso:country":"PK",
    "name:und_x_variant":[
        "Gili\u0101nw\u0101la",
        "Gill\u0101nw\u0101la"
    ],
    "wof:name":"Chak One Hundred Twenty-seven -Fifteen Left",
    "wof:placetype":"locality"
},
  "geometry": {"coordinates":[72.39895,30.48283],"type":"Point"}
}