{
  "type": "Feature",
  "properties": {
    "gn:admin1_code":"4",
    "gn:asciiname":"Chak Thirty-eight",
    "gn:country_code":"PK",
    "gn:dem":194,
    "gn:feature_class":"P",
    "gn:feature_code":"PPL",
    "gn:name":"Chak Thirty-eight",
    "gn:population":0,
    "gn:timezone":"Asia/Karachi",
    "iso:country":"PK",
    "name:und_x_variant":[
        "J\u0101ngli\u0101nw\u0101la"
    ],
    "wof:name":"Chak Thirty-eight",
    "wof:placetype":"locality"
},
  "geometry": {"coordinates":[73.79753000000002,31.02417],"type":"Point"}
}