{
  "type": "Feature",
  "properties": {
    "gn:admin1_code":"5.0",
    "gn:asciiname":"Bahawal Gohrar",
    "gn:country_code":"PK",
    "gn:dem":47,
    "gn:feature_class":"P",
    "gn:feature_code":"PPL",
    "gn:name":"Bahawal Gohrar",
    "gn:population":0,
    "gn:timezone":"Asia/Karachi",
    "iso:country":"PK",
    "wof:name":"Bahawal Gohrar",
    "wof:placetype":"locality"
},
  "geometry": {"coordinates":[67.89433000000001,27.25833],"type":"Point"}
}