{
  "type": "Feature",
  "properties": {
    "gn:admin1_code":"3.0",
    "gn:asciiname":"Garhi Ayub Khan",
    "gn:country_code":"PK",
    "gn:dem":310,
    "gn:feature_class":"P",
    "gn:feature_code":"PPL",
    "gn:name":"Garhi Ayub Khan",
    "gn:population":0,
    "gn:timezone":"Asia/Karachi",
    "iso:country":"PK",
    "wof:name":"Garhi Ayub Khan",
    "wof:placetype":"locality"
},
  "geometry": {"coordinates":[71.67296999999998,33.99428],"type":"Point"}
}