{
  "type": "Feature",
  "properties": {
    "gn:admin1_code":"03",
    "gn:asciiname":"Mandao Manzai",
    "gn:country_code":"PK",
    "gn:dem":1690,
    "gn:feature_class":"P",
    "gn:feature_code":"PPL",
    "gn:name":"Mandao Manzai",
    "gn:population":0,
    "gn:timezone":"Asia/Karachi",
    "iso:country":"PK",
    "name:eng_x_preferred":[
        "Mandao Manzai"
    ],
    "wof:name":"Mandao Manzai",
    "wof:placetype":"locality"
},
  "geometry": {"coordinates":[71.90959000000002,34.95766],"type":"Point"}
}