{
  "type": "Feature",
  "properties": {
    "gn:admin1_code":"5.0",
    "gn:asciiname":"Ali Muhammad Chandio",
    "gn:country_code":"PK",
    "gn:dem":33,
    "gn:feature_class":"P",
    "gn:feature_code":"PPL",
    "gn:name":"Ali Muhammad Chandio",
    "gn:population":0,
    "gn:timezone":"Asia/Karachi",
    "iso:country":"PK",
    "name:und_x_variant":[
        "Izat Ch\u0101ndio"
    ],
    "wof:name":"Ali Muhammad Chandio",
    "wof:placetype":"locality"
},
  "geometry": {"coordinates":[68.26023000000001,26.15746],"type":"Point"}
}