{
  "type": "Feature",
  "properties": {
    "gn:admin1_code":"4",
    "gn:asciiname":"Humayun Khelanwala",
    "gn:country_code":"PK",
    "gn:dem":206,
    "gn:feature_class":"P",
    "gn:feature_code":"PPL",
    "gn:name":"Humayun Khelanwala",
    "gn:population":0,
    "gn:timezone":"Asia/Karachi",
    "iso:country":"PK",
    "name:und_x_variant":[
        "Hum\u0101y\u016bn Khelanw\u0101la"
    ],
    "wof:name":"Humayun Khelanwala",
    "wof:placetype":"locality"
},
  "geometry": {"coordinates":[71.51259,32.80602],"type":"Point"}
}