{
  "type": "Feature",
  "properties": {
    "gn:admin1_code":"3",
    "gn:asciiname":"Khunigai",
    "gn:country_code":"PK",
    "gn:dem":728,
    "gn:feature_class":"P",
    "gn:feature_code":"PPL",
    "gn:name":"Khunigai",
    "gn:population":0,
    "gn:timezone":"Asia/Karachi",
    "iso:country":"PK",
    "name:eng_x_preferred":[
        "Kh\u0101ngai"
    ],
    "name:und_x_variant":[
        "Khungai",
        "Khunigai"
    ],
    "wof:name":"Khunigai",
    "wof:placetype":"locality"
},
  "geometry": {"coordinates":[72.35348,34.39312],"type":"Point"}
}