{
  "type": "Feature",
  "properties": {
    "gn:admin1_code":"6",
    "gn:asciiname":"Kamali Chner",
    "gn:country_code":"PK",
    "gn:dem":352,
    "gn:feature_class":"P",
    "gn:feature_code":"PPL",
    "gn:name":"Kamali Chner",
    "gn:population":0,
    "gn:timezone":"Asia/Karachi",
    "iso:country":"PK",
    "name:und_x_variant":[
        "Kumauli Chhappar"
    ],
    "wof:name":"Kamali Chner",
    "wof:placetype":"locality"
},
  "geometry": {"coordinates":[74.38594999999999,32.88845999999999],"type":"Point"}
}