{
  "type": "Feature",
  "properties": {
    "gn:admin1_code":"3.0",
    "gn:asciiname":"Gurakar",
    "gn:country_code":"PK",
    "gn:dem":2258,
    "gn:feature_class":"P",
    "gn:feature_code":"PPL",
    "gn:name":"Gurakar",
    "gn:population":0,
    "gn:timezone":"Asia/Karachi",
    "iso:country":"PK",
    "wof:name":"Gurakar",
    "wof:placetype":"locality"
},
  "geometry": {"coordinates":[72.89498,34.52552],"type":"Point"}
}