{
  "type": "Feature",
  "properties": {
    "gn:admin1_code":"4.0",
    "gn:asciiname":"Ghandhi Uttar",
    "gn:country_code":"PK",
    "gn:dem":203,
    "gn:feature_class":"P",
    "gn:feature_code":"PPL",
    "gn:name":"Ghandhi Uttar",
    "gn:population":0,
    "gn:timezone":"Asia/Karachi",
    "iso:country":"PK",
    "name:und_x_variant":[
        "Gandhi Utar",
        "Gandi Utt\u0101r",
        "Ghandhi Uttar"
    ],
    "wof:name":"Ghandhi Uttar",
    "wof:placetype":"locality"
},
  "geometry": {"coordinates":[74.06466999999998,31.10941],"type":"Point"}
}