{
  "type": "Feature",
  "properties": {
    "gn:admin1_code":"3.0",
    "gn:asciiname":"Derre Plari Kalla",
    "gn:country_code":"PK",
    "gn:dem":377,
    "gn:feature_class":"P",
    "gn:feature_code":"PPL",
    "gn:name":"Derre Plari Kalla",
    "gn:population":0,
    "gn:timezone":"Asia/Karachi",
    "iso:country":"PK",
    "name:und_x_variant":[
        "Baromai",
        "Derre Pi\u0101ri Kalla",
        "Derre Plari Kalla"
    ],
    "wof:name":"Derre Plari Kalla",
    "wof:placetype":"locality"
},
  "geometry": {"coordinates":[70.91065999999999,32.92489],"type":"Point"}
}