{
  "type": "Feature",
  "properties": {
    "gn:admin1_code":"3.0",
    "gn:asciiname":"Chalor Silli",
    "gn:country_code":"PK",
    "gn:dem":1665,
    "gn:feature_class":"P",
    "gn:feature_code":"PPL",
    "gn:name":"Chalor Silli",
    "gn:population":0,
    "gn:timezone":"Asia/Karachi",
    "iso:country":"PK",
    "wof:name":"Chalor Silli",
    "wof:placetype":"locality"
},
  "geometry": {"coordinates":[70.88998000000002,33.54624],"type":"Point"}
}