{
  "type": "Feature",
  "properties": {
    "gn:admin1_code":"6.0",
    "gn:asciiname":"Budhyar",
    "gn:country_code":"PK",
    "gn:dem":486,
    "gn:feature_class":"P",
    "gn:feature_code":"PPL",
    "gn:name":"Budhyar",
    "gn:population":0,
    "gn:timezone":"Asia/Karachi",
    "iso:country":"PK",
    "name:und_x_variant":[
        "Budhy\u0101r Kal\u0101n"
    ],
    "wof:name":"Budhyar",
    "wof:placetype":"locality"
},
  "geometry": {"coordinates":[73.6121,33.19047],"type":"Point"}
}