{
  "type": "Feature",
  "properties": {
    "gn:admin1_code":"6.0",
    "gn:asciiname":"Bara-wala Khu",
    "gn:country_code":"PK",
    "gn:dem":260,
    "gn:feature_class":"P",
    "gn:feature_code":"PPL",
    "gn:name":"Bara-wala Khu",
    "gn:population":0,
    "gn:timezone":"Asia/Karachi",
    "iso:country":"PK",
    "wof:name":"Bara-wala Khu",
    "wof:placetype":"locality"
},
  "geometry": {"coordinates":[73.65926,33.1071],"type":"Point"}
}