{
  "type": "Feature",
  "properties": {
    "gn:admin1_code":"3",
    "gn:asciiname":"Bar Bargin",
    "gn:country_code":"PK",
    "gn:dem":1737,
    "gn:feature_class":"P",
    "gn:feature_code":"PPL",
    "gn:name":"Bar Bargin",
    "gn:population":0,
    "gn:timezone":"Asia/Karachi",
    "iso:country":"PK",
    "name:und_x_variant":[
        "B\u0101rg\u012bn",
        "Bar Bargin"
    ],
    "wof:name":"Bar Bargin",
    "wof:placetype":"locality"
},
  "geometry": {"coordinates":[72.52649,35.002],"type":"Point"}
}