{
  "type": "Feature",
  "properties": {
    "gn:admin1_code":"5",
    "gn:asciiname":"Imam Bakhsh Bhatti",
    "gn:country_code":"PK",
    "gn:dem":59,
    "gn:feature_class":"P",
    "gn:feature_code":"PPL",
    "gn:name":"Imam Bakhsh Bhatti",
    "gn:population":0,
    "gn:timezone":"Asia/Karachi",
    "iso:country":"PK",
    "wof:name":"Imam Bakhsh Bhatti",
    "wof:placetype":"locality"
},
  "geometry": {"coordinates":[68.44497,28.1539],"type":"Point"}
}