{
  "type": "Feature",
  "properties": {
    "gn:admin1_code":"3.0",
    "gn:asciiname":"Jani Talao",
    "gn:country_code":"PK",
    "gn:dem":509,
    "gn:feature_class":"P",
    "gn:feature_code":"PPL",
    "gn:name":"Jani Talao",
    "gn:population":0,
    "gn:timezone":"Asia/Karachi",
    "iso:country":"PK",
    "wof:name":"Jani Talao",
    "wof:placetype":"locality"
},
  "geometry": {"coordinates":[71.51824999999999,33.80751],"type":"Point"}
}