{
  "type": "Feature",
  "properties": {
    "gn:admin1_code":"4.0",
    "gn:asciiname":"Bewal",
    "gn:country_code":"PK",
    "gn:dem":472,
    "gn:feature_class":"P",
    "gn:feature_code":"PPL",
    "gn:name":"Bewal",
    "gn:population":0,
    "gn:timezone":"Asia/Karachi",
    "iso:country":"PK",
    "name:pnb_x_preferred":[
        "\u0628\u06cc\u0648\u0644"
    ],
    "name:urd_x_preferred":[
        "\u0628\u06cc\u0648\u0644"
    ],
    "wof:name":"Bewal",
    "wof:placetype":"locality"
},
  "geometry": {"coordinates":[73.44830999999998,33.33779000000001],"type":"Point"}
}