{
  "type": "Feature",
  "properties": {
    "gn:admin1_code":"2.0",
    "gn:asciiname":"Hor Bazar",
    "gn:country_code":"PK",
    "gn:dem":552,
    "gn:feature_class":"P",
    "gn:feature_code":"PPL",
    "gn:name":"Hor Bazar",
    "gn:population":0,
    "gn:timezone":"Asia/Karachi",
    "iso:country":"PK",
    "name:und_x_variant":[
        "Hor"
    ],
    "wof:name":"Hor Bazar",
    "wof:placetype":"locality"
},
  "geometry": {"coordinates":[64.63606,26.22271],"type":"Point"}
}