{
  "type": "Feature",
  "properties": {
    "gn:admin1_code":"3.0",
    "gn:asciiname":"Sheshtiabad",
    "gn:country_code":"PK",
    "gn:dem":336,
    "gn:feature_class":"P",
    "gn:feature_code":"PPL",
    "gn:name":"Sheshtiabad",
    "gn:population":0,
    "gn:timezone":"Asia/Karachi",
    "iso:country":"PK",
    "wof:name":"Sheshtiabad",
    "wof:placetype":"locality"
},
  "geometry": {"coordinates":[71.7415,34.262],"type":"Point"}
}