{
  "type": "Feature",
  "properties": {
    "gn:admin1_code":"05",
    "gn:asciiname":"Rawtani",
    "gn:country_code":"PK",
    "gn:dem":24,
    "gn:feature_class":"P",
    "gn:feature_code":"PPL",
    "gn:name":"Rawtani",
    "gn:population":0,
    "gn:timezone":"Asia/Karachi",
    "iso:country":"PK",
    "name:und_x_variant":[
        "Deh",
        "Rawtani",
        "R\u0101wati\u0101ni"
    ],
    "wof:name":"Rawtani",
    "wof:placetype":"locality"
},
  "geometry": {"coordinates":[68.81667,26.13333],"type":"Point"}
}