{
  "type": "Feature",
  "properties": {
    "gn:admin1_code":"5",
    "gn:asciiname":"Goth Hamerabah",
    "gn:country_code":"PK",
    "gn:dem":51,
    "gn:feature_class":"P",
    "gn:feature_code":"PPL",
    "gn:name":"Goth Hamerabah",
    "gn:population":0,
    "gn:timezone":"Asia/Karachi",
    "iso:country":"PK",
    "name:und_x_variant":[
        "Ham\u012br\u0101bah"
    ],
    "wof:name":"Goth Hamerabah",
    "wof:placetype":"locality"
},
  "geometry": {"coordinates":[69.49323000000001,24.79247],"type":"Point"}
}