{
  "type": "Feature",
  "properties": {
    "gn:admin1_code":"7.0",
    "gn:asciiname":"Tarkary",
    "gn:country_code":"PK",
    "gn:dem":2621,
    "gn:feature_class":"P",
    "gn:feature_code":"PPL",
    "gn:name":"Tarkary",
    "gn:population":0,
    "gn:timezone":"Asia/Karachi",
    "iso:country":"PK",
    "wof:name":"Tarkary",
    "wof:placetype":"locality"
},
  "geometry": {"coordinates":[76.43496999999998,35.155],"type":"Point"}
}