{
  "type": "Feature",
  "properties": {
    "gn:admin1_code":"4.0",
    "gn:asciiname":"Jari",
    "gn:country_code":"PK",
    "gn:dem":643,
    "gn:feature_class":"P",
    "gn:feature_code":"PPL",
    "gn:name":"Jari",
    "gn:population":0,
    "gn:timezone":"Asia/Karachi",
    "iso:country":"PK",
    "name:ara_x_preferred":[
        "\u062c\u0627\u0631\u064a"
    ],
    "name:ben_x_preferred":[
        "\u099c\u09be\u09b0\u09bf"
    ],
    "name:ceb_x_preferred":[
        "Jari"
    ],
    "name:ces_x_preferred":[
        "Jari"
    ],
    "name:deu_x_preferred":[
        "Rio Jari"
    ],
    "name:deu_x_variant":[
        "Jari"
    ],
    "name:ell_x_preferred":[
        "\u03a4\u03b6\u03ac\u03c1\u03b9"
    ],
    "name:fas_x_preferred":[
        "\u062c\u0627\u0631\u06cc"
    ],
    "name:fin_x_preferred":[
        "Jari"
    ],
    "name:fra_x_preferred":[
        "Rio Jari"
    ],
    "name:fra_x_variant":[
        "Jari"
    ],
    "name:heb_x_preferred":[
        "\u05d2'\u05d0\u05e8\u05d9"
    ],
    "name:hin_x_preferred":[
        "\u091c\u0930\u0940"
    ],
    "name:hun_x_preferred":[
        "Jari"
    ],
    "name:ind_x_preferred":[
        "Jari"
    ],
    "name:ita_x_preferred":[
        "Jari"
    ],
    "name:jpn_x_preferred":[
        "\u30b8\u30e3\u30ea\u5ddd"
    ],
    "name:kor_x_preferred":[
        "\uc790\ub9ac"
    ],
    "name:nld_x_preferred":[
        "Jari"
    ],
    "name:pol_x_preferred":[
        "Jari"
    ],
    "name:por_x_preferred":[
        "Jari"
    ],
    "name:rus_x_preferred":[
        "\u0440\u0435\u043a\u0430 \u0416\u0430\u0440\u0438"
    ],
    "name:spa_x_preferred":[
        "Jari"
    ],
    "name:swe_x_preferred":[
        "Jarifloden"
    ],
    "name:swe_x_variant":[
        "Jari"
    ],
    "name:tur_x_preferred":[
        "Jari"
    ],
    "name:ukr_x_preferred":[
        "\u0416\u0430\u0440\u0456"
    ],
    "name:urd_x_preferred":[
        "\u062c\u0627\u0631\u06cc"
    ],
    "name:vie_x_preferred":[
        "S\u00f4ng Jari"
    ],
    "name:zho_cn_x_preferred":[
        "\u672d\u91cc\u6cb3"
    ],
    "name:zho_tw_x_preferred":[
        "\u96c5\u91cc\u6cb3"
    ],
    "wof:name":"Jari",
    "wof:placetype":"locality"
},
  "geometry": {"coordinates":[73.36718999999999,33.51836],"type":"Point"}
}