{
  "type": "Feature",
  "properties": {
    "gn:admin1_code":"4.0",
    "gn:asciiname":"Jari",
    "gn:country_code":"PK",
    "gn:dem":643,
    "gn:feature_class":"P",
    "gn:feature_code":"PPL",
    "gn:name":"Jari",
    "gn:population":0,
    "gn:timezone":"Asia/Karachi",
    "iso:country":"PK",
    "wof:name":"Jari",
    "wof:placetype":"locality"
},
  "geometry": {"coordinates":[73.36719000000002,33.51835999999999],"type":"Point"}
}