{
  "type": "Feature",
  "properties": {
    "gn:admin1_code":"4.0",
    "gn:asciiname":"Jari",
    "gn:country_code":"PK",
    "gn:dem":643,
    "gn:feature_class":"P",
    "gn:feature_code":"PPL",
    "gn:name":"Jari",
    "gn:population":0,
    "gn:timezone":"Asia/Karachi",
    "iso:country":"PK",
    "name:ceb_x_preferred":[
        "Jari"
    ],
    "name:ces_x_preferred":[
        "Jari"
    ],
    "name:deu_x_preferred":[
        "Jari"
    ],
    "name:fin_x_preferred":[
        "Jari"
    ],
    "name:fra_x_preferred":[
        "Jari"
    ],
    "name:nld_x_preferred":[
        "Jari"
    ],
    "name:por_x_preferred":[
        "Jari"
    ],
    "name:spa_x_preferred":[
        "Jari"
    ],
    "name:swe_x_preferred":[
        "Jari"
    ],
    "wof:name":"Jari",
    "wof:placetype":"locality"
},
  "geometry": {"coordinates":[73.36719000000002,33.51835999999999],"type":"Point"}
}