{
  "type": "Feature",
  "properties": {
    "gn:admin1_code":"4.0",
    "gn:asciiname":"Dhiro Sial",
    "gn:country_code":"PK",
    "gn:dem":174,
    "gn:feature_class":"P",
    "gn:feature_code":"PPL",
    "gn:name":"Dhiro Sial",
    "gn:population":0,
    "gn:timezone":"Asia/Karachi",
    "iso:country":"PK",
    "name:und_x_variant":[
        "Dhiro Si\u0101l",
        "Dhero Si\u0101l",
        "Dhiro Sial"
    ],
    "wof:name":"Dhiro Sial",
    "wof:placetype":"locality"
},
  "geometry": {"coordinates":[72.37495,32.00726],"type":"Point"}
}