{
  "type": "Feature",
  "properties": {
    "gn:admin1_code":"2",
    "gn:asciiname":"Sagai Band",
    "gn:country_code":"PK",
    "gn:dem":2391,
    "gn:feature_class":"P",
    "gn:feature_code":"PPL",
    "gn:name":"Sagai Band",
    "gn:population":0,
    "gn:timezone":"Asia/Karachi",
    "iso:country":"PK",
    "name:und_x_variant":[
        "Zargai Band"
    ],
    "wof:name":"Sagai Band",
    "wof:placetype":"locality"
},
  "geometry": {"coordinates":[67.70233,30.47935],"type":"Point"}
}