{
  "type": "Feature",
  "properties": {
    "gn:admin1_code":"4",
    "gn:asciiname":"Blndiwala",
    "gn:country_code":"PK",
    "gn:dem":114,
    "gn:feature_class":"P",
    "gn:feature_code":"PPL",
    "gn:name":"Blndiwala",
    "gn:population":0,
    "gn:timezone":"Asia/Karachi",
    "iso:country":"PK",
    "name:und_x_variant":[
        "Bulaidhmdiw\u0101la"
    ],
    "wof:name":"Blndiwala",
    "wof:placetype":"locality"
},
  "geometry": {"coordinates":[70.54432,29.92497],"type":"Point"}
}