{
  "type": "Feature",
  "properties": {
    "gn:admin1_code":"4",
    "gn:asciiname":"Ruhiwala Khuh",
    "gn:country_code":"PK",
    "gn:dem":202,
    "gn:feature_class":"P",
    "gn:feature_code":"PPL",
    "gn:name":"Ruh\u012bw\u0101la Kh\u016bh",
    "gn:population":0,
    "gn:timezone":"Asia/Karachi",
    "iso:country":"PK",
    "wof:name":"Ruhiwala Khuh",
    "wof:placetype":"locality"
},
  "geometry": {"coordinates":[73.70833,31.825],"type":"Point"}
}