{
  "type": "Feature",
  "properties": {
    "gn:admin1_code":"2.0",
    "gn:asciiname":"Joda Kalat",
    "gn:country_code":"PK",
    "gn:dem":715,
    "gn:feature_class":"P",
    "gn:feature_code":"PPL",
    "gn:name":"Joda Kalat",
    "gn:population":0,
    "gn:timezone":"Asia/Karachi",
    "iso:country":"PK",
    "name:und_x_variant":[
        "Jad\u0101i Kal\u0101t"
    ],
    "wof:name":"Joda Kalat",
    "wof:placetype":"locality"
},
  "geometry": {"coordinates":[65.49929,28.45511],"type":"Point"}
}