{
  "type": "Feature",
  "properties": {
    "gn:admin1_code":"2.0",
    "gn:asciiname":"Hajiabad",
    "gn:country_code":"PK",
    "gn:dem":896,
    "gn:feature_class":"P",
    "gn:feature_code":"PPL",
    "gn:name":"Hajiabad",
    "gn:population":0,
    "gn:timezone":"Asia/Karachi",
    "iso:country":"PK",
    "name:und_x_variant":[
        "Surtag\u0101n Jhao",
        "Surtag\u0101n Jhoo",
        "Hajiabad"
    ],
    "wof:name":"Hajiabad",
    "wof:placetype":"locality"
},
  "geometry": {"coordinates":[64.56978000000001,26.45857],"type":"Point"}
}