{
  "type": "Feature",
  "properties": {
    "gn:admin1_code":"6.0",
    "gn:asciiname":"Jhangral",
    "gn:country_code":"PK",
    "gn:dem":410,
    "gn:feature_class":"P",
    "gn:feature_code":"PPL",
    "gn:name":"Jhangral",
    "gn:population":0,
    "gn:timezone":"Asia/Karachi",
    "iso:country":"PK",
    "name:und_x_variant":[
        "Jhangiral",
        "Jhangri\u0101l",
        "Jhangral"
    ],
    "wof:name":"Jhangral",
    "wof:placetype":"locality"
},
  "geometry": {"coordinates":[73.57843000000003,33.21276],"type":"Point"}
}