{
  "type": "Feature",
  "properties": {
    "gn:admin1_code":"4.0",
    "gn:asciiname":"Kadarpur",
    "gn:country_code":"PK",
    "gn:dem":166,
    "gn:feature_class":"P",
    "gn:feature_code":"PPL",
    "gn:name":"Kadarpur",
    "gn:population":0,
    "gn:timezone":"Asia/Karachi",
    "iso:country":"PK",
    "name:und_x_variant":[
        "Kora Khu"
    ],
    "wof:name":"Kadarpur",
    "wof:placetype":"locality"
},
  "geometry": {"coordinates":[73.55332,30.18551],"type":"Point"}
}