{
  "type": "Feature",
  "properties": {
    "gn:admin1_code":"6",
    "gn:asciiname":"Bhir",
    "gn:country_code":"PK",
    "gn:dem":2027,
    "gn:feature_class":"P",
    "gn:feature_code":"PPL",
    "gn:name":"Bhir",
    "gn:population":0,
    "gn:timezone":"Asia/Karachi",
    "iso:country":"PK",
    "name:und_x_variant":[
        "Phir",
        "Ph\u012br"
    ],
    "wof:name":"Bhir",
    "wof:placetype":"locality"
},
  "geometry": {"coordinates":[74.09040999999998,33.90749],"type":"Point"}
}