{
  "type": "Feature",
  "properties": {
    "gn:admin1_code":"3",
    "gn:asciiname":"Chilonai",
    "gn:country_code":"PK",
    "gn:dem":1270,
    "gn:feature_class":"P",
    "gn:feature_code":"PPL",
    "gn:name":"Chilonai",
    "gn:population":0,
    "gn:timezone":"Asia/Karachi",
    "iso:country":"PK",
    "wof:name":"Chilonai",
    "wof:placetype":"locality"
},
  "geometry": {"coordinates":[73.06744999999999,34.61768],"type":"Point"}
}