{
  "type": "Feature",
  "properties": {
    "gn:admin1_code":"2.0",
    "gn:asciiname":"Phal Dal",
    "gn:country_code":"PK",
    "gn:dem":2948,
    "gn:feature_class":"P",
    "gn:feature_code":"PPL",
    "gn:name":"Phal Dal",
    "gn:population":0,
    "gn:timezone":"Asia/Karachi",
    "iso:country":"PK",
    "wof:name":"Phal Dal",
    "wof:placetype":"locality"
},
  "geometry": {"coordinates":[67.7869,30.3492],"type":"Point"}
}