{
  "type": "Feature",
  "properties": {
    "gn:admin1_code":"4",
    "gn:asciiname":"Sharifabad",
    "gn:country_code":"PK",
    "gn:dem":143,
    "gn:feature_class":"P",
    "gn:feature_code":"PPL",
    "gn:name":"Sharifabad",
    "gn:population":0,
    "gn:timezone":"Asia/Karachi",
    "iso:country":"PK",
    "name:aze_x_preferred":[
        "\u015e\u0259rifabad"
    ],
    "name:eng_x_preferred":[
        "Sharifabad"
    ],
    "name:fas_x_preferred":[
        "\u0634\u0631\u06cc\u0641\u200c\u0622\u0628\u0627\u062f"
    ],
    "name:rus_x_preferred":[
        "\u0428\u0435\u0440\u0438\u0444\u0430\u0431\u0430\u0434"
    ],
    "name:urd_x_preferred":[
        "\u0634\u0631\u0641 \u0622\u0628\u0627\u062f"
    ],
    "wof:name":"Sharifabad",
    "wof:placetype":"locality"
},
  "geometry": {"coordinates":[71.91768,30.93598],"type":"Point"}
}