{
  "type": "Feature",
  "properties": {
    "gn:admin1_code":"2",
    "gn:asciiname":"Moedrah",
    "gn:country_code":"PK",
    "gn:dem":72,
    "gn:feature_class":"P",
    "gn:feature_code":"PPL",
    "gn:name":"Moedrah",
    "gn:population":0,
    "gn:timezone":"Asia/Karachi",
    "iso:country":"PK",
    "name:eng_x_preferred":[
        "Goth H\u0101ji Motiah Mondrah"
    ],
    "wof:name":"Moedrah",
    "wof:placetype":"locality"
},
  "geometry": {"coordinates":[66.81506,25.21729],"type":"Point"}
}