{
  "type": "Feature",
  "properties": {
    "gn:admin1_code":"6",
    "gn:asciiname":"Malkal",
    "gn:country_code":"PK",
    "gn:dem":918,
    "gn:feature_class":"P",
    "gn:feature_code":"PPL",
    "gn:name":"Malkal",
    "gn:population":0,
    "gn:timezone":"Asia/Karachi",
    "iso:country":"PK",
    "wof:name":"Malkal",
    "wof:placetype":"locality"
},
  "geometry": {"coordinates":[73.93216,33.43422],"type":"Point"}
}