{
  "type": "Feature",
  "properties": {
    "gn:admin1_code":"3.0",
    "gn:asciiname":"Shikrai Baba",
    "gn:country_code":"PK",
    "gn:dem":366,
    "gn:feature_class":"P",
    "gn:feature_code":"PPL",
    "gn:name":"Shikrai Baba",
    "gn:population":0,
    "gn:timezone":"Asia/Karachi",
    "iso:country":"PK",
    "wof:name":"Shikrai Baba",
    "wof:placetype":"locality"
},
  "geometry": {"coordinates":[72.0805,34.33304],"type":"Point"}
}