{
  "type": "Feature",
  "properties": {
    "gn:admin1_code":"4.0",
    "gn:asciiname":"Umar Khan",
    "gn:country_code":"PK",
    "gn:dem":255,
    "gn:feature_class":"P",
    "gn:feature_code":"PPL",
    "gn:name":"Umar Khan",
    "gn:population":0,
    "gn:timezone":"Asia/Karachi",
    "iso:country":"PK",
    "wof:name":"Umar Khan",
    "wof:placetype":"locality"
},
  "geometry": {"coordinates":[71.27099,32.86433],"type":"Point"}
}