{
  "type": "Feature",
  "properties": {
    "gn:admin1_code":"4.0",
    "gn:asciiname":"Bhaianwala Khurd",
    "gn:country_code":"PK",
    "gn:dem":212,
    "gn:feature_class":"P",
    "gn:feature_code":"PPL",
    "gn:name":"Bhaianwala Khurd",
    "gn:population":0,
    "gn:timezone":"Asia/Karachi",
    "iso:country":"PK",
    "name:und_x_variant":[
        "Bhi\u0101nw\u0101la Khurd"
    ],
    "wof:name":"Bhaianwala Khurd",
    "wof:placetype":"locality"
},
  "geometry": {"coordinates":[74.22678000000001,31.79527],"type":"Point"}
}