{
  "type": "Feature",
  "properties": {
    "gn:admin1_code":"4",
    "gn:asciiname":"Gurha Nagial",
    "gn:country_code":"PK",
    "gn:dem":270,
    "gn:feature_class":"P",
    "gn:feature_code":"PPL",
    "gn:name":"Gurha Nagial",
    "gn:population":0,
    "gn:timezone":"Asia/Karachi",
    "iso:country":"PK",
    "name:und_x_variant":[
        "Gora Nagi\u0101l"
    ],
    "wof:name":"Gurha Nagial",
    "wof:placetype":"locality"
},
  "geometry": {"coordinates":[73.86306,32.97805],"type":"Point"}
}