{
  "type": "Feature",
  "properties": {
    "gn:admin1_code":"5",
    "gn:asciiname":"Ali Hasan",
    "gn:country_code":"PK",
    "gn:dem":51,
    "gn:feature_class":"P",
    "gn:feature_code":"PPL",
    "gn:name":"Ali Hasan",
    "gn:population":0,
    "gn:timezone":"Asia/Karachi",
    "iso:country":"PK",
    "name:ara_x_preferred":[
        "\u0639\u0644\u064a \u062d\u0633\u0646"
    ],
    "wof:name":"Ali Hasan",
    "wof:placetype":"locality"
},
  "geometry": {"coordinates":[68.32639,27.06667],"type":"Point"}
}