{
  "type": "Feature",
  "properties": {
    "gn:admin1_code":"5.0",
    "gn:asciiname":"Goth Smun Khan Bhambhro",
    "gn:country_code":"PK",
    "gn:dem":56,
    "gn:feature_class":"P",
    "gn:feature_code":"PPL",
    "gn:name":"Goth Smun Khan Bhambhro",
    "gn:population":0,
    "gn:timezone":"Asia/Karachi",
    "iso:country":"PK",
    "wof:name":"Goth Smun Khan Bhambhro",
    "wof:placetype":"locality"
},
  "geometry": {"coordinates":[69.08143000000001,27.40625],"type":"Point"}
}