{
  "type": "Feature",
  "properties": {
    "gn:admin1_code":"7.0",
    "gn:asciiname":"Juti Harai",
    "gn:country_code":"PK",
    "gn:dem":3950,
    "gn:feature_class":"P",
    "gn:feature_code":"PPL",
    "gn:name":"Juti Harai",
    "gn:population":0,
    "gn:timezone":"Asia/Karachi",
    "iso:country":"PK",
    "wof:name":"Juti Harai",
    "wof:placetype":"locality"
},
  "geometry": {"coordinates":[73.60936,36.12796],"type":"Point"}
}