{
  "type": "Feature",
  "properties": {
    "gn:admin1_code":"4.0",
    "gn:asciiname":"Dulla Khu",
    "gn:country_code":"PK",
    "gn:dem":141,
    "gn:feature_class":"P",
    "gn:feature_code":"PPL",
    "gn:name":"Dulla Khu",
    "gn:population":0,
    "gn:timezone":"Asia/Karachi",
    "iso:country":"PK",
    "wof:name":"Dulla Khu",
    "wof:placetype":"locality"
},
  "geometry": {"coordinates":[71.11874,30.71364],"type":"Point"}
}