{
  "type": "Feature",
  "properties": {
    "gn:admin1_code":"5.0",
    "gn:asciiname":"Gupchani",
    "gn:country_code":"PK",
    "gn:dem":29,
    "gn:feature_class":"P",
    "gn:feature_code":"PPL",
    "gn:name":"Gupchani",
    "gn:population":0,
    "gn:timezone":"Asia/Karachi",
    "iso:country":"PK",
    "name:und_x_variant":[
        "Gub Ch\u00e1ni",
        "Gupchani"
    ],
    "wof:name":"Gupchani",
    "wof:placetype":"locality"
},
  "geometry": {"coordinates":[68.55112,26.19574],"type":"Point"}
}