{
  "type": "Feature",
  "properties": {
    "gn:admin1_code":"4.0",
    "gn:asciiname":"Ziarat Pir Inayat Shah",
    "gn:country_code":"PK",
    "gn:dem":127,
    "gn:feature_class":"P",
    "gn:feature_code":"PPL",
    "gn:name":"Ziarat Pir Inayat Shah",
    "gn:population":0,
    "gn:timezone":"Asia/Karachi",
    "iso:country":"PK",
    "wof:name":"Ziarat Pir Inayat Shah",
    "wof:placetype":"locality"
},
  "geometry": {"coordinates":[71.76949999999999,30.17288],"type":"Point"}
}