{
  "type": "Feature",
  "properties": {
    "gn:admin1_code":"4.0",
    "gn:asciiname":"Chak Talla",
    "gn:country_code":"PK",
    "gn:dem":289,
    "gn:feature_class":"P",
    "gn:feature_code":"PPL",
    "gn:name":"Chak Talla",
    "gn:population":0,
    "gn:timezone":"Asia/Karachi",
    "iso:country":"PK",
    "wof:name":"Chak Talla",
    "wof:placetype":"locality"
},
  "geometry": {"coordinates":[75.17171999999999,32.40364],"type":"Point"}
}