{
  "type": "Feature",
  "properties": {
    "gn:admin1_code":"4.0",
    "gn:asciiname":"Dhok Nawab",
    "gn:country_code":"PK",
    "gn:dem":465,
    "gn:feature_class":"P",
    "gn:feature_code":"PPL",
    "gn:name":"Dhok Nawab",
    "gn:population":0,
    "gn:timezone":"Asia/Karachi",
    "iso:country":"PK",
    "name:und_x_variant":[
        "Dhok Naw\u0101bw\u0101li"
    ],
    "wof:name":"Dhok Nawab",
    "wof:placetype":"locality"
},
  "geometry": {"coordinates":[72.78928000000001,33.43035],"type":"Point"}
}