{
  "type": "Feature",
  "properties": {
    "gn:admin1_code":"4",
    "gn:asciiname":"Dera Mallahwala",
    "gn:country_code":"PK",
    "gn:dem":193,
    "gn:feature_class":"P",
    "gn:feature_code":"PPL",
    "gn:name":"Dera Mallahwala",
    "gn:population":0,
    "gn:timezone":"Asia/Karachi",
    "iso:country":"PK",
    "name:und_x_variant":[
        "Daphar Malah\u0101da"
    ],
    "wof:name":"Dera Mallahwala",
    "wof:placetype":"locality"
},
  "geometry": {"coordinates":[73.23669,32.00521],"type":"Point"}
}