{
  "type": "Feature",
  "properties": {
    "gn:admin1_code":"4",
    "gn:asciiname":"Samudari Sadat",
    "gn:country_code":"PK",
    "gn:dem":127,
    "gn:feature_class":"P",
    "gn:feature_code":"PPL",
    "gn:name":"Samudari Sadat",
    "gn:population":0,
    "gn:timezone":"Asia/Karachi",
    "iso:country":"PK",
    "name:und_x_variant":[
        "D\u012bw\u0101nw\u0101l",
        "Samundriw\u0101la",
        "Samudari Sadat"
    ],
    "wof:name":"Samudari Sadat",
    "wof:placetype":"locality"
},
  "geometry": {"coordinates":[71.54451999999998,30.30883],"type":"Point"}
}