{
  "type": "Feature",
  "properties": {
    "gn:admin1_code":"2.0",
    "gn:asciiname":"Iskalku",
    "gn:country_code":"PK",
    "gn:dem":2137,
    "gn:feature_class":"P",
    "gn:feature_code":"PPL",
    "gn:name":"Iskalku",
    "gn:population":0,
    "gn:timezone":"Asia/Karachi",
    "iso:country":"PK",
    "name:und_x_variant":[
        "Iskalkoo",
        "Iskalku"
    ],
    "wof:name":"Iskalku",
    "wof:placetype":"locality"
},
  "geometry": {"coordinates":[66.67371,29.03242],"type":"Point"}
}