{
  "type": "Feature",
  "properties": {
    "gn:admin1_code":"2.0",
    "gn:asciiname":"Goth Dhamnani",
    "gn:country_code":"PK",
    "gn:dem":53,
    "gn:feature_class":"P",
    "gn:feature_code":"PPL",
    "gn:name":"Goth Dhamnani",
    "gn:population":0,
    "gn:timezone":"Asia/Karachi",
    "iso:country":"PK",
    "name:und_x_variant":[
        "Goth Dhamnan"
    ],
    "wof:name":"Goth Dhamnani",
    "wof:placetype":"locality"
},
  "geometry": {"coordinates":[66.66034999999999,25.82376],"type":"Point"}
}