{
  "type": "Feature",
  "properties": {
    "gn:admin1_code":"4",
    "gn:asciiname":"Malikwala",
    "gn:country_code":"PK",
    "gn:dem":149,
    "gn:feature_class":"P",
    "gn:feature_code":"PPL",
    "gn:name":"Malikwala",
    "gn:population":0,
    "gn:timezone":"Asia/Karachi",
    "iso:country":"PK",
    "wof:name":"Malikwala",
    "wof:placetype":"locality"
},
  "geometry": {"coordinates":[71.60129999999999,31.02128],"type":"Point"}
}