{
  "type": "Feature",
  "properties": {
    "gn:admin1_code":"4.0",
    "gn:asciiname":"Saleha",
    "gn:country_code":"PK",
    "gn:dem":961,
    "gn:feature_class":"P",
    "gn:feature_code":"PPL",
    "gn:name":"Saleha",
    "gn:population":0,
    "gn:timezone":"Asia/Karachi",
    "iso:country":"PK",
    "name:eng_x_preferred":[
        "Saleha"
    ],
    "wof:name":"Saleha",
    "wof:placetype":"locality"
},
  "geometry": {"coordinates":[73.37827,33.79543],"type":"Point"}
}