{
  "type": "Feature",
  "properties": {
    "gn:admin1_code":"6",
    "gn:asciiname":"Jubot",
    "gn:country_code":"PK",
    "gn:dem":355,
    "gn:feature_class":"P",
    "gn:feature_code":"PPL",
    "gn:name":"Jubot",
    "gn:population":0,
    "gn:timezone":"Asia/Karachi",
    "iso:country":"PK",
    "wof:name":"Jubot",
    "wof:placetype":"locality"
},
  "geometry": {"coordinates":[73.79754,33.19014],"type":"Point"}
}