{
  "type": "Feature",
  "properties": {
    "gn:admin1_code":"3.0",
    "gn:asciiname":"Faruqabad",
    "gn:country_code":"PK",
    "gn:dem":344,
    "gn:feature_class":"P",
    "gn:feature_code":"PPL",
    "gn:name":"Faruqabad",
    "gn:population":0,
    "gn:timezone":"Asia/Karachi",
    "iso:country":"PK",
    "wof:name":"Faruqabad",
    "wof:placetype":"locality"
},
  "geometry": {"coordinates":[72.11462,34.03868],"type":"Point"}
}