{
  "type": "Feature",
  "properties": {
    "gn:admin1_code":"03",
    "gn:asciiname":"Lohigal Ghari",
    "gn:country_code":"PK",
    "gn:dem":4007,
    "gn:feature_class":"P",
    "gn:feature_code":"PPL",
    "gn:name":"Lohigal Gh\u0101ri",
    "gn:population":0,
    "gn:timezone":"Asia/Karachi",
    "iso:country":"PK",
    "wof:name":"Lohigal Ghari",
    "wof:placetype":"locality"
},
  "geometry": {"coordinates":[72.16930000000001,35.8736],"type":"Point"}
}