{
  "type": "Feature",
  "properties": {
    "gn:admin1_code":"3.0",
    "gn:asciiname":"Thandanar Baihk",
    "gn:country_code":"PK",
    "gn:dem":3838,
    "gn:feature_class":"P",
    "gn:feature_code":"PPL",
    "gn:name":"Thandanar Baihk",
    "gn:population":0,
    "gn:timezone":"Asia/Karachi",
    "iso:country":"PK",
    "wof:name":"Thandanar Baihk",
    "wof:placetype":"locality"
},
  "geometry": {"coordinates":[74.01819999999999,35.1021],"type":"Point"}
}