{
  "type": "Feature",
  "properties": {
    "gn:admin1_code":"1.0",
    "gn:asciiname":"Gulmarjan Kala",
    "gn:country_code":"PK",
    "gn:dem":2424,
    "gn:feature_class":"P",
    "gn:feature_code":"PPL",
    "gn:name":"Gulmarjan Kala",
    "gn:population":0,
    "gn:timezone":"Asia/Karachi",
    "iso:country":"PK",
    "wof:name":"Gulmarjan Kala",
    "wof:placetype":"locality"
},
  "geometry": {"coordinates":[69.6485,32.72725],"type":"Point"}
}