{
  "type": "Feature",
  "properties": {
    "gn:admin1_code":"3.0",
    "gn:asciiname":"Gharambak",
    "gn:country_code":"PK",
    "gn:dem":305,
    "gn:feature_class":"P",
    "gn:feature_code":"PPL",
    "gn:name":"Gharambak",
    "gn:population":0,
    "gn:timezone":"Asia/Karachi",
    "iso:country":"PK",
    "name:eng_x_preferred":[
        "Gharambak"
    ],
    "name:und_x_variant":[
        "Ghurambak"
    ],
    "wof:name":"Gharambak",
    "wof:placetype":"locality"
},
  "geometry": {"coordinates":[71.65665,34.15039],"type":"Point"}
}