{
  "type": "Feature",
  "properties": {
    "gn:admin1_code":"4.0",
    "gn:asciiname":"Bagh Sagu",
    "gn:country_code":"PK",
    "gn:dem":151,
    "gn:feature_class":"P",
    "gn:feature_code":"PPL",
    "gn:name":"Bagh Sagu",
    "gn:population":0,
    "gn:timezone":"Asia/Karachi",
    "iso:country":"PK",
    "wof:name":"Bagh Sagu",
    "wof:placetype":"locality"
},
  "geometry": {"coordinates":[71.24127,30.99101],"type":"Point"}
}