{
  "type": "Feature",
  "properties": {
    "gn:admin1_code":"4",
    "gn:asciiname":"Basti Kumharan",
    "gn:country_code":"PK",
    "gn:dem":120,
    "gn:feature_class":"P",
    "gn:feature_code":"PPL",
    "gn:name":"Basti Kumharan",
    "gn:population":0,
    "gn:timezone":"Asia/Karachi",
    "iso:country":"PK",
    "name:und_x_variant":[
        "Kumh\u0101r\u0101n ki Basti"
    ],
    "wof:name":"Basti Kumharan",
    "wof:placetype":"locality"
},
  "geometry": {"coordinates":[71.69871999999999,29.52378],"type":"Point"}
}