{
  "type": "Feature",
  "properties": {
    "gn:admin1_code":"3.0",
    "gn:asciiname":"Kodri",
    "gn:country_code":"PK",
    "gn:dem":402,
    "gn:feature_class":"P",
    "gn:feature_code":"PPL",
    "gn:name":"Kodri",
    "gn:population":0,
    "gn:timezone":"Asia/Karachi",
    "iso:country":"PK",
    "name:eng_x_preferred":[
        "Kodar"
    ],
    "wof:name":"Kodri",
    "wof:placetype":"locality"
},
  "geometry": {"coordinates":[71.92543000000001,34.41242],"type":"Point"}
}