{
  "type": "Feature",
  "properties": {
    "gn:admin1_code":"3.0",
    "gn:asciiname":"Muhammad Wali Kalle",
    "gn:country_code":"PK",
    "gn:dem":325,
    "gn:feature_class":"P",
    "gn:feature_code":"PPL",
    "gn:name":"Muhammad Wali Kalle",
    "gn:population":0,
    "gn:timezone":"Asia/Karachi",
    "iso:country":"PK",
    "wof:name":"Muhammad Wali Kalle",
    "wof:placetype":"locality"
},
  "geometry": {"coordinates":[72.14136999999999,34.10258],"type":"Point"}
}