{
  "type": "Feature",
  "properties": {
    "gn:admin1_code":"3.0",
    "gn:asciiname":"Jabba",
    "gn:country_code":"PK",
    "gn:dem":1360,
    "gn:feature_class":"P",
    "gn:feature_code":"PPL",
    "gn:name":"Jabba",
    "gn:population":0,
    "gn:timezone":"Asia/Karachi",
    "iso:country":"PK",
    "name:ceb_x_preferred":[
        "Jabba"
    ],
    "wof:name":"Jabba",
    "wof:placetype":"locality"
},
  "geometry": {"coordinates":[72.66904,34.27993],"type":"Point"}
}