{
  "type": "Feature",
  "properties": {
    "gn:admin1_code":"5",
    "gn:asciiname":"Goth Mir Khan Abro",
    "gn:country_code":"PK",
    "gn:dem":17,
    "gn:feature_class":"P",
    "gn:feature_code":"PPL",
    "gn:name":"Goth Mir Khan Abro",
    "gn:population":0,
    "gn:timezone":"Asia/Karachi",
    "iso:country":"PK",
    "wof:name":"Goth Mir Khan Abro",
    "wof:placetype":"locality"
},
  "geometry": {"coordinates":[68.81791,25.24824],"type":"Point"}
}