{
  "type": "Feature",
  "properties": {
    "gn:admin1_code":"3",
    "gn:asciiname":"Rasulai Dheri",
    "gn:country_code":"PK",
    "gn:dem":330,
    "gn:feature_class":"P",
    "gn:feature_code":"PPL",
    "gn:name":"Rasulai Dheri",
    "gn:population":0,
    "gn:timezone":"Asia/Karachi",
    "iso:country":"PK",
    "name:eng_x_preferred":[
        "Rasoli Dheri"
    ],
    "wof:name":"Rasulai Dheri",
    "wof:placetype":"locality"
},
  "geometry": {"coordinates":[72.25978000000001,34.23689],"type":"Point"}
}