{
  "type": "Feature",
  "properties": {
    "gn:admin1_code":"4",
    "gn:asciiname":"Chak Miana",
    "gn:country_code":"PK",
    "gn:dem":229,
    "gn:feature_class":"P",
    "gn:feature_code":"PPL",
    "gn:name":"Chak Miana",
    "gn:population":0,
    "gn:timezone":"Asia/Karachi",
    "iso:country":"PK",
    "wof:name":"Chak Miana",
    "wof:placetype":"locality"
},
  "geometry": {"coordinates":[74.44889999999999,32.26580999999999],"type":"Point"}
}