{
  "type": "Feature",
  "properties": {
    "gn:admin1_code":"3.0",
    "gn:asciiname":"Naghergah Bala",
    "gn:country_code":"PK",
    "gn:dem":2390,
    "gn:feature_class":"P",
    "gn:feature_code":"PPL",
    "gn:name":"Naghergah Bala",
    "gn:population":0,
    "gn:timezone":"Asia/Karachi",
    "iso:country":"PK",
    "wof:name":"Naghergah Bala",
    "wof:placetype":"locality"
},
  "geometry": {"coordinates":[71.83010999999998,35.31706],"type":"Point"}
}