{
  "type": "Feature",
  "properties": {
    "gn:admin1_code":"3",
    "gn:asciiname":"Anangurai Tal",
    "gn:country_code":"PK",
    "gn:dem":1519,
    "gn:feature_class":"P",
    "gn:feature_code":"PPL",
    "gn:name":"Anangurai Tal",
    "gn:population":0,
    "gn:timezone":"Asia/Karachi",
    "iso:country":"PK",
    "wof:name":"Anangurai Tal",
    "wof:placetype":"locality"
},
  "geometry": {"coordinates":[72.07822,34.87033],"type":"Point"}
}