{
  "type": "Feature",
  "properties": {
    "gn:admin1_code":"5",
    "gn:asciiname":"Sain Bakhsh Rind Khadro",
    "gn:country_code":"PK",
    "gn:dem":25,
    "gn:feature_class":"P",
    "gn:feature_code":"PPL",
    "gn:name":"Sain Bakhsh Rind Khadro",
    "gn:population":0,
    "gn:timezone":"Asia/Karachi",
    "iso:country":"PK",
    "wof:name":"Sain Bakhsh Rind Khadro",
    "wof:placetype":"locality"
},
  "geometry": {"coordinates":[68.74554000000001,26.13952],"type":"Point"}
}