{
  "type": "Feature",
  "properties": {
    "gn:admin1_code":"4.0",
    "gn:asciiname":"Matamwala",
    "gn:country_code":"PK",
    "gn:dem":108,
    "gn:feature_class":"P",
    "gn:feature_code":"PPL",
    "gn:name":"Matamwala",
    "gn:population":0,
    "gn:timezone":"Asia/Karachi",
    "iso:country":"PK",
    "name:und_x_variant":[
        "Matta M\u0101lw\u0101la"
    ],
    "wof:name":"Matamwala",
    "wof:placetype":"locality"
},
  "geometry": {"coordinates":[71.3591,29.53827],"type":"Point"}
}