{
  "type": "Feature",
  "properties": {
    "gn:admin1_code":"5.0",
    "gn:asciiname":"Kalia",
    "gn:country_code":"PK",
    "gn:dem":39,
    "gn:feature_class":"P",
    "gn:feature_code":"PPL",
    "gn:name":"Kalia",
    "gn:population":0,
    "gn:timezone":"Asia/Karachi",
    "iso:country":"PK",
    "name:ceb_x_preferred":[
        "Kalia"
    ],
    "name:fra_x_preferred":[
        "Kalia"
    ],
    "name:ind_x_preferred":[
        "Kalia"
    ],
    "name:nld_x_preferred":[
        "Kalia"
    ],
    "name:swe_x_preferred":[
        "Kalia"
    ],
    "wof:name":"Kalia",
    "wof:placetype":"locality"
},
  "geometry": {"coordinates":[69.51729,24.71686],"type":"Point"}
}