{
  "type": "Feature",
  "properties": {
    "gn:admin1_code":"4",
    "gn:asciiname":"Abbawala Khu",
    "gn:country_code":"PK",
    "gn:dem":183,
    "gn:feature_class":"P",
    "gn:feature_code":"PPL",
    "gn:name":"Abbawala Khu",
    "gn:population":0,
    "gn:timezone":"Asia/Karachi",
    "iso:country":"PK",
    "name:und_x_variant":[
        "Abb\u0101w\u0101la Ch\u0101h",
        "Akbarw\u0101la",
        "Abbawala Khu"
    ],
    "wof:name":"Abbawala Khu",
    "wof:placetype":"locality"
},
  "geometry": {"coordinates":[72.96831999999998,31.68428],"type":"Point"}
}