{
  "type": "Feature",
  "properties": {
    "gn:admin1_code":"8.0",
    "gn:asciiname":"Kangrian",
    "gn:country_code":"PK",
    "gn:dem":1089,
    "gn:feature_class":"P",
    "gn:feature_code":"PPL",
    "gn:name":"Kangrian",
    "gn:population":0,
    "gn:timezone":"Asia/Karachi",
    "iso:country":"PK",
    "name:eng_x_preferred":[
        "Kangrian"
    ],
    "wof:name":"Kangrian",
    "wof:placetype":"locality"
},
  "geometry": {"coordinates":[73.0425,33.77883],"type":"Point"}
}