{
  "type": "Feature",
  "properties": {
    "gn:admin1_code":"04",
    "gn:asciiname":"Langarpur",
    "gn:country_code":"PK",
    "gn:dem":233,
    "gn:feature_class":"P",
    "gn:feature_code":"PPL",
    "gn:name":"Langarpur",
    "gn:population":0,
    "gn:timezone":"Asia/Karachi",
    "iso:country":"PK",
    "name:und_x_variant":[
        "Langerpur",
        "Langarpur"
    ],
    "wof:name":"Langarpur",
    "wof:placetype":"locality"
},
  "geometry": {"coordinates":[73.78176999999999,32.98669],"type":"Point"}
}