{
  "type": "Feature",
  "properties": {
    "gn:admin1_code":"3",
    "gn:asciiname":"Bhan",
    "gn:country_code":"PK",
    "gn:dem":888,
    "gn:feature_class":"P",
    "gn:feature_code":"PPL",
    "gn:name":"Bhan",
    "gn:population":0,
    "gn:timezone":"Asia/Karachi",
    "iso:country":"PK",
    "wof:name":"Bhan",
    "wof:placetype":"locality"
},
  "geometry": {"coordinates":[73.48239000000002,34.0864],"type":"Point"}
}