{
  "type": "Feature",
  "properties": {
    "gn:admin1_code":"3",
    "gn:asciiname":"Nangrai",
    "gn:country_code":"PK",
    "gn:dem":1354,
    "gn:feature_class":"P",
    "gn:feature_code":"PPL",
    "gn:name":"Nangrai",
    "gn:population":0,
    "gn:timezone":"Asia/Karachi",
    "iso:country":"PK",
    "name:eng_x_preferred":[
        "Nangrai"
    ],
    "wof:name":"Nangrai",
    "wof:placetype":"locality"
},
  "geometry": {"coordinates":[71.83258000000002,35.12107],"type":"Point"}
}