{
  "type": "Feature",
  "properties": {
    "gn:admin1_code":"01",
    "gn:asciiname":"Khaurai",
    "gn:country_code":"PK",
    "gn:dem":1862,
    "gn:feature_class":"P",
    "gn:feature_code":"PPL",
    "gn:name":"Khaurai",
    "gn:population":0,
    "gn:timezone":"Asia/Karachi",
    "iso:country":"PK",
    "wof:name":"Khaurai",
    "wof:placetype":"locality"
},
  "geometry": {"coordinates":[70.52361999999999,33.53708],"type":"Point"}
}