{
  "type": "Feature",
  "properties": {
    "gn:admin1_code":"04",
    "gn:asciiname":"Kot Muhabata",
    "gn:country_code":"PK",
    "gn:dem":168,
    "gn:feature_class":"P",
    "gn:feature_code":"PPL",
    "gn:name":"Kot Muhabata",
    "gn:population":0,
    "gn:timezone":"Asia/Karachi",
    "iso:country":"PK",
    "name:und_x_variant":[
        "Kot Mahabta",
        "Kot Muhabata"
    ],
    "wof:name":"Kot Muhabata",
    "wof:placetype":"locality"
},
  "geometry": {"coordinates":[72.45855999999998,31.65997],"type":"Point"}
}