{
  "type": "Feature",
  "properties": {
    "gn:admin1_code":"4.0",
    "gn:asciiname":"Chak Fourteen",
    "gn:country_code":"PK",
    "gn:dem":104,
    "gn:feature_class":"P",
    "gn:feature_code":"PPL",
    "gn:name":"Chak Fourteen",
    "gn:population":0,
    "gn:timezone":"Asia/Karachi",
    "iso:country":"PK",
    "wof:name":"Chak Fourteen",
    "wof:placetype":"locality"
},
  "geometry": {"coordinates":[71.43316,28.88566],"type":"Point"}
}