{
  "type": "Feature",
  "properties": {
    "gn:admin1_code":"3.0",
    "gn:asciiname":"Shawitakh",
    "gn:country_code":"PK",
    "gn:dem":3602,
    "gn:feature_class":"P",
    "gn:feature_code":"PPL",
    "gn:name":"Shawitakh",
    "gn:population":0,
    "gn:timezone":"Asia/Karachi",
    "iso:country":"PK",
    "name:und_x_variant":[
        "Shawitakh Gh\u0101ri"
    ],
    "wof:name":"Shawitakh",
    "wof:placetype":"locality"
},
  "geometry": {"coordinates":[73.43619,36.86035],"type":"Point"}
}