{
  "type": "Feature",
  "properties": {
    "gn:admin1_code":"1",
    "gn:asciiname":"Trikh Konr",
    "gn:country_code":"PK",
    "gn:dem":1906,
    "gn:feature_class":"P",
    "gn:feature_code":"PPL",
    "gn:name":"Trikh Konr",
    "gn:population":0,
    "gn:timezone":"Asia/Karachi",
    "iso:country":"PK",
    "wof:name":"Trikh Konr",
    "wof:placetype":"locality"
},
  "geometry": {"coordinates":[69.93865,32.69882],"type":"Point"}
}