{
  "type": "Feature",
  "properties": {
    "gn:admin1_code":"2",
    "gn:asciiname":"Loe Kach",
    "gn:country_code":"PK",
    "gn:dem":1995,
    "gn:feature_class":"P",
    "gn:feature_code":"PPL",
    "gn:name":"Loe Kach",
    "gn:population":0,
    "gn:timezone":"Asia/Karachi",
    "iso:country":"PK",
    "wof:name":"Loe Kach",
    "wof:placetype":"locality"
},
  "geometry": {"coordinates":[66.76725,31.11657],"type":"Point"}
}