{
  "type": "Feature",
  "properties": {
    "gn:admin1_code":"4",
    "gn:asciiname":"Mari Sukhe Khan",
    "gn:country_code":"PK",
    "gn:dem":176,
    "gn:feature_class":"P",
    "gn:feature_code":"PPL",
    "gn:name":"Mari Sukhe Khan",
    "gn:population":0,
    "gn:timezone":"Asia/Karachi",
    "iso:country":"PK",
    "name:und_x_variant":[
        "M\u0101ri Sh\u0101h Sukh\u0101n"
    ],
    "wof:name":"Mari Sukhe Khan",
    "wof:placetype":"locality"
},
  "geometry": {"coordinates":[72.10755999999998,31.59565],"type":"Point"}
}