{
  "type": "Feature",
  "properties": {
    "gn:admin1_code":"3.0",
    "gn:asciiname":"Jhandai",
    "gn:country_code":"PK",
    "gn:dem":324,
    "gn:feature_class":"P",
    "gn:feature_code":"PPL",
    "gn:name":"Jhandai",
    "gn:population":0,
    "gn:timezone":"Asia/Karachi",
    "iso:country":"PK",
    "wof:name":"Jhandai",
    "wof:placetype":"locality"
},
  "geometry": {"coordinates":[71.98116999999998,34.24151],"type":"Point"}
}