{
  "type": "Feature",
  "properties": {
    "gn:admin1_code":"5",
    "gn:asciiname":"Goth Pir Khaskheli",
    "gn:country_code":"PK",
    "gn:dem":38,
    "gn:feature_class":"P",
    "gn:feature_code":"PPL",
    "gn:name":"Goth Pir Khaskheli",
    "gn:population":0,
    "gn:timezone":"Asia/Karachi",
    "iso:country":"PK",
    "name:und_x_variant":[
        "\u012assu R\u0101ho"
    ],
    "wof:name":"Goth Pir Khaskheli",
    "wof:placetype":"locality"
},
  "geometry": {"coordinates":[68.07658000000001,26.36431],"type":"Point"}
}