{
  "type": "Feature",
  "properties": {
    "gn:admin1_code":"6.0",
    "gn:asciiname":"Dusut",
    "gn:country_code":"PK",
    "gn:dem":1840,
    "gn:feature_class":"P",
    "gn:feature_code":"PPL",
    "gn:name":"Dusut",
    "gn:population":0,
    "gn:timezone":"Asia/Karachi",
    "iso:country":"PK",
    "name:und_x_variant":[
        "Dusat",
        "Dusut"
    ],
    "wof:name":"Dusut",
    "wof:placetype":"locality"
},
  "geometry": {"coordinates":[74.13869,34.75377],"type":"Point"}
}