{
  "type": "Feature",
  "properties": {
    "gn:admin1_code":"4.0",
    "gn:asciiname":"Dhok Gadali",
    "gn:country_code":"PK",
    "gn:dem":627,
    "gn:feature_class":"P",
    "gn:feature_code":"PPL",
    "gn:name":"Dhok Gadali",
    "gn:population":0,
    "gn:timezone":"Asia/Karachi",
    "iso:country":"PK",
    "wof:name":"Dhok Gadali",
    "wof:placetype":"locality"
},
  "geometry": {"coordinates":[72.33671,32.76614],"type":"Point"}
}