{
  "type": "Feature",
  "properties": {
    "gn:admin1_code":"4",
    "gn:asciiname":"Garli",
    "gn:country_code":"PK",
    "gn:dem":249,
    "gn:feature_class":"P",
    "gn:feature_code":"PPL",
    "gn:name":"Garli",
    "gn:population":0,
    "gn:timezone":"Asia/Karachi",
    "iso:country":"PK",
    "name:und_x_variant":[
        "Ghari",
        "Garli",
        "Garhi"
    ],
    "wof:name":"Garli",
    "wof:placetype":"locality"
},
  "geometry": {"coordinates":[74.53690999999998,32.6561],"type":"Point"}
}