{
  "type": "Feature",
  "properties": {
    "gn:admin1_code":"4",
    "gn:asciiname":"Lalwala",
    "gn:country_code":"PK",
    "gn:dem":403,
    "gn:feature_class":"P",
    "gn:feature_code":"PPL",
    "gn:name":"Lalwala",
    "gn:population":0,
    "gn:timezone":"Asia/Karachi",
    "iso:country":"PK",
    "wof:name":"Lalwala",
    "wof:placetype":"locality"
},
  "geometry": {"coordinates":[72.08128000000001,32.96996],"type":"Point"}
}