{
  "type": "Feature",
  "properties": {
    "gn:admin1_code":"3.0",
    "gn:asciiname":"Mangal Darra",
    "gn:country_code":"PK",
    "gn:dem":1435,
    "gn:feature_class":"P",
    "gn:feature_code":"PPL",
    "gn:name":"Mangal Darra",
    "gn:population":0,
    "gn:timezone":"Asia/Karachi",
    "iso:country":"PK",
    "wof:name":"Mangal Darra",
    "wof:placetype":"locality"
},
  "geometry": {"coordinates":[73.1647,34.16615],"type":"Point"}
}