{
  "type": "Feature",
  "properties": {
    "gn:admin1_code":"5",
    "gn:asciiname":"Goth Mithu Shah",
    "gn:country_code":"PK",
    "gn:dem":27,
    "gn:feature_class":"P",
    "gn:feature_code":"PPL",
    "gn:name":"Goth Mithu Shah",
    "gn:population":0,
    "gn:timezone":"Asia/Karachi",
    "iso:country":"PK",
    "name:eng_x_preferred":[
        "Nithu Sh\u0101h"
    ],
    "wof:name":"Goth Mithu Shah",
    "wof:placetype":"locality"
},
  "geometry": {"coordinates":[68.42962,25.9227],"type":"Point"}
}