{
  "type": "Feature",
  "properties": {
    "gn:admin1_code":"05",
    "gn:asciiname":"Goth Bakhshi Malak Singh",
    "gn:country_code":"PK",
    "gn:dem":10,
    "gn:feature_class":"P",
    "gn:feature_code":"PPL",
    "gn:name":"Goth Bakhshi Malak Singh",
    "gn:population":0,
    "gn:timezone":"Asia/Karachi",
    "iso:country":"PK",
    "name:und_x_variant":[
        "Maluksing",
        "Mal\u016bk Singh",
        "Goth Bakhshi Malak Singh"
    ],
    "wof:name":"Goth Bakhshi Malak Singh",
    "wof:placetype":"locality"
},
  "geometry": {"coordinates":[69.29892,25.06786],"type":"Point"}
}