{
  "type": "Feature",
  "properties": {
    "gn:admin1_code":"4",
    "gn:asciiname":"Chak Thirty-six Western Bank",
    "gn:country_code":"PK",
    "gn:dem":139,
    "gn:feature_class":"P",
    "gn:feature_code":"PPL",
    "gn:name":"Chak Thirty-six Western Bank",
    "gn:population":0,
    "gn:timezone":"Asia/Karachi",
    "iso:country":"PK",
    "name:und_x_variant":[
        "Chak Thirty-six"
    ],
    "wof:name":"Chak Thirty-six Western Bank",
    "wof:placetype":"locality"
},
  "geometry": {"coordinates":[72.27279,30.14739],"type":"Point"}
}