{
  "type": "Feature",
  "properties": {
    "gn:admin1_code":"2.0",
    "gn:asciiname":"Muhammad Umar",
    "gn:country_code":"PK",
    "gn:dem":1368,
    "gn:feature_class":"P",
    "gn:feature_code":"PPL",
    "gn:name":"Muhammad Umar",
    "gn:population":0,
    "gn:timezone":"Asia/Karachi",
    "iso:country":"PK",
    "name:ara_x_preferred":[
        "\u0645\u062d\u0645\u062f \u0639\u0645\u0631"
    ],
    "name:pol_x_preferred":[
        "Muhammad Umar"
    ],
    "wof:name":"Muhammad Umar",
    "wof:placetype":"locality"
},
  "geometry": {"coordinates":[66.47018,30.93501],"type":"Point"}
}