{
  "type": "Feature",
  "properties": {
    "gn:admin1_code":"4.0",
    "gn:asciiname":"Basti Jam Mannu",
    "gn:country_code":"PK",
    "gn:dem":87,
    "gn:feature_class":"P",
    "gn:feature_code":"PPL",
    "gn:name":"Basti Jam Mannu",
    "gn:population":0,
    "gn:timezone":"Asia/Karachi",
    "iso:country":"PK",
    "name:und_x_variant":[
        "J\u0101m Mann\u016bn Nun\u0101ri"
    ],
    "wof:name":"Basti Jam Mannu",
    "wof:placetype":"locality"
},
  "geometry": {"coordinates":[70.22938000000001,28.65281],"type":"Point"}
}