{
  "type": "Feature",
  "properties": {
    "gn:admin1_code":"5",
    "gn:asciiname":"Behram Pahaur",
    "gn:country_code":"PK",
    "gn:dem":63,
    "gn:feature_class":"P",
    "gn:feature_code":"PPL",
    "gn:name":"Behram Pahaur",
    "gn:population":0,
    "gn:timezone":"Asia/Karachi",
    "iso:country":"PK",
    "name:und_x_variant":[
        "Behr\u0101m Pauhar"
    ],
    "wof:name":"Behram Pahaur",
    "wof:placetype":"locality"
},
  "geometry": {"coordinates":[68.80996999999999,28.07065],"type":"Point"}
}