{
  "type": "Feature",
  "properties": {
    "gn:admin1_code":"1.0",
    "gn:asciiname":"Qazi",
    "gn:country_code":"PK",
    "gn:dem":1775,
    "gn:feature_class":"P",
    "gn:feature_code":"PPL",
    "gn:name":"Qazi",
    "gn:population":0,
    "gn:timezone":"Asia/Karachi",
    "iso:country":"PK",
    "name:und_x_variant":[
        "Kuti",
        "Qazi Kili"
    ],
    "wof:name":"Qazi",
    "wof:placetype":"locality"
},
  "geometry": {"coordinates":[70.94722,33.80484000000001],"type":"Point"}
}