{
  "type": "Feature",
  "properties": {
    "gn:admin1_code":"4.0",
    "gn:asciiname":"Ihambawali Band",
    "gn:country_code":"PK",
    "gn:dem":480,
    "gn:feature_class":"P",
    "gn:feature_code":"PPL",
    "gn:name":"Ihambawali Band",
    "gn:population":0,
    "gn:timezone":"Asia/Karachi",
    "iso:country":"PK",
    "name:eng_x_preferred":[
        "Ihambawali Band"
    ],
    "wof:name":"Ihambawali Band",
    "wof:placetype":"locality"
},
  "geometry": {"coordinates":[72.87822,33.20298],"type":"Point"}
}