{
  "type": "Feature",
  "properties": {
    "gn:admin1_code":"2.0",
    "gn:asciiname":"Kili Qaim Khanzai",
    "gn:country_code":"PK",
    "gn:dem":1818,
    "gn:feature_class":"P",
    "gn:feature_code":"PPL",
    "gn:name":"Kili Qaim Khanzai",
    "gn:population":0,
    "gn:timezone":"Asia/Karachi",
    "iso:country":"PK",
    "name:und_x_variant":[
        "Giawandara"
    ],
    "wof:name":"Kili Qaim Khanzai",
    "wof:placetype":"locality"
},
  "geometry": {"coordinates":[66.42713000000001,29.08218],"type":"Point"}
}