{
  "type": "Feature",
  "properties": {
    "gn:admin1_code":"3.0",
    "gn:asciiname":"Kirri Mauladad Miankhel",
    "gn:country_code":"PK",
    "gn:dem":222,
    "gn:feature_class":"P",
    "gn:feature_code":"PPL",
    "gn:name":"Kirri Mauladad Miankhel",
    "gn:population":0,
    "gn:timezone":"Asia/Karachi",
    "iso:country":"PK",
    "name:und_x_variant":[
        "Kirri Maulad\u0101d Mian Khel"
    ],
    "wof:name":"Kirri Mauladad Miankhel",
    "wof:placetype":"locality"
},
  "geometry": {"coordinates":[70.39511,31.69097],"type":"Point"}
}