{
  "type": "Feature",
  "properties": {
    "gn:admin1_code":"4.0",
    "gn:asciiname":"Chak Four Hundred Fifty-five",
    "gn:country_code":"PK",
    "gn:dem":157,
    "gn:feature_class":"P",
    "gn:feature_code":"PPL",
    "gn:name":"Chak Four Hundred Fifty-five",
    "gn:population":0,
    "gn:timezone":"Asia/Karachi",
    "iso:country":"PK",
    "name:und_x_variant":[
        "M\u016bnriw\u0101la",
        "M\u0101driw\u0101la",
        "Chak Four Hundred Fifty-five",
        "M\u0101hi Shar\u012bf"
    ],
    "wof:name":"Chak Four Hundred Fifty-five",
    "wof:placetype":"locality"
},
  "geometry": {"coordinates":[72.42461,31.25362],"type":"Point"}
}