{
  "type": "Feature",
  "properties": {
    "gn:admin1_code":"3",
    "gn:asciiname":"Pashtonai",
    "gn:country_code":"PK",
    "gn:dem":1500,
    "gn:feature_class":"P",
    "gn:feature_code":"PPL",
    "gn:name":"Pashtonai",
    "gn:population":0,
    "gn:timezone":"Asia/Karachi",
    "iso:country":"PK",
    "name:und_x_variant":[
        "Pushtunai"
    ],
    "wof:name":"Pashtonai",
    "wof:placetype":"locality"
},
  "geometry": {"coordinates":[72.31251,35.05726],"type":"Point"}
}