{
  "type": "Feature",
  "properties": {
    "gn:admin1_code":"7.0",
    "gn:asciiname":"Burchat",
    "gn:country_code":"PK",
    "gn:dem":2929,
    "gn:feature_class":"P",
    "gn:feature_code":"PPL",
    "gn:name":"Burchat",
    "gn:population":0,
    "gn:timezone":"Asia/Karachi",
    "iso:country":"PK",
    "wof:name":"Burchat",
    "wof:placetype":"locality"
},
  "geometry": {"coordinates":[73.3248,35.71523],"type":"Point"}
}