{
  "type": "Feature",
  "properties": {
    "gn:admin1_code":"1",
    "gn:asciiname":"Baixale Kamar",
    "gn:country_code":"PK",
    "gn:dem":1420,
    "gn:feature_class":"P",
    "gn:feature_code":"PPL",
    "gn:name":"Baixale Kamar",
    "gn:population":0,
    "gn:timezone":"Asia/Karachi",
    "iso:country":"PK",
    "wof:name":"Baixale Kamar",
    "wof:placetype":"locality"
},
  "geometry": {"coordinates":[69.80616999999999,32.38008],"type":"Point"}
}