{
  "type": "Feature",
  "properties": {
    "gn:admin1_code":"1.0",
    "gn:asciiname":"Daryuba",
    "gn:country_code":"PK",
    "gn:dem":662,
    "gn:feature_class":"P",
    "gn:feature_code":"PPL",
    "gn:name":"Daryuba",
    "gn:population":0,
    "gn:timezone":"Asia/Karachi",
    "iso:country":"PK",
    "name:und_x_variant":[
        "Dary Oba"
    ],
    "wof:name":"Daryuba",
    "wof:placetype":"locality"
},
  "geometry": {"coordinates":[70.64567,33.12687],"type":"Point"}
}