{
  "type": "Feature",
  "properties": {
    "gn:admin1_code":"4.0",
    "gn:asciiname":"Khanan di Basti",
    "gn:country_code":"PK",
    "gn:dem":87,
    "gn:feature_class":"P",
    "gn:feature_code":"PPL",
    "gn:name":"Khanan di Basti",
    "gn:population":0,
    "gn:timezone":"Asia/Karachi",
    "iso:country":"PK",
    "name:und_x_variant":[
        "Tarinda S\u0101hiby\u0101r Kh\u0101n",
        "Tarinda S\u0101hiby\u0101r Kh\u016bn"
    ],
    "wof:name":"Khanan di Basti",
    "wof:placetype":"locality"
},
  "geometry": {"coordinates":[70.36223000000001,28.59819],"type":"Point"}
}