{
  "type": "Feature",
  "properties": {
    "gn:admin1_code":"4",
    "gn:asciiname":"Thatta Wasiranda",
    "gn:country_code":"PK",
    "gn:dem":206,
    "gn:feature_class":"P",
    "gn:feature_code":"PPL",
    "gn:name":"Thatta Wasiranda",
    "gn:population":0,
    "gn:timezone":"Asia/Karachi",
    "iso:country":"PK",
    "name:und_x_variant":[
        "Tatta Vas\u012br\u0101n"
    ],
    "wof:name":"Thatta Wasiranda",
    "wof:placetype":"locality"
},
  "geometry": {"coordinates":[74.15146,31.64109],"type":"Point"}
}