{
  "type": "Feature",
  "properties": {
    "gn:admin1_code":"6",
    "gn:asciiname":"Yigoban",
    "gn:country_code":"PK",
    "gn:dem":2287,
    "gn:feature_class":"P",
    "gn:feature_code":"PPL",
    "gn:name":"Yigoban",
    "gn:population":0,
    "gn:timezone":"Asia/Karachi",
    "iso:country":"PK",
    "name:und_x_variant":[
        "Yagoban",
        "Yigoban"
    ],
    "wof:name":"Yigoban",
    "wof:placetype":"locality"
},
  "geometry": {"coordinates":[74.40971999999999,34.79028],"type":"Point"}
}