{
  "type": "Feature",
  "properties": {
    "gn:admin1_code":"2",
    "gn:asciiname":"Kili Firoz Jan",
    "gn:country_code":"PK",
    "gn:dem":1946,
    "gn:feature_class":"P",
    "gn:feature_code":"PPL",
    "gn:name":"Kili Firoz Jan",
    "gn:population":0,
    "gn:timezone":"Asia/Karachi",
    "iso:country":"PK",
    "name:und_x_variant":[
        "Misri"
    ],
    "wof:name":"Kili Firoz Jan",
    "wof:placetype":"locality"
},
  "geometry": {"coordinates":[66.98891999999999,31.206],"type":"Point"}
}