{
  "type": "Feature",
  "properties": {
    "gn:admin1_code":"7.0",
    "gn:asciiname":"Abadan",
    "gn:country_code":"PK",
    "gn:dem":2693,
    "gn:feature_class":"P",
    "gn:feature_code":"PPL",
    "gn:name":"Abadan",
    "gn:population":0,
    "gn:timezone":"Asia/Karachi",
    "iso:country":"PK",
    "name:und_x_variant":[
        "Abadon"
    ],
    "wof:name":"Abadan",
    "wof:placetype":"locality"
},
  "geometry": {"coordinates":[76.48255,35.11324],"type":"Point"}
}