{
  "type": "Feature",
  "properties": {
    "gn:admin1_code":"5.0",
    "gn:asciiname":"Goth Sumar Khaskheli",
    "gn:country_code":"PK",
    "gn:dem":3,
    "gn:feature_class":"P",
    "gn:feature_code":"PPL",
    "gn:name":"Goth Sumar Khaskheli",
    "gn:population":0,
    "gn:timezone":"Asia/Karachi",
    "iso:country":"PK",
    "name:und_x_variant":[
        "Goth Sum\u0101r Kh\u0101skheli"
    ],
    "wof:name":"Goth Sumar Khaskheli",
    "wof:placetype":"locality"
},
  "geometry": {"coordinates":[67.56406,24.52945],"type":"Point"}
}