{
  "type": "Feature",
  "properties": {
    "gn:admin1_code":"03",
    "gn:asciiname":"Sarkatti Machan Khel",
    "gn:country_code":"PK",
    "gn:dem":262,
    "gn:feature_class":"P",
    "gn:feature_code":"PPL",
    "gn:name":"Sarkatti Machan Khel",
    "gn:population":0,
    "gn:timezone":"Asia/Karachi",
    "iso:country":"PK",
    "name:und_x_variant":[
        "Sarkatti",
        "Serkati Michan Khel",
        "Sarkatti Michan Khel",
        "Sarkatti Machan Khel"
    ],
    "wof:name":"Sarkatti Machan Khel",
    "wof:placetype":"locality"
},
  "geometry": {"coordinates":[70.92057,32.69035],"type":"Point"}
}