{
  "type": "Feature",
  "properties": {
    "gn:admin1_code":"3",
    "gn:asciiname":"Nawe Kalle",
    "gn:country_code":"PK",
    "gn:dem":1649,
    "gn:feature_class":"P",
    "gn:feature_code":"PPL",
    "gn:name":"Nawe Kalle",
    "gn:population":0,
    "gn:timezone":"Asia/Karachi",
    "iso:country":"PK",
    "name:und_x_variant":[
        "Nawe Kili"
    ],
    "wof:name":"Nawe Kalle",
    "wof:placetype":"locality"
},
  "geometry": {"coordinates":[72.10044000000001,34.8161],"type":"Point"}
}