{
  "type": "Feature",
  "properties": {
    "gn:admin1_code":"03",
    "gn:asciiname":"Ghund",
    "gn:country_code":"PK",
    "gn:dem":906,
    "gn:feature_class":"P",
    "gn:feature_code":"PPL",
    "gn:name":"Ghund",
    "gn:population":0,
    "gn:timezone":"Asia/Karachi",
    "iso:country":"PK",
    "name:eng_x_preferred":[
        "Ghund"
    ],
    "wof:name":"Ghund",
    "wof:placetype":"locality"
},
  "geometry": {"coordinates":[71.71007,34.62209],"type":"Point"}
}