{
  "type": "Feature",
  "properties": {
    "gn:admin1_code":"3.0",
    "gn:asciiname":"Saprai",
    "gn:country_code":"PK",
    "gn:dem":1154,
    "gn:feature_class":"P",
    "gn:feature_code":"PPL",
    "gn:name":"Saprai",
    "gn:population":0,
    "gn:timezone":"Asia/Karachi",
    "iso:country":"PK",
    "name:und_x_variant":[
        "Sirai",
        "Tsapparai"
    ],
    "wof:name":"Saprai",
    "wof:placetype":"locality"
},
  "geometry": {"coordinates":[72.61596999999998,34.36808],"type":"Point"}
}