{
  "type": "Feature",
  "properties": {
    "gn:admin1_code":"5",
    "gn:asciiname":"Imam Bakhsh Dahri",
    "gn:country_code":"PK",
    "gn:dem":40,
    "gn:feature_class":"P",
    "gn:feature_code":"PPL",
    "gn:name":"Imam Bakhsh Dahri",
    "gn:population":0,
    "gn:timezone":"Asia/Karachi",
    "iso:country":"PK",
    "wof:name":"Imam Bakhsh Dahri",
    "wof:placetype":"locality"
},
  "geometry": {"coordinates":[68.23328000000001,26.41942],"type":"Point"}
}