{
  "type": "Feature",
  "properties": {
    "gn:admin1_code":"4.0",
    "gn:asciiname":"Chohanwala",
    "gn:country_code":"PK",
    "gn:dem":147,
    "gn:feature_class":"P",
    "gn:feature_code":"PPL",
    "gn:name":"Chohanwala",
    "gn:population":0,
    "gn:timezone":"Asia/Karachi",
    "iso:country":"PK",
    "name:und_x_variant":[
        "Chhah\u0101nw\u0101la"
    ],
    "wof:name":"Chohanwala",
    "wof:placetype":"neighbourhood"
},
  "geometry": {"coordinates":[70.95122000000001,30.9802],"type":"Point"}
}