{
  "type": "Feature",
  "properties": {
    "gn:admin1_code":"02",
    "gn:asciiname":"Saruna",
    "gn:country_code":"PK",
    "gn:dem":322,
    "gn:feature_class":"P",
    "gn:feature_code":"PPL",
    "gn:name":"Saruna",
    "gn:population":0,
    "gn:timezone":"Asia/Karachi",
    "iso:country":"PK",
    "name:und_x_variant":[
        "S\u0101r\u016bna"
    ],
    "wof:name":"Saruna",
    "wof:placetype":"locality"
},
  "geometry": {"coordinates":[67.08754999999999,26.28318],"type":"Point"}
}