{
  "type": "Feature",
  "properties": {
    "gn:admin1_code":"3.0",
    "gn:asciiname":"Muhammad Yaqub Colony",
    "gn:country_code":"PK",
    "gn:dem":256,
    "gn:feature_class":"P",
    "gn:feature_code":"PPL",
    "gn:name":"Muhammad Yaqub Colony",
    "gn:population":0,
    "gn:timezone":"Asia/Karachi",
    "iso:country":"PK",
    "wof:name":"Muhammad Yaqub Colony",
    "wof:placetype":"locality"
},
  "geometry": {"coordinates":[70.37438,32.19577],"type":"Point"}
}