{
  "type": "Feature",
  "properties": {
    "gn:admin1_code":"04",
    "gn:asciiname":"Sultanpur",
    "gn:country_code":"PK",
    "gn:dem":164,
    "gn:feature_class":"P",
    "gn:feature_code":"PPL",
    "gn:name":"Sultanpur",
    "gn:population":0,
    "gn:timezone":"Asia/Karachi",
    "iso:country":"PK",
    "wof:name":"Sultanpur",
    "wof:placetype":"locality"
},
  "geometry": {"coordinates":[72.41427,31.43196],"type":"Point"}
}