{
  "type": "Feature",
  "properties": {
    "gn:admin1_code":"01",
    "gn:asciiname":"Bodin Khel",
    "gn:country_code":"PK",
    "gn:dem":1993,
    "gn:feature_class":"P",
    "gn:feature_code":"PPL",
    "gn:name":"Bodin Khel",
    "gn:population":0,
    "gn:timezone":"Asia/Karachi",
    "iso:country":"PK",
    "name:und_x_variant":[
        "Bod\u012bn"
    ],
    "wof:name":"Bodin Khel",
    "wof:placetype":"locality"
},
  "geometry": {"coordinates":[69.62194000000001,32.4925],"type":"Point"}
}