{
  "type": "Feature",
  "properties": {
    "gn:admin1_code":"3",
    "gn:asciiname":"Khinan",
    "gn:country_code":"PK",
    "gn:dem":567,
    "gn:feature_class":"P",
    "gn:feature_code":"PPL",
    "gn:name":"Kh\u012bn\u0101n",
    "gn:population":0,
    "gn:timezone":"Asia/Karachi",
    "iso:country":"PK",
    "wof:name":"Khinan",
    "wof:placetype":"locality"
},
  "geometry": {"coordinates":[71.15000000000001,32.35833],"type":"Point"}
}