{
  "type": "Feature",
  "properties": {
    "gn:admin1_code":"7.0",
    "gn:asciiname":"Moupa",
    "gn:country_code":"PK",
    "gn:dem":2525,
    "gn:feature_class":"P",
    "gn:feature_code":"PPL",
    "gn:name":"Moupa",
    "gn:population":0,
    "gn:timezone":"Asia/Karachi",
    "iso:country":"PK",
    "wof:name":"Moupa",
    "wof:placetype":"locality"
},
  "geometry": {"coordinates":[75.03169,35.69418],"type":"Point"}
}