{
  "type": "Feature",
  "properties": {
    "gn:admin1_code":"3.0",
    "gn:asciiname":"Dhok Gul Muhammad",
    "gn:country_code":"PK",
    "gn:dem":290,
    "gn:feature_class":"P",
    "gn:feature_code":"PPL",
    "gn:name":"Dhok Gul Muhammad",
    "gn:population":0,
    "gn:timezone":"Asia/Karachi",
    "iso:country":"PK",
    "wof:name":"Dhok Gul Muhammad",
    "wof:placetype":"locality"
},
  "geometry": {"coordinates":[71.98303,33.5714],"type":"Point"}
}