{
  "type": "Feature",
  "properties": {
    "gn:admin1_code":"5",
    "gn:asciiname":"Lal Bakhsh Khosa",
    "gn:country_code":"PK",
    "gn:dem":55,
    "gn:feature_class":"P",
    "gn:feature_code":"PPL",
    "gn:name":"Lal Bakhsh Khosa",
    "gn:population":0,
    "gn:timezone":"Asia/Karachi",
    "iso:country":"PK",
    "wof:name":"Lal Bakhsh Khosa",
    "wof:placetype":"locality"
},
  "geometry": {"coordinates":[68.27648000000001,28.12626],"type":"Point"}
}