{
  "type": "Feature",
  "properties": {
    "gn:admin1_code":"4",
    "gn:asciiname":"Chak Fourty-nine Southern Branch",
    "gn:country_code":"PK",
    "gn:dem":184,
    "gn:feature_class":"P",
    "gn:feature_code":"PPL",
    "gn:name":"Chak Fourty-nine Southern Branch",
    "gn:population":0,
    "gn:timezone":"Asia/Karachi",
    "iso:country":"PK",
    "name:und_x_variant":[
        "Chak Forty-nine SB"
    ],
    "wof:name":"Chak Fourty-nine Southern Branch",
    "wof:placetype":"locality"
},
  "geometry": {"coordinates":[72.68733,31.84474],"type":"Point"}
}