{
  "type": "Feature",
  "properties": {
    "gn:admin1_code":"7.0",
    "gn:asciiname":"Narikarto Harai",
    "gn:country_code":"PK",
    "gn:dem":3243,
    "gn:feature_class":"P",
    "gn:feature_code":"PPL",
    "gn:name":"Narikarto Harai",
    "gn:population":0,
    "gn:timezone":"Asia/Karachi",
    "iso:country":"PK",
    "wof:name":"Narikarto Harai",
    "wof:placetype":"locality"
},
  "geometry": {"coordinates":[73.8065,36.2508],"type":"Point"}
}