{
  "type": "Feature",
  "properties": {
    "gn:admin1_code":"04",
    "gn:asciiname":"Chak Ninety-three D",
    "gn:country_code":"PK",
    "gn:dem":164,
    "gn:feature_class":"P",
    "gn:feature_code":"PPL",
    "gn:name":"Chak Ninety-three D",
    "gn:population":0,
    "gn:timezone":"Asia/Karachi",
    "iso:country":"PK",
    "name:und_x_variant":[
        "Noorpur",
        "N\u016brpur",
        "Chak Ninety-three D"
    ],
    "wof:name":"Chak Ninety-three D",
    "wof:placetype":"locality"
},
  "geometry": {"coordinates":[73.25084,30.4923],"type":"Point"}
}