{
  "type": "Feature",
  "properties": {
    "gn:admin1_code":"4",
    "gn:asciiname":"Daoke Kananian",
    "gn:country_code":"PK",
    "gn:dem":191,
    "gn:feature_class":"P",
    "gn:feature_code":"PPL",
    "gn:name":"Daoke Kananian",
    "gn:population":0,
    "gn:timezone":"Asia/Karachi",
    "iso:country":"PK",
    "name:und_x_variant":[
        "D\u0101oke Khani\u0101na"
    ],
    "wof:name":"Daoke Kananian",
    "wof:placetype":"locality"
},
  "geometry": {"coordinates":[74.19847,30.88273],"type":"Point"}
}