{
  "type": "Feature",
  "properties": {
    "gn:admin1_code":"03",
    "gn:asciiname":"Mundai",
    "gn:country_code":"PK",
    "gn:dem":898,
    "gn:feature_class":"P",
    "gn:feature_code":"PPL",
    "gn:name":"Mundai",
    "gn:population":0,
    "gn:timezone":"Asia/Karachi",
    "iso:country":"PK",
    "name:eng_x_preferred":[
        "Mundai"
    ],
    "wof:name":"Mundai",
    "wof:placetype":"locality"
},
  "geometry": {"coordinates":[71.72133000000002,34.63484],"type":"Point"}
}