{
  "type": "Feature",
  "properties": {
    "gn:admin1_code":"4",
    "gn:asciiname":"Chah Kharuwala",
    "gn:country_code":"PK",
    "gn:dem":179,
    "gn:feature_class":"P",
    "gn:feature_code":"PPL",
    "gn:name":"Chah Kharuwala",
    "gn:population":0,
    "gn:timezone":"Asia/Karachi",
    "iso:country":"PK",
    "name:und_x_variant":[
        "Ch\u0101h Khar\u0101nw\u0101la"
    ],
    "wof:name":"Chah Kharuwala",
    "wof:placetype":"locality"
},
  "geometry": {"coordinates":[72.76992,31.80082],"type":"Point"}
}