{
  "type": "Feature",
  "properties": {
    "gn:admin1_code":"3.0",
    "gn:asciiname":"Miana Zakhai",
    "gn:country_code":"PK",
    "gn:dem":298,
    "gn:feature_class":"P",
    "gn:feature_code":"PPL",
    "gn:name":"Miana Zakhai",
    "gn:population":0,
    "gn:timezone":"Asia/Karachi",
    "iso:country":"PK",
    "name:eng_x_preferred":[
        "Zakhi Ch\u0101r B\u0101gh"
    ],
    "wof:name":"Miana Zakhai",
    "wof:placetype":"locality"
},
  "geometry": {"coordinates":[71.73215999999999,34.06395999999999],"type":"Point"}
}