{
  "type": "Feature",
  "properties": {
    "gn:admin1_code":"4",
    "gn:asciiname":"Shekhu Milyarwali",
    "gn:country_code":"PK",
    "gn:dem":751,
    "gn:feature_class":"P",
    "gn:feature_code":"PPL",
    "gn:name":"Shekhu Milyarwali",
    "gn:population":0,
    "gn:timezone":"Asia/Karachi",
    "iso:country":"PK",
    "wof:name":"Shekhu Milyarwali",
    "wof:placetype":"locality"
},
  "geometry": {"coordinates":[72.22917,32.625],"type":"Point"}
}