{
  "type": "Feature",
  "properties": {
    "gn:admin1_code":"3.0",
    "gn:asciiname":"Khujaram Khel",
    "gn:country_code":"PK",
    "gn:dem":339,
    "gn:feature_class":"P",
    "gn:feature_code":"PPL",
    "gn:name":"Khujaram Khel",
    "gn:population":0,
    "gn:timezone":"Asia/Karachi",
    "iso:country":"PK",
    "name:und_x_variant":[
        "Khuir\u0101m Khel",
        "Khajram Khel",
        "Khujaram Khel"
    ],
    "wof:name":"Khujaram Khel",
    "wof:placetype":"locality"
},
  "geometry": {"coordinates":[70.64128000000002,32.93672],"type":"Point"}
}