{
  "type": "Feature",
  "properties": {
    "gn:admin1_code":"4",
    "gn:asciiname":"Khauri",
    "gn:country_code":"PK",
    "gn:dem":272,
    "gn:feature_class":"P",
    "gn:feature_code":"PPL",
    "gn:name":"Khauri",
    "gn:population":0,
    "gn:timezone":"Asia/Karachi",
    "iso:country":"PK",
    "name:und_x_variant":[
        "Ka\u016br"
    ],
    "wof:name":"Khauri",
    "wof:placetype":"locality"
},
  "geometry": {"coordinates":[74.15208,32.74799],"type":"Point"}
}