{
  "type": "Feature",
  "properties": {
    "gn:admin1_code":"4",
    "gn:asciiname":"Jhandwal",
    "gn:country_code":"PK",
    "gn:dem":213,
    "gn:feature_class":"P",
    "gn:feature_code":"PPL",
    "gn:name":"Jhandwal",
    "gn:population":0,
    "gn:timezone":"Asia/Karachi",
    "iso:country":"PK",
    "name:und_x_variant":[
        "Jandw\u0101li"
    ],
    "wof:name":"Jhandwal",
    "wof:placetype":"locality"
},
  "geometry": {"coordinates":[73.81140000000001,32.08728],"type":"Point"}
}