{
  "type": "Feature",
  "properties": {
    "gn:admin1_code":"2.0",
    "gn:asciiname":"Kandagin Chauki",
    "gn:country_code":"PK",
    "gn:dem":759,
    "gn:feature_class":"P",
    "gn:feature_code":"PPL",
    "gn:name":"Kandagin Chauki",
    "gn:population":0,
    "gn:timezone":"Asia/Karachi",
    "iso:country":"PK",
    "wof:name":"Kandagin Chauki",
    "wof:placetype":"locality"
},
  "geometry": {"coordinates":[65.39267,26.75403],"type":"Point"}
}