{
  "type": "Feature",
  "properties": {
    "gn:admin1_code":"3.0",
    "gn:asciiname":"Ghazikot",
    "gn:country_code":"PK",
    "gn:dem":564,
    "gn:feature_class":"P",
    "gn:feature_code":"PPL",
    "gn:name":"Ghazikot",
    "gn:population":0,
    "gn:timezone":"Asia/Karachi",
    "iso:country":"PK",
    "wof:name":"Ghazikot",
    "wof:placetype":"locality"
},
  "geometry": {"coordinates":[72.83979000000002,34.50259],"type":"Point"}
}