{
  "type": "Feature",
  "properties": {
    "gn:admin1_code":"4",
    "gn:asciiname":"Chak One Hundred Forty-five Rakh Branch",
    "gn:country_code":"PK",
    "gn:dem":187,
    "gn:feature_class":"P",
    "gn:feature_code":"PPL",
    "gn:name":"Chak One Hundred Forty-five Rakh Branch",
    "gn:population":0,
    "gn:timezone":"Asia/Karachi",
    "iso:country":"PK",
    "name:und_x_variant":[
        "Wardpur",
        "Chit Singh"
    ],
    "wof:name":"Chak One Hundred Forty-five Rakh Branch",
    "wof:placetype":"locality"
},
  "geometry": {"coordinates":[73.25598000000002,31.63665],"type":"Point"}
}