{
  "type": "Feature",
  "properties": {
    "gn:admin1_code":"4.0",
    "gn:asciiname":"Dharabi",
    "gn:country_code":"PK",
    "gn:dem":416,
    "gn:feature_class":"P",
    "gn:feature_code":"PPL",
    "gn:name":"Dharabi",
    "gn:population":0,
    "gn:timezone":"Asia/Karachi",
    "iso:country":"PK",
    "name:und_x_variant":[
        "Dhr\u0101bi"
    ],
    "wof:name":"Dharabi",
    "wof:placetype":"locality"
},
  "geometry": {"coordinates":[72.53276,32.94521],"type":"Point"}
}