{
  "type": "Feature",
  "properties": {
    "gn:admin1_code":"4",
    "gn:asciiname":"Jhangar Hakam",
    "gn:country_code":"PK",
    "gn:dem":198,
    "gn:feature_class":"P",
    "gn:feature_code":"PPL",
    "gn:name":"Jhangar Hakam",
    "gn:population":0,
    "gn:timezone":"Asia/Karachi",
    "iso:country":"PK",
    "name:und_x_variant":[
        "Chhota H\u0101kimw\u0101la Jhangar"
    ],
    "wof:name":"Jhangar Hakam",
    "wof:placetype":"locality"
},
  "geometry": {"coordinates":[73.80710999999999,31.46391],"type":"Point"}
}