{
  "type": "Feature",
  "properties": {
    "gn:admin1_code":"4",
    "gn:asciiname":"Chak Forty-seven Muhajir Branch",
    "gn:country_code":"PK",
    "gn:dem":188,
    "gn:feature_class":"P",
    "gn:feature_code":"PPL",
    "gn:name":"Chak Forty-seven Muhajir Branch",
    "gn:population":0,
    "gn:timezone":"Asia/Karachi",
    "iso:country":"PK",
    "name:und_x_variant":[
        "Chak Forty-seven MB"
    ],
    "wof:name":"Chak Forty-seven Muhajir Branch",
    "wof:placetype":"locality"
},
  "geometry": {"coordinates":[72.21051,32.2245],"type":"Point"}
}