{
  "type": "Feature",
  "properties": {
    "gn:admin1_code":"4",
    "gn:asciiname":"Mathela Bhidal",
    "gn:country_code":"PK",
    "gn:dem":174,
    "gn:feature_class":"P",
    "gn:feature_code":"PPL",
    "gn:name":"Mathela Bhidal",
    "gn:population":0,
    "gn:timezone":"Asia/Karachi",
    "iso:country":"PK",
    "name:und_x_variant":[
        "Mangal Bhid\u0101l"
    ],
    "wof:name":"Mathela Bhidal",
    "wof:placetype":"locality"
},
  "geometry": {"coordinates":[73.75944,30.39318],"type":"Point"}
}