{
  "type": "Feature",
  "properties": {
    "gn:admin1_code":"4",
    "gn:asciiname":"Malanawala",
    "gn:country_code":"PK",
    "gn:dem":165,
    "gn:feature_class":"P",
    "gn:feature_code":"PPL",
    "gn:name":"Malanawala",
    "gn:population":0,
    "gn:timezone":"Asia/Karachi",
    "iso:country":"PK",
    "name:und_x_variant":[
        "Mal\u0101new\u0101la",
        "Mal\u0101new\u0101li",
        "Malanawala"
    ],
    "wof:name":"Malanawala",
    "wof:placetype":"locality"
},
  "geometry": {"coordinates":[71.03636,31.60212000000001],"type":"Point"}
}