{
  "type": "Feature",
  "properties": {
    "gn:admin1_code":"3.0",
    "gn:asciiname":"Shahidan Banda",
    "gn:country_code":"PK",
    "gn:dem":499,
    "gn:feature_class":"P",
    "gn:feature_code":"PPL",
    "gn:name":"Shahidan Banda",
    "gn:population":0,
    "gn:timezone":"Asia/Karachi",
    "iso:country":"PK",
    "wof:name":"Shahidan Banda",
    "wof:placetype":"locality"
},
  "geometry": {"coordinates":[71.0487,32.94544],"type":"Point"}
}