{
  "type": "Feature",
  "properties": {
    "gn:admin1_code":"3.0",
    "gn:asciiname":"Mir Akbar Kalla",
    "gn:country_code":"PK",
    "gn:dem":354,
    "gn:feature_class":"P",
    "gn:feature_code":"PPL",
    "gn:name":"Mir Akbar Kalla",
    "gn:population":0,
    "gn:timezone":"Asia/Karachi",
    "iso:country":"PK",
    "name:und_x_variant":[
        "M\u012br Akbar",
        "Mir Akbar Kalla"
    ],
    "wof:name":"Mir Akbar Kalla",
    "wof:placetype":"locality"
},
  "geometry": {"coordinates":[70.87883000000002,32.90600999999999],"type":"Point"}
}