{
  "type": "Feature",
  "properties": {
    "gn:admin1_code":"2.0",
    "gn:asciiname":"Salai Gwaranjo",
    "gn:country_code":"PK",
    "gn:dem":256,
    "gn:feature_class":"P",
    "gn:feature_code":"PPL",
    "gn:name":"Salai Gwaranjo",
    "gn:population":0,
    "gn:timezone":"Asia/Karachi",
    "iso:country":"PK",
    "wof:name":"Salai Gwaranjo",
    "wof:placetype":"locality"
},
  "geometry": {"coordinates":[66.18734000000001,26.39128],"type":"Point"}
}