{
  "type": "Feature",
  "properties": {
    "gn:admin1_code":"7.0",
    "gn:asciiname":"Barendas",
    "gn:country_code":"PK",
    "gn:dem":2422,
    "gn:feature_class":"P",
    "gn:feature_code":"PPL",
    "gn:name":"Barendas",
    "gn:population":0,
    "gn:timezone":"Asia/Karachi",
    "iso:country":"PK",
    "name:und_x_variant":[
        "Barandas"
    ],
    "wof:name":"Barendas",
    "wof:placetype":"locality"
},
  "geometry": {"coordinates":[73.38845999999999,36.47214],"type":"Point"}
}