{
  "type": "Feature",
  "properties": {
    "gn:admin1_code":"7.0",
    "gn:asciiname":"Marbrok",
    "gn:country_code":"PK",
    "gn:dem":3379,
    "gn:feature_class":"P",
    "gn:feature_code":"PPL",
    "gn:name":"Marbrok",
    "gn:population":0,
    "gn:timezone":"Asia/Karachi",
    "iso:country":"PK",
    "wof:name":"Marbrok",
    "wof:placetype":"locality"
},
  "geometry": {"coordinates":[76.09180000000001,35.07624000000001],"type":"Point"}
}