{
  "type": "Feature",
  "properties": {
    "gn:admin1_code":"5.0",
    "gn:asciiname":"Haji Allah Bakhsh Magsi",
    "gn:country_code":"PK",
    "gn:dem":36,
    "gn:feature_class":"P",
    "gn:feature_code":"PPL",
    "gn:name":"Haji Allah Bakhsh Magsi",
    "gn:population":0,
    "gn:timezone":"Asia/Karachi",
    "iso:country":"PK",
    "wof:name":"Haji Allah Bakhsh Magsi",
    "wof:placetype":"locality"
},
  "geometry": {"coordinates":[68.29523,26.20914],"type":"Point"}
}