{
  "type": "Feature",
  "properties": {
    "gn:admin1_code":"6",
    "gn:asciiname":"Chamran",
    "gn:country_code":"PK",
    "gn:dem":1977,
    "gn:feature_class":"P",
    "gn:feature_code":"PPL",
    "gn:name":"Chamran",
    "gn:population":0,
    "gn:timezone":"Asia/Karachi",
    "iso:country":"PK",
    "name:und_x_variant":[
        "Chhamr\u0101n"
    ],
    "wof:name":"Chamran",
    "wof:placetype":"locality"
},
  "geometry": {"coordinates":[73.65781,34.40726],"type":"Point"}
}