{
  "type": "Feature",
  "properties": {
    "gn:admin1_code":"7.0",
    "gn:asciiname":"Tutam",
    "gn:country_code":"PK",
    "gn:dem":2685,
    "gn:feature_class":"P",
    "gn:feature_code":"PPL",
    "gn:name":"Tutam",
    "gn:population":0,
    "gn:timezone":"Asia/Karachi",
    "iso:country":"PK",
    "name:und_x_variant":[
        "T\u016btambai"
    ],
    "wof:name":"Tutam",
    "wof:placetype":"locality"
},
  "geometry": {"coordinates":[74.21892,35.56842],"type":"Point"}
}