{
  "type": "Feature",
  "properties": {
    "gn:admin1_code":"3",
    "gn:asciiname":"Qasim Kalle",
    "gn:country_code":"PK",
    "gn:dem":336,
    "gn:feature_class":"P",
    "gn:feature_code":"PPL",
    "gn:name":"Qasim Kalle",
    "gn:population":0,
    "gn:timezone":"Asia/Karachi",
    "iso:country":"PK",
    "name:eng_x_preferred":[
        "Q\u0101sim Kalle"
    ],
    "name:und_x_variant":[
        "Q\u0101sim Kili",
        "Qasim Kalle"
    ],
    "wof:name":"Qasim Kalle",
    "wof:placetype":"locality"
},
  "geometry": {"coordinates":[72.27124999999999,34.11761],"type":"Point"}
}