{
  "type": "Feature",
  "properties": {
    "gn:admin1_code":"03",
    "gn:asciiname":"Skuch",
    "gn:country_code":"PK",
    "gn:dem":3173,
    "gn:feature_class":"P",
    "gn:feature_code":"PPL",
    "gn:name":"Skuch",
    "gn:population":0,
    "gn:timezone":"Asia/Karachi",
    "iso:country":"PK",
    "name:eng_x_preferred":[
        "Sikuch"
    ],
    "wof:name":"Skuch",
    "wof:placetype":"locality"
},
  "geometry": {"coordinates":[72.56463000000002,36.6202],"type":"Point"}
}