{
  "type": "Feature",
  "properties": {
    "gn:admin1_code":"3",
    "gn:asciiname":"Mandrochh",
    "gn:country_code":"PK",
    "gn:dem":1410,
    "gn:feature_class":"P",
    "gn:feature_code":"PPL",
    "gn:name":"Mandrochh",
    "gn:population":0,
    "gn:timezone":"Asia/Karachi",
    "iso:country":"PK",
    "wof:name":"Mandrochh",
    "wof:placetype":"locality"
},
  "geometry": {"coordinates":[73.26563,34.25475],"type":"Point"}
}