{
  "type": "Feature",
  "properties": {
    "gn:admin1_code":"2.0",
    "gn:asciiname":"Malik Sadiq",
    "gn:country_code":"PK",
    "gn:dem":2097,
    "gn:feature_class":"P",
    "gn:feature_code":"PPL",
    "gn:name":"Malik Sadiq",
    "gn:population":0,
    "gn:timezone":"Asia/Karachi",
    "iso:country":"PK",
    "wof:name":"Malik Sadiq",
    "wof:placetype":"locality"
},
  "geometry": {"coordinates":[66.73693,31.03184000000001],"type":"Point"}
}