{
  "type": "Feature",
  "properties": {
    "gn:admin1_code":"2.0",
    "gn:asciiname":"Shaikh Shahin Kili",
    "gn:country_code":"PK",
    "gn:dem":986,
    "gn:feature_class":"P",
    "gn:feature_code":"PPL",
    "gn:name":"Shaikh Shahin Kili",
    "gn:population":0,
    "gn:timezone":"Asia/Karachi",
    "iso:country":"PK",
    "wof:name":"Shaikh Shahin Kili",
    "wof:placetype":"locality"
},
  "geometry": {"coordinates":[69.18268,30.13805],"type":"Point"}
}