{
  "type": "Feature",
  "properties": {
    "gn:admin1_code":"4.0",
    "gn:asciiname":"Chak Twenty-seven -Two Right A",
    "gn:country_code":"PK",
    "gn:dem":181,
    "gn:feature_class":"P",
    "gn:feature_code":"PPL",
    "gn:name":"Chak Twenty-seven -Two Right A",
    "gn:population":0,
    "gn:timezone":"Asia/Karachi",
    "iso:country":"PK",
    "name:und_x_variant":[
        "Mallarpur",
        "Mullapur"
    ],
    "wof:name":"Chak Twenty-seven -Two Right A",
    "wof:placetype":"locality"
},
  "geometry": {"coordinates":[73.49239,30.8376],"type":"Point"}
}