{
  "type": "Feature",
  "properties": {
    "gn:admin1_code":"4.0",
    "gn:asciiname":"Bucheke",
    "gn:country_code":"PK",
    "gn:dem":193,
    "gn:feature_class":"P",
    "gn:feature_code":"PPL",
    "gn:name":"Bucheke",
    "gn:population":0,
    "gn:timezone":"Asia/Karachi",
    "iso:country":"PK",
    "name:und_x_variant":[
        "Bucheki",
        "Buchikhe",
        "Budheke",
        "Bucheke"
    ],
    "wof:name":"Bucheke",
    "wof:placetype":"locality"
},
  "geometry": {"coordinates":[73.66003000000001,31.30858],"type":"Point"}
}