{
  "type": "Feature",
  "properties": {
    "gn:admin1_code":"4",
    "gn:asciiname":"Thatta Wattuan",
    "gn:country_code":"PK",
    "gn:dem":177,
    "gn:feature_class":"P",
    "gn:feature_code":"PPL",
    "gn:name":"Thatta Wattuan",
    "gn:population":0,
    "gn:timezone":"Asia/Karachi",
    "iso:country":"PK",
    "name:und_x_variant":[
        "Thatta Bhattu\u0101n"
    ],
    "wof:name":"Thatta Wattuan",
    "wof:placetype":"locality"
},
  "geometry": {"coordinates":[73.66882,30.78311],"type":"Point"}
}