{
  "type": "Feature",
  "properties": {
    "gn:admin1_code":"4.0",
    "gn:asciiname":"Talian-ni-kas",
    "gn:country_code":"PK",
    "gn:dem":744,
    "gn:feature_class":"P",
    "gn:feature_code":"PPL",
    "gn:name":"Talian-ni-kas",
    "gn:population":0,
    "gn:timezone":"Asia/Karachi",
    "iso:country":"PK",
    "wof:name":"Talian-ni-kas",
    "wof:placetype":"locality"
},
  "geometry": {"coordinates":[73.27984000000002,33.80253],"type":"Point"}
}