{
  "type": "Feature",
  "properties": {
    "gn:admin1_code":"5.0",
    "gn:asciiname":"Jakhra",
    "gn:country_code":"PK",
    "gn:dem":12,
    "gn:feature_class":"P",
    "gn:feature_code":"PPL",
    "gn:name":"Jakhra",
    "gn:population":0,
    "gn:timezone":"Asia/Karachi",
    "iso:country":"PK",
    "name:eng_x_preferred":[
        "Jakhra"
    ],
    "wof:name":"Jakhra",
    "wof:placetype":"locality"
},
  "geometry": {"coordinates":[68.09163000000001,24.74322],"type":"Point"}
}