{
  "type": "Feature",
  "properties": {
    "gn:admin1_code":"3",
    "gn:asciiname":"Kopai",
    "gn:country_code":"PK",
    "gn:dem":1533,
    "gn:feature_class":"P",
    "gn:feature_code":"PPL",
    "gn:name":"Kopai",
    "gn:population":0,
    "gn:timezone":"Asia/Karachi",
    "iso:country":"PK",
    "wof:name":"Kopai",
    "wof:placetype":"locality"
},
  "geometry": {"coordinates":[73.29460999999998,34.52789],"type":"Point"}
}