{
  "type": "Feature",
  "properties": {
    "gn:admin1_code":"5.0",
    "gn:asciiname":"Rahim Bakhsh",
    "gn:country_code":"PK",
    "gn:dem":62,
    "gn:feature_class":"P",
    "gn:feature_code":"PPL",
    "gn:name":"Rahim Bakhsh",
    "gn:population":0,
    "gn:timezone":"Asia/Karachi",
    "iso:country":"PK",
    "name:azb_x_preferred":[
        "\u0631\u062d\u06cc\u0645\u200c\u0628\u062e\u0634"
    ],
    "name:deu_x_preferred":[
        "Rahim Bakhsh"
    ],
    "name:fas_x_preferred":[
        "\u0631\u062d\u06cc\u0645\u200c\u0628\u062e\u0634"
    ],
    "name:pus_x_preferred":[
        "\u0631\u062d\u06cc\u0645 \u0628\u062e\u0634"
    ],
    "wof:name":"Rahim Bakhsh",
    "wof:placetype":"locality"
},
  "geometry": {"coordinates":[68.83556999999999,28.36054],"type":"Point"}
}