{
  "type": "Feature",
  "properties": {
    "gn:admin1_code":"4.0",
    "gn:asciiname":"Dera Nur Malik",
    "gn:country_code":"PK",
    "gn:dem":252,
    "gn:feature_class":"P",
    "gn:feature_code":"PPL",
    "gn:name":"Dera Nur Malik",
    "gn:population":0,
    "gn:timezone":"Asia/Karachi",
    "iso:country":"PK",
    "name:und_x_variant":[
        "Dera Nur Malak"
    ],
    "wof:name":"Dera Nur Malik",
    "wof:placetype":"locality"
},
  "geometry": {"coordinates":[75.23591,32.12835],"type":"Point"}
}