{
  "type": "Feature",
  "properties": {
    "gn:admin1_code":"4",
    "gn:asciiname":"Chak One Hundred Twenty-four - Ten Right",
    "gn:country_code":"PK",
    "gn:dem":124,
    "gn:feature_class":"P",
    "gn:feature_code":"PPL",
    "gn:name":"Chak One Hundred Twenty-four - Ten Right",
    "gn:population":0,
    "gn:timezone":"Asia/Karachi",
    "iso:country":"PK",
    "name:und_x_variant":[
        "Chak One Hundred Twenty-four"
    ],
    "wof:name":"Chak One Hundred Twenty-four - Ten Right",
    "wof:placetype":"locality"
},
  "geometry": {"coordinates":[71.69763,29.95269],"type":"Point"}
}