{
  "type": "Feature",
  "properties": {
    "gn:admin1_code":"7.0",
    "gn:asciiname":"Gompa Chakhmachan",
    "gn:country_code":"PK",
    "gn:dem":2594,
    "gn:feature_class":"P",
    "gn:feature_code":"PPL",
    "gn:name":"Gompa Chakhmachan",
    "gn:population":0,
    "gn:timezone":"Asia/Karachi",
    "iso:country":"PK",
    "wof:name":"Gompa Chakhmachan",
    "wof:placetype":"locality"
},
  "geometry": {"coordinates":[75.78447,35.4367],"type":"Point"}
}