{
  "type": "Feature",
  "properties": {
    "gn:admin1_code":"3.0",
    "gn:asciiname":"Sanja",
    "gn:country_code":"PK",
    "gn:dem":1184,
    "gn:feature_class":"P",
    "gn:feature_code":"PPL",
    "gn:name":"Sanja",
    "gn:population":0,
    "gn:timezone":"Asia/Karachi",
    "iso:country":"PK",
    "name:eng_x_preferred":[
        "Sanja"
    ],
    "wof:name":"Sanja",
    "wof:placetype":"locality"
},
  "geometry": {"coordinates":[73.31401,33.86652],"type":"Point"}
}