{
  "type": "Feature",
  "properties": {
    "gn:admin1_code":"4",
    "gn:asciiname":"Pir Chhattha",
    "gn:country_code":"PK",
    "gn:dem":100,
    "gn:feature_class":"P",
    "gn:feature_code":"PPL",
    "gn:name":"Pir Chhattha",
    "gn:population":0,
    "gn:timezone":"Asia/Karachi",
    "iso:country":"PK",
    "name:und_x_variant":[
        "P\u012br Chhatta"
    ],
    "wof:name":"Pir Chhattha",
    "wof:placetype":"locality"
},
  "geometry": {"coordinates":[70.81395000000001,29.28442],"type":"Point"}
}