{
  "type": "Feature",
  "properties": {
    "gn:admin1_code":"4",
    "gn:asciiname":"Basti Tarpri",
    "gn:country_code":"PK",
    "gn:dem":82,
    "gn:feature_class":"P",
    "gn:feature_code":"PPL",
    "gn:name":"Basti Tarpri",
    "gn:population":0,
    "gn:timezone":"Asia/Karachi",
    "iso:country":"PK",
    "name:und_x_variant":[
        "J\u0101m Mewa"
    ],
    "wof:name":"Basti Tarpri",
    "wof:placetype":"locality"
},
  "geometry": {"coordinates":[69.94280000000001,28.41118],"type":"Point"}
}