{
  "type": "Feature",
  "properties": {
    "gn:admin1_code":"4.0",
    "gn:asciiname":"Banial",
    "gn:country_code":"PK",
    "gn:dem":266,
    "gn:feature_class":"P",
    "gn:feature_code":"PPL",
    "gn:name":"Banial",
    "gn:population":0,
    "gn:timezone":"Asia/Karachi",
    "iso:country":"PK",
    "name:und_x_variant":[
        "Bani\u0101l Brahman\u0101n"
    ],
    "wof:name":"Banial",
    "wof:placetype":"locality"
},
  "geometry": {"coordinates":[75.19895,32.24203],"type":"Point"}
}