{
  "type": "Feature",
  "properties": {
    "gn:admin1_code":"4.0",
    "gn:asciiname":"Lalpur",
    "gn:country_code":"PK",
    "gn:dem":267,
    "gn:feature_class":"P",
    "gn:feature_code":"PPL",
    "gn:name":"Lalpur",
    "gn:population":0,
    "gn:timezone":"Asia/Karachi",
    "iso:country":"PK",
    "wof:name":"Lalpur",
    "wof:placetype":"locality"
},
  "geometry": {"coordinates":[75.15093,32.25947],"type":"Point"}
}