{
  "type": "Feature",
  "properties": {
    "gn:admin1_code":"2",
    "gn:asciiname":"Koskra",
    "gn:country_code":"PK",
    "gn:dem":1140,
    "gn:feature_class":"P",
    "gn:feature_code":"PPL",
    "gn:name":"Koskra",
    "gn:population":0,
    "gn:timezone":"Asia/Karachi",
    "iso:country":"PK",
    "name:und_x_variant":[
        "Basti Sh\u0101ikh\u0101n"
    ],
    "wof:name":"Koskra",
    "wof:placetype":"locality"
},
  "geometry": {"coordinates":[69.54852,29.92314],"type":"Point"}
}