{
  "type": "Feature",
  "properties": {
    "gn:admin1_code":"2.0",
    "gn:asciiname":"Gujrani",
    "gn:country_code":"PK",
    "gn:dem":1162,
    "gn:feature_class":"P",
    "gn:feature_code":"PPL",
    "gn:name":"Gujrani",
    "gn:population":0,
    "gn:timezone":"Asia/Karachi",
    "iso:country":"PK",
    "name:tat_x_preferred":[
        "\u0413\u0443\u0497\u0440\u0430\u043d\u0438"
    ],
    "wof:name":"Gujrani",
    "wof:placetype":"locality"
},
  "geometry": {"coordinates":[69.97424000000001,30.18075],"type":"Point"}
}