{
  "type": "Feature",
  "properties": {
    "gn:admin1_code":"4.0",
    "gn:asciiname":"Zafarabad",
    "gn:country_code":"PK",
    "gn:dem":97,
    "gn:feature_class":"P",
    "gn:feature_code":"PPL",
    "gn:name":"Zafarabad",
    "gn:population":0,
    "gn:timezone":"Asia/Karachi",
    "iso:country":"PK",
    "name:urd_x_preferred":[
        "Zafarabad"
    ],
    "wof:name":"Zafarabad",
    "wof:placetype":"locality"
},
  "geometry": {"coordinates":[70.65505,28.90672],"type":"Point"}
}