{
  "type": "Feature",
  "properties": {
    "gn:admin1_code":"4.0",
    "gn:asciiname":"Jaglot Khalsa",
    "gn:country_code":"PK",
    "gn:dem":592,
    "gn:feature_class":"P",
    "gn:feature_code":"PPL",
    "gn:name":"Jaglot Khalsa",
    "gn:population":0,
    "gn:timezone":"Asia/Karachi",
    "iso:country":"PK",
    "name:und_x_variant":[
        "Jagrot Kh\u0101lsa"
    ],
    "wof:name":"Jaglot Khalsa",
    "wof:placetype":"locality"
},
  "geometry": {"coordinates":[73.33708,33.58831],"type":"Point"}
}