{
  "type": "Feature",
  "properties": {
    "gn:admin1_code":"6",
    "gn:asciiname":"Gam Kotli",
    "gn:country_code":"PK",
    "gn:dem":1114,
    "gn:feature_class":"P",
    "gn:feature_code":"PPL",
    "gn:name":"Gam Kotli",
    "gn:population":0,
    "gn:timezone":"Asia/Karachi",
    "iso:country":"PK",
    "name:und_x_variant":[
        "Bh\u0101ta Dhara"
    ],
    "wof:name":"Gam Kotli",
    "wof:placetype":"locality"
},
  "geometry": {"coordinates":[73.86085,33.65421],"type":"Point"}
}