{
  "type": "Feature",
  "properties": {
    "gn:admin1_code":"5",
    "gn:asciiname":"Haji Ahmad Hot Jo Wahan",
    "gn:country_code":"PK",
    "gn:dem":41,
    "gn:feature_class":"P",
    "gn:feature_code":"PPL",
    "gn:name":"Haji Ahmad Hot Jo Wahan",
    "gn:population":0,
    "gn:timezone":"Asia/Karachi",
    "iso:country":"PK",
    "name:und_x_variant":[
        "H\u0101ji Ahmad Hoteputa"
    ],
    "wof:name":"Haji Ahmad Hot Jo Wahan",
    "wof:placetype":"locality"
},
  "geometry": {"coordinates":[68.08591,26.47094],"type":"Point"}
}