{
  "type": "Feature",
  "properties": {
    "gn:admin1_code":"4",
    "gn:asciiname":"Thing Basti",
    "gn:country_code":"PK",
    "gn:dem":187,
    "gn:feature_class":"P",
    "gn:feature_code":"PPL",
    "gn:name":"Thing Basti",
    "gn:population":0,
    "gn:timezone":"Asia/Karachi",
    "iso:country":"PK",
    "name:und_x_variant":[
        "Thing"
    ],
    "wof:name":"Thing Basti",
    "wof:placetype":"locality"
},
  "geometry": {"coordinates":[74.03749999999999,30.95332],"type":"Point"}
}