{
  "type": "Feature",
  "properties": {
    "gn:admin1_code":"4.0",
    "gn:asciiname":"Khalilpur",
    "gn:country_code":"PK",
    "gn:dem":275,
    "gn:feature_class":"P",
    "gn:feature_code":"PPL",
    "gn:name":"Khalilpur",
    "gn:population":0,
    "gn:timezone":"Asia/Karachi",
    "iso:country":"PK",
    "name:und_x_variant":[
        "Khailipur"
    ],
    "wof:name":"Khalilpur",
    "wof:placetype":"locality"
},
  "geometry": {"coordinates":[74.89063,32.39328],"type":"Point"}
}