{
  "type": "Feature",
  "properties": {
    "gn:admin1_code":"4",
    "gn:asciiname":"Taraggar",
    "gn:country_code":"PK",
    "gn:dem":130,
    "gn:feature_class":"P",
    "gn:feature_code":"PPL",
    "gn:name":"Taraggar",
    "gn:population":0,
    "gn:timezone":"Asia/Karachi",
    "iso:country":"PK",
    "name:und_x_variant":[
        "Traggar"
    ],
    "wof:name":"Taraggar",
    "wof:placetype":"locality"
},
  "geometry": {"coordinates":[71.95699,29.93829],"type":"Point"}
}