{
  "type": "Feature",
  "properties": {
    "gn:admin1_code":"4",
    "gn:asciiname":"Loharanwala Khu",
    "gn:country_code":"PK",
    "gn:dem":138,
    "gn:feature_class":"P",
    "gn:feature_code":"PPL",
    "gn:name":"Loharanwala Khu",
    "gn:population":0,
    "gn:timezone":"Asia/Karachi",
    "iso:country":"PK",
    "name:und_x_variant":[
        "Loh\u0101r\u0101nw\u0101la"
    ],
    "wof:name":"Loharanwala Khu",
    "wof:placetype":"locality"
},
  "geometry": {"coordinates":[72.30734,30.11922],"type":"Point"}
}