{
  "type": "Feature",
  "properties": {
    "gn:admin1_code":"3.0",
    "gn:asciiname":"Barkhan",
    "gn:country_code":"PK",
    "gn:dem":2944,
    "gn:feature_class":"P",
    "gn:feature_code":"PPL",
    "gn:name":"Barkhan",
    "gn:population":0,
    "gn:timezone":"Asia/Karachi",
    "iso:country":"PK",
    "name:ceb_x_preferred":[
        "B\u0101rkh\u0101n"
    ],
    "name:eng_x_preferred":[
        "Barkhan"
    ],
    "name:fas_x_preferred":[
        "\u0628\u0627\u0631\u062e\u0627\u0646"
    ],
    "name:msa_x_preferred":[
        "Barkhan"
    ],
    "name:por_x_preferred":[
        "Barkhan"
    ],
    "name:rus_x_preferred":[
        "\u0411\u0430\u0440\u0445\u0430\u043d"
    ],
    "name:snd_x_preferred":[
        "\u0628\u0627\u0631\u06a9\u0627\u0646"
    ],
    "name:spa_x_preferred":[
        "Barkhan"
    ],
    "name:swe_x_preferred":[
        "Barkhan"
    ],
    "name:tur_x_preferred":[
        "Barkhan"
    ],
    "name:urd_x_preferred":[
        "\u0628\u0627\u0631\u06a9\u06be\u0627\u0646"
    ],
    "name:urd_x_variant":[
        "\u0628\u0627\u0631\u062e\u0627\u0646"
    ],
    "wof:name":"Barkhan",
    "wof:placetype":"locality"
},
  "geometry": {"coordinates":[72.73537,35.11426],"type":"Point"}
}