{
  "type": "Feature",
  "properties": {
    "gn:admin1_code":"3.0",
    "gn:asciiname":"Barkhan",
    "gn:country_code":"PK",
    "gn:dem":2944,
    "gn:feature_class":"P",
    "gn:feature_code":"PPL",
    "gn:name":"Barkhan",
    "gn:population":0,
    "gn:timezone":"Asia/Karachi",
    "iso:country":"PK",
    "wof:name":"Barkhan",
    "wof:placetype":"locality"
},
  "geometry": {"coordinates":[72.73536999999997,35.11425999999999],"type":"Point"}
}