{
  "type": "Feature",
  "properties": {
    "gn:admin1_code":"3.0",
    "gn:asciiname":"Jachil",
    "gn:country_code":"PK",
    "gn:dem":1929,
    "gn:feature_class":"P",
    "gn:feature_code":"PPL",
    "gn:name":"Jachil",
    "gn:population":0,
    "gn:timezone":"Asia/Karachi",
    "iso:country":"PK",
    "wof:name":"Jachil",
    "wof:placetype":"locality"
},
  "geometry": {"coordinates":[73.62557,35.4432],"type":"Point"}
}