{
  "type": "Feature",
  "properties": {
    "gn:admin1_code":"4.0",
    "gn:asciiname":"Gehatthal",
    "gn:country_code":"PK",
    "gn:dem":973,
    "gn:feature_class":"P",
    "gn:feature_code":"PPL",
    "gn:name":"Gehatthal",
    "gn:population":0,
    "gn:timezone":"Asia/Karachi",
    "iso:country":"PK",
    "wof:name":"Gehatthal",
    "wof:placetype":"locality"
},
  "geometry": {"coordinates":[73.50399999999998,33.99493],"type":"Point"}
}