{
  "type": "Feature",
  "properties": {
    "gn:admin1_code":"3",
    "gn:asciiname":"Utlo",
    "gn:country_code":"PK",
    "gn:dem":1104,
    "gn:feature_class":"P",
    "gn:feature_code":"PPL",
    "gn:name":"Utlo",
    "gn:population":0,
    "gn:timezone":"Asia/Karachi",
    "iso:country":"PK",
    "name:und_x_variant":[
        "Utlu"
    ],
    "wof:name":"Utlo",
    "wof:placetype":"locality"
},
  "geometry": {"coordinates":[72.91748,34.97557],"type":"Point"}
}