{
  "type": "Feature",
  "properties": {
    "gn:admin1_code":"05",
    "gn:asciiname":"Larho",
    "gn:country_code":"PK",
    "gn:dem":9,
    "gn:feature_class":"P",
    "gn:feature_code":"PPL",
    "gn:name":"Larho",
    "gn:population":0,
    "gn:timezone":"Asia/Karachi",
    "iso:country":"PK",
    "wof:name":"Larho",
    "wof:placetype":"locality"
},
  "geometry": {"coordinates":[67.9169,24.49472],"type":"Point"}
}