{
  "type": "Feature",
  "properties": {
    "gn:admin1_code":"2.0",
    "gn:asciiname":"Kili Naik Muhammad",
    "gn:country_code":"PK",
    "gn:dem":848,
    "gn:feature_class":"P",
    "gn:feature_code":"PPL",
    "gn:name":"Kili Naik Muhammad",
    "gn:population":0,
    "gn:timezone":"Asia/Karachi",
    "iso:country":"PK",
    "wof:name":"Kili Naik Muhammad",
    "wof:placetype":"locality"
},
  "geometry": {"coordinates":[65.70174,29.18901],"type":"Point"}
}