{
  "type": "Feature",
  "properties": {
    "gn:admin1_code":"4.0",
    "gn:asciiname":"Chanjni",
    "gn:country_code":"PK",
    "gn:dem":97,
    "gn:feature_class":"P",
    "gn:feature_code":"PPL",
    "gn:name":"Chanjni",
    "gn:population":0,
    "gn:timezone":"Asia/Karachi",
    "iso:country":"PK",
    "name:und_x_variant":[
        "Chandni",
        "Chanjni",
        "Ch\u0101nini"
    ],
    "name:urd_x_preferred":[
        "Basti Ch\u0101nan"
    ],
    "wof:name":"Chanjni",
    "wof:placetype":"locality"
},
  "geometry": {"coordinates":[70.68582000000001,28.90916],"type":"Point"}
}