{
  "type": "Feature",
  "properties": {
    "gn:admin1_code":"2.0",
    "gn:asciiname":"Khuddi Abdul Rahim",
    "gn:country_code":"PK",
    "gn:dem":1973,
    "gn:feature_class":"P",
    "gn:feature_code":"PPL",
    "gn:name":"Khuddi Abdul Rahim",
    "gn:population":0,
    "gn:timezone":"Asia/Karachi",
    "iso:country":"PK",
    "wof:name":"Khuddi Abdul Rahim",
    "wof:placetype":"locality"
},
  "geometry": {"coordinates":[66.84827,28.86576],"type":"Point"}
}