{
  "type": "Feature",
  "properties": {
    "gn:admin1_code":"7.0",
    "gn:asciiname":"Khakai",
    "gn:country_code":"PK",
    "gn:dem":1921,
    "gn:feature_class":"P",
    "gn:feature_code":"PPL",
    "gn:name":"Khakai",
    "gn:population":0,
    "gn:timezone":"Asia/Karachi",
    "iso:country":"PK",
    "wof:name":"Khakai",
    "wof:placetype":"locality"
},
  "geometry": {"coordinates":[73.78225999999999,35.41649],"type":"Point"}
}