{
  "type": "Feature",
  "properties": {
    "gn:admin1_code":"04",
    "gn:asciiname":"Lodhri",
    "gn:country_code":"PK",
    "gn:dem":171,
    "gn:feature_class":"P",
    "gn:feature_code":"PPL",
    "gn:name":"Lodhri",
    "gn:population":0,
    "gn:timezone":"Asia/Karachi",
    "iso:country":"PK",
    "name:und_x_variant":[
        "Lodhre",
        "Lodhri"
    ],
    "wof:name":"Lodhri",
    "wof:placetype":"locality"
},
  "geometry": {"coordinates":[72.65279,31.65024],"type":"Point"}
}