{
  "type": "Feature",
  "properties": {
    "gn:admin1_code":"5.0",
    "gn:asciiname":"Muhammad Ramzan Mallah",
    "gn:country_code":"PK",
    "gn:dem":15,
    "gn:feature_class":"P",
    "gn:feature_code":"PPL",
    "gn:name":"Muhammad Ramzan Mallah",
    "gn:population":0,
    "gn:timezone":"Asia/Karachi",
    "iso:country":"PK",
    "name:und_x_variant":[
        "Goth Barad"
    ],
    "wof:name":"Muhammad Ramzan Mallah",
    "wof:placetype":"locality"
},
  "geometry": {"coordinates":[67.61490000000001,24.76154],"type":"Point"}
}