{
  "type": "Feature",
  "properties": {
    "gn:admin1_code":"3.0",
    "gn:asciiname":"Gotin Bhek",
    "gn:country_code":"PK",
    "gn:dem":3062,
    "gn:feature_class":"P",
    "gn:feature_code":"PPL",
    "gn:name":"Gotin Bhek",
    "gn:population":0,
    "gn:timezone":"Asia/Karachi",
    "iso:country":"PK",
    "wof:name":"Gotin Bhek",
    "wof:placetype":"locality"
},
  "geometry": {"coordinates":[72.85694000000002,35.43096],"type":"Point"}
}