{
  "type": "Feature",
  "properties": {
    "gn:admin1_code":"5",
    "gn:asciiname":"Goth Abdul Latif",
    "gn:country_code":"PK",
    "gn:dem":67,
    "gn:feature_class":"P",
    "gn:feature_code":"PPL",
    "gn:name":"Goth Abdul Latif",
    "gn:population":0,
    "gn:timezone":"Asia/Karachi",
    "iso:country":"PK",
    "name:und_x_variant":[
        "Goth Abdul Lat\u012bf Khosa"
    ],
    "wof:name":"Goth Abdul Latif",
    "wof:placetype":"locality"
},
  "geometry": {"coordinates":[69.01481,28.3865],"type":"Point"}
}