{
  "type": "Feature",
  "properties": {
    "gn:admin1_code":"06",
    "gn:asciiname":"Samani",
    "gn:country_code":"PK",
    "gn:dem":618,
    "gn:feature_class":"P",
    "gn:feature_code":"PPL",
    "gn:name":"Samani",
    "gn:population":0,
    "gn:timezone":"Asia/Karachi",
    "iso:country":"PK",
    "name:und_x_variant":[
        "Sam\u0101ni"
    ],
    "wof:name":"Samani",
    "wof:placetype":"locality"
},
  "geometry": {"coordinates":[74.13585,33.08903],"type":"Point"}
}