{
  "type": "Feature",
  "properties": {
    "gn:admin1_code":"06",
    "gn:asciiname":"Samani",
    "gn:country_code":"PK",
    "gn:dem":618,
    "gn:feature_class":"P",
    "gn:feature_code":"PPL",
    "gn:name":"Samani",
    "gn:population":0,
    "gn:timezone":"Asia/Karachi",
    "iso:country":"PK",
    "name:aze_x_preferred":[
        "S\u0259m\u0259ni"
    ],
    "name:kat_x_preferred":[
        "\u10e1\u10d4\u10db\u10d4\u10dc\u10d8"
    ],
    "name:rus_x_preferred":[
        "\u0421\u044d\u043c\u044d\u043d\u0438"
    ],
    "name:tur_x_preferred":[
        "Semeni"
    ],
    "name:und_x_variant":[
        "Sam\u0101ni"
    ],
    "wof:name":"Samani",
    "wof:placetype":"locality"
},
  "geometry": {"coordinates":[74.13585,33.08903],"type":"Point"}
}