{
  "type": "Feature",
  "properties": {
    "gn:admin1_code":"3.0",
    "gn:asciiname":"Nadar Mian",
    "gn:country_code":"PK",
    "gn:dem":399,
    "gn:feature_class":"P",
    "gn:feature_code":"PPL",
    "gn:name":"Nadar Mian",
    "gn:population":0,
    "gn:timezone":"Asia/Karachi",
    "iso:country":"PK",
    "wof:name":"Nadar Mian",
    "wof:placetype":"locality"
},
  "geometry": {"coordinates":[71.79145,34.36751],"type":"Point"}
}