{
  "type": "Feature",
  "properties": {
    "gn:admin1_code":"5",
    "gn:asciiname":"Amrah Soch Ali Shah",
    "gn:country_code":"PK",
    "gn:dem":38,
    "gn:feature_class":"P",
    "gn:feature_code":"PPL",
    "gn:name":"Amrah Soch Ali Shah",
    "gn:population":0,
    "gn:timezone":"Asia/Karachi",
    "iso:country":"PK",
    "wof:name":"Amrah Soch Ali Shah",
    "wof:placetype":"locality"
},
  "geometry": {"coordinates":[67.74630999999999,26.49874],"type":"Point"}
}