{
  "type": "Feature",
  "properties": {
    "gn:admin1_code":"5",
    "gn:asciiname":"Goth Amir Ali Talpur",
    "gn:country_code":"PK",
    "gn:dem":17,
    "gn:feature_class":"P",
    "gn:feature_code":"PPL",
    "gn:name":"Goth Amir Ali Talpur",
    "gn:population":0,
    "gn:timezone":"Asia/Karachi",
    "iso:country":"PK",
    "name:und_x_variant":[
        "Ali Kh\u0101n T\u0101lpur"
    ],
    "wof:name":"Goth Amir Ali Talpur",
    "wof:placetype":"locality"
},
  "geometry": {"coordinates":[68.60280999999999,25.01972],"type":"Point"}
}