{
  "type": "Feature",
  "properties": {
    "iso:country":"PK",
    "name:und_x_variant":[
        "Naushahro Piroz"
    ],
    "qs:gn_country":"PK",
    "qs:gn_fcode":"PPLA2",
    "qs:gn_pop":17631,
    "qs:name":"Naushahro",
    "qs:name_adm0":"Pakistan",
    "qs:name_adm1":"Sindh",
    "qs:photos":0,
    "qs:photos_1k":0,
    "qs:photos_9k":0,
    "qs:photos_9r":0,
    "qs:photos_all":0,
    "qs:photos_sr":0,
    "qs:placetype":"Town",
    "qs:pop_sr":"6",
    "qs:woe_adm0":23424922,
    "wof:name":"Naushahro",
    "wof:placetype":"locality",
    "wof:population":17631
},
  "geometry": {"coordinates":[68.12298,26.84238],"type":"Point"}
}