{
  "type": "Feature",
  "properties": {
    "gn:admin1_code":"3.0",
    "gn:asciiname":"Ghazan Kalle",
    "gn:country_code":"PK",
    "gn:dem":415,
    "gn:feature_class":"P",
    "gn:feature_code":"PPL",
    "gn:name":"Ghazan Kalle",
    "gn:population":0,
    "gn:timezone":"Asia/Karachi",
    "iso:country":"PK",
    "name:eng_x_preferred":[
        "Masal Khan Kalle"
    ],
    "wof:name":"Ghazan Kalle",
    "wof:placetype":"locality"
},
  "geometry": {"coordinates":[71.73935,34.37108],"type":"Point"}
}