{
  "type": "Feature",
  "properties": {
    "gn:admin1_code":"3",
    "gn:asciiname":"Butseri",
    "gn:country_code":"PK",
    "gn:dem":314,
    "gn:feature_class":"P",
    "gn:feature_code":"PPL",
    "gn:name":"Butseri",
    "gn:population":0,
    "gn:timezone":"Asia/Karachi",
    "iso:country":"PK",
    "name:eng_x_preferred":[
        "Budsarai"
    ],
    "wof:name":"Butseri",
    "wof:placetype":"locality"
},
  "geometry": {"coordinates":[72.18374,34.22594],"type":"Point"}
}