{
  "type": "Feature",
  "properties": {
    "gn:admin1_code":"4",
    "gn:asciiname":"Tahraned Bisharat",
    "gn:country_code":"PK",
    "gn:dem":108,
    "gn:feature_class":"P",
    "gn:feature_code":"PPL",
    "gn:name":"Tahraned Bisharat",
    "gn:population":0,
    "gn:timezone":"Asia/Karachi",
    "iso:country":"PK",
    "name:und_x_variant":[
        "Faqir Basti",
        "Trand Bish\u0101rat",
        "Tahraned Bisharat"
    ],
    "wof:name":"Tahraned Bisharat",
    "wof:placetype":"locality"
},
  "geometry": {"coordinates":[71.10857,29.35505],"type":"Point"}
}