{
  "type": "Feature",
  "properties": {
    "gn:admin1_code":"5",
    "gn:asciiname":"Sethau Tar",
    "gn:country_code":"PK",
    "gn:dem":41,
    "gn:feature_class":"P",
    "gn:feature_code":"PPL",
    "gn:name":"Sethau Tar",
    "gn:population":0,
    "gn:timezone":"Asia/Karachi",
    "iso:country":"PK",
    "name:und_x_variant":[
        "Set\u0101hu Tar"
    ],
    "wof:name":"Sethau Tar",
    "wof:placetype":"locality"
},
  "geometry": {"coordinates":[69.4198,26.41034],"type":"Point"}
}