{
  "type": "Feature",
  "properties": {
    "gn:admin1_code":"5.0",
    "gn:asciiname":"Goth Pira Malik",
    "gn:country_code":"PK",
    "gn:dem":66,
    "gn:feature_class":"P",
    "gn:feature_code":"PPL",
    "gn:name":"Goth Pira Malik",
    "gn:population":0,
    "gn:timezone":"Asia/Karachi",
    "iso:country":"PK",
    "name:und_x_variant":[
        "Goth P\u012bra Malik"
    ],
    "wof:name":"Goth Pira Malik",
    "wof:placetype":"locality"
},
  "geometry": {"coordinates":[69.46205999999999,27.83135],"type":"Point"}
}