{
  "type": "Feature",
  "properties": {
    "gn:admin1_code":"5",
    "gn:asciiname":"Mena",
    "gn:country_code":"PK",
    "gn:dem":9,
    "gn:feature_class":"P",
    "gn:feature_code":"PPL",
    "gn:name":"Mena",
    "gn:population":0,
    "gn:timezone":"Asia/Karachi",
    "iso:country":"PK",
    "name:und_x_variant":[
        "Meno jo Goth",
        "Mena"
    ],
    "wof:name":"Mena",
    "wof:placetype":"locality"
},
  "geometry": {"coordinates":[69.07701,24.9565],"type":"Point"}
}