{
  "type": "Feature",
  "properties": {
    "gn:admin1_code":"4.0",
    "gn:asciiname":"Chura",
    "gn:country_code":"PK",
    "gn:dem":372,
    "gn:feature_class":"P",
    "gn:feature_code":"PPL",
    "gn:name":"Chura",
    "gn:population":0,
    "gn:timezone":"Asia/Karachi",
    "iso:country":"PK",
    "wof:name":"Chura",
    "wof:placetype":"locality"
},
  "geometry": {"coordinates":[72.74798,33.30824],"type":"Point"}
}