{
  "type": "Feature",
  "properties": {
    "gn:admin1_code":"4",
    "gn:asciiname":"Chak Two Hundred Fifty-five Eastern Bar",
    "gn:country_code":"PK",
    "gn:dem":149,
    "gn:feature_class":"P",
    "gn:feature_code":"PPL",
    "gn:name":"Chak Two Hundred Fifty-five Eastern Bar",
    "gn:population":0,
    "gn:timezone":"Asia/Karachi",
    "iso:country":"PK",
    "name:und_x_variant":[
        "Chak Two Hundred Fifty-five"
    ],
    "wof:name":"Chak Two Hundred Fifty-five Eastern Bar",
    "wof:placetype":"locality"
},
  "geometry": {"coordinates":[72.76687,30.17526],"type":"Point"}
}