{
  "type": "Feature",
  "properties": {
    "gn:admin1_code":"3",
    "gn:asciiname":"Kahi",
    "gn:country_code":"PK",
    "gn:dem":2574,
    "gn:feature_class":"P",
    "gn:feature_code":"PPL",
    "gn:name":"Kahi",
    "gn:population":0,
    "gn:timezone":"Asia/Karachi",
    "iso:country":"PK",
    "name:ceb_x_preferred":[
        "Kahi"
    ],
    "name:eng_x_preferred":[
        "Kahi"
    ],
    "name:swe_x_preferred":[
        "Kahi"
    ],
    "wof:name":"Kahi",
    "wof:placetype":"locality"
},
  "geometry": {"coordinates":[72.40031,35.24197],"type":"Point"}
}