{
  "type": "Feature",
  "properties": {
    "gn:admin1_code":"2.0",
    "gn:asciiname":"Mallah Khan Bugti",
    "gn:country_code":"PK",
    "gn:dem":69,
    "gn:feature_class":"P",
    "gn:feature_code":"PPL",
    "gn:name":"Mallah Khan Bugti",
    "gn:population":0,
    "gn:timezone":"Asia/Karachi",
    "iso:country":"PK",
    "wof:name":"Mallah Khan Bugti",
    "wof:placetype":"locality"
},
  "geometry": {"coordinates":[68.34631999999999,28.60479],"type":"Point"}
}