{
  "type": "Feature",
  "properties": {
    "gn:admin1_code":"2.0",
    "gn:asciiname":"Kili Samalani",
    "gn:country_code":"PK",
    "gn:dem":1583,
    "gn:feature_class":"P",
    "gn:feature_code":"PPL",
    "gn:name":"Kili Samalani",
    "gn:population":0,
    "gn:timezone":"Asia/Karachi",
    "iso:country":"PK",
    "wof:name":"Kili Samalani",
    "wof:placetype":"locality"
},
  "geometry": {"coordinates":[66.62350000000001,29.90978],"type":"Point"}
}