{
  "type": "Feature",
  "properties": {
    "gn:admin1_code":"01",
    "gn:asciiname":"Narakai",
    "gn:country_code":"PK",
    "gn:dem":1790,
    "gn:feature_class":"P",
    "gn:feature_code":"PPL",
    "gn:name":"Narakai",
    "gn:population":0,
    "gn:timezone":"Asia/Karachi",
    "iso:country":"PK",
    "wof:name":"Narakai",
    "wof:placetype":"locality"
},
  "geometry": {"coordinates":[69.35694000000001,32.31944],"type":"Point"}
}