{
  "type": "Feature",
  "properties": {
    "gn:admin1_code":"5.0",
    "gn:asciiname":"Gahrji",
    "gn:country_code":"PK",
    "gn:dem":8,
    "gn:feature_class":"P",
    "gn:feature_code":"PPL",
    "gn:name":"Gahrji",
    "gn:population":0,
    "gn:timezone":"Asia/Karachi",
    "iso:country":"PK",
    "name:und_x_variant":[
        "Gohreji"
    ],
    "wof:name":"Gahrji",
    "wof:placetype":"locality"
},
  "geometry": {"coordinates":[68.79713000000001,24.53219],"type":"Point"}
}