{
  "type": "Feature",
  "properties": {
    "gn:admin1_code":"4.0",
    "gn:asciiname":"Sakhanwala",
    "gn:country_code":"PK",
    "gn:dem":121,
    "gn:feature_class":"P",
    "gn:feature_code":"PPL",
    "gn:name":"Sakhanwala",
    "gn:population":0,
    "gn:timezone":"Asia/Karachi",
    "iso:country":"PK",
    "name:und_x_variant":[
        "Kangan"
    ],
    "wof:name":"Sakhanwala",
    "wof:placetype":"locality"
},
  "geometry": {"coordinates":[71.39513000000002,29.96275],"type":"Point"}
}