{
  "type": "Feature",
  "properties": {
    "gn:admin1_code":"6.0",
    "gn:asciiname":"Aima Bari",
    "gn:country_code":"PK",
    "gn:dem":256,
    "gn:feature_class":"P",
    "gn:feature_code":"PPL",
    "gn:name":"Aima Bari",
    "gn:population":0,
    "gn:timezone":"Asia/Karachi",
    "iso:country":"PK",
    "name:und_x_variant":[
        "Aimah Bari",
        "Aima B\u0101ri",
        "Aima Bari"
    ],
    "wof:name":"Aima Bari",
    "wof:placetype":"locality"
},
  "geometry": {"coordinates":[73.69771999999998,33.03425],"type":"Point"}
}