{
  "type": "Feature",
  "properties": {
    "gn:admin1_code":"4",
    "gn:asciiname":"Ghulam Farid Malleke",
    "gn:country_code":"PK",
    "gn:dem":170,
    "gn:feature_class":"P",
    "gn:feature_code":"PPL",
    "gn:name":"Ghulam Farid Malleke",
    "gn:population":0,
    "gn:timezone":"Asia/Karachi",
    "iso:country":"PK",
    "name:und_x_variant":[
        "Ghul\u0101m Far\u012bd"
    ],
    "wof:name":"Ghulam Farid Malleke",
    "wof:placetype":"locality"
},
  "geometry": {"coordinates":[73.50158,30.33874],"type":"Point"}
}