{
  "type": "Feature",
  "properties": {
    "gn:admin1_code":"1.0",
    "gn:asciiname":"Shagai",
    "gn:country_code":"PK",
    "gn:dem":1905,
    "gn:feature_class":"P",
    "gn:feature_code":"PPL",
    "gn:name":"Shagai",
    "gn:population":0,
    "gn:timezone":"Asia/Karachi",
    "iso:country":"PK",
    "name:crh_x_preferred":[
        "A\u015f\u0131q oyun\u0131"
    ],
    "name:deu_x_preferred":[
        "Schagai"
    ],
    "name:fra_x_preferred":[
        "Shagai"
    ],
    "name:kaz_x_preferred":[
        "\u0410\u0441\u044b\u049b"
    ],
    "name:pol_x_preferred":[
        "Szagaj"
    ],
    "name:rus_x_preferred":[
        "\u0410\u0441\u044b\u043a"
    ],
    "name:spa_x_preferred":[
        "Shagai"
    ],
    "name:tgk_x_preferred":[
        "\u0411\u0443\u04b7\u0443\u043b\u0431\u043e\u0437\u04e3"
    ],
    "name:tur_x_preferred":[
        "A\u015f\u0131k oyunu"
    ],
    "name:tyv_x_preferred":[
        "\u041a\u0430\u0436\u044b\u043a \u043e\u044e\u043d\u043d\u0430\u0440\u044b"
    ],
    "name:zho_x_preferred":[
        "\u560e\u62c9\u54c8"
    ],
    "wof:name":"Shagai",
    "wof:placetype":"locality"
},
  "geometry": {"coordinates":[70.77834,33.78172],"type":"Point"}
}