{
  "type": "Feature",
  "properties": {
    "gn:admin1_code":"4.0",
    "gn:asciiname":"Ghulamun Mahar",
    "gn:country_code":"PK",
    "gn:dem":111,
    "gn:feature_class":"P",
    "gn:feature_code":"PPL",
    "gn:name":"Ghulamun Mahar",
    "gn:population":0,
    "gn:timezone":"Asia/Karachi",
    "iso:country":"PK",
    "name:und_x_variant":[
        "Ghul\u0101m\u0101n M\u0101har"
    ],
    "wof:name":"Ghulamun Mahar",
    "wof:placetype":"locality"
},
  "geometry": {"coordinates":[71.44996999999999,29.28136],"type":"Point"}
}