{
  "type": "Feature",
  "properties": {
    "gn:admin1_code":"4.0",
    "gn:asciiname":"Dhok Sharif",
    "gn:country_code":"PK",
    "gn:dem":351,
    "gn:feature_class":"P",
    "gn:feature_code":"PPL",
    "gn:name":"Dhok Sharif",
    "gn:population":0,
    "gn:timezone":"Asia/Karachi",
    "iso:country":"PK",
    "name:und_x_variant":[
        "Dhok Sharfa"
    ],
    "wof:name":"Dhok Sharif",
    "wof:placetype":"locality"
},
  "geometry": {"coordinates":[72.37456999999998,33.75518],"type":"Point"}
}