{
  "type": "Feature",
  "properties": {
    "gn:admin1_code":"7.0",
    "gn:asciiname":"Gul Machah",
    "gn:country_code":"PK",
    "gn:dem":3961,
    "gn:feature_class":"P",
    "gn:feature_code":"PPL",
    "gn:name":"Gul Machah",
    "gn:population":0,
    "gn:timezone":"Asia/Karachi",
    "iso:country":"PK",
    "wof:name":"Gul Machah",
    "wof:placetype":"locality"
},
  "geometry": {"coordinates":[73.68241999999999,35.96379],"type":"Point"}
}