{
  "type": "Feature",
  "properties": {
    "gn:admin1_code":"3",
    "gn:asciiname":"Gishar",
    "gn:country_code":"PK",
    "gn:dem":1406,
    "gn:feature_class":"P",
    "gn:feature_code":"PPL",
    "gn:name":"Gishar",
    "gn:population":0,
    "gn:timezone":"Asia/Karachi",
    "iso:country":"PK",
    "wof:name":"Gishar",
    "wof:placetype":"locality"
},
  "geometry": {"coordinates":[72.67424,34.63016],"type":"Point"}
}