{
  "type": "Feature",
  "properties": {
    "gn:admin1_code":"4",
    "gn:asciiname":"Thatta Said Ali",
    "gn:country_code":"PK",
    "gn:dem":183,
    "gn:feature_class":"P",
    "gn:feature_code":"PPL",
    "gn:name":"Thatta Said Ali",
    "gn:population":0,
    "gn:timezone":"Asia/Karachi",
    "iso:country":"PK",
    "name:und_x_variant":[
        "Thatta Sadalli"
    ],
    "wof:name":"Thatta Said Ali",
    "wof:placetype":"locality"
},
  "geometry": {"coordinates":[73.61275999999999,30.98656],"type":"Point"}
}