{
  "type": "Feature",
  "properties": {
    "gn:admin1_code":"4",
    "gn:asciiname":"Chak Nine Makhdum Rashid",
    "gn:country_code":"PK",
    "gn:dem":121,
    "gn:feature_class":"P",
    "gn:feature_code":"PPL",
    "gn:name":"Chak Nine Makhdum Rashid",
    "gn:population":0,
    "gn:timezone":"Asia/Karachi",
    "iso:country":"PK",
    "name:und_x_variant":[
        "Chak Nine MR"
    ],
    "wof:name":"Chak Nine Makhdum Rashid",
    "wof:placetype":"locality"
},
  "geometry": {"coordinates":[71.63122,30.03125],"type":"Point"}
}