{
  "type": "Feature",
  "properties": {
    "gn:admin1_code":"04",
    "gn:asciiname":"Sathwani",
    "gn:country_code":"PK",
    "gn:dem":569,
    "gn:feature_class":"P",
    "gn:feature_code":"PPL",
    "gn:name":"Sathwani",
    "gn:population":0,
    "gn:timezone":"Asia/Karachi",
    "iso:country":"PK",
    "wof:name":"Sathwani",
    "wof:placetype":"locality"
},
  "geometry": {"coordinates":[73.44031,33.42711],"type":"Point"}
}