{
  "type": "Feature",
  "properties": {
    "gn:admin1_code":"2.0",
    "gn:asciiname":"Goth Dad Ali Gorshani",
    "gn:country_code":"PK",
    "gn:dem":70,
    "gn:feature_class":"P",
    "gn:feature_code":"PPL",
    "gn:name":"Goth Dad Ali Gorshani",
    "gn:population":0,
    "gn:timezone":"Asia/Karachi",
    "iso:country":"PK",
    "wof:name":"Goth Dad Ali Gorshani",
    "wof:placetype":"locality"
},
  "geometry": {"coordinates":[68.27502,28.66752],"type":"Point"}
}