{
  "type": "Feature",
  "properties": {
    "gn:admin1_code":"4",
    "gn:asciiname":"Basti Jhandiri",
    "gn:country_code":"PK",
    "gn:dem":103,
    "gn:feature_class":"P",
    "gn:feature_code":"PPL",
    "gn:name":"Basti Jhandiri",
    "gn:population":0,
    "gn:timezone":"Asia/Karachi",
    "iso:country":"PK",
    "name:und_x_variant":[
        "Mad Jhand\u012br"
    ],
    "wof:name":"Basti Jhandiri",
    "wof:placetype":"locality"
},
  "geometry": {"coordinates":[70.49198,29.4339],"type":"Point"}
}