{
  "type": "Feature",
  "properties": {
    "gn:admin1_code":"4",
    "gn:asciiname":"Jhabelwala",
    "gn:country_code":"PK",
    "gn:dem":119,
    "gn:feature_class":"P",
    "gn:feature_code":"PPL",
    "gn:name":"Jhabelw\u0101la",
    "gn:population":0,
    "gn:timezone":"Asia/Karachi",
    "iso:country":"PK",
    "wof:name":"Jhabelwala",
    "wof:placetype":"locality"
},
  "geometry": {"coordinates":[70.6889,30.11192],"type":"Point"}
}