{
  "type": "Feature",
  "properties": {
    "gn:admin1_code":"4.0",
    "gn:asciiname":"Chak Thirty-three -Two Right A",
    "gn:country_code":"PK",
    "gn:dem":181,
    "gn:feature_class":"P",
    "gn:feature_code":"PPL",
    "gn:name":"Chak Thirty-three -Two Right A",
    "gn:population":0,
    "gn:timezone":"Asia/Karachi",
    "iso:country":"PK",
    "name:und_x_variant":[
        "Chak Thrity-three Two RA"
    ],
    "wof:name":"Chak Thirty-three -Two Right A",
    "wof:placetype":"locality"
},
  "geometry": {"coordinates":[73.44973,30.85204],"type":"Point"}
}