{
  "type": "Feature",
  "properties": {
    "gn:admin1_code":"7.0",
    "gn:asciiname":"Gim",
    "gn:country_code":"PK",
    "gn:dem":1751,
    "gn:feature_class":"P",
    "gn:feature_code":"PPL",
    "gn:name":"Gim",
    "gn:population":0,
    "gn:timezone":"Asia/Karachi",
    "iso:country":"PK",
    "wof:name":"Gim",
    "wof:placetype":"locality"
},
  "geometry": {"coordinates":[73.61521,35.65622000000001],"type":"Point"}
}