{
  "type": "Feature",
  "properties": {
    "gn:admin1_code":"02",
    "gn:asciiname":"Goth Kako",
    "gn:country_code":"PK",
    "gn:dem":178,
    "gn:feature_class":"P",
    "gn:feature_code":"PPL",
    "gn:name":"Goth Kako",
    "gn:population":0,
    "gn:timezone":"Asia/Karachi",
    "iso:country":"PK",
    "name:und_x_variant":[
        "Goth Gullu",
        "Goth Gaggoo",
        "Goth Kako"
    ],
    "wof:name":"Goth Kako",
    "wof:placetype":"locality"
},
  "geometry": {"coordinates":[67.21162,25.70415],"type":"Point"}
}