{
  "type": "Feature",
  "properties": {
    "gn:admin1_code":"5.0",
    "gn:asciiname":"Goth Sangat Faqir",
    "gn:country_code":"PK",
    "gn:dem":386,
    "gn:feature_class":"P",
    "gn:feature_code":"PPL",
    "gn:name":"Goth Sangat Faqir",
    "gn:population":0,
    "gn:timezone":"Asia/Karachi",
    "iso:country":"PK",
    "name:und_x_variant":[
        "Goth Sangat Peqir"
    ],
    "wof:name":"Goth Sangat Faqir",
    "wof:placetype":"locality"
},
  "geometry": {"coordinates":[67.46364,25.53324],"type":"Point"}
}