{
  "type": "Feature",
  "properties": {
    "gn:admin1_code":"3",
    "gn:asciiname":"Mund",
    "gn:country_code":"PK",
    "gn:dem":756,
    "gn:feature_class":"P",
    "gn:feature_code":"PPL",
    "gn:name":"Mund",
    "gn:population":0,
    "gn:timezone":"Asia/Karachi",
    "iso:country":"PK",
    "name:und_x_variant":[
        "Masand"
    ],
    "wof:name":"Mund",
    "wof:placetype":"locality"
},
  "geometry": {"coordinates":[72.95623000000001,34.26834],"type":"Point"}
}