{
  "type": "Feature",
  "properties": {
    "gn:admin1_code":"3",
    "gn:asciiname":"Mund",
    "gn:country_code":"PK",
    "gn:dem":756,
    "gn:feature_class":"P",
    "gn:feature_code":"PPL",
    "gn:name":"Mund",
    "gn:population":0,
    "gn:timezone":"Asia/Karachi",
    "iso:country":"PK",
    "name:cat_x_preferred":[
        "Mund"
    ],
    "name:ceb_x_preferred":[
        "Mund"
    ],
    "name:deu_x_preferred":[
        "Mund"
    ],
    "name:fra_x_preferred":[
        "Mund"
    ],
    "name:ita_x_preferred":[
        "Mund"
    ],
    "name:lmo_x_preferred":[
        "Mund"
    ],
    "name:msa_x_preferred":[
        "Mund"
    ],
    "name:nld_x_preferred":[
        "Mund"
    ],
    "name:nno_x_preferred":[
        "Mund"
    ],
    "name:pms_x_preferred":[
        "Mund"
    ],
    "name:por_x_preferred":[
        "Mund"
    ],
    "name:roh_x_preferred":[
        "Mund"
    ],
    "name:spa_x_preferred":[
        "Mund"
    ],
    "name:sqi_x_preferred":[
        "Mund"
    ],
    "name:swe_x_preferred":[
        "Mund"
    ],
    "name:und_x_variant":[
        "Masand"
    ],
    "name:vol_x_preferred":[
        "Mund"
    ],
    "name:war_x_preferred":[
        "Mund"
    ],
    "wof:name":"Mund",
    "wof:placetype":"locality"
},
  "geometry": {"coordinates":[72.95623000000001,34.26834],"type":"Point"}
}