{
  "type": "Feature",
  "properties": {
    "gn:admin1_code":"05",
    "gn:asciiname":"Goth Mamu Nahanjo",
    "gn:country_code":"PK",
    "gn:dem":7,
    "gn:feature_class":"P",
    "gn:feature_code":"PPL",
    "gn:name":"Goth Mamu Nahanjo",
    "gn:population":0,
    "gn:timezone":"Asia/Karachi",
    "iso:country":"PK",
    "wof:name":"Goth Mamu Nahanjo",
    "wof:placetype":"locality"
},
  "geometry": {"coordinates":[67.74920999999999,24.27286],"type":"Point"}
}