{
  "type": "Feature",
  "properties": {
    "gn:admin1_code":"4.0",
    "gn:asciiname":"Amba",
    "gn:country_code":"PK",
    "gn:dem":205,
    "gn:feature_class":"P",
    "gn:feature_code":"PPL",
    "gn:name":"Amba",
    "gn:population":0,
    "gn:timezone":"Asia/Karachi",
    "iso:country":"PK",
    "name:ceb_x_preferred":[
        "Amba"
    ],
    "name:fra_x_preferred":[
        "Amba"
    ],
    "name:ita_x_preferred":[
        "Amba"
    ],
    "name:pol_x_preferred":[
        "Amba"
    ],
    "name:rus_x_preferred":[
        "\u0410\u043c\u0431\u0430"
    ],
    "name:spa_x_preferred":[
        "Amba"
    ],
    "name:swe_x_preferred":[
        "Amba"
    ],
    "name:und_x_variant":[
        "Ambh"
    ],
    "wof:name":"Amba",
    "wof:placetype":"locality"
},
  "geometry": {"coordinates":[73.96876999999998,31.5816],"type":"Point"}
}