{
  "type": "Feature",
  "properties": {
    "gn:admin1_code":"4.0",
    "gn:asciiname":"Basti Doctor Rahmani",
    "gn:country_code":"PK",
    "gn:dem":137,
    "gn:feature_class":"P",
    "gn:feature_code":"PPL",
    "gn:name":"Basti Doctor Rahmani",
    "gn:population":0,
    "gn:timezone":"Asia/Karachi",
    "iso:country":"PK",
    "wof:name":"Basti Doctor Rahmani",
    "wof:placetype":"locality"
},
  "geometry": {"coordinates":[71.02074,30.56426],"type":"Point"}
}