{
  "type": "Feature",
  "properties": {
    "gn:admin1_code":"5.0",
    "gn:asciiname":"Jherruck",
    "gn:country_code":"PK",
    "gn:dem":28,
    "gn:feature_class":"P",
    "gn:feature_code":"PPL",
    "gn:name":"Jherruck",
    "gn:population":0,
    "gn:timezone":"Asia/Karachi",
    "iso:country":"PK",
    "name:eng_x_preferred":[
        "Jerruck"
    ],
    "name:und_x_variant":[
        "Jhirruck"
    ],
    "wof:name":"Jherruck",
    "wof:placetype":"locality"
},
  "geometry": {"coordinates":[68.25572,25.05429],"type":"Point"}
}