{
  "type": "Feature",
  "properties": {
    "gn:admin1_code":"3",
    "gn:asciiname":"Matnu",
    "gn:country_code":"PK",
    "gn:dem":2955,
    "gn:feature_class":"P",
    "gn:feature_code":"PPL",
    "gn:name":"Matnu",
    "gn:population":0,
    "gn:timezone":"Asia/Karachi",
    "iso:country":"PK",
    "name:und_x_variant":[
        "Mothu"
    ],
    "wof:name":"Matnu",
    "wof:placetype":"locality"
},
  "geometry": {"coordinates":[73.46119,34.75652],"type":"Point"}
}