{
  "type": "Feature",
  "properties": {
    "gn:admin1_code":"3.0",
    "gn:asciiname":"Baghpur Dheri",
    "gn:country_code":"PK",
    "gn:dem":884,
    "gn:feature_class":"P",
    "gn:feature_code":"PPL",
    "gn:name":"Baghpur Dheri",
    "gn:population":0,
    "gn:timezone":"Asia/Karachi",
    "iso:country":"PK",
    "name:eng_x_preferred":[
        "Baghpur Dheri"
    ],
    "wof:name":"Baghpur Dheri",
    "wof:placetype":"locality"
},
  "geometry": {"coordinates":[73.06440000000001,33.80399],"type":"Point"}
}