{
  "type": "Feature",
  "properties": {
    "gn:admin1_code":"1.0",
    "gn:asciiname":"Bakar Garhi",
    "gn:country_code":"PK",
    "gn:dem":1890,
    "gn:feature_class":"P",
    "gn:feature_code":"PPL",
    "gn:name":"Bakar Garhi",
    "gn:population":0,
    "gn:timezone":"Asia/Karachi",
    "iso:country":"PK",
    "wof:name":"Bakar Garhi",
    "wof:placetype":"locality"
},
  "geometry": {"coordinates":[70.8074,33.73419000000001],"type":"Point"}
}