{
  "type": "Feature",
  "properties": {
    "gn:admin1_code":"5",
    "gn:asciiname":"Munshi Ghulam Muhammad",
    "gn:country_code":"PK",
    "gn:dem":10,
    "gn:feature_class":"P",
    "gn:feature_code":"PPL",
    "gn:name":"Munshi Ghulam Muhammad",
    "gn:population":0,
    "gn:timezone":"Asia/Karachi",
    "iso:country":"PK",
    "wof:name":"Munshi Ghulam Muhammad",
    "wof:placetype":"neighbourhood"
},
  "geometry": {"coordinates":[69.56379,25.18634],"type":"Point"}
}