{
  "type": "Feature",
  "properties": {
    "gn:admin1_code":"4.0",
    "gn:asciiname":"Welasar",
    "gn:country_code":"PK",
    "gn:dem":830,
    "gn:feature_class":"P",
    "gn:feature_code":"PPL",
    "gn:name":"Welasar",
    "gn:population":0,
    "gn:timezone":"Asia/Karachi",
    "iso:country":"PK",
    "wof:name":"Welasar",
    "wof:placetype":"locality"
},
  "geometry": {"coordinates":[72.48199,32.6315],"type":"Point"}
}