{
  "type": "Feature",
  "properties": {
    "gn:admin1_code":"07",
    "gn:asciiname":"Nar",
    "gn:country_code":"PK",
    "gn:dem":2284,
    "gn:feature_class":"P",
    "gn:feature_code":"PPL",
    "gn:name":"Nar",
    "gn:population":0,
    "gn:timezone":"Asia/Karachi",
    "iso:country":"PK",
    "name:und_x_variant":[
        "Narh"
    ],
    "wof:name":"Nar",
    "wof:placetype":"locality"
},
  "geometry": {"coordinates":[75.8325,35.34255],"type":"Point"}
}