{
  "type": "Feature",
  "properties": {
    "gn:admin1_code":"4.0",
    "gn:asciiname":"Baba Nur Shah",
    "gn:country_code":"PK",
    "gn:dem":132,
    "gn:feature_class":"P",
    "gn:feature_code":"PPL",
    "gn:name":"Baba Nur Shah",
    "gn:population":0,
    "gn:timezone":"Asia/Karachi",
    "iso:country":"PK",
    "wof:name":"Baba Nur Shah",
    "wof:placetype":"locality"
},
  "geometry": {"coordinates":[71.93361,30.37172],"type":"Point"}
}