{
  "type": "Feature",
  "properties": {
    "gn:admin1_code":"5",
    "gn:asciiname":"Goth Amin Hakro",
    "gn:country_code":"PK",
    "gn:dem":68,
    "gn:feature_class":"P",
    "gn:feature_code":"PPL",
    "gn:name":"Goth Amin Hakro",
    "gn:population":0,
    "gn:timezone":"Asia/Karachi",
    "iso:country":"PK",
    "name:und_x_variant":[
        "L\u0101lu Hakro"
    ],
    "wof:name":"Goth Amin Hakro",
    "wof:placetype":"locality"
},
  "geometry": {"coordinates":[68.80989,27.86249],"type":"Point"}
}