{
  "type": "Feature",
  "properties": {
    "gn:admin1_code":"1",
    "gn:asciiname":"Zauki Kalan",
    "gn:country_code":"PK",
    "gn:dem":573,
    "gn:feature_class":"P",
    "gn:feature_code":"PPL",
    "gn:name":"Zauki Kalan",
    "gn:population":0,
    "gn:timezone":"Asia/Karachi",
    "iso:country":"PK",
    "wof:name":"Zauki Kalan",
    "wof:placetype":"locality"
},
  "geometry": {"coordinates":[70.8381,33.1701],"type":"Point"}
}