{
  "type": "Feature",
  "properties": {
    "gn:admin1_code":"6.0",
    "gn:asciiname":"Kala Katha",
    "gn:country_code":"PK",
    "gn:dem":2732,
    "gn:feature_class":"P",
    "gn:feature_code":"PPL",
    "gn:name":"Kala Katha",
    "gn:population":0,
    "gn:timezone":"Asia/Karachi",
    "iso:country":"PK",
    "wof:name":"Kala Katha",
    "wof:placetype":"locality"
},
  "geometry": {"coordinates":[73.9627,33.99891],"type":"Point"}
}