{
  "type": "Feature",
  "properties": {
    "gn:admin1_code":"02",
    "gn:asciiname":"Libach",
    "gn:country_code":"PK",
    "gn:dem":536,
    "gn:feature_class":"P",
    "gn:feature_code":"PPL",
    "gn:name":"Libach",
    "gn:population":0,
    "gn:timezone":"Asia/Karachi",
    "iso:country":"PK",
    "name:und_x_variant":[
        "Labach"
    ],
    "wof:name":"Libach",
    "wof:placetype":"locality"
},
  "geometry": {"coordinates":[65.22242,26.48176],"type":"Point"}
}