{
  "type": "Feature",
  "properties": {
    "gn:admin1_code":"2.0",
    "gn:asciiname":"Alandur",
    "gn:country_code":"PK",
    "gn:dem":534,
    "gn:feature_class":"P",
    "gn:feature_code":"PPL",
    "gn:name":"Alandur",
    "gn:population":0,
    "gn:timezone":"Asia/Karachi",
    "iso:country":"PK",
    "wof:name":"Alandur",
    "wof:placetype":"locality"
},
  "geometry": {"coordinates":[63.02871,26.2992],"type":"Point"}
}