{
  "type": "Feature",
  "properties": {
    "gn:admin1_code":"7.0",
    "gn:asciiname":"Beyang Baihk",
    "gn:country_code":"PK",
    "gn:dem":3816,
    "gn:feature_class":"P",
    "gn:feature_code":"PPL",
    "gn:name":"Beyang Baihk",
    "gn:population":0,
    "gn:timezone":"Asia/Karachi",
    "iso:country":"PK",
    "wof:name":"Beyang Baihk",
    "wof:placetype":"locality"
},
  "geometry": {"coordinates":[74.73404000000002,35.11665],"type":"Point"}
}