{
  "type": "Feature",
  "properties": {
    "gn:admin1_code":"03",
    "gn:asciiname":"Pore Kalle",
    "gn:country_code":"PK",
    "gn:dem":1002,
    "gn:feature_class":"P",
    "gn:feature_code":"PPL",
    "gn:name":"Pore Kalle",
    "gn:population":0,
    "gn:timezone":"Asia/Karachi",
    "iso:country":"PK",
    "name:eng_x_preferred":[
        "Porai Qal\u0101gai"
    ],
    "wof:name":"Pore Kalle",
    "wof:placetype":"locality"
},
  "geometry": {"coordinates":[71.91216,34.8384],"type":"Point"}
}