{
  "type": "Feature",
  "properties": {
    "gn:admin1_code":"4.0",
    "gn:asciiname":"Jand Khanzada",
    "gn:country_code":"PK",
    "gn:dem":453,
    "gn:feature_class":"P",
    "gn:feature_code":"PPL",
    "gn:name":"Jand Khanzada",
    "gn:population":0,
    "gn:timezone":"Asia/Karachi",
    "iso:country":"PK",
    "wof:name":"Jand Khanzada",
    "wof:placetype":"locality"
},
  "geometry": {"coordinates":[73.10500999999999,32.9394],"type":"Point"}
}