{
  "type": "Feature",
  "properties": {
    "gn:admin1_code":"6.0",
    "gn:asciiname":"Anchhoha",
    "gn:country_code":"PK",
    "gn:dem":483,
    "gn:feature_class":"P",
    "gn:feature_code":"PPL",
    "gn:name":"Anchhoha",
    "gn:population":0,
    "gn:timezone":"Asia/Karachi",
    "iso:country":"PK",
    "wof:name":"Anchhoha",
    "wof:placetype":"locality"
},
  "geometry": {"coordinates":[73.53075,33.39981],"type":"Point"}
}