{
  "type": "Feature",
  "properties": {
    "gn:admin1_code":"5",
    "gn:asciiname":"Miran Shah",
    "gn:country_code":"PK",
    "gn:dem":21,
    "gn:feature_class":"P",
    "gn:feature_code":"PPL",
    "gn:name":"Miran Shah",
    "gn:population":0,
    "gn:timezone":"Asia/Karachi",
    "iso:country":"PK",
    "name:ara_x_preferred":[
        "\u0645\u064a\u0631\u0627\u0646 \u0634\u0627\u0647 \u0628\u0646 \u062a\u064a\u0645\u0648\u0631\u0644\u0646\u0643"
    ],
    "name:azb_x_preferred":[
        "\u0645\u06cc\u0631\u0627\u0646 \u0634\u0627\u0647\u06cc"
    ],
    "name:aze_x_preferred":[
        "Miran \u015fah"
    ],
    "name:cat_x_preferred":[
        "Miran Xah"
    ],
    "name:deu_x_preferred":[
        "Miran Schah"
    ],
    "name:fas_x_preferred":[
        "\u062c\u0644\u0627\u0644\u200c\u0627\u0644\u062f\u06cc\u0646 \u0645\u06cc\u0631\u0627\u0646\u200c\u0634\u0627\u0647 \u062a\u06cc\u0645\u0648\u0631\u06cc"
    ],
    "name:fra_x_preferred":[
        "Miran Shah"
    ],
    "name:jpn_x_preferred":[
        "\u30df\u30fc\u30e9\u30fc\u30f3\u30fb\u30b7\u30e3\u30fc"
    ],
    "name:kor_x_preferred":[
        "\ubbf8\ub780 \uc0e4"
    ],
    "name:pol_x_preferred":[
        "Miranszah"
    ],
    "name:rus_x_preferred":[
        "\u041c\u0438\u0440\u0430\u043d-\u0448\u0430\u0445"
    ],
    "name:slv_x_preferred":[
        "Miran \u0160ah"
    ],
    "name:spa_x_preferred":[
        "Miran Shah"
    ],
    "name:tur_x_preferred":[
        "Miran\u015fah"
    ],
    "name:ukr_x_preferred":[
        "\u041c\u0456\u0440\u0430\u043d-\u0448\u0430\u0445"
    ],
    "name:uzb_x_preferred":[
        "Mironshoh"
    ],
    "name:zho_x_preferred":[
        "\u7c73\u862d\u6c99"
    ],
    "wof:name":"Miran Shah",
    "wof:placetype":"locality"
},
  "geometry": {"coordinates":[68.57437,25.39815],"type":"Point"}
}