{
  "type": "Feature",
  "properties": {
    "gn:admin1_code":"3.0",
    "gn:asciiname":"Talab Yousuf Khan Kalle",
    "gn:country_code":"PK",
    "gn:dem":305,
    "gn:feature_class":"P",
    "gn:feature_code":"PPL",
    "gn:name":"Talab Yousuf Khan Kalle",
    "gn:population":0,
    "gn:timezone":"Asia/Karachi",
    "iso:country":"PK",
    "name:eng_x_preferred":[
        "Yusuf Kh\u0101n Kili"
    ],
    "wof:name":"Talab Yousuf Khan Kalle",
    "wof:placetype":"locality"
},
  "geometry": {"coordinates":[71.88843,34.10115],"type":"Point"}
}