{
  "type": "Feature",
  "properties": {
    "gn:admin1_code":"4.0",
    "gn:asciiname":"Dera Yar Muhammad Luk",
    "gn:country_code":"PK",
    "gn:dem":192,
    "gn:feature_class":"P",
    "gn:feature_code":"PPL",
    "gn:name":"Dera Yar Muhammad Luk",
    "gn:population":0,
    "gn:timezone":"Asia/Karachi",
    "iso:country":"PK",
    "name:und_x_variant":[
        "Dera Y\u0101r Muhammad"
    ],
    "wof:name":"Dera Yar Muhammad Luk",
    "wof:placetype":"locality"
},
  "geometry": {"coordinates":[72.7388,32.24158],"type":"Point"}
}