{
  "type": "Feature",
  "properties": {
    "gn:admin1_code":"3",
    "gn:asciiname":"Zormandai",
    "gn:country_code":"PK",
    "gn:dem":484,
    "gn:feature_class":"P",
    "gn:feature_code":"PPL",
    "gn:name":"Zormandai",
    "gn:population":0,
    "gn:timezone":"Asia/Karachi",
    "iso:country":"PK",
    "name:eng_x_preferred":[
        "Zormandai"
    ],
    "wof:name":"Zormandai",
    "wof:placetype":"locality"
},
  "geometry": {"coordinates":[72.0852,34.52129],"type":"Point"}
}