{
  "type": "Feature",
  "properties": {
    "gn:admin1_code":"6",
    "gn:asciiname":"Chhawa Kasbian",
    "gn:country_code":"PK",
    "gn:dem":753,
    "gn:feature_class":"P",
    "gn:feature_code":"PPL",
    "gn:name":"Chhawa Kasbian",
    "gn:population":0,
    "gn:timezone":"Asia/Karachi",
    "iso:country":"PK",
    "name:und_x_variant":[
        "Chhawa K\u0101abi\u0101n"
    ],
    "wof:name":"Chhawa Kasbian",
    "wof:placetype":"locality"
},
  "geometry": {"coordinates":[74.13004000000002,33.11535],"type":"Point"}
}