{
  "type": "Feature",
  "properties": {
    "gn:admin1_code":"01",
    "gn:asciiname":"Pir Makan",
    "gn:country_code":"PK",
    "gn:dem":1375,
    "gn:feature_class":"P",
    "gn:feature_code":"PPL",
    "gn:name":"Pir Makan",
    "gn:population":0,
    "gn:timezone":"Asia/Karachi",
    "iso:country":"PK",
    "wof:name":"Pir Makan",
    "wof:placetype":"locality"
},
  "geometry": {"coordinates":[69.57701,32.2793],"type":"Point"}
}