{
  "type": "Feature",
  "properties": {
    "gn:admin1_code":"5",
    "gn:asciiname":"Goth Jan Muhammad",
    "gn:country_code":"PK",
    "gn:dem":54,
    "gn:feature_class":"P",
    "gn:feature_code":"PPL",
    "gn:name":"Goth Jan Muhammad",
    "gn:population":0,
    "gn:timezone":"Asia/Karachi",
    "iso:country":"PK",
    "name:und_x_variant":[
        "J\u0101n Muhammad"
    ],
    "wof:name":"Goth Jan Muhammad",
    "wof:placetype":"locality"
},
  "geometry": {"coordinates":[68.38894999999999,27.42769],"type":"Point"}
}