{
  "type": "Feature",
  "properties": {
    "gn:admin1_code":"2.0",
    "gn:asciiname":"Tawak",
    "gn:country_code":"PK",
    "gn:dem":2300,
    "gn:feature_class":"P",
    "gn:feature_code":"PPL",
    "gn:name":"Tawak",
    "gn:population":0,
    "gn:timezone":"Asia/Karachi",
    "iso:country":"PK",
    "wof:name":"Tawak",
    "wof:placetype":"locality"
},
  "geometry": {"coordinates":[66.67124,28.77841],"type":"Point"}
}