{
  "type": "Feature",
  "properties": {
    "gn:admin1_code":"4.0",
    "gn:asciiname":"Doranpur",
    "gn:country_code":"PK",
    "gn:dem":141,
    "gn:feature_class":"P",
    "gn:feature_code":"PPL",
    "gn:name":"Doranpur",
    "gn:population":0,
    "gn:timezone":"Asia/Karachi",
    "iso:country":"PK",
    "name:und_x_variant":[
        "Khudayar Kathia",
        "Doranpur",
        "Daur\u0101npur"
    ],
    "wof:name":"Doranpur",
    "wof:placetype":"locality"
},
  "geometry": {"coordinates":[72.10039999999999,30.77209],"type":"Point"}
}