{
  "type": "Feature",
  "properties": {
    "gn:admin1_code":"4.0",
    "gn:asciiname":"Jaliari Bhai Khan",
    "gn:country_code":"PK",
    "gn:dem":531,
    "gn:feature_class":"P",
    "gn:feature_code":"PPL",
    "gn:name":"Jaliari Bhai Khan",
    "gn:population":0,
    "gn:timezone":"Asia/Karachi",
    "iso:country":"PK",
    "name:und_x_variant":[
        "Jalh\u0101ri Bhai Kh\u0101n"
    ],
    "wof:name":"Jaliari Bhai Khan",
    "wof:placetype":"locality"
},
  "geometry": {"coordinates":[73.22246,33.40088],"type":"Point"}
}