{
  "type": "Feature",
  "properties": {
    "gn:admin1_code":"2.0",
    "gn:asciiname":"Jamatgai",
    "gn:country_code":"PK",
    "gn:dem":2381,
    "gn:feature_class":"P",
    "gn:feature_code":"PPL",
    "gn:name":"Jamatgai",
    "gn:population":0,
    "gn:timezone":"Asia/Karachi",
    "iso:country":"PK",
    "wof:name":"Jamatgai",
    "wof:placetype":"locality"
},
  "geometry": {"coordinates":[67.39615000000001,30.99199],"type":"Point"}
}