{
  "type": "Feature",
  "properties": {
    "gn:admin1_code":"04",
    "gn:asciiname":"Mardani",
    "gn:country_code":"PK",
    "gn:dem":181,
    "gn:feature_class":"P",
    "gn:feature_code":"PPL",
    "gn:name":"Mardani",
    "gn:population":0,
    "gn:timezone":"Asia/Karachi",
    "iso:country":"PK",
    "name:und_x_variant":[
        "Murdani",
        "Mardani"
    ],
    "wof:name":"Mardani",
    "wof:placetype":"locality"
},
  "geometry": {"coordinates":[73.41336,30.98855],"type":"Point"}
}