{
  "type": "Feature",
  "properties": {
    "gn:admin1_code":"6",
    "gn:asciiname":"Basnara",
    "gn:country_code":"PK",
    "gn:dem":866,
    "gn:feature_class":"P",
    "gn:feature_code":"PPL",
    "gn:name":"Basnara",
    "gn:population":0,
    "gn:timezone":"Asia/Karachi",
    "iso:country":"PK",
    "wof:name":"Basnara",
    "wof:placetype":"locality"
},
  "geometry": {"coordinates":[73.49341,34.28103],"type":"Point"}
}