{
  "type": "Feature",
  "properties": {
    "gn:admin1_code":"4.0",
    "gn:asciiname":"Rae da Khu",
    "gn:country_code":"PK",
    "gn:dem":85,
    "gn:feature_class":"P",
    "gn:feature_code":"PPL",
    "gn:name":"Rae da Khu",
    "gn:population":0,
    "gn:timezone":"Asia/Karachi",
    "iso:country":"PK",
    "wof:name":"Rae da Khu",
    "wof:placetype":"locality"
},
  "geometry": {"coordinates":[70.38749,28.57363],"type":"Point"}
}