{
  "type": "Feature",
  "properties": {
    "gn:admin1_code":"5",
    "gn:asciiname":"Khararo",
    "gn:country_code":"PK",
    "gn:dem":69,
    "gn:feature_class":"P",
    "gn:feature_code":"PPL",
    "gn:name":"Khararo",
    "gn:population":0,
    "gn:timezone":"Asia/Karachi",
    "iso:country":"PK",
    "name:und_x_variant":[
        "Kh\u0101fara"
    ],
    "wof:name":"Khararo",
    "wof:placetype":"locality"
},
  "geometry": {"coordinates":[69.15899,27.46245],"type":"Point"}
}