{
  "type": "Feature",
  "properties": {
    "gn:admin1_code":"3.0",
    "gn:asciiname":"Dargai",
    "gn:country_code":"PK",
    "gn:dem":316,
    "gn:feature_class":"P",
    "gn:feature_code":"PPL",
    "gn:name":"Dargai",
    "gn:population":0,
    "gn:timezone":"Asia/Karachi",
    "iso:country":"PK",
    "name:eng_x_preferred":[
        "Dargai"
    ],
    "name:fas_x_preferred":[
        "\u062f\u0631\u06af\u0626\u06cc"
    ],
    "name:urd_x_preferred":[
        "\u062f\u0631\u06af\u0626\u06cc"
    ],
    "wof:name":"Dargai",
    "wof:placetype":"locality"
},
  "geometry": {"coordinates":[71.88672,34.18064],"type":"Point"}
}