{
  "type": "Feature",
  "properties": {
    "gn:admin1_code":"3.0",
    "gn:asciiname":"Madd Adda",
    "gn:country_code":"PK",
    "gn:dem":533,
    "gn:feature_class":"P",
    "gn:feature_code":"PPL",
    "gn:name":"Madd Adda",
    "gn:population":0,
    "gn:timezone":"Asia/Karachi",
    "iso:country":"PK",
    "wof:name":"Madd Adda",
    "wof:placetype":"locality"
},
  "geometry": {"coordinates":[71.64243,33.17372],"type":"Point"}
}