{
  "type": "Feature",
  "properties": {
    "gn:admin1_code":"4.0",
    "gn:asciiname":"Chak Thirty-eight -Two Right",
    "gn:country_code":"PK",
    "gn:dem":177,
    "gn:feature_class":"P",
    "gn:feature_code":"PPL",
    "gn:name":"Chak Thirty-eight -Two Right",
    "gn:population":0,
    "gn:timezone":"Asia/Karachi",
    "iso:country":"PK",
    "wof:name":"Chak Thirty-eight -Two Right",
    "wof:placetype":"locality"
},
  "geometry": {"coordinates":[73.43954000000002,30.8553],"type":"Point"}
}