{
  "type": "Feature",
  "properties": {
    "gn:admin1_code":"3",
    "gn:asciiname":"Kithar",
    "gn:country_code":"PK",
    "gn:dem":2362,
    "gn:feature_class":"P",
    "gn:feature_code":"PPL",
    "gn:name":"Kithar",
    "gn:population":0,
    "gn:timezone":"Asia/Karachi",
    "iso:country":"PK",
    "name:und_x_variant":[
        "Khetar"
    ],
    "wof:name":"Kithar",
    "wof:placetype":"locality"
},
  "geometry": {"coordinates":[73.505,34.69032],"type":"Point"}
}