{
  "type": "Feature",
  "properties": {
    "gn:admin1_code":"3",
    "gn:asciiname":"Manda Gucha",
    "gn:country_code":"PK",
    "gn:dem":1709,
    "gn:feature_class":"P",
    "gn:feature_code":"PPL",
    "gn:name":"Manda Gucha",
    "gn:population":0,
    "gn:timezone":"Asia/Karachi",
    "iso:country":"PK",
    "name:und_x_variant":[
        "Manda",
        "Kuchha",
        "Manda Kuchha",
        "Manda Gucha"
    ],
    "wof:name":"Manda Gucha",
    "wof:placetype":"locality"
},
  "geometry": {"coordinates":[73.26118000000002,34.6641],"type":"Point"}
}