{
  "type": "Feature",
  "properties": {
    "gn:admin1_code":"3.0",
    "gn:asciiname":"Ratian",
    "gn:country_code":"PK",
    "gn:dem":1241,
    "gn:feature_class":"P",
    "gn:feature_code":"PPL",
    "gn:name":"Ratian",
    "gn:population":0,
    "gn:timezone":"Asia/Karachi",
    "iso:country":"PK",
    "name:eng_x_preferred":[
        "Rati\u0101n"
    ],
    "wof:name":"Ratian",
    "wof:placetype":"locality"
},
  "geometry": {"coordinates":[73.07223,33.93101],"type":"Point"}
}