{
  "type": "Feature",
  "properties": {
    "gn:admin1_code":"4.0",
    "gn:asciiname":"Gahnewala Basti",
    "gn:country_code":"PK",
    "gn:dem":127,
    "gn:feature_class":"P",
    "gn:feature_code":"PPL",
    "gn:name":"Gahnewala Basti",
    "gn:population":0,
    "gn:timezone":"Asia/Karachi",
    "iso:country":"PK",
    "name:und_x_variant":[
        "G\u0101hnew\u0101la"
    ],
    "wof:name":"Gahnewala Basti",
    "wof:placetype":"locality"
},
  "geometry": {"coordinates":[71.03109000000001,30.32052],"type":"Point"}
}