{
  "type": "Feature",
  "properties": {
    "gn:admin1_code":"4.0",
    "gn:asciiname":"Bhopattian",
    "gn:country_code":"PK",
    "gn:dem":210,
    "gn:feature_class":"P",
    "gn:feature_code":"PPL",
    "gn:name":"Bhopattian",
    "gn:population":0,
    "gn:timezone":"Asia/Karachi",
    "iso:country":"PK",
    "name:und_x_variant":[
        "Bhopetti\u0101n",
        "Bhopatian",
        "Bhopattian"
    ],
    "wof:name":"Bhopattian",
    "wof:placetype":"locality"
},
  "geometry": {"coordinates":[74.22703,31.40238],"type":"Point"}
}