{
  "type": "Feature",
  "properties": {
    "gn:admin1_code":"6",
    "gn:asciiname":"Rachhyal",
    "gn:country_code":"PK",
    "gn:dem":420,
    "gn:feature_class":"P",
    "gn:feature_code":"PPL",
    "gn:name":"Rachhyal",
    "gn:population":0,
    "gn:timezone":"Asia/Karachi",
    "iso:country":"PK",
    "wof:name":"Rachhyal",
    "wof:placetype":"locality"
},
  "geometry": {"coordinates":[73.74048000000001,33.15036],"type":"Point"}
}