{
  "type": "Feature",
  "properties": {
    "gn:admin1_code":"4.0",
    "gn:asciiname":"Kot Sundarwali",
    "gn:country_code":"PK",
    "gn:dem":159,
    "gn:feature_class":"P",
    "gn:feature_code":"PPL",
    "gn:name":"Kot Sundarwali",
    "gn:population":0,
    "gn:timezone":"Asia/Karachi",
    "iso:country":"PK",
    "name:und_x_variant":[
        "Moza Kair Singh"
    ],
    "wof:name":"Kot Sundarwali",
    "wof:placetype":"locality"
},
  "geometry": {"coordinates":[73.22134,29.76943],"type":"Point"}
}