{
  "type": "Feature",
  "properties": {
    "gn:admin1_code":"3",
    "gn:asciiname":"Dambara",
    "gn:country_code":"PK",
    "gn:dem":932,
    "gn:feature_class":"P",
    "gn:feature_code":"PPL",
    "gn:name":"Dambara",
    "gn:population":0,
    "gn:timezone":"Asia/Karachi",
    "iso:country":"PK",
    "name:und_x_variant":[
        "Dambar\u0101h"
    ],
    "wof:name":"Dambara",
    "wof:placetype":"locality"
},
  "geometry": {"coordinates":[73.1955,34.45095],"type":"Point"}
}