{
  "type": "Feature",
  "properties": {
    "gn:admin1_code":"4.0",
    "gn:asciiname":"Dodhum Kalan",
    "gn:country_code":"PK",
    "gn:dem":293,
    "gn:feature_class":"P",
    "gn:feature_code":"PPL",
    "gn:name":"Dodhum Kalan",
    "gn:population":0,
    "gn:timezone":"Asia/Karachi",
    "iso:country":"PK",
    "wof:name":"Dodhum Kalan",
    "wof:placetype":"locality"
},
  "geometry": {"coordinates":[75.07441,32.39163],"type":"Point"}
}