{
  "type": "Feature",
  "properties": {
    "gn:admin1_code":"2.0",
    "gn:asciiname":"Zaebai Kili",
    "gn:country_code":"PK",
    "gn:dem":1301,
    "gn:feature_class":"P",
    "gn:feature_code":"PPL",
    "gn:name":"Zaebai Kili",
    "gn:population":0,
    "gn:timezone":"Asia/Karachi",
    "iso:country":"PK",
    "wof:name":"Zaebai Kili",
    "wof:placetype":"locality"
},
  "geometry": {"coordinates":[69.59056,31.61029000000001],"type":"Point"}
}