{
  "type": "Feature",
  "properties": {
    "gn:admin1_code":"7.0",
    "gn:asciiname":"Haltar",
    "gn:country_code":"PK",
    "gn:dem":2624,
    "gn:feature_class":"P",
    "gn:feature_code":"PPL",
    "gn:name":"Haltar",
    "gn:population":0,
    "gn:timezone":"Asia/Karachi",
    "iso:country":"PK",
    "wof:name":"Haltar",
    "wof:placetype":"locality"
},
  "geometry": {"coordinates":[74.1703,35.9643],"type":"Point"}
}