{
  "type": "Feature",
  "properties": {
    "gn:admin1_code":"2.0",
    "gn:asciiname":"Firoz-i-Kan",
    "gn:country_code":"PK",
    "gn:dem":2305,
    "gn:feature_class":"P",
    "gn:feature_code":"PPL",
    "gn:name":"Firoz-i-Kan",
    "gn:population":0,
    "gn:timezone":"Asia/Karachi",
    "iso:country":"PK",
    "name:und_x_variant":[
        "Firoz-i-k\u0101nr",
        "Feroz-i-K\u0101n",
        "Firoz-i-Kan"
    ],
    "wof:name":"Firoz-i-Kan",
    "wof:placetype":"locality"
},
  "geometry": {"coordinates":[67.58129,30.69183],"type":"Point"}
}