{
  "type": "Feature",
  "properties": {
    "gn:admin1_code":"3",
    "gn:asciiname":"Shna Ranzara",
    "gn:country_code":"PK",
    "gn:dem":1702,
    "gn:feature_class":"P",
    "gn:feature_code":"PPL",
    "gn:name":"Shna Ranzara",
    "gn:population":0,
    "gn:timezone":"Asia/Karachi",
    "iso:country":"PK",
    "wof:name":"Shna Ranzara",
    "wof:placetype":"locality"
},
  "geometry": {"coordinates":[72.10111999999999,34.87138],"type":"Point"}
}