{
  "type": "Feature",
  "properties": {
    "gn:admin1_code":"2.0",
    "gn:asciiname":"Dozan",
    "gn:country_code":"PK",
    "gn:dem":1731,
    "gn:feature_class":"P",
    "gn:feature_code":"PPL",
    "gn:name":"Dozan",
    "gn:population":0,
    "gn:timezone":"Asia/Karachi",
    "iso:country":"PK",
    "name:und_x_variant":[
        "Doz\u0101ni",
        "Dozan"
    ],
    "wof:name":"Dozan",
    "wof:placetype":"locality"
},
  "geometry": {"coordinates":[67.18602,29.94158],"type":"Point"}
}