{
  "type": "Feature",
  "properties": {
    "gn:admin1_code":"4",
    "gn:asciiname":"Chachanwali",
    "gn:country_code":"PK",
    "gn:dem":121,
    "gn:feature_class":"P",
    "gn:feature_code":"PPL",
    "gn:name":"Chachanwali",
    "gn:population":0,
    "gn:timezone":"Asia/Karachi",
    "iso:country":"PK",
    "name:eng_x_preferred":[
        "Ch\u0101wanwali"
    ],
    "wof:name":"Chachanwali",
    "wof:placetype":"locality"
},
  "geometry": {"coordinates":[71.80914,29.44392],"type":"Point"}
}