{
  "type": "Feature",
  "properties": {
    "gn:admin1_code":"4",
    "gn:asciiname":"Chak Three Hundred Eleven Western Bar",
    "gn:country_code":"PK",
    "gn:dem":124,
    "gn:feature_class":"P",
    "gn:feature_code":"PPL",
    "gn:name":"Chak Three Hundred Eleven Western Bar",
    "gn:population":0,
    "gn:timezone":"Asia/Karachi",
    "iso:country":"PK",
    "name:und_x_variant":[
        "Chak Three Hundred Eleven WB"
    ],
    "wof:name":"Chak Three Hundred Eleven Western Bar",
    "wof:placetype":"locality"
},
  "geometry": {"coordinates":[71.8215,29.85672000000001],"type":"Point"}
}