{
  "type": "Feature",
  "properties": {
    "gn:admin1_code":"5.0",
    "gn:asciiname":"Abdul Wahid Baran",
    "gn:country_code":"PK",
    "gn:dem":9,
    "gn:feature_class":"P",
    "gn:feature_code":"PPL",
    "gn:name":"Abdul Wahid Baran",
    "gn:population":0,
    "gn:timezone":"Asia/Karachi",
    "iso:country":"PK",
    "name:eng_x_preferred":[
        "Abdul Wahid Baran"
    ],
    "wof:name":"Abdul Wahid Baran",
    "wof:placetype":"locality"
},
  "geometry": {"coordinates":[68.19068,24.63882000000001],"type":"Point"}
}