{
  "type": "Feature",
  "properties": {
    "gn:admin1_code":"3.0",
    "gn:asciiname":"Chechian",
    "gn:country_code":"PK",
    "gn:dem":509,
    "gn:feature_class":"P",
    "gn:feature_code":"PPL",
    "gn:name":"Chechian",
    "gn:population":0,
    "gn:timezone":"Asia/Karachi",
    "iso:country":"PK",
    "wof:name":"Chechian",
    "wof:placetype":"locality"
},
  "geometry": {"coordinates":[72.90588000000002,33.93011],"type":"Point"}
}