{
  "type": "Feature",
  "properties": {
    "gn:admin1_code":"4",
    "gn:asciiname":"Chak Twenty-seven Thatta Sohail",
    "gn:country_code":"PK",
    "gn:dem":208,
    "gn:feature_class":"P",
    "gn:feature_code":"PPL",
    "gn:name":"Chak Twenty-seven Thatta Sohail",
    "gn:population":0,
    "gn:timezone":"Asia/Karachi",
    "iso:country":"PK",
    "name:und_x_variant":[
        "Chak Twenty-seven Thatta Sohla"
    ],
    "wof:name":"Chak Twenty-seven Thatta Sohail",
    "wof:placetype":"locality"
},
  "geometry": {"coordinates":[73.18963000000002,32.40116],"type":"Point"}
}