{
  "type": "Feature",
  "properties": {
    "gn:admin1_code":"3.0",
    "gn:asciiname":"Chabian",
    "gn:country_code":"PK",
    "gn:dem":310,
    "gn:feature_class":"P",
    "gn:feature_code":"PPL",
    "gn:name":"Chabian",
    "gn:population":0,
    "gn:timezone":"Asia/Karachi",
    "iso:country":"PK",
    "name:eng_x_preferred":[
        "Chhaba"
    ],
    "name:und_x_variant":[
        "Chaba",
        "Chabian",
        "Chabi\u0101n"
    ],
    "wof:name":"Chabian",
    "wof:placetype":"locality"
},
  "geometry": {"coordinates":[71.62801999999998,34.04054],"type":"Point"}
}