{
  "type": "Feature",
  "properties": {
    "gn:admin1_code":"4",
    "gn:asciiname":"Chak Two Hundred Eighty-two -Two Hundred Eighty-three",
    "gn:country_code":"PK",
    "gn:dem":127,
    "gn:feature_class":"P",
    "gn:feature_code":"PPL",
    "gn:name":"Chak Two Hundred Eighty-two -Two Hundred Eighty-three",
    "gn:population":0,
    "gn:timezone":"Asia/Karachi",
    "iso:country":"PK",
    "name:und_x_variant":[
        "Chak Two Hundred Eighty-one Two Hundred Eighty-three"
    ],
    "wof:name":"Chak Two Hundred Eighty-two -Two Hundred Eighty-three",
    "wof:placetype":"locality"
},
  "geometry": {"coordinates":[71.86738000000003,29.87321],"type":"Point"}
}