{
  "type": "Feature",
  "properties": {
    "gn:admin1_code":"4.0",
    "gn:asciiname":"Jhugian",
    "gn:country_code":"PK",
    "gn:dem":185,
    "gn:feature_class":"P",
    "gn:feature_code":"PPL",
    "gn:name":"Jhugian",
    "gn:population":0,
    "gn:timezone":"Asia/Karachi",
    "iso:country":"PK",
    "name:und_x_variant":[
        "Jhugi\u0101n Shai\u0101n"
    ],
    "wof:name":"Jhugian",
    "wof:placetype":"locality"
},
  "geometry": {"coordinates":[72.64919999999999,32.28369],"type":"Point"}
}