{
  "type": "Feature",
  "properties": {
    "gn:admin1_code":"4.0",
    "gn:asciiname":"Banda Qurashianwala",
    "gn:country_code":"PK",
    "gn:dem":243,
    "gn:feature_class":"P",
    "gn:feature_code":"PPL",
    "gn:name":"Banda Qurashianwala",
    "gn:population":0,
    "gn:timezone":"Asia/Karachi",
    "iso:country":"PK",
    "wof:name":"Banda Qurashianwala",
    "wof:placetype":"locality"
},
  "geometry": {"coordinates":[71.23199,32.81288],"type":"Point"}
}