{
  "type": "Feature",
  "properties": {
    "gn:admin1_code":"5.0",
    "gn:asciiname":"Warayo jo Goth",
    "gn:country_code":"PK",
    "gn:dem":82,
    "gn:feature_class":"P",
    "gn:feature_code":"PPL",
    "gn:name":"Warayo jo Goth",
    "gn:population":0,
    "gn:timezone":"Asia/Karachi",
    "iso:country":"PK",
    "wof:name":"Warayo jo Goth",
    "wof:placetype":"locality"
},
  "geometry": {"coordinates":[69.52454,27.49384],"type":"Point"}
}