{
  "type": "Feature",
  "properties": {
    "gn:admin1_code":"7.0",
    "gn:asciiname":"Hasanabad",
    "gn:country_code":"PK",
    "gn:dem":3042,
    "gn:feature_class":"P",
    "gn:feature_code":"PPL",
    "gn:name":"Hasanabad",
    "gn:population":0,
    "gn:timezone":"Asia/Karachi",
    "iso:country":"PK",
    "name:aze_x_preferred":[
        "H\u0259s\u0259nabad"
    ],
    "name:ceb_x_preferred":[
        "Hasanabad"
    ],
    "name:fas_x_preferred":[
        "\u062d\u0633\u0646\u200c\u0622\u0628\u0627\u062f"
    ],
    "name:ita_x_preferred":[
        "Hasanabad"
    ],
    "name:swe_x_preferred":[
        "Hasanabad"
    ],
    "wof:name":"Hasanabad",
    "wof:placetype":"locality"
},
  "geometry": {"coordinates":[75.84035,35.11985],"type":"Point"}
}