{
  "type": "Feature",
  "properties": {
    "gn:admin1_code":"3.0",
    "gn:asciiname":"Danch",
    "gn:country_code":"PK",
    "gn:dem":1317,
    "gn:feature_class":"P",
    "gn:feature_code":"PPL",
    "gn:name":"Danch",
    "gn:population":0,
    "gn:timezone":"Asia/Karachi",
    "iso:country":"PK",
    "wof:name":"Danch",
    "wof:placetype":"locality"
},
  "geometry": {"coordinates":[73.02580999999998,35.46548],"type":"Point"}
}