{
  "type": "Feature",
  "properties": {
    "gn:admin1_code":"1",
    "gn:asciiname":"Khadi",
    "gn:country_code":"PK",
    "gn:dem":1690,
    "gn:feature_class":"P",
    "gn:feature_code":"PPL",
    "gn:name":"Khadi",
    "gn:population":0,
    "gn:timezone":"Asia/Karachi",
    "iso:country":"PK",
    "name:cat_x_preferred":[
        "Khadi"
    ],
    "name:deu_x_preferred":[
        "Khadi"
    ],
    "name:fra_x_preferred":[
        "Kh\u0101d\u012b"
    ],
    "name:guj_x_preferred":[
        "\u0a96\u0abe\u0aa6\u0ac0"
    ],
    "name:hin_x_preferred":[
        "\u0916\u093e\u0926\u0940"
    ],
    "name:ita_x_preferred":[
        "Khadi"
    ],
    "name:kan_x_preferred":[
        "\u0c96\u0cbe\u0ca6\u0cbf"
    ],
    "name:mal_x_preferred":[
        "\u0d16\u0d3e\u0d26\u0d3f"
    ],
    "name:nld_x_preferred":[
        "Khadi"
    ],
    "name:nno_x_preferred":[
        "Khadi"
    ],
    "name:pan_x_preferred":[
        "\u0a16\u0a71\u0a26\u0a30"
    ],
    "name:pnb_x_preferred":[
        "\u06a9\u06be\u0688\u06cc"
    ],
    "name:por_x_preferred":[
        "Khadi"
    ],
    "name:swe_x_preferred":[
        "Khadi"
    ],
    "name:tam_x_preferred":[
        "\u0b95\u0bbe\u0ba4\u0bbf"
    ],
    "name:tel_x_preferred":[
        "\u0c16\u0c26\u0c4d\u0c26\u0c30\u0c41"
    ],
    "name:ukr_x_preferred":[
        "\u041a\u0445\u0430\u0434\u0456"
    ],
    "name:urd_x_preferred":[
        "\u06a9\u06be\u0627\u062f\u06cc"
    ],
    "wof:name":"Khadi",
    "wof:placetype":"locality"
},
  "geometry": {"coordinates":[69.85666999999999,32.50028],"type":"Point"}
}