{
  "type": "Feature",
  "properties": {
    "gn:admin1_code":"1",
    "gn:asciiname":"Khadi",
    "gn:country_code":"PK",
    "gn:dem":1690,
    "gn:feature_class":"P",
    "gn:feature_code":"PPL",
    "gn:name":"Khadi",
    "gn:population":0,
    "gn:timezone":"Asia/Karachi",
    "iso:country":"PK",
    "wof:name":"Khadi",
    "wof:placetype":"locality"
},
  "geometry": {"coordinates":[69.85666999999999,32.50028],"type":"Point"}
}