{
  "type": "Feature",
  "properties": {
    "gn:admin1_code":"4",
    "gn:asciiname":"Wasu",
    "gn:country_code":"PK",
    "gn:dem":154,
    "gn:feature_class":"P",
    "gn:feature_code":"PPL",
    "gn:name":"Wasu",
    "gn:population":0,
    "gn:timezone":"Asia/Karachi",
    "iso:country":"PK",
    "name:und_x_variant":[
        "W\u0101su \u0100st\u0101na"
    ],
    "wof:name":"Wasu",
    "wof:placetype":"locality"
},
  "geometry": {"coordinates":[72.07723,31.18548],"type":"Point"}
}