{
  "type": "Feature",
  "properties": {
    "gn:admin1_code":"4.0",
    "gn:asciiname":"Chak Four Hundred Two Gugera Branch",
    "gn:country_code":"PK",
    "gn:dem":175,
    "gn:feature_class":"P",
    "gn:feature_code":"PPL",
    "gn:name":"Chak Four Hundred Two Gugera Branch",
    "gn:population":0,
    "gn:timezone":"Asia/Karachi",
    "iso:country":"PK",
    "name:und_x_variant":[
        "Giloipind",
        "Galoi Pind",
        "Chak Four Hundred Two Gugera Branch",
        "Gloiy\u0101nw\u0101la"
    ],
    "wof:name":"Chak Four Hundred Two Gugera Branch",
    "wof:placetype":"locality"
},
  "geometry": {"coordinates":[73.08234,30.95127],"type":"Point"}
}