{
  "type": "Feature",
  "properties": {
    "gn:admin1_code":"5.0",
    "gn:asciiname":"Karamullah Dahri",
    "gn:country_code":"PK",
    "gn:dem":28,
    "gn:feature_class":"P",
    "gn:feature_code":"PPL",
    "gn:name":"Karamullah Dahri",
    "gn:population":0,
    "gn:timezone":"Asia/Karachi",
    "iso:country":"PK",
    "name:und_x_variant":[
        "Karamallah Dahri",
        "Karamullah Dahri"
    ],
    "wof:name":"Karamullah Dahri",
    "wof:placetype":"locality"
},
  "geometry": {"coordinates":[68.64541,26.07824],"type":"Point"}
}