{
  "type": "Feature",
  "properties": {
    "gn:admin1_code":"4.0",
    "gn:asciiname":"Chak Dudhu",
    "gn:country_code":"PK",
    "gn:dem":264,
    "gn:feature_class":"P",
    "gn:feature_code":"PPL",
    "gn:name":"Chak Dudhu",
    "gn:population":0,
    "gn:timezone":"Asia/Karachi",
    "iso:country":"PK",
    "name:und_x_variant":[
        "Chak Dhudu",
        "Chak Dudhu"
    ],
    "wof:name":"Chak Dudhu",
    "wof:placetype":"locality"
},
  "geometry": {"coordinates":[75.02627,32.26812],"type":"Point"}
}