{
  "type": "Feature",
  "properties": {
    "gn:admin1_code":"4",
    "gn:asciiname":"Basti Mumbewala",
    "gn:country_code":"PK",
    "gn:dem":105,
    "gn:feature_class":"P",
    "gn:feature_code":"PPL",
    "gn:name":"Basti Mumbewala",
    "gn:population":0,
    "gn:timezone":"Asia/Karachi",
    "iso:country":"PK",
    "name:und_x_variant":[
        "Mumbew\u0101la",
        "Mamba\u012bw\u0101la",
        "Basti Mumbewala"
    ],
    "wof:name":"Basti Mumbewala",
    "wof:placetype":"locality"
},
  "geometry": {"coordinates":[71.14284000000001,29.32327],"type":"Point"}
}