{
  "type": "Feature",
  "properties": {
    "gn:admin1_code":"4",
    "gn:asciiname":"Chak Fifty-seven South Branch",
    "gn:country_code":"PK",
    "gn:dem":186,
    "gn:feature_class":"P",
    "gn:feature_code":"PPL",
    "gn:name":"Chak Fifty-seven South Branch",
    "gn:population":0,
    "gn:timezone":"Asia/Karachi",
    "iso:country":"PK",
    "name:und_x_variant":[
        "Chak Fifty-seven SB"
    ],
    "wof:name":"Chak Fifty-seven South Branch",
    "wof:placetype":"locality"
},
  "geometry": {"coordinates":[72.80044000000002,31.86212],"type":"Point"}
}