{
  "type": "Feature",
  "properties": {
    "gn:admin1_code":"5.0",
    "gn:asciiname":"Goth Qaisar",
    "gn:country_code":"PK",
    "gn:dem":45,
    "gn:feature_class":"P",
    "gn:feature_code":"PPL",
    "gn:name":"Goth Qaisar",
    "gn:population":0,
    "gn:timezone":"Asia/Karachi",
    "iso:country":"PK",
    "name:und_x_variant":[
        "Goth Qaiser Kh\u0101n Ch\u0101ndio"
    ],
    "wof:name":"Goth Qaisar",
    "wof:placetype":"locality"
},
  "geometry": {"coordinates":[67.70871,27.43997],"type":"Point"}
}