{
  "type": "Feature",
  "properties": {
    "gn:admin1_code":"5.0",
    "gn:asciiname":"Said Khan Panhowar",
    "gn:country_code":"PK",
    "gn:dem":48,
    "gn:feature_class":"P",
    "gn:feature_code":"PPL",
    "gn:name":"Said Khan Panhowar",
    "gn:population":0,
    "gn:timezone":"Asia/Karachi",
    "iso:country":"PK",
    "wof:name":"Said Khan Panhowar",
    "wof:placetype":"locality"
},
  "geometry": {"coordinates":[67.89879000000001,27.3956],"type":"Point"}
}