{
  "type": "Feature",
  "properties": {
    "gn:admin1_code":"03",
    "gn:asciiname":"Utala",
    "gn:country_code":"PK",
    "gn:dem":905,
    "gn:feature_class":"P",
    "gn:feature_code":"PPL",
    "gn:name":"Utala",
    "gn:population":0,
    "gn:timezone":"Asia/Karachi",
    "iso:country":"PK",
    "wof:name":"Utala",
    "wof:placetype":"locality"
},
  "geometry": {"coordinates":[71.78355999999999,34.7166],"type":"Point"}
}