{
  "type": "Feature",
  "properties": {
    "gn:admin1_code":"1.0",
    "gn:asciiname":"Sanda Kot",
    "gn:country_code":"PK",
    "gn:dem":1242,
    "gn:feature_class":"P",
    "gn:feature_code":"PPL",
    "gn:name":"Sanda Kot",
    "gn:population":0,
    "gn:timezone":"Asia/Karachi",
    "iso:country":"PK",
    "wof:name":"Sanda Kot",
    "wof:placetype":"locality"
},
  "geometry": {"coordinates":[70.2812,33.7473],"type":"Point"}
}