{
  "type": "Feature",
  "properties": {
    "gn:admin1_code":"2.0",
    "gn:asciiname":"Yateabad",
    "gn:country_code":"PK",
    "gn:dem":942,
    "gn:feature_class":"P",
    "gn:feature_code":"PPL",
    "gn:name":"Yateabad",
    "gn:population":0,
    "gn:timezone":"Asia/Karachi",
    "iso:country":"PK",
    "wof:name":"Yateabad",
    "wof:placetype":"locality"
},
  "geometry": {"coordinates":[68.83553000000001,30.07778],"type":"Point"}
}