{
  "type": "Feature",
  "properties": {
    "gn:admin1_code":"4",
    "gn:asciiname":"Chak Sixty-eight- Ten Right",
    "gn:country_code":"PK",
    "gn:dem":138,
    "gn:feature_class":"P",
    "gn:feature_code":"PPL",
    "gn:name":"Chak Sixty-eight- Ten Right",
    "gn:population":0,
    "gn:timezone":"Asia/Karachi",
    "iso:country":"PK",
    "name:und_x_variant":[
        "Chak Sixty-Eight",
        "Mathr\u0101pur",
        "Mariw\u0101la",
        "Chak Sixty-eight- Ten Right"
    ],
    "wof:name":"Chak Sixty-eight- Ten Right",
    "wof:placetype":"locality"
},
  "geometry": {"coordinates":[72.02134000000002,30.25177],"type":"Point"}
}