{
  "type": "Feature",
  "properties": {
    "gn:admin1_code":"4.0",
    "gn:asciiname":"Chah Saiyidan",
    "gn:country_code":"PK",
    "gn:dem":209,
    "gn:feature_class":"P",
    "gn:feature_code":"PPL",
    "gn:name":"Chah Saiyidan",
    "gn:population":0,
    "gn:timezone":"Asia/Karachi",
    "iso:country":"PK",
    "name:und_x_variant":[
        "Halt"
    ],
    "wof:name":"Chah Saiyidan",
    "wof:placetype":"locality"
},
  "geometry": {"coordinates":[74.41535,31.7782],"type":"Point"}
}