{
  "type": "Feature",
  "properties": {
    "gn:admin1_code":"6.0",
    "gn:asciiname":"Dalyal",
    "gn:country_code":"PK",
    "gn:dem":255,
    "gn:feature_class":"P",
    "gn:feature_code":"PPL",
    "gn:name":"Dalyal",
    "gn:population":0,
    "gn:timezone":"Asia/Karachi",
    "iso:country":"PK",
    "name:und_x_variant":[
        "Duli\u0101l"
    ],
    "wof:name":"Dalyal",
    "wof:placetype":"locality"
},
  "geometry": {"coordinates":[73.65965,33.07346],"type":"Point"}
}