{
  "type": "Feature",
  "properties": {
    "gn:admin1_code":"3.0",
    "gn:asciiname":"Khida Banda",
    "gn:country_code":"PK",
    "gn:dem":532,
    "gn:feature_class":"P",
    "gn:feature_code":"PPL",
    "gn:name":"Khida Banda",
    "gn:population":0,
    "gn:timezone":"Asia/Karachi",
    "iso:country":"PK",
    "wof:name":"Khida Banda",
    "wof:placetype":"locality"
},
  "geometry": {"coordinates":[71.06585,33.0107],"type":"Point"}
}