{
  "type": "Feature",
  "properties": {
    "gn:admin1_code":"2.0",
    "gn:asciiname":"Sabil",
    "gn:country_code":"PK",
    "gn:dem":1340,
    "gn:feature_class":"P",
    "gn:feature_code":"PPL",
    "gn:name":"Sabil",
    "gn:population":0,
    "gn:timezone":"Asia/Karachi",
    "iso:country":"PK",
    "wof:name":"Sabil",
    "wof:placetype":"locality"
},
  "geometry": {"coordinates":[65.42622,27.4033],"type":"Point"}
}