{
  "type": "Feature",
  "properties": {
    "gn:admin1_code":"2.0",
    "gn:asciiname":"Nadil Bazar",
    "gn:country_code":"PK",
    "gn:dem":852,
    "gn:feature_class":"P",
    "gn:feature_code":"PPL",
    "gn:name":"Nadil Bazar",
    "gn:population":0,
    "gn:timezone":"Asia/Karachi",
    "iso:country":"PK",
    "wof:name":"Nadil Bazar",
    "wof:placetype":"locality"
},
  "geometry": {"coordinates":[63.51866999999999,26.88997],"type":"Point"}
}