{
  "type": "Feature",
  "properties": {
    "gn:admin1_code":"3.0",
    "gn:asciiname":"Dharangi Banda",
    "gn:country_code":"PK",
    "gn:dem":584,
    "gn:feature_class":"P",
    "gn:feature_code":"PPL",
    "gn:name":"Dharangi Banda",
    "gn:population":0,
    "gn:timezone":"Asia/Karachi",
    "iso:country":"PK",
    "name:und_x_variant":[
        "Dharangi"
    ],
    "wof:name":"Dharangi Banda",
    "wof:placetype":"locality"
},
  "geometry": {"coordinates":[71.22143,33.27294000000001],"type":"Point"}
}