{
  "type": "Feature",
  "properties": {
    "gn:admin1_code":"2",
    "gn:asciiname":"Kakozai Kulak",
    "gn:country_code":"PK",
    "gn:dem":1478,
    "gn:feature_class":"P",
    "gn:feature_code":"PPL",
    "gn:name":"Kakozai Kulak",
    "gn:population":0,
    "gn:timezone":"Asia/Karachi",
    "iso:country":"PK",
    "name:und_x_variant":[
        "Takai Kakozai"
    ],
    "wof:name":"Kakozai Kulak",
    "wof:placetype":"locality"
},
  "geometry": {"coordinates":[66.80249999999999,30.72056],"type":"Point"}
}