{
  "type": "Feature",
  "properties": {
    "gn:admin1_code":"3.0",
    "gn:asciiname":"Doru",
    "gn:country_code":"PK",
    "gn:dem":3365,
    "gn:feature_class":"P",
    "gn:feature_code":"PPL",
    "gn:name":"Doru",
    "gn:population":0,
    "gn:timezone":"Asia/Karachi",
    "iso:country":"PK",
    "name:und_x_variant":[
        "Dur",
        "Druh",
        "Doru"
    ],
    "wof:name":"Doru",
    "wof:placetype":"locality"
},
  "geometry": {"coordinates":[72.10831,36.47023],"type":"Point"}
}