{
  "type": "Feature",
  "properties": {
    "gn:admin1_code":"04",
    "gn:asciiname":"Mangat",
    "gn:country_code":"PK",
    "gn:dem":218,
    "gn:feature_class":"P",
    "gn:feature_code":"PPL",
    "gn:name":"Mangat",
    "gn:population":0,
    "gn:timezone":"Asia/Karachi",
    "iso:country":"PK",
    "name:por_x_preferred":[
        "Mangat"
    ],
    "wof:name":"Mangat",
    "wof:placetype":"locality"
},
  "geometry": {"coordinates":[73.50324000000001,32.51578],"type":"Point"}
}