{
  "type": "Feature",
  "properties": {
    "gn:admin1_code":"3.0",
    "gn:asciiname":"Takar",
    "gn:country_code":"PK",
    "gn:dem":2032,
    "gn:feature_class":"P",
    "gn:feature_code":"PPL",
    "gn:name":"Takar",
    "gn:population":0,
    "gn:timezone":"Asia/Karachi",
    "iso:country":"PK",
    "name:ceb_x_preferred":[
        "T\u0101kar"
    ],
    "name:fas_x_preferred":[
        "\u062a\u0627\u06a9\u0631"
    ],
    "name:swe_x_preferred":[
        "T\u0101kar"
    ],
    "wof:name":"Takar",
    "wof:placetype":"locality"
},
  "geometry": {"coordinates":[73.25698,34.6308],"type":"Point"}
}