{
  "type": "Feature",
  "properties": {
    "gn:admin1_code":"2.0",
    "gn:asciiname":"Sirkzai Bazar",
    "gn:country_code":"PK",
    "gn:dem":818,
    "gn:feature_class":"P",
    "gn:feature_code":"PPL",
    "gn:name":"Sirkzai Bazar",
    "gn:population":0,
    "gn:timezone":"Asia/Karachi",
    "iso:country":"PK",
    "wof:name":"Sirkzai Bazar",
    "wof:placetype":"locality"
},
  "geometry": {"coordinates":[62.81223000000001,26.59635],"type":"Point"}
}