{
  "type": "Feature",
  "properties": {
    "gn:admin1_code":"04",
    "gn:asciiname":"Pakka",
    "gn:country_code":"PK",
    "gn:dem":190,
    "gn:feature_class":"P",
    "gn:feature_code":"PPL",
    "gn:name":"Pakka",
    "gn:population":0,
    "gn:timezone":"Asia/Karachi",
    "iso:country":"PK",
    "name:fin_x_preferred":[
        "Pakka"
    ],
    "wof:name":"Pakka",
    "wof:placetype":"locality"
},
  "geometry": {"coordinates":[72.94609,31.92818],"type":"Point"}
}