{
  "type": "Feature",
  "properties": {
    "gn:admin1_code":"4.0",
    "gn:asciiname":"Mullanawala",
    "gn:country_code":"PK",
    "gn:dem":102,
    "gn:feature_class":"P",
    "gn:feature_code":"PPL",
    "gn:name":"Mullanawala",
    "gn:population":0,
    "gn:timezone":"Asia/Karachi",
    "iso:country":"PK",
    "name:und_x_variant":[
        "Mull\u0101niw\u0101la"
    ],
    "wof:name":"Mullanawala",
    "wof:placetype":"locality"
},
  "geometry": {"coordinates":[70.58685,29.49784],"type":"Point"}
}