{
  "type": "Feature",
  "properties": {
    "gn:admin1_code":"5",
    "gn:asciiname":"Goth Gulam Bhambro",
    "gn:country_code":"PK",
    "gn:dem":22,
    "gn:feature_class":"P",
    "gn:feature_code":"PPL",
    "gn:name":"Goth Gulam Bhambro",
    "gn:population":0,
    "gn:timezone":"Asia/Karachi",
    "iso:country":"PK",
    "name:und_x_variant":[
        "Gagan Bhambro"
    ],
    "wof:name":"Goth Gulam Bhambro",
    "wof:placetype":"locality"
},
  "geometry": {"coordinates":[69.01244,25.96502000000001],"type":"Point"}
}