{
  "type": "Feature",
  "properties": {
    "gn:admin1_code":"2",
    "gn:asciiname":"Dangwal",
    "gn:country_code":"PK",
    "gn:dem":1188,
    "gn:feature_class":"P",
    "gn:feature_code":"PPL",
    "gn:name":"Dangwal",
    "gn:population":0,
    "gn:timezone":"Asia/Karachi",
    "iso:country":"PK",
    "wof:name":"Dangwal",
    "wof:placetype":"locality"
},
  "geometry": {"coordinates":[68.98071999999999,30.38131],"type":"Point"}
}