{
  "type": "Feature",
  "properties": {
    "iso:country":"PK",
    "name:eng_x_preferred":[
        "Utm\u0101nzai"
    ],
    "name:unk_x_variant":[
        "Uttmanzai"
    ],
    "qs:gn_country":"PK",
    "qs:gn_fcode":"PPL",
    "qs:gn_pop":29423,
    "qs:name":"Uttamanza",
    "qs:name_adm0":"Pakistan",
    "qs:name_adm1":"North-West Frontier",
    "qs:photos":0,
    "qs:photos_1k":0,
    "qs:photos_9k":0,
    "qs:photos_9r":0,
    "qs:photos_all":0,
    "qs:photos_sr":0,
    "qs:placetype":"Town",
    "qs:pop_sr":"7",
    "qs:woe_adm0":23424922,
    "wof:name":"Uttamanza",
    "wof:placetype":"locality",
    "wof:population":29423
},
  "geometry": {"coordinates":[71.76286,34.18799],"type":"Point"}
}