{
  "type": "Feature",
  "properties": {
    "iso:country":"PK",
    "name:cat_x_preferred":[
        "Hashtnagar"
    ],
    "name:eng_x_preferred":[
        "Utm\u0101nzai"
    ],
    "name:eng_x_variant":[
        "Hashtnagar"
    ],
    "name:fra_x_preferred":[
        "Hashtnagar"
    ],
    "name:nno_x_preferred":[
        "Hashtnagar"
    ],
    "name:nob_x_preferred":[
        "Hashtnagar"
    ],
    "name:pan_x_preferred":[
        "\u0a39\u0a38\u0a3c\u0a24\u0a28\u0a17\u0a30"
    ],
    "name:por_x_preferred":[
        "Utmanzai"
    ],
    "name:tgk_x_preferred":[
        "\u04b2\u0430\u0448\u0442\u043d\u0430\u0433\u0430\u0440"
    ],
    "name:und_x_variant":[
        "Uttmanzai"
    ],
    "qs:gn_country":"PK",
    "qs:gn_fcode":"PPL",
    "qs:gn_pop":29423,
    "qs:name":"Uttamanza",
    "qs:name_adm0":"Pakistan",
    "qs:name_adm1":"North-West Frontier",
    "qs:photos":0,
    "qs:photos_1k":0,
    "qs:photos_9k":0,
    "qs:photos_9r":0,
    "qs:photos_all":0,
    "qs:photos_sr":0,
    "qs:placetype":"Town",
    "qs:pop_sr":"7",
    "qs:woe_adm0":23424922,
    "wof:name":"Uttamanza",
    "wof:placetype":"locality",
    "wof:population":29423
},
  "geometry": {"coordinates":[71.76286,34.18799],"type":"Point"}
}