{
  "type": "Feature",
  "properties": {
    "gn:admin1_code":"4.0",
    "gn:asciiname":"Kachhilawala",
    "gn:country_code":"PK",
    "gn:dem":170,
    "gn:feature_class":"P",
    "gn:feature_code":"PPL",
    "gn:name":"Kachhilawala",
    "gn:population":0,
    "gn:timezone":"Asia/Karachi",
    "iso:country":"PK",
    "name:und_x_variant":[
        "Kachh\u012blw\u0101la"
    ],
    "wof:name":"Kachhilawala",
    "wof:placetype":"locality"
},
  "geometry": {"coordinates":[71.89652,31.48401],"type":"Point"}
}