{
  "type": "Feature",
  "properties": {
    "gn:admin1_code":"3",
    "gn:asciiname":"Andora",
    "gn:country_code":"PK",
    "gn:dem":2042,
    "gn:feature_class":"P",
    "gn:feature_code":"PPL",
    "gn:name":"Andora",
    "gn:population":0,
    "gn:timezone":"Asia/Karachi",
    "iso:country":"PK",
    "name:und_x_variant":[
        "Andera"
    ],
    "wof:name":"Andora",
    "wof:placetype":"locality"
},
  "geometry": {"coordinates":[72.61369000000001,34.7459],"type":"Point"}
}