{
  "type": "Feature",
  "properties": {
    "gn:admin1_code":"3",
    "gn:asciiname":"Andora",
    "gn:country_code":"PK",
    "gn:dem":2042,
    "gn:feature_class":"P",
    "gn:feature_code":"PPL",
    "gn:name":"Andora",
    "gn:population":0,
    "gn:timezone":"Asia/Karachi",
    "iso:country":"PK",
    "name:azb_x_preferred":[
        "\u0622\u0646\u062f\u0648\u0631\u0627"
    ],
    "name:bul_x_preferred":[
        "\u0410\u043d\u0434\u043e\u0440\u0430"
    ],
    "name:cat_x_preferred":[
        "Andora"
    ],
    "name:ceb_x_preferred":[
        "Andora"
    ],
    "name:ces_x_preferred":[
        "Andora"
    ],
    "name:deu_x_preferred":[
        "Andora"
    ],
    "name:epo_x_preferred":[
        "Andora"
    ],
    "name:eus_x_preferred":[
        "Andora"
    ],
    "name:fas_x_preferred":[
        "\u0622\u0646\u062f\u0648\u0631\u0627"
    ],
    "name:fra_x_preferred":[
        "Andora"
    ],
    "name:hin_x_preferred":[
        "\u0905\u0928\u094d\u0921\u094b\u0930\u094d\u0930\u093e"
    ],
    "name:hun_x_preferred":[
        "Andora"
    ],
    "name:hye_x_preferred":[
        "\u0531\u0576\u0564\u0578\u0580\u0561"
    ],
    "name:ina_x_preferred":[
        "Andora"
    ],
    "name:ind_x_preferred":[
        "Andora"
    ],
    "name:ita_x_preferred":[
        "Andora"
    ],
    "name:jpn_x_preferred":[
        "\u30a2\u30f3\u30c9\u30fc\u30e9"
    ],
    "name:kor_x_preferred":[
        "\uc548\ub3c4\ub77c"
    ],
    "name:lat_x_preferred":[
        "Andora"
    ],
    "name:lij_x_preferred":[
        "Andeua"
    ],
    "name:lmo_x_preferred":[
        "Andora"
    ],
    "name:msa_x_preferred":[
        "Andora"
    ],
    "name:nap_x_preferred":[
        "Andora"
    ],
    "name:nld_x_preferred":[
        "Andora"
    ],
    "name:pms_x_preferred":[
        "Andora"
    ],
    "name:pol_x_preferred":[
        "Andora"
    ],
    "name:por_x_preferred":[
        "Andora"
    ],
    "name:ron_x_preferred":[
        "Andora"
    ],
    "name:rus_x_preferred":[
        "\u0410\u043d\u0434\u043e\u0440\u0430"
    ],
    "name:scn_x_preferred":[
        "Andora"
    ],
    "name:spa_x_preferred":[
        "Andora"
    ],
    "name:srp_x_preferred":[
        "\u0410\u043d\u0434\u043e\u0440\u0430"
    ],
    "name:swe_x_preferred":[
        "Andora"
    ],
    "name:ukr_x_preferred":[
        "\u0410\u043d\u0434\u043e\u0440\u0430"
    ],
    "name:und_x_variant":[
        "Andera"
    ],
    "name:vie_x_preferred":[
        "Andora"
    ],
    "name:vol_x_preferred":[
        "Andora"
    ],
    "name:war_x_preferred":[
        "Andora"
    ],
    "name:zho_x_preferred":[
        "\u5b89\u591a\u62c9"
    ],
    "wof:name":"Andora",
    "wof:placetype":"locality"
},
  "geometry": {"coordinates":[72.61369000000001,34.7459],"type":"Point"}
}