{
  "type": "Feature",
  "properties": {
    "gn:admin1_code":"4.0",
    "gn:asciiname":"Barwala",
    "gn:country_code":"PK",
    "gn:dem":311,
    "gn:feature_class":"P",
    "gn:feature_code":"PPL",
    "gn:name":"Barwala",
    "gn:population":0,
    "gn:timezone":"Asia/Karachi",
    "iso:country":"PK",
    "name:und_x_variant":[
        "Bar",
        "Barwala"
    ],
    "wof:name":"Barwala",
    "wof:placetype":"locality"
},
  "geometry": {"coordinates":[71.95631999999998,33.13083],"type":"Point"}
}