{
  "type": "Feature",
  "properties": {
    "gn:admin1_code":"3.0",
    "gn:asciiname":"Shaikh Manhab Kalle",
    "gn:country_code":"PK",
    "gn:dem":335,
    "gn:feature_class":"P",
    "gn:feature_code":"PPL",
    "gn:name":"Shaikh Manhab Kalle",
    "gn:population":0,
    "gn:timezone":"Asia/Karachi",
    "iso:country":"PK",
    "name:eng_x_preferred":[
        "Khl\u0101dhand"
    ],
    "wof:name":"Shaikh Manhab Kalle",
    "wof:placetype":"locality"
},
  "geometry": {"coordinates":[71.76076,34.25489],"type":"Point"}
}