{
  "type": "Feature",
  "properties": {
    "gn:admin1_code":"4.0",
    "gn:asciiname":"Chak Sixty-two - Four Right",
    "gn:country_code":"PK",
    "gn:dem":176,
    "gn:feature_class":"P",
    "gn:feature_code":"PPL",
    "gn:name":"Chak Sixty-two - Four Right",
    "gn:population":0,
    "gn:timezone":"Asia/Karachi",
    "iso:country":"PK",
    "name:und_x_variant":[
        "Am\u012brgarh",
        "Amirgarh"
    ],
    "wof:name":"Chak Sixty-two - Four Right",
    "wof:placetype":"locality"
},
  "geometry": {"coordinates":[73.26097,30.73227],"type":"Point"}
}