{
  "type": "Feature",
  "properties": {
    "gn:admin1_code":"7.0",
    "gn:asciiname":"Rellum",
    "gn:country_code":"PK",
    "gn:dem":3024,
    "gn:feature_class":"P",
    "gn:feature_code":"PPL",
    "gn:name":"Rellum",
    "gn:population":0,
    "gn:timezone":"Asia/Karachi",
    "iso:country":"PK",
    "wof:name":"Rellum",
    "wof:placetype":"locality"
},
  "geometry": {"coordinates":[76.3652,35.3965],"type":"Point"}
}