{
  "type": "Feature",
  "properties": {
    "gn:admin1_code":"5.0",
    "gn:asciiname":"Haji Somar Memon",
    "gn:country_code":"PK",
    "gn:dem":28,
    "gn:feature_class":"P",
    "gn:feature_code":"PPL",
    "gn:name":"Haji Somar Memon",
    "gn:population":0,
    "gn:timezone":"Asia/Karachi",
    "iso:country":"PK",
    "name:und_x_variant":[
        "H\u0101ji Sumar Memon"
    ],
    "wof:name":"Haji Somar Memon",
    "wof:placetype":"locality"
},
  "geometry": {"coordinates":[68.50753,26.27774],"type":"Point"}
}