{
  "type": "Feature",
  "properties": {
    "gn:admin1_code":"1.0",
    "gn:asciiname":"Jaroba",
    "gn:country_code":"PK",
    "gn:dem":681,
    "gn:feature_class":"P",
    "gn:feature_code":"PPL",
    "gn:name":"Jaroba",
    "gn:population":0,
    "gn:timezone":"Asia/Karachi",
    "iso:country":"PK",
    "wof:name":"Jaroba",
    "wof:placetype":"locality"
},
  "geometry": {"coordinates":[70.02179,31.84491],"type":"Point"}
}