{
  "type": "Feature",
  "properties": {
    "gn:admin1_code":"4.0",
    "gn:asciiname":"Mata Virkan",
    "gn:country_code":"PK",
    "gn:dem":217,
    "gn:feature_class":"P",
    "gn:feature_code":"PPL",
    "gn:name":"Mata Virkan",
    "gn:population":0,
    "gn:timezone":"Asia/Karachi",
    "iso:country":"PK",
    "name:und_x_variant":[
        "Mata"
    ],
    "wof:name":"Mata Virkan",
    "wof:placetype":"locality"
},
  "geometry": {"coordinates":[73.97478000000002,31.94268],"type":"Point"}
}