{
  "type": "Feature",
  "properties": {
    "gn:admin1_code":"3",
    "gn:asciiname":"Kotha Mahbub Khan",
    "gn:country_code":"PK",
    "gn:dem":174,
    "gn:feature_class":"P",
    "gn:feature_code":"PPL",
    "gn:name":"Kotha Mahbub Khan",
    "gn:population":0,
    "gn:timezone":"Asia/Karachi",
    "iso:country":"PK",
    "wof:name":"Kotha Mahbub Khan",
    "wof:placetype":"locality"
},
  "geometry": {"coordinates":[70.83781,31.69427],"type":"Point"}
}