{
  "type": "Feature",
  "properties": {
    "gn:admin1_code":"3.0",
    "gn:asciiname":"Kuma",
    "gn:country_code":"PK",
    "gn:dem":2930,
    "gn:feature_class":"P",
    "gn:feature_code":"PPL",
    "gn:name":"Kuma",
    "gn:population":0,
    "gn:timezone":"Asia/Karachi",
    "iso:country":"PK",
    "wof:name":"Kuma",
    "wof:placetype":"locality"
},
  "geometry": {"coordinates":[73.26313,35.35962],"type":"Point"}
}