{
  "type": "Feature",
  "properties": {
    "gn:admin1_code":"3.0",
    "gn:asciiname":"Kuma",
    "gn:country_code":"PK",
    "gn:dem":2930,
    "gn:feature_class":"P",
    "gn:feature_code":"PPL",
    "gn:name":"Kuma",
    "gn:population":0,
    "gn:timezone":"Asia/Karachi",
    "iso:country":"PK",
    "name:bel_x_preferred":[
        "\u041a\u0443\u043c\u0430"
    ],
    "name:bul_x_preferred":[
        "\u041a\u0443\u043c\u0430"
    ],
    "name:ceb_x_preferred":[
        "Kuma"
    ],
    "name:ces_x_preferred":[
        "Kuma"
    ],
    "name:deu_x_preferred":[
        "Kuma"
    ],
    "name:est_x_preferred":[
        "Kuma"
    ],
    "name:fin_x_preferred":[
        "Kuma"
    ],
    "name:fra_x_preferred":[
        "Kuma"
    ],
    "name:hye_x_preferred":[
        "\u053f\u0578\u0582\u0574\u0561"
    ],
    "name:ita_x_preferred":[
        "Kuma"
    ],
    "name:nld_x_preferred":[
        "Kuma"
    ],
    "name:por_x_preferred":[
        "Kuma"
    ],
    "name:rus_x_preferred":[
        "\u041a\u0443\u043c\u0430"
    ],
    "name:slk_x_preferred":[
        "Kuma"
    ],
    "name:spa_x_preferred":[
        "Kuma"
    ],
    "name:swe_x_preferred":[
        "Kuma"
    ],
    "name:ukr_x_preferred":[
        "\u041a\u0443\u043c\u0430"
    ],
    "name:zho_x_preferred":[
        "\u718a"
    ],
    "wof:name":"Kuma",
    "wof:placetype":"locality"
},
  "geometry": {"coordinates":[73.26313,35.35962],"type":"Point"}
}