{
  "type": "Feature",
  "properties": {
    "gn:admin1_code":"3",
    "gn:asciiname":"Tangal Banda",
    "gn:country_code":"PK",
    "gn:dem":1438,
    "gn:feature_class":"P",
    "gn:feature_code":"PPL",
    "gn:name":"Tangal Banda",
    "gn:population":0,
    "gn:timezone":"Asia/Karachi",
    "iso:country":"PK",
    "name:und_x_variant":[
        "S\u012bm\u0101r Tangai B\u0101nda",
        "Tangal Banda"
    ],
    "wof:name":"Tangal Banda",
    "wof:placetype":"locality"
},
  "geometry": {"coordinates":[72.60535,34.65858],"type":"Point"}
}