{
  "type": "Feature",
  "properties": {
    "gn:admin1_code":"4.0",
    "gn:asciiname":"Bhugal Dial",
    "gn:country_code":"PK",
    "gn:dem":223,
    "gn:feature_class":"P",
    "gn:feature_code":"PPL",
    "gn:name":"Bhugal Dial",
    "gn:population":0,
    "gn:timezone":"Asia/Karachi",
    "iso:country":"PK",
    "name:und_x_variant":[
        "Bhago Day\u0101l"
    ],
    "wof:name":"Bhugal Dial",
    "wof:placetype":"locality"
},
  "geometry": {"coordinates":[74.50187,31.96718],"type":"Point"}
}