{
  "type": "Feature",
  "properties": {
    "gn:admin1_code":"7.0",
    "gn:asciiname":"Katzarah",
    "gn:country_code":"PK",
    "gn:dem":2391,
    "gn:feature_class":"P",
    "gn:feature_code":"PPL",
    "gn:name":"Katzarah",
    "gn:population":0,
    "gn:timezone":"Asia/Karachi",
    "iso:country":"PK",
    "wof:name":"Katzarah",
    "wof:placetype":"locality"
},
  "geometry": {"coordinates":[75.44244999999999,35.43656],"type":"Point"}
}