{
  "type": "Feature",
  "properties": {
    "gn:admin1_code":"04",
    "gn:asciiname":"Dheri Maira",
    "gn:country_code":"PK",
    "gn:dem":600,
    "gn:feature_class":"P",
    "gn:feature_code":"PPL",
    "gn:name":"Dheri Maira",
    "gn:population":0,
    "gn:timezone":"Asia/Karachi",
    "iso:country":"PK",
    "name:und_x_variant":[
        "Dheri"
    ],
    "wof:name":"Dheri Maira",
    "wof:placetype":"locality"
},
  "geometry": {"coordinates":[73.32467,33.45333],"type":"Point"}
}