{
  "type": "Feature",
  "properties": {
    "gn:admin1_code":"4.0",
    "gn:asciiname":"Chak Six Hundred Twenty-three",
    "gn:country_code":"PK",
    "gn:dem":172,
    "gn:feature_class":"P",
    "gn:feature_code":"PPL",
    "gn:name":"Chak Six Hundred Twenty-three",
    "gn:population":0,
    "gn:timezone":"Asia/Karachi",
    "iso:country":"PK",
    "name:und_x_variant":[
        "Azmatka"
    ],
    "wof:name":"Chak Six Hundred Twenty-three",
    "wof:placetype":"locality"
},
  "geometry": {"coordinates":[73.01552,30.82877],"type":"Point"}
}