{
  "type": "Feature",
  "properties": {
    "gn:admin1_code":"4.0",
    "gn:asciiname":"Jhok Utran",
    "gn:country_code":"PK",
    "gn:dem":114,
    "gn:feature_class":"P",
    "gn:feature_code":"PPL",
    "gn:name":"Jhok Utran",
    "gn:population":0,
    "gn:timezone":"Asia/Karachi",
    "iso:country":"PK",
    "name:und_x_variant":[
        "Jhok Utera"
    ],
    "wof:name":"Jhok Utran",
    "wof:placetype":"locality"
},
  "geometry": {"coordinates":[71.48826,29.41598],"type":"Point"}
}