{
  "type": "Feature",
  "properties": {
    "gn:admin1_code":"4",
    "gn:asciiname":"Sangerawala",
    "gn:country_code":"PK",
    "gn:dem":169,
    "gn:feature_class":"P",
    "gn:feature_code":"PPL",
    "gn:name":"Sangerawala",
    "gn:population":0,
    "gn:timezone":"Asia/Karachi",
    "iso:country":"PK",
    "name:und_x_variant":[
        "Sangerew\u0101la"
    ],
    "wof:name":"Sangerawala",
    "wof:placetype":"locality"
},
  "geometry": {"coordinates":[71.14683000000002,31.52054],"type":"Point"}
}