{
  "type": "Feature",
  "properties": {
    "gn:admin1_code":"04",
    "gn:asciiname":"Taorian",
    "gn:country_code":"PK",
    "gn:dem":190,
    "gn:feature_class":"P",
    "gn:feature_code":"PPL",
    "gn:name":"Taorian",
    "gn:population":0,
    "gn:timezone":"Asia/Karachi",
    "iso:country":"PK",
    "name:und_x_variant":[
        "Tawrian",
        "T\u0101wari\u0101n",
        "Taorian"
    ],
    "wof:name":"Taorian",
    "wof:placetype":"locality"
},
  "geometry": {"coordinates":[73.80036,31.22768],"type":"Point"}
}