{
  "type": "Feature",
  "properties": {
    "gn:admin1_code":"2.0",
    "gn:asciiname":"Paind Kili",
    "gn:country_code":"PK",
    "gn:dem":964,
    "gn:feature_class":"P",
    "gn:feature_code":"PPL",
    "gn:name":"Paind Kili",
    "gn:population":0,
    "gn:timezone":"Asia/Karachi",
    "iso:country":"PK",
    "wof:name":"Paind Kili",
    "wof:placetype":"locality"
},
  "geometry": {"coordinates":[69.04541999999999,30.04939],"type":"Point"}
}