{
  "type": "Feature",
  "properties": {
    "gn:admin1_code":"4.0",
    "gn:asciiname":"Teliwala",
    "gn:country_code":"PK",
    "gn:dem":214,
    "gn:feature_class":"P",
    "gn:feature_code":"PPL",
    "gn:name":"Teliwala",
    "gn:population":0,
    "gn:timezone":"Asia/Karachi",
    "iso:country":"PK",
    "name:und_x_variant":[
        "Teliw\u0101la"
    ],
    "wof:name":"Teliwala",
    "wof:placetype":"locality"
},
  "geometry": {"coordinates":[74.43083,31.89556],"type":"Point"}
}