{
  "type": "Feature",
  "properties": {
    "gn:admin1_code":"4.0",
    "gn:asciiname":"Basti Shah Gagi",
    "gn:country_code":"PK",
    "gn:dem":85,
    "gn:feature_class":"P",
    "gn:feature_code":"PPL",
    "gn:name":"Basti Shah Gagi",
    "gn:population":0,
    "gn:timezone":"Asia/Karachi",
    "iso:country":"PK",
    "wof:name":"Basti Shah Gagi",
    "wof:placetype":"locality"
},
  "geometry": {"coordinates":[69.74776999999999,28.50672],"type":"Point"}
}