{
  "type": "Feature",
  "properties": {
    "gn:admin1_code":"3.0",
    "gn:asciiname":"Badan Khel",
    "gn:country_code":"PK",
    "gn:dem":466,
    "gn:feature_class":"P",
    "gn:feature_code":"PPL",
    "gn:name":"Badan Khel",
    "gn:population":0,
    "gn:timezone":"Asia/Karachi",
    "iso:country":"PK",
    "wof:name":"Badan Khel",
    "wof:placetype":"locality"
},
  "geometry": {"coordinates":[70.64072,33.08319],"type":"Point"}
}