{
  "type": "Feature",
  "properties": {
    "gn:admin1_code":"5.0",
    "gn:asciiname":"Ghul Tunio",
    "gn:country_code":"PK",
    "gn:dem":45,
    "gn:feature_class":"P",
    "gn:feature_code":"PPL",
    "gn:name":"Ghul Tunio",
    "gn:population":0,
    "gn:timezone":"Asia/Karachi",
    "iso:country":"PK",
    "name:und_x_variant":[
        "Gola"
    ],
    "wof:name":"Ghul Tunio",
    "wof:placetype":"locality"
},
  "geometry": {"coordinates":[67.80591,27.58461],"type":"Point"}
}