{
  "type": "Feature",
  "properties": {
    "gn:admin1_code":"3.0",
    "gn:asciiname":"Dallasa Kalle",
    "gn:country_code":"PK",
    "gn:dem":336,
    "gn:feature_class":"P",
    "gn:feature_code":"PPL",
    "gn:name":"Dallasa Kalle",
    "gn:population":0,
    "gn:timezone":"Asia/Karachi",
    "iso:country":"PK",
    "wof:name":"Dallasa Kalle",
    "wof:placetype":"locality"
},
  "geometry": {"coordinates":[72.05514000000002,34.27777],"type":"Point"}
}