{
  "type": "Feature",
  "properties": {
    "gn:admin1_code":"7.0",
    "gn:asciiname":"Ripng",
    "gn:country_code":"PK",
    "gn:dem":2561,
    "gn:feature_class":"P",
    "gn:feature_code":"PPL",
    "gn:name":"Ripng",
    "gn:population":0,
    "gn:timezone":"Asia/Karachi",
    "iso:country":"PK",
    "wof:name":"Ripng",
    "wof:placetype":"locality"
},
  "geometry": {"coordinates":[75.03776999999999,35.70343],"type":"Point"}
}