{
  "type": "Feature",
  "properties": {
    "gn:admin1_code":"5.0",
    "gn:asciiname":"Goth Bakhar Sahtani",
    "gn:country_code":"PK",
    "gn:dem":135,
    "gn:feature_class":"P",
    "gn:feature_code":"PPL",
    "gn:name":"Goth Bakhar Sahtani",
    "gn:population":0,
    "gn:timezone":"Asia/Karachi",
    "iso:country":"PK",
    "name:und_x_variant":[
        "Bakh\u0101r",
        "Goth Bakhar",
        "Goth Bakhar Sahtani"
    ],
    "wof:name":"Goth Bakhar Sahtani",
    "wof:placetype":"locality"
},
  "geometry": {"coordinates":[67.22758,25.12126],"type":"Point"}
}