{
  "type": "Feature",
  "properties": {
    "gn:admin1_code":"4.0",
    "gn:asciiname":"Aidulpur",
    "gn:country_code":"PK",
    "gn:dem":190,
    "gn:feature_class":"P",
    "gn:feature_code":"PPL",
    "gn:name":"Aidulpur",
    "gn:population":0,
    "gn:timezone":"Asia/Karachi",
    "iso:country":"PK",
    "name:und_x_variant":[
        "Aidalpur",
        "Aidulpur"
    ],
    "wof:name":"Aidulpur",
    "wof:placetype":"locality"
},
  "geometry": {"coordinates":[73.16481,32.01429],"type":"Point"}
}