{
  "type": "Feature",
  "properties": {
    "gn:admin1_code":"01",
    "gn:asciiname":"Parmakhai",
    "gn:country_code":"PK",
    "gn:dem":902,
    "gn:feature_class":"P",
    "gn:feature_code":"PPL",
    "gn:name":"Parmakhai",
    "gn:population":0,
    "gn:timezone":"Asia/Karachi",
    "iso:country":"PK",
    "name:eng_x_preferred":[
        "Parmakhai"
    ],
    "wof:name":"Parmakhai",
    "wof:placetype":"locality"
},
  "geometry": {"coordinates":[71.50191,34.76713],"type":"Point"}
}