{
  "type": "Feature",
  "properties": {
    "gn:admin1_code":"4",
    "gn:asciiname":"Tibbi Pipliwala",
    "gn:country_code":"PK",
    "gn:dem":241,
    "gn:feature_class":"P",
    "gn:feature_code":"PPL",
    "gn:name":"Tibbi Pipliwala",
    "gn:population":0,
    "gn:timezone":"Asia/Karachi",
    "iso:country":"PK",
    "name:und_x_variant":[
        "Tibbi Pipli"
    ],
    "wof:name":"Tibbi Pipliwala",
    "wof:placetype":"locality"
},
  "geometry": {"coordinates":[74.23774,32.64527],"type":"Point"}
}