{
  "type": "Feature",
  "properties": {
    "gn:admin1_code":"4.0",
    "gn:asciiname":"Ghul Ghotuwala",
    "gn:country_code":"PK",
    "gn:dem":123,
    "gn:feature_class":"P",
    "gn:feature_code":"PPL",
    "gn:name":"Ghul Ghotuwala",
    "gn:population":0,
    "gn:timezone":"Asia/Karachi",
    "iso:country":"PK",
    "name:und_x_variant":[
        "Ghul Ghutuw\u0101la"
    ],
    "wof:name":"Ghul Ghotuwala",
    "wof:placetype":"locality"
},
  "geometry": {"coordinates":[71.09726999999999,30.16458],"type":"Point"}
}