{
  "type": "Feature",
  "properties": {
    "gn:admin1_code":"4",
    "gn:asciiname":"Rehmatabad",
    "gn:country_code":"PK",
    "gn:dem":244,
    "gn:feature_class":"P",
    "gn:feature_code":"PPL",
    "gn:name":"Rehmatabad",
    "gn:population":0,
    "gn:timezone":"Asia/Karachi",
    "iso:country":"PK",
    "name:und_x_variant":[
        "Rahmat\u0101b\u0101d"
    ],
    "wof:name":"Rehmatabad",
    "wof:placetype":"locality"
},
  "geometry": {"coordinates":[74.55519,32.37157],"type":"Point"}
}