{
  "type": "Feature",
  "properties": {
    "gn:admin1_code":"6.0",
    "gn:admin2_code":"1180287",
    "gn:asciiname":"Harno",
    "gn:country_code":"PK",
    "gn:dem":470,
    "gn:feature_class":"P",
    "gn:feature_code":"PPL",
    "gn:name":"Harno",
    "gn:population":0,
    "gn:timezone":"Asia/Karachi",
    "iso:country":"PK",
    "wof:name":"Harno",
    "wof:placetype":"locality"
},
  "geometry": {"coordinates":[73.51576,33.31111],"type":"Point"}
}