{
  "type": "Feature",
  "properties": {
    "gn:admin1_code":"5",
    "gn:asciiname":"Goth Faqir Muhammad Thahim",
    "gn:country_code":"PK",
    "gn:dem":19,
    "gn:feature_class":"P",
    "gn:feature_code":"PPL",
    "gn:name":"Goth Faqir Muhammad Thahim",
    "gn:population":0,
    "gn:timezone":"Asia/Karachi",
    "iso:country":"PK",
    "name:und_x_variant":[
        "Faiz Muhammad Th\u0101im"
    ],
    "wof:name":"Goth Faqir Muhammad Thahim",
    "wof:placetype":"locality"
},
  "geometry": {"coordinates":[69.02476999999999,25.83354],"type":"Point"}
}