{
  "type": "Feature",
  "properties": {
    "gn:admin1_code":"2.0",
    "gn:asciiname":"Kasozai",
    "gn:country_code":"PK",
    "gn:dem":1681,
    "gn:feature_class":"P",
    "gn:feature_code":"PPL",
    "gn:name":"Kasozai",
    "gn:population":0,
    "gn:timezone":"Asia/Karachi",
    "iso:country":"PK",
    "name:und_x_variant":[
        "Kateszai",
        "Katsezai",
        "Kasozai"
    ],
    "wof:name":"Kasozai",
    "wof:placetype":"locality"
},
  "geometry": {"coordinates":[69.42894,31.19028],"type":"Point"}
}