{
  "type": "Feature",
  "properties": {
    "gn:admin1_code":"2.0",
    "gn:asciiname":"Shamshan",
    "gn:country_code":"PK",
    "gn:dem":661,
    "gn:feature_class":"P",
    "gn:feature_code":"PPL",
    "gn:name":"Shamshan",
    "gn:population":0,
    "gn:timezone":"Asia/Karachi",
    "iso:country":"PK",
    "name:und_x_variant":[
        "Kili Ch\u0101h Abdul Ghani"
    ],
    "wof:name":"Shamshan",
    "wof:placetype":"locality"
},
  "geometry": {"coordinates":[65.09395000000001,28.33162],"type":"Point"}
}