{
  "type": "Feature",
  "properties": {
    "gn:admin1_code":"5.0",
    "gn:asciiname":"Thare jo Tar",
    "gn:country_code":"PK",
    "gn:dem":70,
    "gn:feature_class":"P",
    "gn:feature_code":"PPL",
    "gn:name":"Thare jo Tar",
    "gn:population":0,
    "gn:timezone":"Asia/Karachi",
    "iso:country":"PK",
    "name:und_x_variant":[
        "Th\u0101re jo Got",
        "Th\u0101re Jo Goth"
    ],
    "wof:name":"Thare jo Tar",
    "wof:placetype":"locality"
},
  "geometry": {"coordinates":[70.36293000000001,24.75156],"type":"Point"}
}