{
  "type": "Feature",
  "properties": {
    "gn:admin1_code":"4",
    "gn:asciiname":"Sohal",
    "gn:country_code":"PK",
    "gn:dem":322,
    "gn:feature_class":"P",
    "gn:feature_code":"PPL",
    "gn:name":"Sohal",
    "gn:population":0,
    "gn:timezone":"Asia/Karachi",
    "iso:country":"PK",
    "name:hin_x_preferred":[
        "\u0938\u094b\u0939\u0932"
    ],
    "wof:name":"Sohal",
    "wof:placetype":"locality"
},
  "geometry": {"coordinates":[74.17156999999997,32.84508],"type":"Point"}
}