{
  "type": "Feature",
  "properties": {
    "gn:admin1_code":"5.0",
    "gn:asciiname":"Muhammad Akram Bihan",
    "gn:country_code":"PK",
    "gn:dem":50,
    "gn:feature_class":"P",
    "gn:feature_code":"PPL",
    "gn:name":"Muhammad Akram Bihan",
    "gn:population":0,
    "gn:timezone":"Asia/Karachi",
    "iso:country":"PK",
    "name:und_x_variant":[
        "Muhammad Akram Bh\u012bn"
    ],
    "wof:name":"Muhammad Akram Bihan",
    "wof:placetype":"locality"
},
  "geometry": {"coordinates":[68.68774000000001,27.16528],"type":"Point"}
}