{
  "type": "Feature",
  "properties": {
    "gn:admin1_code":"2",
    "gn:asciiname":"Desal",
    "gn:country_code":"PK",
    "gn:dem":2049,
    "gn:feature_class":"P",
    "gn:feature_code":"PPL",
    "gn:name":"Desal",
    "gn:population":0,
    "gn:timezone":"Asia/Karachi",
    "iso:country":"PK",
    "wof:name":"Desal",
    "wof:placetype":"locality"
},
  "geometry": {"coordinates":[67.89393000000001,31.01518],"type":"Point"}
}