{
  "type": "Feature",
  "properties": {
    "gn:admin1_code":"6",
    "gn:asciiname":"Mughal",
    "gn:country_code":"PK",
    "gn:dem":237,
    "gn:feature_class":"P",
    "gn:feature_code":"PPL",
    "gn:name":"Mughal",
    "gn:population":0,
    "gn:timezone":"Asia/Karachi",
    "iso:country":"PK",
    "name:ceb_x_preferred":[
        "Mughal"
    ],
    "name:fas_x_preferred":[
        "\u0645\u063a\u0648\u0644"
    ],
    "wof:name":"Mughal",
    "wof:placetype":"locality"
},
  "geometry": {"coordinates":[73.81699999999999,33.00849],"type":"Point"}
}