{
  "type": "Feature",
  "properties": {
    "gn:admin1_code":"4",
    "gn:asciiname":"Chak Ninety-three South Branch",
    "gn:country_code":"PK",
    "gn:dem":190,
    "gn:feature_class":"P",
    "gn:feature_code":"PPL",
    "gn:name":"Chak Ninety-three South Branch",
    "gn:population":0,
    "gn:timezone":"Asia/Karachi",
    "iso:country":"PK",
    "wof:name":"Chak Ninety-three South Branch",
    "wof:placetype":"locality"
},
  "geometry": {"coordinates":[72.78055999999999,32.02799],"type":"Point"}
}