{
  "type": "Feature",
  "properties": {
    "gn:admin1_code":"4.0",
    "gn:asciiname":"Dakwanwala",
    "gn:country_code":"PK",
    "gn:dem":767,
    "gn:feature_class":"P",
    "gn:feature_code":"PPL",
    "gn:name":"Dakwanwala",
    "gn:population":0,
    "gn:timezone":"Asia/Karachi",
    "iso:country":"PK",
    "name:und_x_variant":[
        "D\u0101ku\u0101nw\u0101la"
    ],
    "wof:name":"Dakwanwala",
    "wof:placetype":"locality"
},
  "geometry": {"coordinates":[72.0061,32.46863],"type":"Point"}
}