{
  "type": "Feature",
  "properties": {
    "gn:admin1_code":"4.0",
    "gn:asciiname":"Atalgarh",
    "gn:country_code":"PK",
    "gn:dem":272,
    "gn:feature_class":"P",
    "gn:feature_code":"PPL",
    "gn:name":"Atalgarh",
    "gn:population":0,
    "gn:timezone":"Asia/Karachi",
    "iso:country":"PK",
    "wof:name":"Atalgarh",
    "wof:placetype":"locality"
},
  "geometry": {"coordinates":[75.10269,32.31057],"type":"Point"}
}