{
  "type": "Feature",
  "properties": {
    "gn:admin1_code":"4",
    "gn:asciiname":"Dera Garwanwala",
    "gn:country_code":"PK",
    "gn:dem":164,
    "gn:feature_class":"P",
    "gn:feature_code":"PPL",
    "gn:name":"Dera Garwanwala",
    "gn:population":0,
    "gn:timezone":"Asia/Karachi",
    "iso:country":"PK",
    "name:und_x_variant":[
        "Garw\u0101nw\u0101la"
    ],
    "wof:name":"Dera Garwanwala",
    "wof:placetype":"locality"
},
  "geometry": {"coordinates":[71.15816,31.47023],"type":"Point"}
}