{
  "type": "Feature",
  "properties": {
    "gn:admin1_code":"3.0",
    "gn:asciiname":"Shindur Banal",
    "gn:country_code":"PK",
    "gn:dem":2561,
    "gn:feature_class":"P",
    "gn:feature_code":"PPL",
    "gn:name":"Shindur Banal",
    "gn:population":0,
    "gn:timezone":"Asia/Karachi",
    "iso:country":"PK",
    "wof:name":"Shindur Banal",
    "wof:placetype":"locality"
},
  "geometry": {"coordinates":[72.68428,35.63664],"type":"Point"}
}