{
  "type": "Feature",
  "properties": {
    "gn:admin1_code":"6.0",
    "gn:asciiname":"Kos",
    "gn:country_code":"PK",
    "gn:dem":870,
    "gn:feature_class":"P",
    "gn:feature_code":"PPL",
    "gn:name":"Kos",
    "gn:population":0,
    "gn:timezone":"Asia/Karachi",
    "iso:country":"PK",
    "name:und_x_variant":[
        "Kathi",
        "Kosa",
        "Kos"
    ],
    "wof:name":"Kos",
    "wof:placetype":"locality"
},
  "geometry": {"coordinates":[73.74096,33.60661],"type":"Point"}
}