{
  "type": "Feature",
  "properties": {
    "gn:admin1_code":"03",
    "gn:asciiname":"Shaikhan",
    "gn:country_code":"PK",
    "gn:dem":1040,
    "gn:feature_class":"P",
    "gn:feature_code":"PPL",
    "gn:name":"Shaikhan",
    "gn:population":0,
    "gn:timezone":"Asia/Karachi",
    "iso:country":"PK",
    "wof:name":"Shaikhan",
    "wof:placetype":"locality"
},
  "geometry": {"coordinates":[71.78655000000001,34.83372],"type":"Point"}
}