{
  "type": "Feature",
  "properties": {
    "gn:admin1_code":"4.0",
    "gn:asciiname":"Mauza Muhammadpur",
    "gn:country_code":"PK",
    "gn:dem":99,
    "gn:feature_class":"P",
    "gn:feature_code":"PPL",
    "gn:name":"Mauza Muhammadpur",
    "gn:population":0,
    "gn:timezone":"Asia/Karachi",
    "iso:country":"PK",
    "wof:name":"Mauza Muhammadpur",
    "wof:placetype":"locality"
},
  "geometry": {"coordinates":[71.03187,29.24834],"type":"Point"}
}