{
  "type": "Feature",
  "properties": {
    "gn:admin1_code":"1.0",
    "gn:asciiname":"Nima Parao",
    "gn:country_code":"PK",
    "gn:dem":634,
    "gn:feature_class":"P",
    "gn:feature_code":"PPL",
    "gn:name":"Nima Parao",
    "gn:population":0,
    "gn:timezone":"Asia/Karachi",
    "iso:country":"PK",
    "wof:name":"Nima Parao",
    "wof:placetype":"locality"
},
  "geometry": {"coordinates":[70.33094,33.05774],"type":"Point"}
}