{
  "type": "Feature",
  "properties": {
    "gn:admin1_code":"4",
    "gn:asciiname":"Sultanwala Gharbi",
    "gn:country_code":"PK",
    "gn:dem":204,
    "gn:feature_class":"P",
    "gn:feature_code":"PPL",
    "gn:name":"Sultanwala Gharbi",
    "gn:population":0,
    "gn:timezone":"Asia/Karachi",
    "iso:country":"PK",
    "name:und_x_variant":[
        "Burh\u0101nw\u0101la",
        "Sult\u0101nw\u0101la"
    ],
    "wof:name":"Sultanwala Gharbi",
    "wof:placetype":"locality"
},
  "geometry": {"coordinates":[71.46066999999999,32.74192],"type":"Point"}
}