{
  "type": "Feature",
  "properties": {
    "gn:admin1_code":"2.0",
    "gn:asciiname":"Goth Muhammad Siddique Lasi",
    "gn:country_code":"PK",
    "gn:dem":75,
    "gn:feature_class":"P",
    "gn:feature_code":"PPL",
    "gn:name":"Goth Muhammad Siddique Lasi",
    "gn:population":0,
    "gn:timezone":"Asia/Karachi",
    "iso:country":"PK",
    "wof:name":"Goth Muhammad Siddique Lasi",
    "wof:placetype":"locality"
},
  "geometry": {"coordinates":[66.51082,26.05469],"type":"Point"}
}