{
  "type": "Feature",
  "properties": {
    "gn:admin1_code":"1.0",
    "gn:asciiname":"Daman Kili",
    "gn:country_code":"PK",
    "gn:dem":1179,
    "gn:feature_class":"P",
    "gn:feature_code":"PPL",
    "gn:name":"Daman Kili",
    "gn:population":0,
    "gn:timezone":"Asia/Karachi",
    "iso:country":"PK",
    "wof:name":"Daman Kili",
    "wof:placetype":"locality"
},
  "geometry": {"coordinates":[70.97995999999998,33.92153],"type":"Point"}
}