{
  "type": "Feature",
  "properties": {
    "gn:admin1_code":"4.0",
    "gn:asciiname":"Allo",
    "gn:country_code":"PK",
    "gn:dem":323,
    "gn:feature_class":"P",
    "gn:feature_code":"PPL",
    "gn:name":"Allo",
    "gn:population":0,
    "gn:timezone":"Asia/Karachi",
    "iso:country":"PK",
    "name:arg_x_preferred":[
        "Allo"
    ],
    "name:ceb_x_preferred":[
        "Allo"
    ],
    "name:deu_x_preferred":[
        "Allo"
    ],
    "name:glg_x_preferred":[
        "Allo"
    ],
    "name:rus_x_preferred":[
        "\u0410\u043b\u043b\u043e"
    ],
    "name:swe_x_preferred":[
        "Allo"
    ],
    "name:ukr_x_preferred":[
        "\u0410\u043b\u043b\u043e"
    ],
    "name:und_x_variant":[
        "Alloo"
    ],
    "wof:name":"Allo",
    "wof:placetype":"locality"
},
  "geometry": {"coordinates":[72.53099,33.94365],"type":"Point"}
}