{
  "type": "Feature",
  "properties": {
    "gn:admin1_code":"2.0",
    "gn:asciiname":"Kili Hafizabad",
    "gn:country_code":"PK",
    "gn:dem":1467,
    "gn:feature_class":"P",
    "gn:feature_code":"PPL",
    "gn:name":"Kili Hafizabad",
    "gn:population":0,
    "gn:timezone":"Asia/Karachi",
    "iso:country":"PK",
    "wof:name":"Kili Hafizabad",
    "wof:placetype":"locality"
},
  "geometry": {"coordinates":[66.50431,30.11179000000001],"type":"Point"}
}