{
  "type": "Feature",
  "properties": {
    "gn:admin1_code":"4",
    "gn:asciiname":"Jhalar Sheikhanwala",
    "gn:country_code":"PK",
    "gn:dem":119,
    "gn:feature_class":"P",
    "gn:feature_code":"PPL",
    "gn:name":"Jhalar Sheikhanwala",
    "gn:population":0,
    "gn:timezone":"Asia/Karachi",
    "iso:country":"PK",
    "name:und_x_variant":[
        "Jhal\u0101r Sh\u012br\u012bnw\u0101li"
    ],
    "wof:name":"Jhalar Sheikhanwala",
    "wof:placetype":"locality"
},
  "geometry": {"coordinates":[71.47176999999998,30.05578],"type":"Point"}
}