{
  "type": "Feature",
  "properties": {
    "gn:admin1_code":"4.0",
    "gn:asciiname":"Basti Jhillari",
    "gn:country_code":"PK",
    "gn:dem":107,
    "gn:feature_class":"P",
    "gn:feature_code":"PPL",
    "gn:name":"Basti Jhillari",
    "gn:population":0,
    "gn:timezone":"Asia/Karachi",
    "iso:country":"PK",
    "name:und_x_variant":[
        "Jhal\u0101rin"
    ],
    "wof:name":"Basti Jhillari",
    "wof:placetype":"locality"
},
  "geometry": {"coordinates":[70.95796,29.49486],"type":"Point"}
}