{
  "type": "Feature",
  "properties": {
    "gn:admin1_code":"2.0",
    "gn:asciiname":"Dhaggi",
    "gn:country_code":"PK",
    "gn:dem":563,
    "gn:feature_class":"P",
    "gn:feature_code":"PPL",
    "gn:name":"Dhaggi",
    "gn:population":0,
    "gn:timezone":"Asia/Karachi",
    "iso:country":"PK",
    "wof:name":"Dhaggi",
    "wof:placetype":"locality"
},
  "geometry": {"coordinates":[64.72323,26.11184],"type":"Point"}
}