{
  "type": "Feature",
  "properties": {
    "gn:admin1_code":"4.0",
    "gn:asciiname":"Mahbub Chapari",
    "gn:country_code":"PK",
    "gn:dem":779,
    "gn:feature_class":"P",
    "gn:feature_code":"PPL",
    "gn:name":"Mahbub Chapari",
    "gn:population":0,
    "gn:timezone":"Asia/Karachi",
    "iso:country":"PK",
    "name:und_x_variant":[
        "Mahb\u016bb Chapara"
    ],
    "wof:name":"Mahbub Chapari",
    "wof:placetype":"locality"
},
  "geometry": {"coordinates":[71.49858,33.11709],"type":"Point"}
}