{
  "type": "Feature",
  "properties": {
    "gn:admin1_code":"7.0",
    "gn:asciiname":"Pakora",
    "gn:country_code":"PK",
    "gn:dem":2683,
    "gn:feature_class":"P",
    "gn:feature_code":"PPL",
    "gn:name":"Pakora",
    "gn:population":0,
    "gn:timezone":"Asia/Karachi",
    "iso:country":"PK",
    "wof:name":"Pakora",
    "wof:placetype":"locality"
},
  "geometry": {"coordinates":[74.90316999999997,35.25546],"type":"Point"}
}