{
  "type": "Feature",
  "properties": {
    "gn:admin1_code":"04",
    "gn:asciiname":"Chak Twenty-nine Shumali",
    "gn:country_code":"PK",
    "gn:dem":185,
    "gn:feature_class":"P",
    "gn:feature_code":"PPL",
    "gn:name":"Chak Twenty-nine Shumali",
    "gn:population":0,
    "gn:timezone":"Asia/Karachi",
    "iso:country":"PK",
    "name:und_x_variant":[
        "Sabtewala",
        "Sahtew\u0101la",
        "Chak Twenty-Nine",
        "Chak Twenty-nine Shumali"
    ],
    "wof:name":"Chak Twenty-nine Shumali",
    "wof:placetype":"locality"
},
  "geometry": {"coordinates":[72.92124,31.48411],"type":"Point"}
}