{
  "type": "Feature",
  "properties": {
    "gn:admin1_code":"3.0",
    "gn:asciiname":"Otin Khel",
    "gn:country_code":"PK",
    "gn:dem":382,
    "gn:feature_class":"P",
    "gn:feature_code":"PPL",
    "gn:name":"Otin Khel",
    "gn:population":0,
    "gn:timezone":"Asia/Karachi",
    "iso:country":"PK",
    "name:und_x_variant":[
        "Wali Khel",
        "Otin Khel"
    ],
    "wof:name":"Otin Khel",
    "wof:placetype":"locality"
},
  "geometry": {"coordinates":[70.90679,32.98325],"type":"Point"}
}