{
  "type": "Feature",
  "properties": {
    "gn:admin1_code":"5",
    "gn:asciiname":"Goth Jumma Khaskheli",
    "gn:country_code":"PK",
    "gn:dem":26,
    "gn:feature_class":"P",
    "gn:feature_code":"PPL",
    "gn:name":"Goth Jumma Khaskheli",
    "gn:population":0,
    "gn:timezone":"Asia/Karachi",
    "iso:country":"PK",
    "name:und_x_variant":[
        "Goth Jum\u016bn Kh\u0101skheli"
    ],
    "wof:name":"Goth Jumma Khaskheli",
    "wof:placetype":"locality"
},
  "geometry": {"coordinates":[68.50251999999999,25.73839],"type":"Point"}
}