{
  "type": "Feature",
  "properties": {
    "gn:admin1_code":"4",
    "gn:asciiname":"Bhallu ka Khu",
    "gn:country_code":"PK",
    "gn:dem":203,
    "gn:feature_class":"P",
    "gn:feature_code":"PPL",
    "gn:name":"Bhallu ka Khu",
    "gn:population":0,
    "gn:timezone":"Asia/Karachi",
    "iso:country":"PK",
    "name:und_x_variant":[
        "Bhelluka Khu"
    ],
    "wof:name":"Bhallu ka Khu",
    "wof:placetype":"locality"
},
  "geometry": {"coordinates":[73.36376,32.22354],"type":"Point"}
}