{
  "type": "Feature",
  "properties": {
    "gn:admin1_code":"5",
    "gn:asciiname":"Pir Muhammad Arai",
    "gn:country_code":"PK",
    "gn:dem":8,
    "gn:feature_class":"P",
    "gn:feature_code":"PPL",
    "gn:name":"Pir Muhammad Arai",
    "gn:population":0,
    "gn:timezone":"Asia/Karachi",
    "iso:country":"PK",
    "wof:name":"Pir Muhammad Arai",
    "wof:placetype":"locality"
},
  "geometry": {"coordinates":[69.23661,24.81822],"type":"Point"}
}