{
  "type": "Feature",
  "properties": {
    "gn:admin1_code":"1.0",
    "gn:asciiname":"Shahid Baba",
    "gn:country_code":"PK",
    "gn:dem":900,
    "gn:feature_class":"P",
    "gn:feature_code":"PPL",
    "gn:name":"Shahid Baba",
    "gn:population":0,
    "gn:timezone":"Asia/Karachi",
    "iso:country":"PK",
    "wof:name":"Shahid Baba",
    "wof:placetype":"locality"
},
  "geometry": {"coordinates":[71.60438000000001,34.64439],"type":"Point"}
}