{
  "type": "Feature",
  "properties": {
    "gn:admin1_code":"3",
    "gn:asciiname":"Jiggi Tarli",
    "gn:country_code":"PK",
    "gn:dem":1053,
    "gn:feature_class":"P",
    "gn:feature_code":"PPL",
    "gn:name":"Jiggi Tarli",
    "gn:population":0,
    "gn:timezone":"Asia/Karachi",
    "iso:country":"PK",
    "wof:name":"Jiggi Tarli",
    "wof:placetype":"locality"
},
  "geometry": {"coordinates":[72.93436,34.46145],"type":"Point"}
}