{
  "type": "Feature",
  "properties": {
    "gn:admin1_code":"7.0",
    "gn:asciiname":"Hamdar",
    "gn:country_code":"PK",
    "gn:dem":3280,
    "gn:feature_class":"P",
    "gn:feature_code":"PPL",
    "gn:name":"Hamdar",
    "gn:population":0,
    "gn:timezone":"Asia/Karachi",
    "iso:country":"PK",
    "wof:name":"Hamdar",
    "wof:placetype":"locality"
},
  "geometry": {"coordinates":[74.8266,36.18069000000001],"type":"Point"}
}