{
  "type": "Feature",
  "properties": {
    "gn:admin1_code":"4.0",
    "gn:asciiname":"Chakora",
    "gn:country_code":"PK",
    "gn:dem":253,
    "gn:feature_class":"P",
    "gn:feature_code":"PPL",
    "gn:name":"Chakora",
    "gn:population":0,
    "gn:timezone":"Asia/Karachi",
    "iso:country":"PK",
    "name:und_x_variant":[
        "Chakorah",
        "Chakora"
    ],
    "wof:name":"Chakora",
    "wof:placetype":"locality"
},
  "geometry": {"coordinates":[73.70648,33.03494],"type":"Point"}
}