{
  "type": "Feature",
  "properties": {
    "gn:admin1_code":"04",
    "gn:asciiname":"Qila Jiwan Singh",
    "gn:country_code":"PK",
    "gn:dem":218,
    "gn:feature_class":"P",
    "gn:feature_code":"PPL",
    "gn:name":"Qila Jiwan Singh",
    "gn:population":0,
    "gn:timezone":"Asia/Karachi",
    "iso:country":"PK",
    "name:und_x_variant":[
        "Qila J\u012bwan Singh"
    ],
    "wof:name":"Qila Jiwan Singh",
    "wof:placetype":"locality"
},
  "geometry": {"coordinates":[74.59888000000002,31.5377],"type":"Point"}
}