{
  "type": "Feature",
  "properties": {
    "gn:admin1_code":"3",
    "gn:asciiname":"Sanjaliala",
    "gn:country_code":"PK",
    "gn:dem":831,
    "gn:feature_class":"P",
    "gn:feature_code":"PPL",
    "gn:name":"Sanjaliala",
    "gn:population":0,
    "gn:timezone":"Asia/Karachi",
    "iso:country":"PK",
    "name:und_x_variant":[
        "Sanjli\u0101la"
    ],
    "wof:name":"Sanjaliala",
    "wof:placetype":"locality"
},
  "geometry": {"coordinates":[73.08374000000001,34.37864],"type":"Point"}
}