{
  "type": "Feature",
  "properties": {
    "gn:admin1_code":"4.0",
    "gn:asciiname":"Chagda",
    "gn:country_code":"PK",
    "gn:dem":362,
    "gn:feature_class":"P",
    "gn:feature_code":"PPL",
    "gn:name":"Chagda",
    "gn:population":0,
    "gn:timezone":"Asia/Karachi",
    "iso:country":"PK",
    "name:und_x_variant":[
        "Chak D\u0101h"
    ],
    "wof:name":"Chagda",
    "wof:placetype":"locality"
},
  "geometry": {"coordinates":[71.85913000000002,32.71749000000001],"type":"Point"}
}