{
  "type": "Feature",
  "properties": {
    "gn:admin1_code":"4.0",
    "gn:asciiname":"Chagda",
    "gn:country_code":"PK",
    "gn:dem":362,
    "gn:feature_class":"P",
    "gn:feature_code":"PPL",
    "gn:name":"Chagda",
    "gn:population":0,
    "gn:timezone":"Asia/Karachi",
    "iso:country":"PK",
    "name:ara_x_preferred":[
        "\u062a\u0634\u0627\u062c\u062f\u0627"
    ],
    "name:ben_x_preferred":[
        "\u099a\u09be\u0997\u09a6\u09be"
    ],
    "name:deu_x_preferred":[
        "Chagda"
    ],
    "name:ell_x_preferred":[
        "\u03a4\u03c3\u03ac\u03b3\u03ba\u03bd\u03c4\u03b1"
    ],
    "name:eng_x_preferred":[
        "Chagda"
    ],
    "name:fas_x_preferred":[
        "\u0686\u0627\u06af\u062f\u0627"
    ],
    "name:fra_x_preferred":[
        "Chagda"
    ],
    "name:heb_x_preferred":[
        "\u05e6'\u05d0\u05d2\u05d3\u05d4"
    ],
    "name:hin_x_preferred":[
        "\u091a\u093e\u0917\u0926\u093e"
    ],
    "name:hun_x_preferred":[
        "Chagda"
    ],
    "name:ind_x_preferred":[
        "Chagda"
    ],
    "name:ita_x_preferred":[
        "Chagda"
    ],
    "name:jpn_x_preferred":[
        "\u30c1\u30e3\u30b0\u30c0"
    ],
    "name:kor_x_preferred":[
        "\ucc28\uadf8\ub2e4"
    ],
    "name:nld_x_preferred":[
        "Chagda"
    ],
    "name:pol_x_preferred":[
        "Chagda"
    ],
    "name:por_x_preferred":[
        "Chagda"
    ],
    "name:rus_x_preferred":[
        "\u0427\u0430\u0433\u0434\u0430"
    ],
    "name:spa_x_preferred":[
        "Chagda"
    ],
    "name:swe_x_preferred":[
        "Tjagda"
    ],
    "name:tur_x_preferred":[
        "Chagda"
    ],
    "name:ukr_x_preferred":[
        "\u0427\u0430\u0433\u0434\u0430"
    ],
    "name:und_x_variant":[
        "Chak D\u0101h"
    ],
    "name:urd_x_preferred":[
        "\u0686\u0627\u06af\u0688\u0627"
    ],
    "name:vie_x_preferred":[
        "Chagda"
    ],
    "name:zho_cn_x_preferred":[
        "\u67e5\u683c\u8fbe"
    ],
    "name:zho_tw_x_preferred":[
        "\u67e5\u683c\u9054"
    ],
    "wof:name":"Chagda",
    "wof:placetype":"locality"
},
  "geometry": {"coordinates":[71.85912999999999,32.71749],"type":"Point"}
}