{
  "type": "Feature",
  "properties": {
    "gn:admin1_code":"5.0",
    "gn:asciiname":"Goth Haji Sher Khan",
    "gn:country_code":"PK",
    "gn:dem":8,
    "gn:feature_class":"P",
    "gn:feature_code":"PPL",
    "gn:name":"Goth Haji Sher Khan",
    "gn:population":0,
    "gn:timezone":"Asia/Karachi",
    "iso:country":"PK",
    "name:und_x_variant":[
        "Goth H\u0101ji M\u012br Kh\u0101n",
        "H\u0101ji M\u012br Kh\u0101n",
        "Goth Haji Sher Khan"
    ],
    "wof:name":"Goth Haji Sher Khan",
    "wof:placetype":"locality"
},
  "geometry": {"coordinates":[67.664,24.60677],"type":"Point"}
}