{
  "type": "Feature",
  "properties": {
    "gn:admin1_code":"3",
    "gn:asciiname":"Birkhal",
    "gn:country_code":"PK",
    "gn:dem":1601,
    "gn:feature_class":"P",
    "gn:feature_code":"PPL",
    "gn:name":"Birkhal",
    "gn:population":0,
    "gn:timezone":"Asia/Karachi",
    "iso:country":"PK",
    "name:und_x_variant":[
        "B\u012brkhal"
    ],
    "wof:name":"Birkhal",
    "wof:placetype":"locality"
},
  "geometry": {"coordinates":[73.50754000000001,34.65944],"type":"Point"}
}