{
  "type": "Feature",
  "properties": {
    "gn:admin1_code":"3",
    "gn:asciiname":"Razwala",
    "gn:country_code":"PK",
    "gn:dem":2010,
    "gn:feature_class":"P",
    "gn:feature_code":"PPL",
    "gn:name":"Razwala",
    "gn:population":0,
    "gn:timezone":"Asia/Karachi",
    "iso:country":"PK",
    "name:und_x_variant":[
        "R\u0101jw\u0101la"
    ],
    "wof:name":"Razwala",
    "wof:placetype":"locality"
},
  "geometry": {"coordinates":[73.33268000000002,34.09841],"type":"Point"}
}