{
  "type": "Feature",
  "properties": {
    "gn:admin1_code":"3.0",
    "gn:asciiname":"Gumbot",
    "gn:country_code":"PK",
    "gn:dem":1137,
    "gn:feature_class":"P",
    "gn:feature_code":"PPL",
    "gn:name":"Gumbot",
    "gn:population":0,
    "gn:timezone":"Asia/Karachi",
    "iso:country":"PK",
    "wof:name":"Gumbot",
    "wof:placetype":"locality"
},
  "geometry": {"coordinates":[72.30110000000001,34.65024],"type":"Point"}
}