{
  "type": "Feature",
  "properties": {
    "gn:admin1_code":"3",
    "gn:asciiname":"Shangrai",
    "gn:country_code":"PK",
    "gn:dem":1618,
    "gn:feature_class":"P",
    "gn:feature_code":"PPL",
    "gn:name":"Shangrai",
    "gn:population":0,
    "gn:timezone":"Asia/Karachi",
    "iso:country":"PK",
    "name:und_x_variant":[
        "Shangra"
    ],
    "wof:name":"Shangrai",
    "wof:placetype":"locality"
},
  "geometry": {"coordinates":[72.70653,34.58154],"type":"Point"}
}