{
  "type": "Feature",
  "properties": {
    "gn:admin1_code":"3",
    "gn:asciiname":"Jala Banda",
    "gn:country_code":"PK",
    "gn:dem":558,
    "gn:feature_class":"P",
    "gn:feature_code":"PPL",
    "gn:name":"Jala Banda",
    "gn:population":0,
    "gn:timezone":"Asia/Karachi",
    "iso:country":"PK",
    "wof:name":"Jala Banda",
    "wof:placetype":"locality"
},
  "geometry": {"coordinates":[70.96339999999999,33.15262],"type":"Point"}
}