{
  "type": "Feature",
  "properties": {
    "gn:admin1_code":"3.0",
    "gn:asciiname":"Nekam",
    "gn:country_code":"PK",
    "gn:dem":314,
    "gn:feature_class":"P",
    "gn:feature_code":"PPL",
    "gn:name":"Nekam",
    "gn:population":0,
    "gn:timezone":"Asia/Karachi",
    "iso:country":"PK",
    "name:und_x_variant":[
        "Nakam Gul",
        "Nekam Gul",
        "Nekam"
    ],
    "wof:name":"Nekam",
    "wof:placetype":"locality"
},
  "geometry": {"coordinates":[70.72156,32.82784],"type":"Point"}
}