{
  "type": "Feature",
  "properties": {
    "gn:admin1_code":"4.0",
    "gn:asciiname":"Chak One Hundred Fifteen A Southern Branch",
    "gn:country_code":"PK",
    "gn:dem":185,
    "gn:feature_class":"P",
    "gn:feature_code":"PPL",
    "gn:name":"Chak One Hundred Fifteen A Southern Branch",
    "gn:population":0,
    "gn:timezone":"Asia/Karachi",
    "iso:country":"PK",
    "name:und_x_variant":[
        "Chak One Hundred Fifteen A SB",
        "Ras\u0101la"
    ],
    "wof:name":"Chak One Hundred Fifteen A Southern Branch",
    "wof:placetype":"locality"
},
  "geometry": {"coordinates":[72.7248,31.87735],"type":"Point"}
}