{
  "type": "Feature",
  "properties": {
    "gn:admin1_code":"3.0",
    "gn:asciiname":"Gulabad",
    "gn:country_code":"PK",
    "gn:dem":766,
    "gn:feature_class":"P",
    "gn:feature_code":"PPL",
    "gn:name":"Gulabad",
    "gn:population":0,
    "gn:timezone":"Asia/Karachi",
    "iso:country":"PK",
    "wof:name":"Gulabad",
    "wof:placetype":"locality"
},
  "geometry": {"coordinates":[72.03054,34.69856],"type":"Point"}
}