{
  "type": "Feature",
  "properties": {
    "gn:admin1_code":"5.0",
    "gn:asciiname":"Mamu Samu Goth",
    "gn:country_code":"PK",
    "gn:dem":12,
    "gn:feature_class":"P",
    "gn:feature_code":"PPL",
    "gn:name":"Mamu Samu Goth",
    "gn:population":0,
    "gn:timezone":"Asia/Karachi",
    "iso:country":"PK",
    "name:und_x_variant":[
        "Goth M\u0101mu Samu"
    ],
    "wof:name":"Mamu Samu Goth",
    "wof:placetype":"locality"
},
  "geometry": {"coordinates":[67.93434999999999,24.78401],"type":"Point"}
}