{
  "type": "Feature",
  "properties": {
    "gn:admin1_code":"04",
    "gn:asciiname":"Mungwal",
    "gn:country_code":"PK",
    "gn:dem":199,
    "gn:feature_class":"P",
    "gn:feature_code":"PPL",
    "gn:name":"Mungwal",
    "gn:population":0,
    "gn:timezone":"Asia/Karachi",
    "iso:country":"PK",
    "name:und_x_variant":[
        "Mangw\u0101l",
        "Mungwal"
    ],
    "wof:name":"Mungwal",
    "wof:placetype":"locality"
},
  "geometry": {"coordinates":[72.56947,32.53743],"type":"Point"}
}