{
  "type": "Feature",
  "properties": {
    "gn:admin1_code":"6",
    "gn:asciiname":"Purani Ghagri",
    "gn:country_code":"PK",
    "gn:dem":518,
    "gn:feature_class":"P",
    "gn:feature_code":"PPL",
    "gn:name":"Purani Ghagri",
    "gn:population":0,
    "gn:timezone":"Asia/Karachi",
    "iso:country":"PK",
    "name:und_x_variant":[
        "Pur\u0101ni Gokha"
    ],
    "wof:name":"Purani Ghagri",
    "wof:placetype":"locality"
},
  "geometry": {"coordinates":[74.32769999999999,32.95215],"type":"Point"}
}