{
  "type": "Feature",
  "properties": {
    "gn:admin1_code":"4",
    "gn:asciiname":"Basti Mission",
    "gn:country_code":"PK",
    "gn:dem":97,
    "gn:feature_class":"P",
    "gn:feature_code":"PPL",
    "gn:name":"Basti Mission",
    "gn:population":0,
    "gn:timezone":"Asia/Karachi",
    "iso:country":"PK",
    "name:und_x_variant":[
        "Nabi Bakhsh Mission"
    ],
    "wof:name":"Basti Mission",
    "wof:placetype":"locality"
},
  "geometry": {"coordinates":[70.82765000000001,28.93212],"type":"Point"}
}