{
  "type": "Feature",
  "properties": {
    "gn:admin1_code":"5.0",
    "gn:asciiname":"Goth Bachal Lakhatia",
    "gn:country_code":"PK",
    "gn:dem":12,
    "gn:feature_class":"P",
    "gn:feature_code":"PPL",
    "gn:name":"Goth Bachal Lakhatia",
    "gn:population":0,
    "gn:timezone":"Asia/Karachi",
    "iso:country":"PK",
    "wof:name":"Goth Bachal Lakhatia",
    "wof:placetype":"locality"
},
  "geometry": {"coordinates":[68.24409,24.7569],"type":"Point"}
}