{
  "type": "Feature",
  "properties": {
    "gn:admin1_code":"3",
    "gn:asciiname":"Richarai",
    "gn:country_code":"PK",
    "gn:dem":1591,
    "gn:feature_class":"P",
    "gn:feature_code":"PPL",
    "gn:name":"Richarai",
    "gn:population":0,
    "gn:timezone":"Asia/Karachi",
    "iso:country":"PK",
    "name:und_x_variant":[
        "Rich\u0101rai"
    ],
    "wof:name":"Richarai",
    "wof:placetype":"locality"
},
  "geometry": {"coordinates":[73.03962,34.88087],"type":"Point"}
}