{
  "type": "Feature",
  "properties": {
    "gn:admin1_code":"4.0",
    "gn:asciiname":"Itifadpur",
    "gn:country_code":"PK",
    "gn:dem":252,
    "gn:feature_class":"P",
    "gn:feature_code":"PPL",
    "gn:name":"Itifadpur",
    "gn:population":0,
    "gn:timezone":"Asia/Karachi",
    "iso:country":"PK",
    "wof:name":"Itifadpur",
    "wof:placetype":"locality"
},
  "geometry": {"coordinates":[74.56925,32.48724],"type":"Point"}
}