{
  "type": "Feature",
  "properties": {
    "gn:admin1_code":"04",
    "gn:asciiname":"Kotha",
    "gn:country_code":"PK",
    "gn:dem":306,
    "gn:feature_class":"P",
    "gn:feature_code":"PPL",
    "gn:name":"Kotha",
    "gn:population":0,
    "gn:timezone":"Asia/Karachi",
    "iso:country":"PK",
    "name:und_x_variant":[
        "Kotha Kalan",
        "Kotha"
    ],
    "wof:name":"Kotha",
    "wof:placetype":"locality"
},
  "geometry": {"coordinates":[72.37612,33.88963],"type":"Point"}
}