{
  "type": "Feature",
  "properties": {
    "gn:admin1_code":"5",
    "gn:asciiname":"Goth Abdul Latif Rahu",
    "gn:country_code":"PK",
    "gn:dem":27,
    "gn:feature_class":"P",
    "gn:feature_code":"PPL",
    "gn:name":"Goth Abdul Latif Rahu",
    "gn:population":0,
    "gn:timezone":"Asia/Karachi",
    "iso:country":"PK",
    "name:eng_x_preferred":[
        "Abdul Lat\u012bf R\u0101hu"
    ],
    "wof:name":"Goth Abdul Latif Rahu",
    "wof:placetype":"locality"
},
  "geometry": {"coordinates":[68.41598,25.98218],"type":"Point"}
}