{
  "type": "Feature",
  "properties": {
    "gn:admin1_code":"2",
    "gn:asciiname":"Nauroz Khan Kili",
    "gn:country_code":"PK",
    "gn:dem":951,
    "gn:feature_class":"P",
    "gn:feature_code":"PPL",
    "gn:name":"Nauroz Khan Kili",
    "gn:population":0,
    "gn:timezone":"Asia/Karachi",
    "iso:country":"PK",
    "name:eng_x_preferred":[
        "Nauroz Khan Kili"
    ],
    "wof:name":"Nauroz Khan Kili",
    "wof:placetype":"locality"
},
  "geometry": {"coordinates":[68.91846,30.1017],"type":"Point"}
}