{
  "type": "Feature",
  "properties": {
    "gn:admin1_code":"4",
    "gn:asciiname":"Dhok Rajgan",
    "gn:country_code":"PK",
    "gn:dem":479,
    "gn:feature_class":"P",
    "gn:feature_code":"PPL",
    "gn:name":"Dhok Rajgan",
    "gn:population":0,
    "gn:timezone":"Asia/Karachi",
    "iso:country":"PK",
    "name:und_x_variant":[
        "Dhok Minh\u0101s",
        "Dhok R\u0101ji\u0101n"
    ],
    "wof:name":"Dhok Rajgan",
    "wof:placetype":"locality"
},
  "geometry": {"coordinates":[73.3182,33.19403],"type":"Point"}
}