{
  "type": "Feature",
  "properties": {
    "gn:admin1_code":"3",
    "gn:asciiname":"Tamborari",
    "gn:country_code":"PK",
    "gn:dem":1635,
    "gn:feature_class":"P",
    "gn:feature_code":"PPL",
    "gn:name":"Tamborari",
    "gn:population":0,
    "gn:timezone":"Asia/Karachi",
    "iso:country":"PK",
    "wof:name":"Tamborari",
    "wof:placetype":"locality"
},
  "geometry": {"coordinates":[73.40755,34.65503],"type":"Point"}
}