{
  "type": "Feature",
  "properties": {
    "gn:admin1_code":"4.0",
    "gn:asciiname":"Tibbawala Khu",
    "gn:country_code":"PK",
    "gn:dem":161,
    "gn:feature_class":"P",
    "gn:feature_code":"PPL",
    "gn:name":"Tibbawala Khu",
    "gn:population":0,
    "gn:timezone":"Asia/Karachi",
    "iso:country":"PK",
    "wof:name":"Tibbawala Khu",
    "wof:placetype":"locality"
},
  "geometry": {"coordinates":[73.22004,30.46395],"type":"Point"}
}