{
  "type": "Feature",
  "properties": {
    "gn:admin1_code":"4.0",
    "gn:asciiname":"Khara",
    "gn:country_code":"PK",
    "gn:dem":430,
    "gn:feature_class":"P",
    "gn:feature_code":"PPL",
    "gn:name":"Khara",
    "gn:population":0,
    "gn:timezone":"Asia/Karachi",
    "iso:country":"PK",
    "name:eng_x_preferred":[
        "Khara"
    ],
    "wof:name":"Khara",
    "wof:placetype":"locality"
},
  "geometry": {"coordinates":[72.64071,33.0887],"type":"Point"}
}