{
  "type": "Feature",
  "properties": {
    "gn:admin1_code":"5",
    "gn:asciiname":"Goth Koreja",
    "gn:country_code":"PK",
    "gn:dem":33,
    "gn:feature_class":"P",
    "gn:feature_code":"PPL",
    "gn:name":"Goth Koreja",
    "gn:population":0,
    "gn:timezone":"Asia/Karachi",
    "iso:country":"PK",
    "name:eng_x_preferred":[
        "Kureja"
    ],
    "wof:name":"Goth Koreja",
    "wof:placetype":"locality"
},
  "geometry": {"coordinates":[68.29348,25.7445],"type":"Point"}
}