{
  "type": "Feature",
  "properties": {
    "gn:admin1_code":"4",
    "gn:asciiname":"Amar Colony",
    "gn:country_code":"PK",
    "gn:dem":233,
    "gn:feature_class":"P",
    "gn:feature_code":"PPL",
    "gn:name":"Amar Colony",
    "gn:population":0,
    "gn:timezone":"Asia/Karachi",
    "iso:country":"PK",
    "name:und_x_variant":[
        "Amar"
    ],
    "wof:name":"Amar Colony",
    "wof:placetype":"locality"
},
  "geometry": {"coordinates":[74.05660999999998,32.58693],"type":"Point"}
}