{
  "type": "Feature",
  "properties": {
    "gn:admin1_code":"6",
    "gn:asciiname":"Angra",
    "gn:country_code":"PK",
    "gn:dem":2306,
    "gn:feature_class":"P",
    "gn:feature_code":"PPL",
    "gn:name":"Angra",
    "gn:population":0,
    "gn:timezone":"Asia/Karachi",
    "iso:country":"PK",
    "name:ceb_x_preferred":[
        "Angra"
    ],
    "name:deu_x_preferred":[
        "Angra"
    ],
    "name:fra_x_preferred":[
        "Angra"
    ],
    "name:jpn_x_preferred":[
        "\u30a2\u30f3\u30b0\u30e9"
    ],
    "name:por_x_preferred":[
        "Angra"
    ],
    "name:sco_x_preferred":[
        "Angra"
    ],
    "name:spa_x_preferred":[
        "Angra"
    ],
    "name:swe_x_preferred":[
        "Angra"
    ],
    "name:ukr_x_preferred":[
        "\u0410\u043d\u0433\u0440\u0430"
    ],
    "wof:name":"Angra",
    "wof:placetype":"locality"
},
  "geometry": {"coordinates":[74.25833,33.95417],"type":"Point"}
}