{
  "type": "Feature",
  "properties": {
    "gn:admin1_code":"2.0",
    "gn:asciiname":"Pirki Dun",
    "gn:country_code":"PK",
    "gn:dem":2298,
    "gn:feature_class":"P",
    "gn:feature_code":"PPL",
    "gn:name":"Pirki Dun",
    "gn:population":0,
    "gn:timezone":"Asia/Karachi",
    "iso:country":"PK",
    "wof:name":"Pirki Dun",
    "wof:placetype":"locality"
},
  "geometry": {"coordinates":[66.6194,28.61918],"type":"Point"}
}