{
  "type": "Feature",
  "properties": {
    "gn:admin1_code":"5",
    "gn:asciiname":"Qazi Khair Muhammad",
    "gn:country_code":"PK",
    "gn:dem":17,
    "gn:feature_class":"P",
    "gn:feature_code":"PPL",
    "gn:name":"Qazi Khair Muhammad",
    "gn:population":0,
    "gn:timezone":"Asia/Karachi",
    "iso:country":"PK",
    "wof:name":"Qazi Khair Muhammad",
    "wof:placetype":"locality"
},
  "geometry": {"coordinates":[69.19306999999999,25.86072],"type":"Point"}
}