{
  "type": "Feature",
  "properties": {
    "gn:admin1_code":"3.0",
    "gn:asciiname":"Sumbaliati",
    "gn:country_code":"PK",
    "gn:dem":1834,
    "gn:feature_class":"P",
    "gn:feature_code":"PPL",
    "gn:name":"Sumbaliati",
    "gn:population":0,
    "gn:timezone":"Asia/Karachi",
    "iso:country":"PK",
    "wof:name":"Sumbaliati",
    "wof:placetype":"locality"
},
  "geometry": {"coordinates":[73.36006,34.01286],"type":"Point"}
}