{
  "type": "Feature",
  "properties": {
    "gn:admin1_code":"1.0",
    "gn:asciiname":"Narpe",
    "gn:country_code":"PK",
    "gn:dem":1630,
    "gn:feature_class":"P",
    "gn:feature_code":"PPL",
    "gn:name":"Narpe",
    "gn:population":0,
    "gn:timezone":"Asia/Karachi",
    "iso:country":"PK",
    "name:und_x_variant":[
        "Narapa"
    ],
    "wof:name":"Narpe",
    "wof:placetype":"locality"
},
  "geometry": {"coordinates":[69.68000000000001,33.01107],"type":"Point"}
}