{
  "type": "Feature",
  "properties": {
    "gn:admin1_code":"2.0",
    "gn:asciiname":"Durai",
    "gn:country_code":"PK",
    "gn:dem":1109,
    "gn:feature_class":"P",
    "gn:feature_code":"PPL",
    "gn:name":"Durai",
    "gn:population":0,
    "gn:timezone":"Asia/Karachi",
    "iso:country":"PK",
    "name:nld_x_preferred":[
        "Durai"
    ],
    "wof:name":"Durai",
    "wof:placetype":"locality"
},
  "geometry": {"coordinates":[69.17827,30.27571],"type":"Point"}
}