{
  "type": "Feature",
  "properties": {
    "gn:admin1_code":"3.0",
    "gn:asciiname":"Must Sar",
    "gn:country_code":"PK",
    "gn:dem":687,
    "gn:feature_class":"P",
    "gn:feature_code":"PPL",
    "gn:name":"Must Sar",
    "gn:population":0,
    "gn:timezone":"Asia/Karachi",
    "iso:country":"PK",
    "wof:name":"Must Sar",
    "wof:placetype":"locality"
},
  "geometry": {"coordinates":[72.57359,34.44452],"type":"Point"}
}