{
  "type": "Feature",
  "properties": {
    "gn:admin1_code":"3.0",
    "gn:asciiname":"Qasimabad",
    "gn:country_code":"PK",
    "gn:dem":405,
    "gn:feature_class":"P",
    "gn:feature_code":"PPL",
    "gn:name":"Qasimabad",
    "gn:population":0,
    "gn:timezone":"Asia/Karachi",
    "iso:country":"PK",
    "wof:name":"Qasimabad",
    "wof:placetype":"locality"
},
  "geometry": {"coordinates":[72.59076999999998,34.13965],"type":"Point"}
}