{
  "type": "Feature",
  "properties": {
    "gn:admin1_code":"4",
    "gn:asciiname":"Khu Chabianwala",
    "gn:country_code":"PK",
    "gn:dem":159,
    "gn:feature_class":"P",
    "gn:feature_code":"PPL",
    "gn:name":"Khu Chabianwala",
    "gn:population":0,
    "gn:timezone":"Asia/Karachi",
    "iso:country":"PK",
    "name:und_x_variant":[
        "Kot Jal\u0101l"
    ],
    "wof:name":"Khu Chabianwala",
    "wof:placetype":"locality"
},
  "geometry": {"coordinates":[72.69289000000001,30.71593],"type":"Point"}
}