{
  "type": "Feature",
  "properties": {
    "gn:admin1_code":"5.0",
    "gn:asciiname":"Goth Muhammad Yusuf Chandio",
    "gn:country_code":"PK",
    "gn:dem":6,
    "gn:feature_class":"P",
    "gn:feature_code":"PPL",
    "gn:name":"Goth Muhammad Yusuf Chandio",
    "gn:population":0,
    "gn:timezone":"Asia/Karachi",
    "iso:country":"PK",
    "wof:name":"Goth Muhammad Yusuf Chandio",
    "wof:placetype":"locality"
},
  "geometry": {"coordinates":[69.47355999999999,25.07598],"type":"Point"}
}