{
  "type": "Feature",
  "properties": {
    "gn:admin1_code":"5",
    "gn:asciiname":"Goth Pahlwan Khan Khakhrani",
    "gn:country_code":"PK",
    "gn:dem":53,
    "gn:feature_class":"P",
    "gn:feature_code":"PPL",
    "gn:name":"Goth Pahlwan Khan Khakhrani",
    "gn:population":0,
    "gn:timezone":"Asia/Karachi",
    "iso:country":"PK",
    "name:und_x_variant":[
        "Pahlw\u0101n Kh\u0101n Ghagr\u0101ni"
    ],
    "wof:name":"Goth Pahlwan Khan Khakhrani",
    "wof:placetype":"locality"
},
  "geometry": {"coordinates":[68.28213000000001,27.88345],"type":"Point"}
}