{
  "type": "Feature",
  "properties": {
    "gn:admin1_code":"2.0",
    "gn:asciiname":"Kach",
    "gn:country_code":"PK",
    "gn:dem":2186,
    "gn:feature_class":"P",
    "gn:feature_code":"PPL",
    "gn:name":"Kach",
    "gn:population":0,
    "gn:timezone":"Asia/Karachi",
    "iso:country":"PK",
    "name:ceb_x_preferred":[
        "Kach"
    ],
    "name:eng_x_preferred":[
        "Kach"
    ],
    "name:ind_x_preferred":[
        "Kach"
    ],
    "name:swe_x_preferred":[
        "Kach"
    ],
    "name:und_x_variant":[
        "Kas Kandr",
        "Kas Kandi"
    ],
    "wof:name":"Kach",
    "wof:placetype":"locality"
},
  "geometry": {"coordinates":[67.42310000000001,30.80525],"type":"Point"}
}