{
  "type": "Feature",
  "properties": {
    "gn:admin1_code":"04",
    "gn:asciiname":"Nurpur",
    "gn:country_code":"PK",
    "gn:dem":99,
    "gn:feature_class":"P",
    "gn:feature_code":"PPL",
    "gn:name":"Nurpur",
    "gn:population":0,
    "gn:timezone":"Asia/Karachi",
    "iso:country":"PK",
    "name:ceb_x_preferred":[
        "Nurpur"
    ],
    "name:swe_x_preferred":[
        "Nurpur"
    ],
    "wof:name":"Nurpur",
    "wof:placetype":"locality"
},
  "geometry": {"coordinates":[70.47284999999999,29.09167],"type":"Point"}
}