{
  "type": "Feature",
  "properties": {
    "gn:admin1_code":"2.0",
    "gn:asciiname":"Panchzai",
    "gn:country_code":"PK",
    "gn:dem":1461,
    "gn:feature_class":"P",
    "gn:feature_code":"PPL",
    "gn:name":"Panchzai",
    "gn:population":0,
    "gn:timezone":"Asia/Karachi",
    "iso:country":"PK",
    "name:und_x_variant":[
        "Panjizai"
    ],
    "wof:name":"Panchzai",
    "wof:placetype":"locality"
},
  "geometry": {"coordinates":[69.23328000000001,31.02425],"type":"Point"}
}