{
  "type": "Feature",
  "properties": {
    "gn:admin1_code":"5",
    "gn:asciiname":"Goth Nawab Korai",
    "gn:country_code":"PK",
    "gn:dem":17,
    "gn:feature_class":"P",
    "gn:feature_code":"PPL",
    "gn:name":"Goth Naw\u0101b Kor\u0101i",
    "gn:population":0,
    "gn:timezone":"Asia/Karachi",
    "iso:country":"PK",
    "wof:name":"Goth Nawab Korai",
    "wof:placetype":"locality"
},
  "geometry": {"coordinates":[68.95,25.15556],"type":"Point"}
}