{
  "type": "Feature",
  "properties": {
    "gn:admin1_code":"5.0",
    "gn:asciiname":"Abdul Rehman Surki",
    "gn:country_code":"PK",
    "gn:dem":63,
    "gn:feature_class":"P",
    "gn:feature_code":"PPL",
    "gn:name":"Abdul Rehman Surki",
    "gn:population":0,
    "gn:timezone":"Asia/Karachi",
    "iso:country":"PK",
    "name:und_x_variant":[
        "Abdul Rehm\u0101n Sarki"
    ],
    "wof:name":"Abdul Rehman Surki",
    "wof:placetype":"locality"
},
  "geometry": {"coordinates":[68.79189000000001,28.28869000000001],"type":"Point"}
}