{
  "type": "Feature",
  "properties": {
    "gn:admin1_code":"5.0",
    "gn:asciiname":"Fateh Ali Lashari",
    "gn:country_code":"PK",
    "gn:dem":55,
    "gn:feature_class":"P",
    "gn:feature_code":"PPL",
    "gn:name":"Fateh Ali Lashari",
    "gn:population":0,
    "gn:timezone":"Asia/Karachi",
    "iso:country":"PK",
    "wof:name":"Fateh Ali Lashari",
    "wof:placetype":"locality"
},
  "geometry": {"coordinates":[68.70068000000001,27.42742],"type":"Point"}
}