{
  "type": "Feature",
  "properties": {
    "gn:admin1_code":"4.0",
    "gn:asciiname":"Gurha Bharta",
    "gn:country_code":"PK",
    "gn:dem":549,
    "gn:feature_class":"P",
    "gn:feature_code":"PPL",
    "gn:name":"Gurha Bharta",
    "gn:population":0,
    "gn:timezone":"Asia/Karachi",
    "iso:country":"PK",
    "name:und_x_variant":[
        "Gurha Bhartha"
    ],
    "wof:name":"Gurha Bharta",
    "wof:placetype":"locality"
},
  "geometry": {"coordinates":[73.19488,33.45027],"type":"Point"}
}