{
  "type": "Feature",
  "properties": {
    "gn:admin1_code":"4",
    "gn:asciiname":"Wadifiwala",
    "gn:country_code":"PK",
    "gn:dem":131,
    "gn:feature_class":"P",
    "gn:feature_code":"PPL",
    "gn:name":"Wad\u012bf\u012bw\u0101la",
    "gn:population":0,
    "gn:timezone":"Asia/Karachi",
    "iso:country":"PK",
    "name:eng_x_preferred":[
        "Wad\u012bf\u012bw\u0101la"
    ],
    "wof:name":"Wadifiwala",
    "wof:placetype":"locality"
},
  "geometry": {"coordinates":[70.88483000000002,30.43637],"type":"Point"}
}