{
  "type": "Feature",
  "properties": {
    "gn:admin1_code":"5",
    "gn:asciiname":"Goth Ali Bakhsh Khosa",
    "gn:country_code":"PK",
    "gn:dem":55,
    "gn:feature_class":"P",
    "gn:feature_code":"PPL",
    "gn:name":"Goth Ali Bakhsh Khosa",
    "gn:population":0,
    "gn:timezone":"Asia/Karachi",
    "iso:country":"PK",
    "name:und_x_variant":[
        "H\u0101ji Sh\u0101hb\u0101z Kh\u0101n"
    ],
    "wof:name":"Goth Ali Bakhsh Khosa",
    "wof:placetype":"locality"
},
  "geometry": {"coordinates":[68.35840999999999,27.9543],"type":"Point"}
}