{
  "type": "Feature",
  "properties": {
    "gn:admin1_code":"4",
    "gn:asciiname":"Allah Ditta Bohr",
    "gn:country_code":"PK",
    "gn:dem":163,
    "gn:feature_class":"P",
    "gn:feature_code":"PPL",
    "gn:name":"Allah Ditta Bohr",
    "gn:population":0,
    "gn:timezone":"Asia/Karachi",
    "iso:country":"PK",
    "name:und_x_variant":[
        "Thul Bah\u0101r",
        "Thal Bah\u0101r",
        "Allah Ditta Bohr"
    ],
    "wof:name":"Allah Ditta Bohr",
    "wof:placetype":"locality"
},
  "geometry": {"coordinates":[70.25079000000001,29.68547],"type":"Point"}
}