{
  "type": "Feature",
  "properties": {
    "gn:admin1_code":"4.0",
    "gn:asciiname":"Dera Nazuwala",
    "gn:country_code":"PK",
    "gn:dem":174,
    "gn:feature_class":"P",
    "gn:feature_code":"PPL",
    "gn:name":"Dera Nazuwala",
    "gn:population":0,
    "gn:timezone":"Asia/Karachi",
    "iso:country":"PK",
    "name:und_x_variant":[
        "Dera Malik N\u0101zu"
    ],
    "wof:name":"Dera Nazuwala",
    "wof:placetype":"locality"
},
  "geometry": {"coordinates":[71.37935,31.6589],"type":"Point"}
}