{
  "type": "Feature",
  "properties": {
    "gn:admin1_code":"03",
    "gn:asciiname":"Kutha",
    "gn:country_code":"PK",
    "gn:dem":346,
    "gn:feature_class":"P",
    "gn:feature_code":"PPL",
    "gn:name":"Kutha",
    "gn:population":0,
    "gn:timezone":"Asia/Karachi",
    "iso:country":"PK",
    "name:und_x_variant":[
        "Kota",
        "Kotha",
        "Kutha"
    ],
    "wof:name":"Kutha",
    "wof:placetype":"locality"
},
  "geometry": {"coordinates":[72.58383000000001,34.06777],"type":"Point"}
}