{
  "type": "Feature",
  "properties": {
    "gn:admin1_code":"6",
    "gn:asciiname":"Mangora",
    "gn:country_code":"PK",
    "gn:dem":1643,
    "gn:feature_class":"P",
    "gn:feature_code":"PPL",
    "gn:name":"Mangora",
    "gn:population":0,
    "gn:timezone":"Asia/Karachi",
    "iso:country":"PK",
    "name:ita_x_preferred":[
        "Mangora"
    ],
    "wof:name":"Mangora",
    "wof:placetype":"locality"
},
  "geometry": {"coordinates":[73.976,33.87535],"type":"Point"}
}