{
  "type": "Feature",
  "properties": {
    "gn:admin1_code":"3",
    "gn:asciiname":"Kas",
    "gn:country_code":"PK",
    "gn:dem":1331,
    "gn:feature_class":"P",
    "gn:feature_code":"PPL",
    "gn:name":"Kas",
    "gn:population":0,
    "gn:timezone":"Asia/Karachi",
    "iso:country":"PK",
    "name:eng_x_preferred":[
        "Kas"
    ],
    "wof:name":"Kas",
    "wof:placetype":"locality"
},
  "geometry": {"coordinates":[71.78395,35.00759],"type":"Point"}
}