{
  "type": "Feature",
  "properties": {
    "gn:admin1_code":"2.0",
    "gn:asciiname":"Malik Muhammad Shah Kili",
    "gn:country_code":"PK",
    "gn:dem":1455,
    "gn:feature_class":"P",
    "gn:feature_code":"PPL",
    "gn:name":"Malik Muhammad Shah Kili",
    "gn:population":0,
    "gn:timezone":"Asia/Karachi",
    "iso:country":"PK",
    "name:und_x_variant":[
        "Malik Muhammad Shali Kili",
        "Malik Muhammad Shah Kili"
    ],
    "wof:name":"Malik Muhammad Shah Kili",
    "wof:placetype":"locality"
},
  "geometry": {"coordinates":[66.54913000000001,30.56353],"type":"Point"}
}