{
  "type": "Feature",
  "properties": {
    "gn:admin1_code":"05",
    "gn:asciiname":"Zarkhel Nawo",
    "gn:country_code":"PK",
    "gn:dem":63,
    "gn:feature_class":"P",
    "gn:feature_code":"PPL",
    "gn:name":"Zarkhel Nawo",
    "gn:population":0,
    "gn:timezone":"Asia/Karachi",
    "iso:country":"PK",
    "name:und_x_variant":[
        "Zar Khel",
        "Zarkhel Nawo",
        "Zarkhel Nau"
    ],
    "wof:name":"Zarkhel Nawo",
    "wof:placetype":"locality"
},
  "geometry": {"coordinates":[68.68309000000001,28.11679],"type":"Point"}
}