{
  "type": "Feature",
  "properties": {
    "gn:admin1_code":"3",
    "gn:asciiname":"Tareri",
    "gn:country_code":"PK",
    "gn:dem":1765,
    "gn:feature_class":"P",
    "gn:feature_code":"PPL",
    "gn:name":"Tareri",
    "gn:population":0,
    "gn:timezone":"Asia/Karachi",
    "iso:country":"PK",
    "name:und_x_variant":[
        "Tarerai"
    ],
    "wof:name":"Tareri",
    "wof:placetype":"locality"
},
  "geometry": {"coordinates":[73.05308000000002,34.56436],"type":"Point"}
}