{
  "type": "Feature",
  "properties": {
    "gn:admin1_code":"3.0",
    "gn:asciiname":"Chatri",
    "gn:country_code":"PK",
    "gn:dem":1211,
    "gn:feature_class":"P",
    "gn:feature_code":"PPL",
    "gn:name":"Chatri",
    "gn:population":0,
    "gn:timezone":"Asia/Karachi",
    "iso:country":"PK",
    "wof:name":"Chatri",
    "wof:placetype":"locality"
},
  "geometry": {"coordinates":[73.40058000000001,35.49103],"type":"Point"}
}