{
  "type": "Feature",
  "properties": {
    "gn:admin1_code":"6.0",
    "gn:asciiname":"Ai",
    "gn:country_code":"PK",
    "gn:dem":331,
    "gn:feature_class":"P",
    "gn:feature_code":"PPL",
    "gn:name":"Ai",
    "gn:population":0,
    "gn:timezone":"Asia/Karachi",
    "iso:country":"PK",
    "name:est_x_preferred":[
        "Ai"
    ],
    "name:eus_x_preferred":[
        "Ai"
    ],
    "name:swe_x_preferred":[
        "Ai"
    ],
    "name:und_x_variant":[
        "\u0100hi"
    ],
    "wof:name":"Ai",
    "wof:placetype":"locality"
},
  "geometry": {"coordinates":[74.23966999999998,32.84974],"type":"Point"}
}