{
  "type": "Feature",
  "properties": {
    "gn:admin1_code":"5.0",
    "gn:asciiname":"Goth Bachal Ahmadani",
    "gn:country_code":"PK",
    "gn:dem":6,
    "gn:feature_class":"P",
    "gn:feature_code":"PPL",
    "gn:name":"Goth Bachal Ahmadani",
    "gn:population":0,
    "gn:timezone":"Asia/Karachi",
    "iso:country":"PK",
    "name:und_x_variant":[
        "Bachhal \u0100md\u0101ni"
    ],
    "wof:name":"Goth Bachal Ahmadani",
    "wof:placetype":"locality"
},
  "geometry": {"coordinates":[69.14995,24.68681],"type":"Point"}
}