{
  "type": "Feature",
  "properties": {
    "gn:admin1_code":"2.0",
    "gn:asciiname":"Nur Muhammad Gis",
    "gn:country_code":"PK",
    "gn:dem":1513,
    "gn:feature_class":"P",
    "gn:feature_code":"PPL",
    "gn:name":"Nur Muhammad Gis",
    "gn:population":0,
    "gn:timezone":"Asia/Karachi",
    "iso:country":"PK",
    "wof:name":"Nur Muhammad Gis",
    "wof:placetype":"locality"
},
  "geometry": {"coordinates":[64.0069,29.3196],"type":"Point"}
}