{
  "type": "Feature",
  "properties": {
    "gn:admin1_code":"3.0",
    "gn:asciiname":"Sheikh Allah Din",
    "gn:country_code":"PK",
    "gn:dem":668,
    "gn:feature_class":"P",
    "gn:feature_code":"PPL",
    "gn:name":"Sheikh Allah Din",
    "gn:population":0,
    "gn:timezone":"Asia/Karachi",
    "iso:country":"PK",
    "wof:name":"Sheikh Allah Din",
    "wof:placetype":"locality"
},
  "geometry": {"coordinates":[71.16974999999999,33.35494],"type":"Point"}
}