{
  "type": "Feature",
  "properties": {
    "gn:admin1_code":"2.0",
    "gn:asciiname":"Adorah",
    "gn:country_code":"PK",
    "gn:dem":2246,
    "gn:feature_class":"P",
    "gn:feature_code":"PPL",
    "gn:name":"Adorah",
    "gn:population":0,
    "gn:timezone":"Asia/Karachi",
    "iso:country":"PK",
    "name:eng_x_preferred":[
        "Adori"
    ],
    "wof:name":"Adorah",
    "wof:placetype":"locality"
},
  "geometry": {"coordinates":[67.19748,30.93419],"type":"Point"}
}