{
  "type": "Feature",
  "properties": {
    "gn:admin1_code":"4.0",
    "gn:asciiname":"Dera Muhammad Nawaz",
    "gn:country_code":"PK",
    "gn:dem":349,
    "gn:feature_class":"P",
    "gn:feature_code":"PPL",
    "gn:name":"Dera Muhammad Nawaz",
    "gn:population":0,
    "gn:timezone":"Asia/Karachi",
    "iso:country":"PK",
    "wof:name":"Dera Muhammad Nawaz",
    "wof:placetype":"locality"
},
  "geometry": {"coordinates":[71.83229,32.91322],"type":"Point"}
}