{
  "type": "Feature",
  "properties": {
    "gn:admin1_code":"2.0",
    "gn:asciiname":"Nazir Ahmed Bazar",
    "gn:country_code":"PK",
    "gn:dem":1009,
    "gn:feature_class":"P",
    "gn:feature_code":"PPL",
    "gn:name":"Nazir Ahmed Bazar",
    "gn:population":0,
    "gn:timezone":"Asia/Karachi",
    "iso:country":"PK",
    "wof:name":"Nazir Ahmed Bazar",
    "wof:placetype":"locality"
},
  "geometry": {"coordinates":[64.23926999999999,26.77518],"type":"Point"}
}