{
  "type": "Feature",
  "properties": {
    "gn:admin1_code":"03",
    "gn:asciiname":"Gor",
    "gn:country_code":"PK",
    "gn:dem":1216,
    "gn:feature_class":"P",
    "gn:feature_code":"PPL",
    "gn:name":"Gor",
    "gn:population":0,
    "gn:timezone":"Asia/Karachi",
    "iso:country":"PK",
    "name:eng_x_preferred":[
        "Gor"
    ],
    "name:nld_x_preferred":[
        "Gor"
    ],
    "name:ron_x_preferred":[
        "Gor"
    ],
    "name:rus_x_preferred":[
        "\u0413\u043e\u0440"
    ],
    "name:tur_x_preferred":[
        "Gor"
    ],
    "name:ukr_x_preferred":[
        "\u0413\u043e\u0440"
    ],
    "name:zho_x_preferred":[
        "Gor"
    ],
    "wof:name":"Gor",
    "wof:placetype":"locality"
},
  "geometry": {"coordinates":[71.79724,34.99692],"type":"Point"}
}