{
  "type": "Feature",
  "properties": {
    "gn:admin1_code":"1.0",
    "gn:asciiname":"Aipai",
    "gn:country_code":"PK",
    "gn:dem":1790,
    "gn:feature_class":"P",
    "gn:feature_code":"PPL",
    "gn:name":"Aipai",
    "gn:population":0,
    "gn:timezone":"Asia/Karachi",
    "iso:country":"PK",
    "name:und_x_variant":[
        "A\u012bpai"
    ],
    "wof:name":"Aipai",
    "wof:placetype":"locality"
},
  "geometry": {"coordinates":[70.40529000000002,33.81231],"type":"Point"}
}