{
  "type": "Feature",
  "properties": {
    "gn:admin1_code":"5.0",
    "gn:asciiname":"Sumar Magsi Goth",
    "gn:country_code":"PK",
    "gn:dem":13,
    "gn:feature_class":"P",
    "gn:feature_code":"PPL",
    "gn:name":"Sumar Magsi Goth",
    "gn:population":0,
    "gn:timezone":"Asia/Karachi",
    "iso:country":"PK",
    "wof:name":"Sumar Magsi Goth",
    "wof:placetype":"locality"
},
  "geometry": {"coordinates":[67.94783000000001,24.79189],"type":"Point"}
}