{
  "type": "Feature",
  "properties": {
    "gn:admin1_code":"1.0",
    "gn:asciiname":"Regu",
    "gn:country_code":"PK",
    "gn:dem":1895,
    "gn:feature_class":"P",
    "gn:feature_code":"PPL",
    "gn:name":"Regu",
    "gn:population":0,
    "gn:timezone":"Asia/Karachi",
    "iso:country":"PK",
    "name:und_x_variant":[
        "Rego"
    ],
    "wof:name":"Regu",
    "wof:placetype":"locality"
},
  "geometry": {"coordinates":[70.41628,33.82696],"type":"Point"}
}