{
  "type": "Feature",
  "properties": {
    "gn:admin1_code":"5.0",
    "gn:asciiname":"Goth Barkat Ali Pundabi",
    "gn:country_code":"PK",
    "gn:dem":23,
    "gn:feature_class":"P",
    "gn:feature_code":"PPL",
    "gn:name":"Goth Barkat Ali Pundabi",
    "gn:population":0,
    "gn:timezone":"Asia/Karachi",
    "iso:country":"PK",
    "wof:name":"Goth Barkat Ali Pundabi",
    "wof:placetype":"locality"
},
  "geometry": {"coordinates":[69.09441,26.05134],"type":"Point"}
}