{
  "type": "Feature",
  "properties": {
    "gn:admin1_code":"4",
    "gn:asciiname":"Mouazam Khelanwala",
    "gn:country_code":"PK",
    "gn:dem":206,
    "gn:feature_class":"P",
    "gn:feature_code":"PPL",
    "gn:name":"Mouazam Khelanwala",
    "gn:population":0,
    "gn:timezone":"Asia/Karachi",
    "iso:country":"PK",
    "name:und_x_variant":[
        "Moazzam Khel\u0101nw\u0101la"
    ],
    "wof:name":"Mouazam Khelanwala",
    "wof:placetype":"locality"
},
  "geometry": {"coordinates":[71.72887,32.45713],"type":"Point"}
}