{
  "type": "Feature",
  "properties": {
    "gn:admin1_code":"6.0",
    "gn:asciiname":"Rawali",
    "gn:country_code":"PK",
    "gn:dem":1767,
    "gn:feature_class":"P",
    "gn:feature_code":"PPL",
    "gn:name":"Rawali",
    "gn:population":0,
    "gn:timezone":"Asia/Karachi",
    "iso:country":"PK",
    "wof:name":"Rawali",
    "wof:placetype":"locality"
},
  "geometry": {"coordinates":[73.84873,33.67838],"type":"Point"}
}