{
  "type": "Feature",
  "properties": {
    "gn:admin1_code":"4",
    "gn:asciiname":"Machhiwala",
    "gn:country_code":"PK",
    "gn:dem":158,
    "gn:feature_class":"P",
    "gn:feature_code":"PPL",
    "gn:name":"Machhiwala",
    "gn:population":0,
    "gn:timezone":"Asia/Karachi",
    "iso:country":"PK",
    "name:und_x_variant":[
        "M\u0101ch\u012bw\u0101la"
    ],
    "wof:name":"Machhiwala",
    "wof:placetype":"locality"
},
  "geometry": {"coordinates":[71.58723000000001,31.27687],"type":"Point"}
}