{
  "type": "Feature",
  "properties": {
    "gn:admin1_code":"5",
    "gn:asciiname":"Phalio Samijo",
    "gn:country_code":"PK",
    "gn:dem":63,
    "gn:feature_class":"P",
    "gn:feature_code":"PPL",
    "gn:name":"Phalio Samijo",
    "gn:population":0,
    "gn:timezone":"Asia/Karachi",
    "iso:country":"PK",
    "name:und_x_variant":[
        "Phul S\u0101w\u0101n"
    ],
    "wof:name":"Phalio Samijo",
    "wof:placetype":"locality"
},
  "geometry": {"coordinates":[68.90785,28.18227000000001],"type":"Point"}
}