{
  "type": "Feature",
  "properties": {
    "gn:admin1_code":"1.0",
    "gn:asciiname":"Nasir Khan Kalle",
    "gn:country_code":"PK",
    "gn:dem":994,
    "gn:feature_class":"P",
    "gn:feature_code":"PPL",
    "gn:name":"Nasir Khan Kalle",
    "gn:population":0,
    "gn:timezone":"Asia/Karachi",
    "iso:country":"PK",
    "wof:name":"Nasir Khan Kalle",
    "wof:placetype":"locality"
},
  "geometry": {"coordinates":[70.33691999999999,33.3008],"type":"Point"}
}