{
  "type": "Feature",
  "properties": {
    "gn:admin1_code":"5",
    "gn:asciiname":"Goth Messu Sangi",
    "gn:country_code":"PK",
    "gn:dem":67,
    "gn:feature_class":"P",
    "gn:feature_code":"PPL",
    "gn:name":"Goth Messu Sangi",
    "gn:population":0,
    "gn:timezone":"Asia/Karachi",
    "iso:country":"PK",
    "name:und_x_variant":[
        "S\u0101ngi Goth"
    ],
    "wof:name":"Goth Messu Sangi",
    "wof:placetype":"locality"
},
  "geometry": {"coordinates":[69.19901,27.88051],"type":"Point"}
}