{
  "type": "Feature",
  "properties": {
    "gn:admin1_code":"4.0",
    "gn:asciiname":"Basti Ghulam Qadir",
    "gn:country_code":"PK",
    "gn:dem":95,
    "gn:feature_class":"P",
    "gn:feature_code":"PPL",
    "gn:name":"Basti Ghulam Qadir",
    "gn:population":0,
    "gn:timezone":"Asia/Karachi",
    "iso:country":"PK",
    "name:und_x_variant":[
        "Basti Lubh\u0101na"
    ],
    "wof:name":"Basti Ghulam Qadir",
    "wof:placetype":"locality"
},
  "geometry": {"coordinates":[70.93543000000003,29.03175],"type":"Point"}
}