{
  "type": "Feature",
  "properties": {
    "gn:admin1_code":"5",
    "gn:asciiname":"Lal Bakhsh Mir Bahar",
    "gn:country_code":"PK",
    "gn:dem":61,
    "gn:feature_class":"P",
    "gn:feature_code":"PPL",
    "gn:name":"Lal Bakhsh Mir Bahar",
    "gn:population":0,
    "gn:timezone":"Asia/Karachi",
    "iso:country":"PK",
    "wof:name":"Lal Bakhsh Mir Bahar",
    "wof:placetype":"locality"
},
  "geometry": {"coordinates":[68.99104,27.60882],"type":"Point"}
}