{
  "type": "Feature",
  "properties": {
    "gn:admin1_code":"4",
    "gn:asciiname":"Sattoke",
    "gn:country_code":"PK",
    "gn:dem":235,
    "gn:feature_class":"P",
    "gn:feature_code":"PPL",
    "gn:name":"Sattoke",
    "gn:population":0,
    "gn:timezone":"Asia/Karachi",
    "iso:country":"PK",
    "wof:name":"Sattoke",
    "wof:placetype":"locality"
},
  "geometry": {"coordinates":[74.47739,32.29512],"type":"Point"}
}