{
  "type": "Feature",
  "properties": {
    "gn:admin1_code":"6",
    "gn:asciiname":"Khappi",
    "gn:country_code":"PK",
    "gn:dem":2712,
    "gn:feature_class":"P",
    "gn:feature_code":"PPL",
    "gn:name":"Khappi",
    "gn:population":0,
    "gn:timezone":"Asia/Karachi",
    "iso:country":"PK",
    "wof:name":"Khappi",
    "wof:placetype":"locality"
},
  "geometry": {"coordinates":[73.91164000000001,34.33335],"type":"Point"}
}