{
  "type": "Feature",
  "properties": {
    "gn:admin1_code":"2.0",
    "gn:asciiname":"Damb Bazar",
    "gn:country_code":"PK",
    "gn:dem":518,
    "gn:feature_class":"P",
    "gn:feature_code":"PPL",
    "gn:name":"Damb Bazar",
    "gn:population":0,
    "gn:timezone":"Asia/Karachi",
    "iso:country":"PK",
    "name:und_x_variant":[
        "D\u016bmag"
    ],
    "wof:name":"Damb Bazar",
    "wof:placetype":"locality"
},
  "geometry": {"coordinates":[63.89228000000001,25.9995],"type":"Point"}
}