{
  "type": "Feature",
  "properties": {
    "gn:admin1_code":"3",
    "gn:asciiname":"Jabarbat",
    "gn:country_code":"PK",
    "gn:dem":1039,
    "gn:feature_class":"P",
    "gn:feature_code":"PPL",
    "gn:name":"Jabarbat",
    "gn:population":0,
    "gn:timezone":"Asia/Karachi",
    "iso:country":"PK",
    "name:und_x_variant":[
        "Chaparbat B\u0101nda"
    ],
    "wof:name":"Jabarbat",
    "wof:placetype":"locality"
},
  "geometry": {"coordinates":[72.39914,34.63982],"type":"Point"}
}