{
  "type": "Feature",
  "properties": {
    "gn:admin1_code":"2.0",
    "gn:asciiname":"Khair Muhammad Takri",
    "gn:country_code":"PK",
    "gn:dem":1504,
    "gn:feature_class":"P",
    "gn:feature_code":"PPL",
    "gn:name":"Khair Muhammad Takri",
    "gn:population":0,
    "gn:timezone":"Asia/Karachi",
    "iso:country":"PK",
    "wof:name":"Khair Muhammad Takri",
    "wof:placetype":"locality"
},
  "geometry": {"coordinates":[66.32196,28.0076],"type":"Point"}
}