{
  "type": "Feature",
  "properties": {
    "gn:admin1_code":"6",
    "gn:asciiname":"Sarsala",
    "gn:country_code":"PK",
    "gn:dem":630,
    "gn:feature_class":"P",
    "gn:feature_code":"PPL",
    "gn:name":"Sarsala",
    "gn:population":0,
    "gn:timezone":"Asia/Karachi",
    "iso:country":"PK",
    "wof:name":"Sarsala",
    "wof:placetype":"locality"
},
  "geometry": {"coordinates":[74.11162,33.1037],"type":"Point"}
}