{
  "type": "Feature",
  "properties": {
    "gn:admin1_code":"5.0",
    "gn:asciiname":"Ranjho Chandio",
    "gn:country_code":"PK",
    "gn:dem":35,
    "gn:feature_class":"P",
    "gn:feature_code":"PPL",
    "gn:name":"Ranjho Chandio",
    "gn:population":0,
    "gn:timezone":"Asia/Karachi",
    "iso:country":"PK",
    "name:und_x_variant":[
        "R\u0101niho Ch\u0101ndio"
    ],
    "wof:name":"Ranjho Chandio",
    "wof:placetype":"locality"
},
  "geometry": {"coordinates":[68.1729,26.41962],"type":"Point"}
}