{
  "type": "Feature",
  "properties": {
    "gn:admin1_code":"4.0",
    "gn:asciiname":"Sokho Khund",
    "gn:country_code":"PK",
    "gn:dem":1132,
    "gn:feature_class":"P",
    "gn:feature_code":"PPL",
    "gn:name":"Sokho Khund",
    "gn:population":0,
    "gn:timezone":"Asia/Karachi",
    "iso:country":"PK",
    "wof:name":"Sokho Khund",
    "wof:placetype":"locality"
},
  "geometry": {"coordinates":[70.05634000000001,30.33852000000001],"type":"Point"}
}