{
  "type": "Feature",
  "properties": {
    "gn:admin1_code":"5.0",
    "gn:asciiname":"Goth Mazzor Khan",
    "gn:country_code":"PK",
    "gn:dem":59,
    "gn:feature_class":"P",
    "gn:feature_code":"PPL",
    "gn:name":"Goth Mazzor Khan",
    "gn:population":0,
    "gn:timezone":"Asia/Karachi",
    "iso:country":"PK",
    "name:und_x_variant":[
        "Goth Maz\u0101r Jokhio"
    ],
    "wof:name":"Goth Mazzor Khan",
    "wof:placetype":"locality"
},
  "geometry": {"coordinates":[67.31709000000001,24.92142],"type":"Point"}
}