{
  "type": "Feature",
  "properties": {
    "gn:admin1_code":"4.0",
    "gn:asciiname":"Eidil ki Lokri",
    "gn:country_code":"PK",
    "gn:dem":216,
    "gn:feature_class":"P",
    "gn:feature_code":"PPL",
    "gn:name":"Eidil ki Lokri",
    "gn:population":0,
    "gn:timezone":"Asia/Karachi",
    "iso:country":"PK",
    "wof:name":"Eidil ki Lokri",
    "wof:placetype":"locality"
},
  "geometry": {"coordinates":[73.36091999999999,32.46941],"type":"Point"}
}