{
  "type": "Feature",
  "properties": {
    "gn:admin1_code":"6",
    "gn:asciiname":"Tarkhan Bandi",
    "gn:country_code":"PK",
    "gn:dem":1250,
    "gn:feature_class":"P",
    "gn:feature_code":"PPL",
    "gn:name":"Tarkhan Bandi",
    "gn:population":0,
    "gn:timezone":"Asia/Karachi",
    "iso:country":"PK",
    "name:und_x_variant":[
        "Narhotar"
    ],
    "wof:name":"Tarkhan Bandi",
    "wof:placetype":"locality"
},
  "geometry": {"coordinates":[73.47225999999998,34.44209],"type":"Point"}
}