{
  "type": "Feature",
  "properties": {
    "gn:admin1_code":"7.0",
    "gn:asciiname":"Akalo Chhich",
    "gn:country_code":"PK",
    "gn:dem":3225,
    "gn:feature_class":"P",
    "gn:feature_code":"PPL",
    "gn:name":"Akalo Chhich",
    "gn:population":0,
    "gn:timezone":"Asia/Karachi",
    "iso:country":"PK",
    "wof:name":"Akalo Chhich",
    "wof:placetype":"locality"
},
  "geometry": {"coordinates":[75.03923,35.22787],"type":"Point"}
}