{
  "type": "Feature",
  "properties": {
    "gn:admin1_code":"4.0",
    "gn:asciiname":"Jam Ali Muhammad Kallar",
    "gn:country_code":"PK",
    "gn:dem":87,
    "gn:feature_class":"P",
    "gn:feature_code":"PPL",
    "gn:name":"Jam Ali Muhammad Kallar",
    "gn:population":0,
    "gn:timezone":"Asia/Karachi",
    "iso:country":"PK",
    "name:und_x_variant":[
        "Jam Ali Muhammad"
    ],
    "wof:name":"Jam Ali Muhammad Kallar",
    "wof:placetype":"locality"
},
  "geometry": {"coordinates":[70.40845999999998,28.68537],"type":"Point"}
}