{
  "type": "Feature",
  "properties": {
    "gn:admin1_code":"4",
    "gn:asciiname":"Kotli Kandu",
    "gn:country_code":"PK",
    "gn:dem":232,
    "gn:feature_class":"P",
    "gn:feature_code":"PPL",
    "gn:name":"Kotli Kandu",
    "gn:population":0,
    "gn:timezone":"Asia/Karachi",
    "iso:country":"PK",
    "name:und_x_variant":[
        "Kotli"
    ],
    "wof:name":"Kotli Kandu",
    "wof:placetype":"locality"
},
  "geometry": {"coordinates":[74.11008000000002,32.55723],"type":"Point"}
}