{
  "type": "Feature",
  "properties": {
    "gn:admin1_code":"2.0",
    "gn:asciiname":"Kili Niam Bela",
    "gn:country_code":"PK",
    "gn:dem":909,
    "gn:feature_class":"P",
    "gn:feature_code":"PPL",
    "gn:name":"Kili Niam Bela",
    "gn:population":0,
    "gn:timezone":"Asia/Karachi",
    "iso:country":"PK",
    "name:und_x_variant":[
        "Baghak Killi",
        "B\u0101ghak",
        "Kili Niam Bela"
    ],
    "wof:name":"Kili Niam Bela",
    "wof:placetype":"locality"
},
  "geometry": {"coordinates":[65.9384,29.44043],"type":"Point"}
}