{
  "type": "Feature",
  "properties": {
    "gn:admin1_code":"4",
    "gn:asciiname":"Islampura",
    "gn:country_code":"PK",
    "gn:dem":185,
    "gn:feature_class":"P",
    "gn:feature_code":"PPL",
    "gn:name":"Isl\u0101mpura",
    "gn:population":0,
    "gn:timezone":"Asia/Karachi",
    "iso:country":"PK",
    "name:hin_x_preferred":[
        "\u0907\u0938\u094d\u0932\u093e\u092e\u092a\u0941\u0930\u093e"
    ],
    "name:urd_x_preferred":[
        "\u0627\u0633\u0644\u0627\u0645 \u067e\u0648\u0631\u06c1"
    ],
    "wof:name":"Islampura",
    "wof:placetype":"locality"
},
  "geometry": {"coordinates":[73.50417,31.24444],"type":"Point"}
}