{
  "type": "Feature",
  "properties": {
    "gn:admin1_code":"4",
    "gn:asciiname":"Islampura",
    "gn:country_code":"PK",
    "gn:dem":185,
    "gn:feature_class":"P",
    "gn:feature_code":"PPL",
    "gn:name":"Isl\u0101mpura",
    "gn:population":0,
    "gn:timezone":"Asia/Karachi",
    "iso:country":"PK",
    "wof:name":"Islampura",
    "wof:placetype":"locality"
},
  "geometry": {"coordinates":[73.50417,31.24444],"type":"Point"}
}