{
  "type": "Feature",
  "properties": {
    "gn:admin1_code":"2.0",
    "gn:asciiname":"Kili Ali Ian",
    "gn:country_code":"PK",
    "gn:dem":618,
    "gn:feature_class":"P",
    "gn:feature_code":"PPL",
    "gn:name":"Kili Ali Ian",
    "gn:population":0,
    "gn:timezone":"Asia/Karachi",
    "iso:country":"PK",
    "wof:name":"Kili Ali Ian",
    "wof:placetype":"locality"
},
  "geometry": {"coordinates":[64.4999,28.33118],"type":"Point"}
}