{
  "type": "Feature",
  "properties": {
    "gn:admin1_code":"4",
    "gn:asciiname":"Changranwala",
    "gn:country_code":"PK",
    "gn:dem":193,
    "gn:feature_class":"P",
    "gn:feature_code":"PPL",
    "gn:name":"Changranwala",
    "gn:population":0,
    "gn:timezone":"Asia/Karachi",
    "iso:country":"PK",
    "name:und_x_variant":[
        "Changar\u0101nw\u0101la"
    ],
    "wof:name":"Changranwala",
    "wof:placetype":"locality"
},
  "geometry": {"coordinates":[71.45063,32.13254000000001],"type":"Point"}
}