{
  "type": "Feature",
  "properties": {
    "gn:admin1_code":"5.0",
    "gn:asciiname":"Jhanda Khan Gadio",
    "gn:country_code":"PK",
    "gn:dem":44,
    "gn:feature_class":"P",
    "gn:feature_code":"PPL",
    "gn:name":"Jhanda Khan Gadio",
    "gn:population":0,
    "gn:timezone":"Asia/Karachi",
    "iso:country":"PK",
    "wof:name":"Jhanda Khan Gadio",
    "wof:placetype":"locality"
},
  "geometry": {"coordinates":[67.69136999999999,27.10186],"type":"Point"}
}