{
  "type": "Feature",
  "properties": {
    "gn:admin1_code":"6",
    "gn:asciiname":"Khhanian",
    "gn:country_code":"PK",
    "gn:dem":1427,
    "gn:feature_class":"P",
    "gn:feature_code":"PPL",
    "gn:name":"Khhanian",
    "gn:population":0,
    "gn:timezone":"Asia/Karachi",
    "iso:country":"PK",
    "name:und_x_variant":[
        "Khani\u0101n"
    ],
    "wof:name":"Khhanian",
    "wof:placetype":"locality"
},
  "geometry": {"coordinates":[73.48716,34.45417],"type":"Point"}
}