{
  "type": "Feature",
  "properties": {
    "gn:admin1_code":"2.0",
    "gn:asciiname":"Haji Muhammad Hasain",
    "gn:country_code":"PK",
    "gn:dem":1062,
    "gn:feature_class":"P",
    "gn:feature_code":"PPL",
    "gn:name":"Haji Muhammad Hasain",
    "gn:population":0,
    "gn:timezone":"Asia/Karachi",
    "iso:country":"PK",
    "wof:name":"Haji Muhammad Hasain",
    "wof:placetype":"locality"
},
  "geometry": {"coordinates":[64.34406,26.79804],"type":"Point"}
}