{
  "type": "Feature",
  "properties": {
    "gn:admin1_code":"4.0",
    "gn:asciiname":"Shahamidpur",
    "gn:country_code":"PK",
    "gn:dem":254,
    "gn:feature_class":"P",
    "gn:feature_code":"PPL",
    "gn:name":"Shahamidpur",
    "gn:population":0,
    "gn:timezone":"Asia/Karachi",
    "iso:country":"PK",
    "wof:name":"Shahamidpur",
    "wof:placetype":"locality"
},
  "geometry": {"coordinates":[73.56241999999997,32.97626],"type":"Point"}
}