{
  "type": "Feature",
  "properties": {
    "gn:admin1_code":"4",
    "gn:asciiname":"Basti Rindan",
    "gn:country_code":"PK",
    "gn:dem":99,
    "gn:feature_class":"P",
    "gn:feature_code":"PPL",
    "gn:name":"Basti Rindan",
    "gn:population":0,
    "gn:timezone":"Asia/Karachi",
    "iso:country":"PK",
    "name:und_x_variant":[
        "Basti R\u012bnd"
    ],
    "wof:name":"Basti Rindan",
    "wof:placetype":"locality"
},
  "geometry": {"coordinates":[70.88478000000001,29.28382],"type":"Point"}
}