{
  "type": "Feature",
  "properties": {
    "gn:admin1_code":"4",
    "gn:asciiname":"Basti Dadpotra",
    "gn:country_code":"PK",
    "gn:dem":110,
    "gn:feature_class":"P",
    "gn:feature_code":"PPL",
    "gn:name":"Basti Dadpotra",
    "gn:population":0,
    "gn:timezone":"Asia/Karachi",
    "iso:country":"PK",
    "name:und_x_variant":[
        "Basti D\u0101dpotre"
    ],
    "wof:name":"Basti Dadpotra",
    "wof:placetype":"locality"
},
  "geometry": {"coordinates":[71.44195000000001,29.23425],"type":"Point"}
}