{
  "type": "Feature",
  "properties": {
    "gn:admin1_code":"02",
    "gn:asciiname":"Saiyid",
    "gn:country_code":"PK",
    "gn:dem":1603,
    "gn:feature_class":"P",
    "gn:feature_code":"PPL",
    "gn:name":"Saiyid",
    "gn:population":0,
    "gn:timezone":"Asia/Karachi",
    "iso:country":"PK",
    "name:und_x_variant":[
        "Sayed Wal",
        "Saiyid"
    ],
    "wof:name":"Saiyid",
    "wof:placetype":"locality"
},
  "geometry": {"coordinates":[66.79380999999999,29.89863],"type":"Point"}
}