{
  "type": "Feature",
  "properties": {
    "gn:admin1_code":"5.0",
    "gn:asciiname":"Bhupe jo Tar",
    "gn:country_code":"PK",
    "gn:dem":70,
    "gn:feature_class":"P",
    "gn:feature_code":"PPL",
    "gn:name":"Bhupe jo Tar",
    "gn:population":0,
    "gn:timezone":"Asia/Karachi",
    "iso:country":"PK",
    "name:und_x_variant":[
        "Bh\u016bpe ro Tar"
    ],
    "wof:name":"Bhupe jo Tar",
    "wof:placetype":"locality"
},
  "geometry": {"coordinates":[70.10701999999999,24.84178],"type":"Point"}
}