{
  "type": "Feature",
  "properties": {
    "gn:admin1_code":"4.0",
    "gn:asciiname":"Hayat Muhammadwala",
    "gn:country_code":"PK",
    "gn:dem":168,
    "gn:feature_class":"P",
    "gn:feature_code":"PPL",
    "gn:name":"Hay\u0101t Muhammadw\u0101la",
    "gn:population":0,
    "gn:timezone":"Asia/Karachi",
    "iso:country":"PK",
    "wof:name":"Hayat Muhammadwala",
    "wof:placetype":"locality"
},
  "geometry": {"coordinates":[71.32214,31.58761],"type":"Point"}
}