{
  "type": "Feature",
  "properties": {
    "gn:admin1_code":"6",
    "gn:asciiname":"Dharmsai",
    "gn:country_code":"PK",
    "gn:dem":802,
    "gn:feature_class":"P",
    "gn:feature_code":"PPL",
    "gn:name":"Dharmsai",
    "gn:population":0,
    "gn:timezone":"Asia/Karachi",
    "iso:country":"PK",
    "wof:name":"Dharmsai",
    "wof:placetype":"locality"
},
  "geometry": {"coordinates":[73.95555999999998,33.72153],"type":"Point"}
}