{
  "type": "Feature",
  "properties": {
    "gn:admin1_code":"7.0",
    "gn:asciiname":"Lulsum",
    "gn:country_code":"PK",
    "gn:dem":2326,
    "gn:feature_class":"P",
    "gn:feature_code":"PPL",
    "gn:name":"Lulsum",
    "gn:population":0,
    "gn:timezone":"Asia/Karachi",
    "iso:country":"PK",
    "wof:name":"Lulsum",
    "wof:placetype":"locality"
},
  "geometry": {"coordinates":[74.15645000000001,35.31002],"type":"Point"}
}