{
  "type": "Feature",
  "properties": {
    "gn:admin1_code":"4",
    "gn:asciiname":"Chak Six Hundred Thirty-three Gogera Branch",
    "gn:country_code":"PK",
    "gn:dem":188,
    "gn:feature_class":"P",
    "gn:feature_code":"PPL",
    "gn:name":"Chak Six Hundred Thirty-three Gogera Branch",
    "gn:population":0,
    "gn:timezone":"Asia/Karachi",
    "iso:country":"PK",
    "name:und_x_variant":[
        "Ganeshpura"
    ],
    "wof:name":"Chak Six Hundred Thirty-three Gogera Branch",
    "wof:placetype":"locality"
},
  "geometry": {"coordinates":[73.48905999999999,31.21758],"type":"Point"}
}