{
  "type": "Feature",
  "properties": {
    "gn:admin1_code":"2.0",
    "gn:asciiname":"Marav Khand",
    "gn:country_code":"PK",
    "gn:dem":1773,
    "gn:feature_class":"P",
    "gn:feature_code":"PPL",
    "gn:name":"Marav Khand",
    "gn:population":0,
    "gn:timezone":"Asia/Karachi",
    "iso:country":"PK",
    "wof:name":"Marav Khand",
    "wof:placetype":"locality"
},
  "geometry": {"coordinates":[67.03806,29.68592],"type":"Point"}
}