{
  "type": "Feature",
  "properties": {
    "gn:admin1_code":"4.0",
    "gn:asciiname":"Topa Adam",
    "gn:country_code":"PK",
    "gn:dem":232,
    "gn:feature_class":"P",
    "gn:feature_code":"PPL",
    "gn:name":"Topa Adam",
    "gn:population":0,
    "gn:timezone":"Asia/Karachi",
    "iso:country":"PK",
    "wof:name":"Topa Adam",
    "wof:placetype":"locality"
},
  "geometry": {"coordinates":[73.84246999999998,32.61394],"type":"Point"}
}