{
  "type": "Feature",
  "properties": {
    "gn:admin1_code":"5.0",
    "gn:asciiname":"Goth Khan Muhammad",
    "gn:country_code":"PK",
    "gn:dem":8,
    "gn:feature_class":"P",
    "gn:feature_code":"PPL",
    "gn:name":"Goth Kh\u0101n Muhammad",
    "gn:population":0,
    "gn:timezone":"Asia/Karachi",
    "iso:country":"PK",
    "wof:name":"Goth Khan Muhammad",
    "wof:placetype":"locality"
},
  "geometry": {"coordinates":[67.78944,24.57861],"type":"Point"}
}