{
  "type": "Feature",
  "properties": {
    "gn:admin1_code":"3",
    "gn:asciiname":"Moga",
    "gn:country_code":"PK",
    "gn:dem":192,
    "gn:feature_class":"P",
    "gn:feature_code":"PPL",
    "gn:name":"Moga",
    "gn:population":0,
    "gn:timezone":"Asia/Karachi",
    "iso:country":"PK",
    "name:ceb_x_preferred":[
        "Moga"
    ],
    "name:deu_x_preferred":[
        "Moga"
    ],
    "name:nld_x_preferred":[
        "Moga"
    ],
    "name:pnb_x_preferred":[
        "\u0645\u0648\u06af\u0627"
    ],
    "name:rus_x_preferred":[
        "\u041c\u043e\u0433\u0430"
    ],
    "name:swe_x_preferred":[
        "Moga"
    ],
    "wof:name":"Moga",
    "wof:placetype":"locality"
},
  "geometry": {"coordinates":[70.56034,31.56866],"type":"Point"}
}