{
  "type": "Feature",
  "properties": {
    "gn:admin1_code":"2.0",
    "gn:asciiname":"Tal",
    "gn:country_code":"PK",
    "gn:dem":1761,
    "gn:feature_class":"P",
    "gn:feature_code":"PPL",
    "gn:name":"Tal",
    "gn:population":0,
    "gn:timezone":"Asia/Karachi",
    "iso:country":"PK",
    "wof:name":"Tal",
    "wof:placetype":"locality"
},
  "geometry": {"coordinates":[69.60435,31.22507],"type":"Point"}
}