{
  "type": "Feature",
  "properties": {
    "gn:admin1_code":"4",
    "gn:asciiname":"Sohlewali",
    "gn:country_code":"PK",
    "gn:dem":505,
    "gn:feature_class":"P",
    "gn:feature_code":"PPL",
    "gn:name":"Sohlewali",
    "gn:population":0,
    "gn:timezone":"Asia/Karachi",
    "iso:country":"PK",
    "name:und_x_variant":[
        "Sukhaw\u0101li"
    ],
    "wof:name":"Sohlewali",
    "wof:placetype":"locality"
},
  "geometry": {"coordinates":[72.17104999999999,32.82126],"type":"Point"}
}