{
  "type": "Feature",
  "properties": {
    "gn:admin1_code":"5",
    "gn:asciiname":"Ghulam Haider Jamali",
    "gn:country_code":"PK",
    "gn:dem":12,
    "gn:feature_class":"P",
    "gn:feature_code":"PPL",
    "gn:name":"Ghulam Haider Jamali",
    "gn:population":0,
    "gn:timezone":"Asia/Karachi",
    "iso:country":"PK",
    "name:und_x_variant":[
        "Ghul\u0101m Haidar",
        "Ghul\u0101m Haidar Jam\u0101li",
        "Ghulam Haider Jamali"
    ],
    "wof:name":"Ghulam Haider Jamali",
    "wof:placetype":"locality"
},
  "geometry": {"coordinates":[69.06601999999999,24.90483],"type":"Point"}
}