{
  "type": "Feature",
  "properties": {
    "gn:admin1_code":"4.0",
    "gn:asciiname":"Bet Shahi Khan",
    "gn:country_code":"PK",
    "gn:dem":110,
    "gn:feature_class":"P",
    "gn:feature_code":"PPL",
    "gn:name":"Bet Shahi Khan",
    "gn:population":0,
    "gn:timezone":"Asia/Karachi",
    "iso:country":"PK",
    "name:und_x_variant":[
        "Bet Sh\u0101hal Kh\u0101n",
        "Bet Sh\u0101hl Kh\u0101n",
        "Bet Shahi Khan"
    ],
    "wof:name":"Bet Shahi Khan",
    "wof:placetype":"locality"
},
  "geometry": {"coordinates":[70.8454,29.63162],"type":"Point"}
}