{
  "type": "Feature",
  "properties": {
    "gn:admin1_code":"2.0",
    "gn:asciiname":"Mir Qalam",
    "gn:country_code":"PK",
    "gn:dem":1453,
    "gn:feature_class":"P",
    "gn:feature_code":"PPL",
    "gn:name":"Mir Qalam",
    "gn:population":0,
    "gn:timezone":"Asia/Karachi",
    "iso:country":"PK",
    "wof:name":"Mir Qalam",
    "wof:placetype":"locality"
},
  "geometry": {"coordinates":[66.60219000000001,30.55311],"type":"Point"}
}