{
  "type": "Feature",
  "properties": {
    "gn:admin1_code":"4.0",
    "gn:asciiname":"Musawerwala Khu",
    "gn:country_code":"PK",
    "gn:dem":140,
    "gn:feature_class":"P",
    "gn:feature_code":"PPL",
    "gn:name":"Musawerwala Khu",
    "gn:population":0,
    "gn:timezone":"Asia/Karachi",
    "iso:country":"PK",
    "wof:name":"Musawerwala Khu",
    "wof:placetype":"locality"
},
  "geometry": {"coordinates":[72.02786999999999,30.73863],"type":"Point"}
}