{
  "type": "Feature",
  "properties": {
    "gn:admin1_code":"3.0",
    "gn:asciiname":"Khanshai",
    "gn:country_code":"PK",
    "gn:dem":4022,
    "gn:feature_class":"P",
    "gn:feature_code":"PPL",
    "gn:name":"Khanshai",
    "gn:population":0,
    "gn:timezone":"Asia/Karachi",
    "iso:country":"PK",
    "wof:name":"Khanshai",
    "wof:placetype":"locality"
},
  "geometry": {"coordinates":[72.53899,35.60845],"type":"Point"}
}