{
  "type": "Feature",
  "properties": {
    "gn:admin1_code":"3",
    "gn:asciiname":"Aziz Dheri",
    "gn:country_code":"PK",
    "gn:dem":370,
    "gn:feature_class":"P",
    "gn:feature_code":"PPL",
    "gn:name":"Aziz Dheri",
    "gn:population":0,
    "gn:timezone":"Asia/Karachi",
    "iso:country":"PK",
    "name:eng_x_preferred":[
        "Aziz Dheri"
    ],
    "wof:name":"Aziz Dheri",
    "wof:placetype":"locality"
},
  "geometry": {"coordinates":[72.39135,34.24387],"type":"Point"}
}