{
  "type": "Feature",
  "properties": {
    "gn:admin1_code":"4.0",
    "gn:asciiname":"Bhikhiwand",
    "gn:country_code":"PK",
    "gn:dem":202,
    "gn:feature_class":"P",
    "gn:feature_code":"PPL",
    "gn:name":"Bhikhiwand",
    "gn:population":0,
    "gn:timezone":"Asia/Kolkata",
    "iso:country":"PK",
    "name:und_x_variant":[
        "Bhikhi Wind Hithhar",
        "Bhikhiwind",
        "Bhikk\u012bwind Hith\u0101r",
        "Bhikhiwand"
    ],
    "wof:name":"Bhikhiwand",
    "wof:placetype":"locality"
},
  "geometry": {"coordinates":[74.57925999999998,31.05802000000001],"type":"Point"}
}