{
  "type": "Feature",
  "properties": {
    "gn:admin1_code":"2.0",
    "gn:asciiname":"Khuda-i-Rahim",
    "gn:country_code":"PK",
    "gn:dem":1034,
    "gn:feature_class":"P",
    "gn:feature_code":"PPL",
    "gn:name":"Khuda-i-Rahim",
    "gn:population":0,
    "gn:timezone":"Asia/Karachi",
    "iso:country":"PK",
    "wof:name":"Khuda-i-Rahim",
    "wof:placetype":"locality"
},
  "geometry": {"coordinates":[63.89058000000001,29.06268],"type":"Point"}
}