{
  "type": "Feature",
  "properties": {
    "gn:admin1_code":"5.0",
    "gn:asciiname":"Otaq Wali Muhammad Dohat",
    "gn:country_code":"PK",
    "gn:dem":9,
    "gn:feature_class":"P",
    "gn:feature_code":"PPL",
    "gn:name":"Otaq Wali Muhammad Dohat",
    "gn:population":0,
    "gn:timezone":"Asia/Karachi",
    "iso:country":"PK",
    "wof:name":"Otaq Wali Muhammad Dohat",
    "wof:placetype":"locality"
},
  "geometry": {"coordinates":[69.32800999999999,24.74872],"type":"Point"}
}