{
  "type": "Feature",
  "properties": {
    "gn:admin1_code":"5",
    "gn:asciiname":"Goth Ghulan Mustafa Jatoi",
    "gn:country_code":"PK",
    "gn:dem":63,
    "gn:feature_class":"P",
    "gn:feature_code":"PPL",
    "gn:name":"Goth Ghulan Mustafa Jatoi",
    "gn:population":0,
    "gn:timezone":"Asia/Karachi",
    "iso:country":"PK",
    "name:und_x_variant":[
        "Gul Muhammad Faq\u012br jo Goth"
    ],
    "wof:name":"Goth Ghulan Mustafa Jatoi",
    "wof:placetype":"locality"
},
  "geometry": {"coordinates":[68.84009,27.68822],"type":"Point"}
}