{
  "type": "Feature",
  "properties": {
    "gn:admin1_code":"4.0",
    "gn:asciiname":"Doda Lar",
    "gn:country_code":"PK",
    "gn:dem":90,
    "gn:feature_class":"P",
    "gn:feature_code":"PPL",
    "gn:name":"Doda Lar",
    "gn:population":0,
    "gn:timezone":"Asia/Karachi",
    "iso:country":"PK",
    "name:urd_x_preferred":[
        "Doda Lar"
    ],
    "wof:name":"Doda Lar",
    "wof:placetype":"locality"
},
  "geometry": {"coordinates":[70.67886999999997,28.77357],"type":"Point"}
}