{
  "type": "Feature",
  "properties": {
    "gn:admin1_code":"4.0",
    "gn:asciiname":"Rati Dhandwala",
    "gn:country_code":"PK",
    "gn:dem":471,
    "gn:feature_class":"P",
    "gn:feature_code":"PPL",
    "gn:name":"Rati Dhandwala",
    "gn:population":0,
    "gn:timezone":"Asia/Karachi",
    "iso:country":"PK",
    "name:und_x_variant":[
        "Ratti Dand\u012bw\u0101li"
    ],
    "wof:name":"Rati Dhandwala",
    "wof:placetype":"locality"
},
  "geometry": {"coordinates":[71.99118,32.68734],"type":"Point"}
}