{
  "type": "Feature",
  "properties": {
    "gn:admin1_code":"4.0",
    "gn:asciiname":"Bagga Miana",
    "gn:country_code":"PK",
    "gn:dem":532,
    "gn:feature_class":"P",
    "gn:feature_code":"PPL",
    "gn:name":"Bagga Miana",
    "gn:population":0,
    "gn:timezone":"Asia/Karachi",
    "iso:country":"PK",
    "name:und_x_variant":[
        "Bagga Mi\u0101na"
    ],
    "wof:name":"Bagga Miana",
    "wof:placetype":"locality"
},
  "geometry": {"coordinates":[73.20504,33.44513],"type":"Point"}
}