{
  "type": "Feature",
  "properties": {
    "gn:admin1_code":"03",
    "gn:asciiname":"Kuz Kalle",
    "gn:country_code":"PK",
    "gn:dem":636,
    "gn:feature_class":"P",
    "gn:feature_code":"PPL",
    "gn:name":"Kuz Kalle",
    "gn:population":0,
    "gn:timezone":"Asia/Karachi",
    "iso:country":"PK",
    "name:und_x_variant":[
        "Kooz Kalai",
        "Kuz Kili",
        "K\u016bz Kalai",
        "Kuz Kalle"
    ],
    "wof:name":"Kuz Kalle",
    "wof:placetype":"locality"
},
  "geometry": {"coordinates":[72.66431999999998,34.42631],"type":"Point"}
}