{
  "type": "Feature",
  "properties": {
    "gn:admin1_code":"01",
    "gn:asciiname":"Kurambai",
    "gn:country_code":"PK",
    "gn:dem":2027,
    "gn:feature_class":"P",
    "gn:feature_code":"PPL",
    "gn:name":"Kurambai",
    "gn:population":0,
    "gn:timezone":"Asia/Karachi",
    "iso:country":"PK",
    "name:und_x_variant":[
        "Krumbai"
    ],
    "wof:name":"Kurambai",
    "wof:placetype":"locality"
},
  "geometry": {"coordinates":[70.67004,33.79494],"type":"Point"}
}