{
  "type": "Feature",
  "properties": {
    "gn:admin1_code":"5.0",
    "gn:asciiname":"Goth Agha Korai",
    "gn:country_code":"PK",
    "gn:dem":15,
    "gn:feature_class":"P",
    "gn:feature_code":"PPL",
    "gn:name":"Goth Agha Korai",
    "gn:population":0,
    "gn:timezone":"Asia/Karachi",
    "iso:country":"PK",
    "name:und_x_variant":[
        "Goth Agha Kalori"
    ],
    "wof:name":"Goth Agha Korai",
    "wof:placetype":"locality"
},
  "geometry": {"coordinates":[68.97126999999999,25.15828],"type":"Point"}
}