{
  "type": "Feature",
  "properties": {
    "gn:admin1_code":"3.0",
    "gn:asciiname":"Sarn",
    "gn:country_code":"PK",
    "gn:dem":3249,
    "gn:feature_class":"P",
    "gn:feature_code":"PPL",
    "gn:name":"Sarn",
    "gn:population":0,
    "gn:timezone":"Asia/Karachi",
    "iso:country":"PK",
    "name:bre_x_preferred":[
        "Sarn"
    ],
    "name:ceb_x_preferred":[
        "Sarn"
    ],
    "name:cym_x_preferred":[
        "Sarn"
    ],
    "name:fra_x_preferred":[
        "Sarn"
    ],
    "name:spa_x_preferred":[
        "Sarn"
    ],
    "name:swe_x_preferred":[
        "Sarn"
    ],
    "wof:name":"Sarn",
    "wof:placetype":"locality"
},
  "geometry": {"coordinates":[73.78494999999999,34.85117],"type":"Point"}
}