{
  "type": "Feature",
  "properties": {
    "gn:admin1_code":"5.0",
    "gn:asciiname":"Goth Haji Abdullah Halepota",
    "gn:country_code":"PK",
    "gn:dem":18,
    "gn:feature_class":"P",
    "gn:feature_code":"PPL",
    "gn:name":"Goth Haji Abdullah Halepota",
    "gn:population":0,
    "gn:timezone":"Asia/Karachi",
    "iso:country":"PK",
    "name:und_x_variant":[
        "Goth H\u0101ji Abdullah Halepoto",
        "Abdull\u0101h H\u0101lepoto"
    ],
    "wof:name":"Goth Haji Abdullah Halepota",
    "wof:placetype":"locality"
},
  "geometry": {"coordinates":[68.92057,25.24337],"type":"Point"}
}