{
  "type": "Feature",
  "properties": {
    "gn:admin1_code":"4",
    "gn:asciiname":"Thatta Isa",
    "gn:country_code":"PK",
    "gn:dem":194,
    "gn:feature_class":"P",
    "gn:feature_code":"PPL",
    "gn:name":"Thatta Isa",
    "gn:population":0,
    "gn:timezone":"Asia/Karachi",
    "iso:country":"PK",
    "name:und_x_variant":[
        "\u012asa ka Thatta"
    ],
    "wof:name":"Thatta Isa",
    "wof:placetype":"locality"
},
  "geometry": {"coordinates":[73.68434000000001,31.3784],"type":"Point"}
}