{
  "type": "Feature",
  "properties": {
    "gn:admin1_code":"4",
    "gn:asciiname":"Mangewali",
    "gn:country_code":"PK",
    "gn:dem":532,
    "gn:feature_class":"P",
    "gn:feature_code":"PPL",
    "gn:name":"Mangewali",
    "gn:population":0,
    "gn:timezone":"Asia/Karachi",
    "iso:country":"PK",
    "wof:name":"Mangewali",
    "wof:placetype":"locality"
},
  "geometry": {"coordinates":[72.0838,32.68541],"type":"Point"}
}