{
  "type": "Feature",
  "properties": {
    "gn:admin1_code":"4",
    "gn:asciiname":"Kallarwala",
    "gn:country_code":"PK",
    "gn:dem":167,
    "gn:feature_class":"P",
    "gn:feature_code":"PPL",
    "gn:name":"Kallarwala",
    "gn:population":0,
    "gn:timezone":"Asia/Karachi",
    "iso:country":"PK",
    "name:und_x_variant":[
        "Saiyid Jal\u0101l",
        "Sharqi"
    ],
    "wof:name":"Kallarwala",
    "wof:placetype":"locality"
},
  "geometry": {"coordinates":[72.56506999999998,31.47427],"type":"Point"}
}