{
  "type": "Feature",
  "properties": {
    "gn:admin1_code":"4",
    "gn:asciiname":"Bhopa Chadhar",
    "gn:country_code":"PK",
    "gn:dem":199,
    "gn:feature_class":"P",
    "gn:feature_code":"PPL",
    "gn:name":"Bhopa Chadhar",
    "gn:population":0,
    "gn:timezone":"Asia/Karachi",
    "iso:country":"PK",
    "name:und_x_variant":[
        "Bhopa"
    ],
    "wof:name":"Bhopa Chadhar",
    "wof:placetype":"locality"
},
  "geometry": {"coordinates":[73.49124999999999,32.08694000000001],"type":"Point"}
}