{
  "type": "Feature",
  "properties": {
    "gn:admin1_code":"3",
    "gn:asciiname":"Utreri",
    "gn:country_code":"PK",
    "gn:dem":1502,
    "gn:feature_class":"P",
    "gn:feature_code":"PPL",
    "gn:name":"Utreri",
    "gn:population":0,
    "gn:timezone":"Asia/Karachi",
    "iso:country":"PK",
    "wof:name":"Utreri",
    "wof:placetype":"locality"
},
  "geometry": {"coordinates":[73.37904,34.49675],"type":"Point"}
}