{
  "type": "Feature",
  "properties": {
    "gn:admin1_code":"2.0",
    "gn:asciiname":"Mulla Muhammad Rafique",
    "gn:country_code":"PK",
    "gn:dem":1105,
    "gn:feature_class":"P",
    "gn:feature_code":"PPL",
    "gn:name":"Mulla Muhammad Rafique",
    "gn:population":0,
    "gn:timezone":"Asia/Karachi",
    "iso:country":"PK",
    "wof:name":"Mulla Muhammad Rafique",
    "wof:placetype":"locality"
},
  "geometry": {"coordinates":[63.46502,29.1968],"type":"Point"}
}