{
  "type": "Feature",
  "properties": {
    "gn:admin1_code":"4",
    "gn:asciiname":"Pir Shahwala",
    "gn:country_code":"PK",
    "gn:dem":155,
    "gn:feature_class":"P",
    "gn:feature_code":"PPL",
    "gn:name":"Pir Shahwala",
    "gn:population":0,
    "gn:timezone":"Asia/Karachi",
    "iso:country":"PK",
    "name:und_x_variant":[
        "Bish\u0101rat Sh\u0101hw\u0101la"
    ],
    "wof:name":"Pir Shahwala",
    "wof:placetype":"locality"
},
  "geometry": {"coordinates":[71.42161,31.17154],"type":"Point"}
}