{
  "type": "Feature",
  "properties": {
    "gn:admin1_code":"1.0",
    "gn:asciiname":"Walidad",
    "gn:country_code":"PK",
    "gn:dem":1680,
    "gn:feature_class":"P",
    "gn:feature_code":"PPL",
    "gn:name":"Walidad",
    "gn:population":0,
    "gn:timezone":"Asia/Karachi",
    "iso:country":"PK",
    "wof:name":"Walidad",
    "wof:placetype":"locality"
},
  "geometry": {"coordinates":[71.14473000000002,34.62821],"type":"Point"}
}