{
  "type": "Feature",
  "properties": {
    "gn:admin1_code":"4.0",
    "gn:asciiname":"Dali Pind",
    "gn:country_code":"PK",
    "gn:dem":441,
    "gn:feature_class":"P",
    "gn:feature_code":"PPL",
    "gn:name":"Dali Pind",
    "gn:population":0,
    "gn:timezone":"Asia/Karachi",
    "iso:country":"PK",
    "wof:name":"Dali Pind",
    "wof:placetype":"locality"
},
  "geometry": {"coordinates":[72.72036,33.83652],"type":"Point"}
}