{
  "type": "Feature",
  "properties": {
    "gn:admin1_code":"5.0",
    "gn:asciiname":"Goth Anjuman",
    "gn:country_code":"PK",
    "gn:dem":33,
    "gn:feature_class":"P",
    "gn:feature_code":"PPL",
    "gn:name":"Goth Anjuman",
    "gn:population":0,
    "gn:timezone":"Asia/Karachi",
    "iso:country":"PK",
    "wof:name":"Goth Anjuman",
    "wof:placetype":"locality"
},
  "geometry": {"coordinates":[68.12194000000001,26.30904],"type":"Point"}
}