{
  "type": "Feature",
  "properties": {
    "gn:admin1_code":"6.0",
    "gn:asciiname":"Muttial Maira",
    "gn:country_code":"PK",
    "gn:dem":1616,
    "gn:feature_class":"P",
    "gn:feature_code":"PPL",
    "gn:name":"Muttial Maira",
    "gn:population":0,
    "gn:timezone":"Asia/Karachi",
    "iso:country":"PK",
    "wof:name":"Muttial Maira",
    "wof:placetype":"locality"
},
  "geometry": {"coordinates":[73.73994999999999,33.8403],"type":"Point"}
}