{
  "type": "Feature",
  "properties": {
    "gn:admin1_code":"2.0",
    "gn:asciiname":"Adosh Chinar",
    "gn:country_code":"PK",
    "gn:dem":2456,
    "gn:feature_class":"P",
    "gn:feature_code":"PPL",
    "gn:name":"Adosh Chinar",
    "gn:population":0,
    "gn:timezone":"Asia/Karachi",
    "iso:country":"PK",
    "wof:name":"Adosh Chinar",
    "wof:placetype":"locality"
},
  "geometry": {"coordinates":[66.92868,30.9489],"type":"Point"}
}