{
  "type": "Feature",
  "properties": {
    "gn:admin1_code":"3.0",
    "gn:asciiname":"Alagram",
    "gn:country_code":"PK",
    "gn:dem":1480,
    "gn:feature_class":"P",
    "gn:feature_code":"PPL",
    "gn:name":"Alagram",
    "gn:population":0,
    "gn:timezone":"Asia/Karachi",
    "iso:country":"PK",
    "name:und_x_variant":[
        "Algram",
        "Alagram"
    ],
    "wof:name":"Alagram",
    "wof:placetype":"locality"
},
  "geometry": {"coordinates":[72.68035,34.78701],"type":"Point"}
}