{
  "type": "Feature",
  "properties": {
    "gn:admin1_code":"4.0",
    "gn:asciiname":"Chak Forty-two Fateh",
    "gn:country_code":"PK",
    "gn:dem":158,
    "gn:feature_class":"P",
    "gn:feature_code":"PPL",
    "gn:name":"Chak Forty-two Fateh",
    "gn:population":0,
    "gn:timezone":"Asia/Karachi",
    "iso:country":"PK",
    "wof:name":"Chak Forty-two Fateh",
    "wof:placetype":"locality"
},
  "geometry": {"coordinates":[72.88911,29.75],"type":"Point"}
}