{
  "type": "Feature",
  "properties": {
    "gn:admin1_code":"04",
    "gn:asciiname":"Sohian",
    "gn:country_code":"PK",
    "gn:dem":262,
    "gn:feature_class":"P",
    "gn:feature_code":"PPL",
    "gn:name":"Sohian",
    "gn:population":0,
    "gn:timezone":"Asia/Karachi",
    "iso:country":"PK",
    "wof:name":"Sohian",
    "wof:placetype":"locality"
},
  "geometry": {"coordinates":[74.91311999999998,32.27732],"type":"Point"}
}