{
  "type": "Feature",
  "properties": {
    "gn:admin1_code":"3.0",
    "gn:asciiname":"Dhok Gulistan",
    "gn:country_code":"PK",
    "gn:dem":414,
    "gn:feature_class":"P",
    "gn:feature_code":"PPL",
    "gn:name":"Dhok Gulistan",
    "gn:population":0,
    "gn:timezone":"Asia/Karachi",
    "iso:country":"PK",
    "name:und_x_variant":[
        "Dhok Gulest\u0101n"
    ],
    "wof:name":"Dhok Gulistan",
    "wof:placetype":"locality"
},
  "geometry": {"coordinates":[71.61805,33.49252],"type":"Point"}
}