{
  "type": "Feature",
  "properties": {
    "gn:admin1_code":"2",
    "gn:asciiname":"Landi Two Hundred Fifty-nine",
    "gn:country_code":"PK",
    "gn:dem":671,
    "gn:feature_class":"P",
    "gn:feature_code":"PPL",
    "gn:name":"Landi Two Hundred Fifty-nine",
    "gn:population":0,
    "gn:timezone":"Asia/Karachi",
    "iso:country":"PK",
    "name:und_x_variant":[
        "L\u0101ndi",
        "L\u0101ndi 259",
        "Landi Two Hundred Fifty-nine"
    ],
    "wof:name":"Landi Two Hundred Fifty-nine",
    "wof:placetype":"locality"
},
  "geometry": {"coordinates":[63.42136,28.7274],"type":"Point"}
}