{
  "type": "Feature",
  "properties": {
    "gn:admin1_code":"6",
    "gn:asciiname":"Kichmohri",
    "gn:country_code":"PK",
    "gn:dem":2944,
    "gn:feature_class":"P",
    "gn:feature_code":"PPL",
    "gn:name":"Kichmohri",
    "gn:population":0,
    "gn:timezone":"Asia/Karachi",
    "iso:country":"PK",
    "name:und_x_variant":[
        "Rechmonri",
        "Kichm\u014dhri"
    ],
    "wof:name":"Kichmohri",
    "wof:placetype":"locality"
},
  "geometry": {"coordinates":[74.30556,34.83889],"type":"Point"}
}