{
  "type": "Feature",
  "properties": {
    "gn:admin1_code":"4.0",
    "gn:asciiname":"Basti Babar",
    "gn:country_code":"PK",
    "gn:dem":90,
    "gn:feature_class":"P",
    "gn:feature_code":"PPL",
    "gn:name":"Basti B\u0101bar",
    "gn:population":0,
    "gn:timezone":"Asia/Karachi",
    "iso:country":"PK",
    "wof:name":"Basti Babar",
    "wof:placetype":"locality"
},
  "geometry": {"coordinates":[70.27764000000001,28.93357],"type":"Point"}
}