{
  "type": "Feature",
  "properties": {
    "gn:admin1_code":"4.0",
    "gn:asciiname":"Dhapoi Hasanwali",
    "gn:country_code":"PK",
    "gn:dem":219,
    "gn:feature_class":"P",
    "gn:feature_code":"PPL",
    "gn:name":"Dhapoi Hasanwali",
    "gn:population":0,
    "gn:timezone":"Asia/Karachi",
    "iso:country":"PK",
    "name:und_x_variant":[
        "Dhapai Hasanw\u0101li"
    ],
    "wof:name":"Dhapoi Hasanwali",
    "wof:placetype":"locality"
},
  "geometry": {"coordinates":[73.89667,32.32557],"type":"Point"}
}