{
  "type": "Feature",
  "properties": {
    "gn:admin1_code":"4",
    "gn:asciiname":"Dahariwala",
    "gn:country_code":"PK",
    "gn:dem":149,
    "gn:feature_class":"P",
    "gn:feature_code":"PPL",
    "gn:name":"Dahariwala",
    "gn:population":0,
    "gn:timezone":"Asia/Karachi",
    "iso:country":"PK",
    "name:und_x_variant":[
        "Dh\u0101riw\u0101la"
    ],
    "wof:name":"Dahariwala",
    "wof:placetype":"locality"
},
  "geometry": {"coordinates":[71.35292,31.08673],"type":"Point"}
}