{
  "type": "Feature",
  "properties": {
    "gn:admin1_code":"3",
    "gn:asciiname":"Kana",
    "gn:country_code":"PK",
    "gn:dem":2517,
    "gn:feature_class":"P",
    "gn:feature_code":"PPL",
    "gn:name":"Kana",
    "gn:population":0,
    "gn:timezone":"Asia/Karachi",
    "iso:country":"PK",
    "wof:name":"Kana",
    "wof:placetype":"locality"
},
  "geometry": {"coordinates":[73.11868,34.89935999999999],"type":"Point"}
}