{
  "type": "Feature",
  "properties": {
    "gn:admin1_code":"2.0",
    "gn:asciiname":"Sianwaro Khuanr",
    "gn:country_code":"PK",
    "gn:dem":59,
    "gn:feature_class":"P",
    "gn:feature_code":"PPL",
    "gn:name":"Si\u0101nwaro Khuanr",
    "gn:population":0,
    "gn:timezone":"Asia/Karachi",
    "iso:country":"PK",
    "wof:name":"Sianwaro Khuanr",
    "wof:placetype":"locality"
},
  "geometry": {"coordinates":[66.57528000000001,25.93556],"type":"Point"}
}