{
  "type": "Feature",
  "properties": {
    "gn:admin1_code":"5.0",
    "gn:asciiname":"Goth Faqir Qasim",
    "gn:country_code":"PK",
    "gn:dem":9,
    "gn:feature_class":"P",
    "gn:feature_code":"PPL",
    "gn:name":"Goth Faqir Qasim",
    "gn:population":0,
    "gn:timezone":"Asia/Karachi",
    "iso:country":"PK",
    "wof:name":"Goth Faqir Qasim",
    "wof:placetype":"locality"
},
  "geometry": {"coordinates":[69.43395,25.18716],"type":"Point"}
}