{
  "type": "Feature",
  "properties": {
    "gn:admin1_code":"01",
    "gn:asciiname":"Artanawa",
    "gn:country_code":"PK",
    "gn:dem":1119,
    "gn:feature_class":"P",
    "gn:feature_code":"PPL",
    "gn:name":"Artanawa",
    "gn:population":0,
    "gn:timezone":"Asia/Karachi",
    "iso:country":"PK",
    "name:eng_x_preferred":[
        "Artanawa"
    ],
    "wof:name":"Artanawa",
    "wof:placetype":"locality"
},
  "geometry": {"coordinates":[71.72996999999999,34.66655],"type":"Point"}
}