{
  "type": "Feature",
  "properties": {
    "gn:admin1_code":"3",
    "gn:asciiname":"Chhapar",
    "gn:country_code":"PK",
    "gn:dem":1356,
    "gn:feature_class":"P",
    "gn:feature_code":"PPL",
    "gn:name":"Chhapar",
    "gn:population":0,
    "gn:timezone":"Asia/Karachi",
    "iso:country":"PK",
    "name:und_x_variant":[
        "Chhappar"
    ],
    "wof:name":"Chhapar",
    "wof:placetype":"locality"
},
  "geometry": {"coordinates":[73.09503000000002,34.44432],"type":"Point"}
}