{
  "type": "Feature",
  "properties": {
    "gn:admin1_code":"4",
    "gn:asciiname":"Kolla",
    "gn:country_code":"PK",
    "gn:dem":535,
    "gn:feature_class":"P",
    "gn:feature_code":"PPL",
    "gn:name":"Kolla",
    "gn:population":0,
    "gn:timezone":"Asia/Karachi",
    "iso:country":"PK",
    "name:ceb_x_preferred":[
        "Kolla"
    ],
    "name:nno_x_preferred":[
        "Kolla"
    ],
    "name:nor_x_preferred":[
        "Kolla"
    ],
    "name:und_x_variant":[
        "Kazla"
    ],
    "wof:name":"Kolla",
    "wof:placetype":"locality"
},
  "geometry": {"coordinates":[73.16346999999998,33.23423],"type":"Point"}
}