{
  "type": "Feature",
  "properties": {
    "gn:admin1_code":"2.0",
    "gn:asciiname":"Murid",
    "gn:country_code":"PK",
    "gn:dem":1846,
    "gn:feature_class":"P",
    "gn:feature_code":"PPL",
    "gn:name":"Murid",
    "gn:population":0,
    "gn:timezone":"Asia/Karachi",
    "iso:country":"PK",
    "name:ara_x_preferred":[
        "\u0645\u0631\u064a\u062f"
    ],
    "name:deu_x_preferred":[
        "Mur\u012bd"
    ],
    "name:hin_x_preferred":[
        "\u092e\u0941\u0930\u0940\u0926"
    ],
    "name:ita_x_preferred":[
        "Murid"
    ],
    "name:mal_x_preferred":[
        "\u0d2e\u0d41\u0d30\u0d40\u0d26\u0d4d"
    ],
    "name:pan_x_preferred":[
        "\u0a2e\u0a41\u0a30\u0a40\u0a26"
    ],
    "name:rus_x_preferred":[
        "\u041c\u044e\u0440\u0438\u0434"
    ],
    "name:tgk_x_preferred":[
        "\u041c\u0443\u0440\u0438\u0434"
    ],
    "name:tur_x_preferred":[
        "M\u00fcrid"
    ],
    "name:ukr_x_preferred":[
        "\u041c\u0443\u0440\u0438\u0434"
    ],
    "name:urd_x_preferred":[
        "\u0645\u0631\u06cc\u062f"
    ],
    "name:uzb_x_preferred":[
        "Murid"
    ],
    "wof:name":"Murid",
    "wof:placetype":"locality"
},
  "geometry": {"coordinates":[66.81823,28.70088],"type":"Point"}
}