{
  "type": "Feature",
  "properties": {
    "gn:admin1_code":"2.0",
    "gn:asciiname":"Bahram Khan",
    "gn:country_code":"PK",
    "gn:dem":82,
    "gn:feature_class":"P",
    "gn:feature_code":"PPL",
    "gn:name":"Bahram Khan",
    "gn:population":0,
    "gn:timezone":"Asia/Karachi",
    "iso:country":"PK",
    "name:und_x_variant":[
        "Behram Khan",
        "Bahram Khan"
    ],
    "wof:name":"Bahram Khan",
    "wof:placetype":"locality"
},
  "geometry": {"coordinates":[67.83333,28.78333],"type":"Point"}
}