{
  "type": "Feature",
  "properties": {
    "gn:admin1_code":"2.0",
    "gn:asciiname":"Huram",
    "gn:country_code":"PK",
    "gn:dem":67,
    "gn:feature_class":"P",
    "gn:feature_code":"PPL",
    "gn:name":"Huram",
    "gn:population":0,
    "gn:timezone":"Asia/Karachi",
    "iso:country":"PK",
    "wof:name":"Huram",
    "wof:placetype":"locality"
},
  "geometry": {"coordinates":[68.25535000000001,28.47183],"type":"Point"}
}