{
  "type": "Feature",
  "properties": {
    "gn:admin1_code":"4",
    "gn:asciiname":"Chak One Hundred Fifty-seven Eastern Bar",
    "gn:country_code":"PK",
    "gn:dem":155,
    "gn:feature_class":"P",
    "gn:feature_code":"PPL",
    "gn:name":"Chak One Hundred Fifty-seven Eastern Bar",
    "gn:population":0,
    "gn:timezone":"Asia/Karachi",
    "iso:country":"PK",
    "name:und_x_variant":[
        "Chak One Hundred Fifty-seven EB"
    ],
    "wof:name":"Chak One Hundred Fifty-seven Eastern Bar",
    "wof:placetype":"locality"
},
  "geometry": {"coordinates":[72.98594,30.31193],"type":"Point"}
}