{
  "type": "Feature",
  "properties": {
    "gn:admin1_code":"3.0",
    "gn:asciiname":"Quli Beg Banda",
    "gn:country_code":"PK",
    "gn:dem":534,
    "gn:feature_class":"P",
    "gn:feature_code":"PPL",
    "gn:name":"Quli Beg B\u0101nda",
    "gn:population":0,
    "gn:timezone":"Asia/Karachi",
    "iso:country":"PK",
    "wof:name":"Quli Beg Banda",
    "wof:placetype":"locality"
},
  "geometry": {"coordinates":[71.06667,32.98333],"type":"Point"}
}