{
  "type": "Feature",
  "properties": {
    "gn:admin1_code":"3.0",
    "gn:asciiname":"Khawaja Khel",
    "gn:country_code":"PK",
    "gn:dem":571,
    "gn:feature_class":"P",
    "gn:feature_code":"PPL",
    "gn:name":"Khawaja Khel",
    "gn:population":0,
    "gn:timezone":"Asia/Karachi",
    "iso:country":"PK",
    "name:und_x_variant":[
        "Khowaja Khel",
        "Khw\u0101ja Khel",
        "Khawaja Khel"
    ],
    "wof:name":"Khawaja Khel",
    "wof:placetype":"locality"
},
  "geometry": {"coordinates":[71.81044,33.67002],"type":"Point"}
}