{
  "type": "Feature",
  "properties": {
    "gn:admin1_code":"3",
    "gn:asciiname":"Singal Kot",
    "gn:country_code":"PK",
    "gn:dem":1459,
    "gn:feature_class":"P",
    "gn:feature_code":"PPL",
    "gn:name":"Singal Kot",
    "gn:population":0,
    "gn:timezone":"Asia/Karachi",
    "iso:country":"PK",
    "wof:name":"Singal Kot",
    "wof:placetype":"locality"
},
  "geometry": {"coordinates":[73.1296,34.56774],"type":"Point"}
}