{
  "type": "Feature",
  "properties": {
    "gn:admin1_code":"3",
    "gn:asciiname":"Kar Banda",
    "gn:country_code":"PK",
    "gn:dem":2707,
    "gn:feature_class":"P",
    "gn:feature_code":"PPL",
    "gn:name":"K\u0101r B\u0101nda",
    "gn:population":0,
    "gn:timezone":"Asia/Karachi",
    "iso:country":"PK",
    "wof:name":"Kar Banda",
    "wof:placetype":"locality"
},
  "geometry": {"coordinates":[72.53749999999999,35.28611],"type":"Point"}
}