{
  "type": "Feature",
  "properties": {
    "gn:admin1_code":"3",
    "gn:asciiname":"Noshbil",
    "gn:country_code":"PK",
    "gn:dem":1644,
    "gn:feature_class":"P",
    "gn:feature_code":"PPL",
    "gn:name":"Noshbil",
    "gn:population":0,
    "gn:timezone":"Asia/Karachi",
    "iso:country":"PK",
    "name:eng_x_preferred":[
        "Noshbu"
    ],
    "wof:name":"Noshbil",
    "wof:placetype":"locality"
},
  "geometry": {"coordinates":[71.72100999999998,35.64830999999999],"type":"Point"}
}