{
  "type": "Feature",
  "properties": {
    "gn:admin1_code":"2",
    "gn:asciiname":"Jamat",
    "gn:country_code":"PK",
    "gn:dem":2354,
    "gn:feature_class":"P",
    "gn:feature_code":"PPL",
    "gn:name":"Jamat",
    "gn:population":0,
    "gn:timezone":"Asia/Karachi",
    "iso:country":"PK",
    "wof:name":"Jamat",
    "wof:placetype":"locality"
},
  "geometry": {"coordinates":[67.04514,31.03678],"type":"Point"}
}