{
  "type": "Feature",
  "properties": {
    "gn:admin1_code":"3.0",
    "gn:asciiname":"Nasibabad Gambar",
    "gn:country_code":"PK",
    "gn:dem":325,
    "gn:feature_class":"P",
    "gn:feature_code":"PPL",
    "gn:name":"Nasibabad Gambar",
    "gn:population":0,
    "gn:timezone":"Asia/Karachi",
    "iso:country":"PK",
    "name:und_x_variant":[
        "Panchakki",
        "Nasibabad Gambar"
    ],
    "wof:name":"Nasibabad Gambar",
    "wof:placetype":"locality"
},
  "geometry": {"coordinates":[70.69186999999999,32.93914],"type":"Point"}
}