{
  "type": "Feature",
  "properties": {
    "gn:admin1_code":"4.0",
    "gn:asciiname":"Behk Muqaiyyaddin",
    "gn:country_code":"PK",
    "gn:dem":202,
    "gn:feature_class":"P",
    "gn:feature_code":"PPL",
    "gn:name":"Behk Muqaiyyaddin",
    "gn:population":0,
    "gn:timezone":"Asia/Karachi",
    "iso:country":"PK",
    "name:und_x_variant":[
        "Behk Muqayyad-ud-Din",
        "Bahak Muqaiyadd\u012bn",
        "Behk Muqaiyyaddin"
    ],
    "wof:name":"Behk Muqaiyyaddin",
    "wof:placetype":"locality"
},
  "geometry": {"coordinates":[73.48095000000001,32.20532],"type":"Point"}
}