{
  "type": "Feature",
  "properties": {
    "gn:admin1_code":"3",
    "gn:asciiname":"Shahban",
    "gn:country_code":"PK",
    "gn:dem":937,
    "gn:feature_class":"P",
    "gn:feature_code":"PPL",
    "gn:name":"Shahban",
    "gn:population":0,
    "gn:timezone":"Asia/Karachi",
    "iso:country":"PK",
    "wof:name":"Shahban",
    "wof:placetype":"locality"
},
  "geometry": {"coordinates":[72.08475,34.75598],"type":"Point"}
}