{
  "type": "Feature",
  "properties": {
    "gn:admin1_code":"4",
    "gn:asciiname":"Chak One Hundred Five Rakh Branch",
    "gn:country_code":"PK",
    "gn:dem":191,
    "gn:feature_class":"P",
    "gn:feature_code":"PPL",
    "gn:name":"Chak One Hundred Five Rakh Branch",
    "gn:population":0,
    "gn:timezone":"Asia/Karachi",
    "iso:country":"PK",
    "name:und_x_variant":[
        "Gabbiw\u0101la",
        "Gabiy\u0101nw\u0101la"
    ],
    "wof:name":"Chak One Hundred Five Rakh Branch",
    "wof:placetype":"locality"
},
  "geometry": {"coordinates":[73.34886999999998,31.428],"type":"Point"}
}