{
  "type": "Feature",
  "properties": {
    "gn:admin1_code":"2.0",
    "gn:asciiname":"Kili Haji Mir Hasan",
    "gn:country_code":"PK",
    "gn:dem":850,
    "gn:feature_class":"P",
    "gn:feature_code":"PPL",
    "gn:name":"Kili Haji Mir Hasan",
    "gn:population":0,
    "gn:timezone":"Asia/Karachi",
    "iso:country":"PK",
    "wof:name":"Kili Haji Mir Hasan",
    "wof:placetype":"locality"
},
  "geometry": {"coordinates":[64.70260999999999,29.24011],"type":"Point"}
}