{
  "type": "Feature",
  "properties": {
    "gn:admin1_code":"04",
    "gn:asciiname":"Qadra",
    "gn:country_code":"PK",
    "gn:dem":89,
    "gn:feature_class":"P",
    "gn:feature_code":"PPL",
    "gn:name":"Qadra",
    "gn:population":0,
    "gn:timezone":"Asia/Karachi",
    "iso:country":"PK",
    "name:und_x_variant":[
        "K\u0101dra Khas",
        "Qadra"
    ],
    "wof:name":"Qadra",
    "wof:placetype":"locality"
},
  "geometry": {"coordinates":[70.20678000000001,28.88558],"type":"Point"}
}