{
  "type": "Feature",
  "properties": {
    "gn:admin1_code":"3.0",
    "gn:asciiname":"Sari",
    "gn:country_code":"PK",
    "gn:dem":1887,
    "gn:feature_class":"P",
    "gn:feature_code":"PPL",
    "gn:name":"Sari",
    "gn:population":0,
    "gn:timezone":"Asia/Karachi",
    "iso:country":"PK",
    "wof:name":"Sari",
    "wof:placetype":"locality"
},
  "geometry": {"coordinates":[73.24115,35.34825],"type":"Point"}
}