{
  "type": "Feature",
  "properties": {
    "gn:admin1_code":"1.0",
    "gn:asciiname":"Tagha Sam",
    "gn:country_code":"PK",
    "gn:dem":1800,
    "gn:feature_class":"P",
    "gn:feature_code":"PPL",
    "gn:name":"Tagha Sam",
    "gn:population":0,
    "gn:timezone":"Asia/Karachi",
    "iso:country":"PK",
    "wof:name":"Tagha Sam",
    "wof:placetype":"locality"
},
  "geometry": {"coordinates":[70.86319,33.73648],"type":"Point"}
}