{
  "type": "Feature",
  "properties": {
    "gn:admin1_code":"4.0",
    "gn:asciiname":"Chah Qazirwala",
    "gn:country_code":"PK",
    "gn:dem":118,
    "gn:feature_class":"P",
    "gn:feature_code":"PPL",
    "gn:name":"Chah Qazirwala",
    "gn:population":0,
    "gn:timezone":"Asia/Karachi",
    "iso:country":"PK",
    "name:und_x_variant":[
        "Q\u0101ziw\u0101la"
    ],
    "wof:name":"Chah Qazirwala",
    "wof:placetype":"locality"
},
  "geometry": {"coordinates":[71.37066999999998,29.89898],"type":"Point"}
}