{
  "type": "Feature",
  "properties": {
    "gn:admin1_code":"4.0",
    "gn:asciiname":"Chak Seven - Four Left",
    "gn:country_code":"PK",
    "gn:dem":178,
    "gn:feature_class":"P",
    "gn:feature_code":"PPL",
    "gn:name":"Chak Seven - Four Left",
    "gn:population":0,
    "gn:timezone":"Asia/Karachi",
    "iso:country":"PK",
    "name:und_x_variant":[
        "Chak 7",
        "Chak 7-4 L",
        "Chak Seven Four L",
        "Chak Seven - Four Left"
    ],
    "wof:name":"Chak Seven - Four Left",
    "wof:placetype":"locality"
},
  "geometry": {"coordinates":[73.4308,30.74484],"type":"Point"}
}