{
  "type": "Feature",
  "properties": {
    "gn:admin1_code":"4.0",
    "gn:asciiname":"Basti Hirjan",
    "gn:country_code":"PK",
    "gn:dem":154,
    "gn:feature_class":"P",
    "gn:feature_code":"PPL",
    "gn:name":"Basti Hirjan",
    "gn:population":0,
    "gn:timezone":"Asia/Karachi",
    "iso:country":"PK",
    "name:und_x_variant":[
        "Basti Hiraj\u0101n"
    ],
    "wof:name":"Basti Hirjan",
    "wof:placetype":"locality"
},
  "geometry": {"coordinates":[72.29399000000002,31.09856],"type":"Point"}
}