{
  "type": "Feature",
  "properties": {
    "gn:admin1_code":"4",
    "gn:asciiname":"Burana Shahi",
    "gn:country_code":"PK",
    "gn:dem":140,
    "gn:feature_class":"P",
    "gn:feature_code":"PPL",
    "gn:name":"Burana Shahi",
    "gn:population":0,
    "gn:timezone":"Asia/Karachi",
    "iso:country":"PK",
    "name:und_x_variant":[
        "Bur\u0101na S\u0101ni"
    ],
    "wof:name":"Burana Shahi",
    "wof:placetype":"locality"
},
  "geometry": {"coordinates":[72.52099,29.8777],"type":"Point"}
}