{
  "type": "Feature",
  "properties": {
    "gn:admin1_code":"6.0",
    "gn:asciiname":"Hillan",
    "gn:country_code":"PK",
    "gn:dem":873,
    "gn:feature_class":"P",
    "gn:feature_code":"PPL",
    "gn:name":"Hillan",
    "gn:population":0,
    "gn:timezone":"Asia/Karachi",
    "iso:country":"PK",
    "wof:name":"Hillan",
    "wof:placetype":"locality"
},
  "geometry": {"coordinates":[73.99594999999999,33.54042],"type":"Point"}
}