{
  "type": "Feature",
  "properties": {
    "gn:admin1_code":"3",
    "gn:asciiname":"Chapra",
    "gn:country_code":"PK",
    "gn:dem":1824,
    "gn:feature_class":"P",
    "gn:feature_code":"PPL",
    "gn:name":"Chapra",
    "gn:population":0,
    "gn:timezone":"Asia/Karachi",
    "iso:country":"PK",
    "name:ceb_x_preferred":[
        "Chapra"
    ],
    "name:fra_x_preferred":[
        "Chapra"
    ],
    "name:swe_x_preferred":[
        "Chapra"
    ],
    "name:und_x_variant":[
        "Chaphra"
    ],
    "wof:name":"Chapra",
    "wof:placetype":"locality"
},
  "geometry": {"coordinates":[73.51755,34.66125],"type":"Point"}
}