{
  "type": "Feature",
  "properties": {
    "gn:admin1_code":"4.0",
    "gn:asciiname":"Three Hundred Eighty-seven Jhang Branch",
    "gn:country_code":"PK",
    "gn:dem":154,
    "gn:feature_class":"P",
    "gn:feature_code":"PPL",
    "gn:name":"Three Hundred Eighty-seven Jhang Branch",
    "gn:population":0,
    "gn:timezone":"Asia/Karachi",
    "iso:country":"PK",
    "name:und_x_variant":[
        "Nai \u0100b\u0101dil"
    ],
    "wof:name":"Three Hundred Eighty-seven Jhang Branch",
    "wof:placetype":"locality"
},
  "geometry": {"coordinates":[72.37551999999999,31.04584],"type":"Point"}
}