{
  "type": "Feature",
  "properties": {
    "gn:admin1_code":"4",
    "gn:asciiname":"Head Rajkan",
    "gn:country_code":"PK",
    "gn:dem":115,
    "gn:feature_class":"P",
    "gn:feature_code":"PPL",
    "gn:name":"Head Rajkan",
    "gn:population":0,
    "gn:timezone":"Asia/Karachi",
    "iso:country":"PK",
    "name:fas_x_preferred":[
        "\u0647\u06cc\u062f \u0631\u0627\u062c\u06a9\u0627\u0646"
    ],
    "name:und_x_variant":[
        "R\u0101jk\u0101n Head"
    ],
    "name:urd_x_preferred":[
        "\u06c1\u06cc\u0688 \u0631\u0627\u062c\u06a9\u0627\u0646"
    ],
    "wof:name":"Head Rajkan",
    "wof:placetype":"locality"
},
  "geometry": {"coordinates":[71.49325,29.10642],"type":"Point"}
}