{
  "type": "Feature",
  "properties": {
    "gn:admin1_code":"4.0",
    "gn:asciiname":"Deputywala",
    "gn:country_code":"PK",
    "gn:dem":122,
    "gn:feature_class":"P",
    "gn:feature_code":"PPL",
    "gn:name":"Deputywala",
    "gn:population":0,
    "gn:timezone":"Asia/Karachi",
    "iso:country":"PK",
    "wof:name":"Deputywala",
    "wof:placetype":"locality"
},
  "geometry": {"coordinates":[71.52364,30.01124],"type":"Point"}
}