{
  "type": "Feature",
  "properties": {
    "gn:admin1_code":"4.0",
    "gn:asciiname":"Chak Sixty-one",
    "gn:country_code":"PK",
    "gn:dem":181,
    "gn:feature_class":"P",
    "gn:feature_code":"PPL",
    "gn:name":"Chak Sixty-one",
    "gn:population":0,
    "gn:timezone":"Asia/Karachi",
    "iso:country":"PK",
    "name:und_x_variant":[
        "Dhorawar",
        "Dhar\u0101war",
        "Chak Sixty-one",
        "Nasir\u0101b\u0101d",
        "Dharror\u0101n"
    ],
    "wof:name":"Chak Sixty-one",
    "wof:placetype":"locality"
},
  "geometry": {"coordinates":[72.95973000000002,31.43668],"type":"Point"}
}