{
  "type": "Feature",
  "properties": {
    "gn:admin1_code":"4.0",
    "gn:asciiname":"Haveli Perhananwali",
    "gn:country_code":"PK",
    "gn:dem":205,
    "gn:feature_class":"P",
    "gn:feature_code":"PPL",
    "gn:name":"Haveli Perhananwali",
    "gn:population":0,
    "gn:timezone":"Asia/Karachi",
    "iso:country":"PK",
    "name:und_x_variant":[
        "Bad\u0101new\u0101li"
    ],
    "wof:name":"Haveli Perhananwali",
    "wof:placetype":"locality"
},
  "geometry": {"coordinates":[74.37541,31.12013],"type":"Point"}
}