{
  "type": "Feature",
  "properties": {
    "gn:admin1_code":"4.0",
    "gn:asciiname":"Gulluwala",
    "gn:country_code":"PK",
    "gn:dem":190,
    "gn:feature_class":"P",
    "gn:feature_code":"PPL",
    "gn:name":"Gulluwala",
    "gn:population":0,
    "gn:timezone":"Asia/Karachi",
    "iso:country":"PK",
    "name:und_x_variant":[
        "Galluwala",
        "Gulluwala"
    ],
    "wof:name":"Gulluwala",
    "wof:placetype":"locality"
},
  "geometry": {"coordinates":[72.74644000000001,32.3751],"type":"Point"}
}