{
  "type": "Feature",
  "properties": {
    "gn:admin1_code":"5",
    "gn:asciiname":"Gohraim",
    "gn:country_code":"PK",
    "gn:dem":73,
    "gn:feature_class":"P",
    "gn:feature_code":"PPL",
    "gn:name":"Gohraim",
    "gn:population":0,
    "gn:timezone":"Asia/Karachi",
    "iso:country":"PK",
    "name:und_x_variant":[
        "Gohr\u0101m"
    ],
    "wof:name":"Gohraim",
    "wof:placetype":"locality"
},
  "geometry": {"coordinates":[69.73913,28.07185],"type":"Point"}
}