{
  "type": "Feature",
  "properties": {
    "gn:admin1_code":"01",
    "gn:asciiname":"Palang",
    "gn:country_code":"PK",
    "gn:dem":843,
    "gn:feature_class":"P",
    "gn:feature_code":"PPL",
    "gn:name":"Palang",
    "gn:population":0,
    "gn:timezone":"Asia/Karachi",
    "iso:country":"PK",
    "name:eng_x_preferred":[
        "Palang"
    ],
    "wof:name":"Palang",
    "wof:placetype":"locality"
},
  "geometry": {"coordinates":[71.53765,34.73893],"type":"Point"}
}