{
  "type": "Feature",
  "properties": {
    "gn:admin1_code":"1.0",
    "gn:asciiname":"Darange",
    "gn:country_code":"PK",
    "gn:dem":1756,
    "gn:feature_class":"P",
    "gn:feature_code":"PPL",
    "gn:name":"Darange",
    "gn:population":0,
    "gn:timezone":"Asia/Karachi",
    "iso:country":"PK",
    "name:und_x_variant":[
        "Dafangai"
    ],
    "wof:name":"Darange",
    "wof:placetype":"locality"
},
  "geometry": {"coordinates":[70.89683000000002,33.72636],"type":"Point"}
}