{
  "type": "Feature",
  "properties": {
    "gn:admin1_code":"3.0",
    "gn:asciiname":"Marmandi Multan",
    "gn:country_code":"PK",
    "gn:dem":289,
    "gn:feature_class":"P",
    "gn:feature_code":"PPL",
    "gn:name":"Marmandi Multan",
    "gn:population":0,
    "gn:timezone":"Asia/Karachi",
    "iso:country":"PK",
    "wof:name":"Marmandi Multan",
    "wof:placetype":"locality"
},
  "geometry": {"coordinates":[70.82654000000002,32.78964000000001],"type":"Point"}
}