{
  "type": "Feature",
  "properties": {
    "gn:admin1_code":"3",
    "gn:asciiname":"Mangazai",
    "gn:country_code":"PK",
    "gn:dem":2852,
    "gn:feature_class":"P",
    "gn:feature_code":"PPL",
    "gn:name":"Mangazai",
    "gn:population":0,
    "gn:timezone":"Asia/Karachi",
    "iso:country":"PK",
    "wof:name":"Mangazai",
    "wof:placetype":"locality"
},
  "geometry": {"coordinates":[72.63348000000001,35.04889],"type":"Point"}
}