{
  "type": "Feature",
  "properties": {
    "gn:admin1_code":"4",
    "gn:asciiname":"Maharewala",
    "gn:country_code":"PK",
    "gn:dem":138,
    "gn:feature_class":"P",
    "gn:feature_code":"PPL",
    "gn:name":"Maharewala",
    "gn:population":0,
    "gn:timezone":"Asia/Karachi",
    "iso:country":"PK",
    "wof:name":"Maharewala",
    "wof:placetype":"locality"
},
  "geometry": {"coordinates":[70.97926,30.65844],"type":"Point"}
}