{
  "type": "Feature",
  "properties": {
    "gn:admin1_code":"4",
    "gn:asciiname":"Awan",
    "gn:country_code":"PK",
    "gn:dem":191,
    "gn:feature_class":"P",
    "gn:feature_code":"PPL",
    "gn:name":"Awan",
    "gn:population":0,
    "gn:timezone":"Asia/Karachi",
    "iso:country":"PK",
    "ks:ks_name":"Awan",
    "ks:ks_pop":300,
    "ks:ks_type":"VILLAGE",
    "name:ceb_x_preferred":[
        "Awan"
    ],
    "name:deu_x_preferred":[
        "Awan"
    ],
    "name:eng_x_preferred":[
        "Awan"
    ],
    "name:nld_x_preferred":[
        "Awan"
    ],
    "name:rus_x_preferred":[
        "\u0410\u0432\u0430\u043d"
    ],
    "name:spa_x_preferred":[
        "Awan"
    ],
    "name:swe_x_preferred":[
        "Awan"
    ],
    "wof:name":"Awan",
    "wof:placetype":"locality",
    "wof:population":300
},
  "geometry": {"coordinates":[74.36528,30.78333],"type":"Point"}
}