{
  "type": "Feature",
  "properties": {
    "gn:admin1_code":"3",
    "gn:asciiname":"Maban Dheri",
    "gn:country_code":"PK",
    "gn:dem":307,
    "gn:feature_class":"P",
    "gn:feature_code":"PPL",
    "gn:name":"Maban Dheri",
    "gn:population":0,
    "gn:timezone":"Asia/Karachi",
    "iso:country":"PK",
    "name:eng_x_preferred":[
        "Maban Dheri"
    ],
    "wof:name":"Maban Dheri",
    "wof:placetype":"locality"
},
  "geometry": {"coordinates":[72.08920999999999,34.17238],"type":"Point"}
}