{
  "type": "Feature",
  "properties": {
    "gn:admin1_code":"2.0",
    "gn:asciiname":"Khanai",
    "gn:country_code":"PK",
    "gn:dem":1710,
    "gn:feature_class":"P",
    "gn:feature_code":"PPL",
    "gn:name":"Khanai",
    "gn:population":0,
    "gn:timezone":"Asia/Karachi",
    "iso:country":"PK",
    "name:eng_x_preferred":[
        "Khanai"
    ],
    "name:und_x_variant":[
        "Khani"
    ],
    "wof:name":"Khanai",
    "wof:placetype":"locality"
},
  "geometry": {"coordinates":[67.12483,30.49702000000001],"type":"Point"}
}