{
  "type": "Feature",
  "properties": {
    "gn:admin1_code":"4",
    "gn:asciiname":"Daulatpur",
    "gn:country_code":"PK",
    "gn:dem":122,
    "gn:feature_class":"P",
    "gn:feature_code":"PPL",
    "gn:name":"Daulatpur",
    "gn:population":0,
    "gn:timezone":"Asia/Karachi",
    "iso:country":"PK",
    "name:ben_x_preferred":[
        "\u09a6\u09cc\u09b2\u09a4\u09aa\u09c1\u09b0"
    ],
    "name:bpy_x_preferred":[
        "\u09a6\u09cc\u09b2\u09a4\u09aa\u09c1\u09b0"
    ],
    "name:ceb_x_preferred":[
        "Daulatpur"
    ],
    "name:eng_x_preferred":[
        "Daulatpur"
    ],
    "name:fra_x_preferred":[
        "Daulatpur"
    ],
    "name:ita_x_preferred":[
        "Daulatpur"
    ],
    "name:nld_x_preferred":[
        "Daulatpur"
    ],
    "name:pol_x_preferred":[
        "Daulatpur"
    ],
    "name:swe_x_preferred":[
        "Daulatpur"
    ],
    "name:urd_x_preferred":[
        "\u062f\u0648\u0644\u062a \u067e\u0648\u0631"
    ],
    "name:zho_x_preferred":[
        "\u8fbe\u4e4c\u62c9\u7279\u666e\u5c14"
    ],
    "wof:name":"Daulatpur",
    "wof:placetype":"locality"
},
  "geometry": {"coordinates":[71.89583,29.70139],"type":"Point"}
}