{
  "type": "Feature",
  "properties": {
    "gn:admin1_code":"3.0",
    "gn:asciiname":"Tarher Sahoch",
    "gn:country_code":"PK",
    "gn:dem":3076,
    "gn:feature_class":"P",
    "gn:feature_code":"PPL",
    "gn:name":"Tarher Sahoch",
    "gn:population":0,
    "gn:timezone":"Asia/Karachi",
    "iso:country":"PK",
    "wof:name":"Tarher Sahoch",
    "wof:placetype":"locality"
},
  "geometry": {"coordinates":[73.74056,34.95176],"type":"Point"}
}