{
  "type": "Feature",
  "properties": {
    "gn:admin1_code":"2.0",
    "gn:asciiname":"Warah Kili",
    "gn:country_code":"PK",
    "gn:dem":1430,
    "gn:feature_class":"P",
    "gn:feature_code":"PPL",
    "gn:name":"Warah Kili",
    "gn:population":0,
    "gn:timezone":"Asia/Karachi",
    "iso:country":"PK",
    "wof:name":"Warah Kili",
    "wof:placetype":"locality"
},
  "geometry": {"coordinates":[69.23528,31.07528],"type":"Point"}
}