{
  "type": "Feature",
  "properties": {
    "gn:admin1_code":"4",
    "gn:asciiname":"Bannawala",
    "gn:country_code":"PK",
    "gn:dem":121,
    "gn:feature_class":"P",
    "gn:feature_code":"PPL",
    "gn:name":"Bannawala",
    "gn:population":0,
    "gn:timezone":"Asia/Karachi",
    "iso:country":"PK",
    "name:und_x_variant":[
        "Bann\u0101w\u0101la"
    ],
    "wof:name":"Bannawala",
    "wof:placetype":"locality"
},
  "geometry": {"coordinates":[71.55628,30.15991],"type":"Point"}
}