{
  "type": "Feature",
  "properties": {
    "gn:admin1_code":"3.0",
    "gn:asciiname":"Bar Kahian",
    "gn:country_code":"PK",
    "gn:dem":1219,
    "gn:feature_class":"P",
    "gn:feature_code":"PPL",
    "gn:name":"Bar Kahian",
    "gn:population":0,
    "gn:timezone":"Asia/Karachi",
    "iso:country":"PK",
    "name:eng_x_preferred":[
        "K\u0101nj\u0101n ni B\u0101r"
    ],
    "wof:name":"Bar Kahian",
    "wof:placetype":"locality"
},
  "geometry": {"coordinates":[73.24305,33.85156],"type":"Point"}
}