{
  "type": "Feature",
  "properties": {
    "gn:admin1_code":"3.0",
    "gn:asciiname":"Kotka Alam Gul",
    "gn:country_code":"PK",
    "gn:dem":400,
    "gn:feature_class":"P",
    "gn:feature_code":"PPL",
    "gn:name":"Kotka Alam Gul",
    "gn:population":0,
    "gn:timezone":"Asia/Karachi",
    "iso:country":"PK",
    "name:und_x_variant":[
        "Barat Karir\u012b",
        "Kotka Alam Gul"
    ],
    "wof:name":"Kotka Alam Gul",
    "wof:placetype":"locality"
},
  "geometry": {"coordinates":[70.92804,32.96718],"type":"Point"}
}