{
  "type": "Feature",
  "properties": {
    "gn:admin1_code":"04",
    "gn:asciiname":"Musepur",
    "gn:cc2":"PK",
    "gn:country_code":"PK",
    "gn:dem":259,
    "gn:feature_class":"P",
    "gn:feature_code":"PPL",
    "gn:name":"Musepur",
    "gn:population":0,
    "gn:timezone":"Asia/Karachi",
    "iso:country":"PK",
    "name:und_x_variant":[
        "Musapur",
        "Musepur"
    ],
    "wof:name":"Musepur",
    "wof:placetype":"locality"
},
  "geometry": {"coordinates":[75.31667,32.23333],"type":"Point"}
}