{
  "type": "Feature",
  "properties": {
    "gn:admin1_code":"4",
    "gn:asciiname":"Dhok Daltal",
    "gn:country_code":"PK",
    "gn:dem":487,
    "gn:feature_class":"P",
    "gn:feature_code":"PPL",
    "gn:name":"Dhok Daltal",
    "gn:population":0,
    "gn:timezone":"Asia/Karachi",
    "iso:country":"PK",
    "name:und_x_variant":[
        "Sahra"
    ],
    "wof:name":"Dhok Daltal",
    "wof:placetype":"locality"
},
  "geometry": {"coordinates":[72.10293,32.77794],"type":"Point"}
}