{
  "type": "Feature",
  "properties": {
    "gn:admin1_code":"4.0",
    "gn:asciiname":"Chah Pir Sher Ali",
    "gn:country_code":"PK",
    "gn:dem":152,
    "gn:feature_class":"P",
    "gn:feature_code":"PPL",
    "gn:name":"Chah Pir Sher Ali",
    "gn:population":0,
    "gn:timezone":"Asia/Karachi",
    "iso:country":"PK",
    "wof:name":"Chah Pir Sher Ali",
    "wof:placetype":"locality"
},
  "geometry": {"coordinates":[73.0371,30.12971],"type":"Point"}
}