{
  "type": "Feature",
  "properties": {
    "gn:admin1_code":"5.0",
    "gn:asciiname":"Kathrahu Jo Goth",
    "gn:country_code":"PK",
    "gn:dem":38,
    "gn:feature_class":"P",
    "gn:feature_code":"PPL",
    "gn:name":"Kathrahu Jo Goth",
    "gn:population":0,
    "gn:timezone":"Asia/Karachi",
    "iso:country":"PK",
    "wof:name":"Kathrahu Jo Goth",
    "wof:placetype":"locality"
},
  "geometry": {"coordinates":[69.80431999999999,26.00435],"type":"Point"}
}