{
  "type": "Feature",
  "properties": {
    "gn:admin1_code":"4",
    "gn:asciiname":"Sarkpur",
    "gn:country_code":"PK",
    "gn:dem":232,
    "gn:feature_class":"P",
    "gn:feature_code":"PPL",
    "gn:name":"Sarkpur",
    "gn:population":0,
    "gn:timezone":"Asia/Karachi",
    "iso:country":"PK",
    "name:und_x_variant":[
        "Saragpur"
    ],
    "wof:name":"Sarkpur",
    "wof:placetype":"locality"
},
  "geometry": {"coordinates":[74.5543,32.20236],"type":"Point"}
}