{
  "type": "Feature",
  "properties": {
    "gn:admin1_code":"7.0",
    "gn:asciiname":"Sesoni",
    "gn:country_code":"PK",
    "gn:dem":2503,
    "gn:feature_class":"P",
    "gn:feature_code":"PPL",
    "gn:name":"Sesoni",
    "gn:population":0,
    "gn:timezone":"Asia/Karachi",
    "iso:country":"PK",
    "name:und_x_variant":[
        "Hussini",
        "Husaini"
    ],
    "wof:name":"Sesoni",
    "wof:placetype":"locality"
},
  "geometry": {"coordinates":[74.87454,36.42605],"type":"Point"}
}