{
  "type": "Feature",
  "properties": {
    "gn:admin1_code":"4.0",
    "gn:asciiname":"Dhok Nawab Khel",
    "gn:country_code":"PK",
    "gn:dem":356,
    "gn:feature_class":"P",
    "gn:feature_code":"PPL",
    "gn:name":"Dhok Nawab Khel",
    "gn:population":0,
    "gn:timezone":"Asia/Karachi",
    "iso:country":"PK",
    "wof:name":"Dhok Nawab Khel",
    "wof:placetype":"locality"
},
  "geometry": {"coordinates":[71.90278000000001,32.78959],"type":"Point"}
}