{
  "type": "Feature",
  "properties": {
    "gn:admin1_code":"6",
    "gn:asciiname":"Dhara",
    "gn:country_code":"PK",
    "gn:dem":1279,
    "gn:feature_class":"P",
    "gn:feature_code":"PPL",
    "gn:name":"Dhara",
    "gn:population":0,
    "gn:timezone":"Asia/Karachi",
    "iso:country":"PK",
    "wof:name":"Dhara",
    "wof:placetype":"locality"
},
  "geometry": {"coordinates":[73.95926,33.79216],"type":"Point"}
}