{
  "type": "Feature",
  "properties": {
    "gn:admin1_code":"5",
    "gn:asciiname":"Goth Khair Muhammad Brahui",
    "gn:country_code":"PK",
    "gn:dem":54,
    "gn:feature_class":"P",
    "gn:feature_code":"PPL",
    "gn:name":"Goth Khair Muhammad Brahui",
    "gn:population":0,
    "gn:timezone":"Asia/Karachi",
    "iso:country":"PK",
    "name:und_x_variant":[
        "M\u012br Muhammad Brah\u016bi",
        "Khair Muhammad Brohi",
        "Goth Khair Muhammad Brahui"
    ],
    "wof:name":"Goth Khair Muhammad Brahui",
    "wof:placetype":"locality"
},
  "geometry": {"coordinates":[68.23571,27.87183],"type":"Point"}
}