{
  "type": "Feature",
  "properties": {
    "gn:admin1_code":"2.0",
    "gn:asciiname":"Sardar Mir Israr",
    "gn:country_code":"PK",
    "gn:dem":1492,
    "gn:feature_class":"P",
    "gn:feature_code":"PPL",
    "gn:name":"Sardar Mir Israr",
    "gn:population":0,
    "gn:timezone":"Asia/Karachi",
    "iso:country":"PK",
    "name:und_x_variant":[
        "Muhammad Isr\u0101f"
    ],
    "wof:name":"Sardar Mir Israr",
    "wof:placetype":"locality"
},
  "geometry": {"coordinates":[66.39433000000001,28.05619],"type":"Point"}
}