{
  "type": "Feature",
  "properties": {
    "gn:admin1_code":"5",
    "gn:asciiname":"Deh One Hundred Seventy-three",
    "gn:country_code":"PK",
    "gn:dem":11,
    "gn:feature_class":"P",
    "gn:feature_code":"PPL",
    "gn:name":"Deh One Hundred Seventy-three",
    "gn:population":0,
    "gn:timezone":"Asia/Karachi",
    "iso:country":"PK",
    "wof:name":"Deh One Hundred Seventy-three",
    "wof:placetype":"locality"
},
  "geometry": {"coordinates":[69.10528000000001,25.13519],"type":"Point"}
}