{
  "type": "Feature",
  "properties": {
    "gn:admin1_code":"7.0",
    "gn:asciiname":"Ziarpa Baihk",
    "gn:country_code":"PK",
    "gn:dem":4329,
    "gn:feature_class":"P",
    "gn:feature_code":"PPL",
    "gn:name":"Ziarpa Baihk",
    "gn:population":0,
    "gn:timezone":"Asia/Karachi",
    "iso:country":"PK",
    "wof:name":"Ziarpa Baihk",
    "wof:placetype":"locality"
},
  "geometry": {"coordinates":[75.61785999999999,35.06768],"type":"Point"}
}