{
  "type": "Feature",
  "properties": {
    "gn:admin1_code":"4.0",
    "gn:asciiname":"Basti Haji Ghulam",
    "gn:country_code":"PK",
    "gn:dem":105,
    "gn:feature_class":"P",
    "gn:feature_code":"PPL",
    "gn:name":"Basti Haji Ghulam",
    "gn:population":0,
    "gn:timezone":"Asia/Karachi",
    "iso:country":"PK",
    "wof:name":"Basti Haji Ghulam",
    "wof:placetype":"locality"
},
  "geometry": {"coordinates":[71.12675,29.37169],"type":"Point"}
}