{
  "type": "Feature",
  "properties": {
    "gn:admin1_code":"3.0",
    "gn:asciiname":"Dalli Dheri",
    "gn:country_code":"PK",
    "gn:dem":359,
    "gn:feature_class":"P",
    "gn:feature_code":"PPL",
    "gn:name":"Dalli Dheri",
    "gn:population":0,
    "gn:timezone":"Asia/Karachi",
    "iso:country":"PK",
    "wof:name":"Dalli Dheri",
    "wof:placetype":"locality"
},
  "geometry": {"coordinates":[71.58575,33.92809],"type":"Point"}
}