{
  "type": "Feature",
  "properties": {
    "gn:admin1_code":"4",
    "gn:asciiname":"Chak Eighty-four ML",
    "gn:country_code":"PK",
    "gn:dem":163,
    "gn:feature_class":"P",
    "gn:feature_code":"PPL",
    "gn:name":"Chak Eighty-four ML",
    "gn:population":0,
    "gn:timezone":"Asia/Karachi",
    "iso:country":"PK",
    "name:und_x_variant":[
        "Chak 84 ML"
    ],
    "wof:name":"Chak Eighty-four ML",
    "wof:placetype":"locality"
},
  "geometry": {"coordinates":[71.05764000000001,31.36586],"type":"Point"}
}