{
  "type": "Feature",
  "properties": {
    "gn:admin1_code":"2.0",
    "gn:asciiname":"Kili Gokab",
    "gn:country_code":"PK",
    "gn:dem":830,
    "gn:feature_class":"P",
    "gn:feature_code":"PPL",
    "gn:name":"Kili Gokab",
    "gn:population":0,
    "gn:timezone":"Asia/Karachi",
    "iso:country":"PK",
    "wof:name":"Kili Gokab",
    "wof:placetype":"locality"
},
  "geometry": {"coordinates":[65.44471,29.05041],"type":"Point"}
}