{
  "type": "Feature",
  "properties": {
    "gn:admin1_code":"4",
    "gn:asciiname":"Azmatabad",
    "gn:country_code":"PK",
    "gn:dem":175,
    "gn:feature_class":"P",
    "gn:feature_code":"PPL",
    "gn:name":"Azmatabad",
    "gn:population":0,
    "gn:timezone":"Asia/Karachi",
    "iso:country":"PK",
    "name:und_x_variant":[
        "Asmat\u0101b\u0101d"
    ],
    "wof:name":"Azmatabad",
    "wof:placetype":"locality"
},
  "geometry": {"coordinates":[70.64081999999998,31.1409],"type":"Point"}
}