{
  "type": "Feature",
  "properties": {
    "gn:admin1_code":"3.0",
    "gn:asciiname":"Kai",
    "gn:country_code":"PK",
    "gn:dem":917,
    "gn:feature_class":"P",
    "gn:feature_code":"PPL",
    "gn:name":"Kai",
    "gn:population":0,
    "gn:timezone":"Asia/Karachi",
    "iso:country":"PK",
    "name:und_x_variant":[
        "Kayya Kach"
    ],
    "wof:name":"Kai",
    "wof:placetype":"locality"
},
  "geometry": {"coordinates":[71.37336999999999,33.13637],"type":"Point"}
}