{
  "type": "Feature",
  "properties": {
    "gn:admin1_code":"4",
    "gn:asciiname":"Jhok Khewawali",
    "gn:country_code":"PK",
    "gn:dem":185,
    "gn:feature_class":"P",
    "gn:feature_code":"PPL",
    "gn:name":"Jhok Khewawali",
    "gn:population":0,
    "gn:timezone":"Asia/Karachi",
    "iso:country":"PK",
    "name:und_x_variant":[
        "Khewew\u0101li"
    ],
    "wof:name":"Jhok Khewawali",
    "wof:placetype":"locality"
},
  "geometry": {"coordinates":[70.58763,30.66204],"type":"Point"}
}