{
  "type": "Feature",
  "properties": {
    "gn:admin1_code":"4.0",
    "gn:asciiname":"Halla",
    "gn:country_code":"PK",
    "gn:dem":191,
    "gn:feature_class":"P",
    "gn:feature_code":"PPL",
    "gn:name":"Halla",
    "gn:population":0,
    "gn:timezone":"Asia/Karachi",
    "iso:country":"PK",
    "name:fas_x_preferred":[
        "\u0647\u0644\u0627"
    ],
    "name:urd_x_preferred":[
        "\u06c1\u0644\u06c1"
    ],
    "wof:name":"Halla",
    "wof:placetype":"locality"
},
  "geometry": {"coordinates":[73.7248,31.11937],"type":"Point"}
}