{
  "type": "Feature",
  "properties": {
    "gn:admin1_code":"4",
    "gn:asciiname":"Salhanwala",
    "gn:country_code":"PK",
    "gn:dem":162,
    "gn:feature_class":"P",
    "gn:feature_code":"PPL",
    "gn:name":"Salhanwala",
    "gn:population":0,
    "gn:timezone":"Asia/Karachi",
    "iso:country":"PK",
    "name:und_x_variant":[
        "Solhanw\u0101la"
    ],
    "wof:name":"Salhanwala",
    "wof:placetype":"locality"
},
  "geometry": {"coordinates":[71.00608000000003,31.40074000000001],"type":"Point"}
}