{
  "type": "Feature",
  "properties": {
    "gn:admin1_code":"3.0",
    "gn:asciiname":"Dallo Khel",
    "gn:country_code":"PK",
    "gn:dem":275,
    "gn:feature_class":"P",
    "gn:feature_code":"PPL",
    "gn:name":"Dallo Khel",
    "gn:population":0,
    "gn:timezone":"Asia/Karachi",
    "iso:country":"PK",
    "name:und_x_variant":[
        "Dalu Khel",
        "Dallo Khel"
    ],
    "wof:name":"Dallo Khel",
    "wof:placetype":"locality"
},
  "geometry": {"coordinates":[70.86069000000001,32.60326],"type":"Point"}
}