{
  "type": "Feature",
  "properties": {
    "gn:admin1_code":"3.0",
    "gn:asciiname":"Mairi Banda",
    "gn:country_code":"PK",
    "gn:dem":877,
    "gn:feature_class":"P",
    "gn:feature_code":"PPL",
    "gn:name":"Mairi Banda",
    "gn:population":0,
    "gn:timezone":"Asia/Karachi",
    "iso:country":"PK",
    "wof:name":"Mairi Banda",
    "wof:placetype":"locality"
},
  "geometry": {"coordinates":[72.64381,34.24454],"type":"Point"}
}