{
  "type": "Feature",
  "properties": {
    "gn:admin1_code":"4.0",
    "gn:asciiname":"Shah Miani Basti",
    "gn:country_code":"PK",
    "gn:dem":123,
    "gn:feature_class":"P",
    "gn:feature_code":"PPL",
    "gn:name":"Shah Miani Basti",
    "gn:population":0,
    "gn:timezone":"Asia/Karachi",
    "iso:country":"PK",
    "name:eng_x_preferred":[
        "Sh\u0101h Mi\u0101ni Busti"
    ],
    "wof:name":"Shah Miani Basti",
    "wof:placetype":"locality"
},
  "geometry": {"coordinates":[70.66512,30.18264000000001],"type":"Point"}
}