{
  "type": "Feature",
  "properties": {
    "gn:admin1_code":"6",
    "gn:asciiname":"Haila",
    "gn:country_code":"PK",
    "gn:dem":993,
    "gn:feature_class":"P",
    "gn:feature_code":"PPL",
    "gn:name":"Haila",
    "gn:population":0,
    "gn:timezone":"Asia/Karachi",
    "iso:country":"PK",
    "wof:name":"Haila",
    "wof:placetype":"locality"
},
  "geometry": {"coordinates":[73.72906999999999,34.17148],"type":"Point"}
}