{
  "type": "Feature",
  "properties": {
    "gn:admin1_code":"3",
    "gn:asciiname":"Smats",
    "gn:country_code":"PK",
    "gn:dem":1967,
    "gn:feature_class":"P",
    "gn:feature_code":"PPL",
    "gn:name":"Smats",
    "gn:population":0,
    "gn:timezone":"Asia/Karachi",
    "iso:country":"PK",
    "wof:name":"Smats",
    "wof:placetype":"locality"
},
  "geometry": {"coordinates":[72.56371999999998,35.18198],"type":"Point"}
}