{
  "type": "Feature",
  "properties": {
    "gn:admin1_code":"5.0",
    "gn:asciiname":"Goth Haji Sahrab Khan Jakhrani",
    "gn:country_code":"PK",
    "gn:dem":55,
    "gn:feature_class":"P",
    "gn:feature_code":"PPL",
    "gn:name":"Goth Haji Sahrab Khan Jakhrani",
    "gn:population":0,
    "gn:timezone":"Asia/Karachi",
    "iso:country":"PK",
    "name:und_x_variant":[
        "Goth H\u0101ji Sohr\u0101b Kh\u0101n Jakhr\u0101"
    ],
    "wof:name":"Goth Haji Sahrab Khan Jakhrani",
    "wof:placetype":"locality"
},
  "geometry": {"coordinates":[68.28543000000001,27.94874],"type":"Point"}
}