{
  "type": "Feature",
  "properties": {
    "gn:admin1_code":"4",
    "gn:asciiname":"Basti Babar",
    "gn:country_code":"PK",
    "gn:dem":83,
    "gn:feature_class":"P",
    "gn:feature_code":"PPL",
    "gn:name":"Basti Babar",
    "gn:population":0,
    "gn:timezone":"Asia/Karachi",
    "iso:country":"PK",
    "name:und_x_variant":[
        "Goth B\u0101bre"
    ],
    "wof:name":"Basti Babar",
    "wof:placetype":"locality"
},
  "geometry": {"coordinates":[69.95805,28.49044],"type":"Point"}
}