{
  "type": "Feature",
  "properties": {
    "gn:admin1_code":"8.0",
    "gn:asciiname":"Dhok Nawab",
    "gn:country_code":"PK",
    "gn:dem":457,
    "gn:feature_class":"P",
    "gn:feature_code":"PPL",
    "gn:name":"Dhok Nawab",
    "gn:population":0,
    "gn:timezone":"Asia/Karachi",
    "iso:country":"PK",
    "name:eng_x_preferred":[
        "Dhok Mai Naw\u0101b"
    ],
    "wof:name":"Dhok Nawab",
    "wof:placetype":"locality"
},
  "geometry": {"coordinates":[73.13504,33.55642],"type":"Point"}
}