{
  "type": "Feature",
  "properties": {
    "gn:admin1_code":"3.0",
    "gn:asciiname":"Bhanrh",
    "gn:country_code":"PK",
    "gn:dem":3060,
    "gn:feature_class":"P",
    "gn:feature_code":"PPL",
    "gn:name":"Bhanrh",
    "gn:population":0,
    "gn:timezone":"Asia/Karachi",
    "iso:country":"PK",
    "name:eng_x_preferred":[
        "Bhanrh"
    ],
    "wof:name":"Bhanrh",
    "wof:placetype":"locality"
},
  "geometry": {"coordinates":[72.41343000000001,35.70999000000001],"type":"Point"}
}