{
  "type": "Feature",
  "properties": {
    "gn:admin1_code":"5.0",
    "gn:asciiname":"Miani",
    "gn:country_code":"PK",
    "gn:dem":41,
    "gn:feature_class":"P",
    "gn:feature_code":"PPL",
    "gn:name":"Miani",
    "gn:population":0,
    "gn:timezone":"Asia/Karachi",
    "iso:country":"PK",
    "name:cat_x_preferred":[
        "Miani"
    ],
    "name:ceb_x_preferred":[
        "Miani"
    ],
    "name:deu_x_preferred":[
        "Miani"
    ],
    "name:ita_x_preferred":[
        "Miani"
    ],
    "name:rus_x_preferred":[
        "\u041c\u0438\u0430\u043d\u0438"
    ],
    "name:swe_x_preferred":[
        "Miani"
    ],
    "name:und_x_variant":[
        "Mi\u0101n"
    ],
    "wof:name":"Miani",
    "wof:placetype":"locality"
},
  "geometry": {"coordinates":[67.69204999999999,27.02205],"type":"Point"}
}