{
  "type": "Feature",
  "properties": {
    "gn:admin1_code":"4.0",
    "gn:asciiname":"Para Arjun",
    "gn:country_code":"PK",
    "gn:dem":501,
    "gn:feature_class":"P",
    "gn:feature_code":"PPL",
    "gn:name":"Para Arjun",
    "gn:population":0,
    "gn:timezone":"Asia/Karachi",
    "iso:country":"PK",
    "wof:name":"Para Arjun",
    "wof:placetype":"locality"
},
  "geometry": {"coordinates":[73.21204,33.3575],"type":"Point"}
}