{
  "type": "Feature",
  "properties": {
    "gn:admin1_code":"5.0",
    "gn:asciiname":"Dost Mohammad Chandio",
    "gn:country_code":"PK",
    "gn:dem":8,
    "gn:feature_class":"P",
    "gn:feature_code":"PPL",
    "gn:name":"Dost Mohammad Chandio",
    "gn:population":0,
    "gn:timezone":"Asia/Karachi",
    "iso:country":"PK",
    "name:und_x_variant":[
        "H\u0101ji Dost Muhamm Ch\u0101ndio"
    ],
    "wof:name":"Dost Mohammad Chandio",
    "wof:placetype":"locality"
},
  "geometry": {"coordinates":[68.78231,24.63045],"type":"Point"}
}