{
  "type": "Feature",
  "properties": {
    "gn:admin1_code":"5.0",
    "gn:asciiname":"Gothi Haji Mithu Marri",
    "gn:country_code":"PK",
    "gn:dem":14,
    "gn:feature_class":"P",
    "gn:feature_code":"PPL",
    "gn:name":"Gothi Haji Mithu Marri",
    "gn:population":0,
    "gn:timezone":"Asia/Karachi",
    "iso:country":"PK",
    "wof:name":"Gothi Haji Mithu Marri",
    "wof:placetype":"locality"
},
  "geometry": {"coordinates":[69.31973000000001,25.66073],"type":"Point"}
}