{
  "type": "Feature",
  "properties": {
    "gn:admin1_code":"4.0",
    "gn:asciiname":"Dhok Milan",
    "gn:country_code":"PK",
    "gn:dem":406,
    "gn:feature_class":"P",
    "gn:feature_code":"PPL",
    "gn:name":"Dhok Milan",
    "gn:population":0,
    "gn:timezone":"Asia/Karachi",
    "iso:country":"PK",
    "name:und_x_variant":[
        "Dhok Mela",
        "Dhokmila",
        "Dhok Milan"
    ],
    "wof:name":"Dhok Milan",
    "wof:placetype":"locality"
},
  "geometry": {"coordinates":[72.48666999999998,33.19148],"type":"Point"}
}