{
  "type": "Feature",
  "properties": {
    "gn:admin1_code":"5",
    "gn:asciiname":"Siraj Punjabi",
    "gn:country_code":"PK",
    "gn:dem":35,
    "gn:feature_class":"P",
    "gn:feature_code":"PPL",
    "gn:name":"Siraj Punjabi",
    "gn:population":0,
    "gn:timezone":"Asia/Karachi",
    "iso:country":"PK",
    "name:und_x_variant":[
        "Sar\u0101j Kh\u0101n"
    ],
    "wof:name":"Siraj Punjabi",
    "wof:placetype":"locality"
},
  "geometry": {"coordinates":[68.17274999999999,26.42941],"type":"Point"}
}