{
  "type": "Feature",
  "properties": {
    "gn:admin1_code":"4.0",
    "gn:asciiname":"Chah Mahmudwala",
    "gn:country_code":"PK",
    "gn:dem":152,
    "gn:feature_class":"P",
    "gn:feature_code":"PPL",
    "gn:name":"Chah Mahmudwala",
    "gn:population":0,
    "gn:timezone":"Asia/Karachi",
    "iso:country":"PK",
    "name:und_x_variant":[
        "Ch\u0101h Muhammadw\u0101la"
    ],
    "wof:name":"Chah Mahmudwala",
    "wof:placetype":"locality"
},
  "geometry": {"coordinates":[72.25619,31.20916],"type":"Point"}
}