{
  "type": "Feature",
  "properties": {
    "gn:admin1_code":"5",
    "gn:asciiname":"Rawal Solangi",
    "gn:country_code":"PK",
    "gn:dem":44,
    "gn:feature_class":"P",
    "gn:feature_code":"PPL",
    "gn:name":"Rawal Solangi",
    "gn:population":0,
    "gn:timezone":"Asia/Karachi",
    "iso:country":"PK",
    "name:und_x_variant":[
        "Ish\u0101q Phul"
    ],
    "wof:name":"Rawal Solangi",
    "wof:placetype":"locality"
},
  "geometry": {"coordinates":[68.15831,26.81401],"type":"Point"}
}