{
  "type": "Feature",
  "properties": {
    "gn:admin1_code":"3",
    "gn:asciiname":"Banda",
    "gn:country_code":"PK",
    "gn:dem":1461,
    "gn:feature_class":"P",
    "gn:feature_code":"PPL",
    "gn:name":"Banda",
    "gn:population":0,
    "gn:timezone":"Asia/Karachi",
    "iso:country":"PK",
    "name:und_x_variant":[
        "Y\u0101ro B\u0101nda"
    ],
    "wof:name":"Banda",
    "wof:placetype":"locality"
},
  "geometry": {"coordinates":[73.10173,34.66825],"type":"Point"}
}