{
  "type": "Feature",
  "properties": {
    "gn:admin1_code":"2.0",
    "gn:asciiname":"Gang Karki",
    "gn:country_code":"PK",
    "gn:dem":637,
    "gn:feature_class":"P",
    "gn:feature_code":"PPL",
    "gn:name":"Gang Karki",
    "gn:population":0,
    "gn:timezone":"Asia/Karachi",
    "iso:country":"PK",
    "wof:name":"Gang Karki",
    "wof:placetype":"locality"
},
  "geometry": {"coordinates":[63.74929,26.36545],"type":"Point"}
}