{
  "type": "Feature",
  "properties": {
    "gn:admin1_code":"6.0",
    "gn:asciiname":"Tanguha",
    "gn:country_code":"PK",
    "gn:dem":598,
    "gn:feature_class":"P",
    "gn:feature_code":"PPL",
    "gn:name":"Tanguha",
    "gn:population":0,
    "gn:timezone":"Asia/Karachi",
    "iso:country":"PK",
    "wof:name":"Tanguha",
    "wof:placetype":"locality"
},
  "geometry": {"coordinates":[73.67237,33.56937],"type":"Point"}
}