{
  "type": "Feature",
  "properties": {
    "gn:admin1_code":"2.0",
    "gn:asciiname":"Bibargi",
    "gn:country_code":"PK",
    "gn:dem":1467,
    "gn:feature_class":"P",
    "gn:feature_code":"PPL",
    "gn:name":"Bibargi",
    "gn:population":0,
    "gn:timezone":"Asia/Karachi",
    "iso:country":"PK",
    "name:und_x_variant":[
        "Bilbargi",
        "Bibargi"
    ],
    "wof:name":"Bibargi",
    "wof:placetype":"locality"
},
  "geometry": {"coordinates":[67.17278,29.21365],"type":"Point"}
}