{
  "type": "Feature",
  "properties": {
    "gn:admin1_code":"4",
    "gn:asciiname":"Lotanwala Khu",
    "gn:country_code":"PK",
    "gn:dem":84,
    "gn:feature_class":"P",
    "gn:feature_code":"PPL",
    "gn:name":"Lotanw\u0101la Khu",
    "gn:population":0,
    "gn:timezone":"Asia/Karachi",
    "iso:country":"PK",
    "wof:name":"Lotanwala Khu",
    "wof:placetype":"locality"
},
  "geometry": {"coordinates":[70.64305999999998,28.5125],"type":"Point"}
}