{
  "type": "Feature",
  "properties": {
    "gn:admin1_code":"1.0",
    "gn:asciiname":"Ayub Khel",
    "gn:country_code":"PK",
    "gn:dem":1100,
    "gn:feature_class":"P",
    "gn:feature_code":"PPL",
    "gn:name":"Ayub Khel",
    "gn:population":0,
    "gn:timezone":"Asia/Karachi",
    "iso:country":"PK",
    "wof:name":"Ayub Khel",
    "wof:placetype":"locality"
},
  "geometry": {"coordinates":[71.02689000000002,33.92236],"type":"Point"}
}