{
  "type": "Feature",
  "properties": {
    "gn:admin1_code":"4.0",
    "gn:asciiname":"Baknal Lar",
    "gn:country_code":"PK",
    "gn:dem":91,
    "gn:feature_class":"P",
    "gn:feature_code":"PPL",
    "gn:name":"B\u0101kn\u0101l L\u0101r",
    "gn:population":0,
    "gn:timezone":"Asia/Karachi",
    "iso:country":"PK",
    "wof:name":"Baknal Lar",
    "wof:placetype":"locality"
},
  "geometry": {"coordinates":[70.62778,28.74306],"type":"Point"}
}