{
  "type": "Feature",
  "properties": {
    "gn:admin1_code":"5",
    "gn:asciiname":"Gul Muhammad Behrani",
    "gn:country_code":"PK",
    "gn:dem":22,
    "gn:feature_class":"P",
    "gn:feature_code":"PPL",
    "gn:name":"Gul Muhammad Behrani",
    "gn:population":0,
    "gn:timezone":"Asia/Karachi",
    "iso:country":"PK",
    "name:und_x_variant":[
        "Gular Bhar\u0101ni"
    ],
    "wof:name":"Gul Muhammad Behrani",
    "wof:placetype":"locality"
},
  "geometry": {"coordinates":[68.62066999999999,25.46629],"type":"Point"}
}