{
  "type": "Feature",
  "properties": {
    "gn:admin1_code":"5.0",
    "gn:asciiname":"Goth Mihal Khaskheli",
    "gn:country_code":"PK",
    "gn:dem":12,
    "gn:feature_class":"P",
    "gn:feature_code":"PPL",
    "gn:name":"Goth Mihal Khaskheli",
    "gn:population":0,
    "gn:timezone":"Asia/Karachi",
    "iso:country":"PK",
    "name:und_x_variant":[
        "Goth G\u0101do",
        "Goth Mihal Khaskheli"
    ],
    "wof:name":"Goth Mihal Khaskheli",
    "wof:placetype":"locality"
},
  "geometry": {"coordinates":[67.94564,24.69352],"type":"Point"}
}