{
  "type": "Feature",
  "properties": {
    "gn:admin1_code":"4",
    "gn:asciiname":"Basti Drigh",
    "gn:country_code":"PK",
    "gn:dem":79,
    "gn:feature_class":"P",
    "gn:feature_code":"PPL",
    "gn:name":"Basti Drigh",
    "gn:population":0,
    "gn:timezone":"Asia/Karachi",
    "iso:country":"PK",
    "name:und_x_variant":[
        "Goth Drig"
    ],
    "wof:name":"Basti Drigh",
    "wof:placetype":"locality"
},
  "geometry": {"coordinates":[69.94065000000001,28.49873],"type":"Point"}
}