{
  "type": "Feature",
  "properties": {
    "gn:admin1_code":"4.0",
    "gn:asciiname":"Khobar",
    "gn:country_code":"PK",
    "gn:dem":160,
    "gn:feature_class":"P",
    "gn:feature_code":"PPL",
    "gn:name":"Khobar",
    "gn:population":0,
    "gn:timezone":"Asia/Karachi",
    "iso:country":"PK",
    "name:ara_x_preferred":[
        "\u0645\u062d\u0627\u0641\u0638\u0629 \u0627\u0644\u062e\u0628\u0631"
    ],
    "name:arz_x_preferred":[
        "\u0627\u0644\u062e\u0628\u0631"
    ],
    "name:ben_x_preferred":[
        "\u0996\u09cb\u09ac\u09be\u09b0"
    ],
    "name:cat_x_preferred":[
        "Al-Khubar"
    ],
    "name:ceb_x_preferred":[
        "Khobar"
    ],
    "name:che_x_preferred":[
        "\u0425\u043e\u0431\u0430\u0440"
    ],
    "name:deu_x_preferred":[
        "Khobar"
    ],
    "name:epo_x_preferred":[
        "\u0124ubar"
    ],
    "name:fas_x_preferred":[
        "\u062e\u0628\u0631"
    ],
    "name:fin_x_preferred":[
        "Al-Khobar"
    ],
    "name:fra_x_preferred":[
        "Khobar"
    ],
    "name:heb_x_preferred":[
        "\u05d7'\u05d5\u05d1\u05d0\u05e8"
    ],
    "name:hin_x_preferred":[
        "\u0905\u0932-\u0916\u094b\u092c\u0930"
    ],
    "name:hrv_x_preferred":[
        "Khobar"
    ],
    "name:ind_x_preferred":[
        "Khobar"
    ],
    "name:jpn_x_preferred":[
        "\u30a2\u30eb\u30fb\u30b3\u30d0\u30fc\u30eb"
    ],
    "name:kal_x_preferred":[
        "Khobar"
    ],
    "name:kaz_x_preferred":[
        "\u04d8\u043b-\u0425\u0443\u0431\u0430\u0440"
    ],
    "name:kor_x_preferred":[
        "\ucf54\ubc14\ub974"
    ],
    "name:mal_x_preferred":[
        "\u0d16\u0d4b\u0d2c\u0d3e\u0d7c"
    ],
    "name:mzn_x_preferred":[
        "\u0627\u0644\u062e\u0628\u0631"
    ],
    "name:nld_x_preferred":[
        "Khobar"
    ],
    "name:nno_x_preferred":[
        "Al-Khobar"
    ],
    "name:pol_x_preferred":[
        "Al-Chubar"
    ],
    "name:rus_x_preferred":[
        "\u042d\u043b\u044c-\u0425\u0443\u0431\u0430\u0440"
    ],
    "name:spa_x_preferred":[
        "Al Kobhar"
    ],
    "name:swe_x_preferred":[
        "Khobar"
    ],
    "name:tgl_x_preferred":[
        "Khobar"
    ],
    "name:tur_x_preferred":[
        "El-Huber"
    ],
    "name:ukr_x_preferred":[
        "\u0415\u043b\u044c-\u0425\u0443\u0431\u0430\u0440"
    ],
    "name:urd_x_preferred":[
        "\u0627\u0644\u062e\u0628\u0631"
    ],
    "name:vie_x_preferred":[
        "Khobar"
    ],
    "wof:name":"Khobar",
    "wof:placetype":"locality"
},
  "geometry": {"coordinates":[73.14650999999998,29.78856],"type":"Point"}
}