{
  "type": "Feature",
  "properties": {
    "gn:admin1_code":"5",
    "gn:asciiname":"Goth Pajootha",
    "gn:country_code":"PK",
    "gn:dem":35,
    "gn:feature_class":"P",
    "gn:feature_code":"PPL",
    "gn:name":"Goth Pajootha",
    "gn:population":0,
    "gn:timezone":"Asia/Karachi",
    "iso:country":"PK",
    "name:und_x_variant":[
        "Goth Panju Memon"
    ],
    "wof:name":"Goth Pajootha",
    "wof:placetype":"locality"
},
  "geometry": {"coordinates":[67.83005,26.40532],"type":"Point"}
}