{
  "type": "Feature",
  "properties": {
    "gn:admin1_code":"5.0",
    "gn:asciiname":"Mithrio Bhogi",
    "gn:country_code":"PK",
    "gn:dem":31,
    "gn:feature_class":"P",
    "gn:feature_code":"PPL",
    "gn:name":"Mithrio Bhogi",
    "gn:population":0,
    "gn:timezone":"Asia/Karachi",
    "iso:country":"PK",
    "name:und_x_variant":[
        "Mithrio Boghi"
    ],
    "wof:name":"Mithrio Bhogi",
    "wof:placetype":"locality"
},
  "geometry": {"coordinates":[70.96019,24.7291],"type":"Point"}
}