{
  "type": "Feature",
  "properties": {
    "gn:admin1_code":"3.0",
    "gn:asciiname":"Kot Muhammad Jan",
    "gn:country_code":"PK",
    "gn:dem":424,
    "gn:feature_class":"P",
    "gn:feature_code":"PPL",
    "gn:name":"Kot Muhammad Jan",
    "gn:population":0,
    "gn:timezone":"Asia/Karachi",
    "iso:country":"PK",
    "name:und_x_variant":[
        "Kotkai Muhammad J\u0101n"
    ],
    "wof:name":"Kot Muhammad Jan",
    "wof:placetype":"locality"
},
  "geometry": {"coordinates":[70.54034,33.02782],"type":"Point"}
}