{
  "type": "Feature",
  "properties": {
    "gn:admin1_code":"3.0",
    "gn:asciiname":"Chapli Banda",
    "gn:country_code":"PK",
    "gn:dem":745,
    "gn:feature_class":"P",
    "gn:feature_code":"PPL",
    "gn:name":"Chapli Banda",
    "gn:population":0,
    "gn:timezone":"Asia/Karachi",
    "iso:country":"PK",
    "name:und_x_variant":[
        "B\u0101nda Chapli"
    ],
    "wof:name":"Chapli Banda",
    "wof:placetype":"locality"
},
  "geometry": {"coordinates":[71.26368000000002,33.18217],"type":"Point"}
}