{
  "type": "Feature",
  "properties": {
    "gn:admin1_code":"3",
    "gn:asciiname":"Shah Alam Serai",
    "gn:country_code":"PK",
    "gn:dem":374,
    "gn:feature_class":"P",
    "gn:feature_code":"PPL",
    "gn:name":"Shah Alam Serai",
    "gn:population":0,
    "gn:timezone":"Asia/Karachi",
    "iso:country":"PK",
    "name:eng_x_preferred":[
        "Lakha Tibba Dheri"
    ],
    "name:und_x_variant":[
        "Lakha Tiga Dheri",
        "Shah Alam Serai"
    ],
    "wof:name":"Shah Alam Serai",
    "wof:placetype":"locality"
},
  "geometry": {"coordinates":[72.35011999999998,34.27779],"type":"Point"}
}