{
  "type": "Feature",
  "properties": {
    "gn:admin1_code":"1.0",
    "gn:asciiname":"Haiki Gada",
    "gn:country_code":"PK",
    "gn:dem":2198,
    "gn:feature_class":"P",
    "gn:feature_code":"PPL",
    "gn:name":"Haiki Gada",
    "gn:population":0,
    "gn:timezone":"Asia/Karachi",
    "iso:country":"PK",
    "name:und_x_variant":[
        "Haiki Kadda"
    ],
    "wof:name":"Haiki Gada",
    "wof:placetype":"locality"
},
  "geometry": {"coordinates":[70.61190999999999,33.77969],"type":"Point"}
}