{
  "type": "Feature",
  "properties": {
    "gn:admin1_code":"5.0",
    "gn:asciiname":"Shahabad",
    "gn:country_code":"PK",
    "gn:dem":48,
    "gn:feature_class":"P",
    "gn:feature_code":"PPL",
    "gn:name":"Shahabad",
    "gn:population":0,
    "gn:timezone":"Asia/Karachi",
    "iso:country":"PK",
    "name:ben_x_preferred":[
        "\u09b6\u09be\u09b9\u09be\u09ac\u09be\u09a6"
    ],
    "name:ceb_x_preferred":[
        "Shahabad"
    ],
    "name:fas_x_preferred":[
        "\u0634\u0627\u0647\u200c\u0622\u0628\u0627\u062f"
    ],
    "name:nld_x_preferred":[
        "Shahabad"
    ],
    "name:pol_x_preferred":[
        "Shahabad"
    ],
    "name:swe_x_preferred":[
        "Shahabad"
    ],
    "wof:name":"Shahabad",
    "wof:placetype":"locality"
},
  "geometry": {"coordinates":[67.95926999999999,27.88989],"type":"Point"}
}