{
  "type": "Feature",
  "properties": {
    "gn:admin1_code":"4.0",
    "gn:asciiname":"Deodi",
    "gn:country_code":"PK",
    "gn:dem":247,
    "gn:feature_class":"P",
    "gn:feature_code":"PPL",
    "gn:name":"Deodi",
    "gn:population":0,
    "gn:timezone":"Asia/Karachi",
    "iso:country":"PK",
    "name:und_x_variant":[
        "Deodhi",
        "Deodi"
    ],
    "wof:name":"Deodi",
    "wof:placetype":"locality"
},
  "geometry": {"coordinates":[75.02665999999998,32.15866],"type":"Point"}
}