{
  "type": "Feature",
  "properties": {
    "gn:admin1_code":"4",
    "gn:asciiname":"Jolaianwali Basti",
    "gn:country_code":"PK",
    "gn:dem":131,
    "gn:feature_class":"P",
    "gn:feature_code":"PPL",
    "gn:name":"Jolaianwali Basti",
    "gn:population":0,
    "gn:timezone":"Asia/Karachi",
    "iso:country":"PK",
    "name:und_x_variant":[
        "Jol\u0101i\u0101nw\u0101la"
    ],
    "wof:name":"Jolaianwali Basti",
    "wof:placetype":"locality"
},
  "geometry": {"coordinates":[72.30533,29.60865],"type":"Point"}
}