{
  "type": "Feature",
  "properties": {
    "gn:admin1_code":"3.0",
    "gn:asciiname":"Khanu",
    "gn:country_code":"PK",
    "gn:dem":228,
    "gn:feature_class":"P",
    "gn:feature_code":"PPL",
    "gn:name":"Khanu",
    "gn:population":0,
    "gn:timezone":"Asia/Karachi",
    "iso:country":"PK",
    "name:und_x_variant":[
        "Kh\u0101n\u016bn"
    ],
    "wof:name":"Khanu",
    "wof:placetype":"locality"
},
  "geometry": {"coordinates":[70.55067,32.19394],"type":"Point"}
}