{
  "type": "Feature",
  "properties": {
    "gn:admin1_code":"2.0",
    "gn:asciiname":"Ghaus Bakhsh",
    "gn:country_code":"PK",
    "gn:dem":63,
    "gn:feature_class":"P",
    "gn:feature_code":"PPL",
    "gn:name":"Ghaus Bakhsh",
    "gn:population":0,
    "gn:timezone":"Asia/Karachi",
    "iso:country":"PK",
    "name:und_x_variant":[
        "Ghous Bakhsh"
    ],
    "wof:name":"Ghaus Bakhsh",
    "wof:placetype":"locality"
},
  "geometry": {"coordinates":[68.09943,28.4556],"type":"Point"}
}