{
  "type": "Feature",
  "properties": {
    "gn:admin1_code":"2.0",
    "gn:asciiname":"Atta Muhammad",
    "gn:country_code":"PK",
    "gn:dem":2098,
    "gn:feature_class":"P",
    "gn:feature_code":"PPL",
    "gn:name":"Atta Muhammad",
    "gn:population":0,
    "gn:timezone":"Asia/Karachi",
    "iso:country":"PK",
    "wof:name":"Atta Muhammad",
    "wof:placetype":"locality"
},
  "geometry": {"coordinates":[67.83157,31.50816],"type":"Point"}
}