{
  "type": "Feature",
  "properties": {
    "gn:admin1_code":"1",
    "gn:asciiname":"Kharasha",
    "gn:country_code":"PK",
    "gn:dem":1448,
    "gn:feature_class":"P",
    "gn:feature_code":"PPL",
    "gn:name":"Kharasha",
    "gn:population":0,
    "gn:timezone":"Asia/Karachi",
    "iso:country":"PK",
    "name:und_x_variant":[
        "Kharsh\u0101h"
    ],
    "wof:name":"Kharasha",
    "wof:placetype":"locality"
},
  "geometry": {"coordinates":[71.08206,33.79037],"type":"Point"}
}