{
  "type": "Feature",
  "properties": {
    "gn:admin1_code":"5.0",
    "gn:asciiname":"Goth Haibat Khoso",
    "gn:country_code":"PK",
    "gn:dem":114,
    "gn:feature_class":"P",
    "gn:feature_code":"PPL",
    "gn:name":"Goth Haibat Khoso",
    "gn:population":0,
    "gn:timezone":"Asia/Karachi",
    "iso:country":"PK",
    "name:und_x_variant":[
        "Goth Ha\u012bbat Kh\u0101n"
    ],
    "wof:name":"Goth Haibat Khoso",
    "wof:placetype":"locality"
},
  "geometry": {"coordinates":[67.92319000000001,25.55435],"type":"Point"}
}