{
  "type": "Feature",
  "properties": {
    "gn:admin1_code":"01",
    "gn:asciiname":"Bar Spparai",
    "gn:country_code":"PK",
    "gn:dem":1352,
    "gn:feature_class":"P",
    "gn:feature_code":"PPL",
    "gn:name":"Bar Spparai",
    "gn:population":0,
    "gn:timezone":"Asia/Karachi",
    "iso:country":"PK",
    "name:eng_x_preferred":[
        "Bar Tsapparai"
    ],
    "name:und_x_variant":[
        "Bar Sapparai",
        "Bar Spparai",
        "Ber Saparai"
    ],
    "wof:name":"Bar Spparai",
    "wof:placetype":"locality"
},
  "geometry": {"coordinates":[71.71351,34.68078],"type":"Point"}
}