{
  "type": "Feature",
  "properties": {
    "gn:admin1_code":"2.0",
    "gn:asciiname":"Kili Ramzan",
    "gn:country_code":"PK",
    "gn:dem":1788,
    "gn:feature_class":"P",
    "gn:feature_code":"PPL",
    "gn:name":"Kili Ramzan",
    "gn:population":0,
    "gn:timezone":"Asia/Karachi",
    "iso:country":"PK",
    "name:und_x_variant":[
        "Kili"
    ],
    "wof:name":"Kili Ramzan",
    "wof:placetype":"locality"
},
  "geometry": {"coordinates":[69.7882,31.38227],"type":"Point"}
}