{
  "type": "Feature",
  "properties": {
    "gn:admin1_code":"4.0",
    "gn:asciiname":"Faridabad",
    "gn:country_code":"PK",
    "gn:dem":93,
    "gn:feature_class":"P",
    "gn:feature_code":"PPL",
    "gn:name":"Faridabad",
    "gn:population":0,
    "gn:timezone":"Asia/Karachi",
    "iso:country":"PK",
    "name:urd_x_preferred":[
        "Basti Far\u012bd\u0101bad"
    ],
    "wof:name":"Faridabad",
    "wof:placetype":"locality"
},
  "geometry": {"coordinates":[70.59993,28.83799],"type":"Point"}
}