{
  "type": "Feature",
  "properties": {
    "gn:admin1_code":"01",
    "gn:asciiname":"Pitag Kalle",
    "gn:country_code":"PK",
    "gn:dem":1557,
    "gn:feature_class":"P",
    "gn:feature_code":"PPL",
    "gn:name":"Pitag Kalle",
    "gn:population":0,
    "gn:timezone":"Asia/Karachi",
    "iso:country":"PK",
    "name:und_x_variant":[
        "Pit\u0101g Kili"
    ],
    "wof:name":"Pitag Kalle",
    "wof:placetype":"locality"
},
  "geometry": {"coordinates":[69.51952,32.86405],"type":"Point"}
}