{
  "type": "Feature",
  "properties": {
    "gn:admin1_code":"3",
    "gn:asciiname":"Shongali",
    "gn:country_code":"PK",
    "gn:dem":1445,
    "gn:feature_class":"P",
    "gn:feature_code":"PPL",
    "gn:name":"Shongali",
    "gn:population":0,
    "gn:timezone":"Asia/Karachi",
    "iso:country":"PK",
    "name:und_x_variant":[
        "Shungali"
    ],
    "wof:name":"Shongali",
    "wof:placetype":"locality"
},
  "geometry": {"coordinates":[72.92023,34.48277],"type":"Point"}
}