{
  "type": "Feature",
  "properties": {
    "gn:admin1_code":"3",
    "gn:asciiname":"Kunj",
    "gn:country_code":"PK",
    "gn:dem":1037,
    "gn:feature_class":"P",
    "gn:feature_code":"PPL",
    "gn:name":"Kunj",
    "gn:population":0,
    "gn:timezone":"Asia/Karachi",
    "iso:country":"PK",
    "wof:name":"Kunj",
    "wof:placetype":"locality"
},
  "geometry": {"coordinates":[72.34708000000001,34.83166],"type":"Point"}
}