{
  "type": "Feature",
  "properties": {
    "gn:admin1_code":"5",
    "gn:asciiname":"Hashim Khan Dhahri",
    "gn:country_code":"PK",
    "gn:dem":28,
    "gn:feature_class":"P",
    "gn:feature_code":"PPL",
    "gn:name":"Hashim Khan Dhahri",
    "gn:population":0,
    "gn:timezone":"Asia/Karachi",
    "iso:country":"PK",
    "name:und_x_variant":[
        "Hashim Kh\u0101n"
    ],
    "wof:name":"Hashim Khan Dhahri",
    "wof:placetype":"locality"
},
  "geometry": {"coordinates":[68.64095999999999,26.12576],"type":"Point"}
}