{
  "type": "Feature",
  "properties": {
    "gn:admin1_code":"6.0",
    "gn:asciiname":"Nailian",
    "gn:country_code":"PK",
    "gn:dem":1332,
    "gn:feature_class":"P",
    "gn:feature_code":"PPL",
    "gn:name":"Nailian",
    "gn:population":0,
    "gn:timezone":"Asia/Karachi",
    "iso:country":"PK",
    "wof:name":"Nailian",
    "wof:placetype":"locality"
},
  "geometry": {"coordinates":[73.64453,33.88817],"type":"Point"}
}