{
  "type": "Feature",
  "properties": {
    "gn:admin1_code":"4",
    "gn:asciiname":"Jindo Shahwala",
    "gn:country_code":"PK",
    "gn:dem":124,
    "gn:feature_class":"P",
    "gn:feature_code":"PPL",
    "gn:name":"Jindo Shahwala",
    "gn:population":0,
    "gn:timezone":"Asia/Karachi",
    "iso:country":"PK",
    "name:und_x_variant":[
        "Jinda Sh\u0101hw\u0101la"
    ],
    "wof:name":"Jindo Shahwala",
    "wof:placetype":"locality"
},
  "geometry": {"coordinates":[71.96361999999998,29.56358],"type":"Point"}
}