{
  "type": "Feature",
  "properties": {
    "gn:admin1_code":"04",
    "gn:asciiname":"Tib Chohan Khan",
    "gn:country_code":"PK",
    "gn:dem":84,
    "gn:feature_class":"P",
    "gn:feature_code":"PPL",
    "gn:name":"Tib Chohan Khan",
    "gn:population":0,
    "gn:timezone":"Asia/Karachi",
    "iso:country":"PK",
    "name:und_x_variant":[
        "Tib Chuhan",
        "Tib Chauh\u0101n",
        "Tib Chohan Khan"
    ],
    "wof:name":"Tib Chohan Khan",
    "wof:placetype":"locality"
},
  "geometry": {"coordinates":[70.23475000000001,28.57093],"type":"Point"}
}