{
  "type": "Feature",
  "properties": {
    "gn:admin1_code":"4.0",
    "gn:asciiname":"Chak One Hundred Eighty-nine Thal Development Authority",
    "gn:country_code":"PK",
    "gn:dem":178,
    "gn:feature_class":"P",
    "gn:feature_code":"PPL",
    "gn:name":"Chak One Hundred Eighty-nine Thal Development Authority",
    "gn:population":0,
    "gn:timezone":"Asia/Karachi",
    "iso:country":"PK",
    "wof:name":"Chak One Hundred Eighty-nine Thal Development Authority",
    "wof:placetype":"locality"
},
  "geometry": {"coordinates":[71.35966999999999,31.69249000000001],"type":"Point"}
}