{
  "type": "Feature",
  "properties": {
    "gn:admin1_code":"04",
    "gn:asciiname":"Siadhupura",
    "gn:country_code":"PK",
    "gn:dem":199,
    "gn:feature_class":"P",
    "gn:feature_code":"PPL",
    "gn:name":"Siadhupura",
    "gn:population":0,
    "gn:timezone":"Asia/Karachi",
    "iso:country":"PK",
    "name:und_x_variant":[
        "Sidhupura"
    ],
    "wof:name":"Siadhupura",
    "wof:placetype":"locality"
},
  "geometry": {"coordinates":[74.25059,31.13039],"type":"Point"}
}