{
  "type": "Feature",
  "properties": {
    "gn:admin1_code":"2.0",
    "gn:asciiname":"Ghuriasa",
    "gn:country_code":"PK",
    "gn:dem":1857,
    "gn:feature_class":"P",
    "gn:feature_code":"PPL",
    "gn:name":"Ghuriasa",
    "gn:population":0,
    "gn:timezone":"Asia/Karachi",
    "iso:country":"PK",
    "wof:name":"Ghuriasa",
    "wof:placetype":"locality"
},
  "geometry": {"coordinates":[69.96517,31.01244],"type":"Point"}
}