{
  "type": "Feature",
  "properties": {
    "gn:admin1_code":"04",
    "gn:asciiname":"Marali",
    "gn:country_code":"PK",
    "gn:dem":409,
    "gn:feature_class":"P",
    "gn:feature_code":"PPL",
    "gn:name":"Marali",
    "gn:population":0,
    "gn:timezone":"Asia/Karachi",
    "iso:country":"PK",
    "name:und_x_variant":[
        "Mor\u0101li"
    ],
    "wof:name":"Marali",
    "wof:placetype":"locality"
},
  "geometry": {"coordinates":[72.45146,33.04832],"type":"Point"}
}