{
  "type": "Feature",
  "properties": {
    "gn:admin1_code":"3",
    "gn:asciiname":"Sar Mirgam",
    "gn:country_code":"PK",
    "gn:dem":1562,
    "gn:feature_class":"P",
    "gn:feature_code":"PPL",
    "gn:name":"Sar Mirgam",
    "gn:population":0,
    "gn:timezone":"Asia/Karachi",
    "iso:country":"PK",
    "name:eng_x_preferred":[
        "Lar Mirg\u0101m"
    ],
    "wof:name":"Sar Mirgam",
    "wof:placetype":"locality"
},
  "geometry": {"coordinates":[71.81843000000001,35.02774],"type":"Point"}
}