{
  "type": "Feature",
  "properties": {
    "gn:admin1_code":"2.0",
    "gn:asciiname":"Pongai",
    "gn:country_code":"PK",
    "gn:dem":1237,
    "gn:feature_class":"P",
    "gn:feature_code":"PPL",
    "gn:name":"Pongai",
    "gn:population":0,
    "gn:timezone":"Asia/Karachi",
    "iso:country":"PK",
    "wof:name":"Pongai",
    "wof:placetype":"locality"
},
  "geometry": {"coordinates":[67.75278,30.19583],"type":"Point"}
}