{
  "type": "Feature",
  "properties": {
    "gn:admin1_code":"3",
    "gn:asciiname":"Bharasi",
    "gn:country_code":"PK",
    "gn:dem":3071,
    "gn:feature_class":"P",
    "gn:feature_code":"PPL",
    "gn:name":"Bharasi",
    "gn:population":0,
    "gn:timezone":"Asia/Karachi",
    "iso:country":"PK",
    "name:und_x_variant":[
        "Bar\u0101si"
    ],
    "wof:name":"Bharasi",
    "wof:placetype":"locality"
},
  "geometry": {"coordinates":[73.39841,34.72983],"type":"Point"}
}