{
  "type": "Feature",
  "properties": {
    "gn:admin1_code":"2.0",
    "gn:asciiname":"Bazal Karez",
    "gn:country_code":"PK",
    "gn:dem":2099,
    "gn:feature_class":"P",
    "gn:feature_code":"PPL",
    "gn:name":"Bazal Karez",
    "gn:population":0,
    "gn:timezone":"Asia/Karachi",
    "iso:country":"PK",
    "wof:name":"Bazal Karez",
    "wof:placetype":"locality"
},
  "geometry": {"coordinates":[67.91589999999999,31.55123],"type":"Point"}
}