{
  "type": "Feature",
  "properties": {
    "gn:admin1_code":"6.0",
    "gn:asciiname":"Rerah",
    "gn:country_code":"PK",
    "gn:dem":1400,
    "gn:feature_class":"P",
    "gn:feature_code":"PPL",
    "gn:name":"Rerah",
    "gn:population":0,
    "gn:timezone":"Asia/Karachi",
    "iso:country":"PK",
    "wof:name":"Rerah",
    "wof:placetype":"locality"
},
  "geometry": {"coordinates":[73.86686,33.93327],"type":"Point"}
}