{
  "type": "Feature",
  "properties": {
    "gn:admin1_code":"4.0",
    "gn:asciiname":"Pindi Sheriwali",
    "gn:country_code":"PK",
    "gn:dem":181,
    "gn:feature_class":"P",
    "gn:feature_code":"PPL",
    "gn:name":"Pindi Sheriwali",
    "gn:population":0,
    "gn:timezone":"Asia/Karachi",
    "iso:country":"PK",
    "name:und_x_variant":[
        "Pindi Sherew\u0101li"
    ],
    "wof:name":"Pindi Sheriwali",
    "wof:placetype":"locality"
},
  "geometry": {"coordinates":[72.53015000000001,32.22929],"type":"Point"}
}