{
  "type": "Feature",
  "properties": {
    "gn:admin1_code":"6.0",
    "gn:asciiname":"Ziarat Pir Kanhati",
    "gn:country_code":"PK",
    "gn:dem":3297,
    "gn:feature_class":"P",
    "gn:feature_code":"PPL",
    "gn:name":"Ziarat Pir Kanhati",
    "gn:population":0,
    "gn:timezone":"Asia/Karachi",
    "iso:country":"PK",
    "wof:name":"Ziarat Pir Kanhati",
    "wof:placetype":"locality"
},
  "geometry": {"coordinates":[73.90767,34.01859],"type":"Point"}
}