{
  "type": "Feature",
  "properties": {
    "gn:admin1_code":"4.0",
    "gn:asciiname":"Dhok Detial",
    "gn:country_code":"PK",
    "gn:dem":639,
    "gn:feature_class":"P",
    "gn:feature_code":"PPL",
    "gn:name":"Dhok Detial",
    "gn:population":0,
    "gn:timezone":"Asia/Karachi",
    "iso:country":"PK",
    "wof:name":"Dhok Detial",
    "wof:placetype":"locality"
},
  "geometry": {"coordinates":[72.39555,32.76926],"type":"Point"}
}