{
  "type": "Feature",
  "properties": {
    "gn:admin1_code":"5",
    "gn:asciiname":"Yaqub Pinnu Jo Goth",
    "gn:country_code":"PK",
    "gn:dem":16,
    "gn:feature_class":"P",
    "gn:feature_code":"PPL",
    "gn:name":"Yaqub Pinnu Jo Goth",
    "gn:population":0,
    "gn:timezone":"Asia/Karachi",
    "iso:country":"PK",
    "wof:name":"Yaqub Pinnu Jo Goth",
    "wof:placetype":"locality"
},
  "geometry": {"coordinates":[69.1037,25.745],"type":"Point"}
}