{
  "type": "Feature",
  "properties": {
    "gn:admin1_code":"03",
    "gn:asciiname":"Mulla Khel",
    "gn:country_code":"PK",
    "gn:dem":269,
    "gn:feature_class":"P",
    "gn:feature_code":"PPL",
    "gn:name":"Mulla Khel",
    "gn:population":0,
    "gn:timezone":"Asia/Karachi",
    "iso:country":"PK",
    "name:und_x_variant":[
        "Muhammad Kh\u0101n",
        "Mulla Khel"
    ],
    "wof:name":"Mulla Khel",
    "wof:placetype":"locality"
},
  "geometry": {"coordinates":[70.82709,32.69169],"type":"Point"}
}