{
  "type": "Feature",
  "properties": {
    "gn:admin1_code":"3",
    "gn:asciiname":"Pitao Banda",
    "gn:country_code":"PK",
    "gn:dem":858,
    "gn:feature_class":"P",
    "gn:feature_code":"PPL",
    "gn:name":"Pitao B\u0101nda",
    "gn:population":0,
    "gn:timezone":"Asia/Karachi",
    "iso:country":"PK",
    "wof:name":"Pitao Banda",
    "wof:placetype":"locality"
},
  "geometry": {"coordinates":[72.73889,34.46944000000001],"type":"Point"}
}