{
  "type": "Feature",
  "properties": {
    "gn:admin1_code":"3",
    "gn:asciiname":"Darsen",
    "gn:country_code":"PK",
    "gn:dem":2411,
    "gn:feature_class":"P",
    "gn:feature_code":"PPL",
    "gn:name":"Darsen",
    "gn:population":0,
    "gn:timezone":"Asia/Karachi",
    "iso:country":"PK",
    "name:und_x_variant":[
        "Darseri"
    ],
    "wof:name":"Darsen",
    "wof:placetype":"locality"
},
  "geometry": {"coordinates":[73.63226999999998,34.88501],"type":"Point"}
}