{
  "type": "Feature",
  "properties": {
    "gn:admin1_code":"4.0",
    "gn:asciiname":"Wasulpura",
    "gn:country_code":"PK",
    "gn:dem":203,
    "gn:feature_class":"P",
    "gn:feature_code":"PPL",
    "gn:name":"Wasulpura",
    "gn:population":0,
    "gn:timezone":"Asia/Karachi",
    "iso:country":"PK",
    "wof:name":"Wasulpura",
    "wof:placetype":"locality"
},
  "geometry": {"coordinates":[74.25973,31.62855],"type":"Point"}
}