{
  "type": "Feature",
  "properties": {
    "gn:admin1_code":"3",
    "gn:asciiname":"Balai",
    "gn:country_code":"PK",
    "gn:dem":2500,
    "gn:feature_class":"P",
    "gn:feature_code":"PPL",
    "gn:name":"Balai",
    "gn:population":0,
    "gn:timezone":"Asia/Karachi",
    "iso:country":"PK",
    "name:mar_x_preferred":[
        "\u092c\u0932\u093e\u0908"
    ],
    "name:und_x_variant":[
        "B\u0101tai"
    ],
    "wof:name":"Balai",
    "wof:placetype":"locality"
},
  "geometry": {"coordinates":[72.56007,34.74899],"type":"Point"}
}