{
  "type": "Feature",
  "properties": {
    "gn:admin1_code":"5",
    "gn:asciiname":"Goth Samianawali",
    "gn:country_code":"PK",
    "gn:dem":9,
    "gn:feature_class":"P",
    "gn:feature_code":"PPL",
    "gn:name":"Goth Samianawali",
    "gn:population":0,
    "gn:timezone":"Asia/Karachi",
    "iso:country":"PK",
    "name:und_x_variant":[
        "Goth Samr\u0101n\u0101w\u0101li"
    ],
    "wof:name":"Goth Samianawali",
    "wof:placetype":"locality"
},
  "geometry": {"coordinates":[69.62684,25.06438],"type":"Point"}
}