{
  "type": "Feature",
  "properties": {
    "gn:admin1_code":"1.0",
    "gn:asciiname":"Khao Kalle",
    "gn:country_code":"PK",
    "gn:dem":1414,
    "gn:feature_class":"P",
    "gn:feature_code":"PPL",
    "gn:name":"Khao Kalle",
    "gn:population":0,
    "gn:timezone":"Asia/Karachi",
    "iso:country":"PK",
    "name:und_x_variant":[
        "Kh\u0101o"
    ],
    "wof:name":"Khao Kalle",
    "wof:placetype":"locality"
},
  "geometry": {"coordinates":[70.42959999999999,33.64919],"type":"Point"}
}