{
  "type": "Feature",
  "properties": {
    "gn:admin1_code":"2.0",
    "gn:asciiname":"Ghazgai",
    "gn:country_code":"PK",
    "gn:dem":2211,
    "gn:feature_class":"P",
    "gn:feature_code":"PPL",
    "gn:name":"Ghazgai",
    "gn:population":0,
    "gn:timezone":"Asia/Karachi",
    "iso:country":"PK",
    "wof:name":"Ghazgai",
    "wof:placetype":"locality"
},
  "geometry": {"coordinates":[67.85139000000001,30.69167],"type":"Point"}
}