{
  "type": "Feature",
  "properties": {
    "gn:admin1_code":"3.0",
    "gn:asciiname":"Khati Gol",
    "gn:country_code":"PK",
    "gn:dem":1736,
    "gn:feature_class":"P",
    "gn:feature_code":"PPL",
    "gn:name":"Khati Gol",
    "gn:population":0,
    "gn:timezone":"Asia/Karachi",
    "iso:country":"PK",
    "wof:name":"Khati Gol",
    "wof:placetype":"locality"
},
  "geometry": {"coordinates":[73.41965,33.98267],"type":"Point"}
}