{
  "type": "Feature",
  "properties": {
    "gn:admin1_code":"4.0",
    "gn:asciiname":"Hafial",
    "gn:country_code":"PK",
    "gn:dem":465,
    "gn:feature_class":"P",
    "gn:feature_code":"PPL",
    "gn:name":"Hafial",
    "gn:population":0,
    "gn:timezone":"Asia/Karachi",
    "iso:country":"PK",
    "wof:name":"Hafial",
    "wof:placetype":"locality"
},
  "geometry": {"coordinates":[73.44555,33.32946],"type":"Point"}
}