{
  "type": "Feature",
  "properties": {
    "gn:admin1_code":"3.0",
    "gn:asciiname":"Bangla Desh",
    "gn:country_code":"PK",
    "gn:dem":299,
    "gn:feature_class":"P",
    "gn:feature_code":"PPL",
    "gn:name":"Bangla Desh",
    "gn:population":0,
    "gn:timezone":"Asia/Karachi",
    "iso:country":"PK",
    "wof:name":"Bangla Desh",
    "wof:placetype":"locality"
},
  "geometry": {"coordinates":[71.8519,34.09495],"type":"Point"}
}