{
  "type": "Feature",
  "properties": {
    "gn:admin1_code":"6.0",
    "gn:asciiname":"Talipatra",
    "gn:country_code":"PK",
    "gn:dem":1574,
    "gn:feature_class":"P",
    "gn:feature_code":"PPL",
    "gn:name":"Talipatra",
    "gn:population":0,
    "gn:timezone":"Asia/Karachi",
    "iso:country":"PK",
    "wof:name":"Talipatra",
    "wof:placetype":"locality"
},
  "geometry": {"coordinates":[73.88615,34.13812],"type":"Point"}
}