{
  "type": "Feature",
  "properties": {
    "gn:admin1_code":"4",
    "gn:asciiname":"Jhok Mlahdadwali",
    "gn:country_code":"PK",
    "gn:dem":158,
    "gn:feature_class":"P",
    "gn:feature_code":"PPL",
    "gn:name":"Jhok Mlahdadwali",
    "gn:population":0,
    "gn:timezone":"Asia/Karachi",
    "iso:country":"PK",
    "name:und_x_variant":[
        "Jhok L\u0101lw\u0101li"
    ],
    "wof:name":"Jhok Mlahdadwali",
    "wof:placetype":"locality"
},
  "geometry": {"coordinates":[70.63979999999999,30.81657],"type":"Point"}
}