{
  "type": "Feature",
  "properties": {
    "gn:admin1_code":"5.0",
    "gn:asciiname":"Musa Meman",
    "gn:country_code":"PK",
    "gn:dem":3,
    "gn:feature_class":"P",
    "gn:feature_code":"PPL",
    "gn:name":"Musa Meman",
    "gn:population":0,
    "gn:timezone":"Asia/Karachi",
    "iso:country":"PK",
    "wof:name":"Musa Meman",
    "wof:placetype":"locality"
},
  "geometry": {"coordinates":[68.94775,24.4095],"type":"Point"}
}