{
  "type": "Feature",
  "properties": {
    "gn:admin1_code":"4.0",
    "gn:asciiname":"Usri Dhok",
    "gn:country_code":"PK",
    "gn:dem":616,
    "gn:feature_class":"P",
    "gn:feature_code":"PPL",
    "gn:name":"Usri Dhok",
    "gn:population":0,
    "gn:timezone":"Asia/Karachi",
    "iso:country":"PK",
    "wof:name":"Usri Dhok",
    "wof:placetype":"locality"
},
  "geometry": {"coordinates":[72.32764,32.77288],"type":"Point"}
}