{
  "type": "Feature",
  "properties": {
    "gn:admin1_code":"04",
    "gn:asciiname":"Thatta Jae Singh",
    "gn:country_code":"PK",
    "gn:dem":174,
    "gn:feature_class":"P",
    "gn:feature_code":"PPL",
    "gn:name":"Thatta Jae Singh",
    "gn:population":0,
    "gn:timezone":"Asia/Karachi",
    "iso:country":"PK",
    "name:und_x_variant":[
        "Tibbi Jai Singh"
    ],
    "wof:name":"Thatta Jae Singh",
    "wof:placetype":"locality"
},
  "geometry": {"coordinates":[73.23698,30.86405],"type":"Point"}
}