{
  "type": "Feature",
  "properties": {
    "gn:admin1_code":"03",
    "gn:asciiname":"Satbani",
    "gn:country_code":"PK",
    "gn:dem":1362,
    "gn:feature_class":"P",
    "gn:feature_code":"PPL",
    "gn:name":"Satbani",
    "gn:population":0,
    "gn:timezone":"Asia/Karachi",
    "iso:country":"PK",
    "name:urd_x_preferred":[
        "\u0633\u062a \u0628\u0646\u06cc"
    ],
    "wof:name":"Satbani",
    "wof:placetype":"locality"
},
  "geometry": {"coordinates":[73.31829999999999,34.56022],"type":"Point"}
}