{
  "type": "Feature",
  "properties": {
    "gn:admin1_code":"3.0",
    "gn:asciiname":"Daber",
    "gn:country_code":"PK",
    "gn:dem":2036,
    "gn:feature_class":"P",
    "gn:feature_code":"PPL",
    "gn:name":"Daber",
    "gn:population":0,
    "gn:timezone":"Asia/Karachi",
    "iso:country":"PK",
    "wof:name":"Daber",
    "wof:placetype":"locality"
},
  "geometry": {"coordinates":[72.13405999999998,35.18162],"type":"Point"}
}