{
  "type": "Feature",
  "properties": {
    "gn:admin1_code":"4",
    "gn:asciiname":"Dahuwala",
    "gn:country_code":"PK",
    "gn:dem":171,
    "gn:feature_class":"P",
    "gn:feature_code":"PPL",
    "gn:name":"Dahuwala",
    "gn:population":0,
    "gn:timezone":"Asia/Karachi",
    "iso:country":"PK",
    "name:und_x_variant":[
        "Dauw\u0101la"
    ],
    "wof:name":"Dahuwala",
    "wof:placetype":"locality"
},
  "geometry": {"coordinates":[71.1636,31.66166],"type":"Point"}
}