{
  "type": "Feature",
  "properties": {
    "gn:admin1_code":"4",
    "gn:asciiname":"Basti Haji Musa",
    "gn:country_code":"PK",
    "gn:dem":97,
    "gn:feature_class":"P",
    "gn:feature_code":"PPL",
    "gn:name":"Basti Haji Musa",
    "gn:population":0,
    "gn:timezone":"Asia/Karachi",
    "iso:country":"PK",
    "name:und_x_variant":[
        "Juma Dangar"
    ],
    "wof:name":"Basti Haji Musa",
    "wof:placetype":"locality"
},
  "geometry": {"coordinates":[70.49916,29.14561],"type":"Point"}
}