{
  "type": "Feature",
  "properties": {
    "gn:admin1_code":"5.0",
    "gn:asciiname":"Goth Rahim Bakhsh Jakhro",
    "gn:country_code":"PK",
    "gn:dem":14,
    "gn:feature_class":"P",
    "gn:feature_code":"PPL",
    "gn:name":"Goth Rahim Bakhsh Jakhro",
    "gn:population":0,
    "gn:timezone":"Asia/Karachi",
    "iso:country":"PK",
    "name:und_x_variant":[
        "Kotri Pur\u0101n\u012b",
        "Goth Rahim Bakhsh Jakhro"
    ],
    "wof:name":"Goth Rahim Bakhsh Jakhro",
    "wof:placetype":"locality"
},
  "geometry": {"coordinates":[67.98484999999999,24.77478],"type":"Point"}
}