{
  "type": "Feature",
  "properties": {
    "gn:admin1_code":"3.0",
    "gn:asciiname":"Yakh Kohi",
    "gn:country_code":"PK",
    "gn:dem":376,
    "gn:feature_class":"P",
    "gn:feature_code":"PPL",
    "gn:name":"Yakh Kohi",
    "gn:population":0,
    "gn:timezone":"Asia/Karachi",
    "iso:country":"PK",
    "wof:name":"Yakh Kohi",
    "wof:placetype":"locality"
},
  "geometry": {"coordinates":[71.86098,34.32448],"type":"Point"}
}