{
  "type": "Feature",
  "properties": {
    "gn:admin1_code":"4",
    "gn:asciiname":"Garah Rawan",
    "gn:country_code":"PK",
    "gn:dem":168,
    "gn:feature_class":"P",
    "gn:feature_code":"PPL",
    "gn:name":"Garah Rawan",
    "gn:population":0,
    "gn:timezone":"Asia/Karachi",
    "iso:country":"PK",
    "name:und_x_variant":[
        "Girah R\u0101w\u0101n"
    ],
    "wof:name":"Garah Rawan",
    "wof:placetype":"locality"
},
  "geometry": {"coordinates":[70.96478,31.66017],"type":"Point"}
}