{
  "type": "Feature",
  "properties": {
    "gn:admin1_code":"5.0",
    "gn:asciiname":"Kacho Bhil",
    "gn:country_code":"PK",
    "gn:dem":99,
    "gn:feature_class":"P",
    "gn:feature_code":"PPL",
    "gn:name":"Kacho Bhil",
    "gn:population":0,
    "gn:timezone":"Asia/Karachi",
    "iso:country":"PK",
    "wof:name":"Kacho Bhil",
    "wof:placetype":"locality"
},
  "geometry": {"coordinates":[70.32772,24.95161],"type":"Point"}
}