{
  "type": "Feature",
  "properties": {
    "gn:admin1_code":"2.0",
    "gn:asciiname":"Said Khan Bent",
    "gn:country_code":"PK",
    "gn:dem":332,
    "gn:feature_class":"P",
    "gn:feature_code":"PPL",
    "gn:name":"Said Khan Bent",
    "gn:population":0,
    "gn:timezone":"Asia/Karachi",
    "iso:country":"PK",
    "wof:name":"Said Khan Bent",
    "wof:placetype":"locality"
},
  "geometry": {"coordinates":[66.4233,26.51833],"type":"Point"}
}