{
  "type": "Feature",
  "properties": {
    "gn:admin1_code":"7.0",
    "gn:asciiname":"Balam",
    "gn:country_code":"PK",
    "gn:dem":3618,
    "gn:feature_class":"P",
    "gn:feature_code":"PPL",
    "gn:name":"Balam",
    "gn:population":0,
    "gn:timezone":"Asia/Karachi",
    "iso:country":"PK",
    "wof:name":"Balam",
    "wof:placetype":"locality"
},
  "geometry": {"coordinates":[75.76396,35.11042],"type":"Point"}
}