{
  "type": "Feature",
  "properties": {
    "gn:admin1_code":"4",
    "gn:asciiname":"Chunan",
    "gn:country_code":"PK",
    "gn:dem":232,
    "gn:feature_class":"P",
    "gn:feature_code":"PPL",
    "gn:name":"Chunan",
    "gn:population":0,
    "gn:timezone":"Asia/Karachi",
    "iso:country":"PK",
    "name:und_x_variant":[
        "Chanan"
    ],
    "wof:name":"Chunan",
    "wof:placetype":"locality"
},
  "geometry": {"coordinates":[73.76043,32.68644],"type":"Point"}
}