{
  "type": "Feature",
  "properties": {
    "gn:admin1_code":"2",
    "gn:asciiname":"Haji Karez",
    "gn:country_code":"PK",
    "gn:dem":966,
    "gn:feature_class":"P",
    "gn:feature_code":"PPL",
    "gn:name":"Haji Karez",
    "gn:population":0,
    "gn:timezone":"Asia/Karachi",
    "iso:country":"PK",
    "name:und_x_variant":[
        "Karez Zark\u016bm"
    ],
    "wof:name":"Haji Karez",
    "wof:placetype":"locality"
},
  "geometry": {"coordinates":[69.12741,30.15843],"type":"Point"}
}