{
  "type": "Feature",
  "properties": {
    "gn:admin1_code":"4",
    "gn:asciiname":"Chak Seventy-two A South Branch",
    "gn:country_code":"PK",
    "gn:dem":192,
    "gn:feature_class":"P",
    "gn:feature_code":"PPL",
    "gn:name":"Chak Seventy-two A South Branch",
    "gn:population":0,
    "gn:timezone":"Asia/Karachi",
    "iso:country":"PK",
    "name:und_x_variant":[
        "Chak Seventy-two A SB"
    ],
    "wof:name":"Chak Seventy-two A South Branch",
    "wof:placetype":"locality"
},
  "geometry": {"coordinates":[72.84316,32.11273],"type":"Point"}
}