{
  "type": "Feature",
  "properties": {
    "gn:admin1_code":"4",
    "gn:asciiname":"Basti Imam Shah",
    "gn:country_code":"PK",
    "gn:dem":93,
    "gn:feature_class":"P",
    "gn:feature_code":"PPL",
    "gn:name":"Basti Imam Shah",
    "gn:population":0,
    "gn:timezone":"Asia/Karachi",
    "iso:country":"PK",
    "name:und_x_variant":[
        "Im\u0101m Sh\u0101h"
    ],
    "wof:name":"Basti Imam Shah",
    "wof:placetype":"locality"
},
  "geometry": {"coordinates":[70.90804,28.92917000000001],"type":"Point"}
}