{
  "type": "Feature",
  "properties": {
    "gn:admin1_code":"5.0",
    "gn:asciiname":"Khuda Bakhsh Jo Goth",
    "gn:country_code":"PK",
    "gn:dem":58,
    "gn:feature_class":"P",
    "gn:feature_code":"PPL",
    "gn:name":"Khuda Bakhsh Jo Goth",
    "gn:population":0,
    "gn:timezone":"Asia/Karachi",
    "iso:country":"PK",
    "name:eng_x_preferred":[
        "Khuda Bakhsh-Jo-Goth"
    ],
    "wof:name":"Khuda Bakhsh Jo Goth",
    "wof:placetype":"locality"
},
  "geometry": {"coordinates":[68.62546,27.43612000000001],"type":"Point"}
}