{
  "type": "Feature",
  "properties": {
    "gn:admin1_code":"4",
    "gn:asciiname":"Wasanwala",
    "gn:country_code":"PK",
    "gn:dem":131,
    "gn:feature_class":"P",
    "gn:feature_code":"PPL",
    "gn:name":"W\u0101sanw\u0101la",
    "gn:population":0,
    "gn:timezone":"Asia/Karachi",
    "iso:country":"PK",
    "name:eng_x_preferred":[
        "W\u0101sanw\u0101la"
    ],
    "wof:name":"Wasanwala",
    "wof:placetype":"locality"
},
  "geometry": {"coordinates":[70.89148,30.4956],"type":"Point"}
}