{
  "type": "Feature",
  "properties": {
    "gn:admin1_code":"2",
    "gn:asciiname":"Goth Bashkan",
    "gn:country_code":"PK",
    "gn:dem":48,
    "gn:feature_class":"P",
    "gn:feature_code":"PPL",
    "gn:name":"Goth Bashkan",
    "gn:population":0,
    "gn:timezone":"Asia/Karachi",
    "iso:country":"PK",
    "wof:name":"Goth Bashkan",
    "wof:placetype":"locality"
},
  "geometry": {"coordinates":[67.92643000000001,28.07399],"type":"Point"}
}