{
  "type": "Feature",
  "properties": {
    "gn:admin1_code":"2.0",
    "gn:asciiname":"Aghbarg Nishpa",
    "gn:country_code":"PK",
    "gn:dem":1869,
    "gn:feature_class":"P",
    "gn:feature_code":"PPL",
    "gn:name":"Aghbarg Nishpa",
    "gn:population":0,
    "gn:timezone":"Asia/Karachi",
    "iso:country":"PK",
    "wof:name":"Aghbarg Nishpa",
    "wof:placetype":"locality"
},
  "geometry": {"coordinates":[69.94979000000001,31.15524000000001],"type":"Point"}
}