{
  "type": "Feature",
  "properties": {
    "gn:admin1_code":"3",
    "gn:asciiname":"Raluli Gali",
    "gn:country_code":"PK",
    "gn:dem":1720,
    "gn:feature_class":"P",
    "gn:feature_code":"PPL",
    "gn:name":"Raluli Gali",
    "gn:population":0,
    "gn:timezone":"Asia/Karachi",
    "iso:country":"PK",
    "wof:name":"Raluli Gali",
    "wof:placetype":"locality"
},
  "geometry": {"coordinates":[73.29894,34.17975999999999],"type":"Point"}
}