{
  "type": "Feature",
  "properties": {
    "gn:admin1_code":"5.0",
    "gn:asciiname":"Ali Hasan Ramezai",
    "gn:country_code":"PK",
    "gn:dem":65,
    "gn:feature_class":"P",
    "gn:feature_code":"PPL",
    "gn:name":"Ali Hasan Ramezai",
    "gn:population":0,
    "gn:timezone":"Asia/Karachi",
    "iso:country":"PK",
    "wof:name":"Ali Hasan Ramezai",
    "wof:placetype":"locality"
},
  "geometry": {"coordinates":[68.95128000000001,28.39143],"type":"Point"}
}