{
  "type": "Feature",
  "properties": {
    "gn:admin1_code":"4",
    "gn:asciiname":"Mad Bahim",
    "gn:country_code":"PK",
    "gn:dem":87,
    "gn:feature_class":"P",
    "gn:feature_code":"PPL",
    "gn:name":"Mad Bahim",
    "gn:population":0,
    "gn:timezone":"Asia/Karachi",
    "iso:country":"PK",
    "name:und_x_variant":[
        "Mad Rah\u012bm"
    ],
    "wof:name":"Mad Bahim",
    "wof:placetype":"locality"
},
  "geometry": {"coordinates":[70.57380999999999,28.53805],"type":"Point"}
}