{
  "type": "Feature",
  "properties": {
    "gn:admin1_code":"4",
    "gn:asciiname":"Mad Haji Lakhewala",
    "gn:country_code":"PK",
    "gn:dem":98,
    "gn:feature_class":"P",
    "gn:feature_code":"PPL",
    "gn:name":"Mad Haji Lakhewala",
    "gn:population":0,
    "gn:timezone":"Asia/Karachi",
    "iso:country":"PK",
    "name:und_x_variant":[
        "Mad H\u0101ji L\u0101kkew\u0101la"
    ],
    "wof:name":"Mad Haji Lakhewala",
    "wof:placetype":"locality"
},
  "geometry": {"coordinates":[70.30485,29.22167],"type":"Point"}
}