{
  "type": "Feature",
  "properties": {
    "gn:admin1_code":"01",
    "gn:asciiname":"Amlok",
    "gn:country_code":"PK",
    "gn:dem":1831,
    "gn:feature_class":"P",
    "gn:feature_code":"PPL",
    "gn:name":"Amlok",
    "gn:population":0,
    "gn:timezone":"Asia/Karachi",
    "iso:country":"PK",
    "wof:name":"Amlok",
    "wof:placetype":"locality"
},
  "geometry": {"coordinates":[70.52516999999997,33.74082],"type":"Point"}
}