{
  "type": "Feature",
  "properties": {
    "gn:admin1_code":"3",
    "gn:asciiname":"Chaeni",
    "gn:country_code":"PK",
    "gn:dem":952,
    "gn:feature_class":"P",
    "gn:feature_code":"PPL",
    "gn:name":"Chaeni",
    "gn:population":0,
    "gn:timezone":"Asia/Karachi",
    "iso:country":"PK",
    "name:und_x_variant":[
        "Chahoja"
    ],
    "wof:name":"Chaeni",
    "wof:placetype":"locality"
},
  "geometry": {"coordinates":[72.98411,34.31148],"type":"Point"}
}