{
  "type": "Feature",
  "properties": {
    "gn:admin1_code":"4",
    "gn:asciiname":"Kovira Kalan",
    "gn:country_code":"PK",
    "gn:dem":179,
    "gn:feature_class":"P",
    "gn:feature_code":"PPL",
    "gn:name":"Kovira Kalan",
    "gn:population":0,
    "gn:timezone":"Asia/Karachi",
    "iso:country":"PK",
    "name:und_x_variant":[
        "Kav\u012bra"
    ],
    "wof:name":"Kovira Kalan",
    "wof:placetype":"locality"
},
  "geometry": {"coordinates":[73.38724999999999,31.07118],"type":"Point"}
}