{
  "type": "Feature",
  "properties": {
    "gn:admin1_code":"4.0",
    "gn:asciiname":"Thatta Mehr Faqir",
    "gn:country_code":"PK",
    "gn:dem":212,
    "gn:feature_class":"P",
    "gn:feature_code":"PPL",
    "gn:name":"Thatta Mehr Faqir",
    "gn:population":0,
    "gn:timezone":"Asia/Karachi",
    "iso:country":"PK",
    "name:und_x_variant":[
        "Basti Faqir Muhammad"
    ],
    "wof:name":"Thatta Mehr Faqir",
    "wof:placetype":"locality"
},
  "geometry": {"coordinates":[74.32698000000001,31.81453],"type":"Point"}
}