{
  "type": "Feature",
  "properties": {
    "gn:admin1_code":"4",
    "gn:asciiname":"Chak Seven Hundred Sixty-three Gugera Branch",
    "gn:country_code":"PK",
    "gn:dem":145,
    "gn:feature_class":"P",
    "gn:feature_code":"PPL",
    "gn:name":"Chak Seven Hundred Sixty-three Gugera Branch",
    "gn:population":0,
    "gn:timezone":"Asia/Karachi",
    "iso:country":"PK",
    "name:und_x_variant":[
        "Chak Seven Hundred Sixty-three"
    ],
    "wof:name":"Chak Seven Hundred Sixty-three Gugera Branch",
    "wof:placetype":"locality"
},
  "geometry": {"coordinates":[72.33141999999999,30.63399],"type":"Point"}
}