{
  "type": "Feature",
  "properties": {
    "gn:admin1_code":"05",
    "gn:asciiname":"Goth Usman Jamali",
    "gn:country_code":"PK",
    "gn:dem":9,
    "gn:feature_class":"P",
    "gn:feature_code":"PPL",
    "gn:name":"Goth Usman Jamali",
    "gn:population":0,
    "gn:timezone":"Asia/Karachi",
    "iso:country":"PK",
    "name:und_x_variant":[
        "Goth Usm\u0101n J\u0101m\u0101li"
    ],
    "wof:name":"Goth Usman Jamali",
    "wof:placetype":"locality"
},
  "geometry": {"coordinates":[67.92359,24.40882],"type":"Point"}
}