{
  "type": "Feature",
  "properties": {
    "gn:admin1_code":"1.0",
    "gn:asciiname":"Pakha Kalle",
    "gn:country_code":"PK",
    "gn:dem":2218,
    "gn:feature_class":"P",
    "gn:feature_code":"PPL",
    "gn:name":"Pakha Kalle",
    "gn:population":0,
    "gn:timezone":"Asia/Karachi",
    "iso:country":"PK",
    "name:und_x_variant":[
        "Pakha"
    ],
    "wof:name":"Pakha Kalle",
    "wof:placetype":"locality"
},
  "geometry": {"coordinates":[70.31713000000001,33.85717],"type":"Point"}
}