{
  "type": "Feature",
  "properties": {
    "gn:admin1_code":"4",
    "gn:asciiname":"Chak Seventy-four Rakh Branch",
    "gn:country_code":"PK",
    "gn:dem":193,
    "gn:feature_class":"P",
    "gn:feature_code":"PPL",
    "gn:name":"Chak Seventy-four Rakh Branch",
    "gn:population":0,
    "gn:timezone":"Asia/Karachi",
    "iso:country":"PK",
    "name:und_x_variant":[
        "Gurb\u0101jpur",
        "Lohke"
    ],
    "wof:name":"Chak Seventy-four Rakh Branch",
    "wof:placetype":"locality"
},
  "geometry": {"coordinates":[73.31024000000002,31.49066],"type":"Point"}
}