{
  "type": "Feature",
  "properties": {
    "gn:admin1_code":"1.0",
    "gn:asciiname":"Jangai",
    "gn:country_code":"PK",
    "gn:dem":2715,
    "gn:feature_class":"P",
    "gn:feature_code":"PPL",
    "gn:name":"Jangai",
    "gn:population":0,
    "gn:timezone":"Asia/Karachi",
    "iso:country":"PK",
    "wof:name":"Jangai",
    "wof:placetype":"locality"
},
  "geometry": {"coordinates":[70.58584,33.91775],"type":"Point"}
}