{
  "type": "Feature",
  "properties": {
    "gn:admin1_code":"02",
    "gn:asciiname":"Murnal",
    "gn:country_code":"PK",
    "gn:dem":57,
    "gn:feature_class":"P",
    "gn:feature_code":"PPL",
    "gn:name":"Murnal",
    "gn:population":0,
    "gn:timezone":"Asia/Karachi",
    "iso:country":"PK",
    "name:und_x_variant":[
        "Mamal"
    ],
    "wof:name":"Murnal",
    "wof:placetype":"locality"
},
  "geometry": {"coordinates":[68.3677,28.32394],"type":"Point"}
}