{
  "type": "Feature",
  "properties": {
    "gn:admin1_code":"2.0",
    "gn:asciiname":"Jumma Khan",
    "gn:country_code":"PK",
    "gn:dem":1404,
    "gn:feature_class":"P",
    "gn:feature_code":"PPL",
    "gn:name":"Jumma Khan",
    "gn:population":0,
    "gn:timezone":"Asia/Karachi",
    "iso:country":"PK",
    "wof:name":"Jumma Khan",
    "wof:placetype":"locality"
},
  "geometry": {"coordinates":[66.17312,29.72155],"type":"Point"}
}