{
  "type": "Feature",
  "properties": {
    "gn:admin1_code":"4",
    "gn:asciiname":"Farrukhpur Nau",
    "gn:country_code":"PK",
    "gn:dem":203,
    "gn:feature_class":"P",
    "gn:feature_code":"PPL",
    "gn:name":"Farrukhpur Nau",
    "gn:population":0,
    "gn:timezone":"Asia/Karachi",
    "iso:country":"PK",
    "wof:name":"Farrukhpur Nau",
    "wof:placetype":"locality"
},
  "geometry": {"coordinates":[73.43711,32.25491],"type":"Point"}
}