{
  "type": "Feature",
  "properties": {
    "gn:admin1_code":"4.0",
    "gn:asciiname":"Ibrahimwala",
    "gn:country_code":"PK",
    "gn:dem":117,
    "gn:feature_class":"P",
    "gn:feature_code":"PPL",
    "gn:name":"Ibrahimwala",
    "gn:population":0,
    "gn:timezone":"Asia/Karachi",
    "iso:country":"PK",
    "wof:name":"Ibrahimwala",
    "wof:placetype":"locality"
},
  "geometry": {"coordinates":[71.34993,29.82896],"type":"Point"}
}