{
  "type": "Feature",
  "properties": {
    "gn:admin1_code":"3.0",
    "gn:asciiname":"Theh",
    "gn:country_code":"PK",
    "gn:dem":1380,
    "gn:feature_class":"P",
    "gn:feature_code":"PPL",
    "gn:name":"Theh",
    "gn:population":0,
    "gn:timezone":"Asia/Karachi",
    "iso:country":"PK",
    "name:eng_x_preferred":[
        "Theh"
    ],
    "wof:name":"Theh",
    "wof:placetype":"locality"
},
  "geometry": {"coordinates":[73.02349,33.87699],"type":"Point"}
}