{
  "type": "Feature",
  "properties": {
    "gn:admin1_code":"03",
    "gn:asciiname":"Taru Khel",
    "gn:country_code":"PK",
    "gn:dem":268,
    "gn:feature_class":"P",
    "gn:feature_code":"PPL",
    "gn:name":"Taru Khel",
    "gn:population":0,
    "gn:timezone":"Asia/Karachi",
    "iso:country":"PK",
    "name:und_x_variant":[
        "Razza Kh\u0101n",
        "Taru Khel"
    ],
    "wof:name":"Taru Khel",
    "wof:placetype":"locality"
},
  "geometry": {"coordinates":[70.82164,32.68599],"type":"Point"}
}