{
  "type": "Feature",
  "properties": {
    "gn:admin1_code":"2.0",
    "gn:asciiname":"Sabzal Bazar",
    "gn:country_code":"PK",
    "gn:dem":926,
    "gn:feature_class":"P",
    "gn:feature_code":"PPL",
    "gn:name":"Sabzal Bazar",
    "gn:population":0,
    "gn:timezone":"Asia/Karachi",
    "iso:country":"PK",
    "wof:name":"Sabzal Bazar",
    "wof:placetype":"locality"
},
  "geometry": {"coordinates":[64.0797,26.707],"type":"Point"}
}