{
  "type": "Feature",
  "properties": {
    "gn:admin1_code":"2.0",
    "gn:asciiname":"Kilarkot",
    "gn:country_code":"PK",
    "gn:dem":103,
    "gn:feature_class":"P",
    "gn:feature_code":"PPL",
    "gn:name":"Kilarkot",
    "gn:population":0,
    "gn:timezone":"Asia/Karachi",
    "iso:country":"PK",
    "name:und_x_variant":[
        "Goth Rahm\u0101n Kh\u0101n"
    ],
    "wof:name":"Kilarkot",
    "wof:placetype":"locality"
},
  "geometry": {"coordinates":[68.01220000000001,29.07401],"type":"Point"}
}