{
  "type": "Feature",
  "properties": {
    "gn:admin1_code":"2.0",
    "gn:asciiname":"Kili Haji Faizo",
    "gn:country_code":"PK",
    "gn:dem":1521,
    "gn:feature_class":"P",
    "gn:feature_code":"PPL",
    "gn:name":"Kili Haji Faizo",
    "gn:population":0,
    "gn:timezone":"Asia/Karachi",
    "iso:country":"PK",
    "wof:name":"Kili Haji Faizo",
    "wof:placetype":"locality"
},
  "geometry": {"coordinates":[66.99481999999999,30.72231],"type":"Point"}
}