{
  "type": "Feature",
  "properties": {
    "gn:admin1_code":"4.0",
    "gn:asciiname":"Baryarwala",
    "gn:country_code":"PK",
    "gn:dem":183,
    "gn:feature_class":"P",
    "gn:feature_code":"PPL",
    "gn:name":"Baryarwala",
    "gn:population":0,
    "gn:timezone":"Asia/Karachi",
    "iso:country":"PK",
    "name:und_x_variant":[
        "Bari\u0101rw\u0101la"
    ],
    "wof:name":"Baryarwala",
    "wof:placetype":"locality"
},
  "geometry": {"coordinates":[73.33333,31.23333],"type":"Point"}
}