{
  "type": "Feature",
  "properties": {
    "gn:admin1_code":"4.0",
    "gn:asciiname":"Munshiwak",
    "gn:country_code":"PK",
    "gn:dem":116,
    "gn:feature_class":"P",
    "gn:feature_code":"PPL",
    "gn:name":"Munshiwak",
    "gn:population":0,
    "gn:timezone":"Asia/Karachi",
    "iso:country":"PK",
    "name:und_x_variant":[
        "Munshiw\u0101la"
    ],
    "wof:name":"Munshiwak",
    "wof:placetype":"locality"
},
  "geometry": {"coordinates":[71.38930000000001,29.63358],"type":"Point"}
}