{
  "type": "Feature",
  "properties": {
    "gn:admin1_code":"5.0",
    "gn:asciiname":"Yar Khan Khoso",
    "gn:country_code":"PK",
    "gn:dem":66,
    "gn:feature_class":"P",
    "gn:feature_code":"PPL",
    "gn:name":"Yar Khan Khoso",
    "gn:population":0,
    "gn:timezone":"Asia/Karachi",
    "iso:country":"PK",
    "wof:name":"Yar Khan Khoso",
    "wof:placetype":"locality"
},
  "geometry": {"coordinates":[68.81358,28.30333],"type":"Point"}
}