{
  "type": "Feature",
  "properties": {
    "gn:admin1_code":"2.0",
    "gn:asciiname":"Daro Baloch Kili",
    "gn:country_code":"PK",
    "gn:dem":1419,
    "gn:feature_class":"P",
    "gn:feature_code":"PPL",
    "gn:name":"Daro Baloch Kili",
    "gn:population":0,
    "gn:timezone":"Asia/Karachi",
    "iso:country":"PK",
    "wof:name":"Daro Baloch Kili",
    "wof:placetype":"locality"
},
  "geometry": {"coordinates":[66.62691,30.33366],"type":"Point"}
}