{
  "type": "Feature",
  "properties": {
    "gn:admin1_code":"3.0",
    "gn:asciiname":"Amb",
    "gn:country_code":"PK",
    "gn:dem":430,
    "gn:feature_class":"P",
    "gn:feature_code":"PPL",
    "gn:name":"Amb",
    "gn:population":0,
    "gn:timezone":"Asia/Karachi",
    "iso:country":"PK",
    "wof:name":"Amb",
    "wof:placetype":"locality"
},
  "geometry": {"coordinates":[72.85186999999998,34.30968],"type":"Point"}
}