{
  "type": "Feature",
  "properties": {
    "gn:admin1_code":"4.0",
    "gn:asciiname":"Kot Nazir",
    "gn:country_code":"PK",
    "gn:dem":214,
    "gn:feature_class":"P",
    "gn:feature_code":"PPL",
    "gn:name":"Kot Nazir",
    "gn:population":0,
    "gn:timezone":"Asia/Karachi",
    "iso:country":"PK",
    "wof:name":"Kot Nazir",
    "wof:placetype":"locality"
},
  "geometry": {"coordinates":[74.34066999999997,31.81807],"type":"Point"}
}