{
  "type": "Feature",
  "properties": {
    "gn:admin1_code":"03",
    "gn:asciiname":"Piskand",
    "gn:country_code":"PK",
    "gn:dem":728,
    "gn:feature_class":"P",
    "gn:feature_code":"PPL",
    "gn:name":"Piskand",
    "gn:population":0,
    "gn:timezone":"Asia/Karachi",
    "iso:country":"PK",
    "name:und_x_variant":[
        "P\u012bshkanda",
        "Pushkaund",
        "P\u012bshkand",
        "Piskand"
    ],
    "wof:name":"Piskand",
    "wof:placetype":"locality"
},
  "geometry": {"coordinates":[72.73309999999999,34.63666],"type":"Point"}
}