{
  "type": "Feature",
  "properties": {
    "gn:admin1_code":"4.0",
    "gn:asciiname":"Budhon di Basti",
    "gn:country_code":"PK",
    "gn:dem":100,
    "gn:feature_class":"P",
    "gn:feature_code":"PPL",
    "gn:name":"Budhon di Basti",
    "gn:population":0,
    "gn:timezone":"Asia/Karachi",
    "iso:country":"PK",
    "name:und_x_variant":[
        "Basti Budhl\u0101n di"
    ],
    "wof:name":"Budhon di Basti",
    "wof:placetype":"locality"
},
  "geometry": {"coordinates":[71.06787,29.25399],"type":"Point"}
}