{
  "type": "Feature",
  "properties": {
    "gn:admin1_code":"6",
    "gn:asciiname":"Narakot",
    "gn:country_code":"PK",
    "gn:dem":816,
    "gn:feature_class":"P",
    "gn:feature_code":"PPL",
    "gn:name":"Narakot",
    "gn:population":0,
    "gn:timezone":"Asia/Karachi",
    "iso:country":"PK",
    "name:ceb_x_preferred":[
        "Narakot"
    ],
    "name:fra_x_preferred":[
        "Narakot"
    ],
    "name:mai_x_preferred":[
        "\u0928\u0930\u093e\u0915\u094b\u091f"
    ],
    "name:msa_x_preferred":[
        "Narakot"
    ],
    "name:nep_x_preferred":[
        "\u0928\u0930\u093e\u0915\u094b\u091f"
    ],
    "name:pol_x_preferred":[
        "Narakot"
    ],
    "name:und_x_variant":[
        "N\u0101ra Kot"
    ],
    "wof:name":"Narakot",
    "wof:placetype":"locality"
},
  "geometry": {"coordinates":[73.97435,33.28824],"type":"Point"}
}