{
  "type": "Feature",
  "properties": {
    "gn:admin1_code":"3.0",
    "gn:asciiname":"Parao",
    "gn:country_code":"PK",
    "gn:dem":330,
    "gn:feature_class":"P",
    "gn:feature_code":"PPL",
    "gn:name":"Parao",
    "gn:population":0,
    "gn:timezone":"Asia/Karachi",
    "iso:country":"PK",
    "wof:name":"Parao",
    "wof:placetype":"locality"
},
  "geometry": {"coordinates":[71.93174999999999,33.65503],"type":"Point"}
}