{
  "type": "Feature",
  "properties": {
    "gn:admin1_code":"2",
    "gn:asciiname":"Fatehzai",
    "gn:country_code":"PK",
    "gn:dem":1723,
    "gn:feature_class":"P",
    "gn:feature_code":"PPL",
    "gn:name":"Fatehzai",
    "gn:population":0,
    "gn:timezone":"Asia/Karachi",
    "iso:country":"PK",
    "name:und_x_variant":[
        "Pate\u0101nzai"
    ],
    "wof:name":"Fatehzai",
    "wof:placetype":"locality"
},
  "geometry": {"coordinates":[66.57583000000001,29.52565],"type":"Point"}
}