{
  "type": "Feature",
  "properties": {
    "gn:admin1_code":"5.0",
    "gn:asciiname":"Arbab Wali Muhammad Babai",
    "gn:country_code":"PK",
    "gn:dem":23,
    "gn:feature_class":"P",
    "gn:feature_code":"PPL",
    "gn:name":"Arbab Wali Muhammad Babai",
    "gn:population":0,
    "gn:timezone":"Asia/Karachi",
    "iso:country":"PK",
    "name:eng_x_preferred":[
        "Arb\u0101b Wali Muhammad"
    ],
    "wof:name":"Arbab Wali Muhammad Babai",
    "wof:placetype":"locality"
},
  "geometry": {"coordinates":[68.24231,25.11609],"type":"Point"}
}