{
  "type": "Feature",
  "properties": {
    "gn:admin1_code":"2.0",
    "gn:asciiname":"Jumma Gis",
    "gn:country_code":"PK",
    "gn:dem":1324,
    "gn:feature_class":"P",
    "gn:feature_code":"PPL",
    "gn:name":"Jumma Gis",
    "gn:population":0,
    "gn:timezone":"Asia/Karachi",
    "iso:country":"PK",
    "wof:name":"Jumma Gis",
    "wof:placetype":"locality"
},
  "geometry": {"coordinates":[64.18416999999999,29.27779],"type":"Point"}
}