{
  "type": "Feature",
  "properties": {
    "gn:admin1_code":"3.0",
    "gn:asciiname":"Net Bil",
    "gn:country_code":"PK",
    "gn:dem":958,
    "gn:feature_class":"P",
    "gn:feature_code":"PPL",
    "gn:name":"Net Bil",
    "gn:population":0,
    "gn:timezone":"Asia/Karachi",
    "iso:country":"PK",
    "wof:name":"Net Bil",
    "wof:placetype":"locality"
},
  "geometry": {"coordinates":[73.18843000000003,35.46057000000001],"type":"Point"}
}