{
  "type": "Feature",
  "properties": {
    "gn:admin1_code":"4.0",
    "gn:asciiname":"Dhok Mian Kharo Khel",
    "gn:country_code":"PK",
    "gn:dem":394,
    "gn:feature_class":"P",
    "gn:feature_code":"PPL",
    "gn:name":"Dhok Mian Kharo Khel",
    "gn:population":0,
    "gn:timezone":"Asia/Karachi",
    "iso:country":"PK",
    "name:und_x_variant":[
        "Dhok Mi\u0101n K\u0101lu Khel"
    ],
    "wof:name":"Dhok Mian Kharo Khel",
    "wof:placetype":"locality"
},
  "geometry": {"coordinates":[72.02821999999998,32.80117],"type":"Point"}
}