{
  "type": "Feature",
  "properties": {
    "gn:admin1_code":"4.0",
    "gn:asciiname":"Mohra",
    "gn:country_code":"PK",
    "gn:dem":704,
    "gn:feature_class":"P",
    "gn:feature_code":"PPL",
    "gn:name":"Mohra",
    "gn:population":0,
    "gn:timezone":"Asia/Karachi",
    "iso:country":"PK",
    "name:und_x_variant":[
        "Mahora"
    ],
    "wof:name":"Mohra",
    "wof:placetype":"locality"
},
  "geometry": {"coordinates":[73.5193,33.5066],"type":"Point"}
}