{
  "type": "Feature",
  "properties": {
    "gn:admin1_code":"5",
    "gn:asciiname":"Goth Sukhio Burrho",
    "gn:country_code":"PK",
    "gn:dem":63,
    "gn:feature_class":"P",
    "gn:feature_code":"PPL",
    "gn:name":"Goth Sukhio Burrho",
    "gn:population":0,
    "gn:timezone":"Asia/Karachi",
    "iso:country":"PK",
    "name:und_x_variant":[
        "Sukhio Burra"
    ],
    "wof:name":"Goth Sukhio Burrho",
    "wof:placetype":"locality"
},
  "geometry": {"coordinates":[68.72936,28.20845],"type":"Point"}
}