{
  "type": "Feature",
  "properties": {
    "gn:admin1_code":"4.0",
    "gn:asciiname":"Faiz Dhuddi da Khu",
    "gn:country_code":"PK",
    "gn:dem":157,
    "gn:feature_class":"P",
    "gn:feature_code":"PPL",
    "gn:name":"Faiz Dhuddi da Khu",
    "gn:population":0,
    "gn:timezone":"Asia/Karachi",
    "iso:country":"PK",
    "wof:name":"Faiz Dhuddi da Khu",
    "wof:placetype":"locality"
},
  "geometry": {"coordinates":[73.28121,30.06287],"type":"Point"}
}