{
  "type": "Feature",
  "properties": {
    "gn:admin1_code":"5",
    "gn:asciiname":"Miran Jo Goth",
    "gn:country_code":"PK",
    "gn:dem":54,
    "gn:feature_class":"P",
    "gn:feature_code":"PPL",
    "gn:name":"Miran Jo Goth",
    "gn:population":0,
    "gn:timezone":"Asia/Karachi",
    "iso:country":"PK",
    "name:und_x_variant":[
        "Miran"
    ],
    "wof:name":"Miran Jo Goth",
    "wof:placetype":"locality"
},
  "geometry": {"coordinates":[68.47183000000001,27.17847],"type":"Point"}
}