{
  "type": "Feature",
  "properties": {
    "gn:admin1_code":"3",
    "gn:asciiname":"Karghano",
    "gn:country_code":"PK",
    "gn:dem":2373,
    "gn:feature_class":"P",
    "gn:feature_code":"PPL",
    "gn:name":"Karghano",
    "gn:population":0,
    "gn:timezone":"Asia/Karachi",
    "iso:country":"PK",
    "name:und_x_variant":[
        "K\u0101rgh\u0101no Sar"
    ],
    "wof:name":"Karghano",
    "wof:placetype":"locality"
},
  "geometry": {"coordinates":[72.63519000000002,34.86366],"type":"Point"}
}