{
  "type": "Feature",
  "properties": {
    "gn:admin1_code":"5",
    "gn:asciiname":"Bhakko Amdani",
    "gn:country_code":"PK",
    "gn:dem":15,
    "gn:feature_class":"P",
    "gn:feature_code":"PPL",
    "gn:name":"Bhakko Amd\u0101ni",
    "gn:population":0,
    "gn:timezone":"Asia/Karachi",
    "iso:country":"PK",
    "wof:name":"Bhakko Amdani",
    "wof:placetype":"locality"
},
  "geometry": {"coordinates":[68.90278000000001,25.15833],"type":"Point"}
}