{
  "type": "Feature",
  "properties": {
    "gn:admin1_code":"5.0",
    "gn:asciiname":"Jokhio Jo Goth",
    "gn:country_code":"PK",
    "gn:dem":2,
    "gn:feature_class":"P",
    "gn:feature_code":"PPL",
    "gn:name":"Jokhio Jo Goth",
    "gn:population":0,
    "gn:timezone":"Asia/Karachi",
    "iso:country":"PK",
    "wof:name":"Jokhio Jo Goth",
    "wof:placetype":"locality"
},
  "geometry": {"coordinates":[67.57873000000001,24.22006],"type":"Point"}
}