{
  "type": "Feature",
  "properties": {
    "gn:admin1_code":"5",
    "gn:asciiname":"Goth Taiyib Buzdar",
    "gn:country_code":"PK",
    "gn:dem":16,
    "gn:feature_class":"P",
    "gn:feature_code":"PPL",
    "gn:name":"Goth Taiyib Buzdar",
    "gn:population":0,
    "gn:timezone":"Asia/Karachi",
    "iso:country":"PK",
    "name:und_x_variant":[
        "Goth H\u0101ji Ghul\u0101m Ras\u016bl"
    ],
    "wof:name":"Goth Taiyib Buzdar",
    "wof:placetype":"locality"
},
  "geometry": {"coordinates":[69.40538000000001,25.82218],"type":"Point"}
}