{
  "type": "Feature",
  "properties": {
    "gn:admin1_code":"7.0",
    "gn:asciiname":"Gone",
    "gn:country_code":"PK",
    "gn:dem":2396,
    "gn:feature_class":"P",
    "gn:feature_code":"PPL",
    "gn:name":"Gone",
    "gn:population":0,
    "gn:timezone":"Asia/Karachi",
    "iso:country":"PK",
    "name:deu_x_preferred":[
        "Gone"
    ],
    "name:fin_x_preferred":[
        "Gone"
    ],
    "name:fra_x_preferred":[
        "Gone"
    ],
    "name:ita_x_preferred":[
        "Gone"
    ],
    "name:kor_x_preferred":[
        "Gone"
    ],
    "name:nld_x_preferred":[
        "Gone"
    ],
    "name:pol_x_preferred":[
        "Gone"
    ],
    "name:por_x_preferred":[
        "Gone"
    ],
    "name:ron_x_preferred":[
        "Gone"
    ],
    "name:spa_x_preferred":[
        "Gone"
    ],
    "name:swe_x_preferred":[
        "Gone"
    ],
    "name:tur_x_preferred":[
        "Gone"
    ],
    "wof:name":"Gone",
    "wof:placetype":"locality"
},
  "geometry": {"coordinates":[75.98715,35.21031],"type":"Point"}
}