{
  "type": "Feature",
  "properties": {
    "gn:admin1_code":"4.0",
    "gn:asciiname":"Bajani Basti",
    "gn:country_code":"PK",
    "gn:dem":726,
    "gn:feature_class":"P",
    "gn:feature_code":"PPL",
    "gn:name":"Bajani Basti",
    "gn:population":0,
    "gn:timezone":"Asia/Karachi",
    "iso:country":"PK",
    "name:eng_x_preferred":[
        "B\u0101j\u0101ni Ban"
    ],
    "wof:name":"Bajani Basti",
    "wof:placetype":"locality"
},
  "geometry": {"coordinates":[70.29928000000001,30.29171],"type":"Point"}
}