{
  "type": "Feature",
  "properties": {
    "gn:admin1_code":"4",
    "gn:asciiname":"Basti Araianwali",
    "gn:country_code":"PK",
    "gn:dem":87,
    "gn:feature_class":"P",
    "gn:feature_code":"PPL",
    "gn:name":"Basti Ar\u0101i\u0101nw\u0101li",
    "gn:population":0,
    "gn:timezone":"Asia/Karachi",
    "iso:country":"PK",
    "wof:name":"Basti Araianwali",
    "wof:placetype":"locality"
},
  "geometry": {"coordinates":[70.58333,28.62778],"type":"Point"}
}