{
  "type": "Feature",
  "properties": {
    "gn:admin1_code":"5.0",
    "gn:asciiname":"Sardar Muqim Khoso",
    "gn:country_code":"PK",
    "gn:dem":66,
    "gn:feature_class":"P",
    "gn:feature_code":"PPL",
    "gn:name":"Sardar Muqim Khoso",
    "gn:population":0,
    "gn:timezone":"Asia/Karachi",
    "iso:country":"PK",
    "name:eng_x_preferred":[
        "Sardar Muqim Khoso"
    ],
    "wof:name":"Sardar Muqim Khoso",
    "wof:placetype":"locality"
},
  "geometry": {"coordinates":[68.65819999999999,27.90291],"type":"Point"}
}