{
  "type": "Feature",
  "properties": {
    "gn:admin1_code":"4",
    "gn:asciiname":"Chak Three Mailsi",
    "gn:country_code":"PK",
    "gn:dem":128,
    "gn:feature_class":"P",
    "gn:feature_code":"PPL",
    "gn:name":"Chak Three Mailsi",
    "gn:population":0,
    "gn:timezone":"Asia/Karachi",
    "iso:country":"PK",
    "name:und_x_variant":[
        "Chak Three M"
    ],
    "wof:name":"Chak Three Mailsi",
    "wof:placetype":"locality"
},
  "geometry": {"coordinates":[71.98769,29.78457],"type":"Point"}
}