{
  "type": "Feature",
  "properties": {
    "gn:admin1_code":"5.0",
    "gn:asciiname":"Kajle Khan Mughairi",
    "gn:country_code":"PK",
    "gn:dem":50,
    "gn:feature_class":"P",
    "gn:feature_code":"PPL",
    "gn:name":"Kajle Khan Mughairi",
    "gn:population":0,
    "gn:timezone":"Asia/Karachi",
    "iso:country":"PK",
    "wof:name":"Kajle Khan Mughairi",
    "wof:placetype":"locality"
},
  "geometry": {"coordinates":[68.00778000000001,27.62665],"type":"Point"}
}