{
  "type": "Feature",
  "properties": {
    "gn:admin1_code":"3",
    "gn:asciiname":"Lachi Mang",
    "gn:country_code":"PK",
    "gn:dem":1692,
    "gn:feature_class":"P",
    "gn:feature_code":"PPL",
    "gn:name":"Lachi Mang",
    "gn:population":0,
    "gn:timezone":"Asia/Karachi",
    "iso:country":"PK",
    "wof:name":"Lachi Mang",
    "wof:placetype":"locality"
},
  "geometry": {"coordinates":[73.14031999999997,34.60629],"type":"Point"}
}