{
  "type": "Feature",
  "properties": {
    "gn:admin1_code":"5",
    "gn:asciiname":"Goth Matha Khan",
    "gn:country_code":"PK",
    "gn:dem":48,
    "gn:feature_class":"P",
    "gn:feature_code":"PPL",
    "gn:name":"Goth Matha Khan",
    "gn:population":0,
    "gn:timezone":"Asia/Karachi",
    "iso:country":"PK",
    "name:und_x_variant":[
        "Goth Mat H\u0101ji"
    ],
    "wof:name":"Goth Matha Khan",
    "wof:placetype":"locality"
},
  "geometry": {"coordinates":[68.06529999999999,28.11435],"type":"Point"}
}