{
  "type": "Feature",
  "properties": {
    "gn:admin1_code":"5.0",
    "gn:asciiname":"Khahi",
    "gn:country_code":"PK",
    "gn:dem":15,
    "gn:feature_class":"P",
    "gn:feature_code":"PPL",
    "gn:name":"Khahi",
    "gn:population":0,
    "gn:timezone":"Asia/Karachi",
    "iso:country":"PK",
    "name:und_x_variant":[
        "Khipro",
        "Kh\u0101i",
        "Kh\u0101hi",
        "Khahi"
    ],
    "wof:name":"Khahi",
    "wof:placetype":"locality"
},
  "geometry": {"coordinates":[69.42081999999999,25.62712],"type":"Point"}
}