{
  "type": "Feature",
  "properties": {
    "gn:admin1_code":"3.0",
    "gn:asciiname":"Dhok Sher Ghulam",
    "gn:country_code":"PK",
    "gn:dem":337,
    "gn:feature_class":"P",
    "gn:feature_code":"PPL",
    "gn:name":"Dhok Sher Ghulam",
    "gn:population":0,
    "gn:timezone":"Asia/Karachi",
    "iso:country":"PK",
    "wof:name":"Dhok Sher Ghulam",
    "wof:placetype":"locality"
},
  "geometry": {"coordinates":[71.9383,33.66869000000001],"type":"Point"}
}