{
  "type": "Feature",
  "properties": {
    "gn:admin1_code":"1.0",
    "gn:asciiname":"Haji Niaz Gul Kalle",
    "gn:country_code":"PK",
    "gn:dem":873,
    "gn:feature_class":"P",
    "gn:feature_code":"PPL",
    "gn:name":"Haji Niaz Gul Kalle",
    "gn:population":0,
    "gn:timezone":"Asia/Karachi",
    "iso:country":"PK",
    "wof:name":"Haji Niaz Gul Kalle",
    "wof:placetype":"locality"
},
  "geometry": {"coordinates":[70.32683,33.25797],"type":"Point"}
}