{
  "type": "Feature",
  "properties": {
    "gn:admin1_code":"4",
    "gn:asciiname":"Phailuwala",
    "gn:country_code":"PK",
    "gn:dem":183,
    "gn:feature_class":"P",
    "gn:feature_code":"PPL",
    "gn:name":"Phailuwala",
    "gn:population":0,
    "gn:timezone":"Asia/Karachi",
    "iso:country":"PK",
    "name:und_x_variant":[
        "Phull\u016bw\u0101la"
    ],
    "wof:name":"Phailuwala",
    "wof:placetype":"locality"
},
  "geometry": {"coordinates":[71.63871999999998,31.83101],"type":"Point"}
}