{
  "type": "Feature",
  "properties": {
    "gn:admin1_code":"3",
    "gn:asciiname":"Wazir Kalle",
    "gn:country_code":"PK",
    "gn:dem":310,
    "gn:feature_class":"P",
    "gn:feature_code":"PPL",
    "gn:name":"Wazir Kalle",
    "gn:population":0,
    "gn:timezone":"Asia/Karachi",
    "iso:country":"PK",
    "name:eng_x_preferred":[
        "Mi\u0101n Kili"
    ],
    "wof:name":"Wazir Kalle",
    "wof:placetype":"locality"
},
  "geometry": {"coordinates":[72.08051,34.03966],"type":"Point"}
}