{
  "type": "Feature",
  "properties": {
    "gn:admin1_code":"3",
    "gn:asciiname":"Bhagran",
    "gn:country_code":"PK",
    "gn:dem":1296,
    "gn:feature_class":"P",
    "gn:feature_code":"PPL",
    "gn:name":"Bhagran",
    "gn:population":0,
    "gn:timezone":"Asia/Karachi",
    "iso:country":"PK",
    "name:und_x_variant":[
        "Big\u0101ri\u0101n",
        "Sharula Gali"
    ],
    "wof:name":"Bhagran",
    "wof:placetype":"locality"
},
  "geometry": {"coordinates":[73.07066999999998,34.16789],"type":"Point"}
}