{
  "type": "Feature",
  "properties": {
    "gn:admin1_code":"3.0",
    "gn:asciiname":"Ochhal",
    "gn:country_code":"PK",
    "gn:dem":1330,
    "gn:feature_class":"P",
    "gn:feature_code":"PPL",
    "gn:name":"Ochhal",
    "gn:population":0,
    "gn:timezone":"Asia/Karachi",
    "iso:country":"PK",
    "name:eng_x_preferred":[
        "Ochhal"
    ],
    "wof:name":"Ochhal",
    "wof:placetype":"locality"
},
  "geometry": {"coordinates":[73.29965,33.97977],"type":"Point"}
}