{
  "type": "Feature",
  "properties": {
    "gn:admin1_code":"3",
    "gn:asciiname":"Bar Shingara",
    "gn:country_code":"PK",
    "gn:dem":1719,
    "gn:feature_class":"P",
    "gn:feature_code":"PPL",
    "gn:name":"Bar Shingara",
    "gn:population":0,
    "gn:timezone":"Asia/Karachi",
    "iso:country":"PK",
    "name:eng_x_preferred":[
        "Bar Shingara"
    ],
    "name:und_x_variant":[
        "Bar Shing\u0101rah"
    ],
    "wof:name":"Bar Shingara",
    "wof:placetype":"locality"
},
  "geometry": {"coordinates":[71.73594,35.12425],"type":"Point"}
}