{
  "type": "Feature",
  "properties": {
    "gn:admin1_code":"5.0",
    "gn:asciiname":"Goth Muhammad Husain",
    "gn:country_code":"PK",
    "gn:dem":45,
    "gn:feature_class":"P",
    "gn:feature_code":"PPL",
    "gn:name":"Goth Muhammad Husain",
    "gn:population":0,
    "gn:timezone":"Asia/Karachi",
    "iso:country":"PK",
    "name:und_x_variant":[
        "Goth P\u012br H\u0101ji Husain Shah"
    ],
    "wof:name":"Goth Muhammad Husain",
    "wof:placetype":"locality"
},
  "geometry": {"coordinates":[68.36434,26.90526],"type":"Point"}
}