{
  "type": "Feature",
  "properties": {
    "gn:admin1_code":"5.0",
    "gn:asciiname":"Aklo",
    "gn:country_code":"PK",
    "gn:dem":16,
    "gn:feature_class":"P",
    "gn:feature_code":"PPL",
    "gn:name":"Aklo",
    "gn:population":0,
    "gn:timezone":"Asia/Karachi",
    "iso:country":"PK",
    "name:ast_x_preferred":[
        "Aklo"
    ],
    "name:ita_x_preferred":[
        "Aklo"
    ],
    "name:spa_x_preferred":[
        "Aklo"
    ],
    "name:und_x_variant":[
        "\u0100nklo"
    ],
    "wof:name":"Aklo",
    "wof:placetype":"locality"
},
  "geometry": {"coordinates":[70.9836,24.67269],"type":"Point"}
}