{
  "type": "Feature",
  "properties": {
    "gn:admin1_code":"4.0",
    "gn:asciiname":"Basti Haji Imam Bakhsh",
    "gn:country_code":"PK",
    "gn:dem":87,
    "gn:feature_class":"P",
    "gn:feature_code":"PPL",
    "gn:name":"Basti H\u0101ji Im\u0101m Bakhsh",
    "gn:population":0,
    "gn:timezone":"Asia/Karachi",
    "iso:country":"PK",
    "wof:name":"Basti Haji Imam Bakhsh",
    "wof:placetype":"locality"
},
  "geometry": {"coordinates":[70.38056,28.77083],"type":"Point"}
}