{
  "type": "Feature",
  "properties": {
    "gn:admin1_code":"7.0",
    "gn:asciiname":"Baili Baihk",
    "gn:country_code":"PK",
    "gn:dem":3189,
    "gn:feature_class":"P",
    "gn:feature_code":"PPL",
    "gn:name":"Baili Baihk",
    "gn:population":0,
    "gn:timezone":"Asia/Karachi",
    "iso:country":"PK",
    "wof:name":"Baili Baihk",
    "wof:placetype":"locality"
},
  "geometry": {"coordinates":[74.02054,35.90108],"type":"Point"}
}