{
  "type": "Feature",
  "properties": {
    "gn:admin1_code":"4",
    "gn:asciiname":"Khanawala",
    "gn:country_code":"PK",
    "gn:dem":200,
    "gn:feature_class":"P",
    "gn:feature_code":"PPL",
    "gn:name":"Khanawala",
    "gn:population":0,
    "gn:timezone":"Asia/Karachi",
    "iso:country":"PK",
    "name:und_x_variant":[
        "Aula Kh\u0101nw\u0101la"
    ],
    "wof:name":"Khanawala",
    "wof:placetype":"locality"
},
  "geometry": {"coordinates":[71.51353,32.32731],"type":"Point"}
}