{
  "type": "Feature",
  "properties": {
    "gn:admin1_code":"4.0",
    "gn:asciiname":"Wali Muhammad Jhandi",
    "gn:country_code":"PK",
    "gn:dem":135,
    "gn:feature_class":"P",
    "gn:feature_code":"PPL",
    "gn:name":"Wali Muhammad Jhandi",
    "gn:population":0,
    "gn:timezone":"Asia/Karachi",
    "iso:country":"PK",
    "name:und_x_variant":[
        "Wali Muhammad",
        "Basti Wali Muhammad",
        "Wali Muhammad Jhandi"
    ],
    "wof:name":"Wali Muhammad Jhandi",
    "wof:placetype":"locality"
},
  "geometry": {"coordinates":[71.72784,30.61348],"type":"Point"}
}