{
  "type": "Feature",
  "properties": {
    "gn:admin1_code":"4",
    "gn:asciiname":"Chak One Hundred Thirty-one",
    "gn:country_code":"PK",
    "gn:dem":148,
    "gn:feature_class":"P",
    "gn:feature_code":"PPL",
    "gn:name":"Chak One Hundred Thirty-one",
    "gn:population":0,
    "gn:timezone":"Asia/Karachi",
    "iso:country":"PK",
    "name:und_x_variant":[
        "N\u0101gn\u012bw\u0101la"
    ],
    "wof:name":"Chak One Hundred Thirty-one",
    "wof:placetype":"locality"
},
  "geometry": {"coordinates":[71.10081,30.98283],"type":"Point"}
}