{
  "type": "Feature",
  "properties": {
    "gn:admin1_code":"6",
    "gn:asciiname":"Ambagai",
    "gn:country_code":"PK",
    "gn:dem":701,
    "gn:feature_class":"P",
    "gn:feature_code":"PPL",
    "gn:name":"Ambagai",
    "gn:population":0,
    "gn:timezone":"Asia/Karachi",
    "iso:country":"PK",
    "wof:name":"Ambagai",
    "wof:placetype":"locality"
},
  "geometry": {"coordinates":[74.17260999999998,33.05143],"type":"Point"}
}