{
  "type": "Feature",
  "properties": {
    "gn:admin1_code":"1.0",
    "gn:asciiname":"Suji Khan Kili",
    "gn:country_code":"PK",
    "gn:dem":1714,
    "gn:feature_class":"P",
    "gn:feature_code":"PPL",
    "gn:name":"Suji Khan Kili",
    "gn:population":0,
    "gn:timezone":"Asia/Karachi",
    "iso:country":"PK",
    "name:und_x_variant":[
        "Jarobi"
    ],
    "wof:name":"Suji Khan Kili",
    "wof:placetype":"locality"
},
  "geometry": {"coordinates":[70.92995999999999,33.97765],"type":"Point"}
}