{
  "type": "Feature",
  "properties": {
    "gn:admin1_code":"3.0",
    "gn:asciiname":"Akhundan Kalle",
    "gn:country_code":"PK",
    "gn:dem":315,
    "gn:feature_class":"P",
    "gn:feature_code":"PPL",
    "gn:name":"Akhundan Kalle",
    "gn:population":0,
    "gn:timezone":"Asia/Karachi",
    "iso:country":"PK",
    "name:und_x_variant":[
        "Akhund\u0101n",
        "Akhond\u0101n",
        "Akhundan Kalle"
    ],
    "wof:name":"Akhundan Kalle",
    "wof:placetype":"locality"
},
  "geometry": {"coordinates":[70.72913,32.93787],"type":"Point"}
}