{
  "type": "Feature",
  "properties": {
    "gn:admin1_code":"2",
    "gn:asciiname":"Khudadad",
    "gn:country_code":"PK",
    "gn:dem":1778,
    "gn:feature_class":"P",
    "gn:feature_code":"PPL",
    "gn:name":"Khudadad",
    "gn:population":0,
    "gn:timezone":"Asia/Karachi",
    "iso:country":"PK",
    "name:eng_x_preferred":[
        "Khudadad"
    ],
    "name:urd_x_preferred":[
        "\u062e\u062f\u0627\u062f\u0627\u062f"
    ],
    "wof:name":"Khudadad",
    "wof:placetype":"locality"
},
  "geometry": {"coordinates":[67.02307,29.85787],"type":"Point"}
}