{
  "type": "Feature",
  "properties": {
    "gn:admin1_code":"2",
    "gn:asciiname":"Khudadad",
    "gn:country_code":"PK",
    "gn:dem":1778,
    "gn:feature_class":"P",
    "gn:feature_code":"PPL",
    "gn:name":"Khudadad",
    "gn:population":0,
    "gn:timezone":"Asia/Karachi",
    "iso:country":"PK",
    "wof:name":"Khudadad",
    "wof:placetype":"locality"
},
  "geometry": {"coordinates":[67.02306999999999,29.85787],"type":"Point"}
}