{
  "type": "Feature",
  "properties": {
    "gn:admin1_code":"2.0",
    "gn:asciiname":"Wali Muhammad Selaj",
    "gn:country_code":"PK",
    "gn:dem":1283,
    "gn:feature_class":"P",
    "gn:feature_code":"PPL",
    "gn:name":"Wali Muhammad Selaj",
    "gn:population":0,
    "gn:timezone":"Asia/Karachi",
    "iso:country":"PK",
    "wof:name":"Wali Muhammad Selaj",
    "wof:placetype":"locality"
},
  "geometry": {"coordinates":[69.87593000000001,30.2587],"type":"Point"}
}