{
  "type": "Feature",
  "properties": {
    "gn:admin1_code":"04",
    "gn:asciiname":"Shaikhpur",
    "gn:country_code":"PK",
    "gn:dem":257,
    "gn:feature_class":"P",
    "gn:feature_code":"PPL",
    "gn:name":"Shaikhpur",
    "gn:population":0,
    "gn:timezone":"Asia/Karachi",
    "iso:country":"PK",
    "name:und_x_variant":[
        "Sheikhupura",
        "Shekhpur",
        "Shaikhpur"
    ],
    "wof:name":"Shaikhpur",
    "wof:placetype":"locality"
},
  "geometry": {"coordinates":[74.68825,32.45457],"type":"Point"}
}