{
  "type": "Feature",
  "properties": {
    "gn:admin1_code":"5.0",
    "gn:asciiname":"Goth Muhammad Bachal Khaskeli",
    "gn:country_code":"PK",
    "gn:dem":20,
    "gn:feature_class":"P",
    "gn:feature_code":"PPL",
    "gn:name":"Goth Muhammad Bachal Khaskeli",
    "gn:population":0,
    "gn:timezone":"Asia/Karachi",
    "iso:country":"PK",
    "name:und_x_variant":[
        "Goth Bandarabad"
    ],
    "wof:name":"Goth Muhammad Bachal Khaskeli",
    "wof:placetype":"locality"
},
  "geometry": {"coordinates":[68.58301,25.07761],"type":"Point"}
}