{
  "type": "Feature",
  "properties": {
    "gn:admin1_code":"4.0",
    "gn:asciiname":"Chak One Hundred Eighteen -Twelve Left",
    "gn:country_code":"PK",
    "gn:dem":155,
    "gn:feature_class":"P",
    "gn:feature_code":"PPL",
    "gn:name":"Chak One Hundred Eighteen -Twelve Left",
    "gn:population":0,
    "gn:timezone":"Asia/Karachi",
    "iso:country":"PK",
    "name:und_x_variant":[
        "Dhan\u012bw\u0101l",
        "Dhaniw\u0101li"
    ],
    "wof:name":"Chak One Hundred Eighteen -Twelve Left",
    "wof:placetype":"locality"
},
  "geometry": {"coordinates":[72.54523,30.48119],"type":"Point"}
}