{
  "type": "Feature",
  "properties": {
    "gn:admin1_code":"3.0",
    "gn:asciiname":"Patao",
    "gn:country_code":"PK",
    "gn:dem":1691,
    "gn:feature_class":"P",
    "gn:feature_code":"PPL",
    "gn:name":"Patao",
    "gn:population":0,
    "gn:timezone":"Asia/Karachi",
    "iso:country":"PK",
    "wof:name":"Patao",
    "wof:placetype":"locality"
},
  "geometry": {"coordinates":[72.94606,35.44594],"type":"Point"}
}