{
  "type": "Feature",
  "properties": {
    "gn:admin1_code":"5.0",
    "gn:asciiname":"Goth Yaru Lakhair",
    "gn:country_code":"PK",
    "gn:dem":49,
    "gn:feature_class":"P",
    "gn:feature_code":"PPL",
    "gn:name":"Goth Yaru Lakhair",
    "gn:population":0,
    "gn:timezone":"Asia/Karachi",
    "iso:country":"PK",
    "name:und_x_variant":[
        "Y\u0101ru Lakhi\u0101r",
        "Y\u0101ru Lokhi\u0101r",
        "Goth Badhal Lakhi\u0101r",
        "Goth Yaru Lakhair"
    ],
    "wof:name":"Goth Yaru Lakhair",
    "wof:placetype":"locality"
},
  "geometry": {"coordinates":[67.97396999999999,27.19404],"type":"Point"}
}