{
  "type": "Feature",
  "properties": {
    "gn:admin1_code":"2",
    "gn:asciiname":"Mandwani",
    "gn:country_code":"PK",
    "gn:dem":1279,
    "gn:feature_class":"P",
    "gn:feature_code":"PPL",
    "gn:name":"Mandwani",
    "gn:population":0,
    "gn:timezone":"Asia/Karachi",
    "iso:country":"PK",
    "wof:name":"Mandwani",
    "wof:placetype":"locality"
},
  "geometry": {"coordinates":[69.7829,30.08602],"type":"Point"}
}