{
  "type": "Feature",
  "properties": {
    "gn:admin1_code":"2",
    "gn:asciiname":"Gangal",
    "gn:country_code":"PK",
    "gn:dem":2149,
    "gn:feature_class":"P",
    "gn:feature_code":"PPL",
    "gn:name":"Gangal",
    "gn:population":0,
    "gn:timezone":"Asia/Karachi",
    "iso:country":"PK",
    "name:und_x_variant":[
        "Gand\u0101b"
    ],
    "wof:name":"Gangal",
    "wof:placetype":"locality"
},
  "geometry": {"coordinates":[68.06514,30.36608],"type":"Point"}
}