{
  "type": "Feature",
  "properties": {
    "gn:admin1_code":"3.0",
    "gn:asciiname":"Sadr Basti",
    "gn:country_code":"PK",
    "gn:dem":3755,
    "gn:feature_class":"P",
    "gn:feature_code":"PPL",
    "gn:name":"Sadr Basti",
    "gn:population":0,
    "gn:timezone":"Asia/Karachi",
    "iso:country":"PK",
    "name:und_x_variant":[
        "Sadr"
    ],
    "wof:name":"Sadr Basti",
    "wof:placetype":"locality"
},
  "geometry": {"coordinates":[74.03013,35.03906],"type":"Point"}
}