{
  "type": "Feature",
  "properties": {
    "gn:admin1_code":"5.0",
    "gn:asciiname":"Adhigaim",
    "gn:country_code":"PK",
    "gn:dem":51,
    "gn:feature_class":"P",
    "gn:feature_code":"PPL",
    "gn:name":"Adhigaim",
    "gn:population":0,
    "gn:timezone":"Asia/Karachi",
    "iso:country":"PK",
    "name:und_x_variant":[
        "Adig\u0101on"
    ],
    "wof:name":"Adhigaim",
    "wof:placetype":"locality"
},
  "geometry": {"coordinates":[70.65895999999999,24.30263],"type":"Point"}
}