{
  "type": "Feature",
  "properties": {
    "gn:admin1_code":"6.0",
    "gn:asciiname":"Kathnan",
    "gn:country_code":"PK",
    "gn:dem":657,
    "gn:feature_class":"P",
    "gn:feature_code":"PPL",
    "gn:name":"Kathnan",
    "gn:population":0,
    "gn:timezone":"Asia/Karachi",
    "iso:country":"PK",
    "wof:name":"Kathnan",
    "wof:placetype":"locality"
},
  "geometry": {"coordinates":[73.66033,33.62374000000001],"type":"Point"}
}