{
  "type": "Feature",
  "properties": {
    "gn:admin1_code":"5",
    "gn:asciiname":"Mehar",
    "gn:country_code":"PK",
    "gn:dem":52,
    "gn:feature_class":"P",
    "gn:feature_code":"PPL",
    "gn:name":"Mehar",
    "gn:population":0,
    "gn:timezone":"Asia/Karachi",
    "iso:country":"PK",
    "name:hin_x_preferred":[
        "\u092e\u0947\u0939\u0930"
    ],
    "name:pnb_x_preferred":[
        "\u0645\u06be\u0631"
    ],
    "wof:name":"Mehar",
    "wof:placetype":"locality"
},
  "geometry": {"coordinates":[68.63215,27.35427],"type":"Point"}
}