{
  "type": "Feature",
  "properties": {
    "gn:admin1_code":"4.0",
    "gn:asciiname":"Ghazjabad",
    "gn:country_code":"PK",
    "gn:dem":161,
    "gn:feature_class":"P",
    "gn:feature_code":"PPL",
    "gn:name":"Ghazjabad",
    "gn:population":0,
    "gn:timezone":"Asia/Karachi",
    "iso:country":"PK",
    "wof:name":"Ghazjabad",
    "wof:placetype":"locality"
},
  "geometry": {"coordinates":[72.29576,31.5744],"type":"Point"}
}