{
  "type": "Feature",
  "properties": {
    "gn:admin1_code":"3.0",
    "gn:asciiname":"Shah Dhana",
    "gn:country_code":"PK",
    "gn:dem":329,
    "gn:feature_class":"P",
    "gn:feature_code":"PPL",
    "gn:name":"Shah Dhana",
    "gn:population":0,
    "gn:timezone":"Asia/Karachi",
    "iso:country":"PK",
    "wof:name":"Shah Dhana",
    "wof:placetype":"locality"
},
  "geometry": {"coordinates":[72.54893,34.06947],"type":"Point"}
}