{
  "type": "Feature",
  "properties": {
    "gn:admin1_code":"04",
    "gn:asciiname":"Kotli Juned",
    "gn:country_code":"PK",
    "gn:dem":129,
    "gn:feature_class":"P",
    "gn:feature_code":"PPL",
    "gn:name":"Kotli Juned",
    "gn:population":0,
    "gn:timezone":"Asia/Karachi",
    "iso:country":"PK",
    "name:und_x_variant":[
        "Kotla Junaid",
        "Kotli Juned"
    ],
    "wof:name":"Kotli Juned",
    "wof:placetype":"locality"
},
  "geometry": {"coordinates":[72.0667,29.71246],"type":"Point"}
}