{
  "type": "Feature",
  "properties": {
    "gn:admin1_code":"6",
    "gn:asciiname":"Pailan",
    "gn:country_code":"PK",
    "gn:dem":803,
    "gn:feature_class":"P",
    "gn:feature_code":"PPL",
    "gn:name":"Pailan",
    "gn:population":0,
    "gn:timezone":"Asia/Karachi",
    "iso:country":"PK",
    "name:und_x_variant":[
        "Paila"
    ],
    "wof:name":"Pailan",
    "wof:placetype":"locality"
},
  "geometry": {"coordinates":[74.05394,33.32066],"type":"Point"}
}