{
  "type": "Feature",
  "properties": {
    "gn:admin1_code":"1.0",
    "gn:asciiname":"Chaprai",
    "gn:country_code":"PK",
    "gn:dem":1803,
    "gn:feature_class":"P",
    "gn:feature_code":"PPL",
    "gn:name":"Chaprai",
    "gn:population":0,
    "gn:timezone":"Asia/Karachi",
    "iso:country":"PK",
    "wof:name":"Chaprai",
    "wof:placetype":"locality"
},
  "geometry": {"coordinates":[69.57083,32.80167],"type":"Point"}
}