{
  "type": "Feature",
  "properties": {
    "gn:admin1_code":"5.0",
    "gn:asciiname":"Khabbar Khan Chakram",
    "gn:country_code":"PK",
    "gn:dem":23,
    "gn:feature_class":"P",
    "gn:feature_code":"PPL",
    "gn:name":"Khabbar Khan Chakram",
    "gn:population":0,
    "gn:timezone":"Asia/Karachi",
    "iso:country":"PK",
    "wof:name":"Khabbar Khan Chakram",
    "wof:placetype":"locality"
},
  "geometry": {"coordinates":[68.84314000000001,26.11059],"type":"Point"}
}