{
  "type": "Feature",
  "properties": {
    "gn:admin1_code":"2.0",
    "gn:asciiname":"Paln Logar",
    "gn:country_code":"PK",
    "gn:dem":1310,
    "gn:feature_class":"P",
    "gn:feature_code":"PPL",
    "gn:name":"Paln Logar",
    "gn:population":0,
    "gn:timezone":"Asia/Karachi",
    "iso:country":"PK",
    "wof:name":"Paln Logar",
    "wof:placetype":"locality"
},
  "geometry": {"coordinates":[70.06723000000001,30.9464],"type":"Point"}
}