{
  "type": "Feature",
  "properties": {
    "gn:admin1_code":"01",
    "gn:asciiname":"Dandukai",
    "gn:country_code":"PK",
    "gn:dem":1188,
    "gn:feature_class":"P",
    "gn:feature_code":"PPL",
    "gn:name":"Dandukai",
    "gn:population":0,
    "gn:timezone":"Asia/Karachi",
    "iso:country":"PK",
    "name:und_x_variant":[
        "Dandokai"
    ],
    "wof:name":"Dandukai",
    "wof:placetype":"locality"
},
  "geometry": {"coordinates":[71.73621999999997,34.68158],"type":"Point"}
}