{
  "type": "Feature",
  "properties": {
    "gn:admin1_code":"4.0",
    "gn:asciiname":"Dera Ahmad Nawazwala",
    "gn:country_code":"PK",
    "gn:dem":171,
    "gn:feature_class":"P",
    "gn:feature_code":"PPL",
    "gn:name":"Dera Ahmad Nawazwala",
    "gn:population":0,
    "gn:timezone":"Asia/Karachi",
    "iso:country":"PK",
    "name:und_x_variant":[
        "Dera Muhammad Naw\u0101zw\u0101la"
    ],
    "wof:name":"Dera Ahmad Nawazwala",
    "wof:placetype":"locality"
},
  "geometry": {"coordinates":[71.06186,31.55179],"type":"Point"}
}