{
  "type": "Feature",
  "properties": {
    "gn:admin1_code":"3.0",
    "gn:asciiname":"Gumbad Mian Sahib",
    "gn:country_code":"PK",
    "gn:dem":362,
    "gn:feature_class":"P",
    "gn:feature_code":"PPL",
    "gn:name":"Gumbad Mi\u0101n S\u0101hib",
    "gn:population":0,
    "gn:timezone":"Asia/Karachi",
    "iso:country":"PK",
    "name:eng_x_preferred":[
        "Gumbad Mi\u0101n S\u0101hib"
    ],
    "wof:name":"Gumbad Mian Sahib",
    "wof:placetype":"locality"
},
  "geometry": {"coordinates":[71.65778,34.30722],"type":"Point"}
}