{
  "type": "Feature",
  "properties": {
    "gn:admin1_code":"1.0",
    "gn:asciiname":"Esham",
    "gn:country_code":"PK",
    "gn:dem":1646,
    "gn:feature_class":"P",
    "gn:feature_code":"PPL",
    "gn:name":"Esham",
    "gn:population":0,
    "gn:timezone":"Asia/Karachi",
    "iso:country":"PK",
    "name:deu_x_preferred":[
        "Esham"
    ],
    "name:fin_x_preferred":[
        "Esham"
    ],
    "name:fra_x_preferred":[
        "Esham"
    ],
    "name:ita_x_preferred":[
        "Esham"
    ],
    "name:por_x_preferred":[
        "Esham"
    ],
    "name:ron_x_preferred":[
        "Esham"
    ],
    "name:rus_x_preferred":[
        "Esham"
    ],
    "name:spa_x_preferred":[
        "Esham"
    ],
    "name:ukr_x_preferred":[
        "Esham"
    ],
    "name:und_x_variant":[
        "\u012asham"
    ],
    "wof:name":"Esham",
    "wof:placetype":"locality"
},
  "geometry": {"coordinates":[69.67749000000001,33.01559],"type":"Point"}
}