{
  "type": "Feature",
  "properties": {
    "gn:admin1_code":"03",
    "gn:asciiname":"Mamun Khawara",
    "gn:country_code":"PK",
    "gn:dem":812,
    "gn:feature_class":"P",
    "gn:feature_code":"PPL",
    "gn:name":"Mamun Khawara",
    "gn:population":0,
    "gn:timezone":"Asia/Karachi",
    "iso:country":"PK",
    "name:und_x_variant":[
        "Mamun"
    ],
    "wof:name":"Mamun Khawara",
    "wof:placetype":"locality"
},
  "geometry": {"coordinates":[70.62809,33.39802],"type":"Point"}
}