{
  "type": "Feature",
  "properties": {
    "gn:admin1_code":"5.0",
    "gn:asciiname":"Suba Khan",
    "gn:country_code":"PK",
    "gn:dem":46,
    "gn:feature_class":"P",
    "gn:feature_code":"PPL",
    "gn:name":"Suba Khan",
    "gn:population":0,
    "gn:timezone":"Asia/Karachi",
    "iso:country":"PK",
    "name:und_x_variant":[
        "Sooba Kh\u0101n"
    ],
    "wof:name":"Suba Khan",
    "wof:placetype":"locality"
},
  "geometry": {"coordinates":[67.89315000000001,27.63426],"type":"Point"}
}