{
  "type": "Feature",
  "properties": {
    "gn:admin1_code":"3",
    "gn:asciiname":"Jaba Banda",
    "gn:country_code":"PK",
    "gn:dem":1103,
    "gn:feature_class":"P",
    "gn:feature_code":"PPL",
    "gn:name":"Jaba Banda",
    "gn:population":0,
    "gn:timezone":"Asia/Karachi",
    "iso:country":"PK",
    "wof:name":"Jaba Banda",
    "wof:placetype":"locality"
},
  "geometry": {"coordinates":[72.733,34.68252],"type":"Point"}
}