{
  "type": "Feature",
  "properties": {
    "gn:admin1_code":"4.0",
    "gn:asciiname":"Chak Two Hundred Twenty-four",
    "gn:country_code":"PK",
    "gn:dem":169,
    "gn:feature_class":"P",
    "gn:feature_code":"PPL",
    "gn:name":"Chak Two Hundred Twenty-four",
    "gn:population":0,
    "gn:timezone":"Asia/Karachi",
    "iso:country":"PK",
    "name:eng_x_preferred":[
        "Chak Two Hundred Twenty-four"
    ],
    "name:und_x_variant":[
        "Burew\u0101la",
        "Chachkana"
    ],
    "wof:name":"Chak Two Hundred Twenty-four",
    "wof:placetype":"locality"
},
  "geometry": {"coordinates":[72.65134,31.47954],"type":"Point"}
}