{
  "type": "Feature",
  "properties": {
    "gn:admin1_code":"3.0",
    "gn:asciiname":"Loiran",
    "gn:country_code":"PK",
    "gn:dem":1574,
    "gn:feature_class":"P",
    "gn:feature_code":"PPL",
    "gn:name":"Loiran",
    "gn:population":0,
    "gn:timezone":"Asia/Karachi",
    "iso:country":"PK",
    "name:eng_x_preferred":[
        "Lair\u0101n"
    ],
    "wof:name":"Loiran",
    "wof:placetype":"locality"
},
  "geometry": {"coordinates":[73.34246,33.92661],"type":"Point"}
}