{
  "type": "Feature",
  "properties": {
    "gn:admin1_code":"5.0",
    "gn:asciiname":"Banhun Khari Mughairi",
    "gn:country_code":"PK",
    "gn:dem":50,
    "gn:feature_class":"P",
    "gn:feature_code":"PPL",
    "gn:name":"Banhun Khari Mughairi",
    "gn:population":0,
    "gn:timezone":"Asia/Karachi",
    "iso:country":"PK",
    "wof:name":"Banhun Khari Mughairi",
    "wof:placetype":"locality"
},
  "geometry": {"coordinates":[67.97209000000001,27.48234],"type":"Point"}
}