{
  "type": "Feature",
  "properties": {
    "gn:admin1_code":"3",
    "gn:asciiname":"Bar Nar",
    "gn:country_code":"PK",
    "gn:dem":2828,
    "gn:feature_class":"P",
    "gn:feature_code":"PPL",
    "gn:name":"Bar Nar",
    "gn:population":0,
    "gn:timezone":"Asia/Karachi",
    "iso:country":"PK",
    "wof:name":"Bar Nar",
    "wof:placetype":"locality"
},
  "geometry": {"coordinates":[73.31612,34.81936],"type":"Point"}
}