{
  "type": "Feature",
  "properties": {
    "gn:admin1_code":"4.0",
    "gn:asciiname":"Chak One Hundred Thirty Thal Development Authority",
    "gn:country_code":"PK",
    "gn:dem":150,
    "gn:feature_class":"P",
    "gn:feature_code":"PPL",
    "gn:name":"Chak One Hundred Thirty Thal Development Authority",
    "gn:population":0,
    "gn:timezone":"Asia/Karachi",
    "iso:country":"PK",
    "name:und_x_variant":[
        "Dang\u012bw\u0101la",
        "Chak 130 TDA",
        "Chak One Hundred Thirty TDA",
        "Chak One Hundred Thirty Thal Development Authority"
    ],
    "wof:name":"Chak One Hundred Thirty Thal Development Authority",
    "wof:placetype":"locality"
},
  "geometry": {"coordinates":[71.10824000000002,31.00203],"type":"Point"}
}