{
  "type": "Feature",
  "properties": {
    "gn:admin1_code":"4.0",
    "gn:asciiname":"Basti Jatoi",
    "gn:country_code":"PK",
    "gn:dem":96,
    "gn:feature_class":"P",
    "gn:feature_code":"PPL",
    "gn:name":"Basti Jatoi",
    "gn:population":0,
    "gn:timezone":"Asia/Karachi",
    "iso:country":"PK",
    "wof:name":"Basti Jatoi",
    "wof:placetype":"locality"
},
  "geometry": {"coordinates":[70.82118,29.05403],"type":"Point"}
}