{
  "type": "Feature",
  "properties": {
    "gn:admin1_code":"02",
    "gn:asciiname":"Tegak",
    "gn:country_code":"PK",
    "gn:dem":1676,
    "gn:feature_class":"P",
    "gn:feature_code":"PPL",
    "gn:name":"Tegak",
    "gn:population":0,
    "gn:timezone":"Asia/Karachi",
    "iso:country":"PK",
    "wof:name":"Tegak",
    "wof:placetype":"locality"
},
  "geometry": {"coordinates":[66.18111999999999,28.38271],"type":"Point"}
}