{
  "type": "Feature",
  "properties": {
    "gn:admin1_code":"5",
    "gn:asciiname":"Goth Salar Brahui",
    "gn:country_code":"PK",
    "gn:dem":57,
    "gn:feature_class":"P",
    "gn:feature_code":"PPL",
    "gn:name":"Goth Salar Brahui",
    "gn:population":0,
    "gn:timezone":"Asia/Karachi",
    "iso:country":"PK",
    "name:und_x_variant":[
        "Goth S\u0101l\u0101r Burio",
        "S\u0101l\u0101r Burio",
        "Goth Salar Brahui"
    ],
    "wof:name":"Goth Salar Brahui",
    "wof:placetype":"locality"
},
  "geometry": {"coordinates":[68.20784,27.81694],"type":"Point"}
}