{
  "type": "Feature",
  "properties": {
    "gn:admin1_code":"5",
    "gn:asciiname":"Goth Baran Laghari",
    "gn:country_code":"PK",
    "gn:dem":18,
    "gn:feature_class":"P",
    "gn:feature_code":"PPL",
    "gn:name":"Goth Baran Laghari",
    "gn:population":0,
    "gn:timezone":"Asia/Karachi",
    "iso:country":"PK",
    "name:und_x_variant":[
        "Bar\u0101n Lagh\u0101ri"
    ],
    "wof:name":"Goth Baran Laghari",
    "wof:placetype":"locality"
},
  "geometry": {"coordinates":[68.59871,25.10429],"type":"Point"}
}