{
  "type": "Feature",
  "properties": {
    "gn:admin1_code":"03",
    "gn:asciiname":"Shakkar Khel",
    "gn:country_code":"PK",
    "gn:dem":702,
    "gn:feature_class":"P",
    "gn:feature_code":"PPL",
    "gn:name":"Shakkar Khel",
    "gn:population":0,
    "gn:timezone":"Asia/Karachi",
    "iso:country":"PK",
    "name:und_x_variant":[
        "Shaker Khel",
        "Shakkar Khel"
    ],
    "wof:name":"Shakkar Khel",
    "wof:placetype":"locality"
},
  "geometry": {"coordinates":[71.11148,33.35024],"type":"Point"}
}