{
  "type": "Feature",
  "properties": {
    "gn:admin1_code":"04",
    "gn:asciiname":"Wirwala",
    "gn:country_code":"PK",
    "gn:dem":234,
    "gn:feature_class":"P",
    "gn:feature_code":"PPL",
    "gn:name":"Wirwala",
    "gn:population":0,
    "gn:timezone":"Asia/Karachi",
    "iso:country":"PK",
    "name:und_x_variant":[
        "Virwala",
        "Wirwala"
    ],
    "wof:name":"Wirwala",
    "wof:placetype":"locality"
},
  "geometry": {"coordinates":[74.46485,32.20729],"type":"Point"}
}