{
  "type": "Feature",
  "properties": {
    "gn:admin1_code":"4",
    "gn:asciiname":"Kot Sarwar",
    "gn:country_code":"PK",
    "gn:dem":183,
    "gn:feature_class":"P",
    "gn:feature_code":"PPL",
    "gn:name":"Kot Sarwar",
    "gn:population":0,
    "gn:timezone":"Asia/Karachi",
    "iso:country":"PK",
    "name:fas_x_preferred":[
        "\u06a9\u0648\u062a \u0633\u0631\u0648\u0631"
    ],
    "name:urd_x_preferred":[
        "\u06a9\u0648\u0679 \u0633\u0631\u0648\u0631"
    ],
    "wof:name":"Kot Sarwar",
    "wof:placetype":"locality"
},
  "geometry": {"coordinates":[73.05728000000001,31.73457],"type":"Point"}
}