{
  "type": "Feature",
  "properties": {
    "gn:admin1_code":"5",
    "gn:asciiname":"Goth Fazal Agro",
    "gn:country_code":"PK",
    "gn:dem":48,
    "gn:feature_class":"P",
    "gn:feature_code":"PPL",
    "gn:name":"Goth Fazal Agro",
    "gn:population":0,
    "gn:timezone":"Asia/Karachi",
    "iso:country":"PK",
    "name:und_x_variant":[
        "Goth Agra"
    ],
    "wof:name":"Goth Fazal Agro",
    "wof:placetype":"locality"
},
  "geometry": {"coordinates":[67.98345,27.1689],"type":"Point"}
}