{
  "type": "Feature",
  "properties": {
    "gn:admin1_code":"5.0",
    "gn:asciiname":"Goth Allah Warayo",
    "gn:country_code":"PK",
    "gn:dem":15,
    "gn:feature_class":"P",
    "gn:feature_code":"PPL",
    "gn:name":"Goth Allah Warayo",
    "gn:population":0,
    "gn:timezone":"Asia/Karachi",
    "iso:country":"PK",
    "name:und_x_variant":[
        "Goth All\u0101h Wardio"
    ],
    "wof:name":"Goth Allah Warayo",
    "wof:placetype":"locality"
},
  "geometry": {"coordinates":[68.73663000000001,25.0108],"type":"Point"}
}