{
  "type": "Feature",
  "properties": {
    "gn:admin1_code":"7.0",
    "gn:asciiname":"Khachah",
    "gn:country_code":"PK",
    "gn:dem":3301,
    "gn:feature_class":"P",
    "gn:feature_code":"PPL",
    "gn:name":"Khachah",
    "gn:population":0,
    "gn:timezone":"Asia/Karachi",
    "iso:country":"PK",
    "wof:name":"Khachah",
    "wof:placetype":"locality"
},
  "geometry": {"coordinates":[76.06522,35.2018],"type":"Point"}
}