{
  "type": "Feature",
  "properties": {
    "gn:admin1_code":"4.0",
    "gn:asciiname":"Kharmallian",
    "gn:country_code":"PK",
    "gn:dem":215,
    "gn:feature_class":"P",
    "gn:feature_code":"PPL",
    "gn:name":"Kharmallian",
    "gn:population":0,
    "gn:timezone":"Asia/Karachi",
    "iso:country":"PK",
    "name:und_x_variant":[
        "Khur Mallian",
        "Khor Malli\u0101n",
        "Kharmallian"
    ],
    "wof:name":"Kharmallian",
    "wof:placetype":"locality"
},
  "geometry": {"coordinates":[74.59124,31.48368],"type":"Point"}
}