{
  "type": "Feature",
  "properties": {
    "gn:admin1_code":"2.0",
    "gn:asciiname":"Tamachi",
    "gn:country_code":"PK",
    "gn:dem":1176,
    "gn:feature_class":"P",
    "gn:feature_code":"PPL",
    "gn:name":"Tamachi",
    "gn:population":0,
    "gn:timezone":"Asia/Karachi",
    "iso:country":"PK",
    "name:fas_x_preferred":[
        "\u062a\u0627\u0645\u0627\u0686\u06cc"
    ],
    "name:fra_x_preferred":[
        "Tamachi"
    ],
    "name:jpn_x_preferred":[
        "\u7530\u753a"
    ],
    "name:zho_x_preferred":[
        "\u7530\u753a"
    ],
    "wof:name":"Tamachi",
    "wof:placetype":"locality"
},
  "geometry": {"coordinates":[66.6694,27.74355],"type":"Point"}
}