{
  "type": "Feature",
  "properties": {
    "gn:admin1_code":"3",
    "gn:asciiname":"Shakar",
    "gn:country_code":"PK",
    "gn:dem":2979,
    "gn:feature_class":"P",
    "gn:feature_code":"PPL",
    "gn:name":"Shakar",
    "gn:population":0,
    "gn:timezone":"Asia/Karachi",
    "iso:country":"PK",
    "name:und_x_variant":[
        "Shikre"
    ],
    "wof:name":"Shakar",
    "wof:placetype":"locality"
},
  "geometry": {"coordinates":[73.18997,34.70561],"type":"Point"}
}