{
  "type": "Feature",
  "properties": {
    "gn:admin1_code":"04",
    "gn:asciiname":"Lehri",
    "gn:country_code":"PK",
    "gn:dem":313,
    "gn:feature_class":"P",
    "gn:feature_code":"PPL",
    "gn:name":"Lehri",
    "gn:population":0,
    "gn:timezone":"Asia/Karachi",
    "iso:country":"PK",
    "name:und_x_variant":[
        "Lahri",
        "Lehri"
    ],
    "wof:name":"Lehri",
    "wof:placetype":"locality"
},
  "geometry": {"coordinates":[73.98196,32.87793],"type":"Point"}
}