{
  "type": "Feature",
  "properties": {
    "gn:admin1_code":"4",
    "gn:asciiname":"Ada Jehan Khanwala",
    "gn:country_code":"PK",
    "gn:dem":168,
    "gn:feature_class":"P",
    "gn:feature_code":"PPL",
    "gn:name":"Ada Jehan Khanwala",
    "gn:population":0,
    "gn:timezone":"Asia/Karachi",
    "iso:country":"PK",
    "name:und_x_variant":[
        "Jeh\u0101n Kh\u0101nw\u0101la"
    ],
    "wof:name":"Ada Jehan Khanwala",
    "wof:placetype":"locality"
},
  "geometry": {"coordinates":[71.16703000000003,31.55495],"type":"Point"}
}