{
  "type": "Feature",
  "properties": {
    "gn:admin1_code":"4",
    "gn:asciiname":"Khangahi",
    "gn:country_code":"PK",
    "gn:dem":138,
    "gn:feature_class":"P",
    "gn:feature_code":"PPL",
    "gn:name":"Khangahi",
    "gn:population":0,
    "gn:timezone":"Asia/Karachi",
    "iso:country":"PK",
    "name:und_x_variant":[
        "Kh\u0101nq\u0101hi",
        "Basti Kh\u0101ng\u0101hi",
        "Khangahi"
    ],
    "wof:name":"Khangahi",
    "wof:placetype":"locality"
},
  "geometry": {"coordinates":[70.71439000000002,30.53464],"type":"Point"}
}