{
  "type": "Feature",
  "properties": {
    "gn:admin1_code":"4",
    "gn:asciiname":"Dholanwali",
    "gn:country_code":"PK",
    "gn:dem":227,
    "gn:feature_class":"P",
    "gn:feature_code":"PPL",
    "gn:name":"Dholanwali",
    "gn:population":0,
    "gn:timezone":"Asia/Karachi",
    "iso:country":"PK",
    "wof:name":"Dholanwali",
    "wof:placetype":"neighbourhood"
},
  "geometry": {"coordinates":[74.11275999999999,32.25601],"type":"Point"}
}