{
  "type": "Feature",
  "properties": {
    "gn:admin1_code":"5",
    "gn:asciiname":"Goth Ali Muhammad Nizamani",
    "gn:country_code":"PK",
    "gn:dem":26,
    "gn:feature_class":"P",
    "gn:feature_code":"PPL",
    "gn:name":"Goth Ali Muhammad Nizamani",
    "gn:population":0,
    "gn:timezone":"Asia/Karachi",
    "iso:country":"PK",
    "name:eng_x_preferred":[
        "Muhammad Niz\u0101m\u0101ni"
    ],
    "wof:name":"Goth Ali Muhammad Nizamani",
    "wof:placetype":"locality"
},
  "geometry": {"coordinates":[68.4756,25.84724],"type":"Point"}
}