{
  "type": "Feature",
  "properties": {
    "gn:admin1_code":"3.0",
    "gn:asciiname":"Ranolia",
    "gn:country_code":"PK",
    "gn:dem":762,
    "gn:feature_class":"P",
    "gn:feature_code":"PPL",
    "gn:name":"Ranolia",
    "gn:population":0,
    "gn:timezone":"Asia/Karachi",
    "iso:country":"PK",
    "name:fas_x_preferred":[
        "\u0631\u0646\u0648\u0644\u06cc\u0647"
    ],
    "name:urd_x_preferred":[
        "\u0631\u0646\u0648\u0644\u06cc\u06c1"
    ],
    "wof:name":"Ranolia",
    "wof:placetype":"locality"
},
  "geometry": {"coordinates":[72.89057,35.04925],"type":"Point"}
}