{
  "type": "Feature",
  "properties": {
    "gn:admin1_code":"4",
    "gn:asciiname":"Dhok Tahlian",
    "gn:country_code":"PK",
    "gn:dem":240,
    "gn:feature_class":"P",
    "gn:feature_code":"PPL",
    "gn:name":"Dhok Tahlian",
    "gn:population":0,
    "gn:timezone":"Asia/Karachi",
    "iso:country":"PK",
    "name:und_x_variant":[
        "Dhok T\u0101hli"
    ],
    "wof:name":"Dhok Tahlian",
    "wof:placetype":"locality"
},
  "geometry": {"coordinates":[73.72769,32.99440999999999],"type":"Point"}
}