{
  "type": "Feature",
  "properties": {
    "gn:admin1_code":"5",
    "gn:asciiname":"Goth Mirza Khan Kabbal",
    "gn:country_code":"PK",
    "gn:dem":53,
    "gn:feature_class":"P",
    "gn:feature_code":"PPL",
    "gn:name":"Goth Mirza Khan Kabbal",
    "gn:population":0,
    "gn:timezone":"Asia/Karachi",
    "iso:country":"PK",
    "name:und_x_variant":[
        "Goth Mirza Kh\u0101n"
    ],
    "wof:name":"Goth Mirza Khan Kabbal",
    "wof:placetype":"locality"
},
  "geometry": {"coordinates":[68.22024999999999,28.23259],"type":"Point"}
}