{
  "type": "Feature",
  "properties": {
    "gn:admin1_code":"04",
    "gn:asciiname":"Qadirpura Sethan",
    "gn:country_code":"PK",
    "gn:dem":166,
    "gn:feature_class":"P",
    "gn:feature_code":"PPL",
    "gn:name":"Qadirpura Sethan",
    "gn:population":0,
    "gn:timezone":"Asia/Karachi",
    "iso:country":"PK",
    "name:und_x_variant":[
        "Q\u0101dirpur"
    ],
    "wof:name":"Qadirpura Sethan",
    "wof:placetype":"locality"
},
  "geometry": {"coordinates":[73.50979,30.18201],"type":"Point"}
}