{
  "type": "Feature",
  "properties": {
    "gn:admin1_code":"4",
    "gn:asciiname":"Basti Meran",
    "gn:country_code":"PK",
    "gn:dem":101,
    "gn:feature_class":"P",
    "gn:feature_code":"PPL",
    "gn:name":"Basti Meran",
    "gn:population":0,
    "gn:timezone":"Asia/Karachi",
    "iso:country":"PK",
    "name:und_x_variant":[
        "Basti Mirh\u0101n",
        "Mirh\u0101n",
        "Basti Meran"
    ],
    "wof:name":"Basti Meran",
    "wof:placetype":"locality"
},
  "geometry": {"coordinates":[70.50091,29.22546],"type":"Point"}
}