{
  "type": "Feature",
  "properties": {
    "gn:admin1_code":"5.0",
    "gn:asciiname":"Gorgeja",
    "gn:country_code":"PK",
    "gn:dem":46,
    "gn:feature_class":"P",
    "gn:feature_code":"PPL",
    "gn:name":"Gorgeja",
    "gn:population":0,
    "gn:timezone":"Asia/Karachi",
    "iso:country":"PK",
    "name:und_x_variant":[
        "Goga"
    ],
    "wof:name":"Gorgeja",
    "wof:placetype":"locality"
},
  "geometry": {"coordinates":[67.75877,27.53562],"type":"Point"}
}