{
  "type": "Feature",
  "properties": {
    "iso:country":"PK",
    "name:unk_x_variant":[
        "Garho"
    ],
    "qs:gn_country":"PK",
    "qs:gn_fcode":"PPL",
    "qs:gn_pop":19524,
    "qs:name":"Gharo",
    "qs:name_adm0":"Pakistan",
    "qs:name_adm1":"Sindh",
    "qs:photos":0,
    "qs:photos_1k":0,
    "qs:photos_9k":1,
    "qs:photos_9r":1,
    "qs:photos_all":1,
    "qs:photos_sr":0,
    "qs:placetype":"Town",
    "qs:pop_sr":"6",
    "qs:woe_adm0":23424922,
    "wd:wordcount":75,
    "wof:name":"Gharo",
    "wof:placetype":"locality",
    "wof:population":19524
},
  "geometry": {"coordinates":[67.58565,24.74241],"type":"Point"}
}