{
  "type": "Feature",
  "properties": {
    "gn:admin1_code":"6",
    "gn:asciiname":"Langer",
    "gn:country_code":"PK",
    "gn:dem":722,
    "gn:feature_class":"P",
    "gn:feature_code":"PPL",
    "gn:name":"Langer",
    "gn:population":0,
    "gn:timezone":"Asia/Karachi",
    "iso:country":"PK",
    "name:und_x_variant":[
        "Jangar"
    ],
    "wof:name":"Langer",
    "wof:placetype":"locality"
},
  "geometry": {"coordinates":[74.04892,33.06664],"type":"Point"}
}