{
  "type": "Feature",
  "properties": {
    "gn:admin1_code":"3.0",
    "gn:asciiname":"Basha",
    "gn:country_code":"PK",
    "gn:dem":1141,
    "gn:feature_class":"P",
    "gn:feature_code":"PPL",
    "gn:name":"Basha",
    "gn:population":0,
    "gn:timezone":"Asia/Karachi",
    "iso:country":"PK",
    "name:ceb_x_preferred":[
        "Basha"
    ],
    "name:deu_x_preferred":[
        "Basha"
    ],
    "name:fra_x_preferred":[
        "Basha"
    ],
    "name:ita_x_preferred":[
        "Basha"
    ],
    "name:nld_x_preferred":[
        "Basha"
    ],
    "wof:name":"Basha",
    "wof:placetype":"locality"
},
  "geometry": {"coordinates":[73.71433,35.52786],"type":"Point"}
}