{
  "type": "Feature",
  "properties": {
    "gn:admin1_code":"4.0",
    "gn:asciiname":"Dhalke Khurd",
    "gn:country_code":"PK",
    "gn:dem":196,
    "gn:feature_class":"P",
    "gn:feature_code":"PPL",
    "gn:name":"Dhalke Khurd",
    "gn:population":0,
    "gn:timezone":"Asia/Karachi",
    "iso:country":"PK",
    "name:und_x_variant":[
        "Dhalke",
        "Dhalke Khurd"
    ],
    "wof:name":"Dhalke Khurd",
    "wof:placetype":"locality"
},
  "geometry": {"coordinates":[73.34193,31.97077],"type":"Point"}
}