{
  "type": "Feature",
  "properties": {
    "gn:admin1_code":"01",
    "gn:asciiname":"Munda Dhand",
    "gn:country_code":"PK",
    "gn:dem":785,
    "gn:feature_class":"P",
    "gn:feature_code":"PPL",
    "gn:name":"Munda Dhand",
    "gn:population":0,
    "gn:timezone":"Asia/Karachi",
    "iso:country":"PK",
    "name:eng_x_preferred":[
        "Murda Dand"
    ],
    "wof:name":"Munda Dhand",
    "wof:placetype":"locality"
},
  "geometry": {"coordinates":[71.57378,34.57599],"type":"Point"}
}