{
  "type": "Feature",
  "properties": {
    "gn:admin1_code":"5",
    "gn:asciiname":"Goth Seth Muhammad Harun",
    "gn:country_code":"PK",
    "gn:dem":9,
    "gn:feature_class":"P",
    "gn:feature_code":"PPL",
    "gn:name":"Goth Seth Muhammad Harun",
    "gn:population":0,
    "gn:timezone":"Asia/Karachi",
    "iso:country":"PK",
    "name:und_x_variant":[
        "Seth Muhammad H\u0101r\u016bn"
    ],
    "wof:name":"Goth Seth Muhammad Harun",
    "wof:placetype":"locality"
},
  "geometry": {"coordinates":[69.56201999999999,24.98905],"type":"Point"}
}