{
  "type": "Feature",
  "properties": {
    "gn:admin1_code":"3.0",
    "gn:asciiname":"Shorag",
    "gn:country_code":"PK",
    "gn:dem":835,
    "gn:feature_class":"P",
    "gn:feature_code":"PPL",
    "gn:name":"Shorag",
    "gn:population":0,
    "gn:timezone":"Asia/Karachi",
    "iso:country":"PK",
    "name:eng_x_preferred":[
        "Shorag"
    ],
    "wof:name":"Shorag",
    "wof:placetype":"locality"
},
  "geometry": {"coordinates":[73.0997,33.97938],"type":"Point"}
}