{
  "type": "Feature",
  "properties": {
    "gn:admin1_code":"4",
    "gn:asciiname":"Jagu Chhanili",
    "gn:country_code":"PK",
    "gn:dem":92,
    "gn:feature_class":"P",
    "gn:feature_code":"PPL",
    "gn:name":"Jagu Chhanili",
    "gn:population":0,
    "gn:timezone":"Asia/Karachi",
    "iso:country":"PK",
    "name:und_x_variant":[
        "Chhanell",
        "J\u0101m Banna",
        "Jagu Chhanili"
    ],
    "wof:name":"Jagu Chhanili",
    "wof:placetype":"locality"
},
  "geometry": {"coordinates":[70.80019,28.87088],"type":"Point"}
}