{
  "type": "Feature",
  "properties": {
    "gn:admin1_code":"2",
    "gn:asciiname":"Taib Zerin",
    "gn:country_code":"PK",
    "gn:dem":111,
    "gn:feature_class":"P",
    "gn:feature_code":"PPL",
    "gn:name":"Taib Zerin",
    "gn:population":0,
    "gn:timezone":"Asia/Karachi",
    "iso:country":"PK",
    "name:und_x_variant":[
        "T\u0101ib"
    ],
    "wof:name":"Taib Zerin",
    "wof:placetype":"locality"
},
  "geometry": {"coordinates":[67.58634000000001,29.12276],"type":"Point"}
}