{
  "type": "Feature",
  "properties": {
    "gn:admin1_code":"3.0",
    "gn:asciiname":"Tano Dheri",
    "gn:country_code":"PK",
    "gn:dem":294,
    "gn:feature_class":"P",
    "gn:feature_code":"PPL",
    "gn:name":"Tano Dheri",
    "gn:population":0,
    "gn:timezone":"Asia/Karachi",
    "iso:country":"PK",
    "wof:name":"Tano Dheri",
    "wof:placetype":"locality"
},
  "geometry": {"coordinates":[72.31563,33.97542],"type":"Point"}
}