{
  "type": "Feature",
  "properties": {
    "gn:admin1_code":"3.0",
    "gn:asciiname":"Baico",
    "gn:country_code":"PK",
    "gn:dem":2179,
    "gn:feature_class":"P",
    "gn:feature_code":"PPL",
    "gn:name":"Baico",
    "gn:population":0,
    "gn:timezone":"Asia/Karachi",
    "iso:country":"PK",
    "wof:name":"Baico",
    "wof:placetype":"locality"
},
  "geometry": {"coordinates":[73.58645,35.47749],"type":"Point"}
}