{
  "type": "Feature",
  "properties": {
    "gn:admin1_code":"3.0",
    "gn:asciiname":"Kand",
    "gn:country_code":"PK",
    "gn:dem":1481,
    "gn:feature_class":"P",
    "gn:feature_code":"PPL",
    "gn:name":"Kand",
    "gn:population":0,
    "gn:timezone":"Asia/Karachi",
    "iso:country":"PK",
    "name:ceb_x_preferred":[
        "Kand"
    ],
    "name:swe_x_preferred":[
        "Kand"
    ],
    "wof:name":"Kand",
    "wof:placetype":"locality"
},
  "geometry": {"coordinates":[73.0536,34.17117],"type":"Point"}
}