{
  "type": "Feature",
  "properties": {
    "gn:admin1_code":"4.0",
    "gn:asciiname":"Soruan",
    "gn:country_code":"PK",
    "gn:dem":135,
    "gn:feature_class":"P",
    "gn:feature_code":"PPL",
    "gn:name":"Soruan",
    "gn:population":0,
    "gn:timezone":"Asia/Karachi",
    "iso:country":"PK",
    "wof:name":"Soruan",
    "wof:placetype":"locality"
},
  "geometry": {"coordinates":[72.47124000000002,29.71115],"type":"Point"}
}