{
  "type": "Feature",
  "properties": {
    "gn:admin1_code":"5.0",
    "gn:asciiname":"Goth Saban Shaikh",
    "gn:country_code":"PK",
    "gn:dem":6,
    "gn:feature_class":"P",
    "gn:feature_code":"PPL",
    "gn:name":"Goth Saban Shaikh",
    "gn:population":0,
    "gn:timezone":"Asia/Karachi",
    "iso:country":"PK",
    "name:und_x_variant":[
        "Saban Sheikh",
        "Goth Saban Shaikh"
    ],
    "wof:name":"Goth Saban Shaikh",
    "wof:placetype":"locality"
},
  "geometry": {"coordinates":[67.64163000000001,24.50192],"type":"Point"}
}