{
  "type": "Feature",
  "properties": {
    "gn:admin1_code":"5.0",
    "gn:asciiname":"Goth Muhammad Ramzan Baloch",
    "gn:country_code":"PK",
    "gn:dem":56,
    "gn:feature_class":"P",
    "gn:feature_code":"PPL",
    "gn:name":"Goth Muhammad Ramzan Baloch",
    "gn:population":0,
    "gn:timezone":"Asia/Karachi",
    "iso:country":"PK",
    "name:eng_x_preferred":[
        "Muhammad Ramzan Shar Balouch"
    ],
    "wof:name":"Goth Muhammad Ramzan Baloch",
    "wof:placetype":"locality"
},
  "geometry": {"coordinates":[68.73172,27.46899],"type":"Point"}
}