{
  "type": "Feature",
  "properties": {
    "gn:admin1_code":"04",
    "gn:asciiname":"Muhib Ali Uttar",
    "gn:country_code":"PK",
    "gn:dem":168,
    "gn:feature_class":"P",
    "gn:feature_code":"PPL",
    "gn:name":"Muhib Ali Uttar",
    "gn:population":0,
    "gn:timezone":"Asia/Karachi",
    "iso:country":"PK",
    "name:und_x_variant":[
        "Muhibb Ali Hithar",
        "Muhib Ali Hith\u0101r",
        "Muhib Ali Uttar"
    ],
    "wof:name":"Muhib Ali Uttar",
    "wof:placetype":"locality"
},
  "geometry": {"coordinates":[73.62158000000002,30.36915],"type":"Point"}
}