{
  "type": "Feature",
  "properties": {
    "gn:admin1_code":"3",
    "gn:asciiname":"Kanaba",
    "gn:country_code":"PK",
    "gn:dem":1913,
    "gn:feature_class":"P",
    "gn:feature_code":"PPL",
    "gn:name":"Kanaba",
    "gn:population":0,
    "gn:timezone":"Asia/Karachi",
    "iso:country":"PK",
    "name:und_x_variant":[
        "K\u0101ndba",
        "Kanaba"
    ],
    "wof:name":"Kanaba",
    "wof:placetype":"locality"
},
  "geometry": {"coordinates":[72.60143000000002,34.86388],"type":"Point"}
}