{
  "type": "Feature",
  "properties": {
    "gn:admin1_code":"4.0",
    "gn:asciiname":"Basti Babbi",
    "gn:country_code":"PK",
    "gn:dem":162,
    "gn:feature_class":"P",
    "gn:feature_code":"PPL",
    "gn:name":"Basti Babbi",
    "gn:population":0,
    "gn:timezone":"Asia/Karachi",
    "iso:country":"PK",
    "name:und_x_variant":[
        "Babi",
        "Babbe",
        "Babbi",
        "Basti Babbi"
    ],
    "wof:name":"Basti Babbi",
    "wof:placetype":"locality"
},
  "geometry": {"coordinates":[70.68016,31.07678],"type":"Point"}
}