{
  "type": "Feature",
  "properties": {
    "gn:admin1_code":"5",
    "gn:asciiname":"Deh One Hundred Sixty-one",
    "gn:country_code":"PK",
    "gn:dem":14,
    "gn:feature_class":"P",
    "gn:feature_code":"PPL",
    "gn:name":"Deh One Hundred Sixty-one",
    "gn:population":0,
    "gn:timezone":"Asia/Karachi",
    "iso:country":"PK",
    "wof:name":"Deh One Hundred Sixty-one",
    "wof:placetype":"locality"
},
  "geometry": {"coordinates":[69.04120999999999,25.17197],"type":"Point"}
}