{
  "type": "Feature",
  "properties": {
    "gn:admin1_code":"5.0",
    "gn:asciiname":"Goth Amir Khan",
    "gn:country_code":"PK",
    "gn:dem":21,
    "gn:feature_class":"P",
    "gn:feature_code":"PPL",
    "gn:name":"Goth Amir Khan",
    "gn:population":0,
    "gn:timezone":"Asia/Karachi",
    "iso:country":"PK",
    "wof:name":"Goth Amir Khan",
    "wof:placetype":"locality"
},
  "geometry": {"coordinates":[68.85553,25.99665],"type":"Point"}
}