{
  "type": "Feature",
  "properties": {
    "gn:admin1_code":"4.0",
    "gn:asciiname":"Mohra Nagial",
    "gn:country_code":"PK",
    "gn:dem":513,
    "gn:feature_class":"P",
    "gn:feature_code":"PPL",
    "gn:name":"Mohra Nagial",
    "gn:population":0,
    "gn:timezone":"Asia/Karachi",
    "iso:country":"PK",
    "wof:name":"Mohra Nagial",
    "wof:placetype":"locality"
},
  "geometry": {"coordinates":[73.42012,33.34757],"type":"Point"}
}