{
  "type": "Feature",
  "properties": {
    "gn:admin1_code":"2.0",
    "gn:asciiname":"Ibrahimzai",
    "gn:country_code":"PK",
    "gn:dem":1284,
    "gn:feature_class":"P",
    "gn:feature_code":"PPL",
    "gn:name":"Ibrahimzai",
    "gn:population":0,
    "gn:timezone":"Asia/Karachi",
    "iso:country":"PK",
    "name:und_x_variant":[
        "Auzdan Kili"
    ],
    "wof:name":"Ibrahimzai",
    "wof:placetype":"locality"
},
  "geometry": {"coordinates":[69.90374,31.01026],"type":"Point"}
}