{
  "type": "Feature",
  "properties": {
    "gn:admin1_code":"3.0",
    "gn:asciiname":"Said Imran",
    "gn:country_code":"PK",
    "gn:dem":401,
    "gn:feature_class":"P",
    "gn:feature_code":"PPL",
    "gn:name":"Said Imran",
    "gn:population":0,
    "gn:timezone":"Asia/Karachi",
    "iso:country":"PK",
    "wof:name":"Said Imran",
    "wof:placetype":"locality"
},
  "geometry": {"coordinates":[71.80301999999998,34.37104],"type":"Point"}
}