{
  "type": "Feature",
  "properties": {
    "iso:country":"PK",
    "name:ceb_x_preferred":[
        "Daulatpur"
    ],
    "name:eng_x_preferred":[
        "Daulatpur"
    ],
    "name:nld_x_preferred":[
        "Daulatpur"
    ],
    "name:snd_x_preferred":[
        "\u062f\u0648\u0644\u062a\u067e\u0648\u0631"
    ],
    "name:unk_x_variant":[
        "Doulatpur"
    ],
    "qs:gn_country":"PK",
    "qs:gn_fcode":"PPL",
    "qs:gn_pop":14574,
    "qs:name":"Daulatpur",
    "qs:name_adm0":"Pakistan",
    "qs:name_adm1":"Sindh",
    "qs:photos":0,
    "qs:photos_1k":0,
    "qs:photos_9k":0,
    "qs:photos_9r":0,
    "qs:photos_all":0,
    "qs:photos_sr":0,
    "qs:placetype":"Town",
    "qs:pop_sr":"6",
    "qs:woe_adm0":23424922,
    "wd:wordcount":167,
    "wof:name":"Daulatpur",
    "wof:placetype":"locality",
    "wof:population":14574
},
  "geometry": {"coordinates":[67.9706,26.50154],"type":"Point"}
}