{
  "type": "Feature",
  "properties": {
    "gn:admin1_code":"4.0",
    "gn:asciiname":"Dera Mian Ahmad Danbda",
    "gn:country_code":"PK",
    "gn:dem":187,
    "gn:feature_class":"P",
    "gn:feature_code":"PPL",
    "gn:name":"Dera Mian Ahmad Danbda",
    "gn:population":0,
    "gn:timezone":"Asia/Karachi",
    "iso:country":"PK",
    "name:und_x_variant":[
        "Dera Ahmad Kh\u0101n Baluch"
    ],
    "wof:name":"Dera Mian Ahmad Danbda",
    "wof:placetype":"locality"
},
  "geometry": {"coordinates":[72.06019000000001,31.89325],"type":"Point"}
}