{
  "type": "Feature",
  "properties": {
    "gn:admin1_code":"2.0",
    "gn:asciiname":"Khuddi Ali Murad",
    "gn:country_code":"PK",
    "gn:dem":2723,
    "gn:feature_class":"P",
    "gn:feature_code":"PPL",
    "gn:name":"Khuddi Ali Murad",
    "gn:population":0,
    "gn:timezone":"Asia/Karachi",
    "iso:country":"PK",
    "wof:name":"Khuddi Ali Murad",
    "wof:placetype":"locality"
},
  "geometry": {"coordinates":[66.78553000000001,28.95122000000001],"type":"Point"}
}