{
  "type": "Feature",
  "properties": {
    "gn:admin1_code":"3",
    "gn:asciiname":"Riala",
    "gn:country_code":"PK",
    "gn:dem":1336,
    "gn:feature_class":"P",
    "gn:feature_code":"PPL",
    "gn:name":"Riala",
    "gn:population":0,
    "gn:timezone":"Asia/Karachi",
    "iso:country":"PK",
    "name:ceb_x_preferred":[
        "Riala"
    ],
    "name:fas_x_preferred":[
        "\u0631\u06cc\u0627\u0644\u0627"
    ],
    "name:ita_x_preferred":[
        "Riala"
    ],
    "name:nld_x_preferred":[
        "Riala"
    ],
    "name:nno_x_preferred":[
        "Riala"
    ],
    "name:nor_x_preferred":[
        "Riala"
    ],
    "name:swe_x_preferred":[
        "Riala"
    ],
    "wof:name":"Riala",
    "wof:placetype":"locality"
},
  "geometry": {"coordinates":[73.46185,34.01411],"type":"Point"}
}