{
  "type": "Feature",
  "properties": {
    "gn:admin1_code":"3",
    "gn:asciiname":"Lashkar",
    "gn:country_code":"PK",
    "gn:dem":1127,
    "gn:feature_class":"P",
    "gn:feature_code":"PPL",
    "gn:name":"Lashkar",
    "gn:population":0,
    "gn:timezone":"Asia/Karachi",
    "iso:country":"PK",
    "wof:name":"Lashkar",
    "wof:placetype":"locality"
},
  "geometry": {"coordinates":[72.81916,34.93617],"type":"Point"}
}