{
  "type": "Feature",
  "properties": {
    "gn:admin1_code":"3",
    "gn:asciiname":"Larai",
    "gn:country_code":"PK",
    "gn:dem":1974,
    "gn:feature_class":"P",
    "gn:feature_code":"PPL",
    "gn:name":"Larai",
    "gn:population":0,
    "gn:timezone":"Asia/Karachi",
    "iso:country":"PK",
    "wof:name":"Larai",
    "wof:placetype":"locality"
},
  "geometry": {"coordinates":[72.7238,35.02936],"type":"Point"}
}