{
  "type": "Feature",
  "properties": {
    "gn:admin1_code":"3.0",
    "gn:asciiname":"Raisan",
    "gn:country_code":"PK",
    "gn:dem":731,
    "gn:feature_class":"P",
    "gn:feature_code":"PPL",
    "gn:name":"Raisan",
    "gn:population":0,
    "gn:timezone":"Asia/Karachi",
    "iso:country":"PK",
    "name:und_x_variant":[
        "Ra\u012bs\u0101n"
    ],
    "wof:name":"Raisan",
    "wof:placetype":"locality"
},
  "geometry": {"coordinates":[71.19126,33.57322],"type":"Point"}
}