{
  "type": "Feature",
  "properties": {
    "gn:admin1_code":"1.0",
    "gn:asciiname":"Badshah Men",
    "gn:country_code":"PK",
    "gn:dem":925,
    "gn:feature_class":"P",
    "gn:feature_code":"PPL",
    "gn:name":"Badshah Men",
    "gn:population":0,
    "gn:timezone":"Asia/Karachi",
    "iso:country":"PK",
    "wof:name":"Badshah Men",
    "wof:placetype":"locality"
},
  "geometry": {"coordinates":[71.10786,34.10529],"type":"Point"}
}