{
  "type": "Feature",
  "properties": {
    "gn:admin1_code":"3",
    "gn:asciiname":"Bangla",
    "gn:country_code":"PK",
    "gn:dem":1908,
    "gn:feature_class":"P",
    "gn:feature_code":"PPL",
    "gn:name":"Bangla",
    "gn:population":0,
    "gn:timezone":"Asia/Karachi",
    "iso:country":"PK",
    "wof:name":"Bangla",
    "wof:placetype":"locality"
},
  "geometry": {"coordinates":[73.06769,34.55574],"type":"Point"}
}