{
  "type": "Feature",
  "properties": {
    "gn:admin1_code":"1.0",
    "gn:asciiname":"Ut Mela",
    "gn:country_code":"PK",
    "gn:dem":1899,
    "gn:feature_class":"P",
    "gn:feature_code":"PPL",
    "gn:name":"Ut Mela",
    "gn:population":0,
    "gn:timezone":"Asia/Karachi",
    "iso:country":"PK",
    "name:und_x_variant":[
        "Otmela"
    ],
    "wof:name":"Ut Mela",
    "wof:placetype":"locality"
},
  "geometry": {"coordinates":[70.82209,33.71815],"type":"Point"}
}