{
  "type": "Feature",
  "properties": {
    "gn:admin1_code":"01",
    "gn:asciiname":"Kasurrai",
    "gn:country_code":"PK",
    "gn:dem":676,
    "gn:feature_class":"P",
    "gn:feature_code":"PPL",
    "gn:name":"Kasurrai",
    "gn:population":0,
    "gn:timezone":"Asia/Karachi",
    "iso:country":"PK",
    "name:und_x_variant":[
        "Katsorai"
    ],
    "wof:name":"Kasurrai",
    "wof:placetype":"locality"
},
  "geometry": {"coordinates":[71.37635,34.5185],"type":"Point"}
}