{
  "type": "Feature",
  "properties": {
    "gn:admin1_code":"4",
    "gn:asciiname":"Chak Two Hundred Thirty-one Rakh Branch",
    "gn:country_code":"PK",
    "gn:dem":182,
    "gn:feature_class":"P",
    "gn:feature_code":"PPL",
    "gn:name":"Chak Two Hundred Thirty-one Rakh Branch",
    "gn:population":0,
    "gn:timezone":"Asia/Karachi",
    "iso:country":"PK",
    "name:und_x_variant":[
        "Ris\u0101lew\u0101la",
        "Chak Two Hundred Thirty-One RB",
        "Chak Two Hundred Thirty-one Rakh Branch"
    ],
    "wof:name":"Chak Two Hundred Thirty-one Rakh Branch",
    "wof:placetype":"neighbourhood"
},
  "geometry": {"coordinates":[73.01224999999999,31.36531],"type":"Point"}
}