{
  "type": "Feature",
  "properties": {
    "gn:admin1_code":"4",
    "gn:asciiname":"Basti Lodhr Wali",
    "gn:country_code":"PK",
    "gn:dem":90,
    "gn:feature_class":"P",
    "gn:feature_code":"PPL",
    "gn:name":"Basti Lodhr Wali",
    "gn:population":0,
    "gn:timezone":"Asia/Karachi",
    "iso:country":"PK",
    "name:und_x_variant":[
        "P\u012braw\u0101la"
    ],
    "wof:name":"Basti Lodhr Wali",
    "wof:placetype":"locality"
},
  "geometry": {"coordinates":[70.36286,29.01421],"type":"Point"}
}