{
  "type": "Feature",
  "properties": {
    "gn:admin1_code":"4",
    "gn:asciiname":"Basti Allah Bakhsh",
    "gn:country_code":"PK",
    "gn:dem":96,
    "gn:feature_class":"P",
    "gn:feature_code":"PPL",
    "gn:name":"Basti Allah Bakhsh",
    "gn:population":0,
    "gn:timezone":"Asia/Karachi",
    "iso:country":"PK",
    "wof:name":"Basti Allah Bakhsh",
    "wof:placetype":"locality"
},
  "geometry": {"coordinates":[70.80785999999998,29.09758],"type":"Point"}
}