{
  "type": "Feature",
  "properties": {
    "gn:admin1_code":"04",
    "gn:asciiname":"Chak Ninety-eight Gugera Branch",
    "gn:country_code":"PK",
    "gn:dem":193,
    "gn:feature_class":"P",
    "gn:feature_code":"PPL",
    "gn:name":"Chak Ninety-eight Gugera Branch",
    "gn:population":0,
    "gn:timezone":"Asia/Karachi",
    "iso:country":"PK",
    "name:und_x_variant":[
        "Saddowal",
        "Saidow\u0101la",
        "Chak Ninety-eight Gugera Branch",
        "Rurka"
    ],
    "wof:name":"Chak Ninety-eight Gugera Branch",
    "wof:placetype":"locality"
},
  "geometry": {"coordinates":[73.41864,31.44207],"type":"Point"}
}