{
  "type": "Feature",
  "properties": {
    "gn:admin1_code":"3.0",
    "gn:asciiname":"Khutti",
    "gn:country_code":"PK",
    "gn:dem":186,
    "gn:feature_class":"P",
    "gn:feature_code":"PPL",
    "gn:name":"Khutti",
    "gn:population":0,
    "gn:timezone":"Asia/Karachi",
    "iso:country":"PK",
    "name:und_x_variant":[
        "Khathi",
        "Khuthi",
        "Khutti"
    ],
    "wof:name":"Khutti",
    "wof:placetype":"locality"
},
  "geometry": {"coordinates":[70.71222,31.83089],"type":"Point"}
}