{
  "type": "Feature",
  "properties": {
    "gn:admin1_code":"4",
    "gn:asciiname":"Kot Paraiya",
    "gn:country_code":"PK",
    "gn:dem":223,
    "gn:feature_class":"P",
    "gn:feature_code":"PPL",
    "gn:name":"Kot Paraiya",
    "gn:population":0,
    "gn:timezone":"Asia/Karachi",
    "iso:country":"PK",
    "name:und_x_variant":[
        "Kot Paroiya"
    ],
    "wof:name":"Kot Paraiya",
    "wof:placetype":"locality"
},
  "geometry": {"coordinates":[74.00505,32.23493],"type":"Point"}
}