{
  "type": "Feature",
  "properties": {
    "gn:admin1_code":"2.0",
    "gn:asciiname":"Iftikhar Stadium",
    "gn:country_code":"PK",
    "gn:dem":1825,
    "gn:feature_class":"P",
    "gn:feature_code":"PPL",
    "gn:name":"Iftikhar Stadium",
    "gn:population":0,
    "gn:timezone":"Asia/Karachi",
    "iso:country":"PK",
    "name:und_x_variant":[
        "Iftikh\u0101r"
    ],
    "wof:name":"Iftikhar Stadium",
    "wof:placetype":"locality"
},
  "geometry": {"coordinates":[67.07639,30.22556],"type":"Point"}
}