{
  "type": "Feature",
  "properties": {
    "gn:admin1_code":"7.0",
    "gn:asciiname":"Gharian Mal",
    "gn:country_code":"PK",
    "gn:dem":3855,
    "gn:feature_class":"P",
    "gn:feature_code":"PPL",
    "gn:name":"Gharian Mal",
    "gn:population":0,
    "gn:timezone":"Asia/Karachi",
    "iso:country":"PK",
    "name:und_x_variant":[
        "Gr\u0101n Muir"
    ],
    "wof:name":"Gharian Mal",
    "wof:placetype":"locality"
},
  "geometry": {"coordinates":[72.61058,36.18503],"type":"Point"}
}