{
  "type": "Feature",
  "properties": {
    "gn:admin1_code":"3.0",
    "gn:asciiname":"Shanu Jur Sair",
    "gn:country_code":"PK",
    "gn:dem":2690,
    "gn:feature_class":"P",
    "gn:feature_code":"PPL",
    "gn:name":"Shanu Jur Sair",
    "gn:population":0,
    "gn:timezone":"Asia/Karachi",
    "iso:country":"PK",
    "wof:name":"Shanu Jur Sair",
    "wof:placetype":"locality"
},
  "geometry": {"coordinates":[71.7453,36.04762],"type":"Point"}
}