{
  "type": "Feature",
  "properties": {
    "gn:admin1_code":"4.0",
    "gn:asciiname":"Sebbar",
    "gn:country_code":"PK",
    "gn:dem":487,
    "gn:feature_class":"P",
    "gn:feature_code":"PPL",
    "gn:name":"Sebbar",
    "gn:population":0,
    "gn:timezone":"Asia/Karachi",
    "iso:country":"PK",
    "wof:name":"Sebbar",
    "wof:placetype":"locality"
},
  "geometry": {"coordinates":[73.37179999999999,33.32437],"type":"Point"}
}