{
  "type": "Feature",
  "properties": {
    "gn:admin1_code":"3.0",
    "gn:asciiname":"Shadad Kalle",
    "gn:country_code":"PK",
    "gn:dem":337,
    "gn:feature_class":"P",
    "gn:feature_code":"PPL",
    "gn:name":"Shadad Kalle",
    "gn:population":0,
    "gn:timezone":"Asia/Karachi",
    "iso:country":"PK",
    "name:eng_x_preferred":[
        "Shadad Kalle"
    ],
    "wof:name":"Shadad Kalle",
    "wof:placetype":"locality"
},
  "geometry": {"coordinates":[72.27207,34.11285],"type":"Point"}
}