{
  "type": "Feature",
  "properties": {
    "gn:admin1_code":"3",
    "gn:asciiname":"Dushankar",
    "gn:country_code":"PK",
    "gn:dem":764,
    "gn:feature_class":"P",
    "gn:feature_code":"PPL",
    "gn:name":"Dushankar",
    "gn:population":0,
    "gn:timezone":"Asia/Karachi",
    "iso:country":"PK",
    "name:und_x_variant":[
        "Dushkanr"
    ],
    "wof:name":"Dushankar",
    "wof:placetype":"locality"
},
  "geometry": {"coordinates":[72.81905999999999,34.47426],"type":"Point"}
}