{
  "type": "Feature",
  "properties": {
    "gn:admin1_code":"3.0",
    "gn:asciiname":"Tungawala Mora",
    "gn:country_code":"PK",
    "gn:dem":1452,
    "gn:feature_class":"P",
    "gn:feature_code":"PPL",
    "gn:name":"Tungawala Mora",
    "gn:population":0,
    "gn:timezone":"Asia/Karachi",
    "iso:country":"PK",
    "name:und_x_variant":[
        "T\u016bngow\u0101la Morah"
    ],
    "wof:name":"Tungawala Mora",
    "wof:placetype":"locality"
},
  "geometry": {"coordinates":[72.40515000000001,34.72209],"type":"Point"}
}