{
  "type": "Feature",
  "properties": {
    "gn:admin1_code":"03",
    "gn:asciiname":"Darbar",
    "gn:country_code":"PK",
    "gn:dem":664,
    "gn:feature_class":"P",
    "gn:feature_code":"PPL",
    "gn:name":"Darbar",
    "gn:population":0,
    "gn:timezone":"Asia/Karachi",
    "iso:country":"PK",
    "name:eng_x_preferred":[
        "Darb\u0101r"
    ],
    "name:und_x_variant":[
        "Darb\u0101o"
    ],
    "wof:name":"Darbar",
    "wof:placetype":"locality"
},
  "geometry": {"coordinates":[71.96719,34.64812],"type":"Point"}
}