{
  "type": "Feature",
  "properties": {
    "gn:admin1_code":"04",
    "gn:asciiname":"Saiyid",
    "gn:country_code":"PK",
    "gn:dem":495,
    "gn:feature_class":"P",
    "gn:feature_code":"PPL",
    "gn:name":"Saiyid",
    "gn:population":0,
    "gn:timezone":"Asia/Karachi",
    "iso:country":"PK",
    "name:und_x_variant":[
        "Sayyed",
        "Saiyid Hamid",
        "Saiyid"
    ],
    "wof:name":"Saiyid",
    "wof:placetype":"locality"
},
  "geometry": {"coordinates":[73.04353,33.10992],"type":"Point"}
}