{
  "type": "Feature",
  "properties": {
    "gn:admin1_code":"3.0",
    "gn:asciiname":"Hamlet",
    "gn:country_code":"PK",
    "gn:dem":362,
    "gn:feature_class":"P",
    "gn:feature_code":"PPL",
    "gn:name":"Hamlet",
    "gn:population":0,
    "gn:timezone":"Asia/Karachi",
    "iso:country":"PK",
    "wof:name":"Hamlet",
    "wof:placetype":"locality"
},
  "geometry": {"coordinates":[72.66235999999998,34.00499],"type":"Point"}
}