{
  "type": "Feature",
  "properties": {
    "gn:admin1_code":"4.0",
    "gn:asciiname":"Khangah Sher Pir",
    "gn:country_code":"PK",
    "gn:dem":98,
    "gn:feature_class":"P",
    "gn:feature_code":"PPL",
    "gn:name":"Khangah Sher Pir",
    "gn:population":0,
    "gn:timezone":"Asia/Karachi",
    "iso:country":"PK",
    "wof:name":"Khangah Sher Pir",
    "wof:placetype":"locality"
},
  "geometry": {"coordinates":[71.00489,29.04365],"type":"Point"}
}