{
  "type": "Feature",
  "properties": {
    "gn:admin1_code":"2.0",
    "gn:asciiname":"Abdul Rahman Pathan",
    "gn:country_code":"PK",
    "gn:dem":58,
    "gn:feature_class":"P",
    "gn:feature_code":"PPL",
    "gn:name":"Abdul Rahman Pathan",
    "gn:population":0,
    "gn:timezone":"Asia/Karachi",
    "iso:country":"PK",
    "name:und_x_variant":[
        "Abdul Rehm\u0101n Path\u0101n"
    ],
    "wof:name":"Abdul Rahman Pathan",
    "wof:placetype":"locality"
},
  "geometry": {"coordinates":[68.23134,28.35585],"type":"Point"}
}