{
  "type": "Feature",
  "properties": {
    "gn:admin1_code":"4.0",
    "gn:asciiname":"Katarian",
    "gn:country_code":"PK",
    "gn:dem":248,
    "gn:feature_class":"P",
    "gn:feature_code":"PPL",
    "gn:name":"Katarian",
    "gn:population":0,
    "gn:timezone":"Asia/Karachi",
    "iso:country":"PK",
    "name:por_x_preferred":[
        "Katarian"
    ],
    "name:und_x_variant":[
        "Kat\u0101ri\u0101n"
    ],
    "wof:name":"Katarian",
    "wof:placetype":"locality"
},
  "geometry": {"coordinates":[75.10514999999999,32.16242],"type":"Point"}
}