{
  "type": "Feature",
  "properties": {
    "gn:admin1_code":"5.0",
    "gn:asciiname":"Goth Lal Khan Hisbani",
    "gn:country_code":"PK",
    "gn:dem":43,
    "gn:feature_class":"P",
    "gn:feature_code":"PPL",
    "gn:name":"Goth Lal Khan Hisbani",
    "gn:population":0,
    "gn:timezone":"Asia/Karachi",
    "iso:country":"PK",
    "wof:name":"Goth Lal Khan Hisbani",
    "wof:placetype":"locality"
},
  "geometry": {"coordinates":[68.25771999999999,26.85544],"type":"Point"}
}