{
  "type": "Feature",
  "properties": {
    "gn:admin1_code":"3.0",
    "gn:asciiname":"Kalu",
    "gn:country_code":"PK",
    "gn:dem":396,
    "gn:feature_class":"P",
    "gn:feature_code":"PPL",
    "gn:name":"Kalu",
    "gn:population":0,
    "gn:timezone":"Asia/Karachi",
    "iso:country":"PK",
    "name:eng_x_preferred":[
        "Kalu"
    ],
    "wof:name":"Kalu",
    "wof:placetype":"locality"
},
  "geometry": {"coordinates":[71.97468000000001,34.41145],"type":"Point"}
}