{
  "type": "Feature",
  "properties": {
    "gn:admin1_code":"6",
    "gn:asciiname":"Chokolni",
    "gn:country_code":"PK",
    "gn:dem":3172,
    "gn:feature_class":"P",
    "gn:feature_code":"PPL",
    "gn:name":"Chokolni",
    "gn:population":0,
    "gn:timezone":"Asia/Karachi",
    "iso:country":"PK",
    "name:und_x_variant":[
        "Chukolni"
    ],
    "wof:name":"Chokolni",
    "wof:placetype":"locality"
},
  "geometry": {"coordinates":[73.64442,34.53346],"type":"Point"}
}