{
  "type": "Feature",
  "properties": {
    "gn:admin1_code":"05",
    "gn:asciiname":"Mahmud Bijarani",
    "gn:country_code":"PK",
    "gn:dem":1,
    "gn:feature_class":"P",
    "gn:feature_code":"PPL",
    "gn:name":"Mahmud Bijarani",
    "gn:population":0,
    "gn:timezone":"Asia/Karachi",
    "iso:country":"PK",
    "wof:name":"Mahmud Bijarani",
    "wof:placetype":"locality"
},
  "geometry": {"coordinates":[67.44783000000001,24.08658],"type":"Point"}
}