{
  "type": "Feature",
  "properties": {
    "gn:admin1_code":"2.0",
    "gn:asciiname":"Abdur Rahman Gis",
    "gn:country_code":"PK",
    "gn:dem":1392,
    "gn:feature_class":"P",
    "gn:feature_code":"PPL",
    "gn:name":"Abdur Rahman Gis",
    "gn:population":0,
    "gn:timezone":"Asia/Karachi",
    "iso:country":"PK",
    "wof:name":"Abdur Rahman Gis",
    "wof:placetype":"locality"
},
  "geometry": {"coordinates":[64.04355,29.28281],"type":"Point"}
}