{
  "type": "Feature",
  "properties": {
    "gn:admin1_code":"2.0",
    "gn:asciiname":"Goth Yaru",
    "gn:country_code":"PK",
    "gn:dem":540,
    "gn:feature_class":"P",
    "gn:feature_code":"PPL",
    "gn:name":"Goth Yaru",
    "gn:population":0,
    "gn:timezone":"Asia/Karachi",
    "iso:country":"PK",
    "wof:name":"Goth Yaru",
    "wof:placetype":"locality"
},
  "geometry": {"coordinates":[65.08150000000001,26.38658],"type":"Point"}
}