{
  "type": "Feature",
  "properties": {
    "gn:admin1_code":"1.0",
    "gn:asciiname":"Loe Shah",
    "gn:country_code":"PK",
    "gn:dem":880,
    "gn:feature_class":"P",
    "gn:feature_code":"PPL",
    "gn:name":"Loe Shah",
    "gn:population":0,
    "gn:timezone":"Asia/Karachi",
    "iso:country":"PK",
    "wof:name":"Loe Shah",
    "wof:placetype":"locality"
},
  "geometry": {"coordinates":[71.45278,34.43595],"type":"Point"}
}