{
  "type": "Feature",
  "properties": {
    "gn:admin1_code":"4.0",
    "gn:asciiname":"Qandharipur",
    "gn:country_code":"PK",
    "gn:dem":423,
    "gn:feature_class":"P",
    "gn:feature_code":"PPL",
    "gn:name":"Qandharipur",
    "gn:population":0,
    "gn:timezone":"Asia/Karachi",
    "iso:country":"PK",
    "wof:name":"Qandharipur",
    "wof:placetype":"locality"
},
  "geometry": {"coordinates":[72.67859,33.7996],"type":"Point"}
}