{
  "type": "Feature",
  "properties": {
    "gn:admin1_code":"3.0",
    "gn:asciiname":"Ashkot",
    "gn:country_code":"PK",
    "gn:dem":1637,
    "gn:feature_class":"P",
    "gn:feature_code":"PPL",
    "gn:name":"Ashkot",
    "gn:population":0,
    "gn:timezone":"Asia/Karachi",
    "iso:country":"PK",
    "wof:name":"Ashkot",
    "wof:placetype":"locality"
},
  "geometry": {"coordinates":[72.84766999999999,34.52495],"type":"Point"}
}