{
  "type": "Feature",
  "properties": {
    "gn:admin1_code":"6",
    "gn:asciiname":"Baruth",
    "gn:country_code":"PK",
    "gn:dem":788,
    "gn:feature_class":"P",
    "gn:feature_code":"PPL",
    "gn:name":"Baruth",
    "gn:population":0,
    "gn:timezone":"Asia/Karachi",
    "iso:country":"PK",
    "name:und_x_variant":[
        "B\u0101r\u016bth"
    ],
    "wof:name":"Baruth",
    "wof:placetype":"locality"
},
  "geometry": {"coordinates":[74.03513000000002,33.33717],"type":"Point"}
}