{
  "type": "Feature",
  "properties": {
    "gn:admin1_code":"4.0",
    "gn:asciiname":"Dhok Saifal",
    "gn:country_code":"PK",
    "gn:dem":480,
    "gn:feature_class":"P",
    "gn:feature_code":"PPL",
    "gn:name":"Dhok Saifal",
    "gn:population":0,
    "gn:timezone":"Asia/Karachi",
    "iso:country":"PK",
    "wof:name":"Dhok Saifal",
    "wof:placetype":"locality"
},
  "geometry": {"coordinates":[71.92981999999998,33.22483],"type":"Point"}
}