{
  "type": "Feature",
  "properties": {
    "gn:admin1_code":"03",
    "gn:asciiname":"Niaze Banda",
    "gn:country_code":"PK",
    "gn:dem":958,
    "gn:feature_class":"P",
    "gn:feature_code":"PPL",
    "gn:name":"Niaze Banda",
    "gn:population":0,
    "gn:timezone":"Asia/Karachi",
    "iso:country":"PK",
    "wof:name":"Niaze Banda",
    "wof:placetype":"locality"
},
  "geometry": {"coordinates":[70.74817,33.36285],"type":"Point"}
}