{
  "type": "Feature",
  "properties": {
    "gn:admin1_code":"4",
    "gn:asciiname":"Bunga Jiwan",
    "gn:country_code":"PK",
    "gn:dem":172,
    "gn:feature_class":"P",
    "gn:feature_code":"PPL",
    "gn:name":"Bunga Jiwan",
    "gn:population":0,
    "gn:timezone":"Asia/Karachi",
    "iso:country":"PK",
    "name:und_x_variant":[
        "Bunga Sindhu\u0101n"
    ],
    "wof:name":"Bunga Jiwan",
    "wof:placetype":"locality"
},
  "geometry": {"coordinates":[73.80298000000001,30.27657],"type":"Point"}
}