{
  "type": "Feature",
  "properties": {
    "gn:admin1_code":"4.0",
    "gn:asciiname":"Dhangran",
    "gn:country_code":"PK",
    "gn:dem":1507,
    "gn:feature_class":"P",
    "gn:feature_code":"PPL",
    "gn:name":"Dhangran",
    "gn:population":0,
    "gn:timezone":"Asia/Karachi",
    "iso:country":"PK",
    "name:und_x_variant":[
        "Dhan Garan",
        "Dhangran"
    ],
    "wof:name":"Dhangran",
    "wof:placetype":"locality"
},
  "geometry": {"coordinates":[73.51264999999999,33.86207],"type":"Point"}
}