{
  "type": "Feature",
  "properties": {
    "gn:admin1_code":"5",
    "gn:asciiname":"Goth Bakhshu",
    "gn:country_code":"PK",
    "gn:dem":14,
    "gn:feature_class":"P",
    "gn:feature_code":"PPL",
    "gn:name":"Goth Bakhshu",
    "gn:population":0,
    "gn:timezone":"Asia/Karachi",
    "iso:country":"PK",
    "name:und_x_variant":[
        "Goth Bakhshu Baloch"
    ],
    "wof:name":"Goth Bakhshu",
    "wof:placetype":"locality"
},
  "geometry": {"coordinates":[69.00634000000001,25.11987],"type":"Point"}
}