{
  "type": "Feature",
  "properties": {
    "gn:admin1_code":"2.0",
    "gn:asciiname":"Mast",
    "gn:country_code":"PK",
    "gn:dem":1470,
    "gn:feature_class":"P",
    "gn:feature_code":"PPL",
    "gn:name":"Mast",
    "gn:population":0,
    "gn:timezone":"Asia/Karachi",
    "iso:country":"PK",
    "wof:name":"Mast",
    "wof:placetype":"locality"
},
  "geometry": {"coordinates":[66.51644,30.45478],"type":"Point"}
}