{
  "type": "Feature",
  "properties": {
    "gn:admin1_code":"5.0",
    "gn:asciiname":"Goth Abdullah Mallah",
    "gn:country_code":"PK",
    "gn:dem":1,
    "gn:feature_class":"P",
    "gn:feature_code":"PPL",
    "gn:name":"Goth Abdullah Mallah",
    "gn:population":0,
    "gn:timezone":"Asia/Karachi",
    "iso:country":"PK",
    "wof:name":"Goth Abdullah Mallah",
    "wof:placetype":"locality"
},
  "geometry": {"coordinates":[67.59635,24.19128],"type":"Point"}
}