{
  "type": "Feature",
  "properties": {
    "gn:admin1_code":"5",
    "gn:asciiname":"Ghazi Hashim",
    "gn:country_code":"PK",
    "gn:dem":20,
    "gn:feature_class":"P",
    "gn:feature_code":"PPL",
    "gn:name":"Ghazi Hashim",
    "gn:population":0,
    "gn:timezone":"Asia/Karachi",
    "iso:country":"PK",
    "wof:name":"Ghazi Hashim",
    "wof:placetype":"locality"
},
  "geometry": {"coordinates":[69.44956999999999,25.9938],"type":"Point"}
}