{
  "type": "Feature",
  "properties": {
    "gn:admin1_code":"2.0",
    "gn:asciiname":"Sur Tangai Kili",
    "gn:country_code":"PK",
    "gn:dem":1640,
    "gn:feature_class":"P",
    "gn:feature_code":"PPL",
    "gn:name":"Sur Tangai Kili",
    "gn:population":0,
    "gn:timezone":"Asia/Karachi",
    "iso:country":"PK",
    "wof:name":"Sur Tangai Kili",
    "wof:placetype":"locality"
},
  "geometry": {"coordinates":[68.47728000000001,30.87324000000001],"type":"Point"}
}