{
  "type": "Feature",
  "properties": {
    "gn:admin1_code":"1.0",
    "gn:asciiname":"Mala Kalle",
    "gn:country_code":"PK",
    "gn:dem":1964,
    "gn:feature_class":"P",
    "gn:feature_code":"PPL",
    "gn:name":"Mala Kalle",
    "gn:population":0,
    "gn:timezone":"Asia/Karachi",
    "iso:country":"PK",
    "wof:name":"Mala Kalle",
    "wof:placetype":"locality"
},
  "geometry": {"coordinates":[70.79120999999998,33.74232],"type":"Point"}
}