{
  "type": "Feature",
  "properties": {
    "gn:admin1_code":"1.0",
    "gn:asciiname":"Angar",
    "gn:country_code":"PK",
    "gn:dem":1441,
    "gn:feature_class":"P",
    "gn:feature_code":"PPL",
    "gn:name":"Angar",
    "gn:population":0,
    "gn:timezone":"Asia/Karachi",
    "iso:country":"PK",
    "name:und_x_variant":[
        "Kharkai N\u0101o"
    ],
    "wof:name":"Angar",
    "wof:placetype":"locality"
},
  "geometry": {"coordinates":[71.43071999999999,34.88392],"type":"Point"}
}