{
  "type": "Feature",
  "properties": {
    "gn:admin1_code":"2.0",
    "gn:asciiname":"Jumma Gul Kili",
    "gn:country_code":"PK",
    "gn:dem":973,
    "gn:feature_class":"P",
    "gn:feature_code":"PPL",
    "gn:name":"Jumma Gul Kili",
    "gn:population":0,
    "gn:timezone":"Asia/Karachi",
    "iso:country":"PK",
    "wof:name":"Jumma Gul Kili",
    "wof:placetype":"locality"
},
  "geometry": {"coordinates":[69.48312,31.93198],"type":"Point"}
}