{
  "type": "Feature",
  "properties": {
    "gn:admin1_code":"4",
    "gn:asciiname":"Chak Three Hundred Ninety-three Jhang Branch",
    "gn:country_code":"PK",
    "gn:dem":155,
    "gn:feature_class":"P",
    "gn:feature_code":"PPL",
    "gn:name":"Chak Three Hundred Ninety-three Jhang Branch",
    "gn:population":0,
    "gn:timezone":"Asia/Karachi",
    "iso:country":"PK",
    "name:und_x_variant":[
        "Chak Three Hundred Ninety-Three JB",
        "Kh\u0101npur",
        "Chak Three Hundred Ninety-three Jhang Branch"
    ],
    "wof:name":"Chak Three Hundred Ninety-three Jhang Branch",
    "wof:placetype":"locality"
},
  "geometry": {"coordinates":[72.41543,30.97148],"type":"Point"}
}