{
  "type": "Feature",
  "properties": {
    "gn:admin1_code":"4",
    "gn:asciiname":"Mohra Kalial",
    "gn:country_code":"PK",
    "gn:dem":483,
    "gn:feature_class":"P",
    "gn:feature_code":"PPL",
    "gn:name":"Mohra Kalial",
    "gn:population":0,
    "gn:timezone":"Asia/Karachi",
    "iso:country":"PK",
    "wof:name":"Mohra Kalial",
    "wof:placetype":"locality"
},
  "geometry": {"coordinates":[73.2801,33.13330999999999],"type":"Point"}
}