{
  "type": "Feature",
  "properties": {
    "gn:admin1_code":"4.0",
    "gn:asciiname":"Faqirwala",
    "gn:country_code":"PK",
    "gn:dem":143,
    "gn:feature_class":"P",
    "gn:feature_code":"PPL",
    "gn:name":"Faqirwala",
    "gn:population":0,
    "gn:timezone":"Asia/Karachi",
    "iso:country":"PK",
    "name:fas_x_preferred":[
        "\u0641\u0642\u06cc\u0631\u0648\u0627\u0644\u0627"
    ],
    "name:und_x_variant":[
        "Faq\u012br\u0101nw\u0101la"
    ],
    "wof:name":"Faqirwala",
    "wof:placetype":"locality"
},
  "geometry": {"coordinates":[70.98098,30.80109],"type":"Point"}
}