{
  "type": "Feature",
  "properties": {
    "gn:admin1_code":"4",
    "gn:asciiname":"Chah Wazirwala",
    "gn:country_code":"PK",
    "gn:dem":129,
    "gn:feature_class":"P",
    "gn:feature_code":"PPL",
    "gn:name":"Chah Wazirwala",
    "gn:population":0,
    "gn:timezone":"Asia/Karachi",
    "iso:country":"PK",
    "name:und_x_variant":[
        "Basti Wasso R\u0101mw\u0101li",
        "Bastin Wasso R\u0101mw\u0101li",
        "Chah Wazirwala"
    ],
    "wof:name":"Chah Wazirwala",
    "wof:placetype":"locality"
},
  "geometry": {"coordinates":[71.58558000000002,30.19025],"type":"Point"}
}