{
  "type": "Feature",
  "properties": {
    "gn:admin1_code":"01",
    "gn:asciiname":"Zor Mandai",
    "gn:country_code":"PK",
    "gn:dem":884,
    "gn:feature_class":"P",
    "gn:feature_code":"PPL",
    "gn:name":"Zor Mandai",
    "gn:population":0,
    "gn:timezone":"Asia/Karachi",
    "iso:country":"PK",
    "name:und_x_variant":[
        "Zar Mandai"
    ],
    "wof:name":"Zor Mandai",
    "wof:placetype":"locality"
},
  "geometry": {"coordinates":[71.4631,34.70513],"type":"Point"}
}