{
  "type": "Feature",
  "properties": {
    "gn:admin1_code":"4.0",
    "gn:asciiname":"Kandiwal",
    "gn:country_code":"PK",
    "gn:dem":189,
    "gn:feature_class":"P",
    "gn:feature_code":"PPL",
    "gn:name":"Kandiwal",
    "gn:population":0,
    "gn:timezone":"Asia/Karachi",
    "iso:country":"PK",
    "name:und_x_variant":[
        "Kand\u012bw\u0101la"
    ],
    "wof:name":"Kandiwal",
    "wof:placetype":"locality"
},
  "geometry": {"coordinates":[72.94009,31.91087000000001],"type":"Point"}
}