{
  "type": "Feature",
  "properties": {
    "gn:admin1_code":"4.0",
    "gn:asciiname":"Dhok Haji Feroz",
    "gn:country_code":"PK",
    "gn:dem":346,
    "gn:feature_class":"P",
    "gn:feature_code":"PPL",
    "gn:name":"Dhok Haji Feroz",
    "gn:population":0,
    "gn:timezone":"Asia/Karachi",
    "iso:country":"PK",
    "name:und_x_variant":[
        "Dhok H\u0101ji Feroz"
    ],
    "wof:name":"Dhok Haji Feroz",
    "wof:placetype":"locality"
},
  "geometry": {"coordinates":[71.97386,33.14798],"type":"Point"}
}