{
  "type": "Feature",
  "properties": {
    "gn:admin1_code":"3.0",
    "gn:asciiname":"Dhok Lani",
    "gn:country_code":"PK",
    "gn:dem":303,
    "gn:feature_class":"P",
    "gn:feature_code":"PPL",
    "gn:name":"Dhok Lani",
    "gn:population":0,
    "gn:timezone":"Asia/Karachi",
    "iso:country":"PK",
    "wof:name":"Dhok Lani",
    "wof:placetype":"locality"
},
  "geometry": {"coordinates":[71.86405000000001,33.47017],"type":"Point"}
}