{
  "type": "Feature",
  "properties": {
    "gn:admin1_code":"03",
    "gn:asciiname":"Banda Begran",
    "gn:country_code":"PK",
    "gn:dem":273,
    "gn:feature_class":"P",
    "gn:feature_code":"PPL",
    "gn:name":"Banda Begran",
    "gn:population":0,
    "gn:timezone":"Asia/Karachi",
    "iso:country":"PK",
    "name:und_x_variant":[
        "Muhammad Kh\u0101n B\u0101nda",
        "Banda Begran"
    ],
    "wof:name":"Banda Begran",
    "wof:placetype":"locality"
},
  "geometry": {"coordinates":[70.81338000000002,32.61649],"type":"Point"}
}