{
  "type": "Feature",
  "properties": {
    "gn:admin1_code":"1",
    "gn:asciiname":"Spedorai",
    "gn:country_code":"PK",
    "gn:dem":1477,
    "gn:feature_class":"P",
    "gn:feature_code":"PPL",
    "gn:name":"Spedorai",
    "gn:population":0,
    "gn:timezone":"Asia/Karachi",
    "iso:country":"PK",
    "wof:name":"Spedorai",
    "wof:placetype":"locality"
},
  "geometry": {"coordinates":[69.95365,32.57404],"type":"Point"}
}