{
  "type": "Feature",
  "properties": {
    "gn:admin1_code":"7.0",
    "gn:asciiname":"Chamangul",
    "gn:country_code":"PK",
    "gn:dem":2512,
    "gn:feature_class":"P",
    "gn:feature_code":"PPL",
    "gn:name":"Chamangul",
    "gn:population":0,
    "gn:timezone":"Asia/Karachi",
    "iso:country":"PK",
    "wof:name":"Chamangul",
    "wof:placetype":"locality"
},
  "geometry": {"coordinates":[74.86004,36.38023],"type":"Point"}
}