{
  "type": "Feature",
  "properties": {
    "gn:admin1_code":"5.0",
    "gn:asciiname":"Goth Haji Khan Laghari",
    "gn:country_code":"PK",
    "gn:dem":23,
    "gn:feature_class":"P",
    "gn:feature_code":"PPL",
    "gn:name":"Goth Haji Khan Laghari",
    "gn:population":0,
    "gn:timezone":"Asia/Karachi",
    "iso:country":"PK",
    "name:eng_x_preferred":[
        "Goth Ans\u0101ri"
    ],
    "name:eng_x_variant":[
        "Goth Haji Khan Laghari"
    ],
    "wof:name":"Goth Haji Khan Laghari",
    "wof:placetype":"locality"
},
  "geometry": {"coordinates":[68.34931,25.34881],"type":"Point"}
}