{
  "type": "Feature",
  "properties": {
    "gn:admin1_code":"6",
    "gn:asciiname":"Grangan",
    "gn:country_code":"PK",
    "gn:dem":2159,
    "gn:feature_class":"P",
    "gn:feature_code":"PPL",
    "gn:name":"Grangan",
    "gn:population":0,
    "gn:timezone":"Asia/Karachi",
    "iso:country":"PK",
    "name:und_x_variant":[
        "Khetar"
    ],
    "wof:name":"Grangan",
    "wof:placetype":"locality"
},
  "geometry": {"coordinates":[73.69261,34.34776],"type":"Point"}
}