{
  "type": "Feature",
  "properties": {
    "gn:admin1_code":"1.0",
    "gn:asciiname":"Channe Kalle",
    "gn:country_code":"PK",
    "gn:dem":1271,
    "gn:feature_class":"P",
    "gn:feature_code":"PPL",
    "gn:name":"Channe Kalle",
    "gn:population":0,
    "gn:timezone":"Asia/Karachi",
    "iso:country":"PK",
    "wof:name":"Channe Kalle",
    "wof:placetype":"locality"
},
  "geometry": {"coordinates":[70.94573000000003,33.63206],"type":"Point"}
}