{
  "type": "Feature",
  "properties": {
    "gn:admin1_code":"4",
    "gn:asciiname":"Kaura Saldeva",
    "gn:country_code":"PK",
    "gn:dem":143,
    "gn:feature_class":"P",
    "gn:feature_code":"PPL",
    "gn:name":"Kaura Saldeva",
    "gn:population":0,
    "gn:timezone":"Asia/Karachi",
    "iso:country":"PK",
    "name:und_x_variant":[
        "B\u0101gh Ali Saldera"
    ],
    "wof:name":"Kaura Saldeva",
    "wof:placetype":"locality"
},
  "geometry": {"coordinates":[72.68841,29.9561],"type":"Point"}
}