{
  "type": "Feature",
  "properties": {
    "gn:admin1_code":"4.0",
    "gn:asciiname":"Fatehb",
    "gn:country_code":"PK",
    "gn:dem":165,
    "gn:feature_class":"P",
    "gn:feature_code":"PPL",
    "gn:name":"Fatehb",
    "gn:population":0,
    "gn:timezone":"Asia/Karachi",
    "iso:country":"PK",
    "wof:name":"Fatehb",
    "wof:placetype":"locality"
},
  "geometry": {"coordinates":[73.62619000000002,30.14794],"type":"Point"}
}