{
  "type": "Feature",
  "properties": {
    "gn:admin1_code":"2.0",
    "gn:asciiname":"Chakar Kaur",
    "gn:country_code":"PK",
    "gn:dem":717,
    "gn:feature_class":"P",
    "gn:feature_code":"PPL",
    "gn:name":"Chakar Kaur",
    "gn:population":0,
    "gn:timezone":"Asia/Karachi",
    "iso:country":"PK",
    "wof:name":"Chakar Kaur",
    "wof:placetype":"locality"
},
  "geometry": {"coordinates":[65.51009999999999,28.41453],"type":"Point"}
}