{
  "type": "Feature",
  "properties": {
    "gn:admin1_code":"04",
    "gn:asciiname":"Basti Tatepur",
    "gn:country_code":"PK",
    "gn:dem":125,
    "gn:feature_class":"P",
    "gn:feature_code":"PPL",
    "gn:name":"Basti Tatepur",
    "gn:population":0,
    "gn:timezone":"Asia/Karachi",
    "iso:country":"PK",
    "name:und_x_variant":[
        "T\u0101tipur",
        "T\u0101tepur",
        "Basti Tatepur"
    ],
    "wof:name":"Basti Tatepur",
    "wof:placetype":"locality"
},
  "geometry": {"coordinates":[71.6617,30.23067],"type":"Point"}
}