{
  "type": "Feature",
  "properties": {
    "gn:admin1_code":"4.0",
    "gn:asciiname":"Wan Bhulleki",
    "gn:country_code":"PK",
    "gn:dem":179,
    "gn:feature_class":"P",
    "gn:feature_code":"PPL",
    "gn:name":"Wan Bhulleki",
    "gn:population":0,
    "gn:timezone":"Asia/Karachi",
    "iso:country":"PK",
    "name:und_x_variant":[
        "W\u0101n B\u016bhleka"
    ],
    "wof:name":"Wan Bhulleki",
    "wof:placetype":"locality"
},
  "geometry": {"coordinates":[73.39674000000002,30.97419],"type":"Point"}
}