{
  "type": "Feature",
  "properties": {
    "gn:admin1_code":"4",
    "gn:asciiname":"Kale Arain",
    "gn:country_code":"PK",
    "gn:dem":98,
    "gn:feature_class":"P",
    "gn:feature_code":"PPL",
    "gn:name":"Kale Arain",
    "gn:population":0,
    "gn:timezone":"Asia/Karachi",
    "iso:country":"PK",
    "name:und_x_variant":[
        "Ar\u0101\u012bnw\u0101la"
    ],
    "wof:name":"Kale Arain",
    "wof:placetype":"locality"
},
  "geometry": {"coordinates":[70.74087,29.26473],"type":"Point"}
}