{
  "type": "Feature",
  "properties": {
    "gn:admin1_code":"6",
    "gn:asciiname":"Bani",
    "gn:country_code":"PK",
    "gn:dem":1773,
    "gn:feature_class":"P",
    "gn:feature_code":"PPL",
    "gn:name":"Bani",
    "gn:population":0,
    "gn:timezone":"Asia/Karachi",
    "iso:country":"PK",
    "name:cat_x_preferred":[
        "Bani"
    ],
    "name:ceb_x_preferred":[
        "Bani"
    ],
    "name:ces_x_preferred":[
        "Bani"
    ],
    "name:deu_x_preferred":[
        "Bani"
    ],
    "name:fas_x_preferred":[
        "\u0628\u0627\u0646\u06cc"
    ],
    "name:fra_x_preferred":[
        "Bani"
    ],
    "name:ita_x_preferred":[
        "Bani"
    ],
    "name:kat_x_preferred":[
        "\u10d1\u10d0\u10dc\u10d8"
    ],
    "name:nld_x_preferred":[
        "Bani"
    ],
    "name:por_x_preferred":[
        "Bani"
    ],
    "name:rus_x_preferred":[
        "\u0411\u0430\u043d\u0438"
    ],
    "name:spa_x_preferred":[
        "Bani"
    ],
    "name:swe_x_preferred":[
        "Bani"
    ],
    "name:und_x_variant":[
        "Bhengar Bagi",
        "Bhangar Bani"
    ],
    "name:war_x_preferred":[
        "Bani"
    ],
    "wof:name":"Bani",
    "wof:placetype":"locality"
},
  "geometry": {"coordinates":[74.13836999999999,33.90286],"type":"Point"}
}