{
  "type": "Feature",
  "properties": {
    "gn:admin1_code":"04",
    "gn:asciiname":"Naragghi",
    "gn:country_code":"PK",
    "gn:dem":385,
    "gn:feature_class":"P",
    "gn:feature_code":"PPL",
    "gn:name":"Naragghi",
    "gn:population":0,
    "gn:timezone":"Asia/Karachi",
    "iso:country":"PK",
    "name:und_x_variant":[
        "Naraggi"
    ],
    "wof:name":"Naragghi",
    "wof:placetype":"locality"
},
  "geometry": {"coordinates":[72.41535999999998,33.11207],"type":"Point"}
}