{
  "type": "Feature",
  "properties": {
    "gn:admin1_code":"5",
    "gn:asciiname":"Goth Bari Dubarji",
    "gn:country_code":"PK",
    "gn:dem":13,
    "gn:feature_class":"P",
    "gn:feature_code":"PPL",
    "gn:name":"Goth Bari Dubarji",
    "gn:population":0,
    "gn:timezone":"Asia/Karachi",
    "iso:country":"PK",
    "name:und_x_variant":[
        "Ras\u016blpur"
    ],
    "wof:name":"Goth Bari Dubarji",
    "wof:placetype":"locality"
},
  "geometry": {"coordinates":[69.19232,25.18385],"type":"Point"}
}