{
  "type": "Feature",
  "properties": {
    "gn:admin1_code":"4.0",
    "gn:asciiname":"Sambli Tijal",
    "gn:country_code":"PK",
    "gn:dem":1204,
    "gn:feature_class":"P",
    "gn:feature_code":"PPL",
    "gn:name":"Sambli Tijal",
    "gn:population":0,
    "gn:timezone":"Asia/Karachi",
    "iso:country":"PK",
    "name:eng_x_preferred":[
        "S\u0101mbir Tilal"
    ],
    "wof:name":"Sambli Tijal",
    "wof:placetype":"locality"
},
  "geometry": {"coordinates":[73.32026,33.85998],"type":"Point"}
}