{
  "type": "Feature",
  "properties": {
    "gn:admin1_code":"2.0",
    "gn:asciiname":"Kasag",
    "gn:country_code":"PK",
    "gn:dem":1502,
    "gn:feature_class":"P",
    "gn:feature_code":"PPL",
    "gn:name":"Kasag",
    "gn:population":0,
    "gn:timezone":"Asia/Karachi",
    "iso:country":"PK",
    "wof:name":"Kasag",
    "wof:placetype":"locality"
},
  "geometry": {"coordinates":[69.92191,31.30554],"type":"Point"}
}