{
  "type": "Feature",
  "properties": {
    "gn:admin1_code":"3",
    "gn:asciiname":"Asharai",
    "gn:country_code":"PK",
    "gn:dem":1057,
    "gn:feature_class":"P",
    "gn:feature_code":"PPL",
    "gn:name":"Asharai",
    "gn:population":0,
    "gn:timezone":"Asia/Karachi",
    "iso:country":"PK",
    "name:und_x_variant":[
        "As\u012brai"
    ],
    "wof:name":"Asharai",
    "wof:placetype":"locality"
},
  "geometry": {"coordinates":[72.71338,34.68752],"type":"Point"}
}