{
  "type": "Feature",
  "properties": {
    "gn:admin1_code":"3.0",
    "gn:asciiname":"Adina",
    "gn:country_code":"PK",
    "gn:dem":320,
    "gn:feature_class":"P",
    "gn:feature_code":"PPL",
    "gn:name":"Adina",
    "gn:population":0,
    "gn:timezone":"Asia/Karachi",
    "iso:country":"PK",
    "name:deu_x_preferred":[
        "Adina"
    ],
    "name:eng_x_preferred":[
        "Adina"
    ],
    "name:glg_x_preferred":[
        "Adina"
    ],
    "name:hun_x_preferred":[
        "Adina"
    ],
    "name:ita_x_preferred":[
        "Adina"
    ],
    "name:pol_x_preferred":[
        "Adina"
    ],
    "name:slk_x_preferred":[
        "Adina"
    ],
    "wof:name":"Adina",
    "wof:placetype":"locality"
},
  "geometry": {"coordinates":[72.26205,34.21943],"type":"Point"}
}