{
  "type": "Feature",
  "properties": {
    "gn:admin1_code":"3",
    "gn:asciiname":"Jabri",
    "gn:country_code":"PK",
    "gn:dem":1154,
    "gn:feature_class":"P",
    "gn:feature_code":"PPL",
    "gn:name":"Jabri",
    "gn:population":0,
    "gn:timezone":"Asia/Karachi",
    "iso:country":"PK",
    "wof:name":"Jabri",
    "wof:placetype":"locality"
},
  "geometry": {"coordinates":[73.24235999999998,34.54133],"type":"Point"}
}