{
  "type": "Feature",
  "properties": {
    "gn:admin1_code":"5",
    "gn:asciiname":"Goth Hayat Bhatti",
    "gn:country_code":"PK",
    "gn:dem":24,
    "gn:feature_class":"P",
    "gn:feature_code":"PPL",
    "gn:name":"Goth Hayat Bhatti",
    "gn:population":0,
    "gn:timezone":"Asia/Karachi",
    "iso:country":"PK",
    "name:eng_x_preferred":[
        "Hay\u0101t Bhatti"
    ],
    "wof:name":"Goth Hayat Bhatti",
    "wof:placetype":"locality"
},
  "geometry": {"coordinates":[68.46332,25.46293],"type":"Point"}
}