{
  "type": "Feature",
  "properties": {
    "gn:admin1_code":"4",
    "gn:asciiname":"Basti Dhora Jasuani",
    "gn:country_code":"PK",
    "gn:dem":94,
    "gn:feature_class":"P",
    "gn:feature_code":"PPL",
    "gn:name":"Basti Dhora Jasuani",
    "gn:population":0,
    "gn:timezone":"Asia/Karachi",
    "iso:country":"PK",
    "name:und_x_variant":[
        "Basti S\u0101diq"
    ],
    "wof:name":"Basti Dhora Jasuani",
    "wof:placetype":"locality"
},
  "geometry": {"coordinates":[70.42066,29.08956],"type":"Point"}
}