{
  "type": "Feature",
  "properties": {
    "gn:admin1_code":"3.0",
    "gn:asciiname":"Harno Bazar",
    "gn:country_code":"PK",
    "gn:dem":1298,
    "gn:feature_class":"P",
    "gn:feature_code":"PPL",
    "gn:name":"Harno Bazar",
    "gn:population":0,
    "gn:timezone":"Asia/Karachi",
    "iso:country":"PK",
    "wof:name":"Harno Bazar",
    "wof:placetype":"locality"
},
  "geometry": {"coordinates":[73.30274,34.15351],"type":"Point"}
}