{
  "type": "Feature",
  "properties": {
    "gn:admin1_code":"5.0",
    "gn:asciiname":"Jhupia",
    "gn:country_code":"PK",
    "gn:dem":30,
    "gn:feature_class":"P",
    "gn:feature_code":"PPL",
    "gn:name":"Jhupia",
    "gn:population":0,
    "gn:timezone":"Asia/Karachi",
    "iso:country":"PK",
    "name:und_x_variant":[
        "Jhupio"
    ],
    "wof:name":"Jhupia",
    "wof:placetype":"locality"
},
  "geometry": {"coordinates":[69.61717,24.35954],"type":"Point"}
}