{
  "type": "Feature",
  "properties": {
    "gn:admin1_code":"4",
    "gn:asciiname":"Thatta Ranera Kalan",
    "gn:country_code":"PK",
    "gn:dem":181,
    "gn:feature_class":"P",
    "gn:feature_code":"PPL",
    "gn:name":"Thatta Ranera Kalan",
    "gn:population":0,
    "gn:timezone":"Asia/Karachi",
    "iso:country":"PK",
    "wof:name":"Thatta Ranera Kalan",
    "wof:placetype":"locality"
},
  "geometry": {"coordinates":[73.41249999999999,31.10694],"type":"Point"}
}