{
  "type": "Feature",
  "properties": {
    "gn:admin1_code":"2.0",
    "gn:asciiname":"Wahid Bakhsh Brahui",
    "gn:country_code":"PK",
    "gn:dem":57,
    "gn:feature_class":"P",
    "gn:feature_code":"PPL",
    "gn:name":"Wahid Bakhsh Brahui",
    "gn:population":0,
    "gn:timezone":"Asia/Karachi",
    "iso:country":"PK",
    "wof:name":"Wahid Bakhsh Brahui",
    "wof:placetype":"locality"
},
  "geometry": {"coordinates":[68.17429,28.24068],"type":"Point"}
}