{
  "type": "Feature",
  "properties": {
    "gn:admin1_code":"5.0",
    "gn:asciiname":"Goth Muhammad Khan Bhatti",
    "gn:country_code":"PK",
    "gn:dem":13,
    "gn:feature_class":"P",
    "gn:feature_code":"PPL",
    "gn:name":"Goth Muhammad Khan Bhatti",
    "gn:population":0,
    "gn:timezone":"Asia/Karachi",
    "iso:country":"PK",
    "name:und_x_variant":[
        "Goth Muhammad Khan Bhatt"
    ],
    "wof:name":"Goth Muhammad Khan Bhatti",
    "wof:placetype":"locality"
},
  "geometry": {"coordinates":[67.99408000000001,24.78333],"type":"Point"}
}