{
  "type": "Feature",
  "properties": {
    "gn:admin1_code":"6",
    "gn:asciiname":"Mohra Khakharial",
    "gn:country_code":"PK",
    "gn:dem":779,
    "gn:feature_class":"P",
    "gn:feature_code":"PPL",
    "gn:name":"Mohra Khakharial",
    "gn:population":0,
    "gn:timezone":"Asia/Karachi",
    "iso:country":"PK",
    "wof:name":"Mohra Khakharial",
    "wof:placetype":"locality"
},
  "geometry": {"coordinates":[73.94286,33.6349],"type":"Point"}
}