{
  "type": "Feature",
  "properties": {
    "gn:admin1_code":"8.0",
    "gn:asciiname":"Shahdara Kalan",
    "gn:country_code":"PK",
    "gn:dem":800,
    "gn:feature_class":"P",
    "gn:feature_code":"PPL",
    "gn:name":"Shahdara Kalan",
    "gn:population":0,
    "gn:timezone":"Asia/Karachi",
    "iso:country":"PK",
    "wof:name":"Shahdara Kalan",
    "wof:placetype":"locality"
},
  "geometry": {"coordinates":[73.19604,33.80135],"type":"Point"}
}