{
  "type": "Feature",
  "properties": {
    "gn:admin1_code":"05",
    "gn:asciiname":"Goth Shevo Jamali",
    "gn:country_code":"PK",
    "gn:dem":65,
    "gn:feature_class":"P",
    "gn:feature_code":"PPL",
    "gn:name":"Goth Shevo Jamali",
    "gn:population":0,
    "gn:timezone":"Asia/Karachi",
    "iso:country":"PK",
    "name:und_x_variant":[
        "Sewe Jam\u0101li"
    ],
    "wof:name":"Goth Shevo Jamali",
    "wof:placetype":"locality"
},
  "geometry": {"coordinates":[67.38259000000001,26.7524],"type":"Point"}
}