{
  "type": "Feature",
  "properties": {
    "gn:admin1_code":"5.0",
    "gn:asciiname":"Goth Gulab Laghari",
    "gn:country_code":"PK",
    "gn:dem":21,
    "gn:feature_class":"P",
    "gn:feature_code":"PPL",
    "gn:name":"Goth Gulab Laghari",
    "gn:population":0,
    "gn:timezone":"Asia/Karachi",
    "iso:country":"PK",
    "name:und_x_variant":[
        "Gul\u0101b Lagh\u0101ri"
    ],
    "wof:name":"Goth Gulab Laghari",
    "wof:placetype":"locality"
},
  "geometry": {"coordinates":[68.77837,25.21863],"type":"Point"}
}