{
  "type": "Feature",
  "properties": {
    "gn:admin1_code":"5.0",
    "gn:asciiname":"Goth Razaq Shoro",
    "gn:country_code":"PK",
    "gn:dem":7,
    "gn:feature_class":"P",
    "gn:feature_code":"PPL",
    "gn:name":"Goth Razaq Shoro",
    "gn:population":0,
    "gn:timezone":"Asia/Karachi",
    "iso:country":"PK",
    "name:und_x_variant":[
        "Goth Razz\u0101q Shoro"
    ],
    "wof:name":"Goth Razaq Shoro",
    "wof:placetype":"locality"
},
  "geometry": {"coordinates":[67.68628000000001,24.60283],"type":"Point"}
}