{
  "type": "Feature",
  "properties": {
    "gn:admin1_code":"4",
    "gn:asciiname":"Khachi Kalan",
    "gn:country_code":"PK",
    "gn:dem":171,
    "gn:feature_class":"P",
    "gn:feature_code":"PPL",
    "gn:name":"Khachi Kalan",
    "gn:population":0,
    "gn:timezone":"Asia/Karachi",
    "iso:country":"PK",
    "name:und_x_variant":[
        "Khachi Khan",
        "Khhichi Kal\u0101n",
        "Khachi Kalan"
    ],
    "wof:name":"Khachi Kalan",
    "wof:placetype":"locality"
},
  "geometry": {"coordinates":[71.03859,31.66617],"type":"Point"}
}