{
  "type": "Feature",
  "properties": {
    "gn:admin1_code":"2.0",
    "gn:asciiname":"Chhutto",
    "gn:country_code":"PK",
    "gn:dem":791,
    "gn:feature_class":"P",
    "gn:feature_code":"PPL",
    "gn:name":"Chhutto",
    "gn:population":0,
    "gn:timezone":"Asia/Karachi",
    "iso:country":"PK",
    "wof:name":"Chhutto",
    "wof:placetype":"locality"
},
  "geometry": {"coordinates":[67.16229,27.73973],"type":"Point"}
}