{
  "type": "Feature",
  "properties": {
    "gn:admin1_code":"4.0",
    "gn:asciiname":"Chak Five Eastern Bar",
    "gn:country_code":"PK",
    "gn:dem":160,
    "gn:feature_class":"P",
    "gn:feature_code":"PPL",
    "gn:name":"Chak Five Eastern Bar",
    "gn:population":0,
    "gn:timezone":"Asia/Karachi",
    "iso:country":"PK",
    "wof:name":"Chak Five Eastern Bar",
    "wof:placetype":"locality"
},
  "geometry": {"coordinates":[73.17343000000002,30.32162000000001],"type":"Point"}
}