{
  "type": "Feature",
  "properties": {
    "gn:admin1_code":"3.0",
    "gn:asciiname":"Khunda",
    "gn:country_code":"PK",
    "gn:dem":311,
    "gn:feature_class":"P",
    "gn:feature_code":"PPL",
    "gn:name":"Khunda",
    "gn:population":0,
    "gn:timezone":"Asia/Karachi",
    "iso:country":"PK",
    "name:eng_x_preferred":[
        "Khunda"
    ],
    "name:fas_x_preferred":[
        "\u06a9\u0647\u0648\u0646\u062f\u0647"
    ],
    "name:und_x_variant":[
        "Kunda"
    ],
    "wof:name":"Khunda",
    "wof:placetype":"locality"
},
  "geometry": {"coordinates":[72.43080999999999,34.04996],"type":"Point"}
}