{
  "type": "Feature",
  "properties": {
    "gn:admin1_code":"4",
    "gn:asciiname":"Puprali",
    "gn:country_code":"PK",
    "gn:dem":787,
    "gn:feature_class":"P",
    "gn:feature_code":"PPL",
    "gn:name":"Puprali",
    "gn:population":0,
    "gn:timezone":"Asia/Karachi",
    "iso:country":"PK",
    "name:und_x_variant":[
        "Pupr\u0101l",
        "Papr\u0101li",
        "Puprali"
    ],
    "wof:name":"Puprali",
    "wof:placetype":"locality"
},
  "geometry": {"coordinates":[72.13665999999998,32.48822],"type":"Point"}
}