{
  "type": "Feature",
  "properties": {
    "gn:admin1_code":"2.0",
    "gn:asciiname":"Atif Sinirani",
    "gn:country_code":"PK",
    "gn:dem":837,
    "gn:feature_class":"P",
    "gn:feature_code":"PPL",
    "gn:name":"Atif Sinirani",
    "gn:population":0,
    "gn:timezone":"Asia/Karachi",
    "iso:country":"PK",
    "wof:name":"Atif Sinirani",
    "wof:placetype":"locality"
},
  "geometry": {"coordinates":[64.5621,28.95517000000001],"type":"Point"}
}