{
  "type": "Feature",
  "properties": {
    "gn:admin1_code":"4",
    "gn:asciiname":"Jatewali",
    "gn:country_code":"PK",
    "gn:dem":246,
    "gn:feature_class":"P",
    "gn:feature_code":"PPL",
    "gn:name":"Jatewali",
    "gn:population":0,
    "gn:timezone":"Asia/Karachi",
    "iso:country":"PK",
    "name:und_x_variant":[
        "Janew\u0101l"
    ],
    "wof:name":"Jatewali",
    "wof:placetype":"locality"
},
  "geometry": {"coordinates":[74.69027,32.35262],"type":"Point"}
}