{
  "type": "Feature",
  "properties": {
    "gn:admin1_code":"4.0",
    "gn:asciiname":"Basti Jam Allah Yar",
    "gn:country_code":"PK",
    "gn:dem":89,
    "gn:feature_class":"P",
    "gn:feature_code":"PPL",
    "gn:name":"Basti J\u0101m All\u0101h Y\u0101r",
    "gn:population":0,
    "gn:timezone":"Asia/Karachi",
    "iso:country":"PK",
    "name:urd_x_preferred":[
        "Basti J\u0101m All\u0101h Y\u0101r"
    ],
    "wof:name":"Basti Jam Allah Yar",
    "wof:placetype":"locality"
},
  "geometry": {"coordinates":[70.59166999999999,28.80417000000001],"type":"Point"}
}