{
  "type": "Feature",
  "properties": {
    "gn:admin1_code":"4.0",
    "gn:asciiname":"Chak Sixty-two",
    "gn:country_code":"PK",
    "gn:dem":184,
    "gn:feature_class":"P",
    "gn:feature_code":"PPL",
    "gn:name":"Chak Sixty-two",
    "gn:population":0,
    "gn:timezone":"Asia/Karachi",
    "iso:country":"PK",
    "name:und_x_variant":[
        "Chananke",
        "Chandanke",
        "Chak Sixty-two",
        "Chananki"
    ],
    "wof:name":"Chak Sixty-two",
    "wof:placetype":"locality"
},
  "geometry": {"coordinates":[72.92301999999999,31.4285],"type":"Point"}
}