{
  "type": "Feature",
  "properties": {
    "gn:admin1_code":"2",
    "gn:asciiname":"Goth Mob Ali",
    "gn:country_code":"PK",
    "gn:dem":313,
    "gn:feature_class":"P",
    "gn:feature_code":"PPL",
    "gn:name":"Goth Mob Ali",
    "gn:population":0,
    "gn:timezone":"Asia/Karachi",
    "iso:country":"PK",
    "name:eng_x_preferred":[
        "Goth Mob Ali"
    ],
    "wof:name":"Goth Mob Ali",
    "wof:placetype":"locality"
},
  "geometry": {"coordinates":[66.89594,25.80554],"type":"Point"}
}