{
  "type": "Feature",
  "properties": {
    "gn:admin1_code":"4",
    "gn:asciiname":"Channiwala",
    "gn:country_code":"PK",
    "gn:dem":138,
    "gn:feature_class":"P",
    "gn:feature_code":"PPL",
    "gn:name":"Channiwala",
    "gn:population":0,
    "gn:timezone":"Asia/Karachi",
    "iso:country":"PK",
    "name:und_x_variant":[
        "Paurew\u0101la",
        "Ch\u0101n\u012bw\u0101la"
    ],
    "wof:name":"Channiwala",
    "wof:placetype":"locality"
},
  "geometry": {"coordinates":[70.92891999999998,30.60189],"type":"Point"}
}