{
  "type": "Feature",
  "properties": {
    "gn:admin1_code":"1.0",
    "gn:asciiname":"Palosin",
    "gn:country_code":"PK",
    "gn:dem":1161,
    "gn:feature_class":"P",
    "gn:feature_code":"PPL",
    "gn:name":"Palosin",
    "gn:population":0,
    "gn:timezone":"Asia/Karachi",
    "iso:country":"PK",
    "wof:name":"Palosin",
    "wof:placetype":"locality"
},
  "geometry": {"coordinates":[71.17997,34.69551],"type":"Point"}
}