{
  "type": "Feature",
  "properties": {
    "gn:admin1_code":"7.0",
    "gn:asciiname":"Chalt Pain",
    "gn:country_code":"PK",
    "gn:dem":1792,
    "gn:feature_class":"P",
    "gn:feature_code":"PPL",
    "gn:name":"Chalt Pain",
    "gn:population":0,
    "gn:timezone":"Asia/Karachi",
    "iso:country":"PK",
    "wof:name":"Chalt Pain",
    "wof:placetype":"locality"
},
  "geometry": {"coordinates":[74.31248000000002,36.2442],"type":"Point"}
}