{
  "type": "Feature",
  "properties": {
    "gn:admin1_code":"3",
    "gn:asciiname":"Paladar Baik",
    "gn:country_code":"PK",
    "gn:dem":1891,
    "gn:feature_class":"P",
    "gn:feature_code":"PPL",
    "gn:name":"Paladar Baik",
    "gn:population":0,
    "gn:timezone":"Asia/Karachi",
    "iso:country":"PK",
    "wof:name":"Paladar Baik",
    "wof:placetype":"locality"
},
  "geometry": {"coordinates":[73.37885,34.22000999999999],"type":"Point"}
}