{
  "type": "Feature",
  "properties": {
    "gn:admin1_code":"04",
    "gn:asciiname":"Mari Wallian",
    "gn:country_code":"PK",
    "gn:dem":128,
    "gn:feature_class":"P",
    "gn:feature_code":"PPL",
    "gn:name":"Mari Wallian",
    "gn:population":0,
    "gn:timezone":"Asia/Karachi",
    "iso:country":"PK",
    "name:und_x_variant":[
        "M\u0101ri Wali\u0101n"
    ],
    "wof:name":"Mari Wallian",
    "wof:placetype":"locality"
},
  "geometry": {"coordinates":[71.69181,30.19906],"type":"Point"}
}