{
  "type": "Feature",
  "properties": {
    "gn:admin1_code":"4",
    "gn:asciiname":"Dhindwal",
    "gn:country_code":"PK",
    "gn:dem":242,
    "gn:feature_class":"P",
    "gn:feature_code":"PPL",
    "gn:name":"Dhindwal",
    "gn:population":0,
    "gn:timezone":"Asia/Karachi",
    "iso:country":"PK",
    "name:und_x_variant":[
        "Dhinda"
    ],
    "wof:name":"Dhindwal",
    "wof:placetype":"locality"
},
  "geometry": {"coordinates":[73.96426,32.65187],"type":"Point"}
}