{
  "type": "Feature",
  "properties": {
    "gn:admin1_code":"4.0",
    "gn:asciiname":"Chak Three",
    "gn:country_code":"PK",
    "gn:dem":196,
    "gn:feature_class":"P",
    "gn:feature_code":"PPL",
    "gn:name":"Chak Three",
    "gn:population":0,
    "gn:timezone":"Asia/Karachi",
    "iso:country":"PK",
    "name:und_x_variant":[
        "Ahmadpur",
        "Chak Three NB",
        "Chak 3 NB",
        "Chak Three"
    ],
    "wof:name":"Chak Three",
    "wof:placetype":"locality"
},
  "geometry": {"coordinates":[72.91274,32.33434],"type":"Point"}
}