{
  "type": "Feature",
  "properties": {
    "gn:admin1_code":"4.0",
    "gn:asciiname":"Chak Seventy-two Gugera Branch",
    "gn:country_code":"PK",
    "gn:dem":184,
    "gn:feature_class":"P",
    "gn:feature_code":"PPL",
    "gn:name":"Chak Seventy-two Gugera Branch",
    "gn:population":0,
    "gn:timezone":"Asia/Karachi",
    "iso:country":"PK",
    "name:und_x_variant":[
        "Chhini Tikka",
        "Chhanni Tikka",
        "Chak Seventy-Two GB",
        "Chak Seventy-two Gugera Branch",
        "Channi Tikka"
    ],
    "wof:name":"Chak Seventy-two Gugera Branch",
    "wof:placetype":"locality"
},
  "geometry": {"coordinates":[73.20545,31.29262],"type":"Point"}
}