{
  "type": "Feature",
  "properties": {
    "gn:admin1_code":"5.0",
    "gn:asciiname":"Goth Khairu",
    "gn:country_code":"PK",
    "gn:dem":42,
    "gn:feature_class":"P",
    "gn:feature_code":"PPL",
    "gn:name":"Goth Khairu",
    "gn:population":0,
    "gn:timezone":"Asia/Karachi",
    "iso:country":"PK",
    "name:und_x_variant":[
        "Khairu"
    ],
    "wof:name":"Goth Khairu",
    "wof:placetype":"locality"
},
  "geometry": {"coordinates":[68.26645000000001,26.74061],"type":"Point"}
}