{
  "type": "Feature",
  "properties": {
    "gn:admin1_code":"2",
    "gn:asciiname":"Hurri",
    "gn:country_code":"PK",
    "gn:dem":1157,
    "gn:feature_class":"P",
    "gn:feature_code":"PPL",
    "gn:name":"Hurri",
    "gn:population":0,
    "gn:timezone":"Asia/Karachi",
    "iso:country":"PK",
    "name:cat_x_preferred":[
        "Khurri"
    ],
    "name:und_x_variant":[
        "Arri"
    ],
    "wof:name":"Hurri",
    "wof:placetype":"locality"
},
  "geometry": {"coordinates":[66.19269,27.63134],"type":"Point"}
}