{
  "type": "Feature",
  "properties": {
    "gn:admin1_code":"4",
    "gn:asciiname":"Badduwala",
    "gn:country_code":"PK",
    "gn:dem":158,
    "gn:feature_class":"P",
    "gn:feature_code":"PPL",
    "gn:name":"Badduwala",
    "gn:population":0,
    "gn:timezone":"Asia/Karachi",
    "iso:country":"PK",
    "wof:name":"Badduwala",
    "wof:placetype":"locality"
},
  "geometry": {"coordinates":[71.19282,31.22713],"type":"Point"}
}