{
  "type": "Feature",
  "properties": {
    "gn:admin1_code":"01",
    "gn:asciiname":"Landawar",
    "gn:country_code":"PK",
    "gn:dem":1829,
    "gn:feature_class":"P",
    "gn:feature_code":"PPL",
    "gn:name":"Landawar",
    "gn:population":0,
    "gn:timezone":"Asia/Karachi",
    "iso:country":"PK",
    "wof:name":"Landawar",
    "wof:placetype":"locality"
},
  "geometry": {"coordinates":[70.78751,33.82688],"type":"Point"}
}