{
  "type": "Feature",
  "properties": {
    "gn:admin1_code":"5.0",
    "gn:asciiname":"Baloch Kochar",
    "gn:country_code":"PK",
    "gn:dem":48,
    "gn:feature_class":"P",
    "gn:feature_code":"PPL",
    "gn:name":"Baloch Kochar",
    "gn:population":0,
    "gn:timezone":"Asia/Karachi",
    "iso:country":"PK",
    "wof:name":"Baloch Kochar",
    "wof:placetype":"locality"
},
  "geometry": {"coordinates":[69.56444,26.32904000000001],"type":"Point"}
}