{
  "type": "Feature",
  "properties": {
    "gn:admin1_code":"4",
    "gn:asciiname":"Mandi Jattan",
    "gn:country_code":"PK",
    "gn:dem":274,
    "gn:feature_class":"P",
    "gn:feature_code":"PPL",
    "gn:name":"Mandi Jattan",
    "gn:population":0,
    "gn:timezone":"Asia/Karachi",
    "iso:country":"PK",
    "name:und_x_variant":[
        "Mandi"
    ],
    "wof:name":"Mandi Jattan",
    "wof:placetype":"locality"
},
  "geometry": {"coordinates":[73.90385000000001,32.99354],"type":"Point"}
}