{
  "type": "Feature",
  "properties": {
    "gn:admin1_code":"3.0",
    "gn:asciiname":"Panian Baihk",
    "gn:country_code":"PK",
    "gn:dem":3704,
    "gn:feature_class":"P",
    "gn:feature_code":"PPL",
    "gn:name":"Panian Baihk",
    "gn:population":0,
    "gn:timezone":"Asia/Karachi",
    "iso:country":"PK",
    "wof:name":"Panian Baihk",
    "wof:placetype":"locality"
},
  "geometry": {"coordinates":[73.76881,35.17574],"type":"Point"}
}