{
  "type": "Feature",
  "properties": {
    "gn:admin1_code":"5",
    "gn:asciiname":"Rawat Hajiana",
    "gn:country_code":"PK",
    "gn:dem":26,
    "gn:feature_class":"P",
    "gn:feature_code":"PPL",
    "gn:name":"Rawat Hajiana",
    "gn:population":0,
    "gn:timezone":"Asia/Karachi",
    "iso:country":"PK",
    "name:eng_x_preferred":[
        "Rawat Hajiana"
    ],
    "wof:name":"Rawat Hajiana",
    "wof:placetype":"locality"
},
  "geometry": {"coordinates":[68.46252,25.51233],"type":"Point"}
}