{
  "type": "Feature",
  "properties": {
    "gn:admin1_code":"2.0",
    "gn:asciiname":"Kili Elahi Bakhsh",
    "gn:country_code":"PK",
    "gn:dem":1246,
    "gn:feature_class":"P",
    "gn:feature_code":"PPL",
    "gn:name":"Kili Elahi Bakhsh",
    "gn:population":0,
    "gn:timezone":"Asia/Karachi",
    "iso:country":"PK",
    "wof:name":"Kili Elahi Bakhsh",
    "wof:placetype":"locality"
},
  "geometry": {"coordinates":[66.31645999999999,27.30607],"type":"Point"}
}