{
  "type": "Feature",
  "properties": {
    "gn:admin1_code":"4.0",
    "gn:asciiname":"Gulhari",
    "gn:country_code":"PK",
    "gn:dem":130,
    "gn:feature_class":"P",
    "gn:feature_code":"PPL",
    "gn:name":"Gulh\u0101ri",
    "gn:population":0,
    "gn:timezone":"Asia/Karachi",
    "iso:country":"PK",
    "wof:name":"Gulhari",
    "wof:placetype":"locality"
},
  "geometry": {"coordinates":[72.11444,29.74944],"type":"Point"}
}