{
  "type": "Feature",
  "properties": {
    "gn:admin1_code":"4.0",
    "gn:asciiname":"Bela Ali Khanana",
    "gn:country_code":"PK",
    "gn:dem":140,
    "gn:feature_class":"P",
    "gn:feature_code":"PPL",
    "gn:name":"Bela Ali Khan\u0101na",
    "gn:population":0,
    "gn:timezone":"Asia/Karachi",
    "iso:country":"PK",
    "wof:name":"Bela Ali Khanana",
    "wof:placetype":"locality"
},
  "geometry": {"coordinates":[72.13333,31.05],"type":"Point"}
}