{
  "type": "Feature",
  "properties": {
    "gn:admin1_code":"5",
    "gn:asciiname":"Goth Sultan Mahar",
    "gn:country_code":"PK",
    "gn:dem":8,
    "gn:feature_class":"P",
    "gn:feature_code":"PPL",
    "gn:name":"Goth Sultan Mahar",
    "gn:population":0,
    "gn:timezone":"Asia/Karachi",
    "iso:country":"PK",
    "name:und_x_variant":[
        "Goth Mehr"
    ],
    "wof:name":"Goth Sultan Mahar",
    "wof:placetype":"locality"
},
  "geometry": {"coordinates":[69.27109,24.89968],"type":"Point"}
}