{
  "type": "Feature",
  "properties": {
    "gn:admin1_code":"4.0",
    "gn:asciiname":"Chak Two Hundred Seventy-three Hakra Right",
    "gn:country_code":"PK",
    "gn:dem":146,
    "gn:feature_class":"P",
    "gn:feature_code":"PPL",
    "gn:name":"Chak Two Hundred Seventy-three Hakra Right",
    "gn:population":0,
    "gn:timezone":"Asia/Karachi",
    "iso:country":"PK",
    "wof:name":"Chak Two Hundred Seventy-three Hakra Right",
    "wof:placetype":"locality"
},
  "geometry": {"coordinates":[72.85427,29.22967],"type":"Point"}
}