{
  "type": "Feature",
  "properties": {
    "gn:admin1_code":"5.0",
    "gn:asciiname":"Khair Muhammad Lashari",
    "gn:country_code":"PK",
    "gn:dem":48,
    "gn:feature_class":"P",
    "gn:feature_code":"PPL",
    "gn:name":"Khair Muhammad Lashari",
    "gn:population":0,
    "gn:timezone":"Asia/Karachi",
    "iso:country":"PK",
    "name:und_x_variant":[
        "Goth Khair Muhammad Lash\u0101ri"
    ],
    "wof:name":"Khair Muhammad Lashari",
    "wof:placetype":"locality"
},
  "geometry": {"coordinates":[68.66515,27.07495],"type":"Point"}
}