{
  "type": "Feature",
  "properties": {
    "gn:admin1_code":"3.0",
    "gn:asciiname":"Faizah",
    "gn:country_code":"PK",
    "gn:dem":1378,
    "gn:feature_class":"P",
    "gn:feature_code":"PPL",
    "gn:name":"Faizah",
    "gn:population":0,
    "gn:timezone":"Asia/Karachi",
    "iso:country":"PK",
    "wof:name":"Faizah",
    "wof:placetype":"locality"
},
  "geometry": {"coordinates":[72.39764,34.73433],"type":"Point"}
}