{
  "type": "Feature",
  "properties": {
    "gn:admin1_code":"4",
    "gn:asciiname":"Khu Gamanwala",
    "gn:country_code":"PK",
    "gn:dem":130,
    "gn:feature_class":"P",
    "gn:feature_code":"PPL",
    "gn:name":"Khu Gamanwala",
    "gn:population":0,
    "gn:timezone":"Asia/Karachi",
    "iso:country":"PK",
    "name:eng_x_preferred":[
        "G\u0101manw\u0101la"
    ],
    "wof:name":"Khu Gamanwala",
    "wof:placetype":"locality"
},
  "geometry": {"coordinates":[70.65907,30.32181],"type":"Point"}
}