{
  "type": "Feature",
  "properties": {
    "gn:admin1_code":"2.0",
    "gn:asciiname":"Nali",
    "gn:country_code":"PK",
    "gn:dem":1487,
    "gn:feature_class":"P",
    "gn:feature_code":"PPL",
    "gn:name":"Nali",
    "gn:population":0,
    "gn:timezone":"Asia/Karachi",
    "iso:country":"PK",
    "name:ceb_x_preferred":[
        "Nali"
    ],
    "name:swe_x_preferred":[
        "Nali"
    ],
    "wof:name":"Nali",
    "wof:placetype":"locality"
},
  "geometry": {"coordinates":[66.72319,28.04714],"type":"Point"}
}