{
  "type": "Feature",
  "properties": {
    "gn:admin1_code":"04",
    "gn:asciiname":"Chak One Hundred Sixty-five Eastern Bar",
    "gn:country_code":"PK",
    "gn:dem":155,
    "gn:feature_class":"P",
    "gn:feature_code":"PPL",
    "gn:name":"Chak One Hundred Sixty-five Eastern Bar",
    "gn:population":0,
    "gn:timezone":"Asia/Karachi",
    "iso:country":"PK",
    "name:und_x_variant":[
        "Sh\u0101hz\u0101d\u0101b\u0101d"
    ],
    "wof:name":"Chak One Hundred Sixty-five Eastern Bar",
    "wof:placetype":"locality"
},
  "geometry": {"coordinates":[72.95487,30.26444],"type":"Point"}
}