{
  "type": "Feature",
  "properties": {
    "gn:admin1_code":"7.0",
    "gn:asciiname":"Mashkal",
    "gn:country_code":"PK",
    "gn:dem":2068,
    "gn:feature_class":"P",
    "gn:feature_code":"PPL",
    "gn:name":"Mashkal",
    "gn:population":0,
    "gn:timezone":"Asia/Karachi",
    "iso:country":"PK",
    "wof:name":"Mashkal",
    "wof:placetype":"locality"
},
  "geometry": {"coordinates":[73.38843,35.72747000000001],"type":"Point"}
}