{
  "type": "Feature",
  "properties": {
    "gn:admin1_code":"2.0",
    "gn:asciiname":"Mir Allah Ditta",
    "gn:country_code":"PK",
    "gn:dem":61,
    "gn:feature_class":"P",
    "gn:feature_code":"PPL",
    "gn:name":"Mir Allah Ditta",
    "gn:population":0,
    "gn:timezone":"Asia/Karachi",
    "iso:country":"PK",
    "name:und_x_variant":[
        "Goth M\u012br All\u0101h Ditta"
    ],
    "wof:name":"Mir Allah Ditta",
    "wof:placetype":"locality"
},
  "geometry": {"coordinates":[68.01105,28.37548],"type":"Point"}
}