{
  "type": "Feature",
  "properties": {
    "gn:admin1_code":"2.0",
    "gn:asciiname":"Mulia Shabb",
    "gn:country_code":"PK",
    "gn:dem":1297,
    "gn:feature_class":"P",
    "gn:feature_code":"PPL",
    "gn:name":"Mulia Shabb",
    "gn:population":0,
    "gn:timezone":"Asia/Karachi",
    "iso:country":"PK",
    "wof:name":"Mulia Shabb",
    "wof:placetype":"locality"
},
  "geometry": {"coordinates":[69.86870999999999,30.8987],"type":"Point"}
}