{
  "type": "Feature",
  "properties": {
    "gn:admin1_code":"4.0",
    "gn:asciiname":"Dr Diwan Ali Kat",
    "gn:country_code":"PK",
    "gn:dem":152,
    "gn:feature_class":"P",
    "gn:feature_code":"PPL",
    "gn:name":"Dr Diwan Ali Kat",
    "gn:population":0,
    "gn:timezone":"Asia/Karachi",
    "iso:country":"PK",
    "wof:name":"Dr Diwan Ali Kat",
    "wof:placetype":"locality"
},
  "geometry": {"coordinates":[73.11910999999998,29.95334],"type":"Point"}
}