{
  "type": "Feature",
  "properties": {
    "gn:admin1_code":"5",
    "gn:asciiname":"Sattar Darkhan",
    "gn:country_code":"PK",
    "gn:dem":72,
    "gn:feature_class":"P",
    "gn:feature_code":"PPL",
    "gn:name":"Sattar Darkhan",
    "gn:population":0,
    "gn:timezone":"Asia/Karachi",
    "iso:country":"PK",
    "name:und_x_variant":[
        "Satt\u0101r Darkh\u0101n"
    ],
    "wof:name":"Sattar Darkhan",
    "wof:placetype":"locality"
},
  "geometry": {"coordinates":[69.72211,28.08703],"type":"Point"}
}