{
  "type": "Feature",
  "properties": {
    "gn:admin1_code":"4",
    "gn:asciiname":"Chak Seventy-three",
    "gn:country_code":"PK",
    "gn:dem":134,
    "gn:feature_class":"P",
    "gn:feature_code":"PPL",
    "gn:name":"Chak Seventy-three",
    "gn:population":0,
    "gn:timezone":"Asia/Karachi",
    "iso:country":"PK",
    "name:und_x_variant":[
        "Mar\u0101li\u0101nw\u0101la",
        "M\u0101ralianw\u0101la"
    ],
    "wof:name":"Chak Seventy-three",
    "wof:placetype":"locality"
},
  "geometry": {"coordinates":[71.95168000000002,30.20372],"type":"Point"}
}