{
  "type": "Feature",
  "properties": {
    "gn:admin1_code":"4",
    "gn:asciiname":"Gulwala",
    "gn:country_code":"PK",
    "gn:dem":114,
    "gn:feature_class":"P",
    "gn:feature_code":"PPL",
    "gn:name":"Gulwala",
    "gn:population":0,
    "gn:timezone":"Asia/Karachi",
    "iso:country":"PK",
    "name:und_x_variant":[
        "Golw\u0101la"
    ],
    "wof:name":"Gulwala",
    "wof:placetype":"locality"
},
  "geometry": {"coordinates":[71.32074,30.00302000000001],"type":"Point"}
}