{
  "type": "Feature",
  "properties": {
    "gn:admin1_code":"4",
    "gn:asciiname":"Chak Three Hundred Eighty Thal Development Authority",
    "gn:country_code":"PK",
    "gn:dem":147,
    "gn:feature_class":"P",
    "gn:feature_code":"PPL",
    "gn:name":"Chak Three Hundred Eighty Thal Development Authority",
    "gn:population":0,
    "gn:timezone":"Asia/Karachi",
    "iso:country":"PK",
    "name:und_x_variant":[
        "Chak Three Hundred Eighty TDA",
        "Chak Three Hundred Eighty",
        "Chak Three Hundred Eighty Thal Development Authority"
    ],
    "wof:name":"Chak Three Hundred Eighty Thal Development Authority",
    "wof:placetype":"locality"
},
  "geometry": {"coordinates":[71.29495,30.91867],"type":"Point"}
}