{
  "type": "Feature",
  "properties": {
    "gn:admin1_code":"03",
    "gn:asciiname":"Sodher",
    "gn:country_code":"PK",
    "gn:dem":333,
    "gn:feature_class":"P",
    "gn:feature_code":"PPL",
    "gn:name":"Sodher",
    "gn:population":0,
    "gn:timezone":"Asia/Karachi",
    "iso:country":"PK",
    "name:eng_x_preferred":[
        "Sudher"
    ],
    "name:und_x_variant":[
        "Sodhair",
        "Sodher"
    ],
    "wof:name":"Sodher",
    "wof:placetype":"locality"
},
  "geometry": {"coordinates":[72.28425,34.14403],"type":"Point"}
}