{
  "type": "Feature",
  "properties": {
    "gn:admin1_code":"2.0",
    "gn:asciiname":"Sherwai Kili",
    "gn:country_code":"PK",
    "gn:dem":1891,
    "gn:feature_class":"P",
    "gn:feature_code":"PPL",
    "gn:name":"Sherwai Kili",
    "gn:population":0,
    "gn:timezone":"Asia/Karachi",
    "iso:country":"PK",
    "wof:name":"Sherwai Kili",
    "wof:placetype":"locality"
},
  "geometry": {"coordinates":[69.72816999999999,31.40861],"type":"Point"}
}