{
  "type": "Feature",
  "properties": {
    "gn:admin1_code":"4.0",
    "gn:asciiname":"Kamalpur Bajwa",
    "gn:country_code":"PK",
    "gn:dem":247,
    "gn:feature_class":"P",
    "gn:feature_code":"PPL",
    "gn:name":"Kamalpur Bajwa",
    "gn:population":0,
    "gn:timezone":"Asia/Karachi",
    "iso:country":"PK",
    "name:und_x_variant":[
        "Kam\u0101lpur"
    ],
    "wof:name":"Kamalpur Bajwa",
    "wof:placetype":"locality"
},
  "geometry": {"coordinates":[74.72702,32.31543],"type":"Point"}
}