{
  "type": "Feature",
  "properties": {
    "gn:admin1_code":"7.0",
    "gn:asciiname":"Bakure Harai",
    "gn:country_code":"PK",
    "gn:dem":3717,
    "gn:feature_class":"P",
    "gn:feature_code":"PPL",
    "gn:name":"Bakure Harai",
    "gn:population":0,
    "gn:timezone":"Asia/Karachi",
    "iso:country":"PK",
    "name:und_x_variant":[
        "B\u0101kura Harai"
    ],
    "wof:name":"Bakure Harai",
    "wof:placetype":"locality"
},
  "geometry": {"coordinates":[73.71868000000001,36.08919],"type":"Point"}
}