{
  "type": "Feature",
  "properties": {
    "gn:admin1_code":"03",
    "gn:asciiname":"Khadagzai",
    "gn:country_code":"PK",
    "gn:dem":634,
    "gn:feature_class":"P",
    "gn:feature_code":"PPL",
    "gn:name":"Khadagzai",
    "gn:population":0,
    "gn:timezone":"Asia/Karachi",
    "iso:country":"PK",
    "name:eng_x_preferred":[
        "Kuz Barangola"
    ],
    "wof:name":"Khadagzai",
    "wof:placetype":"locality"
},
  "geometry": {"coordinates":[71.88933,34.63702],"type":"Point"}
}