{
  "type": "Feature",
  "properties": {
    "gn:admin1_code":"5",
    "gn:asciiname":"Goth Fateh Muhammad Thahim",
    "gn:country_code":"PK",
    "gn:dem":20,
    "gn:feature_class":"P",
    "gn:feature_code":"PPL",
    "gn:name":"Goth Fateh Muhammad Thahim",
    "gn:population":0,
    "gn:timezone":"Asia/Karachi",
    "iso:country":"PK",
    "name:und_x_variant":[
        "Goth Faq\u012br Muhammad Thah\u012bm"
    ],
    "wof:name":"Goth Fateh Muhammad Thahim",
    "wof:placetype":"locality"
},
  "geometry": {"coordinates":[68.97624999999999,25.93012],"type":"Point"}
}