{
  "type": "Feature",
  "properties": {
    "gn:admin1_code":"1.0",
    "gn:asciiname":"Wazirabad",
    "gn:country_code":"PK",
    "gn:dem":1512,
    "gn:feature_class":"P",
    "gn:feature_code":"PPL",
    "gn:name":"Wazirabad",
    "gn:population":0,
    "gn:timezone":"Asia/Karachi",
    "iso:country":"PK",
    "wof:name":"Wazirabad",
    "wof:placetype":"locality"
},
  "geometry": {"coordinates":[70.01822,33.83229],"type":"Point"}
}