{
  "type": "Feature",
  "properties": {
    "gn:admin1_code":"5.0",
    "gn:asciiname":"Gul Hasan Brahui",
    "gn:country_code":"PK",
    "gn:dem":52,
    "gn:feature_class":"P",
    "gn:feature_code":"PPL",
    "gn:name":"Gul Hasan Brahui",
    "gn:population":0,
    "gn:timezone":"Asia/Karachi",
    "iso:country":"PK",
    "wof:name":"Gul Hasan Brahui",
    "wof:placetype":"locality"
},
  "geometry": {"coordinates":[66.85668000000001,24.93212],"type":"Point"}
}