{
  "type": "Feature",
  "properties": {
    "gn:admin1_code":"7.0",
    "gn:asciiname":"Girik",
    "gn:country_code":"PK",
    "gn:dem":2417,
    "gn:feature_class":"P",
    "gn:feature_code":"PPL",
    "gn:name":"Girik",
    "gn:population":0,
    "gn:timezone":"Asia/Karachi",
    "iso:country":"PK",
    "name:und_x_variant":[
        "Gehrak"
    ],
    "wof:name":"Girik",
    "wof:placetype":"locality"
},
  "geometry": {"coordinates":[74.83816,35.27768],"type":"Point"}
}