{
  "type": "Feature",
  "properties": {
    "gn:admin1_code":"7.0",
    "gn:asciiname":"Girik",
    "gn:country_code":"PK",
    "gn:dem":2417,
    "gn:feature_class":"P",
    "gn:feature_code":"PPL",
    "gn:name":"Girik",
    "gn:population":0,
    "gn:timezone":"Asia/Karachi",
    "iso:country":"PK",
    "name:aze_x_preferred":[
        "Girik"
    ],
    "name:ceb_x_preferred":[
        "Girik"
    ],
    "name:ita_x_preferred":[
        "Girik"
    ],
    "name:kat_x_preferred":[
        "\u10d2\u10d8\u10e0\u10d8\u10e5\u10d8"
    ],
    "name:lez_x_preferred":[
        "\u041a\u0438\u0440\u0438\u0433\u0430\u0440"
    ],
    "name:msa_x_preferred":[
        "Girik"
    ],
    "name:und_x_variant":[
        "Gehrak"
    ],
    "wof:name":"Girik",
    "wof:placetype":"locality"
},
  "geometry": {"coordinates":[74.83816,35.27768],"type":"Point"}
}