{
  "type": "Feature",
  "properties": {
    "gn:admin1_code":"2.0",
    "gn:asciiname":"MR and Safty Station Sinjidi",
    "gn:country_code":"PK",
    "gn:dem":1727,
    "gn:feature_class":"P",
    "gn:feature_code":"PPL",
    "gn:name":"MR and Safty Station Sinjidi",
    "gn:population":0,
    "gn:timezone":"Asia/Karachi",
    "iso:country":"PK",
    "name:eng_x_preferred":[
        "Sinj\u012bdi"
    ],
    "name:und_x_variant":[
        "Lease Number Eight Colony"
    ],
    "wof:name":"MR and Safty Station Sinjidi",
    "wof:placetype":"locality"
},
  "geometry": {"coordinates":[67.27231999999999,30.10662],"type":"Point"}
}