{
  "type": "Feature",
  "properties": {
    "gn:admin1_code":"4",
    "gn:asciiname":"Umarwala",
    "gn:country_code":"PK",
    "gn:dem":102,
    "gn:feature_class":"P",
    "gn:feature_code":"PPL",
    "gn:name":"Umarwala",
    "gn:population":0,
    "gn:timezone":"Asia/Karachi",
    "iso:country":"PK",
    "name:und_x_variant":[
        "Basti Rojh\u0101n",
        "Rojah\u0101n",
        "Umarwala"
    ],
    "wof:name":"Umarwala",
    "wof:placetype":"locality"
},
  "geometry": {"coordinates":[70.58201,29.44912],"type":"Point"}
}