{
  "type": "Feature",
  "properties": {
    "iso:country":"PK",
    "qs:gn_country":"PK",
    "qs:gn_fcode":"PPL",
    "qs:gn_pop":39757,
    "qs:name":"Ladhewala Waraich",
    "qs:name_adm0":"Pakistan",
    "qs:name_adm1":"Punjab",
    "qs:photos":0,
    "qs:photos_1k":0,
    "qs:photos_9k":0,
    "qs:photos_9r":0,
    "qs:photos_all":0,
    "qs:photos_sr":0,
    "qs:placetype":"Town",
    "qs:pop_sr":"7",
    "qs:woe_adm0":23424922,
    "wof:name":"Ladhewala Waraich",
    "wof:placetype":"locality",
    "wof:population":39757
},
  "geometry": {"coordinates":[74.11700999999999,32.15656],"type":"Point"}
}