{
  "type": "Feature",
  "properties": {
    "gn:admin1_code":"4.0",
    "gn:asciiname":"Duna Khokharan",
    "gn:country_code":"PK",
    "gn:dem":171,
    "gn:feature_class":"P",
    "gn:feature_code":"PPL",
    "gn:name":"Duna Khokharan",
    "gn:population":0,
    "gn:timezone":"Asia/Karachi",
    "iso:country":"PK",
    "wof:name":"Duna Khokharan",
    "wof:placetype":"locality"
},
  "geometry": {"coordinates":[73.75138000000003,30.34792],"type":"Point"}
}