{
  "type": "Feature",
  "properties": {
    "gn:admin1_code":"3.0",
    "gn:asciiname":"Maian Koi",
    "gn:country_code":"PK",
    "gn:dem":2405,
    "gn:feature_class":"P",
    "gn:feature_code":"PPL",
    "gn:name":"Maian Koi",
    "gn:population":0,
    "gn:timezone":"Asia/Karachi",
    "iso:country":"PK",
    "wof:name":"Maian Koi",
    "wof:placetype":"locality"
},
  "geometry": {"coordinates":[73.0536,35.09369],"type":"Point"}
}