{
  "type": "Feature",
  "properties": {
    "gn:admin1_code":"3.0",
    "gn:asciiname":"Kalo",
    "gn:country_code":"PK",
    "gn:dem":2364,
    "gn:feature_class":"P",
    "gn:feature_code":"PPL",
    "gn:name":"Kalo",
    "gn:population":0,
    "gn:timezone":"Asia/Karachi",
    "iso:country":"PK",
    "wof:name":"Kalo",
    "wof:placetype":"locality"
},
  "geometry": {"coordinates":[73.05620999999999,35.05959],"type":"Point"}
}