{
  "type": "Feature",
  "properties": {
    "gn:admin1_code":"03",
    "gn:asciiname":"Qasmi",
    "gn:country_code":"PK",
    "gn:dem":435,
    "gn:feature_class":"P",
    "gn:feature_code":"PPL",
    "gn:name":"Qasmi",
    "gn:population":0,
    "gn:timezone":"Asia/Karachi",
    "iso:country":"PK",
    "name:eng_x_preferred":[
        "Qasmi"
    ],
    "name:und_x_variant":[
        "Q\u0101sm"
    ],
    "wof:name":"Qasmi",
    "wof:placetype":"locality"
},
  "geometry": {"coordinates":[72.05538,34.45137],"type":"Point"}
}