{
  "type": "Feature",
  "properties": {
    "gn:admin1_code":"2.0",
    "gn:asciiname":"Mazahsar",
    "gn:country_code":"PK",
    "gn:dem":513,
    "gn:feature_class":"P",
    "gn:feature_code":"PPL",
    "gn:name":"Mazahsar",
    "gn:population":0,
    "gn:timezone":"Asia/Karachi",
    "iso:country":"PK",
    "name:und_x_variant":[
        "Kili Sh\u0101h Dost"
    ],
    "wof:name":"Mazahsar",
    "wof:placetype":"locality"
},
  "geometry": {"coordinates":[62.77374,28.01631],"type":"Point"}
}