{
  "type": "Feature",
  "properties": {
    "gn:admin1_code":"4.0",
    "gn:asciiname":"Basti Ghaimi",
    "gn:country_code":"PK",
    "gn:dem":78,
    "gn:feature_class":"P",
    "gn:feature_code":"PPL",
    "gn:name":"Basti Ghaimi",
    "gn:population":0,
    "gn:timezone":"Asia/Karachi",
    "iso:country":"PK",
    "name:und_x_variant":[
        "Ghemi",
        "Ghaimi",
        "Basti Ghaimi"
    ],
    "wof:name":"Basti Ghaimi",
    "wof:placetype":"locality"
},
  "geometry": {"coordinates":[69.96043,28.20732000000001],"type":"Point"}
}