{
  "type": "Feature",
  "properties": {
    "gn:admin1_code":"7.0",
    "gn:asciiname":"Lazhdar",
    "gn:country_code":"PK",
    "gn:dem":3943,
    "gn:feature_class":"P",
    "gn:feature_code":"PPL",
    "gn:name":"Lazhdar",
    "gn:population":0,
    "gn:timezone":"Asia/Karachi",
    "iso:country":"PK",
    "wof:name":"Lazhdar",
    "wof:placetype":"locality"
},
  "geometry": {"coordinates":[74.80831999999999,36.47146],"type":"Point"}
}