{
  "type": "Feature",
  "properties": {
    "gn:admin1_code":"5.0",
    "gn:asciiname":"Goth Haji Sabbhio Laghari",
    "gn:country_code":"PK",
    "gn:dem":19,
    "gn:feature_class":"P",
    "gn:feature_code":"PPL",
    "gn:name":"Goth Haji Sabbhio Laghari",
    "gn:population":0,
    "gn:timezone":"Asia/Karachi",
    "iso:country":"PK",
    "wof:name":"Goth Haji Sabbhio Laghari",
    "wof:placetype":"locality"
},
  "geometry": {"coordinates":[68.58464000000001,25.08652],"type":"Point"}
}