{
  "type": "Feature",
  "properties": {
    "gn:admin1_code":"2",
    "gn:asciiname":"Han Karim Kili",
    "gn:country_code":"PK",
    "gn:dem":2224,
    "gn:feature_class":"P",
    "gn:feature_code":"PPL",
    "gn:name":"Han Karim Kili",
    "gn:population":0,
    "gn:timezone":"Asia/Karachi",
    "iso:country":"PK",
    "name:und_x_variant":[
        "Chat Kach"
    ],
    "wof:name":"Han Karim Kili",
    "wof:placetype":"locality"
},
  "geometry": {"coordinates":[66.81083000000001,30.96],"type":"Point"}
}