{
  "type": "Feature",
  "properties": {
    "gn:admin1_code":"4.0",
    "gn:asciiname":"Chak One Hundred Seventy/One Hundred Seventy-Two NB",
    "gn:country_code":"PK",
    "gn:dem":170,
    "gn:feature_class":"P",
    "gn:feature_code":"PPL",
    "gn:name":"Chak One Hundred Seventy/One Hundred Seventy-Two NB",
    "gn:population":0,
    "gn:timezone":"Asia/Karachi",
    "iso:country":"PK",
    "name:und_x_variant":[
        "Chak One Hundred Seventy/One Hundred Seventy-Two",
        "Chak 170/172 NB"
    ],
    "wof:name":"Chak One Hundred Seventy/One Hundred Seventy-Two NB",
    "wof:placetype":"locality"
},
  "geometry": {"coordinates":[72.40942,31.69831],"type":"Point"}
}