{
  "type": "Feature",
  "properties": {
    "gn:admin1_code":"4.0",
    "gn:asciiname":"Ban",
    "gn:country_code":"PK",
    "gn:dem":1608,
    "gn:feature_class":"P",
    "gn:feature_code":"PPL",
    "gn:name":"Ban",
    "gn:population":0,
    "gn:timezone":"Asia/Karachi",
    "iso:country":"PK",
    "name:eng_x_preferred":[
        "Ban"
    ],
    "wof:name":"Ban",
    "wof:placetype":"locality"
},
  "geometry": {"coordinates":[73.45794000000002,33.82112],"type":"Point"}
}