{
  "type": "Feature",
  "properties": {
    "gn:admin1_code":"3",
    "gn:asciiname":"Salatar",
    "gn:country_code":"PK",
    "gn:dem":1600,
    "gn:feature_class":"P",
    "gn:feature_code":"PPL",
    "gn:name":"Salatar",
    "gn:population":0,
    "gn:timezone":"Asia/Karachi",
    "iso:country":"PK",
    "name:und_x_variant":[
        "Chatar"
    ],
    "wof:name":"Salatar",
    "wof:placetype":"locality"
},
  "geometry": {"coordinates":[73.32954000000002,34.17285],"type":"Point"}
}