{
  "type": "Feature",
  "properties": {
    "gn:admin1_code":"4.0",
    "gn:asciiname":"Imam di Bhaini",
    "gn:country_code":"PK",
    "gn:dem":158,
    "gn:feature_class":"P",
    "gn:feature_code":"PPL",
    "gn:name":"Imam di Bhaini",
    "gn:population":0,
    "gn:timezone":"Asia/Karachi",
    "iso:country":"PK",
    "wof:name":"Imam di Bhaini",
    "wof:placetype":"locality"
},
  "geometry": {"coordinates":[73.43855000000001,30.05667],"type":"Point"}
}