{
  "type": "Feature",
  "properties": {
    "gn:admin1_code":"5",
    "gn:asciiname":"Goth Muhammad Khan Khoso",
    "gn:country_code":"PK",
    "gn:dem":73,
    "gn:feature_class":"P",
    "gn:feature_code":"PPL",
    "gn:name":"Goth Muhammad Khan Khoso",
    "gn:population":0,
    "gn:timezone":"Asia/Karachi",
    "iso:country":"PK",
    "name:und_x_variant":[
        "Abdull Qad\u012br"
    ],
    "wof:name":"Goth Muhammad Khan Khoso",
    "wof:placetype":"locality"
},
  "geometry": {"coordinates":[69.60829,28.15652],"type":"Point"}
}