{
  "type": "Feature",
  "properties": {
    "gn:admin1_code":"4.0",
    "gn:asciiname":"Shehru ka Jhallar",
    "gn:country_code":"PK",
    "gn:dem":173,
    "gn:feature_class":"P",
    "gn:feature_code":"PPL",
    "gn:name":"Shehru ka Jhallar",
    "gn:population":0,
    "gn:timezone":"Asia/Karachi",
    "iso:country":"PK",
    "wof:name":"Shehru ka Jhallar",
    "wof:placetype":"locality"
},
  "geometry": {"coordinates":[72.69094,31.63516],"type":"Point"}
}