{
  "type": "Feature",
  "properties": {
    "gn:admin1_code":"3",
    "gn:asciiname":"Zimdarra",
    "gn:country_code":"PK",
    "gn:dem":1573,
    "gn:feature_class":"P",
    "gn:feature_code":"PPL",
    "gn:name":"Zimdarra",
    "gn:population":0,
    "gn:timezone":"Asia/Karachi",
    "iso:country":"PK",
    "name:und_x_variant":[
        "Z\u012bmdaria",
        "Zimdarra"
    ],
    "wof:name":"Zimdarra",
    "wof:placetype":"locality"
},
  "geometry": {"coordinates":[72.41557,35.05509],"type":"Point"}
}