{
  "type": "Feature",
  "properties": {
    "gn:admin1_code":"5.0",
    "gn:asciiname":"Goth Pahan Khan Daidano",
    "gn:country_code":"PK",
    "gn:dem":56,
    "gn:feature_class":"P",
    "gn:feature_code":"PPL",
    "gn:name":"Goth Pahan Khan Daidano",
    "gn:population":0,
    "gn:timezone":"Asia/Karachi",
    "iso:country":"PK",
    "wof:name":"Goth Pahan Khan Daidano",
    "wof:placetype":"locality"
},
  "geometry": {"coordinates":[68.59025,26.64124],"type":"Point"}
}