{
  "type": "Feature",
  "properties": {
    "gn:gn_country":"PK",
    "gn:gn_fcode":"PPL",
    "gn:gn_pop":44120,
    "gn:population":44120,
    "iso:country":"PK",
    "name:ceb_x_preferred":[
        "Sar\u0101i \u0100lamg\u012br"
    ],
    "name:eng_x_preferred":[
        "Sarai Alamgir Tehsil"
    ],
    "name:fas_x_preferred":[
        "\u0633\u0631\u0627\u0626\u06cc \u0639\u0627\u0644\u0645\u200c\u06af\u06cc\u0631"
    ],
    "name:fra_x_preferred":[
        "Sarai Alamgir"
    ],
    "name:nld_x_preferred":[
        "Sarai Alamgir Tehsil"
    ],
    "name:pnb_x_preferred":[
        "\u0633\u0631\u0627\u06d3 \u0639\u0627\u0644\u0645\u06af\u06cc\u0631"
    ],
    "name:por_x_preferred":[
        "Sarai Alamgir"
    ],
    "name:snd_x_preferred":[
        "\u0633\u0631\u0627\u0626\u064a \u0639\u0627\u0644\u0645\u06af\u064a\u0631"
    ],
    "name:urd_x_preferred":[
        "\u0633\u0631\u0627\u0626\u06d2 \u0639\u0627\u0644\u0645\u06af\u06cc\u0631"
    ],
    "name:urd_x_variant":[
        "\u0633\u0631\u0627\u0626\u06d2 \u0639\u0627\u0644\u0645\u06af\u064a\u0631"
    ],
    "qs_pg:aaroncc":"PK",
    "qs_pg:gn_country":"PK",
    "qs_pg:gn_fcode":"PPL",
    "qs_pg:gn_pop":44120,
    "qs_pg:name":"Sar\u0101i \u0100lamg\u012br",
    "qs_pg:photos_9r":0,
    "qs_pg:photos_sr":0,
    "qs_pg:pop_sr":7,
    "qs_pg:qs_pg_placetype":"locality",
    "wof:name":"Sar\u0101i \u0100lamg\u012br",
    "wof:placetype":"locality",
    "wof:population":44120
},
  "geometry": {"coordinates":[73.75591,32.90122],"type":"Point"}
}