{
  "type": "Feature",
  "properties": {
    "gn:admin1_code":"04",
    "gn:asciiname":"Nalhad",
    "gn:country_code":"PK",
    "gn:dem":383,
    "gn:feature_class":"P",
    "gn:feature_code":"PPL",
    "gn:name":"Nalhad",
    "gn:population":0,
    "gn:timezone":"Asia/Karachi",
    "iso:country":"PK",
    "wof:name":"Nalhad",
    "wof:placetype":"locality"
},
  "geometry": {"coordinates":[72.04886999999999,33.23179],"type":"Point"}
}