{
  "type": "Feature",
  "properties": {
    "gn:admin1_code":"4",
    "gn:asciiname":"Tharo",
    "gn:country_code":"PK",
    "gn:dem":177,
    "gn:feature_class":"P",
    "gn:feature_code":"PPL",
    "gn:name":"Tharo",
    "gn:population":0,
    "gn:timezone":"Asia/Karachi",
    "iso:country":"PK",
    "name:und_x_variant":[
        "Tharu"
    ],
    "wof:name":"Tharo",
    "wof:placetype":"locality"
},
  "geometry": {"coordinates":[71.17310000000001,31.7845],"type":"Point"}
}