{
  "type": "Feature",
  "properties": {
    "gn:admin1_code":"3",
    "gn:asciiname":"Tako Banda",
    "gn:country_code":"PK",
    "gn:dem":2498,
    "gn:feature_class":"P",
    "gn:feature_code":"PPL",
    "gn:name":"Tako Banda",
    "gn:population":0,
    "gn:timezone":"Asia/Karachi",
    "iso:country":"PK",
    "name:eng_x_preferred":[
        "Tako Banda"
    ],
    "wof:name":"Tako Banda",
    "wof:placetype":"locality"
},
  "geometry": {"coordinates":[71.93228000000001,35.27534],"type":"Point"}
}