{
  "type": "Feature",
  "properties": {
    "gn:admin1_code":"4.0",
    "gn:asciiname":"Kalian Kalan",
    "gn:country_code":"PK",
    "gn:dem":350,
    "gn:feature_class":"P",
    "gn:feature_code":"PPL",
    "gn:name":"Kalian Kalan",
    "gn:population":0,
    "gn:timezone":"Asia/Karachi",
    "iso:country":"PK",
    "name:und_x_variant":[
        "Palahgir\u0101n Khurd"
    ],
    "wof:name":"Kalian Kalan",
    "wof:placetype":"locality"
},
  "geometry": {"coordinates":[74.15083,32.88046],"type":"Point"}
}