{
  "type": "Feature",
  "properties": {
    "gn:admin1_code":"04",
    "gn:asciiname":"Mahbal",
    "gn:country_code":"PK",
    "gn:dem":188,
    "gn:feature_class":"P",
    "gn:feature_code":"PPL",
    "gn:name":"Mahbal",
    "gn:population":0,
    "gn:timezone":"Asia/Karachi",
    "iso:country":"PK",
    "name:und_x_variant":[
        "Mautbal",
        "Mahbal",
        "Maibal",
        "Maihb\u0101l"
    ],
    "wof:name":"Mahbal",
    "wof:placetype":"locality"
},
  "geometry": {"coordinates":[71.19781999999999,32.04125],"type":"Point"}
}