{
  "type": "Feature",
  "properties": {
    "gn:admin1_code":"5.0",
    "gn:asciiname":"Goth Ali Muhammad Sanjirani",
    "gn:country_code":"PK",
    "gn:dem":33,
    "gn:feature_class":"P",
    "gn:feature_code":"PPL",
    "gn:name":"Goth Ali Muhammad Sanjirani",
    "gn:population":0,
    "gn:timezone":"Asia/Karachi",
    "iso:country":"PK",
    "name:und_x_variant":[
        "Ali Muhammad Sanjr\u0101ni"
    ],
    "wof:name":"Goth Ali Muhammad Sanjirani",
    "wof:placetype":"locality"
},
  "geometry": {"coordinates":[68.32486,26.05082],"type":"Point"}
}