{
  "type": "Feature",
  "properties": {
    "gn:admin1_code":"5",
    "gn:asciiname":"Goth Salamat Kerio",
    "gn:country_code":"PK",
    "gn:dem":28,
    "gn:feature_class":"P",
    "gn:feature_code":"PPL",
    "gn:name":"Goth Salamat Kerio",
    "gn:population":0,
    "gn:timezone":"Asia/Karachi",
    "iso:country":"PK",
    "name:und_x_variant":[
        "Goth Sal\u0101mat Kario",
        "Goth M\u0101li Sh\u0101h"
    ],
    "wof:name":"Goth Salamat Kerio",
    "wof:placetype":"locality"
},
  "geometry": {"coordinates":[68.54056,25.76059],"type":"Point"}
}