{
  "type": "Feature",
  "properties": {
    "gn:admin1_code":"5.0",
    "gn:asciiname":"Kachhela",
    "gn:country_code":"PK",
    "gn:dem":14,
    "gn:feature_class":"P",
    "gn:feature_code":"PPL",
    "gn:name":"Kachhela",
    "gn:population":0,
    "gn:timezone":"Asia/Karachi",
    "iso:country":"PK",
    "name:und_x_variant":[
        "Kachelu",
        "Kachhela",
        "Kachelo",
        "K\u0101chhelo"
    ],
    "wof:name":"Kachhela",
    "wof:placetype":"locality"
},
  "geometry": {"coordinates":[69.18333,25.21667],"type":"Point"}
}