{
  "type": "Feature",
  "properties": {
    "gn:admin1_code":"4",
    "gn:asciiname":"Mahmoodwala",
    "gn:country_code":"PK",
    "gn:dem":130,
    "gn:feature_class":"P",
    "gn:feature_code":"PPL",
    "gn:name":"Mahmoodwala",
    "gn:population":0,
    "gn:timezone":"Asia/Karachi",
    "iso:country":"PK",
    "name:und_x_variant":[
        "Mahm\u016bdw\u0101la"
    ],
    "wof:name":"Mahmoodwala",
    "wof:placetype":"locality"
},
  "geometry": {"coordinates":[71.05863000000002,30.39945],"type":"Point"}
}