{
  "type": "Feature",
  "properties": {
    "gn:admin1_code":"4",
    "gn:asciiname":"Basti Jindu Khan Hulwani",
    "gn:country_code":"PK",
    "gn:dem":109,
    "gn:feature_class":"P",
    "gn:feature_code":"PPL",
    "gn:name":"Basti Jindu Khan Hulwani",
    "gn:population":0,
    "gn:timezone":"Asia/Karachi",
    "iso:country":"PK",
    "name:und_x_variant":[
        "Mad Jhindu Hulw\u0101ni"
    ],
    "wof:name":"Basti Jindu Khan Hulwani",
    "wof:placetype":"locality"
},
  "geometry": {"coordinates":[70.39577,29.43803],"type":"Point"}
}