{
  "type": "Feature",
  "properties": {
    "gn:admin1_code":"4.0",
    "gn:asciiname":"Dhok Jattanwali",
    "gn:country_code":"PK",
    "gn:dem":490,
    "gn:feature_class":"P",
    "gn:feature_code":"PPL",
    "gn:name":"Dhok Jattanwali",
    "gn:population":0,
    "gn:timezone":"Asia/Karachi",
    "iso:country":"PK",
    "name:und_x_variant":[
        "Dhok Jattanw\u0101li"
    ],
    "wof:name":"Dhok Jattanwali",
    "wof:placetype":"locality"
},
  "geometry": {"coordinates":[72.61386999999998,33.60723],"type":"Point"}
}