{
  "type": "Feature",
  "properties": {
    "gn:admin1_code":"5",
    "gn:asciiname":"Goth Watro",
    "gn:country_code":"PK",
    "gn:dem":69,
    "gn:feature_class":"P",
    "gn:feature_code":"PPL",
    "gn:name":"Goth Watro",
    "gn:population":0,
    "gn:timezone":"Asia/Karachi",
    "iso:country":"PK",
    "name:und_x_variant":[
        "Wata"
    ],
    "wof:name":"Goth Watro",
    "wof:placetype":"locality"
},
  "geometry": {"coordinates":[69.22717,27.64219000000001],"type":"Point"}
}