{
  "type": "Feature",
  "properties": {
    "gn:admin1_code":"4.0",
    "gn:asciiname":"Chak Eighty-nine C",
    "gn:country_code":"PK",
    "gn:dem":159,
    "gn:feature_class":"P",
    "gn:feature_code":"PPL",
    "gn:name":"Chak Eighty-nine C",
    "gn:population":0,
    "gn:timezone":"Asia/Karachi",
    "iso:country":"PK",
    "wof:name":"Chak Eighty-nine C",
    "wof:placetype":"locality"
},
  "geometry": {"coordinates":[73.18541999999999,29.55607],"type":"Point"}
}