{
  "type": "Feature",
  "properties": {
    "gn:admin1_code":"2.0",
    "gn:asciiname":"Kaneti",
    "gn:country_code":"PK",
    "gn:dem":1682,
    "gn:feature_class":"P",
    "gn:feature_code":"PPL",
    "gn:name":"Kaneti",
    "gn:population":0,
    "gn:timezone":"Asia/Karachi",
    "iso:country":"PK",
    "name:und_x_variant":[
        "Khnati",
        "Kaneti"
    ],
    "wof:name":"Kaneti",
    "wof:placetype":"locality"
},
  "geometry": {"coordinates":[66.64073,29.67874],"type":"Point"}
}