{
  "type": "Feature",
  "properties": {
    "gn:admin1_code":"4",
    "gn:asciiname":"Chak Sixteen and Sixty-three",
    "gn:country_code":"PK",
    "gn:dem":182,
    "gn:feature_class":"P",
    "gn:feature_code":"PPL",
    "gn:name":"Chak Sixteen and Sixty-three",
    "gn:population":0,
    "gn:timezone":"Asia/Karachi",
    "iso:country":"PK",
    "wof:name":"Chak Sixteen and Sixty-three",
    "wof:placetype":"locality"
},
  "geometry": {"coordinates":[73.50139,31.15556],"type":"Point"}
}