{
  "type": "Feature",
  "properties": {
    "gn:admin1_code":"4.0",
    "gn:asciiname":"Basti Haji Abdul Qadir",
    "gn:country_code":"PK",
    "gn:dem":89,
    "gn:feature_class":"P",
    "gn:feature_code":"PPL",
    "gn:name":"Basti H\u0101ji Abdul Q\u0101dir",
    "gn:population":0,
    "gn:timezone":"Asia/Karachi",
    "iso:country":"PK",
    "name:urd_x_preferred":[
        "Basti H\u0101ji Abdul Q\u0101dir"
    ],
    "wof:name":"Basti Haji Abdul Qadir",
    "wof:placetype":"locality"
},
  "geometry": {"coordinates":[70.52360999999998,28.83333],"type":"Point"}
}