{
  "type": "Feature",
  "properties": {
    "gn:admin1_code":"6",
    "gn:asciiname":"Mandhar",
    "gn:country_code":"PK",
    "gn:dem":1981,
    "gn:feature_class":"P",
    "gn:feature_code":"PPL",
    "gn:name":"Mandhar",
    "gn:population":0,
    "gn:timezone":"Asia/Karachi",
    "iso:country":"PK",
    "name:und_x_variant":[
        "Menjah\u0101r",
        "Mantahar"
    ],
    "wof:name":"Mandhar",
    "wof:placetype":"locality"
},
  "geometry": {"coordinates":[74.1626,33.84995],"type":"Point"}
}