{
  "type": "Feature",
  "properties": {
    "gn:admin1_code":"5.0",
    "gn:asciiname":"Darya Khan Laghari",
    "gn:country_code":"PK",
    "gn:dem":10,
    "gn:feature_class":"P",
    "gn:feature_code":"PPL",
    "gn:name":"Darya Khan Laghari",
    "gn:population":0,
    "gn:timezone":"Asia/Karachi",
    "iso:country":"PK",
    "name:eng_x_preferred":[
        "Darya Khan Laghari"
    ],
    "wof:name":"Darya Khan Laghari",
    "wof:placetype":"locality"
},
  "geometry": {"coordinates":[68.12663000000001,24.71108],"type":"Point"}
}