{
  "type": "Feature",
  "properties": {
    "gn:admin1_code":"6",
    "gn:asciiname":"Panial",
    "gn:country_code":"PK",
    "gn:dem":766,
    "gn:feature_class":"P",
    "gn:feature_code":"PPL",
    "gn:name":"Panial",
    "gn:population":0,
    "gn:timezone":"Asia/Karachi",
    "iso:country":"PK",
    "name:und_x_variant":[
        "Karuhin"
    ],
    "wof:name":"Panial",
    "wof:placetype":"locality"
},
  "geometry": {"coordinates":[73.83393000000002,33.50474000000001],"type":"Point"}
}