{
  "type": "Feature",
  "properties": {
    "gn:admin1_code":"3.0",
    "gn:asciiname":"Gur Khwar Bando",
    "gn:country_code":"PK",
    "gn:dem":2531,
    "gn:feature_class":"P",
    "gn:feature_code":"PPL",
    "gn:name":"Gur Khwar Bando",
    "gn:population":0,
    "gn:timezone":"Asia/Karachi",
    "iso:country":"PK",
    "wof:name":"Gur Khwar Bando",
    "wof:placetype":"locality"
},
  "geometry": {"coordinates":[71.94580000000001,35.36424],"type":"Point"}
}