{
  "type": "Feature",
  "properties": {
    "gn:admin1_code":"4.0",
    "gn:asciiname":"Dhok Panja",
    "gn:country_code":"PK",
    "gn:dem":361,
    "gn:feature_class":"P",
    "gn:feature_code":"PPL",
    "gn:name":"Dhok Panja",
    "gn:population":0,
    "gn:timezone":"Asia/Karachi",
    "iso:country":"PK",
    "wof:name":"Dhok Panja",
    "wof:placetype":"locality"
},
  "geometry": {"coordinates":[71.91970000000001,32.81310999999999],"type":"Point"}
}