{
  "type": "Feature",
  "properties": {
    "gn:admin1_code":"4",
    "gn:asciiname":"Jahanewala",
    "gn:country_code":"PK",
    "gn:dem":121,
    "gn:feature_class":"P",
    "gn:feature_code":"PPL",
    "gn:name":"Jahanewala",
    "gn:population":0,
    "gn:timezone":"Asia/Karachi",
    "iso:country":"PK",
    "name:und_x_variant":[
        "J\u0101niw\u0101la"
    ],
    "wof:name":"Jahanewala",
    "wof:placetype":"locality"
},
  "geometry": {"coordinates":[71.43997,30.05134],"type":"Point"}
}