{
  "type": "Feature",
  "properties": {
    "gn:admin1_code":"5",
    "gn:asciiname":"Goth Abdul Rashid Arain",
    "gn:country_code":"PK",
    "gn:dem":12,
    "gn:feature_class":"P",
    "gn:feature_code":"PPL",
    "gn:name":"Goth Abdul Rashid Arain",
    "gn:population":0,
    "gn:timezone":"Asia/Karachi",
    "iso:country":"PK",
    "name:und_x_variant":[
        "Abdul Rashid Ar\u0101\u012bn"
    ],
    "wof:name":"Goth Abdul Rashid Arain",
    "wof:placetype":"locality"
},
  "geometry": {"coordinates":[69.19515,25.1026],"type":"Point"}
}