{
  "type": "Feature",
  "properties": {
    "gn:admin1_code":"01",
    "gn:asciiname":"Raghgan",
    "gn:country_code":"PK",
    "gn:dem":848,
    "gn:feature_class":"P",
    "gn:feature_code":"PPL",
    "gn:name":"Raghgan",
    "gn:population":0,
    "gn:timezone":"Asia/Karachi",
    "iso:country":"PK",
    "name:eng_x_preferred":[
        "Raghag\u0101n"
    ],
    "name:und_x_variant":[
        "Lar Raghagan"
    ],
    "wof:name":"Raghgan",
    "wof:placetype":"locality"
},
  "geometry": {"coordinates":[71.58583,34.78533],"type":"Point"}
}