{
  "type": "Feature",
  "properties": {
    "gn:admin1_code":"2.0",
    "gn:asciiname":"Ulmi",
    "gn:country_code":"PK",
    "gn:dem":879,
    "gn:feature_class":"P",
    "gn:feature_code":"PPL",
    "gn:name":"Ulmi",
    "gn:population":0,
    "gn:timezone":"Asia/Karachi",
    "iso:country":"PK",
    "name:ceb_x_preferred":[
        "Ulmi"
    ],
    "name:ita_x_preferred":[
        "Ulmi"
    ],
    "name:srp_x_preferred":[
        "\u0423\u043b\u043c\u0438"
    ],
    "name:und_x_variant":[
        "Ulme"
    ],
    "name:vol_x_preferred":[
        "Ulmi"
    ],
    "wof:name":"Ulmi",
    "wof:placetype":"locality"
},
  "geometry": {"coordinates":[70.122,31.23349],"type":"Point"}
}