{
  "type": "Feature",
  "properties": {
    "gn:admin1_code":"04",
    "gn:asciiname":"Kot Allozai",
    "gn:country_code":"PK",
    "gn:dem":192,
    "gn:feature_class":"P",
    "gn:feature_code":"PPL",
    "gn:name":"Kot Allozai",
    "gn:population":0,
    "gn:timezone":"Asia/Karachi",
    "iso:country":"PK",
    "name:und_x_variant":[
        "Chak 52 NB",
        "Kot Allozai"
    ],
    "wof:name":"Kot Allozai",
    "wof:placetype":"locality"
},
  "geometry": {"coordinates":[72.69540000000001,32.14824],"type":"Point"}
}