{
  "type": "Feature",
  "properties": {
    "gn:admin1_code":"4.0",
    "gn:asciiname":"Adda Balani",
    "gn:country_code":"PK",
    "gn:dem":276,
    "gn:feature_class":"P",
    "gn:feature_code":"PPL",
    "gn:name":"Adda Balani",
    "gn:population":0,
    "gn:timezone":"Asia/Karachi",
    "iso:country":"PK",
    "wof:name":"Adda Balani",
    "wof:placetype":"locality"
},
  "geometry": {"coordinates":[73.92910000000001,32.92547],"type":"Point"}
}