{
  "type": "Feature",
  "properties": {
    "gn:admin1_code":"2.0",
    "gn:asciiname":"Tagh Shahar",
    "gn:country_code":"PK",
    "gn:dem":1367,
    "gn:feature_class":"P",
    "gn:feature_code":"PPL",
    "gn:name":"Tagh Shahar",
    "gn:population":0,
    "gn:timezone":"Asia/Karachi",
    "iso:country":"PK",
    "wof:name":"Tagh Shahar",
    "wof:placetype":"locality"
},
  "geometry": {"coordinates":[69.96089000000001,30.90066],"type":"Point"}
}