{
  "type": "Feature",
  "properties": {
    "gn:admin1_code":"5",
    "gn:asciiname":"Lal Khan Bangwar",
    "gn:country_code":"PK",
    "gn:dem":69,
    "gn:feature_class":"P",
    "gn:feature_code":"PPL",
    "gn:name":"Lal Khan Bangwar",
    "gn:population":0,
    "gn:timezone":"Asia/Karachi",
    "iso:country":"PK",
    "wof:name":"Lal Khan Bangwar",
    "wof:placetype":"locality"
},
  "geometry": {"coordinates":[69.23156999999999,28.32809],"type":"Point"}
}