{
  "type": "Feature",
  "properties": {
    "gn:admin1_code":"5",
    "gn:asciiname":"Goth Hamid Khaskheli",
    "gn:country_code":"PK",
    "gn:dem":15,
    "gn:feature_class":"P",
    "gn:feature_code":"PPL",
    "gn:name":"Goth Hamid Khaskheli",
    "gn:population":0,
    "gn:timezone":"Asia/Karachi",
    "iso:country":"PK",
    "name:und_x_variant":[
        "Ham\u012bd Kh\u0101skheli"
    ],
    "wof:name":"Goth Hamid Khaskheli",
    "wof:placetype":"locality"
},
  "geometry": {"coordinates":[68.52542,25.00251],"type":"Point"}
}