{
  "type": "Feature",
  "properties": {
    "gn:admin1_code":"4.0",
    "gn:asciiname":"Dhok Qureshi",
    "gn:country_code":"PK",
    "gn:dem":444,
    "gn:feature_class":"P",
    "gn:feature_code":"PPL",
    "gn:name":"Dhok Qureshi",
    "gn:population":0,
    "gn:timezone":"Asia/Karachi",
    "iso:country":"PK",
    "name:und_x_variant":[
        "Dhok Quraishi"
    ],
    "wof:name":"Dhok Qureshi",
    "wof:placetype":"locality"
},
  "geometry": {"coordinates":[72.17124,33.32375],"type":"Point"}
}