{
  "type": "Feature",
  "properties": {
    "gn:admin1_code":"4",
    "gn:asciiname":"Juthianwala",
    "gn:country_code":"PK",
    "gn:dem":150,
    "gn:feature_class":"P",
    "gn:feature_code":"PPL",
    "gn:name":"Juthi\u0101nw\u0101la",
    "gn:population":0,
    "gn:timezone":"Asia/Karachi",
    "iso:country":"PK",
    "wof:name":"Juthianwala",
    "wof:placetype":"locality"
},
  "geometry": {"coordinates":[71.0625,31.02917],"type":"Point"}
}