{
  "type": "Feature",
  "properties": {
    "gn:admin1_code":"3",
    "gn:asciiname":"Kuz Pirsar Banda",
    "gn:country_code":"PK",
    "gn:dem":2008,
    "gn:feature_class":"P",
    "gn:feature_code":"PPL",
    "gn:name":"Kuz Pirsar Banda",
    "gn:population":0,
    "gn:timezone":"Asia/Karachi",
    "iso:country":"PK",
    "wof:name":"Kuz Pirsar Banda",
    "wof:placetype":"locality"
},
  "geometry": {"coordinates":[72.88336,34.81841],"type":"Point"}
}