{
  "type": "Feature",
  "properties": {
    "gn:admin1_code":"4.0",
    "gn:asciiname":"Basti Khuda Bakhsh Faqir",
    "gn:country_code":"PK",
    "gn:dem":80,
    "gn:feature_class":"P",
    "gn:feature_code":"PPL",
    "gn:name":"Basti Khuda Bakhsh Faqir",
    "gn:population":0,
    "gn:timezone":"Asia/Karachi",
    "iso:country":"PK",
    "name:und_x_variant":[
        "Basti Khuda Bukhsh Faqir"
    ],
    "wof:name":"Basti Khuda Bakhsh Faqir",
    "wof:placetype":"locality"
},
  "geometry": {"coordinates":[69.89404,28.51625],"type":"Point"}
}