{
  "type": "Feature",
  "properties": {
    "gn:admin1_code":"3",
    "gn:asciiname":"Nawar Khel",
    "gn:country_code":"PK",
    "gn:dem":280,
    "gn:feature_class":"P",
    "gn:feature_code":"PPL",
    "gn:name":"Nawar Khel",
    "gn:population":0,
    "gn:timezone":"Asia/Karachi",
    "iso:country":"PK",
    "wof:name":"Nawar Khel",
    "wof:placetype":"locality"
},
  "geometry": {"coordinates":[71.0675,32.58499],"type":"Point"}
}