{
  "type": "Feature",
  "properties": {
    "gn:admin1_code":"4.0",
    "gn:asciiname":"Nai Khangah",
    "gn:country_code":"PK",
    "gn:dem":535,
    "gn:feature_class":"P",
    "gn:feature_code":"PPL",
    "gn:name":"Nai Khangah",
    "gn:population":0,
    "gn:timezone":"Asia/Karachi",
    "iso:country":"PK",
    "wof:name":"Nai Khangah",
    "wof:placetype":"locality"
},
  "geometry": {"coordinates":[73.34435000000001,33.11071],"type":"Point"}
}