{
  "type": "Feature",
  "properties": {
    "gn:admin1_code":"5.0",
    "gn:asciiname":"Nur Muhammad Khor",
    "gn:country_code":"PK",
    "gn:dem":8,
    "gn:feature_class":"P",
    "gn:feature_code":"PPL",
    "gn:name":"Nur Muhammad Khor",
    "gn:population":0,
    "gn:timezone":"Asia/Karachi",
    "iso:country":"PK",
    "name:eng_x_preferred":[
        "Nur Muhammad Khor"
    ],
    "wof:name":"Nur Muhammad Khor",
    "wof:placetype":"locality"
},
  "geometry": {"coordinates":[68.37496999999999,24.5402],"type":"Point"}
}