{
  "type": "Feature",
  "properties": {
    "gn:admin1_code":"6.0",
    "gn:asciiname":"Jhikka Gali",
    "gn:country_code":"PK",
    "gn:dem":1023,
    "gn:feature_class":"P",
    "gn:feature_code":"PPL",
    "gn:name":"Jhikka Gali",
    "gn:population":0,
    "gn:timezone":"Asia/Karachi",
    "iso:country":"PK",
    "name:und_x_variant":[
        "Jhikka Gala"
    ],
    "wof:name":"Jhikka Gali",
    "wof:placetype":"locality"
},
  "geometry": {"coordinates":[73.62572,33.69479],"type":"Point"}
}