{
  "type": "Feature",
  "properties": {
    "gn:admin1_code":"2.0",
    "gn:asciiname":"Pir Bukhsh",
    "gn:country_code":"PK",
    "gn:dem":62,
    "gn:feature_class":"P",
    "gn:feature_code":"PPL",
    "gn:name":"Pir Bukhsh",
    "gn:population":0,
    "gn:timezone":"Asia/Karachi",
    "iso:country":"PK",
    "name:und_x_variant":[
        "Sh\u0101bu",
        "Sh\u0101hu"
    ],
    "wof:name":"Pir Bukhsh",
    "wof:placetype":"locality"
},
  "geometry": {"coordinates":[67.49663000000001,28.25354],"type":"Point"}
}