{
  "type": "Feature",
  "properties": {
    "gn:admin1_code":"4.0",
    "gn:asciiname":"Chak Seventy-nine M",
    "gn:country_code":"PK",
    "gn:dem":109,
    "gn:feature_class":"P",
    "gn:feature_code":"PPL",
    "gn:name":"Chak Seventy-nine M",
    "gn:population":0,
    "gn:timezone":"Asia/Karachi",
    "iso:country":"PK",
    "name:und_x_variant":[
        "Chak 79 M"
    ],
    "wof:name":"Chak Seventy-nine M",
    "wof:placetype":"locality"
},
  "geometry": {"coordinates":[71.2677,29.57016],"type":"Point"}
}