{
  "type": "Feature",
  "properties": {
    "gn:admin1_code":"5",
    "gn:asciiname":"Kamal Khan Lashari",
    "gn:country_code":"PK",
    "gn:dem":11,
    "gn:feature_class":"P",
    "gn:feature_code":"PPL",
    "gn:name":"Kamal Khan Lashari",
    "gn:population":0,
    "gn:timezone":"Asia/Karachi",
    "iso:country":"PK",
    "wof:name":"Kamal Khan Lashari",
    "wof:placetype":"locality"
},
  "geometry": {"coordinates":[69.07671999999999,24.89356],"type":"Point"}
}