{
  "type": "Feature",
  "properties": {
    "gn:admin1_code":"3",
    "gn:asciiname":"Itwara",
    "gn:country_code":"PK",
    "gn:dem":456,
    "gn:feature_class":"P",
    "gn:feature_code":"PPL",
    "gn:name":"Itwara",
    "gn:population":0,
    "gn:timezone":"Asia/Karachi",
    "iso:country":"PK",
    "wof:name":"Itwara",
    "wof:placetype":"locality"
},
  "geometry": {"coordinates":[72.82979,34.45329],"type":"Point"}
}