{
  "type": "Feature",
  "properties": {
    "gn:admin1_code":"4.0",
    "gn:asciiname":"Rasulpur",
    "gn:country_code":"PK",
    "gn:dem":162,
    "gn:feature_class":"P",
    "gn:feature_code":"PPL",
    "gn:name":"Rasulpur",
    "gn:population":0,
    "gn:timezone":"Asia/Karachi",
    "iso:country":"PK",
    "name:fas_x_preferred":[
        "\u0631\u0633\u0648\u0644\u200c\u067e\u0648\u0631"
    ],
    "name:urd_x_preferred":[
        "\u0631\u0633\u0648\u0644\u067e\u0648\u0631"
    ],
    "wof:name":"Rasulpur",
    "wof:placetype":"locality"
},
  "geometry": {"coordinates":[73.43143000000001,30.2944],"type":"Point"}
}