{
  "type": "Feature",
  "properties": {
    "gn:admin1_code":"04",
    "gn:asciiname":"Zendi",
    "gn:country_code":"PK",
    "gn:dem":416,
    "gn:feature_class":"P",
    "gn:feature_code":"PPL",
    "gn:name":"Zendi",
    "gn:population":0,
    "gn:timezone":"Asia/Karachi",
    "iso:country":"PK",
    "name:und_x_variant":[
        "Kot Zendi"
    ],
    "wof:name":"Zendi",
    "wof:placetype":"locality"
},
  "geometry": {"coordinates":[72.57167,33.69611],"type":"Point"}
}