{
  "type": "Feature",
  "properties": {
    "gn:admin1_code":"1",
    "gn:asciiname":"Shamkai",
    "gn:country_code":"PK",
    "gn:dem":1659,
    "gn:feature_class":"P",
    "gn:feature_code":"PPL",
    "gn:name":"Shamkai",
    "gn:population":0,
    "gn:timezone":"Asia/Karachi",
    "iso:country":"PK",
    "name:und_x_variant":[
        "Michi Khel",
        "Shamkai"
    ],
    "wof:name":"Shamkai",
    "wof:placetype":"locality"
},
  "geometry": {"coordinates":[69.82111,32.41167],"type":"Point"}
}