{
  "type": "Feature",
  "properties": {
    "gn:admin1_code":"4.0",
    "gn:asciiname":"Chak One Hundred Seventeen Nine Left",
    "gn:country_code":"PK",
    "gn:dem":162,
    "gn:feature_class":"P",
    "gn:feature_code":"PPL",
    "gn:name":"Chak One Hundred Seventeen Nine Left",
    "gn:population":0,
    "gn:timezone":"Asia/Karachi",
    "iso:country":"PK",
    "name:und_x_variant":[
        "Kangniw\u0101la"
    ],
    "wof:name":"Chak One Hundred Seventeen Nine Left",
    "wof:placetype":"locality"
},
  "geometry": {"coordinates":[73.07989999999999,30.49799],"type":"Point"}
}