{
  "type": "Feature",
  "properties": {
    "gn:admin1_code":"3",
    "gn:asciiname":"Garah Bala",
    "gn:country_code":"PK",
    "gn:dem":191,
    "gn:feature_class":"P",
    "gn:feature_code":"PPL",
    "gn:name":"Garah Bala",
    "gn:population":0,
    "gn:timezone":"Asia/Karachi",
    "iso:country":"PK",
    "name:und_x_variant":[
        "B\u0101la"
    ],
    "wof:name":"Garah Bala",
    "wof:placetype":"locality"
},
  "geometry": {"coordinates":[70.71088,31.89206],"type":"Point"}
}