{
  "type": "Feature",
  "properties": {
    "gn:admin1_code":"5.0",
    "gn:asciiname":"Goth Saiyid Jamal ud Din Shah",
    "gn:country_code":"PK",
    "gn:dem":21,
    "gn:feature_class":"P",
    "gn:feature_code":"PPL",
    "gn:name":"Goth Saiyid Jamal ud Din Shah",
    "gn:population":0,
    "gn:timezone":"Asia/Karachi",
    "iso:country":"PK",
    "wof:name":"Goth Saiyid Jamal ud Din Shah",
    "wof:placetype":"locality"
},
  "geometry": {"coordinates":[69.19358000000001,26.03945],"type":"Point"}
}