{
  "type": "Feature",
  "properties": {
    "gn:admin1_code":"4.0",
    "gn:asciiname":"Jhuggian Naulan",
    "gn:country_code":"PK",
    "gn:dem":205,
    "gn:feature_class":"P",
    "gn:feature_code":"PPL",
    "gn:name":"Jhuggian Naulan",
    "gn:population":0,
    "gn:timezone":"Asia/Karachi",
    "iso:country":"PK",
    "name:und_x_variant":[
        "Jhuggi\u0101n Naul"
    ],
    "wof:name":"Jhuggian Naulan",
    "wof:placetype":"locality"
},
  "geometry": {"coordinates":[74.09193,31.42602],"type":"Point"}
}