{
  "type": "Feature",
  "properties": {
    "gn:admin1_code":"4.0",
    "gn:asciiname":"Chah Nur Muhammad",
    "gn:country_code":"PK",
    "gn:dem":359,
    "gn:feature_class":"P",
    "gn:feature_code":"PPL",
    "gn:name":"Chah Nur Muhammad",
    "gn:population":0,
    "gn:timezone":"Asia/Karachi",
    "iso:country":"PK",
    "name:und_x_variant":[
        "N\u016br Muhammad"
    ],
    "wof:name":"Chah Nur Muhammad",
    "wof:placetype":"locality"
},
  "geometry": {"coordinates":[71.86385,32.72888],"type":"Point"}
}