{
  "type": "Feature",
  "properties": {
    "gn:admin1_code":"03",
    "gn:asciiname":"Thandiani",
    "gn:country_code":"PK",
    "gn:dem":2654,
    "gn:feature_class":"P",
    "gn:feature_code":"PPL",
    "gn:name":"Thandiani",
    "gn:population":0,
    "gn:timezone":"Asia/Karachi",
    "iso:country":"PK",
    "name:urd_x_preferred":[
        "\u0679\u06be\u0646\u0688\u06cc\u0627\u0646\u06cc"
    ],
    "wof:name":"Thandiani",
    "wof:placetype":"locality"
},
  "geometry": {"coordinates":[73.35196999999999,34.23183],"type":"Point"}
}