{
  "type": "Feature",
  "properties": {
    "gn:admin1_code":"4",
    "gn:asciiname":"Basti Allah Dittawali",
    "gn:country_code":"PK",
    "gn:dem":88,
    "gn:feature_class":"P",
    "gn:feature_code":"PPL",
    "gn:name":"Basti All\u0101h Dittaw\u0101li",
    "gn:population":0,
    "gn:timezone":"Asia/Karachi",
    "iso:country":"PK",
    "wof:name":"Basti Allah Dittawali",
    "wof:placetype":"locality"
},
  "geometry": {"coordinates":[70.69028,28.5375],"type":"Point"}
}