{
  "type": "Feature",
  "properties": {
    "gn:admin1_code":"3.0",
    "gn:asciiname":"Painda Banda",
    "gn:country_code":"PK",
    "gn:dem":435,
    "gn:feature_class":"P",
    "gn:feature_code":"PPL",
    "gn:name":"Painda Banda",
    "gn:population":0,
    "gn:timezone":"Asia/Karachi",
    "iso:country":"PK",
    "wof:name":"Painda Banda",
    "wof:placetype":"locality"
},
  "geometry": {"coordinates":[71.01177,32.85949],"type":"Point"}
}