{
  "type": "Feature",
  "properties": {
    "gn:admin1_code":"1.0",
    "gn:asciiname":"Panwar",
    "gn:country_code":"PK",
    "gn:dem":460,
    "gn:feature_class":"P",
    "gn:feature_code":"PPL",
    "gn:name":"Panwar",
    "gn:population":0,
    "gn:timezone":"Asia/Karachi",
    "iso:country":"PK",
    "wof:name":"Panwar",
    "wof:placetype":"locality"
},
  "geometry": {"coordinates":[73.70662,33.38304],"type":"Point"}
}