{
  "type": "Feature",
  "properties": {
    "gn:admin1_code":"3.0",
    "gn:asciiname":"Mirak Bat",
    "gn:country_code":"PK",
    "gn:dem":1229,
    "gn:feature_class":"P",
    "gn:feature_code":"PPL",
    "gn:name":"Mirak Bat",
    "gn:population":0,
    "gn:timezone":"Asia/Karachi",
    "iso:country":"PK",
    "wof:name":"Mirak Bat",
    "wof:placetype":"locality"
},
  "geometry": {"coordinates":[71.56541,35.29268],"type":"Point"}
}