{
  "type": "Feature",
  "properties": {
    "gn:admin1_code":"3.0",
    "gn:asciiname":"Buto Bando",
    "gn:country_code":"PK",
    "gn:dem":496,
    "gn:feature_class":"P",
    "gn:feature_code":"PPL",
    "gn:name":"Buto Bando",
    "gn:population":0,
    "gn:timezone":"Asia/Karachi",
    "iso:country":"PK",
    "wof:name":"Buto Bando",
    "wof:placetype":"locality"
},
  "geometry": {"coordinates":[72.80764000000001,34.66485],"type":"Point"}
}