{
  "type": "Feature",
  "properties": {
    "gn:admin1_code":"3",
    "gn:asciiname":"Jajok",
    "gn:country_code":"PK",
    "gn:dem":2718,
    "gn:feature_class":"P",
    "gn:feature_code":"PPL",
    "gn:name":"Jajok",
    "gn:population":0,
    "gn:timezone":"Asia/Karachi",
    "iso:country":"PK",
    "name:eng_x_preferred":[
        "Jajok"
    ],
    "wof:name":"Jajok",
    "wof:placetype":"locality"
},
  "geometry": {"coordinates":[71.64604,35.81935],"type":"Point"}
}