{
  "type": "Feature",
  "properties": {
    "gn:admin1_code":"4",
    "gn:asciiname":"Hazratwala",
    "gn:country_code":"PK",
    "gn:dem":131,
    "gn:feature_class":"P",
    "gn:feature_code":"PPL",
    "gn:name":"Hazratwala",
    "gn:population":0,
    "gn:timezone":"Asia/Karachi",
    "iso:country":"PK",
    "wof:name":"Hazratwala",
    "wof:placetype":"locality"
},
  "geometry": {"coordinates":[71.05334999999999,30.41469],"type":"Point"}
}