{
  "type": "Feature",
  "properties": {
    "gn:admin1_code":"3.0",
    "gn:asciiname":"Sharid",
    "gn:country_code":"PK",
    "gn:dem":2566,
    "gn:feature_class":"P",
    "gn:feature_code":"PPL",
    "gn:name":"Sharid",
    "gn:population":0,
    "gn:timezone":"Asia/Karachi",
    "iso:country":"PK",
    "wof:name":"Sharid",
    "wof:placetype":"locality"
},
  "geometry": {"coordinates":[73.29677,35.01033],"type":"Point"}
}