{
  "type": "Feature",
  "properties": {
    "gn:admin1_code":"5",
    "gn:asciiname":"Goth Kharani",
    "gn:country_code":"PK",
    "gn:dem":41,
    "gn:feature_class":"P",
    "gn:feature_code":"PPL",
    "gn:name":"Goth Kharani",
    "gn:population":0,
    "gn:timezone":"Asia/Karachi",
    "iso:country":"PK",
    "name:und_x_variant":[
        "Goth Mur\u012bd Babbar"
    ],
    "wof:name":"Goth Kharani",
    "wof:placetype":"locality"
},
  "geometry": {"coordinates":[67.71247,26.79835],"type":"Point"}
}