{
  "type": "Feature",
  "properties": {
    "gn:admin1_code":"4",
    "gn:asciiname":"Chak Four Hundred Fifty-three Eastern Bar",
    "gn:country_code":"PK",
    "gn:dem":144,
    "gn:feature_class":"P",
    "gn:feature_code":"PPL",
    "gn:name":"Chak Four Hundred Fifty-three Eastern Bar",
    "gn:population":0,
    "gn:timezone":"Asia/Karachi",
    "iso:country":"PK",
    "name:und_x_variant":[
        "Rados"
    ],
    "wof:name":"Chak Four Hundred Fifty-three Eastern Bar",
    "wof:placetype":"locality"
},
  "geometry": {"coordinates":[72.63299000000001,30.12576],"type":"Point"}
}