{
  "type": "Feature",
  "properties": {
    "gn:admin1_code":"4.0",
    "gn:asciiname":"Chak Fourty-seven -Gogera Distributary",
    "gn:country_code":"PK",
    "gn:dem":174,
    "gn:feature_class":"P",
    "gn:feature_code":"PPL",
    "gn:name":"Chak Fourty-seven -Gogera Distributary",
    "gn:population":0,
    "gn:timezone":"Asia/Karachi",
    "iso:country":"PK",
    "name:und_x_variant":[
        "Sh\u012bst Khara"
    ],
    "wof:name":"Chak Fourty-seven -Gogera Distributary",
    "wof:placetype":"locality"
},
  "geometry": {"coordinates":[73.25754999999999,30.86773],"type":"Point"}
}