{
  "type": "Feature",
  "properties": {
    "gn:admin1_code":"04",
    "gn:asciiname":"Rang Shah Number Two",
    "gn:country_code":"PK",
    "gn:dem":168,
    "gn:feature_class":"P",
    "gn:feature_code":"PPL",
    "gn:name":"Rang Shah Number Two",
    "gn:population":0,
    "gn:timezone":"Asia/Karachi",
    "iso:country":"PK",
    "name:und_x_variant":[
        "Rang Sh\u0101h"
    ],
    "wof:name":"Rang Shah Number Two",
    "wof:placetype":"locality"
},
  "geometry": {"coordinates":[72.90674,30.72786],"type":"Point"}
}