{
  "type": "Feature",
  "properties": {
    "gn:admin1_code":"2.0",
    "gn:asciiname":"Malang Gis",
    "gn:country_code":"PK",
    "gn:dem":1396,
    "gn:feature_class":"P",
    "gn:feature_code":"PPL",
    "gn:name":"Malang Gis",
    "gn:population":0,
    "gn:timezone":"Asia/Karachi",
    "iso:country":"PK",
    "wof:name":"Malang Gis",
    "wof:placetype":"locality"
},
  "geometry": {"coordinates":[63.75281,29.26053],"type":"Point"}
}