{
  "type": "Feature",
  "properties": {
    "gn:admin1_code":"4.0",
    "gn:asciiname":"Balagnah",
    "gn:country_code":"PK",
    "gn:dem":716,
    "gn:feature_class":"P",
    "gn:feature_code":"PPL",
    "gn:name":"Balagnah",
    "gn:population":0,
    "gn:timezone":"Asia/Karachi",
    "iso:country":"PK",
    "name:und_x_variant":[
        "Balagre"
    ],
    "wof:name":"Balagnah",
    "wof:placetype":"locality"
},
  "geometry": {"coordinates":[73.50225999999998,33.52295],"type":"Point"}
}