{
  "type": "Feature",
  "properties": {
    "gn:admin1_code":"4.0",
    "gn:asciiname":"Chak Seventy-three -Four Right",
    "gn:country_code":"PK",
    "gn:dem":174,
    "gn:feature_class":"P",
    "gn:feature_code":"PPL",
    "gn:name":"Chak Seventy-three -Four Right",
    "gn:population":0,
    "gn:timezone":"Asia/Karachi",
    "iso:country":"PK",
    "wof:name":"Chak Seventy-three -Four Right",
    "wof:placetype":"locality"
},
  "geometry": {"coordinates":[73.17444999999999,30.71948],"type":"Point"}
}