{
  "type": "Feature",
  "properties": {
    "gn:admin1_code":"5",
    "gn:asciiname":"Taghay Jo",
    "gn:country_code":"PK",
    "gn:dem":58,
    "gn:feature_class":"P",
    "gn:feature_code":"PPL",
    "gn:name":"Taghay Jo",
    "gn:population":0,
    "gn:timezone":"Asia/Karachi",
    "iso:country":"PK",
    "name:und_x_variant":[
        "Tagbu Khosa"
    ],
    "wof:name":"Taghay Jo",
    "wof:placetype":"locality"
},
  "geometry": {"coordinates":[68.39429,28.13665],"type":"Point"}
}