{
  "type": "Feature",
  "properties": {
    "gn:admin1_code":"4",
    "gn:asciiname":"Sobhewala",
    "gn:country_code":"PK",
    "gn:dem":142,
    "gn:feature_class":"P",
    "gn:feature_code":"PPL",
    "gn:name":"Sobhewala",
    "gn:population":0,
    "gn:timezone":"Asia/Karachi",
    "iso:country":"PK",
    "name:und_x_variant":[
        "Sohbaw\u0101la",
        "Khajjiw\u0101la"
    ],
    "wof:name":"Sobhewala",
    "wof:placetype":"locality"
},
  "geometry": {"coordinates":[71.48895,30.87467],"type":"Point"}
}