{
  "type": "Feature",
  "properties": {
    "gn:admin1_code":"3.0",
    "gn:asciiname":"Ghuliu Kalle",
    "gn:country_code":"PK",
    "gn:dem":1561,
    "gn:feature_class":"P",
    "gn:feature_code":"PPL",
    "gn:name":"Ghuliu Kalle",
    "gn:population":0,
    "gn:timezone":"Asia/Karachi",
    "iso:country":"PK",
    "wof:name":"Ghuliu Kalle",
    "wof:placetype":"locality"
},
  "geometry": {"coordinates":[71.88708000000003,34.69941],"type":"Point"}
}