{
  "type": "Feature",
  "properties": {
    "gn:admin1_code":"05",
    "gn:asciiname":"Madde",
    "gn:country_code":"PK",
    "gn:dem":43,
    "gn:feature_class":"P",
    "gn:feature_code":"PPL",
    "gn:name":"Madde",
    "gn:population":0,
    "gn:timezone":"Asia/Karachi",
    "iso:country":"PK",
    "name:und_x_variant":[
        "M\u0101do",
        "Madde"
    ],
    "wof:name":"Madde",
    "wof:placetype":"locality"
},
  "geometry": {"coordinates":[67.59213000000001,27.18544],"type":"Point"}
}