{
  "type": "Feature",
  "properties": {
    "gn:admin1_code":"3.0",
    "gn:asciiname":"Chingalai",
    "gn:country_code":"PK",
    "gn:dem":1391,
    "gn:feature_class":"P",
    "gn:feature_code":"PPL",
    "gn:name":"Chingalai",
    "gn:population":0,
    "gn:timezone":"Asia/Karachi",
    "iso:country":"PK",
    "name:und_x_variant":[
        "Chinkolay",
        "Chingalai"
    ],
    "wof:name":"Chingalai",
    "wof:placetype":"locality"
},
  "geometry": {"coordinates":[72.46531999999998,34.87474],"type":"Point"}
}