{
  "type": "Feature",
  "properties": {
    "gn:admin1_code":"01",
    "gn:asciiname":"Gul Shah Kili",
    "gn:country_code":"PK",
    "gn:dem":2025,
    "gn:feature_class":"P",
    "gn:feature_code":"PPL",
    "gn:name":"Gul Shah Kili",
    "gn:population":0,
    "gn:timezone":"Asia/Karachi",
    "iso:country":"PK",
    "wof:name":"Gul Shah Kili",
    "wof:placetype":"locality"
},
  "geometry": {"coordinates":[70.54531999999998,33.70713],"type":"Point"}
}