{
  "type": "Feature",
  "properties": {
    "gn:admin1_code":"3.0",
    "gn:asciiname":"Rabaki",
    "gn:country_code":"PK",
    "gn:dem":351,
    "gn:feature_class":"P",
    "gn:feature_code":"PPL",
    "gn:name":"Rabaki",
    "gn:population":0,
    "gn:timezone":"Asia/Karachi",
    "iso:country":"PK",
    "wof:name":"Rabaki",
    "wof:placetype":"locality"
},
  "geometry": {"coordinates":[70.56093,32.87517],"type":"Point"}
}