{
  "type": "Feature",
  "properties": {
    "gn:admin1_code":"5",
    "gn:asciiname":"Berido",
    "gn:country_code":"PK",
    "gn:dem":67,
    "gn:feature_class":"P",
    "gn:feature_code":"PPL",
    "gn:name":"Berido",
    "gn:population":0,
    "gn:timezone":"Asia/Karachi",
    "iso:country":"PK",
    "name:und_x_variant":[
        "Ber\u012blo"
    ],
    "wof:name":"Berido",
    "wof:placetype":"locality"
},
  "geometry": {"coordinates":[69.18373000000001,27.49437],"type":"Point"}
}