{
  "type": "Feature",
  "properties": {
    "gn:admin1_code":"1",
    "gn:asciiname":"Tarka",
    "gn:country_code":"PK",
    "gn:dem":1083,
    "gn:feature_class":"P",
    "gn:feature_code":"PPL",
    "gn:name":"Tarka",
    "gn:population":0,
    "gn:timezone":"Asia/Karachi",
    "iso:country":"PK",
    "name:ceb_x_preferred":[
        "Tarka"
    ],
    "name:deu_x_preferred":[
        "Tarka"
    ],
    "name:ita_x_preferred":[
        "Tarka"
    ],
    "name:pol_x_preferred":[
        "Tarka"
    ],
    "name:und_x_variant":[
        "Tarka Khel"
    ],
    "wof:name":"Tarka",
    "wof:placetype":"locality"
},
  "geometry": {"coordinates":[69.90331,32.94954],"type":"Point"}
}