{
  "type": "Feature",
  "properties": {
    "gn:admin1_code":"3",
    "gn:asciiname":"Kamar Khwa",
    "gn:country_code":"PK",
    "gn:dem":2555,
    "gn:feature_class":"P",
    "gn:feature_code":"PPL",
    "gn:name":"Kamar Khwa",
    "gn:population":0,
    "gn:timezone":"Asia/Karachi",
    "iso:country":"PK",
    "name:eng_x_preferred":[
        "Kamar Khwa"
    ],
    "wof:name":"Kamar Khwa",
    "wof:placetype":"locality"
},
  "geometry": {"coordinates":[72.68219999999999,35.35870999999999],"type":"Point"}
}