{
  "type": "Feature",
  "properties": {
    "gn:admin1_code":"4.0",
    "gn:asciiname":"Chuhar",
    "gn:country_code":"PK",
    "gn:dem":640,
    "gn:feature_class":"P",
    "gn:feature_code":"PPL",
    "gn:name":"Chuhar",
    "gn:population":0,
    "gn:timezone":"Asia/Karachi",
    "iso:country":"PK",
    "wof:name":"Chuhar",
    "wof:placetype":"locality"
},
  "geometry": {"coordinates":[73.45658,33.62677],"type":"Point"}
}