{
  "type": "Feature",
  "properties": {
    "gn:admin1_code":"5",
    "gn:asciiname":"Haji Rajio Bughio",
    "gn:country_code":"PK",
    "gn:dem":29,
    "gn:feature_class":"P",
    "gn:feature_code":"PPL",
    "gn:name":"Haji Rajio Bughio",
    "gn:population":0,
    "gn:timezone":"Asia/Karachi",
    "iso:country":"PK",
    "wof:name":"Haji Rajio Bughio",
    "wof:placetype":"locality"
},
  "geometry": {"coordinates":[68.55916999999999,26.13399],"type":"Point"}
}