{
  "type": "Feature",
  "properties": {
    "gn:admin1_code":"4",
    "gn:asciiname":"Chak Four Hundred Forty-five Eastern Bar",
    "gn:country_code":"PK",
    "gn:dem":148,
    "gn:feature_class":"P",
    "gn:feature_code":"PPL",
    "gn:name":"Chak Four Hundred Forty-five Eastern Bar",
    "gn:population":0,
    "gn:timezone":"Asia/Karachi",
    "iso:country":"PK",
    "name:und_x_variant":[
        "Kot Ghul\u0101m Hasan",
        "Kot Ghul\u0101m Hussain"
    ],
    "wof:name":"Chak Four Hundred Forty-five Eastern Bar",
    "wof:placetype":"locality"
},
  "geometry": {"coordinates":[72.69648000000002,30.14544],"type":"Point"}
}