{
  "type": "Feature",
  "properties": {
    "gn:admin1_code":"4.0",
    "gn:asciiname":"Chak Thirty-nine - Four Left",
    "gn:country_code":"PK",
    "gn:dem":168,
    "gn:feature_class":"P",
    "gn:feature_code":"PPL",
    "gn:name":"Chak Thirty-nine - Four Left",
    "gn:population":0,
    "gn:timezone":"Asia/Karachi",
    "iso:country":"PK",
    "name:und_x_variant":[
        "Bhojw\u0101naw\u0101la"
    ],
    "wof:name":"Chak Thirty-nine - Four Left",
    "wof:placetype":"locality"
},
  "geometry": {"coordinates":[73.3419,30.55221],"type":"Point"}
}