{
  "type": "Feature",
  "properties": {
    "gn:admin1_code":"01",
    "gn:asciiname":"Sultani Adda",
    "gn:country_code":"PK",
    "gn:dem":1503,
    "gn:feature_class":"P",
    "gn:feature_code":"PPL",
    "gn:name":"Sultani Adda",
    "gn:population":0,
    "gn:timezone":"Asia/Karachi",
    "iso:country":"PK",
    "name:und_x_variant":[
        "Sult\u0101nai",
        "Sultani"
    ],
    "wof:name":"Sultani Adda",
    "wof:placetype":"locality"
},
  "geometry": {"coordinates":[70.43460999999998,33.76327],"type":"Point"}
}