{
  "type": "Feature",
  "properties": {
    "gn:admin1_code":"4",
    "gn:asciiname":"Chak Seventy-seven Western Bank",
    "gn:country_code":"PK",
    "gn:dem":139,
    "gn:feature_class":"P",
    "gn:feature_code":"PPL",
    "gn:name":"Chak Seventy-seven Western Bank",
    "gn:population":0,
    "gn:timezone":"Asia/Karachi",
    "iso:country":"PK",
    "name:und_x_variant":[
        "Chak Seventy-seven-Eight AL"
    ],
    "wof:name":"Chak Seventy-seven Western Bank",
    "wof:placetype":"locality"
},
  "geometry": {"coordinates":[72.30013000000002,30.05642000000001],"type":"Point"}
}