{
  "type": "Feature",
  "properties": {
    "gn:admin1_code":"5",
    "gn:asciiname":"Goth Saheb Sial",
    "gn:country_code":"PK",
    "gn:dem":50,
    "gn:feature_class":"P",
    "gn:feature_code":"PPL",
    "gn:name":"Goth Saheb Sial",
    "gn:population":0,
    "gn:timezone":"Asia/Karachi",
    "iso:country":"PK",
    "name:und_x_variant":[
        "S\u0101hi S\u012bal"
    ],
    "wof:name":"Goth Saheb Sial",
    "wof:placetype":"locality"
},
  "geometry": {"coordinates":[68.31896,27.23525],"type":"Point"}
}