{
  "type": "Feature",
  "properties": {
    "gn:admin1_code":"4.0",
    "gn:asciiname":"Bidadpur",
    "gn:country_code":"PK",
    "gn:dem":214,
    "gn:feature_class":"P",
    "gn:feature_code":"PPL",
    "gn:name":"Bidadpur",
    "gn:population":0,
    "gn:timezone":"Asia/Karachi",
    "iso:country":"PK",
    "name:und_x_variant":[
        "Bed\u0101dpur"
    ],
    "wof:name":"Bidadpur",
    "wof:placetype":"locality"
},
  "geometry": {"coordinates":[74.16889999999999,31.84717],"type":"Point"}
}