{
  "type": "Feature",
  "properties": {
    "gn:admin1_code":"6",
    "gn:asciiname":"Majhoi",
    "gn:country_code":"PK",
    "gn:dem":825,
    "gn:feature_class":"P",
    "gn:feature_code":"PPL",
    "gn:name":"Majhoi",
    "gn:population":0,
    "gn:timezone":"Asia/Karachi",
    "iso:country":"PK",
    "wof:name":"Majhoi",
    "wof:placetype":"locality"
},
  "geometry": {"coordinates":[73.58734,34.25197],"type":"Point"}
}