{
  "type": "Feature",
  "properties": {
    "gn:admin1_code":"3",
    "gn:asciiname":"Dag",
    "gn:country_code":"PK",
    "gn:dem":607,
    "gn:feature_class":"P",
    "gn:feature_code":"PPL",
    "gn:name":"Dag",
    "gn:population":0,
    "gn:timezone":"Asia/Karachi",
    "iso:country":"PK",
    "name:und_x_variant":[
        "D\u0101g B\u0101nda"
    ],
    "wof:name":"Dag",
    "wof:placetype":"locality"
},
  "geometry": {"coordinates":[71.16764999999999,32.37589000000001],"type":"Point"}
}