{
  "type": "Feature",
  "properties": {
    "gn:admin1_code":"3",
    "gn:asciiname":"Dag",
    "gn:country_code":"PK",
    "gn:dem":607,
    "gn:feature_class":"P",
    "gn:feature_code":"PPL",
    "gn:name":"Dag",
    "gn:population":0,
    "gn:timezone":"Asia/Karachi",
    "iso:country":"PK",
    "name:ceb_x_preferred":[
        "Dag"
    ],
    "name:dan_x_preferred":[
        "Dag"
    ],
    "name:fra_x_preferred":[
        "Dag"
    ],
    "name:hun_x_preferred":[
        "DAG"
    ],
    "name:isl_x_preferred":[
        "Dag"
    ],
    "name:lat_x_preferred":[
        "Dag"
    ],
    "name:nld_x_preferred":[
        "Dag"
    ],
    "name:nor_x_preferred":[
        "Dag"
    ],
    "name:pol_x_preferred":[
        "Dag"
    ],
    "name:rus_x_preferred":[
        "\u0414\u0430\u0433"
    ],
    "name:slk_x_preferred":[
        "Dag"
    ],
    "name:srp_x_preferred":[
        "\u0414\u0430\u0433"
    ],
    "name:swe_x_preferred":[
        "Dag"
    ],
    "name:und_x_variant":[
        "D\u0101g B\u0101nda"
    ],
    "wof:name":"Dag",
    "wof:placetype":"locality"
},
  "geometry": {"coordinates":[71.16764999999999,32.37589000000001],"type":"Point"}
}