{
  "type": "Feature",
  "properties": {
    "gn:admin1_code":"2.0",
    "gn:asciiname":"WAPDA Colony",
    "gn:country_code":"PK",
    "gn:dem":13,
    "gn:feature_class":"P",
    "gn:feature_code":"PPL",
    "gn:name":"WAPDA Colony",
    "gn:population":0,
    "gn:timezone":"Asia/Karachi",
    "iso:country":"PK",
    "wof:name":"WAPDA Colony",
    "wof:placetype":"locality"
},
  "geometry": {"coordinates":[62.33751,25.21384],"type":"Point"}
}