{
  "type": "Feature",
  "properties": {
    "gn:admin1_code":"2",
    "gn:asciiname":"Mulla Dahya",
    "gn:country_code":"PK",
    "gn:dem":2108,
    "gn:feature_class":"P",
    "gn:feature_code":"PPL",
    "gn:name":"Mulla Dahya",
    "gn:population":0,
    "gn:timezone":"Asia/Karachi",
    "iso:country":"PK",
    "name:eng_x_preferred":[
        "Mulla Dahya"
    ],
    "wof:name":"Mulla Dahya",
    "wof:placetype":"locality"
},
  "geometry": {"coordinates":[67.35279,30.75857],"type":"Point"}
}