{
  "type": "Feature",
  "properties": {
    "gn:admin1_code":"4.0",
    "gn:asciiname":"Balar",
    "gn:country_code":"PK",
    "gn:dem":137,
    "gn:feature_class":"P",
    "gn:feature_code":"PPL",
    "gn:name":"Balar",
    "gn:population":0,
    "gn:timezone":"Asia/Karachi",
    "iso:country":"PK",
    "name:ceb_x_preferred":[
        "Balar"
    ],
    "name:nld_x_preferred":[
        "Balar"
    ],
    "name:pol_x_preferred":[
        "Balar"
    ],
    "name:swe_x_preferred":[
        "Balar"
    ],
    "wof:name":"Balar",
    "wof:placetype":"locality"
},
  "geometry": {"coordinates":[71.68997,30.75613],"type":"Point"}
}