{
  "type": "Feature",
  "properties": {
    "gn:admin1_code":"03",
    "gn:asciiname":"Jangi Khan",
    "gn:country_code":"PK",
    "gn:dem":288,
    "gn:feature_class":"P",
    "gn:feature_code":"PPL",
    "gn:name":"Jangi Khan",
    "gn:population":0,
    "gn:timezone":"Asia/Karachi",
    "iso:country":"PK",
    "wof:name":"Jangi Khan",
    "wof:placetype":"locality"
},
  "geometry": {"coordinates":[70.71611,32.72873],"type":"Point"}
}