{
  "type": "Feature",
  "properties": {
    "gn:admin1_code":"4.0",
    "gn:asciiname":"Liani",
    "gn:country_code":"PK",
    "gn:dem":642,
    "gn:feature_class":"P",
    "gn:feature_code":"PPL",
    "gn:name":"Liani",
    "gn:population":0,
    "gn:timezone":"Asia/Karachi",
    "iso:country":"PK",
    "wof:name":"Liani",
    "wof:placetype":"locality"
},
  "geometry": {"coordinates":[72.523,32.75585],"type":"Point"}
}