{
  "type": "Feature",
  "properties": {
    "gn:admin1_code":"4",
    "gn:asciiname":"Warhi Charagh Khel",
    "gn:country_code":"PK",
    "gn:dem":186,
    "gn:feature_class":"P",
    "gn:feature_code":"PPL",
    "gn:name":"Warhi Charagh Khel",
    "gn:population":0,
    "gn:timezone":"Asia/Karachi",
    "iso:country":"PK",
    "name:und_x_variant":[
        "Char\u0101ghw\u0101li Warhi"
    ],
    "wof:name":"Warhi Charagh Khel",
    "wof:placetype":"locality"
},
  "geometry": {"coordinates":[71.81116,32.03972],"type":"Point"}
}