{
  "type": "Feature",
  "properties": {
    "gn:admin1_code":"4.0",
    "gn:asciiname":"Nilagh",
    "gn:country_code":"PK",
    "gn:dem":827,
    "gn:feature_class":"P",
    "gn:feature_code":"PPL",
    "gn:name":"Nilagh",
    "gn:population":0,
    "gn:timezone":"Asia/Karachi",
    "iso:country":"PK",
    "wof:name":"Nilagh",
    "wof:placetype":"locality"
},
  "geometry": {"coordinates":[70.35271,30.83768],"type":"Point"}
}