{
  "type": "Feature",
  "properties": {
    "gn:admin1_code":"4.0",
    "gn:asciiname":"Bhubber",
    "gn:country_code":"PK",
    "gn:dem":502,
    "gn:feature_class":"P",
    "gn:feature_code":"PPL",
    "gn:name":"Bhubber",
    "gn:population":0,
    "gn:timezone":"Asia/Karachi",
    "iso:country":"PK",
    "name:und_x_variant":[
        "Bhobhar",
        "Bh\u016bbar",
        "Bhubber"
    ],
    "wof:name":"Bhubber",
    "wof:placetype":"locality"
},
  "geometry": {"coordinates":[73.1155,33.00762],"type":"Point"}
}