{
  "type": "Feature",
  "properties": {
    "gn:admin1_code":"4",
    "gn:asciiname":"Jalanwala",
    "gn:country_code":"PK",
    "gn:dem":169,
    "gn:feature_class":"P",
    "gn:feature_code":"PPL",
    "gn:name":"Jalanwala",
    "gn:population":0,
    "gn:timezone":"Asia/Karachi",
    "iso:country":"PK",
    "name:und_x_variant":[
        "Millanw\u0101la",
        "Jelanw\u0101la",
        "Jalanwala"
    ],
    "wof:name":"Jalanwala",
    "wof:placetype":"locality"
},
  "geometry": {"coordinates":[71.15094999999999,31.56308],"type":"Point"}
}