{
  "type": "Feature",
  "properties": {
    "gn:admin1_code":"6",
    "gn:asciiname":"Jabba",
    "gn:country_code":"PK",
    "gn:dem":652,
    "gn:feature_class":"P",
    "gn:feature_code":"PPL",
    "gn:name":"Jabba",
    "gn:population":0,
    "gn:timezone":"Asia/Karachi",
    "iso:country":"PK",
    "name:ceb_x_preferred":[
        "Jabba"
    ],
    "name:und_x_variant":[
        "Jar\u0101i"
    ],
    "wof:name":"Jabba",
    "wof:placetype":"locality"
},
  "geometry": {"coordinates":[73.81349,33.55747],"type":"Point"}
}