{
  "type": "Feature",
  "properties": {
    "gn:admin1_code":"04",
    "gn:asciiname":"Thatti Syed Bahram",
    "gn:country_code":"PK",
    "gn:dem":160,
    "gn:feature_class":"P",
    "gn:feature_code":"PPL",
    "gn:name":"Thatti Syed Bahram",
    "gn:population":0,
    "gn:timezone":"Asia/Karachi",
    "iso:country":"PK",
    "name:und_x_variant":[
        "Thatti Said Brahim",
        "Thatti Syed Bahram",
        "Thatti Saiyid Bir\u0101him"
    ],
    "wof:name":"Thatti Syed Bahram",
    "wof:placetype":"locality"
},
  "geometry": {"coordinates":[72.22605,31.51414],"type":"Point"}
}