{
  "type": "Feature",
  "properties": {
    "gn:admin1_code":"4.0",
    "gn:asciiname":"Ganwin Kotni",
    "gn:country_code":"PK",
    "gn:dem":111,
    "gn:feature_class":"P",
    "gn:feature_code":"PPL",
    "gn:name":"Ganwin Kotni",
    "gn:population":0,
    "gn:timezone":"Asia/Karachi",
    "iso:country":"PK",
    "name:und_x_variant":[
        "Gaw\u0101n Kothi"
    ],
    "wof:name":"Ganwin Kotni",
    "wof:placetype":"locality"
},
  "geometry": {"coordinates":[71.26555,29.70175],"type":"Point"}
}