{
  "type": "Feature",
  "properties": {
    "gn:admin1_code":"2.0",
    "gn:asciiname":"Soradar",
    "gn:country_code":"PK",
    "gn:dem":744,
    "gn:feature_class":"P",
    "gn:feature_code":"PPL",
    "gn:name":"Soradar",
    "gn:population":0,
    "gn:timezone":"Asia/Karachi",
    "iso:country":"PK",
    "wof:name":"Soradar",
    "wof:placetype":"locality"
},
  "geometry": {"coordinates":[67.07115999999999,27.36086],"type":"Point"}
}