{
  "type": "Feature",
  "properties": {
    "gn:admin1_code":"05",
    "gn:asciiname":"Goth Jam Bijar Khan",
    "gn:country_code":"PK",
    "gn:dem":7,
    "gn:feature_class":"P",
    "gn:feature_code":"PPL",
    "gn:name":"Goth Jam Bijar Khan",
    "gn:population":0,
    "gn:timezone":"Asia/Karachi",
    "iso:country":"PK",
    "name:und_x_variant":[
        "J\u0101g\u012br"
    ],
    "wof:name":"Goth Jam Bijar Khan",
    "wof:placetype":"locality"
},
  "geometry": {"coordinates":[67.77105,24.46991],"type":"Point"}
}