{
  "type": "Feature",
  "properties": {
    "gn:admin1_code":"2.0",
    "gn:asciiname":"Khor",
    "gn:country_code":"PK",
    "gn:dem":56,
    "gn:feature_class":"P",
    "gn:feature_code":"PPL",
    "gn:name":"Khor",
    "gn:population":0,
    "gn:timezone":"Asia/Karachi",
    "iso:country":"PK",
    "name:und_x_variant":[
        "Khatoor",
        "Kathur",
        "Khor"
    ],
    "wof:name":"Khor",
    "wof:placetype":"locality"
},
  "geometry": {"coordinates":[67.83471999999999,28.32748],"type":"Point"}
}