{
  "type": "Feature",
  "properties": {
    "gn:admin1_code":"6.0",
    "gn:asciiname":"Jhanda Maira",
    "gn:country_code":"PK",
    "gn:dem":472,
    "gn:feature_class":"P",
    "gn:feature_code":"PPL",
    "gn:name":"Jhanda Maira",
    "gn:population":0,
    "gn:timezone":"Asia/Karachi",
    "iso:country":"PK",
    "name:und_x_variant":[
        "Jhando Maira"
    ],
    "wof:name":"Jhanda Maira",
    "wof:placetype":"locality"
},
  "geometry": {"coordinates":[73.5078,33.209],"type":"Point"}
}