{
  "type": "Feature",
  "properties": {
    "gn:admin1_code":"3.0",
    "gn:asciiname":"Palasho Bhek",
    "gn:country_code":"PK",
    "gn:dem":2205,
    "gn:feature_class":"P",
    "gn:feature_code":"PPL",
    "gn:name":"Palasho Bhek",
    "gn:population":0,
    "gn:timezone":"Asia/Karachi",
    "iso:country":"PK",
    "wof:name":"Palasho Bhek",
    "wof:placetype":"locality"
},
  "geometry": {"coordinates":[72.97219,35.44544000000001],"type":"Point"}
}