{
  "type": "Feature",
  "properties": {
    "gn:admin1_code":"1.0",
    "gn:asciiname":"Tangai",
    "gn:country_code":"PK",
    "gn:dem":568,
    "gn:feature_class":"P",
    "gn:feature_code":"PPL",
    "gn:name":"Tangai",
    "gn:population":0,
    "gn:timezone":"Asia/Karachi",
    "iso:country":"PK",
    "wof:name":"Tangai",
    "wof:placetype":"locality"
},
  "geometry": {"coordinates":[70.57680000000001,33.1611],"type":"Point"}
}