{
  "type": "Feature",
  "properties": {
    "gn:admin1_code":"4",
    "gn:asciiname":"Chak One Hundred Eighty-eight Gugera Branch",
    "gn:country_code":"PK",
    "gn:dem":160,
    "gn:feature_class":"P",
    "gn:feature_code":"PPL",
    "gn:name":"Chak One Hundred Eighty-eight Gugera Branch",
    "gn:population":0,
    "gn:timezone":"Asia/Karachi",
    "iso:country":"PK",
    "name:und_x_variant":[
        "Chak One Hundred Eighty-Eight GB",
        "Jhok Sh\u0101kar",
        "Khurd",
        "Chak One Hundred Eighty-eight Gugera Branch"
    ],
    "wof:name":"Chak One Hundred Eighty-eight Gugera Branch",
    "wof:placetype":"locality"
},
  "geometry": {"coordinates":[72.66825,30.77007],"type":"Point"}
}