{
  "type": "Feature",
  "properties": {
    "gn:admin1_code":"6",
    "gn:asciiname":"Mikol",
    "gn:country_code":"PK",
    "gn:dem":2123,
    "gn:feature_class":"P",
    "gn:feature_code":"PPL",
    "gn:name":"Mikol",
    "gn:population":0,
    "gn:timezone":"Asia/Karachi",
    "iso:country":"PK",
    "name:und_x_variant":[
        "Mi Kol"
    ],
    "wof:name":"Mikol",
    "wof:placetype":"locality"
},
  "geometry": {"coordinates":[73.91419,34.29894],"type":"Point"}
}