{
  "type": "Feature",
  "properties": {
    "gn:admin1_code":"5.0",
    "gn:asciiname":"Goth Basiro",
    "gn:country_code":"PK",
    "gn:dem":45,
    "gn:feature_class":"P",
    "gn:feature_code":"PPL",
    "gn:name":"Goth Basiro",
    "gn:population":0,
    "gn:timezone":"Asia/Karachi",
    "iso:country":"PK",
    "name:und_x_variant":[
        "Basiro",
        "Bas\u012bra",
        "Goth Basiro",
        "Goth Bas\u012bro"
    ],
    "wof:name":"Goth Basiro",
    "wof:placetype":"locality"
},
  "geometry": {"coordinates":[68.50833,26.85228],"type":"Point"}
}