{
  "type": "Feature",
  "properties": {
    "gn:admin1_code":"5",
    "gn:asciiname":"Kalri",
    "gn:country_code":"PK",
    "gn:dem":45,
    "gn:feature_class":"P",
    "gn:feature_code":"PPL",
    "gn:name":"Kalri",
    "gn:population":0,
    "gn:timezone":"Asia/Karachi",
    "iso:country":"PK",
    "wof:name":"Kalri",
    "wof:placetype":"locality"
},
  "geometry": {"coordinates":[67.87855999999999,26.94204],"type":"Point"}
}