{
  "type": "Feature",
  "properties": {
    "gn:admin1_code":"5.0",
    "gn:asciiname":"Farid Mazari",
    "gn:country_code":"PK",
    "gn:dem":76,
    "gn:feature_class":"P",
    "gn:feature_code":"PPL",
    "gn:name":"Farid Mazari",
    "gn:population":0,
    "gn:timezone":"Asia/Karachi",
    "iso:country":"PK",
    "wof:name":"Farid Mazari",
    "wof:placetype":"locality"
},
  "geometry": {"coordinates":[69.56856999999999,28.47839],"type":"Point"}
}