{
  "type": "Feature",
  "properties": {
    "gn:admin1_code":"7.0",
    "gn:asciiname":"Tirsit",
    "gn:country_code":"PK",
    "gn:dem":2550,
    "gn:feature_class":"P",
    "gn:feature_code":"PPL",
    "gn:name":"Tirsit",
    "gn:population":0,
    "gn:timezone":"Asia/Karachi",
    "iso:country":"PK",
    "wof:name":"Tirsit",
    "wof:placetype":"locality"
},
  "geometry": {"coordinates":[73.42917,36.54321],"type":"Point"}
}