{
  "type": "Feature",
  "properties": {
    "gn:admin1_code":"4",
    "gn:asciiname":"Chak One Hundred Twenty - Eastern Bar",
    "gn:country_code":"PK",
    "gn:dem":149,
    "gn:feature_class":"P",
    "gn:feature_code":"PPL",
    "gn:name":"Chak One Hundred Twenty - Eastern Bar",
    "gn:population":0,
    "gn:timezone":"Asia/Karachi",
    "iso:country":"PK",
    "name:und_x_variant":[
        "Chak One Hundred Twenty EB"
    ],
    "wof:name":"Chak One Hundred Twenty - Eastern Bar",
    "wof:placetype":"locality"
},
  "geometry": {"coordinates":[72.64116999999997,30.29422000000001],"type":"Point"}
}