{
  "type": "Feature",
  "properties": {
    "gn:admin1_code":"3.0",
    "gn:asciiname":"Tarnawa",
    "gn:country_code":"PK",
    "gn:dem":533,
    "gn:feature_class":"P",
    "gn:feature_code":"PPL",
    "gn:name":"Tarnawa",
    "gn:population":0,
    "gn:timezone":"Asia/Karachi",
    "iso:country":"PK",
    "wof:name":"Tarnawa",
    "wof:placetype":"locality"
},
  "geometry": {"coordinates":[72.89957,33.78841],"type":"Point"}
}