{
  "type": "Feature",
  "properties": {
    "gn:admin1_code":"2.0",
    "gn:asciiname":"Sardar Khuda Bakhsh",
    "gn:country_code":"PK",
    "gn:dem":1153,
    "gn:feature_class":"P",
    "gn:feature_code":"PPL",
    "gn:name":"Sardar Khuda Bakhsh",
    "gn:population":0,
    "gn:timezone":"Asia/Karachi",
    "iso:country":"PK",
    "wof:name":"Sardar Khuda Bakhsh",
    "wof:placetype":"locality"
},
  "geometry": {"coordinates":[64.36187,29.26132],"type":"Point"}
}