{
  "type": "Feature",
  "properties": {
    "gn:admin1_code":"3",
    "gn:asciiname":"Pulai",
    "gn:country_code":"PK",
    "gn:dem":1417,
    "gn:feature_class":"P",
    "gn:feature_code":"PPL",
    "gn:name":"Pulai",
    "gn:population":0,
    "gn:timezone":"Asia/Karachi",
    "iso:country":"PK",
    "name:eng_x_preferred":[
        "Pulai"
    ],
    "wof:name":"Pulai",
    "wof:placetype":"locality"
},
  "geometry": {"coordinates":[71.80525,35.01538],"type":"Point"}
}