{
  "type": "Feature",
  "properties": {
    "gn:admin1_code":"1.0",
    "gn:asciiname":"Lora Garhi",
    "gn:country_code":"PK",
    "gn:dem":1648,
    "gn:feature_class":"P",
    "gn:feature_code":"PPL",
    "gn:name":"Lora Garhi",
    "gn:population":0,
    "gn:timezone":"Asia/Karachi",
    "iso:country":"PK",
    "wof:name":"Lora Garhi",
    "wof:placetype":"locality"
},
  "geometry": {"coordinates":[70.81811,33.68],"type":"Point"}
}