{
  "type": "Feature",
  "properties": {
    "gn:admin1_code":"6",
    "gn:asciiname":"Jabban",
    "gn:country_code":"PK",
    "gn:dem":1244,
    "gn:feature_class":"P",
    "gn:feature_code":"PPL",
    "gn:name":"Jabban",
    "gn:population":0,
    "gn:timezone":"Asia/Karachi",
    "iso:country":"PK",
    "name:und_x_variant":[
        "Tatre\u0101l"
    ],
    "wof:name":"Jabban",
    "wof:placetype":"locality"
},
  "geometry": {"coordinates":[73.6335,34.42813],"type":"Point"}
}