{
  "type": "Feature",
  "properties": {
    "gn:admin1_code":"2.0",
    "gn:asciiname":"Goth Mir Haidar Khan",
    "gn:country_code":"PK",
    "gn:dem":64,
    "gn:feature_class":"P",
    "gn:feature_code":"PPL",
    "gn:name":"Goth Mir Haidar Khan",
    "gn:population":0,
    "gn:timezone":"Asia/Karachi",
    "iso:country":"PK",
    "wof:name":"Goth Mir Haidar Khan",
    "wof:placetype":"locality"
},
  "geometry": {"coordinates":[68.28206,28.55811],"type":"Point"}
}