{
  "type": "Feature",
  "properties": {
    "gn:admin1_code":"6.0",
    "gn:asciiname":"Bharuz Baihk",
    "gn:country_code":"PK",
    "gn:dem":2538,
    "gn:feature_class":"P",
    "gn:feature_code":"PPL",
    "gn:name":"Bharuz Baihk",
    "gn:population":0,
    "gn:timezone":"Asia/Karachi",
    "iso:country":"PK",
    "wof:name":"Bharuz Baihk",
    "wof:placetype":"locality"
},
  "geometry": {"coordinates":[73.80577,34.52196],"type":"Point"}
}