{
  "type": "Feature",
  "properties": {
    "gn:admin1_code":"4",
    "gn:asciiname":"Hathia Dhamial",
    "gn:country_code":"PK",
    "gn:dem":430,
    "gn:feature_class":"P",
    "gn:feature_code":"PPL",
    "gn:name":"Hathia Dhamial",
    "gn:population":0,
    "gn:timezone":"Asia/Karachi",
    "iso:country":"PK",
    "name:und_x_variant":[
        "Dhok Dhami\u0101l"
    ],
    "wof:name":"Hathia Dhamial",
    "wof:placetype":"locality"
},
  "geometry": {"coordinates":[73.44439,33.20997],"type":"Point"}
}