{
  "type": "Feature",
  "properties": {
    "gn:admin1_code":"4",
    "gn:asciiname":"Dhul Faqir Bakhsh",
    "gn:country_code":"PK",
    "gn:dem":178,
    "gn:feature_class":"P",
    "gn:feature_code":"PPL",
    "gn:name":"Dhul Faqir Bakhsh",
    "gn:population":0,
    "gn:timezone":"Asia/Karachi",
    "iso:country":"PK",
    "wof:name":"Dhul Faqir Bakhsh",
    "wof:placetype":"locality"
},
  "geometry": {"coordinates":[73.81395999999999,30.55453],"type":"Point"}
}