{
  "type": "Feature",
  "properties": {
    "gn:admin1_code":"4",
    "gn:asciiname":"Kot Asa Singh",
    "gn:country_code":"PK",
    "gn:dem":191,
    "gn:feature_class":"P",
    "gn:feature_code":"PPL",
    "gn:name":"Kot Asa Singh",
    "gn:population":0,
    "gn:timezone":"Asia/Karachi",
    "iso:country":"PK",
    "name:und_x_variant":[
        "Kot L\u0101bh Singh"
    ],
    "wof:name":"Kot Asa Singh",
    "wof:placetype":"locality"
},
  "geometry": {"coordinates":[73.89664999999999,30.95789000000001],"type":"Point"}
}