{
  "type": "Feature",
  "properties": {
    "gn:admin1_code":"4",
    "gn:asciiname":"Kotli Shaikhan",
    "gn:country_code":"PK",
    "gn:dem":208,
    "gn:feature_class":"P",
    "gn:feature_code":"PPL",
    "gn:name":"Kotli Shaikhan",
    "gn:population":0,
    "gn:timezone":"Asia/Karachi",
    "iso:country":"PK",
    "wof:name":"Kotli Shaikhan",
    "wof:placetype":"neighbourhood"
},
  "geometry": {"coordinates":[73.20462999999999,32.55593],"type":"Point"}
}