{
  "type": "Feature",
  "properties": {
    "gn:admin1_code":"2.0",
    "gn:asciiname":"Nawe Viala",
    "gn:country_code":"PK",
    "gn:dem":1364,
    "gn:feature_class":"P",
    "gn:feature_code":"PPL",
    "gn:name":"Nawe Viala",
    "gn:population":0,
    "gn:timezone":"Asia/Karachi",
    "iso:country":"PK",
    "wof:name":"Nawe Viala",
    "wof:placetype":"locality"
},
  "geometry": {"coordinates":[68.68346,30.34061],"type":"Point"}
}