{
  "type": "Feature",
  "properties": {
    "gn:admin1_code":"4.0",
    "gn:asciiname":"Said di Wasun",
    "gn:country_code":"PK",
    "gn:dem":194,
    "gn:feature_class":"P",
    "gn:feature_code":"PPL",
    "gn:name":"Said di Wasun",
    "gn:population":0,
    "gn:timezone":"Asia/Karachi",
    "iso:country":"PK",
    "name:und_x_variant":[
        "Said di Was\u016b Khurd"
    ],
    "wof:name":"Said di Wasun",
    "wof:placetype":"locality"
},
  "geometry": {"coordinates":[73.29963000000002,31.79112000000001],"type":"Point"}
}