{
  "type": "Feature",
  "properties": {
    "gn:admin1_code":"4.0",
    "gn:asciiname":"Ghafurabad",
    "gn:country_code":"PK",
    "gn:dem":183,
    "gn:feature_class":"P",
    "gn:feature_code":"PPL",
    "gn:name":"Ghafurabad",
    "gn:population":0,
    "gn:timezone":"Asia/Karachi",
    "iso:country":"PK",
    "name:und_x_variant":[
        "Chak Muhammad Kh\u0101n"
    ],
    "wof:name":"Ghafurabad",
    "wof:placetype":"locality"
},
  "geometry": {"coordinates":[72.40130000000001,32.31258],"type":"Point"}
}