{
  "type": "Feature",
  "properties": {
    "gn:admin1_code":"3.0",
    "gn:asciiname":"Kahughurt",
    "gn:country_code":"PK",
    "gn:dem":3687,
    "gn:feature_class":"P",
    "gn:feature_code":"PPL",
    "gn:name":"Kahughurt",
    "gn:population":0,
    "gn:timezone":"Asia/Karachi",
    "iso:country":"PK",
    "wof:name":"Kahughurt",
    "wof:placetype":"locality"
},
  "geometry": {"coordinates":[71.52717,36.16147],"type":"Point"}
}