{
  "type": "Feature",
  "properties": {
    "gn:admin1_code":"2.0",
    "gn:asciiname":"Kili Ghabaizai",
    "gn:country_code":"PK",
    "gn:dem":1496,
    "gn:feature_class":"P",
    "gn:feature_code":"PPL",
    "gn:name":"Kili Ghabaizai",
    "gn:population":0,
    "gn:timezone":"Asia/Karachi",
    "iso:country":"PK",
    "wof:name":"Kili Ghabaizai",
    "wof:placetype":"locality"
},
  "geometry": {"coordinates":[66.63491999999999,30.66111],"type":"Point"}
}