{
  "type": "Feature",
  "properties": {
    "gn:admin1_code":"1.0",
    "gn:asciiname":"Cwara Punga",
    "gn:country_code":"PK",
    "gn:dem":2464,
    "gn:feature_class":"P",
    "gn:feature_code":"PPL",
    "gn:name":"Cwara Punga",
    "gn:population":0,
    "gn:timezone":"Asia/Karachi",
    "iso:country":"PK",
    "wof:name":"Cwara Punga",
    "wof:placetype":"locality"
},
  "geometry": {"coordinates":[69.66428000000001,32.67094],"type":"Point"}
}