{
  "type": "Feature",
  "properties": {
    "gn:admin1_code":"6",
    "gn:asciiname":"Katha Gujran",
    "gn:country_code":"PK",
    "gn:dem":1654,
    "gn:feature_class":"P",
    "gn:feature_code":"PPL",
    "gn:name":"Katha Gujran",
    "gn:population":0,
    "gn:timezone":"Asia/Karachi",
    "iso:country":"PK",
    "name:und_x_variant":[
        "Katha"
    ],
    "wof:name":"Katha Gujran",
    "wof:placetype":"locality"
},
  "geometry": {"coordinates":[73.61060000000001,34.28655],"type":"Point"}
}