{
  "type": "Feature",
  "properties": {
    "gn:admin1_code":"3.0",
    "gn:asciiname":"Ujarian",
    "gn:country_code":"PK",
    "gn:dem":1050,
    "gn:feature_class":"P",
    "gn:feature_code":"PPL",
    "gn:name":"Ujarian",
    "gn:population":0,
    "gn:timezone":"Asia/Karachi",
    "iso:country":"PK",
    "wof:name":"Ujarian",
    "wof:placetype":"locality"
},
  "geometry": {"coordinates":[73.27252,34.37325],"type":"Point"}
}