{
  "type": "Feature",
  "properties": {
    "gn:admin1_code":"04",
    "gn:asciiname":"Makkal",
    "gn:country_code":"PK",
    "gn:dem":130,
    "gn:feature_class":"P",
    "gn:feature_code":"PPL",
    "gn:name":"Makkal",
    "gn:population":0,
    "gn:timezone":"Asia/Karachi",
    "iso:country":"PK",
    "name:mal_x_preferred":[
        "\u0d2e\u0d15\u0d4d\u0d15\u0d7e"
    ],
    "wof:name":"Makkal",
    "wof:placetype":"locality"
},
  "geometry": {"coordinates":[72.10039999999999,29.68587],"type":"Point"}
}