{
  "type": "Feature",
  "properties": {
    "gn:admin1_code":"3.0",
    "gn:asciiname":"Jatku",
    "gn:country_code":"PK",
    "gn:dem":1676,
    "gn:feature_class":"P",
    "gn:feature_code":"PPL",
    "gn:name":"Jatku",
    "gn:population":0,
    "gn:timezone":"Asia/Karachi",
    "iso:country":"PK",
    "name:eng_x_preferred":[
        "Jatk\u016bl"
    ],
    "wof:name":"Jatku",
    "wof:placetype":"locality"
},
  "geometry": {"coordinates":[71.96189,35.24139],"type":"Point"}
}