{
  "type": "Feature",
  "properties": {
    "gn:admin1_code":"3.0",
    "gn:asciiname":"Gatta",
    "gn:country_code":"PK",
    "gn:dem":764,
    "gn:feature_class":"P",
    "gn:feature_code":"PPL",
    "gn:name":"Gatta",
    "gn:population":0,
    "gn:timezone":"Asia/Karachi",
    "iso:country":"PK",
    "wof:name":"Gatta",
    "wof:placetype":"locality"
},
  "geometry": {"coordinates":[72.58145999999998,34.5077],"type":"Point"}
}