{
  "type": "Feature",
  "properties": {
    "gn:admin1_code":"1.0",
    "gn:asciiname":"Ali Zai",
    "gn:country_code":"PK",
    "gn:dem":2158,
    "gn:feature_class":"P",
    "gn:feature_code":"PPL",
    "gn:name":"Ali Zai",
    "gn:population":0,
    "gn:timezone":"Asia/Karachi",
    "iso:country":"PK",
    "name:und_x_variant":[
        "Al\u012bzai"
    ],
    "wof:name":"Ali Zai",
    "wof:placetype":"locality"
},
  "geometry": {"coordinates":[69.94396,33.95376],"type":"Point"}
}