{
  "type": "Feature",
  "properties": {
    "gn:admin1_code":"03",
    "gn:asciiname":"Kuz Banda",
    "gn:country_code":"PK",
    "gn:dem":1275,
    "gn:feature_class":"P",
    "gn:feature_code":"PPL",
    "gn:name":"Kuz Banda",
    "gn:population":0,
    "gn:timezone":"Asia/Karachi",
    "iso:country":"PK",
    "wof:name":"Kuz Banda",
    "wof:placetype":"locality"
},
  "geometry": {"coordinates":[71.99721,34.88154],"type":"Point"}
}