{
  "type": "Feature",
  "properties": {
    "gn:admin1_code":"4.0",
    "gn:asciiname":"Vairowali",
    "gn:country_code":"PK",
    "gn:dem":262,
    "gn:feature_class":"P",
    "gn:feature_code":"PPL",
    "gn:name":"Vairowali",
    "gn:population":0,
    "gn:timezone":"Asia/Karachi",
    "iso:country":"PK",
    "wof:name":"Vairowali",
    "wof:placetype":"locality"
},
  "geometry": {"coordinates":[75.10086,32.24466],"type":"Point"}
}