{
  "type": "Feature",
  "properties": {
    "gn:admin1_code":"5",
    "gn:asciiname":"Goth Habibullah Sand",
    "gn:country_code":"PK",
    "gn:dem":12,
    "gn:feature_class":"P",
    "gn:feature_code":"PPL",
    "gn:name":"Goth Habibullah Sand",
    "gn:population":0,
    "gn:timezone":"Asia/Karachi",
    "iso:country":"PK",
    "name:und_x_variant":[
        "Hab\u012bbull\u0101h S\u0101nd"
    ],
    "wof:name":"Goth Habibullah Sand",
    "wof:placetype":"locality"
},
  "geometry": {"coordinates":[69.60880999999999,25.40904],"type":"Point"}
}