{
  "type": "Feature",
  "properties": {
    "gn:admin1_code":"7.0",
    "gn:asciiname":"Zangi Basti",
    "gn:country_code":"PK",
    "gn:dem":3605,
    "gn:feature_class":"P",
    "gn:feature_code":"PPL",
    "gn:name":"Zangi Basti",
    "gn:population":0,
    "gn:timezone":"Asia/Karachi",
    "iso:country":"PK",
    "wof:name":"Zangi Basti",
    "wof:placetype":"locality"
},
  "geometry": {"coordinates":[74.13123,35.1619],"type":"Point"}
}