{
  "type": "Feature",
  "properties": {
    "gn:admin1_code":"4",
    "gn:asciiname":"Tibbi Butha Gharbi",
    "gn:country_code":"PK",
    "gn:dem":121,
    "gn:feature_class":"P",
    "gn:feature_code":"PPL",
    "gn:name":"Tibbi Butha Gharbi",
    "gn:population":0,
    "gn:timezone":"Asia/Karachi",
    "iso:country":"PK",
    "name:eng_x_preferred":[
        "Tibbi Borh Gharbi"
    ],
    "wof:name":"Tibbi Butha Gharbi",
    "wof:placetype":"locality"
},
  "geometry": {"coordinates":[70.9923,30.11297],"type":"Point"}
}