{
  "type": "Feature",
  "properties": {
    "gn:admin1_code":"3",
    "gn:asciiname":"Lur",
    "gn:country_code":"PK",
    "gn:dem":1508,
    "gn:feature_class":"P",
    "gn:feature_code":"PPL",
    "gn:name":"Lur",
    "gn:population":0,
    "gn:timezone":"Asia/Karachi",
    "iso:country":"PK",
    "name:dan_x_preferred":[
        "Lur"
    ],
    "name:deu_x_preferred":[
        "Lure"
    ],
    "name:fin_x_preferred":[
        "Lur"
    ],
    "name:fra_x_preferred":[
        "Lur"
    ],
    "name:hun_x_preferred":[
        "Lur"
    ],
    "name:ind_x_preferred":[
        "Lur"
    ],
    "name:nld_x_preferred":[
        "Lure"
    ],
    "name:nno_x_preferred":[
        "Lur"
    ],
    "name:nor_x_preferred":[
        "Lur"
    ],
    "name:pol_x_preferred":[
        "Lura"
    ],
    "name:rus_x_preferred":[
        "\u041b\u0443\u0440"
    ],
    "name:spa_x_preferred":[
        "Lur"
    ],
    "name:swe_x_preferred":[
        "Lur"
    ],
    "name:ukr_x_preferred":[
        "\u041b\u0443\u0440"
    ],
    "name:und_x_variant":[
        "Lahur"
    ],
    "wof:name":"Lur",
    "wof:placetype":"locality"
},
  "geometry": {"coordinates":[73.44435,34.03953],"type":"Point"}
}