{
  "type": "Feature",
  "properties": {
    "gn:admin1_code":"4",
    "gn:asciiname":"Chak One Hundred Six - Eastern Bar",
    "gn:country_code":"PK",
    "gn:dem":149,
    "gn:feature_class":"P",
    "gn:feature_code":"PPL",
    "gn:name":"Chak One Hundred Six - Eastern Bar",
    "gn:population":0,
    "gn:timezone":"Asia/Karachi",
    "iso:country":"PK",
    "name:und_x_variant":[
        "Chak One Hundred Six-Two BR"
    ],
    "wof:name":"Chak One Hundred Six - Eastern Bar",
    "wof:placetype":"locality"
},
  "geometry": {"coordinates":[72.72544000000001,30.30827],"type":"Point"}
}