{
  "type": "Feature",
  "properties": {
    "gn:admin1_code":"2.0",
    "gn:asciiname":"Adamzai",
    "gn:country_code":"PK",
    "gn:dem":1437,
    "gn:feature_class":"P",
    "gn:feature_code":"PPL",
    "gn:name":"Adamzai",
    "gn:population":0,
    "gn:timezone":"Asia/Karachi",
    "iso:country":"PK",
    "name:und_x_variant":[
        "\u0100damzai"
    ],
    "wof:name":"Adamzai",
    "wof:placetype":"locality"
},
  "geometry": {"coordinates":[66.6872,30.48498],"type":"Point"}
}