{
  "type": "Feature",
  "properties": {
    "gn:admin1_code":"2.0",
    "gn:asciiname":"Kacchi Awara",
    "gn:country_code":"PK",
    "gn:dem":1451,
    "gn:feature_class":"P",
    "gn:feature_code":"PPL",
    "gn:name":"Kacchi Awara",
    "gn:population":0,
    "gn:timezone":"Asia/Karachi",
    "iso:country":"PK",
    "wof:name":"Kacchi Awara",
    "wof:placetype":"locality"
},
  "geometry": {"coordinates":[68.56054,30.32853],"type":"Point"}
}