{
  "type": "Feature",
  "properties": {
    "gn:admin1_code":"4",
    "gn:asciiname":"Baghanwala",
    "gn:country_code":"PK",
    "gn:dem":214,
    "gn:feature_class":"P",
    "gn:feature_code":"PPL",
    "gn:name":"Baghanwala",
    "gn:population":0,
    "gn:timezone":"Asia/Karachi",
    "iso:country":"PK",
    "wof:name":"Baghanwala",
    "wof:placetype":"locality"
},
  "geometry": {"coordinates":[73.62703,32.49467],"type":"Point"}
}