{
  "type": "Feature",
  "properties": {
    "gn:admin1_code":"5.0",
    "gn:asciiname":"Lal Muhammad Bhambro",
    "gn:country_code":"PK",
    "gn:dem":52,
    "gn:feature_class":"P",
    "gn:feature_code":"PPL",
    "gn:name":"Lal Muhammad Bhambro",
    "gn:population":0,
    "gn:timezone":"Asia/Karachi",
    "iso:country":"PK",
    "wof:name":"Lal Muhammad Bhambro",
    "wof:placetype":"locality"
},
  "geometry": {"coordinates":[69.02965999999999,27.21832],"type":"Point"}
}