{
  "type": "Feature",
  "properties": {
    "gn:admin1_code":"05",
    "gn:asciiname":"Mahrab Wai",
    "gn:country_code":"PK",
    "gn:dem":37,
    "gn:feature_class":"P",
    "gn:feature_code":"PPL",
    "gn:name":"Mahrab Wai",
    "gn:population":0,
    "gn:timezone":"Asia/Karachi",
    "iso:country":"PK",
    "name:und_x_variant":[
        "Mehrab Wai",
        "Mahrab Wai"
    ],
    "wof:name":"Mahrab Wai",
    "wof:placetype":"locality"
},
  "geometry": {"coordinates":[68.11498,26.3854],"type":"Point"}
}