{
  "type": "Feature",
  "properties": {
    "gn:admin1_code":"04",
    "gn:asciiname":"Sohawi",
    "gn:country_code":"PK",
    "gn:dem":241,
    "gn:feature_class":"P",
    "gn:feature_code":"PPL",
    "gn:name":"Sohawi",
    "gn:population":0,
    "gn:timezone":"Asia/Karachi",
    "iso:country":"PK",
    "name:und_x_variant":[
        "Sohavi",
        "Sohawi"
    ],
    "wof:name":"Sohawi",
    "wof:placetype":"locality"
},
  "geometry": {"coordinates":[74.51228,32.31574000000001],"type":"Point"}
}