{
  "type": "Feature",
  "properties": {
    "gn:admin1_code":"3.0",
    "gn:asciiname":"Durmangi",
    "gn:country_code":"PK",
    "gn:dem":314,
    "gn:feature_class":"P",
    "gn:feature_code":"PPL",
    "gn:name":"Durmangi",
    "gn:population":0,
    "gn:timezone":"Asia/Karachi",
    "iso:country":"PK",
    "wof:name":"Durmangi",
    "wof:placetype":"locality"
},
  "geometry": {"coordinates":[71.5463,34.0476],"type":"Point"}
}