{
  "type": "Feature",
  "properties": {
    "gn:admin1_code":"4.0",
    "gn:asciiname":"Chak Fifty-three-Fifteen Left",
    "gn:country_code":"PK",
    "gn:dem":140,
    "gn:feature_class":"P",
    "gn:feature_code":"PPL",
    "gn:name":"Chak Fifty-three-Fifteen Left",
    "gn:population":0,
    "gn:timezone":"Asia/Karachi",
    "iso:country":"PK",
    "name:und_x_variant":[
        "Bhatti\u0101nw\u0101la"
    ],
    "wof:name":"Chak Fifty-three-Fifteen Left",
    "wof:placetype":"locality"
},
  "geometry": {"coordinates":[72.36998,30.23496],"type":"Point"}
}