{
  "type": "Feature",
  "properties": {
    "gn:admin1_code":"01",
    "gn:asciiname":"Kurezai",
    "gn:country_code":"PK",
    "gn:dem":1421,
    "gn:feature_class":"P",
    "gn:feature_code":"PPL",
    "gn:name":"Kurezai",
    "gn:population":0,
    "gn:timezone":"Asia/Karachi",
    "iso:country":"PK",
    "wof:name":"Kurezai",
    "wof:placetype":"locality"
},
  "geometry": {"coordinates":[69.52509000000001,32.26938],"type":"Point"}
}