{
  "type": "Feature",
  "properties": {
    "gn:admin1_code":"5.0",
    "gn:asciiname":"Goth Haji Pirdino",
    "gn:country_code":"PK",
    "gn:dem":13,
    "gn:feature_class":"P",
    "gn:feature_code":"PPL",
    "gn:name":"Goth Haji Pirdino",
    "gn:population":0,
    "gn:timezone":"Asia/Karachi",
    "iso:country":"PK",
    "name:eng_x_preferred":[
        "Goth Haji Pirdino"
    ],
    "wof:name":"Goth Haji Pirdino",
    "wof:placetype":"locality"
},
  "geometry": {"coordinates":[68.04966999999999,24.71888],"type":"Point"}
}