{
  "type": "Feature",
  "properties": {
    "gn:admin1_code":"5.0",
    "gn:asciiname":"Teju jo Par",
    "gn:country_code":"PK",
    "gn:dem":81,
    "gn:feature_class":"P",
    "gn:feature_code":"PPL",
    "gn:name":"Teju jo Par",
    "gn:population":0,
    "gn:timezone":"Asia/Karachi",
    "iso:country":"PK",
    "wof:name":"Teju jo Par",
    "wof:placetype":"locality"
},
  "geometry": {"coordinates":[70.13967,25.04849],"type":"Point"}
}