{
  "type": "Feature",
  "properties": {
    "gn:admin1_code":"2.0",
    "gn:asciiname":"Landhi Karedak",
    "gn:country_code":"PK",
    "gn:dem":824,
    "gn:feature_class":"P",
    "gn:feature_code":"PPL",
    "gn:name":"Landhi Karedak",
    "gn:population":0,
    "gn:timezone":"Asia/Karachi",
    "iso:country":"PK",
    "name:und_x_variant":[
        "Karodak L\u0101ndi"
    ],
    "wof:name":"Landhi Karedak",
    "wof:placetype":"locality"
},
  "geometry": {"coordinates":[64.70931,28.94571],"type":"Point"}
}