{
  "type": "Feature",
  "properties": {
    "gn:admin1_code":"3.0",
    "gn:asciiname":"Raqib Bela",
    "gn:country_code":"PK",
    "gn:dem":818,
    "gn:feature_class":"P",
    "gn:feature_code":"PPL",
    "gn:name":"Raqib Bela",
    "gn:population":0,
    "gn:timezone":"Asia/Karachi",
    "iso:country":"PK",
    "wof:name":"Raqib Bela",
    "wof:placetype":"locality"
},
  "geometry": {"coordinates":[73.13184,34.36909],"type":"Point"}
}