{
  "type": "Feature",
  "properties": {
    "gn:admin1_code":"6",
    "gn:asciiname":"Kanbi",
    "gn:country_code":"PK",
    "gn:dem":302,
    "gn:feature_class":"P",
    "gn:feature_code":"PPL",
    "gn:name":"Kanbi",
    "gn:population":0,
    "gn:timezone":"Asia/Karachi",
    "iso:country":"PK",
    "name:und_x_variant":[
        "Khambi",
        "Kanbi"
    ],
    "wof:name":"Kanbi",
    "wof:placetype":"locality"
},
  "geometry": {"coordinates":[73.92385,33.03304],"type":"Point"}
}