{
  "type": "Feature",
  "properties": {
    "gn:admin1_code":"3.0",
    "gn:asciiname":"Nasatta Khurd",
    "gn:country_code":"PK",
    "gn:dem":323,
    "gn:feature_class":"P",
    "gn:feature_code":"PPL",
    "gn:name":"Nasatta Khurd",
    "gn:population":0,
    "gn:timezone":"Asia/Karachi",
    "iso:country":"PK",
    "name:eng_x_preferred":[
        "Nisatta B\u0101nda"
    ],
    "wof:name":"Nasatta Khurd",
    "wof:placetype":"locality"
},
  "geometry": {"coordinates":[71.53434,34.10667],"type":"Point"}
}