{
  "type": "Feature",
  "properties": {
    "gn:admin1_code":"2.0",
    "gn:asciiname":"Pittan",
    "gn:country_code":"PK",
    "gn:dem":149,
    "gn:feature_class":"P",
    "gn:feature_code":"PPL",
    "gn:name":"Pittan",
    "gn:population":0,
    "gn:timezone":"Asia/Karachi",
    "iso:country":"PK",
    "wof:name":"Pittan",
    "wof:placetype":"locality"
},
  "geometry": {"coordinates":[62.98766,25.83573],"type":"Point"}
}