{
  "type": "Feature",
  "properties": {
    "gn:admin1_code":"4.0",
    "gn:asciiname":"Naldaf",
    "gn:country_code":"PK",
    "gn:dem":463,
    "gn:feature_class":"P",
    "gn:feature_code":"PPL",
    "gn:name":"Naldaf",
    "gn:population":0,
    "gn:timezone":"Asia/Karachi",
    "iso:country":"PK",
    "name:und_x_variant":[
        "K\u0101ldof"
    ],
    "wof:name":"Naldaf",
    "wof:placetype":"locality"
},
  "geometry": {"coordinates":[70.37324,30.53943],"type":"Point"}
}