{
  "type": "Feature",
  "properties": {
    "gn:admin1_code":"5",
    "gn:asciiname":"Haji Faqir Muhammad",
    "gn:country_code":"PK",
    "gn:dem":52,
    "gn:feature_class":"P",
    "gn:feature_code":"PPL",
    "gn:name":"H\u0101ji Faq\u012br Muhammad",
    "gn:population":0,
    "gn:timezone":"Asia/Karachi",
    "iso:country":"PK",
    "wof:name":"Haji Faqir Muhammad",
    "wof:placetype":"locality"
},
  "geometry": {"coordinates":[68.34999999999999,27.86667000000001],"type":"Point"}
}