{
  "type": "Feature",
  "properties": {
    "gn:admin1_code":"2.0",
    "gn:asciiname":"Goth Sumar",
    "gn:country_code":"PK",
    "gn:dem":12,
    "gn:feature_class":"P",
    "gn:feature_code":"PPL",
    "gn:name":"Goth Sumar",
    "gn:population":0,
    "gn:timezone":"Asia/Karachi",
    "iso:country":"PK",
    "name:und_x_variant":[
        "Goth Lawang",
        "Goth Sumar"
    ],
    "wof:name":"Goth Sumar",
    "wof:placetype":"locality"
},
  "geometry": {"coordinates":[66.20959000000001,25.66554],"type":"Point"}
}