{
  "type": "Feature",
  "properties": {
    "gn:admin1_code":"4.0",
    "gn:asciiname":"Smattha",
    "gn:country_code":"PK",
    "gn:dem":205,
    "gn:feature_class":"P",
    "gn:feature_code":"PPL",
    "gn:name":"Smattha",
    "gn:population":0,
    "gn:timezone":"Asia/Karachi",
    "iso:country":"PK",
    "name:und_x_variant":[
        "Smarttha",
        "Sahotha",
        "Smattha"
    ],
    "wof:name":"Smattha",
    "wof:placetype":"locality"
},
  "geometry": {"coordinates":[73.71295000000001,31.85508],"type":"Point"}
}