{
  "type": "Feature",
  "properties": {
    "gn:admin1_code":"4.0",
    "gn:asciiname":"Chak One Hundred Eleven -Nine Left",
    "gn:country_code":"PK",
    "gn:dem":164,
    "gn:feature_class":"P",
    "gn:feature_code":"PPL",
    "gn:name":"Chak One Hundred Eleven -Nine Left",
    "gn:population":0,
    "gn:timezone":"Asia/Karachi",
    "iso:country":"PK",
    "name:und_x_variant":[
        "Shaduki"
    ],
    "wof:name":"Chak One Hundred Eleven -Nine Left",
    "wof:placetype":"locality"
},
  "geometry": {"coordinates":[73.15380999999999,30.55406],"type":"Point"}
}