{
  "type": "Feature",
  "properties": {
    "gn:admin1_code":"3.0",
    "gn:asciiname":"Sherzad Khel",
    "gn:country_code":"PK",
    "gn:dem":362,
    "gn:feature_class":"P",
    "gn:feature_code":"PPL",
    "gn:name":"Sherzad Khel",
    "gn:population":0,
    "gn:timezone":"Asia/Karachi",
    "iso:country":"PK",
    "name:und_x_variant":[
        "Sherz\u0101d Kh\u0101n",
        "Sherzad Khel"
    ],
    "wof:name":"Sherzad Khel",
    "wof:placetype":"locality"
},
  "geometry": {"coordinates":[70.63197,32.98806],"type":"Point"}
}