{
  "type": "Feature",
  "properties": {
    "gn:admin1_code":"02",
    "gn:asciiname":"Saindak",
    "gn:country_code":"PK",
    "gn:dem":1012,
    "gn:feature_class":"P",
    "gn:feature_code":"PPL",
    "gn:name":"Saindak",
    "gn:population":0,
    "gn:timezone":"Asia/Karachi",
    "iso:country":"PK",
    "name:fas_x_preferred":[
        "\u0633\u06cc\u0646\u062f\u06a9"
    ],
    "name:tur_x_preferred":[
        "Saindak"
    ],
    "name:und_x_variant":[
        "Saindek Tribal Militia Post",
        "Saindak Th\u0101n\u0101"
    ],
    "name:urd_x_preferred":[
        "\u0633\u06cc\u0646\u062f\u06a9"
    ],
    "wof:name":"Saindak",
    "wof:placetype":"locality"
},
  "geometry": {"coordinates":[61.56619,29.27769],"type":"Point"}
}