{
  "type": "Feature",
  "properties": {
    "gn:admin1_code":"4",
    "gn:asciiname":"Lundawala",
    "gn:country_code":"PK",
    "gn:dem":141,
    "gn:feature_class":"P",
    "gn:feature_code":"PPL",
    "gn:name":"Lundawala",
    "gn:population":0,
    "gn:timezone":"Asia/Karachi",
    "iso:country":"PK",
    "name:und_x_variant":[
        "Lud\u0101w\u0101la"
    ],
    "wof:name":"Lundawala",
    "wof:placetype":"locality"
},
  "geometry": {"coordinates":[71.59721999999999,30.74407],"type":"Point"}
}