{
  "type": "Feature",
  "properties": {
    "gn:admin1_code":"4.0",
    "gn:asciiname":"Golianwala",
    "gn:country_code":"PK",
    "gn:dem":208,
    "gn:feature_class":"P",
    "gn:feature_code":"PPL",
    "gn:name":"Golianwala",
    "gn:population":0,
    "gn:timezone":"Asia/Karachi",
    "iso:country":"PK",
    "name:und_x_variant":[
        "B\u012brw\u0101la"
    ],
    "wof:name":"Golianwala",
    "wof:placetype":"locality"
},
  "geometry": {"coordinates":[73.88643,31.75421],"type":"Point"}
}