{
  "type": "Feature",
  "properties": {
    "gn:admin1_code":"6.0",
    "gn:asciiname":"Khari",
    "gn:country_code":"PK",
    "gn:dem":470,
    "gn:feature_class":"P",
    "gn:feature_code":"PPL",
    "gn:name":"Khari",
    "gn:population":0,
    "gn:timezone":"Asia/Karachi",
    "iso:country":"PK",
    "name:ceb_x_preferred":[
        "Khari"
    ],
    "name:deu_x_preferred":[
        "Khari"
    ],
    "name:msa_x_preferred":[
        "Khari"
    ],
    "name:new_x_preferred":[
        "\u0916\u0930\u0940"
    ],
    "name:pol_x_preferred":[
        "Khari"
    ],
    "wof:name":"Khari",
    "wof:placetype":"locality"
},
  "geometry": {"coordinates":[73.64926,33.56562],"type":"Point"}
}