{
  "type": "Feature",
  "properties": {
    "gn:admin1_code":"2.0",
    "gn:asciiname":"Goth Tota Khan",
    "gn:country_code":"PK",
    "gn:dem":59,
    "gn:feature_class":"P",
    "gn:feature_code":"PPL",
    "gn:name":"Goth Tota Khan",
    "gn:population":0,
    "gn:timezone":"Asia/Karachi",
    "iso:country":"PK",
    "name:und_x_variant":[
        "Goth Tote Kh\u0101n"
    ],
    "wof:name":"Goth Tota Khan",
    "wof:placetype":"locality"
},
  "geometry": {"coordinates":[68.08004,28.2757],"type":"Point"}
}