{
  "type": "Feature",
  "properties": {
    "gn:admin1_code":"4",
    "gn:asciiname":"Basti Lashari",
    "gn:country_code":"PK",
    "gn:dem":99,
    "gn:feature_class":"P",
    "gn:feature_code":"PPL",
    "gn:name":"Basti Lashari",
    "gn:population":0,
    "gn:timezone":"Asia/Karachi",
    "iso:country":"PK",
    "name:und_x_variant":[
        "Mad Muhammad Shaffiw\u0101la",
        "Basti Mithu Kh\u0101n"
    ],
    "wof:name":"Basti Lashari",
    "wof:placetype":"locality"
},
  "geometry": {"coordinates":[70.26685999999999,29.22017],"type":"Point"}
}