{
  "type": "Feature",
  "properties": {
    "gn:admin1_code":"1.0",
    "gn:asciiname":"Mashir Khel",
    "gn:country_code":"PK",
    "gn:dem":459,
    "gn:feature_class":"P",
    "gn:feature_code":"PPL",
    "gn:name":"Mashir Khel",
    "gn:population":0,
    "gn:timezone":"Asia/Karachi",
    "iso:country":"PK",
    "wof:name":"Mashir Khel",
    "wof:placetype":"locality"
},
  "geometry": {"coordinates":[70.42453,32.87237],"type":"Point"}
}