{
  "type": "Feature",
  "properties": {
    "gn:admin1_code":"4.0",
    "gn:asciiname":"Jalalana",
    "gn:country_code":"PK",
    "gn:dem":201,
    "gn:feature_class":"P",
    "gn:feature_code":"PPL",
    "gn:name":"Jalalana",
    "gn:population":0,
    "gn:timezone":"Asia/Karachi",
    "iso:country":"PK",
    "name:und_x_variant":[
        "Jal\u0101li\u0101na"
    ],
    "wof:name":"Jalalana",
    "wof:placetype":"locality"
},
  "geometry": {"coordinates":[73.59605000000001,31.91016],"type":"Point"}
}