{
  "type": "Feature",
  "properties": {
    "gn:admin1_code":"7.0",
    "gn:asciiname":"Khun",
    "gn:country_code":"PK",
    "gn:dem":1920,
    "gn:feature_class":"P",
    "gn:feature_code":"PPL",
    "gn:name":"Khun",
    "gn:population":0,
    "gn:timezone":"Asia/Karachi",
    "iso:country":"PK",
    "name:deu_x_preferred":[
        "Khun"
    ],
    "name:spa_x_preferred":[
        "Khun"
    ],
    "wof:name":"Khun",
    "wof:placetype":"locality"
},
  "geometry": {"coordinates":[73.80359,35.35785999999999],"type":"Point"}
}