{
  "type": "Feature",
  "properties": {
    "gn:admin1_code":"5",
    "gn:asciiname":"Garhi Wara Janwari",
    "gn:country_code":"PK",
    "gn:dem":47,
    "gn:feature_class":"P",
    "gn:feature_code":"PPL",
    "gn:name":"Garhi Wara Janwari",
    "gn:population":0,
    "gn:timezone":"Asia/Karachi",
    "iso:country":"PK",
    "name:und_x_variant":[
        "Goth Pah\u0101wal"
    ],
    "wof:name":"Garhi Wara Janwari",
    "wof:placetype":"locality"
},
  "geometry": {"coordinates":[67.95359000000001,27.16177],"type":"Point"}
}