{
  "type": "Feature",
  "properties": {
    "gn:admin1_code":"6",
    "gn:asciiname":"Nurpur",
    "gn:country_code":"PK",
    "gn:dem":1974,
    "gn:feature_class":"P",
    "gn:feature_code":"PPL",
    "gn:name":"Nurpur",
    "gn:population":0,
    "gn:timezone":"Asia/Karachi",
    "iso:country":"PK",
    "wof:name":"Nurpur",
    "wof:placetype":"locality"
},
  "geometry": {"coordinates":[74.02081,33.86392],"type":"Point"}
}