{
  "type": "Feature",
  "properties": {
    "gn:admin1_code":"1",
    "gn:asciiname":"Manzai",
    "gn:country_code":"PK",
    "gn:dem":1889,
    "gn:feature_class":"P",
    "gn:feature_code":"PPL",
    "gn:name":"Manzai",
    "gn:population":0,
    "gn:timezone":"Asia/Karachi",
    "iso:country":"PK",
    "name:ara_x_preferred":[
        "\u0627\u0644\u0645\u0646\u0632\u0627\u064a"
    ],
    "name:cat_x_preferred":[
        "Manzai"
    ],
    "name:deu_x_preferred":[
        "Manzai"
    ],
    "name:fas_x_preferred":[
        "\u0645\u0627\u0646\u0632\u0627\u06cc"
    ],
    "name:fra_x_preferred":[
        "Manzai"
    ],
    "name:hin_x_preferred":[
        "\u092e\u093e\u0928\u091c\u093c\u093e\u0908"
    ],
    "name:ind_x_preferred":[
        "Manzai"
    ],
    "name:ita_x_preferred":[
        "Manzai"
    ],
    "name:jav_x_preferred":[
        "Manzai"
    ],
    "name:pol_x_preferred":[
        "Manzai"
    ],
    "name:rus_x_preferred":[
        "\u041c\u0430\u043d\u0434\u0437\u0430\u0439"
    ],
    "name:spa_x_preferred":[
        "Manzai"
    ],
    "name:swe_x_preferred":[
        "Manzai"
    ],
    "name:tur_x_preferred":[
        "Manzai"
    ],
    "wof:name":"Manzai",
    "wof:placetype":"locality"
},
  "geometry": {"coordinates":[69.80405999999999,32.58576],"type":"Point"}
}