{
  "type": "Feature",
  "properties": {
    "gn:admin1_code":"1",
    "gn:asciiname":"Manzai",
    "gn:country_code":"PK",
    "gn:dem":1889,
    "gn:feature_class":"P",
    "gn:feature_code":"PPL",
    "gn:name":"Manzai",
    "gn:population":0,
    "gn:timezone":"Asia/Karachi",
    "iso:country":"PK",
    "wof:name":"Manzai",
    "wof:placetype":"locality"
},
  "geometry": {"coordinates":[69.80405999999999,32.58576],"type":"Point"}
}