{
  "type": "Feature",
  "properties": {
    "gn:admin1_code":"5.0",
    "gn:asciiname":"Pasarko",
    "gn:country_code":"PK",
    "gn:dem":33,
    "gn:feature_class":"P",
    "gn:feature_code":"PPL",
    "gn:name":"Pasarko",
    "gn:population":0,
    "gn:timezone":"Asia/Karachi",
    "iso:country":"PK",
    "name:und_x_variant":[
        "Po Sarko"
    ],
    "wof:name":"Pasarko",
    "wof:placetype":"locality"
},
  "geometry": {"coordinates":[69.65803000000001,24.70401],"type":"Point"}
}