{
  "type": "Feature",
  "properties": {
    "gn:admin1_code":"5.0",
    "gn:asciiname":"Gachero",
    "gn:country_code":"PK",
    "gn:dem":48,
    "gn:feature_class":"P",
    "gn:feature_code":"PPL",
    "gn:name":"Gachero",
    "gn:population":0,
    "gn:timezone":"Asia/Karachi",
    "iso:country":"PK",
    "name:und_x_variant":[
        "Gachera",
        "Gachero"
    ],
    "wof:name":"Gachero",
    "wof:placetype":"locality"
},
  "geometry": {"coordinates":[67.94252,26.60923],"type":"Point"}
}