{
  "type": "Feature",
  "properties": {
    "gn:admin1_code":"6",
    "gn:asciiname":"Saidpur",
    "gn:country_code":"PK",
    "gn:dem":812,
    "gn:feature_class":"P",
    "gn:feature_code":"PPL",
    "gn:name":"Saidpur",
    "gn:population":0,
    "gn:timezone":"Asia/Karachi",
    "iso:country":"PK",
    "wof:name":"Saidpur",
    "wof:placetype":"locality"
},
  "geometry": {"coordinates":[74.05504000000001,33.33155],"type":"Point"}
}