{
  "type": "Feature",
  "properties": {
    "gn:admin1_code":"5.0",
    "gn:asciiname":"Biro Khan Jakhrani",
    "gn:country_code":"PK",
    "gn:dem":63,
    "gn:feature_class":"P",
    "gn:feature_code":"PPL",
    "gn:name":"Biro Khan Jakhrani",
    "gn:population":0,
    "gn:timezone":"Asia/Karachi",
    "iso:country":"PK",
    "wof:name":"Biro Khan Jakhrani",
    "wof:placetype":"locality"
},
  "geometry": {"coordinates":[68.92338000000001,28.38194],"type":"Point"}
}