{
  "type": "Feature",
  "properties": {
    "gn:admin1_code":"01",
    "gn:asciiname":"Mir Dad Kot",
    "gn:country_code":"PK",
    "gn:dem":1657,
    "gn:feature_class":"P",
    "gn:feature_code":"PPL",
    "gn:name":"Mir Dad Kot",
    "gn:population":0,
    "gn:timezone":"Asia/Karachi",
    "iso:country":"PK",
    "wof:name":"Mir Dad Kot",
    "wof:placetype":"locality"
},
  "geometry": {"coordinates":[69.69471999999999,32.38972],"type":"Point"}
}