{
  "type": "Feature",
  "properties": {
    "gn:admin1_code":"4.0",
    "gn:asciiname":"Dheri Sudhnan",
    "gn:country_code":"PK",
    "gn:dem":670,
    "gn:feature_class":"P",
    "gn:feature_code":"PPL",
    "gn:name":"Dheri Sudhnan",
    "gn:population":0,
    "gn:timezone":"Asia/Karachi",
    "iso:country":"PK",
    "wof:name":"Dheri Sudhnan",
    "wof:placetype":"locality"
},
  "geometry": {"coordinates":[73.55316999999999,33.52285],"type":"Point"}
}