{
  "type": "Feature",
  "properties": {
    "gn:admin1_code":"3.0",
    "gn:asciiname":"Shaikhandeh",
    "gn:country_code":"PK",
    "gn:dem":2057,
    "gn:feature_class":"P",
    "gn:feature_code":"PPL",
    "gn:name":"Shaikhandeh",
    "gn:population":0,
    "gn:timezone":"Asia/Karachi",
    "iso:country":"PK",
    "wof:name":"Shaikhandeh",
    "wof:placetype":"locality"
},
  "geometry": {"coordinates":[71.71243,35.57882],"type":"Point"}
}