{
  "type": "Feature",
  "properties": {
    "gn:admin1_code":"3",
    "gn:asciiname":"Khue",
    "gn:country_code":"PK",
    "gn:dem":877,
    "gn:feature_class":"P",
    "gn:feature_code":"PPL",
    "gn:name":"Khue",
    "gn:population":0,
    "gn:timezone":"Asia/Karachi",
    "iso:country":"PK",
    "name:eng_x_preferred":[
        "Kuai"
    ],
    "wof:name":"Khue",
    "wof:placetype":"locality"
},
  "geometry": {"coordinates":[72.16360999999998,34.70746],"type":"Point"}
}