{
  "type": "Feature",
  "properties": {
    "gn:admin1_code":"2.0",
    "gn:asciiname":"Aqil Jagirani",
    "gn:country_code":"PK",
    "gn:dem":51,
    "gn:feature_class":"P",
    "gn:feature_code":"PPL",
    "gn:name":"Aqil Jagirani",
    "gn:population":0,
    "gn:timezone":"Asia/Karachi",
    "iso:country":"PK",
    "name:und_x_variant":[
        "Chak 70",
        "Chak Seventy"
    ],
    "wof:name":"Aqil Jagirani",
    "wof:placetype":"locality"
},
  "geometry": {"coordinates":[67.70484,28.08255],"type":"Point"}
}