{
  "type": "Feature",
  "properties": {
    "gn:admin1_code":"7.0",
    "gn:asciiname":"Khurup",
    "gn:country_code":"PK",
    "gn:dem":2651,
    "gn:feature_class":"P",
    "gn:feature_code":"PPL",
    "gn:name":"Khurup",
    "gn:population":0,
    "gn:timezone":"Asia/Karachi",
    "iso:country":"PK",
    "wof:name":"Khurup",
    "wof:placetype":"locality"
},
  "geometry": {"coordinates":[74.90869000000001,35.23754],"type":"Point"}
}