{
  "type": "Feature",
  "properties": {
    "gn:admin1_code":"7.0",
    "gn:asciiname":"Dumia",
    "gn:country_code":"PK",
    "gn:dem":2863,
    "gn:feature_class":"P",
    "gn:feature_code":"PPL",
    "gn:name":"Dumia",
    "gn:population":0,
    "gn:timezone":"Asia/Karachi",
    "iso:country":"PK",
    "wof:name":"Dumia",
    "wof:placetype":"locality"
},
  "geometry": {"coordinates":[74.1965,36.152],"type":"Point"}
}