{
  "type": "Feature",
  "properties": {
    "gn:admin1_code":"5.0",
    "gn:asciiname":"Goth Master Sultan",
    "gn:country_code":"PK",
    "gn:dem":32,
    "gn:feature_class":"P",
    "gn:feature_code":"PPL",
    "gn:name":"Goth Master Sultan",
    "gn:population":0,
    "gn:timezone":"Asia/Karachi",
    "iso:country":"PK",
    "wof:name":"Goth Master Sultan",
    "wof:placetype":"locality"
},
  "geometry": {"coordinates":[68.58754,26.4335],"type":"Point"}
}