{
  "type": "Feature",
  "properties": {
    "gn:admin1_code":"4.0",
    "gn:asciiname":"Athla",
    "gn:country_code":"PK",
    "gn:dem":997,
    "gn:feature_class":"P",
    "gn:feature_code":"PPL",
    "gn:name":"Athla",
    "gn:population":0,
    "gn:timezone":"Asia/Karachi",
    "iso:country":"PK",
    "wof:name":"Athla",
    "wof:placetype":"locality"
},
  "geometry": {"coordinates":[71.91441999999998,32.55815],"type":"Point"}
}