{
  "type": "Feature",
  "properties": {
    "gn:admin1_code":"3.0",
    "gn:asciiname":"Kunder",
    "gn:country_code":"PK",
    "gn:dem":1362,
    "gn:feature_class":"P",
    "gn:feature_code":"PPL",
    "gn:name":"Kunder",
    "gn:population":0,
    "gn:timezone":"Asia/Karachi",
    "iso:country":"PK",
    "wof:name":"Kunder",
    "wof:placetype":"locality"
},
  "geometry": {"coordinates":[73.28209,35.17406],"type":"Point"}
}