{
  "type": "Feature",
  "properties": {
    "gn:admin1_code":"4.0",
    "gn:asciiname":"Chhichhiana",
    "gn:country_code":"PK",
    "gn:dem":209,
    "gn:feature_class":"P",
    "gn:feature_code":"PPL",
    "gn:name":"Chhichhiana",
    "gn:population":0,
    "gn:timezone":"Asia/Karachi",
    "iso:country":"PK",
    "name:und_x_variant":[
        "Chichi\u0101na Khu"
    ],
    "wof:name":"Chhichhiana",
    "wof:placetype":"locality"
},
  "geometry": {"coordinates":[73.86588,31.83316],"type":"Point"}
}