{
  "type": "Feature",
  "properties": {
    "gn:admin1_code":"5",
    "gn:asciiname":"Goth Bilawal Baghdar",
    "gn:country_code":"PK",
    "gn:dem":55,
    "gn:feature_class":"P",
    "gn:feature_code":"PPL",
    "gn:name":"Goth Bilawal Baghdar",
    "gn:population":0,
    "gn:timezone":"Asia/Karachi",
    "iso:country":"PK",
    "name:und_x_variant":[
        "Goth Baghd\u0101d"
    ],
    "wof:name":"Goth Bilawal Baghdar",
    "wof:placetype":"locality"
},
  "geometry": {"coordinates":[68.34359000000001,27.93446],"type":"Point"}
}