{
  "type": "Feature",
  "properties": {
    "gn:admin1_code":"3.0",
    "gn:asciiname":"Rahmat Shah",
    "gn:country_code":"PK",
    "gn:dem":345,
    "gn:feature_class":"P",
    "gn:feature_code":"PPL",
    "gn:name":"Rahmat Shah",
    "gn:population":0,
    "gn:timezone":"Asia/Karachi",
    "iso:country":"PK",
    "name:ara_x_preferred":[
        "\u0631\u062d\u0645\u062a \u0634\u0627\u0647"
    ],
    "name:ben_x_preferred":[
        "\u09b0\u09b9\u09ae\u09a4 \u09b6\u09be\u09b9"
    ],
    "name:hin_x_preferred":[
        "\u0930\u0939\u092e\u0924 \u0936\u093e\u0939"
    ],
    "name:urd_x_preferred":[
        "\u0631\u062d\u0645\u062a \u0634\u0627\u06c1"
    ],
    "wof:name":"Rahmat Shah",
    "wof:placetype":"locality"
},
  "geometry": {"coordinates":[70.59786,32.8978],"type":"Point"}
}