{
  "type": "Feature",
  "properties": {
    "gn:admin1_code":"4",
    "gn:asciiname":"Dera Chaudhrian",
    "gn:country_code":"PK",
    "gn:dem":215,
    "gn:feature_class":"P",
    "gn:feature_code":"PPL",
    "gn:name":"Dera Chaudhrian",
    "gn:population":0,
    "gn:timezone":"Asia/Karachi",
    "iso:country":"PK",
    "wof:name":"Dera Chaudhrian",
    "wof:placetype":"locality"
},
  "geometry": {"coordinates":[73.34279000000002,32.40413],"type":"Point"}
}