{
  "type": "Feature",
  "properties": {
    "gn:admin1_code":"4",
    "gn:asciiname":"Gharibabad",
    "gn:country_code":"PK",
    "gn:dem":133,
    "gn:feature_class":"P",
    "gn:feature_code":"PPL",
    "gn:name":"Gharibabad",
    "gn:population":0,
    "gn:timezone":"Asia/Karachi",
    "iso:country":"PK",
    "name:diq_x_preferred":[
        "\u011eeribabad"
    ],
    "name:eng_x_preferred":[
        "Gharibabad"
    ],
    "name:urd_x_preferred":[
        "\u063a\u0631\u06cc\u0628 \u0622\u0628\u0627\u062f"
    ],
    "wof:name":"Gharibabad",
    "wof:placetype":"locality"
},
  "geometry": {"coordinates":[71.72284000000001,30.28288],"type":"Point"}
}