{
  "type": "Feature",
  "properties": {
    "gn:admin1_code":"5",
    "gn:asciiname":"Goth Kerio Khoso",
    "gn:country_code":"PK",
    "gn:dem":27,
    "gn:feature_class":"P",
    "gn:feature_code":"PPL",
    "gn:name":"Goth Kerio Khoso",
    "gn:population":0,
    "gn:timezone":"Asia/Karachi",
    "iso:country":"PK",
    "name:und_x_variant":[
        "Goth Hot Kh\u0101n Baloch"
    ],
    "wof:name":"Goth Kerio Khoso",
    "wof:placetype":"locality"
},
  "geometry": {"coordinates":[68.58145,25.75743],"type":"Point"}
}