{
  "type": "Feature",
  "properties": {
    "gn:admin1_code":"4.0",
    "gn:asciiname":"Nata Chhatar",
    "gn:country_code":"PK",
    "gn:dem":560,
    "gn:feature_class":"P",
    "gn:feature_code":"PPL",
    "gn:name":"Nata Chhatar",
    "gn:population":0,
    "gn:timezone":"Asia/Karachi",
    "iso:country":"PK",
    "name:und_x_variant":[
        "Chattar"
    ],
    "wof:name":"Nata Chhatar",
    "wof:placetype":"locality"
},
  "geometry": {"coordinates":[73.15822,33.17521],"type":"Point"}
}