{
  "type": "Feature",
  "properties": {
    "gn:admin1_code":"5.0",
    "gn:asciiname":"Jarrar Zaur",
    "gn:country_code":"PK",
    "gn:dem":11,
    "gn:feature_class":"P",
    "gn:feature_code":"PPL",
    "gn:name":"Jarrar Zaur",
    "gn:population":0,
    "gn:timezone":"Asia/Karachi",
    "iso:country":"PK",
    "name:eng_x_preferred":[
        "Jarrar Zaur"
    ],
    "wof:name":"Jarrar Zaur",
    "wof:placetype":"locality"
},
  "geometry": {"coordinates":[68.31395000000001,24.73699],"type":"Point"}
}