{
  "type": "Feature",
  "properties": {
    "gn:admin1_code":"5.0",
    "gn:asciiname":"Darya Khan",
    "gn:country_code":"PK",
    "gn:dem":22,
    "gn:feature_class":"P",
    "gn:feature_code":"PPL",
    "gn:name":"Darya Khan",
    "gn:population":0,
    "gn:timezone":"Asia/Karachi",
    "iso:country":"PK",
    "name:eng_x_preferred":[
        "Darya Khan"
    ],
    "name:eng_x_variant":[
        "Muhammad Kh\u0101n"
    ],
    "wof:name":"Darya Khan",
    "wof:placetype":"locality"
},
  "geometry": {"coordinates":[68.45952,25.47833],"type":"Point"}
}