{
  "type": "Feature",
  "properties": {
    "gn:admin1_code":"3.0",
    "gn:asciiname":"Hola",
    "gn:country_code":"PK",
    "gn:dem":2200,
    "gn:feature_class":"P",
    "gn:feature_code":"PPL",
    "gn:name":"Hola",
    "gn:population":0,
    "gn:timezone":"Asia/Karachi",
    "iso:country":"PK",
    "name:ceb_x_preferred":[
        "Hola"
    ],
    "name:est_x_preferred":[
        "Hola"
    ],
    "name:fra_x_preferred":[
        "Hola"
    ],
    "name:ita_x_preferred":[
        "Hola"
    ],
    "name:lit_x_preferred":[
        "Hola"
    ],
    "name:nld_x_preferred":[
        "Hola"
    ],
    "name:pol_x_preferred":[
        "Hola"
    ],
    "name:spa_x_preferred":[
        "Hola"
    ],
    "name:swe_x_preferred":[
        "Hola"
    ],
    "name:ukr_x_preferred":[
        "\u0413\u043e\u043b\u044f"
    ],
    "wof:name":"Hola",
    "wof:placetype":"locality"
},
  "geometry": {"coordinates":[73.43087,34.59759],"type":"Point"}
}