{
  "type": "Feature",
  "properties": {
    "gn:admin1_code":"1",
    "gn:asciiname":"Toji Khel",
    "gn:country_code":"PK",
    "gn:dem":1071,
    "gn:feature_class":"P",
    "gn:feature_code":"PPL",
    "gn:name":"Toji Khel",
    "gn:population":0,
    "gn:timezone":"Asia/Karachi",
    "iso:country":"PK",
    "wof:name":"Toji Khel",
    "wof:placetype":"locality"
},
  "geometry": {"coordinates":[69.60009000000001,32.168],"type":"Point"}
}