{
  "type": "Feature",
  "properties": {
    "gn:admin1_code":"4.0",
    "gn:asciiname":"Panniwala",
    "gn:country_code":"PK",
    "gn:dem":160,
    "gn:feature_class":"P",
    "gn:feature_code":"PPL",
    "gn:name":"Panniwala",
    "gn:population":0,
    "gn:timezone":"Asia/Karachi",
    "iso:country":"PK",
    "name:und_x_variant":[
        "Pannlw\u0101l",
        "Panniwala"
    ],
    "wof:name":"Panniwala",
    "wof:placetype":"locality"
},
  "geometry": {"coordinates":[72.48419,31.38376],"type":"Point"}
}