{
  "type": "Feature",
  "properties": {
    "gn:admin1_code":"1.0",
    "gn:asciiname":"Mulla Oba",
    "gn:country_code":"PK",
    "gn:dem":572,
    "gn:feature_class":"P",
    "gn:feature_code":"PPL",
    "gn:name":"Mulla Oba",
    "gn:population":0,
    "gn:timezone":"Asia/Karachi",
    "iso:country":"PK",
    "name:und_x_variant":[
        "Mulla Obj",
        "M\u016blla Oba",
        "Mulla Oba"
    ],
    "wof:name":"Mulla Oba",
    "wof:placetype":"locality"
},
  "geometry": {"coordinates":[70.12436,31.66017],"type":"Point"}
}