{
  "type": "Feature",
  "properties": {
    "gn:admin1_code":"4",
    "gn:asciiname":"Chak Eighty-six A ML",
    "gn:country_code":"PK",
    "gn:dem":164,
    "gn:feature_class":"P",
    "gn:feature_code":"PPL",
    "gn:name":"Chak Eighty-six A ML",
    "gn:population":0,
    "gn:timezone":"Asia/Karachi",
    "iso:country":"PK",
    "name:und_x_variant":[
        "Chak Eighty-Six TDA",
        "Chak 86 TDA",
        "Chak Eighty-six A ML"
    ],
    "wof:name":"Chak Eighty-six A ML",
    "wof:placetype":"locality"
},
  "geometry": {"coordinates":[71.10384000000001,31.37388],"type":"Point"}
}