{
  "type": "Feature",
  "properties": {
    "gn:admin1_code":"5",
    "gn:asciiname":"Mitta Khan Chandio",
    "gn:country_code":"PK",
    "gn:dem":12,
    "gn:feature_class":"P",
    "gn:feature_code":"PPL",
    "gn:name":"Mitta Khan Chandio",
    "gn:population":0,
    "gn:timezone":"Asia/Karachi",
    "iso:country":"PK",
    "name:und_x_variant":[
        "Mitha Kh\u0101n Ch\u0101ndia"
    ],
    "wof:name":"Mitta Khan Chandio",
    "wof:placetype":"locality"
},
  "geometry": {"coordinates":[69.13717,24.91555],"type":"Point"}
}