{
  "type": "Feature",
  "properties": {
    "gn:admin1_code":"3.0",
    "gn:asciiname":"Shao Kach",
    "gn:country_code":"PK",
    "gn:dem":463,
    "gn:feature_class":"P",
    "gn:feature_code":"PPL",
    "gn:name":"Shao Kach",
    "gn:population":0,
    "gn:timezone":"Asia/Karachi",
    "iso:country":"PK",
    "wof:name":"Shao Kach",
    "wof:placetype":"locality"
},
  "geometry": {"coordinates":[71.82041,33.64938],"type":"Point"}
}