{
  "type": "Feature",
  "properties": {
    "gn:admin1_code":"4.0",
    "gn:asciiname":"Chak Shaikhan",
    "gn:country_code":"PK",
    "gn:dem":191,
    "gn:feature_class":"P",
    "gn:feature_code":"PPL",
    "gn:name":"Chak Shaikhan",
    "gn:population":0,
    "gn:timezone":"Asia/Karachi",
    "iso:country":"PK",
    "name:und_x_variant":[
        "Chak Shekha",
        "Chak Sheikha",
        "Chak Shaikhan"
    ],
    "wof:name":"Chak Shaikhan",
    "wof:placetype":"locality"
},
  "geometry": {"coordinates":[72.69631,32.38541],"type":"Point"}
}