{
  "type": "Feature",
  "properties": {
    "gn:admin1_code":"5",
    "gn:asciiname":"Goth Lal Bakhsh Chand",
    "gn:country_code":"PK",
    "gn:dem":26,
    "gn:feature_class":"P",
    "gn:feature_code":"PPL",
    "gn:name":"Goth Lal Bakhsh Chand",
    "gn:population":0,
    "gn:timezone":"Asia/Karachi",
    "iso:country":"PK",
    "name:eng_x_preferred":[
        "Chand"
    ],
    "wof:name":"Goth Lal Bakhsh Chand",
    "wof:placetype":"locality"
},
  "geometry": {"coordinates":[68.44714,25.8607],"type":"Point"}
}