{
  "type": "Feature",
  "properties": {
    "gn:admin1_code":"4.0",
    "gn:asciiname":"Allu",
    "gn:cc2":"PK",
    "gn:country_code":"PK",
    "gn:dem":76,
    "gn:feature_class":"P",
    "gn:feature_code":"PPL",
    "gn:name":"Allu",
    "gn:population":0,
    "gn:timezone":"Asia/Karachi",
    "iso:country":"PK",
    "name:fin_x_preferred":[
        "Allu"
    ],
    "name:und_x_variant":[
        "Goth Alu"
    ],
    "wof:name":"Allu",
    "wof:placetype":"locality"
},
  "geometry": {"coordinates":[69.93333,28.23333],"type":"Point"}
}