{
  "type": "Feature",
  "properties": {
    "gn:admin1_code":"1.0",
    "gn:asciiname":"Bissatu",
    "gn:country_code":"PK",
    "gn:dem":1273,
    "gn:feature_class":"P",
    "gn:feature_code":"PPL",
    "gn:name":"Bissatu",
    "gn:population":0,
    "gn:timezone":"Asia/Karachi",
    "iso:country":"PK",
    "name:und_x_variant":[
        "Bisatu",
        "Bissatu",
        "Bisattu"
    ],
    "wof:name":"Bissatu",
    "wof:placetype":"locality"
},
  "geometry": {"coordinates":[70.2432,33.75680999999999],"type":"Point"}
}