{
  "type": "Feature",
  "properties": {
    "gn:admin1_code":"1.0",
    "gn:asciiname":"Lali Garhi",
    "gn:country_code":"PK",
    "gn:dem":551,
    "gn:feature_class":"P",
    "gn:feature_code":"PPL",
    "gn:name":"Lali Garhi",
    "gn:population":0,
    "gn:timezone":"Asia/Karachi",
    "iso:country":"PK",
    "name:und_x_variant":[
        "Ch\u012bno Ber\u0101i Kili",
        "L\u0101li Garhi"
    ],
    "wof:name":"Lali Garhi",
    "wof:placetype":"locality"
},
  "geometry": {"coordinates":[71.24495999999998,34.22404],"type":"Point"}
}