{
  "type": "Feature",
  "properties": {
    "gn:admin1_code":"3.0",
    "gn:asciiname":"Trimman",
    "gn:country_code":"PK",
    "gn:dem":1071,
    "gn:feature_class":"P",
    "gn:feature_code":"PPL",
    "gn:name":"Trimman",
    "gn:population":0,
    "gn:timezone":"Asia/Karachi",
    "iso:country":"PK",
    "name:eng_x_preferred":[
        "Trimman"
    ],
    "name:und_x_variant":[
        "Trimmah"
    ],
    "wof:name":"Trimman",
    "wof:placetype":"locality"
},
  "geometry": {"coordinates":[73.24768,33.94682],"type":"Point"}
}