{
  "type": "Feature",
  "properties": {
    "gn:admin1_code":"5",
    "gn:asciiname":"Goth Muhammad Bakhsh Gorchani",
    "gn:country_code":"PK",
    "gn:dem":14,
    "gn:feature_class":"P",
    "gn:feature_code":"PPL",
    "gn:name":"Goth Muhammad Bakhsh Gorchani",
    "gn:population":0,
    "gn:timezone":"Asia/Karachi",
    "iso:country":"PK",
    "name:und_x_variant":[
        "Goth Said Kh\u0101n Lagh\u0101ri",
        "Goth Qut uddin Laghari"
    ],
    "wof:name":"Goth Muhammad Bakhsh Gorchani",
    "wof:placetype":"locality"
},
  "geometry": {"coordinates":[69.13639000000001,25.27486],"type":"Point"}
}