{
  "type": "Feature",
  "properties": {
    "gn:admin1_code":"03",
    "gn:asciiname":"Bazid Koruna",
    "gn:country_code":"PK",
    "gn:dem":347,
    "gn:feature_class":"P",
    "gn:feature_code":"PPL",
    "gn:name":"Bazid Koruna",
    "gn:population":0,
    "gn:timezone":"Asia/Karachi",
    "iso:country":"PK",
    "name:eng_x_preferred":[
        "Bazid Koruna"
    ],
    "wof:name":"Bazid Koruna",
    "wof:placetype":"locality"
},
  "geometry": {"coordinates":[71.86955,34.2865],"type":"Point"}
}