{
  "type": "Feature",
  "properties": {
    "gn:admin1_code":"4",
    "gn:asciiname":"Chak Six Hundred Sixty-six -Seven Gugera Branch",
    "gn:country_code":"PK",
    "gn:dem":149,
    "gn:feature_class":"P",
    "gn:feature_code":"PPL",
    "gn:name":"Chak Six Hundred Sixty-six -Seven Gugera Branch",
    "gn:population":0,
    "gn:timezone":"Asia/Karachi",
    "iso:country":"PK",
    "name:und_x_variant":[
        "Chak Six Hundred Sixty-Eight-Seven GB",
        "Chak Seven",
        "Chak Six Hundred Sixty-six -Seven Gugera Branch"
    ],
    "wof:name":"Chak Six Hundred Sixty-six -Seven Gugera Branch",
    "wof:placetype":"locality"
},
  "geometry": {"coordinates":[72.48432,30.77028],"type":"Point"}
}