{
  "type": "Feature",
  "properties": {
    "gn:admin1_code":"4.0",
    "gn:asciiname":"Jhugian Nagra",
    "gn:country_code":"PK",
    "gn:dem":212,
    "gn:feature_class":"P",
    "gn:feature_code":"PPL",
    "gn:name":"Jhugian Nagra",
    "gn:population":0,
    "gn:timezone":"Asia/Karachi",
    "iso:country":"PK",
    "name:eng_x_preferred":[
        "Jhugian Nagra"
    ],
    "wof:name":"Jhugian Nagra",
    "wof:placetype":"locality"
},
  "geometry": {"coordinates":[74.2693,31.5267],"type":"Point"}
}