{
  "type": "Feature",
  "properties": {
    "gn:admin1_code":"2.0",
    "gn:asciiname":"Sadiq Umrani Muhammad",
    "gn:country_code":"PK",
    "gn:dem":58,
    "gn:feature_class":"P",
    "gn:feature_code":"PPL",
    "gn:name":"Sadiq Umrani Muhammad",
    "gn:population":0,
    "gn:timezone":"Asia/Karachi",
    "iso:country":"PK",
    "name:und_x_variant":[
        "Goth H\u0101ji Kh\u0101n Muhammad"
    ],
    "wof:name":"Sadiq Umrani Muhammad",
    "wof:placetype":"locality"
},
  "geometry": {"coordinates":[67.98801999999999,28.29749],"type":"Point"}
}