{
  "type": "Feature",
  "properties": {
    "gn:admin1_code":"3.0",
    "gn:asciiname":"Munkar Banda",
    "gn:country_code":"PK",
    "gn:dem":401,
    "gn:feature_class":"P",
    "gn:feature_code":"PPL",
    "gn:name":"Munkar Banda",
    "gn:population":0,
    "gn:timezone":"Asia/Karachi",
    "iso:country":"PK",
    "name:eng_x_preferred":[
        "Mannakra"
    ],
    "wof:name":"Munkar Banda",
    "wof:placetype":"locality"
},
  "geometry": {"coordinates":[72.05367,34.38695999999999],"type":"Point"}
}