{
  "type": "Feature",
  "properties": {
    "gn:admin1_code":"4.0",
    "gn:asciiname":"Dhok Ucha",
    "gn:country_code":"PK",
    "gn:dem":373,
    "gn:feature_class":"P",
    "gn:feature_code":"PPL",
    "gn:name":"Dhok Ucha",
    "gn:population":0,
    "gn:timezone":"Asia/Karachi",
    "iso:country":"PK",
    "wof:name":"Dhok Ucha",
    "wof:placetype":"locality"
},
  "geometry": {"coordinates":[71.96585999999998,32.96034],"type":"Point"}
}