{
  "type": "Feature",
  "properties": {
    "gn:admin1_code":"2.0",
    "gn:asciiname":"Guni",
    "gn:country_code":"PK",
    "gn:dem":1560,
    "gn:feature_class":"P",
    "gn:feature_code":"PPL",
    "gn:name":"Guni",
    "gn:population":0,
    "gn:timezone":"Asia/Karachi",
    "iso:country":"PK",
    "wof:name":"Guni",
    "wof:placetype":"locality"
},
  "geometry": {"coordinates":[66.55062,27.31344],"type":"Point"}
}