{
  "type": "Feature",
  "properties": {
    "gn:admin1_code":"5",
    "gn:asciiname":"Goth Muhammad Khan",
    "gn:country_code":"PK",
    "gn:dem":15,
    "gn:feature_class":"P",
    "gn:feature_code":"PPL",
    "gn:name":"Goth Muhammad Khan",
    "gn:population":0,
    "gn:timezone":"Asia/Karachi",
    "iso:country":"PK",
    "name:und_x_variant":[
        "Goth Mehr\u0101b Kh\u0101n"
    ],
    "wof:name":"Goth Muhammad Khan",
    "wof:placetype":"locality"
},
  "geometry": {"coordinates":[69.02681,25.03713],"type":"Point"}
}