{
  "type": "Feature",
  "properties": {
    "gn:admin1_code":"3",
    "gn:asciiname":"Chur Banda",
    "gn:country_code":"PK",
    "gn:dem":1669,
    "gn:feature_class":"P",
    "gn:feature_code":"PPL",
    "gn:name":"Chur Banda",
    "gn:population":0,
    "gn:timezone":"Asia/Karachi",
    "iso:country":"PK",
    "wof:name":"Chur Banda",
    "wof:placetype":"locality"
},
  "geometry": {"coordinates":[72.19983000000001,34.93992],"type":"Point"}
}