{
  "type": "Feature",
  "properties": {
    "gn:admin1_code":"2.0",
    "gn:asciiname":"Tierai Muhammad Jan",
    "gn:country_code":"PK",
    "gn:dem":2116,
    "gn:feature_class":"P",
    "gn:feature_code":"PPL",
    "gn:name":"Tierai Muhammad Jan",
    "gn:population":0,
    "gn:timezone":"Asia/Karachi",
    "iso:country":"PK",
    "name:und_x_variant":[
        "Tlerai Muhammad J\u0101n"
    ],
    "wof:name":"Tierai Muhammad Jan",
    "wof:placetype":"locality"
},
  "geometry": {"coordinates":[67.70498000000001,30.88614],"type":"Point"}
}