{
  "type": "Feature",
  "properties": {
    "gn:admin1_code":"4",
    "gn:asciiname":"Lakkha Singhwala",
    "gn:country_code":"PK",
    "gn:dem":193,
    "gn:feature_class":"P",
    "gn:feature_code":"PPL",
    "gn:name":"Lakkha Singhwala",
    "gn:population":0,
    "gn:timezone":"Asia/Karachi",
    "iso:country":"PK",
    "wof:name":"Lakkha Singhwala",
    "wof:placetype":"locality"
},
  "geometry": {"coordinates":[74.39305999999998,30.87222],"type":"Point"}
}