{
  "type": "Feature",
  "properties": {
    "gn:admin1_code":"04",
    "gn:asciiname":"Westonabad",
    "gn:country_code":"PK",
    "gn:dem":197,
    "gn:feature_class":"P",
    "gn:feature_code":"PPL",
    "gn:name":"Westonabad",
    "gn:population":0,
    "gn:timezone":"Asia/Karachi",
    "iso:country":"PK",
    "name:und_x_variant":[
        "Chak 5 NB",
        "Chak Five NB",
        "Chak Five North Branch"
    ],
    "wof:name":"Westonabad",
    "wof:placetype":"locality"
},
  "geometry": {"coordinates":[72.94158,32.31538],"type":"Point"}
}