{
  "type": "Feature",
  "properties": {
    "gn:admin1_code":"2.0",
    "gn:asciiname":"Haji Habibullah",
    "gn:country_code":"PK",
    "gn:dem":1322,
    "gn:feature_class":"P",
    "gn:feature_code":"PPL",
    "gn:name":"Haji Habibullah",
    "gn:population":0,
    "gn:timezone":"Asia/Karachi",
    "iso:country":"PK",
    "wof:name":"Haji Habibullah",
    "wof:placetype":"locality"
},
  "geometry": {"coordinates":[69.8426,30.21019],"type":"Point"}
}