{
  "type": "Feature",
  "properties": {
    "gn:admin1_code":"4.0",
    "gn:asciiname":"Basti Islamabad",
    "gn:country_code":"PK",
    "gn:dem":103,
    "gn:feature_class":"P",
    "gn:feature_code":"PPL",
    "gn:name":"Basti Islamabad",
    "gn:population":0,
    "gn:timezone":"Asia/Karachi",
    "iso:country":"PK",
    "name:fas_x_preferred":[
        "\u0628\u0633\u062a\u06cc \u0627\u0633\u0644\u0627\u0645\u200c\u0622\u0628\u0627\u062f"
    ],
    "name:urd_x_preferred":[
        "\u0628\u0633\u062a\u06cc \u0627\u0633\u0644\u0627\u0645 \u0622\u0628\u0627\u062f"
    ],
    "wof:name":"Basti Islamabad",
    "wof:placetype":"locality"
},
  "geometry": {"coordinates":[71.12586999999998,29.23355],"type":"Point"}
}