{
  "type": "Feature",
  "properties": {
    "gn:admin1_code":"3.0",
    "gn:asciiname":"Kurmai Sar Banda",
    "gn:country_code":"PK",
    "gn:dem":3461,
    "gn:feature_class":"P",
    "gn:feature_code":"PPL",
    "gn:name":"Kurmai Sar Banda",
    "gn:population":0,
    "gn:timezone":"Asia/Karachi",
    "iso:country":"PK",
    "name:eng_x_preferred":[
        "Kurmai Sar Banda"
    ],
    "wof:name":"Kurmai Sar Banda",
    "wof:placetype":"locality"
},
  "geometry": {"coordinates":[72.08725,35.58517],"type":"Point"}
}