{
  "type": "Feature",
  "properties": {
    "gn:admin1_code":"4.0",
    "gn:asciiname":"Chak Fifty-seven Oamar Kot",
    "gn:country_code":"PK",
    "gn:dem":204,
    "gn:feature_class":"P",
    "gn:feature_code":"PPL",
    "gn:name":"Chak Fifty-seven Oamar Kot",
    "gn:population":0,
    "gn:timezone":"Asia/Karachi",
    "iso:country":"PK",
    "name:und_x_variant":[
        "Kot All\u0101h Bakhsh Kh\u0101n",
        "Kot Allah Bakhsh"
    ],
    "wof:name":"Chak Fifty-seven Oamar Kot",
    "wof:placetype":"locality"
},
  "geometry": {"coordinates":[74.09458000000002,31.21586],"type":"Point"}
}