{
  "type": "Feature",
  "properties": {
    "gn:admin1_code":"3.0",
    "gn:asciiname":"Dadar",
    "gn:country_code":"PK",
    "gn:dem":2992,
    "gn:feature_class":"P",
    "gn:feature_code":"PPL",
    "gn:name":"Dadar",
    "gn:population":0,
    "gn:timezone":"Asia/Karachi",
    "iso:country":"PK",
    "wof:name":"Dadar",
    "wof:placetype":"locality"
},
  "geometry": {"coordinates":[73.87149000000002,34.94476],"type":"Point"}
}