{
  "type": "Feature",
  "properties": {
    "gn:admin1_code":"4",
    "gn:asciiname":"Basti Pir Shah",
    "gn:country_code":"PK",
    "gn:dem":128,
    "gn:feature_class":"P",
    "gn:feature_code":"PPL",
    "gn:name":"Basti Pir Shah",
    "gn:population":0,
    "gn:timezone":"Asia/Karachi",
    "iso:country":"PK",
    "name:und_x_variant":[
        "P\u012br Sh\u0101h"
    ],
    "wof:name":"Basti Pir Shah",
    "wof:placetype":"locality"
},
  "geometry": {"coordinates":[72.05542,29.59936],"type":"Point"}
}