{
  "type": "Feature",
  "properties": {
    "gn:admin1_code":"3",
    "gn:asciiname":"Jan Patai",
    "gn:country_code":"PK",
    "gn:dem":2388,
    "gn:feature_class":"P",
    "gn:feature_code":"PPL",
    "gn:name":"Jan Patai",
    "gn:population":0,
    "gn:timezone":"Asia/Karachi",
    "iso:country":"PK",
    "wof:name":"Jan Patai",
    "wof:placetype":"locality"
},
  "geometry": {"coordinates":[72.59505,34.95149],"type":"Point"}
}