{
  "type": "Feature",
  "properties": {
    "gn:admin1_code":"4",
    "gn:asciiname":"Hafizwala",
    "gn:country_code":"PK",
    "gn:dem":199,
    "gn:feature_class":"P",
    "gn:feature_code":"PPL",
    "gn:name":"Hafizwala",
    "gn:population":0,
    "gn:timezone":"Asia/Karachi",
    "iso:country":"PK",
    "name:und_x_variant":[
        "Muzaffar Kh\u0101nw\u0101la"
    ],
    "wof:name":"Hafizwala",
    "wof:placetype":"locality"
},
  "geometry": {"coordinates":[71.44583,32.27917],"type":"Point"}
}