{
  "type": "Feature",
  "properties": {
    "gn:admin1_code":"4.0",
    "gn:asciiname":"Dhok Jandial",
    "gn:country_code":"PK",
    "gn:dem":317,
    "gn:feature_class":"P",
    "gn:feature_code":"PPL",
    "gn:name":"Dhok Jandial",
    "gn:population":0,
    "gn:timezone":"Asia/Karachi",
    "iso:country":"PK",
    "name:und_x_variant":[
        "Jandi\u0101l Dhok"
    ],
    "wof:name":"Dhok Jandial",
    "wof:placetype":"locality"
},
  "geometry": {"coordinates":[72.2107,33.24034],"type":"Point"}
}