{
  "type": "Feature",
  "properties": {
    "gn:admin1_code":"2",
    "gn:asciiname":"Bunarni",
    "gn:country_code":"PK",
    "gn:dem":1496,
    "gn:feature_class":"P",
    "gn:feature_code":"PPL",
    "gn:name":"Bunarni",
    "gn:population":0,
    "gn:timezone":"Asia/Karachi",
    "iso:country":"PK",
    "name:und_x_variant":[
        "Ch\u0101rgul Bun\u0101r\u0101ni",
        "Ch\u0101rgul Burar\u0101ni",
        "Bunarni"
    ],
    "wof:name":"Bunarni",
    "wof:placetype":"locality"
},
  "geometry": {"coordinates":[69.67048,30.10846],"type":"Point"}
}