{
  "type": "Feature",
  "properties": {
    "gn:admin1_code":"4",
    "gn:asciiname":"Jhok Ghilja",
    "gn:country_code":"PK",
    "gn:dem":255,
    "gn:feature_class":"P",
    "gn:feature_code":"PPL",
    "gn:name":"Jhok Ghilja",
    "gn:population":0,
    "gn:timezone":"Asia/Karachi",
    "iso:country":"PK",
    "wof:name":"Jhok Ghilja",
    "wof:placetype":"locality"
},
  "geometry": {"coordinates":[70.47143,30.99815],"type":"Point"}
}