{
  "type": "Feature",
  "properties": {
    "gn:admin1_code":"4",
    "gn:asciiname":"Ghouswala",
    "gn:country_code":"PK",
    "gn:dem":129,
    "gn:feature_class":"P",
    "gn:feature_code":"PPL",
    "gn:name":"Ghouswala",
    "gn:population":0,
    "gn:timezone":"Asia/Karachi",
    "iso:country":"PK",
    "name:eng_x_preferred":[
        "Ghausw\u0101la"
    ],
    "wof:name":"Ghouswala",
    "wof:placetype":"locality"
},
  "geometry": {"coordinates":[70.88781,30.44875],"type":"Point"}
}