{
  "type": "Feature",
  "properties": {
    "gn:admin1_code":"04",
    "gn:asciiname":"Rakh Jalalpur",
    "gn:country_code":"PK",
    "gn:dem":272,
    "gn:feature_class":"P",
    "gn:feature_code":"PPL",
    "gn:name":"Rakh Jal\u0101lpur",
    "gn:population":0,
    "gn:timezone":"Asia/Karachi",
    "iso:country":"PK",
    "wof:name":"Rakh Jalalpur",
    "wof:placetype":"locality"
},
  "geometry": {"coordinates":[73.40000000000001,32.68333],"type":"Point"}
}