{
  "type": "Feature",
  "properties": {
    "gn:admin1_code":"4",
    "gn:asciiname":"Dhok Chamiara",
    "gn:country_code":"PK",
    "gn:dem":349,
    "gn:feature_class":"P",
    "gn:feature_code":"PPL",
    "gn:name":"Dhok Chamiara",
    "gn:population":0,
    "gn:timezone":"Asia/Karachi",
    "iso:country":"PK",
    "name:und_x_variant":[
        "Dhok Chanjiara"
    ],
    "wof:name":"Dhok Chamiara",
    "wof:placetype":"locality"
},
  "geometry": {"coordinates":[73.46655,32.88643],"type":"Point"}
}