{
  "type": "Feature",
  "properties": {
    "gn:admin1_code":"5.0",
    "gn:asciiname":"Faqir Muhammad Khokar",
    "gn:country_code":"PK",
    "gn:dem":49,
    "gn:feature_class":"P",
    "gn:feature_code":"PPL",
    "gn:name":"Faqir Muhammad Khokar",
    "gn:population":0,
    "gn:timezone":"Asia/Karachi",
    "iso:country":"PK",
    "wof:name":"Faqir Muhammad Khokar",
    "wof:placetype":"locality"
},
  "geometry": {"coordinates":[67.55396999999999,27.8873],"type":"Point"}
}