{
  "type": "Feature",
  "properties": {
    "gn:admin1_code":"4.0",
    "gn:asciiname":"Mullahki Jhugi",
    "gn:country_code":"PK",
    "gn:dem":205,
    "gn:feature_class":"P",
    "gn:feature_code":"PPL",
    "gn:name":"Mullahki Jhugi",
    "gn:population":0,
    "gn:timezone":"Asia/Karachi",
    "iso:country":"PK",
    "wof:name":"Mullahki Jhugi",
    "wof:placetype":"locality"
},
  "geometry": {"coordinates":[73.0607,32.58126],"type":"Point"}
}