{
  "type": "Feature",
  "properties": {
    "gn:admin1_code":"3",
    "gn:asciiname":"Khiari",
    "gn:country_code":"PK",
    "gn:dem":1546,
    "gn:feature_class":"P",
    "gn:feature_code":"PPL",
    "gn:name":"Khiari",
    "gn:population":0,
    "gn:timezone":"Asia/Karachi",
    "iso:country":"PK",
    "name:ceb_x_preferred":[
        "Kh\u012b\u0101r\u012b"
    ],
    "name:eng_x_preferred":[
        "Khay\u0101ri"
    ],
    "name:fas_x_preferred":[
        "\u062e\u06cc\u0627\u0631\u06cc"
    ],
    "name:msa_x_preferred":[
        "Khiari"
    ],
    "name:swe_x_preferred":[
        "Kh\u012b\u0101r\u012b"
    ],
    "wof:name":"Khiari",
    "wof:placetype":"locality"
},
  "geometry": {"coordinates":[71.87481,35.61207],"type":"Point"}
}