{
  "type": "Feature",
  "properties": {
    "gn:admin1_code":"04",
    "gn:asciiname":"Samrai",
    "gn:country_code":"PK",
    "gn:dem":251,
    "gn:feature_class":"P",
    "gn:feature_code":"PPL",
    "gn:name":"Samrai",
    "gn:population":0,
    "gn:timezone":"Asia/Karachi",
    "iso:country":"PK",
    "name:und_x_variant":[
        "Samr\u0101i"
    ],
    "wof:name":"Samrai",
    "wof:placetype":"locality"
},
  "geometry": {"coordinates":[75.02036,32.19813],"type":"Point"}
}