{
  "type": "Feature",
  "properties": {
    "gn:admin1_code":"1.0",
    "gn:asciiname":"Chira Khargai",
    "gn:country_code":"PK",
    "gn:dem":490,
    "gn:feature_class":"P",
    "gn:feature_code":"PPL",
    "gn:name":"Chira Khargai",
    "gn:population":0,
    "gn:timezone":"Asia/Karachi",
    "iso:country":"PK",
    "wof:name":"Chira Khargai",
    "wof:placetype":"locality"
},
  "geometry": {"coordinates":[71.39131,33.93256],"type":"Point"}
}