{
  "type": "Feature",
  "properties": {
    "gn:admin1_code":"3.0",
    "gn:asciiname":"Kuz Shudag",
    "gn:country_code":"PK",
    "gn:dem":408,
    "gn:feature_class":"P",
    "gn:feature_code":"PPL",
    "gn:name":"Kuz Shudag",
    "gn:population":0,
    "gn:timezone":"Asia/Karachi",
    "iso:country":"PK",
    "name:eng_x_preferred":[
        "Koz Shodag"
    ],
    "name:und_x_variant":[
        "Sheod\u0101g B\u0101la",
        "Kuz Shudag"
    ],
    "wof:name":"Kuz Shudag",
    "wof:placetype":"locality"
},
  "geometry": {"coordinates":[71.74809999999999,34.36231],"type":"Point"}
}