{
  "type": "Feature",
  "properties": {
    "gn:admin1_code":"4.0",
    "gn:asciiname":"Khu Sianwala",
    "gn:country_code":"PK",
    "gn:dem":97,
    "gn:feature_class":"P",
    "gn:feature_code":"PPL",
    "gn:name":"Khu Sianwala",
    "gn:population":0,
    "gn:timezone":"Asia/Karachi",
    "iso:country":"PK",
    "name:und_x_variant":[
        "Khu Shan\u0101nw\u0101la"
    ],
    "wof:name":"Khu Sianwala",
    "wof:placetype":"locality"
},
  "geometry": {"coordinates":[71.02013000000002,29.14874],"type":"Point"}
}