{
  "type": "Feature",
  "properties": {
    "gn:admin1_code":"2.0",
    "gn:asciiname":"Thal",
    "gn:country_code":"PK",
    "gn:dem":1478,
    "gn:feature_class":"P",
    "gn:feature_code":"PPL",
    "gn:name":"Thal",
    "gn:population":0,
    "gn:timezone":"Asia/Karachi",
    "iso:country":"PK",
    "name:als_x_preferred":[
        "Thal"
    ],
    "name:ceb_x_preferred":[
        "Thal"
    ],
    "name:deu_x_preferred":[
        "Thal"
    ],
    "name:epo_x_preferred":[
        "Thal"
    ],
    "name:fra_x_preferred":[
        "Thal"
    ],
    "name:ita_x_preferred":[
        "Thal"
    ],
    "name:nld_x_preferred":[
        "Thal"
    ],
    "name:pol_x_preferred":[
        "Thal"
    ],
    "name:spa_x_preferred":[
        "Thal"
    ],
    "name:swe_x_preferred":[
        "Thal"
    ],
    "name:vol_x_preferred":[
        "Thal"
    ],
    "wof:name":"Thal",
    "wof:placetype":"locality"
},
  "geometry": {"coordinates":[69.80888,30.35033],"type":"Point"}
}