{
  "type": "Feature",
  "properties": {
    "gn:admin1_code":"5.0",
    "gn:asciiname":"Goth Chaudhry Yusuf",
    "gn:country_code":"PK",
    "gn:dem":24,
    "gn:feature_class":"P",
    "gn:feature_code":"PPL",
    "gn:name":"Goth Chaudhry Yusuf",
    "gn:population":0,
    "gn:timezone":"Asia/Karachi",
    "iso:country":"PK",
    "name:und_x_variant":[
        "Chaudhri Yousaf"
    ],
    "wof:name":"Goth Chaudhry Yusuf",
    "wof:placetype":"locality"
},
  "geometry": {"coordinates":[68.70394,25.69623],"type":"Point"}
}