{
  "type": "Feature",
  "properties": {
    "gn:admin1_code":"4.0",
    "gn:asciiname":"Naganpura",
    "gn:country_code":"PK",
    "gn:dem":136,
    "gn:feature_class":"P",
    "gn:feature_code":"PPL",
    "gn:name":"Naganpura",
    "gn:population":0,
    "gn:timezone":"Asia/Karachi",
    "iso:country":"PK",
    "wof:name":"Naganpura",
    "wof:placetype":"locality"
},
  "geometry": {"coordinates":[72.55631,29.72365],"type":"Point"}
}