{
  "type": "Feature",
  "properties": {
    "gn:admin1_code":"3",
    "gn:asciiname":"Keba",
    "gn:country_code":"PK",
    "gn:dem":1689,
    "gn:feature_class":"P",
    "gn:feature_code":"PPL",
    "gn:name":"Keba",
    "gn:population":0,
    "gn:timezone":"Asia/Karachi",
    "iso:country":"PK",
    "name:eng_x_preferred":[
        "Keba"
    ],
    "wof:name":"Keba",
    "wof:placetype":"locality"
},
  "geometry": {"coordinates":[72.61570999999998,35.31491],"type":"Point"}
}