{
  "type": "Feature",
  "properties": {
    "gn:admin1_code":"2.0",
    "gn:asciiname":"Ghous Muhammad Kaul",
    "gn:country_code":"PK",
    "gn:dem":2324,
    "gn:feature_class":"P",
    "gn:feature_code":"PPL",
    "gn:name":"Ghous Muhammad Kaul",
    "gn:population":0,
    "gn:timezone":"Asia/Karachi",
    "iso:country":"PK",
    "wof:name":"Ghous Muhammad Kaul",
    "wof:placetype":"locality"
},
  "geometry": {"coordinates":[66.8112,30.90235],"type":"Point"}
}