{
  "type": "Feature",
  "properties": {
    "gn:admin1_code":"3",
    "gn:asciiname":"Sadiqabad",
    "gn:country_code":"PK",
    "gn:dem":1174,
    "gn:feature_class":"P",
    "gn:feature_code":"PPL",
    "gn:name":"Sadiqabad",
    "gn:population":0,
    "gn:timezone":"Asia/Karachi",
    "iso:country":"PK",
    "name:und_x_variant":[
        "Mehr\u0101n di B\u0101ndi",
        "Mehran di B\u0101ndi"
    ],
    "wof:name":"Sadiqabad",
    "wof:placetype":"locality"
},
  "geometry": {"coordinates":[73.20739,34.29733],"type":"Point"}
}