{
  "type": "Feature",
  "properties": {
    "gn:admin1_code":"3",
    "gn:asciiname":"Sadiqabad",
    "gn:country_code":"PK",
    "gn:dem":1174,
    "gn:feature_class":"P",
    "gn:feature_code":"PPL",
    "gn:name":"Sadiqabad",
    "gn:population":0,
    "gn:timezone":"Asia/Karachi",
    "iso:country":"PK",
    "name:ell_x_preferred":[
        "\u03a3\u03b1\u03bd\u03c4\u03b9\u03ba\u03b1\u03bc\u03c0\u03ac\u03bd\u03c4"
    ],
    "name:heb_x_preferred":[
        "\u05e1\u05d0\u05d3\u05d9\u05e7\u05d0\u05d1\u05d0\u05d3"
    ],
    "name:hun_x_preferred":[
        "Sadiqabad"
    ],
    "name:ind_x_preferred":[
        "Sadiqabad"
    ],
    "name:jpn_x_preferred":[
        "\u30b5\u30c7\u30a3\u30ab\u30d0\u30fc\u30c9"
    ],
    "name:kor_x_preferred":[
        "\uc0ac\ub514\uce74\ubc14\ub4dc"
    ],
    "name:tur_x_preferred":[
        "Sadiqabad"
    ],
    "name:ukr_x_preferred":[
        "\u0421\u0430\u0434\u0456\u043a\u0430\u0431\u0430\u0434"
    ],
    "name:und_x_variant":[
        "Mehr\u0101n di B\u0101ndi",
        "Mehran di B\u0101ndi"
    ],
    "name:zho_cn_x_preferred":[
        "\u8428\u8fea\u52a0\u5df4\u5fb7"
    ],
    "name:zho_tw_x_preferred":[
        "\u85a9\u8fea\u5361\u5df4\u5fb7"
    ],
    "wof:name":"Sadiqabad",
    "wof:placetype":"locality"
},
  "geometry": {"coordinates":[73.20739,34.29733],"type":"Point"}
}