{
  "type": "Feature",
  "properties": {
    "gn:admin1_code":"5",
    "gn:asciiname":"Mangu",
    "gn:country_code":"PK",
    "gn:dem":47,
    "gn:feature_class":"P",
    "gn:feature_code":"PPL",
    "gn:name":"Mangu",
    "gn:population":0,
    "gn:timezone":"Asia/Karachi",
    "iso:country":"PK",
    "name:ceb_x_preferred":[
        "Mangu"
    ],
    "name:ita_x_preferred":[
        "Mangu"
    ],
    "name:swe_x_preferred":[
        "Mangu"
    ],
    "name:und_x_variant":[
        "Mang"
    ],
    "wof:name":"Mangu",
    "wof:placetype":"locality"
},
  "geometry": {"coordinates":[68.23183,26.95014],"type":"Point"}
}