{
  "type": "Feature",
  "properties": {
    "gn:admin1_code":"5",
    "gn:asciiname":"Goth Bakhsh Ali Talpur",
    "gn:country_code":"PK",
    "gn:dem":14,
    "gn:feature_class":"P",
    "gn:feature_code":"PPL",
    "gn:name":"Goth Bakhsh Ali T\u0101lpur",
    "gn:population":0,
    "gn:timezone":"Asia/Karachi",
    "iso:country":"PK",
    "wof:name":"Goth Bakhsh Ali Talpur",
    "wof:placetype":"locality"
},
  "geometry": {"coordinates":[68.75875000000001,25.03657],"type":"Point"}
}