{
  "type": "Feature",
  "properties": {
    "gn:admin1_code":"4",
    "gn:asciiname":"Basti Khofli",
    "gn:country_code":"PK",
    "gn:dem":175,
    "gn:feature_class":"P",
    "gn:feature_code":"PPL",
    "gn:name":"Basti Khofli",
    "gn:population":0,
    "gn:timezone":"Asia/Karachi",
    "iso:country":"PK",
    "name:eng_x_preferred":[
        "Belab"
    ],
    "wof:name":"Basti Khofli",
    "wof:placetype":"locality"
},
  "geometry": {"coordinates":[70.54693,30.31248],"type":"Point"}
}