{
  "type": "Feature",
  "properties": {
    "gn:admin1_code":"5",
    "gn:asciiname":"Mir Bandeh Ali jo Goth",
    "gn:country_code":"PK",
    "gn:dem":15,
    "gn:feature_class":"P",
    "gn:feature_code":"PPL",
    "gn:name":"M\u012br Bandeh Ali jo Goth",
    "gn:population":0,
    "gn:timezone":"Asia/Karachi",
    "iso:country":"PK",
    "wof:name":"Mir Bandeh Ali jo Goth",
    "wof:placetype":"locality"
},
  "geometry": {"coordinates":[68.97221999999999,25.16389],"type":"Point"}
}