{
  "type": "Feature",
  "properties": {
    "gn:admin1_code":"4.0",
    "gn:asciiname":"Nakka Afghan",
    "gn:country_code":"PK",
    "gn:dem":365,
    "gn:feature_class":"P",
    "gn:feature_code":"PPL",
    "gn:name":"Nakka Afghan",
    "gn:population":0,
    "gn:timezone":"Asia/Karachi",
    "iso:country":"PK",
    "name:und_x_variant":[
        "Nawl Nakka",
        "Nakka Afghan"
    ],
    "wof:name":"Nakka Afghan",
    "wof:placetype":"locality"
},
  "geometry": {"coordinates":[71.83424000000002,33.165],"type":"Point"}
}