{
  "type": "Feature",
  "properties": {
    "gn:admin1_code":"5",
    "gn:asciiname":"Saltar Dino Sangi",
    "gn:country_code":"PK",
    "gn:dem":54,
    "gn:feature_class":"P",
    "gn:feature_code":"PPL",
    "gn:name":"Saltar Dino Sangi",
    "gn:population":0,
    "gn:timezone":"Asia/Karachi",
    "iso:country":"PK",
    "name:und_x_variant":[
        "Satt\u0101r-D\u012bno-S\u0101ng"
    ],
    "wof:name":"Saltar Dino Sangi",
    "wof:placetype":"locality"
},
  "geometry": {"coordinates":[68.20777,27.61421],"type":"Point"}
}