{
  "type": "Feature",
  "properties": {
    "gn:admin1_code":"4.0",
    "gn:asciiname":"Basti Chandia",
    "gn:country_code":"PK",
    "gn:dem":95,
    "gn:feature_class":"P",
    "gn:feature_code":"PPL",
    "gn:name":"Basti Ch\u0101ndia",
    "gn:population":0,
    "gn:timezone":"Asia/Karachi",
    "iso:country":"PK",
    "wof:name":"Basti Chandia",
    "wof:placetype":"locality"
},
  "geometry": {"coordinates":[70.68604000000001,29.00623],"type":"Point"}
}