{
  "type": "Feature",
  "properties": {
    "gn:admin1_code":"6",
    "gn:asciiname":"Bhabban",
    "gn:country_code":"PK",
    "gn:dem":2441,
    "gn:feature_class":"P",
    "gn:feature_code":"PPL",
    "gn:name":"Bhabban",
    "gn:population":0,
    "gn:timezone":"Asia/Karachi",
    "iso:country":"PK",
    "name:und_x_variant":[
        "Babbanwal",
        "Bhabb\u0101n"
    ],
    "wof:name":"Bhabban",
    "wof:placetype":"locality"
},
  "geometry": {"coordinates":[74.1263,34.7307],"type":"Point"}
}