{
  "type": "Feature",
  "properties": {
    "gn:admin1_code":"7.0",
    "gn:asciiname":"Sikandar di Baihk",
    "gn:country_code":"PK",
    "gn:dem":3762,
    "gn:feature_class":"P",
    "gn:feature_code":"PPL",
    "gn:name":"Sikandar di Baihk",
    "gn:population":0,
    "gn:timezone":"Asia/Karachi",
    "iso:country":"PK",
    "wof:name":"Sikandar di Baihk",
    "wof:placetype":"locality"
},
  "geometry": {"coordinates":[73.89121999999998,35.88304],"type":"Point"}
}