{
  "type": "Feature",
  "properties": {
    "gn:admin1_code":"4",
    "gn:asciiname":"Rahdarianwala",
    "gn:country_code":"PK",
    "gn:dem":192,
    "gn:feature_class":"P",
    "gn:feature_code":"PPL",
    "gn:name":"Rahdarianwala",
    "gn:population":0,
    "gn:timezone":"Asia/Karachi",
    "iso:country":"PK",
    "name:und_x_variant":[
        "R\u0101hd\u0101riw\u0101la"
    ],
    "wof:name":"Rahdarianwala",
    "wof:placetype":"locality"
},
  "geometry": {"coordinates":[71.38979,32.10858],"type":"Point"}
}