{
  "type": "Feature",
  "properties": {
    "gn:admin1_code":"4",
    "gn:asciiname":"Jora",
    "gn:country_code":"PK",
    "gn:dem":245,
    "gn:feature_class":"P",
    "gn:feature_code":"PPL",
    "gn:name":"Jora",
    "gn:population":0,
    "gn:timezone":"Asia/Karachi",
    "iso:country":"PK",
    "name:ceb_x_preferred":[
        "Jora"
    ],
    "name:deu_x_preferred":[
        "Jora"
    ],
    "name:fra_x_preferred":[
        "Jora"
    ],
    "name:swe_x_preferred":[
        "Jora"
    ],
    "wof:name":"Jora",
    "wof:placetype":"locality"
},
  "geometry": {"coordinates":[74.06506999999998,32.64425],"type":"Point"}
}