{
  "type": "Feature",
  "properties": {
    "gn:admin1_code":"1.0",
    "gn:asciiname":"Laklargai",
    "gn:country_code":"PK",
    "gn:dem":2312,
    "gn:feature_class":"P",
    "gn:feature_code":"PPL",
    "gn:name":"Laklargai",
    "gn:population":0,
    "gn:timezone":"Asia/Karachi",
    "iso:country":"PK",
    "wof:name":"Laklargai",
    "wof:placetype":"locality"
},
  "geometry": {"coordinates":[69.4315,32.53303],"type":"Point"}
}