{
  "type": "Feature",
  "properties": {
    "gn:admin1_code":"3.0",
    "gn:asciiname":"Gedar",
    "gn:country_code":"PK",
    "gn:dem":2272,
    "gn:feature_class":"P",
    "gn:feature_code":"PPL",
    "gn:name":"Gedar",
    "gn:population":0,
    "gn:timezone":"Asia/Karachi",
    "iso:country":"PK",
    "wof:name":"Gedar",
    "wof:placetype":"locality"
},
  "geometry": {"coordinates":[72.88598,35.55248],"type":"Point"}
}