{
  "type": "Feature",
  "properties": {
    "gn:admin1_code":"6",
    "gn:asciiname":"Tutanwala",
    "gn:country_code":"PK",
    "gn:dem":298,
    "gn:feature_class":"P",
    "gn:feature_code":"PPL",
    "gn:name":"Tutanwala",
    "gn:population":0,
    "gn:timezone":"Asia/Karachi",
    "iso:country":"PK",
    "wof:name":"Tutanwala",
    "wof:placetype":"locality"
},
  "geometry": {"coordinates":[74.36350999999998,32.85113],"type":"Point"}
}