{
  "type": "Feature",
  "properties": {
    "gn:admin1_code":"2.0",
    "gn:asciiname":"Haji Mahar",
    "gn:country_code":"PK",
    "gn:dem":1554,
    "gn:feature_class":"P",
    "gn:feature_code":"PPL",
    "gn:name":"Haji Mahar",
    "gn:population":0,
    "gn:timezone":"Asia/Karachi",
    "iso:country":"PK",
    "wof:name":"Haji Mahar",
    "wof:placetype":"locality"
},
  "geometry": {"coordinates":[66.67142,30.7309],"type":"Point"}
}