{
  "type": "Feature",
  "properties": {
    "gn:admin1_code":"4",
    "gn:asciiname":"Dhorewala",
    "gn:country_code":"PK",
    "gn:dem":124,
    "gn:feature_class":"P",
    "gn:feature_code":"PPL",
    "gn:name":"Dhorewala",
    "gn:population":0,
    "gn:timezone":"Asia/Karachi",
    "iso:country":"PK",
    "wof:name":"Dhorewala",
    "wof:placetype":"locality"
},
  "geometry": {"coordinates":[71.92738,29.66494],"type":"Point"}
}