{
  "type": "Feature",
  "properties": {
    "gn:admin1_code":"2.0",
    "gn:asciiname":"Hasal Khan Gurnari",
    "gn:country_code":"PK",
    "gn:dem":751,
    "gn:feature_class":"P",
    "gn:feature_code":"PPL",
    "gn:name":"Hasal Khan Gurnari",
    "gn:population":0,
    "gn:timezone":"Asia/Karachi",
    "iso:country":"PK",
    "wof:name":"Hasal Khan Gurnari",
    "wof:placetype":"locality"
},
  "geometry": {"coordinates":[64.22962,26.414],"type":"Point"}
}