{
  "type": "Feature",
  "properties": {
    "gn:admin1_code":"5.0",
    "gn:asciiname":"Goth Morio Lashari",
    "gn:country_code":"PK",
    "gn:dem":13,
    "gn:feature_class":"P",
    "gn:feature_code":"PPL",
    "gn:name":"Goth Morio Lashari",
    "gn:population":0,
    "gn:timezone":"Asia/Karachi",
    "iso:country":"PK",
    "name:und_x_variant":[
        "Goth Morio L\u0101sh\u0101ri"
    ],
    "wof:name":"Goth Morio Lashari",
    "wof:placetype":"locality"
},
  "geometry": {"coordinates":[68.25731999999999,24.89745],"type":"Point"}
}