{
  "type": "Feature",
  "properties": {
    "gn:admin1_code":"6.0",
    "gn:asciiname":"Bhurota",
    "gn:country_code":"PK",
    "gn:dem":417,
    "gn:feature_class":"P",
    "gn:feature_code":"PPL",
    "gn:name":"Bhurota",
    "gn:population":0,
    "gn:timezone":"Asia/Karachi",
    "iso:country":"PK",
    "wof:name":"Bhurota",
    "wof:placetype":"locality"
},
  "geometry": {"coordinates":[73.60005,33.43306],"type":"Point"}
}