{
  "type": "Feature",
  "properties": {
    "gn:admin1_code":"4.0",
    "gn:asciiname":"Asim Chauk",
    "gn:country_code":"PK",
    "gn:dem":127,
    "gn:feature_class":"P",
    "gn:feature_code":"PPL",
    "gn:name":"Asim Chauk",
    "gn:population":0,
    "gn:timezone":"Asia/Karachi",
    "iso:country":"PK",
    "name:eng_x_preferred":[
        "Asim Choke"
    ],
    "wof:name":"Asim Chauk",
    "wof:placetype":"locality"
},
  "geometry": {"coordinates":[71.88592,29.98091],"type":"Point"}
}