{
  "type": "Feature",
  "properties": {
    "gn:admin1_code":"7.0",
    "gn:asciiname":"Satsari",
    "gn:country_code":"PK",
    "gn:dem":3099,
    "gn:feature_class":"P",
    "gn:feature_code":"PPL",
    "gn:name":"Satsari",
    "gn:population":0,
    "gn:timezone":"Asia/Karachi",
    "iso:country":"PK",
    "wof:name":"Satsari",
    "wof:placetype":"locality"
},
  "geometry": {"coordinates":[73.8069,35.28100999999999],"type":"Point"}
}