{
  "type": "Feature",
  "properties": {
    "gn:admin1_code":"5",
    "gn:asciiname":"Goth Ghulam Muhammad Dhari",
    "gn:country_code":"PK",
    "gn:dem":30,
    "gn:feature_class":"P",
    "gn:feature_code":"PPL",
    "gn:name":"Goth Ghulam Muhammad Dhari",
    "gn:population":0,
    "gn:timezone":"Asia/Karachi",
    "iso:country":"PK",
    "name:und_x_variant":[
        "Ghul\u0101m Muhammad D\u0101hr\u012b"
    ],
    "wof:name":"Goth Ghulam Muhammad Dhari",
    "wof:placetype":"locality"
},
  "geometry": {"coordinates":[68.71334,26.30729],"type":"Point"}
}