{
  "type": "Feature",
  "properties": {
    "gn:admin1_code":"4.0",
    "gn:asciiname":"Piranwala Bhaik",
    "gn:country_code":"PK",
    "gn:dem":196,
    "gn:feature_class":"P",
    "gn:feature_code":"PPL",
    "gn:name":"Piranwala Bhaik",
    "gn:population":0,
    "gn:timezone":"Asia/Karachi",
    "iso:country":"PK",
    "wof:name":"Piranwala Bhaik",
    "wof:placetype":"locality"
},
  "geometry": {"coordinates":[74.00971,31.32208],"type":"Point"}
}