{
  "type": "Feature",
  "properties": {
    "gn:admin1_code":"2.0",
    "gn:asciiname":"Karki",
    "gn:country_code":"PK",
    "gn:dem":451,
    "gn:feature_class":"P",
    "gn:feature_code":"PPL",
    "gn:name":"Karki",
    "gn:population":0,
    "gn:timezone":"Asia/Karachi",
    "iso:country":"PK",
    "name:fra_x_preferred":[
        "Karki"
    ],
    "name:ita_x_preferred":[
        "Karki"
    ],
    "name:nld_x_preferred":[
        "Karki"
    ],
    "name:por_x_preferred":[
        "Karki"
    ],
    "name:rus_x_preferred":[
        "\u041a\u044f\u0440\u043a\u0438"
    ],
    "wof:name":"Karki",
    "wof:placetype":"locality"
},
  "geometry": {"coordinates":[63.69213000000001,26.01768],"type":"Point"}
}