{
  "type": "Feature",
  "properties": {
    "gn:admin1_code":"5.0",
    "gn:asciiname":"Goth Ladha Khan Dahri",
    "gn:country_code":"PK",
    "gn:dem":42,
    "gn:feature_class":"P",
    "gn:feature_code":"PPL",
    "gn:name":"Goth Ladha Khan Dahri",
    "gn:population":0,
    "gn:timezone":"Asia/Karachi",
    "iso:country":"PK",
    "wof:name":"Goth Ladha Khan Dahri",
    "wof:placetype":"locality"
},
  "geometry": {"coordinates":[68.26138,26.62446],"type":"Point"}
}