{
  "type": "Feature",
  "properties": {
    "gn:admin1_code":"1.0",
    "gn:asciiname":"Nawe Kalle",
    "gn:country_code":"PK",
    "gn:dem":1000,
    "gn:feature_class":"P",
    "gn:feature_code":"PPL",
    "gn:name":"Nawe Kalle",
    "gn:population":0,
    "gn:timezone":"Asia/Karachi",
    "iso:country":"PK",
    "wof:name":"Nawe Kalle",
    "wof:placetype":"locality"
},
  "geometry": {"coordinates":[71.31354,33.76195],"type":"Point"}
}