{
  "type": "Feature",
  "properties": {
    "iso:country":"PK",
    "qs:gn_pop":0,
    "qs:name":"Arain Road",
    "qs:name_adm0":"Pakistan",
    "qs:name_adm1":"Sindh",
    "qs:photos":3,
    "qs:photos_1k":1,
    "qs:photos_9k":1,
    "qs:photos_9r":1,
    "qs:photos_all":3,
    "qs:photos_sr":1,
    "qs:placetype":"Town",
    "qs:pop_sr":"0",
    "qs:woe_adm0":23424922,
    "wof:name":"Arain Road",
    "wof:placetype":"locality"
},
  "geometry": {"coordinates":[68.817601,27.727654],"type":"Point"}
}