{
  "type": "Feature",
  "properties": {
    "iso:country":"PK",
    "name:ara_x_preferred":[
        "\u0628\u064a\u0634\u0627\u0645"
    ],
    "name:ben_x_preferred":[
        "\u09ac\u09c7\u09b6\u09be\u09ae"
    ],
    "name:dan_x_preferred":[
        "Besham"
    ],
    "name:dut_x_preferred":[
        "Besham"
    ],
    "name:eng_x_preferred":[
        "Besham"
    ],
    "name:fin_x_preferred":[
        "Besham"
    ],
    "name:fre_x_preferred":[
        "Besham"
    ],
    "name:gre_x_preferred":[
        "\u039c\u03c0\u03ad\u03c3\u03b1\u03bc"
    ],
    "name:guj_x_preferred":[
        "\u0aac\u0ac7\u0ab6\u0aae"
    ],
    "name:hin_x_preferred":[
        "\u092c\u0947\u0936\u093e\u092e"
    ],
    "name:ind_x_preferred":[
        "Besham"
    ],
    "name:ita_x_preferred":[
        "Besham"
    ],
    "name:jpn_x_preferred":[
        "\u30d9\u30b7\u30e3\u30e0"
    ],
    "name:kan_x_preferred":[
        "\u0cac\u0cc6\u0cb8\u0cae\u0ccd"
    ],
    "name:kor_x_preferred":[
        "\ubca0\uc2a4\ud584"
    ],
    "name:lav_x_preferred":[
        "Be\u0161ama"
    ],
    "name:lit_x_preferred":[
        "Be\u0161amas"
    ],
    "name:mar_x_preferred":[
        "\u092c\u0947\u0936\u092e"
    ],
    "name:may_x_preferred":[
        "Besham"
    ],
    "name:nob_x_preferred":[
        "Besham"
    ],
    "name:pol_x_preferred":[
        "Besham"
    ],
    "name:por_x_preferred":[
        "Besham"
    ],
    "name:rus_x_preferred":[
        "\u0411\u0435\u0448\u0430\u043c"
    ],
    "name:sin_x_preferred":[
        "\u0db6\u0dd9\u0dc1\u0dcf\u0db8\u0dca"
    ],
    "name:spa_x_preferred":[
        "Besham"
    ],
    "name:swe_x_preferred":[
        "Besham"
    ],
    "name:tam_x_preferred":[
        "\u0baa\u0bc7\u0bb7\u0bae\u0bcd"
    ],
    "name:tel_x_preferred":[
        "\u0c2c\u0c47\u0c37\u0c02"
    ],
    "name:tha_x_preferred":[
        "\u0e40\u0e1a\u0e0a\u0e2e\u0e32\u0e21"
    ],
    "name:tur_x_preferred":[
        "Besham"
    ],
    "name:ukr_x_preferred":[
        "\u0411\u0435\u0448\u0430\u043c"
    ],
    "name:unk_x_variant":[
        "Bisham"
    ],
    "name:urd_x_preferred":[
        "\u0628\u06cc\u0634\u0627\u0645"
    ],
    "name:vie_x_preferred":[
        "Besham"
    ],
    "qs:gn_country":"PK",
    "qs:gn_fcode":"PPL",
    "qs:gn_pop":0,
    "qs:name":"Besham Qala",
    "qs:name_adm0":"Pakistan",
    "qs:name_adm1":"North-West Frontier",
    "qs:photos":46,
    "qs:photos_1k":9,
    "qs:photos_9k":1,
    "qs:photos_9r":2,
    "qs:photos_all":46,
    "qs:photos_sr":2,
    "qs:placetype":"Town",
    "qs:pop_sr":"0",
    "qs:woe_adm0":23424922,
    "wof:name":"Besham Qala",
    "wof:placetype":"locality"
},
  "geometry": {"coordinates":[72.87908,34.92995],"type":"Point"}
}