{
  "type": "Feature",
  "properties": {
    "gn:admin1_code":"4.0",
    "gn:asciiname":"Manno Abad Dhakampur",
    "gn:country_code":"PK",
    "gn:dem":213,
    "gn:feature_class":"P",
    "gn:feature_code":"PPL",
    "gn:name":"Manno Abad Dhakampur",
    "gn:population":0,
    "gn:timezone":"Asia/Karachi",
    "iso:country":"PK",
    "name:und_x_variant":[
        "Tukampura"
    ],
    "wof:name":"Manno Abad Dhakampur",
    "wof:placetype":"locality"
},
  "geometry": {"coordinates":[74.25783,31.76692],"type":"Point"}
}