{
  "type": "Feature",
  "properties": {
    "gn:admin1_code":"3.0",
    "gn:asciiname":"Bero",
    "gn:country_code":"PK",
    "gn:dem":1037,
    "gn:feature_class":"P",
    "gn:feature_code":"PPL",
    "gn:name":"Bero",
    "gn:population":0,
    "gn:timezone":"Asia/Karachi",
    "iso:country":"PK",
    "name:und_x_variant":[
        "Bairo",
        "Beroo",
        "Bero"
    ],
    "wof:name":"Bero",
    "wof:placetype":"locality"
},
  "geometry": {"coordinates":[72.68738,34.55956],"type":"Point"}
}