{
  "type": "Feature",
  "properties": {
    "gn:admin1_code":"3",
    "gn:asciiname":"Laruka",
    "gn:country_code":"PK",
    "gn:dem":1150,
    "gn:feature_class":"P",
    "gn:feature_code":"PPL",
    "gn:name":"Laruka",
    "gn:population":0,
    "gn:timezone":"Asia/Karachi",
    "iso:country":"PK",
    "name:eng_x_preferred":[
        "Laruka"
    ],
    "wof:name":"Laruka",
    "wof:placetype":"locality"
},
  "geometry": {"coordinates":[72.16037,34.59693],"type":"Point"}
}