{
  "type": "Feature",
  "properties": {
    "gn:admin1_code":"1.0",
    "gn:asciiname":"Bobali",
    "gn:country_code":"PK",
    "gn:dem":646,
    "gn:feature_class":"P",
    "gn:feature_code":"PPL",
    "gn:name":"Bobali",
    "gn:population":0,
    "gn:timezone":"Asia/Karachi",
    "iso:country":"PK",
    "name:und_x_variant":[
        "Bobli"
    ],
    "wof:name":"Bobali",
    "wof:placetype":"locality"
},
  "geometry": {"coordinates":[70.32477,33.07198],"type":"Point"}
}