{
  "type": "Feature",
  "properties": {
    "gn:admin1_code":"4.0",
    "gn:asciiname":"Dhok Rohianwali",
    "gn:country_code":"PK",
    "gn:dem":507,
    "gn:feature_class":"P",
    "gn:feature_code":"PPL",
    "gn:name":"Dhok Rohianwali",
    "gn:population":0,
    "gn:timezone":"Asia/Karachi",
    "iso:country":"PK",
    "name:und_x_variant":[
        "Dhok Rai\u0101nw\u0101li"
    ],
    "wof:name":"Dhok Rohianwali",
    "wof:placetype":"locality"
},
  "geometry": {"coordinates":[72.76328000000002,33.43857],"type":"Point"}
}