{
  "type": "Feature",
  "properties": {
    "gn:admin1_code":"7.0",
    "gn:asciiname":"Salibur",
    "gn:country_code":"PK",
    "gn:dem":3237,
    "gn:feature_class":"P",
    "gn:feature_code":"PPL",
    "gn:name":"Salibur",
    "gn:population":0,
    "gn:timezone":"Asia/Karachi",
    "iso:country":"PK",
    "wof:name":"Salibur",
    "wof:placetype":"locality"
},
  "geometry": {"coordinates":[74.84496,35.51119],"type":"Point"}
}