{
  "type": "Feature",
  "properties": {
    "gn:admin1_code":"5",
    "gn:asciiname":"Gada",
    "gn:country_code":"PK",
    "gn:dem":36,
    "gn:feature_class":"P",
    "gn:feature_code":"PPL",
    "gn:name":"Gada",
    "gn:population":0,
    "gn:timezone":"Asia/Karachi",
    "iso:country":"PK",
    "name:ceb_x_preferred":[
        "Gada"
    ],
    "name:deu_x_preferred":[
        "Gada"
    ],
    "name:heb_x_preferred":[
        "\u05d2\u05d3\u05d4"
    ],
    "name:swe_x_preferred":[
        "Gada"
    ],
    "name:ukr_x_preferred":[
        "\u0413\u0430\u0434\u0430"
    ],
    "wof:name":"Gada",
    "wof:placetype":"locality"
},
  "geometry": {"coordinates":[68.19620999999999,25.85825],"type":"Point"}
}