{
  "type": "Feature",
  "properties": {
    "gn:admin1_code":"5.0",
    "gn:asciiname":"Gul Hasan Kaleri",
    "gn:country_code":"PK",
    "gn:dem":21,
    "gn:feature_class":"P",
    "gn:feature_code":"PPL",
    "gn:name":"Gul Hasan Kaleri",
    "gn:population":0,
    "gn:timezone":"Asia/Karachi",
    "iso:country":"PK",
    "wof:name":"Gul Hasan Kaleri",
    "wof:placetype":"locality"
},
  "geometry": {"coordinates":[68.48669,25.40844],"type":"Point"}
}