{
  "type": "Feature",
  "properties": {
    "gn:admin1_code":"4.0",
    "gn:asciiname":"Chak Two Hundred Sixty-two Shumali",
    "gn:country_code":"PK",
    "gn:dem":160,
    "gn:feature_class":"P",
    "gn:feature_code":"PPL",
    "gn:name":"Chak Two Hundred Sixty-two Shumali",
    "gn:population":0,
    "gn:timezone":"Asia/Karachi",
    "iso:country":"PK",
    "name:und_x_variant":[
        "Chak Two Hundred Sixty-Two",
        "Chak 262",
        "Chak Two Hundred Sixty-two Shumali"
    ],
    "wof:name":"Chak Two Hundred Sixty-two Shumali",
    "wof:placetype":"locality"
},
  "geometry": {"coordinates":[72.46958000000002,31.35138],"type":"Point"}
}