{
  "type": "Feature",
  "properties": {
    "gn:admin1_code":"4",
    "gn:asciiname":"Chah Sugerwala",
    "gn:country_code":"PK",
    "gn:dem":180,
    "gn:feature_class":"P",
    "gn:feature_code":"PPL",
    "gn:name":"Chah Sugerwala",
    "gn:population":0,
    "gn:timezone":"Asia/Karachi",
    "iso:country":"PK",
    "name:und_x_variant":[
        "Chak Gugera"
    ],
    "wof:name":"Chah Sugerwala",
    "wof:placetype":"locality"
},
  "geometry": {"coordinates":[73.39139,31.00225],"type":"Point"}
}