{
  "type": "Feature",
  "properties": {
    "gn:admin1_code":"4.0",
    "gn:asciiname":"Hasanwala",
    "gn:country_code":"PK",
    "gn:dem":142,
    "gn:feature_class":"P",
    "gn:feature_code":"PPL",
    "gn:name":"Hasanwala",
    "gn:population":0,
    "gn:timezone":"Asia/Karachi",
    "iso:country":"PK",
    "name:und_x_variant":[
        "H\u0101nsew\u0101la"
    ],
    "wof:name":"Hasanwala",
    "wof:placetype":"locality"
},
  "geometry": {"coordinates":[70.96798000000003,30.78994],"type":"Point"}
}