{
  "type": "Feature",
  "properties": {
    "gn:admin1_code":"3.0",
    "gn:asciiname":"Mane Banda",
    "gn:country_code":"PK",
    "gn:dem":307,
    "gn:feature_class":"P",
    "gn:feature_code":"PPL",
    "gn:name":"Mane Banda",
    "gn:population":0,
    "gn:timezone":"Asia/Karachi",
    "iso:country":"PK",
    "name:eng_x_preferred":[
        "M\u0101na B\u0101nda"
    ],
    "wof:name":"Mane Banda",
    "wof:placetype":"locality"
},
  "geometry": {"coordinates":[72.41311999999998,34.02207],"type":"Point"}
}