{
  "type": "Feature",
  "properties": {
    "gn:admin1_code":"4",
    "gn:asciiname":"Basti Mian Juma",
    "gn:country_code":"PK",
    "gn:dem":163,
    "gn:feature_class":"P",
    "gn:feature_code":"PPL",
    "gn:name":"Basti Mian Juma",
    "gn:population":0,
    "gn:timezone":"Asia/Karachi",
    "iso:country":"PK",
    "name:und_x_variant":[
        "Mi\u0101n Juma Zi\u0101rat",
        "Basti Mian Juma"
    ],
    "wof:name":"Basti Mian Juma",
    "wof:placetype":"locality"
},
  "geometry": {"coordinates":[70.66724000000001,31.27691],"type":"Point"}
}