{
  "type": "Feature",
  "properties": {
    "gn:admin1_code":"3",
    "gn:asciiname":"Jingeret",
    "gn:country_code":"PK",
    "gn:dem":1300,
    "gn:feature_class":"P",
    "gn:feature_code":"PPL",
    "gn:name":"Jingeret",
    "gn:population":0,
    "gn:timezone":"Asia/Karachi",
    "iso:country":"PK",
    "name:eng_x_preferred":[
        "Jingeret"
    ],
    "name:urd_x_preferred":[
        "Jinjire\u1e6d"
    ],
    "name:urd_x_variant":[
        "\u062c\u0650\u0646\u0652\u062c\u0650\u0631\u06cc\u0679"
    ],
    "wof:name":"Jingeret",
    "wof:placetype":"locality"
},
  "geometry": {"coordinates":[71.75923,35.52930999999999],"type":"Point"}
}