{
  "type": "Feature",
  "properties": {
    "gn:admin1_code":"3.0",
    "gn:asciiname":"Gulzar Kalle",
    "gn:country_code":"PK",
    "gn:dem":180,
    "gn:feature_class":"P",
    "gn:feature_code":"PPL",
    "gn:name":"Gulzar Kalle",
    "gn:population":0,
    "gn:timezone":"Asia/Karachi",
    "iso:country":"PK",
    "name:urd_x_preferred":[
        "\u06af\u0644\u0632\u0627\u0631 \u06a9\u0644\u06d2"
    ],
    "wof:name":"Gulzar Kalle",
    "wof:placetype":"locality"
},
  "geometry": {"coordinates":[70.83283,31.84321],"type":"Point"}
}