{
  "type": "Feature",
  "properties": {
    "gn:admin1_code":"4.0",
    "gn:asciiname":"Bhelol",
    "gn:country_code":"PK",
    "gn:dem":463,
    "gn:feature_class":"P",
    "gn:feature_code":"PPL",
    "gn:name":"Bhelol",
    "gn:population":0,
    "gn:timezone":"Asia/Karachi",
    "iso:country":"PK",
    "name:und_x_variant":[
        "Bahlol",
        "Bharol",
        "Bhelol"
    ],
    "wof:name":"Bhelol",
    "wof:placetype":"locality"
},
  "geometry": {"coordinates":[72.65609000000001,33.67777],"type":"Point"}
}