{
  "type": "Feature",
  "properties": {
    "gn:admin1_code":"4",
    "gn:asciiname":"Ahata Mir Fattiana",
    "gn:country_code":"PK",
    "gn:dem":168,
    "gn:feature_class":"P",
    "gn:feature_code":"PPL",
    "gn:name":"Ahata Mir Fattiana",
    "gn:population":0,
    "gn:timezone":"Asia/Karachi",
    "iso:country":"PK",
    "wof:name":"Ahata Mir Fattiana",
    "wof:placetype":"locality"
},
  "geometry": {"coordinates":[72.99167,30.85556],"type":"Point"}
}