{
  "type": "Feature",
  "properties": {
    "gn:admin1_code":"4.0",
    "gn:asciiname":"Chak Five Hundred Twenty-three",
    "gn:country_code":"PK",
    "gn:dem":202,
    "gn:feature_class":"P",
    "gn:feature_code":"PPL",
    "gn:name":"Chak Five Hundred Twenty-three",
    "gn:population":0,
    "gn:timezone":"Asia/Karachi",
    "iso:country":"PK",
    "name:und_x_variant":[
        "Jhinda Jangal",
        "Purana Jhinda"
    ],
    "wof:name":"Chak Five Hundred Twenty-three",
    "wof:placetype":"locality"
},
  "geometry": {"coordinates":[73.76179,31.68975],"type":"Point"}
}