{
  "type": "Feature",
  "properties": {
    "gn:admin1_code":"4.0",
    "gn:asciiname":"Dhing Shah",
    "gn:country_code":"PK",
    "gn:dem":192,
    "gn:feature_class":"P",
    "gn:feature_code":"PPL",
    "gn:name":"Dhing Shah",
    "gn:population":0,
    "gn:timezone":"Asia/Karachi",
    "iso:country":"PK",
    "name:fas_x_preferred":[
        "\u062f\u0647\u0646\u06af \u0634\u0627\u0647"
    ],
    "name:urd_x_preferred":[
        "\u062f\u06be\u0646\u06af \u0634\u0627\u06c1"
    ],
    "wof:name":"Dhing Shah",
    "wof:placetype":"locality"
},
  "geometry": {"coordinates":[74.21259999999999,30.93542],"type":"Point"}
}