{
  "type": "Feature",
  "properties": {
    "gn:admin1_code":"4",
    "gn:asciiname":"Mahinwal Parhar",
    "gn:country_code":"PK",
    "gn:dem":107,
    "gn:feature_class":"P",
    "gn:feature_code":"PPL",
    "gn:name":"Mahinwal Parhar",
    "gn:population":0,
    "gn:timezone":"Asia/Karachi",
    "iso:country":"PK",
    "name:und_x_variant":[
        "Mahinw\u0101l Parh\u0101r Parhar",
        "Mahinwal Parhar"
    ],
    "wof:name":"Mahinwal Parhar",
    "wof:placetype":"locality"
},
  "geometry": {"coordinates":[70.73219,29.52992],"type":"Point"}
}