{
  "type": "Feature",
  "properties": {
    "gn:admin1_code":"3",
    "gn:asciiname":"Zor Shalpin",
    "gn:country_code":"PK",
    "gn:dem":1685,
    "gn:feature_class":"P",
    "gn:feature_code":"PPL",
    "gn:name":"Zor Shalpin",
    "gn:population":0,
    "gn:timezone":"Asia/Karachi",
    "iso:country":"PK",
    "wof:name":"Zor Shalpin",
    "wof:placetype":"locality"
},
  "geometry": {"coordinates":[72.56437,34.95147],"type":"Point"}
}