{
  "type": "Feature",
  "properties": {
    "gn:admin1_code":"4",
    "gn:asciiname":"Shere di Basti",
    "gn:country_code":"PK",
    "gn:dem":144,
    "gn:feature_class":"P",
    "gn:feature_code":"PPL",
    "gn:name":"Shere di Basti",
    "gn:population":0,
    "gn:timezone":"Asia/Karachi",
    "iso:country":"PK",
    "name:und_x_variant":[
        "Shera"
    ],
    "wof:name":"Shere di Basti",
    "wof:placetype":"locality"
},
  "geometry": {"coordinates":[71.0642,30.84181],"type":"Point"}
}