{
  "type": "Feature",
  "properties": {
    "gn:admin1_code":"3.0",
    "gn:asciiname":"Buro",
    "gn:country_code":"PK",
    "gn:dem":544,
    "gn:feature_class":"P",
    "gn:feature_code":"PPL",
    "gn:name":"Buro",
    "gn:population":0,
    "gn:timezone":"Asia/Karachi",
    "iso:country":"PK",
    "wof:name":"Buro",
    "wof:placetype":"locality"
},
  "geometry": {"coordinates":[71.30959,33.52689],"type":"Point"}
}