{
  "type": "Feature",
  "properties": {
    "gn:admin1_code":"4.0",
    "gn:asciiname":"Dhok Gulab Khan",
    "gn:country_code":"PK",
    "gn:dem":331,
    "gn:feature_class":"P",
    "gn:feature_code":"PPL",
    "gn:name":"Dhok Gulab Khan",
    "gn:population":0,
    "gn:timezone":"Asia/Karachi",
    "iso:country":"PK",
    "wof:name":"Dhok Gulab Khan",
    "wof:placetype":"locality"
},
  "geometry": {"coordinates":[72.24495,33.72378],"type":"Point"}
}