{
  "type": "Feature",
  "properties": {
    "gn:admin1_code":"3",
    "gn:asciiname":"Banj Banda",
    "gn:country_code":"PK",
    "gn:dem":1744,
    "gn:feature_class":"P",
    "gn:feature_code":"PPL",
    "gn:name":"Banj Banda",
    "gn:population":0,
    "gn:timezone":"Asia/Karachi",
    "iso:country":"PK",
    "wof:name":"Banj Banda",
    "wof:placetype":"locality"
},
  "geometry": {"coordinates":[72.32335999999999,34.91239],"type":"Point"}
}