{
  "type": "Feature",
  "properties": {
    "gn:admin1_code":"2.0",
    "gn:asciiname":"Ghulam Haider Baluch Kili",
    "gn:country_code":"PK",
    "gn:dem":962,
    "gn:feature_class":"P",
    "gn:feature_code":"PPL",
    "gn:name":"Ghulam Haider Baluch Kili",
    "gn:population":0,
    "gn:timezone":"Asia/Karachi",
    "iso:country":"PK",
    "wof:name":"Ghulam Haider Baluch Kili",
    "wof:placetype":"locality"
},
  "geometry": {"coordinates":[69.09753000000001,30.09106],"type":"Point"}
}