{
  "type": "Feature",
  "properties": {
    "gn:admin1_code":"3.0",
    "gn:asciiname":"Bagra",
    "gn:country_code":"PK",
    "gn:dem":865,
    "gn:feature_class":"P",
    "gn:feature_code":"PPL",
    "gn:name":"Bagra",
    "gn:population":0,
    "gn:timezone":"Asia/Karachi",
    "iso:country":"PK",
    "name:bul_x_preferred":[
        "\u0411\u0430\u0433\u0440\u0430"
    ],
    "name:ceb_x_preferred":[
        "Bagra"
    ],
    "name:rus_x_preferred":[
        "\u0411\u0430\u0433\u0440\u0430"
    ],
    "name:swe_x_preferred":[
        "Bagra"
    ],
    "name:und_x_variant":[
        "Baggrah",
        "Bagra"
    ],
    "wof:name":"Bagra",
    "wof:placetype":"locality"
},
  "geometry": {"coordinates":[72.51531,34.5866],"type":"Point"}
}