{
  "type": "Feature",
  "properties": {
    "gn:admin1_code":"7.0",
    "gn:asciiname":"Muza",
    "gn:country_code":"PK",
    "gn:dem":2076,
    "gn:feature_class":"P",
    "gn:feature_code":"PPL",
    "gn:name":"Muza",
    "gn:population":0,
    "gn:timezone":"Asia/Karachi",
    "iso:country":"PK",
    "name:ceb_x_preferred":[
        "Muza"
    ],
    "name:deu_x_preferred":[
        "Muza"
    ],
    "name:fra_x_preferred":[
        "Muza"
    ],
    "name:pol_x_preferred":[
        "Muza"
    ],
    "name:spa_x_preferred":[
        "Muza"
    ],
    "name:swe_x_preferred":[
        "Muza"
    ],
    "wof:name":"Muza",
    "wof:placetype":"locality"
},
  "geometry": {"coordinates":[73.77129000000002,35.40792000000001],"type":"Point"}
}