{
  "type": "Feature",
  "properties": {
    "gn:admin1_code":"1.0",
    "gn:asciiname":"Sarfaraz",
    "gn:country_code":"PK",
    "gn:dem":943,
    "gn:feature_class":"P",
    "gn:feature_code":"PPL",
    "gn:name":"Sarfaraz",
    "gn:population":0,
    "gn:timezone":"Asia/Karachi",
    "iso:country":"PK",
    "wof:name":"Sarfaraz",
    "wof:placetype":"locality"
},
  "geometry": {"coordinates":[71.14055999999999,34.49],"type":"Point"}
}