{
  "type": "Feature",
  "properties": {
    "gn:admin1_code":"4",
    "gn:asciiname":"Watowani",
    "gn:country_code":"PK",
    "gn:dem":192,
    "gn:feature_class":"P",
    "gn:feature_code":"PPL",
    "gn:name":"Watowani",
    "gn:population":0,
    "gn:timezone":"Asia/Karachi",
    "iso:country":"PK",
    "name:eng_x_preferred":[
        "Basti Dallu"
    ],
    "name:und_x_variant":[
        "Basti Dallu\u0101ni"
    ],
    "wof:name":"Watowani",
    "wof:placetype":"locality"
},
  "geometry": {"coordinates":[70.39214,29.91809000000001],"type":"Point"}
}