{
  "type": "Feature",
  "properties": {
    "gn:admin1_code":"4.0",
    "gn:asciiname":"Rokhri",
    "gn:country_code":"PK",
    "gn:dem":202,
    "gn:feature_class":"P",
    "gn:feature_code":"PPL",
    "gn:name":"Rokhri",
    "gn:population":0,
    "gn:timezone":"Asia/Karachi",
    "iso:country":"PK",
    "name:ben_x_preferred":[
        "\u09b0\u09cb\u0996\u09b0\u09bf"
    ],
    "name:fas_x_preferred":[
        "\u0631\u0648\u06a9\u0647\u0631\u06cc"
    ],
    "name:urd_x_preferred":[
        "\u0631\u0648\u06a9\u06be\u0691\u06cc"
    ],
    "wof:name":"Rokhri",
    "wof:placetype":"locality"
},
  "geometry": {"coordinates":[71.50929000000002,32.65902],"type":"Point"}
}