{
  "type": "Feature",
  "properties": {
    "gn:admin1_code":"4.0",
    "gn:asciiname":"Qasirabad",
    "gn:country_code":"PK",
    "gn:dem":230,
    "gn:feature_class":"P",
    "gn:feature_code":"PPL",
    "gn:name":"Qasirabad",
    "gn:population":0,
    "gn:timezone":"Asia/Karachi",
    "iso:country":"PK",
    "wof:name":"Qasirabad",
    "wof:placetype":"locality"
},
  "geometry": {"coordinates":[73.71011999999997,32.93660999999999],"type":"Point"}
}