{
  "type": "Feature",
  "properties": {
    "gn:admin1_code":"4",
    "gn:asciiname":"Qatal Shah",
    "gn:country_code":"PK",
    "gn:dem":107,
    "gn:feature_class":"P",
    "gn:feature_code":"PPL",
    "gn:name":"Qatal Shah",
    "gn:population":0,
    "gn:timezone":"Asia/Karachi",
    "iso:country":"PK",
    "name:und_x_variant":[
        "Q\u0101tal Sh\u0101hw\u0101la"
    ],
    "wof:name":"Qatal Shah",
    "wof:placetype":"locality"
},
  "geometry": {"coordinates":[70.76949,29.44311],"type":"Point"}
}