{
  "type": "Feature",
  "properties": {
    "gn:admin1_code":"3",
    "gn:asciiname":"Darkane",
    "gn:country_code":"PK",
    "gn:dem":3011,
    "gn:feature_class":"P",
    "gn:feature_code":"PPL",
    "gn:name":"Darkane",
    "gn:population":0,
    "gn:timezone":"Asia/Karachi",
    "iso:country":"PK",
    "name:deu_x_preferred":[
        "Darkane"
    ],
    "name:fra_x_preferred":[
        "Darkane"
    ],
    "name:hun_x_preferred":[
        "Darkane"
    ],
    "name:ita_x_preferred":[
        "Darkane"
    ],
    "name:jpn_x_preferred":[
        "\u30c0\u30fc\u30b1\u30a4\u30f3"
    ],
    "name:pol_x_preferred":[
        "Darkane"
    ],
    "name:spa_x_preferred":[
        "Darkane"
    ],
    "name:swe_x_preferred":[
        "Darkane"
    ],
    "wof:name":"Darkane",
    "wof:placetype":"locality"
},
  "geometry": {"coordinates":[73.64612,34.64813],"type":"Point"}
}