{
  "type": "Feature",
  "properties": {
    "gn:admin1_code":"6",
    "gn:asciiname":"Gupal",
    "gn:country_code":"PK",
    "gn:dem":327,
    "gn:feature_class":"P",
    "gn:feature_code":"PPL",
    "gn:name":"Gupal",
    "gn:population":0,
    "gn:timezone":"Asia/Karachi",
    "iso:country":"PK",
    "name:und_x_variant":[
        "Gopal",
        "Gupal"
    ],
    "wof:name":"Gupal",
    "wof:placetype":"locality"
},
  "geometry": {"coordinates":[73.93422,33.09013],"type":"Point"}
}