{
  "type": "Feature",
  "properties": {
    "gn:admin1_code":"4.0",
    "gn:asciiname":"Dhapai",
    "gn:country_code":"PK",
    "gn:dem":219,
    "gn:feature_class":"P",
    "gn:feature_code":"PPL",
    "gn:name":"Dhapai",
    "gn:population":0,
    "gn:timezone":"Asia/Karachi",
    "iso:country":"PK",
    "name:fas_x_preferred":[
        "\u062f\u0647\u0627\u067e\u0627\u06cc"
    ],
    "name:und_x_variant":[
        "Dhapai Bas\u0101kha Singh"
    ],
    "name:urd_x_preferred":[
        "\u062f\u06be\u0627\u067e\u0626\u06cc"
    ],
    "wof:name":"Dhapai",
    "wof:placetype":"locality"
},
  "geometry": {"coordinates":[73.93985000000001,32.17248],"type":"Point"}
}