{
  "type": "Feature",
  "properties": {
    "iso:country":"PK",
    "qs:gn_country":"PK",
    "qs:gn_fcode":"PPL",
    "qs:gn_pop":9975,
    "qs:name":"Berani",
    "qs:name_adm0":"Pakistan",
    "qs:name_adm1":"Sindh",
    "qs:photos":0,
    "qs:photos_1k":0,
    "qs:photos_9k":1,
    "qs:photos_9r":2,
    "qs:photos_all":69,
    "qs:photos_sr":0,
    "qs:placetype":"Town",
    "qs:pop_sr":"5",
    "qs:woe_adm0":23424922,
    "wof:name":"Berani",
    "wof:placetype":"locality",
    "wof:population":9975
},
  "geometry": {"coordinates":[68.80686,25.785],"type":"Point"}
}