{
  "type": "Feature",
  "properties": {
    "gn:admin1_code":"3",
    "gn:asciiname":"Alogai",
    "gn:country_code":"PK",
    "gn:dem":1742,
    "gn:feature_class":"P",
    "gn:feature_code":"PPL",
    "gn:name":"Alogai",
    "gn:population":0,
    "gn:timezone":"Asia/Karachi",
    "iso:country":"PK",
    "wof:name":"Alogai",
    "wof:placetype":"locality"
},
  "geometry": {"coordinates":[72.73862,34.70584],"type":"Point"}
}