{
  "type": "Feature",
  "properties": {
    "gn:admin1_code":"3",
    "gn:asciiname":"Chino Baba Ziarat",
    "gn:country_code":"PK",
    "gn:dem":920,
    "gn:feature_class":"P",
    "gn:feature_code":"PPL",
    "gn:name":"Chino Baba Ziarat",
    "gn:population":0,
    "gn:timezone":"Asia/Karachi",
    "iso:country":"PK",
    "wof:name":"Chino Baba Ziarat",
    "wof:placetype":"locality"
},
  "geometry": {"coordinates":[72.32158000000003,34.8025],"type":"Point"}
}