{
  "type": "Feature",
  "properties": {
    "gn:admin1_code":"1.0",
    "gn:asciiname":"Ahmadi Shama",
    "gn:country_code":"PK",
    "gn:dem":864,
    "gn:feature_class":"P",
    "gn:feature_code":"PPL",
    "gn:name":"Ahmadi Shama",
    "gn:population":0,
    "gn:timezone":"Asia/Karachi",
    "iso:country":"PK",
    "wof:name":"Ahmadi Shama",
    "wof:placetype":"locality"
},
  "geometry": {"coordinates":[70.44144,33.44777],"type":"Point"}
}