{
  "type": "Feature",
  "properties": {
    "gn:admin1_code":"4.0",
    "gn:asciiname":"Chhanguwali",
    "gn:country_code":"PK",
    "gn:dem":245,
    "gn:feature_class":"P",
    "gn:feature_code":"PPL",
    "gn:name":"Chhanguwali",
    "gn:population":0,
    "gn:timezone":"Asia/Karachi",
    "iso:country":"PK",
    "name:und_x_variant":[
        "R\u0101jow\u0101il"
    ],
    "wof:name":"Chhanguwali",
    "wof:placetype":"locality"
},
  "geometry": {"coordinates":[74.96938,32.17857],"type":"Point"}
}