{
  "type": "Feature",
  "properties": {
    "gn:admin1_code":"4.0",
    "gn:asciiname":"Nawan Biriar",
    "gn:country_code":"PK",
    "gn:dem":225,
    "gn:feature_class":"P",
    "gn:feature_code":"PPL",
    "gn:name":"Nawan Biriar",
    "gn:population":0,
    "gn:timezone":"Asia/Karachi",
    "iso:country":"PK",
    "name:und_x_variant":[
        "Hardo Bari\u0101r Jad\u012ba"
    ],
    "wof:name":"Nawan Biriar",
    "wof:placetype":"locality"
},
  "geometry": {"coordinates":[74.59511999999999,31.91852],"type":"Point"}
}