{
  "type": "Feature",
  "properties": {
    "gn:admin1_code":"1.0",
    "gn:asciiname":"Nili Saiydan",
    "gn:country_code":"PK",
    "gn:dem":510,
    "gn:feature_class":"P",
    "gn:feature_code":"PPL",
    "gn:name":"Nili Saiydan",
    "gn:population":0,
    "gn:timezone":"Asia/Karachi",
    "iso:country":"PK",
    "name:und_x_variant":[
        "Neli Saiyid\u0101n"
    ],
    "wof:name":"Nili Saiydan",
    "wof:placetype":"locality"
},
  "geometry": {"coordinates":[73.69651999999998,33.45328],"type":"Point"}
}