{
  "type": "Feature",
  "properties": {
    "gn:admin1_code":"3.0",
    "gn:asciiname":"Gul Rehan Kalle",
    "gn:country_code":"PK",
    "gn:dem":484,
    "gn:feature_class":"P",
    "gn:feature_code":"PPL",
    "gn:name":"Gul Rehan Kalle",
    "gn:population":0,
    "gn:timezone":"Asia/Karachi",
    "iso:country":"PK",
    "name:und_x_variant":[
        "Gul Rekh\u0101n Kilai"
    ],
    "wof:name":"Gul Rehan Kalle",
    "wof:placetype":"locality"
},
  "geometry": {"coordinates":[71.81059999999999,33.88315],"type":"Point"}
}