{
  "type": "Feature",
  "properties": {
    "gn:admin1_code":"4",
    "gn:asciiname":"Qadirwala",
    "gn:country_code":"PK",
    "gn:dem":128,
    "gn:feature_class":"P",
    "gn:feature_code":"PPL",
    "gn:name":"Qadirwala",
    "gn:population":0,
    "gn:timezone":"Asia/Karachi",
    "iso:country":"PK",
    "name:eng_x_preferred":[
        "Qadirwala"
    ],
    "wof:name":"Qadirwala",
    "wof:placetype":"locality"
},
  "geometry": {"coordinates":[70.90991,30.38877],"type":"Point"}
}