{
  "type": "Feature",
  "properties": {
    "gn:admin1_code":"5",
    "gn:asciiname":"Nabi Bakhsh",
    "gn:country_code":"PK",
    "gn:dem":36,
    "gn:feature_class":"P",
    "gn:feature_code":"PPL",
    "gn:name":"Nabi Bakhsh",
    "gn:population":0,
    "gn:timezone":"Asia/Karachi",
    "iso:country":"PK",
    "name:und_x_variant":[
        "H\u0101ji Dhani Bakhsh Khosa"
    ],
    "wof:name":"Nabi Bakhsh",
    "wof:placetype":"locality"
},
  "geometry": {"coordinates":[68.08266999999999,26.42627],"type":"Point"}
}