{
  "type": "Feature",
  "properties": {
    "gn:admin1_code":"1.0",
    "gn:asciiname":"Qasim Khel",
    "gn:country_code":"PK",
    "gn:dem":635,
    "gn:feature_class":"P",
    "gn:feature_code":"PPL",
    "gn:name":"Qasim Khel",
    "gn:population":0,
    "gn:timezone":"Asia/Karachi",
    "iso:country":"PK",
    "name:und_x_variant":[
        "Qasmi Khel",
        "Qasim Khel"
    ],
    "wof:name":"Qasim Khel",
    "wof:placetype":"locality"
},
  "geometry": {"coordinates":[71.50499000000001,33.68785],"type":"Point"}
}