{
  "type": "Feature",
  "properties": {
    "gn:admin1_code":"5",
    "gn:asciiname":"Goth Usman Shoro",
    "gn:country_code":"PK",
    "gn:dem":16,
    "gn:feature_class":"P",
    "gn:feature_code":"PPL",
    "gn:name":"Goth Usman Shoro",
    "gn:population":0,
    "gn:timezone":"Asia/Karachi",
    "iso:country":"PK",
    "name:eng_x_preferred":[
        "Goth Usman Shoro"
    ],
    "wof:name":"Goth Usman Shoro",
    "wof:placetype":"locality"
},
  "geometry": {"coordinates":[68.41059,25.17032],"type":"Point"}
}