{
  "type": "Feature",
  "properties": {
    "gn:admin1_code":"3.0",
    "gn:asciiname":"Tarkanna",
    "gn:country_code":"PK",
    "gn:dem":3090,
    "gn:feature_class":"P",
    "gn:feature_code":"PPL",
    "gn:name":"Tarkanna",
    "gn:population":0,
    "gn:timezone":"Asia/Karachi",
    "iso:country":"PK",
    "wof:name":"Tarkanna",
    "wof:placetype":"locality"
},
  "geometry": {"coordinates":[73.64390999999998,34.7999],"type":"Point"}
}