{
  "type": "Feature",
  "properties": {
    "gn:admin1_code":"3",
    "gn:asciiname":"Cholundrian",
    "gn:country_code":"PK",
    "gn:dem":1279,
    "gn:feature_class":"P",
    "gn:feature_code":"PPL",
    "gn:name":"Cholundrian",
    "gn:population":0,
    "gn:timezone":"Asia/Karachi",
    "iso:country":"PK",
    "name:und_x_variant":[
        "Ghalundri\u0101n"
    ],
    "wof:name":"Cholundrian",
    "wof:placetype":"locality"
},
  "geometry": {"coordinates":[73.01989,34.53879000000001],"type":"Point"}
}