{
  "type": "Feature",
  "properties": {
    "gn:admin1_code":"5",
    "gn:asciiname":"Goth Gulab Laghari",
    "gn:country_code":"PK",
    "gn:dem":20,
    "gn:feature_class":"P",
    "gn:feature_code":"PPL",
    "gn:name":"Goth Gulab Laghari",
    "gn:population":0,
    "gn:timezone":"Asia/Karachi",
    "iso:country":"PK",
    "name:und_x_variant":[
        "Gul\u0101b Kh\u0101skheli Goth"
    ],
    "wof:name":"Goth Gulab Laghari",
    "wof:placetype":"locality"
},
  "geometry": {"coordinates":[68.85826,25.23306],"type":"Point"}
}