{
  "type": "Feature",
  "properties": {
    "gn:admin1_code":"4.0",
    "gn:asciiname":"Narail",
    "gn:country_code":"PK",
    "gn:dem":1565,
    "gn:feature_class":"P",
    "gn:feature_code":"PPL",
    "gn:name":"Narail",
    "gn:population":0,
    "gn:timezone":"Asia/Karachi",
    "iso:country":"PK",
    "wof:name":"Narail",
    "wof:placetype":"locality"
},
  "geometry": {"coordinates":[70.06744999999999,30.26032],"type":"Point"}
}