{
  "type": "Feature",
  "properties": {
    "gn:admin1_code":"4",
    "gn:asciiname":"Basti Terpai Bosan",
    "gn:country_code":"PK",
    "gn:dem":127,
    "gn:feature_class":"P",
    "gn:feature_code":"PPL",
    "gn:name":"Basti Terpai Bosan",
    "gn:population":0,
    "gn:timezone":"Asia/Karachi",
    "iso:country":"PK",
    "name:und_x_variant":[
        "Tarpa"
    ],
    "wof:name":"Basti Terpai Bosan",
    "wof:placetype":"locality"
},
  "geometry": {"coordinates":[71.74829,30.17274],"type":"Point"}
}