{
  "type": "Feature",
  "properties": {
    "gn:admin1_code":"5",
    "gn:asciiname":"Goth Ayub Wasan",
    "gn:country_code":"PK",
    "gn:dem":18,
    "gn:feature_class":"P",
    "gn:feature_code":"PPL",
    "gn:name":"Goth Ayub Wasan",
    "gn:population":0,
    "gn:timezone":"Asia/Karachi",
    "iso:country":"PK",
    "name:und_x_variant":[
        "Dhannu Was\u0101n"
    ],
    "wof:name":"Goth Ayub Wasan",
    "wof:placetype":"locality"
},
  "geometry": {"coordinates":[69.18682,25.91075],"type":"Point"}
}