{
  "type": "Feature",
  "properties": {
    "gn:admin1_code":"3",
    "gn:asciiname":"Lammi",
    "gn:country_code":"PK",
    "gn:dem":1585,
    "gn:feature_class":"P",
    "gn:feature_code":"PPL",
    "gn:name":"Lammi",
    "gn:population":0,
    "gn:timezone":"Asia/Karachi",
    "iso:country":"PK",
    "wof:name":"Lammi",
    "wof:placetype":"locality"
},
  "geometry": {"coordinates":[73.10876999999998,34.56515],"type":"Point"}
}