{
  "type": "Feature",
  "properties": {
    "gn:admin1_code":"3",
    "gn:asciiname":"Lammi",
    "gn:country_code":"PK",
    "gn:dem":1585,
    "gn:feature_class":"P",
    "gn:feature_code":"PPL",
    "gn:name":"Lammi",
    "gn:population":0,
    "gn:timezone":"Asia/Karachi",
    "iso:country":"PK",
    "name:ceb_x_preferred":[
        "Lammi"
    ],
    "name:deu_x_preferred":[
        "Lammi"
    ],
    "name:est_x_preferred":[
        "Lammi vald"
    ],
    "name:eus_x_preferred":[
        "Lammi"
    ],
    "name:fin_x_preferred":[
        "Lammi"
    ],
    "name:fra_x_preferred":[
        "Lammi"
    ],
    "name:ita_x_preferred":[
        "Lammi"
    ],
    "name:nld_x_preferred":[
        "Lammi"
    ],
    "name:nor_x_preferred":[
        "Lammi"
    ],
    "name:ron_x_preferred":[
        "Lammi"
    ],
    "name:sme_x_preferred":[
        "Lammi"
    ],
    "name:swe_x_preferred":[
        "Lampis"
    ],
    "wof:name":"Lammi",
    "wof:placetype":"locality"
},
  "geometry": {"coordinates":[73.10876999999998,34.56515],"type":"Point"}
}