{
  "type": "Feature",
  "properties": {
    "gn:admin1_code":"4",
    "gn:asciiname":"Shirinwali Miani",
    "gn:country_code":"PK",
    "gn:dem":121,
    "gn:feature_class":"P",
    "gn:feature_code":"PPL",
    "gn:name":"Shirinwali Miani",
    "gn:population":0,
    "gn:timezone":"Asia/Karachi",
    "iso:country":"PK",
    "name:eng_x_preferred":[
        "Shirinwali Miani"
    ],
    "wof:name":"Shirinwali Miani",
    "wof:placetype":"locality"
},
  "geometry": {"coordinates":[70.87356,30.12698],"type":"Point"}
}