{
  "type": "Feature",
  "properties": {
    "gn:admin1_code":"2",
    "gn:asciiname":"Uchhro",
    "gn:country_code":"PK",
    "gn:dem":1235,
    "gn:feature_class":"P",
    "gn:feature_code":"PPL",
    "gn:name":"Uchhro",
    "gn:population":0,
    "gn:timezone":"Asia/Karachi",
    "iso:country":"PK",
    "name:und_x_variant":[
        "Ucharo",
        "Uchro",
        "Uchhro"
    ],
    "wof:name":"Uchhro",
    "wof:placetype":"locality"
},
  "geometry": {"coordinates":[66.24625,27.19543],"type":"Point"}
}