{
  "type": "Feature",
  "properties": {
    "gn:admin1_code":"5.0",
    "gn:asciiname":"Goth Magsi",
    "gn:country_code":"PK",
    "gn:dem":47,
    "gn:feature_class":"P",
    "gn:feature_code":"PPL",
    "gn:name":"Goth Magsi",
    "gn:population":0,
    "gn:timezone":"Asia/Karachi",
    "iso:country":"PK",
    "wof:name":"Goth Magsi",
    "wof:placetype":"locality"
},
  "geometry": {"coordinates":[68.00553000000001,27.04988],"type":"Point"}
}