{
  "type": "Feature",
  "properties": {
    "gn:admin1_code":"7.0",
    "gn:asciiname":"Kami",
    "gn:country_code":"PK",
    "gn:dem":2758,
    "gn:feature_class":"P",
    "gn:feature_code":"PPL",
    "gn:name":"Kami",
    "gn:population":0,
    "gn:timezone":"Asia/Karachi",
    "iso:country":"PK",
    "wof:name":"Kami",
    "wof:placetype":"locality"
},
  "geometry": {"coordinates":[73.38688,35.71069],"type":"Point"}
}