{
  "type": "Feature",
  "properties": {
    "gn:admin1_code":"3.0",
    "gn:asciiname":"Ziarat Kalle",
    "gn:country_code":"PK",
    "gn:dem":365,
    "gn:feature_class":"P",
    "gn:feature_code":"PPL",
    "gn:name":"Ziarat Kalle",
    "gn:population":0,
    "gn:timezone":"Asia/Karachi",
    "iso:country":"PK",
    "name:und_x_variant":[
        "Zi\u0101rat Kili",
        "Ziarat Kalle"
    ],
    "wof:name":"Ziarat Kalle",
    "wof:placetype":"locality"
},
  "geometry": {"coordinates":[71.61369999999999,34.31054],"type":"Point"}
}