{
  "type": "Feature",
  "properties": {
    "gn:admin1_code":"3",
    "gn:asciiname":"Bhogia",
    "gn:country_code":"PK",
    "gn:dem":2076,
    "gn:feature_class":"P",
    "gn:feature_code":"PPL",
    "gn:name":"Bhogia",
    "gn:population":0,
    "gn:timezone":"Asia/Karachi",
    "iso:country":"PK",
    "wof:name":"Bhogia",
    "wof:placetype":"locality"
},
  "geometry": {"coordinates":[73.41771999999997,34.50225],"type":"Point"}
}