{
  "type": "Feature",
  "properties": {
    "gn:admin1_code":"1.0",
    "gn:asciiname":"Jamal Zai",
    "gn:country_code":"PK",
    "gn:dem":1115,
    "gn:feature_class":"P",
    "gn:feature_code":"PPL",
    "gn:name":"Jamal Zai",
    "gn:population":0,
    "gn:timezone":"Asia/Karachi",
    "iso:country":"PK",
    "name:und_x_variant":[
        "Jam\u0101lzai"
    ],
    "wof:name":"Jamal Zai",
    "wof:placetype":"locality"
},
  "geometry": {"coordinates":[70.04172,31.46112],"type":"Point"}
}