{
  "type": "Feature",
  "properties": {
    "gn:admin1_code":"4",
    "gn:asciiname":"Tibbi",
    "gn:country_code":"PK",
    "gn:dem":131,
    "gn:feature_class":"P",
    "gn:feature_code":"PPL",
    "gn:name":"Tibbi",
    "gn:population":0,
    "gn:timezone":"Asia/Karachi",
    "iso:country":"PK",
    "name:ben_x_preferred":[
        "\u09b0\u09be\u0993\u09af\u09bc\u09be\u09a4\u09b8\u09b0"
    ],
    "name:bpy_x_preferred":[
        "\u09b0\u09be\u09f1\u09be\u09a4\u09b8\u09b0"
    ],
    "name:hin_x_preferred":[
        "\u091f\u093f\u092c\u094d\u092c\u0940"
    ],
    "name:por_x_preferred":[
        "Rawatsar"
    ],
    "wof:name":"Tibbi",
    "wof:placetype":"locality"
},
  "geometry": {"coordinates":[72.21250000000001,29.76944],"type":"Point"}
}