{
  "type": "Feature",
  "properties": {
    "gn:admin1_code":"6",
    "gn:asciiname":"Jhugian",
    "gn:country_code":"PK",
    "gn:dem":2255,
    "gn:feature_class":"P",
    "gn:feature_code":"PPL",
    "gn:name":"Jhugian",
    "gn:population":0,
    "gn:timezone":"Asia/Karachi",
    "iso:country":"PK",
    "wof:name":"Jhugian",
    "wof:placetype":"locality"
},
  "geometry": {"coordinates":[73.58937,34.38355],"type":"Point"}
}