{
  "type": "Feature",
  "properties": {
    "gn:admin1_code":"1.0",
    "gn:asciiname":"Nishpa",
    "gn:country_code":"PK",
    "gn:dem":1138,
    "gn:feature_class":"P",
    "gn:feature_code":"PPL",
    "gn:name":"Nishpa",
    "gn:population":0,
    "gn:timezone":"Asia/Karachi",
    "iso:country":"PK",
    "wof:name":"Nishpa",
    "wof:placetype":"locality"
},
  "geometry": {"coordinates":[70.02556,31.55944],"type":"Point"}
}