{
  "type": "Feature",
  "properties": {
    "gn:admin1_code":"2.0",
    "gn:asciiname":"Posti",
    "gn:country_code":"PK",
    "gn:dem":1210,
    "gn:feature_class":"P",
    "gn:feature_code":"PPL",
    "gn:name":"Posti",
    "gn:population":0,
    "gn:timezone":"Asia/Karachi",
    "iso:country":"PK",
    "name:deu_x_preferred":[
        "Posti"
    ],
    "name:fin_x_preferred":[
        "Posti"
    ],
    "wof:name":"Posti",
    "wof:placetype":"locality"
},
  "geometry": {"coordinates":[64.25288,29.25304],"type":"Point"}
}