{
  "type": "Feature",
  "properties": {
    "gn:admin1_code":"2.0",
    "gn:asciiname":"Izzat Bazar",
    "gn:country_code":"PK",
    "gn:dem":680,
    "gn:feature_class":"P",
    "gn:feature_code":"PPL",
    "gn:name":"Izzat Bazar",
    "gn:population":0,
    "gn:timezone":"Asia/Karachi",
    "iso:country":"PK",
    "wof:name":"Izzat Bazar",
    "wof:placetype":"locality"
},
  "geometry": {"coordinates":[63.65836,26.38724],"type":"Point"}
}