{
  "type": "Feature",
  "properties": {
    "gn:admin1_code":"4.0",
    "gn:asciiname":"Dhaulr",
    "gn:country_code":"PK",
    "gn:dem":161,
    "gn:feature_class":"P",
    "gn:feature_code":"PPL",
    "gn:name":"Dhaulr",
    "gn:population":0,
    "gn:timezone":"Asia/Karachi",
    "iso:country":"PK",
    "name:und_x_variant":[
        "Dholri",
        "Dhaulri",
        "Dhaulr"
    ],
    "wof:name":"Dhaulr",
    "wof:placetype":"locality"
},
  "geometry": {"coordinates":[72.76614000000002,30.7474],"type":"Point"}
}