{
  "type": "Feature",
  "properties": {
    "gn:admin1_code":"2.0",
    "gn:asciiname":"Akhtar Kili",
    "gn:country_code":"PK",
    "gn:dem":1369,
    "gn:feature_class":"P",
    "gn:feature_code":"PPL",
    "gn:name":"Akhtar Kili",
    "gn:population":0,
    "gn:timezone":"Asia/Karachi",
    "iso:country":"PK",
    "wof:name":"Akhtar Kili",
    "wof:placetype":"locality"
},
  "geometry": {"coordinates":[66.45891999999999,30.25003],"type":"Point"}
}