{
  "type": "Feature",
  "properties": {
    "gn:admin1_code":"2.0",
    "gn:asciiname":"Pir Muhammad Gis",
    "gn:country_code":"PK",
    "gn:dem":1623,
    "gn:feature_class":"P",
    "gn:feature_code":"PPL",
    "gn:name":"Pir Muhammad Gis",
    "gn:population":0,
    "gn:timezone":"Asia/Karachi",
    "iso:country":"PK",
    "wof:name":"Pir Muhammad Gis",
    "wof:placetype":"locality"
},
  "geometry": {"coordinates":[63.77956,29.38381],"type":"Point"}
}