{
  "type": "Feature",
  "properties": {
    "gn:admin1_code":"2.0",
    "gn:asciiname":"Sra Kheza",
    "gn:country_code":"PK",
    "gn:dem":1699,
    "gn:feature_class":"P",
    "gn:feature_code":"PPL",
    "gn:name":"Sra Kheza",
    "gn:population":0,
    "gn:timezone":"Asia/Karachi",
    "iso:country":"PK",
    "name:und_x_variant":[
        "Sra Kheza Kili"
    ],
    "wof:name":"Sra Kheza",
    "wof:placetype":"locality"
},
  "geometry": {"coordinates":[69.28927,30.82057],"type":"Point"}
}