{
  "type": "Feature",
  "properties": {
    "gn:admin1_code":"4",
    "gn:asciiname":"Wasuwala",
    "gn:country_code":"PK",
    "gn:dem":134,
    "gn:feature_class":"P",
    "gn:feature_code":"PPL",
    "gn:name":"Wasuwala",
    "gn:population":0,
    "gn:timezone":"Asia/Karachi",
    "iso:country":"PK",
    "name:und_x_variant":[
        "V\u0101s\u016bw\u0101la"
    ],
    "wof:name":"Wasuwala",
    "wof:placetype":"locality"
},
  "geometry": {"coordinates":[71.21289,30.53131],"type":"Point"}
}