{
  "type": "Feature",
  "properties": {
    "gn:admin1_code":"4",
    "gn:asciiname":"Basti Naianwali",
    "gn:country_code":"PK",
    "gn:dem":106,
    "gn:feature_class":"P",
    "gn:feature_code":"PPL",
    "gn:name":"Basti Naianwali",
    "gn:population":0,
    "gn:timezone":"Asia/Karachi",
    "iso:country":"PK",
    "name:und_x_variant":[
        "Nai\u0101nw\u0101li Basti",
        "N\u0101\u012bw\u0101li Basti",
        "Basti Naianwali"
    ],
    "wof:name":"Basti Naianwali",
    "wof:placetype":"locality"
},
  "geometry": {"coordinates":[71.29713000000002,29.31912],"type":"Point"}
}