{
  "type": "Feature",
  "properties": {
    "gn:admin1_code":"5",
    "gn:asciiname":"Goth Bhai Khan Mehar",
    "gn:country_code":"PK",
    "gn:dem":14,
    "gn:feature_class":"P",
    "gn:feature_code":"PPL",
    "gn:name":"Goth Bhai Khan Mehar",
    "gn:population":0,
    "gn:timezone":"Asia/Karachi",
    "iso:country":"PK",
    "name:und_x_variant":[
        "Goth Bh\u0101i Kh\u0101n Mehar"
    ],
    "wof:name":"Goth Bhai Khan Mehar",
    "wof:placetype":"locality"
},
  "geometry": {"coordinates":[69.2109,25.43688],"type":"Point"}
}