{
  "type": "Feature",
  "properties": {
    "gn:admin1_code":"2.0",
    "gn:asciiname":"Goth Dhani Bakhsh",
    "gn:country_code":"PK",
    "gn:dem":50,
    "gn:feature_class":"P",
    "gn:feature_code":"PPL",
    "gn:name":"Goth Dhani Bakhsh",
    "gn:population":0,
    "gn:timezone":"Asia/Karachi",
    "iso:country":"PK",
    "wof:name":"Goth Dhani Bakhsh",
    "wof:placetype":"locality"
},
  "geometry": {"coordinates":[67.92139,28.0724],"type":"Point"}
}