{
  "type": "Feature",
  "properties": {
    "gn:admin1_code":"05",
    "gn:asciiname":"Goth Kettai",
    "gn:country_code":"PK",
    "gn:dem":9,
    "gn:feature_class":"P",
    "gn:feature_code":"PPL",
    "gn:name":"Goth Kettai",
    "gn:population":0,
    "gn:timezone":"Asia/Karachi",
    "iso:country":"PK",
    "name:und_x_variant":[
        "Goth Butjo"
    ],
    "wof:name":"Goth Kettai",
    "wof:placetype":"locality"
},
  "geometry": {"coordinates":[67.81825000000001,24.49688],"type":"Point"}
}