{
  "type": "Feature",
  "properties": {
    "gn:admin1_code":"03",
    "gn:asciiname":"Zardad Koruna",
    "gn:country_code":"PK",
    "gn:dem":399,
    "gn:feature_class":"P",
    "gn:feature_code":"PPL",
    "gn:name":"Zardad Koruna",
    "gn:population":0,
    "gn:timezone":"Asia/Karachi",
    "iso:country":"PK",
    "name:eng_x_preferred":[
        "Zardad Koruna"
    ],
    "wof:name":"Zardad Koruna",
    "wof:placetype":"locality"
},
  "geometry": {"coordinates":[71.78147,34.35804],"type":"Point"}
}