{
  "type": "Feature",
  "properties": {
    "gn:admin1_code":"4.0",
    "gn:asciiname":"Chak Two Hundred Three",
    "gn:country_code":"PK",
    "gn:dem":171,
    "gn:feature_class":"P",
    "gn:feature_code":"PPL",
    "gn:name":"Chak Two Hundred Three",
    "gn:population":0,
    "gn:timezone":"Asia/Karachi",
    "iso:country":"PK",
    "name:eng_x_preferred":[
        "Chak Two Hundred Three"
    ],
    "name:und_x_variant":[
        "Ballu\u0101na Kal\u0101n",
        "Jhangi Balw\u0101na"
    ],
    "wof:name":"Chak Two Hundred Three",
    "wof:placetype":"locality"
},
  "geometry": {"coordinates":[72.74106,31.39789],"type":"Point"}
}