{
  "type": "Feature",
  "properties": {
    "gn:admin1_code":"3",
    "gn:asciiname":"Torai Patai",
    "gn:country_code":"PK",
    "gn:dem":2006,
    "gn:feature_class":"P",
    "gn:feature_code":"PPL",
    "gn:name":"Torai Patai",
    "gn:population":0,
    "gn:timezone":"Asia/Karachi",
    "iso:country":"PK",
    "wof:name":"Torai Patai",
    "wof:placetype":"locality"
},
  "geometry": {"coordinates":[72.06477,34.84133],"type":"Point"}
}