{
  "type": "Feature",
  "properties": {
    "gn:admin1_code":"5",
    "gn:asciiname":"Nedra",
    "gn:country_code":"PK",
    "gn:dem":57,
    "gn:feature_class":"P",
    "gn:feature_code":"PPL",
    "gn:name":"Nedra",
    "gn:population":0,
    "gn:timezone":"Asia/Karachi",
    "iso:country":"PK",
    "name:ceb_x_preferred":[
        "Nedra"
    ],
    "name:swe_x_preferred":[
        "Nedra"
    ],
    "name:vie_x_preferred":[
        "Nedra"
    ],
    "name:war_x_preferred":[
        "Nedra"
    ],
    "wof:name":"Nedra",
    "wof:placetype":"locality"
},
  "geometry": {"coordinates":[69.13463,27.19475],"type":"Point"}
}