{
  "type": "Feature",
  "properties": {
    "gn:admin1_code":"2.0",
    "gn:asciiname":"Sorai Raghzai",
    "gn:country_code":"PK",
    "gn:dem":903,
    "gn:feature_class":"P",
    "gn:feature_code":"PPL",
    "gn:name":"Sorai Raghzai",
    "gn:population":0,
    "gn:timezone":"Asia/Karachi",
    "iso:country":"PK",
    "wof:name":"Sorai Raghzai",
    "wof:placetype":"locality"
},
  "geometry": {"coordinates":[70.12361999999999,31.36116],"type":"Point"}
}