{
  "type": "Feature",
  "properties": {
    "gn:admin1_code":"2.0",
    "gn:asciiname":"Bashu Chot",
    "gn:country_code":"PK",
    "gn:dem":208,
    "gn:feature_class":"P",
    "gn:feature_code":"PPL",
    "gn:name":"Bashu Chot",
    "gn:population":0,
    "gn:timezone":"Asia/Karachi",
    "iso:country":"PK",
    "wof:name":"Bashu Chot",
    "wof:placetype":"locality"
},
  "geometry": {"coordinates":[64.44757,25.6967],"type":"Point"}
}