{
  "type": "Feature",
  "properties": {
    "gn:admin1_code":"04",
    "gn:asciiname":"Tariwala",
    "gn:country_code":"PK",
    "gn:dem":216,
    "gn:feature_class":"P",
    "gn:feature_code":"PPL",
    "gn:name":"Tariwala",
    "gn:population":0,
    "gn:timezone":"Asia/Karachi",
    "iso:country":"PK",
    "name:und_x_variant":[
        "T\u0101rew\u0101la"
    ],
    "wof:name":"Tariwala",
    "wof:placetype":"locality"
},
  "geometry": {"coordinates":[73.91925000000001,32.17066],"type":"Point"}
}