{
  "type": "Feature",
  "properties": {
    "gn:admin1_code":"3",
    "gn:asciiname":"Mangar Kot",
    "gn:country_code":"PK",
    "gn:dem":1647,
    "gn:feature_class":"P",
    "gn:feature_code":"PPL",
    "gn:name":"Mangar Kot",
    "gn:population":0,
    "gn:timezone":"Asia/Karachi",
    "iso:country":"PK",
    "wof:name":"Mangar Kot",
    "wof:placetype":"locality"
},
  "geometry": {"coordinates":[72.57224000000002,34.87656],"type":"Point"}
}