{
  "type": "Feature",
  "properties": {
    "gn:admin1_code":"5",
    "gn:asciiname":"Dano",
    "gn:country_code":"PK",
    "gn:dem":66,
    "gn:feature_class":"P",
    "gn:feature_code":"PPL",
    "gn:name":"Dano",
    "gn:population":0,
    "gn:timezone":"Asia/Karachi",
    "iso:country":"PK",
    "name:ceb_x_preferred":[
        "Dano"
    ],
    "name:deu_x_preferred":[
        "Dano"
    ],
    "name:fra_x_preferred":[
        "Dano"
    ],
    "name:nld_x_preferred":[
        "Dano"
    ],
    "name:por_x_preferred":[
        "Dano"
    ],
    "name:slk_x_preferred":[
        "Dano"
    ],
    "name:swe_x_preferred":[
        "Dano"
    ],
    "wof:name":"Dano",
    "wof:placetype":"locality"
},
  "geometry": {"coordinates":[68.63056,27.9875],"type":"Point"}
}