{
  "type": "Feature",
  "properties": {
    "gn:admin1_code":"4",
    "gn:asciiname":"Gurangi",
    "gn:country_code":"PK",
    "gn:dem":241,
    "gn:feature_class":"P",
    "gn:feature_code":"PPL",
    "gn:name":"Gurangi",
    "gn:population":0,
    "gn:timezone":"Asia/Karachi",
    "iso:country":"PK",
    "name:und_x_variant":[
        "Garangi"
    ],
    "wof:name":"Gurangi",
    "wof:placetype":"locality"
},
  "geometry": {"coordinates":[71.8151,32.49329],"type":"Point"}
}