{
  "type": "Feature",
  "properties": {
    "gn:admin1_code":"4.0",
    "gn:asciiname":"Ratti Pindi",
    "gn:country_code":"PK",
    "gn:dem":159,
    "gn:feature_class":"P",
    "gn:feature_code":"PPL",
    "gn:name":"Ratti Pindi",
    "gn:population":0,
    "gn:timezone":"Asia/Karachi",
    "iso:country":"PK",
    "wof:name":"Ratti Pindi",
    "wof:placetype":"locality"
},
  "geometry": {"coordinates":[72.42534000000001,31.1747],"type":"Point"}
}