{
  "type": "Feature",
  "properties": {
    "gn:admin1_code":"04",
    "gn:asciiname":"Qadirpur",
    "gn:country_code":"PK",
    "gn:dem":628,
    "gn:feature_class":"P",
    "gn:feature_code":"PPL",
    "gn:name":"Qadirpur",
    "gn:population":0,
    "gn:timezone":"Asia/Karachi",
    "iso:country":"PK",
    "wof:name":"Qadirpur",
    "wof:placetype":"locality"
},
  "geometry": {"coordinates":[72.45794000000002,32.74608],"type":"Point"}
}