{
  "type": "Feature",
  "properties": {
    "gn:admin1_code":"2.0",
    "gn:asciiname":"Bareri",
    "gn:country_code":"PK",
    "gn:dem":1150,
    "gn:feature_class":"P",
    "gn:feature_code":"PPL",
    "gn:name":"Bareri",
    "gn:population":0,
    "gn:timezone":"Asia/Karachi",
    "iso:country":"PK",
    "name:und_x_variant":[
        "Bareor"
    ],
    "wof:name":"Bareri",
    "wof:placetype":"locality"
},
  "geometry": {"coordinates":[66.17746,27.59333],"type":"Point"}
}