{
  "type": "Feature",
  "properties": {
    "gn:admin1_code":"4",
    "gn:asciiname":"Chak One Hundred Twenty-four-Seven E Right",
    "gn:country_code":"PK",
    "gn:dem":153,
    "gn:feature_class":"P",
    "gn:feature_code":"PPL",
    "gn:name":"Chak One Hundred Twenty-four-Seven E Right",
    "gn:population":0,
    "gn:timezone":"Asia/Karachi",
    "iso:country":"PK",
    "name:und_x_variant":[
        "Chak One Hundred Twenty-four-Seven ER"
    ],
    "wof:name":"Chak One Hundred Twenty-four-Seven E Right",
    "wof:placetype":"locality"
},
  "geometry": {"coordinates":[72.44946999999998,30.54015],"type":"Point"}
}