{
  "type": "Feature",
  "properties": {
    "gn:admin1_code":"08",
    "gn:asciiname":"Kuri",
    "gn:country_code":"PK",
    "gn:dem":516,
    "gn:feature_class":"P",
    "gn:feature_code":"PPL",
    "gn:name":"Kuri",
    "gn:population":0,
    "gn:timezone":"Asia/Karachi",
    "iso:country":"PK",
    "name:ceb_x_preferred":[
        "Kuri"
    ],
    "name:ces_x_preferred":[
        "Kuri"
    ],
    "name:deu_x_preferred":[
        "Kuri"
    ],
    "name:fra_x_preferred":[
        "Kuri"
    ],
    "name:spa_x_preferred":[
        "Kuri"
    ],
    "name:swe_x_preferred":[
        "Kuri"
    ],
    "name:und_x_variant":[
        "Korri",
        "Kuri"
    ],
    "wof:name":"Kuri",
    "wof:placetype":"locality"
},
  "geometry": {"coordinates":[73.17983000000002,33.68068],"type":"Point"}
}