{
  "type": "Feature",
  "properties": {
    "gn:admin1_code":"02",
    "gn:asciiname":"Reg Farang",
    "gn:cc2":"PK",
    "gn:country_code":"PK",
    "gn:dem":532,
    "gn:feature_class":"P",
    "gn:feature_code":"PPL",
    "gn:name":"Reg Farang",
    "gn:population":0,
    "gn:timezone":"Asia/Karachi",
    "iso:country":"PK",
    "name:und_x_variant":[
        "Reg Furang",
        "Reg Farang"
    ],
    "wof:name":"Reg Farang",
    "wof:placetype":"locality"
},
  "geometry": {"coordinates":[63.49083,27.92778],"type":"Point"}
}