{
  "type": "Feature",
  "properties": {
    "gn:admin1_code":"3.0",
    "gn:asciiname":"Nawe Dhand",
    "gn:country_code":"PK",
    "gn:dem":950,
    "gn:feature_class":"P",
    "gn:feature_code":"PPL",
    "gn:name":"Nawe Dhand",
    "gn:population":0,
    "gn:timezone":"Asia/Karachi",
    "iso:country":"PK",
    "wof:name":"Nawe Dhand",
    "wof:placetype":"locality"
},
  "geometry": {"coordinates":[72.21991,34.5239],"type":"Point"}
}