{
  "type": "Feature",
  "properties": {
    "gn:admin1_code":"3.0",
    "gn:asciiname":"Bringwal",
    "gn:country_code":"PK",
    "gn:dem":725,
    "gn:feature_class":"P",
    "gn:feature_code":"PPL",
    "gn:name":"Bringwal",
    "gn:population":0,
    "gn:timezone":"Asia/Karachi",
    "iso:country":"PK",
    "wof:name":"Bringwal",
    "wof:placetype":"locality"
},
  "geometry": {"coordinates":[72.78062,34.30293],"type":"Point"}
}