{
  "type": "Feature",
  "properties": {
    "gn:admin1_code":"2.0",
    "gn:asciiname":"Sui",
    "gn:country_code":"PK",
    "gn:dem":230,
    "gn:feature_class":"P",
    "gn:feature_code":"PPL",
    "gn:name":"Sui",
    "gn:population":0,
    "gn:timezone":"Asia/Karachi",
    "iso:country":"PK",
    "name:deu_x_preferred":[
        "Sui"
    ],
    "name:fas_x_preferred":[
        "\u0633\u0648\u0626\u06cc"
    ],
    "name:ita_x_preferred":[
        "Sui"
    ],
    "name:pol_x_preferred":[
        "Sui"
    ],
    "name:tur_x_preferred":[
        "Sui"
    ],
    "name:urd_x_preferred":[
        "\u0633\u0648\u0626\u06cc"
    ],
    "wof:name":"Sui",
    "wof:placetype":"locality"
},
  "geometry": {"coordinates":[69.17888000000001,28.63167],"type":"Point"}
}