{
  "type": "Feature",
  "properties": {
    "gn:admin1_code":"5",
    "gn:asciiname":"Karim Dino Dehr",
    "gn:country_code":"PK",
    "gn:dem":45,
    "gn:feature_class":"P",
    "gn:feature_code":"PPL",
    "gn:name":"Karim Dino Dehr",
    "gn:population":0,
    "gn:timezone":"Asia/Karachi",
    "iso:country":"PK",
    "name:und_x_variant":[
        "Dehr\u0101j"
    ],
    "wof:name":"Karim Dino Dehr",
    "wof:placetype":"locality"
},
  "geometry": {"coordinates":[68.09536999999999,26.9444],"type":"Point"}
}