{
  "type": "Feature",
  "properties": {
    "gn:admin1_code":"4",
    "gn:asciiname":"Basti Mari",
    "gn:country_code":"PK",
    "gn:dem":116,
    "gn:feature_class":"P",
    "gn:feature_code":"PPL",
    "gn:name":"Basti Mari",
    "gn:population":0,
    "gn:timezone":"Asia/Karachi",
    "iso:country":"PK",
    "name:und_x_variant":[
        "M\u0101ri"
    ],
    "wof:name":"Basti Mari",
    "wof:placetype":"locality"
},
  "geometry": {"coordinates":[70.64574,29.95898],"type":"Point"}
}