{
  "type": "Feature",
  "properties": {
    "gn:admin1_code":"4.0",
    "gn:asciiname":"Dera Javid Khan",
    "gn:country_code":"PK",
    "gn:dem":169,
    "gn:feature_class":"P",
    "gn:feature_code":"PPL",
    "gn:name":"Dera Javid Khan",
    "gn:population":0,
    "gn:timezone":"Asia/Karachi",
    "iso:country":"PK",
    "name:und_x_variant":[
        "Dera J\u0101ved Isr\u0101r Kh\u0101n"
    ],
    "wof:name":"Dera Javid Khan",
    "wof:placetype":"locality"
},
  "geometry": {"coordinates":[71.26756999999998,31.58887],"type":"Point"}
}