{
  "type": "Feature",
  "properties": {
    "gn:admin1_code":"4.0",
    "gn:asciiname":"Kabirwala",
    "gn:country_code":"PK",
    "gn:dem":101,
    "gn:feature_class":"P",
    "gn:feature_code":"PPL",
    "gn:name":"Kabirwala",
    "gn:population":0,
    "gn:timezone":"Asia/Karachi",
    "iso:country":"PK",
    "name:eng_x_preferred":[
        "Kabirwala"
    ],
    "name:fas_x_preferred":[
        "\u06a9\u0628\u06cc\u0631 \u0648\u0627\u0644\u0627"
    ],
    "name:fra_x_preferred":[
        "Kabirwala"
    ],
    "name:pol_x_preferred":[
        "Kabirwala"
    ],
    "name:por_x_preferred":[
        "Kabirwala"
    ],
    "name:spa_x_preferred":[
        "Kabirwala"
    ],
    "name:urd_x_preferred":[
        "\u06a9\u0628\u06cc\u0631 \u0648\u0627\u0644\u0627"
    ],
    "wof:name":"Kabirwala",
    "wof:placetype":"locality"
},
  "geometry": {"coordinates":[70.85993999999999,29.33386],"type":"Point"}
}