{
  "type": "Feature",
  "properties": {
    "gn:admin1_code":"1",
    "gn:asciiname":"Mir Ghundkai",
    "gn:country_code":"PK",
    "gn:dem":1444,
    "gn:feature_class":"P",
    "gn:feature_code":"PPL",
    "gn:name":"Mir Ghundkai",
    "gn:population":0,
    "gn:timezone":"Asia/Karachi",
    "iso:country":"PK",
    "wof:name":"Mir Ghundkai",
    "wof:placetype":"locality"
},
  "geometry": {"coordinates":[69.94028,32.49778],"type":"Point"}
}