{
  "type": "Feature",
  "properties": {
    "gn:admin1_code":"5.0",
    "gn:asciiname":"Goth Bolari",
    "gn:country_code":"PK",
    "gn:dem":40,
    "gn:feature_class":"P",
    "gn:feature_code":"PPL",
    "gn:name":"Goth Bolari",
    "gn:population":0,
    "gn:timezone":"Asia/Karachi",
    "iso:country":"PK",
    "name:und_x_variant":[
        "Bol\u0101ri",
        "Bolair",
        "Bhol\u0101ri",
        "Goth Bolari"
    ],
    "name:urd_x_preferred":[
        "\u0628\u06be\u0648\u0644\u0627\u0631\u06cc"
    ],
    "wof:name":"Goth Bolari",
    "wof:placetype":"locality"
},
  "geometry": {"coordinates":[68.21661,25.28899],"type":"Point"}
}