{
  "type": "Feature",
  "properties": {
    "gn:admin1_code":"3.0",
    "gn:asciiname":"Shalizar",
    "gn:country_code":"PK",
    "gn:dem":622,
    "gn:feature_class":"P",
    "gn:feature_code":"PPL",
    "gn:name":"Shalizar",
    "gn:population":0,
    "gn:timezone":"Asia/Karachi",
    "iso:country":"PK",
    "wof:name":"Shalizar",
    "wof:placetype":"locality"
},
  "geometry": {"coordinates":[72.67923,34.43624000000001],"type":"Point"}
}