{
  "type": "Feature",
  "properties": {
    "gn:admin1_code":"5",
    "gn:asciiname":"Tando Hafiz Shah",
    "gn:country_code":"PK",
    "gn:dem":22,
    "gn:feature_class":"P",
    "gn:feature_code":"PPL",
    "gn:name":"Tando Hafiz Shah",
    "gn:population":0,
    "gn:timezone":"Asia/Karachi",
    "iso:country":"PK",
    "name:eng_x_preferred":[
        "Tando Hafiz Shah"
    ],
    "wof:name":"Tando Hafiz Shah",
    "wof:placetype":"locality"
},
  "geometry": {"coordinates":[68.31019000000001,25.17465],"type":"Point"}
}