{
  "type": "Feature",
  "properties": {
    "gn:admin1_code":"4.0",
    "gn:asciiname":"Jafarwala",
    "gn:country_code":"PK",
    "gn:dem":110,
    "gn:feature_class":"P",
    "gn:feature_code":"PPL",
    "gn:name":"Jafarwala",
    "gn:population":0,
    "gn:timezone":"Asia/Karachi",
    "iso:country":"PK",
    "name:und_x_variant":[
        "J\u0101farw\u0101la"
    ],
    "wof:name":"Jafarwala",
    "wof:placetype":"locality"
},
  "geometry": {"coordinates":[71.25320000000001,29.64423],"type":"Point"}
}