{
  "type": "Feature",
  "properties": {
    "gn:admin1_code":"4.0",
    "gn:asciiname":"Maliwala",
    "gn:country_code":"PK",
    "gn:dem":201,
    "gn:feature_class":"P",
    "gn:feature_code":"PPL",
    "gn:name":"Maliwala",
    "gn:population":0,
    "gn:timezone":"Asia/Karachi",
    "iso:country":"PK",
    "name:und_x_variant":[
        "Malliw\u0101la"
    ],
    "wof:name":"Maliwala",
    "wof:placetype":"locality"
},
  "geometry": {"coordinates":[74.03173000000002,31.41971],"type":"Point"}
}