{
  "type": "Feature",
  "properties": {
    "gn:admin1_code":"2.0",
    "gn:asciiname":"Haji Mihrab",
    "gn:country_code":"PK",
    "gn:dem":1032,
    "gn:feature_class":"P",
    "gn:feature_code":"PPL",
    "gn:name":"Haji Mihrab",
    "gn:population":0,
    "gn:timezone":"Asia/Karachi",
    "iso:country":"PK",
    "wof:name":"Haji Mihrab",
    "wof:placetype":"locality"
},
  "geometry": {"coordinates":[66.21438000000001,27.02454],"type":"Point"}
}