{
  "type": "Feature",
  "properties": {
    "gn:admin1_code":"03",
    "gn:asciiname":"Sharahdata Banda",
    "gn:country_code":"PK",
    "gn:dem":715,
    "gn:feature_class":"P",
    "gn:feature_code":"PPL",
    "gn:name":"Sharahdata Banda",
    "gn:population":0,
    "gn:timezone":"Asia/Karachi",
    "iso:country":"PK",
    "name:eng_x_preferred":[
        "Sharabdara Banda"
    ],
    "wof:name":"Sharahdata Banda",
    "wof:placetype":"locality"
},
  "geometry": {"coordinates":[71.99871,34.60974],"type":"Point"}
}