{
  "type": "Feature",
  "properties": {
    "gn:admin1_code":"5.0",
    "gn:asciiname":"Goth Jafar Khan Buzdar",
    "gn:country_code":"PK",
    "gn:dem":18,
    "gn:feature_class":"P",
    "gn:feature_code":"PPL",
    "gn:name":"Goth Jafar Khan Buzdar",
    "gn:population":0,
    "gn:timezone":"Asia/Karachi",
    "iso:country":"PK",
    "name:und_x_variant":[
        "Jafar Khan Bozdar",
        "Goth Jafar Khan Buzdar",
        "J\u0101far Kh\u0101n Buzd\u0101r"
    ],
    "wof:name":"Goth Jafar Khan Buzdar",
    "wof:placetype":"locality"
},
  "geometry": {"coordinates":[68.61967,25.119],"type":"Point"}
}