{
  "type": "Feature",
  "properties": {
    "gn:admin1_code":"6",
    "gn:asciiname":"Kunjri Mul",
    "gn:country_code":"PK",
    "gn:dem":367,
    "gn:feature_class":"P",
    "gn:feature_code":"PPL",
    "gn:name":"Kunjri Mul",
    "gn:population":0,
    "gn:timezone":"Asia/Karachi",
    "iso:country":"PK",
    "name:und_x_variant":[
        "Kunjri",
        "Kunjri Mul"
    ],
    "wof:name":"Kunjri Mul",
    "wof:placetype":"locality"
},
  "geometry": {"coordinates":[73.76913,33.16801],"type":"Point"}
}