{
  "type": "Feature",
  "properties": {
    "gn:admin1_code":"3.0",
    "gn:asciiname":"Aru",
    "gn:country_code":"PK",
    "gn:dem":1829,
    "gn:feature_class":"P",
    "gn:feature_code":"PPL",
    "gn:name":"Aru",
    "gn:population":0,
    "gn:timezone":"Asia/Karachi",
    "iso:country":"PK",
    "wof:name":"Aru",
    "wof:placetype":"locality"
},
  "geometry": {"coordinates":[73.28504000000002,34.55656],"type":"Point"}
}