{
  "type": "Feature",
  "properties": {
    "gn:admin1_code":"3.0",
    "gn:asciiname":"Aru",
    "gn:country_code":"PK",
    "gn:dem":1829,
    "gn:feature_class":"P",
    "gn:feature_code":"PPL",
    "gn:name":"Aru",
    "gn:population":0,
    "gn:timezone":"Asia/Karachi",
    "iso:country":"PK",
    "name:ast_x_preferred":[
        "Aru"
    ],
    "name:ceb_x_preferred":[
        "Aru"
    ],
    "name:est_x_preferred":[
        "Aru"
    ],
    "name:hye_x_preferred":[
        "\u0531\u057c\u0578\u0582"
    ],
    "name:ind_x_preferred":[
        "Aru"
    ],
    "name:nld_x_preferred":[
        "Aru"
    ],
    "name:pol_x_preferred":[
        "Aru"
    ],
    "name:por_x_preferred":[
        "Aru"
    ],
    "name:rus_x_preferred":[
        "\u0410\u0440\u0443"
    ],
    "name:srp_x_preferred":[
        "\u0410\u0440\u0443"
    ],
    "name:swe_x_preferred":[
        "Aru"
    ],
    "name:vol_x_preferred":[
        "Aru"
    ],
    "wof:name":"Aru",
    "wof:placetype":"locality"
},
  "geometry": {"coordinates":[73.28504000000002,34.55656],"type":"Point"}
}