{
  "type": "Feature",
  "properties": {
    "gn:admin1_code":"6",
    "gn:asciiname":"Chitial",
    "gn:country_code":"PK",
    "gn:dem":2041,
    "gn:feature_class":"P",
    "gn:feature_code":"PPL",
    "gn:name":"Chitial",
    "gn:population":0,
    "gn:timezone":"Asia/Karachi",
    "iso:country":"PK",
    "name:und_x_variant":[
        "Chiti\u0101l"
    ],
    "wof:name":"Chitial",
    "wof:placetype":"locality"
},
  "geometry": {"coordinates":[73.79680999999999,34.31114],"type":"Point"}
}