{
  "type": "Feature",
  "properties": {
    "gn:admin1_code":"4.0",
    "gn:asciiname":"Katimar",
    "gn:country_code":"PK",
    "gn:dem":179,
    "gn:feature_class":"P",
    "gn:feature_code":"PPL",
    "gn:name":"Katimar",
    "gn:population":0,
    "gn:timezone":"Asia/Karachi",
    "iso:country":"PK",
    "name:eng_x_preferred":[
        "Katimar"
    ],
    "wof:name":"Katimar",
    "wof:placetype":"locality"
},
  "geometry": {"coordinates":[71.86409999999999,31.68947],"type":"Point"}
}