{
  "type": "Feature",
  "properties": {
    "gn:admin1_code":"3",
    "gn:asciiname":"Kohistan Tikai",
    "gn:country_code":"PK",
    "gn:dem":3426,
    "gn:feature_class":"P",
    "gn:feature_code":"PPL",
    "gn:name":"Kohistan Tikai",
    "gn:population":0,
    "gn:timezone":"Asia/Karachi",
    "iso:country":"PK",
    "name:eng_x_preferred":[
        "Kohistan Tikai"
    ],
    "wof:name":"Kohistan Tikai",
    "wof:placetype":"locality"
},
  "geometry": {"coordinates":[72.50211999999998,35.26979],"type":"Point"}
}