{
  "type": "Feature",
  "properties": {
    "gn:admin1_code":"4",
    "gn:asciiname":"Khangah",
    "gn:country_code":"PK",
    "gn:dem":184,
    "gn:feature_class":"P",
    "gn:feature_code":"PPL",
    "gn:name":"Khangah",
    "gn:population":0,
    "gn:timezone":"Asia/Karachi",
    "iso:country":"PK",
    "name:und_x_variant":[
        "Dingar Faq\u012br",
        "Khangah"
    ],
    "wof:name":"Khangah",
    "wof:placetype":"locality"
},
  "geometry": {"coordinates":[71.80459999999999,32.05633],"type":"Point"}
}