{
  "type": "Feature",
  "properties": {
    "gn:admin1_code":"4.0",
    "gn:asciiname":"Dhok Luna",
    "gn:country_code":"PK",
    "gn:dem":263,
    "gn:feature_class":"P",
    "gn:feature_code":"PPL",
    "gn:name":"Dhok Luna",
    "gn:population":0,
    "gn:timezone":"Asia/Karachi",
    "iso:country":"PK",
    "wof:name":"Dhok Luna",
    "wof:placetype":"locality"
},
  "geometry": {"coordinates":[73.43269000000002,32.81329],"type":"Point"}
}