{
  "type": "Feature",
  "properties": {
    "gn:admin1_code":"3.0",
    "gn:asciiname":"Taruri",
    "gn:country_code":"PK",
    "gn:dem":1165,
    "gn:feature_class":"P",
    "gn:feature_code":"PPL",
    "gn:name":"Taruri",
    "gn:population":0,
    "gn:timezone":"Asia/Karachi",
    "iso:country":"PK",
    "name:eng_x_preferred":[
        "Dharauri"
    ],
    "wof:name":"Taruri",
    "wof:placetype":"locality"
},
  "geometry": {"coordinates":[73.17531,33.95083],"type":"Point"}
}