{
  "type": "Feature",
  "properties": {
    "gn:admin1_code":"3",
    "gn:asciiname":"Dad Banda",
    "gn:country_code":"PK",
    "gn:dem":2325,
    "gn:feature_class":"P",
    "gn:feature_code":"PPL",
    "gn:name":"Dad Banda",
    "gn:population":0,
    "gn:timezone":"Asia/Karachi",
    "iso:country":"PK",
    "name:eng_x_preferred":[
        "Dad Banda"
    ],
    "wof:name":"Dad Banda",
    "wof:placetype":"locality"
},
  "geometry": {"coordinates":[71.99379999999999,35.17295],"type":"Point"}
}