{
  "type": "Feature",
  "properties": {
    "gn:admin1_code":"03",
    "gn:asciiname":"Paraikas",
    "gn:country_code":"PK",
    "gn:dem":1033,
    "gn:feature_class":"P",
    "gn:feature_code":"PPL",
    "gn:name":"Paraikas",
    "gn:population":0,
    "gn:timezone":"Asia/Karachi",
    "iso:country":"PK",
    "name:eng_x_preferred":[
        "Paraikas"
    ],
    "wof:name":"Paraikas",
    "wof:placetype":"locality"
},
  "geometry": {"coordinates":[71.79959000000002,34.94981],"type":"Point"}
}