{
  "type": "Feature",
  "properties": {
    "gn:admin1_code":"5",
    "gn:asciiname":"Mir Muhammad Halipota",
    "gn:country_code":"PK",
    "gn:dem":9,
    "gn:feature_class":"P",
    "gn:feature_code":"PPL",
    "gn:name":"Mir Muhammad Halipota",
    "gn:population":0,
    "gn:timezone":"Asia/Karachi",
    "iso:country":"PK",
    "wof:name":"Mir Muhammad Halipota",
    "wof:placetype":"locality"
},
  "geometry": {"coordinates":[69.49167,25.34444],"type":"Point"}
}