{
  "type": "Feature",
  "properties": {
    "gn:admin1_code":"02",
    "gn:asciiname":"Goth Lahro",
    "gn:country_code":"PK",
    "gn:dem":68,
    "gn:feature_class":"P",
    "gn:feature_code":"PPL",
    "gn:name":"Goth Lahro",
    "gn:population":0,
    "gn:timezone":"Asia/Karachi",
    "iso:country":"PK",
    "name:und_x_variant":[
        "Lang Lohar\u0101ni"
    ],
    "wof:name":"Goth Lahro",
    "wof:placetype":"locality"
},
  "geometry": {"coordinates":[67.05443000000001,25.22426],"type":"Point"}
}