{
  "type": "Feature",
  "properties": {
    "gn:admin1_code":"3.0",
    "gn:asciiname":"Garhi Sharif Khan",
    "gn:country_code":"PK",
    "gn:dem":304,
    "gn:feature_class":"P",
    "gn:feature_code":"PPL",
    "gn:name":"Garhi Sharif Khan",
    "gn:population":0,
    "gn:timezone":"Asia/Karachi",
    "iso:country":"PK",
    "name:eng_x_preferred":[
        "Garhi Shar\u012bf Kh\u0101n"
    ],
    "wof:name":"Garhi Sharif Khan",
    "wof:placetype":"locality"
},
  "geometry": {"coordinates":[71.64931999999997,34.13377],"type":"Point"}
}