{
  "type": "Feature",
  "properties": {
    "gn:admin1_code":"03",
    "gn:asciiname":"Shahidano Kas",
    "gn:country_code":"PK",
    "gn:dem":938,
    "gn:feature_class":"P",
    "gn:feature_code":"PPL",
    "gn:name":"Shahidano Kas",
    "gn:population":0,
    "gn:timezone":"Asia/Karachi",
    "iso:country":"PK",
    "name:eng_x_preferred":[
        "Shah\u012bd\u0101no Kats"
    ],
    "wof:name":"Shahidano Kas",
    "wof:placetype":"locality"
},
  "geometry": {"coordinates":[71.94996,34.88684],"type":"Point"}
}