{
  "type": "Feature",
  "properties": {
    "gn:admin1_code":"3",
    "gn:asciiname":"Shahjahan Banda",
    "gn:country_code":"PK",
    "gn:dem":1667,
    "gn:feature_class":"P",
    "gn:feature_code":"PPL",
    "gn:name":"Shahjahan Banda",
    "gn:population":0,
    "gn:timezone":"Asia/Karachi",
    "iso:country":"PK",
    "wof:name":"Shahjahan Banda",
    "wof:placetype":"locality"
},
  "geometry": {"coordinates":[72.19795000000001,34.90364],"type":"Point"}
}