{
  "type": "Feature",
  "properties": {
    "gn:admin1_code":"6",
    "gn:asciiname":"Nanga Tak",
    "gn:country_code":"PK",
    "gn:dem":2749,
    "gn:feature_class":"P",
    "gn:feature_code":"PPL",
    "gn:name":"Nanga Tak",
    "gn:population":0,
    "gn:timezone":"Asia/Karachi",
    "iso:country":"PK",
    "name:und_x_variant":[
        "N\u0101nga Tak"
    ],
    "wof:name":"Nanga Tak",
    "wof:placetype":"locality"
},
  "geometry": {"coordinates":[73.85703000000002,34.20336],"type":"Point"}
}