{
  "type": "Feature",
  "properties": {
    "gn:admin1_code":"5",
    "gn:asciiname":"Haji Muhamamd Bakhsh Kubar",
    "gn:country_code":"PK",
    "gn:dem":15,
    "gn:feature_class":"P",
    "gn:feature_code":"PPL",
    "gn:name":"Haji Muhamamd Bakhsh Kubar",
    "gn:population":0,
    "gn:timezone":"Asia/Karachi",
    "iso:country":"PK",
    "name:und_x_variant":[
        "Goth Kubar"
    ],
    "wof:name":"Haji Muhamamd Bakhsh Kubar",
    "wof:placetype":"locality"
},
  "geometry": {"coordinates":[69.33195000000001,25.7926],"type":"Point"}
}