{
  "type": "Feature",
  "properties": {
    "gn:admin1_code":"7.0",
    "gn:asciiname":"Shagari Bala",
    "gn:country_code":"PK",
    "gn:dem":2397,
    "gn:feature_class":"P",
    "gn:feature_code":"PPL",
    "gn:name":"Shagari Bala",
    "gn:population":0,
    "gn:timezone":"Asia/Karachi",
    "iso:country":"PK",
    "name:und_x_variant":[
        "Shagari"
    ],
    "wof:name":"Shagari Bala",
    "wof:placetype":"locality"
},
  "geometry": {"coordinates":[75.55513000000001,35.28742000000001],"type":"Point"}
}