{
  "type": "Feature",
  "properties": {
    "gn:admin1_code":"3.0",
    "gn:asciiname":"Saka Kas",
    "gn:country_code":"PK",
    "gn:dem":1998,
    "gn:feature_class":"P",
    "gn:feature_code":"PPL",
    "gn:name":"Saka Kas",
    "gn:population":0,
    "gn:timezone":"Asia/Karachi",
    "iso:country":"PK",
    "wof:name":"Saka Kas",
    "wof:placetype":"locality"
},
  "geometry": {"coordinates":[73.38292,34.05087],"type":"Point"}
}