{
  "type": "Feature",
  "properties": {
    "gn:admin1_code":"4",
    "gn:asciiname":"Musewala",
    "gn:country_code":"PK",
    "gn:dem":127,
    "gn:feature_class":"P",
    "gn:feature_code":"PPL",
    "gn:name":"M\u016bsew\u0101la",
    "gn:population":0,
    "gn:timezone":"Asia/Karachi",
    "iso:country":"PK",
    "name:eng_x_preferred":[
        "M\u016bsew\u0101la"
    ],
    "wof:name":"Musewala",
    "wof:placetype":"locality"
},
  "geometry": {"coordinates":[70.91654,30.33349],"type":"Point"}
}