{
  "type": "Feature",
  "properties": {
    "gn:admin1_code":"3",
    "gn:asciiname":"Dherai",
    "gn:country_code":"PK",
    "gn:dem":1961,
    "gn:feature_class":"P",
    "gn:feature_code":"PPL",
    "gn:name":"Dherai",
    "gn:population":0,
    "gn:timezone":"Asia/Karachi",
    "iso:country":"PK",
    "name:und_x_variant":[
        "Derai",
        "Dherai"
    ],
    "wof:name":"Dherai",
    "wof:placetype":"locality"
},
  "geometry": {"coordinates":[72.73663000000001,35.0424],"type":"Point"}
}