{
  "type": "Feature",
  "properties": {
    "gn:admin1_code":"3.0",
    "gn:asciiname":"Tarnawai",
    "gn:country_code":"PK",
    "gn:dem":1316,
    "gn:feature_class":"P",
    "gn:feature_code":"PPL",
    "gn:name":"Tarnawai",
    "gn:population":0,
    "gn:timezone":"Asia/Karachi",
    "iso:country":"PK",
    "wof:name":"Tarnawai",
    "wof:placetype":"locality"
},
  "geometry": {"coordinates":[73.33734,34.35756],"type":"Point"}
}