{
  "type": "Feature",
  "properties": {
    "gn:admin1_code":"01",
    "gn:asciiname":"Pipal Shah",
    "gn:country_code":"PK",
    "gn:dem":920,
    "gn:feature_class":"P",
    "gn:feature_code":"PPL",
    "gn:name":"Pipal Shah",
    "gn:population":0,
    "gn:timezone":"Asia/Karachi",
    "iso:country":"PK",
    "wof:name":"Pipal Shah",
    "wof:placetype":"locality"
},
  "geometry": {"coordinates":[71.69345,34.75077],"type":"Point"}
}