{
  "type": "Feature",
  "properties": {
    "gn:admin1_code":"1.0",
    "gn:asciiname":"Shamal Khel",
    "gn:country_code":"PK",
    "gn:dem":994,
    "gn:feature_class":"P",
    "gn:feature_code":"PPL",
    "gn:name":"Shamal Khel",
    "gn:population":0,
    "gn:timezone":"Asia/Karachi",
    "iso:country":"PK",
    "name:und_x_variant":[
        "Sh\u0101hmal Khel"
    ],
    "wof:name":"Shamal Khel",
    "wof:placetype":"locality"
},
  "geometry": {"coordinates":[71.63781,33.68011],"type":"Point"}
}