{
  "type": "Feature",
  "properties": {
    "gn:admin1_code":"1.0",
    "gn:asciiname":"Toti Bagh",
    "gn:country_code":"PK",
    "gn:dem":1550,
    "gn:feature_class":"P",
    "gn:feature_code":"PPL",
    "gn:name":"Toti Bagh",
    "gn:population":0,
    "gn:timezone":"Asia/Karachi",
    "iso:country":"PK",
    "wof:name":"Toti Bagh",
    "wof:placetype":"locality"
},
  "geometry": {"coordinates":[71.01808,33.78225],"type":"Point"}
}