{
  "type": "Feature",
  "properties": {
    "gn:admin1_code":"04",
    "gn:asciiname":"Vidor",
    "gn:country_code":"PK",
    "gn:dem":154,
    "gn:feature_class":"P",
    "gn:feature_code":"PPL",
    "gn:name":"Vidor",
    "gn:population":0,
    "gn:timezone":"Asia/Karachi",
    "iso:country":"PK",
    "name:azb_x_preferred":[
        "\u0648\u06cc\u062f\u0648\u0631"
    ],
    "name:bul_x_preferred":[
        "\u0412\u0438\u0434\u043e\u0440"
    ],
    "name:ceb_x_preferred":[
        "Vidor"
    ],
    "name:deu_x_preferred":[
        "Vidor"
    ],
    "name:epo_x_preferred":[
        "Vidor"
    ],
    "name:eus_x_preferred":[
        "Vidor"
    ],
    "name:fas_x_preferred":[
        "\u0648\u06cc\u062f\u0648\u0631"
    ],
    "name:fra_x_preferred":[
        "Vidor"
    ],
    "name:hun_x_preferred":[
        "Vidor"
    ],
    "name:hye_x_preferred":[
        "\u054e\u056b\u0564\u0578\u0580"
    ],
    "name:ita_x_preferred":[
        "Vidor"
    ],
    "name:jpn_x_preferred":[
        "\u30f4\u30a3\u30c9\u30fc\u30eb"
    ],
    "name:lat_x_preferred":[
        "Vidor"
    ],
    "name:lmo_x_preferred":[
        "Vidor"
    ],
    "name:msa_x_preferred":[
        "Vidor"
    ],
    "name:nap_x_preferred":[
        "Vidor"
    ],
    "name:nld_x_preferred":[
        "Vidor"
    ],
    "name:pms_x_preferred":[
        "Vidor"
    ],
    "name:pol_x_preferred":[
        "Vidor"
    ],
    "name:por_x_preferred":[
        "Vidor"
    ],
    "name:ron_x_preferred":[
        "Vidor"
    ],
    "name:rus_x_preferred":[
        "\u0412\u0438\u0434\u043e\u0440"
    ],
    "name:scn_x_preferred":[
        "Vidor"
    ],
    "name:spa_x_preferred":[
        "Vidor"
    ],
    "name:srp_x_preferred":[
        "\u0412\u0438\u0434\u043e\u0440"
    ],
    "name:tgl_x_preferred":[
        "Vidor"
    ],
    "name:ukr_x_preferred":[
        "\u0412\u0456\u0434\u043e\u0440"
    ],
    "name:und_x_variant":[
        "Wadoor"
    ],
    "name:vec_x_preferred":[
        "Vidor"
    ],
    "name:vie_x_preferred":[
        "Vidor"
    ],
    "name:vol_x_preferred":[
        "Vidor"
    ],
    "name:war_x_preferred":[
        "Vidor"
    ],
    "wof:name":"Vidor",
    "wof:placetype":"locality"
},
  "geometry": {"coordinates":[70.5416,30.07836],"type":"Point"}
}