{
  "type": "Feature",
  "properties": {
    "gn:admin1_code":"04",
    "gn:asciiname":"Vidor",
    "gn:country_code":"PK",
    "gn:dem":154,
    "gn:feature_class":"P",
    "gn:feature_code":"PPL",
    "gn:name":"Vidor",
    "gn:population":0,
    "gn:timezone":"Asia/Karachi",
    "iso:country":"PK",
    "name:und_x_variant":[
        "Wadoor",
        "Vidor"
    ],
    "wof:name":"Vidor",
    "wof:placetype":"locality"
},
  "geometry": {"coordinates":[70.5416,30.07836],"type":"Point"}
}