{
  "type": "Feature",
  "properties": {
    "gn:admin1_code":"4.0",
    "gn:asciiname":"Dera Khudayar",
    "gn:country_code":"PK",
    "gn:dem":225,
    "gn:feature_class":"P",
    "gn:feature_code":"PPL",
    "gn:name":"Dera Khudayar",
    "gn:population":0,
    "gn:timezone":"Asia/Karachi",
    "iso:country":"PK",
    "wof:name":"Dera Khudayar",
    "wof:placetype":"locality"
},
  "geometry": {"coordinates":[71.60604000000002,32.76024],"type":"Point"}
}