{
  "type": "Feature",
  "properties": {
    "gn:admin1_code":"5.0",
    "gn:asciiname":"Nawabad",
    "gn:country_code":"PK",
    "gn:dem":7,
    "gn:feature_class":"P",
    "gn:feature_code":"PPL",
    "gn:name":"Nawabad",
    "gn:population":0,
    "gn:timezone":"Asia/Karachi",
    "iso:country":"PK",
    "name:eng_x_preferred":[
        "Nawabad"
    ],
    "wof:name":"Nawabad",
    "wof:placetype":"locality"
},
  "geometry": {"coordinates":[68.16412,24.52105],"type":"Point"}
}