{
  "type": "Feature",
  "properties": {
    "gn:admin1_code":"4.0",
    "gn:asciiname":"Alamgir",
    "gn:country_code":"PK",
    "gn:dem":121,
    "gn:feature_class":"P",
    "gn:feature_code":"PPL",
    "gn:name":"Alamgir",
    "gn:population":0,
    "gn:timezone":"Asia/Karachi",
    "iso:country":"PK",
    "name:ben_x_preferred":[
        "\u0986\u09b2\u09ae\u0997\u09c0\u09b0"
    ],
    "name:deu_x_preferred":[
        "Alamgir"
    ],
    "name:jpn_x_preferred":[
        "\u30a2\u30fc\u30e9\u30e0\u30ae\u30fc\u30eb"
    ],
    "wof:name":"Alamgir",
    "wof:placetype":"locality"
},
  "geometry": {"coordinates":[71.41839,30.12232],"type":"Point"}
}