{
  "type": "Feature",
  "properties": {
    "gn:admin1_code":"3.0",
    "gn:asciiname":"Mujguli",
    "gn:country_code":"PK",
    "gn:dem":1615,
    "gn:feature_class":"P",
    "gn:feature_code":"PPL",
    "gn:name":"Mujguli",
    "gn:population":0,
    "gn:timezone":"Asia/Karachi",
    "iso:country":"PK",
    "wof:name":"Mujguli",
    "wof:placetype":"locality"
},
  "geometry": {"coordinates":[72.90756,35.17568],"type":"Point"}
}