{
  "type": "Feature",
  "properties": {
    "gn:admin1_code":"2.0",
    "gn:asciiname":"Tut Masezai",
    "gn:country_code":"PK",
    "gn:dem":1534,
    "gn:feature_class":"P",
    "gn:feature_code":"PPL",
    "gn:name":"Tut Masezai",
    "gn:population":0,
    "gn:timezone":"Asia/Karachi",
    "iso:country":"PK",
    "wof:name":"Tut Masezai",
    "wof:placetype":"locality"
},
  "geometry": {"coordinates":[66.73151999999999,30.7253],"type":"Point"}
}