{
  "type": "Feature",
  "properties": {
    "gn:admin1_code":"4",
    "gn:asciiname":"Boranewala",
    "gn:country_code":"PK",
    "gn:dem":172,
    "gn:feature_class":"P",
    "gn:feature_code":"PPL",
    "gn:name":"Boranewala",
    "gn:population":0,
    "gn:timezone":"Asia/Karachi",
    "iso:country":"PK",
    "name:und_x_variant":[
        "Soranew\u0101la"
    ],
    "wof:name":"Boranewala",
    "wof:placetype":"locality"
},
  "geometry": {"coordinates":[71.16495,31.62007],"type":"Point"}
}