{
  "type": "Feature",
  "properties": {
    "gn:admin1_code":"7.0",
    "gn:asciiname":"Mango",
    "gn:country_code":"PK",
    "gn:dem":3684,
    "gn:feature_class":"P",
    "gn:feature_code":"PPL",
    "gn:name":"Mango",
    "gn:population":0,
    "gn:timezone":"Asia/Karachi",
    "iso:country":"PK",
    "wof:name":"Mango",
    "wof:placetype":"locality"
},
  "geometry": {"coordinates":[75.82701999999998,35.77245],"type":"Point"}
}