{
  "type": "Feature",
  "properties": {
    "gn:admin1_code":"3.0",
    "gn:asciiname":"Zarinbagh",
    "gn:country_code":"PK",
    "gn:dem":2424,
    "gn:feature_class":"P",
    "gn:feature_code":"PPL",
    "gn:name":"Zarinbagh",
    "gn:population":0,
    "gn:timezone":"Asia/Karachi",
    "iso:country":"PK",
    "wof:name":"Zarinbagh",
    "wof:placetype":"locality"
},
  "geometry": {"coordinates":[71.73276,35.35379000000001],"type":"Point"}
}