{
  "type": "Feature",
  "properties": {
    "gn:admin1_code":"2.0",
    "gn:asciiname":"Rachil",
    "gn:country_code":"PK",
    "gn:dem":677,
    "gn:feature_class":"P",
    "gn:feature_code":"PPL",
    "gn:name":"Rachil",
    "gn:population":0,
    "gn:timezone":"Asia/Karachi",
    "iso:country":"PK",
    "name:und_x_variant":[
        "Abdul Kar\u012bm"
    ],
    "wof:name":"Rachil",
    "wof:placetype":"locality"
},
  "geometry": {"coordinates":[65.3265,28.33562],"type":"Point"}
}