{
  "type": "Feature",
  "properties": {
    "gn:admin1_code":"2.0",
    "gn:asciiname":"Obashtgai",
    "gn:country_code":"PK",
    "gn:dem":2346,
    "gn:feature_class":"P",
    "gn:feature_code":"PPL",
    "gn:name":"Obashtgai",
    "gn:population":0,
    "gn:timezone":"Asia/Karachi",
    "iso:country":"PK",
    "name:eng_x_preferred":[
        "Obashtgai"
    ],
    "name:und_x_variant":[
        "Obashtkai"
    ],
    "wof:name":"Obashtgai",
    "wof:placetype":"locality"
},
  "geometry": {"coordinates":[67.41504999999999,30.7314],"type":"Point"}
}