{
  "type": "Feature",
  "properties": {
    "gn:admin1_code":"4.0",
    "gn:asciiname":"Alujhana",
    "gn:country_code":"PK",
    "gn:dem":261,
    "gn:feature_class":"P",
    "gn:feature_code":"PPL",
    "gn:name":"Alujhana",
    "gn:population":0,
    "gn:timezone":"Asia/Karachi",
    "iso:country":"PK",
    "name:und_x_variant":[
        "Atolhna"
    ],
    "wof:name":"Alujhana",
    "wof:placetype":"locality"
},
  "geometry": {"coordinates":[74.87143,32.28932],"type":"Point"}
}