{
  "type": "Feature",
  "properties": {
    "gn:admin1_code":"2.0",
    "gn:asciiname":"Haji Ghulle Muhammad",
    "gn:country_code":"PK",
    "gn:dem":1284,
    "gn:feature_class":"P",
    "gn:feature_code":"PPL",
    "gn:name":"Haji Ghulle Muhammad",
    "gn:population":0,
    "gn:timezone":"Asia/Karachi",
    "iso:country":"PK",
    "wof:name":"Haji Ghulle Muhammad",
    "wof:placetype":"locality"
},
  "geometry": {"coordinates":[69.89506999999999,30.28337],"type":"Point"}
}