{
  "type": "Feature",
  "properties": {
    "gn:admin1_code":"5.0",
    "gn:asciiname":"Kakepupa",
    "gn:country_code":"PK",
    "gn:dem":43,
    "gn:feature_class":"P",
    "gn:feature_code":"PPL",
    "gn:name":"Kakepupa",
    "gn:population":0,
    "gn:timezone":"Asia/Karachi",
    "iso:country":"PK",
    "name:und_x_variant":[
        "K\u0101keputra"
    ],
    "wof:name":"Kakepupa",
    "wof:placetype":"locality"
},
  "geometry": {"coordinates":[68.12255,26.80363],"type":"Point"}
}