{
  "type": "Feature",
  "properties": {
    "gn:admin1_code":"4.0",
    "gn:asciiname":"Dhok Hashu",
    "gn:country_code":"PK",
    "gn:dem":514,
    "gn:feature_class":"P",
    "gn:feature_code":"PPL",
    "gn:name":"Dhok Hashu",
    "gn:population":0,
    "gn:timezone":"Asia/Karachi",
    "iso:country":"PK",
    "wof:name":"Dhok Hashu",
    "wof:placetype":"locality"
},
  "geometry": {"coordinates":[73.05544999999999,33.14465999999999],"type":"Point"}
}