{
  "type": "Feature",
  "properties": {
    "gn:admin1_code":"5.0",
    "gn:asciiname":"Faiz Muhammad Sial",
    "gn:country_code":"PK",
    "gn:dem":47,
    "gn:feature_class":"P",
    "gn:feature_code":"PPL",
    "gn:name":"Faiz Muhammad Sial",
    "gn:population":0,
    "gn:timezone":"Asia/Karachi",
    "iso:country":"PK",
    "wof:name":"Faiz Muhammad Sial",
    "wof:placetype":"locality"
},
  "geometry": {"coordinates":[68.01478,27.54546],"type":"Point"}
}