{
  "type": "Feature",
  "properties": {
    "gn:admin1_code":"3.0",
    "gn:asciiname":"Asu Ram",
    "gn:country_code":"PK",
    "gn:dem":310,
    "gn:feature_class":"P",
    "gn:feature_code":"PPL",
    "gn:name":"Asu R\u0101m",
    "gn:population":0,
    "gn:timezone":"Asia/Karachi",
    "iso:country":"PK",
    "wof:name":"Asu Ram",
    "wof:placetype":"locality"
},
  "geometry": {"coordinates":[70.73416999999998,32.80860999999999],"type":"Point"}
}