{
  "type": "Feature",
  "properties": {
    "gn:admin1_code":"2.0",
    "gn:asciiname":"Kili Muhammad Jafar",
    "gn:country_code":"PK",
    "gn:dem":1901,
    "gn:feature_class":"P",
    "gn:feature_code":"PPL",
    "gn:name":"Kili Muhammad Jafar",
    "gn:population":0,
    "gn:timezone":"Asia/Karachi",
    "iso:country":"PK",
    "wof:name":"Kili Muhammad Jafar",
    "wof:placetype":"locality"
},
  "geometry": {"coordinates":[66.90593,31.14564],"type":"Point"}
}