{
  "type": "Feature",
  "properties": {
    "gn:admin1_code":"2",
    "gn:asciiname":"Kaidan",
    "gn:country_code":"PK",
    "gn:dem":1317,
    "gn:feature_class":"P",
    "gn:feature_code":"PPL",
    "gn:name":"Kaidan",
    "gn:population":0,
    "gn:timezone":"Asia/Karachi",
    "iso:country":"PK",
    "name:epo_x_preferred":[
        "Kajdano"
    ],
    "name:fra_x_preferred":[
        "Kaidan"
    ],
    "name:ita_x_preferred":[
        "Kwaidan"
    ],
    "name:pol_x_preferred":[
        "Kaidan"
    ],
    "name:por_x_preferred":[
        "Kaidan"
    ],
    "name:rus_x_preferred":[
        "\u041a\u0430\u0439\u0434\u0430\u043d"
    ],
    "name:und_x_variant":[
        "Kahed\u0101n"
    ],
    "name:zho_x_preferred":[
        "\u602a\u8ac7"
    ],
    "wof:name":"Kaidan",
    "wof:placetype":"locality"
},
  "geometry": {"coordinates":[66.43496,27.77272],"type":"Point"}
}