{
  "type": "Feature",
  "properties": {
    "gn:admin1_code":"5",
    "gn:asciiname":"Goth Muhabat Khan Bhurgari",
    "gn:country_code":"PK",
    "gn:dem":20,
    "gn:feature_class":"P",
    "gn:feature_code":"PPL",
    "gn:name":"Goth Muhabat Khan Bhurgari",
    "gn:population":0,
    "gn:timezone":"Asia/Karachi",
    "iso:country":"PK",
    "name:und_x_variant":[
        "Goth Mohabot Kh\u0101n Bhurgari",
        "Bhurgari",
        "Goth Muhabat Khan Bhurgari"
    ],
    "wof:name":"Goth Muhabat Khan Bhurgari",
    "wof:placetype":"locality"
},
  "geometry": {"coordinates":[68.55247,25.15772],"type":"Point"}
}