{
  "type": "Feature",
  "properties": {
    "gn:admin1_code":"4.0",
    "gn:asciiname":"Jawa",
    "gn:country_code":"PK",
    "gn:dem":1464,
    "gn:feature_class":"P",
    "gn:feature_code":"PPL",
    "gn:name":"Jawa",
    "gn:population":0,
    "gn:timezone":"Asia/Karachi",
    "iso:country":"PK",
    "name:ceb_x_preferred":[
        "Jawa"
    ],
    "name:dan_x_preferred":[
        "Jawa"
    ],
    "name:deu_x_preferred":[
        "Jawa"
    ],
    "name:eng_x_preferred":[
        "Jawa"
    ],
    "name:fas_x_preferred":[
        "\u062c\u0627\u0648\u0647"
    ],
    "name:fra_x_preferred":[
        "Jawa"
    ],
    "name:hun_x_preferred":[
        "Jawa"
    ],
    "name:ind_x_preferred":[
        "Jawa"
    ],
    "name:ita_x_preferred":[
        "Jawa"
    ],
    "name:min_x_preferred":[
        "Jawa"
    ],
    "name:nld_x_preferred":[
        "Jawa"
    ],
    "name:pol_x_preferred":[
        "Jawa"
    ],
    "name:sco_x_preferred":[
        "Jawa"
    ],
    "name:slv_x_preferred":[
        "Jawa"
    ],
    "name:spa_x_preferred":[
        "Jawa"
    ],
    "name:sun_x_preferred":[
        "Jawa"
    ],
    "name:swe_x_preferred":[
        "Jawa"
    ],
    "wof:name":"Jawa",
    "wof:placetype":"locality"
},
  "geometry": {"coordinates":[73.36206,33.91056],"type":"Point"}
}