{
  "type": "Feature",
  "properties": {
    "gn:admin1_code":"3.0",
    "gn:asciiname":"Nalgah",
    "gn:country_code":"PK",
    "gn:dem":3106,
    "gn:feature_class":"P",
    "gn:feature_code":"PPL",
    "gn:name":"Nalgah",
    "gn:population":0,
    "gn:timezone":"Asia/Karachi",
    "iso:country":"PK",
    "wof:name":"Nalgah",
    "wof:placetype":"locality"
},
  "geometry": {"coordinates":[72.45985,36.01359],"type":"Point"}
}