{
  "type": "Feature",
  "properties": {
    "gn:admin1_code":"4.0",
    "gn:asciiname":"Karumb Admal",
    "gn:country_code":"PK",
    "gn:dem":520,
    "gn:feature_class":"P",
    "gn:feature_code":"PPL",
    "gn:name":"Karumb Admal",
    "gn:population":0,
    "gn:timezone":"Asia/Karachi",
    "iso:country":"PK",
    "name:und_x_variant":[
        "Karumb"
    ],
    "wof:name":"Karumb Admal",
    "wof:placetype":"locality"
},
  "geometry": {"coordinates":[73.23000999999999,33.25012],"type":"Point"}
}