{
  "type": "Feature",
  "properties": {
    "gn:admin1_code":"7.0",
    "gn:asciiname":"Gullo Das",
    "gn:country_code":"PK",
    "gn:dem":1565,
    "gn:feature_class":"P",
    "gn:feature_code":"PPL",
    "gn:name":"Gullo Das",
    "gn:population":0,
    "gn:timezone":"Asia/Karachi",
    "iso:country":"PK",
    "wof:name":"Gullo Das",
    "wof:placetype":"locality"
},
  "geometry": {"coordinates":[74.37384,35.95502000000001],"type":"Point"}
}