{
  "type": "Feature",
  "properties": {
    "gn:admin1_code":"4",
    "gn:asciiname":"Bariwali Man",
    "gn:country_code":"PK",
    "gn:dem":131,
    "gn:feature_class":"P",
    "gn:feature_code":"PPL",
    "gn:name":"Bariwali Man",
    "gn:population":0,
    "gn:timezone":"Asia/Karachi",
    "iso:country":"PK",
    "name:und_x_variant":[
        "B\u0101riw\u0101la"
    ],
    "wof:name":"Bariwali Man",
    "wof:placetype":"locality"
},
  "geometry": {"coordinates":[71.40125,30.42445],"type":"Point"}
}