{
  "type": "Feature",
  "properties": {
    "gn:admin1_code":"5.0",
    "gn:asciiname":"Buli",
    "gn:country_code":"PK",
    "gn:dem":31,
    "gn:feature_class":"P",
    "gn:feature_code":"PPL",
    "gn:name":"Buli",
    "gn:population":0,
    "gn:timezone":"Asia/Karachi",
    "iso:country":"PK",
    "name:ceb_x_preferred":[
        "Buli"
    ],
    "name:deu_x_preferred":[
        "Buli"
    ],
    "name:hrv_x_preferred":[
        "Buli"
    ],
    "name:nld_x_preferred":[
        "Buli"
    ],
    "name:rus_x_preferred":[
        "\u0411\u0443\u043b\u0438"
    ],
    "name:srp_x_preferred":[
        "\u0411\u0443\u043b\u0438"
    ],
    "name:swe_x_preferred":[
        "Buli"
    ],
    "name:tgl_x_preferred":[
        "Buli"
    ],
    "name:und_x_variant":[
        "Waria Las"
    ],
    "wof:name":"Buli",
    "wof:placetype":"locality"
},
  "geometry": {"coordinates":[69.76775000000001,24.34306],"type":"Point"}
}