{
  "type": "Feature",
  "properties": {
    "gn:admin1_code":"2.0",
    "gn:asciiname":"Khakan Shah",
    "gn:country_code":"PK",
    "gn:dem":56,
    "gn:feature_class":"P",
    "gn:feature_code":"PPL",
    "gn:name":"Khakan Shah",
    "gn:population":0,
    "gn:timezone":"Asia/Karachi",
    "iso:country":"PK",
    "wof:name":"Khakan Shah",
    "wof:placetype":"locality"
},
  "geometry": {"coordinates":[68.14029000000001,28.26248],"type":"Point"}
}