{
  "type": "Feature",
  "properties": {
    "gn:admin1_code":"5",
    "gn:asciiname":"Goth Sumar Dahri",
    "gn:country_code":"PK",
    "gn:dem":48,
    "gn:feature_class":"P",
    "gn:feature_code":"PPL",
    "gn:name":"Goth Sumar Dahri",
    "gn:population":0,
    "gn:timezone":"Asia/Karachi",
    "iso:country":"PK",
    "name:und_x_variant":[
        "Goth Somar Dh\u0101ri"
    ],
    "wof:name":"Goth Sumar Dahri",
    "wof:placetype":"locality"
},
  "geometry": {"coordinates":[68.1481,27.0157],"type":"Point"}
}