{
  "type": "Feature",
  "properties": {
    "gn:admin1_code":"4.0",
    "gn:asciiname":"Hassanwala",
    "gn:country_code":"PK",
    "gn:dem":206,
    "gn:feature_class":"P",
    "gn:feature_code":"PPL",
    "gn:name":"Hassanwala",
    "gn:population":0,
    "gn:timezone":"Asia/Karachi",
    "iso:country":"PK",
    "name:und_x_variant":[
        "Husainw\u0101la"
    ],
    "wof:name":"Hassanwala",
    "wof:placetype":"locality"
},
  "geometry": {"coordinates":[71.55099,32.6489],"type":"Point"}
}