{
  "type": "Feature",
  "properties": {
    "gn:admin1_code":"1.0",
    "gn:asciiname":"Nazar Kai",
    "gn:country_code":"PK",
    "gn:dem":2070,
    "gn:feature_class":"P",
    "gn:feature_code":"PPL",
    "gn:name":"Nazar Kai",
    "gn:population":0,
    "gn:timezone":"Asia/Karachi",
    "iso:country":"PK",
    "name:und_x_variant":[
        "Nazar Kar"
    ],
    "wof:name":"Nazar Kai",
    "wof:placetype":"locality"
},
  "geometry": {"coordinates":[70.66184,33.78969],"type":"Point"}
}