{
  "type": "Feature",
  "properties": {
    "gn:admin1_code":"4.0",
    "gn:asciiname":"Jhalar Sagla",
    "gn:country_code":"PK",
    "gn:dem":158,
    "gn:feature_class":"P",
    "gn:feature_code":"PPL",
    "gn:name":"Jhal\u0101r Sagla",
    "gn:population":0,
    "gn:timezone":"Asia/Karachi",
    "iso:country":"PK",
    "wof:name":"Jhalar Sagla",
    "wof:placetype":"locality"
},
  "geometry": {"coordinates":[72.73333000000002,30.63333],"type":"Point"}
}