{
  "type": "Feature",
  "properties": {
    "gn:admin1_code":"4.0",
    "gn:asciiname":"Jalilpur",
    "gn:country_code":"PK",
    "gn:dem":257,
    "gn:feature_class":"P",
    "gn:feature_code":"PPL",
    "gn:name":"Jalilpur",
    "gn:population":0,
    "gn:timezone":"Asia/Karachi",
    "iso:country":"PK",
    "wof:name":"Jalilpur",
    "wof:placetype":"locality"
},
  "geometry": {"coordinates":[74.95555999999998,32.24638],"type":"Point"}
}