{
  "type": "Feature",
  "properties": {
    "gn:admin1_code":"4.0",
    "gn:asciiname":"Maddu Khelanwala",
    "gn:country_code":"PK",
    "gn:dem":230,
    "gn:feature_class":"P",
    "gn:feature_code":"PPL",
    "gn:name":"Maddu Khelanwala",
    "gn:population":0,
    "gn:timezone":"Asia/Karachi",
    "iso:country":"PK",
    "name:und_x_variant":[
        "Maddo Khel\u0101nw\u0101la"
    ],
    "wof:name":"Maddu Khelanwala",
    "wof:placetype":"locality"
},
  "geometry": {"coordinates":[71.73850999999998,32.54755],"type":"Point"}
}