{
  "type": "Feature",
  "properties": {
    "gn:admin1_code":"4",
    "gn:asciiname":"Chak Nura Ahloka",
    "gn:country_code":"PK",
    "gn:dem":166,
    "gn:feature_class":"P",
    "gn:feature_code":"PPL",
    "gn:name":"Chak Nura Ahloka",
    "gn:population":0,
    "gn:timezone":"Asia/Karachi",
    "iso:country":"PK",
    "name:und_x_variant":[
        "N\u016bra Ahloka"
    ],
    "wof:name":"Chak Nura Ahloka",
    "wof:placetype":"locality"
},
  "geometry": {"coordinates":[73.45546999999998,30.29975],"type":"Point"}
}