{
  "type": "Feature",
  "properties": {
    "gn:admin1_code":"4.0",
    "gn:asciiname":"Chak Four Khidar Branch",
    "gn:country_code":"PK",
    "gn:dem":159,
    "gn:feature_class":"P",
    "gn:feature_code":"PPL",
    "gn:name":"Chak Four Khidar Branch",
    "gn:population":0,
    "gn:timezone":"Asia/Karachi",
    "iso:country":"PK",
    "wof:name":"Chak Four Khidar Branch",
    "wof:placetype":"locality"
},
  "geometry": {"coordinates":[73.32804,30.29123],"type":"Point"}
}