{
  "type": "Feature",
  "properties": {
    "gn:admin1_code":"3",
    "gn:asciiname":"Kanok",
    "gn:country_code":"PK",
    "gn:dem":1365,
    "gn:feature_class":"P",
    "gn:feature_code":"PPL",
    "gn:name":"Kanok",
    "gn:population":0,
    "gn:timezone":"Asia/Karachi",
    "iso:country":"PK",
    "wof:name":"Kanok",
    "wof:placetype":"locality"
},
  "geometry": {"coordinates":[73.25606999999999,34.6026],"type":"Point"}
}