{
  "type": "Feature",
  "properties": {
    "gn:admin1_code":"4.0",
    "gn:asciiname":"Konal Sheroana",
    "gn:country_code":"PK",
    "gn:dem":164,
    "gn:feature_class":"P",
    "gn:feature_code":"PPL",
    "gn:name":"Konal Sheroana",
    "gn:population":0,
    "gn:timezone":"Asia/Karachi",
    "iso:country":"PK",
    "wof:name":"Konal Sheroana",
    "wof:placetype":"locality"
},
  "geometry": {"coordinates":[72.05723,31.29807000000001],"type":"Point"}
}