{
  "type": "Feature",
  "properties": {
    "gn:admin1_code":"04",
    "gn:asciiname":"Sidhanwali",
    "gn:country_code":"PK",
    "gn:dem":217,
    "gn:feature_class":"P",
    "gn:feature_code":"PPL",
    "gn:name":"Sidhanwali",
    "gn:population":0,
    "gn:timezone":"Asia/Karachi",
    "iso:country":"PK",
    "name:und_x_variant":[
        "Bidnanwali",
        "Sidhanwali"
    ],
    "wof:name":"Sidhanwali",
    "wof:placetype":"locality"
},
  "geometry": {"coordinates":[74.48608,31.80003],"type":"Point"}
}