{
  "type": "Feature",
  "properties": {
    "gn:admin1_code":"02",
    "gn:asciiname":"Saimi Aghbarg",
    "gn:country_code":"PK",
    "gn:dem":1294,
    "gn:feature_class":"P",
    "gn:feature_code":"PPL",
    "gn:name":"Saimi Aghbarg",
    "gn:population":0,
    "gn:timezone":"Asia/Karachi",
    "iso:country":"PK",
    "name:und_x_variant":[
        "Samal Aghbarg",
        "Sami Aghbarg",
        "Saimi Aghbarg"
    ],
    "wof:name":"Saimi Aghbarg",
    "wof:placetype":"locality"
},
  "geometry": {"coordinates":[69.94147,30.8473],"type":"Point"}
}