{
  "type": "Feature",
  "properties": {
    "gn:admin1_code":"2.0",
    "gn:asciiname":"Kili Haji Habibullah",
    "gn:country_code":"PK",
    "gn:dem":2162,
    "gn:feature_class":"P",
    "gn:feature_code":"PPL",
    "gn:name":"Kili Haji Habibullah",
    "gn:population":0,
    "gn:timezone":"Asia/Karachi",
    "iso:country":"PK",
    "wof:name":"Kili Haji Habibullah",
    "wof:placetype":"locality"
},
  "geometry": {"coordinates":[66.72112,30.97312],"type":"Point"}
}