{
  "type": "Feature",
  "properties": {
    "gn:admin1_code":"4.0",
    "gn:asciiname":"Qadri Darbar Colony",
    "gn:country_code":"PK",
    "gn:dem":169,
    "gn:feature_class":"P",
    "gn:feature_code":"PPL",
    "gn:name":"Qadri Darbar Colony",
    "gn:population":0,
    "gn:timezone":"Asia/Karachi",
    "iso:country":"PK",
    "wof:name":"Qadri Darbar Colony",
    "wof:placetype":"locality"
},
  "geometry": {"coordinates":[72.70156999999998,31.15141],"type":"Point"}
}