{
  "type": "Feature",
  "properties": {
    "gn:admin1_code":"4",
    "gn:asciiname":"Sajjurwala",
    "gn:country_code":"PK",
    "gn:dem":149,
    "gn:feature_class":"P",
    "gn:feature_code":"PPL",
    "gn:name":"Sajjurwala",
    "gn:population":0,
    "gn:timezone":"Asia/Karachi",
    "iso:country":"PK",
    "name:und_x_variant":[
        "Saijurw\u0101la"
    ],
    "wof:name":"Sajjurwala",
    "wof:placetype":"locality"
},
  "geometry": {"coordinates":[72.07935999999999,31.13672],"type":"Point"}
}