{
  "type": "Feature",
  "properties": {
    "gn:admin1_code":"01",
    "gn:asciiname":"Tapu Kalle",
    "gn:country_code":"PK",
    "gn:dem":1457,
    "gn:feature_class":"P",
    "gn:feature_code":"PPL",
    "gn:name":"Tapu Kalle",
    "gn:population":0,
    "gn:timezone":"Asia/Karachi",
    "iso:country":"PK",
    "name:und_x_variant":[
        "Tap Kili",
        "Tapu Kali",
        "Tapu Kili",
        "Tapu Kalle",
        "Tapu Kila"
    ],
    "wof:name":"Tapu Kalle",
    "wof:placetype":"locality"
},
  "geometry": {"coordinates":[70.12734,33.83102],"type":"Point"}
}