{
  "type": "Feature",
  "properties": {
    "gn:admin1_code":"4.0",
    "gn:asciiname":"Kharala Jhangianwala",
    "gn:country_code":"PK",
    "gn:dem":485,
    "gn:feature_class":"P",
    "gn:feature_code":"PPL",
    "gn:name":"Kharala Jhangianwala",
    "gn:population":0,
    "gn:timezone":"Asia/Karachi",
    "iso:country":"PK",
    "wof:name":"Kharala Jhangianwala",
    "wof:placetype":"locality"
},
  "geometry": {"coordinates":[72.59702,33.53451],"type":"Point"}
}