{
  "type": "Feature",
  "properties": {
    "gn:admin1_code":"2.0",
    "gn:asciiname":"Wali Kach",
    "gn:country_code":"PK",
    "gn:dem":2405,
    "gn:feature_class":"P",
    "gn:feature_code":"PPL",
    "gn:name":"Wali Kach",
    "gn:population":0,
    "gn:timezone":"Asia/Karachi",
    "iso:country":"PK",
    "wof:name":"Wali Kach",
    "wof:placetype":"locality"
},
  "geometry": {"coordinates":[67.54354000000001,30.81822],"type":"Point"}
}