{
  "type": "Feature",
  "properties": {
    "gn:admin1_code":"3.0",
    "gn:asciiname":"Doniel Jarandai",
    "gn:country_code":"PK",
    "gn:dem":964,
    "gn:feature_class":"P",
    "gn:feature_code":"PPL",
    "gn:name":"Doniel Jarandai",
    "gn:population":0,
    "gn:timezone":"Asia/Karachi",
    "iso:country":"PK",
    "wof:name":"Doniel Jarandai",
    "wof:placetype":"locality"
},
  "geometry": {"coordinates":[72.75691999999999,34.52851],"type":"Point"}
}