{
  "type": "Feature",
  "properties": {
    "gn:admin1_code":"4",
    "gn:asciiname":"Mad Shama",
    "gn:country_code":"PK",
    "gn:dem":94,
    "gn:feature_class":"P",
    "gn:feature_code":"PPL",
    "gn:name":"Mad Shama",
    "gn:population":0,
    "gn:timezone":"Asia/Karachi",
    "iso:country":"PK",
    "name:und_x_variant":[
        "Mad Sh\u0101m\u0101n",
        "Mad Sh\u0101mew\u0101la",
        "Mad Shama"
    ],
    "wof:name":"Mad Shama",
    "wof:placetype":"locality"
},
  "geometry": {"coordinates":[70.4414,29.01808],"type":"Point"}
}