{
  "type": "Feature",
  "properties": {
    "gn:admin1_code":"5.0",
    "gn:asciiname":"Goth Fateh Muhammad Laghari",
    "gn:country_code":"PK",
    "gn:dem":19,
    "gn:feature_class":"P",
    "gn:feature_code":"PPL",
    "gn:name":"Goth Fateh Muhammad Laghari",
    "gn:population":0,
    "gn:timezone":"Asia/Karachi",
    "iso:country":"PK",
    "name:und_x_variant":[
        "Goth Fateh Khan Lagh\u0101ri"
    ],
    "wof:name":"Goth Fateh Muhammad Laghari",
    "wof:placetype":"locality"
},
  "geometry": {"coordinates":[68.93946,25.36653],"type":"Point"}
}