{
  "type": "Feature",
  "properties": {
    "gn:admin1_code":"3.0",
    "gn:asciiname":"Asoka",
    "gn:country_code":"PK",
    "gn:dem":1220,
    "gn:feature_class":"P",
    "gn:feature_code":"PPL",
    "gn:name":"Asoka",
    "gn:population":0,
    "gn:timezone":"Asia/Karachi",
    "iso:country":"PK",
    "name:und_x_variant":[
        "Asoka\u2019s Stones"
    ],
    "wof:name":"Asoka",
    "wof:placetype":"locality"
},
  "geometry": {"coordinates":[73.18024,34.35425],"type":"Point"}
}