{
  "type": "Feature",
  "properties": {
    "gn:admin1_code":"4",
    "gn:asciiname":"Chak One Hundred Twenty-six -Fifteen Left",
    "gn:country_code":"PK",
    "gn:dem":151,
    "gn:feature_class":"P",
    "gn:feature_code":"PPL",
    "gn:name":"Chak One Hundred Twenty-six -Fifteen Left",
    "gn:population":0,
    "gn:timezone":"Asia/Karachi",
    "iso:country":"PK",
    "name:und_x_variant":[
        "Chak One Hundred Twenty-six-One Fifteen L"
    ],
    "wof:name":"Chak One Hundred Twenty-six -Fifteen Left",
    "wof:placetype":"locality"
},
  "geometry": {"coordinates":[72.39376999999998,30.43924],"type":"Point"}
}