{
  "type": "Feature",
  "properties": {
    "gn:admin1_code":"3",
    "gn:asciiname":"Lagar",
    "gn:country_code":"PK",
    "gn:dem":1202,
    "gn:feature_class":"P",
    "gn:feature_code":"PPL",
    "gn:name":"Lagar",
    "gn:population":0,
    "gn:timezone":"Asia/Karachi",
    "iso:country":"PK",
    "wof:name":"Lagar",
    "wof:placetype":"locality"
},
  "geometry": {"coordinates":[72.60289,34.71181],"type":"Point"}
}