{
  "type": "Feature",
  "properties": {
    "gn:admin1_code":"6",
    "gn:asciiname":"Bandi Faqir Muhammad",
    "gn:country_code":"PK",
    "gn:dem":1257,
    "gn:feature_class":"P",
    "gn:feature_code":"PPL",
    "gn:name":"Bandi Faqir Muhammad",
    "gn:population":0,
    "gn:timezone":"Asia/Karachi",
    "iso:country":"PK",
    "name:und_x_variant":[
        "B\u0101ndi Fak\u012br Muhammad"
    ],
    "wof:name":"Bandi Faqir Muhammad",
    "wof:placetype":"locality"
},
  "geometry": {"coordinates":[73.54326999999998,34.346],"type":"Point"}
}