{
  "type": "Feature",
  "properties": {
    "gn:admin1_code":"03",
    "gn:asciiname":"Pano",
    "gn:country_code":"PK",
    "gn:dem":1344,
    "gn:feature_class":"P",
    "gn:feature_code":"PPL",
    "gn:name":"Pano",
    "gn:population":0,
    "gn:timezone":"Asia/Karachi",
    "iso:country":"PK",
    "name:ceb_x_preferred":[
        "Pano"
    ],
    "name:deu_x_preferred":[
        "Pano"
    ],
    "name:eng_x_preferred":[
        "Pano"
    ],
    "name:fin_x_preferred":[
        "Pano"
    ],
    "name:fra_x_preferred":[
        "Pano"
    ],
    "name:por_x_preferred":[
        "Pano"
    ],
    "name:spa_x_preferred":[
        "Pano"
    ],
    "name:swe_x_preferred":[
        "Pano"
    ],
    "wof:name":"Pano",
    "wof:placetype":"locality"
},
  "geometry": {"coordinates":[71.91931,34.81827],"type":"Point"}
}