{
  "type": "Feature",
  "properties": {
    "gn:admin1_code":"5",
    "gn:asciiname":"Drakhana jo Goth",
    "gn:country_code":"PK",
    "gn:dem":58,
    "gn:feature_class":"P",
    "gn:feature_code":"PPL",
    "gn:name":"Drakhana jo Goth",
    "gn:population":0,
    "gn:timezone":"Asia/Karachi",
    "iso:country":"PK",
    "wof:name":"Drakhana jo Goth",
    "wof:placetype":"locality"
},
  "geometry": {"coordinates":[68.99468,27.53663],"type":"Point"}
}