{
  "type": "Feature",
  "properties": {
    "gn:admin1_code":"4.0",
    "gn:asciiname":"Dhok Ghaghi",
    "gn:country_code":"PK",
    "gn:dem":260,
    "gn:feature_class":"P",
    "gn:feature_code":"PPL",
    "gn:name":"Dhok Ghaghi",
    "gn:population":0,
    "gn:timezone":"Asia/Karachi",
    "iso:country":"PK",
    "name:und_x_variant":[
        "Ghaghian Dhok",
        "Dhok Ghaghi"
    ],
    "wof:name":"Dhok Ghaghi",
    "wof:placetype":"locality"
},
  "geometry": {"coordinates":[71.96601,33.1042],"type":"Point"}
}