{
  "type": "Feature",
  "properties": {
    "gn:admin1_code":"3.0",
    "gn:asciiname":"Bukhtawalan Shal",
    "gn:country_code":"PK",
    "gn:dem":3601,
    "gn:feature_class":"P",
    "gn:feature_code":"PPLL",
    "gn:name":"Bukhtawalan Shal",
    "gn:population":0,
    "gn:timezone":"Asia/Karachi",
    "iso:country":"PK",
    "name:eng_x_preferred":[
        "Bukhtawalan Shal"
    ],
    "wof:name":"Bukhtawalan Shal",
    "wof:placetype":"locality"
},
  "geometry": {"coordinates":[72.1534,35.91138],"type":"Point"}
}