{
  "type": "Feature",
  "properties": {
    "gn:admin1_code":"7.0",
    "gn:asciiname":"Ishkuman",
    "gn:country_code":"PK",
    "gn:dem":2428,
    "gn:feature_class":"P",
    "gn:feature_code":"PPL",
    "gn:name":"Ishkuman",
    "gn:population":0,
    "gn:timezone":"Asia/Karachi",
    "iso:country":"PK",
    "name:und_x_variant":[
        "Ashkaman",
        "Ashkum\u0101n",
        "Ishkuman"
    ],
    "name:urd_x_preferred":[
        "Ishkom\u0101n"
    ],
    "name:urd_x_variant":[
        "\u0625\u0634\u0652\u06a9\u0648\u0645\u064e\u0627\u0646"
    ],
    "wof:name":"Ishkuman",
    "wof:placetype":"locality"
},
  "geometry": {"coordinates":[73.82044,36.53589],"type":"Point"}
}