{
  "type": "Feature",
  "properties": {
    "gn:admin1_code":"4",
    "gn:asciiname":"Chak One Hundred Ten Jhang Branch",
    "gn:country_code":"PK",
    "gn:dem":188,
    "gn:feature_class":"P",
    "gn:feature_code":"PPL",
    "gn:name":"Chak One Hundred Ten Jhang Branch",
    "gn:population":0,
    "gn:timezone":"Asia/Karachi",
    "iso:country":"PK",
    "name:und_x_variant":[
        "Chak One Hundred Ten",
        "Ghul\u0101m Faridw\u0101la",
        "Chak One Hundred Ten Jhang Branch",
        "Deputyw\u0101la"
    ],
    "wof:name":"Chak One Hundred Ten Jhang Branch",
    "wof:placetype":"locality"
},
  "geometry": {"coordinates":[73.11371,31.60032],"type":"Point"}
}