{
  "type": "Feature",
  "properties": {
    "gn:admin1_code":"4",
    "gn:asciiname":"Maluwala",
    "gn:country_code":"PK",
    "gn:dem":195,
    "gn:feature_class":"P",
    "gn:feature_code":"PPL",
    "gn:name":"Maluwala",
    "gn:population":0,
    "gn:timezone":"Asia/Karachi",
    "iso:country":"PK",
    "wof:name":"Maluwala",
    "wof:placetype":"locality"
},
  "geometry": {"coordinates":[71.47542,32.30764],"type":"Point"}
}