{
  "type": "Feature",
  "properties": {
    "gn:admin1_code":"04",
    "gn:asciiname":"Chak Five Hundred Fifty-six Gugera Branch",
    "gn:country_code":"PK",
    "gn:dem":170,
    "gn:feature_class":"P",
    "gn:feature_code":"PPL",
    "gn:name":"Chak Five Hundred Fifty-six Gugera Branch",
    "gn:population":0,
    "gn:timezone":"Asia/Karachi",
    "iso:country":"PK",
    "name:und_x_variant":[
        "Nallawala",
        "Naliw\u0101la",
        "Chak Five Hundred Fifty-six Gugera Branch"
    ],
    "wof:name":"Chak Five Hundred Fifty-six Gugera Branch",
    "wof:placetype":"locality"
},
  "geometry": {"coordinates":[72.83958,30.8032],"type":"Point"}
}