{
  "type": "Feature",
  "properties": {
    "gn:admin1_code":"4.0",
    "gn:asciiname":"Dhok Adra",
    "gn:country_code":"PK",
    "gn:dem":541,
    "gn:feature_class":"P",
    "gn:feature_code":"PPL",
    "gn:name":"Dhok Adra",
    "gn:population":0,
    "gn:timezone":"Asia/Karachi",
    "iso:country":"PK",
    "wof:name":"Dhok Adra",
    "wof:placetype":"locality"
},
  "geometry": {"coordinates":[73.17004,33.48845],"type":"Point"}
}