{
  "type": "Feature",
  "properties": {
    "gn:admin1_code":"4.0",
    "gn:asciiname":"Jandiali",
    "gn:country_code":"PK",
    "gn:dem":142,
    "gn:feature_class":"P",
    "gn:feature_code":"PPL",
    "gn:name":"Jandi\u0101li",
    "gn:population":0,
    "gn:timezone":"Asia/Karachi",
    "iso:country":"PK",
    "name:por_x_preferred":[
        "Jandiali"
    ],
    "wof:name":"Jandiali",
    "wof:placetype":"locality"
},
  "geometry": {"coordinates":[72.34999999999999,30.25],"type":"Point"}
}