{
  "type": "Feature",
  "properties": {
    "gn:admin1_code":"04",
    "gn:asciiname":"Kotla Arab Ali Khan",
    "gn:country_code":"PK",
    "gn:dem":314,
    "gn:feature_class":"P",
    "gn:feature_code":"PPL",
    "gn:name":"Kotla Arab Ali Khan",
    "gn:population":0,
    "gn:timezone":"Asia/Karachi",
    "iso:country":"PK",
    "name:pol_x_preferred":[
        "Kotla Arab Ali Khan"
    ],
    "name:und_x_variant":[
        "Kotla"
    ],
    "name:urd_x_preferred":[
        "\u06a9\u0648\u0679\u0644\u06c1 \u0639\u0631\u0628 \u0639\u0644\u06cc \u062e\u0627\u0646"
    ],
    "wof:name":"Kotla Arab Ali Khan",
    "wof:placetype":"locality"
},
  "geometry": {"coordinates":[74.07122,32.85274],"type":"Point"}
}