{
  "type": "Feature",
  "properties": {
    "gn:admin1_code":"2",
    "gn:asciiname":"Gom",
    "gn:country_code":"PK",
    "gn:dem":2022,
    "gn:feature_class":"P",
    "gn:feature_code":"PPL",
    "gn:name":"Gom",
    "gn:population":0,
    "gn:timezone":"Asia/Karachi",
    "iso:country":"PK",
    "wof:name":"Gom",
    "wof:placetype":"locality"
},
  "geometry": {"coordinates":[66.59008,29.01666],"type":"Point"}
}