{
  "type": "Feature",
  "properties": {
    "gn:admin1_code":"4",
    "gn:asciiname":"Jhok Allah Bakhshwali",
    "gn:country_code":"PK",
    "gn:dem":163,
    "gn:feature_class":"P",
    "gn:feature_code":"PPL",
    "gn:name":"Jhok All\u0101h Bakhshw\u0101li",
    "gn:population":0,
    "gn:timezone":"Asia/Karachi",
    "iso:country":"PK",
    "wof:name":"Jhok Allah Bakhshwali",
    "wof:placetype":"locality"
},
  "geometry": {"coordinates":[70.66389000000002,30.56528],"type":"Point"}
}