{
  "type": "Feature",
  "properties": {
    "gn:admin1_code":"3.0",
    "gn:asciiname":"Janbhatai",
    "gn:country_code":"PK",
    "gn:dem":1578,
    "gn:feature_class":"P",
    "gn:feature_code":"PPL",
    "gn:name":"Janbhatai",
    "gn:population":0,
    "gn:timezone":"Asia/Karachi",
    "iso:country":"PK",
    "name:eng_x_preferred":[
        "J\u0101mbatai"
    ],
    "wof:name":"Janbhatai",
    "wof:placetype":"locality"
},
  "geometry": {"coordinates":[71.70239000000002,35.06001],"type":"Point"}
}