{
  "type": "Feature",
  "properties": {
    "gn:admin1_code":"4",
    "gn:asciiname":"Kot Diwan Ali Shah",
    "gn:country_code":"PK",
    "gn:dem":198,
    "gn:feature_class":"P",
    "gn:feature_code":"PPL",
    "gn:name":"Kot Diwan Ali Shah",
    "gn:population":0,
    "gn:timezone":"Asia/Karachi",
    "iso:country":"PK",
    "name:und_x_variant":[
        "Kot D\u012bwan Ali Sh\u0101h"
    ],
    "wof:name":"Kot Diwan Ali Shah",
    "wof:placetype":"locality"
},
  "geometry": {"coordinates":[73.87364000000002,31.48959],"type":"Point"}
}