{
  "type": "Feature",
  "properties": {
    "gn:admin1_code":"7.0",
    "gn:asciiname":"Chalachari",
    "gn:country_code":"PK",
    "gn:dem":3041,
    "gn:feature_class":"P",
    "gn:feature_code":"PPL",
    "gn:name":"Chalachari",
    "gn:population":0,
    "gn:timezone":"Asia/Karachi",
    "iso:country":"PK",
    "name:und_x_variant":[
        "Chalach\u0101r"
    ],
    "wof:name":"Chalachari",
    "wof:placetype":"locality"
},
  "geometry": {"coordinates":[73.73321999999997,35.32859000000001],"type":"Point"}
}