{
  "type": "Feature",
  "properties": {
    "gn:admin1_code":"4",
    "gn:asciiname":"Shah Nasir",
    "gn:country_code":"PK",
    "gn:dem":114,
    "gn:feature_class":"P",
    "gn:feature_code":"PPL",
    "gn:name":"Shah Nasir",
    "gn:population":0,
    "gn:timezone":"Asia/Karachi",
    "iso:country":"PK",
    "name:und_x_variant":[
        "Sabra"
    ],
    "wof:name":"Shah Nasir",
    "wof:placetype":"locality"
},
  "geometry": {"coordinates":[70.73829000000001,29.95881],"type":"Point"}
}