{
  "type": "Feature",
  "properties": {
    "gn:admin1_code":"2.0",
    "gn:asciiname":"Kunri",
    "gn:country_code":"PK",
    "gn:dem":360,
    "gn:feature_class":"P",
    "gn:feature_code":"PPL",
    "gn:name":"Kunri",
    "gn:population":0,
    "gn:timezone":"Asia/Karachi",
    "iso:country":"PK",
    "name:eng_x_preferred":[
        "Kunri"
    ],
    "name:fas_x_preferred":[
        "\u06a9\u0646\u0631\u06cc"
    ],
    "name:snd_x_preferred":[
        "\u06aa\u0646\u0631\u064a"
    ],
    "name:urd_x_preferred":[
        "\u06a9\u0646\u0631\u06cc"
    ],
    "wof:name":"Kunri",
    "wof:placetype":"locality"
},
  "geometry": {"coordinates":[65.60301,26.30902],"type":"Point"}
}