{
  "type": "Feature",
  "properties": {
    "gn:admin1_code":"4.0",
    "gn:asciiname":"Jaqat Singh",
    "gn:country_code":"PK",
    "gn:dem":136,
    "gn:feature_class":"P",
    "gn:feature_code":"PPL",
    "gn:name":"Jaqat Singh",
    "gn:population":0,
    "gn:timezone":"Asia/Karachi",
    "iso:country":"PK",
    "wof:name":"Jaqat Singh",
    "wof:placetype":"locality"
},
  "geometry": {"coordinates":[71.90509,30.43231],"type":"Point"}
}