{
  "type": "Feature",
  "properties": {
    "gn:admin1_code":"4.0",
    "gn:asciiname":"Khalilabad",
    "gn:country_code":"PK",
    "gn:dem":150,
    "gn:feature_class":"P",
    "gn:feature_code":"PPL",
    "gn:name":"Khalilabad",
    "gn:population":0,
    "gn:timezone":"Asia/Karachi",
    "iso:country":"PK",
    "name:aze_x_preferred":[
        "X\u0259lilabad"
    ],
    "name:ceb_x_preferred":[
        "Khalilabad"
    ],
    "name:fas_x_preferred":[
        "\u062e\u0644\u06cc\u0644\u200c\u0622\u0628\u0627\u062f"
    ],
    "name:swe_x_preferred":[
        "Khalilabad"
    ],
    "wof:name":"Khalilabad",
    "wof:placetype":"locality"
},
  "geometry": {"coordinates":[72.28520999999998,31.08114],"type":"Point"}
}