{
  "type": "Feature",
  "properties": {
    "gn:admin1_code":"3.0",
    "gn:asciiname":"Siri Khawah",
    "gn:country_code":"PK",
    "gn:dem":596,
    "gn:feature_class":"P",
    "gn:feature_code":"PPL",
    "gn:name":"Siri Khawah",
    "gn:population":0,
    "gn:timezone":"Asia/Karachi",
    "iso:country":"PK",
    "name:und_x_variant":[
        "Sweri Khwah"
    ],
    "wof:name":"Siri Khawah",
    "wof:placetype":"locality"
},
  "geometry": {"coordinates":[71.20477,33.25214],"type":"Point"}
}