{
  "type": "Feature",
  "properties": {
    "gn:admin1_code":"5",
    "gn:asciiname":"Goth Muqamwari",
    "gn:country_code":"PK",
    "gn:dem":64,
    "gn:feature_class":"P",
    "gn:feature_code":"PPL",
    "gn:name":"Goth Muqamwari",
    "gn:population":0,
    "gn:timezone":"Asia/Karachi",
    "iso:country":"PK",
    "name:und_x_variant":[
        "Maq\u0101mw\u0101ri",
        "Goth Maq\u0101mw\u0101ri",
        "Goth Muqamwari"
    ],
    "wof:name":"Goth Muqamwari",
    "wof:placetype":"locality"
},
  "geometry": {"coordinates":[69.26746,26.5168],"type":"Point"}
}