{
  "type": "Feature",
  "properties": {
    "gn:admin1_code":"3.0",
    "gn:asciiname":"Atchiku",
    "gn:country_code":"PK",
    "gn:dem":2588,
    "gn:feature_class":"P",
    "gn:feature_code":"PPL",
    "gn:name":"Atchiku",
    "gn:population":0,
    "gn:timezone":"Asia/Karachi",
    "iso:country":"PK",
    "wof:name":"Atchiku",
    "wof:placetype":"locality"
},
  "geometry": {"coordinates":[72.0078,35.7391],"type":"Point"}
}