{
  "type": "Feature",
  "properties": {
    "gn:admin1_code":"4.0",
    "gn:asciiname":"Thatta Chaudhrian",
    "gn:country_code":"PK",
    "gn:dem":209,
    "gn:feature_class":"P",
    "gn:feature_code":"PPL",
    "gn:name":"Thatta Chaudhrian",
    "gn:population":0,
    "gn:timezone":"Asia/Karachi",
    "iso:country":"PK",
    "name:und_x_variant":[
        "Thatta Khud\u0101yar"
    ],
    "wof:name":"Thatta Chaudhrian",
    "wof:placetype":"locality"
},
  "geometry": {"coordinates":[74.21473,31.6137],"type":"Point"}
}