{
  "type": "Feature",
  "properties": {
    "gn:admin1_code":"4",
    "gn:asciiname":"Sher Kot",
    "gn:country_code":"PK",
    "gn:dem":156,
    "gn:feature_class":"P",
    "gn:feature_code":"PPL",
    "gn:name":"Sher Kot",
    "gn:population":0,
    "gn:timezone":"Asia/Karachi",
    "iso:country":"PK",
    "name:und_x_variant":[
        "Sherkot"
    ],
    "wof:name":"Sher Kot",
    "wof:placetype":"locality"
},
  "geometry": {"coordinates":[72.15130000000001,31.35608],"type":"Point"}
}