{
  "type": "Feature",
  "properties": {
    "gn:admin1_code":"6",
    "gn:asciiname":"Namjar",
    "gn:country_code":"PK",
    "gn:dem":1539,
    "gn:feature_class":"P",
    "gn:feature_code":"PPL",
    "gn:name":"Namjar",
    "gn:population":0,
    "gn:timezone":"Asia/Karachi",
    "iso:country":"PK",
    "wof:name":"Namjar",
    "wof:placetype":"locality"
},
  "geometry": {"coordinates":[73.95083000000002,33.85675],"type":"Point"}
}