{
  "type": "Feature",
  "properties": {
    "gn:admin1_code":"4",
    "gn:asciiname":"Kotwala",
    "gn:country_code":"PK",
    "gn:dem":111,
    "gn:feature_class":"P",
    "gn:feature_code":"PPL",
    "gn:name":"Kotwala",
    "gn:population":0,
    "gn:timezone":"Asia/Karachi",
    "iso:country":"PK",
    "wof:name":"Kotwala",
    "wof:placetype":"locality"
},
  "geometry": {"coordinates":[70.68078,29.73579],"type":"Point"}
}