{
  "type": "Feature",
  "properties": {
    "gn:admin1_code":"04",
    "gn:asciiname":"Mekhowal",
    "gn:country_code":"PK",
    "gn:dem":217,
    "gn:feature_class":"P",
    "gn:feature_code":"PPL",
    "gn:name":"Mekhowal",
    "gn:population":0,
    "gn:timezone":"Asia/Karachi",
    "iso:country":"PK",
    "name:und_x_variant":[
        "Mikhow\u0101li"
    ],
    "wof:name":"Mekhowal",
    "wof:placetype":"locality"
},
  "geometry": {"coordinates":[74.37533000000001,31.72341],"type":"Point"}
}