{
  "type": "Feature",
  "properties": {
    "gn:admin1_code":"3",
    "gn:asciiname":"Sari Blolian",
    "gn:country_code":"PK",
    "gn:dem":1384,
    "gn:feature_class":"P",
    "gn:feature_code":"PPL",
    "gn:name":"Sari Blolian",
    "gn:population":0,
    "gn:timezone":"Asia/Karachi",
    "iso:country":"PK",
    "name:und_x_variant":[
        "Baloli\u0101n"
    ],
    "wof:name":"Sari Blolian",
    "wof:placetype":"locality"
},
  "geometry": {"coordinates":[72.97806,34.39974],"type":"Point"}
}