{
  "type": "Feature",
  "properties": {
    "gn:admin1_code":"4.0",
    "gn:asciiname":"Chholianwali",
    "gn:country_code":"PK",
    "gn:dem":150,
    "gn:feature_class":"P",
    "gn:feature_code":"PPL",
    "gn:name":"Chholianwali",
    "gn:population":0,
    "gn:timezone":"Asia/Karachi",
    "iso:country":"PK",
    "wof:name":"Chholianwali",
    "wof:placetype":"locality"
},
  "geometry": {"coordinates":[73.06354,29.98182000000001],"type":"Point"}
}