{
  "type": "Feature",
  "properties": {
    "gn:admin1_code":"3",
    "gn:asciiname":"Kotla Qaim Shah",
    "gn:country_code":"PK",
    "gn:dem":174,
    "gn:feature_class":"P",
    "gn:feature_code":"PPL",
    "gn:name":"Kotla Qaim Shah",
    "gn:population":0,
    "gn:timezone":"Asia/Karachi",
    "iso:country":"PK",
    "name:und_x_variant":[
        "Kalla Q\u0101im Shah",
        "Q\u0101im Sh\u0101h",
        "Kolla Q\u0101im Shah",
        "Kotla Qaim Shah"
    ],
    "wof:name":"Kotla Qaim Shah",
    "wof:placetype":"locality"
},
  "geometry": {"coordinates":[70.86453,31.75894000000001],"type":"Point"}
}