{
  "type": "Feature",
  "properties": {
    "gn:admin1_code":"2.0",
    "gn:asciiname":"Palli Mas",
    "gn:country_code":"PK",
    "gn:dem":1305,
    "gn:feature_class":"P",
    "gn:feature_code":"PPL",
    "gn:name":"Palli Mas",
    "gn:population":0,
    "gn:timezone":"Asia/Karachi",
    "iso:country":"PK",
    "wof:name":"Palli Mas",
    "wof:placetype":"locality"
},
  "geometry": {"coordinates":[66.5138,27.3602],"type":"Point"}
}