{
  "type": "Feature",
  "properties": {
    "gn:admin1_code":"3.0",
    "gn:asciiname":"Garah Nowabi",
    "gn:country_code":"PK",
    "gn:dem":229,
    "gn:feature_class":"P",
    "gn:feature_code":"PPL",
    "gn:name":"Garah Nowabi",
    "gn:population":0,
    "gn:timezone":"Asia/Karachi",
    "iso:country":"PK",
    "name:und_x_variant":[
        "Garah Naw\u0101bi"
    ],
    "wof:name":"Garah Nowabi",
    "wof:placetype":"locality"
},
  "geometry": {"coordinates":[70.58965999999999,32.21396],"type":"Point"}
}