{
  "type": "Feature",
  "properties": {
    "gn:admin1_code":"4",
    "gn:asciiname":"Gamar Khukhar",
    "gn:country_code":"PK",
    "gn:dem":194,
    "gn:feature_class":"P",
    "gn:feature_code":"PPL",
    "gn:name":"Gamar Khukhar",
    "gn:population":0,
    "gn:timezone":"Asia/Karachi",
    "iso:country":"PK",
    "wof:name":"Gamar Khukhar",
    "wof:placetype":"locality"
},
  "geometry": {"coordinates":[71.92778,32.34444000000001],"type":"Point"}
}