{
  "type": "Feature",
  "properties": {
    "gn:admin1_code":"2",
    "gn:asciiname":"Guldad Kili",
    "gn:country_code":"PK",
    "gn:dem":940,
    "gn:feature_class":"P",
    "gn:feature_code":"PPL",
    "gn:name":"Guldad Kili",
    "gn:population":0,
    "gn:timezone":"Asia/Karachi",
    "iso:country":"PK",
    "wof:name":"Guldad Kili",
    "wof:placetype":"locality"
},
  "geometry": {"coordinates":[68.49290999999999,29.982],"type":"Point"}
}