{
  "type": "Feature",
  "properties": {
    "gn:admin1_code":"2.0",
    "gn:asciiname":"Killi Ibrahim",
    "gn:country_code":"PK",
    "gn:dem":793,
    "gn:feature_class":"P",
    "gn:feature_code":"PPL",
    "gn:name":"Killi Ibrahim",
    "gn:population":0,
    "gn:timezone":"Asia/Karachi",
    "iso:country":"PK",
    "wof:name":"Killi Ibrahim",
    "wof:placetype":"locality"
},
  "geometry": {"coordinates":[63.97911,28.79421],"type":"Point"}
}