{
  "type": "Feature",
  "properties": {
    "gn:admin1_code":"3.0",
    "gn:asciiname":"Bhatiarano Kalle",
    "gn:country_code":"PK",
    "gn:dem":339,
    "gn:feature_class":"P",
    "gn:feature_code":"PPL",
    "gn:name":"Bhatiarano Kalle",
    "gn:population":0,
    "gn:timezone":"Asia/Karachi",
    "iso:country":"PK",
    "name:eng_x_preferred":[
        "Bhati\u0101r\u0101n"
    ],
    "wof:name":"Bhatiarano Kalle",
    "wof:placetype":"locality"
},
  "geometry": {"coordinates":[71.75215,34.26345],"type":"Point"}
}