{
  "type": "Feature",
  "properties": {
    "gn:admin1_code":"2.0",
    "gn:asciiname":"Haji Dildar Gis",
    "gn:country_code":"PK",
    "gn:dem":1342,
    "gn:feature_class":"P",
    "gn:feature_code":"PPL",
    "gn:name":"Haji Dildar Gis",
    "gn:population":0,
    "gn:timezone":"Asia/Karachi",
    "iso:country":"PK",
    "wof:name":"Haji Dildar Gis",
    "wof:placetype":"locality"
},
  "geometry": {"coordinates":[64.19385,29.31903],"type":"Point"}
}