{
  "type": "Feature",
  "properties": {
    "gn:admin1_code":"3.0",
    "gn:asciiname":"Ratta Depot",
    "gn:country_code":"PK",
    "gn:dem":887,
    "gn:feature_class":"P",
    "gn:feature_code":"PPL",
    "gn:name":"Ratta Depot",
    "gn:population":0,
    "gn:timezone":"Asia/Karachi",
    "iso:country":"PK",
    "wof:name":"Ratta Depot",
    "wof:placetype":"locality"
},
  "geometry": {"coordinates":[73.08787,34.3896],"type":"Point"}
}