{
  "type": "Feature",
  "properties": {
    "gn:admin1_code":"04",
    "gn:asciiname":"Shaikh Ahmad Nau",
    "gn:cc2":"PK",
    "gn:country_code":"PK",
    "gn:dem":193,
    "gn:feature_class":"P",
    "gn:feature_code":"PPL",
    "gn:name":"Shaikh Ahmad Nau",
    "gn:population":0,
    "gn:timezone":"Asia/Karachi",
    "iso:country":"PK",
    "name:und_x_variant":[
        "Sheikh Ammad Nau",
        "Shaikh Ahmad Nau"
    ],
    "wof:name":"Shaikh Ahmad Nau",
    "wof:placetype":"locality"
},
  "geometry": {"coordinates":[74.36667,30.98333],"type":"Point"}
}