{
  "type": "Feature",
  "properties": {
    "gn:admin1_code":"2.0",
    "gn:asciiname":"Hotizal",
    "gn:country_code":"PK",
    "gn:dem":1671,
    "gn:feature_class":"P",
    "gn:feature_code":"PPL",
    "gn:name":"Hotizal",
    "gn:population":0,
    "gn:timezone":"Asia/Karachi",
    "iso:country":"PK",
    "name:und_x_variant":[
        "Hotiz\u0101i"
    ],
    "wof:name":"Hotizal",
    "wof:placetype":"locality"
},
  "geometry": {"coordinates":[66.84116,29.79401],"type":"Point"}
}