{
  "type": "Feature",
  "properties": {
    "gn:admin1_code":"4.0",
    "gn:asciiname":"Bhatti Colony",
    "gn:country_code":"PK",
    "gn:dem":1034,
    "gn:feature_class":"P",
    "gn:feature_code":"PPL",
    "gn:name":"Bhatti Colony",
    "gn:population":0,
    "gn:timezone":"Asia/Karachi",
    "iso:country":"PK",
    "wof:name":"Bhatti Colony",
    "wof:placetype":"locality"
},
  "geometry": {"coordinates":[73.37105,33.73062],"type":"Point"}
}