{
  "type": "Feature",
  "properties": {
    "gn:admin1_code":"04",
    "gn:asciiname":"Maira Sharif",
    "gn:country_code":"PK",
    "gn:dem":497,
    "gn:feature_class":"P",
    "gn:feature_code":"PPL",
    "gn:name":"Maira Sharif",
    "gn:population":0,
    "gn:timezone":"Asia/Karachi",
    "iso:country":"PK",
    "name:und_x_variant":[
        "Maira Khurd",
        "Maria Sharif",
        "Maira Sharif"
    ],
    "wof:name":"Maira Sharif",
    "wof:placetype":"locality"
},
  "geometry": {"coordinates":[72.92196,33.46255],"type":"Point"}
}