{
  "type": "Feature",
  "properties": {
    "gn:admin1_code":"4",
    "gn:asciiname":"Dadiwala",
    "gn:country_code":"PK",
    "gn:dem":114,
    "gn:feature_class":"P",
    "gn:feature_code":"PPL",
    "gn:name":"Dadiwala",
    "gn:population":0,
    "gn:timezone":"Asia/Karachi",
    "iso:country":"PK",
    "name:und_x_variant":[
        "Basti Muhib"
    ],
    "wof:name":"Dadiwala",
    "wof:placetype":"locality"
},
  "geometry": {"coordinates":[70.71453000000002,29.79947],"type":"Point"}
}