{
  "type": "Feature",
  "properties": {
    "gn:admin1_code":"4.0",
    "gn:asciiname":"Kutehra",
    "gn:country_code":"PK",
    "gn:dem":523,
    "gn:feature_class":"P",
    "gn:feature_code":"PPL",
    "gn:name":"Kutehra",
    "gn:population":0,
    "gn:timezone":"Asia/Karachi",
    "iso:country":"PK",
    "wof:name":"Kutehra",
    "wof:placetype":"locality"
},
  "geometry": {"coordinates":[72.48524,33.57907],"type":"Point"}
}