{
  "type": "Feature",
  "properties": {
    "gn:admin1_code":"3",
    "gn:asciiname":"Shehbat",
    "gn:country_code":"PK",
    "gn:dem":2340,
    "gn:feature_class":"P",
    "gn:feature_code":"PPL",
    "gn:name":"Shehbat",
    "gn:population":0,
    "gn:timezone":"Asia/Karachi",
    "iso:country":"PK",
    "name:eng_x_preferred":[
        "Shiddat"
    ],
    "wof:name":"Shehbat",
    "wof:placetype":"locality"
},
  "geometry": {"coordinates":[71.78785000000001,35.21874000000001],"type":"Point"}
}