{
  "type": "Feature",
  "properties": {
    "gn:admin1_code":"05",
    "gn:asciiname":"Goth Darvesh Ali Shah",
    "gn:country_code":"PK",
    "gn:dem":8,
    "gn:feature_class":"P",
    "gn:feature_code":"PPL",
    "gn:name":"Goth Darvesh Ali Shah",
    "gn:population":0,
    "gn:timezone":"Asia/Karachi",
    "iso:country":"PK",
    "wof:name":"Goth Darvesh Ali Shah",
    "wof:placetype":"locality"
},
  "geometry": {"coordinates":[67.92986999999999,24.4948],"type":"Point"}
}