{
  "type": "Feature",
  "properties": {
    "gn:admin1_code":"2.0",
    "gn:asciiname":"Mulla Kurba Ziarat",
    "gn:country_code":"PK",
    "gn:dem":2123,
    "gn:feature_class":"P",
    "gn:feature_code":"PPL",
    "gn:name":"Mulla Kurba Ziarat",
    "gn:population":0,
    "gn:timezone":"Asia/Karachi",
    "iso:country":"PK",
    "wof:name":"Mulla Kurba Ziarat",
    "wof:placetype":"locality"
},
  "geometry": {"coordinates":[68.09019000000001,31.35132],"type":"Point"}
}