{
  "type": "Feature",
  "properties": {
    "gn:admin1_code":"1",
    "gn:asciiname":"Ghulam Khel Azrap",
    "gn:country_code":"PK",
    "gn:dem":1015,
    "gn:feature_class":"P",
    "gn:feature_code":"PPL",
    "gn:name":"Ghulam Khel Azrap",
    "gn:population":0,
    "gn:timezone":"Asia/Karachi",
    "iso:country":"PK",
    "name:und_x_variant":[
        "Dotanni"
    ],
    "wof:name":"Ghulam Khel Azrap",
    "wof:placetype":"locality"
},
  "geometry": {"coordinates":[69.58851999999999,32.14452],"type":"Point"}
}