{
  "type": "Feature",
  "properties": {
    "gn:admin1_code":"1.0",
    "gn:asciiname":"Takhtak",
    "gn:country_code":"PK",
    "gn:dem":2276,
    "gn:feature_class":"P",
    "gn:feature_code":"PPL",
    "gn:name":"Takhtak",
    "gn:population":0,
    "gn:timezone":"Asia/Karachi",
    "iso:country":"PK",
    "name:fas_x_preferred":[
        "\u062a\u062e\u062a\u06a9"
    ],
    "name:msa_x_preferred":[
        "Takhtak"
    ],
    "wof:name":"Takhtak",
    "wof:placetype":"locality"
},
  "geometry": {"coordinates":[70.44970000000001,33.83824],"type":"Point"}
}