{
  "type": "Feature",
  "properties": {
    "gn:admin1_code":"4.0",
    "gn:asciiname":"Jhungawala",
    "gn:country_code":"PK",
    "gn:dem":832,
    "gn:feature_class":"P",
    "gn:feature_code":"PPL",
    "gn:name":"Jhungawala",
    "gn:population":0,
    "gn:timezone":"Asia/Karachi",
    "iso:country":"PK",
    "name:und_x_variant":[
        "Jhunga Saloh",
        "Jhunga",
        "Jhungawala"
    ],
    "wof:name":"Jhungawala",
    "wof:placetype":"locality"
},
  "geometry": {"coordinates":[72.32808,32.62157],"type":"Point"}
}