{
  "type": "Feature",
  "properties": {
    "gn:admin1_code":"5.0",
    "gn:asciiname":"Usman Khaskheli",
    "gn:country_code":"PK",
    "gn:dem":11,
    "gn:feature_class":"P",
    "gn:feature_code":"PPL",
    "gn:name":"Usman Khaskheli",
    "gn:population":0,
    "gn:timezone":"Asia/Karachi",
    "iso:country":"PK",
    "name:eng_x_preferred":[
        "Usm\u0101n Kh\u0101skheli"
    ],
    "wof:name":"Usman Khaskheli",
    "wof:placetype":"locality"
},
  "geometry": {"coordinates":[68.43094000000001,24.72917],"type":"Point"}
}