{
  "type": "Feature",
  "properties": {
    "gn:admin1_code":"2.0",
    "gn:asciiname":"Khawazha Kili",
    "gn:country_code":"PK",
    "gn:dem":2039,
    "gn:feature_class":"P",
    "gn:feature_code":"PPL",
    "gn:name":"Khawazha Kili",
    "gn:population":0,
    "gn:timezone":"Asia/Karachi",
    "iso:country":"PK",
    "wof:name":"Khawazha Kili",
    "wof:placetype":"locality"
},
  "geometry": {"coordinates":[69.68901,31.61216],"type":"Point"}
}