{
  "type": "Feature",
  "properties": {
    "gn:admin1_code":"3",
    "gn:asciiname":"Birmoghyal",
    "gn:country_code":"PK",
    "gn:dem":1622,
    "gn:feature_class":"P",
    "gn:feature_code":"PPL",
    "gn:name":"Birmoghyal",
    "gn:population":0,
    "gn:timezone":"Asia/Karachi",
    "iso:country":"PK",
    "name:eng_x_preferred":[
        "Birmogh Sh\u0101l"
    ],
    "wof:name":"Birmoghyal",
    "wof:placetype":"locality"
},
  "geometry": {"coordinates":[71.86951999999999,35.58397],"type":"Point"}
}