{
  "type": "Feature",
  "properties": {
    "gn:admin1_code":"4.0",
    "gn:asciiname":"Batere",
    "gn:country_code":"PK",
    "gn:dem":210,
    "gn:feature_class":"P",
    "gn:feature_code":"PPL",
    "gn:name":"Batere",
    "gn:population":0,
    "gn:timezone":"Asia/Karachi",
    "iso:country":"PK",
    "name:und_x_variant":[
        "Batera"
    ],
    "wof:name":"Batere",
    "wof:placetype":"locality"
},
  "geometry": {"coordinates":[73.70296999999999,32.09619],"type":"Point"}
}