{
  "type": "Feature",
  "properties": {
    "gn:admin1_code":"2.0",
    "gn:asciiname":"Chilo Mala",
    "gn:country_code":"PK",
    "gn:dem":424,
    "gn:feature_class":"P",
    "gn:feature_code":"PPL",
    "gn:name":"Chilo Mala",
    "gn:population":0,
    "gn:timezone":"Asia/Karachi",
    "iso:country":"PK",
    "wof:name":"Chilo Mala",
    "wof:placetype":"locality"
},
  "geometry": {"coordinates":[66.92256999999999,25.91984],"type":"Point"}
}