{
  "type": "Feature",
  "properties": {
    "gn:admin1_code":"1.0",
    "gn:asciiname":"Nakka Mela",
    "gn:country_code":"PK",
    "gn:dem":1756,
    "gn:feature_class":"P",
    "gn:feature_code":"PPL",
    "gn:name":"Nakka Mela",
    "gn:population":0,
    "gn:timezone":"Asia/Karachi",
    "iso:country":"PK",
    "wof:name":"Nakka Mela",
    "wof:placetype":"locality"
},
  "geometry": {"coordinates":[70.89695999999998,33.7309],"type":"Point"}
}