{
  "type": "Feature",
  "properties": {
    "gn:admin1_code":"01",
    "gn:asciiname":"Tol Khel",
    "gn:country_code":"PK",
    "gn:dem":945,
    "gn:feature_class":"P",
    "gn:feature_code":"PPL",
    "gn:name":"Tol Khel",
    "gn:population":0,
    "gn:timezone":"Asia/Karachi",
    "iso:country":"PK",
    "name:und_x_variant":[
        "Tabbai Tol Khel",
        "Tabai Tol Khel",
        "Tol Khel"
    ],
    "wof:name":"Tol Khel",
    "wof:placetype":"locality"
},
  "geometry": {"coordinates":[70.14498,33.07468],"type":"Point"}
}