{
  "type": "Feature",
  "properties": {
    "gn:admin1_code":"2.0",
    "gn:asciiname":"Band Malik Rehmatullah",
    "gn:country_code":"PK",
    "gn:dem":956,
    "gn:feature_class":"P",
    "gn:feature_code":"PPL",
    "gn:name":"Band Malik Rehmatullah",
    "gn:population":0,
    "gn:timezone":"Asia/Karachi",
    "iso:country":"PK",
    "wof:name":"Band Malik Rehmatullah",
    "wof:placetype":"locality"
},
  "geometry": {"coordinates":[62.77289,28.96937],"type":"Point"}
}