{
  "type": "Feature",
  "properties": {
    "gn:admin1_code":"4",
    "gn:asciiname":"Chak Twenty-seven Muhajir Branch",
    "gn:country_code":"PK",
    "gn:dem":186,
    "gn:feature_class":"P",
    "gn:feature_code":"PPL",
    "gn:name":"Chak Twenty-seven Muhajir Branch",
    "gn:population":0,
    "gn:timezone":"Asia/Karachi",
    "iso:country":"PK",
    "name:und_x_variant":[
        "Chak Twenty-seven MB"
    ],
    "wof:name":"Chak Twenty-seven Muhajir Branch",
    "wof:placetype":"locality"
},
  "geometry": {"coordinates":[71.96574,32.12015],"type":"Point"}
}