{
  "type": "Feature",
  "properties": {
    "gn:admin1_code":"5.0",
    "gn:asciiname":"Goth Rasul Bakhsh Thora",
    "gn:country_code":"PK",
    "gn:dem":59,
    "gn:feature_class":"P",
    "gn:feature_code":"PPL",
    "gn:name":"Goth Rasul Bakhsh Thora",
    "gn:population":0,
    "gn:timezone":"Asia/Karachi",
    "iso:country":"PK",
    "wof:name":"Goth Rasul Bakhsh Thora",
    "wof:placetype":"locality"
},
  "geometry": {"coordinates":[67.49489,27.18454],"type":"Point"}
}