{
  "type": "Feature",
  "properties": {
    "gn:admin1_code":"3",
    "gn:asciiname":"Dang Khui",
    "gn:country_code":"PK",
    "gn:dem":1792,
    "gn:feature_class":"P",
    "gn:feature_code":"PPL",
    "gn:name":"Dang Khui",
    "gn:population":0,
    "gn:timezone":"Asia/Karachi",
    "iso:country":"PK",
    "name:und_x_variant":[
        "K\u016bai",
        "Dong Kh\u016be",
        "Dang Khui"
    ],
    "wof:name":"Dang Khui",
    "wof:placetype":"locality"
},
  "geometry": {"coordinates":[72.67537,34.57999],"type":"Point"}
}