{
  "type": "Feature",
  "properties": {
    "gn:admin1_code":"5",
    "gn:asciiname":"Goth Baharo Khokhar",
    "gn:country_code":"PK",
    "gn:dem":49,
    "gn:feature_class":"P",
    "gn:feature_code":"PPL",
    "gn:name":"Goth Baharo Khokhar",
    "gn:population":0,
    "gn:timezone":"Asia/Karachi",
    "iso:country":"PK",
    "name:und_x_variant":[
        "Bah\u0101ro Khokhar"
    ],
    "wof:name":"Goth Baharo Khokhar",
    "wof:placetype":"locality"
},
  "geometry": {"coordinates":[68.14048000000001,27.99099],"type":"Point"}
}