{
  "type": "Feature",
  "properties": {
    "gn:admin1_code":"5",
    "gn:asciiname":"Allah Bakhsh Goth",
    "gn:country_code":"PK",
    "gn:dem":22,
    "gn:feature_class":"P",
    "gn:feature_code":"PPL",
    "gn:name":"Allah Bakhsh Goth",
    "gn:population":0,
    "gn:timezone":"Asia/Karachi",
    "iso:country":"PK",
    "name:und_x_variant":[
        "Goth Dil\u0101war Kh\u0101n"
    ],
    "wof:name":"Allah Bakhsh Goth",
    "wof:placetype":"locality"
},
  "geometry": {"coordinates":[68.58891,25.3064],"type":"Point"}
}