{
  "type": "Feature",
  "properties": {
    "gn:admin1_code":"3.0",
    "gn:asciiname":"Gujronwali Basti",
    "gn:country_code":"PK",
    "gn:dem":4023,
    "gn:feature_class":"P",
    "gn:feature_code":"PPL",
    "gn:name":"Gujronwali Basti",
    "gn:population":0,
    "gn:timezone":"Asia/Karachi",
    "iso:country":"PK",
    "wof:name":"Gujronwali Basti",
    "wof:placetype":"locality"
},
  "geometry": {"coordinates":[73.97609,35.17145],"type":"Point"}
}