{
  "type": "Feature",
  "properties": {
    "gn:admin1_code":"4.0",
    "gn:asciiname":"Dhar",
    "gn:country_code":"PK",
    "gn:dem":698,
    "gn:feature_class":"P",
    "gn:feature_code":"PPL",
    "gn:name":"Dhar",
    "gn:population":0,
    "gn:timezone":"Asia/Karachi",
    "iso:country":"PK",
    "wof:name":"Dhar",
    "wof:placetype":"locality"
},
  "geometry": {"coordinates":[73.43818,33.5353],"type":"Point"}
}