{
  "type": "Feature",
  "properties": {
    "gn:admin1_code":"2",
    "gn:asciiname":"Kili Maroi",
    "gn:country_code":"PK",
    "gn:dem":1305,
    "gn:feature_class":"P",
    "gn:feature_code":"PPL",
    "gn:name":"Kili Maroi",
    "gn:population":0,
    "gn:timezone":"Asia/Karachi",
    "iso:country":"PK",
    "name:und_x_variant":[
        "M\u0101roi"
    ],
    "wof:name":"Kili Maroi",
    "wof:placetype":"locality"
},
  "geometry": {"coordinates":[66.46088,27.43005],"type":"Point"}
}