{
  "type": "Feature",
  "properties": {
    "gn:admin1_code":"5",
    "gn:asciiname":"Goth Mahmud Dahiry",
    "gn:country_code":"PK",
    "gn:dem":11,
    "gn:feature_class":"P",
    "gn:feature_code":"PPL",
    "gn:name":"Goth Mahmud Dahiry",
    "gn:population":0,
    "gn:timezone":"Asia/Karachi",
    "iso:country":"PK",
    "name:und_x_variant":[
        "Sh\u0101h Ali Kh\u0101n Dhahari"
    ],
    "wof:name":"Goth Mahmud Dahiry",
    "wof:placetype":"locality"
},
  "geometry": {"coordinates":[69.49486,25.36428],"type":"Point"}
}