{
  "type": "Feature",
  "properties": {
    "gn:admin1_code":"4.0",
    "gn:asciiname":"Dera Dilawar",
    "gn:country_code":"PK",
    "gn:dem":125,
    "gn:feature_class":"P",
    "gn:feature_code":"PPL",
    "gn:name":"Dera Dilawar",
    "gn:population":0,
    "gn:timezone":"Asia/Karachi",
    "iso:country":"PK",
    "wof:name":"Dera Dilawar",
    "wof:placetype":"locality"
},
  "geometry": {"coordinates":[72.01191999999998,29.55253],"type":"Point"}
}