{
  "type": "Feature",
  "properties": {
    "gn:admin1_code":"3.0",
    "gn:asciiname":"Meragai",
    "gn:country_code":"PK",
    "gn:dem":1369,
    "gn:feature_class":"P",
    "gn:feature_code":"PPL",
    "gn:name":"Meragai",
    "gn:population":0,
    "gn:timezone":"Asia/Karachi",
    "iso:country":"PK",
    "name:und_x_variant":[
        "Merdgai"
    ],
    "wof:name":"Meragai",
    "wof:placetype":"locality"
},
  "geometry": {"coordinates":[72.45446,34.70723],"type":"Point"}
}