{
  "type": "Feature",
  "properties": {
    "gn:admin1_code":"4",
    "gn:asciiname":"Basti Pir Charian Punan",
    "gn:country_code":"PK",
    "gn:dem":87,
    "gn:feature_class":"P",
    "gn:feature_code":"PPL",
    "gn:name":"Basti Pir Charian Punan",
    "gn:population":0,
    "gn:timezone":"Asia/Karachi",
    "iso:country":"PK",
    "name:und_x_variant":[
        "Chak Twenty-four"
    ],
    "wof:name":"Basti Pir Charian Punan",
    "wof:placetype":"locality"
},
  "geometry": {"coordinates":[70.67694,28.52816],"type":"Point"}
}