{
  "type": "Feature",
  "properties": {
    "gn:admin1_code":"5",
    "gn:asciiname":"Goth Muhammad Khan Zardari",
    "gn:country_code":"PK",
    "gn:dem":42,
    "gn:feature_class":"P",
    "gn:feature_code":"PPL",
    "gn:name":"Goth Muhammad Khan Zardari",
    "gn:population":0,
    "gn:timezone":"Asia/Karachi",
    "iso:country":"PK",
    "wof:name":"Goth Muhammad Khan Zardari",
    "wof:placetype":"locality"
},
  "geometry": {"coordinates":[68.06149000000001,26.62467],"type":"Point"}
}