{
  "type": "Feature",
  "properties": {
    "gn:admin1_code":"5",
    "gn:asciiname":"Chhutto Joyo",
    "gn:country_code":"PK",
    "gn:dem":52,
    "gn:feature_class":"P",
    "gn:feature_code":"PPL",
    "gn:name":"Chhutto Joyo",
    "gn:population":0,
    "gn:timezone":"Asia/Karachi",
    "iso:country":"PK",
    "name:und_x_variant":[
        "Chhutto Joya"
    ],
    "wof:name":"Chhutto Joyo",
    "wof:placetype":"locality"
},
  "geometry": {"coordinates":[68.04666999999999,27.70326],"type":"Point"}
}