{
  "type": "Feature",
  "properties": {
    "gn:admin1_code":"3.0",
    "gn:asciiname":"Manra",
    "gn:country_code":"PK",
    "gn:dem":2279,
    "gn:feature_class":"P",
    "gn:feature_code":"PPL",
    "gn:name":"Manra",
    "gn:population":0,
    "gn:timezone":"Asia/Karachi",
    "iso:country":"PK",
    "wof:name":"Manra",
    "wof:placetype":"locality"
},
  "geometry": {"coordinates":[73.17256,34.81359],"type":"Point"}
}