{
  "type": "Feature",
  "properties": {
    "gn:admin1_code":"4",
    "gn:asciiname":"Chak Five Dullewala Branch",
    "gn:country_code":"PK",
    "gn:dem":201,
    "gn:feature_class":"P",
    "gn:feature_code":"PPL",
    "gn:name":"Chak Five Dullewala Branch",
    "gn:population":0,
    "gn:timezone":"Asia/Karachi",
    "iso:country":"PK",
    "name:und_x_variant":[
        "Chak Five DB"
    ],
    "wof:name":"Chak Five Dullewala Branch",
    "wof:placetype":"locality"
},
  "geometry": {"coordinates":[71.51005000000001,32.37899],"type":"Point"}
}