{
  "type": "Feature",
  "properties": {
    "gn:admin1_code":"4.0",
    "gn:asciiname":"Basti Bakhsha Machhi",
    "gn:country_code":"PK",
    "gn:dem":93,
    "gn:feature_class":"P",
    "gn:feature_code":"PPL",
    "gn:name":"Basti Bakhsha M\u0101chhi",
    "gn:population":0,
    "gn:timezone":"Asia/Karachi",
    "iso:country":"PK",
    "wof:name":"Basti Bakhsha Machhi",
    "wof:placetype":"locality"
},
  "geometry": {"coordinates":[70.45713000000001,29.05731],"type":"Point"}
}