{
  "type": "Feature",
  "properties": {
    "gn:admin1_code":"4.0",
    "gn:asciiname":"Rehman Nagar",
    "gn:country_code":"PK",
    "gn:dem":152,
    "gn:feature_class":"P",
    "gn:feature_code":"PPL",
    "gn:name":"Rehman Nagar",
    "gn:population":0,
    "gn:timezone":"Asia/Karachi",
    "iso:country":"PK",
    "name:und_x_variant":[
        "Rahman Nagar",
        "Lakhbudhar"
    ],
    "wof:name":"Rehman Nagar",
    "wof:placetype":"locality"
},
  "geometry": {"coordinates":[72.29313,31.18979],"type":"Point"}
}