{
  "type": "Feature",
  "properties": {
    "gn:admin1_code":"3.0",
    "gn:asciiname":"Sunai",
    "gn:country_code":"PK",
    "gn:dem":2042,
    "gn:feature_class":"P",
    "gn:feature_code":"PPL",
    "gn:name":"Sunai",
    "gn:population":0,
    "gn:timezone":"Asia/Karachi",
    "iso:country":"PK",
    "name:eng_x_preferred":[
        "Sunai"
    ],
    "wof:name":"Sunai",
    "wof:placetype":"locality"
},
  "geometry": {"coordinates":[71.59520000000001,35.07579],"type":"Point"}
}