{
  "type": "Feature",
  "properties": {
    "gn:admin1_code":"3.0",
    "gn:asciiname":"Godar",
    "gn:country_code":"PK",
    "gn:dem":1897,
    "gn:feature_class":"P",
    "gn:feature_code":"PPL",
    "gn:name":"Godar",
    "gn:population":0,
    "gn:timezone":"Asia/Karachi",
    "iso:country":"PK",
    "name:ceb_x_preferred":[
        "Godar"
    ],
    "name:msa_x_preferred":[
        "Godar"
    ],
    "name:new_x_preferred":[
        "\u0917\u094b\u0926\u093e\u0930"
    ],
    "name:pol_x_preferred":[
        "Godar"
    ],
    "wof:name":"Godar",
    "wof:placetype":"locality"
},
  "geometry": {"coordinates":[72.38321999999999,34.69893],"type":"Point"}
}