{
  "type": "Feature",
  "properties": {
    "gn:admin1_code":"5.0",
    "gn:asciiname":"Goth Suleman",
    "gn:country_code":"PK",
    "gn:dem":61,
    "gn:feature_class":"P",
    "gn:feature_code":"PPL",
    "gn:name":"Goth Suleman",
    "gn:population":0,
    "gn:timezone":"Asia/Karachi",
    "iso:country":"PK",
    "name:und_x_variant":[
        "Goth Sulam\u0101n"
    ],
    "wof:name":"Goth Suleman",
    "wof:placetype":"locality"
},
  "geometry": {"coordinates":[68.83225,28.40407],"type":"Point"}
}