{
  "type": "Feature",
  "properties": {
    "gn:admin1_code":"4",
    "gn:asciiname":"Puldiggar",
    "gn:country_code":"PK",
    "gn:dem":205,
    "gn:feature_class":"P",
    "gn:feature_code":"PPL",
    "gn:name":"Puldiggar",
    "gn:population":0,
    "gn:timezone":"Asia/Karachi",
    "iso:country":"PK",
    "name:und_x_variant":[
        "Puldaggar"
    ],
    "wof:name":"Puldiggar",
    "wof:placetype":"locality"
},
  "geometry": {"coordinates":[70.54765,30.67518],"type":"Point"}
}