{
  "type": "Feature",
  "properties": {
    "gn:admin1_code":"4.0",
    "gn:asciiname":"Chak Seventeen North Branch Colony",
    "gn:country_code":"PK",
    "gn:dem":192,
    "gn:feature_class":"P",
    "gn:feature_code":"PPL",
    "gn:name":"Chak Seventeen North Branch Colony",
    "gn:population":0,
    "gn:timezone":"Asia/Karachi",
    "iso:country":"PK",
    "name:und_x_variant":[
        "Chak Seventeen NB Colony",
        "Chak 17 NB Colony",
        "Chak Seventeen North Branch Colony"
    ],
    "wof:name":"Chak Seventeen North Branch Colony",
    "wof:placetype":"locality"
},
  "geometry": {"coordinates":[72.79456999999999,32.26965999999999],"type":"Point"}
}