{
  "type": "Feature",
  "properties": {
    "gn:admin1_code":"2.0",
    "gn:asciiname":"Khuddi Fateh Muhammad",
    "gn:country_code":"PK",
    "gn:dem":1817,
    "gn:feature_class":"P",
    "gn:feature_code":"PPL",
    "gn:name":"Khuddi Fateh Muhammad",
    "gn:population":0,
    "gn:timezone":"Asia/Karachi",
    "iso:country":"PK",
    "wof:name":"Khuddi Fateh Muhammad",
    "wof:placetype":"locality"
},
  "geometry": {"coordinates":[66.82539,28.76226],"type":"Point"}
}