{
  "type": "Feature",
  "properties": {
    "gn:admin1_code":"4.0",
    "gn:asciiname":"Maniand",
    "gn:country_code":"PK",
    "gn:dem":607,
    "gn:feature_class":"P",
    "gn:feature_code":"PPL",
    "gn:name":"Maniand",
    "gn:population":0,
    "gn:timezone":"Asia/Karachi",
    "iso:country":"PK",
    "wof:name":"Maniand",
    "wof:placetype":"locality"
},
  "geometry": {"coordinates":[73.41463,33.60693],"type":"Point"}
}