{
  "type": "Feature",
  "properties": {
    "gn:admin1_code":"3.0",
    "gn:asciiname":"Batgram",
    "gn:country_code":"PK",
    "gn:dem":329,
    "gn:feature_class":"P",
    "gn:feature_code":"PPL",
    "gn:name":"Batgram",
    "gn:population":0,
    "gn:timezone":"Asia/Karachi",
    "iso:country":"PK",
    "name:eng_x_preferred":[
        "Batgar\u0101m"
    ],
    "name:und_x_variant":[
        "Batagr\u0101m"
    ],
    "wof:name":"Batgram",
    "wof:placetype":"locality"
},
  "geometry": {"coordinates":[71.62635999999998,34.21987],"type":"Point"}
}