{
  "type": "Feature",
  "properties": {
    "gn:admin1_code":"3.0",
    "gn:asciiname":"Nagir Shah Rambil",
    "gn:country_code":"PK",
    "gn:dem":2181,
    "gn:feature_class":"P",
    "gn:feature_code":"PPL",
    "gn:name":"Nagir Shah Rambil",
    "gn:population":0,
    "gn:timezone":"Asia/Karachi",
    "iso:country":"PK",
    "wof:name":"Nagir Shah Rambil",
    "wof:placetype":"locality"
},
  "geometry": {"coordinates":[72.91868000000002,35.6112],"type":"Point"}
}