{
  "type": "Feature",
  "properties": {
    "gn:admin1_code":"6.0",
    "gn:asciiname":"Pothi Chapprian",
    "gn:country_code":"PK",
    "gn:dem":1515,
    "gn:feature_class":"P",
    "gn:feature_code":"PPL",
    "gn:name":"Pothi Chapprian",
    "gn:population":0,
    "gn:timezone":"Asia/Karachi",
    "iso:country":"PK",
    "wof:name":"Pothi Chapprian",
    "wof:placetype":"locality"
},
  "geometry": {"coordinates":[73.88806,33.80694],"type":"Point"}
}