{
  "type": "Feature",
  "properties": {
    "gn:admin1_code":"6",
    "gn:asciiname":"Galuhin",
    "gn:country_code":"PK",
    "gn:dem":712,
    "gn:feature_class":"P",
    "gn:feature_code":"PPL",
    "gn:name":"Galuhin",
    "gn:population":0,
    "gn:timezone":"Asia/Karachi",
    "iso:country":"PK",
    "wof:name":"Galuhin",
    "wof:placetype":"locality"
},
  "geometry": {"coordinates":[73.83856,33.57178],"type":"Point"}
}