{
  "type": "Feature",
  "properties": {
    "gn:admin1_code":"3",
    "gn:asciiname":"Takiasar",
    "gn:country_code":"PK",
    "gn:dem":2165,
    "gn:feature_class":"P",
    "gn:feature_code":"PPL",
    "gn:name":"Takiasar",
    "gn:population":0,
    "gn:timezone":"Asia/Karachi",
    "iso:country":"PK",
    "wof:name":"Takiasar",
    "wof:placetype":"locality"
},
  "geometry": {"coordinates":[72.97444,34.93527],"type":"Point"}
}