{
  "type": "Feature",
  "properties": {
    "gn:admin1_code":"05",
    "gn:asciiname":"Haji Umar Jat",
    "gn:country_code":"PK",
    "gn:dem":2,
    "gn:feature_class":"P",
    "gn:feature_code":"PPL",
    "gn:name":"Haji Umar Jat",
    "gn:population":0,
    "gn:timezone":"Asia/Karachi",
    "iso:country":"PK",
    "name:und_x_variant":[
        "H\u0101ji Usm\u0101n Jat"
    ],
    "wof:name":"Haji Umar Jat",
    "wof:placetype":"locality"
},
  "geometry": {"coordinates":[67.43231,24.08302],"type":"Point"}
}