{
  "type": "Feature",
  "properties": {
    "gn:admin1_code":"4.0",
    "gn:asciiname":"Qila Gaus",
    "gn:country_code":"PK",
    "gn:dem":202,
    "gn:feature_class":"P",
    "gn:feature_code":"PPL",
    "gn:name":"Qila Gaus",
    "gn:population":0,
    "gn:timezone":"Asia/Karachi",
    "iso:country":"PK",
    "name:und_x_variant":[
        "Qila Ghos"
    ],
    "wof:name":"Qila Gaus",
    "wof:placetype":"locality"
},
  "geometry": {"coordinates":[74.14713,31.52194],"type":"Point"}
}