{
  "type": "Feature",
  "properties": {
    "gn:admin1_code":"4.0",
    "gn:asciiname":"Aqilpur",
    "gn:country_code":"PK",
    "gn:dem":95,
    "gn:feature_class":"P",
    "gn:feature_code":"PPL",
    "gn:name":"Aqilpur",
    "gn:population":0,
    "gn:timezone":"Asia/Karachi",
    "iso:country":"PK",
    "name:und_x_variant":[
        "Aquilpur",
        "\u0100qilpur",
        "Aqilpur"
    ],
    "wof:name":"Aqilpur",
    "wof:placetype":"locality"
},
  "geometry": {"coordinates":[70.40106,29.11914],"type":"Point"}
}