{
  "type": "Feature",
  "properties": {
    "gn:admin1_code":"4.0",
    "gn:asciiname":"Baduwal",
    "gn:country_code":"PK",
    "gn:dem":229,
    "gn:feature_class":"P",
    "gn:feature_code":"PPL",
    "gn:name":"Baduwal",
    "gn:population":0,
    "gn:timezone":"Asia/Karachi",
    "iso:country":"PK",
    "name:und_x_variant":[
        "Budhowal",
        "Buddh\u016bw\u0101l",
        "Budh\u016bw\u0101la",
        "Baduwal"
    ],
    "wof:name":"Baduwal",
    "wof:placetype":"locality"
},
  "geometry": {"coordinates":[73.62891999999999,32.69422],"type":"Point"}
}