{
  "type": "Feature",
  "properties": {
    "gn:admin1_code":"5",
    "gn:asciiname":"Goth Haji Abdul Aziz Khosa",
    "gn:country_code":"PK",
    "gn:dem":69,
    "gn:feature_class":"P",
    "gn:feature_code":"PPL",
    "gn:name":"Goth Haji Abdul Aziz Khosa",
    "gn:population":0,
    "gn:timezone":"Asia/Karachi",
    "iso:country":"PK",
    "name:und_x_variant":[
        "Samandar Kh\u0101n Gola"
    ],
    "wof:name":"Goth Haji Abdul Aziz Khosa",
    "wof:placetype":"locality"
},
  "geometry": {"coordinates":[69.16838,28.39754000000001],"type":"Point"}
}