{
  "type": "Feature",
  "properties": {
    "gn:admin1_code":"5.0",
    "gn:asciiname":"Saum ji Dhani",
    "gn:country_code":"PK",
    "gn:dem":143,
    "gn:feature_class":"P",
    "gn:feature_code":"PPL",
    "gn:name":"Saum ji Dhani",
    "gn:population":0,
    "gn:timezone":"Asia/Karachi",
    "iso:country":"PK",
    "wof:name":"Saum ji Dhani",
    "wof:placetype":"locality"
},
  "geometry": {"coordinates":[70.52533000000003,25.23363],"type":"Point"}
}