{
  "type": "Feature",
  "properties": {
    "gn:admin1_code":"01",
    "gn:asciiname":"Kamar Garhi",
    "gn:country_code":"PK",
    "gn:dem":1872,
    "gn:feature_class":"P",
    "gn:feature_code":"PPL",
    "gn:name":"Kamar Garhi",
    "gn:population":0,
    "gn:timezone":"Asia/Karachi",
    "iso:country":"PK",
    "wof:name":"Kamar Garhi",
    "wof:placetype":"locality"
},
  "geometry": {"coordinates":[70.7223,33.67327],"type":"Point"}
}