{
  "type": "Feature",
  "properties": {
    "gn:admin1_code":"3.0",
    "gn:asciiname":"Khotian di Taro",
    "gn:country_code":"PK",
    "gn:dem":3479,
    "gn:feature_class":"P",
    "gn:feature_code":"PPL",
    "gn:name":"Khotian di Taro",
    "gn:population":0,
    "gn:timezone":"Asia/Karachi",
    "iso:country":"PK",
    "wof:name":"Khotian di Taro",
    "wof:placetype":"locality"
},
  "geometry": {"coordinates":[73.98661,34.99310999999999],"type":"Point"}
}