{
  "type": "Feature",
  "properties": {
    "gn:admin1_code":"2.0",
    "gn:asciiname":"Kundeli",
    "gn:country_code":"PK",
    "gn:dem":702,
    "gn:feature_class":"P",
    "gn:feature_code":"PPL",
    "gn:name":"Kundeli",
    "gn:population":0,
    "gn:timezone":"Asia/Karachi",
    "iso:country":"PK",
    "wof:name":"Kundeli",
    "wof:placetype":"locality"
},
  "geometry": {"coordinates":[69.53072,29.4534],"type":"Point"}
}