{
  "type": "Feature",
  "properties": {
    "gn:admin1_code":"4.0",
    "gn:asciiname":"Mahranwala Dera",
    "gn:country_code":"PK",
    "gn:dem":213,
    "gn:feature_class":"P",
    "gn:feature_code":"PPL",
    "gn:name":"Mahranwala Dera",
    "gn:population":0,
    "gn:timezone":"Asia/Karachi",
    "iso:country":"PK",
    "name:und_x_variant":[
        "Mah\u0101r"
    ],
    "wof:name":"Mahranwala Dera",
    "wof:placetype":"locality"
},
  "geometry": {"coordinates":[74.01600999999999,31.86364],"type":"Point"}
}