{
  "type": "Feature",
  "properties": {
    "gn:admin1_code":"4",
    "gn:asciiname":"Dakwali",
    "gn:country_code":"PK",
    "gn:dem":121,
    "gn:feature_class":"P",
    "gn:feature_code":"PPL",
    "gn:name":"Dakwali",
    "gn:population":0,
    "gn:timezone":"Asia/Karachi",
    "iso:country":"PK",
    "name:eng_x_preferred":[
        "Dakaw\u0101li"
    ],
    "wof:name":"Dakwali",
    "wof:placetype":"locality"
},
  "geometry": {"coordinates":[71.80566,29.35383],"type":"Point"}
}