{
  "type": "Feature",
  "properties": {
    "gn:admin1_code":"4.0",
    "gn:asciiname":"Pir Chittewattewala",
    "gn:country_code":"PK",
    "gn:dem":496,
    "gn:feature_class":"P",
    "gn:feature_code":"PPL",
    "gn:name":"Pir Chittewattewala",
    "gn:population":0,
    "gn:timezone":"Asia/Karachi",
    "iso:country":"PK",
    "wof:name":"Pir Chittewattewala",
    "wof:placetype":"locality"
},
  "geometry": {"coordinates":[72.56659000000001,32.89591],"type":"Point"}
}