{
  "type": "Feature",
  "properties": {
    "gn:admin1_code":"4.0",
    "gn:asciiname":"Chak Three Hundred Forty-six Jhang Branch",
    "gn:country_code":"PK",
    "gn:dem":166,
    "gn:feature_class":"P",
    "gn:feature_code":"PPL",
    "gn:name":"Chak Three Hundred Forty-six Jhang Branch",
    "gn:population":0,
    "gn:timezone":"Asia/Karachi",
    "iso:country":"PK",
    "name:eng_x_preferred":[
        "Chak Three Hundred Forty-six"
    ],
    "name:und_x_variant":[
        "Kot Kodhan",
        "B\u0101r\u0101ni Kodan",
        "B\u0101r\u0101i Kodan",
        "Chak Three Hundred Forty-six Jhang Branch",
        "Kodh\u0101n"
    ],
    "wof:name":"Chak Three Hundred Forty-six Jhang Branch",
    "wof:placetype":"locality"
},
  "geometry": {"coordinates":[72.64664999999999,31.29962],"type":"Point"}
}