{
  "type": "Feature",
  "properties": {
    "gn:admin1_code":"4",
    "gn:asciiname":"Basti Haji Wahid Bakhsh Buhar",
    "gn:country_code":"PK",
    "gn:dem":93,
    "gn:feature_class":"P",
    "gn:feature_code":"PPL",
    "gn:name":"Basti Haji Wahid Bakhsh Buhar",
    "gn:population":0,
    "gn:timezone":"Asia/Karachi",
    "iso:country":"PK",
    "wof:name":"Basti Haji Wahid Bakhsh Buhar",
    "wof:placetype":"locality"
},
  "geometry": {"coordinates":[70.55762,29.10901],"type":"Point"}
}