{
  "type": "Feature",
  "properties": {
    "gn:admin1_code":"05",
    "gn:asciiname":"Salamat Kehri",
    "gn:country_code":"PK",
    "gn:dem":26,
    "gn:feature_class":"P",
    "gn:feature_code":"PPL",
    "gn:name":"Salamat Kehri",
    "gn:population":0,
    "gn:timezone":"Asia/Karachi",
    "iso:country":"PK",
    "name:und_x_variant":[
        "Sal\u0101mat Kehrio"
    ],
    "wof:name":"Salamat Kehri",
    "wof:placetype":"locality"
},
  "geometry": {"coordinates":[68.58333,25.75],"type":"Point"}
}