{
  "type": "Feature",
  "properties": {
    "gn:admin1_code":"3.0",
    "gn:asciiname":"Batang Katha",
    "gn:country_code":"PK",
    "gn:dem":922,
    "gn:feature_class":"P",
    "gn:feature_code":"PPL",
    "gn:name":"Batang Katha",
    "gn:population":0,
    "gn:timezone":"Asia/Karachi",
    "iso:country":"PK",
    "wof:name":"Batang Katha",
    "wof:placetype":"locality"
},
  "geometry": {"coordinates":[73.1784,34.45962],"type":"Point"}
}