{
  "type": "Feature",
  "properties": {
    "gn:admin1_code":"5",
    "gn:asciiname":"Goth Nathu Pitafi",
    "gn:country_code":"PK",
    "gn:dem":19,
    "gn:feature_class":"P",
    "gn:feature_code":"PPL",
    "gn:name":"Goth Nathu Pitafi",
    "gn:population":0,
    "gn:timezone":"Asia/Karachi",
    "iso:country":"PK",
    "name:und_x_variant":[
        "Nathu Pat\u0101fi"
    ],
    "wof:name":"Goth Nathu Pitafi",
    "wof:placetype":"locality"
},
  "geometry": {"coordinates":[68.8228,25.36551],"type":"Point"}
}