{
  "type": "Feature",
  "properties": {
    "gn:admin1_code":"2",
    "gn:asciiname":"Drazanda",
    "gn:country_code":"PK",
    "gn:dem":1771,
    "gn:feature_class":"P",
    "gn:feature_code":"PPL",
    "gn:name":"Drazanda",
    "gn:population":0,
    "gn:timezone":"Asia/Karachi",
    "iso:country":"PK",
    "wof:name":"Drazanda",
    "wof:placetype":"locality"
},
  "geometry": {"coordinates":[68.28452,30.50709],"type":"Point"}
}