{
  "type": "Feature",
  "properties": {
    "gn:admin1_code":"2.0",
    "gn:asciiname":"Raz Ahmad Kili",
    "gn:country_code":"PK",
    "gn:dem":2497,
    "gn:feature_class":"P",
    "gn:feature_code":"PPL",
    "gn:name":"Raz Ahmad Kili",
    "gn:population":0,
    "gn:timezone":"Asia/Karachi",
    "iso:country":"PK",
    "wof:name":"Raz Ahmad Kili",
    "wof:placetype":"locality"
},
  "geometry": {"coordinates":[68.46649000000001,31.22133],"type":"Point"}
}