{
  "type": "Feature",
  "properties": {
    "gn:admin1_code":"5",
    "gn:asciiname":"Goth Muhammad Juman Jarwar",
    "gn:country_code":"PK",
    "gn:dem":12,
    "gn:feature_class":"P",
    "gn:feature_code":"PPL",
    "gn:name":"Goth Muhammad Juman Jarwar",
    "gn:population":0,
    "gn:timezone":"Asia/Karachi",
    "iso:country":"PK",
    "name:und_x_variant":[
        "Goth L\u0101l Bakhsh"
    ],
    "wof:name":"Goth Muhammad Juman Jarwar",
    "wof:placetype":"locality"
},
  "geometry": {"coordinates":[69.14155,25.02873],"type":"Point"}
}