{
  "type": "Feature",
  "properties": {
    "gn:admin1_code":"2.0",
    "gn:asciiname":"Kili Yar Muhammad Shahwani",
    "gn:country_code":"PK",
    "gn:dem":1512,
    "gn:feature_class":"P",
    "gn:feature_code":"PPL",
    "gn:name":"Kili Yar Muhammad Shahwani",
    "gn:population":0,
    "gn:timezone":"Asia/Karachi",
    "iso:country":"PK",
    "wof:name":"Kili Yar Muhammad Shahwani",
    "wof:placetype":"locality"
},
  "geometry": {"coordinates":[66.4529,29.89914000000001],"type":"Point"}
}