{
  "type": "Feature",
  "properties": {
    "gn:admin1_code":"2.0",
    "gn:asciiname":"Kadai Sarona Kili",
    "gn:country_code":"PK",
    "gn:dem":1663,
    "gn:feature_class":"P",
    "gn:feature_code":"PPL",
    "gn:name":"Kadai Sarona Kili",
    "gn:population":0,
    "gn:timezone":"Asia/Karachi",
    "iso:country":"PK",
    "wof:name":"Kadai Sarona Kili",
    "wof:placetype":"locality"
},
  "geometry": {"coordinates":[69.57896,31.34557],"type":"Point"}
}