{
  "type": "Feature",
  "properties": {
    "gn:admin1_code":"04",
    "gn:asciiname":"Ubhanwala",
    "gn:country_code":"PK",
    "gn:dem":155,
    "gn:feature_class":"P",
    "gn:feature_code":"PPL",
    "gn:name":"Ubhanwala",
    "gn:population":0,
    "gn:timezone":"Asia/Karachi",
    "iso:country":"PK",
    "name:und_x_variant":[
        "Ubh\u0101nanw\u0101la"
    ],
    "wof:name":"Ubhanwala",
    "wof:placetype":"locality"
},
  "geometry": {"coordinates":[72.23333000000002,31.31667],"type":"Point"}
}