{
  "type": "Feature",
  "properties": {
    "gn:admin1_code":"05",
    "gn:asciiname":"Shadi Shahid",
    "gn:country_code":"PK",
    "gn:dem":58,
    "gn:feature_class":"P",
    "gn:feature_code":"PPL",
    "gn:name":"Shadi Shahid",
    "gn:population":0,
    "gn:timezone":"Asia/Karachi",
    "iso:country":"PK",
    "name:und_x_variant":[
        "Shadishahid Jagir",
        "Shadi Shahid"
    ],
    "wof:name":"Shadi Shahid",
    "wof:placetype":"locality"
},
  "geometry": {"coordinates":[68.83333,27.46667],"type":"Point"}
}