{
  "type": "Feature",
  "properties": {
    "gn:admin1_code":"04",
    "gn:asciiname":"Chak One Hundred Seven Gugera Branch",
    "gn:country_code":"PK",
    "gn:dem":189,
    "gn:feature_class":"P",
    "gn:feature_code":"PPL",
    "gn:name":"Chak One Hundred Seven Gugera Branch",
    "gn:population":0,
    "gn:timezone":"Asia/Karachi",
    "iso:country":"PK",
    "name:und_x_variant":[
        "Path\u0101nkot",
        "Kh\u0101ls\u0101pur"
    ],
    "wof:name":"Chak One Hundred Seven Gugera Branch",
    "wof:placetype":"locality"
},
  "geometry": {"coordinates":[73.29649999999999,31.37611],"type":"Point"}
}