{
  "type": "Feature",
  "properties": {
    "gn:admin1_code":"2.0",
    "gn:asciiname":"Jahli Kaladar",
    "gn:country_code":"PK",
    "gn:dem":625,
    "gn:feature_class":"P",
    "gn:feature_code":"PPL",
    "gn:name":"Jahli Kaladar",
    "gn:population":0,
    "gn:timezone":"Asia/Karachi",
    "iso:country":"PK",
    "wof:name":"Jahli Kaladar",
    "wof:placetype":"locality"
},
  "geometry": {"coordinates":[62.79896,26.38391],"type":"Point"}
}