{
  "type": "Feature",
  "properties": {
    "gn:admin1_code":"4",
    "gn:asciiname":"Ladian",
    "gn:country_code":"PK",
    "gn:dem":289,
    "gn:feature_class":"P",
    "gn:feature_code":"PPL",
    "gn:name":"Ladian",
    "gn:population":0,
    "gn:timezone":"Asia/Karachi",
    "iso:country":"PK",
    "name:fas_x_preferred":[
        "\u0644\u0627\u062f\u06cc\u0627\u0646"
    ],
    "name:und_x_variant":[
        "Ladi\u0101"
    ],
    "name:urd_x_preferred":[
        "\u0644\u0627\u062f\u06cc\u0627\u06ba"
    ],
    "wof:name":"Ladian",
    "wof:placetype":"locality"
},
  "geometry": {"coordinates":[74.03408,32.80205],"type":"Point"}
}