{
  "type": "Feature",
  "properties": {
    "gn:admin1_code":"6",
    "gn:asciiname":"Nakka",
    "gn:country_code":"PK",
    "gn:dem":2154,
    "gn:feature_class":"P",
    "gn:feature_code":"PPL",
    "gn:name":"Nakka",
    "gn:population":0,
    "gn:timezone":"Asia/Karachi",
    "iso:country":"PK",
    "wof:name":"Nakka",
    "wof:placetype":"locality"
},
  "geometry": {"coordinates":[73.7296,34.44681],"type":"Point"}
}