{
  "type": "Feature",
  "properties": {
    "gn:admin1_code":"3.0",
    "gn:asciiname":"Ga Chattor",
    "gn:country_code":"PK",
    "gn:dem":2942,
    "gn:feature_class":"P",
    "gn:feature_code":"PPL",
    "gn:name":"Ga Chattor",
    "gn:population":0,
    "gn:timezone":"Asia/Karachi",
    "iso:country":"PK",
    "wof:name":"Ga Chattor",
    "wof:placetype":"locality"
},
  "geometry": {"coordinates":[72.26316,36.33236],"type":"Point"}
}