{
  "type": "Feature",
  "properties": {
    "gn:admin1_code":"2",
    "gn:asciiname":"Bahare Khan Jamali",
    "gn:country_code":"PK",
    "gn:dem":49,
    "gn:feature_class":"P",
    "gn:feature_code":"PPL",
    "gn:name":"Bahare Khan Jamali",
    "gn:population":0,
    "gn:timezone":"Asia/Karachi",
    "iso:country":"PK",
    "wof:name":"Bahare Khan Jamali",
    "wof:placetype":"locality"
},
  "geometry": {"coordinates":[67.86667,28.07778],"type":"Point"}
}