{
  "type": "Feature",
  "properties": {
    "gn:admin1_code":"4.0",
    "gn:asciiname":"Dhok Kalan",
    "gn:country_code":"PK",
    "gn:dem":349,
    "gn:feature_class":"P",
    "gn:feature_code":"PPL",
    "gn:name":"Dhok Kalan",
    "gn:population":0,
    "gn:timezone":"Asia/Karachi",
    "iso:country":"PK",
    "name:und_x_variant":[
        "Kallanw\u0101li"
    ],
    "wof:name":"Dhok Kalan",
    "wof:placetype":"locality"
},
  "geometry": {"coordinates":[71.85278000000002,32.8657],"type":"Point"}
}