{
  "type": "Feature",
  "properties": {
    "gn:admin1_code":"4",
    "gn:asciiname":"Chak One Dera Nawab Branch Janubi",
    "gn:country_code":"PK",
    "gn:dem":117,
    "gn:feature_class":"P",
    "gn:feature_code":"PPL",
    "gn:name":"Chak One Dera Nawab Branch Janubi",
    "gn:population":0,
    "gn:timezone":"Asia/Karachi",
    "iso:country":"PK",
    "name:eng_x_preferred":[
        "Chak One DNB Jan\u016bbi"
    ],
    "wof:name":"Chak One Dera Nawab Branch Janubi",
    "wof:placetype":"locality"
},
  "geometry": {"coordinates":[71.55414,29.08823],"type":"Point"}
}