{
  "type": "Feature",
  "properties": {
    "gn:admin1_code":"5",
    "gn:asciiname":"Azizuddin Surveyor",
    "gn:country_code":"PK",
    "gn:dem":15,
    "gn:feature_class":"P",
    "gn:feature_code":"PPL",
    "gn:name":"Az\u012bzudd\u012bn Surveyor",
    "gn:population":0,
    "gn:timezone":"Asia/Karachi",
    "iso:country":"PK",
    "wof:name":"Azizuddin Surveyor",
    "wof:placetype":"locality"
},
  "geometry": {"coordinates":[68.95,25.29028],"type":"Point"}
}