{
  "type": "Feature",
  "properties": {
    "gn:admin1_code":"5",
    "gn:asciiname":"Goth Haji Muhammad Hashim",
    "gn:country_code":"PK",
    "gn:dem":19,
    "gn:feature_class":"P",
    "gn:feature_code":"PPL",
    "gn:name":"Goth Haji Muhammad Hashim",
    "gn:population":0,
    "gn:timezone":"Asia/Karachi",
    "iso:country":"PK",
    "name:und_x_variant":[
        "Goth H\u0101ji Hashim Panwhar",
        "H\u0101ji Sidd\u012bq Panwhar",
        "Goth Haji Muhammad Hashim"
    ],
    "wof:name":"Goth Haji Muhammad Hashim",
    "wof:placetype":"locality"
},
  "geometry": {"coordinates":[68.67938000000001,25.1716],"type":"Point"}
}