{
  "type": "Feature",
  "properties": {
    "gn:admin1_code":"6",
    "gn:asciiname":"Darra",
    "gn:country_code":"PK",
    "gn:dem":1771,
    "gn:feature_class":"P",
    "gn:feature_code":"PPL",
    "gn:name":"Darra",
    "gn:population":0,
    "gn:timezone":"Asia/Karachi",
    "iso:country":"PK",
    "name:ceb_x_preferred":[
        "Darra"
    ],
    "name:swe_x_preferred":[
        "Darra"
    ],
    "name:und_x_variant":[
        "Dara"
    ],
    "wof:name":"Darra",
    "wof:placetype":"locality"
},
  "geometry": {"coordinates":[73.76323000000002,34.04291],"type":"Point"}
}