{
  "type": "Feature",
  "properties": {
    "gn:admin1_code":"5.0",
    "gn:asciiname":"Aba Shoikh",
    "gn:country_code":"PK",
    "gn:dem":7,
    "gn:feature_class":"P",
    "gn:feature_code":"PPL",
    "gn:name":"Aba Shoikh",
    "gn:population":0,
    "gn:timezone":"Asia/Karachi",
    "iso:country":"PK",
    "name:und_x_variant":[
        "Abu Shaikha"
    ],
    "wof:name":"Aba Shoikh",
    "wof:placetype":"locality"
},
  "geometry": {"coordinates":[68.85019,24.61578],"type":"Point"}
}