{
  "type": "Feature",
  "properties": {
    "gn:admin1_code":"2.0",
    "gn:asciiname":"Kawas Sharqi",
    "gn:country_code":"PK",
    "gn:dem":2109,
    "gn:feature_class":"P",
    "gn:feature_code":"PPL",
    "gn:name":"Kawas Sharqi",
    "gn:population":0,
    "gn:timezone":"Asia/Karachi",
    "iso:country":"PK",
    "name:pol_x_preferred":[
        "Kawas"
    ],
    "name:und_x_variant":[
        "Kow\u0101s",
        "Kawas",
        "Kawas Sharqi"
    ],
    "wof:name":"Kawas Sharqi",
    "wof:placetype":"locality"
},
  "geometry": {"coordinates":[67.58917,30.46871],"type":"Point"}
}