{
  "type": "Feature",
  "properties": {
    "gn:admin1_code":"2.0",
    "gn:asciiname":"Bulbul",
    "gn:country_code":"PK",
    "gn:dem":1486,
    "gn:feature_class":"P",
    "gn:feature_code":"PPL",
    "gn:name":"Bulbul",
    "gn:population":0,
    "gn:timezone":"Asia/Karachi",
    "iso:country":"PK",
    "wof:name":"Bulbul",
    "wof:placetype":"locality"
},
  "geometry": {"coordinates":[66.65071999999999,28.49639],"type":"Point"}
}