{
  "type": "Feature",
  "properties": {
    "gn:admin1_code":"1.0",
    "gn:asciiname":"Tarwam Sar Kalle",
    "gn:country_code":"PK",
    "gn:dem":588,
    "gn:feature_class":"P",
    "gn:feature_code":"PPL",
    "gn:name":"Tarwam Sar Kalle",
    "gn:population":0,
    "gn:timezone":"Asia/Karachi",
    "iso:country":"PK",
    "name:und_x_variant":[
        "Tarwam Sar Kill Tower",
        "Tarwam Sar Kill",
        "Tarwam Sar Kalle",
        "Tarwam Sar Kili"
    ],
    "wof:name":"Tarwam Sar Kalle",
    "wof:placetype":"locality"
},
  "geometry": {"coordinates":[70.43373000000003,32.58883],"type":"Point"}
}