{
  "type": "Feature",
  "properties": {
    "gn:admin1_code":"3.0",
    "gn:asciiname":"Ashrait",
    "gn:country_code":"PK",
    "gn:dem":2618,
    "gn:feature_class":"P",
    "gn:feature_code":"PPL",
    "gn:name":"Ashrait",
    "gn:population":0,
    "gn:timezone":"Asia/Karachi",
    "iso:country":"PK",
    "name:eng_x_preferred":[
        "Ashrait"
    ],
    "wof:name":"Ashrait",
    "wof:placetype":"locality"
},
  "geometry": {"coordinates":[72.02088000000001,35.48137],"type":"Point"}
}