{
  "type": "Feature",
  "properties": {
    "gn:admin1_code":"03",
    "gn:asciiname":"Gujar Kalle",
    "gn:country_code":"PK",
    "gn:dem":1467,
    "gn:feature_class":"P",
    "gn:feature_code":"PPL",
    "gn:name":"Gujar Kalle",
    "gn:population":0,
    "gn:timezone":"Asia/Karachi",
    "iso:country":"PK",
    "name:eng_x_preferred":[
        "G\u016bjar"
    ],
    "wof:name":"Gujar Kalle",
    "wof:placetype":"locality"
},
  "geometry": {"coordinates":[71.73721,34.93143],"type":"Point"}
}