{
  "type": "Feature",
  "properties": {
    "gn:admin1_code":"2.0",
    "gn:asciiname":"Liaqutabad",
    "gn:country_code":"PK",
    "gn:dem":1034,
    "gn:feature_class":"P",
    "gn:feature_code":"PPL",
    "gn:name":"Liaqutabad",
    "gn:population":0,
    "gn:timezone":"Asia/Karachi",
    "iso:country":"PK",
    "wof:name":"Liaqutabad",
    "wof:placetype":"locality"
},
  "geometry": {"coordinates":[65.59595,27.10507],"type":"Point"}
}