{
  "type": "Feature",
  "properties": {
    "gn:admin1_code":"04",
    "gn:asciiname":"Chak One Hundred Ninety-five Gugera Branch",
    "gn:country_code":"PK",
    "gn:dem":165,
    "gn:feature_class":"P",
    "gn:feature_code":"PPL",
    "gn:name":"Chak One Hundred Ninety-five Gugera Branch",
    "gn:population":0,
    "gn:timezone":"Asia/Karachi",
    "iso:country":"PK",
    "name:und_x_variant":[
        "Chak One Hundred Ninety-Five GB",
        "Pindori",
        "Chak One Hundred Ninety-five Gugera Branch"
    ],
    "wof:name":"Chak One Hundred Ninety-five Gugera Branch",
    "wof:placetype":"locality"
},
  "geometry": {"coordinates":[72.73348,30.8687],"type":"Point"}
}