{
  "type": "Feature",
  "properties": {
    "gn:admin1_code":"3.0",
    "gn:asciiname":"Puliru Shal",
    "gn:country_code":"PK",
    "gn:dem":3133,
    "gn:feature_class":"P",
    "gn:feature_code":"PPL",
    "gn:name":"Puliru Shal",
    "gn:population":0,
    "gn:timezone":"Asia/Karachi",
    "iso:country":"PK",
    "name:eng_x_preferred":[
        "Puliru Shal"
    ],
    "wof:name":"Puliru Shal",
    "wof:placetype":"locality"
},
  "geometry": {"coordinates":[72.09004,35.92351],"type":"Point"}
}