{
  "type": "Feature",
  "properties": {
    "gn:admin1_code":"5",
    "gn:asciiname":"Goth Rajhan Jhattial",
    "gn:country_code":"PK",
    "gn:dem":47,
    "gn:feature_class":"P",
    "gn:feature_code":"PPL",
    "gn:name":"Goth Rajhan Jhattial",
    "gn:population":0,
    "gn:timezone":"Asia/Karachi",
    "iso:country":"PK",
    "name:und_x_variant":[
        "Goth R\u0101njho Jhatti\u0101l"
    ],
    "wof:name":"Goth Rajhan Jhattial",
    "wof:placetype":"locality"
},
  "geometry": {"coordinates":[67.89375,27.17639],"type":"Point"}
}