{
  "type": "Feature",
  "properties": {
    "gn:admin1_code":"3.0",
    "gn:asciiname":"Sarkandi",
    "gn:country_code":"PK",
    "gn:dem":2624,
    "gn:feature_class":"P",
    "gn:feature_code":"PPL",
    "gn:name":"Sarkandi",
    "gn:population":0,
    "gn:timezone":"Asia/Karachi",
    "iso:country":"PK",
    "wof:name":"Sarkandi",
    "wof:placetype":"locality"
},
  "geometry": {"coordinates":[73.16897,34.84623],"type":"Point"}
}