{
  "type": "Feature",
  "properties": {
    "gn:admin1_code":"4.0",
    "gn:asciiname":"Bagga",
    "gn:country_code":"PK",
    "gn:dem":278,
    "gn:feature_class":"P",
    "gn:feature_code":"PPL",
    "gn:name":"Bagga",
    "gn:population":0,
    "gn:timezone":"Asia/Karachi",
    "iso:country":"PK",
    "wof:name":"Bagga",
    "wof:placetype":"locality"
},
  "geometry": {"coordinates":[75.25743,32.31044],"type":"Point"}
}