{
  "type": "Feature",
  "properties": {
    "gn:admin1_code":"7.0",
    "gn:asciiname":"Tulch",
    "gn:country_code":"PK",
    "gn:dem":2247,
    "gn:feature_class":"P",
    "gn:feature_code":"PPL",
    "gn:name":"Tulch",
    "gn:population":0,
    "gn:timezone":"Asia/Karachi",
    "iso:country":"PK",
    "wof:name":"Tulch",
    "wof:placetype":"locality"
},
  "geometry": {"coordinates":[74.85505999999999,35.70065],"type":"Point"}
}