{
  "type": "Feature",
  "properties": {
    "gn:admin1_code":"2.0",
    "gn:asciiname":"Kanro",
    "gn:country_code":"PK",
    "gn:dem":1035,
    "gn:feature_class":"P",
    "gn:feature_code":"PPL",
    "gn:name":"Kanro",
    "gn:population":0,
    "gn:timezone":"Asia/Karachi",
    "iso:country":"PK",
    "wof:name":"Kanro",
    "wof:placetype":"locality"
},
  "geometry": {"coordinates":[66.21857,27.02463],"type":"Point"}
}