{
  "type": "Feature",
  "properties": {
    "gn:admin1_code":"4.0",
    "gn:asciiname":"Chab",
    "gn:country_code":"PK",
    "gn:dem":460,
    "gn:feature_class":"P",
    "gn:feature_code":"PPL",
    "gn:name":"Chab",
    "gn:population":0,
    "gn:timezone":"Asia/Karachi",
    "iso:country":"PK",
    "name:deu_x_preferred":[
        "Chab"
    ],
    "name:fra_x_preferred":[
        "Chab"
    ],
    "name:spa_x_preferred":[
        "Chab"
    ],
    "wof:name":"Chab",
    "wof:placetype":"locality"
},
  "geometry": {"coordinates":[71.89497,33.25923],"type":"Point"}
}