{
  "type": "Feature",
  "properties": {
    "gn:admin1_code":"1.0",
    "gn:asciiname":"Saib Rajgan",
    "gn:country_code":"PK",
    "gn:dem":393,
    "gn:feature_class":"P",
    "gn:feature_code":"PPL",
    "gn:name":"Saib Rajgan",
    "gn:population":0,
    "gn:timezone":"Asia/Karachi",
    "iso:country":"PK",
    "name:und_x_variant":[
        "Seb"
    ],
    "wof:name":"Saib Rajgan",
    "wof:placetype":"locality"
},
  "geometry": {"coordinates":[73.70053,33.18952],"type":"Point"}
}