{
  "type": "Feature",
  "properties": {
    "gn:admin1_code":"6",
    "gn:asciiname":"Kai",
    "gn:country_code":"PK",
    "gn:dem":2412,
    "gn:feature_class":"P",
    "gn:feature_code":"PPL",
    "gn:name":"Kai",
    "gn:population":0,
    "gn:timezone":"Asia/Karachi",
    "iso:country":"PK",
    "wof:name":"Kai",
    "wof:placetype":"locality"
},
  "geometry": {"coordinates":[73.73860999999999,34.33586],"type":"Point"}
}