{
  "type": "Feature",
  "properties": {
    "gn:admin1_code":"3",
    "gn:asciiname":"Jhok Chappanwali",
    "gn:country_code":"PK",
    "gn:dem":182,
    "gn:feature_class":"P",
    "gn:feature_code":"PPL",
    "gn:name":"Jhok Chappanwali",
    "gn:population":0,
    "gn:timezone":"Asia/Karachi",
    "iso:country":"PK",
    "name:und_x_variant":[
        "Chappan ki Jhok"
    ],
    "wof:name":"Jhok Chappanwali",
    "wof:placetype":"locality"
},
  "geometry": {"coordinates":[71.05609,32.07906],"type":"Point"}
}