{
  "type": "Feature",
  "properties": {
    "gn:admin1_code":"4",
    "gn:asciiname":"Khizarke",
    "gn:country_code":"PK",
    "gn:dem":177,
    "gn:feature_class":"P",
    "gn:feature_code":"PPL",
    "gn:name":"Khizarke",
    "gn:population":0,
    "gn:timezone":"Asia/Karachi",
    "iso:country":"PK",
    "name:und_x_variant":[
        "Khizar ke",
        "Khirke",
        "Khizarke"
    ],
    "wof:name":"Khizarke",
    "wof:placetype":"locality"
},
  "geometry": {"coordinates":[72.8248,31.71889],"type":"Point"}
}