{
  "type": "Feature",
  "properties": {
    "gn:admin1_code":"3.0",
    "gn:asciiname":"Zahri Dera",
    "gn:country_code":"PK",
    "gn:dem":1240,
    "gn:feature_class":"P",
    "gn:feature_code":"PPL",
    "gn:name":"Zahri Dera",
    "gn:population":0,
    "gn:timezone":"Asia/Karachi",
    "iso:country":"PK",
    "wof:name":"Zahri Dera",
    "wof:placetype":"locality"
},
  "geometry": {"coordinates":[73.14449,35.23185],"type":"Point"}
}