{
  "type": "Feature",
  "properties": {
    "gn:admin1_code":"1.0",
    "gn:asciiname":"Kaza Khel",
    "gn:country_code":"PK",
    "gn:dem":1330,
    "gn:feature_class":"P",
    "gn:feature_code":"PPL",
    "gn:name":"Kaza Khel",
    "gn:population":0,
    "gn:timezone":"Asia/Karachi",
    "iso:country":"PK",
    "name:und_x_variant":[
        "Kara Khel"
    ],
    "wof:name":"Kaza Khel",
    "wof:placetype":"locality"
},
  "geometry": {"coordinates":[70.8818,33.91423],"type":"Point"}
}