{
  "type": "Feature",
  "properties": {
    "gn:admin1_code":"4.0",
    "gn:asciiname":"Kattha Saghral",
    "gn:country_code":"PK",
    "gn:dem":224,
    "gn:feature_class":"P",
    "gn:feature_code":"PPL",
    "gn:name":"Kattha Saghral",
    "gn:population":0,
    "gn:timezone":"Asia/Karachi",
    "iso:country":"PK",
    "name:und_x_variant":[
        "Katha Saghr\u0101l",
        "Kattha Saghral"
    ],
    "wof:name":"Kattha Saghral",
    "wof:placetype":"locality"
},
  "geometry": {"coordinates":[72.44457,32.50787],"type":"Point"}
}