{
  "type": "Feature",
  "properties": {
    "gn:admin1_code":"4.0",
    "gn:asciiname":"Kattha Saghral",
    "gn:country_code":"PK",
    "gn:dem":224,
    "gn:feature_class":"P",
    "gn:feature_code":"PPL",
    "gn:name":"Kattha Saghral",
    "gn:population":0,
    "gn:timezone":"Asia/Karachi",
    "iso:country":"PK",
    "name:fas_x_preferred":[
        "\u06a9\u062a\u0647\u0647 \u0633\u06af\u0647\u0631\u0627\u0644"
    ],
    "name:und_x_variant":[
        "Katha Saghr\u0101l",
        "Kattha Saghral"
    ],
    "name:urd_x_preferred":[
        "\u06a9\u0679\u06be\u06c1 \u0633\u06af\u06be\u0631\u0627\u0644"
    ],
    "wof:name":"Kattha Saghral",
    "wof:placetype":"locality"
},
  "geometry": {"coordinates":[72.44457,32.50787],"type":"Point"}
}