{
  "type": "Feature",
  "properties": {
    "gn:admin1_code":"4.0",
    "gn:asciiname":"Rana Singh",
    "gn:country_code":"PK",
    "gn:dem":432,
    "gn:feature_class":"P",
    "gn:feature_code":"PPL",
    "gn:name":"Rana Singh",
    "gn:population":0,
    "gn:timezone":"Asia/Karachi",
    "iso:country":"PK",
    "wof:name":"Rana Singh",
    "wof:placetype":"locality"
},
  "geometry": {"coordinates":[72.51246,32.8393],"type":"Point"}
}