{
  "type": "Feature",
  "properties": {
    "gn:admin1_code":"5.0",
    "gn:asciiname":"Goth Bajhani",
    "gn:country_code":"PK",
    "gn:dem":59,
    "gn:feature_class":"P",
    "gn:feature_code":"PPL",
    "gn:name":"Goth Bajhani",
    "gn:population":0,
    "gn:timezone":"Asia/Karachi",
    "iso:country":"PK",
    "name:und_x_variant":[
        "B\u0101jh\u0101ni"
    ],
    "wof:name":"Goth Bajhani",
    "wof:placetype":"locality"
},
  "geometry": {"coordinates":[68.29644999999999,28.1511],"type":"Point"}
}