{
  "type": "Feature",
  "properties": {
    "gn:admin1_code":"4.0",
    "gn:asciiname":"Dauburji",
    "gn:country_code":"PK",
    "gn:dem":219,
    "gn:feature_class":"P",
    "gn:feature_code":"PPL",
    "gn:name":"Dauburji",
    "gn:population":0,
    "gn:timezone":"Asia/Karachi",
    "iso:country":"PK",
    "name:und_x_variant":[
        "Garhi Mustafa"
    ],
    "wof:name":"Dauburji",
    "wof:placetype":"locality"
},
  "geometry": {"coordinates":[74.02301,31.98492],"type":"Point"}
}