{
  "type": "Feature",
  "properties": {
    "gn:admin1_code":"4.0",
    "gn:asciiname":"Chak Fifty-seven - D",
    "gn:country_code":"PK",
    "gn:dem":169,
    "gn:feature_class":"P",
    "gn:feature_code":"PPL",
    "gn:name":"Chak Fifty-seven - D",
    "gn:population":0,
    "gn:timezone":"Asia/Karachi",
    "iso:country":"PK",
    "name:und_x_variant":[
        "Kor\u0101y\u0101nw\u0101la",
        "Chak 57",
        "Chak Fifty-seven",
        "Chak Fifty-seven - D"
    ],
    "wof:name":"Chak Fifty-seven - D",
    "wof:placetype":"locality"
},
  "geometry": {"coordinates":[73.40439000000001,30.615],"type":"Point"}
}