{
  "type": "Feature",
  "properties": {
    "gn:admin1_code":"4.0",
    "gn:asciiname":"Chak Six Hundred Twelve",
    "gn:country_code":"PK",
    "gn:dem":175,
    "gn:feature_class":"P",
    "gn:feature_code":"PPL",
    "gn:name":"Chak Six Hundred Twelve",
    "gn:population":0,
    "gn:timezone":"Asia/Karachi",
    "iso:country":"PK",
    "name:und_x_variant":[
        "M\u016bhabbat"
    ],
    "wof:name":"Chak Six Hundred Twelve",
    "wof:placetype":"locality"
},
  "geometry": {"coordinates":[73.08556999999998,30.88932],"type":"Point"}
}