{
  "type": "Feature",
  "properties": {
    "gn:admin1_code":"6.0",
    "gn:asciiname":"Dhok Kumharan",
    "gn:country_code":"PK",
    "gn:dem":451,
    "gn:feature_class":"P",
    "gn:feature_code":"PPL",
    "gn:name":"Dhok Kumharan",
    "gn:population":0,
    "gn:timezone":"Asia/Karachi",
    "iso:country":"PK",
    "wof:name":"Dhok Kumharan",
    "wof:placetype":"locality"
},
  "geometry": {"coordinates":[73.50391,33.24302],"type":"Point"}
}