{
  "type": "Feature",
  "properties": {
    "gn:admin1_code":"2.0",
    "gn:asciiname":"Phait",
    "gn:country_code":"PK",
    "gn:dem":1799,
    "gn:feature_class":"P",
    "gn:feature_code":"PPL",
    "gn:name":"Phait",
    "gn:population":0,
    "gn:timezone":"Asia/Karachi",
    "iso:country":"PK",
    "wof:name":"Phait",
    "wof:placetype":"locality"
},
  "geometry": {"coordinates":[67.11695,29.86726],"type":"Point"}
}