{
  "type": "Feature",
  "properties": {
    "gn:admin1_code":"6",
    "gn:asciiname":"Kar",
    "gn:country_code":"PK",
    "gn:dem":2094,
    "gn:feature_class":"P",
    "gn:feature_code":"PPL",
    "gn:name":"Kar",
    "gn:population":0,
    "gn:timezone":"Asia/Karachi",
    "iso:country":"PK",
    "name:und_x_variant":[
        "Rarri",
        "Barri"
    ],
    "wof:name":"Kar",
    "wof:placetype":"locality"
},
  "geometry": {"coordinates":[74.1054,33.9433],"type":"Point"}
}