{
  "type": "Feature",
  "properties": {
    "gn:admin1_code":"6",
    "gn:asciiname":"Kar",
    "gn:country_code":"PK",
    "gn:dem":2094,
    "gn:feature_class":"P",
    "gn:feature_code":"PPL",
    "gn:name":"Kar",
    "gn:population":0,
    "gn:timezone":"Asia/Karachi",
    "iso:country":"PK",
    "name:bul_x_preferred":[
        "\u041a\u0430\u0440"
    ],
    "name:ceb_x_preferred":[
        "Kar"
    ],
    "name:dan_x_preferred":[
        "Kar"
    ],
    "name:deu_x_preferred":[
        "Kar"
    ],
    "name:fra_x_preferred":[
        "Kar"
    ],
    "name:hrv_x_preferred":[
        "Kar"
    ],
    "name:hun_x_preferred":[
        "Kar"
    ],
    "name:ltz_x_preferred":[
        "Kar"
    ],
    "name:nld_x_preferred":[
        "Kar"
    ],
    "name:nor_x_preferred":[
        "Kar"
    ],
    "name:pol_x_preferred":[
        "Kar"
    ],
    "name:rus_x_preferred":[
        "\u041a\u0430\u0440"
    ],
    "name:slk_x_preferred":[
        "Kar"
    ],
    "name:spa_x_preferred":[
        "Kar"
    ],
    "name:swe_x_preferred":[
        "Kar"
    ],
    "name:tur_x_preferred":[
        "Kar"
    ],
    "name:ukr_x_preferred":[
        "\u041a\u0430\u0440"
    ],
    "name:und_x_variant":[
        "Rarri",
        "Barri"
    ],
    "wof:name":"Kar",
    "wof:placetype":"locality"
},
  "geometry": {"coordinates":[74.1054,33.9433],"type":"Point"}
}