{
  "type": "Feature",
  "properties": {
    "gn:admin1_code":"4.0",
    "gn:asciiname":"Dhok Abdul Aziz",
    "gn:country_code":"PK",
    "gn:dem":488,
    "gn:feature_class":"P",
    "gn:feature_code":"PPL",
    "gn:name":"Dhok Abdul Aziz",
    "gn:population":0,
    "gn:timezone":"Asia/Karachi",
    "iso:country":"PK",
    "wof:name":"Dhok Abdul Aziz",
    "wof:placetype":"locality"
},
  "geometry": {"coordinates":[73.05974999999999,33.38882],"type":"Point"}
}