{
  "type": "Feature",
  "properties": {
    "gn:admin1_code":"4.0",
    "gn:asciiname":"Naiwala",
    "gn:country_code":"PK",
    "gn:dem":149,
    "gn:feature_class":"P",
    "gn:feature_code":"PPL",
    "gn:name":"Naiwala",
    "gn:population":0,
    "gn:timezone":"Asia/Karachi",
    "iso:country":"PK",
    "name:fas_x_preferred":[
        "\u0646\u0627\u0626\u06cc \u0648\u0627\u0644\u0627"
    ],
    "name:urd_x_preferred":[
        "\u0646\u0627\u0626\u06cc \u0648\u0627\u0644\u0627"
    ],
    "wof:name":"Naiwala",
    "wof:placetype":"locality"
},
  "geometry": {"coordinates":[70.89001,30.99592],"type":"Point"}
}