{
  "type": "Feature",
  "properties": {
    "gn:admin1_code":"4",
    "gn:asciiname":"Khu Sahibwala",
    "gn:country_code":"PK",
    "gn:dem":126,
    "gn:feature_class":"P",
    "gn:feature_code":"PPL",
    "gn:name":"Khu Sahibwala",
    "gn:population":0,
    "gn:timezone":"Asia/Karachi",
    "iso:country":"PK",
    "name:eng_x_preferred":[
        "S\u0101hibw\u0101la"
    ],
    "wof:name":"Khu Sahibwala",
    "wof:placetype":"locality"
},
  "geometry": {"coordinates":[70.74802,30.26497],"type":"Point"}
}