{
  "type": "Feature",
  "properties": {
    "gn:admin1_code":"6",
    "gn:asciiname":"Tararan",
    "gn:country_code":"PK",
    "gn:dem":2079,
    "gn:feature_class":"P",
    "gn:feature_code":"PPL",
    "gn:name":"Tararan",
    "gn:population":0,
    "gn:timezone":"Asia/Karachi",
    "iso:country":"PK",
    "name:und_x_variant":[
        "Tr\u0101r\u0101n"
    ],
    "wof:name":"Tararan",
    "wof:placetype":"locality"
},
  "geometry": {"coordinates":[73.85884,34.21854],"type":"Point"}
}