{
  "type": "Feature",
  "properties": {
    "gn:admin1_code":"4.0",
    "gn:asciiname":"Chandar Khan-Da-Dera",
    "gn:country_code":"PK",
    "gn:dem":230,
    "gn:feature_class":"P",
    "gn:feature_code":"PPL",
    "gn:name":"Chandar Khan-Da-Dera",
    "gn:population":0,
    "gn:timezone":"Asia/Karachi",
    "iso:country":"PK",
    "wof:name":"Chandar Khan-Da-Dera",
    "wof:placetype":"locality"
},
  "geometry": {"coordinates":[74.39555,32.22168],"type":"Point"}
}