{
  "type": "Feature",
  "properties": {
    "gn:admin1_code":"3.0",
    "gn:asciiname":"Khordor",
    "gn:country_code":"PK",
    "gn:dem":3595,
    "gn:feature_class":"P",
    "gn:feature_code":"PPL",
    "gn:name":"Khordor",
    "gn:population":0,
    "gn:timezone":"Asia/Karachi",
    "iso:country":"PK",
    "wof:name":"Khordor",
    "wof:placetype":"locality"
},
  "geometry": {"coordinates":[72.57226999999997,35.58267],"type":"Point"}
}