{
  "type": "Feature",
  "properties": {
    "gn:admin1_code":"4",
    "gn:asciiname":"Basti Tyeb Baluch",
    "gn:country_code":"PK",
    "gn:dem":100,
    "gn:feature_class":"P",
    "gn:feature_code":"PPL",
    "gn:name":"Basti Tyeb Baluch",
    "gn:population":0,
    "gn:timezone":"Asia/Karachi",
    "iso:country":"PK",
    "name:und_x_variant":[
        "Basti Taib Baloch",
        "Taibw\u0101li"
    ],
    "wof:name":"Basti Tyeb Baluch",
    "wof:placetype":"locality"
},
  "geometry": {"coordinates":[70.9198,29.18201],"type":"Point"}
}