{
  "type": "Feature",
  "properties": {
    "gn:admin1_code":"04",
    "gn:asciiname":"Chak Fifty-three -Twelve Left",
    "gn:country_code":"PK",
    "gn:dem":156,
    "gn:feature_class":"P",
    "gn:feature_code":"PPL",
    "gn:name":"Chak Fifty-three -Twelve Left",
    "gn:population":0,
    "gn:timezone":"Asia/Karachi",
    "iso:country":"PK",
    "name:und_x_variant":[
        "M\u012br S\u0101hibw\u0101la",
        "Misali"
    ],
    "wof:name":"Chak Fifty-three -Twelve Left",
    "wof:placetype":"locality"
},
  "geometry": {"coordinates":[72.62047,30.38117],"type":"Point"}
}