{
  "type": "Feature",
  "properties": {
    "gn:admin1_code":"2.0",
    "gn:asciiname":"Goth Mazar Kori",
    "gn:country_code":"PK",
    "gn:dem":58,
    "gn:feature_class":"P",
    "gn:feature_code":"PPL",
    "gn:name":"Goth Mazar Kori",
    "gn:population":0,
    "gn:timezone":"Asia/Karachi",
    "iso:country":"PK",
    "name:und_x_variant":[
        "Goth Maz\u0101r Kore"
    ],
    "wof:name":"Goth Mazar Kori",
    "wof:placetype":"locality"
},
  "geometry": {"coordinates":[68.01000999999999,28.32025],"type":"Point"}
}