{
  "type": "Feature",
  "properties": {
    "gn:admin1_code":"2.0",
    "gn:asciiname":"Goth Qasu",
    "gn:country_code":"PK",
    "gn:dem":330,
    "gn:feature_class":"P",
    "gn:feature_code":"PPL",
    "gn:name":"Goth Qasu",
    "gn:population":0,
    "gn:timezone":"Asia/Karachi",
    "iso:country":"PK",
    "wof:name":"Goth Qasu",
    "wof:placetype":"locality"
},
  "geometry": {"coordinates":[67.07419,25.63908],"type":"Point"}
}