{
  "type": "Feature",
  "properties": {
    "gn:admin1_code":"4",
    "gn:asciiname":"Jafarwala",
    "gn:country_code":"PK",
    "gn:dem":129,
    "gn:feature_class":"P",
    "gn:feature_code":"PPL",
    "gn:name":"Jafarwala",
    "gn:population":0,
    "gn:timezone":"Asia/Karachi",
    "iso:country":"PK",
    "name:eng_x_preferred":[
        "Jafarwala"
    ],
    "wof:name":"Jafarwala",
    "wof:placetype":"locality"
},
  "geometry": {"coordinates":[70.74101999999998,30.32428],"type":"Point"}
}