{
  "type": "Feature",
  "properties": {
    "gn:admin1_code":"3.0",
    "gn:asciiname":"Akram Khan",
    "gn:country_code":"PK",
    "gn:dem":370,
    "gn:feature_class":"P",
    "gn:feature_code":"PPL",
    "gn:name":"Akram Khan",
    "gn:population":0,
    "gn:timezone":"Asia/Karachi",
    "iso:country":"PK",
    "name:ben_x_preferred":[
        "\u0986\u0995\u09b0\u09be\u09ae \u0996\u09be\u09a8"
    ],
    "name:eng_x_preferred":[
        "Akram Khan"
    ],
    "name:ind_x_preferred":[
        "Akram Khan"
    ],
    "wof:name":"Akram Khan",
    "wof:placetype":"locality"
},
  "geometry": {"coordinates":[71.92201,34.34083],"type":"Point"}
}