{
  "type": "Feature",
  "properties": {
    "gn:admin1_code":"3.0",
    "gn:asciiname":"Kas-Pul",
    "gn:country_code":"PK",
    "gn:dem":1036,
    "gn:feature_class":"P",
    "gn:feature_code":"PPL",
    "gn:name":"Kas-Pul",
    "gn:population":0,
    "gn:timezone":"Asia/Karachi",
    "iso:country":"PK",
    "wof:name":"Kas-Pul",
    "wof:placetype":"locality"
},
  "geometry": {"coordinates":[72.99269,34.67119],"type":"Point"}
}