{
  "type": "Feature",
  "properties": {
    "gn:admin1_code":"4.0",
    "gn:asciiname":"Chak Eleven",
    "gn:country_code":"PK",
    "gn:dem":156,
    "gn:feature_class":"P",
    "gn:feature_code":"PPL",
    "gn:name":"Chak Eleven",
    "gn:population":0,
    "gn:timezone":"Asia/Karachi",
    "iso:country":"PK",
    "name:eng_x_preferred":[
        "Sat\u0101n"
    ],
    "wof:name":"Chak Eleven",
    "wof:placetype":"locality"
},
  "geometry": {"coordinates":[71.88609,31.19524],"type":"Point"}
}