{
  "type": "Feature",
  "properties": {
    "gn:admin1_code":"2.0",
    "gn:asciiname":"Chimney",
    "gn:country_code":"PK",
    "gn:dem":1511,
    "gn:feature_class":"P",
    "gn:feature_code":"PPL",
    "gn:name":"Chimney",
    "gn:population":0,
    "gn:timezone":"Asia/Karachi",
    "iso:country":"PK",
    "wof:name":"Chimney",
    "wof:placetype":"locality"
},
  "geometry": {"coordinates":[66.95076999999999,30.49776],"type":"Point"}
}