{
  "type": "Feature",
  "properties": {
    "gn:admin1_code":"3.0",
    "gn:asciiname":"Shewa Chowk",
    "gn:country_code":"PK",
    "gn:dem":338,
    "gn:feature_class":"P",
    "gn:feature_code":"PPL",
    "gn:name":"Shewa Chowk",
    "gn:population":0,
    "gn:timezone":"Asia/Karachi",
    "iso:country":"PK",
    "name:eng_x_preferred":[
        "Shewa Chowk"
    ],
    "wof:name":"Shewa Chowk",
    "wof:placetype":"locality"
},
  "geometry": {"coordinates":[72.31249,34.21382],"type":"Point"}
}