{
  "type": "Feature",
  "properties": {
    "gn:admin1_code":"5",
    "gn:asciiname":"Goth Qazi Sultan Muhammad",
    "gn:country_code":"PK",
    "gn:dem":10,
    "gn:feature_class":"P",
    "gn:feature_code":"PPL",
    "gn:name":"Goth Qazi Sultan Muhammad",
    "gn:population":0,
    "gn:timezone":"Asia/Karachi",
    "iso:country":"PK",
    "name:und_x_variant":[
        "Q\u0101zi Sult\u0101n Muhammad"
    ],
    "wof:name":"Goth Qazi Sultan Muhammad",
    "wof:placetype":"locality"
},
  "geometry": {"coordinates":[69.52938,25.1915],"type":"Point"}
}