{
  "type": "Feature",
  "properties": {
    "gn:admin1_code":"3",
    "gn:asciiname":"Kharkai",
    "gn:country_code":"PK",
    "gn:dem":1504,
    "gn:feature_class":"P",
    "gn:feature_code":"PPL",
    "gn:name":"Kharkai",
    "gn:population":0,
    "gn:timezone":"Asia/Karachi",
    "iso:country":"PK",
    "wof:name":"Kharkai",
    "wof:placetype":"locality"
},
  "geometry": {"coordinates":[72.01262,34.82172],"type":"Point"}
}