{
  "type": "Feature",
  "properties": {
    "gn:admin1_code":"3.0",
    "gn:asciiname":"Kopra",
    "gn:country_code":"PK",
    "gn:dem":2191,
    "gn:feature_class":"P",
    "gn:feature_code":"PPL",
    "gn:name":"Kopra",
    "gn:population":0,
    "gn:timezone":"Asia/Karachi",
    "iso:country":"PK",
    "wof:name":"Kopra",
    "wof:placetype":"locality"
},
  "geometry": {"coordinates":[72.93779000000001,34.59466],"type":"Point"}
}