{
  "type": "Feature",
  "properties": {
    "gn:admin1_code":"2",
    "gn:asciiname":"Haveli Ahmad",
    "gn:country_code":"PK",
    "gn:dem":1027,
    "gn:feature_class":"P",
    "gn:feature_code":"PPL",
    "gn:name":"Haveli Ahmad",
    "gn:population":0,
    "gn:timezone":"Asia/Karachi",
    "iso:country":"PK",
    "wof:name":"Haveli Ahmad",
    "wof:placetype":"locality"
},
  "geometry": {"coordinates":[69.44407,29.82905],"type":"Point"}
}