{
  "type": "Feature",
  "properties": {
    "gn:admin1_code":"1.0",
    "gn:asciiname":"Surdag",
    "gn:country_code":"PK",
    "gn:dem":769,
    "gn:feature_class":"P",
    "gn:feature_code":"PPL",
    "gn:name":"Surdag",
    "gn:population":0,
    "gn:timezone":"Asia/Karachi",
    "iso:country":"PK",
    "wof:name":"Surdag",
    "wof:placetype":"locality"
},
  "geometry": {"coordinates":[71.31582,34.38005],"type":"Point"}
}