{
  "type": "Feature",
  "properties": {
    "gn:admin1_code":"4.0",
    "gn:asciiname":"Kotla Madho Ram",
    "gn:country_code":"PK",
    "gn:dem":183,
    "gn:feature_class":"P",
    "gn:feature_code":"PPL",
    "gn:name":"Kotla Madho Ram",
    "gn:population":0,
    "gn:timezone":"Asia/Karachi",
    "iso:country":"PK",
    "name:und_x_variant":[
        "Madhar\u0101m"
    ],
    "wof:name":"Kotla Madho Ram",
    "wof:placetype":"locality"
},
  "geometry": {"coordinates":[73.47225999999998,30.99009],"type":"Point"}
}