{
  "type": "Feature",
  "properties": {
    "gn:admin1_code":"4",
    "gn:asciiname":"Jhandwala",
    "gn:country_code":"PK",
    "gn:dem":233,
    "gn:feature_class":"P",
    "gn:feature_code":"PPL",
    "gn:name":"Jhandwala",
    "gn:population":0,
    "gn:timezone":"Asia/Karachi",
    "iso:country":"PK",
    "name:und_x_variant":[
        "Jhandew\u0101la"
    ],
    "wof:name":"Jhandwala",
    "wof:placetype":"locality"
},
  "geometry": {"coordinates":[74.00332,32.58275],"type":"Point"}
}