{
  "type": "Feature",
  "properties": {
    "gn:admin1_code":"1.0",
    "gn:asciiname":"Mian Kalle",
    "gn:country_code":"PK",
    "gn:dem":963,
    "gn:feature_class":"P",
    "gn:feature_code":"PPL",
    "gn:name":"Mian Kalle",
    "gn:population":0,
    "gn:timezone":"Asia/Karachi",
    "iso:country":"PK",
    "wof:name":"Mian Kalle",
    "wof:placetype":"locality"
},
  "geometry": {"coordinates":[71.42634,34.76916],"type":"Point"}
}