{
  "type": "Feature",
  "properties": {
    "gn:admin1_code":"4",
    "gn:asciiname":"Ranjhe Phanuwala",
    "gn:country_code":"PK",
    "gn:dem":114,
    "gn:feature_class":"P",
    "gn:feature_code":"PPL",
    "gn:name":"Ranjhe Phanuwala",
    "gn:population":0,
    "gn:timezone":"Asia/Karachi",
    "iso:country":"PK",
    "name:und_x_variant":[
        "R\u0101njhe Pham\u012bw\u0101la"
    ],
    "wof:name":"Ranjhe Phanuwala",
    "wof:placetype":"locality"
},
  "geometry": {"coordinates":[70.93518,29.81485],"type":"Point"}
}