{
  "type": "Feature",
  "properties": {
    "gn:admin1_code":"5.0",
    "gn:asciiname":"Goth Rasig",
    "gn:country_code":"PK",
    "gn:dem":254,
    "gn:feature_class":"P",
    "gn:feature_code":"PPL",
    "gn:name":"Goth Rasig",
    "gn:population":0,
    "gn:timezone":"Asia/Karachi",
    "iso:country":"PK",
    "wof:name":"Goth Rasig",
    "wof:placetype":"locality"
},
  "geometry": {"coordinates":[67.66611,25.15806],"type":"Point"}
}