{
  "type": "Feature",
  "properties": {
    "gn:admin1_code":"3.0",
    "gn:asciiname":"Mir Shafu",
    "gn:country_code":"PK",
    "gn:dem":1904,
    "gn:feature_class":"P",
    "gn:feature_code":"PPL",
    "gn:name":"Mir Shafu",
    "gn:population":0,
    "gn:timezone":"Asia/Karachi",
    "iso:country":"PK",
    "wof:name":"Mir Shafu",
    "wof:placetype":"locality"
},
  "geometry": {"coordinates":[72.85556,35.52486],"type":"Point"}
}