{
  "type": "Feature",
  "properties": {
    "gn:admin1_code":"4",
    "gn:asciiname":"Chah Ahmad Lukwala",
    "gn:country_code":"PK",
    "gn:dem":164,
    "gn:feature_class":"P",
    "gn:feature_code":"PPL",
    "gn:name":"Chah Ahmad Lukwala",
    "gn:population":0,
    "gn:timezone":"Asia/Karachi",
    "iso:country":"PK",
    "name:und_x_variant":[
        "Athar\u0101h Tukray"
    ],
    "wof:name":"Chah Ahmad Lukwala",
    "wof:placetype":"locality"
},
  "geometry": {"coordinates":[72.86776999999999,30.65316],"type":"Point"}
}