{
  "type": "Feature",
  "properties": {
    "gn:admin1_code":"4",
    "gn:asciiname":"Mahteke Wan",
    "gn:country_code":"PK",
    "gn:dem":173,
    "gn:feature_class":"P",
    "gn:feature_code":"PPL",
    "gn:name":"Mahteke Wan",
    "gn:population":0,
    "gn:timezone":"Asia/Karachi",
    "iso:country":"PK",
    "name:und_x_variant":[
        "Mahte ki W\u0101n"
    ],
    "wof:name":"Mahteke Wan",
    "wof:placetype":"locality"
},
  "geometry": {"coordinates":[73.69651999999998,30.55288],"type":"Point"}
}