{
  "type": "Feature",
  "properties": {
    "gn:admin1_code":"2.0",
    "gn:asciiname":"Ragha",
    "gn:country_code":"PK",
    "gn:dem":2183,
    "gn:feature_class":"P",
    "gn:feature_code":"PPL",
    "gn:name":"Ragha",
    "gn:population":0,
    "gn:timezone":"Asia/Karachi",
    "iso:country":"PK",
    "name:eng_x_preferred":[
        "Ragha"
    ],
    "wof:name":"Ragha",
    "wof:placetype":"locality"
},
  "geometry": {"coordinates":[67.30538,30.89701],"type":"Point"}
}