{
  "type": "Feature",
  "properties": {
    "gn:admin1_code":"4",
    "gn:asciiname":"Ahmad Dhandi",
    "gn:country_code":"PK",
    "gn:dem":189,
    "gn:feature_class":"P",
    "gn:feature_code":"PPL",
    "gn:name":"Ahmad Dhandi",
    "gn:population":0,
    "gn:timezone":"Asia/Karachi",
    "iso:country":"PK",
    "ks:ks_name":"Ahmad Dhandi",
    "ks:ks_pop":1535,
    "ks:ks_type":"VILLAGE",
    "name:eng_x_preferred":[
        "Ahmad Dhandi"
    ],
    "wof:name":"Ahmad Dhandi",
    "wof:placetype":"locality",
    "wof:population":1535
},
  "geometry": {"coordinates":[74.38056,30.77639],"type":"Point"}
}