{
  "type": "Feature",
  "properties": {
    "gn:admin1_code":"3.0",
    "gn:asciiname":"Kali Banda",
    "gn:country_code":"PK",
    "gn:dem":265,
    "gn:feature_class":"P",
    "gn:feature_code":"PPL",
    "gn:name":"Kali Banda",
    "gn:population":0,
    "gn:timezone":"Asia/Karachi",
    "iso:country":"PK",
    "name:und_x_variant":[
        "Chunda"
    ],
    "wof:name":"Kali Banda",
    "wof:placetype":"locality"
},
  "geometry": {"coordinates":[70.72861999999998,32.25472],"type":"Point"}
}