{
  "type": "Feature",
  "properties": {
    "gn:admin1_code":"4.0",
    "gn:asciiname":"Dera Muhammad Bashir Jhkhar",
    "gn:country_code":"PK",
    "gn:dem":151,
    "gn:feature_class":"P",
    "gn:feature_code":"PPL",
    "gn:name":"Dera Muhammad Bashir Jhkhar",
    "gn:population":0,
    "gn:timezone":"Asia/Karachi",
    "iso:country":"PK",
    "wof:name":"Dera Muhammad Bashir Jhkhar",
    "wof:placetype":"locality"
},
  "geometry": {"coordinates":[72.95453000000001,29.62837],"type":"Point"}
}