{
  "type": "Feature",
  "properties": {
    "gn:admin1_code":"4",
    "gn:asciiname":"Chak One Hundred Five - Nine Left Western Branch",
    "gn:country_code":"PK",
    "gn:dem":136,
    "gn:feature_class":"P",
    "gn:feature_code":"PPL",
    "gn:name":"Chak One Hundred Five - Nine Left Western Branch",
    "gn:population":0,
    "gn:timezone":"Asia/Karachi",
    "iso:country":"PK",
    "name:und_x_variant":[
        "Kh\u012bwa Baloch"
    ],
    "wof:name":"Chak One Hundred Five - Nine Left Western Branch",
    "wof:placetype":"locality"
},
  "geometry": {"coordinates":[72.21998000000001,30.0023],"type":"Point"}
}