{
  "type": "Feature",
  "properties": {
    "gn:admin1_code":"05",
    "gn:asciiname":"Haji Muhammad Umar Bhatti",
    "gn:country_code":"PK",
    "gn:dem":3,
    "gn:feature_class":"P",
    "gn:feature_code":"PPL",
    "gn:name":"Haji Muhammad Umar Bhatti",
    "gn:population":0,
    "gn:timezone":"Asia/Karachi",
    "iso:country":"PK",
    "name:und_x_variant":[
        "H\u0101ji All\u0101h Wario"
    ],
    "wof:name":"Haji Muhammad Umar Bhatti",
    "wof:placetype":"locality"
},
  "geometry": {"coordinates":[67.90748000000001,24.21472],"type":"Point"}
}