{
  "type": "Feature",
  "properties": {
    "gn:admin1_code":"5",
    "gn:asciiname":"Goth Wahid Bakhsh Mahar",
    "gn:country_code":"PK",
    "gn:dem":74,
    "gn:feature_class":"P",
    "gn:feature_code":"PPL",
    "gn:name":"Goth Wahid Bakhsh Mahar",
    "gn:population":0,
    "gn:timezone":"Asia/Karachi",
    "iso:country":"PK",
    "name:und_x_variant":[
        "W\u0101hid Bakhsh Mah\u0101r"
    ],
    "wof:name":"Goth Wahid Bakhsh Mahar",
    "wof:placetype":"locality"
},
  "geometry": {"coordinates":[69.68040000000001,28.09693],"type":"Point"}
}