{
  "type": "Feature",
  "properties": {
    "gn:admin1_code":"1.0",
    "gn:asciiname":"Wahabian",
    "gn:country_code":"PK",
    "gn:dem":763,
    "gn:feature_class":"P",
    "gn:feature_code":"PPL",
    "gn:name":"Wahabian",
    "gn:population":0,
    "gn:timezone":"Asia/Karachi",
    "iso:country":"PK",
    "wof:name":"Wahabian",
    "wof:placetype":"locality"
},
  "geometry": {"coordinates":[71.46880999999998,33.64912],"type":"Point"}
}