{
  "type": "Feature",
  "properties": {
    "gn:admin1_code":"4",
    "gn:asciiname":"Basti Bhandiwala",
    "gn:country_code":"PK",
    "gn:dem":116,
    "gn:feature_class":"P",
    "gn:feature_code":"PPL",
    "gn:name":"Basti Bhandiwala",
    "gn:population":0,
    "gn:timezone":"Asia/Karachi",
    "iso:country":"PK",
    "name:und_x_variant":[
        "B\u0101diw\u0101la"
    ],
    "wof:name":"Basti Bhandiwala",
    "wof:placetype":"locality"
},
  "geometry": {"coordinates":[70.55986999999998,29.93802],"type":"Point"}
}