{
  "type": "Feature",
  "properties": {
    "gn:admin1_code":"4",
    "gn:asciiname":"Thatta Rupchand",
    "gn:country_code":"PK",
    "gn:dem":178,
    "gn:feature_class":"P",
    "gn:feature_code":"PPL",
    "gn:name":"Thatta R\u016bpchand",
    "gn:population":0,
    "gn:timezone":"Asia/Karachi",
    "iso:country":"PK",
    "wof:name":"Thatta Rupchand",
    "wof:placetype":"locality"
},
  "geometry": {"coordinates":[73.48333000000002,31.11944],"type":"Point"}
}