{
  "type": "Feature",
  "properties": {
    "gn:admin1_code":"2.0",
    "gn:asciiname":"Babar",
    "gn:country_code":"PK",
    "gn:dem":1802,
    "gn:feature_class":"P",
    "gn:feature_code":"PPL",
    "gn:name":"Babar",
    "gn:population":0,
    "gn:timezone":"Asia/Karachi",
    "iso:country":"PK",
    "name:ceb_x_preferred":[
        "Babar"
    ],
    "name:deu_x_preferred":[
        "Babar"
    ],
    "name:fin_x_preferred":[
        "Babar"
    ],
    "name:fra_x_preferred":[
        "Babar"
    ],
    "name:jpn_x_preferred":[
        "\u30d0\u30d0\u30fc\u30eb"
    ],
    "name:nld_x_preferred":[
        "Babar"
    ],
    "name:por_x_preferred":[
        "Babar"
    ],
    "name:spa_x_preferred":[
        "Babar"
    ],
    "name:swe_x_preferred":[
        "Babar"
    ],
    "name:und_x_variant":[
        "B\u0101b\u0101r"
    ],
    "wof:name":"Babar",
    "wof:placetype":"locality"
},
  "geometry": {"coordinates":[69.57745,31.22962],"type":"Point"}
}