{
  "type": "Feature",
  "properties": {
    "gn:admin1_code":"4.0",
    "gn:asciiname":"Chak Fifty-eight - Five Left",
    "gn:country_code":"PK",
    "gn:dem":176,
    "gn:feature_class":"P",
    "gn:feature_code":"PPL",
    "gn:name":"Chak Fifty-eight - Five Left",
    "gn:population":0,
    "gn:timezone":"Asia/Karachi",
    "iso:country":"PK",
    "name:und_x_variant":[
        "Gunnu",
        "Gannu"
    ],
    "wof:name":"Chak Fifty-eight - Five Left",
    "wof:placetype":"locality"
},
  "geometry": {"coordinates":[73.29021999999998,30.67103],"type":"Point"}
}