{
  "type": "Feature",
  "properties": {
    "gn:admin1_code":"2.0",
    "gn:asciiname":"Kili Gul Muhammad",
    "gn:country_code":"PK",
    "gn:dem":785,
    "gn:feature_class":"P",
    "gn:feature_code":"PPL",
    "gn:name":"Kili Gul Muhammad",
    "gn:population":0,
    "gn:timezone":"Asia/Karachi",
    "iso:country":"PK",
    "wof:name":"Kili Gul Muhammad",
    "wof:placetype":"locality"
},
  "geometry": {"coordinates":[65.44313000000001,28.68055],"type":"Point"}
}