{
  "type": "Feature",
  "properties": {
    "gn:admin1_code":"2.0",
    "gn:asciiname":"Adosh Sar",
    "gn:country_code":"PK",
    "gn:dem":2137,
    "gn:feature_class":"P",
    "gn:feature_code":"PPL",
    "gn:name":"Adosh Sar",
    "gn:population":0,
    "gn:timezone":"Asia/Karachi",
    "iso:country":"PK",
    "wof:name":"Adosh Sar",
    "wof:placetype":"locality"
},
  "geometry": {"coordinates":[66.89683000000001,30.87909],"type":"Point"}
}