{
  "type": "Feature",
  "properties": {
    "gn:admin1_code":"2",
    "gn:asciiname":"Qutab Khan",
    "gn:country_code":"PK",
    "gn:dem":1081,
    "gn:feature_class":"P",
    "gn:feature_code":"PPL",
    "gn:name":"Qutab Khan",
    "gn:population":0,
    "gn:timezone":"Asia/Karachi",
    "iso:country":"PK",
    "name:und_x_variant":[
        "Qutab"
    ],
    "wof:name":"Qutab Khan",
    "wof:placetype":"locality"
},
  "geometry": {"coordinates":[69.48165,29.8744],"type":"Point"}
}