{
  "type": "Feature",
  "properties": {
    "gn:admin1_code":"5.0",
    "gn:asciiname":"Roshan Khan",
    "gn:country_code":"PK",
    "gn:dem":46,
    "gn:feature_class":"P",
    "gn:feature_code":"PPL",
    "gn:name":"Roshan Khan",
    "gn:population":0,
    "gn:timezone":"Asia/Karachi",
    "iso:country":"PK",
    "name:deu_x_preferred":[
        "Roshan Khan"
    ],
    "name:fra_x_preferred":[
        "Roshan Khan"
    ],
    "name:urd_x_preferred":[
        "\u0631\u0648\u0634\u0646 \u062e\u0627\u0646"
    ],
    "wof:name":"Roshan Khan",
    "wof:placetype":"locality"
},
  "geometry": {"coordinates":[67.81491,27.46692],"type":"Point"}
}