{
  "type": "Feature",
  "properties": {
    "gn:admin1_code":"4",
    "gn:asciiname":"Somre",
    "gn:country_code":"PK",
    "gn:dem":126,
    "gn:feature_class":"P",
    "gn:feature_code":"PPL",
    "gn:name":"Somre",
    "gn:population":0,
    "gn:timezone":"Asia/Karachi",
    "iso:country":"PK",
    "name:eng_x_preferred":[
        "Somre"
    ],
    "wof:name":"Somre",
    "wof:placetype":"locality"
},
  "geometry": {"coordinates":[70.88923,30.20985],"type":"Point"}
}