{
  "type": "Feature",
  "properties": {
    "gn:admin1_code":"1.0",
    "gn:asciiname":"Sarkhawai Dara",
    "gn:country_code":"PK",
    "gn:dem":1608,
    "gn:feature_class":"P",
    "gn:feature_code":"PPL",
    "gn:name":"Sarkhawai Dara",
    "gn:population":0,
    "gn:timezone":"Asia/Karachi",
    "iso:country":"PK",
    "name:und_x_variant":[
        "Sankllawa Darra",
        "Sarkhawa Darra",
        "Sarkhawai Dara"
    ],
    "wof:name":"Sarkhawai Dara",
    "wof:placetype":"locality"
},
  "geometry": {"coordinates":[70.40893,33.63371],"type":"Point"}
}