{
  "type": "Feature",
  "properties": {
    "gn:admin1_code":"5.0",
    "gn:asciiname":"Daphro Goth",
    "gn:country_code":"PK",
    "gn:dem":58,
    "gn:feature_class":"P",
    "gn:feature_code":"PPL",
    "gn:name":"Daphro Goth",
    "gn:population":0,
    "gn:timezone":"Asia/Karachi",
    "iso:country":"PK",
    "wof:name":"Daphro Goth",
    "wof:placetype":"locality"
},
  "geometry": {"coordinates":[69.3565,26.67393],"type":"Point"}
}