{
  "type": "Feature",
  "properties": {
    "gn:admin1_code":"3.0",
    "gn:asciiname":"Dako Baba Kalle",
    "gn:country_code":"PK",
    "gn:dem":341,
    "gn:feature_class":"P",
    "gn:feature_code":"PPL",
    "gn:name":"Dako Baba Kalle",
    "gn:population":0,
    "gn:timezone":"Asia/Karachi",
    "iso:country":"PK",
    "name:eng_x_preferred":[
        "Daku\u0101b\u0101d"
    ],
    "wof:name":"Dako Baba Kalle",
    "wof:placetype":"locality"
},
  "geometry": {"coordinates":[71.97188,34.27655],"type":"Point"}
}