{
  "type": "Feature",
  "properties": {
    "gn:admin1_code":"02",
    "gn:asciiname":"Kolpur",
    "gn:country_code":"PK",
    "gn:dem":1843,
    "gn:feature_class":"P",
    "gn:feature_code":"PPL",
    "gn:name":"Kolpur",
    "gn:population":0,
    "gn:timezone":"Asia/Karachi",
    "iso:country":"PK",
    "name:und_x_variant":[
        "Kolepur",
        "Kolpur Bazar",
        "Kolpur"
    ],
    "wof:name":"Kolpur",
    "wof:placetype":"locality"
},
  "geometry": {"coordinates":[67.13313000000001,29.90321],"type":"Point"}
}