{
  "type": "Feature",
  "properties": {
    "gn:admin1_code":"5",
    "gn:asciiname":"Goth Sulaiman Kalhoro",
    "gn:country_code":"PK",
    "gn:dem":57,
    "gn:feature_class":"P",
    "gn:feature_code":"PPL",
    "gn:name":"Goth Sulaiman Kalhoro",
    "gn:population":0,
    "gn:timezone":"Asia/Karachi",
    "iso:country":"PK",
    "name:und_x_variant":[
        "Sulaim\u0101n Kalhora"
    ],
    "wof:name":"Goth Sulaiman Kalhoro",
    "wof:placetype":"locality"
},
  "geometry": {"coordinates":[68.2599,27.30015],"type":"Point"}
}