{
  "type": "Feature",
  "properties": {
    "gn:admin1_code":"4.0",
    "gn:asciiname":"Bira Rind",
    "gn:country_code":"PK",
    "gn:dem":902,
    "gn:feature_class":"P",
    "gn:feature_code":"PPL",
    "gn:name":"Bira Rind",
    "gn:population":0,
    "gn:timezone":"Asia/Karachi",
    "iso:country":"PK",
    "wof:name":"Bira Rind",
    "wof:placetype":"locality"
},
  "geometry": {"coordinates":[70.14061,30.47968],"type":"Point"}
}