{
  "type": "Feature",
  "properties": {
    "gn:admin1_code":"4.0",
    "gn:asciiname":"Chak Two Hundred Seventeen Gugera Branch",
    "gn:country_code":"PK",
    "gn:dem":172,
    "gn:feature_class":"P",
    "gn:feature_code":"PPL",
    "gn:name":"Chak Two Hundred Seventeen Gugera Branch",
    "gn:population":0,
    "gn:timezone":"Asia/Karachi",
    "iso:country":"PK",
    "name:und_x_variant":[
        "G\u016bjar Pind",
        "Gujarpind"
    ],
    "wof:name":"Chak Two Hundred Seventeen Gugera Branch",
    "wof:placetype":"locality"
},
  "geometry": {"coordinates":[72.86152,31.01678],"type":"Point"}
}