{
  "type": "Feature",
  "properties": {
    "gn:admin1_code":"4.0",
    "gn:asciiname":"Kalhagli",
    "gn:country_code":"PK",
    "gn:dem":193,
    "gn:feature_class":"P",
    "gn:feature_code":"PPL",
    "gn:name":"Kalhagli",
    "gn:population":0,
    "gn:timezone":"Asia/Karachi",
    "iso:country":"PK",
    "name:und_x_variant":[
        "Khagli"
    ],
    "wof:name":"Kalhagli",
    "wof:placetype":"locality"
},
  "geometry": {"coordinates":[71.99290999999999,32.25163],"type":"Point"}
}