{
  "type": "Feature",
  "properties": {
    "gn:admin1_code":"5.0",
    "gn:asciiname":"Wand",
    "gn:country_code":"PK",
    "gn:dem":49,
    "gn:feature_class":"P",
    "gn:feature_code":"PPL",
    "gn:name":"Wand",
    "gn:population":0,
    "gn:timezone":"Asia/Karachi",
    "iso:country":"PK",
    "name:bre_x_preferred":[
        "Gwialenn hud"
    ],
    "name:cat_x_preferred":[
        "Vareta m\u00e0gica"
    ],
    "name:dan_x_preferred":[
        "Tryllestav"
    ],
    "name:deu_x_preferred":[
        "Zauberstab"
    ],
    "name:epo_x_preferred":[
        "Sor\u0109bastono"
    ],
    "name:fin_x_preferred":[
        "Taikasauva"
    ],
    "name:fra_x_preferred":[
        "Baguette magique"
    ],
    "name:fry_x_preferred":[
        "Toverst\u00eaf"
    ],
    "name:heb_x_preferred":[
        "\u05de\u05d8\u05d4 \u05e7\u05e1\u05dd"
    ],
    "name:hrv_x_preferred":[
        "\u010carobni \u0161tap"
    ],
    "name:ita_x_preferred":[
        "Bacchetta magica"
    ],
    "name:kor_x_preferred":[
        "\ub9c8\ubc95 \uc9c0\ud321\uc774"
    ],
    "name:nld_x_preferred":[
        "Toverstaf"
    ],
    "name:nno_x_preferred":[
        "Tryllestav"
    ],
    "name:pol_x_preferred":[
        "R\u00f3\u017cd\u017cka"
    ],
    "name:por_x_preferred":[
        "Varinha m\u00e1gica"
    ],
    "name:rus_x_preferred":[
        "\u0412\u043e\u043b\u0448\u0435\u0431\u043d\u0430\u044f \u043f\u0430\u043b\u043e\u0447\u043a\u0430"
    ],
    "name:slv_x_preferred":[
        "\u010carobna palica"
    ],
    "name:spa_x_preferred":[
        "Varita m\u00e1gica"
    ],
    "name:swe_x_preferred":[
        "Trollstav"
    ],
    "name:tha_x_preferred":[
        "\u0e44\u0e21\u0e49\u0e01\u0e32\u0e22\u0e2a\u0e34\u0e17\u0e18\u0e34\u0e4c"
    ],
    "name:ukr_x_preferred":[
        "\u0427\u0430\u0440\u0456\u0432\u043d\u0430 \u043f\u0430\u043b\u0438\u0447\u043a\u0430"
    ],
    "wof:name":"Wand",
    "wof:placetype":"locality"
},
  "geometry": {"coordinates":[67.88955,27.65344],"type":"Point"}
}