{
  "type": "Feature",
  "properties": {
    "gn:admin1_code":"4",
    "gn:asciiname":"Kumaranwali",
    "gn:country_code":"PK",
    "gn:dem":598,
    "gn:feature_class":"P",
    "gn:feature_code":"PPL",
    "gn:name":"Kum\u0101r\u0101nw\u0101li",
    "gn:population":0,
    "gn:timezone":"Asia/Karachi",
    "iso:country":"PK",
    "name:fas_x_preferred":[
        "\u06a9\u0645\u0627\u0631\u0627\u0646 \u0648\u0627\u0644\u06cc"
    ],
    "name:urd_x_preferred":[
        "\u06a9\u0645\u0627\u0631\u0627\u06ba \u0648\u0627\u0644\u06cc"
    ],
    "wof:name":"Kumaranwali",
    "wof:placetype":"locality"
},
  "geometry": {"coordinates":[71.95278,32.45833],"type":"Point"}
}