{
  "type": "Feature",
  "properties": {
    "gn:admin1_code":"4",
    "gn:asciiname":"Kumaranwali",
    "gn:country_code":"PK",
    "gn:dem":598,
    "gn:feature_class":"P",
    "gn:feature_code":"PPL",
    "gn:name":"Kum\u0101r\u0101nw\u0101li",
    "gn:population":0,
    "gn:timezone":"Asia/Karachi",
    "iso:country":"PK",
    "wof:name":"Kumaranwali",
    "wof:placetype":"locality"
},
  "geometry": {"coordinates":[71.95278,32.45833],"type":"Point"}
}