{
  "type": "Feature",
  "properties": {
    "gn:admin1_code":"3.0",
    "gn:asciiname":"Girokhwarkotai",
    "gn:country_code":"PK",
    "gn:dem":2046,
    "gn:feature_class":"P",
    "gn:feature_code":"PPL",
    "gn:name":"Girokhwarkotai",
    "gn:population":0,
    "gn:timezone":"Asia/Karachi",
    "iso:country":"PK",
    "name:eng_x_preferred":[
        "Girokhwarkotai"
    ],
    "wof:name":"Girokhwarkotai",
    "wof:placetype":"locality"
},
  "geometry": {"coordinates":[71.88625999999999,35.24694],"type":"Point"}
}