{
  "type": "Feature",
  "properties": {
    "gn:admin1_code":"2.0",
    "gn:asciiname":"Ziaba Kili",
    "gn:country_code":"PK",
    "gn:dem":1839,
    "gn:feature_class":"P",
    "gn:feature_code":"PPL",
    "gn:name":"Ziaba Kili",
    "gn:population":0,
    "gn:timezone":"Asia/Karachi",
    "iso:country":"PK",
    "wof:name":"Ziaba Kili",
    "wof:placetype":"locality"
},
  "geometry": {"coordinates":[68.73730999999999,31.08169],"type":"Point"}
}