{
  "type": "Feature",
  "properties": {
    "gn:admin1_code":"4",
    "gn:asciiname":"Basti Loharani",
    "gn:country_code":"PK",
    "gn:dem":113,
    "gn:feature_class":"P",
    "gn:feature_code":"PPL",
    "gn:name":"Basti Loharani",
    "gn:population":0,
    "gn:timezone":"Asia/Karachi",
    "iso:country":"PK",
    "name:eng_x_preferred":[
        "Basti Loh\u0101r\u0101ni"
    ],
    "name:und_x_variant":[
        "Basti Muhammad M\u0101ri"
    ],
    "wof:name":"Basti Loharani",
    "wof:placetype":"locality"
},
  "geometry": {"coordinates":[70.49325999999998,29.80702],"type":"Point"}
}