{
  "type": "Feature",
  "properties": {
    "gn:admin1_code":"4",
    "gn:asciiname":"Basti Mastoi",
    "gn:country_code":"PK",
    "gn:dem":113,
    "gn:feature_class":"P",
    "gn:feature_code":"PPL",
    "gn:name":"Basti Mastoi",
    "gn:population":0,
    "gn:timezone":"Asia/Karachi",
    "iso:country":"PK",
    "wof:name":"Basti Mastoi",
    "wof:placetype":"locality"
},
  "geometry": {"coordinates":[70.8704,29.80022],"type":"Point"}
}