{
  "type": "Feature",
  "properties": {
    "gn:admin1_code":"4.0",
    "gn:asciiname":"Dhok Dulewali",
    "gn:country_code":"PK",
    "gn:dem":377,
    "gn:feature_class":"P",
    "gn:feature_code":"PPL",
    "gn:name":"Dhok Dulewali",
    "gn:population":0,
    "gn:timezone":"Asia/Karachi",
    "iso:country":"PK",
    "name:und_x_variant":[
        "D\u016blew\u0101li"
    ],
    "wof:name":"Dhok Dulewali",
    "wof:placetype":"locality"
},
  "geometry": {"coordinates":[71.96822,32.95453],"type":"Point"}
}