{
  "type": "Feature",
  "properties": {
    "gn:admin1_code":"5",
    "gn:asciiname":"Ali Bakhsh Dars",
    "gn:country_code":"PK",
    "gn:dem":13,
    "gn:feature_class":"P",
    "gn:feature_code":"PPL",
    "gn:name":"Ali Bakhsh Dars",
    "gn:population":0,
    "gn:timezone":"Asia/Karachi",
    "iso:country":"PK",
    "wof:name":"Ali Bakhsh Dars",
    "wof:placetype":"locality"
},
  "geometry": {"coordinates":[69.30795000000001,25.79683],"type":"Point"}
}