{
  "type": "Feature",
  "properties": {
    "gn:admin1_code":"4.0",
    "gn:asciiname":"Basti Ahmadpur",
    "gn:country_code":"PK",
    "gn:dem":160,
    "gn:feature_class":"P",
    "gn:feature_code":"PPL",
    "gn:name":"Basti Ahmadpur",
    "gn:population":0,
    "gn:timezone":"Asia/Karachi",
    "iso:country":"PK",
    "wof:name":"Basti Ahmadpur",
    "wof:placetype":"locality"
},
  "geometry": {"coordinates":[73.05555,29.84407],"type":"Point"}
}