{
  "type": "Feature",
  "properties": {
    "gn:admin1_code":"4.0",
    "gn:asciiname":"Chak One Hundred Twenty - Six Right",
    "gn:country_code":"PK",
    "gn:dem":157,
    "gn:feature_class":"P",
    "gn:feature_code":"PPL",
    "gn:name":"Chak One Hundred Twenty - Six Right",
    "gn:population":0,
    "gn:timezone":"Asia/Karachi",
    "iso:country":"PK",
    "name:und_x_variant":[
        "Madni Colony"
    ],
    "wof:name":"Chak One Hundred Twenty - Six Right",
    "wof:placetype":"locality"
},
  "geometry": {"coordinates":[73.02866999999998,29.44747000000001],"type":"Point"}
}