{
  "type": "Feature",
  "properties": {
    "gn:admin1_code":"2.0",
    "gn:asciiname":"Dari Mal Check Post",
    "gn:country_code":"PK",
    "gn:dem":266,
    "gn:feature_class":"P",
    "gn:feature_code":"PPL",
    "gn:name":"Dari Mal Check Post",
    "gn:population":0,
    "gn:timezone":"Asia/Karachi",
    "iso:country":"PK",
    "name:und_x_variant":[
        "D\u0101ri Mal"
    ],
    "wof:name":"Dari Mal Check Post",
    "wof:placetype":"locality"
},
  "geometry": {"coordinates":[65.74649000000001,26.17318],"type":"Point"}
}