{
  "type": "Feature",
  "properties": {
    "gn:admin1_code":"05",
    "gn:asciiname":"Goth Habibullah Shah",
    "gn:country_code":"PK",
    "gn:dem":21,
    "gn:feature_class":"P",
    "gn:feature_code":"PPL",
    "gn:name":"Goth Habibullah Shah",
    "gn:population":0,
    "gn:timezone":"Asia/Karachi",
    "iso:country":"PK",
    "name:und_x_variant":[
        "Mangr\u0101ri"
    ],
    "wof:name":"Goth Habibullah Shah",
    "wof:placetype":"locality"
},
  "geometry": {"coordinates":[68.86481999999999,25.84852],"type":"Point"}
}