{
  "type": "Feature",
  "properties": {
    "gn:admin1_code":"4.0",
    "gn:asciiname":"Ghalo More",
    "gn:country_code":"PK",
    "gn:dem":137,
    "gn:feature_class":"P",
    "gn:feature_code":"PPL",
    "gn:name":"Ghalo More",
    "gn:population":0,
    "gn:timezone":"Asia/Karachi",
    "iso:country":"PK",
    "wof:name":"Ghalo More",
    "wof:placetype":"locality"
},
  "geometry": {"coordinates":[71.06428000000002,30.65636],"type":"Point"}
}