{
  "type": "Feature",
  "properties": {
    "gn:admin1_code":"3.0",
    "gn:asciiname":"Ghao",
    "gn:country_code":"PK",
    "gn:dem":1181,
    "gn:feature_class":"P",
    "gn:feature_code":"PPL",
    "gn:name":"Ghao",
    "gn:population":0,
    "gn:timezone":"Asia/Karachi",
    "iso:country":"PK",
    "wof:name":"Ghao",
    "wof:placetype":"locality"
},
  "geometry": {"coordinates":[73.39904,35.4894],"type":"Point"}
}