{
  "type": "Feature",
  "properties": {
    "gn:admin1_code":"5",
    "gn:asciiname":"Muhammad Siddia Sudhro",
    "gn:country_code":"PK",
    "gn:dem":50,
    "gn:feature_class":"P",
    "gn:feature_code":"PPL",
    "gn:name":"Muhammad Siddia Sudhro",
    "gn:population":0,
    "gn:timezone":"Asia/Karachi",
    "iso:country":"PK",
    "name:und_x_variant":[
        "Sodro"
    ],
    "wof:name":"Muhammad Siddia Sudhro",
    "wof:placetype":"locality"
},
  "geometry": {"coordinates":[68.65075,27.1619],"type":"Point"}
}