{
  "type": "Feature",
  "properties": {
    "gn:admin1_code":"04",
    "gn:asciiname":"Chak Four Hundred Seventy-seven Gugera Branch",
    "gn:country_code":"PK",
    "gn:dem":169,
    "gn:feature_class":"P",
    "gn:feature_code":"PPL",
    "gn:name":"Chak Four Hundred Seventy-seven Gugera Branch",
    "gn:population":0,
    "gn:timezone":"Asia/Karachi",
    "iso:country":"PK",
    "name:und_x_variant":[
        "Kot",
        "Kot Umra",
        "Chak Four Hundred Seventy-seven Gugera Branch"
    ],
    "wof:name":"Chak Four Hundred Seventy-seven Gugera Branch",
    "wof:placetype":"locality"
},
  "geometry": {"coordinates":[72.87383,30.97098],"type":"Point"}
}