{
  "type": "Feature",
  "properties": {
    "gn:admin1_code":"4.0",
    "gn:asciiname":"Chheppa",
    "gn:country_code":"PK",
    "gn:dem":128,
    "gn:feature_class":"P",
    "gn:feature_code":"PPL",
    "gn:name":"Chheppa",
    "gn:population":0,
    "gn:timezone":"Asia/Karachi",
    "iso:country":"PK",
    "wof:name":"Chheppa",
    "wof:placetype":"locality"
},
  "geometry": {"coordinates":[71.10429000000001,30.19923],"type":"Point"}
}