{
  "type": "Feature",
  "properties": {
    "gn:admin1_code":"3",
    "gn:asciiname":"Sukai",
    "gn:country_code":"PK",
    "gn:dem":1585,
    "gn:feature_class":"P",
    "gn:feature_code":"PPL",
    "gn:name":"Sukai",
    "gn:population":0,
    "gn:timezone":"Asia/Karachi",
    "iso:country":"PK",
    "name:eng_x_preferred":[
        "Tsukai"
    ],
    "wof:name":"Sukai",
    "wof:placetype":"locality"
},
  "geometry": {"coordinates":[71.74325999999998,35.10839],"type":"Point"}
}