{
  "type": "Feature",
  "properties": {
    "gn:admin1_code":"3",
    "gn:asciiname":"Chanjlo Banda",
    "gn:country_code":"PK",
    "gn:dem":1202,
    "gn:feature_class":"P",
    "gn:feature_code":"PPL",
    "gn:name":"Chanjlo Banda",
    "gn:population":0,
    "gn:timezone":"Asia/Karachi",
    "iso:country":"PK",
    "wof:name":"Chanjlo Banda",
    "wof:placetype":"locality"
},
  "geometry": {"coordinates":[72.7824,34.35682],"type":"Point"}
}