{
  "type": "Feature",
  "properties": {
    "gn:admin1_code":"3",
    "gn:asciiname":"Las",
    "gn:country_code":"PK",
    "gn:dem":1448,
    "gn:feature_class":"P",
    "gn:feature_code":"PPL",
    "gn:name":"Las",
    "gn:population":0,
    "gn:timezone":"Asia/Karachi",
    "iso:country":"PK",
    "wof:name":"Las",
    "wof:placetype":"locality"
},
  "geometry": {"coordinates":[72.98241,34.39569],"type":"Point"}
}