{
  "type": "Feature",
  "properties": {
    "gn:admin1_code":"3",
    "gn:asciiname":"Khakhu",
    "gn:country_code":"PK",
    "gn:dem":1478,
    "gn:feature_class":"P",
    "gn:feature_code":"PPL",
    "gn:name":"Khakhu",
    "gn:population":0,
    "gn:timezone":"Asia/Karachi",
    "iso:country":"PK",
    "name:und_x_variant":[
        "Khaku"
    ],
    "wof:name":"Khakhu",
    "wof:placetype":"locality"
},
  "geometry": {"coordinates":[73.12595,34.57145999999999],"type":"Point"}
}