{
  "type": "Feature",
  "properties": {
    "gn:admin1_code":"4",
    "gn:asciiname":"Ganeshpur",
    "gn:country_code":"PK",
    "gn:dem":199,
    "gn:feature_class":"P",
    "gn:feature_code":"PPL",
    "gn:name":"Ganeshpur",
    "gn:population":0,
    "gn:timezone":"Asia/Karachi",
    "iso:country":"PK",
    "name:ceb_x_preferred":[
        "Ganeshpur"
    ],
    "name:nep_x_preferred":[
        "\u0917\u0923\u0947\u0936\u092a\u0941\u0930"
    ],
    "name:pol_x_preferred":[
        "Ganeshpur"
    ],
    "wof:name":"Ganeshpur",
    "wof:placetype":"locality"
},
  "geometry": {"coordinates":[73.98090000000001,31.35851],"type":"Point"}
}