{
  "type": "Feature",
  "properties": {
    "gn:admin1_code":"4",
    "gn:asciiname":"Baghwala",
    "gn:country_code":"PK",
    "gn:dem":121,
    "gn:feature_class":"P",
    "gn:feature_code":"PPL",
    "gn:name":"Baghwala",
    "gn:population":0,
    "gn:timezone":"Asia/Karachi",
    "iso:country":"PK",
    "name:und_x_variant":[
        "B\u0101gew\u0101la"
    ],
    "wof:name":"Baghwala",
    "wof:placetype":"locality"
},
  "geometry": {"coordinates":[70.64303000000002,30.11722],"type":"Point"}
}