{
  "type": "Feature",
  "properties": {
    "gn:admin1_code":"4",
    "gn:asciiname":"Khu Duttewala",
    "gn:country_code":"PK",
    "gn:dem":132,
    "gn:feature_class":"P",
    "gn:feature_code":"PPL",
    "gn:name":"Khu Duttewala",
    "gn:population":0,
    "gn:timezone":"Asia/Karachi",
    "iso:country":"PK",
    "name:eng_x_preferred":[
        "J\u012btew\u0101la"
    ],
    "wof:name":"Khu Duttewala",
    "wof:placetype":"locality"
},
  "geometry": {"coordinates":[70.72447,30.34075],"type":"Point"}
}