{
  "type": "Feature",
  "properties": {
    "gn:admin1_code":"4.0",
    "gn:asciiname":"Gungewali Dhok",
    "gn:country_code":"PK",
    "gn:dem":617,
    "gn:feature_class":"P",
    "gn:feature_code":"PPL",
    "gn:name":"Gungewali Dhok",
    "gn:population":0,
    "gn:timezone":"Asia/Karachi",
    "iso:country":"PK",
    "wof:name":"Gungewali Dhok",
    "wof:placetype":"locality"
},
  "geometry": {"coordinates":[72.39841,32.80075],"type":"Point"}
}