{
  "type": "Feature",
  "properties": {
    "gn:admin1_code":"05",
    "gn:asciiname":"Goth Suharo Bhatti",
    "gn:country_code":"PK",
    "gn:dem":52,
    "gn:feature_class":"P",
    "gn:feature_code":"PPL",
    "gn:name":"Goth Suharo Bhatti",
    "gn:population":0,
    "gn:timezone":"Asia/Karachi",
    "iso:country":"PK",
    "name:und_x_variant":[
        "Suharo Bhati",
        "Suhanro Bhatti",
        "Goth Suharo Bhatti",
        "Suh\u0101ro Bhatti"
    ],
    "wof:name":"Goth Suharo Bhatti",
    "wof:placetype":"locality"
},
  "geometry": {"coordinates":[68.10321999999999,27.85731],"type":"Point"}
}