{
  "type": "Feature",
  "properties": {
    "gn:admin1_code":"04",
    "gn:asciiname":"Nurpur Katwi",
    "gn:country_code":"PK",
    "gn:dem":199,
    "gn:feature_class":"P",
    "gn:feature_code":"PPL",
    "gn:name":"Nurpur Katwi",
    "gn:population":0,
    "gn:timezone":"Asia/Karachi",
    "iso:country":"PK",
    "name:und_x_variant":[
        "Noorpur Katri",
        "N\u016brpur",
        "Nurpur Katwi"
    ],
    "wof:name":"Nurpur Katwi",
    "wof:placetype":"locality"
},
  "geometry": {"coordinates":[73.39372,32.2348],"type":"Point"}
}