{
  "type": "Feature",
  "properties": {
    "gn:admin1_code":"5.0",
    "gn:asciiname":"Allahno Mandhro",
    "gn:country_code":"PK",
    "gn:dem":5,
    "gn:feature_class":"P",
    "gn:feature_code":"PPL",
    "gn:name":"Allahno Mandhro",
    "gn:population":0,
    "gn:timezone":"Asia/Karachi",
    "iso:country":"PK",
    "wof:name":"Allahno Mandhro",
    "wof:placetype":"locality"
},
  "geometry": {"coordinates":[68.76648,24.45967000000001],"type":"Point"}
}