{
  "type": "Feature",
  "properties": {
    "gn:admin1_code":"4.0",
    "gn:asciiname":"Santh Anwali",
    "gn:country_code":"PK",
    "gn:dem":1361,
    "gn:feature_class":"P",
    "gn:feature_code":"PPL",
    "gn:name":"Santh Anwali",
    "gn:population":0,
    "gn:timezone":"Asia/Karachi",
    "iso:country":"PK",
    "wof:name":"Santh Anwali",
    "wof:placetype":"locality"
},
  "geometry": {"coordinates":[73.54108000000002,33.85809],"type":"Point"}
}