{
  "type": "Feature",
  "properties": {
    "gn:admin1_code":"4",
    "gn:asciiname":"Basti Khyber",
    "gn:country_code":"PK",
    "gn:dem":159,
    "gn:feature_class":"P",
    "gn:feature_code":"PPL",
    "gn:name":"Basti Khyber",
    "gn:population":0,
    "gn:timezone":"Asia/Karachi",
    "iso:country":"PK",
    "name:und_x_variant":[
        "Khyber"
    ],
    "wof:name":"Basti Khyber",
    "wof:placetype":"locality"
},
  "geometry": {"coordinates":[70.9105,31.41275],"type":"Point"}
}