{
  "type": "Feature",
  "properties": {
    "gn:admin1_code":"2.0",
    "gn:asciiname":"Abdakai Bala",
    "gn:country_code":"PK",
    "gn:dem":2175,
    "gn:feature_class":"P",
    "gn:feature_code":"PPL",
    "gn:name":"Abdakai Bala",
    "gn:population":0,
    "gn:timezone":"Asia/Karachi",
    "iso:country":"PK",
    "name:eng_x_preferred":[
        "Abdakai Bala"
    ],
    "wof:name":"Abdakai Bala",
    "wof:placetype":"locality"
},
  "geometry": {"coordinates":[67.38215,30.88628],"type":"Point"}
}