{
  "type": "Feature",
  "properties": {
    "gn:admin1_code":"4",
    "gn:asciiname":"Yara Mangreja",
    "gn:country_code":"PK",
    "gn:dem":108,
    "gn:feature_class":"P",
    "gn:feature_code":"PPL",
    "gn:name":"Yara Mangreja",
    "gn:population":0,
    "gn:timezone":"Asia/Karachi",
    "iso:country":"PK",
    "wof:name":"Yara Mangreja",
    "wof:placetype":"locality"
},
  "geometry": {"coordinates":[70.30278,29.29722000000001],"type":"Point"}
}