{
  "type": "Feature",
  "properties": {
    "gn:admin1_code":"3",
    "gn:asciiname":"Shimbal Bandi",
    "gn:country_code":"PK",
    "gn:dem":1041,
    "gn:feature_class":"P",
    "gn:feature_code":"PPL",
    "gn:name":"Shimbal Bandi",
    "gn:population":0,
    "gn:timezone":"Asia/Karachi",
    "iso:country":"PK",
    "name:und_x_variant":[
        "Shambal B\u0101nda"
    ],
    "wof:name":"Shimbal Bandi",
    "wof:placetype":"locality"
},
  "geometry": {"coordinates":[72.88448000000002,34.29783],"type":"Point"}
}