{
  "type": "Feature",
  "properties": {
    "gn:admin1_code":"2.0",
    "gn:asciiname":"Shingar",
    "gn:country_code":"PK",
    "gn:dem":1388,
    "gn:feature_class":"P",
    "gn:feature_code":"PPL",
    "gn:name":"Shingar",
    "gn:population":0,
    "gn:timezone":"Asia/Karachi",
    "iso:country":"PK",
    "name:und_x_variant":[
        "Q\u0101dir\u0101b\u0101d"
    ],
    "wof:name":"Shingar",
    "wof:placetype":"locality"
},
  "geometry": {"coordinates":[65.50798,27.4749],"type":"Point"}
}