{
  "type": "Feature",
  "properties": {
    "gn:admin1_code":"4.0",
    "gn:asciiname":"Chak Eighty-six D",
    "gn:country_code":"PK",
    "gn:dem":161,
    "gn:feature_class":"P",
    "gn:feature_code":"PPL",
    "gn:name":"Chak Eighty-six D",
    "gn:population":0,
    "gn:timezone":"Asia/Karachi",
    "iso:country":"PK",
    "name:und_x_variant":[
        "Baloch\u0101nw\u0101la"
    ],
    "wof:name":"Chak Eighty-six D",
    "wof:placetype":"locality"
},
  "geometry": {"coordinates":[73.18539,30.522],"type":"Point"}
}