{
  "type": "Feature",
  "properties": {
    "gn:admin1_code":"3.0",
    "gn:asciiname":"Arif Shah Khel",
    "gn:country_code":"PK",
    "gn:dem":553,
    "gn:feature_class":"P",
    "gn:feature_code":"PPL",
    "gn:name":"Arif Shah Khel",
    "gn:population":0,
    "gn:timezone":"Asia/Karachi",
    "iso:country":"PK",
    "name:und_x_variant":[
        "Arif Sh\u0101h Khel"
    ],
    "wof:name":"Arif Shah Khel",
    "wof:placetype":"locality"
},
  "geometry": {"coordinates":[71.51725,33.6113],"type":"Point"}
}