{
  "type": "Feature",
  "properties": {
    "gn:admin1_code":"3.0",
    "gn:asciiname":"Azizabad",
    "gn:country_code":"PK",
    "gn:dem":303,
    "gn:feature_class":"P",
    "gn:feature_code":"PPL",
    "gn:name":"Azizabad",
    "gn:population":0,
    "gn:timezone":"Asia/Karachi",
    "iso:country":"PK",
    "name:eng_x_preferred":[
        "Azizabad"
    ],
    "wof:name":"Azizabad",
    "wof:placetype":"locality"
},
  "geometry": {"coordinates":[71.86865,34.12574],"type":"Point"}
}