{
  "type": "Feature",
  "properties": {
    "gn:admin1_code":"3.0",
    "gn:asciiname":"Usorai",
    "gn:country_code":"PK",
    "gn:dem":1401,
    "gn:feature_class":"P",
    "gn:feature_code":"PPL",
    "gn:name":"Usorai",
    "gn:population":0,
    "gn:timezone":"Asia/Karachi",
    "iso:country":"PK",
    "name:und_x_variant":[
        "Usar\u0101i"
    ],
    "wof:name":"Usorai",
    "wof:placetype":"locality"
},
  "geometry": {"coordinates":[72.04386,35.05205],"type":"Point"}
}