{
  "type": "Feature",
  "properties": {
    "gn:admin1_code":"2",
    "gn:asciiname":"Aghbargai",
    "gn:country_code":"PK",
    "gn:dem":1984,
    "gn:feature_class":"P",
    "gn:feature_code":"PPL",
    "gn:name":"Aghbargai",
    "gn:population":0,
    "gn:timezone":"Asia/Karachi",
    "iso:country":"PK",
    "wof:name":"Aghbargai",
    "wof:placetype":"locality"
},
  "geometry": {"coordinates":[68.05539,30.94477],"type":"Point"}
}