{
  "type": "Feature",
  "properties": {
    "gn:admin1_code":"2.0",
    "gn:asciiname":"Halq Gudri",
    "gn:country_code":"PK",
    "gn:dem":722,
    "gn:feature_class":"P",
    "gn:feature_code":"PPL",
    "gn:name":"Halq Gudri",
    "gn:population":0,
    "gn:timezone":"Asia/Karachi",
    "iso:country":"PK",
    "wof:name":"Halq Gudri",
    "wof:placetype":"locality"
},
  "geometry": {"coordinates":[64.29318000000001,26.33598],"type":"Point"}
}