{
  "type": "Feature",
  "properties": {
    "gn:admin1_code":"5.0",
    "gn:asciiname":"Goth Bagh Mehr",
    "gn:country_code":"PK",
    "gn:dem":55,
    "gn:feature_class":"P",
    "gn:feature_code":"PPL",
    "gn:name":"Goth Bagh Mehr",
    "gn:population":0,
    "gn:timezone":"Asia/Karachi",
    "iso:country":"PK",
    "name:eng_x_preferred":[
        "Goth Bagh Meher"
    ],
    "wof:name":"Goth Bagh Mehr",
    "wof:placetype":"locality"
},
  "geometry": {"coordinates":[68.5493,27.36731],"type":"Point"}
}