{
  "type": "Feature",
  "properties": {
    "gn:admin1_code":"3",
    "gn:asciiname":"Lidi",
    "gn:country_code":"PK",
    "gn:dem":1959,
    "gn:feature_class":"P",
    "gn:feature_code":"PPL",
    "gn:name":"Lidi",
    "gn:population":0,
    "gn:timezone":"Asia/Karachi",
    "iso:country":"PK",
    "name:und_x_variant":[
        "Ledi"
    ],
    "wof:name":"Lidi",
    "wof:placetype":"locality"
},
  "geometry": {"coordinates":[73.31368000000001,34.58493],"type":"Point"}
}