{
  "type": "Feature",
  "properties": {
    "gn:admin1_code":"3.0",
    "gn:asciiname":"Aspar",
    "gn:country_code":"PK",
    "gn:dem":1872,
    "gn:feature_class":"P",
    "gn:feature_code":"PPL",
    "gn:name":"Aspar",
    "gn:population":0,
    "gn:timezone":"Asia/Karachi",
    "iso:country":"PK",
    "name:eng_x_preferred":[
        "Aspar"
    ],
    "wof:name":"Aspar",
    "wof:placetype":"locality"
},
  "geometry": {"coordinates":[71.69959,35.64544],"type":"Point"}
}