{
  "type": "Feature",
  "properties": {
    "gn:admin1_code":"3.0",
    "gn:asciiname":"Dowsair",
    "gn:country_code":"PK",
    "gn:dem":2712,
    "gn:feature_class":"P",
    "gn:feature_code":"PPL",
    "gn:name":"Dowsair",
    "gn:population":0,
    "gn:timezone":"Asia/Karachi",
    "iso:country":"PK",
    "name:und_x_variant":[
        "Dirsir"
    ],
    "wof:name":"Dowsair",
    "wof:placetype":"locality"
},
  "geometry": {"coordinates":[72.84350999999999,36.57706],"type":"Point"}
}