{
  "type": "Feature",
  "properties": {
    "gn:admin1_code":"4",
    "gn:asciiname":"Chak Eighty-nine Desert Branch",
    "gn:country_code":"PK",
    "gn:dem":118,
    "gn:feature_class":"P",
    "gn:feature_code":"PPL",
    "gn:name":"Chak Eighty-nine Desert Branch",
    "gn:population":0,
    "gn:timezone":"Asia/Karachi",
    "iso:country":"PK",
    "name:und_x_variant":[
        "Chak Eigthy-nine D B"
    ],
    "wof:name":"Chak Eighty-nine Desert Branch",
    "wof:placetype":"locality"
},
  "geometry": {"coordinates":[71.76734999999999,29.09396],"type":"Point"}
}