{
  "type": "Feature",
  "properties": {
    "gn:admin1_code":"2.0",
    "gn:asciiname":"Habibubad",
    "gn:country_code":"PK",
    "gn:dem":1574,
    "gn:feature_class":"P",
    "gn:feature_code":"PPL",
    "gn:name":"Habibubad",
    "gn:population":0,
    "gn:timezone":"Asia/Karachi",
    "iso:country":"PK",
    "wof:name":"Habibubad",
    "wof:placetype":"locality"
},
  "geometry": {"coordinates":[66.31716999999999,28.11383],"type":"Point"}
}