{
  "type": "Feature",
  "properties": {
    "gn:admin1_code":"3.0",
    "gn:asciiname":"Sarangi Mumsh Khel",
    "gn:country_code":"PK",
    "gn:dem":405,
    "gn:feature_class":"P",
    "gn:feature_code":"PPL",
    "gn:name":"Sarangi Mumsh Khel",
    "gn:population":0,
    "gn:timezone":"Asia/Karachi",
    "iso:country":"PK",
    "name:und_x_variant":[
        "Sorang"
    ],
    "wof:name":"Sarangi Mumsh Khel",
    "wof:placetype":"locality"
},
  "geometry": {"coordinates":[70.57205999999999,33.0056],"type":"Point"}
}