{
  "type": "Feature",
  "properties": {
    "gn:admin1_code":"4.0",
    "gn:asciiname":"Basti Ruk",
    "gn:country_code":"PK",
    "gn:dem":131,
    "gn:feature_class":"P",
    "gn:feature_code":"PPL",
    "gn:name":"Basti Ruk",
    "gn:population":0,
    "gn:timezone":"Asia/Karachi",
    "iso:country":"PK",
    "name:eng_x_preferred":[
        "Basti Ruk"
    ],
    "name:eng_x_variant":[
        "Bet Ruk"
    ],
    "name:und_x_variant":[
        "Bet Ruk"
    ],
    "wof:name":"Basti Ruk",
    "wof:placetype":"locality"
},
  "geometry": {"coordinates":[70.88955,30.38779000000001],"type":"Point"}
}