{
  "type": "Feature",
  "properties": {
    "gn:admin1_code":"4.0",
    "gn:asciiname":"Ghauspur",
    "gn:country_code":"PK",
    "gn:dem":132,
    "gn:feature_class":"P",
    "gn:feature_code":"PPL",
    "gn:name":"Ghauspur",
    "gn:population":0,
    "gn:timezone":"Asia/Karachi",
    "iso:country":"PK",
    "name:eng_x_preferred":[
        "Ghauspur"
    ],
    "name:und_x_variant":[
        "Kund Azeem",
        "Kund Azim",
        "Ghauspur"
    ],
    "name:urd_x_preferred":[
        "\u063a\u0648\u062b \u067e\u0648\u0631"
    ],
    "wof:name":"Ghauspur",
    "wof:placetype":"locality"
},
  "geometry": {"coordinates":[72.21111999999999,29.72688],"type":"Point"}
}