{
  "type": "Feature",
  "properties": {
    "gn:admin1_code":"4.0",
    "gn:asciiname":"Dhok Sain Qurban",
    "gn:country_code":"PK",
    "gn:dem":373,
    "gn:feature_class":"P",
    "gn:feature_code":"PPL",
    "gn:name":"Dhok Sain Qurban",
    "gn:population":0,
    "gn:timezone":"Asia/Karachi",
    "iso:country":"PK",
    "wof:name":"Dhok Sain Qurban",
    "wof:placetype":"locality"
},
  "geometry": {"coordinates":[72.92024000000001,33.3197],"type":"Point"}
}