{
  "type": "Feature",
  "properties": {
    "gn:admin1_code":"03",
    "gn:asciiname":"Mahmoodabad",
    "gn:country_code":"PK",
    "gn:dem":323,
    "gn:feature_class":"P",
    "gn:feature_code":"PPL",
    "gn:name":"Mahmoodabad",
    "gn:population":0,
    "gn:timezone":"Asia/Karachi",
    "iso:country":"PK",
    "name:und_x_variant":[
        "Mahm\u016bd\u0101b\u0101d",
        "Mahmoodabad"
    ],
    "wof:name":"Mahmoodabad",
    "wof:placetype":"locality"
},
  "geometry": {"coordinates":[71.72468000000001,34.24773],"type":"Point"}
}