{
  "type": "Feature",
  "properties": {
    "gn:admin1_code":"4.0",
    "gn:asciiname":"Rehmanabad",
    "gn:country_code":"PK",
    "gn:dem":200,
    "gn:feature_class":"P",
    "gn:feature_code":"PPL",
    "gn:name":"Rehmanabad",
    "gn:population":0,
    "gn:timezone":"Asia/Karachi",
    "iso:country":"PK",
    "name:und_x_variant":[
        "Kot Arjun Singh",
        "Kot Arjan Singh"
    ],
    "name:urd_x_preferred":[
        "\u0631\u062d\u0645\u0646 \u0622\u0628\u0627\u062f"
    ],
    "wof:name":"Rehmanabad",
    "wof:placetype":"locality"
},
  "geometry": {"coordinates":[74.06528,31.0469],"type":"Point"}
}