{
  "type": "Feature",
  "properties": {
    "gn:admin1_code":"3",
    "gn:asciiname":"Chikar Baian Khurd",
    "gn:country_code":"PK",
    "gn:dem":750,
    "gn:feature_class":"P",
    "gn:feature_code":"PPL",
    "gn:name":"Chikar Baian Khurd",
    "gn:population":0,
    "gn:timezone":"Asia/Karachi",
    "iso:country":"PK",
    "name:und_x_variant":[
        "Chikar B\u0101hi\u0101n Khurd"
    ],
    "wof:name":"Chikar Baian Khurd",
    "wof:placetype":"locality"
},
  "geometry": {"coordinates":[73.0334,34.25808],"type":"Point"}
}