{
  "type": "Feature",
  "properties": {
    "gn:admin1_code":"4.0",
    "gn:asciiname":"Chakian",
    "gn:country_code":"PK",
    "gn:dem":271,
    "gn:feature_class":"P",
    "gn:feature_code":"PPL",
    "gn:name":"Chakian",
    "gn:population":0,
    "gn:timezone":"Asia/Karachi",
    "iso:country":"PK",
    "name:und_x_variant":[
        "Chukyam",
        "Chuki\u0101m",
        "Chakian"
    ],
    "wof:name":"Chakian",
    "wof:placetype":"locality"
},
  "geometry": {"coordinates":[73.51241999999998,32.94252],"type":"Point"}
}