{
  "type": "Feature",
  "properties": {
    "gn:admin1_code":"3",
    "gn:asciiname":"Bikanai",
    "gn:country_code":"PK",
    "gn:dem":1806,
    "gn:feature_class":"P",
    "gn:feature_code":"PPL",
    "gn:name":"Bikanai",
    "gn:population":0,
    "gn:timezone":"Asia/Karachi",
    "iso:country":"PK",
    "wof:name":"Bikanai",
    "wof:placetype":"locality"
},
  "geometry": {"coordinates":[72.99581999999999,34.89837],"type":"Point"}
}