{
  "type": "Feature",
  "properties": {
    "gn:admin1_code":"5.0",
    "gn:asciiname":"Photo Bhotani",
    "gn:country_code":"PK",
    "gn:dem":9,
    "gn:feature_class":"P",
    "gn:feature_code":"PPL",
    "gn:name":"Photo Bhotani",
    "gn:population":0,
    "gn:timezone":"Asia/Karachi",
    "iso:country":"PK",
    "wof:name":"Photo Bhotani",
    "wof:placetype":"locality"
},
  "geometry": {"coordinates":[68.17468000000001,24.57494],"type":"Point"}
}