{
  "type": "Feature",
  "properties": {
    "gn:admin1_code":"4",
    "gn:asciiname":"Sawar Shah",
    "gn:country_code":"PK",
    "gn:dem":117,
    "gn:feature_class":"P",
    "gn:feature_code":"PPL",
    "gn:name":"Sawar Shah",
    "gn:population":0,
    "gn:timezone":"Asia/Karachi",
    "iso:country":"PK",
    "name:und_x_variant":[
        "Sawar Sh\u0101b",
        "Basti Sohanre Sh\u0101hw\u0101li",
        "Sawar Shah"
    ],
    "wof:name":"Sawar Shah",
    "wof:placetype":"locality"
},
  "geometry": {"coordinates":[71.01980999999998,30.00113],"type":"Point"}
}