{
  "type": "Feature",
  "properties": {
    "gn:admin1_code":"4.0",
    "gn:asciiname":"Basti Jhalian",
    "gn:country_code":"PK",
    "gn:dem":90,
    "gn:feature_class":"P",
    "gn:feature_code":"PPL",
    "gn:name":"Basti Jhalian",
    "gn:population":0,
    "gn:timezone":"Asia/Karachi",
    "iso:country":"PK",
    "wof:name":"Basti Jhalian",
    "wof:placetype":"locality"
},
  "geometry": {"coordinates":[70.70045,28.71607],"type":"Point"}
}