{
  "type": "Feature",
  "properties": {
    "gn:admin1_code":"4",
    "gn:asciiname":"Chak Four Western Bar",
    "gn:country_code":"PK",
    "gn:dem":145,
    "gn:feature_class":"P",
    "gn:feature_code":"PPL",
    "gn:name":"Chak Four Western Bar",
    "gn:population":0,
    "gn:timezone":"Asia/Karachi",
    "iso:country":"PK",
    "name:und_x_variant":[
        "Chak Four WB"
    ],
    "wof:name":"Chak Four Western Bar",
    "wof:placetype":"locality"
},
  "geometry": {"coordinates":[72.50024999999999,30.13241],"type":"Point"}
}