{
  "type": "Feature",
  "properties": {
    "gn:admin1_code":"03",
    "gn:asciiname":"Rahimabad",
    "gn:country_code":"PK",
    "gn:dem":1080,
    "gn:feature_class":"P",
    "gn:feature_code":"PPL",
    "gn:name":"Rahimabad",
    "gn:population":0,
    "gn:timezone":"Asia/Karachi",
    "iso:country":"PK",
    "name:aze_x_preferred":[
        "R\u0259himabad"
    ],
    "name:eng_x_preferred":[
        "Nawe Kotai"
    ],
    "name:fas_x_preferred":[
        "\u0631\u062d\u06cc\u0645\u200c\u0622\u0628\u0627\u062f"
    ],
    "wof:name":"Rahimabad",
    "wof:placetype":"locality"
},
  "geometry": {"coordinates":[71.70535,34.9545],"type":"Point"}
}