{
  "type": "Feature",
  "properties": {
    "gn:admin1_code":"4",
    "gn:asciiname":"Kot Khudayar",
    "gn:country_code":"PK",
    "gn:dem":229,
    "gn:feature_class":"P",
    "gn:feature_code":"PPL",
    "gn:name":"Kot Khudayar",
    "gn:population":0,
    "gn:timezone":"Asia/Karachi",
    "iso:country":"PK",
    "name:und_x_variant":[
        "Kot Kh\u016bd\u0101y\u0101r"
    ],
    "wof:name":"Kot Khudayar",
    "wof:placetype":"locality"
},
  "geometry": {"coordinates":[74.23312,32.45932],"type":"Point"}
}