{
  "type": "Feature",
  "properties": {
    "gn:admin1_code":"5.0",
    "gn:asciiname":"Goth Muhammad Yusuf Rustamani",
    "gn:country_code":"PK",
    "gn:dem":1544,
    "gn:feature_class":"P",
    "gn:feature_code":"PPL",
    "gn:name":"Goth Muhammad Yusuf Rustamani",
    "gn:population":0,
    "gn:timezone":"Asia/Karachi",
    "iso:country":"PK",
    "wof:name":"Goth Muhammad Yusuf Rustamani",
    "wof:placetype":"locality"
},
  "geometry": {"coordinates":[67.18089999999999,27.20054],"type":"Point"}
}