{
  "type": "Feature",
  "properties": {
    "gn:admin1_code":"5",
    "gn:asciiname":"Goth Ali Bukhsh",
    "gn:country_code":"PK",
    "gn:dem":43,
    "gn:feature_class":"P",
    "gn:feature_code":"PPL",
    "gn:name":"Goth Ali Bukhsh",
    "gn:population":0,
    "gn:timezone":"Asia/Karachi",
    "iso:country":"PK",
    "name:und_x_variant":[
        "Goth Ali Bakhsh"
    ],
    "wof:name":"Goth Ali Bukhsh",
    "wof:placetype":"locality"
},
  "geometry": {"coordinates":[67.70610000000001,26.97056],"type":"Point"}
}