{
  "type": "Feature",
  "properties": {
    "gn:admin1_code":"1.0",
    "gn:asciiname":"Shahida Tala",
    "gn:country_code":"PK",
    "gn:dem":675,
    "gn:feature_class":"P",
    "gn:feature_code":"PPL",
    "gn:name":"Shahida Tala",
    "gn:population":0,
    "gn:timezone":"Asia/Karachi",
    "iso:country":"PK",
    "name:und_x_variant":[
        "Shah\u012bda Tal\u0101o"
    ],
    "wof:name":"Shahida Tala",
    "wof:placetype":"locality"
},
  "geometry": {"coordinates":[71.5444,33.6754],"type":"Point"}
}