{
  "type": "Feature",
  "properties": {
    "gn:admin1_code":"3",
    "gn:asciiname":"Tatogram",
    "gn:country_code":"PK",
    "gn:dem":1324,
    "gn:feature_class":"P",
    "gn:feature_code":"PPL",
    "gn:name":"Tatogram",
    "gn:population":0,
    "gn:timezone":"Asia/Karachi",
    "iso:country":"PK",
    "wof:name":"Tatogram",
    "wof:placetype":"locality"
},
  "geometry": {"coordinates":[72.05,34.9594],"type":"Point"}
}