{
  "type": "Feature",
  "properties": {
    "gn:admin1_code":"4.0",
    "gn:asciiname":"Khund",
    "gn:country_code":"PK",
    "gn:dem":1410,
    "gn:feature_class":"P",
    "gn:feature_code":"PPL",
    "gn:name":"Khund",
    "gn:population":0,
    "gn:timezone":"Asia/Karachi",
    "iso:country":"PK",
    "name:ita_x_preferred":[
        "Khund"
    ],
    "wof:name":"Khund",
    "wof:placetype":"locality"
},
  "geometry": {"coordinates":[70.17024000000001,30.40574],"type":"Point"}
}