{
  "type": "Feature",
  "properties": {
    "gn:admin1_code":"5",
    "gn:asciiname":"Goth Gahi Lakho",
    "gn:country_code":"PK",
    "gn:dem":29,
    "gn:feature_class":"P",
    "gn:feature_code":"PPL",
    "gn:name":"Goth Gahi Lakho",
    "gn:population":0,
    "gn:timezone":"Asia/Karachi",
    "iso:country":"PK",
    "name:eng_x_preferred":[
        "G\u0101hi L\u0101kho"
    ],
    "wof:name":"Goth Gahi Lakho",
    "wof:placetype":"locality"
},
  "geometry": {"coordinates":[68.43666999999999,25.77439],"type":"Point"}
}