{
  "type": "Feature",
  "properties": {
    "gn:admin1_code":"2.0",
    "gn:asciiname":"Chong Mengal",
    "gn:country_code":"PK",
    "gn:dem":1866,
    "gn:feature_class":"P",
    "gn:feature_code":"PPL",
    "gn:name":"Chong Mengal",
    "gn:population":0,
    "gn:timezone":"Asia/Karachi",
    "iso:country":"PK",
    "name:und_x_variant":[
        "Takri Moula Bakhsh"
    ],
    "wof:name":"Chong Mengal",
    "wof:placetype":"locality"
},
  "geometry": {"coordinates":[66.35316,28.94736],"type":"Point"}
}