{
  "type": "Feature",
  "properties": {
    "gn:admin1_code":"3.0",
    "gn:asciiname":"Wuz",
    "gn:country_code":"PK",
    "gn:dem":3161,
    "gn:feature_class":"P",
    "gn:feature_code":"PPL",
    "gn:name":"Wuz",
    "gn:population":0,
    "gn:timezone":"Asia/Karachi",
    "iso:country":"PK",
    "wof:name":"Wuz",
    "wof:placetype":"locality"
},
  "geometry": {"coordinates":[72.14985,36.29482],"type":"Point"}
}