{
  "type": "Feature",
  "properties": {
    "gn:admin1_code":"3",
    "gn:asciiname":"Gudi",
    "gn:country_code":"PK",
    "gn:dem":1283,
    "gn:feature_class":"P",
    "gn:feature_code":"PPL",
    "gn:name":"Gudi",
    "gn:population":0,
    "gn:timezone":"Asia/Karachi",
    "iso:country":"PK",
    "name:und_x_variant":[
        "Guddi"
    ],
    "wof:name":"Gudi",
    "wof:placetype":"locality"
},
  "geometry": {"coordinates":[73.41122,34.62544],"type":"Point"}
}