{
  "type": "Feature",
  "properties": {
    "gn:admin1_code":"4.0",
    "gn:asciiname":"Chah Mokhlarwala",
    "gn:country_code":"PK",
    "gn:dem":161,
    "gn:feature_class":"P",
    "gn:feature_code":"PPL",
    "gn:name":"Chah Mokhlarwala",
    "gn:population":0,
    "gn:timezone":"Asia/Karachi",
    "iso:country":"PK",
    "name:und_x_variant":[
        "Ch\u0101h Mukhti\u0101rw\u0101la"
    ],
    "wof:name":"Chah Mokhlarwala",
    "wof:placetype":"locality"
},
  "geometry": {"coordinates":[72.40961,31.44117],"type":"Point"}
}