{
  "type": "Feature",
  "properties": {
    "gn:admin1_code":"4",
    "gn:asciiname":"Phathi",
    "gn:country_code":"PK",
    "gn:dem":204,
    "gn:feature_class":"P",
    "gn:feature_code":"PPL",
    "gn:name":"Phathi",
    "gn:population":0,
    "gn:timezone":"Asia/Karachi",
    "iso:country":"PK",
    "name:und_x_variant":[
        "Pj\u0101ti"
    ],
    "wof:name":"Phathi",
    "wof:placetype":"locality"
},
  "geometry": {"coordinates":[71.49619,32.34974],"type":"Point"}
}