{
  "type": "Feature",
  "properties": {
    "gn:admin1_code":"2.0",
    "gn:asciiname":"Mar Gat",
    "gn:country_code":"PK",
    "gn:dem":1690,
    "gn:feature_class":"P",
    "gn:feature_code":"PPL",
    "gn:name":"Mar Gat",
    "gn:population":0,
    "gn:timezone":"Asia/Karachi",
    "iso:country":"PK",
    "name:eng_x_preferred":[
        "Mar Gat"
    ],
    "wof:name":"Mar Gat",
    "wof:placetype":"locality"
},
  "geometry": {"coordinates":[67.28336999999999,30.11752000000001],"type":"Point"}
}