{
  "type": "Feature",
  "properties": {
    "gn:admin1_code":"4",
    "gn:asciiname":"Tufkiwali Dhok",
    "gn:country_code":"PK",
    "gn:dem":806,
    "gn:feature_class":"P",
    "gn:feature_code":"PPL",
    "gn:name":"Tufkiwali Dhok",
    "gn:population":0,
    "gn:timezone":"Asia/Karachi",
    "iso:country":"PK",
    "wof:name":"Tufkiwali Dhok",
    "wof:placetype":"locality"
},
  "geometry": {"coordinates":[72.17083000000002,32.58333],"type":"Point"}
}