{
  "type": "Feature",
  "properties": {
    "gn:admin1_code":"3",
    "gn:asciiname":"Sangra Banda",
    "gn:country_code":"PK",
    "gn:dem":1460,
    "gn:feature_class":"P",
    "gn:feature_code":"PPL",
    "gn:name":"Sangra Banda",
    "gn:population":0,
    "gn:timezone":"Asia/Karachi",
    "iso:country":"PK",
    "name:und_x_variant":[
        "S\u0101ngrra B\u0101nda",
        "Sangra Banda"
    ],
    "wof:name":"Sangra Banda",
    "wof:placetype":"locality"
},
  "geometry": {"coordinates":[72.79723,34.93232],"type":"Point"}
}