{
  "type": "Feature",
  "properties": {
    "gn:admin1_code":"5",
    "gn:asciiname":"Goth Halin",
    "gn:country_code":"PK",
    "gn:dem":18,
    "gn:feature_class":"P",
    "gn:feature_code":"PPL",
    "gn:name":"Goth Halin",
    "gn:population":0,
    "gn:timezone":"Asia/Karachi",
    "iso:country":"PK",
    "name:und_x_variant":[
        "Goth Halan",
        "Halan",
        "Goth Halin"
    ],
    "wof:name":"Goth Halin",
    "wof:placetype":"locality"
},
  "geometry": {"coordinates":[68.57563,25.04313],"type":"Point"}
}