{
  "type": "Feature",
  "properties": {
    "gn:admin1_code":"7.0",
    "gn:asciiname":"Rajiobal",
    "gn:country_code":"PK",
    "gn:dem":3354,
    "gn:feature_class":"P",
    "gn:feature_code":"PPL",
    "gn:name":"Rajiobal",
    "gn:population":0,
    "gn:timezone":"Asia/Karachi",
    "iso:country":"PK",
    "wof:name":"Rajiobal",
    "wof:placetype":"locality"
},
  "geometry": {"coordinates":[72.73742,36.04786],"type":"Point"}
}