{
  "type": "Feature",
  "properties": {
    "gn:admin1_code":"04",
    "gn:asciiname":"Shaikh Alipur",
    "gn:country_code":"PK",
    "gn:dem":217,
    "gn:feature_class":"P",
    "gn:feature_code":"PPL",
    "gn:name":"Shaikh Alipur",
    "gn:population":0,
    "gn:timezone":"Asia/Karachi",
    "iso:country":"PK",
    "name:und_x_variant":[
        "Sheikh Alipur",
        "Shaikh Alipur"
    ],
    "wof:name":"Shaikh Alipur",
    "wof:placetype":"locality"
},
  "geometry": {"coordinates":[73.69665999999999,32.4819],"type":"Point"}
}