{
  "type": "Feature",
  "properties": {
    "gn:admin1_code":"2",
    "gn:asciiname":"Shahr Rasul Bakhsh",
    "gn:country_code":"PK",
    "gn:dem":1738,
    "gn:feature_class":"P",
    "gn:feature_code":"PPL",
    "gn:name":"Shahr Rasul Bakhsh",
    "gn:population":0,
    "gn:timezone":"Asia/Karachi",
    "iso:country":"PK",
    "wof:name":"Shahr Rasul Bakhsh",
    "wof:placetype":"locality"
},
  "geometry": {"coordinates":[66.28407,29.2681],"type":"Point"}
}