{
  "type": "Feature",
  "properties": {
    "gn:admin1_code":"5.0",
    "gn:asciiname":"Goth Muhammad Murad",
    "gn:country_code":"PK",
    "gn:dem":43,
    "gn:feature_class":"P",
    "gn:feature_code":"PPL",
    "gn:name":"Goth Muhammad Murad",
    "gn:population":0,
    "gn:timezone":"Asia/Karachi",
    "iso:country":"PK",
    "name:und_x_variant":[
        "Murad Khakhar"
    ],
    "wof:name":"Goth Muhammad Murad",
    "wof:placetype":"locality"
},
  "geometry": {"coordinates":[68.26257,26.7055],"type":"Point"}
}