{
  "type": "Feature",
  "properties": {
    "gn:admin1_code":"2",
    "gn:asciiname":"Prang",
    "gn:country_code":"PK",
    "gn:dem":2189,
    "gn:feature_class":"P",
    "gn:feature_code":"PPL",
    "gn:name":"Prang",
    "gn:population":0,
    "gn:timezone":"Asia/Karachi",
    "iso:country":"PK",
    "name:deu_x_preferred":[
        "Prang"
    ],
    "wof:name":"Prang",
    "wof:placetype":"locality"
},
  "geometry": {"coordinates":[66.81667,31.06523],"type":"Point"}
}