{
  "type": "Feature",
  "properties": {
    "gn:admin1_code":"2.0",
    "gn:asciiname":"Sultan Ziarat",
    "gn:country_code":"PK",
    "gn:dem":1046,
    "gn:feature_class":"P",
    "gn:feature_code":"PPL",
    "gn:name":"Sultan Ziarat",
    "gn:population":0,
    "gn:timezone":"Asia/Karachi",
    "iso:country":"PK",
    "wof:name":"Sultan Ziarat",
    "wof:placetype":"locality"
},
  "geometry": {"coordinates":[66.05660999999999,29.56472],"type":"Point"}
}