{
  "type": "Feature",
  "properties": {
    "gn:admin1_code":"1.0",
    "gn:asciiname":"Shingharai Patai",
    "gn:country_code":"PK",
    "gn:dem":1088,
    "gn:feature_class":"P",
    "gn:feature_code":"PPL",
    "gn:name":"Shingharai Patai",
    "gn:population":0,
    "gn:timezone":"Asia/Karachi",
    "iso:country":"PK",
    "name:eng_x_preferred":[
        "Shingharai Patai"
    ],
    "wof:name":"Shingharai Patai",
    "wof:placetype":"locality"
},
  "geometry": {"coordinates":[71.52493,34.43261],"type":"Point"}
}