{
  "type": "Feature",
  "properties": {
    "gn:admin1_code":"8.0",
    "gn:asciiname":"Dora",
    "gn:country_code":"PK",
    "gn:dem":547,
    "gn:feature_class":"P",
    "gn:feature_code":"PPL",
    "gn:name":"Dora",
    "gn:population":0,
    "gn:timezone":"Asia/Karachi",
    "iso:country":"PK",
    "wof:name":"Dora",
    "wof:placetype":"locality"
},
  "geometry": {"coordinates":[72.87090999999999,33.6344],"type":"Point"}
}