{
  "type": "Feature",
  "properties": {
    "gn:admin1_code":"5",
    "gn:asciiname":"Goth Jahan Khan Jarwar",
    "gn:country_code":"PK",
    "gn:dem":57,
    "gn:feature_class":"P",
    "gn:feature_code":"PPL",
    "gn:name":"Goth Jahan Khan Jarwar",
    "gn:population":0,
    "gn:timezone":"Asia/Karachi",
    "iso:country":"PK",
    "name:und_x_variant":[
        "Goth S\u0101nwal"
    ],
    "wof:name":"Goth Jahan Khan Jarwar",
    "wof:placetype":"locality"
},
  "geometry": {"coordinates":[68.33131,27.70514],"type":"Point"}
}