{
  "type": "Feature",
  "properties": {
    "gn:admin1_code":"3.0",
    "gn:asciiname":"Dairi",
    "gn:country_code":"PK",
    "gn:dem":2629,
    "gn:feature_class":"P",
    "gn:feature_code":"PPL",
    "gn:name":"Dairi",
    "gn:population":0,
    "gn:timezone":"Asia/Karachi",
    "iso:country":"PK",
    "wof:name":"Dairi",
    "wof:placetype":"locality"
},
  "geometry": {"coordinates":[71.59005999999999,36.01665999999999],"type":"Point"}
}