{
  "type": "Feature",
  "properties": {
    "gn:admin1_code":"6.0",
    "gn:asciiname":"Nilai",
    "gn:country_code":"PK",
    "gn:dem":709,
    "gn:feature_class":"P",
    "gn:feature_code":"PPL",
    "gn:name":"Nilai",
    "gn:population":0,
    "gn:timezone":"Asia/Karachi",
    "iso:country":"PK",
    "name:fra_x_preferred":[
        "Nilai"
    ],
    "name:msa_x_preferred":[
        "Nilai"
    ],
    "name:nld_x_preferred":[
        "Nilai"
    ],
    "name:pol_x_preferred":[
        "Nilai"
    ],
    "name:tha_x_preferred":[
        "\u0e19\u0e35\u0e44\u0e25"
    ],
    "name:urd_x_preferred":[
        "\u0646\u06cc\u0644\u0627\u06cc"
    ],
    "wof:name":"Nilai",
    "wof:placetype":"locality"
},
  "geometry": {"coordinates":[73.64243,33.76073],"type":"Point"}
}