{
  "type": "Feature",
  "properties": {
    "gn:admin1_code":"6.0",
    "gn:asciiname":"Nilai",
    "gn:country_code":"PK",
    "gn:dem":709,
    "gn:feature_class":"P",
    "gn:feature_code":"PPL",
    "gn:name":"Nilai",
    "gn:population":0,
    "gn:timezone":"Asia/Karachi",
    "iso:country":"PK",
    "wof:name":"Nilai",
    "wof:placetype":"locality"
},
  "geometry": {"coordinates":[73.64243,33.76073],"type":"Point"}
}