{
  "type": "Feature",
  "properties": {
    "gn:admin1_code":"02",
    "gn:asciiname":"Dolak Chah",
    "gn:country_code":"PK",
    "gn:dem":1125,
    "gn:feature_class":"P",
    "gn:feature_code":"PPL",
    "gn:name":"Dolak Chah",
    "gn:population":0,
    "gn:timezone":"Asia/Karachi",
    "iso:country":"PK",
    "wof:name":"Dolak Chah",
    "wof:placetype":"locality"
},
  "geometry": {"coordinates":[63.68043,29.13802],"type":"Point"}
}