{
  "type": "Feature",
  "properties": {
    "gn:admin1_code":"3",
    "gn:asciiname":"Niazai",
    "gn:country_code":"PK",
    "gn:dem":1998,
    "gn:feature_class":"P",
    "gn:feature_code":"PPL",
    "gn:name":"Niazai",
    "gn:population":0,
    "gn:timezone":"Asia/Karachi",
    "iso:country":"PK",
    "wof:name":"Niazai",
    "wof:placetype":"locality"
},
  "geometry": {"coordinates":[72.59005999999999,34.61758],"type":"Point"}
}