{
  "type": "Feature",
  "properties": {
    "gn:admin1_code":"2.0",
    "gn:asciiname":"Ali Nawaz",
    "gn:country_code":"PK",
    "gn:dem":50,
    "gn:feature_class":"P",
    "gn:feature_code":"PPL",
    "gn:name":"Ali Nawaz",
    "gn:population":0,
    "gn:timezone":"Asia/Karachi",
    "iso:country":"PK",
    "wof:name":"Ali Nawaz",
    "wof:placetype":"locality"
},
  "geometry": {"coordinates":[67.89870999999999,28.07062],"type":"Point"}
}