{
  "type": "Feature",
  "properties": {
    "gn:admin1_code":"3.0",
    "gn:asciiname":"Khulalai",
    "gn:country_code":"PK",
    "gn:dem":423,
    "gn:feature_class":"P",
    "gn:feature_code":"PPL",
    "gn:name":"Khulalai",
    "gn:population":0,
    "gn:timezone":"Asia/Karachi",
    "iso:country":"PK",
    "name:eng_x_preferred":[
        "Khulalai"
    ],
    "wof:name":"Khulalai",
    "wof:placetype":"locality"
},
  "geometry": {"coordinates":[72.30898000000001,34.38992],"type":"Point"}
}