{
  "type": "Feature",
  "properties": {
    "gn:admin1_code":"5.0",
    "gn:asciiname":"Goth Khoro Thakur",
    "gn:country_code":"PK",
    "gn:dem":48,
    "gn:feature_class":"P",
    "gn:feature_code":"PPL",
    "gn:name":"Goth Khoro Thakur",
    "gn:population":0,
    "gn:timezone":"Asia/Karachi",
    "iso:country":"PK",
    "wof:name":"Goth Khoro Thakur",
    "wof:placetype":"locality"
},
  "geometry": {"coordinates":[69.88582,25.41565],"type":"Point"}
}