{
  "type": "Feature",
  "properties": {
    "gn:admin1_code":"5.0",
    "gn:asciiname":"Goth Fateh Muhammad Jamali",
    "gn:country_code":"PK",
    "gn:dem":41,
    "gn:feature_class":"P",
    "gn:feature_code":"PPL",
    "gn:name":"Goth Fateh Muhammad Jamali",
    "gn:population":0,
    "gn:timezone":"Asia/Karachi",
    "iso:country":"PK",
    "name:und_x_variant":[
        "Waz\u012br Kh\u0101n Jam\u0101li"
    ],
    "wof:name":"Goth Fateh Muhammad Jamali",
    "wof:placetype":"locality"
},
  "geometry": {"coordinates":[68.26365,26.56688],"type":"Point"}
}