{
  "type": "Feature",
  "properties": {
    "gn:admin1_code":"3.0",
    "gn:asciiname":"Gashkor",
    "gn:country_code":"PK",
    "gn:dem":1104,
    "gn:feature_class":"P",
    "gn:feature_code":"PPL",
    "gn:name":"Gashkor",
    "gn:population":0,
    "gn:timezone":"Asia/Karachi",
    "iso:country":"PK",
    "name:und_x_variant":[
        "Gash Koar",
        "Gashkor"
    ],
    "wof:name":"Gashkor",
    "wof:placetype":"locality"
},
  "geometry": {"coordinates":[72.45263,34.91531],"type":"Point"}
}