{
  "type": "Feature",
  "properties": {
    "gn:admin1_code":"2.0",
    "gn:asciiname":"Poti",
    "gn:country_code":"PK",
    "gn:dem":1776,
    "gn:feature_class":"P",
    "gn:feature_code":"PPL",
    "gn:name":"Poti",
    "gn:population":0,
    "gn:timezone":"Asia/Karachi",
    "iso:country":"PK",
    "name:eng_x_preferred":[
        "Potai"
    ],
    "wof:name":"Poti",
    "wof:placetype":"locality"
},
  "geometry": {"coordinates":[67.25104,30.79108],"type":"Point"}
}