{
  "type": "Feature",
  "properties": {
    "gn:admin1_code":"4.0",
    "gn:asciiname":"Dhok Kala Khan",
    "gn:country_code":"PK",
    "gn:dem":548,
    "gn:feature_class":"P",
    "gn:feature_code":"PPL",
    "gn:name":"Dhok Kala Khan",
    "gn:population":0,
    "gn:timezone":"Asia/Karachi",
    "iso:country":"PK",
    "wof:name":"Dhok Kala Khan",
    "wof:placetype":"locality"
},
  "geometry": {"coordinates":[73.14698,33.45954],"type":"Point"}
}