{
  "type": "Feature",
  "properties": {
    "gn:admin1_code":"03",
    "gn:asciiname":"Kuza Bandai",
    "gn:country_code":"PK",
    "gn:dem":969,
    "gn:feature_class":"P",
    "gn:feature_code":"PPL",
    "gn:name":"Kuza Bandai",
    "gn:population":0,
    "gn:timezone":"Asia/Karachi",
    "iso:country":"PK",
    "name:und_x_variant":[
        "Kozabanda",
        "Kuz B\u0101ndai",
        "Kuza Bandai"
    ],
    "wof:name":"Kuza Bandai",
    "wof:placetype":"locality"
},
  "geometry": {"coordinates":[72.37469,34.81605],"type":"Point"}
}