{
  "type": "Feature",
  "properties": {
    "gn:admin1_code":"4.0",
    "gn:asciiname":"Nazim Khel Banda",
    "gn:country_code":"PK",
    "gn:dem":290,
    "gn:feature_class":"P",
    "gn:feature_code":"PPL",
    "gn:name":"Nazim Khel Banda",
    "gn:population":0,
    "gn:timezone":"Asia/Karachi",
    "iso:country":"PK",
    "wof:name":"Nazim Khel Banda",
    "wof:placetype":"locality"
},
  "geometry": {"coordinates":[71.19771,32.86756],"type":"Point"}
}