{
  "type": "Feature",
  "properties": {
    "gn:admin1_code":"2.0",
    "gn:asciiname":"Phullan Bazar",
    "gn:country_code":"PK",
    "gn:dem":869,
    "gn:feature_class":"P",
    "gn:feature_code":"PPL",
    "gn:name":"Phullan Bazar",
    "gn:population":0,
    "gn:timezone":"Asia/Karachi",
    "iso:country":"PK",
    "wof:name":"Phullan Bazar",
    "wof:placetype":"locality"
},
  "geometry": {"coordinates":[64.53175999999999,26.46657],"type":"Point"}
}