{
  "type": "Feature",
  "properties": {
    "gn:admin1_code":"5.0",
    "gn:asciiname":"Goth Pauhun Faqir Shar",
    "gn:country_code":"PK",
    "gn:dem":43,
    "gn:feature_class":"P",
    "gn:feature_code":"PPL",
    "gn:name":"Goth Pauhun Faqir Shar",
    "gn:population":0,
    "gn:timezone":"Asia/Karachi",
    "iso:country":"PK",
    "name:und_x_variant":[
        "P\u016bnnu Faq\u012br Shar"
    ],
    "wof:name":"Goth Pauhun Faqir Shar",
    "wof:placetype":"locality"
},
  "geometry": {"coordinates":[68.33707,26.74595],"type":"Point"}
}