{
  "type": "Feature",
  "properties": {
    "gn:admin1_code":"04",
    "gn:asciiname":"Mirzapur",
    "gn:country_code":"PK",
    "gn:dem":101,
    "gn:feature_class":"P",
    "gn:feature_code":"PPL",
    "gn:name":"Mirzapur",
    "gn:population":0,
    "gn:timezone":"Asia/Karachi",
    "iso:country":"PK",
    "name:und_x_variant":[
        "Mirz\u0101npur",
        "Mirz\u0101pur",
        "Mirzapur"
    ],
    "wof:name":"Mirzapur",
    "wof:placetype":"locality"
},
  "geometry": {"coordinates":[70.53638000000002,29.36384],"type":"Point"}
}