{
  "type": "Feature",
  "properties": {
    "gn:admin1_code":"05",
    "gn:asciiname":"Goth Pir Allah Dino Shah",
    "gn:country_code":"PK",
    "gn:dem":4,
    "gn:feature_class":"P",
    "gn:feature_code":"PPL",
    "gn:name":"Goth Pir Allah Dino Shah",
    "gn:population":0,
    "gn:timezone":"Asia/Karachi",
    "iso:country":"PK",
    "name:und_x_variant":[
        "P\u012br All\u0101hanno Sh\u0101h"
    ],
    "wof:name":"Goth Pir Allah Dino Shah",
    "wof:placetype":"locality"
},
  "geometry": {"coordinates":[67.5458,24.16434],"type":"Point"}
}