{
  "type": "Feature",
  "properties": {
    "gn:admin1_code":"3",
    "gn:asciiname":"Nalla",
    "gn:country_code":"PK",
    "gn:dem":2015,
    "gn:feature_class":"P",
    "gn:feature_code":"PPL",
    "gn:name":"Nalla",
    "gn:population":0,
    "gn:timezone":"Asia/Karachi",
    "iso:country":"PK",
    "name:und_x_variant":[
        "Nalo"
    ],
    "wof:name":"Nalla",
    "wof:placetype":"locality"
},
  "geometry": {"coordinates":[73.1932,34.58332],"type":"Point"}
}