{
  "type": "Feature",
  "properties": {
    "gn:admin1_code":"3.0",
    "gn:asciiname":"Bandwal Ganja",
    "gn:country_code":"PK",
    "gn:dem":3157,
    "gn:feature_class":"P",
    "gn:feature_code":"PPL",
    "gn:name":"Bandwal Ganja",
    "gn:population":0,
    "gn:timezone":"Asia/Karachi",
    "iso:country":"PK",
    "wof:name":"Bandwal Ganja",
    "wof:placetype":"locality"
},
  "geometry": {"coordinates":[73.14868,34.77457],"type":"Point"}
}