{
  "type": "Feature",
  "properties": {
    "gn:admin1_code":"6",
    "gn:asciiname":"Chohi",
    "gn:country_code":"PK",
    "gn:dem":1070,
    "gn:feature_class":"P",
    "gn:feature_code":"PPL",
    "gn:name":"Chohi",
    "gn:population":0,
    "gn:timezone":"Asia/Karachi",
    "iso:country":"PK",
    "wof:name":"Chohi",
    "wof:placetype":"locality"
},
  "geometry": {"coordinates":[74.04722,33.61389],"type":"Point"}
}