{
  "type": "Feature",
  "properties": {
    "gn:admin1_code":"01",
    "gn:asciiname":"Shashpali",
    "gn:country_code":"PK",
    "gn:dem":1510,
    "gn:feature_class":"P",
    "gn:feature_code":"PPL",
    "gn:name":"Shashpali",
    "gn:population":0,
    "gn:timezone":"Asia/Karachi",
    "iso:country":"PK",
    "name:und_x_variant":[
        "Shashpail",
        "Shashpali"
    ],
    "wof:name":"Shashpali",
    "wof:placetype":"locality"
},
  "geometry": {"coordinates":[69.53222,32.88969],"type":"Point"}
}