{
  "type": "Feature",
  "properties": {
    "gn:admin1_code":"3",
    "gn:asciiname":"Kasilan",
    "gn:country_code":"PK",
    "gn:dem":1002,
    "gn:feature_class":"P",
    "gn:feature_code":"PPL",
    "gn:name":"Kasilan",
    "gn:population":0,
    "gn:timezone":"Asia/Karachi",
    "iso:country":"PK",
    "name:und_x_variant":[
        "Kusilan"
    ],
    "wof:name":"Kasilan",
    "wof:placetype":"locality"
},
  "geometry": {"coordinates":[73.17754000000002,34.01784],"type":"Point"}
}