{
  "type": "Feature",
  "properties": {
    "gn:admin1_code":"6",
    "gn:asciiname":"Bagle",
    "gn:country_code":"PK",
    "gn:dem":1831,
    "gn:feature_class":"P",
    "gn:feature_code":"PPL",
    "gn:name":"Bagle",
    "gn:population":0,
    "gn:timezone":"Asia/Karachi",
    "iso:country":"PK",
    "wof:name":"Bagle",
    "wof:placetype":"locality"
},
  "geometry": {"coordinates":[73.66897,34.42861],"type":"Point"}
}