{
  "type": "Feature",
  "properties": {
    "gn:admin1_code":"4.0",
    "gn:asciiname":"Darbar Pir Walayat Shah",
    "gn:country_code":"PK",
    "gn:dem":165,
    "gn:feature_class":"P",
    "gn:feature_code":"PPL",
    "gn:name":"Darbar Pir Walayat Shah",
    "gn:population":0,
    "gn:timezone":"Asia/Karachi",
    "iso:country":"PK",
    "wof:name":"Darbar Pir Walayat Shah",
    "wof:placetype":"locality"
},
  "geometry": {"coordinates":[72.08216,31.4245],"type":"Point"}
}