{
  "type": "Feature",
  "properties": {
    "gn:admin1_code":"2.0",
    "gn:asciiname":"Kili Farmanullah",
    "gn:country_code":"PK",
    "gn:dem":745,
    "gn:feature_class":"P",
    "gn:feature_code":"PPL",
    "gn:name":"Kili Farmanullah",
    "gn:population":0,
    "gn:timezone":"Asia/Karachi",
    "iso:country":"PK",
    "wof:name":"Kili Farmanullah",
    "wof:placetype":"locality"
},
  "geometry": {"coordinates":[61.73001,28.74682],"type":"Point"}
}