{
  "type": "Feature",
  "properties": {
    "gn:admin1_code":"3.0",
    "gn:asciiname":"Gulababad",
    "gn:country_code":"PK",
    "gn:dem":292,
    "gn:feature_class":"P",
    "gn:feature_code":"PPL",
    "gn:name":"Gulababad",
    "gn:population":0,
    "gn:timezone":"Asia/Karachi",
    "iso:country":"PK",
    "wof:name":"Gulababad",
    "wof:placetype":"locality"
},
  "geometry": {"coordinates":[72.25533,33.96943],"type":"Point"}
}