{
  "type": "Feature",
  "properties": {
    "gn:admin1_code":"5.0",
    "gn:asciiname":"Goth Dhani Bakhsh Malik",
    "gn:country_code":"PK",
    "gn:dem":69,
    "gn:feature_class":"P",
    "gn:feature_code":"PPL",
    "gn:name":"Goth Dhani Bakhsh Malik",
    "gn:population":0,
    "gn:timezone":"Asia/Karachi",
    "iso:country":"PK",
    "wof:name":"Goth Dhani Bakhsh Malik",
    "wof:placetype":"locality"
},
  "geometry": {"coordinates":[68.75301999999999,27.90385],"type":"Point"}
}