{
  "type": "Feature",
  "properties": {
    "gn:admin1_code":"5.0",
    "gn:asciiname":"Murid Khan Khosa",
    "gn:country_code":"PK",
    "gn:dem":66,
    "gn:feature_class":"P",
    "gn:feature_code":"PPL",
    "gn:name":"Murid Khan Khosa",
    "gn:population":0,
    "gn:timezone":"Asia/Karachi",
    "iso:country":"PK",
    "wof:name":"Murid Khan Khosa",
    "wof:placetype":"locality"
},
  "geometry": {"coordinates":[68.96821,28.27772],"type":"Point"}
}