{
  "type": "Feature",
  "properties": {
    "gn:admin1_code":"4",
    "gn:asciiname":"Chak Twenty-four -Eleven Left",
    "gn:country_code":"PK",
    "gn:dem":156,
    "gn:feature_class":"P",
    "gn:feature_code":"PPL",
    "gn:name":"Chak Twenty-four -Eleven Left",
    "gn:population":0,
    "gn:timezone":"Asia/Karachi",
    "iso:country":"PK",
    "name:und_x_variant":[
        "Nemat\u0101b\u0101d"
    ],
    "wof:name":"Chak Twenty-four -Eleven Left",
    "wof:placetype":"locality"
},
  "geometry": {"coordinates":[72.71778,30.42345],"type":"Point"}
}