{
  "type": "Feature",
  "properties": {
    "gn:admin1_code":"4.0",
    "gn:asciiname":"Chah Waliwala",
    "gn:country_code":"PK",
    "gn:dem":109,
    "gn:feature_class":"P",
    "gn:feature_code":"PPL",
    "gn:name":"Chah Waliwala",
    "gn:population":0,
    "gn:timezone":"Asia/Karachi",
    "iso:country":"PK",
    "wof:name":"Chah Waliwala",
    "wof:placetype":"locality"
},
  "geometry": {"coordinates":[71.47766999999997,29.23482000000001],"type":"Point"}
}