{
  "type": "Feature",
  "properties": {
    "gn:admin1_code":"3",
    "gn:asciiname":"Garai",
    "gn:country_code":"PK",
    "gn:dem":1629,
    "gn:feature_class":"P",
    "gn:feature_code":"PPL",
    "gn:name":"Garai",
    "gn:population":0,
    "gn:timezone":"Asia/Karachi",
    "iso:country":"PK",
    "wof:name":"Garai",
    "wof:placetype":"locality"
},
  "geometry": {"coordinates":[72.55863000000002,34.62044],"type":"Point"}
}