{
  "type": "Feature",
  "properties": {
    "gn:admin1_code":"3.0",
    "gn:asciiname":"Maliari da Khola",
    "gn:country_code":"PK",
    "gn:dem":830,
    "gn:feature_class":"P",
    "gn:feature_code":"PPL",
    "gn:name":"Maliari da Khola",
    "gn:population":0,
    "gn:timezone":"Asia/Karachi",
    "iso:country":"PK",
    "wof:name":"Maliari da Khola",
    "wof:placetype":"locality"
},
  "geometry": {"coordinates":[73.06279000000001,34.32824],"type":"Point"}
}