{
  "type": "Feature",
  "properties": {
    "gn:admin1_code":"5",
    "gn:asciiname":"Goth Sona Lashari",
    "gn:country_code":"PK",
    "gn:dem":13,
    "gn:feature_class":"P",
    "gn:feature_code":"PPL",
    "gn:name":"Goth Sona Lashari",
    "gn:population":0,
    "gn:timezone":"Asia/Karachi",
    "iso:country":"PK",
    "name:und_x_variant":[
        "Goth Sono Lish\u0101ri"
    ],
    "wof:name":"Goth Sona Lashari",
    "wof:placetype":"locality"
},
  "geometry": {"coordinates":[69.09845,25.43066],"type":"Point"}
}