{
  "type": "Feature",
  "properties": {
    "gn:admin1_code":"2.0",
    "gn:asciiname":"Band Qadir Bakhsh",
    "gn:country_code":"PK",
    "gn:dem":880,
    "gn:feature_class":"P",
    "gn:feature_code":"PPL",
    "gn:name":"Band Qadir Bakhsh",
    "gn:population":0,
    "gn:timezone":"Asia/Karachi",
    "iso:country":"PK",
    "wof:name":"Band Qadir Bakhsh",
    "wof:placetype":"locality"
},
  "geometry": {"coordinates":[62.77935,28.94032],"type":"Point"}
}