{
  "type": "Feature",
  "properties": {
    "gn:admin1_code":"2.0",
    "gn:asciiname":"Shahdinzai",
    "gn:country_code":"PK",
    "gn:dem":1691,
    "gn:feature_class":"P",
    "gn:feature_code":"PPL",
    "gn:name":"Shahdinzai",
    "gn:population":0,
    "gn:timezone":"Asia/Karachi",
    "iso:country":"PK",
    "name:und_x_variant":[
        "Kili Sh\u0101hdanzai",
        "Shahdinzai"
    ],
    "wof:name":"Shahdinzai",
    "wof:placetype":"locality"
},
  "geometry": {"coordinates":[66.95161,30.1241],"type":"Point"}
}