{
  "type": "Feature",
  "properties": {
    "gn:admin1_code":"2.0",
    "gn:asciiname":"Misri Khan Gis",
    "gn:country_code":"PK",
    "gn:dem":1636,
    "gn:feature_class":"P",
    "gn:feature_code":"PPL",
    "gn:name":"Misri Khan Gis",
    "gn:population":0,
    "gn:timezone":"Asia/Karachi",
    "iso:country":"PK",
    "wof:name":"Misri Khan Gis",
    "wof:placetype":"locality"
},
  "geometry": {"coordinates":[63.87241,29.36879],"type":"Point"}
}