{
  "type": "Feature",
  "properties": {
    "gn:admin1_code":"05",
    "gn:asciiname":"Mubarakpur",
    "gn:country_code":"PK",
    "gn:dem":66,
    "gn:feature_class":"P",
    "gn:feature_code":"PPL",
    "gn:name":"Mubarakpur",
    "gn:population":0,
    "gn:timezone":"Asia/Karachi",
    "iso:country":"PK",
    "wof:name":"Mubarakpur",
    "wof:placetype":"locality"
},
  "geometry": {"coordinates":[69.29084,27.70548],"type":"Point"}
}