{
  "type": "Feature",
  "properties": {
    "gn:admin1_code":"3.0",
    "gn:asciiname":"Chaik Sukaili",
    "gn:country_code":"PK",
    "gn:dem":694,
    "gn:feature_class":"P",
    "gn:feature_code":"PPL",
    "gn:name":"Chaik Sukaili",
    "gn:population":0,
    "gn:timezone":"Asia/Karachi",
    "iso:country":"PK",
    "wof:name":"Chaik Sukaili",
    "wof:placetype":"locality"
},
  "geometry": {"coordinates":[72.63893,34.21406],"type":"Point"}
}