{
  "type": "Feature",
  "properties": {
    "gn:admin1_code":"4.0",
    "gn:asciiname":"Dhok Nur Shah",
    "gn:country_code":"PK",
    "gn:dem":354,
    "gn:feature_class":"P",
    "gn:feature_code":"PPL",
    "gn:name":"Dhok Nur Shah",
    "gn:population":0,
    "gn:timezone":"Asia/Karachi",
    "iso:country":"PK",
    "name:und_x_variant":[
        "N\u016br Sh\u0101hw\u0101li"
    ],
    "wof:name":"Dhok Nur Shah",
    "wof:placetype":"locality"
},
  "geometry": {"coordinates":[71.82111,32.87693],"type":"Point"}
}