{
  "type": "Feature",
  "properties": {
    "gn:admin1_code":"6",
    "gn:asciiname":"Chamat",
    "gn:country_code":"PK",
    "gn:dem":309,
    "gn:feature_class":"P",
    "gn:feature_code":"PPL",
    "gn:name":"Chamat",
    "gn:population":0,
    "gn:timezone":"Asia/Karachi",
    "iso:country":"PK",
    "wof:name":"Chamat",
    "wof:placetype":"locality"
},
  "geometry": {"coordinates":[73.97979000000002,32.99701],"type":"Point"}
}