{
  "type": "Feature",
  "properties": {
    "gn:admin1_code":"03",
    "gn:asciiname":"Khui Kalle",
    "gn:country_code":"PK",
    "gn:dem":764,
    "gn:feature_class":"P",
    "gn:feature_code":"PPL",
    "gn:name":"Khui Kalle",
    "gn:population":0,
    "gn:timezone":"Asia/Karachi",
    "iso:country":"PK",
    "name:und_x_variant":[
        "Kota Killi",
        "Kotha Kili",
        "Khui Kalle"
    ],
    "wof:name":"Khui Kalle",
    "wof:placetype":"locality"
},
  "geometry": {"coordinates":[71.22934000000002,33.15115],"type":"Point"}
}