{
  "type": "Feature",
  "properties": {
    "gn:admin1_code":"4",
    "gn:asciiname":"Bajewali",
    "gn:country_code":"PK",
    "gn:dem":887,
    "gn:feature_class":"P",
    "gn:feature_code":"PPL",
    "gn:name":"Bajewali",
    "gn:population":0,
    "gn:timezone":"Asia/Karachi",
    "iso:country":"PK",
    "wof:name":"Bajewali",
    "wof:placetype":"locality"
},
  "geometry": {"coordinates":[72.2375,32.65],"type":"Point"}
}