{
  "type": "Feature",
  "properties": {
    "gn:admin1_code":"04",
    "gn:asciiname":"Nigarian",
    "gn:country_code":"PK",
    "gn:dem":249,
    "gn:feature_class":"P",
    "gn:feature_code":"PPL",
    "gn:name":"Nigarian",
    "gn:population":0,
    "gn:timezone":"Asia/Karachi",
    "iso:country":"PK",
    "wof:name":"Nigarian",
    "wof:placetype":"locality"
},
  "geometry": {"coordinates":[73.73151999999997,32.74981],"type":"Point"}
}