{
  "type": "Feature",
  "properties": {
    "gn:admin1_code":"4",
    "gn:asciiname":"Chhani Jowaie Shah",
    "gn:country_code":"PK",
    "gn:dem":212,
    "gn:feature_class":"P",
    "gn:feature_code":"PPL",
    "gn:name":"Chhani Jowaie Shah",
    "gn:population":0,
    "gn:timezone":"Asia/Karachi",
    "iso:country":"PK",
    "name:und_x_variant":[
        "Chhanni Jow\u0101ya Sh\u0101h"
    ],
    "wof:name":"Chhani Jowaie Shah",
    "wof:placetype":"locality"
},
  "geometry": {"coordinates":[73.55848,32.46563],"type":"Point"}
}