{
  "type": "Feature",
  "properties": {
    "gn:admin1_code":"3",
    "gn:asciiname":"Katgiran",
    "gn:country_code":"PK",
    "gn:dem":705,
    "gn:feature_class":"P",
    "gn:feature_code":"PPL",
    "gn:name":"Katgiran",
    "gn:population":0,
    "gn:timezone":"Asia/Karachi",
    "iso:country":"PK",
    "name:und_x_variant":[
        "Bar\u012bla Kal\u0101n",
        "Barila K\u0101l\u0101n"
    ],
    "wof:name":"Katgiran",
    "wof:placetype":"locality"
},
  "geometry": {"coordinates":[73.02188000000002,34.26953],"type":"Point"}
}