{
  "type": "Feature",
  "properties": {
    "gn:admin1_code":"2",
    "gn:asciiname":"Tirazh",
    "gn:country_code":"PK",
    "gn:dem":1430,
    "gn:feature_class":"P",
    "gn:feature_code":"PPL",
    "gn:name":"Tirazh",
    "gn:population":0,
    "gn:timezone":"Asia/Karachi",
    "iso:country":"PK",
    "wof:name":"Tirazh",
    "wof:placetype":"locality"
},
  "geometry": {"coordinates":[69.07388,30.5883],"type":"Point"}
}