{
  "type": "Feature",
  "properties": {
    "gn:admin1_code":"1",
    "gn:asciiname":"Geza Paoza",
    "gn:country_code":"PK",
    "gn:dem":748,
    "gn:feature_class":"P",
    "gn:feature_code":"PPL",
    "gn:name":"Geza Paoza",
    "gn:population":0,
    "gn:timezone":"Asia/Karachi",
    "iso:country":"PK",
    "name:und_x_variant":[
        "Geza R\u0101aza",
        "Geza Paaza",
        "Geza Paoza"
    ],
    "wof:name":"Geza Paoza",
    "wof:placetype":"locality"
},
  "geometry": {"coordinates":[70.0782,31.69554],"type":"Point"}
}