{
  "type": "Feature",
  "properties": {
    "gn:admin1_code":"4.0",
    "gn:asciiname":"Chak Two Hundred Fifty-six Thal Development Authority",
    "gn:country_code":"PK",
    "gn:dem":153,
    "gn:feature_class":"P",
    "gn:feature_code":"PPL",
    "gn:name":"Chak Two Hundred Fifty-six Thal Development Authority",
    "gn:population":0,
    "gn:timezone":"Asia/Karachi",
    "iso:country":"PK",
    "name:und_x_variant":[
        "Chak 256 TDA",
        "Chak Two Hundred Fifty-Six TDA",
        "Chak Two Hundred Fifty-six Thal Development Authority"
    ],
    "wof:name":"Chak Two Hundred Fifty-six Thal Development Authority",
    "wof:placetype":"locality"
},
  "geometry": {"coordinates":[71.11319,31.136],"type":"Point"}
}