{
  "type": "Feature",
  "properties": {
    "gn:admin1_code":"04",
    "gn:asciiname":"Nanka Gidar",
    "gn:country_code":"PK",
    "gn:dem":146,
    "gn:feature_class":"P",
    "gn:feature_code":"PPL",
    "gn:name":"Nanka Gidar",
    "gn:population":0,
    "gn:timezone":"Asia/Karachi",
    "iso:country":"PK",
    "name:und_x_variant":[
        "N\u0101nka Giddar"
    ],
    "wof:name":"Nanka Gidar",
    "wof:placetype":"locality"
},
  "geometry": {"coordinates":[72.34695000000001,30.60861],"type":"Point"}
}