{
  "type": "Feature",
  "properties": {
    "gn:admin1_code":"4.0",
    "gn:asciiname":"Amir di Kothi",
    "gn:country_code":"PK",
    "gn:dem":156,
    "gn:feature_class":"P",
    "gn:feature_code":"PPL",
    "gn:name":"Amir di Kothi",
    "gn:population":0,
    "gn:timezone":"Asia/Karachi",
    "iso:country":"PK",
    "wof:name":"Amir di Kothi",
    "wof:placetype":"locality"
},
  "geometry": {"coordinates":[73.26554,30.05914000000001],"type":"Point"}
}