{
  "type": "Feature",
  "properties": {
    "gn:admin1_code":"2",
    "gn:asciiname":"Trasiani",
    "gn:country_code":"PK",
    "gn:dem":1474,
    "gn:feature_class":"P",
    "gn:feature_code":"PPL",
    "gn:name":"Trasiani",
    "gn:population":0,
    "gn:timezone":"Asia/Karachi",
    "iso:country":"PK",
    "wof:name":"Trasiani",
    "wof:placetype":"locality"
},
  "geometry": {"coordinates":[66.62108000000001,28.4824],"type":"Point"}
}