{
  "type": "Feature",
  "properties": {
    "gn:admin1_code":"5.0",
    "gn:asciiname":"Qutubuddin Punjabi",
    "gn:country_code":"PK",
    "gn:dem":40,
    "gn:feature_class":"P",
    "gn:feature_code":"PPL",
    "gn:name":"Qutubuddin Punjabi",
    "gn:population":0,
    "gn:timezone":"Asia/Karachi",
    "iso:country":"PK",
    "name:und_x_variant":[
        "Qutubudd\u012b Punj\u0101bi"
    ],
    "wof:name":"Qutubuddin Punjabi",
    "wof:placetype":"locality"
},
  "geometry": {"coordinates":[68.06058,26.49486],"type":"Point"}
}