{
  "type": "Feature",
  "properties": {
    "gn:admin1_code":"3.0",
    "gn:asciiname":"Turo Banda",
    "gn:country_code":"PK",
    "gn:dem":2276,
    "gn:feature_class":"P",
    "gn:feature_code":"PPL",
    "gn:name":"Turo Banda",
    "gn:population":0,
    "gn:timezone":"Asia/Karachi",
    "iso:country":"PK",
    "wof:name":"Turo Banda",
    "wof:placetype":"locality"
},
  "geometry": {"coordinates":[73.09326999999998,34.9769],"type":"Point"}
}