{
  "type": "Feature",
  "properties": {
    "gn:admin1_code":"04",
    "gn:asciiname":"Chak One Hundred Six Northern Branch",
    "gn:country_code":"PK",
    "gn:dem":182,
    "gn:feature_class":"P",
    "gn:feature_code":"PPL",
    "gn:name":"Chak One Hundred Six Northern Branch",
    "gn:population":0,
    "gn:timezone":"Asia/Karachi",
    "iso:country":"PK",
    "name:und_x_variant":[
        "Ror\u0101la",
        "Rur\u0101la",
        "Chak 106 NB",
        "Chak One Hundred Six Northern Branch",
        "Par\u0101la"
    ],
    "wof:name":"Chak One Hundred Six Northern Branch",
    "wof:placetype":"locality"
},
  "geometry": {"coordinates":[72.58246,31.98176],"type":"Point"}
}