{
  "type": "Feature",
  "properties": {
    "gn:admin1_code":"4",
    "gn:asciiname":"Basti Arain",
    "gn:country_code":"PK",
    "gn:dem":98,
    "gn:feature_class":"P",
    "gn:feature_code":"PPL",
    "gn:name":"Basti Arain",
    "gn:population":0,
    "gn:timezone":"Asia/Karachi",
    "iso:country":"PK",
    "name:und_x_variant":[
        "\u0100r\u0101\u012ba"
    ],
    "wof:name":"Basti Arain",
    "wof:placetype":"locality"
},
  "geometry": {"coordinates":[70.87343,28.97275],"type":"Point"}
}