{
  "type": "Feature",
  "properties": {
    "gn:admin1_code":"4.0",
    "gn:asciiname":"Shakkar Kakka",
    "gn:country_code":"PK",
    "gn:dem":431,
    "gn:feature_class":"P",
    "gn:feature_code":"PPL",
    "gn:name":"Shakkar Kakka",
    "gn:population":0,
    "gn:timezone":"Asia/Karachi",
    "iso:country":"PK",
    "wof:name":"Shakkar Kakka",
    "wof:placetype":"locality"
},
  "geometry": {"coordinates":[71.89115,32.63155],"type":"Point"}
}