{
  "type": "Feature",
  "properties": {
    "gn:admin1_code":"5.0",
    "gn:asciiname":"Khabar Khan Khoso",
    "gn:country_code":"PK",
    "gn:dem":10,
    "gn:feature_class":"P",
    "gn:feature_code":"PPL",
    "gn:name":"Khabar Khan Khoso",
    "gn:population":0,
    "gn:timezone":"Asia/Karachi",
    "iso:country":"PK",
    "name:und_x_variant":[
        "P\u012b\u0101ro Khosos"
    ],
    "wof:name":"Khabar Khan Khoso",
    "wof:placetype":"locality"
},
  "geometry": {"coordinates":[68.90915,24.71266],"type":"Point"}
}