{
  "type": "Feature",
  "properties": {
    "gn:admin1_code":"5.0",
    "gn:asciiname":"Abdul Jabbar Bugti",
    "gn:country_code":"PK",
    "gn:dem":62,
    "gn:feature_class":"P",
    "gn:feature_code":"PPL",
    "gn:name":"Abdul Jabbar Bugti",
    "gn:population":0,
    "gn:timezone":"Asia/Karachi",
    "iso:country":"PK",
    "wof:name":"Abdul Jabbar Bugti",
    "wof:placetype":"locality"
},
  "geometry": {"coordinates":[68.80970000000001,28.37573],"type":"Point"}
}