{
  "type": "Feature",
  "properties": {
    "gn:admin1_code":"4",
    "gn:asciiname":"Pejoke",
    "gn:country_code":"PK",
    "gn:dem":253,
    "gn:feature_class":"P",
    "gn:feature_code":"PPL",
    "gn:name":"Pejoke",
    "gn:population":0,
    "gn:timezone":"Asia/Karachi",
    "iso:country":"PK",
    "name:und_x_variant":[
        "Pejoke Khurd",
        "Pejoke"
    ],
    "wof:name":"Pejoke",
    "wof:placetype":"locality"
},
  "geometry": {"coordinates":[74.28471999999999,32.675],"type":"Point"}
}