{
  "type": "Feature",
  "properties": {
    "gn:admin1_code":"4.0",
    "gn:asciiname":"Luhna Singwala",
    "gn:country_code":"PK",
    "gn:dem":197,
    "gn:feature_class":"P",
    "gn:feature_code":"PPL",
    "gn:name":"Luhna Singwala",
    "gn:population":0,
    "gn:timezone":"Asia/Karachi",
    "iso:country":"PK",
    "name:und_x_variant":[
        "Lehna Singhw\u0101la"
    ],
    "wof:name":"Luhna Singwala",
    "wof:placetype":"locality"
},
  "geometry": {"coordinates":[74.01061,31.03423],"type":"Point"}
}