{
  "type": "Feature",
  "properties": {
    "gn:admin1_code":"2.0",
    "gn:asciiname":"Kili Shah Wali",
    "gn:country_code":"PK",
    "gn:dem":1858,
    "gn:feature_class":"P",
    "gn:feature_code":"PPL",
    "gn:name":"Kili Shah Wali",
    "gn:population":0,
    "gn:timezone":"Asia/Karachi",
    "iso:country":"PK",
    "wof:name":"Kili Shah Wali",
    "wof:placetype":"locality"
},
  "geometry": {"coordinates":[66.99578000000001,31.23876],"type":"Point"}
}