{
  "type": "Feature",
  "properties": {
    "gn:admin1_code":"2.0",
    "gn:asciiname":"Haji Azizabad",
    "gn:country_code":"PK",
    "gn:dem":1582,
    "gn:feature_class":"P",
    "gn:feature_code":"PPL",
    "gn:name":"Haji Azizabad",
    "gn:population":0,
    "gn:timezone":"Asia/Karachi",
    "iso:country":"PK",
    "wof:name":"Haji Azizabad",
    "wof:placetype":"locality"
},
  "geometry": {"coordinates":[66.32171,28.0972],"type":"Point"}
}