{
  "type": "Feature",
  "properties": {
    "gn:admin1_code":"2.0",
    "gn:asciiname":"Mustafabad Bazar",
    "gn:country_code":"PK",
    "gn:dem":645,
    "gn:feature_class":"P",
    "gn:feature_code":"PPL",
    "gn:name":"Mustafabad Bazar",
    "gn:population":0,
    "gn:timezone":"Asia/Karachi",
    "iso:country":"PK",
    "wof:name":"Mustafabad Bazar",
    "wof:placetype":"locality"
},
  "geometry": {"coordinates":[64.0805,26.26699],"type":"Point"}
}