{
  "type": "Feature",
  "properties": {
    "gn:admin1_code":"1.0",
    "gn:asciiname":"Bazargai",
    "gn:country_code":"PK",
    "gn:dem":1068,
    "gn:feature_class":"P",
    "gn:feature_code":"PPL",
    "gn:name":"B\u0101z\u0101rgai",
    "gn:population":0,
    "gn:timezone":"Asia/Karachi",
    "iso:country":"PK",
    "name:eng_x_preferred":[
        "B\u0101z\u0101rgai"
    ],
    "wof:name":"Bazargai",
    "wof:placetype":"locality"
},
  "geometry": {"coordinates":[71.51389,34.46722],"type":"Point"}
}