{
  "type": "Feature",
  "properties": {
    "gn:admin1_code":"2.0",
    "gn:asciiname":"Samanzai Kili",
    "gn:country_code":"PK",
    "gn:dem":1639,
    "gn:feature_class":"P",
    "gn:feature_code":"PPL",
    "gn:name":"Samanzai Kili",
    "gn:population":0,
    "gn:timezone":"Asia/Karachi",
    "iso:country":"PK",
    "wof:name":"Samanzai Kili",
    "wof:placetype":"locality"
},
  "geometry": {"coordinates":[69.61574,31.47203],"type":"Point"}
}