{
  "type": "Feature",
  "properties": {
    "gn:admin1_code":"5.0",
    "gn:asciiname":"Goth Sona",
    "gn:country_code":"PK",
    "gn:dem":291,
    "gn:feature_class":"P",
    "gn:feature_code":"PPL",
    "gn:name":"Goth Sona",
    "gn:population":0,
    "gn:timezone":"Asia/Karachi",
    "iso:country":"PK",
    "wof:name":"Goth Sona",
    "wof:placetype":"locality"
},
  "geometry": {"coordinates":[67.35760000000001,25.36889],"type":"Point"}
}