{
  "type": "Feature",
  "properties": {
    "gn:admin1_code":"01",
    "gn:asciiname":"Ghunda Mela",
    "gn:country_code":"PK",
    "gn:dem":2104,
    "gn:feature_class":"P",
    "gn:feature_code":"PPL",
    "gn:name":"Ghunda Mela",
    "gn:population":0,
    "gn:timezone":"Asia/Karachi",
    "iso:country":"PK",
    "wof:name":"Ghunda Mela",
    "wof:placetype":"locality"
},
  "geometry": {"coordinates":[70.73307,33.73228],"type":"Point"}
}