{
  "type": "Feature",
  "properties": {
    "gn:admin1_code":"3.0",
    "gn:asciiname":"Teno Dag",
    "gn:country_code":"PK",
    "gn:dem":861,
    "gn:feature_class":"P",
    "gn:feature_code":"PPL",
    "gn:name":"Teno Dag",
    "gn:population":0,
    "gn:timezone":"Asia/Karachi",
    "iso:country":"PK",
    "name:und_x_variant":[
        "Tendo Dok"
    ],
    "wof:name":"Teno Dag",
    "wof:placetype":"locality"
},
  "geometry": {"coordinates":[72.28449000000001,34.73070999999999],"type":"Point"}
}