{
  "type": "Feature",
  "properties": {
    "gn:admin1_code":"4.0",
    "gn:asciiname":"Nalla",
    "gn:country_code":"PK",
    "gn:dem":1587,
    "gn:feature_class":"P",
    "gn:feature_code":"PPL",
    "gn:name":"Nalla",
    "gn:population":0,
    "gn:timezone":"Asia/Karachi",
    "iso:country":"PK",
    "name:eng_x_preferred":[
        "Nalla"
    ],
    "wof:name":"Nalla",
    "wof:placetype":"locality"
},
  "geometry": {"coordinates":[73.45126999999999,33.83423],"type":"Point"}
}