{
  "type": "Feature",
  "properties": {
    "gn:admin1_code":"4.0",
    "gn:asciiname":"Riazwala",
    "gn:country_code":"PK",
    "gn:dem":168,
    "gn:feature_class":"P",
    "gn:feature_code":"PPL",
    "gn:name":"Riazwala",
    "gn:population":0,
    "gn:timezone":"Asia/Karachi",
    "iso:country":"PK",
    "name:und_x_variant":[
        "Ri\u0101zw\u0101la"
    ],
    "wof:name":"Riazwala",
    "wof:placetype":"locality"
},
  "geometry": {"coordinates":[72.57561,31.5063],"type":"Point"}
}