{
  "type": "Feature",
  "properties": {
    "gn:admin1_code":"1.0",
    "gn:asciiname":"Zaga Dheri",
    "gn:country_code":"PK",
    "gn:dem":1050,
    "gn:feature_class":"P",
    "gn:feature_code":"PPL",
    "gn:name":"Zaga Dheri",
    "gn:population":0,
    "gn:timezone":"Asia/Karachi",
    "iso:country":"PK",
    "name:und_x_variant":[
        "Zaga Dherai",
        "Zaga Derai"
    ],
    "wof:name":"Zaga Dheri",
    "wof:placetype":"locality"
},
  "geometry": {"coordinates":[71.40496999999998,34.82155],"type":"Point"}
}