{
  "type": "Feature",
  "properties": {
    "gn:admin1_code":"4.0",
    "gn:asciiname":"Chak Fifty-five/Two Muhajir Branch",
    "gn:country_code":"PK",
    "gn:dem":185,
    "gn:feature_class":"P",
    "gn:feature_code":"PPL",
    "gn:name":"Chak Fifty-five/Two Muhajir Branch",
    "gn:population":0,
    "gn:timezone":"Asia/Karachi",
    "iso:country":"PK",
    "name:und_x_variant":[
        "Chak MB 55/2"
    ],
    "wof:name":"Chak Fifty-five/Two Muhajir Branch",
    "wof:placetype":"locality"
},
  "geometry": {"coordinates":[72.31107,32.35717],"type":"Point"}
}