{
  "type": "Feature",
  "properties": {
    "gn:admin1_code":"7.0",
    "gn:asciiname":"Jagwal Gali",
    "gn:country_code":"PK",
    "gn:dem":1817,
    "gn:feature_class":"P",
    "gn:feature_code":"PPL",
    "gn:name":"Jagwal Gali",
    "gn:population":0,
    "gn:timezone":"Asia/Karachi",
    "iso:country":"PK",
    "name:und_x_variant":[
        "J\u0101g\u012brgali"
    ],
    "wof:name":"Jagwal Gali",
    "wof:placetype":"locality"
},
  "geometry": {"coordinates":[73.44053000000002,35.65231],"type":"Point"}
}