{
  "type": "Feature",
  "properties": {
    "gn:admin1_code":"3",
    "gn:asciiname":"Shah Nur Lari",
    "gn:country_code":"PK",
    "gn:dem":846,
    "gn:feature_class":"P",
    "gn:feature_code":"PPL",
    "gn:name":"Shah Nur Lari",
    "gn:population":0,
    "gn:timezone":"Asia/Karachi",
    "iso:country":"PK",
    "name:und_x_variant":[
        "Sh\u0101h N\u016br Larhi"
    ],
    "wof:name":"Shah Nur Lari",
    "wof:placetype":"locality"
},
  "geometry": {"coordinates":[72.79486,34.23275],"type":"Point"}
}