{
  "type": "Feature",
  "properties": {
    "gn:admin1_code":"4",
    "gn:asciiname":"Basti Sinda",
    "gn:country_code":"PK",
    "gn:dem":170,
    "gn:feature_class":"P",
    "gn:feature_code":"PPL",
    "gn:name":"Basti Sinda",
    "gn:population":0,
    "gn:timezone":"Asia/Karachi",
    "iso:country":"PK",
    "name:und_x_variant":[
        "Basti Sando"
    ],
    "wof:name":"Basti Sinda",
    "wof:placetype":"locality"
},
  "geometry": {"coordinates":[71.05654,31.78045],"type":"Point"}
}