{
  "type": "Feature",
  "properties": {
    "gn:admin1_code":"5.0",
    "gn:asciiname":"Miso Kalhoro",
    "gn:country_code":"PK",
    "gn:dem":51,
    "gn:feature_class":"P",
    "gn:feature_code":"PPL",
    "gn:name":"Miso Kalhoro",
    "gn:population":0,
    "gn:timezone":"Asia/Karachi",
    "iso:country":"PK",
    "wof:name":"Miso Kalhoro",
    "wof:placetype":"locality"
},
  "geometry": {"coordinates":[68.02710999999999,27.61298],"type":"Point"}
}