{
  "type": "Feature",
  "properties": {
    "gn:admin1_code":"2.0",
    "gn:asciiname":"Kili Khair Din",
    "gn:country_code":"PK",
    "gn:dem":993,
    "gn:feature_class":"P",
    "gn:feature_code":"PPL",
    "gn:name":"Kili Khair Din",
    "gn:population":0,
    "gn:timezone":"Asia/Karachi",
    "iso:country":"PK",
    "wof:name":"Kili Khair Din",
    "wof:placetype":"locality"
},
  "geometry": {"coordinates":[65.45903,28.87456],"type":"Point"}
}