{
  "type": "Feature",
  "properties": {
    "gn:admin1_code":"7.0",
    "gn:asciiname":"Gulmitiao Harai",
    "gn:country_code":"PK",
    "gn:dem":3720,
    "gn:feature_class":"P",
    "gn:feature_code":"PPL",
    "gn:name":"Gulmitiao Harai",
    "gn:population":0,
    "gn:timezone":"Asia/Karachi",
    "iso:country":"PK",
    "wof:name":"Gulmitiao Harai",
    "wof:placetype":"locality"
},
  "geometry": {"coordinates":[73.65323000000002,35.96928],"type":"Point"}
}