{
  "type": "Feature",
  "properties": {
    "gn:admin1_code":"03",
    "gn:asciiname":"Patwar Bala",
    "gn:country_code":"PK",
    "gn:dem":328,
    "gn:feature_class":"P",
    "gn:feature_code":"PPL",
    "gn:name":"Patwar Bala",
    "gn:population":0,
    "gn:timezone":"Asia/Karachi",
    "iso:country":"PK",
    "name:und_x_variant":[
        "Patwar B\u0101la"
    ],
    "wof:name":"Patwar Bala",
    "wof:placetype":"locality"
},
  "geometry": {"coordinates":[71.48319000000002,34.08304],"type":"Point"}
}