{
  "type": "Feature",
  "properties": {
    "gn:admin1_code":"2.0",
    "gn:asciiname":"Yaqub Khan Brahui",
    "gn:country_code":"PK",
    "gn:dem":68,
    "gn:feature_class":"P",
    "gn:feature_code":"PPL",
    "gn:name":"Yaqub Khan Brahui",
    "gn:population":0,
    "gn:timezone":"Asia/Karachi",
    "iso:country":"PK",
    "name:und_x_variant":[
        "Yak\u016bb Kh\u0101n Br\u0101hui"
    ],
    "wof:name":"Yaqub Khan Brahui",
    "wof:placetype":"locality"
},
  "geometry": {"coordinates":[68.13042,28.49418],"type":"Point"}
}