{
  "type": "Feature",
  "properties": {
    "gn:admin1_code":"5.0",
    "gn:asciiname":"Ashiq Ali Khan",
    "gn:country_code":"PK",
    "gn:dem":47,
    "gn:feature_class":"P",
    "gn:feature_code":"PPL",
    "gn:name":"Ashiq Ali Khan",
    "gn:population":0,
    "gn:timezone":"Asia/Karachi",
    "iso:country":"PK",
    "wof:name":"Ashiq Ali Khan",
    "wof:placetype":"locality"
},
  "geometry": {"coordinates":[67.6806,27.84824],"type":"Point"}
}