{
  "type": "Feature",
  "properties": {
    "gn:admin1_code":"5.0",
    "gn:asciiname":"Pir Maha Wali",
    "gn:country_code":"PK",
    "gn:dem":32,
    "gn:feature_class":"P",
    "gn:feature_code":"PPL",
    "gn:name":"Pir Maha Wali",
    "gn:population":0,
    "gn:timezone":"Asia/Karachi",
    "iso:country":"PK",
    "wof:name":"Pir Maha Wali",
    "wof:placetype":"locality"
},
  "geometry": {"coordinates":[68.28783,26.06252000000001],"type":"Point"}
}