{
  "type": "Feature",
  "properties": {
    "gn:admin1_code":"5",
    "gn:asciiname":"Goth Wadero Haji Zubair Rajper",
    "gn:country_code":"PK",
    "gn:dem":49,
    "gn:feature_class":"P",
    "gn:feature_code":"PPL",
    "gn:name":"Goth Wadero Haji Zubair Rajper",
    "gn:population":0,
    "gn:timezone":"Asia/Karachi",
    "iso:country":"PK",
    "name:und_x_variant":[
        "H\u0101ji Zubair"
    ],
    "wof:name":"Goth Wadero Haji Zubair Rajper",
    "wof:placetype":"locality"
},
  "geometry": {"coordinates":[68.46285,27.04038],"type":"Point"}
}