{
  "type": "Feature",
  "properties": {
    "gn:admin1_code":"3",
    "gn:asciiname":"Kasai",
    "gn:country_code":"PK",
    "gn:dem":2372,
    "gn:feature_class":"P",
    "gn:feature_code":"PPL",
    "gn:name":"Kasai",
    "gn:population":0,
    "gn:timezone":"Asia/Karachi",
    "iso:country":"PK",
    "name:ara_x_preferred":[
        "\u0643\u0627\u0633\u0627\u064a"
    ],
    "name:cat_x_preferred":[
        "Kasai"
    ],
    "name:ceb_x_preferred":[
        "Kasai"
    ],
    "name:deu_x_preferred":[
        "Kasai"
    ],
    "name:eng_x_preferred":[
        "Kh\u0101rai"
    ],
    "name:epo_x_preferred":[
        "Kasai"
    ],
    "name:est_x_preferred":[
        "Kasai"
    ],
    "name:fra_x_preferred":[
        "Kasa\u00ef"
    ],
    "name:glg_x_preferred":[
        "Kasai"
    ],
    "name:hun_x_preferred":[
        "Kasai"
    ],
    "name:ita_x_preferred":[
        "Kasai"
    ],
    "name:jpn_x_preferred":[
        "\u30ab\u30b5\u30a4"
    ],
    "name:kor_x_preferred":[
        "\uac00\uc0ac\uc774"
    ],
    "name:lav_x_preferred":[
        "Kasai"
    ],
    "name:nld_x_preferred":[
        "Kasa\u00ef"
    ],
    "name:nor_x_preferred":[
        "Kasai"
    ],
    "name:pol_x_preferred":[
        "Kasai"
    ],
    "name:por_x_preferred":[
        "Kasai"
    ],
    "name:ron_x_preferred":[
        "Kasai"
    ],
    "name:rus_x_preferred":[
        "\u041a\u0430\u0441\u0430\u0439"
    ],
    "name:slk_x_preferred":[
        "Kasai"
    ],
    "name:spa_x_preferred":[
        "Kasai"
    ],
    "name:swe_x_preferred":[
        "Kasai"
    ],
    "wof:name":"Kasai",
    "wof:placetype":"locality"
},
  "geometry": {"coordinates":[71.55659,35.06739],"type":"Point"}
}