{
  "type": "Feature",
  "properties": {
    "gn:admin1_code":"3",
    "gn:asciiname":"Kasai",
    "gn:country_code":"PK",
    "gn:dem":2372,
    "gn:feature_class":"P",
    "gn:feature_code":"PPL",
    "gn:name":"Kasai",
    "gn:population":0,
    "gn:timezone":"Asia/Karachi",
    "iso:country":"PK",
    "name:eng_x_preferred":[
        "Kh\u0101rai"
    ],
    "wof:name":"Kasai",
    "wof:placetype":"locality"
},
  "geometry": {"coordinates":[71.55659,35.06739],"type":"Point"}
}