{
  "type": "Feature",
  "properties": {
    "gn:admin1_code":"2.0",
    "gn:asciiname":"Din Muhammad",
    "gn:country_code":"PK",
    "gn:dem":1500,
    "gn:feature_class":"P",
    "gn:feature_code":"PPL",
    "gn:name":"Din Muhammad",
    "gn:population":0,
    "gn:timezone":"Asia/Karachi",
    "iso:country":"PK",
    "wof:name":"Din Muhammad",
    "wof:placetype":"locality"
},
  "geometry": {"coordinates":[66.34481,28.03193],"type":"Point"}
}