{
  "type": "Feature",
  "properties": {
    "gn:admin1_code":"03",
    "gn:asciiname":"Surgul",
    "gn:country_code":"PK",
    "gn:dem":459,
    "gn:feature_class":"P",
    "gn:feature_code":"PPL",
    "gn:name":"Surgul",
    "gn:population":0,
    "gn:timezone":"Asia/Karachi",
    "iso:country":"PK",
    "wof:name":"Surgul",
    "wof:placetype":"locality"
},
  "geometry": {"coordinates":[71.38424999999999,33.51005],"type":"Point"}
}