{
  "type": "Feature",
  "properties": {
    "gn:admin1_code":"2",
    "gn:asciiname":"Kholigabad",
    "gn:country_code":"PK",
    "gn:dem":1690,
    "gn:feature_class":"P",
    "gn:feature_code":"PPL",
    "gn:name":"Kholigabad",
    "gn:population":0,
    "gn:timezone":"Asia/Karachi",
    "iso:country":"PK",
    "name:und_x_variant":[
        "Kh\u0101liq \u0100b\u0101d"
    ],
    "wof:name":"Kholigabad",
    "wof:placetype":"locality"
},
  "geometry": {"coordinates":[66.21235,28.37548],"type":"Point"}
}