{
  "type": "Feature",
  "properties": {
    "gn:admin1_code":"3.0",
    "gn:asciiname":"Khairabad",
    "gn:country_code":"PK",
    "gn:dem":344,
    "gn:feature_class":"P",
    "gn:feature_code":"PPL",
    "gn:name":"Khairabad",
    "gn:population":0,
    "gn:timezone":"Asia/Karachi",
    "iso:country":"PK",
    "name:ceb_x_preferred":[
        "Khairabad"
    ],
    "name:eng_x_preferred":[
        "Khairabad"
    ],
    "name:ita_x_preferred":[
        "Khairabad"
    ],
    "name:nld_x_preferred":[
        "Khairabad"
    ],
    "name:pol_x_preferred":[
        "Khairabad"
    ],
    "name:swe_x_preferred":[
        "Khairabad"
    ],
    "wof:name":"Khairabad",
    "wof:placetype":"locality"
},
  "geometry": {"coordinates":[72.20999,34.28842],"type":"Point"}
}