{
  "type": "Feature",
  "properties": {
    "gn:admin1_code":"4",
    "gn:asciiname":"Rahmunwala",
    "gn:country_code":"PK",
    "gn:dem":135,
    "gn:feature_class":"P",
    "gn:feature_code":"PPL",
    "gn:name":"Rahm\u016bnw\u0101la",
    "gn:population":0,
    "gn:timezone":"Asia/Karachi",
    "iso:country":"PK",
    "wof:name":"Rahmunwala",
    "wof:placetype":"locality"
},
  "geometry": {"coordinates":[71.24583,30.60833],"type":"Point"}
}