{
  "type": "Feature",
  "properties": {
    "gn:admin1_code":"01",
    "gn:asciiname":"Shana Khizai",
    "gn:country_code":"PK",
    "gn:dem":1501,
    "gn:feature_class":"P",
    "gn:feature_code":"PPL",
    "gn:name":"Shana Khizai",
    "gn:population":0,
    "gn:timezone":"Asia/Karachi",
    "iso:country":"PK",
    "name:und_x_variant":[
        "Shne Khizai"
    ],
    "wof:name":"Shana Khizai",
    "wof:placetype":"locality"
},
  "geometry": {"coordinates":[69.5491,32.8855],"type":"Point"}
}