{
  "type": "Feature",
  "properties": {
    "gn:admin1_code":"5.0",
    "gn:asciiname":"Otaq Muhammad Aslam",
    "gn:country_code":"PK",
    "gn:dem":17,
    "gn:feature_class":"P",
    "gn:feature_code":"PPL",
    "gn:name":"Otaq Muhammad Aslam",
    "gn:population":0,
    "gn:timezone":"Asia/Karachi",
    "iso:country":"PK",
    "wof:name":"Otaq Muhammad Aslam",
    "wof:placetype":"locality"
},
  "geometry": {"coordinates":[69.17411,25.64923],"type":"Point"}
}