{
  "type": "Feature",
  "properties": {
    "gn:admin1_code":"5.0",
    "gn:asciiname":"Goth Bakhu Sial",
    "gn:country_code":"PK",
    "gn:dem":51,
    "gn:feature_class":"P",
    "gn:feature_code":"PPL",
    "gn:name":"Goth Bakhu Sial",
    "gn:population":0,
    "gn:timezone":"Asia/Karachi",
    "iso:country":"PK",
    "name:und_x_variant":[
        "Si\u0101l",
        "Goth Bako Si\u0101l",
        "Bako Si\u0101l",
        "Goth Bakhu Sial"
    ],
    "wof:name":"Goth Bakhu Sial",
    "wof:placetype":"locality"
},
  "geometry": {"coordinates":[68.10069,27.96184],"type":"Point"}
}