{
  "type": "Feature",
  "properties": {
    "gn:admin1_code":"1.0",
    "gn:asciiname":"Wam Qazi Khel",
    "gn:country_code":"PK",
    "gn:dem":449,
    "gn:feature_class":"P",
    "gn:feature_code":"PPL",
    "gn:name":"Wam Qazi Khel",
    "gn:population":0,
    "gn:timezone":"Asia/Karachi",
    "iso:country":"PK",
    "wof:name":"Wam Qazi Khel",
    "wof:placetype":"locality"
},
  "geometry": {"coordinates":[70.55110999999999,33.07193],"type":"Point"}
}