{
  "type": "Feature",
  "properties": {
    "gn:admin1_code":"4.0",
    "gn:asciiname":"Sanjot",
    "gn:country_code":"PK",
    "gn:dem":524,
    "gn:feature_class":"P",
    "gn:feature_code":"PPL",
    "gn:name":"Sanjot",
    "gn:population":0,
    "gn:timezone":"Asia/Karachi",
    "iso:country":"PK",
    "name:und_x_variant":[
        "Sajot"
    ],
    "wof:name":"Sanjot",
    "wof:placetype":"locality"
},
  "geometry": {"coordinates":[73.24894,33.32494000000001],"type":"Point"}
}