{
  "type": "Feature",
  "properties": {
    "gn:admin1_code":"3",
    "gn:asciiname":"Pat Bandi",
    "gn:country_code":"PK",
    "gn:dem":810,
    "gn:feature_class":"P",
    "gn:feature_code":"PPL",
    "gn:name":"Pat Bandi",
    "gn:population":0,
    "gn:timezone":"Asia/Karachi",
    "iso:country":"PK",
    "name:und_x_variant":[
        "Put B\u0101ndi"
    ],
    "wof:name":"Pat Bandi",
    "wof:placetype":"locality"
},
  "geometry": {"coordinates":[72.78133000000003,34.29685],"type":"Point"}
}