{
  "type": "Feature",
  "properties": {
    "gn:admin1_code":"1.0",
    "gn:asciiname":"Sanki",
    "gn:country_code":"PK",
    "gn:dem":1032,
    "gn:feature_class":"P",
    "gn:feature_code":"PPL",
    "gn:name":"Sanki",
    "gn:population":0,
    "gn:timezone":"Asia/Karachi",
    "iso:country":"PK",
    "wof:name":"Sanki",
    "wof:placetype":"locality"
},
  "geometry": {"coordinates":[71.62313,34.62205],"type":"Point"}
}