{
  "type": "Feature",
  "properties": {
    "gn:admin1_code":"4.0",
    "gn:asciiname":"Hakim Muhammad Hussainwala",
    "gn:country_code":"PK",
    "gn:dem":165,
    "gn:feature_class":"P",
    "gn:feature_code":"PPL",
    "gn:name":"Hakim Muhammad Hussainwala",
    "gn:population":0,
    "gn:timezone":"Asia/Karachi",
    "iso:country":"PK",
    "wof:name":"Hakim Muhammad Hussainwala",
    "wof:placetype":"locality"
},
  "geometry": {"coordinates":[71.84144000000001,31.38609000000001],"type":"Point"}
}