{
  "type": "Feature",
  "properties": {
    "gn:admin1_code":"03",
    "gn:asciiname":"Kuz Shalkumbnai",
    "gn:country_code":"PK",
    "gn:dem":1308,
    "gn:feature_class":"P",
    "gn:feature_code":"PPL",
    "gn:name":"Kuz Shalkumbnai",
    "gn:population":0,
    "gn:timezone":"Asia/Karachi",
    "iso:country":"PK",
    "name:eng_x_preferred":[
        "Shalkanai"
    ],
    "wof:name":"Kuz Shalkumbnai",
    "wof:placetype":"locality"
},
  "geometry": {"coordinates":[71.99283,34.93782],"type":"Point"}
}