{
  "type": "Feature",
  "properties": {
    "gn:admin1_code":"03",
    "gn:asciiname":"Uch Wala",
    "gn:country_code":"PK",
    "gn:dem":322,
    "gn:feature_class":"P",
    "gn:feature_code":"PPL",
    "gn:name":"Uch Wala",
    "gn:population":0,
    "gn:timezone":"Asia/Karachi",
    "iso:country":"PK",
    "name:eng_x_preferred":[
        "Uchw\u0101la"
    ],
    "name:und_x_variant":[
        "Uchawala",
        "Uch Wala"
    ],
    "wof:name":"Uch Wala",
    "wof:placetype":"locality"
},
  "geometry": {"coordinates":[71.58484,34.19116],"type":"Point"}
}