{
  "type": "Feature",
  "properties": {
    "gn:admin1_code":"01",
    "gn:asciiname":"Bagh",
    "gn:country_code":"PK",
    "gn:dem":1528,
    "gn:feature_class":"P",
    "gn:feature_code":"PPL",
    "gn:name":"Bagh",
    "gn:population":0,
    "gn:timezone":"Asia/Karachi",
    "iso:country":"PK",
    "name:cat_x_preferred":[
        "Bagh"
    ],
    "name:ceb_x_preferred":[
        "Bagh"
    ],
    "name:deu_x_preferred":[
        "Bagh"
    ],
    "name:fas_x_preferred":[
        "\u0628\u0627\u063a"
    ],
    "name:hye_x_preferred":[
        "\u0532\u0561\u0572"
    ],
    "name:nld_x_preferred":[
        "Bagh"
    ],
    "name:swe_x_preferred":[
        "Bagh"
    ],
    "name:urd_x_preferred":[
        "\u0628\u0627\u063a"
    ],
    "wof:name":"Bagh",
    "wof:placetype":"locality"
},
  "geometry": {"coordinates":[70.57765000000001,33.60063],"type":"Point"}
}