{
  "type": "Feature",
  "properties": {
    "gn:admin1_code":"01",
    "gn:asciiname":"Bagh",
    "gn:country_code":"PK",
    "gn:dem":1528,
    "gn:feature_class":"P",
    "gn:feature_code":"PPL",
    "gn:name":"Bagh",
    "gn:population":0,
    "gn:timezone":"Asia/Karachi",
    "iso:country":"PK",
    "wof:name":"Bagh",
    "wof:placetype":"locality"
},
  "geometry": {"coordinates":[70.57765000000001,33.60063],"type":"Point"}
}