{
  "type": "Feature",
  "properties": {
    "gn:admin1_code":"5",
    "gn:asciiname":"Goth Haji Mubarak",
    "gn:country_code":"PK",
    "gn:dem":31,
    "gn:feature_class":"P",
    "gn:feature_code":"PPL",
    "gn:name":"Goth Haji Mubarak",
    "gn:population":0,
    "gn:timezone":"Asia/Karachi",
    "iso:country":"PK",
    "name:und_x_variant":[
        "Goth Khuda Bakhsh Makr\u0101ni",
        "Goth Q\u0101sim Makr\u0101ni"
    ],
    "wof:name":"Goth Haji Mubarak",
    "wof:placetype":"locality"
},
  "geometry": {"coordinates":[68.60619,25.76789],"type":"Point"}
}