{
  "type": "Feature",
  "properties": {
    "gn:admin1_code":"4",
    "gn:asciiname":"Hotewala",
    "gn:country_code":"PK",
    "gn:dem":186,
    "gn:feature_class":"P",
    "gn:feature_code":"PPL",
    "gn:name":"Hotewala",
    "gn:population":0,
    "gn:timezone":"Asia/Karachi",
    "iso:country":"PK",
    "name:und_x_variant":[
        "Hotw\u0101la"
    ],
    "wof:name":"Hotewala",
    "wof:placetype":"locality"
},
  "geometry": {"coordinates":[71.23966999999998,31.91929],"type":"Point"}
}