{
  "type": "Feature",
  "properties": {
    "gn:admin1_code":"2",
    "gn:asciiname":"Kumbi",
    "gn:country_code":"PK",
    "gn:dem":1713,
    "gn:feature_class":"P",
    "gn:feature_code":"PPL",
    "gn:name":"Kumbi",
    "gn:population":0,
    "gn:timezone":"Asia/Karachi",
    "iso:country":"PK",
    "wof:name":"Kumbi",
    "wof:placetype":"locality"
},
  "geometry": {"coordinates":[66.55833,29.55556],"type":"Point"}
}