{
  "type": "Feature",
  "properties": {
    "gn:admin1_code":"2",
    "gn:asciiname":"Kumbi",
    "gn:country_code":"PK",
    "gn:dem":1713,
    "gn:feature_class":"P",
    "gn:feature_code":"PPL",
    "gn:name":"Kumbi",
    "gn:population":0,
    "gn:timezone":"Asia/Karachi",
    "iso:country":"PK",
    "name:ben_x_preferred":[
        "\u0995\u09c1\u09ae\u09cd\u09ac\u09bf"
    ],
    "name:ceb_x_preferred":[
        "Kumbi"
    ],
    "name:ita_x_preferred":[
        "Kumbi"
    ],
    "name:mlg_x_preferred":[
        "Kumbi"
    ],
    "name:msa_x_preferred":[
        "Kumbi"
    ],
    "name:new_x_preferred":[
        "\u0915\u0941\u092e\u094d\u092c\u0940"
    ],
    "name:nld_x_preferred":[
        "Kumbi"
    ],
    "name:pol_x_preferred":[
        "Kumbi"
    ],
    "name:swe_x_preferred":[
        "Kumbi"
    ],
    "name:vie_x_preferred":[
        "Kumbi"
    ],
    "name:zho_x_preferred":[
        "\u5e93\u59c6\u6bd4"
    ],
    "wof:name":"Kumbi",
    "wof:placetype":"locality"
},
  "geometry": {"coordinates":[66.55833,29.55556],"type":"Point"}
}