{
  "type": "Feature",
  "properties": {
    "gn:admin1_code":"6.0",
    "gn:asciiname":"Suri",
    "gn:country_code":"PK",
    "gn:dem":1242,
    "gn:feature_class":"P",
    "gn:feature_code":"PPL",
    "gn:name":"Suri",
    "gn:population":0,
    "gn:timezone":"Asia/Karachi",
    "iso:country":"PK",
    "name:cat_x_preferred":[
        "Suri"
    ],
    "name:ceb_x_preferred":[
        "Suri"
    ],
    "name:deu_x_preferred":[
        "Suri"
    ],
    "name:fas_x_preferred":[
        "\u0633\u0648\u0631\u06cc"
    ],
    "name:ita_x_preferred":[
        "Suri"
    ],
    "name:lav_x_preferred":[
        "Suri"
    ],
    "name:new_x_preferred":[
        "\u0938\u0941\u0930\u0940"
    ],
    "name:rus_x_preferred":[
        "\u0421\u0443\u0440\u0438"
    ],
    "name:spa_x_preferred":[
        "Suri"
    ],
    "name:swe_x_preferred":[
        "Suri"
    ],
    "name:vie_x_preferred":[
        "Suri"
    ],
    "wof:name":"Suri",
    "wof:placetype":"locality"
},
  "geometry": {"coordinates":[73.73651,33.65885],"type":"Point"}
}