{
  "type": "Feature",
  "properties": {
    "gn:admin1_code":"6.0",
    "gn:asciiname":"Suri",
    "gn:country_code":"PK",
    "gn:dem":1242,
    "gn:feature_class":"P",
    "gn:feature_code":"PPL",
    "gn:name":"Suri",
    "gn:population":0,
    "gn:timezone":"Asia/Karachi",
    "iso:country":"PK",
    "wof:name":"Suri",
    "wof:placetype":"locality"
},
  "geometry": {"coordinates":[73.73651,33.65885],"type":"Point"}
}