{
  "type": "Feature",
  "properties": {
    "gn:admin1_code":"03",
    "gn:asciiname":"Kilris",
    "gn:country_code":"PK",
    "gn:dem":370,
    "gn:feature_class":"P",
    "gn:feature_code":"PPL",
    "gn:name":"Kilris",
    "gn:population":0,
    "gn:timezone":"Asia/Karachi",
    "iso:country":"PK",
    "wof:name":"Kilris",
    "wof:placetype":"locality"
},
  "geometry": {"coordinates":[70.61389,32.98056],"type":"Point"}
}