{
  "type": "Feature",
  "properties": {
    "gn:admin1_code":"4",
    "gn:asciiname":"Ramza Shaikhani",
    "gn:country_code":"PK",
    "gn:dem":119,
    "gn:feature_class":"P",
    "gn:feature_code":"PPL",
    "gn:name":"Ramza Shaikhani",
    "gn:population":0,
    "gn:timezone":"Asia/Karachi",
    "iso:country":"PK",
    "name:eng_x_preferred":[
        "Ramza Shaikhani"
    ],
    "wof:name":"Ramza Shaikhani",
    "wof:placetype":"locality"
},
  "geometry": {"coordinates":[70.80703000000003,30.01967],"type":"Point"}
}