{
  "type": "Feature",
  "properties": {
    "gn:admin1_code":"5.0",
    "gn:asciiname":"Bhai Khan Sirai",
    "gn:country_code":"PK",
    "gn:dem":13,
    "gn:feature_class":"P",
    "gn:feature_code":"PPL",
    "gn:name":"Bhai Khan Sirai",
    "gn:population":0,
    "gn:timezone":"Asia/Karachi",
    "iso:country":"PK",
    "name:eng_x_preferred":[
        "G\u0101hi Kh\u0101n Sar\u0101i"
    ],
    "wof:name":"Bhai Khan Sirai",
    "wof:placetype":"locality"
},
  "geometry": {"coordinates":[68.04921,24.62662000000001],"type":"Point"}
}