{
  "type": "Feature",
  "properties": {
    "gn:admin1_code":"4.0",
    "gn:asciiname":"Bulewala",
    "gn:country_code":"PK",
    "gn:dem":102,
    "gn:feature_class":"P",
    "gn:feature_code":"PPL",
    "gn:name":"Bulewala",
    "gn:population":0,
    "gn:timezone":"Asia/Karachi",
    "iso:country":"PK",
    "name:und_x_variant":[
        "B\u016blew\u0101la"
    ],
    "wof:name":"Bulewala",
    "wof:placetype":"locality"
},
  "geometry": {"coordinates":[70.5966,29.46038],"type":"Point"}
}