{
  "type": "Feature",
  "properties": {
    "gn:admin1_code":"6.0",
    "gn:asciiname":"Barothan",
    "gn:country_code":"PK",
    "gn:dem":775,
    "gn:feature_class":"P",
    "gn:feature_code":"PPL",
    "gn:name":"Barothan",
    "gn:population":0,
    "gn:timezone":"Asia/Karachi",
    "iso:country":"PK",
    "name:und_x_variant":[
        "Baroti\u0101n"
    ],
    "wof:name":"Barothan",
    "wof:placetype":"locality"
},
  "geometry": {"coordinates":[73.74558,33.43134000000001],"type":"Point"}
}