{
  "type": "Feature",
  "properties": {
    "gn:admin1_code":"02",
    "gn:asciiname":"Asp Gaz Bazar",
    "gn:country_code":"PK",
    "gn:dem":35,
    "gn:feature_class":"P",
    "gn:feature_code":"PPL",
    "gn:name":"Asp Gaz Bazar",
    "gn:population":0,
    "gn:timezone":"Asia/Karachi",
    "iso:country":"PK",
    "name:und_x_variant":[
        "Asp Gaz",
        "Rikti",
        "Rikri",
        "Asp Gaz Bazar"
    ],
    "wof:name":"Asp Gaz Bazar",
    "wof:placetype":"locality"
},
  "geometry": {"coordinates":[62.26642,25.66963],"type":"Point"}
}