{
  "type": "Feature",
  "properties": {
    "gn:admin1_code":"2.0",
    "gn:asciiname":"Kili Bangal Khan",
    "gn:country_code":"PK",
    "gn:dem":1907,
    "gn:feature_class":"P",
    "gn:feature_code":"PPL",
    "gn:name":"Kili Bangal Khan",
    "gn:population":0,
    "gn:timezone":"Asia/Karachi",
    "iso:country":"PK",
    "wof:name":"Kili Bangal Khan",
    "wof:placetype":"locality"
},
  "geometry": {"coordinates":[67.24800999999999,30.04596],"type":"Point"}
}