{
  "type": "Feature",
  "properties": {
    "gn:admin1_code":"4.0",
    "gn:asciiname":"Sarwai",
    "gn:country_code":"PK",
    "gn:dem":407,
    "gn:feature_class":"P",
    "gn:feature_code":"PPL",
    "gn:name":"Sarwai",
    "gn:population":0,
    "gn:timezone":"Asia/Karachi",
    "iso:country":"PK",
    "name:und_x_variant":[
        "Sarw\u0101li"
    ],
    "wof:name":"Sarwai",
    "wof:placetype":"locality"
},
  "geometry": {"coordinates":[72.20824,33.1647],"type":"Point"}
}