{
  "type": "Feature",
  "properties": {
    "gn:admin1_code":"4.0",
    "gn:asciiname":"Chak Five Hundred Thirty-one Gugera Branch",
    "gn:country_code":"PK",
    "gn:dem":175,
    "gn:feature_class":"P",
    "gn:feature_code":"PPL",
    "gn:name":"Chak Five Hundred Thirty-one Gugera Branch",
    "gn:population":0,
    "gn:timezone":"Asia/Karachi",
    "iso:country":"PK",
    "name:und_x_variant":[
        "Chak Dhilw\u0101n",
        "Dhalw\u0101n"
    ],
    "wof:name":"Chak Five Hundred Thirty-one Gugera Branch",
    "wof:placetype":"locality"
},
  "geometry": {"coordinates":[72.85646,31.13962],"type":"Point"}
}