{
  "type": "Feature",
  "properties": {
    "gn:admin1_code":"4.0",
    "gn:asciiname":"Chandiawala",
    "gn:country_code":"PK",
    "gn:dem":145,
    "gn:feature_class":"P",
    "gn:feature_code":"PPL",
    "gn:name":"Chandiawala",
    "gn:population":0,
    "gn:timezone":"Asia/Karachi",
    "iso:country":"PK",
    "name:fas_x_preferred":[
        "\u0686\u0646\u062f\u06cc\u0627\u0648\u0627\u0644\u0627"
    ],
    "wof:name":"Chandiawala",
    "wof:placetype":"locality"
},
  "geometry": {"coordinates":[70.90291999999999,30.96659],"type":"Point"}
}