{
  "type": "Feature",
  "properties": {
    "gn:admin1_code":"2.0",
    "gn:asciiname":"Nazub",
    "gn:country_code":"PK",
    "gn:dem":1642,
    "gn:feature_class":"P",
    "gn:feature_code":"PPL",
    "gn:name":"Nazub",
    "gn:population":0,
    "gn:timezone":"Asia/Karachi",
    "iso:country":"PK",
    "name:eng_x_preferred":[
        "Nazub"
    ],
    "name:und_x_variant":[
        "Ghul\u0101m Nabi"
    ],
    "wof:name":"Nazub",
    "wof:placetype":"locality"
},
  "geometry": {"coordinates":[67.10098000000001,30.61758],"type":"Point"}
}