{
  "type": "Feature",
  "properties": {
    "gn:admin1_code":"5",
    "gn:asciiname":"Goth Jahan Khan",
    "gn:country_code":"PK",
    "gn:dem":63,
    "gn:feature_class":"P",
    "gn:feature_code":"PPL",
    "gn:name":"Goth Jahan Khan",
    "gn:population":0,
    "gn:timezone":"Asia/Karachi",
    "iso:country":"PK",
    "name:und_x_variant":[
        "Goth J\u0101n Kh\u0101n"
    ],
    "wof:name":"Goth Jahan Khan",
    "wof:placetype":"locality"
},
  "geometry": {"coordinates":[68.43748000000001,27.69757],"type":"Point"}
}