{
  "type": "Feature",
  "properties": {
    "gn:admin1_code":"7.0",
    "gn:asciiname":"Gulmit",
    "gn:country_code":"PK",
    "gn:dem":2480,
    "gn:feature_class":"P",
    "gn:feature_code":"PPL",
    "gn:name":"Gulmit",
    "gn:population":0,
    "gn:timezone":"Asia/Karachi",
    "iso:country":"PK",
    "name:fas_x_preferred":[
        "\u06af\u0644\u0645\u06cc\u062a"
    ],
    "name:hin_x_preferred":[
        "\u0917\u0941\u0932\u092e\u093f\u0924"
    ],
    "name:ita_x_preferred":[
        "Gulmit"
    ],
    "name:rus_x_preferred":[
        "\u0413\u0443\u043b\u044c\u043c\u0438\u0442"
    ],
    "name:urd_x_preferred":[
        "\u06af\u0644\u0645\u06cc\u062a"
    ],
    "name:vie_x_preferred":[
        "Gulmit"
    ],
    "wof:name":"Gulmit",
    "wof:placetype":"locality"
},
  "geometry": {"coordinates":[74.86448,36.38764000000001],"type":"Point"}
}