{
  "type": "Feature",
  "properties": {
    "gn:admin1_code":"7.0",
    "gn:asciiname":"Gulmit",
    "gn:country_code":"PK",
    "gn:dem":2480,
    "gn:feature_class":"P",
    "gn:feature_code":"PPL",
    "gn:name":"Gulmit",
    "gn:population":0,
    "gn:timezone":"Asia/Karachi",
    "iso:country":"PK",
    "wof:name":"Gulmit",
    "wof:placetype":"locality"
},
  "geometry": {"coordinates":[74.86448,36.38764000000001],"type":"Point"}
}