{
  "type": "Feature",
  "properties": {
    "gn:admin1_code":"4",
    "gn:asciiname":"Shekhpur",
    "gn:country_code":"PK",
    "gn:dem":232,
    "gn:feature_class":"P",
    "gn:feature_code":"PPL",
    "gn:name":"Shekhpur",
    "gn:population":0,
    "gn:timezone":"Asia/Karachi",
    "iso:country":"PK",
    "name:und_x_variant":[
        "Shekhupur"
    ],
    "wof:name":"Shekhpur",
    "wof:placetype":"locality"
},
  "geometry": {"coordinates":[74.70741,32.10682],"type":"Point"}
}