{
  "type": "Feature",
  "properties": {
    "gn:admin1_code":"6",
    "gn:asciiname":"Riali",
    "gn:country_code":"PK",
    "gn:dem":1656,
    "gn:feature_class":"P",
    "gn:feature_code":"PPL",
    "gn:name":"Riali",
    "gn:population":0,
    "gn:timezone":"Asia/Karachi",
    "iso:country":"PK",
    "wof:name":"Riali",
    "wof:placetype":"locality"
},
  "geometry": {"coordinates":[73.49120000000001,34.51932],"type":"Point"}
}