{
  "type": "Feature",
  "properties": {
    "gn:admin1_code":"3",
    "gn:asciiname":"Darukai",
    "gn:country_code":"PK",
    "gn:dem":1401,
    "gn:feature_class":"P",
    "gn:feature_code":"PPL",
    "gn:name":"Darukai",
    "gn:population":0,
    "gn:timezone":"Asia/Karachi",
    "iso:country":"PK",
    "name:und_x_variant":[
        "Dar\u016bkal"
    ],
    "wof:name":"Darukai",
    "wof:placetype":"locality"
},
  "geometry": {"coordinates":[72.0716,34.9203],"type":"Point"}
}