{
  "type": "Feature",
  "properties": {
    "gn:admin1_code":"6",
    "gn:asciiname":"Bhatakot",
    "gn:country_code":"PK",
    "gn:dem":1345,
    "gn:feature_class":"P",
    "gn:feature_code":"PPL",
    "gn:name":"Bhatakot",
    "gn:population":0,
    "gn:timezone":"Asia/Karachi",
    "iso:country":"PK",
    "name:und_x_variant":[
        "Bh\u0101ta"
    ],
    "wof:name":"Bhatakot",
    "wof:placetype":"locality"
},
  "geometry": {"coordinates":[74.13207,33.4753],"type":"Point"}
}