{
  "type": "Feature",
  "properties": {
    "gn:admin1_code":"4.0",
    "gn:asciiname":"Khadral",
    "gn:country_code":"PK",
    "gn:dem":275,
    "gn:feature_class":"P",
    "gn:feature_code":"PPL",
    "gn:name":"Khadral",
    "gn:population":0,
    "gn:timezone":"Asia/Karachi",
    "iso:country":"PK",
    "wof:name":"Khadral",
    "wof:placetype":"locality"
},
  "geometry": {"coordinates":[74.83704,32.4634],"type":"Point"}
}