{
  "type": "Feature",
  "properties": {
    "gn:admin1_code":"01",
    "gn:asciiname":"Shawagara",
    "gn:country_code":"PK",
    "gn:dem":1485,
    "gn:feature_class":"P",
    "gn:feature_code":"PPL",
    "gn:name":"Shawagara",
    "gn:population":0,
    "gn:timezone":"Asia/Karachi",
    "iso:country":"PK",
    "name:und_x_variant":[
        "Shawa Gara"
    ],
    "wof:name":"Shawagara",
    "wof:placetype":"locality"
},
  "geometry": {"coordinates":[69.5519,32.88289],"type":"Point"}
}