{
  "type": "Feature",
  "properties": {
    "gn:admin1_code":"3.0",
    "gn:asciiname":"Asaldad Kalle",
    "gn:country_code":"PK",
    "gn:dem":424,
    "gn:feature_class":"P",
    "gn:feature_code":"PPL",
    "gn:name":"Asaldad Kalle",
    "gn:population":0,
    "gn:timezone":"Asia/Karachi",
    "iso:country":"PK",
    "name:und_x_variant":[
        "Asald\u0101d"
    ],
    "wof:name":"Asaldad Kalle",
    "wof:placetype":"locality"
},
  "geometry": {"coordinates":[70.49988,32.95537],"type":"Point"}
}