{
  "type": "Feature",
  "properties": {
    "gn:admin1_code":"3",
    "gn:asciiname":"Gujar Banda",
    "gn:country_code":"PK",
    "gn:dem":2991,
    "gn:feature_class":"P",
    "gn:feature_code":"PPL",
    "gn:name":"Gujar Banda",
    "gn:population":0,
    "gn:timezone":"Asia/Karachi",
    "iso:country":"PK",
    "name:eng_x_preferred":[
        "Gujar Banda"
    ],
    "wof:name":"Gujar Banda",
    "wof:placetype":"locality"
},
  "geometry": {"coordinates":[71.92263,35.29802],"type":"Point"}
}