{
  "type": "Feature",
  "properties": {
    "gn:admin1_code":"2.0",
    "gn:asciiname":"Kili Shabak",
    "gn:country_code":"PK",
    "gn:dem":1776,
    "gn:feature_class":"P",
    "gn:feature_code":"PPL",
    "gn:name":"Kili Shabak",
    "gn:population":0,
    "gn:timezone":"Asia/Karachi",
    "iso:country":"PK",
    "name:und_x_variant":[
        "Shebak Kile",
        "Kili Shabak"
    ],
    "wof:name":"Kili Shabak",
    "wof:placetype":"locality"
},
  "geometry": {"coordinates":[67.06761999999999,30.29111],"type":"Point"}
}