{
  "type": "Feature",
  "properties": {
    "gn:admin1_code":"3",
    "gn:asciiname":"Pallo Kanda",
    "gn:country_code":"PK",
    "gn:dem":370,
    "gn:feature_class":"P",
    "gn:feature_code":"PPL",
    "gn:name":"Pallo Kanda",
    "gn:population":0,
    "gn:timezone":"Asia/Karachi",
    "iso:country":"PK",
    "name:eng_x_preferred":[
        "Pallo Kandar"
    ],
    "wof:name":"Pallo Kanda",
    "wof:placetype":"locality"
},
  "geometry": {"coordinates":[72.30616999999999,34.3492],"type":"Point"}
}