{
  "type": "Feature",
  "properties": {
    "gn:admin1_code":"4.0",
    "gn:asciiname":"Chak One Hundred Seventy-four",
    "gn:country_code":"PK",
    "gn:dem":159,
    "gn:feature_class":"P",
    "gn:feature_code":"PPL",
    "gn:name":"Chak One Hundred Seventy-four",
    "gn:population":0,
    "gn:timezone":"Asia/Karachi",
    "iso:country":"PK",
    "name:und_x_variant":[
        "Bharw\u0101na",
        "Chak 174",
        "Chak One Hundred Seventy-four"
    ],
    "wof:name":"Chak One Hundred Seventy-four",
    "wof:placetype":"locality"
},
  "geometry": {"coordinates":[72.48654000000001,31.32626],"type":"Point"}
}