{
  "type": "Feature",
  "properties": {
    "gn:admin1_code":"5",
    "gn:asciiname":"Naukot",
    "gn:country_code":"PK",
    "gn:dem":73,
    "gn:feature_class":"P",
    "gn:feature_code":"PPL",
    "gn:name":"Naukot",
    "gn:population":0,
    "gn:timezone":"Asia/Karachi",
    "iso:country":"PK",
    "name:und_x_variant":[
        "N\u0101okot"
    ],
    "wof:name":"Naukot",
    "wof:placetype":"locality"
},
  "geometry": {"coordinates":[69.63476999999999,28.04227],"type":"Point"}
}