{
  "type": "Feature",
  "properties": {
    "gn:admin1_code":"4",
    "gn:asciiname":"Sanarewala",
    "gn:country_code":"PK",
    "gn:dem":148,
    "gn:feature_class":"P",
    "gn:feature_code":"PPL",
    "gn:name":"Sanarewala",
    "gn:population":0,
    "gn:timezone":"Asia/Karachi",
    "iso:country":"PK",
    "wof:name":"Sanarewala",
    "wof:placetype":"locality"
},
  "geometry": {"coordinates":[72.19041,31.11998],"type":"Point"}
}