{
  "type": "Feature",
  "properties": {
    "gn:admin1_code":"4",
    "gn:asciiname":"Suianwala",
    "gn:country_code":"PK",
    "gn:dem":137,
    "gn:feature_class":"P",
    "gn:feature_code":"PPL",
    "gn:name":"Sui\u0101nw\u0101la",
    "gn:population":0,
    "gn:timezone":"Asia/Karachi",
    "iso:country":"PK",
    "name:und_x_variant":[
        "Sui\u0101nw\u0101la",
        "Suhi\u0101nw\u0101la"
    ],
    "wof:name":"Suianwala",
    "wof:placetype":"locality"
},
  "geometry": {"coordinates":[71.17281,30.62325],"type":"Point"}
}