{
  "type": "Feature",
  "properties": {
    "gn:admin1_code":"4",
    "gn:asciiname":"Bhekalwali",
    "gn:country_code":"PK",
    "gn:dem":695,
    "gn:feature_class":"P",
    "gn:feature_code":"PPL",
    "gn:name":"Bhekalwali",
    "gn:population":0,
    "gn:timezone":"Asia/Karachi",
    "iso:country":"PK",
    "wof:name":"Bhekalwali",
    "wof:placetype":"locality"
},
  "geometry": {"coordinates":[71.93519000000001,32.52171],"type":"Point"}
}