{
  "type": "Feature",
  "properties": {
    "gn:admin1_code":"5",
    "gn:asciiname":"Rawat Chandio",
    "gn:country_code":"PK",
    "gn:dem":12,
    "gn:feature_class":"P",
    "gn:feature_code":"PPL",
    "gn:name":"Rawat Chandio",
    "gn:population":0,
    "gn:timezone":"Asia/Karachi",
    "iso:country":"PK",
    "name:und_x_variant":[
        "Rawat Ch\u0101ndia"
    ],
    "wof:name":"Rawat Chandio",
    "wof:placetype":"locality"
},
  "geometry": {"coordinates":[69.12474,24.83853],"type":"Point"}
}