{
  "type": "Feature",
  "properties": {
    "gn:admin1_code":"4.0",
    "gn:asciiname":"Chak Seventy-nine -Twelve Left",
    "gn:country_code":"PK",
    "gn:dem":143,
    "gn:feature_class":"P",
    "gn:feature_code":"PPL",
    "gn:name":"Chak Seventy-nine -Twelve Left",
    "gn:population":0,
    "gn:timezone":"Asia/Karachi",
    "iso:country":"PK",
    "name:und_x_variant":[
        "Khaibar"
    ],
    "wof:name":"Chak Seventy-nine -Twelve Left",
    "wof:placetype":"locality"
},
  "geometry": {"coordinates":[72.46764,30.25016],"type":"Point"}
}