{
  "type": "Feature",
  "properties": {
    "gn:admin1_code":"3.0",
    "gn:asciiname":"Bong",
    "gn:country_code":"PK",
    "gn:dem":1954,
    "gn:feature_class":"P",
    "gn:feature_code":"PPL",
    "gn:name":"Bong",
    "gn:population":0,
    "gn:timezone":"Asia/Karachi",
    "iso:country":"PK",
    "wof:name":"Bong",
    "wof:placetype":"locality"
},
  "geometry": {"coordinates":[72.94195000000001,35.40215],"type":"Point"}
}