{
  "type": "Feature",
  "properties": {
    "gn:admin1_code":"2.0",
    "gn:asciiname":"Safi Bund",
    "gn:country_code":"PK",
    "gn:dem":1258,
    "gn:feature_class":"P",
    "gn:feature_code":"PPL",
    "gn:name":"Safi Bund",
    "gn:population":0,
    "gn:timezone":"Asia/Karachi",
    "iso:country":"PK",
    "wof:name":"Safi Bund",
    "wof:placetype":"locality"
},
  "geometry": {"coordinates":[69.77053000000001,30.04588],"type":"Point"}
}