{
  "type": "Feature",
  "properties": {
    "gn:admin1_code":"4.0",
    "gn:asciiname":"Mian Shahbazwala",
    "gn:country_code":"PK",
    "gn:dem":357,
    "gn:feature_class":"P",
    "gn:feature_code":"PPL",
    "gn:name":"Mian Shahbazwala",
    "gn:population":0,
    "gn:timezone":"Asia/Karachi",
    "iso:country":"PK",
    "wof:name":"Mian Shahbazwala",
    "wof:placetype":"locality"
},
  "geometry": {"coordinates":[71.85939999999999,32.75072],"type":"Point"}
}