{
  "type": "Feature",
  "properties": {
    "gn:admin1_code":"2.0",
    "gn:asciiname":"Kili Abdul Karim",
    "gn:country_code":"PK",
    "gn:dem":1669,
    "gn:feature_class":"P",
    "gn:feature_code":"PPL",
    "gn:name":"Kili Abdul Karim",
    "gn:population":0,
    "gn:timezone":"Asia/Karachi",
    "iso:country":"PK",
    "wof:name":"Kili Abdul Karim",
    "wof:placetype":"locality"
},
  "geometry": {"coordinates":[66.19592,28.05757],"type":"Point"}
}