{
  "type": "Feature",
  "properties": {
    "gn:admin1_code":"2.0",
    "gn:asciiname":"Bismillah Kili",
    "gn:country_code":"PK",
    "gn:dem":1470,
    "gn:feature_class":"P",
    "gn:feature_code":"PPL",
    "gn:name":"Bismillah Kili",
    "gn:population":0,
    "gn:timezone":"Asia/Karachi",
    "iso:country":"PK",
    "name:und_x_variant":[
        "Bismill\u0101h"
    ],
    "wof:name":"Bismillah Kili",
    "wof:placetype":"locality"
},
  "geometry": {"coordinates":[66.47747,30.46778],"type":"Point"}
}