{
  "type": "Feature",
  "properties": {
    "gn:admin1_code":"4",
    "gn:asciiname":"Machadiwala",
    "gn:country_code":"PK",
    "gn:dem":169,
    "gn:feature_class":"P",
    "gn:feature_code":"PPL",
    "gn:name":"Machadiwala",
    "gn:population":0,
    "gn:timezone":"Asia/Karachi",
    "iso:country":"PK",
    "name:und_x_variant":[
        "Ch\u0101h Machand\u012bw\u0101la"
    ],
    "wof:name":"Machadiwala",
    "wof:placetype":"locality"
},
  "geometry": {"coordinates":[71.06647,31.69268],"type":"Point"}
}