{
  "type": "Feature",
  "properties": {
    "gn:admin1_code":"3",
    "gn:asciiname":"Shaona",
    "gn:country_code":"PK",
    "gn:dem":2271,
    "gn:feature_class":"P",
    "gn:feature_code":"PPL",
    "gn:name":"Shaona",
    "gn:population":0,
    "gn:timezone":"Asia/Karachi",
    "iso:country":"PK",
    "wof:name":"Shaona",
    "wof:placetype":"locality"
},
  "geometry": {"coordinates":[72.60753000000003,35.13697],"type":"Point"}
}