{
  "type": "Feature",
  "properties": {
    "gn:admin1_code":"1.0",
    "gn:asciiname":"Ardu",
    "gn:country_code":"PK",
    "gn:dem":550,
    "gn:feature_class":"P",
    "gn:feature_code":"PPL",
    "gn:name":"Ardu",
    "gn:population":0,
    "gn:timezone":"Asia/Karachi",
    "iso:country":"PK",
    "name:ceb_x_preferred":[
        "Ardu"
    ],
    "name:est_x_preferred":[
        "Ardu"
    ],
    "name:fra_x_preferred":[
        "Ardu"
    ],
    "name:hye_x_preferred":[
        "\u0531\u057c\u0564\u0578\u0582"
    ],
    "name:pol_x_preferred":[
        "Ardu"
    ],
    "name:rus_x_preferred":[
        "\u0410\u0440\u0434\u0443"
    ],
    "name:sco_x_preferred":[
        "Ardu"
    ],
    "name:spa_x_preferred":[
        "Ardu"
    ],
    "name:swe_x_preferred":[
        "Ardu"
    ],
    "name:und_x_variant":[
        "Urdu Sazo Mela",
        "Urdu",
        "Sazo Mela"
    ],
    "name:vol_x_preferred":[
        "Ardu"
    ],
    "wof:name":"Ardu",
    "wof:placetype":"locality"
},
  "geometry": {"coordinates":[71.66418,33.75305],"type":"Point"}
}