{
  "type": "Feature",
  "properties": {
    "gn:admin1_code":"4",
    "gn:asciiname":"Tarkhanwala",
    "gn:country_code":"PK",
    "gn:dem":199,
    "gn:feature_class":"P",
    "gn:feature_code":"PPL",
    "gn:name":"Tarkhanwala",
    "gn:population":0,
    "gn:timezone":"Asia/Karachi",
    "iso:country":"PK",
    "name:und_x_variant":[
        "Tarkh\u0101n\u0101nw\u0101la"
    ],
    "wof:name":"Tarkhanwala",
    "wof:placetype":"locality"
},
  "geometry": {"coordinates":[73.93048,31.43279],"type":"Point"}
}