{
  "type": "Feature",
  "properties": {
    "iso:country":"PK",
    "name:eng_x_preferred":[
        "Patel-ka-bara"
    ],
    "qs:gn_adm0_cc":"PK",
    "qs:gn_local":1174872,
    "qs:gn_nam_loc":"Karachi, Sindh, PK",
    "qs:gn_namadm1":"05",
    "qs:local_max":2851,
    "qs:local_sum":5348,
    "qs:localhoods":21,
    "qs:name":"Patel-ka-bara",
    "qs:name_adm0":"Pakistan",
    "qs:name_adm1":"Sindh",
    "qs:name_local":"Karachi",
    "qs:photo_max":43,
    "qs:photo_sum":44,
    "qs:placetype":"Suburb",
    "qs:quad_count":2,
    "qs:woe_adm0":23424922,
    "qs:woe_adm1":2346499,
    "qs:woe_adm2":0,
    "qs:woe_lau":0,
    "qs:woe_local":2211096,
    "qs:woe_ver":"7.10.0",
    "wof:lang":[
        "eng"
    ],
    "wof:name":"Patel-ka-bara",
    "wof:placetype":"neighbourhood"
},
  "geometry": {"coordinates":[67.039978,24.875304],"type":"Point"}
}