{
  "type": "Feature",
  "properties": {
    "gn:admin1_code":"1.0",
    "gn:asciiname":"Mirazai",
    "gn:country_code":"PK",
    "gn:dem":1625,
    "gn:feature_class":"P",
    "gn:feature_code":"PPL",
    "gn:name":"Mirazai",
    "gn:population":0,
    "gn:timezone":"Asia/Karachi",
    "iso:country":"PK",
    "name:und_x_variant":[
        "Mira Zai"
    ],
    "wof:name":"Mirazai",
    "wof:placetype":"locality"
},
  "geometry": {"coordinates":[70.96723,33.75954],"type":"Point"}
}