{
  "type": "Feature",
  "properties": {
    "gn:admin1_code":"5.0",
    "gn:asciiname":"Sanhar",
    "gn:country_code":"PK",
    "gn:dem":42,
    "gn:feature_class":"P",
    "gn:feature_code":"PPL",
    "gn:name":"Sanhar",
    "gn:population":0,
    "gn:timezone":"Asia/Karachi",
    "iso:country":"PK",
    "wof:name":"Sanhar",
    "wof:placetype":"locality"
},
  "geometry": {"coordinates":[67.72681999999999,27.22555],"type":"Point"}
}