{
  "type": "Feature",
  "properties": {
    "gn:admin1_code":"2",
    "gn:asciiname":"Wahab",
    "gn:country_code":"PK",
    "gn:dem":1555,
    "gn:feature_class":"P",
    "gn:feature_code":"PPL",
    "gn:name":"Wahab",
    "gn:population":0,
    "gn:timezone":"Asia/Karachi",
    "iso:country":"PK",
    "wof:name":"Wahab",
    "wof:placetype":"locality"
},
  "geometry": {"coordinates":[68.32174999999999,30.74137],"type":"Point"}
}