{
  "type": "Feature",
  "properties": {
    "gn:admin1_code":"4.0",
    "gn:asciiname":"Rajian",
    "gn:country_code":"PK",
    "gn:dem":263,
    "gn:feature_class":"P",
    "gn:feature_code":"PPL",
    "gn:name":"Rajian",
    "gn:population":0,
    "gn:timezone":"Asia/Karachi",
    "iso:country":"PK",
    "wof:name":"Rajian",
    "wof:placetype":"locality"
},
  "geometry": {"coordinates":[74.8826,32.31578],"type":"Point"}
}