{
  "type": "Feature",
  "properties": {
    "gn:admin1_code":"3.0",
    "gn:asciiname":"Mambati Barakzai",
    "gn:country_code":"PK",
    "gn:dem":386,
    "gn:feature_class":"P",
    "gn:feature_code":"PPL",
    "gn:name":"Mambati Barakzai",
    "gn:population":0,
    "gn:timezone":"Asia/Karachi",
    "iso:country":"PK",
    "name:und_x_variant":[
        "Mab\u0101ti",
        "Mambati Barakzai"
    ],
    "wof:name":"Mambati Barakzai",
    "wof:placetype":"locality"
},
  "geometry": {"coordinates":[70.54330999999998,32.92589],"type":"Point"}
}