{
  "type": "Feature",
  "properties": {
    "gn:admin1_code":"6",
    "gn:asciiname":"Dunari",
    "gn:country_code":"PK",
    "gn:dem":1415,
    "gn:feature_class":"P",
    "gn:feature_code":"PPL",
    "gn:name":"Dunari",
    "gn:population":0,
    "gn:timezone":"Asia/Karachi",
    "iso:country":"PK",
    "wof:name":"Dunari",
    "wof:placetype":"locality"
},
  "geometry": {"coordinates":[73.85606999999997,34.53581],"type":"Point"}
}