{
  "type": "Feature",
  "properties": {
    "gn:admin1_code":"5.0",
    "gn:asciiname":"Walari Khan Mughairi",
    "gn:country_code":"PK",
    "gn:dem":49,
    "gn:feature_class":"P",
    "gn:feature_code":"PPL",
    "gn:name":"Walari Khan Mughairi",
    "gn:population":0,
    "gn:timezone":"Asia/Karachi",
    "iso:country":"PK",
    "wof:name":"Walari Khan Mughairi",
    "wof:placetype":"locality"
},
  "geometry": {"coordinates":[67.96441999999999,27.62112],"type":"Point"}
}