{
  "type": "Feature",
  "properties": {
    "gn:admin1_code":"4.0",
    "gn:asciiname":"Rakh Pilo",
    "gn:country_code":"PK",
    "gn:dem":393,
    "gn:feature_class":"P",
    "gn:feature_code":"PPL",
    "gn:name":"Rakh Pilo",
    "gn:population":0,
    "gn:timezone":"Asia/Karachi",
    "iso:country":"PK",
    "wof:name":"Rakh Pilo",
    "wof:placetype":"locality"
},
  "geometry": {"coordinates":[72.69813000000001,33.08059],"type":"Point"}
}