{
  "type": "Feature",
  "properties": {
    "gn:admin1_code":"3",
    "gn:asciiname":"Kadarai Derai",
    "gn:country_code":"PK",
    "gn:dem":1272,
    "gn:feature_class":"P",
    "gn:feature_code":"PPL",
    "gn:name":"Kadarai Derai",
    "gn:population":0,
    "gn:timezone":"Asia/Karachi",
    "iso:country":"PK",
    "name:und_x_variant":[
        "Kodar\u0101i Derai"
    ],
    "wof:name":"Kadarai Derai",
    "wof:placetype":"locality"
},
  "geometry": {"coordinates":[72.19996,34.86104],"type":"Point"}
}