{
  "type": "Feature",
  "properties": {
    "gn:admin1_code":"5.0",
    "gn:asciiname":"Goth Khalid Rabbani",
    "gn:country_code":"PK",
    "gn:dem":12,
    "gn:feature_class":"P",
    "gn:feature_code":"PPL",
    "gn:name":"Goth Khalid Rabbani",
    "gn:population":0,
    "gn:timezone":"Asia/Karachi",
    "iso:country":"PK",
    "name:und_x_variant":[
        "Goth Kh\u0101lid Noh\u0101ni",
        "Goth N\u0101hia",
        "Goth Khalid Rabbani"
    ],
    "wof:name":"Goth Khalid Rabbani",
    "wof:placetype":"locality"
},
  "geometry": {"coordinates":[67.96126,24.61264],"type":"Point"}
}