{
  "type": "Feature",
  "properties": {
    "gn:admin1_code":"04",
    "gn:asciiname":"Chak One Hundred Twenty-eight Rakh Branch",
    "gn:country_code":"PK",
    "gn:dem":189,
    "gn:feature_class":"P",
    "gn:feature_code":"PPL",
    "gn:name":"Chak One Hundred Twenty-eight Rakh Branch",
    "gn:population":0,
    "gn:timezone":"Asia/Karachi",
    "iso:country":"PK",
    "name:und_x_variant":[
        "Chak Wahla",
        "W\u0101hla",
        "Chak One Hundred Twenty-eight Rakh Branch"
    ],
    "wof:name":"Chak One Hundred Twenty-eight Rakh Branch",
    "wof:placetype":"locality"
},
  "geometry": {"coordinates":[73.27741,31.73233],"type":"Point"}
}