{
  "type": "Feature",
  "properties": {
    "gn:admin1_code":"4",
    "gn:asciiname":"Basti Maatam",
    "gn:country_code":"PK",
    "gn:dem":93,
    "gn:feature_class":"P",
    "gn:feature_code":"PPL",
    "gn:name":"Basti Maatam",
    "gn:population":0,
    "gn:timezone":"Asia/Karachi",
    "iso:country":"PK",
    "name:und_x_variant":[
        "Basti Mahtam"
    ],
    "wof:name":"Basti Maatam",
    "wof:placetype":"locality"
},
  "geometry": {"coordinates":[70.52373,29.20729],"type":"Point"}
}