{
  "type": "Feature",
  "properties": {
    "gn:admin1_code":"5.0",
    "gn:asciiname":"Lakho Dars Ji Wand",
    "gn:country_code":"PK",
    "gn:dem":35,
    "gn:feature_class":"P",
    "gn:feature_code":"PPL",
    "gn:name":"Lakho Dars Ji Wand",
    "gn:population":0,
    "gn:timezone":"Asia/Karachi",
    "iso:country":"PK",
    "wof:name":"Lakho Dars Ji Wand",
    "wof:placetype":"locality"
},
  "geometry": {"coordinates":[69.5909,25.75943],"type":"Point"}
}