{
  "type": "Feature",
  "properties": {
    "gn:admin1_code":"2.0",
    "gn:asciiname":"Muhammad Murad Kili",
    "gn:country_code":"PK",
    "gn:dem":1135,
    "gn:feature_class":"P",
    "gn:feature_code":"PPL",
    "gn:name":"Muhammad Murad Kili",
    "gn:population":0,
    "gn:timezone":"Asia/Karachi",
    "iso:country":"PK",
    "wof:name":"Muhammad Murad Kili",
    "wof:placetype":"locality"
},
  "geometry": {"coordinates":[63.87807,29.1197],"type":"Point"}
}