{
  "type": "Feature",
  "properties": {
    "gn:admin1_code":"1",
    "gn:asciiname":"Bara Khel",
    "gn:country_code":"PK",
    "gn:dem":909,
    "gn:feature_class":"P",
    "gn:feature_code":"PPL",
    "gn:name":"Bara Khel",
    "gn:population":0,
    "gn:timezone":"Asia/Karachi",
    "iso:country":"PK",
    "wof:name":"Bara Khel",
    "wof:placetype":"locality"
},
  "geometry": {"coordinates":[71.13023000000003,33.88159],"type":"Point"}
}