{
  "type": "Feature",
  "properties": {
    "gn:admin1_code":"1.0",
    "gn:asciiname":"Qaziabad",
    "gn:country_code":"PK",
    "gn:dem":741,
    "gn:feature_class":"P",
    "gn:feature_code":"PPL",
    "gn:name":"Qaziabad",
    "gn:population":0,
    "gn:timezone":"Asia/Karachi",
    "iso:country":"PK",
    "wof:name":"Qaziabad",
    "wof:placetype":"locality"
},
  "geometry": {"coordinates":[71.16436999999998,34.20924],"type":"Point"}
}