{
  "type": "Feature",
  "properties": {
    "gn:admin1_code":"3.0",
    "gn:asciiname":"Bhalkot",
    "gn:country_code":"PK",
    "gn:dem":1694,
    "gn:feature_class":"P",
    "gn:feature_code":"PPL",
    "gn:name":"Bhalkot",
    "gn:population":0,
    "gn:timezone":"Asia/Karachi",
    "iso:country":"PK",
    "name:eng_x_preferred":[
        "Bhalkot"
    ],
    "wof:name":"Bhalkot",
    "wof:placetype":"locality"
},
  "geometry": {"coordinates":[73.27211,33.99182],"type":"Point"}
}