{
  "type": "Feature",
  "properties": {
    "gn:admin1_code":"1.0",
    "gn:asciiname":"Masud Pakha",
    "gn:country_code":"PK",
    "gn:dem":1816,
    "gn:feature_class":"P",
    "gn:feature_code":"PPL",
    "gn:name":"Masud Pakha",
    "gn:population":0,
    "gn:timezone":"Asia/Karachi",
    "iso:country":"PK",
    "name:und_x_variant":[
        "Masood Pkha"
    ],
    "wof:name":"Masud Pakha",
    "wof:placetype":"locality"
},
  "geometry": {"coordinates":[70.88735,33.7176],"type":"Point"}
}