{
  "type": "Feature",
  "properties": {
    "gn:admin1_code":"2.0",
    "gn:asciiname":"Haji Jabbar Mina",
    "gn:country_code":"PK",
    "gn:dem":1103,
    "gn:feature_class":"P",
    "gn:feature_code":"PPL",
    "gn:name":"Haji Jabbar Mina",
    "gn:population":0,
    "gn:timezone":"Asia/Karachi",
    "iso:country":"PK",
    "wof:name":"Haji Jabbar Mina",
    "wof:placetype":"locality"
},
  "geometry": {"coordinates":[70.13285999999999,31.02677000000001],"type":"Point"}
}