{
  "type": "Feature",
  "properties": {
    "gn:admin1_code":"3.0",
    "gn:asciiname":"Aqa Khel",
    "gn:country_code":"PK",
    "gn:dem":255,
    "gn:feature_class":"P",
    "gn:feature_code":"PPL",
    "gn:name":"Aqa Khel",
    "gn:population":0,
    "gn:timezone":"Asia/Karachi",
    "iso:country":"PK",
    "wof:name":"Aqa Khel",
    "wof:placetype":"locality"
},
  "geometry": {"coordinates":[70.32777,32.19021],"type":"Point"}
}