{
  "type": "Feature",
  "properties": {
    "gn:admin1_code":"4.0",
    "gn:asciiname":"Basti Patan Manara",
    "gn:country_code":"PK",
    "gn:dem":77,
    "gn:feature_class":"P",
    "gn:feature_code":"PPL",
    "gn:name":"Basti Patan Manara",
    "gn:population":0,
    "gn:timezone":"Asia/Karachi",
    "iso:country":"PK",
    "name:und_x_variant":[
        "Pattan Mun\u0101ra"
    ],
    "wof:name":"Basti Patan Manara",
    "wof:placetype":"locality"
},
  "geometry": {"coordinates":[70.31926999999999,28.33138],"type":"Point"}
}