{
  "type": "Feature",
  "properties": {
    "gn:admin1_code":"4.0",
    "gn:asciiname":"Nalla",
    "gn:country_code":"PK",
    "gn:dem":1272,
    "gn:feature_class":"P",
    "gn:feature_code":"PPL",
    "gn:name":"Nalla",
    "gn:population":0,
    "gn:timezone":"Asia/Karachi",
    "iso:country":"PK",
    "name:eng_x_preferred":[
        "Nala"
    ],
    "wof:name":"Nalla",
    "wof:placetype":"locality"
},
  "geometry": {"coordinates":[73.48135000000001,33.89041],"type":"Point"}
}