{
  "type": "Feature",
  "properties": {
    "gn:admin1_code":"5",
    "gn:asciiname":"Goth Jhangi Shoro",
    "gn:country_code":"PK",
    "gn:dem":19,
    "gn:feature_class":"P",
    "gn:feature_code":"PPL",
    "gn:name":"Goth Jhangi Shoro",
    "gn:population":0,
    "gn:timezone":"Asia/Karachi",
    "iso:country":"PK",
    "name:eng_x_preferred":[
        "Jhangli Shoro"
    ],
    "wof:name":"Goth Jhangi Shoro",
    "wof:placetype":"locality"
},
  "geometry": {"coordinates":[68.36766999999999,25.19071],"type":"Point"}
}