{
  "type": "Feature",
  "properties": {
    "gn:admin1_code":"4.0",
    "gn:asciiname":"Basti Mochian",
    "gn:country_code":"PK",
    "gn:dem":94,
    "gn:feature_class":"P",
    "gn:feature_code":"PPL",
    "gn:name":"Basti Mochian",
    "gn:population":0,
    "gn:timezone":"Asia/Karachi",
    "iso:country":"PK",
    "name:urd_x_preferred":[
        "Basti M\u0101chhi\u0101n"
    ],
    "wof:name":"Basti Mochian",
    "wof:placetype":"locality"
},
  "geometry": {"coordinates":[70.5668,28.76607000000001],"type":"Point"}
}