{
  "type": "Feature",
  "properties": {
    "gn:admin1_code":"5.0",
    "gn:asciiname":"Goth Shah Bakhsh Mangi",
    "gn:country_code":"PK",
    "gn:dem":53,
    "gn:feature_class":"P",
    "gn:feature_code":"PPL",
    "gn:name":"Goth Shah Bakhsh Mangi",
    "gn:population":0,
    "gn:timezone":"Asia/Karachi",
    "iso:country":"PK",
    "name:eng_x_preferred":[
        "Goth Shah Bakhsh Mangi"
    ],
    "wof:name":"Goth Shah Bakhsh Mangi",
    "wof:placetype":"locality"
},
  "geometry": {"coordinates":[68.56995999999999,27.32062],"type":"Point"}
}