{
  "type": "Feature",
  "properties": {
    "gn:admin1_code":"3.0",
    "gn:asciiname":"Lai Mir Ahmad Shah",
    "gn:country_code":"PK",
    "gn:dem":303,
    "gn:feature_class":"P",
    "gn:feature_code":"PPL",
    "gn:name":"Lai Mir Ahmad Shah",
    "gn:population":0,
    "gn:timezone":"Asia/Karachi",
    "iso:country":"PK",
    "name:und_x_variant":[
        "L\u0101l M\u012br Ahmad Sh\u0101h",
        "Lai Mir Ahmad Shah"
    ],
    "wof:name":"Lai Mir Ahmad Shah",
    "wof:placetype":"locality"
},
  "geometry": {"coordinates":[70.73494000000002,32.79855],"type":"Point"}
}