{
  "type": "Feature",
  "properties": {
    "gn:admin1_code":"4.0",
    "gn:asciiname":"Kot Jan Muhammad",
    "gn:country_code":"PK",
    "gn:dem":181,
    "gn:feature_class":"P",
    "gn:feature_code":"PPL",
    "gn:name":"Kot Jan Muhammad",
    "gn:population":0,
    "gn:timezone":"Asia/Karachi",
    "iso:country":"PK",
    "name:und_x_variant":[
        "Chak Atam Singh"
    ],
    "wof:name":"Kot Jan Muhammad",
    "wof:placetype":"locality"
},
  "geometry": {"coordinates":[73.84363,30.51874],"type":"Point"}
}