{
  "type": "Feature",
  "properties": {
    "gn:admin1_code":"7.0",
    "gn:asciiname":"Shot",
    "gn:country_code":"PK",
    "gn:dem":2187,
    "gn:feature_class":"P",
    "gn:feature_code":"PPL",
    "gn:name":"Shot",
    "gn:population":0,
    "gn:timezone":"Asia/Karachi",
    "iso:country":"PK",
    "name:und_x_variant":[
        "Shoat"
    ],
    "wof:name":"Shot",
    "wof:placetype":"locality"
},
  "geometry": {"coordinates":[75.16699,35.58425],"type":"Point"}
}