{
  "type": "Feature",
  "properties": {
    "gn:admin1_code":"3.0",
    "gn:asciiname":"Musal",
    "gn:country_code":"PK",
    "gn:dem":489,
    "gn:feature_class":"P",
    "gn:feature_code":"PPL",
    "gn:name":"Musal",
    "gn:population":0,
    "gn:timezone":"Asia/Karachi",
    "iso:country":"PK",
    "wof:name":"Musal",
    "wof:placetype":"locality"
},
  "geometry": {"coordinates":[71.61014,33.19842],"type":"Point"}
}