{
  "type": "Feature",
  "properties": {
    "gn:admin1_code":"5.0",
    "gn:asciiname":"Allana Goth",
    "gn:country_code":"PK",
    "gn:dem":379,
    "gn:feature_class":"P",
    "gn:feature_code":"PPL",
    "gn:name":"Allana Goth",
    "gn:population":0,
    "gn:timezone":"Asia/Karachi",
    "iso:country":"PK",
    "name:und_x_variant":[
        "All\u0101h Goth"
    ],
    "wof:name":"Allana Goth",
    "wof:placetype":"locality"
},
  "geometry": {"coordinates":[67.53113,25.48392],"type":"Point"}
}