{
  "type": "Feature",
  "properties": {
    "gn:admin1_code":"2.0",
    "gn:asciiname":"Surtangi",
    "gn:country_code":"PK",
    "gn:dem":2231,
    "gn:feature_class":"P",
    "gn:feature_code":"PPL",
    "gn:name":"Surtangi",
    "gn:population":0,
    "gn:timezone":"Asia/Karachi",
    "iso:country":"PK",
    "wof:name":"Surtangi",
    "wof:placetype":"locality"
},
  "geometry": {"coordinates":[68.0478,30.41705],"type":"Point"}
}