{
  "type": "Feature",
  "properties": {
    "gn:admin1_code":"4",
    "gn:asciiname":"Qaim Sarki",
    "gn:country_code":"PK",
    "gn:dem":96,
    "gn:feature_class":"P",
    "gn:feature_code":"PPL",
    "gn:name":"Qaim Sarki",
    "gn:population":0,
    "gn:timezone":"Asia/Karachi",
    "iso:country":"PK",
    "name:und_x_variant":[
        "Basti Chakar"
    ],
    "wof:name":"Qaim Sarki",
    "wof:placetype":"locality"
},
  "geometry": {"coordinates":[70.73183,29.14356],"type":"Point"}
}