{
  "type": "Feature",
  "properties": {
    "gn:admin1_code":"5.0",
    "gn:asciiname":"Qadir Shah",
    "gn:country_code":"PK",
    "gn:dem":64,
    "gn:feature_class":"P",
    "gn:feature_code":"PPL",
    "gn:name":"Qadir Shah",
    "gn:population":0,
    "gn:timezone":"Asia/Karachi",
    "iso:country":"PK",
    "name:und_x_variant":[
        "Q\u0101dir Sh\u0101n"
    ],
    "wof:name":"Qadir Shah",
    "wof:placetype":"locality"
},
  "geometry": {"coordinates":[68.88424000000001,28.35496],"type":"Point"}
}