{
  "type": "Feature",
  "properties": {
    "gn:admin1_code":"7.0",
    "gn:asciiname":"Darshai",
    "gn:country_code":"PK",
    "gn:dem":1833,
    "gn:feature_class":"P",
    "gn:feature_code":"PPL",
    "gn:name":"Darshai",
    "gn:population":0,
    "gn:timezone":"Asia/Karachi",
    "iso:country":"PK",
    "name:und_x_variant":[
        "Darshe"
    ],
    "wof:name":"Darshai",
    "wof:placetype":"locality"
},
  "geometry": {"coordinates":[74.14287,35.52504000000001],"type":"Point"}
}