{
  "type": "Feature",
  "properties": {
    "gn:admin1_code":"03",
    "gn:asciiname":"Mardan Cantonment",
    "gn:country_code":"PK",
    "gn:dem":312,
    "gn:feature_class":"P",
    "gn:feature_code":"PPL",
    "gn:name":"Mardan Cantonment",
    "gn:population":0,
    "gn:timezone":"Asia/Karachi",
    "iso:country":"PK",
    "name:eng_x_preferred":[
        "Mardan Cantonment"
    ],
    "wof:name":"Mardan Cantonment",
    "wof:placetype":"neighbourhood"
},
  "geometry": {"coordinates":[72.03610999999999,34.19722],"type":"Point"}
}