{
  "type": "Feature",
  "properties": {
    "gn:admin1_code":"5.0",
    "gn:asciiname":"Goth Pathan Khan Burdi",
    "gn:country_code":"PK",
    "gn:dem":59,
    "gn:feature_class":"P",
    "gn:feature_code":"PPL",
    "gn:name":"Goth Pathan Khan Burdi",
    "gn:population":0,
    "gn:timezone":"Asia/Karachi",
    "iso:country":"PK",
    "wof:name":"Goth Pathan Khan Burdi",
    "wof:placetype":"locality"
},
  "geometry": {"coordinates":[68.66089000000001,27.64452],"type":"Point"}
}