{
  "type": "Feature",
  "properties": {
    "gn:admin1_code":"04",
    "gn:asciiname":"Nadar Badar",
    "gn:cc2":"PK",
    "gn:country_code":"PK",
    "gn:dem":184,
    "gn:feature_class":"P",
    "gn:feature_code":"PPL",
    "gn:name":"Nadar Badar",
    "gn:population":0,
    "gn:timezone":"Asia/Karachi",
    "iso:country":"PK",
    "name:und_x_variant":[
        "Naddar Baddar",
        "Nadar Badar"
    ],
    "wof:name":"Nadar Badar",
    "wof:placetype":"locality"
},
  "geometry": {"coordinates":[70.58333,31.18333],"type":"Point"}
}