{
  "type": "Feature",
  "properties": {
    "gn:admin1_code":"3.0",
    "gn:asciiname":"Tanga Khulla",
    "gn:country_code":"PK",
    "gn:dem":531,
    "gn:feature_class":"P",
    "gn:feature_code":"PPL",
    "gn:name":"Tanga Khulla",
    "gn:population":0,
    "gn:timezone":"Asia/Karachi",
    "iso:country":"PK",
    "wof:name":"Tanga Khulla",
    "wof:placetype":"locality"
},
  "geometry": {"coordinates":[71.83476999999998,33.67281],"type":"Point"}
}