{
  "type": "Feature",
  "properties": {
    "gn:admin1_code":"7.0",
    "gn:asciiname":"Bashal",
    "gn:country_code":"PK",
    "gn:dem":1913,
    "gn:feature_class":"P",
    "gn:feature_code":"PPL",
    "gn:name":"Bashal",
    "gn:population":0,
    "gn:timezone":"Asia/Karachi",
    "iso:country":"PK",
    "wof:name":"Bashal",
    "wof:placetype":"locality"
},
  "geometry": {"coordinates":[73.55034999999999,35.63884],"type":"Point"}
}