{
  "type": "Feature",
  "properties": {
    "gn:admin1_code":"2.0",
    "gn:asciiname":"Goth Sain ji Nai",
    "gn:country_code":"PK",
    "gn:dem":561,
    "gn:feature_class":"P",
    "gn:feature_code":"PPL",
    "gn:name":"Goth Sain ji Nai",
    "gn:population":0,
    "gn:timezone":"Asia/Karachi",
    "iso:country":"PK",
    "wof:name":"Goth Sain ji Nai",
    "wof:placetype":"locality"
},
  "geometry": {"coordinates":[67.30184,27.74134],"type":"Point"}
}