{
  "type": "Feature",
  "properties": {
    "gn:admin1_code":"3",
    "gn:asciiname":"Surbat Bala",
    "gn:country_code":"PK",
    "gn:dem":1319,
    "gn:feature_class":"P",
    "gn:feature_code":"PPL",
    "gn:name":"Surbat Bala",
    "gn:population":0,
    "gn:timezone":"Asia/Karachi",
    "iso:country":"PK",
    "name:eng_x_preferred":[
        "Bar Surbat"
    ],
    "wof:name":"Surbat Bala",
    "wof:placetype":"locality"
},
  "geometry": {"coordinates":[71.8411,35.13064],"type":"Point"}
}