{
  "type": "Feature",
  "properties": {
    "gn:admin1_code":"5",
    "gn:asciiname":"Sial Muhammad Ali",
    "gn:country_code":"PK",
    "gn:dem":10,
    "gn:feature_class":"P",
    "gn:feature_code":"PPL",
    "gn:name":"Sial Muhammad Ali",
    "gn:population":0,
    "gn:timezone":"Asia/Karachi",
    "iso:country":"PK",
    "wof:name":"Sial Muhammad Ali",
    "wof:placetype":"locality"
},
  "geometry": {"coordinates":[69.42674,25.36316],"type":"Point"}
}