{
  "type": "Feature",
  "properties": {
    "gn:admin1_code":"5",
    "gn:asciiname":"Goth Allah Wassayo",
    "gn:country_code":"PK",
    "gn:dem":52,
    "gn:feature_class":"P",
    "gn:feature_code":"PPL",
    "gn:name":"Goth Allah Wassayo",
    "gn:population":0,
    "gn:timezone":"Asia/Karachi",
    "iso:country":"PK",
    "name:und_x_variant":[
        "All\u0101h W\u0101ss\u0101yo"
    ],
    "wof:name":"Goth Allah Wassayo",
    "wof:placetype":"locality"
},
  "geometry": {"coordinates":[68.14929000000001,27.75208],"type":"Point"}
}