{
  "type": "Feature",
  "properties": {
    "gn:admin1_code":"5",
    "gn:asciiname":"Haji Muhammad Khan Unar",
    "gn:country_code":"PK",
    "gn:dem":12,
    "gn:feature_class":"P",
    "gn:feature_code":"PPL",
    "gn:name":"Haji Muhammad Khan Unar",
    "gn:population":0,
    "gn:timezone":"Asia/Karachi",
    "iso:country":"PK",
    "name:und_x_variant":[
        "Jiand Unar"
    ],
    "wof:name":"Haji Muhammad Khan Unar",
    "wof:placetype":"locality"
},
  "geometry": {"coordinates":[69.03989,24.99845],"type":"Point"}
}