{
  "type": "Feature",
  "properties": {
    "gn:admin1_code":"4",
    "gn:asciiname":"Jhok Paddi",
    "gn:country_code":"PK",
    "gn:dem":176,
    "gn:feature_class":"P",
    "gn:feature_code":"PPL",
    "gn:name":"Jhok Paddi",
    "gn:population":0,
    "gn:timezone":"Asia/Karachi",
    "iso:country":"PK",
    "wof:name":"Jhok Paddi",
    "wof:placetype":"locality"
},
  "geometry": {"coordinates":[70.58750000000001,31.24583],"type":"Point"}
}