{
  "type": "Feature",
  "properties": {
    "gn:admin1_code":"1.0",
    "gn:asciiname":"Lahor",
    "gn:country_code":"PK",
    "gn:dem":677,
    "gn:feature_class":"P",
    "gn:feature_code":"PPL",
    "gn:name":"Lahor",
    "gn:population":0,
    "gn:timezone":"Asia/Karachi",
    "iso:country":"PK",
    "name:fas_x_preferred":[
        "\u0644\u0627\u0647\u0648\u0631"
    ],
    "name:urd_x_preferred":[
        "\u0644\u0627\u06c1\u0648\u0631"
    ],
    "wof:name":"Lahor",
    "wof:placetype":"locality"
},
  "geometry": {"coordinates":[71.28934,34.47949000000001],"type":"Point"}
}