{
  "type": "Feature",
  "properties": {
    "gn:admin1_code":"1.0",
    "gn:asciiname":"Tarakai Raghzai",
    "gn:country_code":"PK",
    "gn:dem":814,
    "gn:feature_class":"P",
    "gn:feature_code":"PPL",
    "gn:name":"Tarakai Raghzai",
    "gn:population":0,
    "gn:timezone":"Asia/Karachi",
    "iso:country":"PK",
    "wof:name":"Tarakai Raghzai",
    "wof:placetype":"locality"
},
  "geometry": {"coordinates":[70.70673000000002,33.2127],"type":"Point"}
}