{
  "type": "Feature",
  "properties": {
    "gn:admin1_code":"3.0",
    "gn:asciiname":"Kotka Azmat",
    "gn:country_code":"PK",
    "gn:dem":326,
    "gn:feature_class":"P",
    "gn:feature_code":"PPL",
    "gn:name":"Kotka Azmat",
    "gn:population":0,
    "gn:timezone":"Asia/Karachi",
    "iso:country":"PK",
    "name:und_x_variant":[
        "Azmat",
        "Kotka Azmat"
    ],
    "wof:name":"Kotka Azmat",
    "wof:placetype":"locality"
},
  "geometry": {"coordinates":[70.6982,32.91076],"type":"Point"}
}