{
  "type": "Feature",
  "properties": {
    "gn:admin1_code":"02",
    "gn:asciiname":"Sorap",
    "gn:country_code":"PK",
    "gn:dem":260,
    "gn:feature_class":"P",
    "gn:feature_code":"PPL",
    "gn:name":"Sorap",
    "gn:population":0,
    "gn:timezone":"Asia/Karachi",
    "iso:country":"PK",
    "name:fas_x_preferred":[
        "\u0633\u0648\u0631 \u0622\u0628"
    ],
    "name:fas_x_variant":[
        "S\u016br \u0100b"
    ],
    "wof:name":"Sorap",
    "wof:placetype":"locality"
},
  "geometry": {"coordinates":[61.86813000000001,26.18999],"type":"Point"}
}