{
  "type": "Feature",
  "properties": {
    "gn:admin1_code":"5",
    "gn:asciiname":"Umar Khan Khosa",
    "gn:country_code":"PK",
    "gn:dem":75,
    "gn:feature_class":"P",
    "gn:feature_code":"PPL",
    "gn:name":"Umar Khan Khosa",
    "gn:population":0,
    "gn:timezone":"Asia/Karachi",
    "iso:country":"PK",
    "wof:name":"Umar Khan Khosa",
    "wof:placetype":"locality"
},
  "geometry": {"coordinates":[69.47086,28.40779],"type":"Point"}
}