{
  "type": "Feature",
  "properties": {
    "gn:admin1_code":"3.0",
    "gn:asciiname":"Botot",
    "gn:country_code":"PK",
    "gn:dem":2403,
    "gn:feature_class":"P",
    "gn:feature_code":"PPL",
    "gn:name":"Botot",
    "gn:population":0,
    "gn:timezone":"Asia/Karachi",
    "iso:country":"PK",
    "name:eng_x_preferred":[
        "Batot"
    ],
    "wof:name":"Botot",
    "wof:placetype":"locality"
},
  "geometry": {"coordinates":[72.18791,35.57136],"type":"Point"}
}