{
  "type": "Feature",
  "properties": {
    "gn:admin1_code":"2.0",
    "gn:asciiname":"Nazar Muhammad",
    "gn:country_code":"PK",
    "gn:dem":1787,
    "gn:feature_class":"P",
    "gn:feature_code":"PPL",
    "gn:name":"Nazar Muhammad",
    "gn:population":0,
    "gn:timezone":"Asia/Karachi",
    "iso:country":"PK",
    "wof:name":"Nazar Muhammad",
    "wof:placetype":"locality"
},
  "geometry": {"coordinates":[66.37090000000001,30.53917],"type":"Point"}
}