{
  "type": "Feature",
  "properties": {
    "gn:admin1_code":"1",
    "gn:asciiname":"Raghzai Shahidan",
    "gn:country_code":"PK",
    "gn:dem":596,
    "gn:feature_class":"P",
    "gn:feature_code":"PPL",
    "gn:name":"Raghzai Shahidan",
    "gn:population":0,
    "gn:timezone":"Asia/Karachi",
    "iso:country":"PK",
    "wof:name":"Raghzai Shahidan",
    "wof:placetype":"locality"
},
  "geometry": {"coordinates":[70.51345000000001,33.2116],"type":"Point"}
}