{
  "type": "Feature",
  "properties": {
    "gn:admin1_code":"3.0",
    "gn:asciiname":"Chaghbat",
    "gn:country_code":"PK",
    "gn:dem":1485,
    "gn:feature_class":"P",
    "gn:feature_code":"PPL",
    "gn:name":"Chaghbat",
    "gn:population":0,
    "gn:timezone":"Asia/Karachi",
    "iso:country":"PK",
    "wof:name":"Chaghbat",
    "wof:placetype":"locality"
},
  "geometry": {"coordinates":[72.97563000000002,34.51175],"type":"Point"}
}