{
  "type": "Feature",
  "properties": {
    "gn:admin1_code":"5.0",
    "gn:asciiname":"Behro Mallah",
    "gn:country_code":"PK",
    "gn:dem":9,
    "gn:feature_class":"P",
    "gn:feature_code":"PPL",
    "gn:name":"Behro Mallah",
    "gn:population":0,
    "gn:timezone":"Asia/Karachi",
    "iso:country":"PK",
    "name:und_x_variant":[
        "Gul Moh\u0101na"
    ],
    "wof:name":"Behro Mallah",
    "wof:placetype":"locality"
},
  "geometry": {"coordinates":[68.92533,24.68145],"type":"Point"}
}