{
  "type": "Feature",
  "properties": {
    "gn:admin1_code":"01",
    "gn:asciiname":"Shahzada Kot",
    "gn:cc2":"PK",
    "gn:country_code":"PK",
    "gn:dem":902,
    "gn:feature_class":"P",
    "gn:feature_code":"PPL",
    "gn:name":"Sh\u0101hzada Kot",
    "gn:population":0,
    "gn:timezone":"Asia/Karachi",
    "iso:country":"PK",
    "name:und_x_variant":[
        "Shahzada"
    ],
    "wof:name":"Shahzada Kot",
    "wof:placetype":"locality"
},
  "geometry": {"coordinates":[70.05,32.98333],"type":"Point"}
}