{
  "type": "Feature",
  "properties": {
    "gn:admin1_code":"4.0",
    "gn:asciiname":"Lalupur",
    "gn:country_code":"PK",
    "gn:dem":220,
    "gn:feature_class":"P",
    "gn:feature_code":"PPL",
    "gn:name":"Lalupur",
    "gn:population":0,
    "gn:timezone":"Asia/Karachi",
    "iso:country":"PK",
    "wof:name":"Lalupur",
    "wof:placetype":"locality"
},
  "geometry": {"coordinates":[74.28591999999998,31.99718],"type":"Point"}
}