{
  "type": "Feature",
  "properties": {
    "gn:admin1_code":"5.0",
    "gn:asciiname":"Goth Dingo",
    "gn:country_code":"PK",
    "gn:dem":48,
    "gn:feature_class":"P",
    "gn:feature_code":"PPL",
    "gn:name":"Goth Dingo",
    "gn:population":0,
    "gn:timezone":"Asia/Karachi",
    "iso:country":"PK",
    "name:und_x_variant":[
        "Dingro",
        "Goth Dingo",
        "Dingo"
    ],
    "wof:name":"Goth Dingo",
    "wof:placetype":"locality"
},
  "geometry": {"coordinates":[68.26315,26.91143],"type":"Point"}
}