{
  "type": "Feature",
  "properties": {
    "gn:admin1_code":"4.0",
    "gn:asciiname":"Dhaman",
    "gn:country_code":"PK",
    "gn:dem":811,
    "gn:feature_class":"P",
    "gn:feature_code":"PPL",
    "gn:name":"Dhaman",
    "gn:population":0,
    "gn:timezone":"Asia/Karachi",
    "iso:country":"PK",
    "wof:name":"Dhaman",
    "wof:placetype":"locality"
},
  "geometry": {"coordinates":[72.49120000000001,32.62902],"type":"Point"}
}