{
  "type": "Feature",
  "properties": {
    "gn:admin1_code":"3.0",
    "gn:asciiname":"Banda Gul Amir",
    "gn:country_code":"PK",
    "gn:dem":310,
    "gn:feature_class":"P",
    "gn:feature_code":"PPL",
    "gn:name":"Banda Gul Amir",
    "gn:population":0,
    "gn:timezone":"Asia/Karachi",
    "iso:country":"PK",
    "name:und_x_variant":[
        "Dilli Khel"
    ],
    "wof:name":"Banda Gul Amir",
    "wof:placetype":"locality"
},
  "geometry": {"coordinates":[70.71222,32.31964],"type":"Point"}
}