{
  "type": "Feature",
  "properties": {
    "gn:admin1_code":"2.0",
    "gn:asciiname":"Dhand Curz",
    "gn:country_code":"PK",
    "gn:dem":1664,
    "gn:feature_class":"P",
    "gn:feature_code":"PPL",
    "gn:name":"Dhand Curz",
    "gn:population":0,
    "gn:timezone":"Asia/Karachi",
    "iso:country":"PK",
    "name:und_x_variant":[
        "Dund K\u0101rez"
    ],
    "wof:name":"Dhand Curz",
    "wof:placetype":"locality"
},
  "geometry": {"coordinates":[66.85083,29.81921],"type":"Point"}
}