{
  "type": "Feature",
  "properties": {
    "gn:admin1_code":"3.0",
    "gn:asciiname":"Lal Gul Wazir Kot",
    "gn:country_code":"PK",
    "gn:dem":316,
    "gn:feature_class":"P",
    "gn:feature_code":"PPL",
    "gn:name":"Lal Gul Wazir Kot",
    "gn:population":0,
    "gn:timezone":"Asia/Karachi",
    "iso:country":"PK",
    "wof:name":"Lal Gul Wazir Kot",
    "wof:placetype":"locality"
},
  "geometry": {"coordinates":[70.12933000000001,32.08963],"type":"Point"}
}