{
  "type": "Feature",
  "properties": {
    "gn:admin1_code":"08",
    "gn:asciiname":"Sila",
    "gn:country_code":"PK",
    "gn:dem":661,
    "gn:feature_class":"P",
    "gn:feature_code":"PPL",
    "gn:name":"Sila",
    "gn:population":0,
    "gn:timezone":"Asia/Karachi",
    "iso:country":"PK",
    "wof:name":"Sila",
    "wof:placetype":"locality"
},
  "geometry": {"coordinates":[73.24581999999999,33.78135],"type":"Point"}
}