{
  "type": "Feature",
  "properties": {
    "gn:admin1_code":"2",
    "gn:asciiname":"Kili Wali Muhammad",
    "gn:country_code":"PK",
    "gn:dem":1590,
    "gn:feature_class":"P",
    "gn:feature_code":"PPL",
    "gn:name":"Kili Wali Muhammad",
    "gn:population":0,
    "gn:timezone":"Asia/Karachi",
    "iso:country":"PK",
    "name:und_x_variant":[
        "Wali Muhammad Kili"
    ],
    "wof:name":"Kili Wali Muhammad",
    "wof:placetype":"locality"
},
  "geometry": {"coordinates":[66.72261999999999,29.96851],"type":"Point"}
}