{
  "type": "Feature",
  "properties": {
    "gn:admin1_code":"2.0",
    "gn:asciiname":"Bismillah",
    "gn:country_code":"PK",
    "gn:dem":1594,
    "gn:feature_class":"P",
    "gn:feature_code":"PPL",
    "gn:name":"Bismillah",
    "gn:population":0,
    "gn:timezone":"Asia/Karachi",
    "iso:country":"PK",
    "name:fra_x_preferred":[
        "Bismillah"
    ],
    "name:pan_x_preferred":[
        "\u0a2c\u0a3f\u0a38\u0a2e\u0a3f\u0a71\u0a32\u0a3e\u0a39"
    ],
    "wof:name":"Bismillah",
    "wof:placetype":"locality"
},
  "geometry": {"coordinates":[69.51039,30.78965],"type":"Point"}
}