{
  "type": "Feature",
  "properties": {
    "gn:admin1_code":"2.0",
    "gn:asciiname":"Bismillah",
    "gn:country_code":"PK",
    "gn:dem":1594,
    "gn:feature_class":"P",
    "gn:feature_code":"PPL",
    "gn:name":"Bismillah",
    "gn:population":0,
    "gn:timezone":"Asia/Karachi",
    "iso:country":"PK",
    "wof:name":"Bismillah",
    "wof:placetype":"locality"
},
  "geometry": {"coordinates":[69.51039,30.78965],"type":"Point"}
}