{
  "type": "Feature",
  "properties": {
    "gn:admin1_code":"5.0",
    "gn:asciiname":"Goth Allah Dawaya Lund",
    "gn:country_code":"PK",
    "gn:dem":70,
    "gn:feature_class":"P",
    "gn:feature_code":"PPL",
    "gn:name":"Goth Allah Dawaya Lund",
    "gn:population":0,
    "gn:timezone":"Asia/Karachi",
    "iso:country":"PK",
    "wof:name":"Goth Allah Dawaya Lund",
    "wof:placetype":"locality"
},
  "geometry": {"coordinates":[69.60658000000001,27.79084000000001],"type":"Point"}
}