{
  "type": "Feature",
  "properties": {
    "gn:admin1_code":"5.0",
    "gn:asciiname":"Goth Laung Nohiry",
    "gn:country_code":"PK",
    "gn:dem":11,
    "gn:feature_class":"P",
    "gn:feature_code":"PPL",
    "gn:name":"Goth Laung Nohiry",
    "gn:population":0,
    "gn:timezone":"Asia/Karachi",
    "iso:country":"PK",
    "wof:name":"Goth Laung Nohiry",
    "wof:placetype":"locality"
},
  "geometry": {"coordinates":[69.47173000000001,25.36364],"type":"Point"}
}