{
  "type": "Feature",
  "properties": {
    "gn:admin1_code":"6.0",
    "gn:asciiname":"Jauif Post",
    "gn:country_code":"PK",
    "gn:dem":1309,
    "gn:feature_class":"P",
    "gn:feature_code":"PPL",
    "gn:name":"Jauif Post",
    "gn:population":0,
    "gn:timezone":"Asia/Karachi",
    "iso:country":"PK",
    "wof:name":"Jauif Post",
    "wof:placetype":"locality"
},
  "geometry": {"coordinates":[74.08484,33.83228],"type":"Point"}
}