{
  "type": "Feature",
  "properties": {
    "gn:admin1_code":"04",
    "gn:asciiname":"Kotli Miani",
    "gn:country_code":"PK",
    "gn:dem":216,
    "gn:feature_class":"P",
    "gn:feature_code":"PPL",
    "gn:name":"Kotli Miani",
    "gn:population":0,
    "gn:timezone":"Asia/Karachi",
    "iso:country":"PK",
    "wof:name":"Kotli Miani",
    "wof:placetype":"locality"
},
  "geometry": {"coordinates":[73.85363000000002,32.21211],"type":"Point"}
}