{
  "type": "Feature",
  "properties": {
    "gn:admin1_code":"4",
    "gn:asciiname":"Dera Motwali",
    "gn:country_code":"PK",
    "gn:dem":194,
    "gn:feature_class":"P",
    "gn:feature_code":"PPL",
    "gn:name":"Dera Motwali",
    "gn:population":0,
    "gn:timezone":"Asia/Karachi",
    "iso:country":"PK",
    "name:und_x_variant":[
        "Dera Matw\u0101li Ramha"
    ],
    "wof:name":"Dera Motwali",
    "wof:placetype":"locality"
},
  "geometry": {"coordinates":[73.08674000000001,32.15586],"type":"Point"}
}