{
  "type": "Feature",
  "properties": {
    "gn:admin1_code":"4",
    "gn:asciiname":"Kot Bajwa",
    "gn:country_code":"PK",
    "gn:dem":236,
    "gn:feature_class":"P",
    "gn:feature_code":"PPL",
    "gn:name":"Kot Bajwa",
    "gn:population":0,
    "gn:timezone":"Asia/Karachi",
    "iso:country":"PK",
    "wof:name":"Kot Bajwa",
    "wof:placetype":"locality"
},
  "geometry": {"coordinates":[74.70770999999998,32.19675],"type":"Point"}
}