{
  "type": "Feature",
  "properties": {
    "gn:admin1_code":"3.0",
    "gn:asciiname":"Babuzai",
    "gn:country_code":"PK",
    "gn:dem":1660,
    "gn:feature_class":"P",
    "gn:feature_code":"PPL",
    "gn:name":"Babuzai",
    "gn:population":0,
    "gn:timezone":"Asia/Karachi",
    "iso:country":"PK",
    "name:und_x_variant":[
        "Babozai",
        "Babuzai"
    ],
    "wof:name":"Babuzai",
    "wof:placetype":"locality"
},
  "geometry": {"coordinates":[72.13048000000001,34.83664],"type":"Point"}
}