{
  "type": "Feature",
  "properties": {
    "gn:admin1_code":"4",
    "gn:asciiname":"Dahran",
    "gn:country_code":"PK",
    "gn:dem":140,
    "gn:feature_class":"P",
    "gn:feature_code":"PPL",
    "gn:name":"Dahran",
    "gn:population":0,
    "gn:timezone":"Asia/Karachi",
    "iso:country":"PK",
    "wof:name":"Dahran",
    "wof:placetype":"locality"
},
  "geometry": {"coordinates":[71.96980000000001,30.64837],"type":"Point"}
}