{
  "type": "Feature",
  "properties": {
    "gn:admin1_code":"3",
    "gn:asciiname":"Diranda",
    "gn:country_code":"PK",
    "gn:dem":2451,
    "gn:feature_class":"P",
    "gn:feature_code":"PPL",
    "gn:name":"Diranda",
    "gn:population":0,
    "gn:timezone":"Asia/Karachi",
    "iso:country":"PK",
    "name:und_x_variant":[
        "Daranda"
    ],
    "wof:name":"Diranda",
    "wof:placetype":"locality"
},
  "geometry": {"coordinates":[73.47964,34.74725],"type":"Point"}
}