{
  "type": "Feature",
  "properties": {
    "gn:admin1_code":"2.0",
    "gn:asciiname":"Goth Jamal Shah",
    "gn:country_code":"PK",
    "gn:dem":80,
    "gn:feature_class":"P",
    "gn:feature_code":"PPL",
    "gn:name":"Goth Jamal Shah",
    "gn:population":0,
    "gn:timezone":"Asia/Karachi",
    "iso:country":"PK",
    "name:und_x_variant":[
        "Goth Jam\u0101l Kh\u0101n"
    ],
    "wof:name":"Goth Jamal Shah",
    "wof:placetype":"locality"
},
  "geometry": {"coordinates":[67.56260999999999,28.74313],"type":"Point"}
}