{
  "type": "Feature",
  "properties": {
    "gn:admin1_code":"5.0",
    "gn:asciiname":"Goth Saleh Muhammad Dirha Bhambro",
    "gn:country_code":"PK",
    "gn:dem":16,
    "gn:feature_class":"P",
    "gn:feature_code":"PPL",
    "gn:name":"Goth Saleh Muhammad Dirha Bhambro",
    "gn:population":0,
    "gn:timezone":"Asia/Karachi",
    "iso:country":"PK",
    "wof:name":"Goth Saleh Muhammad Dirha Bhambro",
    "wof:placetype":"locality"
},
  "geometry": {"coordinates":[67.99682,24.83373],"type":"Point"}
}