{
  "type": "Feature",
  "properties": {
    "gn:admin1_code":"3.0",
    "gn:asciiname":"Rahi",
    "gn:country_code":"PK",
    "gn:dem":1043,
    "gn:feature_class":"P",
    "gn:feature_code":"PPL",
    "gn:name":"Rahi",
    "gn:population":0,
    "gn:timezone":"Asia/Karachi",
    "iso:country":"PK",
    "name:ceb_x_preferred":[
        "Rahi"
    ],
    "name:deu_x_preferred":[
        "Rahi"
    ],
    "name:eng_x_preferred":[
        "Rahi"
    ],
    "wof:name":"Rahi",
    "wof:placetype":"locality"
},
  "geometry": {"coordinates":[73.25695999999998,33.90255],"type":"Point"}
}