{
  "type": "Feature",
  "properties": {
    "gn:admin1_code":"1.0",
    "gn:asciiname":"Kundi Mangar Khel",
    "gn:country_code":"PK",
    "gn:dem":577,
    "gn:feature_class":"P",
    "gn:feature_code":"PPL",
    "gn:name":"Kundi Mangar Khel",
    "gn:population":0,
    "gn:timezone":"Asia/Karachi",
    "iso:country":"PK",
    "name:und_x_variant":[
        "Kandi Mangarr Khel"
    ],
    "wof:name":"Kundi Mangar Khel",
    "wof:placetype":"locality"
},
  "geometry": {"coordinates":[71.71865,33.59058],"type":"Point"}
}