{
  "type": "Feature",
  "properties": {
    "gn:admin1_code":"05",
    "gn:asciiname":"Goth Hajan Shah",
    "gn:country_code":"PK",
    "gn:dem":73,
    "gn:feature_class":"P",
    "gn:feature_code":"PPL",
    "gn:name":"Goth Hajan Shah",
    "gn:population":0,
    "gn:timezone":"Asia/Karachi",
    "iso:country":"PK",
    "name:und_x_variant":[
        "M\u0101ri Goth"
    ],
    "wof:name":"Goth Hajan Shah",
    "wof:placetype":"locality"
},
  "geometry": {"coordinates":[68.60653000000001,27.90708],"type":"Point"}
}