{
  "type": "Feature",
  "properties": {
    "gn:admin1_code":"5.0",
    "gn:asciiname":"Khudi Manghulur",
    "gn:country_code":"PK",
    "gn:dem":110,
    "gn:feature_class":"P",
    "gn:feature_code":"PPL",
    "gn:name":"Khudi Manghulur",
    "gn:population":0,
    "gn:timezone":"Asia/Karachi",
    "iso:country":"PK",
    "wof:name":"Khudi Manghulur",
    "wof:placetype":"locality"
},
  "geometry": {"coordinates":[70.60120000000001,25.00204],"type":"Point"}
}