{
  "type": "Feature",
  "properties": {
    "gn:admin1_code":"3",
    "gn:asciiname":"Wuchbela",
    "gn:country_code":"PK",
    "gn:dem":430,
    "gn:feature_class":"P",
    "gn:feature_code":"PPL",
    "gn:name":"Wuchbela",
    "gn:population":0,
    "gn:timezone":"Asia/Karachi",
    "iso:country":"PK",
    "wof:name":"Wuchbela",
    "wof:placetype":"locality"
},
  "geometry": {"coordinates":[72.90288000000002,34.10547],"type":"Point"}
}