{
  "type": "Feature",
  "properties": {
    "gn:admin1_code":"4",
    "gn:asciiname":"Nursar",
    "gn:country_code":"PK",
    "gn:dem":129,
    "gn:feature_class":"P",
    "gn:feature_code":"PPL",
    "gn:name":"Nursar",
    "gn:population":0,
    "gn:timezone":"Asia/Karachi",
    "iso:country":"PK",
    "name:ara_x_preferred":[
        "\u0646\u0648\u0631\u0633\u0631"
    ],
    "name:ceb_x_preferred":[
        "N\u016brsar"
    ],
    "name:fas_x_preferred":[
        "\u0646\u0648\u0631\u0633\u0631"
    ],
    "name:swe_x_preferred":[
        "N\u016brsar"
    ],
    "name:und_x_variant":[
        "Bal\u016bch\u0101nw\u0101la"
    ],
    "wof:name":"Nursar",
    "wof:placetype":"locality"
},
  "geometry": {"coordinates":[72.16276999999999,29.43886],"type":"Point"}
}