{
  "type": "Feature",
  "properties": {
    "gn:admin1_code":"4",
    "gn:asciiname":"Pipli Guraya",
    "gn:country_code":"PK",
    "gn:dem":219,
    "gn:feature_class":"P",
    "gn:feature_code":"PPL",
    "gn:name":"Pipli Guraya",
    "gn:population":0,
    "gn:timezone":"Asia/Karachi",
    "iso:country":"PK",
    "wof:name":"Pipli Guraya",
    "wof:placetype":"locality"
},
  "geometry": {"coordinates":[74.05542,32.02198],"type":"Point"}
}