{
  "type": "Feature",
  "properties": {
    "gn:admin1_code":"5.0",
    "gn:asciiname":"Goth Qaim Jatoi",
    "gn:country_code":"PK",
    "gn:dem":41,
    "gn:feature_class":"P",
    "gn:feature_code":"PPL",
    "gn:name":"Goth Qaim Jatoi",
    "gn:population":0,
    "gn:timezone":"Asia/Karachi",
    "iso:country":"PK",
    "name:und_x_variant":[
        "Goth Q\u0101im Kh\u0101n Jatoi"
    ],
    "wof:name":"Goth Qaim Jatoi",
    "wof:placetype":"locality"
},
  "geometry": {"coordinates":[67.68321999999999,27.25727],"type":"Point"}
}