{
  "type": "Feature",
  "properties": {
    "gn:admin1_code":"4.0",
    "gn:asciiname":"Chak One Hundred Eight -Ten Right",
    "gn:country_code":"PK",
    "gn:dem":129,
    "gn:feature_class":"P",
    "gn:feature_code":"PPL",
    "gn:name":"Chak One Hundred Eight -Ten Right",
    "gn:population":0,
    "gn:timezone":"Asia/Karachi",
    "iso:country":"PK",
    "name:und_x_variant":[
        "Chak One Hundred Eight",
        "Hashmat\u0101b\u0101d",
        "Chak One Hundred Eight -Ten Right",
        "H\u0101shmat\u0101b\u0101d"
    ],
    "wof:name":"Chak One Hundred Eight -Ten Right",
    "wof:placetype":"locality"
},
  "geometry": {"coordinates":[71.8706,30.06662],"type":"Point"}
}