{
  "type": "Feature",
  "properties": {
    "gn:admin1_code":"5.0",
    "gn:asciiname":"Pirani",
    "gn:country_code":"PK",
    "gn:dem":126,
    "gn:feature_class":"P",
    "gn:feature_code":"PPL",
    "gn:name":"Pirani",
    "gn:population":0,
    "gn:timezone":"Asia/Karachi",
    "iso:country":"PK",
    "name:deu_x_preferred":[
        "Pirani"
    ],
    "name:ita_x_preferred":[
        "Pirani"
    ],
    "name:rus_x_preferred":[
        "\u041f\u0438\u0440\u0430\u043d\u0438"
    ],
    "wof:name":"Pirani",
    "wof:placetype":"locality"
},
  "geometry": {"coordinates":[70.46419,25.38549],"type":"Point"}
}