{
  "type": "Feature",
  "properties": {
    "gn:admin1_code":"03",
    "gn:asciiname":"Gidar",
    "gn:country_code":"PK",
    "gn:dem":767,
    "gn:feature_class":"P",
    "gn:feature_code":"PPL",
    "gn:name":"Gidar",
    "gn:population":0,
    "gn:timezone":"Asia/Karachi",
    "iso:country":"PK",
    "wof:name":"Gidar",
    "wof:placetype":"locality"
},
  "geometry": {"coordinates":[71.83983000000001,34.81695999999999],"type":"Point"}
}