{
  "type": "Feature",
  "properties": {
    "gn:admin1_code":"4",
    "gn:asciiname":"Faruqabad",
    "gn:country_code":"PK",
    "gn:dem":141,
    "gn:feature_class":"P",
    "gn:feature_code":"PPL",
    "gn:name":"Far\u016bq\u0101b\u0101d",
    "gn:population":0,
    "gn:timezone":"Asia/Karachi",
    "iso:country":"PK",
    "wof:name":"Faruqabad",
    "wof:placetype":"locality"
},
  "geometry": {"coordinates":[72.59444000000001,29.97083],"type":"Point"}
}