{
  "type": "Feature",
  "properties": {
    "gn:admin1_code":"4",
    "gn:asciiname":"Chak Thirty-one Two Left",
    "gn:country_code":"PK",
    "gn:dem":175,
    "gn:feature_class":"P",
    "gn:feature_code":"PPL",
    "gn:name":"Chak Thirty-one Two Left",
    "gn:population":0,
    "gn:timezone":"Asia/Karachi",
    "iso:country":"PK",
    "name:und_x_variant":[
        "Day\u0101lpur"
    ],
    "wof:name":"Chak Thirty-one Two Left",
    "wof:placetype":"locality"
},
  "geometry": {"coordinates":[73.55209000000001,30.74864],"type":"Point"}
}