{
  "type": "Feature",
  "properties": {
    "gn:admin1_code":"1.0",
    "gn:asciiname":"Wagdalai",
    "gn:country_code":"PK",
    "gn:dem":2422,
    "gn:feature_class":"P",
    "gn:feature_code":"PPL",
    "gn:name":"Wagdalai",
    "gn:population":0,
    "gn:timezone":"Asia/Karachi",
    "iso:country":"PK",
    "wof:name":"Wagdalai",
    "wof:placetype":"locality"
},
  "geometry": {"coordinates":[69.43933,32.56271],"type":"Point"}
}