{
  "type": "Feature",
  "properties": {
    "gn:admin1_code":"5",
    "gn:asciiname":"Goth Bano",
    "gn:country_code":"PK",
    "gn:dem":66,
    "gn:feature_class":"P",
    "gn:feature_code":"PPL",
    "gn:name":"Goth Bano",
    "gn:population":0,
    "gn:timezone":"Asia/Karachi",
    "iso:country":"PK",
    "wof:name":"Goth Bano",
    "wof:placetype":"locality"
},
  "geometry": {"coordinates":[69.27405999999999,27.79646],"type":"Point"}
}