{
  "type": "Feature",
  "properties": {
    "gn:admin1_code":"1",
    "gn:asciiname":"Kharai Mela",
    "gn:country_code":"PK",
    "gn:dem":1192,
    "gn:feature_class":"P",
    "gn:feature_code":"PPL",
    "gn:name":"Kharai Mela",
    "gn:population":0,
    "gn:timezone":"Asia/Karachi",
    "iso:country":"PK",
    "wof:name":"Kharai Mela",
    "wof:placetype":"locality"
},
  "geometry": {"coordinates":[71.09201999999998,33.97105999999999],"type":"Point"}
}