{
  "type": "Feature",
  "properties": {
    "gn:admin1_code":"2.0",
    "gn:asciiname":"Wali Muhammad",
    "gn:country_code":"PK",
    "gn:dem":1504,
    "gn:feature_class":"P",
    "gn:feature_code":"PPL",
    "gn:name":"Wali Muhammad",
    "gn:population":0,
    "gn:timezone":"Asia/Karachi",
    "iso:country":"PK",
    "name:und_x_variant":[
        "Wail Muhammad"
    ],
    "wof:name":"Wali Muhammad",
    "wof:placetype":"locality"
},
  "geometry": {"coordinates":[66.42421,28.06452],"type":"Point"}
}