{
  "type": "Feature",
  "properties": {
    "gn:admin1_code":"6.0",
    "gn:asciiname":"New Palangi",
    "gn:country_code":"PK",
    "gn:dem":1379,
    "gn:feature_class":"P",
    "gn:feature_code":"PPL",
    "gn:name":"New Palangi",
    "gn:population":0,
    "gn:timezone":"Asia/Karachi",
    "iso:country":"PK",
    "wof:name":"New Palangi",
    "wof:placetype":"locality"
},
  "geometry": {"coordinates":[74.06392,33.85918],"type":"Point"}
}