{
  "type": "Feature",
  "properties": {
    "gn:admin1_code":"3",
    "gn:asciiname":"Jhok Mashori",
    "gn:country_code":"PK",
    "gn:dem":202,
    "gn:feature_class":"P",
    "gn:feature_code":"PPL",
    "gn:name":"Jhok Mashori",
    "gn:population":0,
    "gn:timezone":"Asia/Karachi",
    "iso:country":"PK",
    "name:und_x_variant":[
        "Jhok Masori",
        "Masori",
        "Jhok Mashori"
    ],
    "wof:name":"Jhok Mashori",
    "wof:placetype":"locality"
},
  "geometry": {"coordinates":[70.52679999999999,31.42168],"type":"Point"}
}