{
  "type": "Feature",
  "properties": {
    "gn:admin1_code":"4.0",
    "gn:asciiname":"Allahdad Wala",
    "gn:country_code":"PK",
    "gn:dem":115,
    "gn:feature_class":"P",
    "gn:feature_code":"PPL",
    "gn:name":"Allahdad Wala",
    "gn:population":0,
    "gn:timezone":"Asia/Karachi",
    "iso:country":"PK",
    "name:und_x_variant":[
        "All\u0101h\u0101b\u0101d"
    ],
    "wof:name":"Allahdad Wala",
    "wof:placetype":"locality"
},
  "geometry": {"coordinates":[71.40521,29.84535],"type":"Point"}
}