{
  "type": "Feature",
  "properties": {
    "gn:admin1_code":"3.0",
    "gn:asciiname":"Baharistan",
    "gn:country_code":"PK",
    "gn:dem":308,
    "gn:feature_class":"P",
    "gn:feature_code":"PPL",
    "gn:name":"Baharistan",
    "gn:population":0,
    "gn:timezone":"Asia/Karachi",
    "iso:country":"PK",
    "wof:name":"Baharistan",
    "wof:placetype":"locality"
},
  "geometry": {"coordinates":[71.60848,34.12492],"type":"Point"}
}