{
  "type": "Feature",
  "properties": {
    "gn:admin1_code":"3",
    "gn:asciiname":"Landai",
    "gn:country_code":"PK",
    "gn:dem":1741,
    "gn:feature_class":"P",
    "gn:feature_code":"PPL",
    "gn:name":"Landai",
    "gn:population":0,
    "gn:timezone":"Asia/Karachi",
    "iso:country":"PK",
    "name:und_x_variant":[
        "Lanai",
        "Landai"
    ],
    "wof:name":"Landai",
    "wof:placetype":"locality"
},
  "geometry": {"coordinates":[72.38761,35.09275],"type":"Point"}
}