{
  "type": "Feature",
  "properties": {
    "gn:admin1_code":"1",
    "gn:asciiname":"Sale Rogha Sarai",
    "gn:country_code":"PK",
    "gn:dem":1950,
    "gn:feature_class":"P",
    "gn:feature_code":"PPL",
    "gn:name":"Sale Rogha Sarai",
    "gn:population":0,
    "gn:timezone":"Asia/Karachi",
    "iso:country":"PK",
    "wof:name":"Sale Rogha Sarai",
    "wof:placetype":"locality"
},
  "geometry": {"coordinates":[69.77269,32.50745999999999],"type":"Point"}
}