{
  "type": "Feature",
  "properties": {
    "gn:admin1_code":"4.0",
    "gn:asciiname":"Roshan Bhila",
    "gn:country_code":"PK",
    "gn:dem":196,
    "gn:feature_class":"P",
    "gn:feature_code":"PPL",
    "gn:name":"Roshan Bh\u012bl\u0101",
    "gn:population":0,
    "gn:timezone":"Asia/Karachi",
    "iso:country":"PK",
    "name:und_x_variant":[
        "Bhila Hithhar",
        "Bh\u012bl\u0101 Hith\u0101r"
    ],
    "wof:name":"Roshan Bhila",
    "wof:placetype":"locality"
},
  "geometry": {"coordinates":[74.35132,31.06615],"type":"Point"}
}