{
  "type": "Feature",
  "properties": {
    "gn:admin1_code":"2",
    "gn:asciiname":"Mirhan Rabbani",
    "gn:country_code":"PK",
    "gn:dem":1523,
    "gn:feature_class":"P",
    "gn:feature_code":"PPL",
    "gn:name":"Mirhan Rabbani",
    "gn:population":0,
    "gn:timezone":"Asia/Karachi",
    "iso:country":"PK",
    "name:und_x_variant":[
        "Miran Rab\u0101ni"
    ],
    "wof:name":"Mirhan Rabbani",
    "wof:placetype":"locality"
},
  "geometry": {"coordinates":[69.70925,30.12918],"type":"Point"}
}