{
  "type": "Feature",
  "properties": {
    "gn:admin1_code":"5.0",
    "gn:asciiname":"Goth Jumo Mallah",
    "gn:country_code":"PK",
    "gn:dem":6,
    "gn:feature_class":"P",
    "gn:feature_code":"PPL",
    "gn:name":"Goth Jumo Mallah",
    "gn:population":0,
    "gn:timezone":"Asia/Karachi",
    "iso:country":"PK",
    "name:aar_x_preferred":[
        "Goth Jumo Mall\u0101h"
    ],
    "wof:name":"Goth Jumo Mallah",
    "wof:placetype":"locality"
},
  "geometry": {"coordinates":[68.30183000000001,24.42287],"type":"Point"}
}