{
  "type": "Feature",
  "properties": {
    "gn:admin1_code":"4",
    "gn:asciiname":"Yara",
    "gn:country_code":"PK",
    "gn:dem":603,
    "gn:feature_class":"P",
    "gn:feature_code":"PPL",
    "gn:name":"Yara",
    "gn:population":0,
    "gn:timezone":"Asia/Karachi",
    "iso:country":"PK",
    "wof:name":"Yara",
    "wof:placetype":"locality"
},
  "geometry": {"coordinates":[72.22499999999999,32.725],"type":"Point"}
}