{
  "type": "Feature",
  "properties": {
    "gn:admin1_code":"4",
    "gn:asciiname":"Yara",
    "gn:country_code":"PK",
    "gn:dem":603,
    "gn:feature_class":"P",
    "gn:feature_code":"PPL",
    "gn:name":"Yara",
    "gn:population":0,
    "gn:timezone":"Asia/Karachi",
    "iso:country":"PK",
    "name:ara_x_preferred":[
        "\u064a\u0627\u0631\u0627"
    ],
    "name:ceb_x_preferred":[
        "Yara"
    ],
    "name:deu_x_preferred":[
        "Yara"
    ],
    "name:ita_x_preferred":[
        "Yara"
    ],
    "name:nld_x_preferred":[
        "Yara"
    ],
    "name:por_x_preferred":[
        "Yara"
    ],
    "name:swe_x_preferred":[
        "Yara"
    ],
    "wof:name":"Yara",
    "wof:placetype":"locality"
},
  "geometry": {"coordinates":[72.22499999999999,32.725],"type":"Point"}
}