{
  "type": "Feature",
  "properties": {
    "gn:admin1_code":"5.0",
    "gn:asciiname":"Jani Dero",
    "gn:country_code":"PK",
    "gn:dem":57,
    "gn:feature_class":"P",
    "gn:feature_code":"PPL",
    "gn:name":"Jani Dero",
    "gn:population":0,
    "gn:timezone":"Asia/Karachi",
    "iso:country":"PK",
    "name:und_x_variant":[
        "Nazir Muhammad Dhano Lehar"
    ],
    "wof:name":"Jani Dero",
    "wof:placetype":"locality"
},
  "geometry": {"coordinates":[68.43268,28.25155],"type":"Point"}
}