{
  "type": "Feature",
  "properties": {
    "gn:admin1_code":"3",
    "gn:asciiname":"Tapra",
    "gn:country_code":"PK",
    "gn:dem":1347,
    "gn:feature_class":"P",
    "gn:feature_code":"PPL",
    "gn:name":"Tapra",
    "gn:population":0,
    "gn:timezone":"Asia/Karachi",
    "iso:country":"PK",
    "wof:name":"Tapra",
    "wof:placetype":"locality"
},
  "geometry": {"coordinates":[72.37053,34.91903],"type":"Point"}
}