{
  "type": "Feature",
  "properties": {
    "gn:admin1_code":"06",
    "gn:asciiname":"Sid Tajpuraliya",
    "gn:country_code":"PK",
    "gn:dem":269,
    "gn:feature_class":"P",
    "gn:feature_code":"PPL",
    "gn:name":"Sid Tajpuraliya",
    "gn:population":0,
    "gn:timezone":"Asia/Karachi",
    "iso:country":"PK",
    "name:und_x_variant":[
        "Sidh Tajpur Alya",
        "Sidh Tajpuraliya",
        "Sid Tajpuraliya"
    ],
    "wof:name":"Sid Tajpuraliya",
    "wof:placetype":"locality"
},
  "geometry": {"coordinates":[73.63598,33.06439],"type":"Point"}
}