{
  "type": "Feature",
  "properties": {
    "gn:admin1_code":"6",
    "gn:asciiname":"Chhappran",
    "gn:country_code":"PK",
    "gn:dem":2239,
    "gn:feature_class":"P",
    "gn:feature_code":"PPL",
    "gn:name":"Chhappran",
    "gn:population":0,
    "gn:timezone":"Asia/Karachi",
    "iso:country":"PK",
    "name:und_x_variant":[
        "Chhapar"
    ],
    "wof:name":"Chhappran",
    "wof:placetype":"locality"
},
  "geometry": {"coordinates":[73.47141999999999,34.54537],"type":"Point"}
}