{
  "type": "Feature",
  "properties": {
    "gn:admin1_code":"3",
    "gn:asciiname":"Hariana",
    "gn:country_code":"PK",
    "gn:dem":862,
    "gn:feature_class":"P",
    "gn:feature_code":"PPL",
    "gn:name":"Hariana",
    "gn:population":0,
    "gn:timezone":"Asia/Karachi",
    "iso:country":"PK",
    "name:und_x_variant":[
        "Hary\u0101na"
    ],
    "wof:name":"Hariana",
    "wof:placetype":"locality"
},
  "geometry": {"coordinates":[72.81610999999999,34.48376],"type":"Point"}
}