{
  "type": "Feature",
  "properties": {
    "gn:admin1_code":"3",
    "gn:asciiname":"Hariana",
    "gn:country_code":"PK",
    "gn:dem":862,
    "gn:feature_class":"P",
    "gn:feature_code":"PPL",
    "gn:name":"Hariana",
    "gn:population":0,
    "gn:timezone":"Asia/Karachi",
    "iso:country":"PK",
    "name:ben_x_preferred":[
        "\u09b9\u09b0\u09bf\u09af\u09bc\u09be\u09a8\u09be"
    ],
    "name:bpy_x_preferred":[
        "\u09b9\u09b0\u09bf\u09af\u09bc\u09be\u09a8\u09be"
    ],
    "name:cat_x_preferred":[
        "Hariana"
    ],
    "name:ceb_x_preferred":[
        "Hari\u0101na"
    ],
    "name:ita_x_preferred":[
        "Hariana"
    ],
    "name:mlg_x_preferred":[
        "Hariana"
    ],
    "name:msa_x_preferred":[
        "Hariana"
    ],
    "name:nld_x_preferred":[
        "Hariana"
    ],
    "name:pan_x_preferred":[
        "\u0a39\u0a30\u0a3f\u0a06\u0a23\u0a3e"
    ],
    "name:spa_x_preferred":[
        "Hariana"
    ],
    "name:swe_x_preferred":[
        "Hari\u0101na"
    ],
    "name:und_x_variant":[
        "Hary\u0101na"
    ],
    "name:vie_x_preferred":[
        "Hariana"
    ],
    "name:zho_x_preferred":[
        "\u54c8\u91cc\u4e9a\u7eb3"
    ],
    "wof:name":"Hariana",
    "wof:placetype":"locality"
},
  "geometry": {"coordinates":[72.81610999999999,34.48376],"type":"Point"}
}