{
  "type": "Feature",
  "properties": {
    "gn:admin1_code":"5",
    "gn:asciiname":"Goth Abad Bhutto",
    "gn:country_code":"PK",
    "gn:dem":58,
    "gn:feature_class":"P",
    "gn:feature_code":"PPL",
    "gn:name":"Goth Abad Bhutto",
    "gn:population":0,
    "gn:timezone":"Asia/Karachi",
    "iso:country":"PK",
    "name:und_x_variant":[
        "\u0100b\u0101d"
    ],
    "wof:name":"Goth Abad Bhutto",
    "wof:placetype":"locality"
},
  "geometry": {"coordinates":[68.32916,27.7325],"type":"Point"}
}