{
  "type": "Feature",
  "properties": {
    "gn:admin1_code":"5.0",
    "gn:asciiname":"Goth Haji Qadir Bakhsh Baloch",
    "gn:country_code":"PK",
    "gn:dem":3,
    "gn:feature_class":"P",
    "gn:feature_code":"PPL",
    "gn:name":"Goth Haji Qadir Bakhsh Baloch",
    "gn:population":0,
    "gn:timezone":"Asia/Karachi",
    "iso:country":"PK",
    "wof:name":"Goth Haji Qadir Bakhsh Baloch",
    "wof:placetype":"locality"
},
  "geometry": {"coordinates":[67.56243000000001,24.05899],"type":"Point"}
}