{
  "type": "Feature",
  "properties": {
    "gn:admin1_code":"4",
    "gn:asciiname":"Basti Tarkhanan Wali",
    "gn:country_code":"PK",
    "gn:dem":108,
    "gn:feature_class":"P",
    "gn:feature_code":"PPL",
    "gn:name":"Basti Tarkhanan Wali",
    "gn:population":0,
    "gn:timezone":"Asia/Karachi",
    "iso:country":"PK",
    "name:und_x_variant":[
        "Basti Tarkh\u0101nnw\u0101li",
        "Basti Tarkh\u0101n\u0101nw\u0101li",
        "Basti Tarkhanan Wali"
    ],
    "wof:name":"Basti Tarkhanan Wali",
    "wof:placetype":"locality"
},
  "geometry": {"coordinates":[71.3758,29.18686],"type":"Point"}
}