{
  "type": "Feature",
  "properties": {
    "gn:admin1_code":"4.0",
    "gn:asciiname":"Araianwala",
    "gn:country_code":"PK",
    "gn:dem":205,
    "gn:feature_class":"P",
    "gn:feature_code":"PPL",
    "gn:name":"Arai\u0101nw\u0101la",
    "gn:population":0,
    "gn:timezone":"Asia/Karachi",
    "iso:country":"PK",
    "name:mal_x_preferred":[
        "\u0d05\u0d30\u0d48\u0d7b\u0d35\u0d3e\u0d32"
    ],
    "wof:name":"Araianwala",
    "wof:placetype":"locality"
},
  "geometry": {"coordinates":[73.84056,31.62583],"type":"Point"}
}