{
  "type": "Feature",
  "properties": {
    "gn:admin1_code":"04",
    "gn:asciiname":"Tara Haveli Khurd",
    "gn:country_code":"PK",
    "gn:dem":160,
    "gn:feature_class":"P",
    "gn:feature_code":"PPL",
    "gn:name":"Tara Haveli Khurd",
    "gn:population":0,
    "gn:timezone":"Asia/Karachi",
    "iso:country":"PK",
    "name:und_x_variant":[
        "Haveli Tara",
        "T\u0101ra Haveli",
        "Tara Haveli Khurd"
    ],
    "wof:name":"Tara Haveli Khurd",
    "wof:placetype":"locality"
},
  "geometry": {"coordinates":[72.72295,30.66078],"type":"Point"}
}