{
  "type": "Feature",
  "properties": {
    "gn:admin1_code":"6.0",
    "gn:asciiname":"Saila",
    "gn:country_code":"PK",
    "gn:dem":633,
    "gn:feature_class":"P",
    "gn:feature_code":"PPL",
    "gn:name":"Saila",
    "gn:population":0,
    "gn:timezone":"Asia/Karachi",
    "iso:country":"PK",
    "name:und_x_variant":[
        "S\u0101ilah"
    ],
    "wof:name":"Saila",
    "wof:placetype":"locality"
},
  "geometry": {"coordinates":[73.73900999999999,33.51201],"type":"Point"}
}