{
  "type": "Feature",
  "properties": {
    "gn:admin1_code":"5.0",
    "gn:asciiname":"Goth Ghanwar Magsi",
    "gn:country_code":"PK",
    "gn:dem":24,
    "gn:feature_class":"P",
    "gn:feature_code":"PPL",
    "gn:name":"Goth Ghanwar Magsi",
    "gn:population":0,
    "gn:timezone":"Asia/Karachi",
    "iso:country":"PK",
    "name:und_x_variant":[
        "Ghanwar Mangsi"
    ],
    "wof:name":"Goth Ghanwar Magsi",
    "wof:placetype":"locality"
},
  "geometry": {"coordinates":[68.79236,25.73951],"type":"Point"}
}