{
  "type": "Feature",
  "properties": {
    "gn:admin1_code":"5",
    "gn:asciiname":"Qadin Shah Goth",
    "gn:country_code":"PK",
    "gn:dem":60,
    "gn:feature_class":"P",
    "gn:feature_code":"PPL",
    "gn:name":"Qadin Shah Goth",
    "gn:population":0,
    "gn:timezone":"Asia/Karachi",
    "iso:country":"PK",
    "wof:name":"Qadin Shah Goth",
    "wof:placetype":"locality"
},
  "geometry": {"coordinates":[68.90904999999999,27.54973],"type":"Point"}
}