{
  "type": "Feature",
  "properties": {
    "gn:admin1_code":"7.0",
    "gn:asciiname":"Jandoli",
    "gn:country_code":"PK",
    "gn:dem":1982,
    "gn:feature_class":"P",
    "gn:feature_code":"PPL",
    "gn:name":"Jandoli",
    "gn:population":0,
    "gn:timezone":"Asia/Karachi",
    "iso:country":"PK",
    "name:und_x_variant":[
        "Jundoli"
    ],
    "wof:name":"Jandoli",
    "wof:placetype":"locality"
},
  "geometry": {"coordinates":[73.64209,36.26463],"type":"Point"}
}