{
  "type": "Feature",
  "properties": {
    "gn:admin1_code":"4.0",
    "gn:asciiname":"Tibba Khanwala",
    "gn:country_code":"PK",
    "gn:dem":174,
    "gn:feature_class":"P",
    "gn:feature_code":"PPL",
    "gn:name":"Tibba Khanwala",
    "gn:population":0,
    "gn:timezone":"Asia/Karachi",
    "iso:country":"PK",
    "name:und_x_variant":[
        "T\u0101lib Hussainw\u0101la"
    ],
    "wof:name":"Tibba Khanwala",
    "wof:placetype":"locality"
},
  "geometry": {"coordinates":[71.89086999999998,31.33139000000001],"type":"Point"}
}