{
  "type": "Feature",
  "properties": {
    "gn:admin1_code":"4.0",
    "gn:asciiname":"Alamgarh",
    "gn:country_code":"PK",
    "gn:dem":252,
    "gn:feature_class":"P",
    "gn:feature_code":"PPL",
    "gn:name":"Alamgarh",
    "gn:population":0,
    "gn:timezone":"Asia/Karachi",
    "iso:country":"PK",
    "name:fas_x_preferred":[
        "\u0627\u0644\u0627\u0645\u06af\u0627\u0631\u0647"
    ],
    "name:urd_x_preferred":[
        "\u0639\u0627\u0644\u0645 \u06af\u0691\u06be"
    ],
    "wof:name":"Alamgarh",
    "wof:placetype":"locality"
},
  "geometry": {"coordinates":[74.16060999999998,32.68051],"type":"Point"}
}