{
  "type": "Feature",
  "properties": {
    "gn:admin1_code":"3",
    "gn:asciiname":"Chokel Banda",
    "gn:country_code":"PK",
    "gn:dem":3152,
    "gn:feature_class":"P",
    "gn:feature_code":"PPL",
    "gn:name":"Chokel Banda",
    "gn:population":0,
    "gn:timezone":"Asia/Karachi",
    "iso:country":"PK",
    "name:eng_x_preferred":[
        "Chokel Banda"
    ],
    "wof:name":"Chokel Banda",
    "wof:placetype":"locality"
},
  "geometry": {"coordinates":[72.65429,35.35913],"type":"Point"}
}