{
  "type": "Feature",
  "properties": {
    "gn:admin1_code":"04",
    "gn:asciiname":"Shaikhpura Kahna",
    "gn:country_code":"PK",
    "gn:dem":199,
    "gn:feature_class":"P",
    "gn:feature_code":"PPL",
    "gn:name":"Shaikhpura Kahna",
    "gn:population":0,
    "gn:timezone":"Asia/Karachi",
    "iso:country":"PK",
    "name:und_x_variant":[
        "Sheikhpura Kohna",
        "Shaikhpur Kuhna",
        "Shaikhpura Kahna"
    ],
    "wof:name":"Shaikhpura Kahna",
    "wof:placetype":"locality"
},
  "geometry": {"coordinates":[74.55913000000002,31.07507],"type":"Point"}
}