{
  "type": "Feature",
  "properties": {
    "gn:admin1_code":"4.0",
    "gn:asciiname":"Dhok Bulandi",
    "gn:country_code":"PK",
    "gn:dem":553,
    "gn:feature_class":"P",
    "gn:feature_code":"PPL",
    "gn:name":"Dhok Bulandi",
    "gn:population":0,
    "gn:timezone":"Asia/Karachi",
    "iso:country":"PK",
    "name:und_x_variant":[
        "Dhok Badar"
    ],
    "wof:name":"Dhok Bulandi",
    "wof:placetype":"locality"
},
  "geometry": {"coordinates":[73.21682,33.46373],"type":"Point"}
}