{
  "type": "Feature",
  "properties": {
    "gn:admin1_code":"4",
    "gn:asciiname":"Ghbalwala",
    "gn:country_code":"PK",
    "gn:dem":110,
    "gn:feature_class":"P",
    "gn:feature_code":"PPL",
    "gn:name":"Ghbalwala",
    "gn:population":0,
    "gn:timezone":"Asia/Karachi",
    "iso:country":"PK",
    "name:und_x_variant":[
        "Far\u012bdew\u0101la",
        "Gabalw\u0101la",
        "Ghabelw\u0101la"
    ],
    "wof:name":"Ghbalwala",
    "wof:placetype":"locality"
},
  "geometry": {"coordinates":[70.60672,29.72362],"type":"Point"}
}