{
  "type": "Feature",
  "properties": {
    "gn:admin1_code":"4",
    "gn:asciiname":"Nawanwala",
    "gn:country_code":"PK",
    "gn:dem":131,
    "gn:feature_class":"P",
    "gn:feature_code":"PPL",
    "gn:name":"Nawanwala",
    "gn:population":0,
    "gn:timezone":"Asia/Karachi",
    "iso:country":"PK",
    "name:und_x_variant":[
        "Ch\u0101h Naw\u0101n"
    ],
    "wof:name":"Nawanwala",
    "wof:placetype":"locality"
},
  "geometry": {"coordinates":[71.64005,30.5801],"type":"Point"}
}