{
  "type": "Feature",
  "properties": {
    "gn:admin1_code":"4",
    "gn:asciiname":"Shakh Madina",
    "gn:country_code":"PK",
    "gn:dem":140,
    "gn:feature_class":"P",
    "gn:feature_code":"PPL",
    "gn:name":"Shakh Madina",
    "gn:population":0,
    "gn:timezone":"Asia/Karachi",
    "iso:country":"PK",
    "name:und_x_variant":[
        "Mekr\u0101nw\u0101la"
    ],
    "wof:name":"Shakh Madina",
    "wof:placetype":"locality"
},
  "geometry": {"coordinates":[72.08627,30.5561],"type":"Point"}
}