{
  "type": "Feature",
  "properties": {
    "gn:admin1_code":"7.0",
    "gn:asciiname":"Hoto",
    "gn:country_code":"PK",
    "gn:dem":2947,
    "gn:feature_class":"P",
    "gn:feature_code":"PPL",
    "gn:name":"Hoto",
    "gn:population":0,
    "gn:timezone":"Asia/Karachi",
    "iso:country":"PK",
    "name:und_x_variant":[
        "Pokore",
        "Pakore",
        "Hoto"
    ],
    "wof:name":"Hoto",
    "wof:placetype":"locality"
},
  "geometry": {"coordinates":[75.72826999999999,35.68712],"type":"Point"}
}