{
  "type": "Feature",
  "properties": {
    "gn:admin1_code":"3.0",
    "gn:asciiname":"Sadat Madad Shah",
    "gn:country_code":"PK",
    "gn:dem":388,
    "gn:feature_class":"P",
    "gn:feature_code":"PPL",
    "gn:name":"Sadat Madad Shah",
    "gn:population":0,
    "gn:timezone":"Asia/Karachi",
    "iso:country":"PK",
    "name:und_x_variant":[
        "Sad\u0101t Madad Shah"
    ],
    "wof:name":"Sadat Madad Shah",
    "wof:placetype":"locality"
},
  "geometry": {"coordinates":[70.5992,33.01808],"type":"Point"}
}