{
  "type": "Feature",
  "properties": {
    "gn:admin1_code":"04",
    "gn:asciiname":"Rori Sethanwali",
    "gn:country_code":"PK",
    "gn:dem":164,
    "gn:feature_class":"P",
    "gn:feature_code":"PPL",
    "gn:name":"Rori Sethanwali",
    "gn:population":0,
    "gn:timezone":"Asia/Karachi",
    "iso:country":"PK",
    "name:und_x_variant":[
        "Ror\u012bw\u0101la"
    ],
    "wof:name":"Rori Sethanwali",
    "wof:placetype":"locality"
},
  "geometry": {"coordinates":[73.55518000000002,30.22588],"type":"Point"}
}