{
  "type": "Feature",
  "properties": {
    "gn:admin1_code":"3.0",
    "gn:asciiname":"Rokhan Payan",
    "gn:country_code":"PK",
    "gn:dem":1794,
    "gn:feature_class":"P",
    "gn:feature_code":"PPL",
    "gn:name":"Rokhan Payan",
    "gn:population":0,
    "gn:timezone":"Asia/Karachi",
    "iso:country":"PK",
    "wof:name":"Rokhan Payan",
    "wof:placetype":"locality"
},
  "geometry": {"coordinates":[71.90201,35.22452],"type":"Point"}
}