{
  "type": "Feature",
  "properties": {
    "gn:admin1_code":"5.0",
    "gn:asciiname":"Goth Nasir Khan",
    "gn:country_code":"PK",
    "gn:dem":55,
    "gn:feature_class":"P",
    "gn:feature_code":"PPL",
    "gn:name":"Goth Nasir Khan",
    "gn:population":0,
    "gn:timezone":"Asia/Karachi",
    "iso:country":"PK",
    "name:und_x_variant":[
        "Goth Nas\u012br Kh\u0101n Dasti"
    ],
    "wof:name":"Goth Nasir Khan",
    "wof:placetype":"locality"
},
  "geometry": {"coordinates":[68.43314000000001,28.35063],"type":"Point"}
}