{
  "type": "Feature",
  "properties": {
    "gn:admin1_code":"6",
    "gn:asciiname":"Kapar Gala",
    "gn:country_code":"PK",
    "gn:dem":703,
    "gn:feature_class":"P",
    "gn:feature_code":"PPL",
    "gn:name":"Kapar Gala",
    "gn:population":0,
    "gn:timezone":"Asia/Karachi",
    "iso:country":"PK",
    "wof:name":"Kapar Gala",
    "wof:placetype":"locality"
},
  "geometry": {"coordinates":[74.1099,33.07472],"type":"Point"}
}