{
  "type": "Feature",
  "properties": {
    "gn:admin1_code":"2.0",
    "gn:asciiname":"Yahya Kili",
    "gn:country_code":"PK",
    "gn:dem":1471,
    "gn:feature_class":"P",
    "gn:feature_code":"PPL",
    "gn:name":"Yahya Kili",
    "gn:population":0,
    "gn:timezone":"Asia/Karachi",
    "iso:country":"PK",
    "name:und_x_variant":[
        "Mulla Yahya Kili"
    ],
    "wof:name":"Yahya Kili",
    "wof:placetype":"locality"
},
  "geometry": {"coordinates":[66.55116,30.57514],"type":"Point"}
}