{
  "type": "Feature",
  "properties": {
    "gn:admin1_code":"7.0",
    "gn:asciiname":"Lamu",
    "gn:country_code":"PK",
    "gn:dem":3325,
    "gn:feature_class":"P",
    "gn:feature_code":"PPL",
    "gn:name":"Lamu",
    "gn:population":0,
    "gn:timezone":"Asia/Karachi",
    "iso:country":"PK",
    "wof:name":"Lamu",
    "wof:placetype":"locality"
},
  "geometry": {"coordinates":[75.79438,35.12239],"type":"Point"}
}