{
  "type": "Feature",
  "properties": {
    "gn:admin1_code":"05",
    "gn:asciiname":"Rango Khan Rind",
    "gn:country_code":"PK",
    "gn:dem":25,
    "gn:feature_class":"P",
    "gn:feature_code":"PPL",
    "gn:name":"Rango Khan Rind",
    "gn:population":0,
    "gn:timezone":"Asia/Karachi",
    "iso:country":"PK",
    "name:und_x_variant":[
        "Rakh\u016bn Kh\u0101n Rind",
        "Rakhi\u0101l Rind",
        "Rango Khan Rind"
    ],
    "wof:name":"Rango Khan Rind",
    "wof:placetype":"locality"
},
  "geometry": {"coordinates":[68.72457,26.08441],"type":"Point"}
}