{
  "type": "Feature",
  "properties": {
    "gn:admin1_code":"3.0",
    "gn:asciiname":"Ayub Khan",
    "gn:country_code":"PK",
    "gn:dem":325,
    "gn:feature_class":"P",
    "gn:feature_code":"PPL",
    "gn:name":"Ayub Khan",
    "gn:population":0,
    "gn:timezone":"Asia/Karachi",
    "iso:country":"PK",
    "name:eng_x_preferred":[
        "Ayub Khan"
    ],
    "wof:name":"Ayub Khan",
    "wof:placetype":"locality"
},
  "geometry": {"coordinates":[71.98862,34.25309],"type":"Point"}
}