{
  "type": "Feature",
  "properties": {
    "gn:admin1_code":"4.0",
    "gn:asciiname":"Basti Loharanwali",
    "gn:country_code":"PK",
    "gn:dem":114,
    "gn:feature_class":"P",
    "gn:feature_code":"PPL",
    "gn:name":"Basti Loharanwali",
    "gn:population":0,
    "gn:timezone":"Asia/Karachi",
    "iso:country":"PK",
    "name:eng_x_preferred":[
        "Basti Loharanwali"
    ],
    "wof:name":"Basti Loharanwali",
    "wof:placetype":"locality"
},
  "geometry": {"coordinates":[71.51998,29.49625],"type":"Point"}
}