{
  "type": "Feature",
  "properties": {
    "gn:admin1_code":"2.0",
    "gn:asciiname":"Suleman Khel",
    "gn:country_code":"PK",
    "gn:dem":1436,
    "gn:feature_class":"P",
    "gn:feature_code":"PPL",
    "gn:name":"Suleman Khel",
    "gn:population":0,
    "gn:timezone":"Asia/Karachi",
    "iso:country":"PK",
    "name:und_x_variant":[
        "H\u0101ji Khairo"
    ],
    "wof:name":"Suleman Khel",
    "wof:placetype":"locality"
},
  "geometry": {"coordinates":[66.69685,30.47643],"type":"Point"}
}