{
  "type": "Feature",
  "properties": {
    "gn:admin1_code":"6",
    "gn:asciiname":"Mohri",
    "gn:country_code":"PK",
    "gn:dem":2715,
    "gn:feature_class":"P",
    "gn:feature_code":"PPL",
    "gn:name":"Mohri",
    "gn:population":0,
    "gn:timezone":"Asia/Karachi",
    "iso:country":"PK",
    "wof:name":"Mohri",
    "wof:placetype":"locality"
},
  "geometry": {"coordinates":[73.72594000000002,34.54374],"type":"Point"}
}