{
  "type": "Feature",
  "properties": {
    "gn:admin1_code":"5",
    "gn:asciiname":"Goth Muhammad Khadri",
    "gn:country_code":"PK",
    "gn:dem":27,
    "gn:feature_class":"P",
    "gn:feature_code":"PPL",
    "gn:name":"Goth Muhammad Khadri",
    "gn:population":0,
    "gn:timezone":"Asia/Karachi",
    "iso:country":"PK",
    "name:und_x_variant":[
        "Goth Khidrion",
        "Goth Muhammad Khidri"
    ],
    "wof:name":"Goth Muhammad Khadri",
    "wof:placetype":"locality"
},
  "geometry": {"coordinates":[68.56520999999999,25.67494],"type":"Point"}
}