{
  "type": "Feature",
  "properties": {
    "gn:admin1_code":"5.0",
    "gn:asciiname":"Goth Ghulam Sarwar",
    "gn:country_code":"PK",
    "gn:dem":45,
    "gn:feature_class":"P",
    "gn:feature_code":"PPL",
    "gn:name":"Goth Ghulam Sarwar",
    "gn:population":0,
    "gn:timezone":"Asia/Karachi",
    "iso:country":"PK",
    "name:und_x_variant":[
        "Goth Sarwar Kh\u0101n Bhutta"
    ],
    "wof:name":"Goth Ghulam Sarwar",
    "wof:placetype":"locality"
},
  "geometry": {"coordinates":[67.74639999999999,27.47819],"type":"Point"}
}