{
  "type": "Feature",
  "properties": {
    "gn:admin1_code":"5.0",
    "gn:asciiname":"Khamiso Lutani",
    "gn:country_code":"PK",
    "gn:dem":10,
    "gn:feature_class":"P",
    "gn:feature_code":"PPL",
    "gn:name":"Khamiso Lutani",
    "gn:population":0,
    "gn:timezone":"Asia/Karachi",
    "iso:country":"PK",
    "name:eng_x_preferred":[
        "Khamiso Lutani"
    ],
    "wof:name":"Khamiso Lutani",
    "wof:placetype":"locality"
},
  "geometry": {"coordinates":[68.13393000000001,24.52922],"type":"Point"}
}