{
  "type": "Feature",
  "properties": {
    "gn:admin1_code":"4.0",
    "gn:asciiname":"Chak Muhammad Rafiq",
    "gn:country_code":"PK",
    "gn:dem":181,
    "gn:feature_class":"P",
    "gn:feature_code":"PPL",
    "gn:name":"Chak Muhammad Rafiq",
    "gn:population":0,
    "gn:timezone":"Asia/Karachi",
    "iso:country":"PK",
    "wof:name":"Chak Muhammad Rafiq",
    "wof:placetype":"locality"
},
  "geometry": {"coordinates":[74.01380999999998,30.60579],"type":"Point"}
}