{
  "type": "Feature",
  "properties": {
    "gn:admin1_code":"06",
    "gn:asciiname":"Sagri",
    "gn:country_code":"PK",
    "gn:dem":289,
    "gn:feature_class":"P",
    "gn:feature_code":"PPL",
    "gn:name":"Sagri",
    "gn:population":0,
    "gn:timezone":"Asia/Karachi",
    "iso:country":"PK",
    "wof:name":"Sagri",
    "wof:placetype":"locality"
},
  "geometry": {"coordinates":[73.6009,33.07002],"type":"Point"}
}