{
  "type": "Feature",
  "properties": {
    "gn:admin1_code":"05",
    "gn:asciiname":"Panero",
    "gn:country_code":"PK",
    "gn:dem":58,
    "gn:feature_class":"P",
    "gn:feature_code":"PPL",
    "gn:name":"Panero",
    "gn:population":0,
    "gn:timezone":"Asia/Karachi",
    "iso:country":"PK",
    "name:und_x_variant":[
        "Paniro",
        "Panero"
    ],
    "wof:name":"Panero",
    "wof:placetype":"locality"
},
  "geometry": {"coordinates":[68.68926999999999,27.45016],"type":"Point"}
}