{
  "type": "Feature",
  "properties": {
    "gn:admin1_code":"4.0",
    "gn:asciiname":"Gulchandar",
    "gn:country_code":"PK",
    "gn:dem":263,
    "gn:feature_class":"P",
    "gn:feature_code":"PPL",
    "gn:name":"Gulchandar",
    "gn:population":0,
    "gn:timezone":"Asia/Karachi",
    "iso:country":"PK",
    "name:und_x_variant":[
        "Gulohandal"
    ],
    "wof:name":"Gulchandar",
    "wof:placetype":"locality"
},
  "geometry": {"coordinates":[74.75408,32.44008],"type":"Point"}
}