{
  "type": "Feature",
  "properties": {
    "gn:admin1_code":"4.0",
    "gn:asciiname":"Chak Two Hundred Eleven Gugera Branch",
    "gn:country_code":"PK",
    "gn:dem":170,
    "gn:feature_class":"P",
    "gn:feature_code":"PPL",
    "gn:name":"Chak Two Hundred Eleven Gugera Branch",
    "gn:population":0,
    "gn:timezone":"Asia/Karachi",
    "iso:country":"PK",
    "name:und_x_variant":[
        "Al\u012bw\u0101l"
    ],
    "wof:name":"Chak Two Hundred Eleven Gugera Branch",
    "wof:placetype":"locality"
},
  "geometry": {"coordinates":[72.82984,30.98022000000001],"type":"Point"}
}