{
  "type": "Feature",
  "properties": {
    "gn:admin1_code":"4.0",
    "gn:asciiname":"Akwal",
    "gn:country_code":"PK",
    "gn:dem":474,
    "gn:feature_class":"P",
    "gn:feature_code":"PPL",
    "gn:name":"Akwal",
    "gn:population":0,
    "gn:timezone":"Asia/Karachi",
    "iso:country":"PK",
    "wof:name":"Akwal",
    "wof:placetype":"locality"
},
  "geometry": {"coordinates":[72.36476,32.93060999999999],"type":"Point"}
}