{
  "type": "Feature",
  "properties": {
    "gn:admin1_code":"6",
    "gn:asciiname":"Narian",
    "gn:country_code":"PK",
    "gn:dem":1134,
    "gn:feature_class":"P",
    "gn:feature_code":"PPL",
    "gn:name":"Narian",
    "gn:population":0,
    "gn:timezone":"Asia/Karachi",
    "iso:country":"PK",
    "name:und_x_variant":[
        "N\u0101ri\u0101n"
    ],
    "wof:name":"Narian",
    "wof:placetype":"locality"
},
  "geometry": {"coordinates":[73.91927,33.777],"type":"Point"}
}