{
  "type": "Feature",
  "properties": {
    "gn:admin1_code":"5",
    "gn:asciiname":"Goth Talib Moula Colony",
    "gn:country_code":"PK",
    "gn:dem":27,
    "gn:feature_class":"P",
    "gn:feature_code":"PPL",
    "gn:name":"Goth Talib Moula Colony",
    "gn:population":0,
    "gn:timezone":"Asia/Karachi",
    "iso:country":"PK",
    "name:eng_x_preferred":[
        "T\u0101lib M\u016bsa Colony"
    ],
    "wof:name":"Goth Talib Moula Colony",
    "wof:placetype":"locality"
},
  "geometry": {"coordinates":[68.43245,25.52822],"type":"Point"}
}