{
  "type": "Feature",
  "properties": {
    "gn:admin1_code":"3",
    "gn:asciiname":"Chargul",
    "gn:country_code":"PK",
    "gn:dem":337,
    "gn:feature_class":"P",
    "gn:feature_code":"PPL",
    "gn:name":"Chargul",
    "gn:population":0,
    "gn:timezone":"Asia/Karachi",
    "iso:country":"PK",
    "name:eng_x_preferred":[
        "Ch\u0101rgul"
    ],
    "wof:name":"Chargul",
    "wof:placetype":"locality"
},
  "geometry": {"coordinates":[72.25516,34.3019],"type":"Point"}
}