{
  "type": "Feature",
  "properties": {
    "gn:admin1_code":"3",
    "gn:asciiname":"Mial",
    "gn:country_code":"PK",
    "gn:dem":1143,
    "gn:feature_class":"P",
    "gn:feature_code":"PPL",
    "gn:name":"Mial",
    "gn:population":0,
    "gn:timezone":"Asia/Karachi",
    "iso:country":"PK",
    "name:und_x_variant":[
        "Mih\u0101l"
    ],
    "wof:name":"Mial",
    "wof:placetype":"locality"
},
  "geometry": {"coordinates":[73.1407,34.15769],"type":"Point"}
}