{
  "type": "Feature",
  "properties": {
    "gn:admin1_code":"4",
    "gn:asciiname":"Piru Chak",
    "gn:country_code":"PK",
    "gn:dem":229,
    "gn:feature_class":"P",
    "gn:feature_code":"PPL",
    "gn:name":"Piru Chak",
    "gn:population":0,
    "gn:timezone":"Asia/Karachi",
    "iso:country":"PK",
    "wof:name":"Piru Chak",
    "wof:placetype":"locality"
},
  "geometry": {"coordinates":[74.27039000000001,32.18245],"type":"Point"}
}