{
  "type": "Feature",
  "properties": {
    "gn:admin1_code":"2",
    "gn:asciiname":"Landi Three Hundred Sixty-three",
    "gn:country_code":"PK",
    "gn:dem":802,
    "gn:feature_class":"P",
    "gn:feature_code":"PPL",
    "gn:name":"Landi Three Hundred Sixty-three",
    "gn:population":0,
    "gn:timezone":"Asia/Karachi",
    "iso:country":"PK",
    "name:und_x_variant":[
        "L\u0101ndi 363"
    ],
    "wof:name":"Landi Three Hundred Sixty-three",
    "wof:placetype":"locality"
},
  "geometry": {"coordinates":[61.82084,28.92976],"type":"Point"}
}