{
  "type": "Feature",
  "properties": {
    "gn:admin1_code":"4.0",
    "gn:asciiname":"Chak Two Hundred Twenty-four Gugera Branch",
    "gn:country_code":"PK",
    "gn:dem":169,
    "gn:feature_class":"P",
    "gn:feature_code":"PPL",
    "gn:name":"Chak Two Hundred Twenty-four Gugera Branch",
    "gn:population":0,
    "gn:timezone":"Asia/Karachi",
    "iso:country":"PK",
    "name:und_x_variant":[
        "Darp\u0101l"
    ],
    "wof:name":"Chak Two Hundred Twenty-four Gugera Branch",
    "wof:placetype":"locality"
},
  "geometry": {"coordinates":[72.78749000000001,31.07172000000001],"type":"Point"}
}