{
  "type": "Feature",
  "properties": {
    "gn:admin1_code":"3.0",
    "gn:asciiname":"Dhok Amir Khan",
    "gn:country_code":"PK",
    "gn:dem":396,
    "gn:feature_class":"P",
    "gn:feature_code":"PPL",
    "gn:name":"Dhok Amir Khan",
    "gn:population":0,
    "gn:timezone":"Asia/Karachi",
    "iso:country":"PK",
    "wof:name":"Dhok Amir Khan",
    "wof:placetype":"locality"
},
  "geometry": {"coordinates":[71.84784000000001,33.63429],"type":"Point"}
}