{
  "type": "Feature",
  "properties": {
    "gn:admin1_code":"2.0",
    "gn:asciiname":"Barah Halani",
    "gn:country_code":"PK",
    "gn:dem":1597,
    "gn:feature_class":"P",
    "gn:feature_code":"PPL",
    "gn:name":"Barah Halani",
    "gn:population":0,
    "gn:timezone":"Asia/Karachi",
    "iso:country":"PK",
    "wof:name":"Barah Halani",
    "wof:placetype":"locality"
},
  "geometry": {"coordinates":[68.44004,30.29615],"type":"Point"}
}