{
  "type": "Feature",
  "properties": {
    "gn:admin1_code":"4.0",
    "gn:asciiname":"Minandi Gharbi",
    "gn:country_code":"PK",
    "gn:dem":324,
    "gn:feature_class":"P",
    "gn:feature_code":"PPL",
    "gn:name":"Minandi Gharbi",
    "gn:population":0,
    "gn:timezone":"Asia/Karachi",
    "iso:country":"PK",
    "wof:name":"Minandi Gharbi",
    "wof:placetype":"locality"
},
  "geometry": {"coordinates":[71.80306999999998,32.92435],"type":"Point"}
}