{
  "type": "Feature",
  "properties": {
    "gn:admin1_code":"2.0",
    "gn:asciiname":"Muhammad Ayaz",
    "gn:country_code":"PK",
    "gn:dem":2111,
    "gn:feature_class":"P",
    "gn:feature_code":"PPL",
    "gn:name":"Muhammad Ayaz",
    "gn:population":0,
    "gn:timezone":"Asia/Karachi",
    "iso:country":"PK",
    "wof:name":"Muhammad Ayaz",
    "wof:placetype":"locality"
},
  "geometry": {"coordinates":[67.7415,31.49792],"type":"Point"}
}