{
  "type": "Feature",
  "properties": {
    "gn:admin1_code":"2.0",
    "gn:asciiname":"Kili Mehroun",
    "gn:country_code":"PK",
    "gn:dem":1748,
    "gn:feature_class":"P",
    "gn:feature_code":"PPL",
    "gn:name":"Kili Mehroun",
    "gn:population":0,
    "gn:timezone":"Asia/Karachi",
    "iso:country":"PK",
    "wof:name":"Kili Mehroun",
    "wof:placetype":"locality"
},
  "geometry": {"coordinates":[66.59724,29.80702],"type":"Point"}
}