{
  "type": "Feature",
  "properties": {
    "gn:admin1_code":"2.0",
    "gn:asciiname":"Janizai",
    "gn:country_code":"PK",
    "gn:dem":83,
    "gn:feature_class":"P",
    "gn:feature_code":"PPL",
    "gn:name":"Janizai",
    "gn:population":0,
    "gn:timezone":"Asia/Karachi",
    "iso:country":"PK",
    "wof:name":"Janizai",
    "wof:placetype":"locality"
},
  "geometry": {"coordinates":[67.64168000000001,28.82694],"type":"Point"}
}