{
  "type": "Feature",
  "properties": {
    "gn:admin1_code":"3.0",
    "gn:asciiname":"Malanga",
    "gn:country_code":"PK",
    "gn:dem":636,
    "gn:feature_class":"P",
    "gn:feature_code":"PPL",
    "gn:name":"Malanga",
    "gn:population":0,
    "gn:timezone":"Asia/Karachi",
    "iso:country":"PK",
    "wof:name":"Malanga",
    "wof:placetype":"locality"
},
  "geometry": {"coordinates":[71.41049,33.04473],"type":"Point"}
}