{
  "type": "Feature",
  "properties": {
    "gn:admin1_code":"4",
    "gn:asciiname":"Nasirwala",
    "gn:country_code":"PK",
    "gn:dem":134,
    "gn:feature_class":"P",
    "gn:feature_code":"PPL",
    "gn:name":"Nasirwala",
    "gn:population":0,
    "gn:timezone":"Asia/Karachi",
    "iso:country":"PK",
    "name:eng_x_preferred":[
        "N\u0101sirw\u0101la"
    ],
    "wof:name":"Nasirwala",
    "wof:placetype":"locality"
},
  "geometry": {"coordinates":[70.72561,30.48833],"type":"Point"}
}