{
  "type": "Feature",
  "properties": {
    "gn:admin1_code":"3.0",
    "gn:asciiname":"Bar Kand",
    "gn:country_code":"PK",
    "gn:dem":1709,
    "gn:feature_class":"P",
    "gn:feature_code":"PPL",
    "gn:name":"Bar Kand",
    "gn:population":0,
    "gn:timezone":"Asia/Karachi",
    "iso:country":"PK",
    "wof:name":"Bar Kand",
    "wof:placetype":"locality"
},
  "geometry": {"coordinates":[72.87376,34.55171],"type":"Point"}
}