{
  "type": "Feature",
  "properties": {
    "gn:admin1_code":"2.0",
    "gn:asciiname":"Jamia Arbia Zio-ul-Uloom",
    "gn:country_code":"PK",
    "gn:dem":1473,
    "gn:feature_class":"P",
    "gn:feature_code":"PPL",
    "gn:name":"Jamia Arbia Zio-ul-Uloom",
    "gn:population":0,
    "gn:timezone":"Asia/Karachi",
    "iso:country":"PK",
    "wof:name":"Jamia Arbia Zio-ul-Uloom",
    "wof:placetype":"locality"
},
  "geometry": {"coordinates":[66.85639,30.56556],"type":"Point"}
}