{
  "type": "Feature",
  "properties": {
    "gn:admin1_code":"3.0",
    "gn:asciiname":"Isa Khel",
    "gn:country_code":"PK",
    "gn:dem":365,
    "gn:feature_class":"P",
    "gn:feature_code":"PPL",
    "gn:name":"Isa Khel",
    "gn:population":0,
    "gn:timezone":"Asia/Karachi",
    "iso:country":"PK",
    "name:ben_x_preferred":[
        "\u0987\u09b8\u09be\u0996\u09c7\u09b2"
    ],
    "name:cat_x_preferred":[
        "Isakhel"
    ],
    "name:deu_x_preferred":[
        "Isa Khel"
    ],
    "name:fas_x_preferred":[
        "\u0639\u06cc\u0633\u06cc \u062e\u06cc\u0644"
    ],
    "name:fra_x_preferred":[
        "Isakhel"
    ],
    "name:por_x_preferred":[
        "Isa Khel"
    ],
    "name:und_x_variant":[
        "\u012asat"
    ],
    "name:urd_x_preferred":[
        "\u0639\u06cc\u0633\u06cc \u062e\u06cc\u0644"
    ],
    "wof:name":"Isa Khel",
    "wof:placetype":"locality"
},
  "geometry": {"coordinates":[70.91677,32.88224],"type":"Point"}
}