{
  "type": "Feature",
  "properties": {
    "gn:admin1_code":"6",
    "gn:asciiname":"Barawan",
    "gn:country_code":"PK",
    "gn:dem":2452,
    "gn:feature_class":"P",
    "gn:feature_code":"PPL",
    "gn:name":"Barawan",
    "gn:population":0,
    "gn:timezone":"Asia/Karachi",
    "iso:country":"PK",
    "wof:name":"Barawan",
    "wof:placetype":"locality"
},
  "geometry": {"coordinates":[74.1875,34.70417],"type":"Point"}
}