{
  "type": "Feature",
  "properties": {
    "gn:admin1_code":"04",
    "gn:asciiname":"Makhna Thakarke",
    "gn:country_code":"PK",
    "gn:dem":176,
    "gn:feature_class":"P",
    "gn:feature_code":"PPL",
    "gn:name":"Makhna Thakarke",
    "gn:population":0,
    "gn:timezone":"Asia/Karachi",
    "iso:country":"PK",
    "name:und_x_variant":[
        "Thakkarke Banda"
    ],
    "wof:name":"Makhna Thakarke",
    "wof:placetype":"locality"
},
  "geometry": {"coordinates":[73.82524000000002,30.4666],"type":"Point"}
}