{
  "type": "Feature",
  "properties": {
    "gn:admin1_code":"4",
    "gn:asciiname":"Mad Khairu Jua",
    "gn:country_code":"PK",
    "gn:dem":100,
    "gn:feature_class":"P",
    "gn:feature_code":"PPL",
    "gn:name":"Mad Khairu Jua",
    "gn:population":0,
    "gn:timezone":"Asia/Karachi",
    "iso:country":"PK",
    "name:und_x_variant":[
        "Mad Hkalru Iua"
    ],
    "wof:name":"Mad Khairu Jua",
    "wof:placetype":"locality"
},
  "geometry": {"coordinates":[70.32897,29.23107000000001],"type":"Point"}
}