{
  "type": "Feature",
  "properties": {
    "gn:admin1_code":"3.0",
    "gn:asciiname":"Basti Sandilan",
    "gn:country_code":"PK",
    "gn:dem":179,
    "gn:feature_class":"P",
    "gn:feature_code":"PPL",
    "gn:name":"Basti Sandilan",
    "gn:population":0,
    "gn:timezone":"Asia/Karachi",
    "iso:country":"PK",
    "name:und_x_variant":[
        "Basti Sandail\u0101n"
    ],
    "wof:name":"Basti Sandilan",
    "wof:placetype":"locality"
},
  "geometry": {"coordinates":[71.03413,32.11551],"type":"Point"}
}