{
  "type": "Feature",
  "properties": {
    "gn:admin1_code":"03",
    "gn:asciiname":"Milam",
    "gn:country_code":"PK",
    "gn:dem":496,
    "gn:feature_class":"P",
    "gn:feature_code":"PPL",
    "gn:name":"Milam",
    "gn:population":0,
    "gn:timezone":"Asia/Karachi",
    "iso:country":"PK",
    "name:ceb_x_preferred":[
        "Milam"
    ],
    "name:deu_x_preferred":[
        "Milam"
    ],
    "name:fra_x_preferred":[
        "Milam"
    ],
    "name:srp_x_preferred":[
        "\u041c\u0430\u0458\u043b\u0430\u043c"
    ],
    "name:swe_x_preferred":[
        "Milam"
    ],
    "name:und_x_variant":[
        "Mailam",
        "Milam"
    ],
    "name:vol_x_preferred":[
        "Milam"
    ],
    "wof:name":"Milam",
    "wof:placetype":"locality"
},
  "geometry": {"coordinates":[72.89654,33.9992],"type":"Point"}
}