{
  "type": "Feature",
  "properties": {
    "gn:admin1_code":"4.0",
    "gn:asciiname":"Bahianwala",
    "gn:country_code":"PK",
    "gn:dem":251,
    "gn:feature_class":"P",
    "gn:feature_code":"PPL",
    "gn:name":"Bahianwala",
    "gn:population":0,
    "gn:timezone":"Asia/Karachi",
    "iso:country":"PK",
    "name:und_x_variant":[
        "Bhh\u0101\u012by\u0101nw\u0101la"
    ],
    "wof:name":"Bahianwala",
    "wof:placetype":"locality"
},
  "geometry": {"coordinates":[71.73076,32.58642],"type":"Point"}
}