{
  "type": "Feature",
  "properties": {
    "gn:admin1_code":"5",
    "gn:asciiname":"Daro",
    "gn:country_code":"PK",
    "gn:dem":42,
    "gn:feature_class":"P",
    "gn:feature_code":"PPL",
    "gn:name":"Daro",
    "gn:population":0,
    "gn:timezone":"Asia/Karachi",
    "iso:country":"PK",
    "name:eng_x_preferred":[
        "Daro"
    ],
    "name:urd_x_preferred":[
        "\u062f\u0627\u0631\u0648"
    ],
    "wof:name":"Daro",
    "wof:placetype":"locality"
},
  "geometry": {"coordinates":[67.74581999999999,26.76883],"type":"Point"}
}