{
  "type": "Feature",
  "properties": {
    "gn:admin1_code":"5",
    "gn:asciiname":"Zour Muhammad Khan",
    "gn:country_code":"PK",
    "gn:dem":20,
    "gn:feature_class":"P",
    "gn:feature_code":"PPL",
    "gn:name":"Zour Muhammad Khan",
    "gn:population":0,
    "gn:timezone":"Asia/Karachi",
    "iso:country":"PK",
    "name:und_x_variant":[
        "Zaur Muhammad Kh\u0101n"
    ],
    "wof:name":"Zour Muhammad Khan",
    "wof:placetype":"locality"
},
  "geometry": {"coordinates":[68.73857,25.26557],"type":"Point"}
}