{
  "type": "Feature",
  "properties": {
    "gn:admin1_code":"2.0",
    "gn:asciiname":"Warindo",
    "gn:country_code":"PK",
    "gn:dem":824,
    "gn:feature_class":"P",
    "gn:feature_code":"PPL",
    "gn:name":"Warindo",
    "gn:population":0,
    "gn:timezone":"Asia/Karachi",
    "iso:country":"PK",
    "wof:name":"Warindo",
    "wof:placetype":"locality"
},
  "geometry": {"coordinates":[66.98915,27.37359],"type":"Point"}
}