{
  "type": "Feature",
  "properties": {
    "gn:admin1_code":"4.0",
    "gn:asciiname":"Chak Four Hundred Thirty-one Thal Development Authority",
    "gn:country_code":"PK",
    "gn:dem":143,
    "gn:feature_class":"P",
    "gn:feature_code":"PPL",
    "gn:name":"Chak Four Hundred Thirty-one Thal Development Authority",
    "gn:population":0,
    "gn:timezone":"Asia/Karachi",
    "iso:country":"PK",
    "wof:name":"Chak Four Hundred Thirty-one Thal Development Authority",
    "wof:placetype":"locality"
},
  "geometry": {"coordinates":[71.22466999999997,30.77459],"type":"Point"}
}