{
  "type": "Feature",
  "properties": {
    "gn:admin1_code":"3",
    "gn:asciiname":"Topsin",
    "gn:country_code":"PK",
    "gn:dem":1473,
    "gn:feature_class":"P",
    "gn:feature_code":"PPL",
    "gn:name":"Topsin",
    "gn:population":0,
    "gn:timezone":"Asia/Karachi",
    "iso:country":"PK",
    "wof:name":"Topsin",
    "wof:placetype":"locality"
},
  "geometry": {"coordinates":[72.40422,34.72605],"type":"Point"}
}