{
  "type": "Feature",
  "properties": {
    "gn:admin1_code":"1.0",
    "gn:asciiname":"Bichaki Jani Khel",
    "gn:country_code":"PK",
    "gn:dem":390,
    "gn:feature_class":"P",
    "gn:feature_code":"PPL",
    "gn:name":"Bichaki Jani Khel",
    "gn:population":0,
    "gn:timezone":"Asia/Karachi",
    "iso:country":"PK",
    "wof:name":"Bichaki Jani Khel",
    "wof:placetype":"locality"
},
  "geometry": {"coordinates":[70.49455999999998,32.81328],"type":"Point"}
}