{
  "type": "Feature",
  "properties": {
    "gn:admin1_code":"3",
    "gn:asciiname":"Bachorai",
    "gn:country_code":"PK",
    "gn:dem":1954,
    "gn:feature_class":"P",
    "gn:feature_code":"PPL",
    "gn:name":"Bachorai",
    "gn:population":0,
    "gn:timezone":"Asia/Karachi",
    "iso:country":"PK",
    "wof:name":"Bachorai",
    "wof:placetype":"locality"
},
  "geometry": {"coordinates":[72.36968,35.04762],"type":"Point"}
}