{
  "type": "Feature",
  "properties": {
    "gn:admin1_code":"5.0",
    "gn:asciiname":"Goth Haji Muhammad Husain",
    "gn:country_code":"PK",
    "gn:dem":47,
    "gn:feature_class":"P",
    "gn:feature_code":"PPL",
    "gn:name":"Goth Haji Muhammad Husain",
    "gn:population":0,
    "gn:timezone":"Asia/Karachi",
    "iso:country":"PK",
    "name:und_x_variant":[
        "Goth Haji Muhammad Hasan"
    ],
    "wof:name":"Goth Haji Muhammad Husain",
    "wof:placetype":"locality"
},
  "geometry": {"coordinates":[68.35226,26.85645],"type":"Point"}
}