{
  "type": "Feature",
  "properties": {
    "gn:admin1_code":"7.0",
    "gn:asciiname":"Dangat",
    "gn:country_code":"PK",
    "gn:dem":2523,
    "gn:feature_class":"P",
    "gn:feature_code":"PPL",
    "gn:name":"Dangat",
    "gn:population":0,
    "gn:timezone":"Asia/Karachi",
    "iso:country":"PK",
    "wof:name":"Dangat",
    "wof:placetype":"locality"
},
  "geometry": {"coordinates":[74.82250999999999,35.2159],"type":"Point"}
}