{
  "type": "Feature",
  "properties": {
    "gn:admin1_code":"4.0",
    "gn:asciiname":"Dhok Pidwalan",
    "gn:country_code":"PK",
    "gn:dem":622,
    "gn:feature_class":"P",
    "gn:feature_code":"PPL",
    "gn:name":"Dhok Pidwalan",
    "gn:population":0,
    "gn:timezone":"Asia/Karachi",
    "iso:country":"PK",
    "wof:name":"Dhok Pidwalan",
    "wof:placetype":"locality"
},
  "geometry": {"coordinates":[72.64153,32.82798],"type":"Point"}
}