{
  "type": "Feature",
  "properties": {
    "gn:admin1_code":"4.0",
    "gn:asciiname":"Tutanwala Dera",
    "gn:country_code":"PK",
    "gn:dem":210,
    "gn:feature_class":"P",
    "gn:feature_code":"PPL",
    "gn:name":"Tutanwala Dera",
    "gn:population":0,
    "gn:timezone":"Asia/Karachi",
    "iso:country":"PK",
    "name:und_x_variant":[
        "N\u0101n\u0101nw\u0101la",
        "Non\u0101nw\u0101la",
        "Tutanwala Dera"
    ],
    "wof:name":"Tutanwala Dera",
    "wof:placetype":"locality"
},
  "geometry": {"coordinates":[73.98866,31.80056],"type":"Point"}
}