{
  "type": "Feature",
  "properties": {
    "gn:admin1_code":"4",
    "gn:asciiname":"Zisewala Chhamb",
    "gn:country_code":"PK",
    "gn:dem":186,
    "gn:feature_class":"P",
    "gn:feature_code":"PPL",
    "gn:name":"Zisewala Chhamb",
    "gn:population":0,
    "gn:timezone":"Asia/Karachi",
    "iso:country":"PK",
    "wof:name":"Zisewala Chhamb",
    "wof:placetype":"locality"
},
  "geometry": {"coordinates":[72.04722,31.98472000000001],"type":"Point"}
}