{
  "type": "Feature",
  "properties": {
    "gn:admin1_code":"3.0",
    "gn:asciiname":"Banda Chaprai",
    "gn:country_code":"PK",
    "gn:dem":1092,
    "gn:feature_class":"P",
    "gn:feature_code":"PPLL",
    "gn:name":"Banda Chaprai",
    "gn:population":0,
    "gn:timezone":"Asia/Karachi",
    "iso:country":"PK",
    "wof:name":"Banda Chaprai",
    "wof:placetype":"locality"
},
  "geometry": {"coordinates":[71.20058,33.01094000000001],"type":"Point"}
}