{
  "type": "Feature",
  "properties": {
    "gn:admin1_code":"4.0",
    "gn:asciiname":"Sambul",
    "gn:country_code":"PK",
    "gn:dem":732,
    "gn:feature_class":"P",
    "gn:feature_code":"PPL",
    "gn:name":"Sambul",
    "gn:population":0,
    "gn:timezone":"Asia/Karachi",
    "iso:country":"PK",
    "name:und_x_variant":[
        "Sambal"
    ],
    "wof:name":"Sambul",
    "wof:placetype":"locality"
},
  "geometry": {"coordinates":[73.47844000000001,33.56434],"type":"Point"}
}