{
  "type": "Feature",
  "properties": {
    "gn:admin1_code":"2.0",
    "gn:asciiname":"Kili Mulla Khel",
    "gn:country_code":"PK",
    "gn:dem":1588,
    "gn:feature_class":"P",
    "gn:feature_code":"PPL",
    "gn:name":"Kili Mulla Khel",
    "gn:population":0,
    "gn:timezone":"Asia/Karachi",
    "iso:country":"PK",
    "wof:name":"Kili Mulla Khel",
    "wof:placetype":"locality"
},
  "geometry": {"coordinates":[67.06657,30.43454],"type":"Point"}
}