{
  "type": "Feature",
  "properties": {
    "gn:admin1_code":"3.0",
    "gn:asciiname":"New Bagh",
    "gn:country_code":"PK",
    "gn:dem":535,
    "gn:feature_class":"P",
    "gn:feature_code":"PPL",
    "gn:name":"New Bagh",
    "gn:population":0,
    "gn:timezone":"Asia/Karachi",
    "iso:country":"PK",
    "name:eng_x_preferred":[
        "New Bagh"
    ],
    "wof:name":"New Bagh",
    "wof:placetype":"locality"
},
  "geometry": {"coordinates":[72.47658,34.28161],"type":"Point"}
}