{
  "type": "Feature",
  "properties": {
    "gn:admin1_code":"7.0",
    "gn:asciiname":"Nico Baihk",
    "gn:country_code":"PK",
    "gn:dem":3594,
    "gn:feature_class":"P",
    "gn:feature_code":"PPL",
    "gn:name":"Nico Baihk",
    "gn:population":0,
    "gn:timezone":"Asia/Karachi",
    "iso:country":"PK",
    "wof:name":"Nico Baihk",
    "wof:placetype":"locality"
},
  "geometry": {"coordinates":[73.14246999999997,35.99359000000001],"type":"Point"}
}