{
  "type": "Feature",
  "properties": {
    "gn:admin1_code":"4.0",
    "gn:asciiname":"Seri Singhwala",
    "gn:country_code":"PK",
    "gn:dem":204,
    "gn:feature_class":"P",
    "gn:feature_code":"PPL",
    "gn:name":"Seri Singhwala",
    "gn:population":0,
    "gn:timezone":"Asia/Karachi",
    "iso:country":"PK",
    "name:und_x_variant":[
        "Bhaow\u0101t",
        "Mishir Singhw\u0101la"
    ],
    "wof:name":"Seri Singhwala",
    "wof:placetype":"locality"
},
  "geometry": {"coordinates":[74.33729,31.16277],"type":"Point"}
}