{
  "type": "Feature",
  "properties": {
    "gn:admin1_code":"04",
    "gn:asciiname":"Thun",
    "gn:country_code":"PK",
    "gn:dem":918,
    "gn:feature_class":"P",
    "gn:feature_code":"PPL",
    "gn:name":"Thun",
    "gn:population":0,
    "gn:timezone":"Asia/Karachi",
    "iso:country":"PK",
    "name:und_x_variant":[
        "Thoon",
        "Th\u016bn",
        "Thun"
    ],
    "wof:name":"Thun",
    "wof:placetype":"locality"
},
  "geometry": {"coordinates":[73.55315,33.7711],"type":"Point"}
}