{
  "type": "Feature",
  "properties": {
    "gn:admin1_code":"3.0",
    "gn:asciiname":"Shaikhana Kalle",
    "gn:country_code":"PK",
    "gn:dem":389,
    "gn:feature_class":"P",
    "gn:feature_code":"PPL",
    "gn:name":"Shaikhana Kalle",
    "gn:population":0,
    "gn:timezone":"Asia/Karachi",
    "iso:country":"PK",
    "wof:name":"Shaikhana Kalle",
    "wof:placetype":"locality"
},
  "geometry": {"coordinates":[71.90379,34.3779],"type":"Point"}
}