{
  "type": "Feature",
  "properties": {
    "gn:admin1_code":"2.0",
    "gn:asciiname":"Kili Mir Alam Khan",
    "gn:country_code":"PK",
    "gn:dem":897,
    "gn:feature_class":"P",
    "gn:feature_code":"PPL",
    "gn:name":"Kili Mir Alam Khan",
    "gn:population":0,
    "gn:timezone":"Asia/Karachi",
    "iso:country":"PK",
    "wof:name":"Kili Mir Alam Khan",
    "wof:placetype":"locality"
},
  "geometry": {"coordinates":[65.54839,29.58495],"type":"Point"}
}