{
  "type": "Feature",
  "properties": {
    "gn:admin1_code":"3.0",
    "gn:asciiname":"Sur Talao",
    "gn:country_code":"PK",
    "gn:dem":477,
    "gn:feature_class":"P",
    "gn:feature_code":"PPL",
    "gn:name":"Sur Talao",
    "gn:population":0,
    "gn:timezone":"Asia/Karachi",
    "iso:country":"PK",
    "wof:name":"Sur Talao",
    "wof:placetype":"locality"
},
  "geometry": {"coordinates":[71.50714000000001,33.83257],"type":"Point"}
}