{
  "type": "Feature",
  "properties": {
    "gn:admin1_code":"4.0",
    "gn:asciiname":"Behramabad",
    "gn:country_code":"PK",
    "gn:dem":375,
    "gn:feature_class":"P",
    "gn:feature_code":"PPL",
    "gn:name":"Behramabad",
    "gn:population":0,
    "gn:timezone":"Asia/Karachi",
    "iso:country":"PK",
    "wof:name":"Behramabad",
    "wof:placetype":"locality"
},
  "geometry": {"coordinates":[71.82585,33.16979],"type":"Point"}
}