{
  "type": "Feature",
  "properties": {
    "gn:admin1_code":"4.0",
    "gn:asciiname":"Pirm Thia",
    "gn:country_code":"PK",
    "gn:dem":474,
    "gn:feature_class":"P",
    "gn:feature_code":"PPL",
    "gn:name":"Pirm Thia",
    "gn:population":0,
    "gn:timezone":"Asia/Karachi",
    "iso:country":"PK",
    "wof:name":"Pirm Thia",
    "wof:placetype":"locality"
},
  "geometry": {"coordinates":[73.34795,33.19089],"type":"Point"}
}