{
  "type": "Feature",
  "properties": {
    "gn:admin1_code":"1.0",
    "gn:asciiname":"Dab Banda",
    "gn:country_code":"PK",
    "gn:dem":383,
    "gn:feature_class":"P",
    "gn:feature_code":"PPL",
    "gn:name":"Dab Banda",
    "gn:population":0,
    "gn:timezone":"Asia/Karachi",
    "iso:country":"PK",
    "name:eng_x_preferred":[
        "Dab Kalle"
    ],
    "wof:name":"Dab Banda",
    "wof:placetype":"locality"
},
  "geometry": {"coordinates":[71.55766,34.33823],"type":"Point"}
}