{
  "type": "Feature",
  "properties": {
    "gn:admin1_code":"5.0",
    "gn:asciiname":"Goth Muhammad Rahim",
    "gn:country_code":"PK",
    "gn:dem":9,
    "gn:feature_class":"P",
    "gn:feature_code":"PPL",
    "gn:name":"Goth Muhammad Rahim",
    "gn:population":0,
    "gn:timezone":"Asia/Karachi",
    "iso:country":"PK",
    "name:und_x_variant":[
        "Goth Harchand",
        "Goth Muhammad Rahim"
    ],
    "wof:name":"Goth Muhammad Rahim",
    "wof:placetype":"locality"
},
  "geometry": {"coordinates":[67.91948000000001,24.50517],"type":"Point"}
}