{
  "type": "Feature",
  "properties": {
    "gn:admin1_code":"03",
    "gn:asciiname":"Shala Sharif",
    "gn:country_code":"PK",
    "gn:dem":178,
    "gn:feature_class":"P",
    "gn:feature_code":"PPL",
    "gn:name":"Shala Sharif",
    "gn:population":0,
    "gn:timezone":"Asia/Karachi",
    "iso:country":"PK",
    "name:und_x_variant":[
        "Sh\u0101lah",
        "Sh\u0101la",
        "Shala Sharif"
    ],
    "wof:name":"Shala Sharif",
    "wof:placetype":"locality"
},
  "geometry": {"coordinates":[70.80688000000001,31.68959000000001],"type":"Point"}
}