{
  "type": "Feature",
  "properties": {
    "gn:admin1_code":"2.0",
    "gn:asciiname":"Muhammad Hasan Pandrani",
    "gn:country_code":"PK",
    "gn:dem":42,
    "gn:feature_class":"P",
    "gn:feature_code":"PPL",
    "gn:name":"Muhammad Hasan Pandrani",
    "gn:population":0,
    "gn:timezone":"Asia/Karachi",
    "iso:country":"PK",
    "name:und_x_variant":[
        "Chak 62",
        "Chak Sixty-two"
    ],
    "wof:name":"Muhammad Hasan Pandrani",
    "wof:placetype":"locality"
},
  "geometry": {"coordinates":[67.72318,28.16405],"type":"Point"}
}