{
  "type": "Feature",
  "properties": {
    "gn:admin1_code":"3",
    "gn:asciiname":"Landai",
    "gn:country_code":"PK",
    "gn:dem":366,
    "gn:feature_class":"P",
    "gn:feature_code":"PPL",
    "gn:name":"Landai",
    "gn:population":0,
    "gn:timezone":"Asia/Karachi",
    "iso:country":"PK",
    "name:eng_x_preferred":[
        "Landai"
    ],
    "name:und_x_variant":[
        "L\u0101ndi"
    ],
    "wof:name":"Landai",
    "wof:placetype":"locality"
},
  "geometry": {"coordinates":[72.29158000000002,34.359],"type":"Point"}
}