{
  "type": "Feature",
  "properties": {
    "gn:admin1_code":"1.0",
    "gn:asciiname":"Mandakai",
    "gn:country_code":"PK",
    "gn:dem":2289,
    "gn:feature_class":"P",
    "gn:feature_code":"PPL",
    "gn:name":"Mandakai",
    "gn:population":0,
    "gn:timezone":"Asia/Karachi",
    "iso:country":"PK",
    "name:und_x_variant":[
        "Mandalai",
        "Mandakai"
    ],
    "wof:name":"Mandakai",
    "wof:placetype":"locality"
},
  "geometry": {"coordinates":[69.98990000000001,33.96943],"type":"Point"}
}