{
  "type": "Feature",
  "properties": {
    "gn:admin1_code":"5.0",
    "gn:asciiname":"Allah Dino Dars",
    "gn:country_code":"PK",
    "gn:dem":29,
    "gn:feature_class":"P",
    "gn:feature_code":"PPL",
    "gn:name":"Allah Dino Dars",
    "gn:population":0,
    "gn:timezone":"Asia/Karachi",
    "iso:country":"PK",
    "wof:name":"Allah Dino Dars",
    "wof:placetype":"locality"
},
  "geometry": {"coordinates":[69.56426999999999,25.91947],"type":"Point"}
}