{
  "type": "Feature",
  "properties": {
    "gn:admin1_code":"5",
    "gn:asciiname":"Abdullah Khan Domki",
    "gn:country_code":"PK",
    "gn:dem":74,
    "gn:feature_class":"P",
    "gn:feature_code":"PPL",
    "gn:name":"Abdullah Khan Domki",
    "gn:population":0,
    "gn:timezone":"Asia/Karachi",
    "iso:country":"PK",
    "name:und_x_variant":[
        "Qaisar Bat\u0101fi"
    ],
    "wof:name":"Abdullah Khan Domki",
    "wof:placetype":"locality"
},
  "geometry": {"coordinates":[69.40637,28.41617],"type":"Point"}
}