{
  "type": "Feature",
  "properties": {
    "gn:admin1_code":"4",
    "gn:asciiname":"Beli",
    "gn:country_code":"PK",
    "gn:dem":110,
    "gn:feature_class":"P",
    "gn:feature_code":"PPL",
    "gn:name":"Beli",
    "gn:population":0,
    "gn:timezone":"Asia/Karachi",
    "iso:country":"PK",
    "name:und_x_variant":[
        "Bel\u0101",
        "Behli",
        "Beli"
    ],
    "wof:name":"Beli",
    "wof:placetype":"locality"
},
  "geometry": {"coordinates":[71.14941999999998,29.59303],"type":"Point"}
}