{
  "type": "Feature",
  "properties": {
    "gn:admin1_code":"05",
    "gn:asciiname":"Goth Ismail Charan",
    "gn:country_code":"PK",
    "gn:dem":9,
    "gn:feature_class":"P",
    "gn:feature_code":"PPL",
    "gn:name":"Goth Ismail Charan",
    "gn:population":0,
    "gn:timezone":"Asia/Karachi",
    "iso:country":"PK",
    "name:und_x_variant":[
        "Goth Ism\u0101\u012bl Ch\u0101ran"
    ],
    "wof:name":"Goth Ismail Charan",
    "wof:placetype":"locality"
},
  "geometry": {"coordinates":[67.85694000000001,24.31649],"type":"Point"}
}