{
  "type": "Feature",
  "properties": {
    "gn:admin1_code":"6.0",
    "gn:asciiname":"Jaluth",
    "gn:country_code":"PK",
    "gn:dem":1542,
    "gn:feature_class":"P",
    "gn:feature_code":"PPL",
    "gn:name":"Jaluth",
    "gn:population":0,
    "gn:timezone":"Asia/Karachi",
    "iso:country":"PK",
    "wof:name":"Jaluth",
    "wof:placetype":"locality"
},
  "geometry": {"coordinates":[73.66593,33.92027],"type":"Point"}
}