{
  "type": "Feature",
  "properties": {
    "gn:admin1_code":"6.0",
    "gn:asciiname":"Khokhar",
    "gn:country_code":"PK",
    "gn:dem":272,
    "gn:feature_class":"P",
    "gn:feature_code":"PPL",
    "gn:name":"Khokhar",
    "gn:population":0,
    "gn:timezone":"Asia/Karachi",
    "iso:country":"PK",
    "name:cat_x_preferred":[
        "Khokhars"
    ],
    "name:hin_x_preferred":[
        "\u0916\u094b\u0916\u0930 \u0932\u094b\u0917"
    ],
    "name:snd_x_preferred":[
        "\u06a9\u0648\u06a9\u0631"
    ],
    "name:urd_x_preferred":[
        "\u06a9\u06be\u0648\u06a9\u06be\u0631"
    ],
    "wof:name":"Khokhar",
    "wof:placetype":"locality"
},
  "geometry": {"coordinates":[73.6195,33.03974],"type":"Point"}
}