{
  "type": "Feature",
  "properties": {
    "gn:admin1_code":"5",
    "gn:asciiname":"Bhag",
    "gn:country_code":"PK",
    "gn:dem":20,
    "gn:feature_class":"P",
    "gn:feature_code":"PPL",
    "gn:name":"Bhag",
    "gn:population":0,
    "gn:timezone":"Asia/Karachi",
    "iso:country":"PK",
    "name:eng_x_preferred":[
        "Bhag"
    ],
    "name:fas_x_preferred":[
        "\u0628\u0647\u0627\u06af"
    ],
    "name:por_x_preferred":[
        "Bhag"
    ],
    "name:spa_x_preferred":[
        "Bhag"
    ],
    "name:urd_x_preferred":[
        "\u0628\u06be\u06af"
    ],
    "name:urd_x_variant":[
        "\u0628\u06be\u0627\u06af"
    ],
    "wof:name":"Bhag",
    "wof:placetype":"locality"
},
  "geometry": {"coordinates":[69.04953999999999,26.07042],"type":"Point"}
}