{
  "type": "Feature",
  "properties": {
    "gn:admin1_code":"5",
    "gn:asciiname":"Bhag",
    "gn:country_code":"PK",
    "gn:dem":20,
    "gn:feature_class":"P",
    "gn:feature_code":"PPL",
    "gn:name":"Bhag",
    "gn:population":0,
    "gn:timezone":"Asia/Karachi",
    "iso:country":"PK",
    "wof:name":"Bhag",
    "wof:placetype":"locality"
},
  "geometry": {"coordinates":[69.04954000000001,26.07042],"type":"Point"}
}