{
  "type": "Feature",
  "properties": {
    "gn:admin1_code":"3.0",
    "gn:asciiname":"Wanda Nadir Shah",
    "gn:country_code":"PK",
    "gn:dem":183,
    "gn:feature_class":"P",
    "gn:feature_code":"PPL",
    "gn:name":"Wanda Nadir Shah",
    "gn:population":0,
    "gn:timezone":"Asia/Karachi",
    "iso:country":"PK",
    "name:und_x_variant":[
        "N\u0101dir Sh\u0101h",
        "Wanda Nadir Shah"
    ],
    "wof:name":"Wanda Nadir Shah",
    "wof:placetype":"locality"
},
  "geometry": {"coordinates":[70.92795,32.08547],"type":"Point"}
}