{
  "type": "Feature",
  "properties": {
    "gn:admin1_code":"4.0",
    "gn:asciiname":"Ferozeabad",
    "gn:country_code":"PK",
    "gn:dem":336,
    "gn:feature_class":"P",
    "gn:feature_code":"PPL",
    "gn:name":"Ferozeabad",
    "gn:population":0,
    "gn:timezone":"Asia/Karachi",
    "iso:country":"PK",
    "wof:name":"Ferozeabad",
    "wof:placetype":"locality"
},
  "geometry": {"coordinates":[72.56363,33.94006],"type":"Point"}
}