{
  "type": "Feature",
  "properties": {
    "gn:admin1_code":"4.0",
    "gn:asciiname":"Warianwala",
    "gn:country_code":"PK",
    "gn:dem":109,
    "gn:feature_class":"P",
    "gn:feature_code":"PPL",
    "gn:name":"Warianwala",
    "gn:population":0,
    "gn:timezone":"Asia/Karachi",
    "iso:country":"PK",
    "name:und_x_variant":[
        "W\u0101ri\u0101nw\u0101la"
    ],
    "wof:name":"Warianwala",
    "wof:placetype":"locality"
},
  "geometry": {"coordinates":[70.88305,29.63747],"type":"Point"}
}