{
  "type": "Feature",
  "properties": {
    "gn:admin1_code":"05",
    "gn:asciiname":"Sum",
    "gn:country_code":"PK",
    "gn:dem":53,
    "gn:feature_class":"P",
    "gn:feature_code":"PPL",
    "gn:name":"Sum",
    "gn:population":0,
    "gn:timezone":"Asia/Karachi",
    "iso:country":"PK",
    "name:und_x_variant":[
        "Sami",
        "Sum"
    ],
    "wof:name":"Sum",
    "wof:placetype":"locality"
},
  "geometry": {"coordinates":[68.35124999999999,27.24488],"type":"Point"}
}