{
  "type": "Feature",
  "properties": {
    "gn:admin1_code":"5.0",
    "gn:asciiname":"Gul Muhammad",
    "gn:country_code":"PK",
    "gn:dem":13,
    "gn:feature_class":"P",
    "gn:feature_code":"PPL",
    "gn:name":"Gul Muhammad",
    "gn:population":0,
    "gn:timezone":"Asia/Karachi",
    "iso:country":"PK",
    "name:eng_x_preferred":[
        "Gul Muhammad"
    ],
    "wof:name":"Gul Muhammad",
    "wof:placetype":"locality"
},
  "geometry": {"coordinates":[68.1601,24.60877],"type":"Point"}
}