{
  "type": "Feature",
  "properties": {
    "gn:admin1_code":"5",
    "gn:asciiname":"Goth Gulu Sial",
    "gn:country_code":"PK",
    "gn:dem":58,
    "gn:feature_class":"P",
    "gn:feature_code":"PPL",
    "gn:name":"Goth Gulu Sial",
    "gn:population":0,
    "gn:timezone":"Asia/Karachi",
    "iso:country":"PK",
    "name:und_x_variant":[
        "Gulu Si\u0101l"
    ],
    "wof:name":"Goth Gulu Sial",
    "wof:placetype":"locality"
},
  "geometry": {"coordinates":[68.45562,27.56676],"type":"Point"}
}