{
  "type": "Feature",
  "properties": {
    "gn:admin1_code":"3.0",
    "gn:asciiname":"Bokan",
    "gn:country_code":"PK",
    "gn:dem":719,
    "gn:feature_class":"P",
    "gn:feature_code":"PPL",
    "gn:name":"Bokan",
    "gn:population":0,
    "gn:timezone":"Asia/Karachi",
    "iso:country":"PK",
    "name:eng_x_preferred":[
        "Bokan"
    ],
    "wof:name":"Bokan",
    "wof:placetype":"locality"
},
  "geometry": {"coordinates":[73.05301999999998,33.85748],"type":"Point"}
}