{
  "type": "Feature",
  "properties": {
    "gn:admin1_code":"5.0",
    "gn:asciiname":"Songhwari",
    "gn:country_code":"PK",
    "gn:dem":11,
    "gn:feature_class":"P",
    "gn:feature_code":"PPL",
    "gn:name":"Songhwari",
    "gn:population":0,
    "gn:timezone":"Asia/Karachi",
    "iso:country":"PK",
    "name:und_x_variant":[
        "Sarungwari"
    ],
    "wof:name":"Songhwari",
    "wof:placetype":"locality"
},
  "geometry": {"coordinates":[70.38513,24.42444],"type":"Point"}
}