{
  "type": "Feature",
  "properties": {
    "gn:admin1_code":"5.0",
    "gn:asciiname":"Kamdar Dhani Bakhsh",
    "gn:country_code":"PK",
    "gn:dem":41,
    "gn:feature_class":"P",
    "gn:feature_code":"PPL",
    "gn:name":"Kamdar Dhani Bakhsh",
    "gn:population":0,
    "gn:timezone":"Asia/Karachi",
    "iso:country":"PK",
    "name:und_x_variant":[
        "K\u0101md\u0101r Dani Bakhsh"
    ],
    "wof:name":"Kamdar Dhani Bakhsh",
    "wof:placetype":"locality"
},
  "geometry": {"coordinates":[68.09390999999999,26.6329],"type":"Point"}
}