{
  "type": "Feature",
  "properties": {
    "gn:admin1_code":"4",
    "gn:asciiname":"Maruli",
    "gn:country_code":"PK",
    "gn:dem":186,
    "gn:feature_class":"P",
    "gn:feature_code":"PPL",
    "gn:name":"Maruli",
    "gn:population":0,
    "gn:timezone":"Asia/Karachi",
    "iso:country":"PK",
    "name:ell_x_preferred":[
        "\u039c\u03b1\u03c1\u03bf\u03cd\u03bb\u03b7\u03c2"
    ],
    "name:eus_x_preferred":[
        "Maruli"
    ],
    "name:kat_x_preferred":[
        "\u10db\u10d0\u10e0\u10e3\u10da\u10d8"
    ],
    "name:mkd_x_preferred":[
        "\u041c\u0430\u0440\u0443\u043b\u0438"
    ],
    "name:ron_x_preferred":[
        "Maruli"
    ],
    "wof:name":"Maruli",
    "wof:placetype":"locality"
},
  "geometry": {"coordinates":[73.58948000000002,31.1056],"type":"Point"}
}