{
  "type": "Feature",
  "properties": {
    "gn:admin1_code":"4",
    "gn:asciiname":"Chak Forty-three Desert Branch",
    "gn:country_code":"PK",
    "gn:dem":117,
    "gn:feature_class":"P",
    "gn:feature_code":"PPL",
    "gn:name":"Chak Forty-three Desert Branch",
    "gn:population":0,
    "gn:timezone":"Asia/Karachi",
    "iso:country":"PK",
    "name:eng_x_preferred":[
        "Chak Forty-three DB"
    ],
    "wof:name":"Chak Forty-three Desert Branch",
    "wof:placetype":"locality"
},
  "geometry": {"coordinates":[71.70725,29.20537],"type":"Point"}
}