{
  "type": "Feature",
  "properties": {
    "gn:admin1_code":"5.0",
    "gn:asciiname":"New Konkar",
    "gn:country_code":"PK",
    "gn:dem":148,
    "gn:feature_class":"P",
    "gn:feature_code":"PPL",
    "gn:name":"New Konkar",
    "gn:population":0,
    "gn:timezone":"Asia/Karachi",
    "iso:country":"PK",
    "wof:name":"New Konkar",
    "wof:placetype":"locality"
},
  "geometry": {"coordinates":[67.20317,25.1409],"type":"Point"}
}