{
  "type": "Feature",
  "properties": {
    "gn:admin1_code":"6",
    "gn:asciiname":"Chechian",
    "gn:country_code":"PK",
    "gn:dem":250,
    "gn:feature_class":"P",
    "gn:feature_code":"PPL",
    "gn:name":"Chechian",
    "gn:population":0,
    "gn:timezone":"Asia/Karachi",
    "iso:country":"PK",
    "name:fas_x_preferred":[
        "\u0686\u06cc\u0686\u06cc\u0627\u0646"
    ],
    "name:urd_x_preferred":[
        "\u0686\u06cc\u0686\u06cc\u0627\u06ba"
    ],
    "wof:name":"Chechian",
    "wof:placetype":"locality"
},
  "geometry": {"coordinates":[73.75289000000002,33.08357],"type":"Point"}
}