{
  "type": "Feature",
  "properties": {
    "gn:admin1_code":"4",
    "gn:asciiname":"Trehda",
    "gn:country_code":"PK",
    "gn:dem":329,
    "gn:feature_class":"P",
    "gn:feature_code":"PPL",
    "gn:name":"Trehda",
    "gn:population":0,
    "gn:timezone":"Asia/Karachi",
    "iso:country":"PK",
    "name:und_x_variant":[
        "Dhok B\u0101gh"
    ],
    "wof:name":"Trehda",
    "wof:placetype":"locality"
},
  "geometry": {"coordinates":[73.47468000000001,33.08572],"type":"Point"}
}