{
  "type": "Feature",
  "properties": {
    "gn:admin1_code":"3.0",
    "gn:asciiname":"Alim Khan",
    "gn:country_code":"PK",
    "gn:dem":323,
    "gn:feature_class":"P",
    "gn:feature_code":"PPL",
    "gn:name":"Alim Khan",
    "gn:population":0,
    "gn:timezone":"Asia/Karachi",
    "iso:country":"PK",
    "name:und_x_variant":[
        "\u0100lam Kh\u0101n",
        "Aiam Khan",
        "Alim Khan"
    ],
    "wof:name":"Alim Khan",
    "wof:placetype":"locality"
},
  "geometry": {"coordinates":[70.63906,32.87195],"type":"Point"}
}