{
  "type": "Feature",
  "properties": {
    "gn:admin1_code":"2.0",
    "gn:asciiname":"Tadozail",
    "gn:country_code":"PK",
    "gn:dem":1523,
    "gn:feature_class":"P",
    "gn:feature_code":"PPL",
    "gn:name":"Tadozail",
    "gn:population":0,
    "gn:timezone":"Asia/Karachi",
    "iso:country":"PK",
    "name:und_x_variant":[
        "Dod\u0101zai Kili"
    ],
    "wof:name":"Tadozail",
    "wof:placetype":"locality"
},
  "geometry": {"coordinates":[69.28681999999999,31.01704],"type":"Point"}
}