{
  "type": "Feature",
  "properties": {
    "gn:admin1_code":"1.0",
    "gn:asciiname":"Dargai Ghakhai",
    "gn:country_code":"PK",
    "gn:dem":1472,
    "gn:feature_class":"P",
    "gn:feature_code":"PPL",
    "gn:name":"Dargai Ghakhai",
    "gn:population":0,
    "gn:timezone":"Asia/Karachi",
    "iso:country":"PK",
    "name:und_x_variant":[
        "Durgai Gh\u0101khai"
    ],
    "wof:name":"Dargai Ghakhai",
    "wof:placetype":"locality"
},
  "geometry": {"coordinates":[71.04219999999999,33.69435],"type":"Point"}
}