{
  "type": "Feature",
  "properties": {
    "gn:admin1_code":"2.0",
    "gn:asciiname":"Gazzi Zai",
    "gn:country_code":"PK",
    "gn:dem":1163,
    "gn:feature_class":"P",
    "gn:feature_code":"PPL",
    "gn:name":"Gazzi Zai",
    "gn:population":0,
    "gn:timezone":"Asia/Karachi",
    "iso:country":"PK",
    "wof:name":"Gazzi Zai",
    "wof:placetype":"locality"
},
  "geometry": {"coordinates":[66.21611999999999,27.66024],"type":"Point"}
}