{
  "type": "Feature",
  "properties": {
    "gn:admin1_code":"4",
    "gn:asciiname":"Shahianwala",
    "gn:country_code":"PK",
    "gn:dem":194,
    "gn:feature_class":"P",
    "gn:feature_code":"PPL",
    "gn:name":"Shahianwala",
    "gn:population":0,
    "gn:timezone":"Asia/Karachi",
    "iso:country":"PK",
    "name:und_x_variant":[
        "Sh\u0101hy\u0101nw\u0101li"
    ],
    "wof:name":"Shahianwala",
    "wof:placetype":"locality"
},
  "geometry": {"coordinates":[71.72176999999998,32.15694000000001],"type":"Point"}
}