{
  "type": "Feature",
  "properties": {
    "gn:admin1_code":"06",
    "gn:asciiname":"Taobat",
    "gn:country_code":"PK",
    "gn:dem":2492,
    "gn:feature_class":"P",
    "gn:feature_code":"PPL",
    "gn:name":"Taobat",
    "gn:population":0,
    "gn:timezone":"Asia/Karachi",
    "iso:country":"PK",
    "wof:name":"Taobat",
    "wof:placetype":"locality"
},
  "geometry": {"coordinates":[74.69705999999999,34.74097],"type":"Point"}
}