{
  "type": "Feature",
  "properties": {
    "gn:admin1_code":"06",
    "gn:asciiname":"Salgran",
    "gn:country_code":"PK",
    "gn:dem":536,
    "gn:feature_class":"P",
    "gn:feature_code":"PPL",
    "gn:name":"Salgran",
    "gn:population":0,
    "gn:timezone":"Asia/Karachi",
    "iso:country":"PK",
    "wof:name":"Salgran",
    "wof:placetype":"locality"
},
  "geometry": {"coordinates":[73.58555,33.49799],"type":"Point"}
}