{
  "type": "Feature",
  "properties": {
    "gn:admin1_code":"7.0",
    "gn:asciiname":"Narh Bachung",
    "gn:country_code":"PK",
    "gn:dem":2291,
    "gn:feature_class":"P",
    "gn:feature_code":"PPL",
    "gn:name":"Narh Bachung",
    "gn:population":0,
    "gn:timezone":"Asia/Karachi",
    "iso:country":"PK",
    "name:und_x_variant":[
        "Nurhbuchung"
    ],
    "wof:name":"Narh Bachung",
    "wof:placetype":"locality"
},
  "geometry": {"coordinates":[75.80146999999999,35.35227000000001],"type":"Point"}
}