{
  "type": "Feature",
  "properties": {
    "gn:admin1_code":"2.0",
    "gn:asciiname":"Obashtkai",
    "gn:country_code":"PK",
    "gn:dem":2216,
    "gn:feature_class":"P",
    "gn:feature_code":"PPL",
    "gn:name":"Obashtkai",
    "gn:population":0,
    "gn:timezone":"Asia/Karachi",
    "iso:country":"PK",
    "wof:name":"Obashtkai",
    "wof:placetype":"locality"
},
  "geometry": {"coordinates":[67.54687,30.70151],"type":"Point"}
}