{
  "type": "Feature",
  "properties": {
    "gn:admin1_code":"4.0",
    "gn:asciiname":"Dhok Mian Mehr",
    "gn:country_code":"PK",
    "gn:dem":476,
    "gn:feature_class":"P",
    "gn:feature_code":"PPL",
    "gn:name":"Dhok Mian Mehr",
    "gn:population":0,
    "gn:timezone":"Asia/Karachi",
    "iso:country":"PK",
    "name:und_x_variant":[
        "Mian Mair",
        "Dhok Mi\u0101nmher",
        "Dhok Mian Mehr"
    ],
    "wof:name":"Dhok Mian Mehr",
    "wof:placetype":"locality"
},
  "geometry": {"coordinates":[73.02535999999998,32.92959],"type":"Point"}
}