{
  "type": "Feature",
  "properties": {
    "gn:admin1_code":"4.0",
    "gn:asciiname":"Dhok Kasbian",
    "gn:country_code":"PK",
    "gn:dem":511,
    "gn:feature_class":"P",
    "gn:feature_code":"PPL",
    "gn:name":"Dhok Kasbian",
    "gn:population":0,
    "gn:timezone":"Asia/Karachi",
    "iso:country":"PK",
    "wof:name":"Dhok Kasbian",
    "wof:placetype":"locality"
},
  "geometry": {"coordinates":[73.15260000000001,33.35689],"type":"Point"}
}