{
  "type": "Feature",
  "properties": {
    "gn:admin1_code":"5.0",
    "gn:asciiname":"Adam Khan Jo Goth",
    "gn:country_code":"PK",
    "gn:dem":55,
    "gn:feature_class":"P",
    "gn:feature_code":"PPL",
    "gn:name":"Adam Khan Jo Goth",
    "gn:population":0,
    "gn:timezone":"Asia/Karachi",
    "iso:country":"PK",
    "name:eng_x_preferred":[
        "\u0100dam Kh\u0101n-Jo-Goth"
    ],
    "wof:name":"Adam Khan Jo Goth",
    "wof:placetype":"locality"
},
  "geometry": {"coordinates":[68.66029,27.45885],"type":"Point"}
}