{
  "type": "Feature",
  "properties": {
    "gn:admin1_code":"4.0",
    "gn:asciiname":"Basti Allah Ditta Bela",
    "gn:country_code":"PK",
    "gn:dem":98,
    "gn:feature_class":"P",
    "gn:feature_code":"PPL",
    "gn:name":"Basti Allah Ditta Bela",
    "gn:population":0,
    "gn:timezone":"Asia/Karachi",
    "iso:country":"PK",
    "name:urd_x_preferred":[
        "All\u0101h Ditta Bhela"
    ],
    "wof:name":"Basti Allah Ditta Bela",
    "wof:placetype":"locality"
},
  "geometry": {"coordinates":[70.70845,28.98031],"type":"Point"}
}