{
  "type": "Feature",
  "properties": {
    "gn:admin1_code":"4",
    "gn:asciiname":"Bakainwala",
    "gn:country_code":"PK",
    "gn:dem":148,
    "gn:feature_class":"P",
    "gn:feature_code":"PPL",
    "gn:name":"Bakainwala",
    "gn:population":0,
    "gn:timezone":"Asia/Karachi",
    "iso:country":"PK",
    "name:und_x_variant":[
        "Bakainw\u0101la"
    ],
    "wof:name":"Bakainwala",
    "wof:placetype":"locality"
},
  "geometry": {"coordinates":[72.08711,31.16235],"type":"Point"}
}