{
  "type": "Feature",
  "properties": {
    "gn:admin1_code":"2.0",
    "gn:asciiname":"Shinzi",
    "gn:country_code":"PK",
    "gn:dem":910,
    "gn:feature_class":"P",
    "gn:feature_code":"PPL",
    "gn:name":"Shinzi",
    "gn:population":0,
    "gn:timezone":"Asia/Karachi",
    "iso:country":"PK",
    "wof:name":"Shinzi",
    "wof:placetype":"locality"
},
  "geometry": {"coordinates":[65.82576999999999,29.53716],"type":"Point"}
}