{
  "type": "Feature",
  "properties": {
    "gn:admin1_code":"5",
    "gn:asciiname":"Qabul Dasti",
    "gn:country_code":"PK",
    "gn:dem":53,
    "gn:feature_class":"P",
    "gn:feature_code":"PPL",
    "gn:name":"Qabul Dasti",
    "gn:population":0,
    "gn:timezone":"Asia/Karachi",
    "iso:country":"PK",
    "name:und_x_variant":[
        "Dasti Qab\u016bl"
    ],
    "wof:name":"Qabul Dasti",
    "wof:placetype":"locality"
},
  "geometry": {"coordinates":[68.64100999999999,27.06642],"type":"Point"}
}