{
  "type": "Feature",
  "properties": {
    "gn:admin1_code":"4.0",
    "gn:asciiname":"Dera Daduwala",
    "gn:country_code":"PK",
    "gn:dem":196,
    "gn:feature_class":"P",
    "gn:feature_code":"PPL",
    "gn:name":"Dera Daduwala",
    "gn:population":0,
    "gn:timezone":"Asia/Karachi",
    "iso:country":"PK",
    "name:und_x_variant":[
        "D\u0101duw\u0101la"
    ],
    "wof:name":"Dera Daduwala",
    "wof:placetype":"locality"
},
  "geometry": {"coordinates":[73.15597,32.12695],"type":"Point"}
}