{
  "type": "Feature",
  "properties": {
    "gn:admin1_code":"03",
    "gn:asciiname":"Danda",
    "gn:country_code":"PK",
    "gn:dem":1146,
    "gn:feature_class":"P",
    "gn:feature_code":"PPL",
    "gn:name":"Danda",
    "gn:population":0,
    "gn:timezone":"Asia/Karachi",
    "iso:country":"PK",
    "name:eng_x_preferred":[
        "Danda"
    ],
    "wof:name":"Danda",
    "wof:placetype":"locality"
},
  "geometry": {"coordinates":[71.94015999999998,34.65824],"type":"Point"}
}