{
  "type": "Feature",
  "properties": {
    "gn:admin1_code":"4",
    "gn:asciiname":"Chak Forty-eight Khidar Branch",
    "gn:country_code":"PK",
    "gn:dem":144,
    "gn:feature_class":"P",
    "gn:feature_code":"PPL",
    "gn:name":"Chak Forty-eight Khidar Branch",
    "gn:population":0,
    "gn:timezone":"Asia/Karachi",
    "iso:country":"PK",
    "name:und_x_variant":[
        "Chak Forty-eight KB"
    ],
    "wof:name":"Chak Forty-eight Khidar Branch",
    "wof:placetype":"locality"
},
  "geometry": {"coordinates":[72.65385999999999,30.03853],"type":"Point"}
}