{
  "type": "Feature",
  "properties": {
    "gn:admin1_code":"5.0",
    "gn:asciiname":"Goth Shahwasaio",
    "gn:country_code":"PK",
    "gn:dem":46,
    "gn:feature_class":"P",
    "gn:feature_code":"PPL",
    "gn:name":"Goth Shahwasaio",
    "gn:population":0,
    "gn:timezone":"Asia/Karachi",
    "iso:country":"PK",
    "wof:name":"Goth Shahwasaio",
    "wof:placetype":"locality"
},
  "geometry": {"coordinates":[67.82696,27.85738],"type":"Point"}
}