{
  "type": "Feature",
  "properties": {
    "gn:admin1_code":"2.0",
    "gn:asciiname":"Darya Zai",
    "gn:country_code":"PK",
    "gn:dem":1209,
    "gn:feature_class":"P",
    "gn:feature_code":"PPL",
    "gn:name":"Darya Zai",
    "gn:population":0,
    "gn:timezone":"Asia/Karachi",
    "iso:country":"PK",
    "wof:name":"Darya Zai",
    "wof:placetype":"locality"
},
  "geometry": {"coordinates":[69.36417,30.3242],"type":"Point"}
}