{
  "type": "Feature",
  "properties": {
    "gn:admin1_code":"5.0",
    "gn:asciiname":"Goth Waheji",
    "gn:country_code":"PK",
    "gn:dem":47,
    "gn:feature_class":"P",
    "gn:feature_code":"PPL",
    "gn:name":"Goth Waheji",
    "gn:population":0,
    "gn:timezone":"Asia/Karachi",
    "iso:country":"PK",
    "name:und_x_variant":[
        "Waheji",
        "Veji",
        "Goth Waheji"
    ],
    "wof:name":"Goth Waheji",
    "wof:placetype":"locality"
},
  "geometry": {"coordinates":[67.77642,27.03736],"type":"Point"}
}