{
  "type": "Feature",
  "properties": {
    "gn:admin1_code":"4.0",
    "gn:asciiname":"Chak Naurang",
    "gn:country_code":"PK",
    "gn:dem":563,
    "gn:feature_class":"P",
    "gn:feature_code":"PPL",
    "gn:name":"Chak Naurang",
    "gn:population":0,
    "gn:timezone":"Asia/Karachi",
    "iso:country":"PK",
    "name:eng_x_preferred":[
        "Chak Naurang"
    ],
    "wof:name":"Chak Naurang",
    "wof:placetype":"locality"
},
  "geometry": {"coordinates":[72.93855000000001,33.0022],"type":"Point"}
}