{
  "type": "Feature",
  "properties": {
    "gn:admin1_code":"3",
    "gn:asciiname":"Shah Banda",
    "gn:country_code":"PK",
    "gn:dem":723,
    "gn:feature_class":"P",
    "gn:feature_code":"PPL",
    "gn:name":"Shah Banda",
    "gn:population":0,
    "gn:timezone":"Asia/Karachi",
    "iso:country":"PK",
    "name:eng_x_preferred":[
        "Sh\u0101hi B\u0101nda"
    ],
    "wof:name":"Shah Banda",
    "wof:placetype":"locality"
},
  "geometry": {"coordinates":[72.20324000000002,34.54395],"type":"Point"}
}