{
  "type": "Feature",
  "properties": {
    "gn:admin1_code":"4.0",
    "gn:asciiname":"Jadamwala",
    "gn:country_code":"PK",
    "gn:dem":107,
    "gn:feature_class":"P",
    "gn:feature_code":"PPL",
    "gn:name":"Jadamwala",
    "gn:population":0,
    "gn:timezone":"Asia/Karachi",
    "iso:country":"PK",
    "name:und_x_variant":[
        "Basti Awan"
    ],
    "wof:name":"Jadamwala",
    "wof:placetype":"locality"
},
  "geometry": {"coordinates":[70.57857,29.6171],"type":"Point"}
}