{
  "type": "Feature",
  "properties": {
    "gn:admin1_code":"04",
    "gn:asciiname":"Pind Fateh",
    "gn:country_code":"PK",
    "gn:dem":537,
    "gn:feature_class":"P",
    "gn:feature_code":"PPL",
    "gn:name":"Pind Fateh",
    "gn:population":0,
    "gn:timezone":"Asia/Karachi",
    "iso:country":"PK",
    "name:und_x_variant":[
        "Pind Fatta",
        "Pind Fateh"
    ],
    "wof:name":"Pind Fateh",
    "wof:placetype":"locality"
},
  "geometry": {"coordinates":[72.67713000000001,33.45194],"type":"Point"}
}