{
  "type": "Feature",
  "properties": {
    "gn:admin1_code":"01",
    "gn:asciiname":"Talai",
    "gn:country_code":"PK",
    "gn:dem":2053,
    "gn:feature_class":"P",
    "gn:feature_code":"PPL",
    "gn:name":"Talai",
    "gn:population":0,
    "gn:timezone":"Asia/Karachi",
    "iso:country":"PK",
    "wof:name":"Talai",
    "wof:placetype":"locality"
},
  "geometry": {"coordinates":[70.55475,33.71078],"type":"Point"}
}