{
  "type": "Feature",
  "properties": {
    "gn:admin1_code":"1",
    "gn:asciiname":"Bobakra",
    "gn:country_code":"PK",
    "gn:dem":2149,
    "gn:feature_class":"P",
    "gn:feature_code":"PPL",
    "gn:name":"Bobakra",
    "gn:population":0,
    "gn:timezone":"Asia/Karachi",
    "iso:country":"PK",
    "wof:name":"Bobakra",
    "wof:placetype":"locality"
},
  "geometry": {"coordinates":[69.86545,32.73262],"type":"Point"}
}