{
  "type": "Feature",
  "properties": {
    "gn:admin1_code":"5.0",
    "gn:asciiname":"Jummu Magsi",
    "gn:country_code":"PK",
    "gn:dem":32,
    "gn:feature_class":"P",
    "gn:feature_code":"PPL",
    "gn:name":"Jummu Magsi",
    "gn:population":0,
    "gn:timezone":"Asia/Karachi",
    "iso:country":"PK",
    "name:und_x_variant":[
        "Jummo Magsi"
    ],
    "wof:name":"Jummu Magsi",
    "wof:placetype":"locality"
},
  "geometry": {"coordinates":[68.46495999999999,26.09148],"type":"Point"}
}