{
  "type": "Feature",
  "properties": {
    "gn:admin1_code":"4.0",
    "gn:asciiname":"Nutkani Number Two",
    "gn:country_code":"PK",
    "gn:dem":151,
    "gn:feature_class":"P",
    "gn:feature_code":"PPL",
    "gn:name":"Nutkani Number Two",
    "gn:population":0,
    "gn:timezone":"Asia/Karachi",
    "iso:country":"PK",
    "name:und_x_variant":[
        "Nutk\u0101ni No 2",
        "Nutkani Number Two"
    ],
    "wof:name":"Nutkani Number Two",
    "wof:placetype":"locality"
},
  "geometry": {"coordinates":[70.721,31.13355],"type":"Point"}
}