{
  "type": "Feature",
  "properties": {
    "gn:admin1_code":"3.0",
    "gn:asciiname":"Daud Shah",
    "gn:country_code":"PK",
    "gn:dem":412,
    "gn:feature_class":"P",
    "gn:feature_code":"PPL",
    "gn:name":"Daud Shah",
    "gn:population":0,
    "gn:timezone":"Asia/Karachi",
    "iso:country":"PK",
    "wof:name":"Daud Shah",
    "wof:placetype":"locality"
},
  "geometry": {"coordinates":[70.55385,33.00774000000001],"type":"Point"}
}