{
  "type": "Feature",
  "properties": {
    "gn:admin1_code":"4",
    "gn:asciiname":"Wahindwala",
    "gn:country_code":"PK",
    "gn:dem":120,
    "gn:feature_class":"P",
    "gn:feature_code":"PPL",
    "gn:name":"Wahindwala",
    "gn:population":0,
    "gn:timezone":"Asia/Karachi",
    "iso:country":"PK",
    "name:eng_x_preferred":[
        "W\u0101hindw\u0101li"
    ],
    "wof:name":"Wahindwala",
    "wof:placetype":"locality"
},
  "geometry": {"coordinates":[71.83053000000002,29.41482],"type":"Point"}
}