{
  "type": "Feature",
  "properties": {
    "gn:admin1_code":"5.0",
    "gn:asciiname":"Goth Dhani Bakhsh Sumro",
    "gn:country_code":"PK",
    "gn:dem":8,
    "gn:feature_class":"P",
    "gn:feature_code":"PPL",
    "gn:name":"Goth Dhani Bakhsh Sumro",
    "gn:population":0,
    "gn:timezone":"Asia/Karachi",
    "iso:country":"PK",
    "wof:name":"Goth Dhani Bakhsh Sumro",
    "wof:placetype":"locality"
},
  "geometry": {"coordinates":[67.96766,24.39833],"type":"Point"}
}