{
  "type": "Feature",
  "properties": {
    "gn:admin1_code":"5.0",
    "gn:asciiname":"Maruwala",
    "gn:country_code":"PK",
    "gn:dem":76,
    "gn:feature_class":"P",
    "gn:feature_code":"PPL",
    "gn:name":"Maruwala",
    "gn:population":0,
    "gn:timezone":"Asia/Karachi",
    "iso:country":"PK",
    "wof:name":"Maruwala",
    "wof:placetype":"locality"
},
  "geometry": {"coordinates":[69.84407,28.10448],"type":"Point"}
}