{
  "type": "Feature",
  "properties": {
    "gn:admin1_code":"3.0",
    "gn:asciiname":"Mainagah",
    "gn:country_code":"PK",
    "gn:dem":761,
    "gn:feature_class":"P",
    "gn:feature_code":"PPL",
    "gn:name":"Mainagah",
    "gn:population":0,
    "gn:timezone":"Asia/Karachi",
    "iso:country":"PK",
    "name:und_x_variant":[
        "Ghund Patti B\u0101nda",
        "Mainagah"
    ],
    "wof:name":"Mainagah",
    "wof:placetype":"locality"
},
  "geometry": {"coordinates":[71.77637,34.59535],"type":"Point"}
}