{
  "type": "Feature",
  "properties": {
    "gn:admin1_code":"4.0",
    "gn:asciiname":"Chak One -One Right A",
    "gn:country_code":"PK",
    "gn:dem":187,
    "gn:feature_class":"P",
    "gn:feature_code":"PPL",
    "gn:name":"Chak One -One Right A",
    "gn:population":0,
    "gn:timezone":"Asia/Karachi",
    "iso:country":"PK",
    "wof:name":"Chak One -One Right A",
    "wof:placetype":"locality"
},
  "geometry": {"coordinates":[73.63186999999998,30.93033],"type":"Point"}
}