{
  "type": "Feature",
  "properties": {
    "gn:admin1_code":"3.0",
    "gn:asciiname":"Ishkarwarz",
    "gn:country_code":"PK",
    "gn:dem":3521,
    "gn:feature_class":"P",
    "gn:feature_code":"PPL",
    "gn:name":"Ishkarwarz",
    "gn:population":0,
    "gn:timezone":"Asia/Karachi",
    "iso:country":"PK",
    "wof:name":"Ishkarwarz",
    "wof:placetype":"locality"
},
  "geometry": {"coordinates":[73.34748,36.83435],"type":"Point"}
}