{
  "type": "Feature",
  "properties": {
    "gn:admin1_code":"4",
    "gn:asciiname":"Thadag",
    "gn:country_code":"PK",
    "gn:dem":476,
    "gn:feature_class":"P",
    "gn:feature_code":"PPL",
    "gn:name":"Thadag",
    "gn:population":0,
    "gn:timezone":"Asia/Karachi",
    "iso:country":"PK",
    "wof:name":"Thadag",
    "wof:placetype":"locality"
},
  "geometry": {"coordinates":[70.36014,30.99379],"type":"Point"}
}