{
  "type": "Feature",
  "properties": {
    "gn:admin1_code":"4.0",
    "gn:asciiname":"Bhelok",
    "gn:country_code":"PK",
    "gn:dem":249,
    "gn:feature_class":"P",
    "gn:feature_code":"PPL",
    "gn:name":"Bhelok",
    "gn:population":0,
    "gn:timezone":"Asia/Karachi",
    "iso:country":"PK",
    "name:und_x_variant":[
        "Peloke",
        "Bheloke",
        "Bhelok"
    ],
    "wof:name":"Bhelok",
    "wof:placetype":"locality"
},
  "geometry": {"coordinates":[74.65600000000001,32.37184],"type":"Point"}
}