{
  "type": "Feature",
  "properties": {
    "gn:admin1_code":"2.0",
    "gn:asciiname":"Sarel Sulaimani",
    "gn:country_code":"PK",
    "gn:dem":1295,
    "gn:feature_class":"P",
    "gn:feature_code":"PPL",
    "gn:name":"Sarel Sulaimani",
    "gn:population":0,
    "gn:timezone":"Asia/Karachi",
    "iso:country":"PK",
    "wof:name":"Sarel Sulaimani",
    "wof:placetype":"locality"
},
  "geometry": {"coordinates":[69.76656,30.01994],"type":"Point"}
}