{
  "type": "Feature",
  "properties": {
    "gn:admin1_code":"3.0",
    "gn:asciiname":"Darra",
    "gn:country_code":"PK",
    "gn:dem":707,
    "gn:feature_class":"P",
    "gn:feature_code":"PPL",
    "gn:name":"Darra",
    "gn:population":0,
    "gn:timezone":"Asia/Karachi",
    "iso:country":"PK",
    "name:ceb_x_preferred":[
        "Darra"
    ],
    "name:eng_x_preferred":[
        "Dara"
    ],
    "name:swe_x_preferred":[
        "Darra"
    ],
    "wof:name":"Darra",
    "wof:placetype":"locality"
},
  "geometry": {"coordinates":[73.00698,33.85352],"type":"Point"}
}