{
  "type": "Feature",
  "properties": {
    "gn:admin1_code":"4.0",
    "gn:asciiname":"Ziarat Mohra Sharif",
    "gn:country_code":"PK",
    "gn:dem":1496,
    "gn:feature_class":"P",
    "gn:feature_code":"PPL",
    "gn:name":"Ziarat Mohra Sharif",
    "gn:population":0,
    "gn:timezone":"Asia/Karachi",
    "iso:country":"PK",
    "name:eng_x_preferred":[
        "Mora Sharif"
    ],
    "wof:name":"Ziarat Mohra Sharif",
    "wof:placetype":"locality"
},
  "geometry": {"coordinates":[73.42712,33.94503],"type":"Point"}
}