{
  "type": "Feature",
  "properties": {
    "gn:admin1_code":"5",
    "gn:asciiname":"Pir Ismail Jan",
    "gn:country_code":"PK",
    "gn:dem":29,
    "gn:feature_class":"P",
    "gn:feature_code":"PPL",
    "gn:name":"Pir Ismail Jan",
    "gn:population":0,
    "gn:timezone":"Asia/Karachi",
    "iso:country":"PK",
    "wof:name":"Pir Ismail Jan",
    "wof:placetype":"locality"
},
  "geometry": {"coordinates":[68.57071999999999,25.63363],"type":"Point"}
}