{
  "type": "Feature",
  "properties": {
    "gn:admin1_code":"5.0",
    "gn:asciiname":"Goth Ibrahim Khaskehli",
    "gn:country_code":"PK",
    "gn:dem":16,
    "gn:feature_class":"P",
    "gn:feature_code":"PPL",
    "gn:name":"Goth Ibrahim Khaskehli",
    "gn:population":0,
    "gn:timezone":"Asia/Karachi",
    "iso:country":"PK",
    "wof:name":"Goth Ibrahim Khaskehli",
    "wof:placetype":"locality"
},
  "geometry": {"coordinates":[68.90891999999999,25.18871],"type":"Point"}
}