{
  "type": "Feature",
  "properties": {
    "gn:admin1_code":"2",
    "gn:asciiname":"Madat Khan",
    "gn:country_code":"PK",
    "gn:dem":963,
    "gn:feature_class":"P",
    "gn:feature_code":"PPL",
    "gn:name":"Madat Khan",
    "gn:population":0,
    "gn:timezone":"Asia/Karachi",
    "iso:country":"PK",
    "wof:name":"Madat Khan",
    "wof:placetype":"locality"
},
  "geometry": {"coordinates":[69.06922,30.06723],"type":"Point"}
}