{
  "type": "Feature",
  "properties": {
    "gn:admin1_code":"4",
    "gn:asciiname":"Dhok Tredha",
    "gn:country_code":"PK",
    "gn:dem":450,
    "gn:feature_class":"P",
    "gn:feature_code":"PPL",
    "gn:name":"Dhok Tredha",
    "gn:population":0,
    "gn:timezone":"Asia/Karachi",
    "iso:country":"PK",
    "name:und_x_variant":[
        "Dhok Treda"
    ],
    "wof:name":"Dhok Tredha",
    "wof:placetype":"locality"
},
  "geometry": {"coordinates":[73.47014,33.19798],"type":"Point"}
}