{
  "type": "Feature",
  "properties": {
    "gn:admin1_code":"01",
    "gn:asciiname":"Larkhwa",
    "gn:country_code":"PK",
    "gn:dem":1853,
    "gn:feature_class":"P",
    "gn:feature_code":"PPL",
    "gn:name":"Larkhwa",
    "gn:population":0,
    "gn:timezone":"Asia/Karachi",
    "iso:country":"PK",
    "wof:name":"Larkhwa",
    "wof:placetype":"locality"
},
  "geometry": {"coordinates":[69.30639000000001,32.31778],"type":"Point"}
}