{
  "type": "Feature",
  "properties": {
    "gn:admin1_code":"5",
    "gn:asciiname":"Draba",
    "gn:country_code":"PK",
    "gn:dem":64,
    "gn:feature_class":"P",
    "gn:feature_code":"PPL",
    "gn:name":"Draba",
    "gn:population":0,
    "gn:timezone":"Asia/Karachi",
    "iso:country":"PK",
    "name:ara_x_preferred":[
        "\u062f\u0631\u0627\u0628\u0629"
    ],
    "name:azb_x_preferred":[
        "\u06cc\u0627\u0633\u062a\u06cc\u0642 \u0627\u0648\u062a\u0648"
    ],
    "name:aze_x_preferred":[
        "Yast\u0131qotu"
    ],
    "name:bel_x_preferred":[
        "\u0412\u044f\u0441\u043d\u044f\u043d\u043a\u0430"
    ],
    "name:cat_x_preferred":[
        "Draba"
    ],
    "name:ceb_x_preferred":[
        "Draba"
    ],
    "name:ces_x_preferred":[
        "Chudina"
    ],
    "name:dan_x_preferred":[
        "Draba"
    ],
    "name:deu_x_preferred":[
        "Felsenbl\u00fcmchen"
    ],
    "name:est_x_preferred":[
        "Kevadik"
    ],
    "name:fas_x_preferred":[
        "\u0627\u0632\u0645\u06a9\u06cc"
    ],
    "name:fin_x_preferred":[
        "Kynsim\u00f6t"
    ],
    "name:fra_x_preferred":[
        "Draba"
    ],
    "name:hsb_x_preferred":[
        "Skalinka"
    ],
    "name:hun_x_preferred":[
        "Daravir\u00e1g"
    ],
    "name:hye_x_preferred":[
        "\u0543\u0561\u0580\u057f\u0561\u0580\u0578\u0582\u056f"
    ],
    "name:ita_x_preferred":[
        "Draba"
    ],
    "name:kat_x_preferred":[
        "\u10e5\u10e3\u10d3\u10e3\u10dc\u10d0"
    ],
    "name:kaz_x_preferred":[
        "\u04d8\u0436\u0456\u043a"
    ],
    "name:kor_x_preferred":[
        "\uaf43\ub2e4\uc9c0\uc18d"
    ],
    "name:lit_x_preferred":[
        "Anksta"
    ],
    "name:mal_x_preferred":[
        "\u0d21\u0d4d\u0d30\u0d2c"
    ],
    "name:nld_x_preferred":[
        "Hongerbloempje"
    ],
    "name:pol_x_preferred":[
        "G\u0142odek"
    ],
    "name:por_x_preferred":[
        "Draba"
    ],
    "name:rus_x_preferred":[
        "\u041a\u0440\u0443\u043f\u043a\u0430"
    ],
    "name:spa_x_preferred":[
        "Draba"
    ],
    "name:swe_x_preferred":[
        "Drabor"
    ],
    "name:ukr_x_preferred":[
        "\u041a\u0440\u0443\u043f\u043a\u0430"
    ],
    "name:vie_x_preferred":[
        "Draba"
    ],
    "name:war_x_preferred":[
        "Draba"
    ],
    "name:zho_x_preferred":[
        "\u8476\u82c8\u5c5e"
    ],
    "wof:name":"Draba",
    "wof:placetype":"locality"
},
  "geometry": {"coordinates":[69.02601,27.07986],"type":"Point"}
}