{
  "type": "Feature",
  "properties": {
    "gn:admin1_code":"3.0",
    "gn:asciiname":"Kakul",
    "gn:country_code":"PK",
    "gn:dem":1283,
    "gn:feature_class":"P",
    "gn:feature_code":"PPL",
    "gn:name":"Kakul",
    "gn:population":0,
    "gn:timezone":"Asia/Karachi",
    "iso:country":"PK",
    "wof:name":"Kakul",
    "wof:placetype":"locality"
},
  "geometry": {"coordinates":[73.26000000000001,34.1875],"type":"Point"}
}