{
  "type": "Feature",
  "properties": {
    "gn:admin1_code":"4",
    "gn:asciiname":"Chak One Hundred Sixty-five Nine Left",
    "gn:country_code":"PK",
    "gn:dem":150,
    "gn:feature_class":"P",
    "gn:feature_code":"PPL",
    "gn:name":"Chak One Hundred Sixty-five Nine Left",
    "gn:population":0,
    "gn:timezone":"Asia/Karachi",
    "iso:country":"PK",
    "name:und_x_variant":[
        "Chak One Hundred Sixty-five Nine L"
    ],
    "wof:name":"Chak One Hundred Sixty-five Nine Left",
    "wof:placetype":"locality"
},
  "geometry": {"coordinates":[72.75898000000002,30.33822],"type":"Point"}
}