{
  "type": "Feature",
  "properties": {
    "gn:admin1_code":"2",
    "gn:asciiname":"Mor Takoh",
    "gn:country_code":"PK",
    "gn:dem":1625,
    "gn:feature_class":"P",
    "gn:feature_code":"PPL",
    "gn:name":"Mor Takoh",
    "gn:population":0,
    "gn:timezone":"Asia/Karachi",
    "iso:country":"PK",
    "wof:name":"Mor Takoh",
    "wof:placetype":"locality"
},
  "geometry": {"coordinates":[66.10476,28.26034000000001],"type":"Point"}
}