{
  "type": "Feature",
  "properties": {
    "gn:admin1_code":"4.0",
    "gn:asciiname":"Chak One Hundred Forty-seven -One Hundred Forty-eight Northern Branch",
    "gn:country_code":"PK",
    "gn:dem":176,
    "gn:feature_class":"P",
    "gn:feature_code":"PPL",
    "gn:name":"Chak One Hundred Forty-seven -One Hundred Forty-eight Northern Branch",
    "gn:population":0,
    "gn:timezone":"Asia/Karachi",
    "iso:country":"PK",
    "name:und_x_variant":[
        "Chak One Hundred Forty-Seven/One Hundred Forty-Eight NB",
        "Chak One Hundred Forty-Seven NB",
        "Lakhuana",
        "Chak One Hundred Forty-seven -One Hundred Forty-eight Northern Branch",
        "Lakhu\u0101na"
    ],
    "wof:name":"Chak One Hundred Forty-seven -One Hundred Forty-eight Northern Branch",
    "wof:placetype":"locality"
},
  "geometry": {"coordinates":[72.47402,31.79005],"type":"Point"}
}