{
  "type": "Feature",
  "properties": {
    "gn:admin1_code":"4.0",
    "gn:asciiname":"Chak Harma",
    "gn:country_code":"PK",
    "gn:dem":170,
    "gn:feature_class":"P",
    "gn:feature_code":"PPL",
    "gn:name":"Chak Harma",
    "gn:population":0,
    "gn:timezone":"Asia/Karachi",
    "iso:country":"PK",
    "wof:name":"Chak Harma",
    "wof:placetype":"locality"
},
  "geometry": {"coordinates":[73.01430999999999,30.74564],"type":"Point"}
}