{
  "type": "Feature",
  "properties": {
    "gn:admin1_code":"2.0",
    "gn:asciiname":"Ispitingar",
    "gn:country_code":"PK",
    "gn:dem":862,
    "gn:feature_class":"P",
    "gn:feature_code":"PPL",
    "gn:name":"Ispitingar",
    "gn:population":0,
    "gn:timezone":"Asia/Karachi",
    "iso:country":"PK",
    "wof:name":"Ispitingar",
    "wof:placetype":"locality"
},
  "geometry": {"coordinates":[62.51706,26.39063],"type":"Point"}
}