{
  "type": "Feature",
  "properties": {
    "gn:admin1_code":"02",
    "gn:asciiname":"Zama",
    "gn:country_code":"PK",
    "gn:dem":1849,
    "gn:feature_class":"P",
    "gn:feature_code":"PPL",
    "gn:name":"Zama",
    "gn:population":0,
    "gn:timezone":"Asia/Karachi",
    "iso:country":"PK",
    "name:ceb_x_preferred":[
        "Zama"
    ],
    "name:deu_x_preferred":[
        "Zama"
    ],
    "name:fra_x_preferred":[
        "Zama"
    ],
    "name:ind_x_preferred":[
        "Zama"
    ],
    "name:ita_x_preferred":[
        "Zama"
    ],
    "name:nld_x_preferred":[
        "Zama"
    ],
    "name:oci_x_preferred":[
        "Zama"
    ],
    "name:pol_x_preferred":[
        "Zama"
    ],
    "name:por_x_preferred":[
        "Zama"
    ],
    "name:swe_x_preferred":[
        "Zama"
    ],
    "name:tur_x_preferred":[
        "Zama"
    ],
    "name:und_x_variant":[
        "Zama Shah Murad",
        "Zama"
    ],
    "wof:name":"Zama",
    "wof:placetype":"locality"
},
  "geometry": {"coordinates":[67.68523,30.82842],"type":"Point"}
}