{
  "type": "Feature",
  "properties": {
    "gn:admin1_code":"5",
    "gn:asciiname":"Goth Sobho Khokhar",
    "gn:country_code":"PK",
    "gn:dem":53,
    "gn:feature_class":"P",
    "gn:feature_code":"PPL",
    "gn:name":"Goth Sobho Khokhar",
    "gn:population":0,
    "gn:timezone":"Asia/Karachi",
    "iso:country":"PK",
    "name:und_x_variant":[
        "Goth Sobo Khokhar"
    ],
    "wof:name":"Goth Sobho Khokhar",
    "wof:placetype":"locality"
},
  "geometry": {"coordinates":[68.22834,27.20754],"type":"Point"}
}