{
  "type": "Feature",
  "properties": {
    "gn:admin1_code":"5.0",
    "gn:asciiname":"Saiyid Karmallah Shah",
    "gn:country_code":"PK",
    "gn:dem":35,
    "gn:feature_class":"P",
    "gn:feature_code":"PPL",
    "gn:name":"Saiyid Karmallah Shah",
    "gn:population":0,
    "gn:timezone":"Asia/Karachi",
    "iso:country":"PK",
    "name:und_x_variant":[
        "Saiyid Karmull\u0101h Sh\u0101h"
    ],
    "wof:name":"Saiyid Karmallah Shah",
    "wof:placetype":"locality"
},
  "geometry": {"coordinates":[68.28497,26.18859],"type":"Point"}
}