{
  "type": "Feature",
  "properties": {
    "gn:admin1_code":"03",
    "gn:asciiname":"Taoso",
    "gn:country_code":"PK",
    "gn:dem":1212,
    "gn:feature_class":"P",
    "gn:feature_code":"PPL",
    "gn:name":"Taoso",
    "gn:population":0,
    "gn:timezone":"Asia/Karachi",
    "iso:country":"PK",
    "name:eng_x_preferred":[
        "Taoso"
    ],
    "wof:name":"Taoso",
    "wof:placetype":"locality"
},
  "geometry": {"coordinates":[71.75975,34.94918],"type":"Point"}
}