{
  "type": "Feature",
  "properties": {
    "gn:admin1_code":"5",
    "gn:asciiname":"Sakhio Khan",
    "gn:country_code":"PK",
    "gn:dem":73,
    "gn:feature_class":"P",
    "gn:feature_code":"PPL",
    "gn:name":"Sakhio Khan",
    "gn:population":0,
    "gn:timezone":"Asia/Karachi",
    "iso:country":"PK",
    "name:und_x_variant":[
        "Dud\u0101i Kh\u0101n"
    ],
    "wof:name":"Sakhio Khan",
    "wof:placetype":"locality"
},
  "geometry": {"coordinates":[69.65038,28.16599],"type":"Point"}
}