{
  "type": "Feature",
  "properties": {
    "gn:admin1_code":"4.0",
    "gn:asciiname":"Tibba Muhammad Nagar",
    "gn:country_code":"PK",
    "gn:dem":219,
    "gn:feature_class":"P",
    "gn:feature_code":"PPL",
    "gn:name":"Tibba Muhammad Nagar",
    "gn:population":0,
    "gn:timezone":"Asia/Karachi",
    "iso:country":"PK",
    "name:und_x_variant":[
        "Tibba"
    ],
    "wof:name":"Tibba Muhammad Nagar",
    "wof:placetype":"locality"
},
  "geometry": {"coordinates":[74.23378000000002,31.96677],"type":"Point"}
}