{
  "type": "Feature",
  "properties": {
    "gn:admin1_code":"3",
    "gn:asciiname":"Derai",
    "gn:country_code":"PK",
    "gn:dem":2902,
    "gn:feature_class":"P",
    "gn:feature_code":"PPL",
    "gn:name":"Derai",
    "gn:population":0,
    "gn:timezone":"Asia/Karachi",
    "iso:country":"PK",
    "name:und_x_variant":[
        "Der",
        "Derai"
    ],
    "wof:name":"Derai",
    "wof:placetype":"locality"
},
  "geometry": {"coordinates":[72.30710999999999,35.16954],"type":"Point"}
}