{
  "type": "Feature",
  "properties": {
    "gn:admin1_code":"2.0",
    "gn:asciiname":"Kili Haji Kuchal",
    "gn:country_code":"PK",
    "gn:dem":861,
    "gn:feature_class":"P",
    "gn:feature_code":"PPL",
    "gn:name":"Kili Haji Kuchal",
    "gn:population":0,
    "gn:timezone":"Asia/Karachi",
    "iso:country":"PK",
    "wof:name":"Kili Haji Kuchal",
    "wof:placetype":"locality"
},
  "geometry": {"coordinates":[64.67451,29.28352000000001],"type":"Point"}
}