{
  "type": "Feature",
  "properties": {
    "gn:admin1_code":"4.0",
    "gn:asciiname":"Basti Darkhan",
    "gn:country_code":"PK",
    "gn:dem":89,
    "gn:feature_class":"P",
    "gn:feature_code":"PPL",
    "gn:name":"Basti Darkhan",
    "gn:population":0,
    "gn:timezone":"Asia/Karachi",
    "iso:country":"PK",
    "name:und_x_variant":[
        "Basti Darkh\u0101nw\u0101li"
    ],
    "wof:name":"Basti Darkhan",
    "wof:placetype":"locality"
},
  "geometry": {"coordinates":[70.5234,28.70672],"type":"Point"}
}