{
  "type": "Feature",
  "properties": {
    "gn:admin1_code":"6",
    "gn:asciiname":"Batangi",
    "gn:country_code":"PK",
    "gn:dem":1459,
    "gn:feature_class":"P",
    "gn:feature_code":"PPL",
    "gn:name":"Batangi",
    "gn:population":0,
    "gn:timezone":"Asia/Karachi",
    "iso:country":"PK",
    "wof:name":"Batangi",
    "wof:placetype":"locality"
},
  "geometry": {"coordinates":[73.86,34.18309],"type":"Point"}
}