{
  "type": "Feature",
  "properties": {
    "gn:admin1_code":"3",
    "gn:asciiname":"Sorum",
    "gn:country_code":"PK",
    "gn:dem":2316,
    "gn:feature_class":"P",
    "gn:feature_code":"PPL",
    "gn:name":"Sorum",
    "gn:population":0,
    "gn:timezone":"Asia/Karachi",
    "iso:country":"PK",
    "name:eng_x_preferred":[
        "Sorum"
    ],
    "name:kor_x_preferred":[
        "\uc18c\ub984"
    ],
    "name:spa_x_preferred":[
        "Sorum"
    ],
    "wof:name":"Sorum",
    "wof:placetype":"locality"
},
  "geometry": {"coordinates":[71.68997,35.33238],"type":"Point"}
}