{
  "type": "Feature",
  "properties": {
    "gn:admin1_code":"3",
    "gn:asciiname":"Khabbal",
    "gn:country_code":"PK",
    "gn:dem":515,
    "gn:feature_class":"P",
    "gn:feature_code":"PPL",
    "gn:name":"Khabbal",
    "gn:population":0,
    "gn:timezone":"Asia/Karachi",
    "iso:country":"PK",
    "wof:name":"Khabbal",
    "wof:placetype":"locality"
},
  "geometry": {"coordinates":[72.78036999999998,34.15442],"type":"Point"}
}