{
  "type": "Feature",
  "properties": {
    "gn:admin1_code":"5.0",
    "gn:asciiname":"Goth Muhammad Bakhsh Laskani",
    "gn:country_code":"PK",
    "gn:dem":19,
    "gn:feature_class":"P",
    "gn:feature_code":"PPL",
    "gn:name":"Goth Muhammad Bakhsh Laskani",
    "gn:population":0,
    "gn:timezone":"Asia/Karachi",
    "iso:country":"PK",
    "name:und_x_variant":[
        "Goth Mun Lashk\u0101ni"
    ],
    "wof:name":"Goth Muhammad Bakhsh Laskani",
    "wof:placetype":"locality"
},
  "geometry": {"coordinates":[68.94880999999999,25.8193],"type":"Point"}
}