{
  "type": "Feature",
  "properties": {
    "gn:admin1_code":"3.0",
    "gn:asciiname":"Lawi",
    "gn:country_code":"PK",
    "gn:dem":1652,
    "gn:feature_class":"P",
    "gn:feature_code":"PPL",
    "gn:name":"Lawi",
    "gn:population":0,
    "gn:timezone":"Asia/Karachi",
    "iso:country":"PK",
    "name:eng_x_preferred":[
        "Lawi"
    ],
    "wof:name":"Lawi",
    "wof:placetype":"locality"
},
  "geometry": {"coordinates":[71.82143000000001,35.60343],"type":"Point"}
}