{
  "type": "Feature",
  "properties": {
    "gn:admin1_code":"01",
    "gn:asciiname":"Skha Kuhai",
    "gn:country_code":"PK",
    "gn:dem":949,
    "gn:feature_class":"P",
    "gn:feature_code":"PPL",
    "gn:name":"Skha Kuhai",
    "gn:population":0,
    "gn:timezone":"Asia/Karachi",
    "iso:country":"PK",
    "name:eng_x_preferred":[
        "Skha Kuhai"
    ],
    "wof:name":"Skha Kuhai",
    "wof:placetype":"locality"
},
  "geometry": {"coordinates":[71.50633000000001,34.78085],"type":"Point"}
}