{
  "type": "Feature",
  "properties": {
    "gn:admin1_code":"1.0",
    "gn:asciiname":"Zai",
    "gn:country_code":"PK",
    "gn:dem":1993,
    "gn:feature_class":"P",
    "gn:feature_code":"PPL",
    "gn:name":"Zai",
    "gn:population":0,
    "gn:timezone":"Asia/Karachi",
    "iso:country":"PK",
    "name:und_x_variant":[
        "Zaed",
        "Zae",
        "Zai",
        "Zai Saidgi"
    ],
    "wof:name":"Zai",
    "wof:placetype":"locality"
},
  "geometry": {"coordinates":[69.61315,33.04494],"type":"Point"}
}