{
  "type": "Feature",
  "properties": {
    "gn:admin1_code":"4.0",
    "gn:asciiname":"Shah di Khui",
    "gn:country_code":"PK",
    "gn:dem":214,
    "gn:feature_class":"P",
    "gn:feature_code":"PPL",
    "gn:name":"Shah di Khui",
    "gn:population":0,
    "gn:timezone":"Asia/Karachi",
    "iso:country":"PK",
    "name:eng_x_preferred":[
        "Sh\u0101h di Kh\u016bi"
    ],
    "wof:name":"Shah di Khui",
    "wof:placetype":"locality"
},
  "geometry": {"coordinates":[74.29496,31.49308],"type":"Point"}
}