{
  "type": "Feature",
  "properties": {
    "gn:admin1_code":"4.0",
    "gn:asciiname":"Shahidabad",
    "gn:country_code":"PK",
    "gn:dem":94,
    "gn:feature_class":"P",
    "gn:feature_code":"PPL",
    "gn:name":"Shah\u012bd\u0101b\u0101d",
    "gn:population":0,
    "gn:timezone":"Asia/Karachi",
    "iso:country":"PK",
    "wof:name":"Shahidabad",
    "wof:placetype":"locality"
},
  "geometry": {"coordinates":[70.69558000000001,29.01916],"type":"Point"}
}