{
  "type": "Feature",
  "properties": {
    "gn:admin1_code":"6.0",
    "gn:asciiname":"Chaksawari",
    "gn:country_code":"PK",
    "gn:dem":462,
    "gn:feature_class":"P",
    "gn:feature_code":"PPL",
    "gn:name":"Chaksawari",
    "gn:population":0,
    "gn:timezone":"Asia/Karachi",
    "iso:country":"PK",
    "wof:name":"Chaksawari",
    "wof:placetype":"locality"
},
  "geometry": {"coordinates":[73.78530000000001,33.2641],"type":"Point"}
}