{
  "type": "Feature",
  "properties": {
    "gn:admin1_code":"2",
    "gn:asciiname":"Faqirzai",
    "gn:country_code":"PK",
    "gn:dem":956,
    "gn:feature_class":"P",
    "gn:feature_code":"PPL",
    "gn:name":"Faqirzai",
    "gn:population":0,
    "gn:timezone":"Asia/Karachi",
    "iso:country":"PK",
    "name:und_x_variant":[
        "G\u016bjar Kili"
    ],
    "wof:name":"Faqirzai",
    "wof:placetype":"locality"
},
  "geometry": {"coordinates":[69.00669000000001,30.02582],"type":"Point"}
}