{
  "type": "Feature",
  "properties": {
    "gn:admin1_code":"4.0",
    "gn:asciiname":"Dera Ghulam Rasul",
    "gn:country_code":"PK",
    "gn:dem":85,
    "gn:feature_class":"P",
    "gn:feature_code":"PPL",
    "gn:name":"Dera Ghulam Rasul",
    "gn:population":0,
    "gn:timezone":"Asia/Karachi",
    "iso:country":"PK",
    "wof:name":"Dera Ghulam Rasul",
    "wof:placetype":"locality"
},
  "geometry": {"coordinates":[70.73379,28.61858],"type":"Point"}
}