{
  "type": "Feature",
  "properties": {
    "gn:admin1_code":"4",
    "gn:asciiname":"Chak Two Hundred Two Eastern Bank",
    "gn:country_code":"PK",
    "gn:dem":141,
    "gn:feature_class":"P",
    "gn:feature_code":"PPL",
    "gn:name":"Chak Two Hundred Two Eastern Bank",
    "gn:population":0,
    "gn:timezone":"Asia/Karachi",
    "iso:country":"PK",
    "name:und_x_variant":[
        "Chak Thirty-four-Two Hundred Two"
    ],
    "wof:name":"Chak Two Hundred Two Eastern Bank",
    "wof:placetype":"locality"
},
  "geometry": {"coordinates":[72.38319,30.19915],"type":"Point"}
}