{
  "type": "Feature",
  "properties": {
    "gn:admin1_code":"2",
    "gn:asciiname":"Dreneli",
    "gn:country_code":"PK",
    "gn:dem":1164,
    "gn:feature_class":"P",
    "gn:feature_code":"PPL",
    "gn:name":"Dreneli",
    "gn:population":0,
    "gn:timezone":"Asia/Karachi",
    "iso:country":"PK",
    "wof:name":"Dreneli",
    "wof:placetype":"locality"
},
  "geometry": {"coordinates":[66.23421,27.6339],"type":"Point"}
}