{
  "type": "Feature",
  "properties": {
    "gn:admin1_code":"5.0",
    "gn:asciiname":"Ghulam Muhammad Narejo",
    "gn:country_code":"PK",
    "gn:dem":28,
    "gn:feature_class":"P",
    "gn:feature_code":"PPL",
    "gn:name":"Ghulam Muhammad Narejo",
    "gn:population":0,
    "gn:timezone":"Asia/Karachi",
    "iso:country":"PK",
    "wof:name":"Ghulam Muhammad Narejo",
    "wof:placetype":"locality"
},
  "geometry": {"coordinates":[68.69835999999999,26.36781],"type":"Point"}
}