{
  "type": "Feature",
  "properties": {
    "gn:admin1_code":"2.0",
    "gn:asciiname":"Rehmatan",
    "gn:country_code":"PK",
    "gn:dem":1193,
    "gn:feature_class":"P",
    "gn:feature_code":"PPL",
    "gn:name":"Rehmatan",
    "gn:population":0,
    "gn:timezone":"Asia/Karachi",
    "iso:country":"PK",
    "wof:name":"Rehmatan",
    "wof:placetype":"locality"
},
  "geometry": {"coordinates":[69.81536,29.9672],"type":"Point"}
}