{
  "type": "Feature",
  "properties": {
    "gn:admin1_code":"3.0",
    "gn:asciiname":"Jodar",
    "gn:country_code":"PK",
    "gn:dem":1522,
    "gn:feature_class":"P",
    "gn:feature_code":"PPL",
    "gn:name":"Jodar",
    "gn:population":0,
    "gn:timezone":"Asia/Karachi",
    "iso:country":"PK",
    "wof:name":"Jodar",
    "wof:placetype":"locality"
},
  "geometry": {"coordinates":[73.24455999999998,35.3286],"type":"Point"}
}