{
  "type": "Feature",
  "properties": {
    "gn:admin1_code":"3",
    "gn:asciiname":"Manzarai Maidan",
    "gn:country_code":"PK",
    "gn:dem":1153,
    "gn:feature_class":"P",
    "gn:feature_code":"PPL",
    "gn:name":"Manzarai Maidan",
    "gn:population":0,
    "gn:timezone":"Asia/Karachi",
    "iso:country":"PK",
    "name:und_x_variant":[
        "Manzarai Maid\u0101n"
    ],
    "wof:name":"Manzarai Maidan",
    "wof:placetype":"locality"
},
  "geometry": {"coordinates":[72.46951999999997,34.65085999999999],"type":"Point"}
}