{
  "type": "Feature",
  "properties": {
    "gn:admin1_code":"3",
    "gn:asciiname":"Manchora",
    "gn:country_code":"PK",
    "gn:dem":1208,
    "gn:feature_class":"P",
    "gn:feature_code":"PPL",
    "gn:name":"Manchora",
    "gn:population":0,
    "gn:timezone":"Asia/Karachi",
    "iso:country":"PK",
    "name:und_x_variant":[
        "Manchpra"
    ],
    "wof:name":"Manchora",
    "wof:placetype":"locality"
},
  "geometry": {"coordinates":[73.00731,34.51752],"type":"Point"}
}