{
  "type": "Feature",
  "properties": {
    "gn:admin1_code":"1.0",
    "gn:asciiname":"Fazalabad",
    "gn:country_code":"PK",
    "gn:dem":957,
    "gn:feature_class":"P",
    "gn:feature_code":"PPL",
    "gn:name":"Fazalabad",
    "gn:population":0,
    "gn:timezone":"Asia/Karachi",
    "iso:country":"PK",
    "wof:name":"Fazalabad",
    "wof:placetype":"locality"
},
  "geometry": {"coordinates":[71.4027,34.7354],"type":"Point"}
}