{
  "type": "Feature",
  "properties": {
    "gn:admin1_code":"5.0",
    "gn:asciiname":"Gul Muhammad Brahui Goth",
    "gn:country_code":"PK",
    "gn:dem":48,
    "gn:feature_class":"P",
    "gn:feature_code":"PPL",
    "gn:name":"Gul Muhammad Brahui Goth",
    "gn:population":0,
    "gn:timezone":"Asia/Karachi",
    "iso:country":"PK",
    "name:eng_x_preferred":[
        "Goth Gul Muhammad Brahui"
    ],
    "wof:name":"Gul Muhammad Brahui Goth",
    "wof:placetype":"locality"
},
  "geometry": {"coordinates":[66.91573,24.96883],"type":"Point"}
}