{
  "type": "Feature",
  "properties": {
    "gn:admin1_code":"2",
    "gn:asciiname":"Malik Amir",
    "gn:country_code":"PK",
    "gn:dem":1916,
    "gn:feature_class":"P",
    "gn:feature_code":"PPL",
    "gn:name":"Malik Amir",
    "gn:population":0,
    "gn:timezone":"Asia/Karachi",
    "iso:country":"PK",
    "wof:name":"Malik Amir",
    "wof:placetype":"locality"
},
  "geometry": {"coordinates":[66.87576,31.13778],"type":"Point"}
}