{
  "type": "Feature",
  "properties": {
    "gn:admin1_code":"2.0",
    "gn:asciiname":"Tang",
    "gn:country_code":"PK",
    "gn:dem":1252,
    "gn:feature_class":"P",
    "gn:feature_code":"PPL",
    "gn:name":"Tang",
    "gn:population":0,
    "gn:timezone":"Asia/Karachi",
    "iso:country":"PK",
    "wof:name":"Tang",
    "wof:placetype":"locality"
},
  "geometry": {"coordinates":[69.71365,30.00704],"type":"Point"}
}