{
  "type": "Feature",
  "properties": {
    "gn:admin1_code":"5",
    "gn:asciiname":"Haji Fateh Muhammad Brahui",
    "gn:country_code":"PK",
    "gn:dem":37,
    "gn:feature_class":"P",
    "gn:feature_code":"PPL",
    "gn:name":"Haji Fateh Muhammad Brahui",
    "gn:population":0,
    "gn:timezone":"Asia/Karachi",
    "iso:country":"PK",
    "wof:name":"Haji Fateh Muhammad Brahui",
    "wof:placetype":"locality"
},
  "geometry": {"coordinates":[68.57404,26.35931],"type":"Point"}
}