{
  "type": "Feature",
  "properties": {
    "gn:admin1_code":"4.0",
    "gn:asciiname":"Akkuwala",
    "gn:country_code":"PK",
    "gn:dem":109,
    "gn:feature_class":"P",
    "gn:feature_code":"PPL",
    "gn:name":"Akkuwala",
    "gn:population":0,
    "gn:timezone":"Asia/Karachi",
    "iso:country":"PK",
    "name:und_x_variant":[
        "Ch\u0101h Akkuw\u0101la"
    ],
    "wof:name":"Akkuwala",
    "wof:placetype":"locality"
},
  "geometry": {"coordinates":[71.28548000000001,29.61291],"type":"Point"}
}