{
  "type": "Feature",
  "properties": {
    "gn:admin1_code":"03",
    "gn:asciiname":"Mutrachh",
    "gn:country_code":"PK",
    "gn:dem":1227,
    "gn:feature_class":"P",
    "gn:feature_code":"PPL",
    "gn:name":"Mutrachh",
    "gn:population":0,
    "gn:timezone":"Asia/Karachi",
    "iso:country":"PK",
    "wof:name":"Mutrachh",
    "wof:placetype":"locality"
},
  "geometry": {"coordinates":[73.11750000000001,34.22111],"type":"Point"}
}