{
  "type": "Feature",
  "properties": {
    "gn:admin1_code":"2.0",
    "gn:asciiname":"Ghazlana",
    "gn:country_code":"PK",
    "gn:dem":2140,
    "gn:feature_class":"P",
    "gn:feature_code":"PPL",
    "gn:name":"Ghazlana",
    "gn:population":0,
    "gn:timezone":"Asia/Karachi",
    "iso:country":"PK",
    "name:und_x_variant":[
        "Ghazl\u016bna",
        "Ghazlana"
    ],
    "wof:name":"Ghazlana",
    "wof:placetype":"locality"
},
  "geometry": {"coordinates":[67.62035999999999,30.71884],"type":"Point"}
}