{
  "type": "Feature",
  "properties": {
    "gn:admin1_code":"6",
    "gn:asciiname":"Nale",
    "gn:country_code":"PK",
    "gn:dem":1768,
    "gn:feature_class":"P",
    "gn:feature_code":"PPL",
    "gn:name":"Nale",
    "gn:population":0,
    "gn:timezone":"Asia/Karachi",
    "iso:country":"PK",
    "wof:name":"Nale",
    "wof:placetype":"locality"
},
  "geometry": {"coordinates":[73.70477,34.45436],"type":"Point"}
}