{
  "type": "Feature",
  "properties": {
    "gn:admin1_code":"02",
    "gn:asciiname":"Tangi Ziarat",
    "gn:country_code":"PK",
    "gn:dem":1669,
    "gn:feature_class":"P",
    "gn:feature_code":"PPL",
    "gn:name":"Tangi Ziarat",
    "gn:population":0,
    "gn:timezone":"Asia/Karachi",
    "iso:country":"PK",
    "wof:name":"Tangi Ziarat",
    "wof:placetype":"locality"
},
  "geometry": {"coordinates":[68.06104000000001,30.88797000000001],"type":"Point"}
}