{
  "type": "Feature",
  "properties": {
    "gn:admin1_code":"5",
    "gn:asciiname":"Goth Mahmud Rahu",
    "gn:country_code":"PK",
    "gn:dem":15,
    "gn:feature_class":"P",
    "gn:feature_code":"PPL",
    "gn:name":"Goth Mahmud Rahu",
    "gn:population":0,
    "gn:timezone":"Asia/Karachi",
    "iso:country":"PK",
    "name:und_x_variant":[
        "Goth Mahm\u016bd"
    ],
    "wof:name":"Goth Mahmud Rahu",
    "wof:placetype":"locality"
},
  "geometry": {"coordinates":[69.21021999999999,25.5898],"type":"Point"}
}