{
  "type": "Feature",
  "properties": {
    "gn:admin1_code":"04",
    "gn:asciiname":"Chak One Hundred Eighty",
    "gn:country_code":"PK",
    "gn:dem":197,
    "gn:feature_class":"P",
    "gn:feature_code":"PPL",
    "gn:name":"Chak One Hundred Eighty",
    "gn:population":0,
    "gn:timezone":"Asia/Karachi",
    "iso:country":"PK",
    "name:und_x_variant":[
        "Nathuw\u0101la"
    ],
    "wof:name":"Chak One Hundred Eighty",
    "wof:placetype":"locality"
},
  "geometry": {"coordinates":[73.5733,31.56413],"type":"Point"}
}