{
  "type": "Feature",
  "properties": {
    "gn:admin1_code":"4",
    "gn:asciiname":"Maiman",
    "gn:country_code":"PK",
    "gn:dem":184,
    "gn:feature_class":"P",
    "gn:feature_code":"PPL",
    "gn:name":"Maiman",
    "gn:population":0,
    "gn:timezone":"Asia/Karachi",
    "iso:country":"PK",
    "name:heb_x_preferred":[
        "\u05de\u05d9\u05de\u05df"
    ],
    "name:und_x_variant":[
        "Memon"
    ],
    "wof:name":"Maiman",
    "wof:placetype":"locality"
},
  "geometry": {"coordinates":[73.43409,31.13003],"type":"Point"}
}