{
  "type": "Feature",
  "properties": {
    "gn:admin1_code":"5",
    "gn:asciiname":"Goth Bhurgari",
    "gn:country_code":"PK",
    "gn:dem":9,
    "gn:feature_class":"P",
    "gn:feature_code":"PPL",
    "gn:name":"Goth Bhurgari",
    "gn:population":0,
    "gn:timezone":"Asia/Karachi",
    "iso:country":"PK",
    "name:und_x_variant":[
        "Goth Wadal Sh\u0101h"
    ],
    "wof:name":"Goth Bhurgari",
    "wof:placetype":"locality"
},
  "geometry": {"coordinates":[69.36121999999999,24.89973],"type":"Point"}
}