{
  "type": "Feature",
  "properties": {
    "gn:admin1_code":"5.0",
    "gn:asciiname":"Deedsar",
    "gn:country_code":"PK",
    "gn:dem":30,
    "gn:feature_class":"P",
    "gn:feature_code":"PPL",
    "gn:name":"Deedsar",
    "gn:population":0,
    "gn:timezone":"Asia/Karachi",
    "iso:country":"PK",
    "wof:name":"Deedsar",
    "wof:placetype":"locality"
},
  "geometry": {"coordinates":[69.73997,24.46826],"type":"Point"}
}