{
  "type": "Feature",
  "properties": {
    "gn:admin1_code":"2.0",
    "gn:asciiname":"Burj Malan",
    "gn:country_code":"PK",
    "gn:dem":2049,
    "gn:feature_class":"P",
    "gn:feature_code":"PPL",
    "gn:name":"Burj Malan",
    "gn:population":0,
    "gn:timezone":"Asia/Karachi",
    "iso:country":"PK",
    "wof:name":"Burj Malan",
    "wof:placetype":"locality"
},
  "geometry": {"coordinates":[68.15139000000001,30.35784],"type":"Point"}
}