{
  "type": "Feature",
  "properties": {
    "gn:admin1_code":"07",
    "gn:asciiname":"Kurangay",
    "gn:country_code":"PK",
    "gn:dem":2160,
    "gn:feature_class":"P",
    "gn:feature_code":"PPL",
    "gn:name":"Kurangay",
    "gn:population":0,
    "gn:timezone":"Asia/Karachi",
    "iso:country":"PK",
    "name:und_x_variant":[
        "Kuranga"
    ],
    "wof:name":"Kurangay",
    "wof:placetype":"locality"
},
  "geometry": {"coordinates":[73.38759,35.76123],"type":"Point"}
}