{
  "type": "Feature",
  "properties": {
    "gn:admin1_code":"4.0",
    "gn:asciiname":"Rattagarh",
    "gn:country_code":"PK",
    "gn:dem":253,
    "gn:feature_class":"P",
    "gn:feature_code":"PPL",
    "gn:name":"Rattagarh",
    "gn:population":0,
    "gn:timezone":"Asia/Karachi",
    "iso:country":"PK",
    "name:und_x_variant":[
        "Rattangarh"
    ],
    "wof:name":"Rattagarh",
    "wof:placetype":"locality"
},
  "geometry": {"coordinates":[74.79358000000001,32.29342],"type":"Point"}
}