{
  "type": "Feature",
  "properties": {
    "gn:admin1_code":"3",
    "gn:asciiname":"Bankot",
    "gn:country_code":"PK",
    "gn:dem":1170,
    "gn:feature_class":"P",
    "gn:feature_code":"PPL",
    "gn:name":"Bankot",
    "gn:population":0,
    "gn:timezone":"Asia/Karachi",
    "iso:country":"PK",
    "wof:name":"Bankot",
    "wof:placetype":"locality"
},
  "geometry": {"coordinates":[73.04259999999999,34.51822],"type":"Point"}
}