{
  "type": "Feature",
  "properties": {
    "gn:admin1_code":"2.0",
    "gn:asciiname":"Kechi Chah",
    "gn:country_code":"PK",
    "gn:dem":581,
    "gn:feature_class":"P",
    "gn:feature_code":"PPL",
    "gn:name":"Kechi Chah",
    "gn:population":0,
    "gn:timezone":"Asia/Karachi",
    "iso:country":"PK",
    "wof:name":"Kechi Chah",
    "wof:placetype":"locality"
},
  "geometry": {"coordinates":[63.20528,27.72861],"type":"Point"}
}