{
  "type": "Feature",
  "properties": {
    "gn:admin1_code":"1.0",
    "gn:asciiname":"Tarmira",
    "gn:country_code":"PK",
    "gn:dem":1981,
    "gn:feature_class":"P",
    "gn:feature_code":"PPL",
    "gn:name":"Tarmira",
    "gn:population":0,
    "gn:timezone":"Asia/Karachi",
    "iso:country":"PK",
    "wof:name":"Tarmira",
    "wof:placetype":"locality"
},
  "geometry": {"coordinates":[70.47201,33.83456],"type":"Point"}
}