{
  "type": "Feature",
  "properties": {
    "gn:admin1_code":"03",
    "gn:asciiname":"Melogan",
    "gn:country_code":"PK",
    "gn:dem":314,
    "gn:feature_class":"P",
    "gn:feature_code":"PPL",
    "gn:name":"Melogan",
    "gn:population":0,
    "gn:timezone":"Asia/Karachi",
    "iso:country":"PK",
    "name:eng_x_preferred":[
        "Melugan"
    ],
    "wof:name":"Melogan",
    "wof:placetype":"locality"
},
  "geometry": {"coordinates":[71.57715,34.14230999999999],"type":"Point"}
}