{
  "type": "Feature",
  "properties": {
    "gn:admin1_code":"3.0",
    "gn:asciiname":"Shangal",
    "gn:country_code":"PK",
    "gn:dem":604,
    "gn:feature_class":"P",
    "gn:feature_code":"PPL",
    "gn:name":"Shangal",
    "gn:population":0,
    "gn:timezone":"Asia/Karachi",
    "iso:country":"PK",
    "wof:name":"Shangal",
    "wof:placetype":"locality"
},
  "geometry": {"coordinates":[71.82661,34.60773],"type":"Point"}
}