{
  "type": "Feature",
  "properties": {
    "gn:admin1_code":"4.0",
    "gn:asciiname":"Chak Jithianwala",
    "gn:country_code":"PK",
    "gn:dem":208,
    "gn:feature_class":"P",
    "gn:feature_code":"PPL",
    "gn:name":"Chak Jithianwala",
    "gn:population":0,
    "gn:timezone":"Asia/Karachi",
    "iso:country":"PK",
    "wof:name":"Chak Jithianwala",
    "wof:placetype":"locality"
},
  "geometry": {"coordinates":[74.08311999999999,31.71039],"type":"Point"}
}