{
  "type": "Feature",
  "properties": {
    "gn:admin1_code":"4",
    "gn:asciiname":"Bhattiwala",
    "gn:country_code":"PK",
    "gn:dem":111,
    "gn:feature_class":"P",
    "gn:feature_code":"PPL",
    "gn:name":"Bhattiwala",
    "gn:population":0,
    "gn:timezone":"Asia/Karachi",
    "iso:country":"PK",
    "name:und_x_variant":[
        "Basti Hamid"
    ],
    "wof:name":"Bhattiwala",
    "wof:placetype":"locality"
},
  "geometry": {"coordinates":[70.68728,29.83616],"type":"Point"}
}