{
  "type": "Feature",
  "properties": {
    "gn:admin1_code":"3",
    "gn:asciiname":"Glagran",
    "gn:country_code":"PK",
    "gn:dem":2120,
    "gn:feature_class":"P",
    "gn:feature_code":"PPL",
    "gn:name":"Glagran",
    "gn:population":0,
    "gn:timezone":"Asia/Karachi",
    "iso:country":"PK",
    "wof:name":"Glagran",
    "wof:placetype":"locality"
},
  "geometry": {"coordinates":[73.52849999999999,34.77019],"type":"Point"}
}