{
  "type": "Feature",
  "properties": {
    "gn:admin1_code":"5.0",
    "gn:asciiname":"Idu Khan Laghari",
    "gn:country_code":"PK",
    "gn:dem":6,
    "gn:feature_class":"P",
    "gn:feature_code":"PPL",
    "gn:name":"Idu Khan Laghari",
    "gn:population":0,
    "gn:timezone":"Asia/Karachi",
    "iso:country":"PK",
    "wof:name":"Idu Khan Laghari",
    "wof:placetype":"locality"
},
  "geometry": {"coordinates":[68.11651999999999,24.2696],"type":"Point"}
}