{
  "type": "Feature",
  "properties": {
    "gn:admin1_code":"4.0",
    "gn:asciiname":"Dera Muhammad Shabbir",
    "gn:country_code":"PK",
    "gn:dem":151,
    "gn:feature_class":"P",
    "gn:feature_code":"PPL",
    "gn:name":"Dera Muhammad Shabbir",
    "gn:population":0,
    "gn:timezone":"Asia/Karachi",
    "iso:country":"PK",
    "wof:name":"Dera Muhammad Shabbir",
    "wof:placetype":"locality"
},
  "geometry": {"coordinates":[71.26028000000002,31.11301],"type":"Point"}
}