{
  "type": "Feature",
  "properties": {
    "gn:admin1_code":"4.0",
    "gn:asciiname":"Qasimabad",
    "gn:country_code":"PK",
    "gn:dem":152,
    "gn:feature_class":"P",
    "gn:feature_code":"PPL",
    "gn:name":"Qasimabad",
    "gn:population":0,
    "gn:timezone":"Asia/Karachi",
    "iso:country":"PK",
    "name:fas_x_preferred":[
        "\u0642\u0627\u0633\u0645\u200c\u0622\u0628\u0627\u062f"
    ],
    "wof:name":"Qasimabad",
    "wof:placetype":"locality"
},
  "geometry": {"coordinates":[72.46968000000003,30.56777],"type":"Point"}
}