{
  "type": "Feature",
  "properties": {
    "gn:admin1_code":"5.0",
    "gn:asciiname":"Chaneser Khan Khaskheli",
    "gn:country_code":"PK",
    "gn:dem":40,
    "gn:feature_class":"P",
    "gn:feature_code":"PPL",
    "gn:name":"Chaneser Khan Khaskheli",
    "gn:population":0,
    "gn:timezone":"Asia/Karachi",
    "iso:country":"PK",
    "wof:name":"Chaneser Khan Khaskheli",
    "wof:placetype":"locality"
},
  "geometry": {"coordinates":[70.68028000000002,24.60188],"type":"Point"}
}