{
  "type": "Feature",
  "properties": {
    "gn:admin1_code":"3",
    "gn:asciiname":"Bedar Banda",
    "gn:country_code":"PK",
    "gn:dem":1536,
    "gn:feature_class":"P",
    "gn:feature_code":"PPL",
    "gn:name":"Bedar Banda",
    "gn:population":0,
    "gn:timezone":"Asia/Karachi",
    "iso:country":"PK",
    "name:eng_x_preferred":[
        "Bedar Banda"
    ],
    "wof:name":"Bedar Banda",
    "wof:placetype":"locality"
},
  "geometry": {"coordinates":[71.93629,35.13999],"type":"Point"}
}