{
  "type": "Feature",
  "properties": {
    "gn:admin1_code":"4",
    "gn:asciiname":"Chak Three Hundred Thirty-four Jhang Branch",
    "gn:country_code":"PK",
    "gn:dem":178,
    "gn:feature_class":"P",
    "gn:feature_code":"PPL",
    "gn:name":"Chak Three Hundred Thirty-four Jhang Branch",
    "gn:population":0,
    "gn:timezone":"Asia/Karachi",
    "iso:country":"PK",
    "name:und_x_variant":[
        "Tahs\u012bld\u0101rw\u0101la",
        "Chak Three Hundred Thirty-Four",
        "Chak Three Hundred Thirty-four Jhang Branch"
    ],
    "wof:name":"Chak Three Hundred Thirty-four Jhang Branch",
    "wof:placetype":"locality"
},
  "geometry": {"coordinates":[72.76874000000002,31.33731],"type":"Point"}
}