{
  "type": "Feature",
  "properties": {
    "gn:admin1_code":"7.0",
    "gn:asciiname":"Surlo",
    "gn:country_code":"PK",
    "gn:dem":2901,
    "gn:feature_class":"P",
    "gn:feature_code":"PPL",
    "gn:name":"Surlo",
    "gn:population":0,
    "gn:timezone":"Asia/Karachi",
    "iso:country":"PK",
    "name:und_x_variant":[
        "Surbo"
    ],
    "wof:name":"Surlo",
    "wof:placetype":"locality"
},
  "geometry": {"coordinates":[75.28149000000001,35.66604],"type":"Point"}
}