{
  "type": "Feature",
  "properties": {
    "gn:admin1_code":"3.0",
    "gn:asciiname":"Mir Rahman Kalle",
    "gn:country_code":"PK",
    "gn:dem":326,
    "gn:feature_class":"P",
    "gn:feature_code":"PPL",
    "gn:name":"Mir Rahman Kalle",
    "gn:population":0,
    "gn:timezone":"Asia/Karachi",
    "iso:country":"PK",
    "name:eng_x_preferred":[
        "M\u012br Rahm\u0101n Kor\u016bna"
    ],
    "wof:name":"Mir Rahman Kalle",
    "wof:placetype":"locality"
},
  "geometry": {"coordinates":[71.97986,34.23748],"type":"Point"}
}