{
  "type": "Feature",
  "properties": {
    "gn:admin1_code":"2.0",
    "gn:asciiname":"Girdiwah",
    "gn:country_code":"PK",
    "gn:dem":1365,
    "gn:feature_class":"P",
    "gn:feature_code":"PPL",
    "gn:name":"Girdiwah",
    "gn:population":0,
    "gn:timezone":"Asia/Karachi",
    "iso:country":"PK",
    "wof:name":"Girdiwah",
    "wof:placetype":"locality"
},
  "geometry": {"coordinates":[69.66797,30.29894],"type":"Point"}
}