{
  "type": "Feature",
  "properties": {
    "gn:admin1_code":"4",
    "gn:asciiname":"Rupari",
    "gn:country_code":"PK",
    "gn:dem":314,
    "gn:feature_class":"P",
    "gn:feature_code":"PPL",
    "gn:name":"Rupari",
    "gn:population":0,
    "gn:timezone":"Asia/Karachi",
    "iso:country":"PK",
    "name:und_x_variant":[
        "Ruperi"
    ],
    "wof:name":"Rupari",
    "wof:placetype":"locality"
},
  "geometry": {"coordinates":[74.13087,32.84084],"type":"Point"}
}