{
  "type": "Feature",
  "properties": {
    "gn:admin1_code":"4",
    "gn:asciiname":"Shah Baig Khel",
    "gn:country_code":"PK",
    "gn:dem":197,
    "gn:feature_class":"P",
    "gn:feature_code":"PPL",
    "gn:name":"Shah Baig Khel",
    "gn:population":0,
    "gn:timezone":"Asia/Karachi",
    "iso:country":"PK",
    "name:und_x_variant":[
        "Muqarrabw\u0101la",
        "Sh\u0101hbog Khel"
    ],
    "wof:name":"Shah Baig Khel",
    "wof:placetype":"locality"
},
  "geometry": {"coordinates":[71.95,32.34217],"type":"Point"}
}