{
  "type": "Feature",
  "properties": {
    "gn:admin1_code":"4",
    "gn:asciiname":"Habibwala",
    "gn:country_code":"PK",
    "gn:dem":134,
    "gn:feature_class":"P",
    "gn:feature_code":"PPL",
    "gn:name":"Habibwala",
    "gn:population":0,
    "gn:timezone":"Asia/Karachi",
    "iso:country":"PK",
    "name:eng_x_preferred":[
        "Habibwala"
    ],
    "wof:name":"Habibwala",
    "wof:placetype":"locality"
},
  "geometry": {"coordinates":[70.88249999999999,30.50513],"type":"Point"}
}