{
  "type": "Feature",
  "properties": {
    "gn:admin1_code":"5",
    "gn:asciiname":"Goth Sabu Galhro",
    "gn:country_code":"PK",
    "gn:dem":18,
    "gn:feature_class":"P",
    "gn:feature_code":"PPL",
    "gn:name":"Goth Sabu Galhro",
    "gn:population":0,
    "gn:timezone":"Asia/Karachi",
    "iso:country":"PK",
    "name:und_x_variant":[
        "Goth Sabu Ghelro",
        "Goth Sabu Gahelro",
        "Goth Sabu Galhro"
    ],
    "wof:name":"Goth Sabu Galhro",
    "wof:placetype":"locality"
},
  "geometry": {"coordinates":[68.88195999999999,25.18178],"type":"Point"}
}