{
  "type": "Feature",
  "properties": {
    "gn:admin1_code":"2.0",
    "gn:asciiname":"Kili Bakrai",
    "gn:country_code":"PK",
    "gn:dem":1891,
    "gn:feature_class":"P",
    "gn:feature_code":"PPL",
    "gn:name":"Kili Bakrai",
    "gn:population":0,
    "gn:timezone":"Asia/Karachi",
    "iso:country":"PK",
    "wof:name":"Kili Bakrai",
    "wof:placetype":"locality"
},
  "geometry": {"coordinates":[68.80428000000001,31.17871],"type":"Point"}
}