{
  "type": "Feature",
  "properties": {
    "gn:admin1_code":"4.0",
    "gn:asciiname":"Mehr Jumma",
    "gn:country_code":"PK",
    "gn:dem":78,
    "gn:feature_class":"P",
    "gn:feature_code":"PPL",
    "gn:name":"Mehr Jumma",
    "gn:population":0,
    "gn:timezone":"Asia/Karachi",
    "iso:country":"PK",
    "name:und_x_variant":[
        "Mad Juma"
    ],
    "wof:name":"Mehr Jumma",
    "wof:placetype":"locality"
},
  "geometry": {"coordinates":[70.46905,28.39702],"type":"Point"}
}