{
  "type": "Feature",
  "properties": {
    "gn:admin1_code":"7.0",
    "gn:asciiname":"Gumba Ghorse",
    "gn:country_code":"PK",
    "gn:dem":2488,
    "gn:feature_class":"P",
    "gn:feature_code":"PPL",
    "gn:name":"Gumba Ghorse",
    "gn:population":0,
    "gn:timezone":"Asia/Karachi",
    "iso:country":"PK",
    "name:und_x_variant":[
        "Gurtse",
        "Gurtse G\u00f6mpa",
        "Gumba Ghorse"
    ],
    "wof:name":"Gumba Ghorse",
    "wof:placetype":"locality"
},
  "geometry": {"coordinates":[76.43819999999999,35.18279],"type":"Point"}
}