{
  "type": "Feature",
  "properties": {
    "gn:admin1_code":"4.0",
    "gn:asciiname":"Kotli Hashim",
    "gn:country_code":"PK",
    "gn:dem":126,
    "gn:feature_class":"P",
    "gn:feature_code":"PPL",
    "gn:name":"Kotli Hashim",
    "gn:population":0,
    "gn:timezone":"Asia/Karachi",
    "iso:country":"PK",
    "name:eng_x_preferred":[
        "Kotli Hashim"
    ],
    "wof:name":"Kotli Hashim",
    "wof:placetype":"locality"
},
  "geometry": {"coordinates":[71.86913,29.99692000000001],"type":"Point"}
}