{
  "type": "Feature",
  "properties": {
    "gn:admin1_code":"4.0",
    "gn:asciiname":"Chak Two Hundred Fifteen Gugera Branch",
    "gn:country_code":"PK",
    "gn:dem":169,
    "gn:feature_class":"P",
    "gn:feature_code":"PPL",
    "gn:name":"Chak Two Hundred Fifteen Gugera Branch",
    "gn:population":0,
    "gn:timezone":"Asia/Karachi",
    "iso:country":"PK",
    "name:und_x_variant":[
        "Hamza",
        "Da\u016bd Hamza"
    ],
    "wof:name":"Chak Two Hundred Fifteen Gugera Branch",
    "wof:placetype":"locality"
},
  "geometry": {"coordinates":[72.80593,31.02236],"type":"Point"}
}