{
  "type": "Feature",
  "properties": {
    "gn:admin1_code":"4.0",
    "gn:asciiname":"Haji Muhammad Khan da Dera",
    "gn:country_code":"PK",
    "gn:dem":191,
    "gn:feature_class":"P",
    "gn:feature_code":"PPL",
    "gn:name":"Haji Muhammad Khan da Dera",
    "gn:population":0,
    "gn:timezone":"Asia/Karachi",
    "iso:country":"PK",
    "name:und_x_variant":[
        "H\u0101ji Muhammad Kh\u0101ne d\u0101 Dera"
    ],
    "wof:name":"Haji Muhammad Khan da Dera",
    "wof:placetype":"locality"
},
  "geometry": {"coordinates":[72.61725,32.47689],"type":"Point"}
}