{
  "type": "Feature",
  "properties": {
    "gn:admin1_code":"1.0",
    "gn:asciiname":"Chingai Banda",
    "gn:country_code":"PK",
    "gn:dem":435,
    "gn:feature_class":"P",
    "gn:feature_code":"PPL",
    "gn:name":"Chingai Banda",
    "gn:population":0,
    "gn:timezone":"Asia/Karachi",
    "iso:country":"PK",
    "name:und_x_variant":[
        "Chingai B\u0101nda"
    ],
    "wof:name":"Chingai Banda",
    "wof:placetype":"locality"
},
  "geometry": {"coordinates":[71.39270999999999,34.20552],"type":"Point"}
}