{
  "type": "Feature",
  "properties": {
    "gn:admin1_code":"2.0",
    "gn:asciiname":"Kili Gulzar Abad",
    "gn:country_code":"PK",
    "gn:dem":1378,
    "gn:feature_class":"P",
    "gn:feature_code":"PPL",
    "gn:name":"Kili Gulzar Abad",
    "gn:population":0,
    "gn:timezone":"Asia/Karachi",
    "iso:country":"PK",
    "wof:name":"Kili Gulzar Abad",
    "wof:placetype":"locality"
},
  "geometry": {"coordinates":[65.80705,27.85802],"type":"Point"}
}