{
  "type": "Feature",
  "properties": {
    "gn:admin1_code":"4.0",
    "gn:asciiname":"Garamb",
    "gn:country_code":"PK",
    "gn:dem":859,
    "gn:feature_class":"P",
    "gn:feature_code":"PPL",
    "gn:name":"Garamb",
    "gn:population":0,
    "gn:timezone":"Asia/Karachi",
    "iso:country":"PK",
    "name:eng_x_preferred":[
        "Gharamb"
    ],
    "wof:name":"Garamb",
    "wof:placetype":"locality"
},
  "geometry": {"coordinates":[73.2692,33.83167],"type":"Point"}
}