{
  "type": "Feature",
  "properties": {
    "gn:admin1_code":"5",
    "gn:asciiname":"Chachar",
    "gn:country_code":"PK",
    "gn:dem":50,
    "gn:feature_class":"P",
    "gn:feature_code":"PPL",
    "gn:name":"Chachar",
    "gn:population":0,
    "gn:timezone":"Asia/Karachi",
    "iso:country":"PK",
    "name:snd_x_preferred":[
        "\u0686\u0627\u0686\u0699"
    ],
    "wof:name":"Chachar",
    "wof:placetype":"locality"
},
  "geometry": {"coordinates":[68.10059,27.52355],"type":"Point"}
}