{
  "type": "Feature",
  "properties": {
    "gn:admin1_code":"5",
    "gn:asciiname":"Khalrai",
    "gn:country_code":"PK",
    "gn:dem":22,
    "gn:feature_class":"P",
    "gn:feature_code":"PPL",
    "gn:name":"Khalrai",
    "gn:population":0,
    "gn:timezone":"Asia/Karachi",
    "iso:country":"PK",
    "wof:name":"Khalrai",
    "wof:placetype":"locality"
},
  "geometry": {"coordinates":[69.79975999999999,25.44906],"type":"Point"}
}