{
  "type": "Feature",
  "properties": {
    "gn:admin1_code":"4",
    "gn:asciiname":"Muhammadwali",
    "gn:country_code":"PK",
    "gn:dem":829,
    "gn:feature_class":"P",
    "gn:feature_code":"PPL",
    "gn:name":"Muhammadwali",
    "gn:population":0,
    "gn:timezone":"Asia/Karachi",
    "iso:country":"PK",
    "name:und_x_variant":[
        "Muhammadw\u0101li",
        "Muhammad W\u0101li"
    ],
    "wof:name":"Muhammadwali",
    "wof:placetype":"locality"
},
  "geometry": {"coordinates":[72.27021999999999,32.63412],"type":"Point"}
}