{
  "type": "Feature",
  "properties": {
    "gn:admin1_code":"4",
    "gn:asciiname":"Huddiwala",
    "gn:country_code":"PK",
    "gn:dem":172,
    "gn:feature_class":"P",
    "gn:feature_code":"PPL",
    "gn:name":"Huddiwala",
    "gn:population":0,
    "gn:timezone":"Asia/Karachi",
    "iso:country":"PK",
    "name:und_x_variant":[
        "Sard\u0101r Hadd\u012bw\u0101la"
    ],
    "wof:name":"Huddiwala",
    "wof:placetype":"locality"
},
  "geometry": {"coordinates":[73.81659999999999,30.2807],"type":"Point"}
}