{
  "type": "Feature",
  "properties": {
    "gn:admin1_code":"4.0",
    "gn:asciiname":"Dhok Ghulamari Khel",
    "gn:country_code":"PK",
    "gn:dem":377,
    "gn:feature_class":"P",
    "gn:feature_code":"PPL",
    "gn:name":"Dhok Ghulamari Khel",
    "gn:population":0,
    "gn:timezone":"Asia/Karachi",
    "iso:country":"PK",
    "name:und_x_variant":[
        "Y\u0101r Gul"
    ],
    "wof:name":"Dhok Ghulamari Khel",
    "wof:placetype":"locality"
},
  "geometry": {"coordinates":[71.82439000000002,32.74536],"type":"Point"}
}