{
  "type": "Feature",
  "properties": {
    "gn:admin1_code":"3",
    "gn:asciiname":"Sperai",
    "gn:country_code":"PK",
    "gn:dem":1931,
    "gn:feature_class":"P",
    "gn:feature_code":"PPL",
    "gn:name":"Sperai",
    "gn:population":0,
    "gn:timezone":"Asia/Karachi",
    "iso:country":"PK",
    "wof:name":"Sperai",
    "wof:placetype":"locality"
},
  "geometry": {"coordinates":[72.26554,34.99936],"type":"Point"}
}