{
  "type": "Feature",
  "properties": {
    "gn:admin1_code":"3.0",
    "gn:asciiname":"Inzargoi Banda",
    "gn:country_code":"PK",
    "gn:dem":439,
    "gn:feature_class":"P",
    "gn:feature_code":"PPL",
    "gn:name":"Inzargoi Banda",
    "gn:population":0,
    "gn:timezone":"Asia/Karachi",
    "iso:country":"PK",
    "name:und_x_variant":[
        "Matta"
    ],
    "wof:name":"Inzargoi Banda",
    "wof:placetype":"locality"
},
  "geometry": {"coordinates":[72.11044,34.4126],"type":"Point"}
}