{
  "type": "Feature",
  "properties": {
    "gn:admin1_code":"5.0",
    "gn:asciiname":"Goth Haji Iso Khaskheli",
    "gn:country_code":"PK",
    "gn:dem":30,
    "gn:feature_class":"P",
    "gn:feature_code":"PPL",
    "gn:name":"Goth Haji Iso Khaskheli",
    "gn:population":0,
    "gn:timezone":"Asia/Karachi",
    "iso:country":"PK",
    "wof:name":"Goth Haji Iso Khaskheli",
    "wof:placetype":"locality"
},
  "geometry": {"coordinates":[68.43137,25.94401],"type":"Point"}
}