{
  "type": "Feature",
  "properties": {
    "gn:admin1_code":"4.0",
    "gn:asciiname":"Mohra Kanial",
    "gn:country_code":"PK",
    "gn:dem":540,
    "gn:feature_class":"P",
    "gn:feature_code":"PPL",
    "gn:name":"Mohra Kanial",
    "gn:population":0,
    "gn:timezone":"Asia/Karachi",
    "iso:country":"PK",
    "wof:name":"Mohra Kanial",
    "wof:placetype":"locality"
},
  "geometry": {"coordinates":[73.18686,33.26762],"type":"Point"}
}