{
  "type": "Feature",
  "properties": {
    "gn:admin1_code":"1.0",
    "gn:asciiname":"Lerflowzoo",
    "gn:country_code":"PK",
    "gn:dem":986,
    "gn:feature_class":"P",
    "gn:feature_code":"PPL",
    "gn:name":"Lerflowzoo",
    "gn:population":0,
    "gn:timezone":"Asia/Karachi",
    "iso:country":"PK",
    "wof:name":"Lerflowzoo",
    "wof:placetype":"locality"
},
  "geometry": {"coordinates":[71.41996,34.7838],"type":"Point"}
}