{
  "type": "Feature",
  "properties": {
    "gn:admin1_code":"4",
    "gn:asciiname":"Chak Seventy-two -Fifteen Left",
    "gn:country_code":"PK",
    "gn:dem":130,
    "gn:feature_class":"P",
    "gn:feature_code":"PPL",
    "gn:name":"Chak Seventy-two -Fifteen Left",
    "gn:population":0,
    "gn:timezone":"Asia/Karachi",
    "iso:country":"PK",
    "name:und_x_variant":[
        "Chak Seventy-two-Fifteen L"
    ],
    "wof:name":"Chak Seventy-two -Fifteen Left",
    "wof:placetype":"locality"
},
  "geometry": {"coordinates":[72.14624999999999,30.12953],"type":"Point"}
}