{
  "type": "Feature",
  "properties": {
    "gn:admin1_code":"01",
    "gn:asciiname":"Talpaka",
    "gn:country_code":"PK",
    "gn:dem":2104,
    "gn:feature_class":"P",
    "gn:feature_code":"PPL",
    "gn:name":"Talpaka",
    "gn:population":0,
    "gn:timezone":"Asia/Karachi",
    "iso:country":"PK",
    "wof:name":"Talpaka",
    "wof:placetype":"locality"
},
  "geometry": {"coordinates":[70.52906999999998,33.71173],"type":"Point"}
}