{
  "type": "Feature",
  "properties": {
    "gn:admin1_code":"5",
    "gn:asciiname":"Bodlo Bahan",
    "gn:country_code":"PK",
    "gn:dem":40,
    "gn:feature_class":"P",
    "gn:feature_code":"PPL",
    "gn:name":"Bodlo Bahan",
    "gn:population":0,
    "gn:timezone":"Asia/Karachi",
    "iso:country":"PK",
    "name:und_x_variant":[
        "Bod L\u0101bran",
        "Bodlo Baham",
        "Bodlo Bahan"
    ],
    "wof:name":"Bodlo Bahan",
    "wof:placetype":"locality"
},
  "geometry": {"coordinates":[68.07576999999999,26.68546],"type":"Point"}
}