{
  "type": "Feature",
  "properties": {
    "gn:admin1_code":"4.0",
    "gn:asciiname":"Chak Three Hundred Thirteen Western Bar",
    "gn:country_code":"PK",
    "gn:dem":126,
    "gn:feature_class":"P",
    "gn:feature_code":"PPL",
    "gn:name":"Chak Three Hundred Thirteen Western Bar",
    "gn:population":0,
    "gn:timezone":"Asia/Karachi",
    "iso:country":"PK",
    "name:eng_x_preferred":[
        "Chak Three Hundred Thrity-three WB"
    ],
    "wof:name":"Chak Three Hundred Thirteen Western Bar",
    "wof:placetype":"locality"
},
  "geometry": {"coordinates":[71.80925000000001,29.8425],"type":"Point"}
}