{
  "type": "Feature",
  "properties": {
    "gn:admin1_code":"4.0",
    "gn:asciiname":"Nangle Sotkan",
    "gn:country_code":"PK",
    "gn:dem":260,
    "gn:feature_class":"P",
    "gn:feature_code":"PPL",
    "gn:name":"Nangle Sotkan",
    "gn:population":0,
    "gn:timezone":"Asia/Karachi",
    "iso:country":"PK",
    "name:und_x_variant":[
        "Nanga"
    ],
    "wof:name":"Nangle Sotkan",
    "wof:placetype":"locality"
},
  "geometry": {"coordinates":[74.83694,32.32177],"type":"Point"}
}