{
  "type": "Feature",
  "properties": {
    "gn:admin1_code":"2.0",
    "gn:asciiname":"Ibrahim Bazar",
    "gn:country_code":"PK",
    "gn:dem":630,
    "gn:feature_class":"P",
    "gn:feature_code":"PPL",
    "gn:name":"Ibrahim Bazar",
    "gn:population":0,
    "gn:timezone":"Asia/Karachi",
    "iso:country":"PK",
    "wof:name":"Ibrahim Bazar",
    "wof:placetype":"locality"
},
  "geometry": {"coordinates":[64.07174000000001,26.1851],"type":"Point"}
}