{
  "type": "Feature",
  "properties": {
    "gn:admin1_code":"4.0",
    "gn:asciiname":"Fatui Chak",
    "gn:country_code":"PK",
    "gn:dem":249,
    "gn:feature_class":"P",
    "gn:feature_code":"PPL",
    "gn:name":"Fatui Chak",
    "gn:population":0,
    "gn:timezone":"Asia/Karachi",
    "iso:country":"PK",
    "name:und_x_variant":[
        "Fat\u016bhi Chak"
    ],
    "wof:name":"Fatui Chak",
    "wof:placetype":"locality"
},
  "geometry": {"coordinates":[75.163,32.12675],"type":"Point"}
}