{
  "type": "Feature",
  "properties": {
    "gn:admin1_code":"3",
    "gn:asciiname":"Anangurai",
    "gn:country_code":"PK",
    "gn:dem":958,
    "gn:feature_class":"P",
    "gn:feature_code":"PPL",
    "gn:name":"Anangurai",
    "gn:population":0,
    "gn:timezone":"Asia/Karachi",
    "iso:country":"PK",
    "name:eng_x_preferred":[
        "Anangurai"
    ],
    "wof:name":"Anangurai",
    "wof:placetype":"locality"
},
  "geometry": {"coordinates":[72.14875000000001,34.7317],"type":"Point"}
}