{
  "type": "Feature",
  "properties": {
    "gn:admin1_code":"3.0",
    "gn:asciiname":"Bar Sarai",
    "gn:country_code":"PK",
    "gn:dem":2632,
    "gn:feature_class":"P",
    "gn:feature_code":"PPL",
    "gn:name":"Bar Sarai",
    "gn:population":0,
    "gn:timezone":"Asia/Karachi",
    "iso:country":"PK",
    "name:eng_x_preferred":[
        "Barsarai"
    ],
    "wof:name":"Bar Sarai",
    "wof:placetype":"locality"
},
  "geometry": {"coordinates":[72.32141,35.44264000000001],"type":"Point"}
}