{
  "type": "Feature",
  "properties": {
    "gn:admin1_code":"3.0",
    "gn:asciiname":"Shelkho",
    "gn:country_code":"PK",
    "gn:dem":3348,
    "gn:feature_class":"P",
    "gn:feature_code":"PPL",
    "gn:name":"Shelkho",
    "gn:population":0,
    "gn:timezone":"Asia/Karachi",
    "iso:country":"PK",
    "wof:name":"Shelkho",
    "wof:placetype":"locality"
},
  "geometry": {"coordinates":[72.70619000000001,35.15954],"type":"Point"}
}