{
  "type": "Feature",
  "properties": {
    "gn:admin1_code":"4.0",
    "gn:asciiname":"Bakahal Jattan",
    "gn:country_code":"PK",
    "gn:dem":292,
    "gn:feature_class":"P",
    "gn:feature_code":"PPL",
    "gn:name":"Bakahal Jattan",
    "gn:population":0,
    "gn:timezone":"Asia/Karachi",
    "iso:country":"PK",
    "wof:name":"Bakahal Jattan",
    "wof:placetype":"locality"
},
  "geometry": {"coordinates":[73.90895,32.96566],"type":"Point"}
}