{
  "type": "Feature",
  "properties": {
    "gn:admin1_code":"1.0",
    "gn:asciiname":"China",
    "gn:country_code":"PK",
    "gn:dem":2037,
    "gn:feature_class":"P",
    "gn:feature_code":"PPL",
    "gn:name":"China",
    "gn:population":0,
    "gn:timezone":"Asia/Karachi",
    "iso:country":"PK",
    "wof:name":"China",
    "wof:placetype":"locality"
},
  "geometry": {"coordinates":[69.59305999999999,32.49],"type":"Point"}
}