{
  "type": "Feature",
  "properties": {
    "gn:admin1_code":"1",
    "gn:asciiname":"Tangarai",
    "gn:country_code":"PK",
    "gn:dem":1698,
    "gn:feature_class":"P",
    "gn:feature_code":"PPL",
    "gn:name":"Tangarai",
    "gn:population":0,
    "gn:timezone":"Asia/Karachi",
    "iso:country":"PK",
    "wof:name":"Tangarai",
    "wof:placetype":"locality"
},
  "geometry": {"coordinates":[69.82514999999999,32.55315],"type":"Point"}
}