{
  "type": "Feature",
  "properties": {
    "gn:admin1_code":"5.0",
    "gn:asciiname":"Pabuhar",
    "gn:country_code":"PK",
    "gn:dem":34,
    "gn:feature_class":"P",
    "gn:feature_code":"PPL",
    "gn:name":"Pabuhar",
    "gn:population":0,
    "gn:timezone":"Asia/Karachi",
    "iso:country":"PK",
    "name:und_x_variant":[
        "Pabohar"
    ],
    "wof:name":"Pabuhar",
    "wof:placetype":"locality"
},
  "geometry": {"coordinates":[69.85384999999999,24.29417],"type":"Point"}
}