{
  "type": "Feature",
  "properties": {
    "gn:admin1_code":"2.0",
    "gn:asciiname":"Kili Barfi Khan",
    "gn:country_code":"PK",
    "gn:dem":1183,
    "gn:feature_class":"P",
    "gn:feature_code":"PPL",
    "gn:name":"Kili Barfi Khan",
    "gn:population":0,
    "gn:timezone":"Asia/Karachi",
    "iso:country":"PK",
    "wof:name":"Kili Barfi Khan",
    "wof:placetype":"locality"
},
  "geometry": {"coordinates":[66.01059000000001,29.31927],"type":"Point"}
}