{
  "type": "Feature",
  "properties": {
    "gn:admin1_code":"4",
    "gn:asciiname":"Kandhiwala",
    "gn:country_code":"PK",
    "gn:dem":126,
    "gn:feature_class":"P",
    "gn:feature_code":"PPL",
    "gn:name":"Kandhiwala",
    "gn:population":0,
    "gn:timezone":"Asia/Karachi",
    "iso:country":"PK",
    "name:und_x_variant":[
        "Kandh\u012bw\u0101la Khu",
        "Kandhiwala"
    ],
    "wof:name":"Kandhiwala",
    "wof:placetype":"locality"
},
  "geometry": {"coordinates":[71.73824,29.94135],"type":"Point"}
}