{
  "type": "Feature",
  "properties": {
    "gn:admin1_code":"4",
    "gn:asciiname":"Maswan da Khu",
    "gn:country_code":"PK",
    "gn:dem":127,
    "gn:feature_class":"P",
    "gn:feature_code":"PPL",
    "gn:name":"Maswan da Khu",
    "gn:population":0,
    "gn:timezone":"Asia/Karachi",
    "iso:country":"PK",
    "name:und_x_variant":[
        "Wah\u0101nw\u0101la"
    ],
    "wof:name":"Maswan da Khu",
    "wof:placetype":"locality"
},
  "geometry": {"coordinates":[71.94893,29.99189],"type":"Point"}
}