{
  "type": "Feature",
  "properties": {
    "gn:admin1_code":"3",
    "gn:asciiname":"Shako",
    "gn:country_code":"PK",
    "gn:dem":2158,
    "gn:feature_class":"P",
    "gn:feature_code":"PPL",
    "gn:name":"Shako",
    "gn:population":0,
    "gn:timezone":"Asia/Karachi",
    "iso:country":"PK",
    "wof:name":"Shako",
    "wof:placetype":"locality"
},
  "geometry": {"coordinates":[72.69803,34.80827],"type":"Point"}
}