{
  "type": "Feature",
  "properties": {
    "gn:admin1_code":"3",
    "gn:asciiname":"Shako",
    "gn:country_code":"PK",
    "gn:dem":2158,
    "gn:feature_class":"P",
    "gn:feature_code":"PPL",
    "gn:name":"Shako",
    "gn:population":0,
    "gn:timezone":"Asia/Karachi",
    "iso:country":"PK",
    "name:cat_x_preferred":[
        "Xac\u00f3"
    ],
    "name:cym_x_preferred":[
        "Siaco"
    ],
    "name:deu_x_preferred":[
        "Tschako"
    ],
    "name:epo_x_preferred":[
        "\u0108ako"
    ],
    "name:fra_x_preferred":[
        "Shako"
    ],
    "name:ido_x_preferred":[
        "Chako"
    ],
    "name:ita_x_preferred":[
        "Sciacc\u00f2"
    ],
    "name:jpn_x_preferred":[
        "\u30b7\u30e3\u30b3\u30fc\u5e3d"
    ],
    "name:ksh_x_preferred":[
        "Kuletschhoot"
    ],
    "name:lit_x_preferred":[
        "Kiveris"
    ],
    "name:nld_x_preferred":[
        "Tschako"
    ],
    "name:nor_x_preferred":[
        "Sjako"
    ],
    "name:pol_x_preferred":[
        "Czako"
    ],
    "name:rus_x_preferred":[
        "\u041a\u0438\u0432\u0435\u0440"
    ],
    "name:slv_x_preferred":[
        "\u010caka"
    ],
    "name:spa_x_preferred":[
        "Chac\u00f3"
    ],
    "name:swe_x_preferred":[
        "Tschak\u00e5"
    ],
    "name:ukr_x_preferred":[
        "\u041a\u0456\u0432\u0435\u0440"
    ],
    "wof:name":"Shako",
    "wof:placetype":"locality"
},
  "geometry": {"coordinates":[72.69803,34.80827],"type":"Point"}
}