{
  "type": "Feature",
  "properties": {
    "gn:admin1_code":"2.0",
    "gn:asciiname":"Sra Sakai",
    "gn:country_code":"PK",
    "gn:dem":2235,
    "gn:feature_class":"P",
    "gn:feature_code":"PPL",
    "gn:name":"Sra Sakai",
    "gn:population":0,
    "gn:timezone":"Asia/Karachi",
    "iso:country":"PK",
    "wof:name":"Sra Sakai",
    "wof:placetype":"locality"
},
  "geometry": {"coordinates":[68.53544000000001,31.17128],"type":"Point"}
}