{
  "type": "Feature",
  "properties": {
    "gn:admin1_code":"4.0",
    "gn:asciiname":"Fateh Khan",
    "gn:country_code":"PK",
    "gn:dem":154,
    "gn:feature_class":"P",
    "gn:feature_code":"PPL",
    "gn:name":"Fateh Khan",
    "gn:population":0,
    "gn:timezone":"Asia/Karachi",
    "iso:country":"PK",
    "name:fas_x_preferred":[
        "\u0641\u0627\u062a\u062d\u200c\u062e\u0627\u0646"
    ],
    "name:hin_x_preferred":[
        "\u092b\u093c\u0924\u0939 \u0916\u093e\u0928"
    ],
    "name:und_x_variant":[
        "Dera Fateh Kh\u0101n",
        "Fateh Khan"
    ],
    "name:urd_x_preferred":[
        "\u0641\u0627\u062a\u062d \u062e\u0627\u0646"
    ],
    "wof:name":"Fateh Khan",
    "wof:placetype":"locality"
},
  "geometry": {"coordinates":[70.71880999999998,31.05867000000001],"type":"Point"}
}