{
  "type": "Feature",
  "properties": {
    "gn:admin1_code":"4.0",
    "gn:asciiname":"Fateh Khan",
    "gn:country_code":"PK",
    "gn:dem":154,
    "gn:feature_class":"P",
    "gn:feature_code":"PPL",
    "gn:name":"Fateh Khan",
    "gn:population":0,
    "gn:timezone":"Asia/Karachi",
    "iso:country":"PK",
    "name:und_x_variant":[
        "Dera Fateh Kh\u0101n",
        "Fateh Khan"
    ],
    "wof:name":"Fateh Khan",
    "wof:placetype":"locality"
},
  "geometry": {"coordinates":[70.71880999999998,31.05867000000001],"type":"Point"}
}