{
  "type": "Feature",
  "properties": {
    "gn:admin1_code":"3.0",
    "gn:asciiname":"Gujar Banda",
    "gn:country_code":"PK",
    "gn:dem":2396,
    "gn:feature_class":"P",
    "gn:feature_code":"PPL",
    "gn:name":"Gujar Banda",
    "gn:population":0,
    "gn:timezone":"Asia/Karachi",
    "iso:country":"PK",
    "wof:name":"Gujar Banda",
    "wof:placetype":"locality"
},
  "geometry": {"coordinates":[72.2149,35.18792],"type":"Point"}
}