{
  "type": "Feature",
  "properties": {
    "gn:admin1_code":"1.0",
    "gn:asciiname":"Thawa",
    "gn:country_code":"PK",
    "gn:dem":566,
    "gn:feature_class":"P",
    "gn:feature_code":"PPL",
    "gn:name":"Thawa",
    "gn:population":0,
    "gn:timezone":"Asia/Karachi",
    "iso:country":"PK",
    "name:und_x_variant":[
        "Th\u0101ra"
    ],
    "wof:name":"Thawa",
    "wof:placetype":"locality"
},
  "geometry": {"coordinates":[73.66656999999999,33.3992],"type":"Point"}
}