{
  "type": "Feature",
  "properties": {
    "gn:admin1_code":"5.0",
    "gn:asciiname":"Karim Bakhsh Chandio",
    "gn:country_code":"PK",
    "gn:dem":14,
    "gn:feature_class":"P",
    "gn:feature_code":"PPL",
    "gn:name":"Karim Bakhsh Chandio",
    "gn:population":0,
    "gn:timezone":"Asia/Karachi",
    "iso:country":"PK",
    "wof:name":"Karim Bakhsh Chandio",
    "wof:placetype":"locality"
},
  "geometry": {"coordinates":[68.63434000000001,24.84749],"type":"Point"}
}