{
  "type": "Feature",
  "properties": {
    "gn:admin1_code":"4.0",
    "gn:asciiname":"Chak Four Hundred Thirty-eight - One Left",
    "gn:country_code":"PK",
    "gn:dem":147,
    "gn:feature_class":"P",
    "gn:feature_code":"PPL",
    "gn:name":"Chak Four Hundred Thirty-eight - One Left",
    "gn:population":0,
    "gn:timezone":"Asia/Karachi",
    "iso:country":"PK",
    "wof:name":"Chak Four Hundred Thirty-eight - One Left",
    "wof:placetype":"locality"
},
  "geometry": {"coordinates":[72.7786,29.38577],"type":"Point"}
}