{
  "type": "Feature",
  "properties": {
    "gn:admin1_code":"01",
    "gn:asciiname":"Arkan",
    "gn:country_code":"PK",
    "gn:dem":995,
    "gn:feature_class":"P",
    "gn:feature_code":"PPL",
    "gn:name":"Arkan",
    "gn:population":0,
    "gn:timezone":"Asia/Karachi",
    "iso:country":"PK",
    "name:ara_x_preferred":[
        "\u0632\u064a\u0644\u0643\u0648 \u0631\u0627\u0632\u0646\u0627\u062a\u0648\u0641\u064a\u062a\u0634"
    ],
    "name:aze_x_preferred":[
        "Jelko Raznatovi\u00e7"
    ],
    "name:bos_x_preferred":[
        "\u017deljko Ra\u017enatovi\u0107"
    ],
    "name:bul_x_preferred":[
        "\u0416\u0435\u043b\u043a\u043e \u0420\u0430\u0436\u043d\u0430\u0442\u043e\u0432\u0438\u0447"
    ],
    "name:cat_x_preferred":[
        "Arkan"
    ],
    "name:ces_x_preferred":[
        "\u017deljko Ra\u017enatovi\u0107"
    ],
    "name:dan_x_preferred":[
        "\u017deljko Ra\u017enatovi\u0107"
    ],
    "name:deu_x_preferred":[
        "\u017deljko Ra\u017enatovi\u0107"
    ],
    "name:ell_x_preferred":[
        "\u0391\u03c1\u03ba\u03ac\u03bd"
    ],
    "name:eng_x_preferred":[
        "Arkanai"
    ],
    "name:eus_x_preferred":[
        "\u017deljko Ra\u017enatovi\u0107"
    ],
    "name:fas_x_preferred":[
        "\u0622\u0631\u06a9\u0627\u0646"
    ],
    "name:fin_x_preferred":[
        "\u017deljko Ra\u017enatovi\u0107"
    ],
    "name:fra_x_preferred":[
        "\u017deljko Ra\u017enatovi\u0107"
    ],
    "name:heb_x_preferred":[
        "\u05d6'\u05dc\u05e7\u05d5 \u05e8\u05d6\u05e0\u05d8\u05d5\u05d1\u05d9\u05e5'"
    ],
    "name:hrv_x_preferred":[
        "\u017deljko Ra\u017enatovi\u0107"
    ],
    "name:hun_x_preferred":[
        "\u017deljko Ra\u017enatovi\u0107"
    ],
    "name:ita_x_preferred":[
        "\u017deljko Ra\u017enatovi\u0107"
    ],
    "name:jpn_x_preferred":[
        "\u30b8\u30a7\u30ea\u30b3\u30fb\u30e9\u30b8\u30e5\u30ca\u30c8\u30f4\u30a3\u30c3\u30c1"
    ],
    "name:mkd_x_preferred":[
        "\u0416\u0435\u0459\u043a\u043e \u0420\u0430\u0436\u043d\u0430\u0442\u043e\u0432\u0438\u045c"
    ],
    "name:nld_x_preferred":[
        "\u017deljko Ra\u017enatovi\u0107"
    ],
    "name:nor_x_preferred":[
        "\u017deljko Ra\u017enatovi\u0107"
    ],
    "name:pol_x_preferred":[
        "\u017deljko Ra\u017enatovi\u0107"
    ],
    "name:por_x_preferred":[
        "\u017deljko Ra\u017enatovi\u0107"
    ],
    "name:ron_x_preferred":[
        "Arkan"
    ],
    "name:rus_x_preferred":[
        "\u0420\u0430\u0436\u043d\u0430\u0442\u043e\u0432\u0438\u0447"
    ],
    "name:slv_x_preferred":[
        "\u017deljko Ra\u017enatovi\u0107"
    ],
    "name:spa_x_preferred":[
        "\u017deljko Ra\u017enatovi\u0107"
    ],
    "name:sqi_x_preferred":[
        "Arkani"
    ],
    "name:swe_x_preferred":[
        "\u017deljko Ra\u017enatovi\u0107"
    ],
    "name:tur_x_preferred":[
        "\u017deljko Ra\u017enatovi\u0107"
    ],
    "name:ukr_x_preferred":[
        "\u0416\u0435\u043b\u044c\u043a\u043e \u0420\u0430\u0436\u043d\u0430\u0442\u043e\u0432\u0438\u0447"
    ],
    "name:zho_x_preferred":[
        "\u5091\u5229\u79d1\u00b7\u62c9\u8332\u5c3c\u4e9e\u6258\u7dad\u5947"
    ],
    "wof:name":"Arkan",
    "wof:placetype":"locality"
},
  "geometry": {"coordinates":[71.52705999999998,34.88368],"type":"Point"}
}