{
  "type": "Feature",
  "properties": {
    "gn:admin1_code":"01",
    "gn:asciiname":"Arkan",
    "gn:country_code":"PK",
    "gn:dem":995,
    "gn:feature_class":"P",
    "gn:feature_code":"PPL",
    "gn:name":"Arkan",
    "gn:population":0,
    "gn:timezone":"Asia/Karachi",
    "iso:country":"PK",
    "name:eng_x_preferred":[
        "Arkanai"
    ],
    "wof:name":"Arkan",
    "wof:placetype":"locality"
},
  "geometry": {"coordinates":[71.52705999999998,34.88368],"type":"Point"}
}