{
  "type": "Feature",
  "properties": {
    "gn:admin1_code":"2.0",
    "gn:asciiname":"Goth Jamal",
    "gn:country_code":"PK",
    "gn:dem":51,
    "gn:feature_class":"P",
    "gn:feature_code":"PPL",
    "gn:name":"Goth Jamal",
    "gn:population":0,
    "gn:timezone":"Asia/Karachi",
    "iso:country":"PK",
    "name:eng_x_preferred":[
        "Goth Jum\u0101l"
    ],
    "wof:name":"Goth Jamal",
    "wof:placetype":"locality"
},
  "geometry": {"coordinates":[66.77748000000001,25.15134],"type":"Point"}
}