{
  "type": "Feature",
  "properties": {
    "gn:admin1_code":"3.0",
    "gn:asciiname":"Sherabad",
    "gn:country_code":"PK",
    "gn:dem":310,
    "gn:feature_class":"P",
    "gn:feature_code":"PPL",
    "gn:name":"Sherabad",
    "gn:population":0,
    "gn:timezone":"Asia/Karachi",
    "iso:country":"PK",
    "name:eng_x_preferred":[
        "Sherabad"
    ],
    "wof:name":"Sherabad",
    "wof:placetype":"locality"
},
  "geometry": {"coordinates":[72.30153,34.02224],"type":"Point"}
}