{
  "type": "Feature",
  "properties": {
    "gn:admin1_code":"5",
    "gn:asciiname":"Haji Laung Chandia",
    "gn:country_code":"PK",
    "gn:dem":32,
    "gn:feature_class":"P",
    "gn:feature_code":"PPL",
    "gn:name":"Haji Laung Chandia",
    "gn:population":0,
    "gn:timezone":"Asia/Karachi",
    "iso:country":"PK",
    "wof:name":"Haji Laung Chandia",
    "wof:placetype":"locality"
},
  "geometry": {"coordinates":[68.20433,26.16086],"type":"Point"}
}