{
  "type": "Feature",
  "properties": {
    "gn:admin1_code":"5.0",
    "gn:asciiname":"Goth Muhammad Wasan",
    "gn:country_code":"PK",
    "gn:dem":54,
    "gn:feature_class":"P",
    "gn:feature_code":"PPL",
    "gn:name":"Goth Muhammad Wasan",
    "gn:population":0,
    "gn:timezone":"Asia/Karachi",
    "iso:country":"PK",
    "name:und_x_variant":[
        "Muhammad Was\u0101n"
    ],
    "wof:name":"Goth Muhammad Wasan",
    "wof:placetype":"locality"
},
  "geometry": {"coordinates":[68.66269,27.34601],"type":"Point"}
}