{
  "type": "Feature",
  "properties": {
    "gn:admin1_code":"3.0",
    "gn:asciiname":"Tut Kalle",
    "gn:country_code":"PK",
    "gn:dem":319,
    "gn:feature_class":"P",
    "gn:feature_code":"PPL",
    "gn:name":"Tut Kalle",
    "gn:population":0,
    "gn:timezone":"Asia/Karachi",
    "iso:country":"PK",
    "name:eng_x_preferred":[
        "T\u016bt Kili"
    ],
    "wof:name":"Tut Kalle",
    "wof:placetype":"locality"
},
  "geometry": {"coordinates":[71.83924,34.19968],"type":"Point"}
}