{
  "type": "Feature",
  "properties": {
    "gn:admin1_code":"1.0",
    "gn:asciiname":"Darazinda",
    "gn:country_code":"PK",
    "gn:dem":642,
    "gn:feature_class":"P",
    "gn:feature_code":"PPL",
    "gn:name":"Darazinda",
    "gn:population":0,
    "gn:timezone":"Asia/Karachi",
    "iso:country":"PK",
    "name:und_x_variant":[
        "Gazak"
    ],
    "wof:name":"Darazinda",
    "wof:placetype":"locality"
},
  "geometry": {"coordinates":[70.50369000000001,33.24567],"type":"Point"}
}