{
  "type": "Feature",
  "properties": {
    "gn:admin1_code":"4.0",
    "gn:asciiname":"Dhung",
    "gn:country_code":"PK",
    "gn:dem":510,
    "gn:feature_class":"P",
    "gn:feature_code":"PPL",
    "gn:name":"Dhung",
    "gn:population":0,
    "gn:timezone":"Asia/Karachi",
    "iso:country":"PK",
    "name:und_x_variant":[
        "Dhaung",
        "Dh\u016bng",
        "Dhung"
    ],
    "wof:name":"Dhung",
    "wof:placetype":"locality"
},
  "geometry": {"coordinates":[73.11936,33.10615],"type":"Point"}
}