{
  "type": "Feature",
  "properties": {
    "gn:admin1_code":"3.0",
    "gn:asciiname":"Prince Qala",
    "gn:country_code":"PK",
    "gn:dem":321,
    "gn:feature_class":"P",
    "gn:feature_code":"PPL",
    "gn:name":"Prince Qala",
    "gn:population":0,
    "gn:timezone":"Asia/Karachi",
    "iso:country":"PK",
    "wof:name":"Prince Qala",
    "wof:placetype":"locality"
},
  "geometry": {"coordinates":[71.53844000000002,34.16278],"type":"Point"}
}