{
  "type": "Feature",
  "properties": {
    "gn:admin1_code":"5",
    "gn:asciiname":"Goth Hakim Shah Saiyid",
    "gn:country_code":"PK",
    "gn:dem":10,
    "gn:feature_class":"P",
    "gn:feature_code":"PPL",
    "gn:name":"Goth Hakim Shah Saiyid",
    "gn:population":0,
    "gn:timezone":"Asia/Karachi",
    "iso:country":"PK",
    "wof:name":"Goth Hakim Shah Saiyid",
    "wof:placetype":"locality"
},
  "geometry": {"coordinates":[69.63726,25.18166],"type":"Point"}
}