{
  "type": "Feature",
  "properties": {
    "gn:admin1_code":"1.0",
    "gn:asciiname":"Khuramai Kili",
    "gn:country_code":"PK",
    "gn:dem":1184,
    "gn:feature_class":"P",
    "gn:feature_code":"PPL",
    "gn:name":"Khuramai Kili",
    "gn:population":0,
    "gn:timezone":"Asia/Karachi",
    "iso:country":"PK",
    "name:und_x_variant":[
        "Khurami"
    ],
    "wof:name":"Khuramai Kili",
    "wof:placetype":"locality"
},
  "geometry": {"coordinates":[70.99561,33.91951],"type":"Point"}
}