{
  "type": "Feature",
  "properties": {
    "gn:admin1_code":"4.0",
    "gn:asciiname":"Khaur",
    "gn:country_code":"PK",
    "gn:dem":597,
    "gn:feature_class":"P",
    "gn:feature_code":"PPL",
    "gn:name":"Khaur",
    "gn:population":0,
    "gn:timezone":"Asia/Karachi",
    "iso:country":"PK",
    "wof:name":"Khaur",
    "wof:placetype":"locality"
},
  "geometry": {"coordinates":[72.24200999999999,32.71411],"type":"Point"}
}