{
  "type": "Feature",
  "properties": {
    "gn:admin1_code":"5",
    "gn:asciiname":"Fateh Khan Jat",
    "gn:country_code":"PK",
    "gn:dem":6,
    "gn:feature_class":"P",
    "gn:feature_code":"PPL",
    "gn:name":"Fateh Kh\u0101n Jat",
    "gn:population":0,
    "gn:timezone":"Asia/Karachi",
    "iso:country":"PK",
    "wof:name":"Fateh Khan Jat",
    "wof:placetype":"locality"
},
  "geometry": {"coordinates":[69.27221999999999,24.79167],"type":"Point"}
}