{
  "type": "Feature",
  "properties": {
    "gn:admin1_code":"3.0",
    "gn:asciiname":"Suwai",
    "gn:country_code":"PK",
    "gn:dem":1228,
    "gn:feature_class":"P",
    "gn:feature_code":"PPL",
    "gn:name":"Suwai",
    "gn:population":0,
    "gn:timezone":"Asia/Karachi",
    "iso:country":"PK",
    "wof:name":"Suwai",
    "wof:placetype":"locality"
},
  "geometry": {"coordinates":[72.83917,34.53923],"type":"Point"}
}