{
  "type": "Feature",
  "properties": {
    "gn:admin1_code":"3.0",
    "gn:asciiname":"Patrami",
    "gn:country_code":"PK",
    "gn:dem":3101,
    "gn:feature_class":"P",
    "gn:feature_code":"PPL",
    "gn:name":"Patrami",
    "gn:population":0,
    "gn:timezone":"Asia/Karachi",
    "iso:country":"PK",
    "wof:name":"Patrami",
    "wof:placetype":"locality"
},
  "geometry": {"coordinates":[72.20491,36.37049],"type":"Point"}
}