{
  "type": "Feature",
  "properties": {
    "gn:admin1_code":"5",
    "gn:asciiname":"Dulawala Goth",
    "gn:country_code":"PK",
    "gn:dem":68,
    "gn:feature_class":"P",
    "gn:feature_code":"PPL",
    "gn:name":"Dulawala Goth",
    "gn:population":0,
    "gn:timezone":"Asia/Karachi",
    "iso:country":"PK",
    "name:und_x_variant":[
        "Dullew\u0101ri Goth"
    ],
    "wof:name":"Dulawala Goth",
    "wof:placetype":"locality"
},
  "geometry": {"coordinates":[69.78341,27.67723],"type":"Point"}
}