{
  "type": "Feature",
  "properties": {
    "gn:admin1_code":"3.0",
    "gn:asciiname":"Kotka Mulagan",
    "gn:country_code":"PK",
    "gn:dem":321,
    "gn:feature_class":"P",
    "gn:feature_code":"PPL",
    "gn:name":"Kotka Mulagan",
    "gn:population":0,
    "gn:timezone":"Asia/Karachi",
    "iso:country":"PK",
    "wof:name":"Kotka Mulagan",
    "wof:placetype":"locality"
},
  "geometry": {"coordinates":[70.59828,32.73463],"type":"Point"}
}