{
  "type": "Feature",
  "properties": {
    "gn:admin1_code":"7.0",
    "gn:asciiname":"Sterika",
    "gn:country_code":"PK",
    "gn:dem":2483,
    "gn:feature_class":"P",
    "gn:feature_code":"PPL",
    "gn:name":"Sterika",
    "gn:population":0,
    "gn:timezone":"Asia/Karachi",
    "iso:country":"PK",
    "wof:name":"Sterika",
    "wof:placetype":"locality"
},
  "geometry": {"coordinates":[75.09795,35.58778],"type":"Point"}
}