{
  "type": "Feature",
  "properties": {
    "gn:admin1_code":"7.0",
    "gn:asciiname":"Trupa",
    "gn:country_code":"PK",
    "gn:dem":2289,
    "gn:feature_class":"P",
    "gn:feature_code":"PPL",
    "gn:name":"Trupa",
    "gn:population":0,
    "gn:timezone":"Asia/Karachi",
    "iso:country":"PK",
    "wof:name":"Trupa",
    "wof:placetype":"locality"
},
  "geometry": {"coordinates":[75.68665,35.49423],"type":"Point"}
}