{
  "type": "Feature",
  "properties": {
    "gn:admin1_code":"02",
    "gn:asciiname":"Shindi",
    "gn:country_code":"PK",
    "gn:dem":513,
    "gn:feature_class":"P",
    "gn:feature_code":"PPL",
    "gn:name":"Shindi",
    "gn:population":0,
    "gn:timezone":"Asia/Karachi",
    "iso:country":"PK",
    "wof:name":"Shindi",
    "wof:placetype":"locality"
},
  "geometry": {"coordinates":[65.68124,26.63903],"type":"Point"}
}