{
  "type": "Feature",
  "properties": {
    "gn:admin1_code":"4.0",
    "gn:asciiname":"Jafar Colony",
    "gn:country_code":"PK",
    "gn:dem":87,
    "gn:feature_class":"P",
    "gn:feature_code":"PPL",
    "gn:name":"Jafar Colony",
    "gn:population":0,
    "gn:timezone":"Asia/Karachi",
    "iso:country":"PK",
    "name:und_x_variant":[
        "Jafari Colony"
    ],
    "wof:name":"Jafar Colony",
    "wof:placetype":"locality"
},
  "geometry": {"coordinates":[70.43724,28.71409],"type":"Point"}
}