{
  "type": "Feature",
  "properties": {
    "gn:admin1_code":"4.0",
    "gn:asciiname":"Uger",
    "gn:country_code":"PK",
    "gn:dem":1094,
    "gn:feature_class":"P",
    "gn:feature_code":"PPL",
    "gn:name":"Uger",
    "gn:population":0,
    "gn:timezone":"Asia/Karachi",
    "iso:country":"PK",
    "wof:name":"Uger",
    "wof:placetype":"locality"
},
  "geometry": {"coordinates":[70.11126,30.42447],"type":"Point"}
}