{
  "type": "Feature",
  "properties": {
    "gn:admin1_code":"4",
    "gn:asciiname":"Bakhsh Sadwani",
    "gn:country_code":"PK",
    "gn:dem":79,
    "gn:feature_class":"P",
    "gn:feature_code":"PPL",
    "gn:name":"Bakhsh Sadwani",
    "gn:population":0,
    "gn:timezone":"Asia/Karachi",
    "iso:country":"PK",
    "name:und_x_variant":[
        "Rah\u012bm Bakhsh Sadw\u0101n"
    ],
    "wof:name":"Bakhsh Sadwani",
    "wof:placetype":"locality"
},
  "geometry": {"coordinates":[69.81755,28.45537],"type":"Point"}
}