{
  "type": "Feature",
  "properties": {
    "gn:admin1_code":"5",
    "gn:asciiname":"Goth Chaudhri Mustafa",
    "gn:country_code":"PK",
    "gn:dem":8,
    "gn:feature_class":"P",
    "gn:feature_code":"PPL",
    "gn:name":"Goth Chaudhri Mustafa",
    "gn:population":0,
    "gn:timezone":"Asia/Karachi",
    "iso:country":"PK",
    "wof:name":"Goth Chaudhri Mustafa",
    "wof:placetype":"locality"
},
  "geometry": {"coordinates":[69.39564,24.88963],"type":"Point"}
}