{
  "type": "Feature",
  "properties": {
    "gn:admin1_code":"05",
    "gn:asciiname":"Goth Wazir Chachar",
    "gn:country_code":"PK",
    "gn:dem":64,
    "gn:feature_class":"P",
    "gn:feature_code":"PPL",
    "gn:name":"Goth Wazir Chachar",
    "gn:population":0,
    "gn:timezone":"Asia/Karachi",
    "iso:country":"PK",
    "name:und_x_variant":[
        "Wazir Ch\u0101char",
        "Goth Wazir Chachar"
    ],
    "wof:name":"Goth Wazir Chachar",
    "wof:placetype":"locality"
},
  "geometry": {"coordinates":[69.30915,27.86203],"type":"Point"}
}