{
  "type": "Feature",
  "properties": {
    "gn:admin1_code":"4",
    "gn:asciiname":"Khu Basar",
    "gn:country_code":"PK",
    "gn:dem":141,
    "gn:feature_class":"P",
    "gn:feature_code":"PPL",
    "gn:name":"Khu Basar",
    "gn:population":0,
    "gn:timezone":"Asia/Karachi",
    "iso:country":"PK",
    "name:und_x_variant":[
        "Ch\u0101h Kumh\u0101r\u0101n"
    ],
    "wof:name":"Khu Basar",
    "wof:placetype":"locality"
},
  "geometry": {"coordinates":[72.15586999999999,30.58883],"type":"Point"}
}