{
  "type": "Feature",
  "properties": {
    "gn:admin1_code":"4.0",
    "gn:asciiname":"Dera Nawab",
    "gn:country_code":"PK",
    "gn:dem":182,
    "gn:feature_class":"P",
    "gn:feature_code":"PPL",
    "gn:name":"Dera Nawab",
    "gn:population":0,
    "gn:timezone":"Asia/Karachi",
    "iso:country":"PK",
    "name:und_x_variant":[
        "Dera Naw\u0101b All\u0101h Bakhsh"
    ],
    "wof:name":"Dera Nawab",
    "wof:placetype":"locality"
},
  "geometry": {"coordinates":[72.40716999999999,32.20333],"type":"Point"}
}