{
  "type": "Feature",
  "properties": {
    "gn:admin1_code":"1",
    "gn:asciiname":"Nazarbeg Kili",
    "gn:country_code":"PK",
    "gn:dem":1526,
    "gn:feature_class":"P",
    "gn:feature_code":"PPL",
    "gn:name":"Nazarbeg Kili",
    "gn:population":0,
    "gn:timezone":"Asia/Karachi",
    "iso:country":"PK",
    "name:und_x_variant":[
        "Nazarbeg Khel Kili"
    ],
    "wof:name":"Nazarbeg Kili",
    "wof:placetype":"locality"
},
  "geometry": {"coordinates":[69.86917,33.07282],"type":"Point"}
}