{
  "type": "Feature",
  "properties": {
    "gn:admin1_code":"5.0",
    "gn:asciiname":"Goth Siddiq Barhej",
    "gn:country_code":"PK",
    "gn:dem":5,
    "gn:feature_class":"P",
    "gn:feature_code":"PPL",
    "gn:name":"Goth Siddiq Barhej",
    "gn:population":0,
    "gn:timezone":"Asia/Karachi",
    "iso:country":"PK",
    "wof:name":"Goth Siddiq Barhej",
    "wof:placetype":"locality"
},
  "geometry": {"coordinates":[67.53316,24.15768],"type":"Point"}
}