{
  "type": "Feature",
  "properties": {
    "gn:admin1_code":"02",
    "gn:asciiname":"Nau",
    "gn:country_code":"PK",
    "gn:dem":1938,
    "gn:feature_class":"P",
    "gn:feature_code":"PPL",
    "gn:name":"Nau",
    "gn:population":0,
    "gn:timezone":"Asia/Karachi",
    "iso:country":"PK",
    "name:eng_x_preferred":[
        "Nawa"
    ],
    "name:und_x_variant":[
        "Nao",
        "Nau"
    ],
    "wof:name":"Nau",
    "wof:placetype":"locality"
},
  "geometry": {"coordinates":[67.30764000000001,30.77677000000001],"type":"Point"}
}