{
  "type": "Feature",
  "properties": {
    "gn:admin1_code":"01",
    "gn:asciiname":"Sharki",
    "gn:country_code":"PK",
    "gn:dem":1406,
    "gn:feature_class":"P",
    "gn:feature_code":"PPL",
    "gn:name":"Sharki",
    "gn:population":0,
    "gn:timezone":"Asia/Karachi",
    "iso:country":"PK",
    "name:und_x_variant":[
        "Sharkai"
    ],
    "wof:name":"Sharki",
    "wof:placetype":"locality"
},
  "geometry": {"coordinates":[69.60550000000001,32.89028],"type":"Point"}
}