{
  "type": "Feature",
  "properties": {
    "gn:admin1_code":"4.0",
    "gn:asciiname":"Mohlanwali Bhaini",
    "gn:country_code":"PK",
    "gn:dem":158,
    "gn:feature_class":"P",
    "gn:feature_code":"PPL",
    "gn:name":"Mohlanwali Bhaini",
    "gn:population":0,
    "gn:timezone":"Asia/Karachi",
    "iso:country":"PK",
    "wof:name":"Mohlanwali Bhaini",
    "wof:placetype":"locality"
},
  "geometry": {"coordinates":[73.36405999999999,30.04642],"type":"Point"}
}