{
  "type": "Feature",
  "properties": {
    "gn:admin1_code":"5.0",
    "gn:asciiname":"Goth Haji Muhammad Ibrahim Gopang",
    "gn:country_code":"PK",
    "gn:dem":48,
    "gn:feature_class":"P",
    "gn:feature_code":"PPL",
    "gn:name":"Goth Haji Muhammad Ibrahim Gopang",
    "gn:population":0,
    "gn:timezone":"Asia/Karachi",
    "iso:country":"PK",
    "name:und_x_variant":[
        "Goth H\u0101li Muhammad Inr\u0101him Gopung",
        "Goth H\u0101ji Muhammad Ib\u0101h\u012bm Gop\u0101ng"
    ],
    "wof:name":"Goth Haji Muhammad Ibrahim Gopang",
    "wof:placetype":"locality"
},
  "geometry": {"coordinates":[68.00213000000001,27.37495],"type":"Point"}
}