{
  "type": "Feature",
  "properties": {
    "gn:admin1_code":"05",
    "gn:asciiname":"Goth Nazar Ali Shah",
    "gn:country_code":"PK",
    "gn:dem":6,
    "gn:feature_class":"P",
    "gn:feature_code":"PPL",
    "gn:name":"Goth Nazar Ali Shah",
    "gn:population":0,
    "gn:timezone":"Asia/Karachi",
    "iso:country":"PK",
    "wof:name":"Goth Nazar Ali Shah",
    "wof:placetype":"locality"
},
  "geometry": {"coordinates":[67.95196,24.35304],"type":"Point"}
}