{
  "type": "Feature",
  "properties": {
    "gn:admin1_code":"5",
    "gn:asciiname":"Goth Ahmad Mashakh",
    "gn:country_code":"PK",
    "gn:dem":15,
    "gn:feature_class":"P",
    "gn:feature_code":"PPL",
    "gn:name":"Goth Ahmad Mash\u0101kh",
    "gn:population":0,
    "gn:timezone":"Asia/Karachi",
    "iso:country":"PK",
    "wof:name":"Goth Ahmad Mashakh",
    "wof:placetype":"locality"
},
  "geometry": {"coordinates":[68.99115999999999,25.1351],"type":"Point"}
}