{
  "type": "Feature",
  "properties": {
    "gn:admin1_code":"3.0",
    "gn:asciiname":"Kamal Shah",
    "gn:country_code":"PK",
    "gn:dem":349,
    "gn:feature_class":"P",
    "gn:feature_code":"PPL",
    "gn:name":"Kamal Shah",
    "gn:population":0,
    "gn:timezone":"Asia/Karachi",
    "iso:country":"PK",
    "name:und_x_variant":[
        "Khamal Sh\u0101h",
        "Kamal Shah"
    ],
    "wof:name":"Kamal Shah",
    "wof:placetype":"locality"
},
  "geometry": {"coordinates":[70.58419000000001,32.8933],"type":"Point"}
}