{
  "type": "Feature",
  "properties": {
    "gn:admin1_code":"3",
    "gn:asciiname":"Warai",
    "gn:country_code":"PK",
    "gn:dem":1281,
    "gn:feature_class":"P",
    "gn:feature_code":"PPL",
    "gn:name":"Warai",
    "gn:population":0,
    "gn:timezone":"Asia/Karachi",
    "iso:country":"PK",
    "wof:name":"Warai",
    "wof:placetype":"locality"
},
  "geometry": {"coordinates":[73.05537,34.58397],"type":"Point"}
}