{
  "type": "Feature",
  "properties": {
    "gn:admin1_code":"6",
    "gn:asciiname":"Chachetar",
    "gn:country_code":"PK",
    "gn:dem":1415,
    "gn:feature_class":"P",
    "gn:feature_code":"PPL",
    "gn:name":"Chachetar",
    "gn:population":0,
    "gn:timezone":"Asia/Karachi",
    "iso:country":"PK",
    "name:und_x_variant":[
        "Shisetar"
    ],
    "wof:name":"Chachetar",
    "wof:placetype":"locality"
},
  "geometry": {"coordinates":[74.07004999999999,33.44847],"type":"Point"}
}