{
  "type": "Feature",
  "properties": {
    "gn:admin1_code":"04",
    "gn:asciiname":"Patto Kalan",
    "gn:country_code":"PK",
    "gn:dem":206,
    "gn:feature_class":"P",
    "gn:feature_code":"PPL",
    "gn:name":"Patto Kalan",
    "gn:population":0,
    "gn:timezone":"Asia/Karachi",
    "iso:country":"PK",
    "name:und_x_variant":[
        "Patto Kohna",
        "Patto Kuhna",
        "Patto Kalan"
    ],
    "wof:name":"Patto Kalan",
    "wof:placetype":"locality"
},
  "geometry": {"coordinates":[74.51159,31.10837],"type":"Point"}
}