{
  "type": "Feature",
  "properties": {
    "gn:admin1_code":"4",
    "gn:asciiname":"Malik Fateh Muhammadwala Nalka",
    "gn:country_code":"PK",
    "gn:dem":178,
    "gn:feature_class":"P",
    "gn:feature_code":"PPL",
    "gn:name":"Malik Fateh Muhammadwala Nalka",
    "gn:population":0,
    "gn:timezone":"Asia/Karachi",
    "iso:country":"PK",
    "wof:name":"Malik Fateh Muhammadwala Nalka",
    "wof:placetype":"locality"
},
  "geometry": {"coordinates":[71.72226999999999,31.70915],"type":"Point"}
}