{
  "type": "Feature",
  "properties": {
    "gn:admin1_code":"4.0",
    "gn:asciiname":"Chak Kale Khan",
    "gn:country_code":"PK",
    "gn:dem":267,
    "gn:feature_class":"P",
    "gn:feature_code":"PPL",
    "gn:name":"Chak Kale Khan",
    "gn:population":0,
    "gn:timezone":"Asia/Karachi",
    "iso:country":"PK",
    "wof:name":"Chak Kale Khan",
    "wof:placetype":"locality"
},
  "geometry": {"coordinates":[75.23546999999998,32.23305999999999],"type":"Point"}
}