{
  "type": "Feature",
  "properties": {
    "gn:admin1_code":"5.0",
    "gn:asciiname":"Fattu ji Bhit",
    "gn:country_code":"PK",
    "gn:dem":71,
    "gn:feature_class":"P",
    "gn:feature_code":"PPL",
    "gn:name":"Fattu ji Bhit",
    "gn:population":0,
    "gn:timezone":"Asia/Karachi",
    "iso:country":"PK",
    "wof:name":"Fattu ji Bhit",
    "wof:placetype":"locality"
},
  "geometry": {"coordinates":[70.05306999999999,24.58635],"type":"Point"}
}