{
  "type": "Feature",
  "properties": {
    "gn:admin1_code":"2.0",
    "gn:asciiname":"Burj Kili",
    "gn:country_code":"PK",
    "gn:dem":2245,
    "gn:feature_class":"P",
    "gn:feature_code":"PPL",
    "gn:name":"Burj Kili",
    "gn:population":0,
    "gn:timezone":"Asia/Karachi",
    "iso:country":"PK",
    "wof:name":"Burj Kili",
    "wof:placetype":"locality"
},
  "geometry": {"coordinates":[68.0382,31.18927],"type":"Point"}
}