{
  "type": "Feature",
  "properties": {
    "gn:admin1_code":"4.0",
    "gn:asciiname":"Malik Jahangir",
    "gn:country_code":"PK",
    "gn:dem":172,
    "gn:feature_class":"P",
    "gn:feature_code":"PPL",
    "gn:name":"Malik Jahangir",
    "gn:population":0,
    "gn:timezone":"Asia/Karachi",
    "iso:country":"PK",
    "wof:name":"Malik Jahangir",
    "wof:placetype":"locality"
},
  "geometry": {"coordinates":[73.49807,30.63278],"type":"Point"}
}