{
  "type": "Feature",
  "properties": {
    "gn:admin1_code":"2.0",
    "gn:asciiname":"Sinchi",
    "gn:country_code":"PK",
    "gn:dem":315,
    "gn:feature_class":"P",
    "gn:feature_code":"PPL",
    "gn:name":"Sinchi",
    "gn:population":0,
    "gn:timezone":"Asia/Karachi",
    "iso:country":"PK",
    "wof:name":"Sinchi",
    "wof:placetype":"locality"
},
  "geometry": {"coordinates":[66.39283,26.51383],"type":"Point"}
}