{
  "type": "Feature",
  "properties": {
    "gn:admin1_code":"03",
    "gn:asciiname":"Ghazi Baba Ziarat",
    "gn:country_code":"PK",
    "gn:dem":729,
    "gn:feature_class":"P",
    "gn:feature_code":"PPL",
    "gn:name":"Ghazi Baba Ziarat",
    "gn:population":0,
    "gn:timezone":"Asia/Karachi",
    "iso:country":"PK",
    "wof:name":"Ghazi Baba Ziarat",
    "wof:placetype":"locality"
},
  "geometry": {"coordinates":[71.79082,34.79625],"type":"Point"}
}