{
  "type": "Feature",
  "properties": {
    "gn:admin1_code":"5",
    "gn:asciiname":"Pir Ghulam Rasul Shah",
    "gn:country_code":"PK",
    "gn:dem":19,
    "gn:feature_class":"P",
    "gn:feature_code":"PPL",
    "gn:name":"Pir Ghulam Rasul Shah",
    "gn:population":0,
    "gn:timezone":"Asia/Karachi",
    "iso:country":"PK",
    "wof:name":"Pir Ghulam Rasul Shah",
    "wof:placetype":"locality"
},
  "geometry": {"coordinates":[68.92601999999999,25.46039],"type":"Point"}
}