{
  "type": "Feature",
  "properties": {
    "gn:admin1_code":"2.0",
    "gn:asciiname":"Kili Karamzai",
    "gn:country_code":"PK",
    "gn:dem":1921,
    "gn:feature_class":"P",
    "gn:feature_code":"PPL",
    "gn:name":"Kili Karamzai",
    "gn:population":0,
    "gn:timezone":"Asia/Karachi",
    "iso:country":"PK",
    "wof:name":"Kili Karamzai",
    "wof:placetype":"locality"
},
  "geometry": {"coordinates":[66.40309999999999,30.45832],"type":"Point"}
}