{
  "type": "Feature",
  "properties": {
    "gn:admin1_code":"4.0",
    "gn:asciiname":"Pawana",
    "gn:country_code":"PK",
    "gn:dem":659,
    "gn:feature_class":"P",
    "gn:feature_code":"PPL",
    "gn:name":"Pawana",
    "gn:population":0,
    "gn:timezone":"Asia/Karachi",
    "iso:country":"PK",
    "name:fra_x_preferred":[
        "Pawana"
    ],
    "wof:name":"Pawana",
    "wof:placetype":"locality"
},
  "geometry": {"coordinates":[73.42574999999999,33.53784],"type":"Point"}
}