{
  "type": "Feature",
  "properties": {
    "gn:admin1_code":"3.0",
    "gn:asciiname":"Banda Zalo",
    "gn:country_code":"PK",
    "gn:dem":295,
    "gn:feature_class":"P",
    "gn:feature_code":"PPL",
    "gn:name":"Banda Zalo",
    "gn:population":0,
    "gn:timezone":"Asia/Karachi",
    "iso:country":"PK",
    "name:und_x_variant":[
        "Mal\u0101gan",
        "Malagan"
    ],
    "wof:name":"Banda Zalo",
    "wof:placetype":"locality"
},
  "geometry": {"coordinates":[70.63531,32.37042],"type":"Point"}
}