{
  "type": "Feature",
  "properties": {
    "gn:admin1_code":"5.0",
    "gn:asciiname":"Goth Umar Baghio",
    "gn:country_code":"PK",
    "gn:dem":18,
    "gn:feature_class":"P",
    "gn:feature_code":"PPL",
    "gn:name":"Goth Umar Baghio",
    "gn:population":0,
    "gn:timezone":"Asia/Karachi",
    "iso:country":"PK",
    "name:und_x_variant":[
        "Haji Mitha Bhugia"
    ],
    "wof:name":"Goth Umar Baghio",
    "wof:placetype":"locality"
},
  "geometry": {"coordinates":[68.95291999999999,25.44704],"type":"Point"}
}