{
  "type": "Feature",
  "properties": {
    "gn:admin1_code":"4",
    "gn:asciiname":"Multanianwala",
    "gn:country_code":"PK",
    "gn:dem":212,
    "gn:feature_class":"P",
    "gn:feature_code":"PPL",
    "gn:name":"Multanianwala",
    "gn:population":0,
    "gn:timezone":"Asia/Karachi",
    "iso:country":"PK",
    "name:und_x_variant":[
        "Kot Mult\u0101ni\u0101nw\u0101la"
    ],
    "wof:name":"Multanianwala",
    "wof:placetype":"locality"
},
  "geometry": {"coordinates":[73.67095999999999,32.48661],"type":"Point"}
}