{
  "type": "Feature",
  "properties": {
    "gn:admin1_code":"4",
    "gn:asciiname":"Lautariwali",
    "gn:country_code":"PK",
    "gn:dem":118,
    "gn:feature_class":"P",
    "gn:feature_code":"PPL",
    "gn:name":"Lautariwali",
    "gn:population":0,
    "gn:timezone":"Asia/Karachi",
    "iso:country":"PK",
    "name:eng_x_preferred":[
        "Lautariwali"
    ],
    "wof:name":"Lautariwali",
    "wof:placetype":"locality"
},
  "geometry": {"coordinates":[71.80099,29.41435],"type":"Point"}
}