{
  "type": "Feature",
  "properties": {
    "gn:admin1_code":"3",
    "gn:asciiname":"Chhaja",
    "gn:country_code":"PK",
    "gn:dem":2488,
    "gn:feature_class":"P",
    "gn:feature_code":"PPL",
    "gn:name":"Chhaja",
    "gn:population":0,
    "gn:timezone":"Asia/Karachi",
    "iso:country":"PK",
    "name:und_x_variant":[
        "Chhajja"
    ],
    "wof:name":"Chhaja",
    "wof:placetype":"locality"
},
  "geometry": {"coordinates":[73.41776,34.55345],"type":"Point"}
}