{
  "type": "Feature",
  "properties": {
    "gn:admin1_code":"5",
    "gn:asciiname":"Goth Haji Saghir",
    "gn:country_code":"PK",
    "gn:dem":14,
    "gn:feature_class":"P",
    "gn:feature_code":"PPL",
    "gn:name":"Goth Haji Saghir",
    "gn:population":0,
    "gn:timezone":"Asia/Karachi",
    "iso:country":"PK",
    "name:und_x_variant":[
        "Isl\u0101mpur"
    ],
    "wof:name":"Goth Haji Saghir",
    "wof:placetype":"locality"
},
  "geometry": {"coordinates":[69.01828,25.3423],"type":"Point"}
}