{
  "type": "Feature",
  "properties": {
    "gn:admin1_code":"04",
    "gn:asciiname":"Werowal",
    "gn:country_code":"PK",
    "gn:dem":201,
    "gn:feature_class":"P",
    "gn:feature_code":"PPL",
    "gn:name":"Werowal",
    "gn:population":0,
    "gn:timezone":"Asia/Karachi",
    "iso:country":"PK",
    "name:und_x_variant":[
        "Wairowal",
        "Werowal"
    ],
    "wof:name":"Werowal",
    "wof:placetype":"locality"
},
  "geometry": {"coordinates":[73.04677,32.48555],"type":"Point"}
}