{
  "type": "Feature",
  "properties": {
    "gn:admin1_code":"4",
    "gn:asciiname":"Gakhran Di Basti",
    "gn:country_code":"PK",
    "gn:dem":109,
    "gn:feature_class":"P",
    "gn:feature_code":"PPL",
    "gn:name":"Gakhran Di Basti",
    "gn:population":0,
    "gn:timezone":"Asia/Karachi",
    "iso:country":"PK",
    "name:und_x_variant":[
        "Basti Bobh\u0101ni",
        "Basti Babh\u0101nr",
        "Gakhran Di Basti"
    ],
    "wof:name":"Gakhran Di Basti",
    "wof:placetype":"locality"
},
  "geometry": {"coordinates":[71.04658000000001,29.60505],"type":"Point"}
}