{
  "type": "Feature",
  "properties": {
    "gn:admin1_code":"1",
    "gn:asciiname":"Shin Korn",
    "gn:country_code":"PK",
    "gn:dem":1391,
    "gn:feature_class":"P",
    "gn:feature_code":"PPL",
    "gn:name":"Shin Korn",
    "gn:population":0,
    "gn:timezone":"Asia/Karachi",
    "iso:country":"PK",
    "wof:name":"Shin Korn",
    "wof:placetype":"locality"
},
  "geometry": {"coordinates":[69.95975,32.56249],"type":"Point"}
}