{
  "type": "Feature",
  "properties": {
    "gn:admin1_code":"03",
    "gn:asciiname":"Doab",
    "gn:country_code":"PK",
    "gn:dem":1127,
    "gn:feature_class":"P",
    "gn:feature_code":"PPL",
    "gn:name":"Doab",
    "gn:population":0,
    "gn:timezone":"Asia/Karachi",
    "iso:country":"PK",
    "name:ben_x_preferred":[
        "\u09a6\u09cb\u09af\u09bc\u09be\u09ac"
    ],
    "name:cat_x_preferred":[
        "Doab"
    ],
    "name:deu_x_preferred":[
        "Doab"
    ],
    "name:eng_x_preferred":[
        "Dwao"
    ],
    "name:epo_x_preferred":[
        "Doab"
    ],
    "name:fas_x_preferred":[
        "\u062f\u0648\u0622\u0628"
    ],
    "name:fra_x_preferred":[
        "Do\u0101b"
    ],
    "name:guj_x_preferred":[
        "\u0aa6\u0acb\u0a86\u0aac"
    ],
    "name:hin_x_preferred":[
        "\u0926\u094b\u0906\u092c"
    ],
    "name:ita_x_preferred":[
        "Doab"
    ],
    "name:mal_x_preferred":[
        "\u0d26\u0d4a\u0d35\u0d3e\u0d2c\u0d4d"
    ],
    "name:nld_x_preferred":[
        "Doab"
    ],
    "name:pol_x_preferred":[
        "Doab"
    ],
    "name:por_x_preferred":[
        "Doab"
    ],
    "name:rus_x_preferred":[
        "\u0414\u043e\u0430\u0431"
    ],
    "name:spa_x_preferred":[
        "Doab"
    ],
    "name:swe_x_preferred":[
        "Doab"
    ],
    "name:tam_x_preferred":[
        "\u0ba4\u0bcb\u0bb5\u0bbe\u0baa\u0bcd"
    ],
    "wof:name":"Doab",
    "wof:placetype":"locality"
},
  "geometry": {"coordinates":[71.96708000000002,34.92564],"type":"Point"}
}