{
  "type": "Feature",
  "properties": {
    "gn:admin1_code":"03",
    "gn:asciiname":"Doab",
    "gn:country_code":"PK",
    "gn:dem":1127,
    "gn:feature_class":"P",
    "gn:feature_code":"PPL",
    "gn:name":"Doab",
    "gn:population":0,
    "gn:timezone":"Asia/Karachi",
    "iso:country":"PK",
    "name:eng_x_preferred":[
        "Dwao"
    ],
    "wof:name":"Doab",
    "wof:placetype":"locality"
},
  "geometry": {"coordinates":[71.96708000000002,34.92564],"type":"Point"}
}