{
  "type": "Feature",
  "properties": {
    "gn:admin1_code":"3.0",
    "gn:asciiname":"Khwaran Khula",
    "gn:country_code":"PK",
    "gn:dem":1995,
    "gn:feature_class":"P",
    "gn:feature_code":"PPL",
    "gn:name":"Khwaran Khula",
    "gn:population":0,
    "gn:timezone":"Asia/Karachi",
    "iso:country":"PK",
    "wof:name":"Khwaran Khula",
    "wof:placetype":"locality"
},
  "geometry": {"coordinates":[71.66993000000002,35.28804],"type":"Point"}
}