{
  "type": "Feature",
  "properties": {
    "gn:admin1_code":"2",
    "gn:asciiname":"Churmian",
    "gn:country_code":"PK",
    "gn:dem":1865,
    "gn:feature_class":"P",
    "gn:feature_code":"PPL",
    "gn:name":"Churmian",
    "gn:population":0,
    "gn:timezone":"Asia/Karachi",
    "iso:country":"PK",
    "name:eng_x_preferred":[
        "Churmi\u0101n"
    ],
    "wof:name":"Churmian",
    "wof:placetype":"locality"
},
  "geometry": {"coordinates":[67.26676999999999,30.57404],"type":"Point"}
}