{
  "type": "Feature",
  "properties": {
    "gn:admin1_code":"04",
    "gn:asciiname":"Murat",
    "gn:country_code":"PK",
    "gn:dem":475,
    "gn:feature_class":"P",
    "gn:feature_code":"PPL",
    "gn:name":"Murat",
    "gn:population":0,
    "gn:timezone":"Asia/Karachi",
    "iso:country":"PK",
    "wof:name":"Murat",
    "wof:placetype":"locality"
},
  "geometry": {"coordinates":[72.47126999999998,32.90704],"type":"Point"}
}