{
  "type": "Feature",
  "properties": {
    "gn:admin1_code":"4",
    "gn:asciiname":"Chapar",
    "gn:country_code":"PK",
    "gn:dem":625,
    "gn:feature_class":"P",
    "gn:feature_code":"PPL",
    "gn:name":"Chapar",
    "gn:population":0,
    "gn:timezone":"Asia/Karachi",
    "iso:country":"PK",
    "name:ceb_x_preferred":[
        "Chapar"
    ],
    "name:fas_x_preferred":[
        "\u0686\u067e\u0631"
    ],
    "name:swe_x_preferred":[
        "Chapar"
    ],
    "wof:name":"Chapar",
    "wof:placetype":"locality"
},
  "geometry": {"coordinates":[72.98678000000002,32.72224],"type":"Point"}
}