{
  "type": "Feature",
  "properties": {
    "gn:admin1_code":"1.0",
    "gn:asciiname":"Mir Alam Shah Kalle",
    "gn:country_code":"PK",
    "gn:dem":365,
    "gn:feature_class":"P",
    "gn:feature_code":"PPL",
    "gn:name":"Mir Alam Shah Kalle",
    "gn:population":0,
    "gn:timezone":"Asia/Karachi",
    "iso:country":"PK",
    "name:und_x_variant":[
        "Lakai Kili"
    ],
    "wof:name":"Mir Alam Shah Kalle",
    "wof:placetype":"locality"
},
  "geometry": {"coordinates":[70.43070999999998,32.47124],"type":"Point"}
}