{
  "type": "Feature",
  "properties": {
    "gn:admin1_code":"4.0",
    "gn:asciiname":"Sardarpur Jhandir",
    "gn:country_code":"PK",
    "gn:dem":129,
    "gn:feature_class":"P",
    "gn:feature_code":"PPL",
    "gn:name":"Sardarpur Jhandir",
    "gn:population":0,
    "gn:timezone":"Asia/Karachi",
    "iso:country":"PK",
    "name:und_x_variant":[
        "Jhand\u012br"
    ],
    "wof:name":"Sardarpur Jhandir",
    "wof:placetype":"locality"
},
  "geometry": {"coordinates":[72.01461,29.77926],"type":"Point"}
}