{
  "type": "Feature",
  "properties": {
    "gn:admin1_code":"4",
    "gn:asciiname":"Basti Mara",
    "gn:country_code":"PK",
    "gn:dem":150,
    "gn:feature_class":"P",
    "gn:feature_code":"PPL",
    "gn:name":"Basti Mara",
    "gn:population":0,
    "gn:timezone":"Asia/Karachi",
    "iso:country":"PK",
    "name:und_x_variant":[
        "M\u0101ren",
        "Basti M\u0101r\u0101",
        "Basti Mara"
    ],
    "wof:name":"Basti Mara",
    "wof:placetype":"locality"
},
  "geometry": {"coordinates":[70.75336,31.06523],"type":"Point"}
}