{
  "type": "Feature",
  "properties": {
    "gn:admin1_code":"8.0",
    "gn:asciiname":"Malwari",
    "gn:country_code":"PK",
    "gn:dem":1181,
    "gn:feature_class":"P",
    "gn:feature_code":"PPL",
    "gn:name":"Malwari",
    "gn:population":0,
    "gn:timezone":"Asia/Karachi",
    "iso:country":"PK",
    "name:eng_x_preferred":[
        "Malwari"
    ],
    "wof:name":"Malwari",
    "wof:placetype":"locality"
},
  "geometry": {"coordinates":[73.10065999999998,33.78122],"type":"Point"}
}