{
  "type": "Feature",
  "properties": {
    "gn:admin1_code":"5",
    "gn:asciiname":"Gulzar Khan Kotohar",
    "gn:country_code":"PK",
    "gn:dem":52,
    "gn:feature_class":"P",
    "gn:feature_code":"PPL",
    "gn:name":"Gulzar Khan Kotohar",
    "gn:population":0,
    "gn:timezone":"Asia/Karachi",
    "iso:country":"PK",
    "name:und_x_variant":[
        "W\u0101nd Ganda"
    ],
    "wof:name":"Gulzar Khan Kotohar",
    "wof:placetype":"locality"
},
  "geometry": {"coordinates":[68.14073,28.01589],"type":"Point"}
}