{
  "type": "Feature",
  "properties": {
    "gn:admin1_code":"4.0",
    "gn:asciiname":"Dilu Chheine di Basti",
    "gn:country_code":"PK",
    "gn:dem":147,
    "gn:feature_class":"P",
    "gn:feature_code":"PPL",
    "gn:name":"Dilu Chheine di Basti",
    "gn:population":0,
    "gn:timezone":"Asia/Karachi",
    "iso:country":"PK",
    "wof:name":"Dilu Chheine di Basti",
    "wof:placetype":"locality"
},
  "geometry": {"coordinates":[72.92009,29.84734000000001],"type":"Point"}
}