{
  "type": "Feature",
  "properties": {
    "gn:admin1_code":"3.0",
    "gn:asciiname":"Bezari Kalle",
    "gn:country_code":"PK",
    "gn:dem":331,
    "gn:feature_class":"P",
    "gn:feature_code":"PPL",
    "gn:name":"Bezari Kalle",
    "gn:population":0,
    "gn:timezone":"Asia/Karachi",
    "iso:country":"PK",
    "name:und_x_variant":[
        "Beriari Kili",
        "Bez\u0101ri Kili",
        "Bezari Kalle"
    ],
    "wof:name":"Bezari Kalle",
    "wof:placetype":"locality"
},
  "geometry": {"coordinates":[70.67374000000002,32.92019000000001],"type":"Point"}
}