{
  "type": "Feature",
  "properties": {
    "gn:admin1_code":"3.0",
    "gn:asciiname":"Trang",
    "gn:country_code":"PK",
    "gn:dem":2408,
    "gn:feature_class":"P",
    "gn:feature_code":"PPL",
    "gn:name":"Trang",
    "gn:population":0,
    "gn:timezone":"Asia/Karachi",
    "iso:country":"PK",
    "wof:name":"Trang",
    "wof:placetype":"locality"
},
  "geometry": {"coordinates":[73.22753,34.73239],"type":"Point"}
}