{
  "type": "Feature",
  "properties": {
    "gn:admin1_code":"6",
    "gn:asciiname":"Chandral",
    "gn:country_code":"PK",
    "gn:dem":373,
    "gn:feature_class":"P",
    "gn:feature_code":"PPL",
    "gn:name":"Chandral",
    "gn:population":0,
    "gn:timezone":"Asia/Karachi",
    "iso:country":"PK",
    "name:und_x_variant":[
        "Thothal Maira"
    ],
    "wof:name":"Chandral",
    "wof:placetype":"locality"
},
  "geometry": {"coordinates":[73.78403,33.16001],"type":"Point"}
}