{
  "type": "Feature",
  "properties": {
    "gn:admin1_code":"1.0",
    "gn:asciiname":"Tut Kasko Khula",
    "gn:country_code":"PK",
    "gn:dem":2338,
    "gn:feature_class":"P",
    "gn:feature_code":"PPL",
    "gn:name":"Tut Kasko Khula",
    "gn:population":0,
    "gn:timezone":"Asia/Karachi",
    "iso:country":"PK",
    "wof:name":"Tut Kasko Khula",
    "wof:placetype":"locality"
},
  "geometry": {"coordinates":[69.65772,32.7096],"type":"Point"}
}