{
  "type": "Feature",
  "properties": {
    "gn:admin1_code":"3",
    "gn:asciiname":"Sar Banda",
    "gn:country_code":"PK",
    "gn:dem":1820,
    "gn:feature_class":"P",
    "gn:feature_code":"PPL",
    "gn:name":"Sar Banda",
    "gn:population":0,
    "gn:timezone":"Asia/Karachi",
    "iso:country":"PK",
    "wof:name":"Sar Banda",
    "wof:placetype":"locality"
},
  "geometry": {"coordinates":[72.78264,34.93171],"type":"Point"}
}