{
  "type": "Feature",
  "properties": {
    "gn:admin1_code":"2.0",
    "gn:asciiname":"Hafiz Muhammad Nur",
    "gn:country_code":"PK",
    "gn:dem":1436,
    "gn:feature_class":"P",
    "gn:feature_code":"PPL",
    "gn:name":"Hafiz Muhammad Nur",
    "gn:population":0,
    "gn:timezone":"Asia/Karachi",
    "iso:country":"PK",
    "wof:name":"Hafiz Muhammad Nur",
    "wof:placetype":"locality"
},
  "geometry": {"coordinates":[65.88061,27.75094],"type":"Point"}
}