{
  "type": "Feature",
  "properties": {
    "gn:admin1_code":"4",
    "gn:asciiname":"Dramni",
    "gn:country_code":"PK",
    "gn:dem":127,
    "gn:feature_class":"P",
    "gn:feature_code":"PPL",
    "gn:name":"Dramni",
    "gn:population":0,
    "gn:timezone":"Asia/Karachi",
    "iso:country":"PK",
    "name:eng_x_preferred":[
        "Dramni"
    ],
    "wof:name":"Dramni",
    "wof:placetype":"locality"
},
  "geometry": {"coordinates":[70.91580999999999,30.321],"type":"Point"}
}