{
  "type": "Feature",
  "properties": {
    "gn:admin1_code":"4.0",
    "gn:asciiname":"Deu Khara",
    "gn:country_code":"PK",
    "gn:dem":191,
    "gn:feature_class":"P",
    "gn:feature_code":"PPL",
    "gn:name":"Deu Khara",
    "gn:population":0,
    "gn:timezone":"Asia/Karachi",
    "iso:country":"PK",
    "name:und_x_variant":[
        "Deo Kh\u0101ra"
    ],
    "wof:name":"Deu Khara",
    "wof:placetype":"locality"
},
  "geometry": {"coordinates":[74.10004000000001,30.89426],"type":"Point"}
}