{
  "type": "Feature",
  "properties": {
    "gn:admin1_code":"4.0",
    "gn:asciiname":"Gobindgarh",
    "gn:country_code":"PK",
    "gn:dem":167,
    "gn:feature_class":"P",
    "gn:feature_code":"PPL",
    "gn:name":"Gobindgarh",
    "gn:population":0,
    "gn:timezone":"Asia/Karachi",
    "iso:country":"PK",
    "name:und_x_variant":[
        "Govindgarh",
        "Rupewala"
    ],
    "wof:name":"Gobindgarh",
    "wof:placetype":"locality"
},
  "geometry": {"coordinates":[73.64201,30.11748],"type":"Point"}
}