{
  "type": "Feature",
  "properties": {
    "gn:admin1_code":"4",
    "gn:asciiname":"Banwre",
    "gn:country_code":"PK",
    "gn:dem":179,
    "gn:feature_class":"P",
    "gn:feature_code":"PPL",
    "gn:name":"Banwre",
    "gn:population":0,
    "gn:timezone":"Asia/Karachi",
    "iso:country":"PK",
    "name:und_x_variant":[
        "B\u0101ore"
    ],
    "wof:name":"Banwre",
    "wof:placetype":"locality"
},
  "geometry": {"coordinates":[73.87628000000002,30.67773],"type":"Point"}
}