{
  "type": "Feature",
  "properties": {
    "gn:admin1_code":"5.0",
    "gn:asciiname":"Haji Rahim Khan Jokhio",
    "gn:country_code":"PK",
    "gn:dem":26,
    "gn:feature_class":"P",
    "gn:feature_code":"PPL",
    "gn:name":"Haji Rahim Khan Jokhio",
    "gn:population":0,
    "gn:timezone":"Asia/Karachi",
    "iso:country":"PK",
    "wof:name":"Haji Rahim Khan Jokhio",
    "wof:placetype":"locality"
},
  "geometry": {"coordinates":[67.18618000000001,24.89986],"type":"Point"}
}