{
  "type": "Feature",
  "properties": {
    "gn:admin1_code":"5.0",
    "gn:asciiname":"Ashaqabad",
    "gn:country_code":"PK",
    "gn:dem":62,
    "gn:feature_class":"P",
    "gn:feature_code":"PPL",
    "gn:name":"Ashaqabad",
    "gn:population":0,
    "gn:timezone":"Asia/Karachi",
    "iso:country":"PK",
    "wof:name":"Ashaqabad",
    "wof:placetype":"locality"
},
  "geometry": {"coordinates":[68.78016,28.42621],"type":"Point"}
}