{
  "type": "Feature",
  "properties": {
    "gn:admin1_code":"5",
    "gn:asciiname":"Haji Mataro",
    "gn:country_code":"PK",
    "gn:dem":28,
    "gn:feature_class":"P",
    "gn:feature_code":"PPL",
    "gn:name":"Haji Mataro",
    "gn:population":0,
    "gn:timezone":"Asia/Karachi",
    "iso:country":"PK",
    "name:und_x_variant":[
        "H\u0101ji Mat\u0101ra"
    ],
    "wof:name":"Haji Mataro",
    "wof:placetype":"locality"
},
  "geometry": {"coordinates":[68.64449999999999,26.18269],"type":"Point"}
}