{
  "type": "Feature",
  "properties": {
    "gn:admin1_code":"4",
    "gn:asciiname":"Basti Doda Khan",
    "gn:country_code":"PK",
    "gn:dem":84,
    "gn:feature_class":"P",
    "gn:feature_code":"PPL",
    "gn:name":"Basti Doda Khan",
    "gn:population":0,
    "gn:timezone":"Asia/Karachi",
    "iso:country":"PK",
    "name:und_x_variant":[
        "Basti D\u016bdal Kh\u0101n"
    ],
    "wof:name":"Basti Doda Khan",
    "wof:placetype":"locality"
},
  "geometry": {"coordinates":[69.89197,28.60759],"type":"Point"}
}