{
  "type": "Feature",
  "properties": {
    "gn:admin1_code":"5",
    "gn:asciiname":"Goth Bangan Labana",
    "gn:country_code":"PK",
    "gn:dem":69,
    "gn:feature_class":"P",
    "gn:feature_code":"PPL",
    "gn:name":"Goth Bangan Labana",
    "gn:population":0,
    "gn:timezone":"Asia/Karachi",
    "iso:country":"PK",
    "name:und_x_variant":[
        "B\u0101ngan Lab\u0101ni"
    ],
    "wof:name":"Goth Bangan Labana",
    "wof:placetype":"locality"
},
  "geometry": {"coordinates":[68.77248,27.89061],"type":"Point"}
}