{
  "type": "Feature",
  "properties": {
    "gn:admin1_code":"3",
    "gn:asciiname":"Sahibzada Karmitti",
    "gn:country_code":"PK",
    "gn:dem":1598,
    "gn:feature_class":"P",
    "gn:feature_code":"PPL",
    "gn:name":"Sahibzada Karmitti",
    "gn:population":0,
    "gn:timezone":"Asia/Karachi",
    "iso:country":"PK",
    "name:und_x_variant":[
        "Khurmatti"
    ],
    "wof:name":"Sahibzada Karmitti",
    "wof:placetype":"locality"
},
  "geometry": {"coordinates":[73.06673000000001,34.47854],"type":"Point"}
}