{
  "type": "Feature",
  "properties": {
    "gn:admin1_code":"04",
    "gn:asciiname":"Mahar Sharif",
    "gn:country_code":"PK",
    "gn:dem":145,
    "gn:feature_class":"P",
    "gn:feature_code":"PPL",
    "gn:name":"Mahar Sharif",
    "gn:population":0,
    "gn:timezone":"Asia/Karachi",
    "iso:country":"PK",
    "name:und_x_variant":[
        "Muharan Sharif",
        "Mah\u0101r\u0101n",
        "Mahar Sharif"
    ],
    "wof:name":"Mahar Sharif",
    "wof:placetype":"locality"
},
  "geometry": {"coordinates":[72.83689,29.86685],"type":"Point"}
}