{
  "type": "Feature",
  "properties": {
    "gn:admin1_code":"2.0",
    "gn:asciiname":"Sirathki",
    "gn:country_code":"PK",
    "gn:dem":2230,
    "gn:feature_class":"P",
    "gn:feature_code":"PPL",
    "gn:name":"Sirathki",
    "gn:population":0,
    "gn:timezone":"Asia/Karachi",
    "iso:country":"PK",
    "wof:name":"Sirathki",
    "wof:placetype":"locality"
},
  "geometry": {"coordinates":[67.72044,31.24729],"type":"Point"}
}