{
  "type": "Feature",
  "properties": {
    "gn:admin1_code":"5.0",
    "gn:asciiname":"Goth Muhammad Sharif Panjabi",
    "gn:country_code":"PK",
    "gn:dem":74,
    "gn:feature_class":"P",
    "gn:feature_code":"PPL",
    "gn:name":"Goth Muhammad Sharif Panjabi",
    "gn:population":0,
    "gn:timezone":"Asia/Karachi",
    "iso:country":"PK",
    "wof:name":"Goth Muhammad Sharif Panjabi",
    "wof:placetype":"locality"
},
  "geometry": {"coordinates":[69.66835999999999,28.12174000000001],"type":"Point"}
}