{
  "type": "Feature",
  "properties": {
    "gn:admin1_code":"5.0",
    "gn:asciiname":"Jumma Khan Chandio",
    "gn:country_code":"PK",
    "gn:dem":47,
    "gn:feature_class":"P",
    "gn:feature_code":"PPL",
    "gn:name":"Jumma Khan Chandio",
    "gn:population":0,
    "gn:timezone":"Asia/Karachi",
    "iso:country":"PK",
    "name:und_x_variant":[
        "Jumma Kh\u0101n Ch\u0101ndio"
    ],
    "wof:name":"Jumma Khan Chandio",
    "wof:placetype":"locality"
},
  "geometry": {"coordinates":[67.93358000000001,27.97166],"type":"Point"}
}