{
  "type": "Feature",
  "properties": {
    "gn:admin1_code":"5",
    "gn:asciiname":"Fazal Muhammad Sial",
    "gn:country_code":"PK",
    "gn:dem":46,
    "gn:feature_class":"P",
    "gn:feature_code":"PPL",
    "gn:name":"Fazal Muhammad Sial",
    "gn:population":0,
    "gn:timezone":"Asia/Karachi",
    "iso:country":"PK",
    "name:und_x_variant":[
        "Fazal Si\u0101l"
    ],
    "wof:name":"Fazal Muhammad Sial",
    "wof:placetype":"locality"
},
  "geometry": {"coordinates":[68.08441999999999,26.9241],"type":"Point"}
}