{
  "type": "Feature",
  "properties": {
    "gn:admin1_code":"5.0",
    "gn:asciiname":"Dangra",
    "gn:country_code":"PK",
    "gn:dem":60,
    "gn:feature_class":"P",
    "gn:feature_code":"PPL",
    "gn:name":"Dangra",
    "gn:population":0,
    "gn:timezone":"Asia/Karachi",
    "iso:country":"PK",
    "wof:name":"Dangra",
    "wof:placetype":"locality"
},
  "geometry": {"coordinates":[68.46639,28.26306],"type":"Point"}
}