{
  "type": "Feature",
  "properties": {
    "gn:admin1_code":"04",
    "gn:asciiname":"Masudpur Tibba",
    "gn:country_code":"PK",
    "gn:dem":123,
    "gn:feature_class":"P",
    "gn:feature_code":"PPL",
    "gn:name":"Masudpur Tibba",
    "gn:population":0,
    "gn:timezone":"Asia/Karachi",
    "iso:country":"PK",
    "wof:name":"Masudpur Tibba",
    "wof:placetype":"locality"
},
  "geometry": {"coordinates":[71.38268000000002,30.15463],"type":"Point"}
}