{
  "type": "Feature",
  "properties": {
    "gn:admin1_code":"2.0",
    "gn:asciiname":"Goth Ismail",
    "gn:country_code":"PK",
    "gn:dem":65,
    "gn:feature_class":"P",
    "gn:feature_code":"PPL",
    "gn:name":"Goth Ismail",
    "gn:population":0,
    "gn:timezone":"Asia/Karachi",
    "iso:country":"PK",
    "name:eng_x_preferred":[
        "Goth Ism\u0101\u012bl"
    ],
    "wof:name":"Goth Ismail",
    "wof:placetype":"locality"
},
  "geometry": {"coordinates":[66.99348000000001,25.14089],"type":"Point"}
}