{
  "type": "Feature",
  "properties": {
    "gn:admin1_code":"2",
    "gn:asciiname":"Langari",
    "gn:country_code":"PK",
    "gn:dem":2286,
    "gn:feature_class":"P",
    "gn:feature_code":"PPL",
    "gn:name":"Langari",
    "gn:population":0,
    "gn:timezone":"Asia/Karachi",
    "iso:country":"PK",
    "wof:name":"Langari",
    "wof:placetype":"locality"
},
  "geometry": {"coordinates":[66.62168,28.72417],"type":"Point"}
}