{
  "type": "Feature",
  "properties": {
    "gn:admin1_code":"3.0",
    "gn:asciiname":"Kharar Maria",
    "gn:country_code":"PK",
    "gn:dem":1040,
    "gn:feature_class":"P",
    "gn:feature_code":"PPL",
    "gn:name":"Kharar Maria",
    "gn:population":0,
    "gn:timezone":"Asia/Karachi",
    "iso:country":"PK",
    "wof:name":"Kharar Maria",
    "wof:placetype":"locality"
},
  "geometry": {"coordinates":[73.24314,34.36061],"type":"Point"}
}