{
  "type": "Feature",
  "properties": {
    "gn:admin1_code":"5.0",
    "gn:asciiname":"Goth Faizu Hingoro",
    "gn:country_code":"PK",
    "gn:dem":23,
    "gn:feature_class":"P",
    "gn:feature_code":"PPL",
    "gn:name":"Goth Faizu Hingoro",
    "gn:population":0,
    "gn:timezone":"Asia/Karachi",
    "iso:country":"PK",
    "wof:name":"Goth Faizu Hingoro",
    "wof:placetype":"locality"
},
  "geometry": {"coordinates":[68.68125999999999,25.66485],"type":"Point"}
}