{
  "type": "Feature",
  "properties": {
    "gn:admin1_code":"7.0",
    "gn:asciiname":"Paguoh",
    "gn:country_code":"PK",
    "gn:dem":2205,
    "gn:feature_class":"P",
    "gn:feature_code":"PPL",
    "gn:name":"Paguoh",
    "gn:population":0,
    "gn:timezone":"Asia/Karachi",
    "iso:country":"PK",
    "wof:name":"Paguoh",
    "wof:placetype":"locality"
},
  "geometry": {"coordinates":[73.61299,35.62329000000001],"type":"Point"}
}