{
  "type": "Feature",
  "properties": {
    "gn:admin1_code":"5",
    "gn:asciiname":"Jhimpat",
    "gn:country_code":"PK",
    "gn:dem":12,
    "gn:feature_class":"P",
    "gn:feature_code":"PPL",
    "gn:name":"Jhimpat",
    "gn:population":0,
    "gn:timezone":"Asia/Karachi",
    "iso:country":"PK",
    "name:eng_x_preferred":[
        "Jhimpat"
    ],
    "wof:name":"Jhimpat",
    "wof:placetype":"locality"
},
  "geometry": {"coordinates":[68.01666999999999,25.00417],"type":"Point"}
}