{
  "type": "Feature",
  "properties": {
    "gn:admin1_code":"7.0",
    "gn:asciiname":"Karba Thang",
    "gn:country_code":"PK",
    "gn:dem":2511,
    "gn:feature_class":"P",
    "gn:feature_code":"PPL",
    "gn:name":"Karba Thang",
    "gn:population":0,
    "gn:timezone":"Asia/Karachi",
    "iso:country":"PK",
    "wof:name":"Karba Thang",
    "wof:placetype":"locality"
},
  "geometry": {"coordinates":[76.23389,34.93333],"type":"Point"}
}