{
  "type": "Feature",
  "properties": {
    "iso:country":"PK",
    "name:eng_x_preferred":[
        "Saddar"
    ],
    "name:eng_x_variant":[
        "Sadr"
    ],
    "qs:gn_adm0_cc":"PK",
    "qs:gn_fcode":"PPLX",
    "qs:gn_local":1174872,
    "qs:gn_nam_loc":"Karachi, Sindh, PK",
    "qs:gn_namadm1":"05",
    "qs:gn_name":"Saddar",
    "qs:local_max":2851,
    "qs:local_sum":5348,
    "qs:localhoods":21,
    "qs:name":"Saddar",
    "qs:name_adm0":"Pakistan",
    "qs:name_adm1":"Sindh",
    "qs:name_local":"Karachi",
    "qs:photo_max":124,
    "qs:photo_sum":331,
    "qs:placetype":"Suburb",
    "qs:quad_count":13,
    "qs:woe_adm0":23424922,
    "qs:woe_adm1":2346499,
    "qs:woe_adm2":0,
    "qs:woe_lau":0,
    "qs:woe_local":2211096,
    "qs:woe_ver":"7.10.0",
    "wd:wordcount":283,
    "wof:lang":[
        "eng"
    ],
    "wof:name":"Saddar",
    "wof:placetype":"neighbourhood"
},
  "geometry": {"coordinates":[67.015837,24.849187],"type":"Point"}
}