{
  "type": "Feature",
  "properties": {
    "gn:admin1_code":"5",
    "gn:asciiname":"Goth Hamza Jatoi",
    "gn:country_code":"PK",
    "gn:dem":56,
    "gn:feature_class":"P",
    "gn:feature_code":"PPL",
    "gn:name":"Goth Hamza Jatoi",
    "gn:population":0,
    "gn:timezone":"Asia/Karachi",
    "iso:country":"PK",
    "name:und_x_variant":[
        "Goth Hamza"
    ],
    "wof:name":"Goth Hamza Jatoi",
    "wof:placetype":"locality"
},
  "geometry": {"coordinates":[68.26597,27.54718],"type":"Point"}
}