{
  "type": "Feature",
  "properties": {
    "gn:admin1_code":"2.0",
    "gn:asciiname":"Mulla Shah Nazar",
    "gn:country_code":"PK",
    "gn:dem":668,
    "gn:feature_class":"P",
    "gn:feature_code":"PPL",
    "gn:name":"Mulla Shah Nazar",
    "gn:population":0,
    "gn:timezone":"Asia/Karachi",
    "iso:country":"PK",
    "wof:name":"Mulla Shah Nazar",
    "wof:placetype":"locality"
},
  "geometry": {"coordinates":[65.21789,28.34931],"type":"Point"}
}