{
  "type": "Feature",
  "properties": {
    "gn:admin1_code":"2.0",
    "gn:asciiname":"Bagsan Umrani",
    "gn:country_code":"PK",
    "gn:dem":58,
    "gn:feature_class":"P",
    "gn:feature_code":"PPL",
    "gn:name":"Bagsan Umrani",
    "gn:population":0,
    "gn:timezone":"Asia/Karachi",
    "iso:country":"PK",
    "wof:name":"Bagsan Umrani",
    "wof:placetype":"locality"
},
  "geometry": {"coordinates":[67.93454,28.27593],"type":"Point"}
}