{
  "type": "Feature",
  "properties": {
    "gn:admin1_code":"3.0",
    "gn:asciiname":"Roman Dar",
    "gn:country_code":"PK",
    "gn:dem":2046,
    "gn:feature_class":"P",
    "gn:feature_code":"PPL",
    "gn:name":"Roman Dar",
    "gn:population":0,
    "gn:timezone":"Asia/Karachi",
    "iso:country":"PK",
    "wof:name":"Roman Dar",
    "wof:placetype":"locality"
},
  "geometry": {"coordinates":[72.19226,36.22375],"type":"Point"}
}