{
  "type": "Feature",
  "properties": {
    "gn:admin1_code":"4.0",
    "gn:asciiname":"Kurong",
    "gn:country_code":"PK",
    "gn:dem":730,
    "gn:feature_class":"P",
    "gn:feature_code":"PPL",
    "gn:name":"Kurong",
    "gn:population":0,
    "gn:timezone":"Asia/Karachi",
    "iso:country":"PK",
    "name:eng_x_preferred":[
        "Kangr\u0101n"
    ],
    "wof:name":"Kurong",
    "wof:placetype":"locality"
},
  "geometry": {"coordinates":[73.29470000000001,33.7989],"type":"Point"}
}