{
  "type": "Feature",
  "properties": {
    "gn:admin1_code":"3.0",
    "gn:asciiname":"Farm Kalle",
    "gn:country_code":"PK",
    "gn:dem":310,
    "gn:feature_class":"P",
    "gn:feature_code":"PPL",
    "gn:name":"Farm Kalle",
    "gn:population":0,
    "gn:timezone":"Asia/Karachi",
    "iso:country":"PK",
    "wof:name":"Farm Kalle",
    "wof:placetype":"locality"
},
  "geometry": {"coordinates":[72.05844,34.2101],"type":"Point"}
}