{
  "type": "Feature",
  "properties": {
    "gn:admin1_code":"3",
    "gn:asciiname":"Bar Taghan",
    "gn:country_code":"PK",
    "gn:dem":1734,
    "gn:feature_class":"P",
    "gn:feature_code":"PPL",
    "gn:name":"Bar Taghan",
    "gn:population":0,
    "gn:timezone":"Asia/Karachi",
    "iso:country":"PK",
    "wof:name":"Bar Taghan",
    "wof:placetype":"locality"
},
  "geometry": {"coordinates":[72.55065999999999,34.6596],"type":"Point"}
}