{
  "type": "Feature",
  "properties": {
    "gn:admin1_code":"4",
    "gn:asciiname":"Thatha Panah",
    "gn:country_code":"PK",
    "gn:dem":207,
    "gn:feature_class":"P",
    "gn:feature_code":"PPL",
    "gn:name":"Thatha Panah",
    "gn:population":0,
    "gn:timezone":"Asia/Karachi",
    "iso:country":"PK",
    "name:und_x_variant":[
        "Thatta Pan\u0101h"
    ],
    "wof:name":"Thatha Panah",
    "wof:placetype":"locality"
},
  "geometry": {"coordinates":[73.65475000000001,32.25961],"type":"Point"}
}