{
  "type": "Feature",
  "properties": {
    "gn:admin1_code":"1.0",
    "gn:asciiname":"Tora Garga",
    "gn:country_code":"PK",
    "gn:dem":1800,
    "gn:feature_class":"P",
    "gn:feature_code":"PPL",
    "gn:name":"Tora Garga",
    "gn:population":0,
    "gn:timezone":"Asia/Karachi",
    "iso:country":"PK",
    "wof:name":"Tora Garga",
    "wof:placetype":"locality"
},
  "geometry": {"coordinates":[70.76206999999999,33.92466],"type":"Point"}
}