{
  "type": "Feature",
  "properties": {
    "gn:admin1_code":"5",
    "gn:asciiname":"Goth Kehar Jarwar",
    "gn:country_code":"PK",
    "gn:dem":18,
    "gn:feature_class":"P",
    "gn:feature_code":"PPL",
    "gn:name":"Goth Kehar Jarwar",
    "gn:population":0,
    "gn:timezone":"Asia/Karachi",
    "iso:country":"PK",
    "name:und_x_variant":[
        "Goth Ahmad Narejo"
    ],
    "wof:name":"Goth Kehar Jarwar",
    "wof:placetype":"locality"
},
  "geometry": {"coordinates":[69.09625,25.62973],"type":"Point"}
}