{
  "type": "Feature",
  "properties": {
    "gn:admin1_code":"4.0",
    "gn:asciiname":"Daula Zerin",
    "gn:country_code":"PK",
    "gn:dem":169,
    "gn:feature_class":"P",
    "gn:feature_code":"PPL",
    "gn:name":"Daula Zerin",
    "gn:population":0,
    "gn:timezone":"Asia/Karachi",
    "iso:country":"PK",
    "name:und_x_variant":[
        "Dola Zerin",
        "Daula Zerin"
    ],
    "wof:name":"Daula Zerin",
    "wof:placetype":"locality"
},
  "geometry": {"coordinates":[73.0294,30.78969],"type":"Point"}
}