{
  "type": "Feature",
  "properties": {
    "gn:admin1_code":"1",
    "gn:asciiname":"Warsak",
    "gn:country_code":"PK",
    "gn:dem":1307,
    "gn:feature_class":"P",
    "gn:feature_code":"PPL",
    "gn:name":"Warsak",
    "gn:population":0,
    "gn:timezone":"Asia/Karachi",
    "iso:country":"PK",
    "wof:name":"Warsak",
    "wof:placetype":"locality"
},
  "geometry": {"coordinates":[71.03466,33.9915],"type":"Point"}
}