{
  "type": "Feature",
  "properties": {
    "gn:admin1_code":"3",
    "gn:asciiname":"Liknai",
    "gn:country_code":"PK",
    "gn:dem":3191,
    "gn:feature_class":"P",
    "gn:feature_code":"PPL",
    "gn:name":"Liknai",
    "gn:population":0,
    "gn:timezone":"Asia/Karachi",
    "iso:country":"PK",
    "wof:name":"Liknai",
    "wof:placetype":"locality"
},
  "geometry": {"coordinates":[73.34478,34.92839],"type":"Point"}
}