{
  "type": "Feature",
  "properties": {
    "gn:admin1_code":"5",
    "gn:asciiname":"Bogi Nuhani jo Goth",
    "gn:country_code":"PK",
    "gn:dem":11,
    "gn:feature_class":"P",
    "gn:feature_code":"PPL",
    "gn:name":"Bogi Nuhani jo Goth",
    "gn:population":0,
    "gn:timezone":"Asia/Karachi",
    "iso:country":"PK",
    "wof:name":"Bogi Nuhani jo Goth",
    "wof:placetype":"locality"
},
  "geometry": {"coordinates":[69.06359,25.15594],"type":"Point"}
}