{
  "type": "Feature",
  "properties": {
    "gn:admin1_code":"4.0",
    "gn:asciiname":"Bagh Ali di Bahaini",
    "gn:country_code":"PK",
    "gn:dem":161,
    "gn:feature_class":"P",
    "gn:feature_code":"PPL",
    "gn:name":"Bagh Ali di Bahaini",
    "gn:population":0,
    "gn:timezone":"Asia/Karachi",
    "iso:country":"PK",
    "wof:name":"Bagh Ali di Bahaini",
    "wof:placetype":"locality"
},
  "geometry": {"coordinates":[73.46553,30.12887000000001],"type":"Point"}
}