{
  "type": "Feature",
  "properties": {
    "gn:admin1_code":"4.0",
    "gn:asciiname":"Dhok Gujri",
    "gn:country_code":"PK",
    "gn:dem":456,
    "gn:feature_class":"P",
    "gn:feature_code":"PPL",
    "gn:name":"Dhok Gujri",
    "gn:population":0,
    "gn:timezone":"Asia/Karachi",
    "iso:country":"PK",
    "name:eng_x_preferred":[
        "Dhok Gujri"
    ],
    "wof:name":"Dhok Gujri",
    "wof:placetype":"locality"
},
  "geometry": {"coordinates":[72.86521999999999,33.22617],"type":"Point"}
}