{
  "type": "Feature",
  "properties": {
    "gn:admin1_code":"5.0",
    "gn:asciiname":"Goth Ahmad Zaur",
    "gn:country_code":"PK",
    "gn:dem":18,
    "gn:feature_class":"P",
    "gn:feature_code":"PPL",
    "gn:name":"Goth Ahmad Zaur",
    "gn:population":0,
    "gn:timezone":"Asia/Karachi",
    "iso:country":"PK",
    "name:und_x_variant":[
        "Goth Ahmed Z\u0101ur"
    ],
    "wof:name":"Goth Ahmad Zaur",
    "wof:placetype":"locality"
},
  "geometry": {"coordinates":[68.53503000000001,25.02583],"type":"Point"}
}