{
  "type": "Feature",
  "properties": {
    "gn:admin1_code":"4",
    "gn:asciiname":"Nighakon",
    "gn:country_code":"PK",
    "gn:dem":317,
    "gn:feature_class":"P",
    "gn:feature_code":"PPL",
    "gn:name":"Nighakon",
    "gn:population":0,
    "gn:timezone":"Asia/Karachi",
    "iso:country":"PK",
    "name:und_x_variant":[
        "\u0100lam Kh\u0101n"
    ],
    "wof:name":"Nighakon",
    "wof:placetype":"locality"
},
  "geometry": {"coordinates":[71.68448000000002,32.95297],"type":"Point"}
}