{
  "type": "Feature",
  "properties": {
    "gn:admin1_code":"04",
    "gn:asciiname":"Long Dhothar",
    "gn:country_code":"PK",
    "gn:dem":219,
    "gn:feature_class":"P",
    "gn:feature_code":"PPL",
    "gn:name":"Long Dhothar",
    "gn:population":0,
    "gn:timezone":"Asia/Karachi",
    "iso:country":"PK",
    "name:und_x_variant":[
        "Loung",
        "Long Dhothar",
        "Long"
    ],
    "wof:name":"Long Dhothar",
    "wof:placetype":"locality"
},
  "geometry": {"coordinates":[73.84985999999998,32.41631],"type":"Point"}
}