{
  "type": "Feature",
  "properties": {
    "gn:admin1_code":"3",
    "gn:asciiname":"Tangar",
    "gn:country_code":"PK",
    "gn:dem":1532,
    "gn:feature_class":"P",
    "gn:feature_code":"PPL",
    "gn:name":"Tangar",
    "gn:population":0,
    "gn:timezone":"Asia/Karachi",
    "iso:country":"PK",
    "wof:name":"Tangar",
    "wof:placetype":"locality"
},
  "geometry": {"coordinates":[72.55037,35.13824],"type":"Point"}
}