{
  "type": "Feature",
  "properties": {
    "gn:admin1_code":"5",
    "gn:asciiname":"Sonehni Jatoi",
    "gn:country_code":"PK",
    "gn:dem":46,
    "gn:feature_class":"P",
    "gn:feature_code":"PPL",
    "gn:name":"Sonehni Jatoi",
    "gn:population":0,
    "gn:timezone":"Asia/Karachi",
    "iso:country":"PK",
    "name:und_x_variant":[
        "Sonehri"
    ],
    "wof:name":"Sonehni Jatoi",
    "wof:placetype":"locality"
},
  "geometry": {"coordinates":[67.80105999999999,26.74746],"type":"Point"}
}