{
  "type": "Feature",
  "properties": {
    "gn:admin1_code":"7.0",
    "gn:asciiname":"Lodas",
    "gn:country_code":"PK",
    "gn:dem":3141,
    "gn:feature_class":"P",
    "gn:feature_code":"PPL",
    "gn:name":"Lodas",
    "gn:population":0,
    "gn:timezone":"Asia/Karachi",
    "iso:country":"PK",
    "name:und_x_variant":[
        "Ludus"
    ],
    "wof:name":"Lodas",
    "wof:placetype":"locality"
},
  "geometry": {"coordinates":[76.12923000000001,35.35753],"type":"Point"}
}