{
  "type": "Feature",
  "properties": {
    "gn:admin1_code":"7.0",
    "gn:asciiname":"Bito",
    "gn:country_code":"PK",
    "gn:dem":1308,
    "gn:feature_class":"P",
    "gn:feature_code":"PPL",
    "gn:name":"Bito",
    "gn:population":0,
    "gn:timezone":"Asia/Karachi",
    "iso:country":"PK",
    "wof:name":"Bito",
    "wof:placetype":"locality"
},
  "geometry": {"coordinates":[73.86261999999998,35.58526],"type":"Point"}
}