{
  "type": "Feature",
  "properties": {
    "gn:admin1_code":"4",
    "gn:asciiname":"Jandraka",
    "gn:country_code":"PK",
    "gn:dem":204,
    "gn:feature_class":"P",
    "gn:feature_code":"PPL",
    "gn:name":"Jandraka",
    "gn:population":0,
    "gn:timezone":"Asia/Karachi",
    "iso:country":"PK",
    "name:und_x_variant":[
        "Jandrake"
    ],
    "wof:name":"Jandraka",
    "wof:placetype":"locality"
},
  "geometry": {"coordinates":[73.51944,31.84091],"type":"Point"}
}