{
  "type": "Feature",
  "properties": {
    "gn:admin1_code":"1.0",
    "gn:asciiname":"Dere Khutta",
    "gn:country_code":"PK",
    "gn:dem":910,
    "gn:feature_class":"P",
    "gn:feature_code":"PPL",
    "gn:name":"Dere Khutta",
    "gn:population":0,
    "gn:timezone":"Asia/Karachi",
    "iso:country":"PK",
    "wof:name":"Dere Khutta",
    "wof:placetype":"locality"
},
  "geometry": {"coordinates":[71.11960999999999,33.65723],"type":"Point"}
}