{
  "type": "Feature",
  "properties": {
    "gn:admin1_code":"4",
    "gn:asciiname":"Basti Massu Shah",
    "gn:country_code":"PK",
    "gn:dem":108,
    "gn:feature_class":"P",
    "gn:feature_code":"PPL",
    "gn:name":"Basti Massu Shah",
    "gn:population":0,
    "gn:timezone":"Asia/Karachi",
    "iso:country":"PK",
    "name:und_x_variant":[
        "Basti Joya"
    ],
    "wof:name":"Basti Massu Shah",
    "wof:placetype":"locality"
},
  "geometry": {"coordinates":[71.02382,29.64087],"type":"Point"}
}