{
  "type": "Feature",
  "properties": {
    "gn:admin1_code":"4.0",
    "gn:asciiname":"Khudayarwala",
    "gn:country_code":"PK",
    "gn:dem":187,
    "gn:feature_class":"P",
    "gn:feature_code":"PPL",
    "gn:name":"Khudayarwala",
    "gn:population":0,
    "gn:timezone":"Asia/Karachi",
    "iso:country":"PK",
    "name:und_x_variant":[
        "Mehrew\u0101la"
    ],
    "wof:name":"Khudayarwala",
    "wof:placetype":"locality"
},
  "geometry": {"coordinates":[71.24701999999998,32.02200999999999],"type":"Point"}
}