{
  "type": "Feature",
  "properties": {
    "gn:admin1_code":"1.0",
    "gn:asciiname":"Sheikhan Kalle",
    "gn:country_code":"PK",
    "gn:dem":480,
    "gn:feature_class":"P",
    "gn:feature_code":"PPL",
    "gn:name":"Sheikhan Kalle",
    "gn:population":0,
    "gn:timezone":"Asia/Karachi",
    "iso:country":"PK",
    "name:und_x_variant":[
        "Sheikhan Kili"
    ],
    "wof:name":"Sheikhan Kalle",
    "wof:placetype":"locality"
},
  "geometry": {"coordinates":[70.34319000000001,32.45780999999999],"type":"Point"}
}