{
  "type": "Feature",
  "properties": {
    "gn:admin1_code":"3.0",
    "gn:asciiname":"Garanga Bala",
    "gn:country_code":"PK",
    "gn:dem":327,
    "gn:feature_class":"P",
    "gn:feature_code":"PPL",
    "gn:name":"Garanga Bala",
    "gn:population":0,
    "gn:timezone":"Asia/Karachi",
    "iso:country":"PK",
    "name:und_x_variant":[
        "Garanga",
        "Garanga Bala"
    ],
    "wof:name":"Garanga Bala",
    "wof:placetype":"locality"
},
  "geometry": {"coordinates":[71.51098,34.12066],"type":"Point"}
}