{
  "type": "Feature",
  "properties": {
    "gn:admin1_code":"5.0",
    "gn:asciiname":"Jam Khan",
    "gn:country_code":"PK",
    "gn:dem":49,
    "gn:feature_class":"P",
    "gn:feature_code":"PPL",
    "gn:name":"Jam Khan",
    "gn:population":0,
    "gn:timezone":"Asia/Karachi",
    "iso:country":"PK",
    "name:und_x_variant":[
        "Mehr\u0101b Bakhsh Ch\u0101ndio"
    ],
    "wof:name":"Jam Khan",
    "wof:placetype":"locality"
},
  "geometry": {"coordinates":[67.94811999999999,27.59596],"type":"Point"}
}