{
  "type": "Feature",
  "properties": {
    "gn:admin1_code":"04",
    "gn:asciiname":"Qasba Janoobi",
    "gn:country_code":"PK",
    "gn:dem":115,
    "gn:feature_class":"P",
    "gn:feature_code":"PPL",
    "gn:name":"Qasba Janoobi",
    "gn:population":0,
    "gn:timezone":"Asia/Karachi",
    "iso:country":"PK",
    "name:und_x_variant":[
        "Kasba Janubi",
        "Qasba Janoobi",
        "Qasba Jan\u016bbi"
    ],
    "wof:name":"Qasba Janoobi",
    "wof:placetype":"locality"
},
  "geometry": {"coordinates":[71.10309000000002,29.93],"type":"Point"}
}