{
  "type": "Feature",
  "properties": {
    "gn:admin1_code":"4",
    "gn:asciiname":"Haliwala",
    "gn:country_code":"PK",
    "gn:dem":140,
    "gn:feature_class":"P",
    "gn:feature_code":"PPL",
    "gn:name":"Haliwala",
    "gn:population":0,
    "gn:timezone":"Asia/Karachi",
    "iso:country":"PK",
    "wof:name":"Haliwala",
    "wof:placetype":"locality"
},
  "geometry": {"coordinates":[70.97785999999998,30.72792],"type":"Point"}
}