{
  "type": "Feature",
  "properties": {
    "gn:admin1_code":"2.0",
    "gn:asciiname":"Goth Ghulam Haider",
    "gn:country_code":"PK",
    "gn:dem":53,
    "gn:feature_class":"P",
    "gn:feature_code":"PPL",
    "gn:name":"Goth Ghulam Haider",
    "gn:population":0,
    "gn:timezone":"Asia/Karachi",
    "iso:country":"PK",
    "name:und_x_variant":[
        "Ghul\u0101m Haider Khosa"
    ],
    "wof:name":"Goth Ghulam Haider",
    "wof:placetype":"locality"
},
  "geometry": {"coordinates":[67.83753,28.16631],"type":"Point"}
}