{
  "type": "Feature",
  "properties": {
    "gn:admin1_code":"3",
    "gn:asciiname":"Harian",
    "gn:country_code":"PK",
    "gn:dem":1762,
    "gn:feature_class":"P",
    "gn:feature_code":"PPL",
    "gn:name":"Harian",
    "gn:population":0,
    "gn:timezone":"Asia/Karachi",
    "iso:country":"PK",
    "name:und_x_variant":[
        "H\u0101ri\u0101n"
    ],
    "wof:name":"Harian",
    "wof:placetype":"locality"
},
  "geometry": {"coordinates":[72.92452,34.49312],"type":"Point"}
}