{
  "type": "Feature",
  "properties": {
    "gn:admin1_code":"6",
    "gn:asciiname":"Barth Dhok",
    "gn:country_code":"PK",
    "gn:dem":2326,
    "gn:feature_class":"P",
    "gn:feature_code":"PPL",
    "gn:name":"Barth Dhok",
    "gn:population":0,
    "gn:timezone":"Asia/Karachi",
    "iso:country":"PK",
    "wof:name":"Barth Dhok",
    "wof:placetype":"locality"
},
  "geometry": {"coordinates":[73.95465,33.90895],"type":"Point"}
}