{
  "type": "Feature",
  "properties": {
    "gn:admin1_code":"7.0",
    "gn:asciiname":"Shokpa Khu",
    "gn:country_code":"PK",
    "gn:dem":3684,
    "gn:feature_class":"P",
    "gn:feature_code":"PPL",
    "gn:name":"Shokpa Khu",
    "gn:population":0,
    "gn:timezone":"Asia/Karachi",
    "iso:country":"PK",
    "wof:name":"Shokpa Khu",
    "wof:placetype":"locality"
},
  "geometry": {"coordinates":[76.11320000000001,35.39947],"type":"Point"}
}