{
  "type": "Feature",
  "properties": {
    "gn:admin1_code":"5.0",
    "gn:asciiname":"Goth Hiral Station",
    "gn:country_code":"PK",
    "gn:dem":13,
    "gn:feature_class":"P",
    "gn:feature_code":"PPL",
    "gn:name":"Goth Hiral Station",
    "gn:population":0,
    "gn:timezone":"Asia/Karachi",
    "iso:country":"PK",
    "name:und_x_variant":[
        "Hiral"
    ],
    "wof:name":"Goth Hiral Station",
    "wof:placetype":"locality"
},
  "geometry": {"coordinates":[69.47526999999999,25.50814],"type":"Point"}
}