{
  "type": "Feature",
  "properties": {
    "gn:admin1_code":"4",
    "gn:asciiname":"Chak Three Hundred Seven Eastern Bar",
    "gn:country_code":"PK",
    "gn:dem":148,
    "gn:feature_class":"P",
    "gn:feature_code":"PPL",
    "gn:name":"Chak Three Hundred Seven Eastern Bar",
    "gn:population":0,
    "gn:timezone":"Asia/Karachi",
    "iso:country":"PK",
    "name:und_x_variant":[
        "Chak Three Hundred Seven"
    ],
    "wof:name":"Chak Three Hundred Seven Eastern Bar",
    "wof:placetype":"locality"
},
  "geometry": {"coordinates":[72.78742,30.08134],"type":"Point"}
}