{
  "type": "Feature",
  "properties": {
    "gn:admin1_code":"3.0",
    "gn:asciiname":"Batle",
    "gn:country_code":"PK",
    "gn:dem":760,
    "gn:feature_class":"P",
    "gn:feature_code":"PPL",
    "gn:name":"Batle",
    "gn:population":0,
    "gn:timezone":"Asia/Karachi",
    "iso:country":"PK",
    "wof:name":"Batle",
    "wof:placetype":"locality"
},
  "geometry": {"coordinates":[72.95773,34.73131],"type":"Point"}
}