{
  "type": "Feature",
  "properties": {
    "gn:admin1_code":"2.0",
    "gn:asciiname":"Tor Kili",
    "gn:country_code":"PK",
    "gn:dem":1247,
    "gn:feature_class":"P",
    "gn:feature_code":"PPL",
    "gn:name":"Tor Kili",
    "gn:population":0,
    "gn:timezone":"Asia/Karachi",
    "iso:country":"PK",
    "wof:name":"Tor Kili",
    "wof:placetype":"locality"
},
  "geometry": {"coordinates":[69.53083000000001,31.64889],"type":"Point"}
}