{
  "type": "Feature",
  "properties": {
    "gn:admin1_code":"1.0",
    "gn:asciiname":"Sweri Mela",
    "gn:country_code":"PK",
    "gn:dem":1004,
    "gn:feature_class":"P",
    "gn:feature_code":"PPL",
    "gn:name":"Sweri Mela",
    "gn:population":0,
    "gn:timezone":"Asia/Karachi",
    "iso:country":"PK",
    "wof:name":"Sweri Mela",
    "wof:placetype":"locality"
},
  "geometry": {"coordinates":[71.0736,33.63723],"type":"Point"}
}