{
  "type": "Feature",
  "properties": {
    "gn:admin1_code":"5.0",
    "gn:asciiname":"Butta",
    "gn:country_code":"PK",
    "gn:dem":56,
    "gn:feature_class":"P",
    "gn:feature_code":"PPL",
    "gn:name":"Butta",
    "gn:population":0,
    "gn:timezone":"Asia/Karachi",
    "iso:country":"PK",
    "name:und_x_variant":[
        "P\u0101ta"
    ],
    "wof:name":"Butta",
    "wof:placetype":"locality"
},
  "geometry": {"coordinates":[68.63755999999999,27.44707],"type":"Point"}
}