{
  "type": "Feature",
  "properties": {
    "gn:admin1_code":"5.0",
    "gn:asciiname":"Khakhniar",
    "gn:country_code":"PK",
    "gn:dem":30,
    "gn:feature_class":"P",
    "gn:feature_code":"PPL",
    "gn:name":"Khakhniar",
    "gn:population":0,
    "gn:timezone":"Asia/Karachi",
    "iso:country":"PK",
    "name:und_x_variant":[
        "Kh\u0101khani\u0101r"
    ],
    "wof:name":"Khakhniar",
    "wof:placetype":"locality"
},
  "geometry": {"coordinates":[69.35883000000001,24.54353],"type":"Point"}
}