{
  "type": "Feature",
  "properties": {
    "gn:admin1_code":"6",
    "gn:asciiname":"Thandikasi",
    "gn:country_code":"PK",
    "gn:dem":2058,
    "gn:feature_class":"P",
    "gn:feature_code":"PPL",
    "gn:name":"Thandikasi",
    "gn:population":0,
    "gn:timezone":"Asia/Karachi",
    "iso:country":"PK",
    "wof:name":"Thandikasi",
    "wof:placetype":"locality"
},
  "geometry": {"coordinates":[73.56601999999999,34.55284],"type":"Point"}
}