{
  "type": "Feature",
  "properties": {
    "gn:admin1_code":"4.0",
    "gn:asciiname":"Chak Fifty-two-Fifteen Left",
    "gn:country_code":"PK",
    "gn:dem":143,
    "gn:feature_class":"P",
    "gn:feature_code":"PPL",
    "gn:name":"Chak Fifty-two-Fifteen Left",
    "gn:population":0,
    "gn:timezone":"Asia/Karachi",
    "iso:country":"PK",
    "name:und_x_variant":[
        "Khichchi\u0101nw\u0101la",
        "Khichi\u0101nw\u0101la"
    ],
    "wof:name":"Chak Fifty-two-Fifteen Left",
    "wof:placetype":"locality"
},
  "geometry": {"coordinates":[72.39086999999998,30.24829],"type":"Point"}
}