{
  "type": "Feature",
  "properties": {
    "gn:admin1_code":"3.0",
    "gn:asciiname":"Dhok Sharbat",
    "gn:country_code":"PK",
    "gn:dem":311,
    "gn:feature_class":"P",
    "gn:feature_code":"PPL",
    "gn:name":"Dhok Sharbat",
    "gn:population":0,
    "gn:timezone":"Asia/Karachi",
    "iso:country":"PK",
    "name:und_x_variant":[
        "L\u0101lh\u0101na"
    ],
    "wof:name":"Dhok Sharbat",
    "wof:placetype":"locality"
},
  "geometry": {"coordinates":[71.82061999999998,33.43352],"type":"Point"}
}