{
  "type": "Feature",
  "properties": {
    "gn:admin1_code":"4",
    "gn:asciiname":"Chah Lakhuwala",
    "gn:country_code":"PK",
    "gn:dem":121,
    "gn:feature_class":"P",
    "gn:feature_code":"PPL",
    "gn:name":"Chah Lakhuwala",
    "gn:population":0,
    "gn:timezone":"Asia/Karachi",
    "iso:country":"PK",
    "name:und_x_variant":[
        "Chah Bakenw\u0101la"
    ],
    "wof:name":"Chah Lakhuwala",
    "wof:placetype":"locality"
},
  "geometry": {"coordinates":[71.36845,30.076],"type":"Point"}
}