{
  "type": "Feature",
  "properties": {
    "gn:admin1_code":"4.0",
    "gn:asciiname":"Basti Khushkian Wali",
    "gn:country_code":"PK",
    "gn:dem":88,
    "gn:feature_class":"P",
    "gn:feature_code":"PPL",
    "gn:name":"Basti Khushkian Wali",
    "gn:population":0,
    "gn:timezone":"Asia/Karachi",
    "iso:country":"PK",
    "name:und_x_variant":[
        "Basti Khushki\u0101nw\u0101li"
    ],
    "wof:name":"Basti Khushkian Wali",
    "wof:placetype":"locality"
},
  "geometry": {"coordinates":[70.53124,28.65461],"type":"Point"}
}