{
  "type": "Feature",
  "properties": {
    "gn:admin1_code":"5.0",
    "gn:asciiname":"Ghaliun",
    "gn:country_code":"PK",
    "gn:dem":22,
    "gn:feature_class":"P",
    "gn:feature_code":"PPL",
    "gn:name":"Ghali\u016bn",
    "gn:population":0,
    "gn:timezone":"Asia/Karachi",
    "iso:country":"PK",
    "name:eng_x_preferred":[
        "Ghali\u016bn"
    ],
    "wof:name":"Ghaliun",
    "wof:placetype":"locality"
},
  "geometry": {"coordinates":[68.40000000000001,25.53333],"type":"Point"}
}