{
  "type": "Feature",
  "properties": {
    "gn:admin1_code":"2.0",
    "gn:asciiname":"Malik Ali Muhammad Notizai",
    "gn:country_code":"PK",
    "gn:dem":834,
    "gn:feature_class":"P",
    "gn:feature_code":"PPL",
    "gn:name":"Malik Ali Muhammad Notizai",
    "gn:population":0,
    "gn:timezone":"Asia/Karachi",
    "iso:country":"PK",
    "wof:name":"Malik Ali Muhammad Notizai",
    "wof:placetype":"locality"
},
  "geometry": {"coordinates":[64.54963000000001,28.92721],"type":"Point"}
}