{
  "type": "Feature",
  "properties": {
    "gn:admin1_code":"4",
    "gn:asciiname":"Bungla Terkhni",
    "gn:country_code":"PK",
    "gn:dem":155,
    "gn:feature_class":"P",
    "gn:feature_code":"PPL",
    "gn:name":"Bungla Terkhni",
    "gn:population":0,
    "gn:timezone":"Asia/Karachi",
    "iso:country":"PK",
    "name:und_x_variant":[
        "Trikhni"
    ],
    "wof:name":"Bungla Terkhni",
    "wof:placetype":"locality"
},
  "geometry": {"coordinates":[72.93470000000001,30.33195],"type":"Point"}
}