{
  "type": "Feature",
  "properties": {
    "gn:admin1_code":"3.0",
    "gn:asciiname":"Gulshanabad",
    "gn:country_code":"PK",
    "gn:dem":518,
    "gn:feature_class":"P",
    "gn:feature_code":"PPL",
    "gn:name":"Gulshanabad",
    "gn:population":0,
    "gn:timezone":"Asia/Karachi",
    "iso:country":"PK",
    "wof:name":"Gulshanabad",
    "wof:placetype":"neighbourhood"
},
  "geometry": {"coordinates":[71.45247000000001,33.60174],"type":"Point"}
}