{
  "type": "Feature",
  "properties": {
    "gn:admin1_code":"4.0",
    "gn:asciiname":"Daud Khas",
    "gn:country_code":"PK",
    "gn:dem":231,
    "gn:feature_class":"P",
    "gn:feature_code":"PPL",
    "gn:name":"Daud Khas",
    "gn:population":0,
    "gn:timezone":"Asia/Karachi",
    "iso:country":"PK",
    "name:und_x_variant":[
        "Daud",
        "Daud Khas"
    ],
    "wof:name":"Daud Khas",
    "wof:placetype":"locality"
},
  "geometry": {"coordinates":[74.80674,32.00888],"type":"Point"}
}