{
  "type": "Feature",
  "properties": {
    "gn:admin1_code":"4.0",
    "gn:asciiname":"Basti Muhammad Arif",
    "gn:country_code":"PK",
    "gn:dem":80,
    "gn:feature_class":"P",
    "gn:feature_code":"PPL",
    "gn:name":"Basti Muhammad Arif",
    "gn:population":0,
    "gn:timezone":"Asia/Karachi",
    "iso:country":"PK",
    "wof:name":"Basti Muhammad Arif",
    "wof:placetype":"locality"
},
  "geometry": {"coordinates":[69.88709,28.39342000000001],"type":"Point"}
}