{
  "type": "Feature",
  "properties": {
    "gn:admin1_code":"6",
    "gn:asciiname":"Malhar",
    "gn:country_code":"PK",
    "gn:dem":642,
    "gn:feature_class":"P",
    "gn:feature_code":"PPL",
    "gn:name":"Malhar",
    "gn:population":0,
    "gn:timezone":"Asia/Karachi",
    "iso:country":"PK",
    "wof:name":"Malhar",
    "wof:placetype":"locality"
},
  "geometry": {"coordinates":[73.85963000000002,33.53014],"type":"Point"}
}