{
  "type": "Feature",
  "properties": {
    "gn:admin1_code":"6",
    "gn:asciiname":"Malhar",
    "gn:country_code":"PK",
    "gn:dem":642,
    "gn:feature_class":"P",
    "gn:feature_code":"PPL",
    "gn:name":"Malhar",
    "gn:population":0,
    "gn:timezone":"Asia/Karachi",
    "iso:country":"PK",
    "name:hin_x_preferred":[
        "\u092e\u0932\u094d\u0939\u093e\u0930 \u0930\u093e\u0917"
    ],
    "name:mal_x_preferred":[
        "\u0d2e\u0d7d\u0d39\u0d3e\u0d7c"
    ],
    "name:new_x_preferred":[
        "\u092e\u0932\u094d\u0932\u093e\u0930 \u0930\u093e\u0917"
    ],
    "name:pan_x_preferred":[
        "\u0a30\u0a3e\u0a17 \u0a2e\u0a32\u0a3e\u0a30"
    ],
    "name:pnb_x_preferred":[
        "\u0631\u0627\u06af \u0645\u0644\u06c1\u0627\u0631"
    ],
    "name:san_x_preferred":[
        "\u092e\u0932\u094d\u0939\u093e\u0930"
    ],
    "wof:name":"Malhar",
    "wof:placetype":"locality"
},
  "geometry": {"coordinates":[73.85963000000002,33.53014],"type":"Point"}
}