{
  "type": "Feature",
  "properties": {
    "gn:admin1_code":"3",
    "gn:asciiname":"Kakul",
    "gn:country_code":"PK",
    "gn:dem":1440,
    "gn:feature_class":"P",
    "gn:feature_code":"PPL",
    "gn:name":"Kakul",
    "gn:population":0,
    "gn:timezone":"Asia/Karachi",
    "iso:country":"PK",
    "wof:name":"Kakul",
    "wof:placetype":"locality"
},
  "geometry": {"coordinates":[73.28265999999998,34.20365],"type":"Point"}
}