{
  "type": "Feature",
  "properties": {
    "gn:admin1_code":"4",
    "gn:asciiname":"Chak Three Hundred Eighty-four Gogera Branch",
    "gn:country_code":"PK",
    "gn:dem":188,
    "gn:feature_class":"P",
    "gn:feature_code":"PPL",
    "gn:name":"Chak Three Hundred Eighty-four Gogera Branch",
    "gn:population":0,
    "gn:timezone":"Asia/Karachi",
    "iso:country":"PK",
    "name:und_x_variant":[
        "Dh\u0101ri Khichi\u0101n",
        "Dhari\u0101n Khichhi\u0101n"
    ],
    "wof:name":"Chak Three Hundred Eighty-four Gogera Branch",
    "wof:placetype":"locality"
},
  "geometry": {"coordinates":[73.39022,31.21481],"type":"Point"}
}