{
  "type": "Feature",
  "properties": {
    "gn:admin1_code":"3.0",
    "gn:asciiname":"Ghundu",
    "gn:country_code":"PK",
    "gn:dem":760,
    "gn:feature_class":"P",
    "gn:feature_code":"PPL",
    "gn:name":"Ghundu",
    "gn:population":0,
    "gn:timezone":"Asia/Karachi",
    "iso:country":"PK",
    "wof:name":"Ghundu",
    "wof:placetype":"locality"
},
  "geometry": {"coordinates":[71.95838000000001,34.67292],"type":"Point"}
}