{
  "type": "Feature",
  "properties": {
    "gn:admin1_code":"5",
    "gn:asciiname":"Goth Mubarak Dasti",
    "gn:country_code":"PK",
    "gn:dem":16,
    "gn:feature_class":"P",
    "gn:feature_code":"PPL",
    "gn:name":"Goth Mubarak Dasti",
    "gn:population":0,
    "gn:timezone":"Asia/Karachi",
    "iso:country":"PK",
    "name:und_x_variant":[
        "Baloch Kh\u0101n Dasti Goth"
    ],
    "wof:name":"Goth Mubarak Dasti",
    "wof:placetype":"locality"
},
  "geometry": {"coordinates":[68.78563,25.1155],"type":"Point"}
}