{
  "type": "Feature",
  "properties": {
    "gn:admin1_code":"5.0",
    "gn:asciiname":"Goth Muhammad Safar Kirio",
    "gn:country_code":"PK",
    "gn:dem":46,
    "gn:feature_class":"P",
    "gn:feature_code":"PPL",
    "gn:name":"Goth Muhammad Safar Kirio",
    "gn:population":0,
    "gn:timezone":"Asia/Karachi",
    "iso:country":"PK",
    "name:und_x_variant":[
        "Goth Muhammad Safar Kiria"
    ],
    "wof:name":"Goth Muhammad Safar Kirio",
    "wof:placetype":"locality"
},
  "geometry": {"coordinates":[68.26234000000001,26.90603],"type":"Point"}
}