{
  "type": "Feature",
  "properties": {
    "gn:admin1_code":"4.0",
    "gn:asciiname":"Dallu Wattu",
    "gn:cc2":"PK",
    "gn:country_code":"PK",
    "gn:dem":173,
    "gn:feature_class":"P",
    "gn:feature_code":"PPL",
    "gn:name":"Dallu Wattu",
    "gn:population":0,
    "gn:timezone":"Asia/Karachi",
    "iso:country":"PK",
    "name:und_x_variant":[
        "Dillu Wattu",
        "Dallu Wattu"
    ],
    "wof:name":"Dallu Wattu",
    "wof:placetype":"locality"
},
  "geometry": {"coordinates":[73.2775,30.97194],"type":"Point"}
}