{
  "type": "Feature",
  "properties": {
    "gn:admin1_code":"4.0",
    "gn:asciiname":"Chak Four Hundred Three Gugera Branch",
    "gn:country_code":"PK",
    "gn:dem":176,
    "gn:feature_class":"P",
    "gn:feature_code":"PPL",
    "gn:name":"Chak Four Hundred Three Gugera Branch",
    "gn:population":0,
    "gn:timezone":"Asia/Karachi",
    "iso:country":"PK",
    "name:und_x_variant":[
        "Sh\u0101mudw\u0101la"
    ],
    "wof:name":"Chak Four Hundred Three Gugera Branch",
    "wof:placetype":"locality"
},
  "geometry": {"coordinates":[73.09406,30.96357],"type":"Point"}
}