{
  "type": "Feature",
  "properties": {
    "gn:admin1_code":"5",
    "gn:asciiname":"Amirullah Khoso",
    "gn:country_code":"PK",
    "gn:dem":63,
    "gn:feature_class":"P",
    "gn:feature_code":"PPL",
    "gn:name":"Amirullah Khoso",
    "gn:population":0,
    "gn:timezone":"Asia/Karachi",
    "iso:country":"PK",
    "name:und_x_variant":[
        "Am\u012bn Kh\u0101n",
        "Am\u012bn Kh\u0101n Khosa",
        "Amirullah Khoso"
    ],
    "wof:name":"Amirullah Khoso",
    "wof:placetype":"locality"
},
  "geometry": {"coordinates":[68.8869,28.34933],"type":"Point"}
}