{
  "type": "Feature",
  "properties": {
    "gn:admin1_code":"5",
    "gn:asciiname":"Goth Mir Muhammad",
    "gn:country_code":"PK",
    "gn:dem":67,
    "gn:feature_class":"P",
    "gn:feature_code":"PPL",
    "gn:name":"Goth Mir Muhammad",
    "gn:population":0,
    "gn:timezone":"Asia/Karachi",
    "iso:country":"PK",
    "name:und_x_variant":[
        "Mir Muhammad"
    ],
    "wof:name":"Goth Mir Muhammad",
    "wof:placetype":"locality"
},
  "geometry": {"coordinates":[69.05575,28.18875],"type":"Point"}
}