{
  "type": "Feature",
  "properties": {
    "gn:admin1_code":"4.0",
    "gn:asciiname":"Goth Shakhan",
    "gn:country_code":"PK",
    "gn:dem":77,
    "gn:feature_class":"P",
    "gn:feature_code":"PPL",
    "gn:name":"Goth Shakhan",
    "gn:population":0,
    "gn:timezone":"Asia/Karachi",
    "iso:country":"PK",
    "wof:name":"Goth Shakhan",
    "wof:placetype":"locality"
},
  "geometry": {"coordinates":[69.73871,28.28568],"type":"Point"}
}