{
  "type": "Feature",
  "properties": {
    "gn:admin1_code":"2.0",
    "gn:asciiname":"Haikalzai",
    "gn:country_code":"PK",
    "gn:dem":1489,
    "gn:feature_class":"P",
    "gn:feature_code":"PPL",
    "gn:name":"Haikalzai",
    "gn:population":0,
    "gn:timezone":"Asia/Karachi",
    "iso:country":"PK",
    "name:und_x_variant":[
        "Haikalza",
        "Haikalzai"
    ],
    "wof:name":"Haikalzai",
    "wof:placetype":"locality"
},
  "geometry": {"coordinates":[66.92309,30.62154],"type":"Point"}
}