{
  "type": "Feature",
  "properties": {
    "gn:admin1_code":"5.0",
    "gn:asciiname":"Goth Iza Muhammad Jokhio",
    "gn:country_code":"PK",
    "gn:dem":13,
    "gn:feature_class":"P",
    "gn:feature_code":"PPL",
    "gn:name":"Goth Iza Muhammad Jokhio",
    "gn:population":0,
    "gn:timezone":"Asia/Karachi",
    "iso:country":"PK",
    "name:und_x_variant":[
        "H\u0101ji Khairu Jokhio",
        "Goth \u012aza Muhammad",
        "Goth Iza Muhammad Jokhio"
    ],
    "wof:name":"Goth Iza Muhammad Jokhio",
    "wof:placetype":"locality"
},
  "geometry": {"coordinates":[67.58199999999999,24.75429],"type":"Point"}
}