{
  "type": "Feature",
  "properties": {
    "gn:admin1_code":"5",
    "gn:asciiname":"Halepota",
    "gn:country_code":"PK",
    "gn:dem":49,
    "gn:feature_class":"P",
    "gn:feature_code":"PPL",
    "gn:name":"Halepota",
    "gn:population":0,
    "gn:timezone":"Asia/Karachi",
    "iso:country":"PK",
    "wof:name":"Halepota",
    "wof:placetype":"locality"
},
  "geometry": {"coordinates":[68.83096,27.46809],"type":"Point"}
}