{
  "type": "Feature",
  "properties": {
    "gn:admin1_code":"3",
    "gn:asciiname":"Bokrai",
    "gn:country_code":"PK",
    "gn:dem":1300,
    "gn:feature_class":"P",
    "gn:feature_code":"PPL",
    "gn:name":"Bokrai",
    "gn:population":0,
    "gn:timezone":"Asia/Karachi",
    "iso:country":"PK",
    "name:und_x_variant":[
        "Bokra"
    ],
    "wof:name":"Bokrai",
    "wof:placetype":"locality"
},
  "geometry": {"coordinates":[73.27408,34.09973],"type":"Point"}
}