{
  "type": "Feature",
  "properties": {
    "gn:admin1_code":"2.0",
    "gn:asciiname":"Bibi",
    "gn:country_code":"PK",
    "gn:dem":98,
    "gn:feature_class":"P",
    "gn:feature_code":"PPL",
    "gn:name":"Bibi",
    "gn:population":0,
    "gn:timezone":"Asia/Karachi",
    "iso:country":"PK",
    "wof:name":"Bibi",
    "wof:placetype":"locality"
},
  "geometry": {"coordinates":[67.77847,29.11372],"type":"Point"}
}