{
  "type": "Feature",
  "properties": {
    "gn:admin1_code":"3.0",
    "gn:asciiname":"Wasalabad",
    "gn:country_code":"PK",
    "gn:dem":310,
    "gn:feature_class":"P",
    "gn:feature_code":"PPL",
    "gn:name":"Wasalabad",
    "gn:population":0,
    "gn:timezone":"Asia/Karachi",
    "iso:country":"PK",
    "wof:name":"Wasalabad",
    "wof:placetype":"locality"
},
  "geometry": {"coordinates":[72.06702,34.22263],"type":"Point"}
}