{
  "type": "Feature",
  "properties": {
    "gn:admin1_code":"4.0",
    "gn:asciiname":"Kuleke",
    "gn:country_code":"PK",
    "gn:dem":211,
    "gn:feature_class":"P",
    "gn:feature_code":"PPL",
    "gn:name":"Kuleke",
    "gn:population":0,
    "gn:timezone":"Asia/Karachi",
    "iso:country":"PK",
    "name:und_x_variant":[
        "K\u016blle"
    ],
    "wof:name":"Kuleke",
    "wof:placetype":"locality"
},
  "geometry": {"coordinates":[74.44093000000002,31.36196],"type":"Point"}
}