{
  "type": "Feature",
  "properties": {
    "gn:admin1_code":"3",
    "gn:asciiname":"Sabunai",
    "gn:country_code":"PK",
    "gn:dem":1619,
    "gn:feature_class":"P",
    "gn:feature_code":"PPL",
    "gn:name":"Sabunai",
    "gn:population":0,
    "gn:timezone":"Asia/Karachi",
    "iso:country":"PK",
    "wof:name":"Sabunai",
    "wof:placetype":"locality"
},
  "geometry": {"coordinates":[72.39660000000001,34.72833],"type":"Point"}
}