{
  "type": "Feature",
  "properties": {
    "gn:admin1_code":"5",
    "gn:asciiname":"Goth Khabar Shah",
    "gn:country_code":"PK",
    "gn:dem":14,
    "gn:feature_class":"P",
    "gn:feature_code":"PPL",
    "gn:name":"Goth Khabar Shah",
    "gn:population":0,
    "gn:timezone":"Asia/Karachi",
    "iso:country":"PK",
    "name:und_x_variant":[
        "Goth Khabar Sh\u0101h"
    ],
    "wof:name":"Goth Khabar Shah",
    "wof:placetype":"locality"
},
  "geometry": {"coordinates":[69.10988,25.0806],"type":"Point"}
}