{
  "type": "Feature",
  "properties": {
    "gn:admin1_code":"2.0",
    "gn:asciiname":"Dannuk",
    "gn:country_code":"PK",
    "gn:dem":114,
    "gn:feature_class":"P",
    "gn:feature_code":"PPL",
    "gn:name":"Dannuk",
    "gn:population":0,
    "gn:timezone":"Asia/Karachi",
    "iso:country":"PK",
    "name:und_x_variant":[
        "Danuk"
    ],
    "wof:name":"Dannuk",
    "wof:placetype":"locality"
},
  "geometry": {"coordinates":[62.97689,26.00043],"type":"Point"}
}