{
  "type": "Feature",
  "properties": {
    "gn:admin1_code":"2.0",
    "gn:asciiname":"Gogra Sarparra",
    "gn:cc2":"PK",
    "gn:country_code":"PK",
    "gn:dem":109,
    "gn:feature_class":"P",
    "gn:feature_code":"PPL",
    "gn:name":"Gogra Sarparra",
    "gn:population":0,
    "gn:timezone":"Asia/Karachi",
    "iso:country":"PK",
    "name:und_x_variant":[
        "Gogra Sarpra",
        "Gogra Sarparra"
    ],
    "wof:name":"Gogra Sarparra",
    "wof:placetype":"locality"
},
  "geometry": {"coordinates":[67.78333000000001,29.23333],"type":"Point"}
}