{
  "type": "Feature",
  "properties": {
    "gn:admin1_code":"3.0",
    "gn:asciiname":"Zarif Koruna",
    "gn:country_code":"PK",
    "gn:dem":364,
    "gn:feature_class":"P",
    "gn:feature_code":"PPL",
    "gn:name":"Zarif Koruna",
    "gn:population":0,
    "gn:timezone":"Asia/Karachi",
    "iso:country":"PK",
    "name:eng_x_preferred":[
        "Zarif Koruna"
    ],
    "wof:name":"Zarif Koruna",
    "wof:placetype":"locality"
},
  "geometry": {"coordinates":[71.80175,34.28938],"type":"Point"}
}