{
  "type": "Feature",
  "properties": {
    "gn:admin1_code":"2.0",
    "gn:asciiname":"Goth Hussain",
    "gn:country_code":"PK",
    "gn:dem":560,
    "gn:feature_class":"P",
    "gn:feature_code":"PPL",
    "gn:name":"Goth Hussain",
    "gn:population":0,
    "gn:timezone":"Asia/Karachi",
    "iso:country":"PK",
    "wof:name":"Goth Hussain",
    "wof:placetype":"locality"
},
  "geometry": {"coordinates":[66.86479,26.00912000000001],"type":"Point"}
}