{
  "type": "Feature",
  "properties": {
    "gn:admin1_code":"4.0",
    "gn:asciiname":"Chacharanwali",
    "gn:country_code":"PK",
    "gn:dem":92,
    "gn:feature_class":"P",
    "gn:feature_code":"PPL",
    "gn:name":"Chacharanwali",
    "gn:population":0,
    "gn:timezone":"Asia/Karachi",
    "iso:country":"PK",
    "name:und_x_variant":[
        "Ch\u0101char"
    ],
    "wof:name":"Chacharanwali",
    "wof:placetype":"locality"
},
  "geometry": {"coordinates":[70.36939,28.66645],"type":"Point"}
}