{
  "type": "Feature",
  "properties": {
    "gn:admin1_code":"2.0",
    "gn:asciiname":"Adilabad",
    "gn:country_code":"PK",
    "gn:dem":1580,
    "gn:feature_class":"P",
    "gn:feature_code":"PPL",
    "gn:name":"Adilabad",
    "gn:population":0,
    "gn:timezone":"Asia/Karachi",
    "iso:country":"PK",
    "name:und_x_variant":[
        "Chakki"
    ],
    "wof:name":"Adilabad",
    "wof:placetype":"locality"
},
  "geometry": {"coordinates":[66.27243,28.10725],"type":"Point"}
}