{
  "type": "Feature",
  "properties": {
    "gn:admin1_code":"3.0",
    "gn:asciiname":"Kot Gulan",
    "gn:country_code":"PK",
    "gn:dem":289,
    "gn:feature_class":"P",
    "gn:feature_code":"PPL",
    "gn:name":"Kot Gulan",
    "gn:population":0,
    "gn:timezone":"Asia/Karachi",
    "iso:country":"PK",
    "name:und_x_variant":[
        "Kiri Gul\u0101n"
    ],
    "wof:name":"Kot Gulan",
    "wof:placetype":"locality"
},
  "geometry": {"coordinates":[70.30585000000001,32.23781],"type":"Point"}
}