{
  "type": "Feature",
  "properties": {
    "gn:admin1_code":"2.0",
    "gn:asciiname":"Nargozi Kili",
    "gn:country_code":"PK",
    "gn:dem":1661,
    "gn:feature_class":"P",
    "gn:feature_code":"PPL",
    "gn:name":"Nargozi Kili",
    "gn:population":0,
    "gn:timezone":"Asia/Karachi",
    "iso:country":"PK",
    "name:und_x_variant":[
        "Anakzai"
    ],
    "wof:name":"Nargozi Kili",
    "wof:placetype":"locality"
},
  "geometry": {"coordinates":[69.37236,30.99067],"type":"Point"}
}