{
  "type": "Feature",
  "properties": {
    "gn:admin1_code":"4",
    "gn:asciiname":"Chak Thirteen -Fourteen Left",
    "gn:country_code":"PK",
    "gn:dem":152,
    "gn:feature_class":"P",
    "gn:feature_code":"PPL",
    "gn:name":"Chak Thirteen -Fourteen Left",
    "gn:population":0,
    "gn:timezone":"Asia/Karachi",
    "iso:country":"PK",
    "name:und_x_variant":[
        "Tabew\u0101li",
        "Tabbiw\u0101la"
    ],
    "wof:name":"Chak Thirteen -Fourteen Left",
    "wof:placetype":"locality"
},
  "geometry": {"coordinates":[72.52301999999997,30.42794],"type":"Point"}
}