{
  "type": "Feature",
  "properties": {
    "gn:admin1_code":"6",
    "gn:asciiname":"Sarban",
    "gn:country_code":"PK",
    "gn:dem":2114,
    "gn:feature_class":"P",
    "gn:feature_code":"PPL",
    "gn:name":"Sarban",
    "gn:population":0,
    "gn:timezone":"Asia/Karachi",
    "iso:country":"PK",
    "wof:name":"Sarban",
    "wof:placetype":"locality"
},
  "geometry": {"coordinates":[73.82491,34.10618],"type":"Point"}
}