{
  "type": "Feature",
  "properties": {
    "gn:admin1_code":"2.0",
    "gn:asciiname":"Goth Isa",
    "gn:country_code":"PK",
    "gn:dem":47,
    "gn:feature_class":"P",
    "gn:feature_code":"PPL",
    "gn:name":"Goth Isa",
    "gn:population":0,
    "gn:timezone":"Asia/Karachi",
    "iso:country":"PK",
    "wof:name":"Goth Isa",
    "wof:placetype":"locality"
},
  "geometry": {"coordinates":[66.33389,25.95556],"type":"Point"}
}