{
  "type": "Feature",
  "properties": {
    "gn:admin1_code":"5",
    "gn:asciiname":"Goth Rahim Mirjat",
    "gn:country_code":"PK",
    "gn:dem":25,
    "gn:feature_class":"P",
    "gn:feature_code":"PPL",
    "gn:name":"Goth Rahim Mirjat",
    "gn:population":0,
    "gn:timezone":"Asia/Karachi",
    "iso:country":"PK",
    "name:und_x_variant":[
        "Rah\u012bm M\u012br Jat"
    ],
    "wof:name":"Goth Rahim Mirjat",
    "wof:placetype":"locality"
},
  "geometry": {"coordinates":[68.62775000000001,25.56476],"type":"Point"}
}