{
  "type": "Feature",
  "properties": {
    "gn:admin1_code":"3",
    "gn:asciiname":"Tep Banda",
    "gn:country_code":"PK",
    "gn:dem":2850,
    "gn:feature_class":"P",
    "gn:feature_code":"PPL",
    "gn:name":"Tep Banda",
    "gn:population":0,
    "gn:timezone":"Asia/Karachi",
    "iso:country":"PK",
    "name:eng_x_preferred":[
        "Tep"
    ],
    "name:und_x_variant":[
        "Taip",
        "Tep Banda"
    ],
    "wof:name":"Tep Banda",
    "wof:placetype":"locality"
},
  "geometry": {"coordinates":[72.6754,35.28485999999999],"type":"Point"}
}