{
  "type": "Feature",
  "properties": {
    "gn:admin1_code":"2.0",
    "gn:asciiname":"Kili Muhammad Sharif",
    "gn:country_code":"PK",
    "gn:dem":832,
    "gn:feature_class":"P",
    "gn:feature_code":"PPL",
    "gn:name":"Kili Muhammad Sharif",
    "gn:population":0,
    "gn:timezone":"Asia/Karachi",
    "iso:country":"PK",
    "wof:name":"Kili Muhammad Sharif",
    "wof:placetype":"locality"
},
  "geometry": {"coordinates":[64.97448,28.92929],"type":"Point"}
}