{
  "type": "Feature",
  "properties": {
    "gn:admin1_code":"5.0",
    "gn:asciiname":"Goth Saiyid Maluk Shah",
    "gn:country_code":"PK",
    "gn:dem":13,
    "gn:feature_class":"P",
    "gn:feature_code":"PPL",
    "gn:name":"Goth Saiyid Maluk Shah",
    "gn:population":0,
    "gn:timezone":"Asia/Karachi",
    "iso:country":"PK",
    "wof:name":"Goth Saiyid Maluk Shah",
    "wof:placetype":"locality"
},
  "geometry": {"coordinates":[68.22426999999999,24.76519],"type":"Point"}
}