{
  "type": "Feature",
  "properties": {
    "gn:admin1_code":"04",
    "gn:asciiname":"Chak Seventy-five Jakh Branch",
    "gn:country_code":"PK",
    "gn:dem":177,
    "gn:feature_class":"P",
    "gn:feature_code":"PPL",
    "gn:name":"Chak Seventy-five Jakh Branch",
    "gn:population":0,
    "gn:timezone":"Asia/Karachi",
    "iso:country":"PK",
    "name:und_x_variant":[
        "Sohal",
        "Sohl",
        "Chak Fifteen",
        "Chak Seventy-five Jakh Branch",
        "Sonal"
    ],
    "wof:name":"Chak Seventy-five Jakh Branch",
    "wof:placetype":"locality"
},
  "geometry": {"coordinates":[72.85061,31.34169],"type":"Point"}
}