{
  "type": "Feature",
  "properties": {
    "gn:admin1_code":"4",
    "gn:asciiname":"Karari Nun",
    "gn:country_code":"PK",
    "gn:dem":178,
    "gn:feature_class":"P",
    "gn:feature_code":"PPL",
    "gn:name":"Karari Nun",
    "gn:population":0,
    "gn:timezone":"Asia/Karachi",
    "iso:country":"PK",
    "name:und_x_variant":[
        "Kir\u0101r N\u016bn"
    ],
    "wof:name":"Karari Nun",
    "wof:placetype":"locality"
},
  "geometry": {"coordinates":[71.08606999999998,31.88622],"type":"Point"}
}