{
  "type": "Feature",
  "properties": {
    "gn:admin1_code":"01",
    "gn:asciiname":"Sar Panre",
    "gn:country_code":"PK",
    "gn:dem":1777,
    "gn:feature_class":"P",
    "gn:feature_code":"PPL",
    "gn:name":"Sar Panre",
    "gn:population":0,
    "gn:timezone":"Asia/Karachi",
    "iso:country":"PK",
    "name:und_x_variant":[
        "Sar P\u0101nre"
    ],
    "wof:name":"Sar Panre",
    "wof:placetype":"locality"
},
  "geometry": {"coordinates":[70.51241,33.73294],"type":"Point"}
}