{
  "type": "Feature",
  "properties": {
    "gn:admin1_code":"4",
    "gn:asciiname":"Yakke Wala",
    "gn:country_code":"PK",
    "gn:dem":124,
    "gn:feature_class":"P",
    "gn:feature_code":"PPL",
    "gn:name":"Yakke Wala",
    "gn:population":0,
    "gn:timezone":"Asia/Karachi",
    "iso:country":"PK",
    "name:und_x_variant":[
        "Nai Bak",
        "Nikki Boki",
        "Yakke Wala"
    ],
    "wof:name":"Yakke Wala",
    "wof:placetype":"locality"
},
  "geometry": {"coordinates":[71.88023000000003,29.68997],"type":"Point"}
}