{
  "type": "Feature",
  "properties": {
    "gn:admin1_code":"5",
    "gn:asciiname":"Goth Jam Jahan Khan Sabzoi",
    "gn:country_code":"PK",
    "gn:dem":71,
    "gn:feature_class":"P",
    "gn:feature_code":"PPL",
    "gn:name":"Goth Jam Jahan Khan Sabzoi",
    "gn:population":0,
    "gn:timezone":"Asia/Karachi",
    "iso:country":"PK",
    "name:und_x_variant":[
        "Goth Jah\u0101n Kh\u0101n"
    ],
    "wof:name":"Goth Jam Jahan Khan Sabzoi",
    "wof:placetype":"locality"
},
  "geometry": {"coordinates":[69.17171999999999,28.19303],"type":"Point"}
}