{
  "type": "Feature",
  "properties": {
    "gn:admin1_code":"4.0",
    "gn:asciiname":"Hussain Khan",
    "gn:country_code":"PK",
    "gn:dem":177,
    "gn:feature_class":"P",
    "gn:feature_code":"PPL",
    "gn:name":"Hussain Khan",
    "gn:population":0,
    "gn:timezone":"Asia/Karachi",
    "iso:country":"PK",
    "name:und_x_variant":[
        "Husen Kh\u0101n",
        "Hussain Khan",
        "Husain Kh\u0101n"
    ],
    "wof:name":"Hussain Khan",
    "wof:placetype":"locality"
},
  "geometry": {"coordinates":[72.87470999999999,31.65714],"type":"Point"}
}