{
  "type": "Feature",
  "properties": {
    "gn:admin1_code":"4.0",
    "gn:asciiname":"Pata Kalan",
    "gn:country_code":"PK",
    "gn:dem":281,
    "gn:feature_class":"P",
    "gn:feature_code":"PPL",
    "gn:name":"Pata Kalan",
    "gn:population":0,
    "gn:timezone":"Asia/Karachi",
    "iso:country":"PK",
    "wof:name":"Pata Kalan",
    "wof:placetype":"locality"
},
  "geometry": {"coordinates":[75.07956,32.36309],"type":"Point"}
}