{
  "type": "Feature",
  "properties": {
    "gn:admin1_code":"4",
    "gn:asciiname":"Ulmawala",
    "gn:country_code":"PK",
    "gn:dem":261,
    "gn:feature_class":"P",
    "gn:feature_code":"PPL",
    "gn:name":"Ulmawala",
    "gn:population":0,
    "gn:timezone":"Asia/Karachi",
    "iso:country":"PK",
    "name:und_x_variant":[
        "W\u0101nda \u0100lm\u0101nw\u0101la"
    ],
    "wof:name":"Ulmawala",
    "wof:placetype":"locality"
},
  "geometry": {"coordinates":[71.41514000000002,32.93641],"type":"Point"}
}