{
  "type": "Feature",
  "properties": {
    "gn:admin1_code":"5",
    "gn:asciiname":"Malik Dhani",
    "gn:country_code":"PK",
    "gn:dem":67,
    "gn:feature_class":"P",
    "gn:feature_code":"PPL",
    "gn:name":"Malik Dhani",
    "gn:population":0,
    "gn:timezone":"Asia/Karachi",
    "iso:country":"PK",
    "name:und_x_variant":[
        "Mal\u016bk Jakr\u0101ni"
    ],
    "wof:name":"Malik Dhani",
    "wof:placetype":"locality"
},
  "geometry": {"coordinates":[69.01018000000001,28.28938],"type":"Point"}
}