{
  "type": "Feature",
  "properties": {
    "gn:admin1_code":"1.0",
    "gn:asciiname":"Atam Khel",
    "gn:country_code":"PK",
    "gn:dem":765,
    "gn:feature_class":"P",
    "gn:feature_code":"PPL",
    "gn:name":"Atam Khel",
    "gn:population":0,
    "gn:timezone":"Asia/Karachi",
    "iso:country":"PK",
    "wof:name":"Atam Khel",
    "wof:placetype":"locality"
},
  "geometry": {"coordinates":[71.68384,33.73174],"type":"Point"}
}