{
  "type": "Feature",
  "properties": {
    "gn:admin1_code":"5",
    "gn:asciiname":"Goth Meghar",
    "gn:country_code":"PK",
    "gn:dem":44,
    "gn:feature_class":"P",
    "gn:feature_code":"PPL",
    "gn:name":"Goth Meghar",
    "gn:population":0,
    "gn:timezone":"Asia/Karachi",
    "iso:country":"PK",
    "name:und_x_variant":[
        "Goth Megh\u0101r"
    ],
    "wof:name":"Goth Meghar",
    "wof:placetype":"locality"
},
  "geometry": {"coordinates":[69.9832,25.39351],"type":"Point"}
}