{
  "type": "Feature",
  "properties": {
    "gn:admin1_code":"04",
    "gn:asciiname":"Okanhwala",
    "gn:country_code":"PK",
    "gn:dem":159,
    "gn:feature_class":"P",
    "gn:feature_code":"PPL",
    "gn:name":"Okanhwala",
    "gn:population":0,
    "gn:timezone":"Asia/Karachi",
    "iso:country":"PK",
    "name:und_x_variant":[
        "Uk\u0101nw\u0101la"
    ],
    "wof:name":"Okanhwala",
    "wof:placetype":"locality"
},
  "geometry": {"coordinates":[72.59999999999999,30.36667000000001],"type":"Point"}
}