{
  "type": "Feature",
  "properties": {
    "gn:admin1_code":"5.0",
    "gn:asciiname":"Chaudhry Sultan Ahmed",
    "gn:country_code":"PK",
    "gn:dem":25,
    "gn:feature_class":"P",
    "gn:feature_code":"PPL",
    "gn:name":"Chaudhry Sultan Ahmed",
    "gn:population":0,
    "gn:timezone":"Asia/Karachi",
    "iso:country":"PK",
    "wof:name":"Chaudhry Sultan Ahmed",
    "wof:placetype":"locality"
},
  "geometry": {"coordinates":[68.76475000000001,26.16517],"type":"Point"}
}