{
  "type": "Feature",
  "properties": {
    "gn:admin1_code":"4.0",
    "gn:asciiname":"Bhata",
    "gn:country_code":"PK",
    "gn:dem":859,
    "gn:feature_class":"P",
    "gn:feature_code":"PPL",
    "gn:name":"Bhata",
    "gn:population":0,
    "gn:timezone":"Asia/Karachi",
    "iso:country":"PK",
    "name:eng_x_preferred":[
        "Bh\u0101tu"
    ],
    "name:fas_x_preferred":[
        "\u0628\u0647\u0627\u062a\u0627"
    ],
    "name:pnb_x_preferred":[
        "\u0628\u06be\u0627\u0679\u0627"
    ],
    "name:urd_x_preferred":[
        "\u0628\u06be\u0627\u0679\u0627"
    ],
    "wof:name":"Bhata",
    "wof:placetype":"locality"
},
  "geometry": {"coordinates":[73.36199999999999,33.76982],"type":"Point"}
}