{
  "type": "Feature",
  "properties": {
    "gn:admin1_code":"4.0",
    "gn:asciiname":"Bapparwal",
    "gn:country_code":"PK",
    "gn:dem":170,
    "gn:feature_class":"P",
    "gn:feature_code":"PPL",
    "gn:name":"Bapparwal",
    "gn:population":0,
    "gn:timezone":"Asia/Karachi",
    "iso:country":"PK",
    "name:und_x_variant":[
        "Bapar Wal",
        "Bapparwal"
    ],
    "wof:name":"Bapparwal",
    "wof:placetype":"locality"
},
  "geometry": {"coordinates":[73.60091,30.50856],"type":"Point"}
}