{
  "type": "Feature",
  "properties": {
    "gn:admin1_code":"5",
    "gn:asciiname":"Goth Thebo",
    "gn:country_code":"PK",
    "gn:dem":20,
    "gn:feature_class":"P",
    "gn:feature_code":"PPL",
    "gn:name":"Goth Thebo",
    "gn:population":0,
    "gn:timezone":"Asia/Karachi",
    "iso:country":"PK",
    "name:und_x_variant":[
        "Goth Mihri"
    ],
    "wof:name":"Goth Thebo",
    "wof:placetype":"locality"
},
  "geometry": {"coordinates":[68.73203000000001,25.60757000000001],"type":"Point"}
}