{
  "type": "Feature",
  "properties": {
    "gn:admin1_code":"4.0",
    "gn:asciiname":"Chak Forty-one - Four Left",
    "gn:country_code":"PK",
    "gn:dem":165,
    "gn:feature_class":"P",
    "gn:feature_code":"PPL",
    "gn:name":"Chak Forty-one - Four Left",
    "gn:population":0,
    "gn:timezone":"Asia/Karachi",
    "iso:country":"PK",
    "name:und_x_variant":[
        "Chak 41-4 L",
        "Chak Forty-one Four L",
        "Chak Forty-one - Four Left",
        "Pakka"
    ],
    "wof:name":"Chak Forty-one - Four Left",
    "wof:placetype":"locality"
},
  "geometry": {"coordinates":[73.31394,30.5668],"type":"Point"}
}