{
  "type": "Feature",
  "properties": {
    "gn:admin1_code":"3",
    "gn:asciiname":"Gamkat Banda",
    "gn:country_code":"PK",
    "gn:dem":2708,
    "gn:feature_class":"P",
    "gn:feature_code":"PPL",
    "gn:name":"Gamkat Banda",
    "gn:population":0,
    "gn:timezone":"Asia/Karachi",
    "iso:country":"PK",
    "name:und_x_variant":[
        "Gumkat B\u0101nda"
    ],
    "wof:name":"Gamkat Banda",
    "wof:placetype":"locality"
},
  "geometry": {"coordinates":[72.58906999999998,34.97488],"type":"Point"}
}