{
  "type": "Feature",
  "properties": {
    "gn:admin1_code":"5.0",
    "gn:asciiname":"Deh Three Hundred Thirty-five",
    "gn:country_code":"PK",
    "gn:dem":12,
    "gn:feature_class":"P",
    "gn:feature_code":"PPL",
    "gn:name":"Deh Three Hundred Thirty-five",
    "gn:population":0,
    "gn:timezone":"Asia/Karachi",
    "iso:country":"PK",
    "wof:name":"Deh Three Hundred Thirty-five",
    "wof:placetype":"locality"
},
  "geometry": {"coordinates":[69.32146999999999,25.24998],"type":"Point"}
}