{
  "type": "Feature",
  "properties": {
    "gn:admin1_code":"3.0",
    "gn:asciiname":"Phaliat",
    "gn:country_code":"PK",
    "gn:dem":2724,
    "gn:feature_class":"P",
    "gn:feature_code":"PPL",
    "gn:name":"Phaliat",
    "gn:population":0,
    "gn:timezone":"Asia/Karachi",
    "iso:country":"PK",
    "wof:name":"Phaliat",
    "wof:placetype":"locality"
},
  "geometry": {"coordinates":[73.56764,35.19254],"type":"Point"}
}