{
  "type": "Feature",
  "properties": {
    "gn:admin1_code":"4",
    "gn:asciiname":"Gadai",
    "gn:country_code":"PK",
    "gn:dem":185,
    "gn:feature_class":"P",
    "gn:feature_code":"PPL",
    "gn:name":"Gadai",
    "gn:population":0,
    "gn:timezone":"Asia/Karachi",
    "iso:country":"PK",
    "name:und_x_variant":[
        "G\u0101dai"
    ],
    "wof:name":"Gadai",
    "wof:placetype":"locality"
},
  "geometry": {"coordinates":[71.37080999999998,31.89115],"type":"Point"}
}