{
  "type": "Feature",
  "properties": {
    "gn:admin1_code":"4",
    "gn:asciiname":"Chak Ten Panjnad",
    "gn:country_code":"PK",
    "gn:dem":86,
    "gn:feature_class":"P",
    "gn:feature_code":"PPL",
    "gn:name":"Chak Ten Panjnad",
    "gn:population":0,
    "gn:timezone":"Asia/Karachi",
    "iso:country":"PK",
    "name:und_x_variant":[
        "Chak Ten P"
    ],
    "wof:name":"Chak Ten Panjnad",
    "wof:placetype":"locality"
},
  "geometry": {"coordinates":[70.68182,28.56721],"type":"Point"}
}