{
  "type": "Feature",
  "properties": {
    "gn:admin1_code":"3.0",
    "gn:asciiname":"Kharsha",
    "gn:country_code":"PK",
    "gn:dem":797,
    "gn:feature_class":"P",
    "gn:feature_code":"PPL",
    "gn:name":"Kharsha",
    "gn:population":0,
    "gn:timezone":"Asia/Karachi",
    "iso:country":"PK",
    "wof:name":"Kharsha",
    "wof:placetype":"locality"
},
  "geometry": {"coordinates":[71.08377,33.53876],"type":"Point"}
}