{
  "type": "Feature",
  "properties": {
    "gn:admin1_code":"4",
    "gn:asciiname":"Kothi Khawaja Nasir",
    "gn:country_code":"PK",
    "gn:dem":127,
    "gn:feature_class":"P",
    "gn:feature_code":"PPL",
    "gn:name":"Kothi Khawaja Nasir",
    "gn:population":0,
    "gn:timezone":"Asia/Karachi",
    "iso:country":"PK",
    "name:und_x_variant":[
        "Koti Khaw\u0101ja Nas\u012br"
    ],
    "wof:name":"Kothi Khawaja Nasir",
    "wof:placetype":"locality"
},
  "geometry": {"coordinates":[71.78529,29.92297],"type":"Point"}
}