{
  "type": "Feature",
  "properties": {
    "gn:admin1_code":"3.0",
    "gn:asciiname":"Inzari",
    "gn:country_code":"PK",
    "gn:dem":453,
    "gn:feature_class":"P",
    "gn:feature_code":"PPL",
    "gn:name":"Inzari",
    "gn:population":0,
    "gn:timezone":"Asia/Karachi",
    "iso:country":"PK",
    "name:und_x_variant":[
        "Inzari Gandab",
        "Inzari"
    ],
    "wof:name":"Inzari",
    "wof:placetype":"locality"
},
  "geometry": {"coordinates":[72.12912,33.85042],"type":"Point"}
}