{
  "type": "Feature",
  "properties": {
    "gn:admin1_code":"4.0",
    "gn:asciiname":"Shah Murad",
    "gn:country_code":"PK",
    "gn:dem":82,
    "gn:feature_class":"P",
    "gn:feature_code":"PPL",
    "gn:name":"Shah Murad",
    "gn:population":0,
    "gn:timezone":"Asia/Karachi",
    "iso:country":"PK",
    "wof:name":"Shah Murad",
    "wof:placetype":"locality"
},
  "geometry": {"coordinates":[69.92449999999999,28.64925],"type":"Point"}
}