{
  "type": "Feature",
  "properties": {
    "gn:admin1_code":"4.0",
    "gn:asciiname":"Chauntra",
    "gn:country_code":"PK",
    "gn:dem":235,
    "gn:feature_class":"P",
    "gn:feature_code":"PPL",
    "gn:name":"Chauntra",
    "gn:population":0,
    "gn:timezone":"Asia/Karachi",
    "iso:country":"PK",
    "name:und_x_variant":[
        "Chauntrah",
        "Chauntra"
    ],
    "wof:name":"Chauntra",
    "wof:placetype":"locality"
},
  "geometry": {"coordinates":[73.75289000000002,32.96516],"type":"Point"}
}