{
  "type": "Feature",
  "properties": {
    "gn:admin1_code":"3.0",
    "gn:asciiname":"Biz Bagh",
    "gn:country_code":"PK",
    "gn:dem":3125,
    "gn:feature_class":"P",
    "gn:feature_code":"PPL",
    "gn:name":"Biz Bagh",
    "gn:population":0,
    "gn:timezone":"Asia/Karachi",
    "iso:country":"PK",
    "wof:name":"Biz Bagh",
    "wof:placetype":"locality"
},
  "geometry": {"coordinates":[72.32460999999998,36.33999],"type":"Point"}
}