{
  "type": "Feature",
  "properties": {
    "gn:admin1_code":"5.0",
    "gn:asciiname":"Wilayatabad",
    "gn:country_code":"PK",
    "gn:dem":23,
    "gn:feature_class":"P",
    "gn:feature_code":"PPL",
    "gn:name":"Wilayatabad",
    "gn:population":0,
    "gn:timezone":"Asia/Karachi",
    "iso:country":"PK",
    "name:eng_x_preferred":[
        "Wilayatabad"
    ],
    "wof:name":"Wilayatabad",
    "wof:placetype":"locality"
},
  "geometry": {"coordinates":[67.0145,24.8998],"type":"Point"}
}