{
  "type": "Feature",
  "properties": {
    "gn:admin1_code":"4",
    "gn:asciiname":"Dharekan Khurd",
    "gn:country_code":"PK",
    "gn:dem":213,
    "gn:feature_class":"P",
    "gn:feature_code":"PPL",
    "gn:name":"Dharekan Khurd",
    "gn:population":0,
    "gn:timezone":"Asia/Karachi",
    "iso:country":"PK",
    "name:und_x_variant":[
        "Drekh\u0101n Khurd"
    ],
    "wof:name":"Dharekan Khurd",
    "wof:placetype":"locality"
},
  "geometry": {"coordinates":[73.67222,32.40812],"type":"Point"}
}