{
  "type": "Feature",
  "properties": {
    "gn:admin1_code":"5.0",
    "gn:asciiname":"Goth Allah Bachayo",
    "gn:country_code":"PK",
    "gn:dem":8,
    "gn:feature_class":"P",
    "gn:feature_code":"PPL",
    "gn:name":"Goth Allah Bachayo",
    "gn:population":0,
    "gn:timezone":"Asia/Karachi",
    "iso:country":"PK",
    "name:eng_x_preferred":[
        "All\u0101h Bach\u0101yo Bhatti"
    ],
    "wof:name":"Goth Allah Bachayo",
    "wof:placetype":"locality"
},
  "geometry": {"coordinates":[68.10649000000001,24.57122],"type":"Point"}
}