{
  "type": "Feature",
  "properties": {
    "gn:admin1_code":"3.0",
    "gn:asciiname":"Poya",
    "gn:country_code":"PK",
    "gn:dem":656,
    "gn:feature_class":"P",
    "gn:feature_code":"PPL",
    "gn:name":"Poya",
    "gn:population":0,
    "gn:timezone":"Asia/Karachi",
    "iso:country":"PK",
    "wof:name":"Poya",
    "wof:placetype":"locality"
},
  "geometry": {"coordinates":[70.9457,33.21578],"type":"Point"}
}