{
  "type": "Feature",
  "properties": {
    "gn:admin1_code":"1.0",
    "gn:asciiname":"Darra",
    "gn:country_code":"PK",
    "gn:dem":1380,
    "gn:feature_class":"P",
    "gn:feature_code":"PPL",
    "gn:name":"Darra",
    "gn:population":0,
    "gn:timezone":"Asia/Karachi",
    "iso:country":"PK",
    "name:ceb_x_preferred":[
        "Darra"
    ],
    "name:swe_x_preferred":[
        "Darra"
    ],
    "name:und_x_variant":[
        "Khangarb\u016br"
    ],
    "wof:name":"Darra",
    "wof:placetype":"locality"
},
  "geometry": {"coordinates":[70.8678,33.65351],"type":"Point"}
}