{
  "type": "Feature",
  "properties": {
    "gn:admin1_code":"3",
    "gn:asciiname":"Kai",
    "gn:country_code":"PK",
    "gn:dem":2257,
    "gn:feature_class":"P",
    "gn:feature_code":"PPL",
    "gn:name":"Kai",
    "gn:population":0,
    "gn:timezone":"Asia/Karachi",
    "iso:country":"PK",
    "name:und_x_variant":[
        "K\u0101hi"
    ],
    "wof:name":"Kai",
    "wof:placetype":"locality"
},
  "geometry": {"coordinates":[73.4019,34.67307],"type":"Point"}
}