{
  "type": "Feature",
  "properties": {
    "gn:admin1_code":"4.0",
    "gn:asciiname":"Chak One Hundred Ninety-three A Murad Gharpi",
    "gn:country_code":"PK",
    "gn:dem":144,
    "gn:feature_class":"P",
    "gn:feature_code":"PPL",
    "gn:name":"Chak One Hundred Ninety-three A Murad Gharpi",
    "gn:population":0,
    "gn:timezone":"Asia/Karachi",
    "iso:country":"PK",
    "wof:name":"Chak One Hundred Ninety-three A Murad Gharpi",
    "wof:placetype":"locality"
},
  "geometry": {"coordinates":[72.57491999999998,29.44679],"type":"Point"}
}