{
  "type": "Feature",
  "properties": {
    "gn:admin1_code":"4",
    "gn:asciiname":"Umarwali Bhan",
    "gn:country_code":"PK",
    "gn:dem":166,
    "gn:feature_class":"P",
    "gn:feature_code":"PPL",
    "gn:name":"Umarwali Bhan",
    "gn:population":0,
    "gn:timezone":"Asia/Karachi",
    "iso:country":"PK",
    "wof:name":"Umarwali Bhan",
    "wof:placetype":"locality"
},
  "geometry": {"coordinates":[70.91058000000002,31.4595],"type":"Point"}
}