{
  "type": "Feature",
  "properties": {
    "gn:admin1_code":"4.0",
    "gn:asciiname":"Dhok Nagial",
    "gn:country_code":"PK",
    "gn:dem":592,
    "gn:feature_class":"P",
    "gn:feature_code":"PPL",
    "gn:name":"Dhok Nagial",
    "gn:population":0,
    "gn:timezone":"Asia/Karachi",
    "iso:country":"PK",
    "wof:name":"Dhok Nagial",
    "wof:placetype":"locality"
},
  "geometry": {"coordinates":[73.32684999999999,33.58567],"type":"Point"}
}