{
  "type": "Feature",
  "properties": {
    "gn:admin1_code":"4.0",
    "gn:asciiname":"Bhikari Kalan",
    "gn:country_code":"PK",
    "gn:dem":518,
    "gn:feature_class":"P",
    "gn:feature_code":"PPL",
    "gn:name":"Bhikari Kalan",
    "gn:population":0,
    "gn:timezone":"Asia/Karachi",
    "iso:country":"PK",
    "name:und_x_variant":[
        "Bakhari Kalan",
        "Bhikari Kalan"
    ],
    "wof:name":"Bhikari Kalan",
    "wof:placetype":"locality"
},
  "geometry": {"coordinates":[72.63261999999997,32.94937],"type":"Point"}
}