{
  "type": "Feature",
  "properties": {
    "gn:admin1_code":"3",
    "gn:asciiname":"Maliar",
    "gn:country_code":"PK",
    "gn:dem":1452,
    "gn:feature_class":"P",
    "gn:feature_code":"PPL",
    "gn:name":"Mali\u0101r",
    "gn:population":0,
    "gn:timezone":"Asia/Karachi",
    "iso:country":"PK",
    "wof:name":"Maliar",
    "wof:placetype":"locality"
},
  "geometry": {"coordinates":[72.325,35.04028],"type":"Point"}
}