{
  "type": "Feature",
  "properties": {
    "gn:admin1_code":"5",
    "gn:asciiname":"Sultan Jamarani",
    "gn:country_code":"PK",
    "gn:dem":53,
    "gn:feature_class":"P",
    "gn:feature_code":"PPL",
    "gn:name":"Sultan Jamarani",
    "gn:population":0,
    "gn:timezone":"Asia/Karachi",
    "iso:country":"PK",
    "name:und_x_variant":[
        "Sult\u0101n Jam\u0101r\u0101ni"
    ],
    "wof:name":"Sultan Jamarani",
    "wof:placetype":"locality"
},
  "geometry": {"coordinates":[68.09192,27.46184],"type":"Point"}
}