{
  "type": "Feature",
  "properties": {
    "gn:admin1_code":"2.0",
    "gn:asciiname":"Kili Mulla Muhammad Bakhsh",
    "gn:country_code":"PK",
    "gn:dem":1282,
    "gn:feature_class":"P",
    "gn:feature_code":"PPL",
    "gn:name":"Kili Mulla Muhammad Bakhsh",
    "gn:population":0,
    "gn:timezone":"Asia/Karachi",
    "iso:country":"PK",
    "wof:name":"Kili Mulla Muhammad Bakhsh",
    "wof:placetype":"locality"
},
  "geometry": {"coordinates":[63.94566999999999,29.22123],"type":"Point"}
}