{
  "type": "Feature",
  "properties": {
    "gn:admin1_code":"03",
    "gn:asciiname":"Maghdarra",
    "gn:country_code":"PK",
    "gn:dem":439,
    "gn:feature_class":"P",
    "gn:feature_code":"PPL",
    "gn:name":"Maghdarra",
    "gn:population":0,
    "gn:timezone":"Asia/Karachi",
    "iso:country":"PK",
    "name:eng_x_preferred":[
        "Maghdarra"
    ],
    "name:und_x_variant":[
        "Mah Dheri"
    ],
    "wof:name":"Maghdarra",
    "wof:placetype":"locality"
},
  "geometry": {"coordinates":[72.46522,34.2156],"type":"Point"}
}