{
  "type": "Feature",
  "properties": {
    "gn:admin1_code":"3.0",
    "gn:asciiname":"Turi Parwak",
    "gn:country_code":"PK",
    "gn:dem":2289,
    "gn:feature_class":"P",
    "gn:feature_code":"PPL",
    "gn:name":"Turi Parwak",
    "gn:population":0,
    "gn:timezone":"Asia/Karachi",
    "iso:country":"PK",
    "wof:name":"Turi Parwak",
    "wof:placetype":"locality"
},
  "geometry": {"coordinates":[72.41882,36.27881],"type":"Point"}
}