{
  "type": "Feature",
  "properties": {
    "gn:admin1_code":"6",
    "gn:asciiname":"Narachh",
    "gn:country_code":"PK",
    "gn:dem":587,
    "gn:feature_class":"P",
    "gn:feature_code":"PPL",
    "gn:name":"Narachh",
    "gn:population":0,
    "gn:timezone":"Asia/Karachi",
    "iso:country":"PK",
    "name:und_x_variant":[
        "Nur\u016bchil"
    ],
    "wof:name":"Narachh",
    "wof:placetype":"locality"
},
  "geometry": {"coordinates":[73.86256999999998,33.44956],"type":"Point"}
}