{
  "type": "Feature",
  "properties": {
    "gn:admin1_code":"4.0",
    "gn:asciiname":"Baowal",
    "gn:country_code":"PK",
    "gn:dem":265,
    "gn:feature_class":"P",
    "gn:feature_code":"PPL",
    "gn:name":"Baowal",
    "gn:population":0,
    "gn:timezone":"Asia/Karachi",
    "iso:country":"PK",
    "wof:name":"Baowal",
    "wof:placetype":"locality"
},
  "geometry": {"coordinates":[75.20862,32.25959],"type":"Point"}
}