{
  "type": "Feature",
  "properties": {
    "gn:admin1_code":"2.0",
    "gn:asciiname":"Atar",
    "gn:country_code":"PK",
    "gn:dem":400,
    "gn:feature_class":"P",
    "gn:feature_code":"PPL",
    "gn:name":"Atar",
    "gn:population":0,
    "gn:timezone":"Asia/Karachi",
    "iso:country":"PK",
    "wof:name":"Atar",
    "wof:placetype":"locality"
},
  "geometry": {"coordinates":[66.57026999999999,26.29352],"type":"Point"}
}