{
  "type": "Feature",
  "properties": {
    "gn:admin1_code":"04",
    "gn:asciiname":"Sahib Khan",
    "gn:country_code":"PK",
    "gn:dem":419,
    "gn:feature_class":"P",
    "gn:feature_code":"PPL",
    "gn:name":"Sahib Khan",
    "gn:population":0,
    "gn:timezone":"Asia/Karachi",
    "iso:country":"PK",
    "wof:name":"Sahib Khan",
    "wof:placetype":"locality"
},
  "geometry": {"coordinates":[72.60103000000002,33.73072],"type":"Point"}
}