{
  "type": "Feature",
  "properties": {
    "gn:admin1_code":"2",
    "gn:asciiname":"Dehli Jadid",
    "gn:country_code":"PK",
    "gn:dem":52,
    "gn:feature_class":"P",
    "gn:feature_code":"PPL",
    "gn:name":"Dehli Jadid",
    "gn:population":0,
    "gn:timezone":"Asia/Karachi",
    "iso:country":"PK",
    "name:und_x_variant":[
        "Goth Dili Jadid",
        "Dili",
        "Dehli Jadid"
    ],
    "wof:name":"Dehli Jadid",
    "wof:placetype":"locality"
},
  "geometry": {"coordinates":[67.78685,28.03697],"type":"Point"}
}