{
  "type": "Feature",
  "properties": {
    "gn:admin1_code":"4.0",
    "gn:asciiname":"Kotli Gujran",
    "gn:country_code":"PK",
    "gn:dem":221,
    "gn:feature_class":"P",
    "gn:feature_code":"PPL",
    "gn:name":"Kotli Gujran",
    "gn:population":0,
    "gn:timezone":"Asia/Karachi",
    "iso:country":"PK",
    "wof:name":"Kotli Gujran",
    "wof:placetype":"locality"
},
  "geometry": {"coordinates":[74.54099000000002,31.90912],"type":"Point"}
}