{
  "type": "Feature",
  "properties": {
    "gn:admin1_code":"4.0",
    "gn:asciiname":"Saida Chak",
    "gn:country_code":"PK",
    "gn:dem":219,
    "gn:feature_class":"P",
    "gn:feature_code":"PPL",
    "gn:name":"Saida Chak",
    "gn:population":0,
    "gn:timezone":"Asia/Karachi",
    "iso:country":"PK",
    "name:und_x_variant":[
        "Chak Saida"
    ],
    "wof:name":"Saida Chak",
    "wof:placetype":"locality"
},
  "geometry": {"coordinates":[73.71024,32.54236],"type":"Point"}
}