{
  "type": "Feature",
  "properties": {
    "gn:admin1_code":"4.0",
    "gn:asciiname":"Chak Baqir Shah",
    "gn:country_code":"PK",
    "gn:dem":467,
    "gn:feature_class":"P",
    "gn:feature_code":"PPL",
    "gn:name":"Chak Baqir Shah",
    "gn:population":0,
    "gn:timezone":"Asia/Karachi",
    "iso:country":"PK",
    "name:und_x_variant":[
        "Chak B\u0101qar Sh\u0101h",
        "Chak Baqir Shah"
    ],
    "wof:name":"Chak Baqir Shah",
    "wof:placetype":"locality"
},
  "geometry": {"coordinates":[73.02648000000001,32.91765],"type":"Point"}
}