{
  "type": "Feature",
  "properties": {
    "gn:admin1_code":"4.0",
    "gn:asciiname":"Chak Twenty-three -A Gogera Distributary",
    "gn:country_code":"PK",
    "gn:dem":182,
    "gn:feature_class":"P",
    "gn:feature_code":"PPL",
    "gn:name":"Chak Twenty-three -A Gogera Distributary",
    "gn:population":0,
    "gn:timezone":"Asia/Karachi",
    "iso:country":"PK",
    "name:und_x_variant":[
        "Chak Twenty-three A"
    ],
    "wof:name":"Chak Twenty-three -A Gogera Distributary",
    "wof:placetype":"locality"
},
  "geometry": {"coordinates":[73.3831,30.89039],"type":"Point"}
}