{
  "type": "Feature",
  "properties": {
    "gn:admin1_code":"3.0",
    "gn:asciiname":"Akra",
    "gn:country_code":"PK",
    "gn:dem":329,
    "gn:feature_class":"P",
    "gn:feature_code":"PPL",
    "gn:name":"Akra",
    "gn:population":0,
    "gn:timezone":"Asia/Karachi",
    "iso:country":"PK",
    "name:ceb_x_preferred":[
        "Akra"
    ],
    "name:deu_x_preferred":[
        "Akra"
    ],
    "name:pol_x_preferred":[
        "Akra"
    ],
    "name:swe_x_preferred":[
        "Akra"
    ],
    "name:tur_x_preferred":[
        "Akra"
    ],
    "wof:name":"Akra",
    "wof:placetype":"locality"
},
  "geometry": {"coordinates":[70.63778000000001,32.87806],"type":"Point"}
}