{
  "type": "Feature",
  "properties": {
    "gn:admin1_code":"6",
    "gn:asciiname":"Khaladar",
    "gn:country_code":"PK",
    "gn:dem":3219,
    "gn:feature_class":"P",
    "gn:feature_code":"PPL",
    "gn:name":"Khaladar",
    "gn:population":0,
    "gn:timezone":"Asia/Karachi",
    "iso:country":"PK",
    "name:und_x_variant":[
        "Khaldadar"
    ],
    "wof:name":"Khaladar",
    "wof:placetype":"locality"
},
  "geometry": {"coordinates":[73.82836999999998,34.61759],"type":"Point"}
}