{
  "type": "Feature",
  "properties": {
    "gn:admin1_code":"3.0",
    "gn:asciiname":"Poshkari Ghari",
    "gn:country_code":"PK",
    "gn:dem":2973,
    "gn:feature_class":"P",
    "gn:feature_code":"PPL",
    "gn:name":"Poshkari Ghari",
    "gn:population":0,
    "gn:timezone":"Asia/Karachi",
    "iso:country":"PK",
    "name:eng_x_preferred":[
        "Poshkari Ghari"
    ],
    "wof:name":"Poshkari Ghari",
    "wof:placetype":"locality"
},
  "geometry": {"coordinates":[72.07557,35.8052],"type":"Point"}
}