{
  "type": "Feature",
  "properties": {
    "gn:admin1_code":"3.0",
    "gn:asciiname":"Wana Kach",
    "gn:country_code":"PK",
    "gn:dem":3217,
    "gn:feature_class":"P",
    "gn:feature_code":"PPL",
    "gn:name":"Wana Kach",
    "gn:population":0,
    "gn:timezone":"Asia/Karachi",
    "iso:country":"PK",
    "wof:name":"Wana Kach",
    "wof:placetype":"locality"
},
  "geometry": {"coordinates":[71.65170999999999,36.34737],"type":"Point"}
}