{
  "type": "Feature",
  "properties": {
    "gn:admin1_code":"2.0",
    "gn:asciiname":"Goth Mir Allah Bakhsh Khan",
    "gn:country_code":"PK",
    "gn:dem":64,
    "gn:feature_class":"P",
    "gn:feature_code":"PPL",
    "gn:name":"Goth Mir Allah Bakhsh Khan",
    "gn:population":0,
    "gn:timezone":"Asia/Karachi",
    "iso:country":"PK",
    "name:und_x_variant":[
        "Goth Mir All\u0101h Bakhsh"
    ],
    "wof:name":"Goth Mir Allah Bakhsh Khan",
    "wof:placetype":"locality"
},
  "geometry": {"coordinates":[67.99974,28.43181],"type":"Point"}
}