{
  "type": "Feature",
  "properties": {
    "gn:admin1_code":"4",
    "gn:asciiname":"Jatki Basti",
    "gn:country_code":"PK",
    "gn:dem":90,
    "gn:feature_class":"P",
    "gn:feature_code":"PPL",
    "gn:name":"Jatki Basti",
    "gn:population":0,
    "gn:timezone":"Asia/Karachi",
    "iso:country":"PK",
    "name:und_x_variant":[
        "Basti Jatk\u012bw\u0101li"
    ],
    "wof:name":"Jatki Basti",
    "wof:placetype":"neighbourhood"
},
  "geometry": {"coordinates":[70.67386,28.63335],"type":"Point"}
}