{
  "type": "Feature",
  "properties": {
    "gn:admin1_code":"4",
    "gn:asciiname":"Chak Thirty-eight Dolewala Branch",
    "gn:country_code":"PK",
    "gn:dem":196,
    "gn:feature_class":"P",
    "gn:feature_code":"PPL",
    "gn:name":"Chak Thirty-eight Dolewala Branch",
    "gn:population":0,
    "gn:timezone":"Asia/Karachi",
    "iso:country":"PK",
    "name:und_x_variant":[
        "Chak Thirty-eight DB"
    ],
    "wof:name":"Chak Thirty-eight Dolewala Branch",
    "wof:placetype":"locality"
},
  "geometry": {"coordinates":[71.74069,32.22908],"type":"Point"}
}