{
  "type": "Feature",
  "properties": {
    "gn:admin1_code":"2.0",
    "gn:asciiname":"Kili Adam Khan",
    "gn:country_code":"PK",
    "gn:dem":1355,
    "gn:feature_class":"P",
    "gn:feature_code":"PPL",
    "gn:name":"Kili Adam Khan",
    "gn:population":0,
    "gn:timezone":"Asia/Karachi",
    "iso:country":"PK",
    "wof:name":"Kili Adam Khan",
    "wof:placetype":"locality"
},
  "geometry": {"coordinates":[65.46880999999999,27.41309],"type":"Point"}
}