{
  "type": "Feature",
  "properties": {
    "gn:admin1_code":"4.0",
    "gn:asciiname":"Mohra Faizullah",
    "gn:country_code":"PK",
    "gn:dem":504,
    "gn:feature_class":"P",
    "gn:feature_code":"PPL",
    "gn:name":"Mohra Faizullah",
    "gn:population":0,
    "gn:timezone":"Asia/Karachi",
    "iso:country":"PK",
    "name:und_x_variant":[
        "Mohra Faizull\u0101h"
    ],
    "wof:name":"Mohra Faizullah",
    "wof:placetype":"locality"
},
  "geometry": {"coordinates":[73.30726999999997,33.52945],"type":"Point"}
}