{
  "type": "Feature",
  "properties": {
    "iso:country":"PK",
    "name:unk_x_variant":[
        "Farooka"
    ],
    "qs:gn_country":"PK",
    "qs:gn_fcode":"PPL",
    "qs:gn_pop":21747,
    "qs:name":"Faruka",
    "qs:name_adm0":"Pakistan",
    "qs:name_adm1":"Punjab",
    "qs:photos":0,
    "qs:photos_1k":0,
    "qs:photos_9k":0,
    "qs:photos_9r":0,
    "qs:photos_all":0,
    "qs:photos_sr":0,
    "qs:placetype":"Town",
    "qs:pop_sr":"7",
    "qs:woe_adm0":23424922,
    "wof:name":"Faruka",
    "wof:placetype":"locality",
    "wof:population":21747
},
  "geometry": {"coordinates":[72.4144,31.88722],"type":"Point"}
}