{
  "type": "Feature",
  "properties": {
    "gn:admin1_code":"5",
    "gn:asciiname":"Wali Dad Khosa",
    "gn:country_code":"PK",
    "gn:dem":62,
    "gn:feature_class":"P",
    "gn:feature_code":"PPL",
    "gn:name":"Wali D\u0101d Khosa",
    "gn:population":0,
    "gn:timezone":"Asia/Karachi",
    "iso:country":"PK",
    "wof:name":"Wali Dad Khosa",
    "wof:placetype":"locality"
},
  "geometry": {"coordinates":[68.90000000000001,28.33611],"type":"Point"}
}