{
  "type": "Feature",
  "properties": {
    "gn:admin1_code":"4",
    "gn:asciiname":"Kotli Jalainai",
    "gn:country_code":"PK",
    "gn:dem":226,
    "gn:feature_class":"P",
    "gn:feature_code":"PPL",
    "gn:name":"Kotli Jalainai",
    "gn:population":0,
    "gn:timezone":"Asia/Karachi",
    "iso:country":"PK",
    "wof:name":"Kotli Jalainai",
    "wof:placetype":"neighbourhood"
},
  "geometry": {"coordinates":[74.16233,32.19867],"type":"Point"}
}