{
  "type": "Feature",
  "properties": {
    "gn:admin1_code":"5",
    "gn:asciiname":"Goth Dindani",
    "gn:country_code":"PK",
    "gn:dem":48,
    "gn:feature_class":"P",
    "gn:feature_code":"PPL",
    "gn:name":"Goth Dindani",
    "gn:population":0,
    "gn:timezone":"Asia/Karachi",
    "iso:country":"PK",
    "wof:name":"Goth Dindani",
    "wof:placetype":"locality"
},
  "geometry": {"coordinates":[68.20623000000001,27.08687],"type":"Point"}
}