{
  "type": "Feature",
  "properties": {
    "gn:admin1_code":"2.0",
    "gn:asciiname":"Kili Rustam",
    "gn:country_code":"PK",
    "gn:dem":2014,
    "gn:feature_class":"P",
    "gn:feature_code":"PPL",
    "gn:name":"Kili Rustam",
    "gn:population":0,
    "gn:timezone":"Asia/Karachi",
    "iso:country":"PK",
    "wof:name":"Kili Rustam",
    "wof:placetype":"locality"
},
  "geometry": {"coordinates":[68.90801999999999,31.35976],"type":"Point"}
}