{
  "type": "Feature",
  "properties": {
    "gn:admin1_code":"01",
    "gn:asciiname":"Chag Zhawar",
    "gn:country_code":"PK",
    "gn:dem":2568,
    "gn:feature_class":"P",
    "gn:feature_code":"PPL",
    "gn:name":"Chag Zhawar",
    "gn:population":0,
    "gn:timezone":"Asia/Karachi",
    "iso:country":"PK",
    "wof:name":"Chag Zhawar",
    "wof:placetype":"locality"
},
  "geometry": {"coordinates":[69.70411999999999,32.56766],"type":"Point"}
}