{
  "type": "Feature",
  "properties": {
    "gn:admin1_code":"3",
    "gn:asciiname":"Akhora",
    "gn:country_code":"PK",
    "gn:dem":1386,
    "gn:feature_class":"P",
    "gn:feature_code":"PPL",
    "gn:name":"Akhora",
    "gn:population":0,
    "gn:timezone":"Asia/Karachi",
    "iso:country":"PK",
    "wof:name":"Akhora",
    "wof:placetype":"locality"
},
  "geometry": {"coordinates":[73.39521999999999,34.6104],"type":"Point"}
}