{
  "type": "Feature",
  "properties": {
    "gn:admin1_code":"4.0",
    "gn:asciiname":"Khu Mehranwala",
    "gn:country_code":"PK",
    "gn:dem":173,
    "gn:feature_class":"P",
    "gn:feature_code":"PPL",
    "gn:name":"Khu Mehr\u0101nw\u0101la",
    "gn:population":0,
    "gn:timezone":"Asia/Karachi",
    "iso:country":"PK",
    "wof:name":"Khu Mehranwala",
    "wof:placetype":"locality"
},
  "geometry": {"coordinates":[73.34056,30.84278],"type":"Point"}
}