{
  "type": "Feature",
  "properties": {
    "gn:admin1_code":"1",
    "gn:asciiname":"Nir Babo",
    "gn:country_code":"PK",
    "gn:dem":1572,
    "gn:feature_class":"P",
    "gn:feature_code":"PPL",
    "gn:name":"Nir Babo",
    "gn:population":0,
    "gn:timezone":"Asia/Karachi",
    "iso:country":"PK",
    "wof:name":"Nir Babo",
    "wof:placetype":"locality"
},
  "geometry": {"coordinates":[69.89,32.48222],"type":"Point"}
}