{
  "type": "Feature",
  "properties": {
    "gn:admin1_code":"4",
    "gn:asciiname":"Sultanwala",
    "gn:country_code":"PK",
    "gn:dem":111,
    "gn:feature_class":"P",
    "gn:feature_code":"PPL",
    "gn:name":"Sultanwala",
    "gn:population":0,
    "gn:timezone":"Asia/Karachi",
    "iso:country":"PK",
    "name:eng_x_preferred":[
        "Sultanwala"
    ],
    "wof:name":"Sultanwala",
    "wof:placetype":"locality"
},
  "geometry": {"coordinates":[71.51824000000001,29.19521],"type":"Point"}
}