{
  "type": "Feature",
  "properties": {
    "gn:admin1_code":"3.0",
    "gn:asciiname":"Jhandu Khel",
    "gn:country_code":"PK",
    "gn:dem":324,
    "gn:feature_class":"P",
    "gn:feature_code":"PPL",
    "gn:name":"Jhandu Khel",
    "gn:population":0,
    "gn:timezone":"Asia/Karachi",
    "iso:country":"PK",
    "name:und_x_variant":[
        "Jandu Khel",
        "Jhandu Khel"
    ],
    "wof:name":"Jhandu Khel",
    "wof:placetype":"locality"
},
  "geometry": {"coordinates":[70.71387,32.95176],"type":"Point"}
}