{
  "type": "Feature",
  "properties": {
    "gn:admin1_code":"5.0",
    "gn:asciiname":"Adam Sehta",
    "gn:country_code":"PK",
    "gn:dem":8,
    "gn:feature_class":"P",
    "gn:feature_code":"PPL",
    "gn:name":"Adam Sehta",
    "gn:population":0,
    "gn:timezone":"Asia/Karachi",
    "iso:country":"PK",
    "name:eng_x_preferred":[
        "Adam Sehta"
    ],
    "wof:name":"Adam Sehta",
    "wof:placetype":"locality"
},
  "geometry": {"coordinates":[68.06421999999999,24.68241],"type":"Point"}
}