{
  "type": "Feature",
  "properties": {
    "gn:admin1_code":"4",
    "gn:asciiname":"Sialanwala",
    "gn:country_code":"PK",
    "gn:dem":148,
    "gn:feature_class":"P",
    "gn:feature_code":"PPL",
    "gn:name":"Sialanwala",
    "gn:population":0,
    "gn:timezone":"Asia/Karachi",
    "iso:country":"PK",
    "name:und_x_variant":[
        "Si\u0101l\u0101n"
    ],
    "wof:name":"Sialanwala",
    "wof:placetype":"locality"
},
  "geometry": {"coordinates":[72.46500999999998,30.64894],"type":"Point"}
}