{
  "type": "Feature",
  "properties": {
    "gn:admin1_code":"4.0",
    "gn:asciiname":"Rahmatabad",
    "gn:country_code":"PK",
    "gn:dem":228,
    "gn:feature_class":"P",
    "gn:feature_code":"PPL",
    "gn:name":"Rahmatabad",
    "gn:population":0,
    "gn:timezone":"Asia/Karachi",
    "iso:country":"PK",
    "name:ceb_x_preferred":[
        "Rahmatabad"
    ],
    "name:fas_x_preferred":[
        "\u0631\u062d\u0645\u062a\u200c\u0622\u0628\u0627\u062f"
    ],
    "name:swe_x_preferred":[
        "Rahmatabad"
    ],
    "wof:name":"Rahmatabad",
    "wof:placetype":"neighbourhood"
},
  "geometry": {"coordinates":[74.09659000000001,32.56063],"type":"Point"}
}