{
  "type": "Feature",
  "properties": {
    "gn:admin1_code":"4",
    "gn:asciiname":"Bakhuwala",
    "gn:country_code":"PK",
    "gn:dem":196,
    "gn:feature_class":"P",
    "gn:feature_code":"PPL",
    "gn:name":"Bakhuwala",
    "gn:population":0,
    "gn:timezone":"Asia/Karachi",
    "iso:country":"PK",
    "name:fas_x_preferred":[
        "\u0628\u06a9\u0647\u0648\u0648\u0627\u0644\u0627"
    ],
    "name:und_x_variant":[
        "Bukkhuw\u0101la"
    ],
    "wof:name":"Bakhuwala",
    "wof:placetype":"locality"
},
  "geometry": {"coordinates":[73.13136,32.08065],"type":"Point"}
}