{
  "type": "Feature",
  "properties": {
    "gn:admin1_code":"04",
    "gn:asciiname":"Salohke",
    "gn:country_code":"PK",
    "gn:dem":217,
    "gn:feature_class":"P",
    "gn:feature_code":"PPL",
    "gn:name":"Salohke",
    "gn:population":0,
    "gn:timezone":"Asia/Karachi",
    "iso:country":"PK",
    "name:und_x_variant":[
        "Salhoke"
    ],
    "wof:name":"Salohke",
    "wof:placetype":"locality"
},
  "geometry": {"coordinates":[73.83515,32.34542],"type":"Point"}
}