{
  "type": "Feature",
  "properties": {
    "gn:admin1_code":"4",
    "gn:asciiname":"Budhu Dhar",
    "gn:country_code":"PK",
    "gn:dem":155,
    "gn:feature_class":"P",
    "gn:feature_code":"PPL",
    "gn:name":"Budhu Dhar",
    "gn:population":0,
    "gn:timezone":"Asia/Karachi",
    "iso:country":"PK",
    "name:und_x_variant":[
        "Buddu Dhar",
        "Budhu Dhar"
    ],
    "wof:name":"Budhu Dhar",
    "wof:placetype":"locality"
},
  "geometry": {"coordinates":[70.89784,31.26742],"type":"Point"}
}