{
  "type": "Feature",
  "properties": {
    "gn:admin1_code":"4.0",
    "gn:asciiname":"Basti Riasat Bahadur Khan",
    "gn:country_code":"PK",
    "gn:dem":87,
    "gn:feature_class":"P",
    "gn:feature_code":"PPL",
    "gn:name":"Basti Ri\u0101sat Bah\u0101dur Kh\u0101n",
    "gn:population":0,
    "gn:timezone":"Asia/Karachi",
    "iso:country":"PK",
    "wof:name":"Basti Riasat Bahadur Khan",
    "wof:placetype":"locality"
},
  "geometry": {"coordinates":[70.74722,28.69444],"type":"Point"}
}