{
  "type": "Feature",
  "properties": {
    "gn:admin1_code":"4.0",
    "gn:asciiname":"Mohra Moradu",
    "gn:country_code":"PK",
    "gn:dem":515,
    "gn:feature_class":"P",
    "gn:feature_code":"PPL",
    "gn:name":"Mohra Moradu",
    "gn:population":0,
    "gn:timezone":"Asia/Karachi",
    "iso:country":"PK",
    "wof:name":"Mohra Moradu",
    "wof:placetype":"locality"
},
  "geometry": {"coordinates":[72.86050999999998,33.76835999999999],"type":"Point"}
}