{
  "type": "Feature",
  "properties": {
    "gn:admin1_code":"6",
    "gn:asciiname":"Ari",
    "gn:country_code":"PK",
    "gn:dem":2282,
    "gn:feature_class":"P",
    "gn:feature_code":"PPL",
    "gn:name":"Ari",
    "gn:population":0,
    "gn:timezone":"Asia/Karachi",
    "iso:country":"PK",
    "name:cat_x_preferred":[
        "Ari"
    ],
    "name:ceb_x_preferred":[
        "Ari"
    ],
    "name:heb_x_preferred":[
        "\u05d0\u05e8\u05d9"
    ],
    "name:ita_x_preferred":[
        "Ari"
    ],
    "name:lim_x_preferred":[
        "Ari"
    ],
    "name:nld_x_preferred":[
        "Ari"
    ],
    "name:pol_x_preferred":[
        "Ari"
    ],
    "name:por_x_preferred":[
        "Ari"
    ],
    "name:rus_x_preferred":[
        "\u0410\u0440\u0438"
    ],
    "name:slk_x_preferred":[
        "Ari"
    ],
    "name:srp_x_preferred":[
        "\u0410\u0440\u0438"
    ],
    "name:swe_x_preferred":[
        "Ari"
    ],
    "name:ukr_x_preferred":[
        "\u0410\u0440\u0456"
    ],
    "name:und_x_variant":[
        "Ari Dhok"
    ],
    "name:zho_x_preferred":[
        "Ari"
    ],
    "wof:name":"Ari",
    "wof:placetype":"locality"
},
  "geometry": {"coordinates":[74.15071,33.86215],"type":"Point"}
}