{
  "type": "Feature",
  "properties": {
    "gn:admin1_code":"2.0",
    "gn:asciiname":"Nawab Shah",
    "gn:country_code":"PK",
    "gn:dem":1010,
    "gn:feature_class":"P",
    "gn:feature_code":"PPL",
    "gn:name":"Nawab Shah",
    "gn:population":0,
    "gn:timezone":"Asia/Karachi",
    "iso:country":"PK",
    "wof:name":"Nawab Shah",
    "wof:placetype":"locality"
},
  "geometry": {"coordinates":[69.31695000000001,29.77146],"type":"Point"}
}