{
  "type": "Feature",
  "properties": {
    "gn:admin1_code":"4.0",
    "gn:asciiname":"Chak One Hundred Eighty-nine",
    "gn:country_code":"PK",
    "gn:dem":163,
    "gn:feature_class":"P",
    "gn:feature_code":"PPL",
    "gn:name":"Chak One Hundred Eighty-nine",
    "gn:population":0,
    "gn:timezone":"Asia/Karachi",
    "iso:country":"PK",
    "name:und_x_variant":[
        "Chak Eighteen",
        "Patli",
        "Chak One Hundred Eighty-nine"
    ],
    "wof:name":"Chak One Hundred Eighty-nine",
    "wof:placetype":"locality"
},
  "geometry": {"coordinates":[72.70401,30.81],"type":"Point"}
}