{
  "type": "Feature",
  "properties": {
    "gn:admin1_code":"03",
    "gn:asciiname":"Ughuti",
    "gn:country_code":"PK",
    "gn:dem":2623,
    "gn:feature_class":"P",
    "gn:feature_code":"PPL",
    "gn:name":"Ughuti",
    "gn:population":0,
    "gn:timezone":"Asia/Karachi",
    "iso:country":"PK",
    "name:und_x_variant":[
        "Ughuthi"
    ],
    "wof:name":"Ughuti",
    "wof:placetype":"locality"
},
  "geometry": {"coordinates":[71.46356,36.00459],"type":"Point"}
}