{
  "type": "Feature",
  "properties": {
    "gn:admin1_code":"3.0",
    "gn:asciiname":"isa Khel",
    "gn:country_code":"PK",
    "gn:dem":798,
    "gn:feature_class":"P",
    "gn:feature_code":"PPL",
    "gn:name":"isa Khel",
    "gn:population":0,
    "gn:timezone":"Asia/Karachi",
    "iso:country":"PK",
    "name:und_x_variant":[
        "Bar Jangal"
    ],
    "wof:name":"isa Khel",
    "wof:placetype":"locality"
},
  "geometry": {"coordinates":[71.15900999999999,33.6199],"type":"Point"}
}