{
  "type": "Feature",
  "properties": {
    "gn:admin1_code":"6",
    "gn:asciiname":"Hariala Gujaran",
    "gn:country_code":"PK",
    "gn:dem":1732,
    "gn:feature_class":"P",
    "gn:feature_code":"PPL",
    "gn:name":"Hariala Gujaran",
    "gn:population":0,
    "gn:timezone":"Asia/Karachi",
    "iso:country":"PK",
    "name:und_x_variant":[
        "H\u0101ry\u0101la Guj"
    ],
    "wof:name":"Hariala Gujaran",
    "wof:placetype":"locality"
},
  "geometry": {"coordinates":[73.62526,34.30232],"type":"Point"}
}