{
  "type": "Feature",
  "properties": {
    "gn:admin1_code":"5",
    "gn:asciiname":"Goth Dil Murad Khan",
    "gn:country_code":"PK",
    "gn:dem":55,
    "gn:feature_class":"P",
    "gn:feature_code":"PPL",
    "gn:name":"Goth Dil Mur\u0101d Kh\u0101n",
    "gn:population":0,
    "gn:timezone":"Asia/Karachi",
    "iso:country":"PK",
    "wof:name":"Goth Dil Murad Khan",
    "wof:placetype":"locality"
},
  "geometry": {"coordinates":[68.32778,27.99861],"type":"Point"}
}