{
  "type": "Feature",
  "properties": {
    "gn:admin1_code":"04",
    "gn:asciiname":"Rai Khurd",
    "gn:country_code":"PK",
    "gn:dem":211,
    "gn:feature_class":"P",
    "gn:feature_code":"PPL",
    "gn:name":"Rai Khurd",
    "gn:population":0,
    "gn:timezone":"Asia/Karachi",
    "iso:country":"PK",
    "name:und_x_variant":[
        "R\u0101i"
    ],
    "wof:name":"Rai Khurd",
    "wof:placetype":"locality"
},
  "geometry": {"coordinates":[74.48565000000001,31.31881],"type":"Point"}
}