{
  "type": "Feature",
  "properties": {
    "gn:admin1_code":"4.0",
    "gn:asciiname":"Qila Ratianwala",
    "gn:country_code":"PK",
    "gn:dem":216,
    "gn:feature_class":"P",
    "gn:feature_code":"PPL",
    "gn:name":"Qila Ratianwala",
    "gn:population":0,
    "gn:timezone":"Asia/Karachi",
    "iso:country":"PK",
    "name:und_x_variant":[
        "Qila Bhatti\u0101nw\u0101la"
    ],
    "wof:name":"Qila Ratianwala",
    "wof:placetype":"locality"
},
  "geometry": {"coordinates":[74.22371,31.81846],"type":"Point"}
}