{
  "type": "Feature",
  "properties": {
    "gn:admin1_code":"5",
    "gn:asciiname":"Kinjhar",
    "gn:country_code":"PK",
    "gn:dem":72,
    "gn:feature_class":"P",
    "gn:feature_code":"PPL",
    "gn:name":"Kinjhar",
    "gn:population":0,
    "gn:timezone":"Asia/Karachi",
    "iso:country":"PK",
    "name:und_x_variant":[
        "Kinihar"
    ],
    "wof:name":"Kinjhar",
    "wof:placetype":"locality"
},
  "geometry": {"coordinates":[69.58574,28.10627],"type":"Point"}
}