{
  "type": "Feature",
  "properties": {
    "gn:admin1_code":"4",
    "gn:asciiname":"Shahana Dera",
    "gn:country_code":"PK",
    "gn:dem":202,
    "gn:feature_class":"P",
    "gn:feature_code":"PPL",
    "gn:name":"Shahana Dera",
    "gn:population":0,
    "gn:timezone":"Asia/Karachi",
    "iso:country":"PK",
    "name:und_x_variant":[
        "Sh\u0101n\u0101na Dera",
        "Qila Deva Singh",
        "Shahana Dera"
    ],
    "wof:name":"Shahana Dera",
    "wof:placetype":"locality"
},
  "geometry": {"coordinates":[73.5817,31.83105],"type":"Point"}
}