{
  "type": "Feature",
  "properties": {
    "gn:admin1_code":"1.0",
    "gn:asciiname":"Kaka Ziarat",
    "gn:country_code":"PK",
    "gn:dem":856,
    "gn:feature_class":"P",
    "gn:feature_code":"PPL",
    "gn:name":"Kaka Ziarat",
    "gn:population":0,
    "gn:timezone":"Asia/Karachi",
    "iso:country":"PK",
    "wof:name":"Kaka Ziarat",
    "wof:placetype":"locality"
},
  "geometry": {"coordinates":[70.27685,33.23792],"type":"Point"}
}