{
  "type": "Feature",
  "properties": {
    "gn:admin1_code":"3.0",
    "gn:asciiname":"Gali",
    "gn:country_code":"PK",
    "gn:dem":1079,
    "gn:feature_class":"P",
    "gn:feature_code":"PPL",
    "gn:name":"Gali",
    "gn:population":0,
    "gn:timezone":"Asia/Karachi",
    "iso:country":"PK",
    "name:und_x_variant":[
        "Gehli"
    ],
    "wof:name":"Gali",
    "wof:placetype":"locality"
},
  "geometry": {"coordinates":[73.09210999999998,34.15646],"type":"Point"}
}