{
  "type": "Feature",
  "properties": {
    "gn:admin1_code":"3.0",
    "gn:asciiname":"Jaffarabad",
    "gn:country_code":"PK",
    "gn:dem":412,
    "gn:feature_class":"P",
    "gn:feature_code":"PPL",
    "gn:name":"Jaffarabad",
    "gn:population":0,
    "gn:timezone":"Asia/Karachi",
    "iso:country":"PK",
    "wof:name":"Jaffarabad",
    "wof:placetype":"locality"
},
  "geometry": {"coordinates":[72.04219000000001,33.82225],"type":"Point"}
}