{
  "type": "Feature",
  "properties": {
    "gn:admin1_code":"4.0",
    "gn:asciiname":"Jhangar Galotran",
    "gn:country_code":"PK",
    "gn:dem":188,
    "gn:feature_class":"P",
    "gn:feature_code":"PPL",
    "gn:name":"Jhangar Galotran",
    "gn:population":0,
    "gn:timezone":"Asia/Karachi",
    "iso:country":"PK",
    "name:und_x_variant":[
        "Jhangar Gilotr\u0101n"
    ],
    "wof:name":"Jhangar Galotran",
    "wof:placetype":"locality"
},
  "geometry": {"coordinates":[73.13025999999998,31.83611],"type":"Point"}
}