{
  "type": "Feature",
  "properties": {
    "gn:admin1_code":"3",
    "gn:asciiname":"Mulla Pafa",
    "gn:country_code":"PK",
    "gn:dem":1698,
    "gn:feature_class":"P",
    "gn:feature_code":"PPL",
    "gn:name":"Mulla Pafa",
    "gn:population":0,
    "gn:timezone":"Asia/Karachi",
    "iso:country":"PK",
    "wof:name":"Mulla Pafa",
    "wof:placetype":"locality"
},
  "geometry": {"coordinates":[72.27913000000002,34.91492],"type":"Point"}
}