{
  "type": "Feature",
  "properties": {
    "gn:admin1_code":"5",
    "gn:asciiname":"Amir Bakhsh Sial",
    "gn:country_code":"PK",
    "gn:dem":57,
    "gn:feature_class":"P",
    "gn:feature_code":"PPL",
    "gn:name":"Amir Bakhsh Sial",
    "gn:population":0,
    "gn:timezone":"Asia/Karachi",
    "iso:country":"PK",
    "wof:name":"Amir Bakhsh Sial",
    "wof:placetype":"locality"
},
  "geometry": {"coordinates":[68.44701999999999,27.49413],"type":"Point"}
}