{
  "type": "Feature",
  "properties": {
    "gn:admin1_code":"5",
    "gn:asciiname":"Goth Kingoro",
    "gn:country_code":"PK",
    "gn:dem":16,
    "gn:feature_class":"P",
    "gn:feature_code":"PPL",
    "gn:name":"Goth Kingoro",
    "gn:population":0,
    "gn:timezone":"Asia/Karachi",
    "iso:country":"PK",
    "name:und_x_variant":[
        "Kangora"
    ],
    "wof:name":"Goth Kingoro",
    "wof:placetype":"locality"
},
  "geometry": {"coordinates":[69.03423000000001,25.23888],"type":"Point"}
}