{
  "type": "Feature",
  "properties": {
    "gn:admin1_code":"6",
    "gn:asciiname":"Khuind",
    "gn:country_code":"PK",
    "gn:dem":2815,
    "gn:feature_class":"P",
    "gn:feature_code":"PPL",
    "gn:name":"Khuind",
    "gn:population":0,
    "gn:timezone":"Asia/Karachi",
    "iso:country":"PK",
    "name:und_x_variant":[
        "Kund"
    ],
    "wof:name":"Khuind",
    "wof:placetype":"locality"
},
  "geometry": {"coordinates":[73.70425999999998,34.29628],"type":"Point"}
}