{
  "type": "Feature",
  "properties": {
    "gn:admin1_code":"5",
    "gn:asciiname":"Saleh Brahui",
    "gn:country_code":"PK",
    "gn:dem":55,
    "gn:feature_class":"P",
    "gn:feature_code":"PPL",
    "gn:name":"Saleh Brahui",
    "gn:population":0,
    "gn:timezone":"Asia/Karachi",
    "iso:country":"PK",
    "name:und_x_variant":[
        "Bhat\u0101ro Brah\u016bi",
        "Betaro Brohi",
        "Bhat\u0101o Brah\u016bi",
        "Saleh Brahui"
    ],
    "wof:name":"Saleh Brahui",
    "wof:placetype":"locality"
},
  "geometry": {"coordinates":[68.22235999999999,27.59731],"type":"Point"}
}