{
  "type": "Feature",
  "properties": {
    "gn:admin1_code":"2.0",
    "gn:asciiname":"Habibullah Kili",
    "gn:country_code":"PK",
    "gn:dem":1512,
    "gn:feature_class":"P",
    "gn:feature_code":"PPL",
    "gn:name":"Habibullah Kili",
    "gn:population":0,
    "gn:timezone":"Asia/Karachi",
    "iso:country":"PK",
    "wof:name":"Habibullah Kili",
    "wof:placetype":"locality"
},
  "geometry": {"coordinates":[68.60348,30.77868],"type":"Point"}
}