{
  "type": "Feature",
  "properties": {
    "gn:admin1_code":"2.0",
    "gn:asciiname":"Kili Ramzan",
    "gn:country_code":"PK",
    "gn:dem":1670,
    "gn:feature_class":"P",
    "gn:feature_code":"PPL",
    "gn:name":"Kili Ramzan",
    "gn:population":0,
    "gn:timezone":"Asia/Karachi",
    "iso:country":"PK",
    "wof:name":"Kili Ramzan",
    "wof:placetype":"neighbourhood"
},
  "geometry": {"coordinates":[66.95577,30.19888],"type":"Point"}
}