{
  "type": "Feature",
  "properties": {
    "gn:admin1_code":"4.0",
    "gn:asciiname":"Bhindewala",
    "gn:country_code":"PK",
    "gn:dem":116,
    "gn:feature_class":"P",
    "gn:feature_code":"PPL",
    "gn:name":"Bhindewala",
    "gn:population":0,
    "gn:timezone":"Asia/Karachi",
    "iso:country":"PK",
    "wof:name":"Bhindewala",
    "wof:placetype":"locality"
},
  "geometry": {"coordinates":[71.22211,30.0185],"type":"Point"}
}