{
  "type": "Feature",
  "properties": {
    "gn:admin1_code":"03",
    "gn:asciiname":"Kaga",
    "gn:country_code":"PK",
    "gn:dem":1299,
    "gn:feature_class":"P",
    "gn:feature_code":"PPL",
    "gn:name":"Kaga",
    "gn:population":0,
    "gn:timezone":"Asia/Karachi",
    "iso:country":"PK",
    "name:eng_x_preferred":[
        "Kaga"
    ],
    "wof:name":"Kaga",
    "wof:placetype":"locality"
},
  "geometry": {"coordinates":[71.85474000000001,34.95157],"type":"Point"}
}