{
  "type": "Feature",
  "properties": {
    "gn:admin1_code":"2.0",
    "gn:asciiname":"Khuda Bakhsh",
    "gn:country_code":"PK",
    "gn:dem":354,
    "gn:feature_class":"P",
    "gn:feature_code":"PPL",
    "gn:name":"Khuda Bakhsh",
    "gn:population":0,
    "gn:timezone":"Asia/Karachi",
    "iso:country":"PK",
    "wof:name":"Khuda Bakhsh",
    "wof:placetype":"locality"
},
  "geometry": {"coordinates":[65.57568000000001,26.28354],"type":"Point"}
}