{
  "type": "Feature",
  "properties": {
    "gn:admin1_code":"3",
    "gn:asciiname":"Patha",
    "gn:country_code":"PK",
    "gn:dem":1727,
    "gn:feature_class":"P",
    "gn:feature_code":"PPL",
    "gn:name":"Patha",
    "gn:population":0,
    "gn:timezone":"Asia/Karachi",
    "iso:country":"PK",
    "wof:name":"Patha",
    "wof:placetype":"locality"
},
  "geometry": {"coordinates":[73.40056,34.62984],"type":"Point"}
}