{
  "type": "Feature",
  "properties": {
    "gn:admin1_code":"2.0",
    "gn:asciiname":"Shahi Masjid",
    "gn:country_code":"PK",
    "gn:dem":2024,
    "gn:feature_class":"P",
    "gn:feature_code":"PPL",
    "gn:name":"Shahi Masjid",
    "gn:population":0,
    "gn:timezone":"Asia/Karachi",
    "iso:country":"PK",
    "wof:name":"Shahi Masjid",
    "wof:placetype":"locality"
},
  "geometry": {"coordinates":[66.59354999999999,29.01808],"type":"Point"}
}