{
  "type": "Feature",
  "properties": {
    "gn:admin1_code":"5.0",
    "gn:asciiname":"Goth Sain Bakhsh Tangri",
    "gn:country_code":"PK",
    "gn:dem":20,
    "gn:feature_class":"P",
    "gn:feature_code":"PPL",
    "gn:name":"Goth Sain Bakhsh Tangri",
    "gn:population":0,
    "gn:timezone":"Asia/Karachi",
    "iso:country":"PK",
    "wof:name":"Goth Sain Bakhsh Tangri",
    "wof:placetype":"locality"
},
  "geometry": {"coordinates":[68.59732,25.23492],"type":"Point"}
}