{
  "type": "Feature",
  "properties": {
    "gn:admin1_code":"4",
    "gn:asciiname":"Nuran",
    "gn:country_code":"PK",
    "gn:dem":99,
    "gn:feature_class":"P",
    "gn:feature_code":"PPL",
    "gn:name":"Nuran",
    "gn:population":0,
    "gn:timezone":"Asia/Karachi",
    "iso:country":"PK",
    "name:aze_x_preferred":[
        "Nuran"
    ],
    "name:kat_x_preferred":[
        "\u10dc\u10e3\u10e0\u10d0\u10dc\u10d8"
    ],
    "wof:name":"Nuran",
    "wof:placetype":"locality"
},
  "geometry": {"coordinates":[70.44444,29.33056],"type":"Point"}
}