{
  "type": "Feature",
  "properties": {
    "gn:admin1_code":"3",
    "gn:asciiname":"Sarila",
    "gn:country_code":"PK",
    "gn:dem":871,
    "gn:feature_class":"P",
    "gn:feature_code":"PPL",
    "gn:name":"Sarila",
    "gn:population":0,
    "gn:timezone":"Asia/Karachi",
    "iso:country":"PK",
    "name:bpy_x_preferred":[
        "\u09b8\u09be\u09b0\u09bf\u09b2\u09be"
    ],
    "name:cat_x_preferred":[
        "Sarila"
    ],
    "name:ceb_x_preferred":[
        "Sar\u012bla"
    ],
    "name:ita_x_preferred":[
        "Sarila"
    ],
    "name:mlg_x_preferred":[
        "Sarila"
    ],
    "name:msa_x_preferred":[
        "Sarila"
    ],
    "name:nld_x_preferred":[
        "Sarila"
    ],
    "name:ori_x_preferred":[
        "\u0b38\u0b30\u0b3f\u0b32\u0b3e"
    ],
    "name:pol_x_preferred":[
        "Sarila"
    ],
    "name:por_x_preferred":[
        "Sarila"
    ],
    "name:swe_x_preferred":[
        "Sar\u012bla"
    ],
    "name:urd_x_preferred":[
        "\u0633\u0631\u06cc\u0644\u0627"
    ],
    "name:vie_x_preferred":[
        "Sarila"
    ],
    "name:zho_x_preferred":[
        "\u8428\u91cc\u62c9"
    ],
    "wof:name":"Sarila",
    "wof:placetype":"locality"
},
  "geometry": {"coordinates":[73.14558000000002,34.00885],"type":"Point"}
}