{
  "type": "Feature",
  "properties": {
    "gn:admin1_code":"3",
    "gn:asciiname":"Sarila",
    "gn:country_code":"PK",
    "gn:dem":871,
    "gn:feature_class":"P",
    "gn:feature_code":"PPL",
    "gn:name":"Sarila",
    "gn:population":0,
    "gn:timezone":"Asia/Karachi",
    "iso:country":"PK",
    "wof:name":"Sarila",
    "wof:placetype":"locality"
},
  "geometry": {"coordinates":[73.14558000000002,34.00885],"type":"Point"}
}