{
  "type": "Feature",
  "properties": {
    "gn:admin1_code":"4.0",
    "gn:asciiname":"Patian",
    "gn:country_code":"PK",
    "gn:dem":633,
    "gn:feature_class":"P",
    "gn:feature_code":"PPL",
    "gn:name":"Patian",
    "gn:population":0,
    "gn:timezone":"Asia/Karachi",
    "iso:country":"PK",
    "wof:name":"Patian",
    "wof:placetype":"locality"
},
  "geometry": {"coordinates":[73.45078000000002,33.61572],"type":"Point"}
}