{
  "type": "Feature",
  "properties": {
    "gn:admin1_code":"1.0",
    "gn:asciiname":"Kandaro",
    "gn:country_code":"PK",
    "gn:dem":875,
    "gn:feature_class":"P",
    "gn:feature_code":"PPL",
    "gn:name":"Kandaro",
    "gn:population":0,
    "gn:timezone":"Asia/Karachi",
    "iso:country":"PK",
    "name:eng_x_preferred":[
        "Kandaro"
    ],
    "wof:name":"Kandaro",
    "wof:placetype":"locality"
},
  "geometry": {"coordinates":[71.56870000000001,34.83903],"type":"Point"}
}