{
  "type": "Feature",
  "properties": {
    "gn:admin1_code":"02",
    "gn:asciiname":"Zat",
    "gn:country_code":"PK",
    "gn:dem":6,
    "gn:feature_class":"P",
    "gn:feature_code":"PPL",
    "gn:name":"Zat",
    "gn:population":0,
    "gn:timezone":"Asia/Karachi",
    "iso:country":"PK",
    "name:fra_x_preferred":[
        "Zat"
    ],
    "name:nld_x_preferred":[
        "Zat"
    ],
    "name:und_x_variant":[
        "Zato"
    ],
    "wof:name":"Zat",
    "wof:placetype":"locality"
},
  "geometry": {"coordinates":[64.18866,25.36814],"type":"Point"}
}