{
  "type": "Feature",
  "properties": {
    "gn:admin1_code":"3.0",
    "gn:asciiname":"Hafizabad",
    "gn:country_code":"PK",
    "gn:dem":180,
    "gn:feature_class":"P",
    "gn:feature_code":"PPL",
    "gn:name":"Hafizabad",
    "gn:population":0,
    "gn:timezone":"Asia/Karachi",
    "iso:country":"PK",
    "name:bel_x_preferred":[
        "\u0425\u0430\u0444\u0456\u0437\u0430\u0431\u0430\u0434"
    ],
    "name:ceb_x_preferred":[
        "H\u0101fiz\u0101b\u0101d"
    ],
    "name:deu_x_preferred":[
        "Hafizabad"
    ],
    "name:eng_x_preferred":[
        "Hafizabad"
    ],
    "name:fas_x_preferred":[
        "\u062d\u0627\u0641\u0638\u200c\u0622\u0628\u0627\u062f"
    ],
    "name:fra_x_preferred":[
        "Hafizabad"
    ],
    "name:pnb_x_preferred":[
        "\u062d\u0627\u0641\u0638 \u0622\u0628\u0627\u062f"
    ],
    "name:pol_x_preferred":[
        "Hafizabad"
    ],
    "name:por_x_preferred":[
        "Hafizabad"
    ],
    "name:pus_x_preferred":[
        "\u062d\u0627\u0641\u0638 \u0627\u0628\u0627\u062f"
    ],
    "name:rus_x_preferred":[
        "\u0425\u0430\u0444\u0438\u0437\u0430\u0431\u0430\u0434"
    ],
    "name:srp_x_preferred":[
        "\u0425\u0430\u0444\u0438\u0437\u0430\u0431\u0430\u0434"
    ],
    "name:swe_x_preferred":[
        "Hafizabad"
    ],
    "name:urd_x_preferred":[
        "\u062d\u0627\u0641\u0638 \u0622\u0628\u0627\u062f"
    ],
    "name:war_x_preferred":[
        "Hafizabad"
    ],
    "wof:name":"Hafizabad",
    "wof:placetype":"locality"
},
  "geometry": {"coordinates":[71.03574,32.07895],"type":"Point"}
}