{
  "type": "Feature",
  "properties": {
    "gn:admin1_code":"4.0",
    "gn:asciiname":"Bhuckke",
    "gn:country_code":"PK",
    "gn:dem":195,
    "gn:feature_class":"P",
    "gn:feature_code":"PPL",
    "gn:name":"Bhuckke",
    "gn:population":0,
    "gn:timezone":"Asia/Karachi",
    "iso:country":"PK",
    "name:und_x_variant":[
        "Bhuchke"
    ],
    "wof:name":"Bhuckke",
    "wof:placetype":"locality"
},
  "geometry": {"coordinates":[74.40759,31.03715],"type":"Point"}
}