{
  "type": "Feature",
  "properties": {
    "gn:admin1_code":"4",
    "gn:asciiname":"Basti Hayat Khan Khoja",
    "gn:country_code":"PK",
    "gn:dem":127,
    "gn:feature_class":"P",
    "gn:feature_code":"PPL",
    "gn:name":"Basti Hayat Khan Khoja",
    "gn:population":0,
    "gn:timezone":"Asia/Karachi",
    "iso:country":"PK",
    "wof:name":"Basti Hayat Khan Khoja",
    "wof:placetype":"locality"
},
  "geometry": {"coordinates":[72.09860999999999,29.5125],"type":"Point"}
}