{
  "type": "Feature",
  "properties": {
    "gn:admin1_code":"2.0",
    "gn:asciiname":"Sari Tallan",
    "gn:country_code":"PK",
    "gn:dem":904,
    "gn:feature_class":"P",
    "gn:feature_code":"PPL",
    "gn:name":"Sari Tallan",
    "gn:population":0,
    "gn:timezone":"Asia/Karachi",
    "iso:country":"PK",
    "name:und_x_variant":[
        "Sari Tali\u0101n"
    ],
    "wof:name":"Sari Tallan",
    "wof:placetype":"locality"
},
  "geometry": {"coordinates":[63.0814,26.47235],"type":"Point"}
}