{
  "type": "Feature",
  "properties": {
    "gn:admin1_code":"3.0",
    "gn:asciiname":"Gadar",
    "gn:country_code":"PK",
    "gn:dem":1697,
    "gn:feature_class":"P",
    "gn:feature_code":"PPL",
    "gn:name":"Gadar",
    "gn:population":0,
    "gn:timezone":"Asia/Karachi",
    "iso:country":"PK",
    "name:hin_x_preferred":[
        "\u0917\u0926\u0930"
    ],
    "wof:name":"Gadar",
    "wof:placetype":"locality"
},
  "geometry": {"coordinates":[73.1978,35.04869],"type":"Point"}
}