{
  "type": "Feature",
  "properties": {
    "gn:admin1_code":"4.0",
    "gn:asciiname":"Goleki",
    "gn:country_code":"PK",
    "gn:dem":225,
    "gn:feature_class":"P",
    "gn:feature_code":"PPL",
    "gn:name":"Goleki",
    "gn:population":0,
    "gn:timezone":"Asia/Karachi",
    "iso:country":"PK",
    "name:und_x_variant":[
        "Goleke",
        "Goleki"
    ],
    "wof:name":"Goleki",
    "wof:placetype":"locality"
},
  "geometry": {"coordinates":[73.9516,32.45480999999999],"type":"Point"}
}