{
  "type": "Feature",
  "properties": {
    "gn:admin1_code":"4",
    "gn:asciiname":"Dhok Sawan",
    "gn:country_code":"PK",
    "gn:dem":328,
    "gn:feature_class":"P",
    "gn:feature_code":"PPL",
    "gn:name":"Dhok Sawan",
    "gn:population":0,
    "gn:timezone":"Asia/Karachi",
    "iso:country":"PK",
    "name:und_x_variant":[
        "Dhok Saw\u0101n"
    ],
    "wof:name":"Dhok Sawan",
    "wof:placetype":"locality"
},
  "geometry": {"coordinates":[73.44060999999998,33.06287],"type":"Point"}
}