{
  "type": "Feature",
  "properties": {
    "gn:admin1_code":"3.0",
    "gn:asciiname":"Sharafatabad",
    "gn:country_code":"PK",
    "gn:dem":379,
    "gn:feature_class":"P",
    "gn:feature_code":"PPL",
    "gn:name":"Sharafatabad",
    "gn:population":0,
    "gn:timezone":"Asia/Karachi",
    "iso:country":"PK",
    "name:und_x_variant":[
        "Sh\u0101h Gul",
        "Shar\u0101fat\u0101b\u0101d",
        "Sharafatabad"
    ],
    "wof:name":"Sharafatabad",
    "wof:placetype":"locality"
},
  "geometry": {"coordinates":[70.89165,32.96524],"type":"Point"}
}