{
  "type": "Feature",
  "properties": {
    "gn:admin1_code":"2.0",
    "gn:asciiname":"Dost Muhammad",
    "gn:country_code":"PK",
    "gn:dem":1324,
    "gn:feature_class":"P",
    "gn:feature_code":"PPL",
    "gn:name":"Dost Muhammad",
    "gn:population":0,
    "gn:timezone":"Asia/Karachi",
    "iso:country":"PK",
    "wof:name":"Dost Muhammad",
    "wof:placetype":"locality"
},
  "geometry": {"coordinates":[64.97261999999999,27.38168],"type":"Point"}
}