{
  "type": "Feature",
  "properties": {
    "gn:admin1_code":"1.0",
    "gn:asciiname":"Malli Khel",
    "gn:country_code":"PK",
    "gn:dem":1423,
    "gn:feature_class":"P",
    "gn:feature_code":"PPL",
    "gn:name":"Malli Khel",
    "gn:population":0,
    "gn:timezone":"Asia/Karachi",
    "iso:country":"PK",
    "wof:name":"Malli Khel",
    "wof:placetype":"locality"
},
  "geometry": {"coordinates":[70.13297,33.79506],"type":"Point"}
}