{
  "type": "Feature",
  "properties": {
    "gn:admin1_code":"5.0",
    "gn:asciiname":"Goth Ahmad Mahano",
    "gn:country_code":"PK",
    "gn:dem":5,
    "gn:feature_class":"P",
    "gn:feature_code":"PPL",
    "gn:name":"Goth Ahmad Mahano",
    "gn:population":0,
    "gn:timezone":"Asia/Karachi",
    "iso:country":"PK",
    "name:aar_x_preferred":[
        "Goth Ahmad Mahano"
    ],
    "wof:name":"Goth Ahmad Mahano",
    "wof:placetype":"locality"
},
  "geometry": {"coordinates":[68.31369000000001,24.4275],"type":"Point"}
}