{
  "type": "Feature",
  "properties": {
    "gn:admin1_code":"7.0",
    "gn:asciiname":"Khasmik",
    "gn:country_code":"PK",
    "gn:dem":3267,
    "gn:feature_class":"P",
    "gn:feature_code":"PPL",
    "gn:name":"Khasmik",
    "gn:population":0,
    "gn:timezone":"Asia/Karachi",
    "iso:country":"PK",
    "wof:name":"Khasmik",
    "wof:placetype":"locality"
},
  "geometry": {"coordinates":[76.12166999999999,35.37727],"type":"Point"}
}