{
  "type": "Feature",
  "properties": {
    "gn:admin1_code":"3.0",
    "gn:asciiname":"Hamzullah Kote",
    "gn:country_code":"PK",
    "gn:dem":320,
    "gn:feature_class":"P",
    "gn:feature_code":"PPL",
    "gn:name":"Hamzullah Kote",
    "gn:population":0,
    "gn:timezone":"Asia/Karachi",
    "iso:country":"PK",
    "wof:name":"Hamzullah Kote",
    "wof:placetype":"locality"
},
  "geometry": {"coordinates":[72.26538000000002,34.22922],"type":"Point"}
}