{
  "type": "Feature",
  "properties": {
    "gn:admin1_code":"2.0",
    "gn:asciiname":"Haji Shabbir Khan Umrani",
    "gn:country_code":"PK",
    "gn:dem":56,
    "gn:feature_class":"P",
    "gn:feature_code":"PPL",
    "gn:name":"Haji Shabbir Khan Umrani",
    "gn:population":0,
    "gn:timezone":"Asia/Karachi",
    "iso:country":"PK",
    "wof:name":"Haji Shabbir Khan Umrani",
    "wof:placetype":"locality"
},
  "geometry": {"coordinates":[68.04374,28.20697],"type":"Point"}
}