{
  "type": "Feature",
  "properties": {
    "gn:admin1_code":"03",
    "gn:asciiname":"Kuliarai",
    "gn:country_code":"PK",
    "gn:dem":1168,
    "gn:feature_class":"P",
    "gn:feature_code":"PPL",
    "gn:name":"Kuliarai",
    "gn:population":0,
    "gn:timezone":"Asia/Karachi",
    "iso:country":"PK",
    "name:und_x_variant":[
        "Kulyari",
        "Kuliarai"
    ],
    "wof:name":"Kuliarai",
    "wof:placetype":"locality"
},
  "geometry": {"coordinates":[72.76309999999999,34.70261],"type":"Point"}
}