{
  "type": "Feature",
  "properties": {
    "gn:admin1_code":"04",
    "gn:asciiname":"Chak Two Hundred Five Gugera Branch",
    "gn:country_code":"PK",
    "gn:dem":168,
    "gn:feature_class":"P",
    "gn:feature_code":"PPL",
    "gn:name":"Chak Two Hundred Five Gugera Branch",
    "gn:population":0,
    "gn:timezone":"Asia/Karachi",
    "iso:country":"PK",
    "name:und_x_variant":[
        "Rattar Chatar",
        "Rattar Chattar",
        "Chak Two Hundred Five Gugera Branch"
    ],
    "wof:name":"Chak Two Hundred Five Gugera Branch",
    "wof:placetype":"locality"
},
  "geometry": {"coordinates":[72.77925999999999,30.95952],"type":"Point"}
}