{
  "type": "Feature",
  "properties": {
    "gn:admin1_code":"3.0",
    "gn:asciiname":"Pir Garhi",
    "gn:country_code":"PK",
    "gn:dem":313,
    "gn:feature_class":"P",
    "gn:feature_code":"PPL",
    "gn:name":"Pir Garhi",
    "gn:population":0,
    "gn:timezone":"Asia/Karachi",
    "iso:country":"PK",
    "wof:name":"Pir Garhi",
    "wof:placetype":"locality"
},
  "geometry": {"coordinates":[72.03423000000002,34.23483],"type":"Point"}
}