{
  "type": "Feature",
  "properties": {
    "gn:admin1_code":"5",
    "gn:asciiname":"Goth Phulpota",
    "gn:country_code":"PK",
    "gn:dem":54,
    "gn:feature_class":"P",
    "gn:feature_code":"PPL",
    "gn:name":"Goth Phulpota",
    "gn:population":0,
    "gn:timezone":"Asia/Karachi",
    "iso:country":"PK",
    "name:und_x_variant":[
        "Phulpota"
    ],
    "wof:name":"Goth Phulpota",
    "wof:placetype":"locality"
},
  "geometry": {"coordinates":[68.29122,27.7403],"type":"Point"}
}