{
  "type": "Feature",
  "properties": {
    "gn:admin1_code":"01",
    "gn:asciiname":"Kanro Kili",
    "gn:country_code":"PK",
    "gn:dem":619,
    "gn:feature_class":"P",
    "gn:feature_code":"PPL",
    "gn:name":"Kanro Kili",
    "gn:population":0,
    "gn:timezone":"Asia/Karachi",
    "iso:country":"PK",
    "wof:name":"Kanro Kili",
    "wof:placetype":"locality"
},
  "geometry": {"coordinates":[71.44728000000001,34.55484000000001],"type":"Point"}
}