{
  "type": "Feature",
  "properties": {
    "gn:admin1_code":"6.0",
    "gn:asciiname":"Khuntal",
    "gn:country_code":"PK",
    "gn:dem":1686,
    "gn:feature_class":"P",
    "gn:feature_code":"PPL",
    "gn:name":"Khuntal",
    "gn:population":0,
    "gn:timezone":"Asia/Karachi",
    "iso:country":"PK",
    "wof:name":"Khuntal",
    "wof:placetype":"locality"
},
  "geometry": {"coordinates":[73.58279,33.99154],"type":"Point"}
}