{
  "type": "Feature",
  "properties": {
    "gn:admin1_code":"01",
    "gn:asciiname":"Karigaro",
    "gn:country_code":"PK",
    "gn:dem":2069,
    "gn:feature_class":"P",
    "gn:feature_code":"PPL",
    "gn:name":"Karigaro",
    "gn:population":0,
    "gn:timezone":"Asia/Karachi",
    "iso:country":"PK",
    "name:und_x_variant":[
        "Kar\u012bgaro Kili"
    ],
    "wof:name":"Karigaro",
    "wof:placetype":"locality"
},
  "geometry": {"coordinates":[70.58116,33.73027],"type":"Point"}
}