{
  "type": "Feature",
  "properties": {
    "gn:admin1_code":"4.0",
    "gn:asciiname":"Karumb Jagial",
    "gn:country_code":"PK",
    "gn:dem":495,
    "gn:feature_class":"P",
    "gn:feature_code":"PPL",
    "gn:name":"Karumb Jagial",
    "gn:population":0,
    "gn:timezone":"Asia/Karachi",
    "iso:country":"PK",
    "name:und_x_variant":[
        "Karonab Jagial",
        "Karumb Jagial"
    ],
    "wof:name":"Karumb Jagial",
    "wof:placetype":"locality"
},
  "geometry": {"coordinates":[73.22934000000002,33.23859],"type":"Point"}
}