{
  "type": "Feature",
  "properties": {
    "gn:admin1_code":"01",
    "gn:asciiname":"Karam Raghzai",
    "gn:country_code":"PK",
    "gn:dem":2196,
    "gn:feature_class":"P",
    "gn:feature_code":"PPL",
    "gn:name":"Karam Raghzai",
    "gn:population":0,
    "gn:timezone":"Asia/Karachi",
    "iso:country":"PK",
    "wof:name":"Karam Raghzai",
    "wof:placetype":"locality"
},
  "geometry": {"coordinates":[69.52273000000001,32.75115],"type":"Point"}
}