{
  "type": "Feature",
  "properties": {
    "gn:admin1_code":"5",
    "gn:asciiname":"Jan Muhammad Wasan",
    "gn:country_code":"PK",
    "gn:dem":17,
    "gn:feature_class":"P",
    "gn:feature_code":"PPL",
    "gn:name":"Jan Muhammad Wasan",
    "gn:population":0,
    "gn:timezone":"Asia/Karachi",
    "iso:country":"PK",
    "wof:name":"Jan Muhammad Wasan",
    "wof:placetype":"locality"
},
  "geometry": {"coordinates":[69.11235000000001,25.81095],"type":"Point"}
}