{
  "type": "Feature",
  "properties": {
    "gn:admin1_code":"3",
    "gn:asciiname":"Kahi Garhi",
    "gn:country_code":"PK",
    "gn:dem":584,
    "gn:feature_class":"P",
    "gn:feature_code":"PPL",
    "gn:name":"Kahi Garhi",
    "gn:population":0,
    "gn:timezone":"Asia/Karachi",
    "iso:country":"PK",
    "name:und_x_variant":[
        "Kehi Mull\u0101n"
    ],
    "wof:name":"Kahi Garhi",
    "wof:placetype":"locality"
},
  "geometry": {"coordinates":[72.72216999999998,34.43108],"type":"Point"}
}