{
  "type": "Feature",
  "properties": {
    "gn:admin1_code":"3.0",
    "gn:asciiname":"Sore",
    "gn:country_code":"PK",
    "gn:dem":2014,
    "gn:feature_class":"P",
    "gn:feature_code":"PPL",
    "gn:name":"Sore",
    "gn:population":0,
    "gn:timezone":"Asia/Karachi",
    "iso:country":"PK",
    "name:ceb_x_preferred":[
        "Sore"
    ],
    "name:deu_x_preferred":[
        "Sore"
    ],
    "name:fra_x_preferred":[
        "Sore"
    ],
    "name:ind_x_preferred":[
        "Sore"
    ],
    "name:slk_x_preferred":[
        "Sore"
    ],
    "name:swe_x_preferred":[
        "Sore"
    ],
    "wof:name":"Sore",
    "wof:placetype":"locality"
},
  "geometry": {"coordinates":[72.63289,35.13595],"type":"Point"}
}