{
  "type": "Feature",
  "properties": {
    "gn:admin1_code":"5.0",
    "gn:asciiname":"Goth Imam Bakhsh Kanrio",
    "gn:country_code":"PK",
    "gn:dem":192,
    "gn:feature_class":"P",
    "gn:feature_code":"PPL",
    "gn:name":"Goth Imam Bakhsh Kanrio",
    "gn:population":0,
    "gn:timezone":"Asia/Karachi",
    "iso:country":"PK",
    "name:und_x_variant":[
        "Goth Im\u0101m Bakhsh",
        "Goth Im\u0101m Bokhsh",
        "Goth Imam Bakhsh Kanrio"
    ],
    "wof:name":"Goth Imam Bakhsh Kanrio",
    "wof:placetype":"locality"
},
  "geometry": {"coordinates":[67.75979,25.74656],"type":"Point"}
}