{
  "type": "Feature",
  "properties": {
    "gn:admin1_code":"4.0",
    "gn:asciiname":"Loharanwali",
    "gn:country_code":"PK",
    "gn:dem":447,
    "gn:feature_class":"P",
    "gn:feature_code":"PPL",
    "gn:name":"Loharanwali",
    "gn:population":0,
    "gn:timezone":"Asia/Karachi",
    "iso:country":"PK",
    "wof:name":"Loharanwali",
    "wof:placetype":"locality"
},
  "geometry": {"coordinates":[71.90864999999999,32.62526],"type":"Point"}
}