{
  "type": "Feature",
  "properties": {
    "gn:admin1_code":"2.0",
    "gn:asciiname":"Goth Nehal Khan Solangi",
    "gn:country_code":"PK",
    "gn:dem":66,
    "gn:feature_class":"P",
    "gn:feature_code":"PPL",
    "gn:name":"Goth Nehal Khan Solangi",
    "gn:population":0,
    "gn:timezone":"Asia/Karachi",
    "iso:country":"PK",
    "wof:name":"Goth Nehal Khan Solangi",
    "wof:placetype":"locality"
},
  "geometry": {"coordinates":[68.31188,28.57355],"type":"Point"}
}