{
  "type": "Feature",
  "properties": {
    "gn:admin1_code":"2.0",
    "gn:asciiname":"Kundi",
    "gn:country_code":"PK",
    "gn:dem":2219,
    "gn:feature_class":"P",
    "gn:feature_code":"PPL",
    "gn:name":"Kundi",
    "gn:population":0,
    "gn:timezone":"Asia/Karachi",
    "iso:country":"PK",
    "name:ceb_x_preferred":[
        "Kundi"
    ],
    "name:swe_x_preferred":[
        "Kundi"
    ],
    "wof:name":"Kundi",
    "wof:placetype":"locality"
},
  "geometry": {"coordinates":[66.62007,28.7946],"type":"Point"}
}