{
  "type": "Feature",
  "properties": {
    "gn:admin1_code":"3.0",
    "gn:asciiname":"Shahi Nur",
    "gn:country_code":"PK",
    "gn:dem":1498,
    "gn:feature_class":"P",
    "gn:feature_code":"PPL",
    "gn:name":"Shahi Nur",
    "gn:population":0,
    "gn:timezone":"Asia/Karachi",
    "iso:country":"PK",
    "wof:name":"Shahi Nur",
    "wof:placetype":"locality"
},
  "geometry": {"coordinates":[71.86893000000001,35.60743],"type":"Point"}
}