{
  "type": "Feature",
  "properties": {
    "gn:admin1_code":"4.0",
    "gn:asciiname":"Cnitra",
    "gn:country_code":"PK",
    "gn:dem":1878,
    "gn:feature_class":"P",
    "gn:feature_code":"PPL",
    "gn:name":"Cnitra",
    "gn:population":0,
    "gn:timezone":"Asia/Karachi",
    "iso:country":"PK",
    "name:eng_x_preferred":[
        "Cutra Dunga"
    ],
    "wof:name":"Cnitra",
    "wof:placetype":"locality"
},
  "geometry": {"coordinates":[73.40156,33.95846],"type":"Point"}
}