{
  "type": "Feature",
  "properties": {
    "gn:admin1_code":"5",
    "gn:asciiname":"Goth Karo Gaha",
    "gn:country_code":"PK",
    "gn:dem":23,
    "gn:feature_class":"P",
    "gn:feature_code":"PPL",
    "gn:name":"Goth Karo Gaha",
    "gn:population":0,
    "gn:timezone":"Asia/Karachi",
    "iso:country":"PK",
    "wof:name":"Goth Karo Gaha",
    "wof:placetype":"locality"
},
  "geometry": {"coordinates":[68.76953,25.76232000000001],"type":"Point"}
}