{
  "type": "Feature",
  "properties": {
    "gn:admin1_code":"2.0",
    "gn:asciiname":"Juhli",
    "gn:country_code":"PK",
    "gn:dem":1003,
    "gn:feature_class":"P",
    "gn:feature_code":"PPL",
    "gn:name":"Juhli",
    "gn:population":0,
    "gn:timezone":"Asia/Karachi",
    "iso:country":"PK",
    "wof:name":"Juhli",
    "wof:placetype":"locality"
},
  "geometry": {"coordinates":[63.34401,29.14266],"type":"Point"}
}