{
  "type": "Feature",
  "properties": {
    "gn:admin1_code":"3.0",
    "gn:asciiname":"Kuz Surai",
    "gn:country_code":"PK",
    "gn:dem":1333,
    "gn:feature_class":"P",
    "gn:feature_code":"PPL",
    "gn:name":"Kuz Surai",
    "gn:population":0,
    "gn:timezone":"Asia/Karachi",
    "iso:country":"PK",
    "wof:name":"Kuz Surai",
    "wof:placetype":"locality"
},
  "geometry": {"coordinates":[73.07488000000002,34.6395],"type":"Point"}
}