{
  "type": "Feature",
  "properties": {
    "gn:admin1_code":"2.0",
    "gn:asciiname":"Nalli",
    "gn:country_code":"PK",
    "gn:dem":1837,
    "gn:feature_class":"P",
    "gn:feature_code":"PPL",
    "gn:name":"Nalli",
    "gn:population":0,
    "gn:timezone":"Asia/Karachi",
    "iso:country":"PK",
    "name:eng_x_preferred":[
        "Nalli"
    ],
    "wof:name":"Nalli",
    "wof:placetype":"locality"
},
  "geometry": {"coordinates":[66.34249,29.27374],"type":"Point"}
}