{
  "type": "Feature",
  "properties": {
    "gn:admin1_code":"04",
    "gn:asciiname":"Vairowala",
    "gn:country_code":"PK",
    "gn:dem":240,
    "gn:feature_class":"P",
    "gn:feature_code":"PPL",
    "gn:name":"Vairowala",
    "gn:population":0,
    "gn:timezone":"Asia/Karachi",
    "iso:country":"PK",
    "name:und_x_variant":[
        "Wirow\u0101la",
        "Vairowala"
    ],
    "wof:name":"Vairowala",
    "wof:placetype":"locality"
},
  "geometry": {"coordinates":[74.33854000000002,32.39109000000001],"type":"Point"}
}