{
  "type": "Feature",
  "properties": {
    "gn:admin1_code":"3.0",
    "gn:asciiname":"Subhan Kalle",
    "gn:country_code":"PK",
    "gn:dem":332,
    "gn:feature_class":"P",
    "gn:feature_code":"PPL",
    "gn:name":"Subhan Kalle",
    "gn:population":0,
    "gn:timezone":"Asia/Karachi",
    "iso:country":"PK",
    "wof:name":"Subhan Kalle",
    "wof:placetype":"locality"
},
  "geometry": {"coordinates":[71.54334,34.20738],"type":"Point"}
}