{
  "type": "Feature",
  "properties": {
    "gn:admin1_code":"2.0",
    "gn:asciiname":"Marrak",
    "gn:country_code":"PK",
    "gn:dem":22,
    "gn:feature_class":"P",
    "gn:feature_code":"PPL",
    "gn:name":"Marrak",
    "gn:population":0,
    "gn:timezone":"Asia/Karachi",
    "iso:country":"PK",
    "name:eng_x_preferred":[
        "Marrak"
    ],
    "name:und_x_variant":[
        "M\u0101rrok"
    ],
    "wof:name":"Marrak",
    "wof:placetype":"locality"
},
  "geometry": {"coordinates":[62.02219,25.47643],"type":"Point"}
}