{
  "type": "Feature",
  "properties": {
    "gn:admin1_code":"04",
    "gn:asciiname":"Narali Jabbir",
    "gn:country_code":"PK",
    "gn:dem":487,
    "gn:feature_class":"P",
    "gn:feature_code":"PPL",
    "gn:name":"Narali Jabbir",
    "gn:population":0,
    "gn:timezone":"Asia/Karachi",
    "iso:country":"PK",
    "name:und_x_variant":[
        "Narali Jubair",
        "Nar\u0101li Jaber",
        "Narali Jabbir"
    ],
    "wof:name":"Narali Jabbir",
    "wof:placetype":"locality"
},
  "geometry": {"coordinates":[73.40075999999998,33.32857],"type":"Point"}
}