{
  "type": "Feature",
  "properties": {
    "gn:admin1_code":"5.0",
    "gn:asciiname":"Hafiz Muhammad",
    "gn:country_code":"PK",
    "gn:dem":3,
    "gn:feature_class":"P",
    "gn:feature_code":"PPL",
    "gn:name":"Hafiz Muhammad",
    "gn:population":0,
    "gn:timezone":"Asia/Karachi",
    "iso:country":"PK",
    "name:und_x_variant":[
        "H\u0101fiz Muhammad",
        "Goth Hafiz Muhammad",
        "Hafiz Muhammad"
    ],
    "wof:name":"Hafiz Muhammad",
    "wof:placetype":"locality"
},
  "geometry": {"coordinates":[67.57814,24.59167],"type":"Point"}
}