{
  "type": "Feature",
  "properties": {
    "gn:admin1_code":"3",
    "gn:asciiname":"Kuz Bargin",
    "gn:country_code":"PK",
    "gn:dem":1621,
    "gn:feature_class":"P",
    "gn:feature_code":"PPL",
    "gn:name":"Kuz Bargin",
    "gn:population":0,
    "gn:timezone":"Asia/Karachi",
    "iso:country":"PK",
    "wof:name":"Kuz Bargin",
    "wof:placetype":"locality"
},
  "geometry": {"coordinates":[72.51177,35.00877],"type":"Point"}
}