{
  "type": "Feature",
  "properties": {
    "gn:admin1_code":"04",
    "gn:asciiname":"Sakhi Sarwar",
    "gn:country_code":"PK",
    "gn:dem":283,
    "gn:feature_class":"P",
    "gn:feature_code":"PPL",
    "gn:name":"Sakhi Sarwar",
    "gn:population":0,
    "gn:timezone":"Asia/Karachi",
    "iso:country":"PK",
    "name:eng_x_preferred":[
        "Sakhi Sarwar"
    ],
    "name:fas_x_preferred":[
        "\u0633\u062e\u06cc \u0633\u0631\u0648\u0631"
    ],
    "name:hin_x_preferred":[
        "\u0938\u093e\u0916\u0940 \u0938\u0930\u094d\u0935\u0930"
    ],
    "name:pan_x_preferred":[
        "\u0a38\u0a16\u0a40 \u0a38\u0a30\u0a35\u0a30"
    ],
    "wof:name":"Sakhi Sarwar",
    "wof:placetype":"locality"
},
  "geometry": {"coordinates":[70.30614,29.98033],"type":"Point"}
}