{
  "type": "Feature",
  "properties": {
    "gn:admin1_code":"04",
    "gn:asciiname":"Sakhi Sarwar",
    "gn:country_code":"PK",
    "gn:dem":283,
    "gn:feature_class":"P",
    "gn:feature_code":"PPL",
    "gn:name":"Sakhi Sarwar",
    "gn:population":0,
    "gn:timezone":"Asia/Karachi",
    "iso:country":"PK",
    "name:eng_x_preferred":[
        "Sakhi Sarwar"
    ],
    "wof:name":"Sakhi Sarwar",
    "wof:placetype":"locality"
},
  "geometry": {"coordinates":[70.30614,29.98033],"type":"Point"}
}