{
  "type": "Feature",
  "properties": {
    "gn:admin1_code":"2.0",
    "gn:asciiname":"Azam Khan",
    "gn:country_code":"PK",
    "gn:dem":925,
    "gn:feature_class":"P",
    "gn:feature_code":"PPL",
    "gn:name":"Azam Khan",
    "gn:population":0,
    "gn:timezone":"Asia/Karachi",
    "iso:country":"PK",
    "wof:name":"Azam Khan",
    "wof:placetype":"locality"
},
  "geometry": {"coordinates":[65.88333,29.71667],"type":"Point"}
}