{
  "type": "Feature",
  "properties": {
    "gn:admin1_code":"4.0",
    "gn:asciiname":"Dera Sardaruwali",
    "gn:country_code":"PK",
    "gn:dem":191,
    "gn:feature_class":"P",
    "gn:feature_code":"PPL",
    "gn:name":"Dera Sardaruwali",
    "gn:population":0,
    "gn:timezone":"Asia/Karachi",
    "iso:country":"PK",
    "name:und_x_variant":[
        "Sird\u0101ruw\u0101li"
    ],
    "wof:name":"Dera Sardaruwali",
    "wof:placetype":"locality"
},
  "geometry": {"coordinates":[72.27646999999997,32.40173],"type":"Point"}
}