{
  "type": "Feature",
  "properties": {
    "gn:admin1_code":"3.0",
    "gn:asciiname":"Phandu Payan",
    "gn:country_code":"PK",
    "gn:dem":322,
    "gn:feature_class":"P",
    "gn:feature_code":"PPL",
    "gn:name":"Phandu Payan",
    "gn:population":0,
    "gn:timezone":"Asia/Karachi",
    "iso:country":"PK",
    "wof:name":"Phandu Payan",
    "wof:placetype":"locality"
},
  "geometry": {"coordinates":[71.63074,33.9891],"type":"Point"}
}