{
  "type": "Feature",
  "properties": {
    "gn:admin1_code":"4.0",
    "gn:asciiname":"Faisalabad",
    "gn:country_code":"PK",
    "gn:dem":1157,
    "gn:feature_class":"P",
    "gn:feature_code":"PPL",
    "gn:name":"Faisalabad",
    "gn:population":0,
    "gn:timezone":"Asia/Karachi",
    "iso:country":"PK",
    "name:eng_x_preferred":[
        "Patit B\u0101ndi"
    ],
    "wof:name":"Faisalabad",
    "wof:placetype":"locality"
},
  "geometry": {"coordinates":[73.399,33.816],"type":"Point"}
}