{
  "type": "Feature",
  "properties": {
    "gn:admin1_code":"3",
    "gn:asciiname":"Chitta Batta",
    "gn:country_code":"PK",
    "gn:dem":1526,
    "gn:feature_class":"P",
    "gn:feature_code":"PPL",
    "gn:name":"Chitta Batta",
    "gn:population":0,
    "gn:timezone":"Asia/Karachi",
    "iso:country":"PK",
    "wof:name":"Chitta Batta",
    "wof:placetype":"locality"
},
  "geometry": {"coordinates":[73.24088,34.56083],"type":"Point"}
}