{
  "type": "Feature",
  "properties": {
    "gn:admin1_code":"5.0",
    "gn:asciiname":"Goth Raja",
    "gn:country_code":"PK",
    "gn:dem":5,
    "gn:feature_class":"P",
    "gn:feature_code":"PPL",
    "gn:name":"Goth Raja",
    "gn:population":0,
    "gn:timezone":"Asia/Karachi",
    "iso:country":"PK",
    "name:und_x_variant":[
        "Goth R\u0101ja"
    ],
    "wof:name":"Goth Raja",
    "wof:placetype":"locality"
},
  "geometry": {"coordinates":[68.29149,24.31501],"type":"Point"}
}