{
  "type": "Feature",
  "properties": {
    "gn:admin1_code":"4",
    "gn:asciiname":"Kowejawala",
    "gn:country_code":"PK",
    "gn:dem":166,
    "gn:feature_class":"P",
    "gn:feature_code":"PPL",
    "gn:name":"Kowejawala",
    "gn:population":0,
    "gn:timezone":"Asia/Karachi",
    "iso:country":"PK",
    "name:und_x_variant":[
        "Khwajaw\u0101la",
        "Ch\u0101h Khojew\u0101la",
        "Kowejawala"
    ],
    "wof:name":"Kowejawala",
    "wof:placetype":"locality"
},
  "geometry": {"coordinates":[71.04168,31.64885],"type":"Point"}
}