{
  "type": "Feature",
  "properties": {
    "gn:admin1_code":"4",
    "gn:asciiname":"Ganda Singh",
    "gn:country_code":"PK",
    "gn:dem":198,
    "gn:feature_class":"P",
    "gn:feature_code":"PPL",
    "gn:name":"Ganda Singh",
    "gn:population":0,
    "gn:timezone":"Asia/Karachi",
    "iso:country":"PK",
    "name:hin_x_preferred":[
        "\u0917\u0902\u0921\u093e \u0938\u093f\u0902\u0939"
    ],
    "name:pan_x_preferred":[
        "\u0a17\u0a70\u0a21\u0a3e \u0a38\u0a3f\u0a70\u0a18"
    ],
    "wof:name":"Ganda Singh",
    "wof:placetype":"locality"
},
  "geometry": {"coordinates":[73.50833,31.73472000000001],"type":"Point"}
}