{
  "type": "Feature",
  "properties": {
    "gn:admin1_code":"2.0",
    "gn:asciiname":"Gund Pish",
    "gn:country_code":"PK",
    "gn:dem":1111,
    "gn:feature_class":"P",
    "gn:feature_code":"PPL",
    "gn:name":"Gund Pish",
    "gn:population":0,
    "gn:timezone":"Asia/Karachi",
    "iso:country":"PK",
    "wof:name":"Gund Pish",
    "wof:placetype":"locality"
},
  "geometry": {"coordinates":[64.95974,27.01206],"type":"Point"}
}