{
  "type": "Feature",
  "properties": {
    "gn:admin1_code":"6.0",
    "gn:asciiname":"Chak Darya",
    "gn:country_code":"PK",
    "gn:dem":267,
    "gn:feature_class":"P",
    "gn:feature_code":"PPL",
    "gn:name":"Chak Darya",
    "gn:population":0,
    "gn:timezone":"Asia/Karachi",
    "iso:country":"PK",
    "wof:name":"Chak Darya",
    "wof:placetype":"locality"
},
  "geometry": {"coordinates":[73.66207,33.05019],"type":"Point"}
}