{
  "type": "Feature",
  "properties": {
    "gn:admin1_code":"5",
    "gn:asciiname":"Goth Imam Bakhsh Khurs",
    "gn:country_code":"PK",
    "gn:dem":59,
    "gn:feature_class":"P",
    "gn:feature_code":"PPL",
    "gn:name":"Goth Imam Bakhsh Khurs",
    "gn:population":0,
    "gn:timezone":"Asia/Karachi",
    "iso:country":"PK",
    "name:und_x_variant":[
        "Badha Khurs"
    ],
    "wof:name":"Goth Imam Bakhsh Khurs",
    "wof:placetype":"locality"
},
  "geometry": {"coordinates":[68.44374999999999,27.71012],"type":"Point"}
}