{
  "type": "Feature",
  "properties": {
    "gn:admin1_code":"4",
    "gn:asciiname":"Basti Ali Jahangir",
    "gn:country_code":"PK",
    "gn:dem":126,
    "gn:feature_class":"P",
    "gn:feature_code":"PPL",
    "gn:name":"Basti Ali Jah\u0101ng\u012br",
    "gn:population":0,
    "gn:timezone":"Asia/Karachi",
    "iso:country":"PK",
    "wof:name":"Basti Ali Jahangir",
    "wof:placetype":"locality"
},
  "geometry": {"coordinates":[70.61669999999999,30.18921],"type":"Point"}
}