{
  "type": "Feature",
  "properties": {
    "gn:admin1_code":"4.0",
    "gn:asciiname":"Khanewal Kohna",
    "gn:country_code":"PK",
    "gn:dem":134,
    "gn:feature_class":"P",
    "gn:feature_code":"PPL",
    "gn:name":"Khanewal Kohna",
    "gn:population":0,
    "gn:timezone":"Asia/Karachi",
    "iso:country":"PK",
    "name:und_x_variant":[
        "Kh\u0101new\u0101l Kuhna"
    ],
    "wof:name":"Khanewal Kohna",
    "wof:placetype":"locality"
},
  "geometry": {"coordinates":[71.92291999999998,30.31566],"type":"Point"}
}