{
  "type": "Feature",
  "properties": {
    "gn:admin1_code":"3.0",
    "gn:asciiname":"Azhpi",
    "gn:country_code":"PK",
    "gn:dem":2646,
    "gn:feature_class":"P",
    "gn:feature_code":"PPL",
    "gn:name":"Azhpi",
    "gn:population":0,
    "gn:timezone":"Asia/Karachi",
    "iso:country":"PK",
    "wof:name":"Azhpi",
    "wof:placetype":"locality"
},
  "geometry": {"coordinates":[71.70945,36.22038],"type":"Point"}
}