{
  "type": "Feature",
  "properties": {
    "gn:admin1_code":"4.0",
    "gn:asciiname":"Safyalwali",
    "gn:country_code":"PK",
    "gn:dem":334,
    "gn:feature_class":"P",
    "gn:feature_code":"PPL",
    "gn:name":"Safyalwali",
    "gn:population":0,
    "gn:timezone":"Asia/Karachi",
    "iso:country":"PK",
    "name:und_x_variant":[
        "Sh\u0101h Zam\u0101nw\u0101li"
    ],
    "wof:name":"Safyalwali",
    "wof:placetype":"locality"
},
  "geometry": {"coordinates":[71.88723,32.99347],"type":"Point"}
}