{
  "type": "Feature",
  "properties": {
    "gn:admin1_code":"4.0",
    "gn:asciiname":"Jamwat",
    "gn:country_code":"PK",
    "gn:dem":1352,
    "gn:feature_class":"P",
    "gn:feature_code":"PPL",
    "gn:name":"Jamwat",
    "gn:population":0,
    "gn:timezone":"Asia/Karachi",
    "iso:country":"PK",
    "wof:name":"Jamwat",
    "wof:placetype":"locality"
},
  "geometry": {"coordinates":[70.09179,30.6891],"type":"Point"}
}