{
  "type": "Feature",
  "properties": {
    "gn:admin1_code":"2.0",
    "gn:asciiname":"Allahabad",
    "gn:country_code":"PK",
    "gn:dem":1577,
    "gn:feature_class":"P",
    "gn:feature_code":"PPL",
    "gn:name":"Allahabad",
    "gn:population":0,
    "gn:timezone":"Asia/Karachi",
    "iso:country":"PK",
    "name:und_x_variant":[
        "Kh\u0101liq\u0101b\u0101d"
    ],
    "wof:name":"Allahabad",
    "wof:placetype":"locality"
},
  "geometry": {"coordinates":[66.28886,28.12274],"type":"Point"}
}