{
  "type": "Feature",
  "properties": {
    "gn:admin1_code":"4",
    "gn:asciiname":"Dhok Mohra",
    "gn:country_code":"PK",
    "gn:dem":456,
    "gn:feature_class":"P",
    "gn:feature_code":"PPL",
    "gn:name":"Dhok Mohra",
    "gn:population":0,
    "gn:timezone":"Asia/Karachi",
    "iso:country":"PK",
    "name:und_x_variant":[
        "Dhok Mohri"
    ],
    "wof:name":"Dhok Mohra",
    "wof:placetype":"locality"
},
  "geometry": {"coordinates":[73.19608000000002,32.84522],"type":"Point"}
}