{
  "type": "Feature",
  "properties": {
    "gn:admin1_code":"4",
    "gn:asciiname":"Chah Balowala",
    "gn:country_code":"PK",
    "gn:dem":152,
    "gn:feature_class":"P",
    "gn:feature_code":"PPL",
    "gn:name":"Chah Balowala",
    "gn:population":0,
    "gn:timezone":"Asia/Karachi",
    "iso:country":"PK",
    "name:und_x_variant":[
        "B\u0101luw\u0101la",
        "Ch\u0101h B\u0101buw\u0101la",
        "Chah Balowala"
    ],
    "wof:name":"Chah Balowala",
    "wof:placetype":"locality"
},
  "geometry": {"coordinates":[70.87512,31.13787],"type":"Point"}
}