{
  "type": "Feature",
  "properties": {
    "gn:admin1_code":"4.0",
    "gn:asciiname":"Goth Khan Muhammad Jhak",
    "gn:country_code":"PK",
    "gn:dem":80,
    "gn:feature_class":"P",
    "gn:feature_code":"PPL",
    "gn:name":"Goth Khan Muhammad Jhak",
    "gn:population":0,
    "gn:timezone":"Asia/Karachi",
    "iso:country":"PK",
    "name:und_x_variant":[
        "Garhi Khair Muhammad",
        "Garhi Kh\u0101n Muhammad",
        "Goth Khan Muhammad Jhak"
    ],
    "wof:name":"Goth Khan Muhammad Jhak",
    "wof:placetype":"locality"
},
  "geometry": {"coordinates":[69.83434,28.41586],"type":"Point"}
}