{
  "type": "Feature",
  "properties": {
    "gn:admin1_code":"4.0",
    "gn:asciiname":"Nikki Arain",
    "gn:country_code":"PK",
    "gn:dem":109,
    "gn:feature_class":"P",
    "gn:feature_code":"PPL",
    "gn:name":"Nikki Arain",
    "gn:population":0,
    "gn:timezone":"Asia/Karachi",
    "iso:country":"PK",
    "name:und_x_variant":[
        "Nikkew\u0101la"
    ],
    "wof:name":"Nikki Arain",
    "wof:placetype":"locality"
},
  "geometry": {"coordinates":[71.45971999999998,29.55571],"type":"Point"}
}