{
  "type": "Feature",
  "properties": {
    "gn:admin1_code":"2.0",
    "gn:asciiname":"Kili Muhammad Bakhsh Zaik",
    "gn:country_code":"PK",
    "gn:dem":1449,
    "gn:feature_class":"P",
    "gn:feature_code":"PPL",
    "gn:name":"Kili Muhammad Bakhsh Zaik",
    "gn:population":0,
    "gn:timezone":"Asia/Karachi",
    "iso:country":"PK",
    "name:und_x_variant":[
        "Kili Zaik"
    ],
    "wof:name":"Kili Muhammad Bakhsh Zaik",
    "wof:placetype":"locality"
},
  "geometry": {"coordinates":[65.88378,27.91328],"type":"Point"}
}