{
  "type": "Feature",
  "properties": {
    "gn:admin1_code":"3",
    "gn:asciiname":"Bajna",
    "gn:country_code":"PK",
    "gn:dem":1083,
    "gn:feature_class":"P",
    "gn:feature_code":"PPL",
    "gn:name":"Bajna",
    "gn:population":0,
    "gn:timezone":"Asia/Karachi",
    "iso:country":"PK",
    "name:ceb_x_preferred":[
        "Bajna"
    ],
    "name:hun_x_preferred":[
        "Bajna"
    ],
    "name:nld_x_preferred":[
        "Bajna"
    ],
    "name:swe_x_preferred":[
        "Bajna"
    ],
    "wof:name":"Bajna",
    "wof:placetype":"locality"
},
  "geometry": {"coordinates":[72.98633000000002,34.47444],"type":"Point"}
}