{
  "type": "Feature",
  "properties": {
    "gn:admin1_code":"4.0",
    "gn:asciiname":"Nazirabad",
    "gn:country_code":"PK",
    "gn:dem":148,
    "gn:feature_class":"P",
    "gn:feature_code":"PPL",
    "gn:name":"Nazirabad",
    "gn:population":0,
    "gn:timezone":"Asia/Karachi",
    "iso:country":"PK",
    "name:und_x_variant":[
        "Fatehpur"
    ],
    "wof:name":"Nazirabad",
    "wof:placetype":"locality"
},
  "geometry": {"coordinates":[72.24263000000001,30.96495],"type":"Point"}
}