{
  "type": "Feature",
  "properties": {
    "gn:admin1_code":"4.0",
    "gn:asciiname":"Chak Three Hundred Fifty-five",
    "gn:country_code":"PK",
    "gn:dem":168,
    "gn:feature_class":"P",
    "gn:feature_code":"PPL",
    "gn:name":"Chak Three Hundred Fifty-five",
    "gn:population":0,
    "gn:timezone":"Asia/Karachi",
    "iso:country":"PK",
    "name:und_x_variant":[
        "Ibbetsonpur",
        "Ibbetson\u0101b\u0101d",
        "Chak Number Three Hundred Fifty-Five",
        "Chak Three Hundred Fifty-five",
        "Rucha R\u0101m"
    ],
    "wof:name":"Chak Three Hundred Fifty-five",
    "wof:placetype":"locality"
},
  "geometry": {"coordinates":[72.61957,31.18845],"type":"Point"}
}