{
  "type": "Feature",
  "properties": {
    "gn:admin1_code":"02",
    "gn:asciiname":"Tor Kach",
    "gn:country_code":"PK",
    "gn:dem":1989,
    "gn:feature_class":"P",
    "gn:feature_code":"PPL",
    "gn:name":"Tor Kach",
    "gn:population":0,
    "gn:timezone":"Asia/Karachi",
    "iso:country":"PK",
    "wof:name":"Tor Kach",
    "wof:placetype":"locality"
},
  "geometry": {"coordinates":[67.00451,31.19796],"type":"Point"}
}