{
  "type": "Feature",
  "properties": {
    "gn:admin1_code":"05",
    "gn:asciiname":"Kur Kamal",
    "gn:country_code":"PK",
    "gn:dem":50,
    "gn:feature_class":"P",
    "gn:feature_code":"PPL",
    "gn:name":"Kur Kamal",
    "gn:population":0,
    "gn:timezone":"Asia/Karachi",
    "iso:country":"PK",
    "name:und_x_variant":[
        "Kur Kam\u0101l Kh\u0101n"
    ],
    "wof:name":"Kur Kamal",
    "wof:placetype":"locality"
},
  "geometry": {"coordinates":[67.90000000000001,27.66667],"type":"Point"}
}