{
  "type": "Feature",
  "properties": {
    "gn:admin1_code":"5",
    "gn:asciiname":"Ghulam Pitafi",
    "gn:country_code":"PK",
    "gn:dem":21,
    "gn:feature_class":"P",
    "gn:feature_code":"PPL",
    "gn:name":"Ghulam Pitafi",
    "gn:population":0,
    "gn:timezone":"Asia/Karachi",
    "iso:country":"PK",
    "name:und_x_variant":[
        "Goth Ghul\u0101m Pit\u0101fi"
    ],
    "wof:name":"Ghulam Pitafi",
    "wof:placetype":"locality"
},
  "geometry": {"coordinates":[68.66589,25.3194],"type":"Point"}
}