{
  "type": "Feature",
  "properties": {
    "gn:admin1_code":"7.0",
    "gn:asciiname":"Bihmar",
    "gn:country_code":"PK",
    "gn:dem":2428,
    "gn:feature_class":"P",
    "gn:feature_code":"PPL",
    "gn:name":"Bihmar",
    "gn:population":0,
    "gn:timezone":"Asia/Karachi",
    "iso:country":"PK",
    "wof:name":"Bihmar",
    "wof:placetype":"locality"
},
  "geometry": {"coordinates":[74.53554,35.54764],"type":"Point"}
}