{
  "type": "Feature",
  "properties": {
    "gn:admin1_code":"5",
    "gn:asciiname":"Goth Chauk",
    "gn:country_code":"PK",
    "gn:dem":63,
    "gn:feature_class":"P",
    "gn:feature_code":"PPL",
    "gn:name":"Goth Chauk",
    "gn:population":0,
    "gn:timezone":"Asia/Karachi",
    "iso:country":"PK",
    "name:und_x_variant":[
        "Chauk"
    ],
    "wof:name":"Goth Chauk",
    "wof:placetype":"locality"
},
  "geometry": {"coordinates":[68.85859000000001,28.29072],"type":"Point"}
}