{
  "type": "Feature",
  "properties": {
    "gn:admin1_code":"5",
    "gn:asciiname":"Khuda Bakhsh Dalwani",
    "gn:country_code":"PK",
    "gn:dem":9,
    "gn:feature_class":"P",
    "gn:feature_code":"PPL",
    "gn:name":"Khuda Bakhsh Dalwani",
    "gn:population":0,
    "gn:timezone":"Asia/Karachi",
    "iso:country":"PK",
    "wof:name":"Khuda Bakhsh Dalwani",
    "wof:placetype":"locality"
},
  "geometry": {"coordinates":[69.62873,25.25473],"type":"Point"}
}