{
  "type": "Feature",
  "properties": {
    "gn:admin1_code":"4.0",
    "gn:asciiname":"Dhok Allah Dad",
    "gn:country_code":"PK",
    "gn:dem":517,
    "gn:feature_class":"P",
    "gn:feature_code":"PPL",
    "gn:name":"Dhok Allah Dad",
    "gn:population":0,
    "gn:timezone":"Asia/Karachi",
    "iso:country":"PK",
    "wof:name":"Dhok Allah Dad",
    "wof:placetype":"locality"
},
  "geometry": {"coordinates":[73.33163,33.09755],"type":"Point"}
}