{
  "type": "Feature",
  "properties": {
    "gn:admin1_code":"3.0",
    "gn:asciiname":"Besal",
    "gn:country_code":"PK",
    "gn:dem":3245,
    "gn:feature_class":"P",
    "gn:feature_code":"PPL",
    "gn:name":"Besal",
    "gn:population":0,
    "gn:timezone":"Asia/Karachi",
    "iso:country":"PK",
    "wof:name":"Besal",
    "wof:placetype":"locality"
},
  "geometry": {"coordinates":[73.93567,35.05191],"type":"Point"}
}