{
  "type": "Feature",
  "properties": {
    "gn:admin1_code":"4",
    "gn:asciiname":"Chak One Hundred Seventeen Southern Branch",
    "gn:country_code":"PK",
    "gn:dem":187,
    "gn:feature_class":"P",
    "gn:feature_code":"PPL",
    "gn:name":"Chak One Hundred Seventeen Southern Branch",
    "gn:population":0,
    "gn:timezone":"Asia/Karachi",
    "iso:country":"PK",
    "name:und_x_variant":[
        "Chak One Hundred Seventeen SB"
    ],
    "wof:name":"Chak One Hundred Seventeen Southern Branch",
    "wof:placetype":"locality"
},
  "geometry": {"coordinates":[72.64813000000002,31.93575],"type":"Point"}
}