{
  "type": "Feature",
  "properties": {
    "gn:admin1_code":"6",
    "gn:asciiname":"Mera",
    "gn:country_code":"PK",
    "gn:dem":2021,
    "gn:feature_class":"P",
    "gn:feature_code":"PPL",
    "gn:name":"Mera",
    "gn:population":0,
    "gn:timezone":"Asia/Karachi",
    "iso:country":"PK",
    "name:und_x_variant":[
        "Maira"
    ],
    "wof:name":"Mera",
    "wof:placetype":"locality"
},
  "geometry": {"coordinates":[74.23224,33.9435],"type":"Point"}
}