{
  "type": "Feature",
  "properties": {
    "gn:admin1_code":"4",
    "gn:asciiname":"Mad Khairanwala",
    "gn:country_code":"PK",
    "gn:dem":96,
    "gn:feature_class":"P",
    "gn:feature_code":"PPL",
    "gn:name":"Mad Khairanwala",
    "gn:population":0,
    "gn:timezone":"Asia/Karachi",
    "iso:country":"PK",
    "name:und_x_variant":[
        "Mad Khairw\u0101la"
    ],
    "wof:name":"Mad Khairanwala",
    "wof:placetype":"locality"
},
  "geometry": {"coordinates":[70.25681,29.1916],"type":"Point"}
}