{
  "type": "Feature",
  "properties": {
    "gn:admin1_code":"4",
    "gn:asciiname":"Alu Shadio",
    "gn:country_code":"PK",
    "gn:dem":232,
    "gn:feature_class":"P",
    "gn:feature_code":"PPL",
    "gn:name":"Alu Shadio",
    "gn:population":0,
    "gn:timezone":"Asia/Karachi",
    "iso:country":"PK",
    "name:und_x_variant":[
        "\u0100lu Sh\u0101hdeo"
    ],
    "wof:name":"Alu Shadio",
    "wof:placetype":"locality"
},
  "geometry": {"coordinates":[74.19293,32.40658],"type":"Point"}
}