{
  "type": "Feature",
  "properties": {
    "gn:admin1_code":"6",
    "gn:asciiname":"Dora Pari",
    "gn:country_code":"PK",
    "gn:dem":2798,
    "gn:feature_class":"P",
    "gn:feature_code":"PPL",
    "gn:name":"Dora Pari",
    "gn:population":0,
    "gn:timezone":"Asia/Karachi",
    "iso:country":"PK",
    "name:und_x_variant":[
        "Dara Pari"
    ],
    "wof:name":"Dora Pari",
    "wof:placetype":"locality"
},
  "geometry": {"coordinates":[73.76053,34.33239],"type":"Point"}
}