{
  "type": "Feature",
  "properties": {
    "gn:admin1_code":"04",
    "gn:asciiname":"Saidanwali",
    "gn:country_code":"PK",
    "gn:dem":260,
    "gn:feature_class":"P",
    "gn:feature_code":"PPL",
    "gn:name":"Saidanwali",
    "gn:population":0,
    "gn:timezone":"Asia/Karachi",
    "iso:country":"PK",
    "name:und_x_variant":[
        "Saidewali",
        "Said\u0101nw\u0101la",
        "Saidanwali"
    ],
    "wof:name":"Saidanwali",
    "wof:placetype":"locality"
},
  "geometry": {"coordinates":[74.74505000000001,32.41531],"type":"Point"}
}