{
  "type": "Feature",
  "properties": {
    "gn:admin1_code":"4.0",
    "gn:asciiname":"Dhok Nanganwali",
    "gn:country_code":"PK",
    "gn:dem":332,
    "gn:feature_class":"P",
    "gn:feature_code":"PPL",
    "gn:name":"Dhok Nanganwali",
    "gn:population":0,
    "gn:timezone":"Asia/Karachi",
    "iso:country":"PK",
    "wof:name":"Dhok Nanganwali",
    "wof:placetype":"locality"
},
  "geometry": {"coordinates":[72.31995000000001,33.23584],"type":"Point"}
}