{
  "type": "Feature",
  "properties": {
    "gn:admin1_code":"5.0",
    "gn:asciiname":"Jafar Mirakhor",
    "gn:country_code":"PK",
    "gn:dem":8,
    "gn:feature_class":"P",
    "gn:feature_code":"PPL",
    "gn:name":"J\u0101far M\u012brakhor",
    "gn:population":0,
    "gn:timezone":"Asia/Karachi",
    "iso:country":"PK",
    "wof:name":"Jafar Mirakhor",
    "wof:placetype":"locality"
},
  "geometry": {"coordinates":[67.67055999999999,24.62083],"type":"Point"}
}