{
  "type": "Feature",
  "properties": {
    "gn:admin1_code":"5.0",
    "gn:asciiname":"Makhdum Muhammad Zaman",
    "gn:country_code":"PK",
    "gn:dem":33,
    "gn:feature_class":"P",
    "gn:feature_code":"PPL",
    "gn:name":"Makhdum Muhammad Zaman",
    "gn:population":0,
    "gn:timezone":"Asia/Karachi",
    "iso:country":"PK",
    "wof:name":"Makhdum Muhammad Zaman",
    "wof:placetype":"locality"
},
  "geometry": {"coordinates":[68.32029,26.31215],"type":"Point"}
}