{
  "type": "Feature",
  "properties": {
    "gn:admin1_code":"4.0",
    "gn:asciiname":"Kararanwala",
    "gn:cc2":"PK",
    "gn:country_code":"PK",
    "gn:dem":166,
    "gn:feature_class":"P",
    "gn:feature_code":"PPL",
    "gn:name":"Kararanw\u0101la",
    "gn:population":0,
    "gn:timezone":"Asia/Karachi",
    "iso:country":"PK",
    "name:und_x_variant":[
        "Madan L\u0101lw\u0101la",
        "Kararanw\u0101la"
    ],
    "wof:name":"Kararanwala",
    "wof:placetype":"locality"
},
  "geometry": {"coordinates":[72.88333,30.61667000000001],"type":"Point"}
}