{
  "type": "Feature",
  "properties": {
    "gn:admin1_code":"3",
    "gn:asciiname":"Malkan",
    "gn:country_code":"PK",
    "gn:dem":953,
    "gn:feature_class":"P",
    "gn:feature_code":"PPL",
    "gn:name":"Malkan",
    "gn:population":0,
    "gn:timezone":"Asia/Karachi",
    "iso:country":"PK",
    "name:und_x_variant":[
        "Malik"
    ],
    "wof:name":"Malkan",
    "wof:placetype":"locality"
},
  "geometry": {"coordinates":[73.20455,34.07633],"type":"Point"}
}