{
  "type": "Feature",
  "properties": {
    "iso:country":"PK",
    "qs:gn_pop":0,
    "qs:name":"Barian Camp",
    "qs:name_adm0":"Pakistan",
    "qs:name_adm1":"Punjab",
    "qs:photos":38,
    "qs:photos_1k":8,
    "qs:photos_9k":1,
    "qs:photos_9r":2,
    "qs:photos_all":38,
    "qs:photos_sr":2,
    "qs:placetype":"Town",
    "qs:pop_sr":"0",
    "qs:woe_adm0":23424922,
    "wof:name":"Barian Camp",
    "wof:placetype":"locality"
},
  "geometry": {"coordinates":[73.391944,33.959166],"type":"Point"}
}