{
  "type": "Feature",
  "properties": {
    "gn:admin1_code":"04",
    "gn:asciiname":"Maghal",
    "gn:country_code":"PK",
    "gn:dem":735,
    "gn:feature_class":"P",
    "gn:feature_code":"PPL",
    "gn:name":"Maghal",
    "gn:population":0,
    "gn:timezone":"Asia/Karachi",
    "iso:country":"PK",
    "wof:name":"Maghal",
    "wof:placetype":"locality"
},
  "geometry": {"coordinates":[72.85836999999999,32.73613],"type":"Point"}
}