{
  "type": "Feature",
  "properties": {
    "gn:admin1_code":"3.0",
    "gn:asciiname":"Nasrati Kalle",
    "gn:country_code":"PK",
    "gn:dem":305,
    "gn:feature_class":"P",
    "gn:feature_code":"PPL",
    "gn:name":"Nasrati Kalle",
    "gn:population":0,
    "gn:timezone":"Asia/Karachi",
    "iso:country":"PK",
    "wof:name":"Nasrati Kalle",
    "wof:placetype":"locality"
},
  "geometry": {"coordinates":[70.19668,32.1635],"type":"Point"}
}