{
  "type": "Feature",
  "properties": {
    "gn:admin1_code":"3",
    "gn:asciiname":"Maksar Banda",
    "gn:country_code":"PK",
    "gn:dem":3518,
    "gn:feature_class":"P",
    "gn:feature_code":"PPL",
    "gn:name":"Maksar Banda",
    "gn:population":0,
    "gn:timezone":"Asia/Karachi",
    "iso:country":"PK",
    "name:eng_x_preferred":[
        "Maksar Banda"
    ],
    "name:und_x_variant":[
        "Sar B\u0101nda"
    ],
    "wof:name":"Maksar Banda",
    "wof:placetype":"locality"
},
  "geometry": {"coordinates":[72.64586,35.29313],"type":"Point"}
}