{
  "type": "Feature",
  "properties": {
    "gn:admin1_code":"6.0",
    "gn:asciiname":"Jabba Baihk",
    "gn:country_code":"PK",
    "gn:dem":2144,
    "gn:feature_class":"P",
    "gn:feature_code":"PPL",
    "gn:name":"Jabba Baihk",
    "gn:population":0,
    "gn:timezone":"Asia/Karachi",
    "iso:country":"PK",
    "wof:name":"Jabba Baihk",
    "wof:placetype":"locality"
},
  "geometry": {"coordinates":[73.99276,34.75004000000001],"type":"Point"}
}