{
  "type": "Feature",
  "properties": {
    "gn:admin1_code":"4.0",
    "gn:asciiname":"Alipur",
    "gn:country_code":"PK",
    "gn:dem":427,
    "gn:feature_class":"P",
    "gn:feature_code":"PPL",
    "gn:name":"Alipur",
    "gn:population":0,
    "gn:timezone":"Asia/Karachi",
    "iso:country":"PK",
    "name:eng_x_preferred":[
        "Alipur"
    ],
    "name:fas_x_preferred":[
        "\u0639\u0644\u06cc\u200c\u067e\u0648\u0631 \u0686\u062a\u0647\u0647"
    ],
    "name:fra_x_preferred":[
        "Alipur Chatha"
    ],
    "name:pol_x_preferred":[
        "Alipur \u0106atha"
    ],
    "name:por_x_preferred":[
        "Alipur Chatha"
    ],
    "name:spa_x_preferred":[
        "Alipur"
    ],
    "name:urd_x_preferred":[
        "\u0639\u0644\u06cc \u067e\u0648\u0631"
    ],
    "wof:name":"Alipur",
    "wof:placetype":"locality"
},
  "geometry": {"coordinates":[73.22333,32.934],"type":"Point"}
}