{
  "type": "Feature",
  "properties": {
    "gn:admin1_code":"6",
    "gn:asciiname":"Amrutta",
    "gn:country_code":"PK",
    "gn:dem":1006,
    "gn:feature_class":"P",
    "gn:feature_code":"PPL",
    "gn:name":"Amrutta",
    "gn:population":0,
    "gn:timezone":"Asia/Karachi",
    "iso:country":"PK",
    "wof:name":"Amrutta",
    "wof:placetype":"locality"
},
  "geometry": {"coordinates":[73.91611999999998,33.66749],"type":"Point"}
}