{
  "type": "Feature",
  "properties": {
    "gn:admin1_code":"4.0",
    "gn:asciiname":"Kot Alam Shah",
    "gn:country_code":"PK",
    "gn:dem":204,
    "gn:feature_class":"P",
    "gn:feature_code":"PPL",
    "gn:name":"Kot \u0100lam Sh\u0101h",
    "gn:population":0,
    "gn:timezone":"Asia/Karachi",
    "iso:country":"PK",
    "wof:name":"Kot Alam Shah",
    "wof:placetype":"locality"
},
  "geometry": {"coordinates":[74.20944,31.37306],"type":"Point"}
}