{
  "type": "Feature",
  "properties": {
    "gn:admin1_code":"01",
    "gn:asciiname":"Mamit Khan Kot",
    "gn:country_code":"PK",
    "gn:dem":1902,
    "gn:feature_class":"P",
    "gn:feature_code":"PPL",
    "gn:name":"Mamit Khan Kot",
    "gn:population":0,
    "gn:timezone":"Asia/Karachi",
    "iso:country":"PK",
    "name:und_x_variant":[
        "Mohmit Kh\u0101n Kot"
    ],
    "wof:name":"Mamit Khan Kot",
    "wof:placetype":"locality"
},
  "geometry": {"coordinates":[69.63748000000001,32.47395],"type":"Point"}
}