{
  "type": "Feature",
  "properties": {
    "gn:admin1_code":"3.0",
    "gn:asciiname":"Kabalbash Baihk",
    "gn:country_code":"PK",
    "gn:dem":3855,
    "gn:feature_class":"P",
    "gn:feature_code":"PPL",
    "gn:name":"Kabalbash Baihk",
    "gn:population":0,
    "gn:timezone":"Asia/Karachi",
    "iso:country":"PK",
    "wof:name":"Kabalbash Baihk",
    "wof:placetype":"locality"
},
  "geometry": {"coordinates":[74.02259000000002,35.09585999999999],"type":"Point"}
}