{
  "type": "Feature",
  "properties": {
    "gn:admin1_code":"1.0",
    "gn:asciiname":"Bar Landukai",
    "gn:country_code":"PK",
    "gn:dem":2109,
    "gn:feature_class":"P",
    "gn:feature_code":"PPL",
    "gn:name":"Bar Landukai",
    "gn:population":0,
    "gn:timezone":"Asia/Karachi",
    "iso:country":"PK",
    "wof:name":"Bar Landukai",
    "wof:placetype":"locality"
},
  "geometry": {"coordinates":[71.01586,33.71834],"type":"Point"}
}