{
  "type": "Feature",
  "properties": {
    "gn:admin1_code":"4.0",
    "gn:asciiname":"Chak One Hundred Eleven GB",
    "gn:country_code":"PK",
    "gn:dem":182,
    "gn:feature_class":"P",
    "gn:feature_code":"PPL",
    "gn:name":"Chak One Hundred Eleven GB",
    "gn:population":0,
    "gn:timezone":"Asia/Karachi",
    "iso:country":"PK",
    "name:und_x_variant":[
        "Baluch\u0101nw\u0101la",
        "Chak One Hundred Eleven GB"
    ],
    "wof:name":"Chak One Hundred Eleven GB",
    "wof:placetype":"locality"
},
  "geometry": {"coordinates":[73.23942,31.32501],"type":"Point"}
}