{
  "type": "Feature",
  "properties": {
    "gn:admin1_code":"5",
    "gn:asciiname":"Kori",
    "gn:country_code":"PK",
    "gn:dem":59,
    "gn:feature_class":"P",
    "gn:feature_code":"PPL",
    "gn:name":"Kori",
    "gn:population":0,
    "gn:timezone":"Asia/Karachi",
    "iso:country":"PK",
    "name:bel_x_preferred":[
        "\u041a\u043e\u0440\u044b"
    ],
    "name:ben_x_preferred":[
        "\u0995\u09a1\u09bc\u09bf"
    ],
    "name:ceb_x_preferred":[
        "Kori"
    ],
    "name:deu_x_preferred":[
        "Kori"
    ],
    "name:ind_x_preferred":[
        "Kori"
    ],
    "name:lav_x_preferred":[
        "Kori"
    ],
    "name:swe_x_preferred":[
        "Kori"
    ],
    "name:ukr_x_preferred":[
        "\u041a\u043e\u0440\u0456"
    ],
    "wof:name":"Kori",
    "wof:placetype":"locality"
},
  "geometry": {"coordinates":[69.12728,27.53551],"type":"Point"}
}