{
  "type": "Feature",
  "properties": {
    "gn:admin1_code":"4.0",
    "gn:asciiname":"Dhuddian",
    "gn:country_code":"PK",
    "gn:dem":185,
    "gn:feature_class":"P",
    "gn:feature_code":"PPL",
    "gn:name":"Dhuddian",
    "gn:population":0,
    "gn:timezone":"Asia/Karachi",
    "iso:country":"PK",
    "name:und_x_variant":[
        "Dhuddi"
    ],
    "wof:name":"Dhuddian",
    "wof:placetype":"locality"
},
  "geometry": {"coordinates":[74.0493,30.78171],"type":"Point"}
}