{
  "type": "Feature",
  "properties": {
    "gn:admin1_code":"3",
    "gn:asciiname":"Terkani",
    "gn:country_code":"PK",
    "gn:dem":2990,
    "gn:feature_class":"P",
    "gn:feature_code":"PPL",
    "gn:name":"Terkani",
    "gn:population":0,
    "gn:timezone":"Asia/Karachi",
    "iso:country":"PK",
    "name:und_x_variant":[
        "Trekanni"
    ],
    "wof:name":"Terkani",
    "wof:placetype":"locality"
},
  "geometry": {"coordinates":[73.38811,34.69797],"type":"Point"}
}