{
  "type": "Feature",
  "properties": {
    "gn:admin1_code":"5",
    "gn:asciiname":"Abro Goth",
    "gn:country_code":"PK",
    "gn:dem":60,
    "gn:feature_class":"P",
    "gn:feature_code":"PPL",
    "gn:name":"Abro Goth",
    "gn:population":0,
    "gn:timezone":"Asia/Karachi",
    "iso:country":"PK",
    "name:und_x_variant":[
        "Baroch"
    ],
    "wof:name":"Abro Goth",
    "wof:placetype":"locality"
},
  "geometry": {"coordinates":[68.56654,27.83699],"type":"Point"}
}