{
  "type": "Feature",
  "properties": {
    "gn:admin1_code":"3.0",
    "gn:asciiname":"Chitta Batta",
    "gn:country_code":"PK",
    "gn:dem":1095,
    "gn:feature_class":"P",
    "gn:feature_code":"PPL",
    "gn:name":"Chitta Batta",
    "gn:population":0,
    "gn:timezone":"Asia/Karachi",
    "iso:country":"PK",
    "name:und_x_variant":[
        "Chata Batta",
        "Chitta Batta"
    ],
    "wof:name":"Chitta Batta",
    "wof:placetype":"locality"
},
  "geometry": {"coordinates":[73.26139999999999,34.36603],"type":"Point"}
}