{
  "type": "Feature",
  "properties": {
    "gn:admin1_code":"2.0",
    "gn:asciiname":"Ablo",
    "gn:country_code":"PK",
    "gn:dem":1186,
    "gn:feature_class":"P",
    "gn:feature_code":"PPL",
    "gn:name":"Ablo",
    "gn:population":0,
    "gn:timezone":"Asia/Karachi",
    "iso:country":"PK",
    "name:und_x_variant":[
        "Att\u0101 Muhammad",
        "Ablo"
    ],
    "wof:name":"Ablo",
    "wof:placetype":"locality"
},
  "geometry": {"coordinates":[66.14068,27.64802],"type":"Point"}
}