{
  "type": "Feature",
  "properties": {
    "gn:admin1_code":"1.0",
    "gn:asciiname":"Odigram",
    "gn:country_code":"PK",
    "gn:dem":1132,
    "gn:feature_class":"P",
    "gn:feature_code":"PPL",
    "gn:name":"Odigram",
    "gn:population":0,
    "gn:timezone":"Asia/Karachi",
    "iso:country":"PK",
    "name:fas_x_preferred":[
        "\u0648\u062f\u06cc\u06af\u0631\u0627\u0645"
    ],
    "name:und_x_variant":[
        "Odigaram"
    ],
    "name:urd_x_preferred":[
        "\u0648\u0688\u06cc\u06af\u0631\u0627\u0645"
    ],
    "wof:name":"Odigram",
    "wof:placetype":"locality"
},
  "geometry": {"coordinates":[71.47681999999998,34.88534],"type":"Point"}
}