{
  "type": "Feature",
  "properties": {
    "gn:admin1_code":"6",
    "gn:asciiname":"Gail",
    "gn:country_code":"PK",
    "gn:dem":1345,
    "gn:feature_class":"P",
    "gn:feature_code":"PPL",
    "gn:name":"Gail",
    "gn:population":0,
    "gn:timezone":"Asia/Karachi",
    "iso:country":"PK",
    "name:ceb_x_preferred":[
        "Gail"
    ],
    "name:deu_x_preferred":[
        "Gail"
    ],
    "name:fra_x_preferred":[
        "Gail"
    ],
    "name:hun_x_preferred":[
        "Gail"
    ],
    "name:pol_x_preferred":[
        "Gail"
    ],
    "name:por_x_preferred":[
        "Gail"
    ],
    "name:spa_x_preferred":[
        "Gail"
    ],
    "name:srp_x_preferred":[
        "\u0413\u0435\u0458\u043b"
    ],
    "name:swe_x_preferred":[
        "Gail"
    ],
    "wof:name":"Gail",
    "wof:placetype":"locality"
},
  "geometry": {"coordinates":[74.15584,33.45043],"type":"Point"}
}