{
  "type": "Feature",
  "properties": {
    "gn:admin1_code":"6",
    "gn:asciiname":"Gail",
    "gn:country_code":"PK",
    "gn:dem":1345,
    "gn:feature_class":"P",
    "gn:feature_code":"PPL",
    "gn:name":"Gail",
    "gn:population":0,
    "gn:timezone":"Asia/Karachi",
    "iso:country":"PK",
    "wof:name":"Gail",
    "wof:placetype":"locality"
},
  "geometry": {"coordinates":[74.15584,33.45043],"type":"Point"}
}