{
  "type": "Feature",
  "properties": {
    "gn:admin1_code":"1.0",
    "gn:asciiname":"Maizu Baba Said Baba Ziarat",
    "gn:country_code":"PK",
    "gn:dem":1748,
    "gn:feature_class":"P",
    "gn:feature_code":"PPL",
    "gn:name":"Maizu Baba Said Baba Ziarat",
    "gn:population":0,
    "gn:timezone":"Asia/Karachi",
    "iso:country":"PK",
    "name:und_x_variant":[
        "Maizu B\u0101ba Said Baba Zi\u0101rat"
    ],
    "wof:name":"Maizu Baba Said Baba Ziarat",
    "wof:placetype":"locality"
},
  "geometry": {"coordinates":[71.06005,34.56007],"type":"Point"}
}