{
  "type": "Feature",
  "properties": {
    "gn:admin1_code":"2.0",
    "gn:asciiname":"Kohna Kalat",
    "gn:country_code":"PK",
    "gn:dem":1130,
    "gn:feature_class":"P",
    "gn:feature_code":"PPL",
    "gn:name":"Kohna Kalat",
    "gn:population":0,
    "gn:timezone":"Asia/Karachi",
    "iso:country":"PK",
    "wof:name":"Kohna Kalat",
    "wof:placetype":"locality"
},
  "geometry": {"coordinates":[64.76267,26.93235],"type":"Point"}
}