{
  "type": "Feature",
  "properties": {
    "gn:admin1_code":"3.0",
    "gn:asciiname":"Paja",
    "gn:country_code":"PK",
    "gn:dem":3004,
    "gn:feature_class":"P",
    "gn:feature_code":"PPL",
    "gn:name":"Paja",
    "gn:population":0,
    "gn:timezone":"Asia/Karachi",
    "iso:country":"PK",
    "wof:name":"Paja",
    "wof:placetype":"locality"
},
  "geometry": {"coordinates":[73.81115,34.92225999999999],"type":"Point"}
}