{
  "type": "Feature",
  "properties": {
    "gn:admin1_code":"4.0",
    "gn:asciiname":"Khuddozai",
    "gn:country_code":"PK",
    "gn:dem":216,
    "gn:feature_class":"P",
    "gn:feature_code":"PPL",
    "gn:name":"Khuddozai",
    "gn:population":0,
    "gn:timezone":"Asia/Karachi",
    "iso:country":"PK",
    "name:und_x_variant":[
        "Khudozai",
        "Khuddozai"
    ],
    "wof:name":"Khuddozai",
    "wof:placetype":"locality"
},
  "geometry": {"coordinates":[71.43647,32.88541],"type":"Point"}
}