{
  "type": "Feature",
  "properties": {
    "gn:admin1_code":"4",
    "gn:asciiname":"Vasawawala Junubi",
    "gn:country_code":"PK",
    "gn:dem":142,
    "gn:feature_class":"P",
    "gn:feature_code":"PPL",
    "gn:name":"Vasawawala Junubi",
    "gn:population":0,
    "gn:timezone":"Asia/Karachi",
    "iso:country":"PK",
    "name:und_x_variant":[
        "Vas\u0101w\u0101w\u0101la"
    ],
    "wof:name":"Vasawawala Junubi",
    "wof:placetype":"locality"
},
  "geometry": {"coordinates":[71.56211,30.83386],"type":"Point"}
}