{
  "type": "Feature",
  "properties": {
    "gn:admin1_code":"4.0",
    "gn:asciiname":"Wailianwala",
    "gn:country_code":"PK",
    "gn:dem":212,
    "gn:feature_class":"P",
    "gn:feature_code":"PPL",
    "gn:name":"Wailianwala",
    "gn:population":0,
    "gn:timezone":"Asia/Karachi",
    "iso:country":"PK",
    "name:und_x_variant":[
        "Wail\u0101nw\u0101la",
        "Bul\u0101qw\u0101la",
        "Wailianwala"
    ],
    "wof:name":"Wailianwala",
    "wof:placetype":"locality"
},
  "geometry": {"coordinates":[73.95132,31.84831],"type":"Point"}
}