{
  "type": "Feature",
  "properties": {
    "gn:admin1_code":"4.0",
    "gn:asciiname":"Allah Dad Imrana Di Bhini",
    "gn:country_code":"PK",
    "gn:dem":135,
    "gn:feature_class":"P",
    "gn:feature_code":"PPL",
    "gn:name":"Allah Dad Imrana Di Bhini",
    "gn:population":0,
    "gn:timezone":"Asia/Karachi",
    "iso:country":"PK",
    "wof:name":"Allah Dad Imrana Di Bhini",
    "wof:placetype":"locality"
},
  "geometry": {"coordinates":[71.97626,30.21093],"type":"Point"}
}