{
  "type": "Feature",
  "properties": {
    "gn:admin1_code":"4",
    "gn:asciiname":"Chak Five Hundred Forty-five Eastern Bar",
    "gn:country_code":"PK",
    "gn:dem":144,
    "gn:feature_class":"P",
    "gn:feature_code":"PPL",
    "gn:name":"Chak Five Hundred Forty-five Eastern Bar",
    "gn:population":0,
    "gn:timezone":"Asia/Karachi",
    "iso:country":"PK",
    "name:und_x_variant":[
        "Chak Five Hundred Forty-five EB",
        "Baluchw\u0101la"
    ],
    "wof:name":"Chak Five Hundred Forty-five Eastern Bar",
    "wof:placetype":"locality"
},
  "geometry": {"coordinates":[72.56154000000002,30.09392],"type":"Point"}
}