{
  "type": "Feature",
  "properties": {
    "gn:admin1_code":"04",
    "gn:asciiname":"Non Kallu",
    "gn:country_code":"PK",
    "gn:dem":180,
    "gn:feature_class":"P",
    "gn:feature_code":"PPL",
    "gn:name":"Non Kallu",
    "gn:population":0,
    "gn:timezone":"Asia/Karachi",
    "iso:country":"PK",
    "name:und_x_variant":[
        "Noon Kallu",
        "N\u016bn Kallu",
        "Non Kallu"
    ],
    "wof:name":"Non Kallu",
    "wof:placetype":"locality"
},
  "geometry": {"coordinates":[72.41093000000002,32.23511],"type":"Point"}
}