{
  "type": "Feature",
  "properties": {
    "gn:admin1_code":"03",
    "gn:asciiname":"Mochiwal",
    "gn:country_code":"PK",
    "gn:dem":205,
    "gn:feature_class":"P",
    "gn:feature_code":"PPL",
    "gn:name":"Mochiwal",
    "gn:population":0,
    "gn:timezone":"Asia/Karachi",
    "iso:country":"PK",
    "name:und_x_variant":[
        "Muchiwal",
        "Mochiwal"
    ],
    "wof:name":"Mochiwal",
    "wof:placetype":"locality"
},
  "geometry": {"coordinates":[70.51156,31.73506],"type":"Point"}
}