{
  "type": "Feature",
  "properties": {
    "gn:admin1_code":"6",
    "gn:asciiname":"Muhri",
    "gn:country_code":"PK",
    "gn:dem":2828,
    "gn:feature_class":"P",
    "gn:feature_code":"PPL",
    "gn:name":"Muhri",
    "gn:population":0,
    "gn:timezone":"Asia/Karachi",
    "iso:country":"PK",
    "wof:name":"Muhri",
    "wof:placetype":"locality"
},
  "geometry": {"coordinates":[74.15555999999999,34.01944],"type":"Point"}
}