{
  "type": "Feature",
  "properties": {
    "gn:admin1_code":"3",
    "gn:asciiname":"Basian",
    "gn:country_code":"PK",
    "gn:dem":925,
    "gn:feature_class":"P",
    "gn:feature_code":"PPL",
    "gn:name":"Basian",
    "gn:population":0,
    "gn:timezone":"Asia/Karachi",
    "iso:country":"PK",
    "wof:name":"Basian",
    "wof:placetype":"locality"
},
  "geometry": {"coordinates":[73.48251999999999,34.07435],"type":"Point"}
}