{
  "type": "Feature",
  "properties": {
    "gn:admin1_code":"3.0",
    "gn:asciiname":"Parait",
    "gn:country_code":"PK",
    "gn:dem":1828,
    "gn:feature_class":"P",
    "gn:feature_code":"PPL",
    "gn:name":"Parait",
    "gn:population":0,
    "gn:timezone":"Asia/Karachi",
    "iso:country":"PK",
    "name:und_x_variant":[
        "Pret"
    ],
    "wof:name":"Parait",
    "wof:placetype":"locality"
},
  "geometry": {"coordinates":[72.0245,36.05274],"type":"Point"}
}