{
  "type": "Feature",
  "properties": {
    "gn:admin1_code":"05",
    "gn:asciiname":"Thari Mir Wah",
    "gn:country_code":"PK",
    "gn:dem":49,
    "gn:feature_class":"P",
    "gn:feature_code":"PPL",
    "gn:name":"Thari Mir Wah",
    "gn:population":0,
    "gn:timezone":"Asia/Karachi",
    "iso:country":"PK",
    "name:und_x_variant":[
        "M\u012brw\u0101h",
        "Thari",
        "Thari Mir Wah"
    ],
    "wof:name":"Thari Mir Wah",
    "wof:placetype":"locality"
},
  "geometry": {"coordinates":[68.6143,27.06891],"type":"Point"}
}