{
  "type": "Feature",
  "properties": {
    "gn:admin1_code":"3.0",
    "gn:asciiname":"Hassanabad",
    "gn:country_code":"PK",
    "gn:dem":1606,
    "gn:feature_class":"P",
    "gn:feature_code":"PPL",
    "gn:name":"Hassanabad",
    "gn:population":0,
    "gn:timezone":"Asia/Karachi",
    "iso:country":"PK",
    "wof:name":"Hassanabad",
    "wof:placetype":"locality"
},
  "geometry": {"coordinates":[72.12908,34.96262],"type":"Point"}
}