{
  "type": "Feature",
  "properties": {
    "gn:admin1_code":"3",
    "gn:asciiname":"Sirhi",
    "gn:country_code":"PK",
    "gn:dem":671,
    "gn:feature_class":"P",
    "gn:feature_code":"PPL",
    "gn:name":"Sirhi",
    "gn:population":0,
    "gn:timezone":"Asia/Karachi",
    "iso:country":"PK",
    "wof:name":"Sirhi",
    "wof:placetype":"locality"
},
  "geometry": {"coordinates":[72.78604,34.2485],"type":"Point"}
}