{
  "type": "Feature",
  "properties": {
    "gn:admin1_code":"05",
    "gn:asciiname":"Goth Wariaso",
    "gn:country_code":"PK",
    "gn:dem":52,
    "gn:feature_class":"P",
    "gn:feature_code":"PPL",
    "gn:name":"Goth Wariaso",
    "gn:population":0,
    "gn:timezone":"Asia/Karachi",
    "iso:country":"PK",
    "name:und_x_variant":[
        "W\u00e1ri\u00e1so",
        "Waryaso",
        "Goth Wariaso",
        "War\u0101so"
    ],
    "wof:name":"Goth Wariaso",
    "wof:placetype":"locality"
},
  "geometry": {"coordinates":[68.30705,27.91606],"type":"Point"}
}