{
  "type": "Feature",
  "properties": {
    "gn:admin1_code":"2.0",
    "gn:asciiname":"Sajan Goth",
    "gn:country_code":"PK",
    "gn:dem":265,
    "gn:feature_class":"P",
    "gn:feature_code":"PPL",
    "gn:name":"Sajan Goth",
    "gn:population":0,
    "gn:timezone":"Asia/Karachi",
    "iso:country":"PK",
    "wof:name":"Sajan Goth",
    "wof:placetype":"locality"
},
  "geometry": {"coordinates":[67.30812,25.81163],"type":"Point"}
}