{
  "type": "Feature",
  "properties": {
    "gn:admin1_code":"2.0",
    "gn:asciiname":"Darya Khan",
    "gn:country_code":"PK",
    "gn:dem":583,
    "gn:feature_class":"P",
    "gn:feature_code":"PPL",
    "gn:name":"Darya Khan",
    "gn:population":0,
    "gn:timezone":"Asia/Karachi",
    "iso:country":"PK",
    "name:ceb_x_preferred":[
        "Darya Kh\u0101n"
    ],
    "name:fas_x_preferred":[
        "\u062f\u0631\u06cc\u0627\u062e\u0627\u0646"
    ],
    "name:fra_x_preferred":[
        "Darya Khan"
    ],
    "name:hin_x_preferred":[
        "\u0926\u0930\u092f\u093e \u0916\u093e\u0928"
    ],
    "name:pnb_x_preferred":[
        "\u062f\u0631\u06cc\u0627 \u062e\u0627\u0646"
    ],
    "name:por_x_preferred":[
        "Darya Khan"
    ],
    "name:urd_x_preferred":[
        "\u062f\u0631\u06cc\u0627 \u062e\u0627\u0646"
    ],
    "wof:name":"Darya Khan",
    "wof:placetype":"locality"
},
  "geometry": {"coordinates":[66.35708000000001,26.63964],"type":"Point"}
}