{
  "type": "Feature",
  "properties": {
    "gn:admin1_code":"4",
    "gn:asciiname":"Chak One Hundred Fourteen A Desert Branch",
    "gn:country_code":"PK",
    "gn:dem":113,
    "gn:feature_class":"P",
    "gn:feature_code":"PPL",
    "gn:name":"Chak One Hundred Fourteen A Desert Branch",
    "gn:population":0,
    "gn:timezone":"Asia/Karachi",
    "iso:country":"PK",
    "name:eng_x_preferred":[
        "Chak One Hundred Fourteen ADB"
    ],
    "wof:name":"Chak One Hundred Fourteen A Desert Branch",
    "wof:placetype":"locality"
},
  "geometry": {"coordinates":[71.61901999999998,29.03956],"type":"Point"}
}