{
  "type": "Feature",
  "properties": {
    "gn:admin1_code":"4",
    "gn:asciiname":"Balochwala",
    "gn:country_code":"PK",
    "gn:dem":106,
    "gn:feature_class":"P",
    "gn:feature_code":"PPL",
    "gn:name":"Balochwala",
    "gn:population":0,
    "gn:timezone":"Asia/Karachi",
    "iso:country":"PK",
    "name:und_x_variant":[
        "Balochw\u0101li"
    ],
    "wof:name":"Balochwala",
    "wof:placetype":"locality"
},
  "geometry": {"coordinates":[71.26325,29.26659],"type":"Point"}
}