{
  "type": "Feature",
  "properties": {
    "gn:admin1_code":"2.0",
    "gn:asciiname":"Kili Dinarzai",
    "gn:country_code":"PK",
    "gn:dem":1675,
    "gn:feature_class":"P",
    "gn:feature_code":"PPL",
    "gn:name":"Kili Dinarzai",
    "gn:population":0,
    "gn:timezone":"Asia/Karachi",
    "iso:country":"PK",
    "name:und_x_variant":[
        "D\u012bn\u0101r"
    ],
    "wof:name":"Kili Dinarzai",
    "wof:placetype":"locality"
},
  "geometry": {"coordinates":[66.12279000000001,28.38522],"type":"Point"}
}