{
  "type": "Feature",
  "properties": {
    "gn:admin1_code":"3.0",
    "gn:asciiname":"Batangi",
    "gn:country_code":"PK",
    "gn:dem":2149,
    "gn:feature_class":"P",
    "gn:feature_code":"PPL",
    "gn:name":"Batangi",
    "gn:population":0,
    "gn:timezone":"Asia/Karachi",
    "iso:country":"PK",
    "wof:name":"Batangi",
    "wof:placetype":"locality"
},
  "geometry": {"coordinates":[73.15541999999998,34.70141],"type":"Point"}
}