{
  "type": "Feature",
  "properties": {
    "gn:admin1_code":"4",
    "gn:asciiname":"Nagrian",
    "gn:country_code":"PK",
    "gn:dem":291,
    "gn:feature_class":"P",
    "gn:feature_code":"PPL",
    "gn:name":"Nagrian",
    "gn:population":0,
    "gn:timezone":"Asia/Karachi",
    "iso:country":"PK",
    "name:und_x_variant":[
        "N\u0101griah"
    ],
    "wof:name":"Nagrian",
    "wof:placetype":"locality"
},
  "geometry": {"coordinates":[74.11731,32.79666],"type":"Point"}
}