{
  "type": "Feature",
  "properties": {
    "gn:admin1_code":"01",
    "gn:asciiname":"Amrezo",
    "gn:country_code":"PK",
    "gn:dem":1965,
    "gn:feature_class":"P",
    "gn:feature_code":"PPL",
    "gn:name":"Amrezo",
    "gn:population":0,
    "gn:timezone":"Asia/Karachi",
    "iso:country":"PK",
    "name:und_x_variant":[
        "Amraizo"
    ],
    "wof:name":"Amrezo",
    "wof:placetype":"locality"
},
  "geometry": {"coordinates":[70.56463000000002,33.81405],"type":"Point"}
}