{
  "type": "Feature",
  "properties": {
    "gn:admin1_code":"4.0",
    "gn:asciiname":"Waddi Basti",
    "gn:country_code":"PK",
    "gn:dem":112,
    "gn:feature_class":"P",
    "gn:feature_code":"PPL",
    "gn:name":"Waddi Basti",
    "gn:population":0,
    "gn:timezone":"Asia/Karachi",
    "iso:country":"PK",
    "wof:name":"Waddi Basti",
    "wof:placetype":"locality"
},
  "geometry": {"coordinates":[71.13330000000001,29.69107],"type":"Point"}
}