{
  "type": "Feature",
  "properties": {
    "gn:admin1_code":"5.0",
    "gn:asciiname":"Haji Ali Muhammad Sathani",
    "gn:country_code":"PK",
    "gn:dem":305,
    "gn:feature_class":"P",
    "gn:feature_code":"PPL",
    "gn:name":"Haji Ali Muhammad Sathani",
    "gn:population":0,
    "gn:timezone":"Asia/Karachi",
    "iso:country":"PK",
    "name:und_x_variant":[
        "Goth-Jur\u012ba Kh\u0101n"
    ],
    "wof:name":"Haji Ali Muhammad Sathani",
    "wof:placetype":"locality"
},
  "geometry": {"coordinates":[67.51193000000001,25.91312000000001],"type":"Point"}
}