{
  "type": "Feature",
  "properties": {
    "gn:admin1_code":"3",
    "gn:asciiname":"Mian Khan Kharri",
    "gn:country_code":"PK",
    "gn:dem":175,
    "gn:feature_class":"P",
    "gn:feature_code":"PPL",
    "gn:name":"Mian Khan Kharri",
    "gn:population":0,
    "gn:timezone":"Asia/Karachi",
    "iso:country":"PK",
    "name:und_x_variant":[
        "Mi\u0101n Khel Kirri",
        "Mi\u0101n Khel Karri",
        "Mian Khan Kharri"
    ],
    "wof:name":"Mian Khan Kharri",
    "wof:placetype":"locality"
},
  "geometry": {"coordinates":[70.80641,31.69366],"type":"Point"}
}