{
  "type": "Feature",
  "properties": {
    "gn:admin1_code":"4.0",
    "gn:asciiname":"Makha",
    "gn:country_code":"PK",
    "gn:dem":622,
    "gn:feature_class":"P",
    "gn:feature_code":"PPL",
    "gn:name":"Makha",
    "gn:population":0,
    "gn:timezone":"Asia/Karachi",
    "iso:country":"PK",
    "wof:name":"Makha",
    "wof:placetype":"locality"
},
  "geometry": {"coordinates":[70.31976999999999,30.78717],"type":"Point"}
}