{
  "type": "Feature",
  "properties": {
    "gn:admin1_code":"4",
    "gn:asciiname":"Chak Forty-one -Twelve Left",
    "gn:country_code":"PK",
    "gn:dem":163,
    "gn:feature_class":"P",
    "gn:feature_code":"PPL",
    "gn:name":"Chak Forty-one -Twelve Left",
    "gn:population":0,
    "gn:timezone":"Asia/Karachi",
    "iso:country":"PK",
    "name:und_x_variant":[
        "Chak Forty-one-Twelve L"
    ],
    "wof:name":"Chak Forty-one -Twelve Left",
    "wof:placetype":"locality"
},
  "geometry": {"coordinates":[72.71223000000001,30.50433],"type":"Point"}
}