{
  "type": "Feature",
  "properties": {
    "gn:admin1_code":"4.0",
    "gn:asciiname":"Balewala",
    "gn:country_code":"PK",
    "gn:dem":119,
    "gn:feature_class":"P",
    "gn:feature_code":"PPL",
    "gn:name":"Balewala",
    "gn:population":0,
    "gn:timezone":"Asia/Karachi",
    "iso:country":"PK",
    "name:eng_x_preferred":[
        "Balewala"
    ],
    "name:und_x_variant":[
        "Bohrw\u0101la"
    ],
    "wof:name":"Balewala",
    "wof:placetype":"locality"
},
  "geometry": {"coordinates":[70.64121,30.00356],"type":"Point"}
}