{
  "type": "Feature",
  "properties": {
    "gn:admin1_code":"05",
    "gn:asciiname":"Maujwah",
    "gn:country_code":"PK",
    "gn:dem":26,
    "gn:feature_class":"P",
    "gn:feature_code":"PPL",
    "gn:name":"Maujwah",
    "gn:population":0,
    "gn:timezone":"Asia/Karachi",
    "iso:country":"PK",
    "name:und_x_variant":[
        "Maojw\u0101h"
    ],
    "wof:name":"Maujwah",
    "wof:placetype":"locality"
},
  "geometry": {"coordinates":[68.63333,26.05],"type":"Point"}
}