{
  "type": "Feature",
  "properties": {
    "gn:admin1_code":"4",
    "gn:asciiname":"Chak Fifty-six Western Bank",
    "gn:country_code":"PK",
    "gn:dem":139,
    "gn:feature_class":"P",
    "gn:feature_code":"PPL",
    "gn:name":"Chak Fifty-six Western Bank",
    "gn:population":0,
    "gn:timezone":"Asia/Karachi",
    "iso:country":"PK",
    "name:und_x_variant":[
        "Chak Fifty-six"
    ],
    "wof:name":"Chak Fifty-six Western Bank",
    "wof:placetype":"locality"
},
  "geometry": {"coordinates":[72.25973,30.10952],"type":"Point"}
}