{
  "type": "Feature",
  "properties": {
    "gn:admin1_code":"3",
    "gn:asciiname":"Purana Bhogar Mang",
    "gn:country_code":"PK",
    "gn:dem":1282,
    "gn:feature_class":"P",
    "gn:feature_code":"PPL",
    "gn:name":"Purana Bhogar Mang",
    "gn:population":0,
    "gn:timezone":"Asia/Karachi",
    "iso:country":"PK",
    "name:und_x_variant":[
        "Pur\u0101na Bhogarmang"
    ],
    "wof:name":"Purana Bhogar Mang",
    "wof:placetype":"locality"
},
  "geometry": {"coordinates":[73.25618,34.58018],"type":"Point"}
}