{
  "type": "Feature",
  "properties": {
    "gn:admin1_code":"1.0",
    "gn:asciiname":"Shinsara",
    "gn:country_code":"PK",
    "gn:dem":672,
    "gn:feature_class":"P",
    "gn:feature_code":"PPL",
    "gn:name":"Shinsara",
    "gn:population":0,
    "gn:timezone":"Asia/Karachi",
    "iso:country":"PK",
    "name:und_x_variant":[
        "Shinsari"
    ],
    "wof:name":"Shinsara",
    "wof:placetype":"locality"
},
  "geometry": {"coordinates":[71.4348,34.45947],"type":"Point"}
}