{
  "type": "Feature",
  "properties": {
    "gn:admin1_code":"4.0",
    "gn:asciiname":"Biya Singhewala",
    "gn:country_code":"PK",
    "gn:dem":189,
    "gn:feature_class":"P",
    "gn:feature_code":"PPL",
    "gn:name":"Biya Singhewala",
    "gn:population":0,
    "gn:timezone":"Asia/Karachi",
    "iso:country":"PK",
    "name:und_x_variant":[
        "Biha Singhwala",
        "Biya Singhw\u0101la",
        "Biya Singhewala"
    ],
    "wof:name":"Biya Singhewala",
    "wof:placetype":"locality"
},
  "geometry": {"coordinates":[74.19379000000001,30.91339],"type":"Point"}
}