{
  "type": "Feature",
  "properties": {
    "gn:admin1_code":"4",
    "gn:asciiname":"Werewala",
    "gn:country_code":"PK",
    "gn:dem":125,
    "gn:feature_class":"P",
    "gn:feature_code":"PPL",
    "gn:name":"Werewala",
    "gn:population":0,
    "gn:timezone":"Asia/Karachi",
    "iso:country":"PK",
    "name:und_x_variant":[
        "Warew\u0101la"
    ],
    "wof:name":"Werewala",
    "wof:placetype":"locality"
},
  "geometry": {"coordinates":[71.90193000000002,29.58294],"type":"Point"}
}