{
  "type": "Feature",
  "properties": {
    "gn:admin1_code":"5",
    "gn:asciiname":"Arz Muhammad Magsi",
    "gn:country_code":"PK",
    "gn:dem":43,
    "gn:feature_class":"P",
    "gn:feature_code":"PPL",
    "gn:name":"Arz Muhammad Magsi",
    "gn:population":0,
    "gn:timezone":"Asia/Karachi",
    "iso:country":"PK",
    "wof:name":"Arz Muhammad Magsi",
    "wof:placetype":"locality"
},
  "geometry": {"coordinates":[68.104,26.70065],"type":"Point"}
}