{
  "type": "Feature",
  "properties": {
    "gn:admin1_code":"4.0",
    "gn:asciiname":"Chak Wichla",
    "gn:country_code":"PK",
    "gn:dem":288,
    "gn:feature_class":"P",
    "gn:feature_code":"PPL",
    "gn:name":"Chak Wichla",
    "gn:population":0,
    "gn:timezone":"Asia/Karachi",
    "iso:country":"PK",
    "wof:name":"Chak Wichla",
    "wof:placetype":"locality"
},
  "geometry": {"coordinates":[74.96941,32.41623],"type":"Point"}
}