{
  "type": "Feature",
  "properties": {
    "gn:admin1_code":"5.0",
    "gn:asciiname":"Goth Qamber Magsi",
    "gn:country_code":"PK",
    "gn:dem":17,
    "gn:feature_class":"P",
    "gn:feature_code":"PPL",
    "gn:name":"Goth Qamber Magsi",
    "gn:population":0,
    "gn:timezone":"Asia/Karachi",
    "iso:country":"PK",
    "name:und_x_variant":[
        "Mir Muhammad W\u0101dho"
    ],
    "wof:name":"Goth Qamber Magsi",
    "wof:placetype":"locality"
},
  "geometry": {"coordinates":[68.59673000000001,25.01402],"type":"Point"}
}