{
  "type": "Feature",
  "properties": {
    "gn:admin1_code":"3.0",
    "gn:asciiname":"Azurdam",
    "gn:country_code":"PK",
    "gn:dem":1363,
    "gn:feature_class":"P",
    "gn:feature_code":"PPL",
    "gn:name":"Azurdam",
    "gn:population":0,
    "gn:timezone":"Asia/Karachi",
    "iso:country":"PK",
    "wof:name":"Azurdam",
    "wof:placetype":"locality"
},
  "geometry": {"coordinates":[71.82545,35.58886],"type":"Point"}
}