{
  "type": "Feature",
  "properties": {
    "gn:admin1_code":"2.0",
    "gn:asciiname":"Karez",
    "gn:country_code":"PK",
    "gn:dem":1505,
    "gn:feature_class":"P",
    "gn:feature_code":"PPL",
    "gn:name":"Karez",
    "gn:population":0,
    "gn:timezone":"Asia/Karachi",
    "iso:country":"PK",
    "wof:name":"Karez",
    "wof:placetype":"locality"
},
  "geometry": {"coordinates":[66.75556999999999,27.91959],"type":"Point"}
}