{
  "type": "Feature",
  "properties": {
    "gn:admin1_code":"4.0",
    "gn:asciiname":"Chak One Hundred Twelve -Nine Left",
    "gn:country_code":"PK",
    "gn:dem":160,
    "gn:feature_class":"P",
    "gn:feature_code":"PPL",
    "gn:name":"Chak One Hundred Twelve -Nine Left",
    "gn:population":0,
    "gn:timezone":"Asia/Karachi",
    "iso:country":"PK",
    "name:und_x_variant":[
        "Jauti\u0101nw\u0101la"
    ],
    "wof:name":"Chak One Hundred Twelve -Nine Left",
    "wof:placetype":"locality"
},
  "geometry": {"coordinates":[73.1451,30.51447000000001],"type":"Point"}
}