{
  "type": "Feature",
  "properties": {
    "gn:admin1_code":"5.0",
    "gn:asciiname":"Goth Jan Muhammad Mongrio",
    "gn:country_code":"PK",
    "gn:dem":29,
    "gn:feature_class":"P",
    "gn:feature_code":"PPL",
    "gn:name":"Goth Jan Muhammad Mongrio",
    "gn:population":0,
    "gn:timezone":"Asia/Karachi",
    "iso:country":"PK",
    "wof:name":"Goth Jan Muhammad Mongrio",
    "wof:placetype":"locality"
},
  "geometry": {"coordinates":[70.52674,24.56113],"type":"Point"}
}