{
  "type": "Feature",
  "properties": {
    "gn:admin1_code":"4",
    "gn:asciiname":"Mehar Bakkhu",
    "gn:country_code":"PK",
    "gn:dem":92,
    "gn:feature_class":"P",
    "gn:feature_code":"PPL",
    "gn:name":"Mehar Bakkhu",
    "gn:population":0,
    "gn:timezone":"Asia/Karachi",
    "iso:country":"PK",
    "wof:name":"Mehar Bakkhu",
    "wof:placetype":"locality"
},
  "geometry": {"coordinates":[70.90694000000001,28.94028],"type":"Point"}
}