{
  "type": "Feature",
  "properties": {
    "gn:admin1_code":"03",
    "gn:asciiname":"Makhai",
    "gn:country_code":"PK",
    "gn:dem":896,
    "gn:feature_class":"P",
    "gn:feature_code":"PPL",
    "gn:name":"Makhai",
    "gn:population":0,
    "gn:timezone":"Asia/Karachi",
    "iso:country":"PK",
    "wof:name":"Makhai",
    "wof:placetype":"locality"
},
  "geometry": {"coordinates":[71.75100999999999,34.8306],"type":"Point"}
}