{
  "type": "Feature",
  "properties": {
    "gn:admin1_code":"03",
    "gn:asciiname":"Mari",
    "gn:country_code":"PK",
    "gn:dem":560,
    "gn:feature_class":"P",
    "gn:feature_code":"PPL",
    "gn:name":"Mari",
    "gn:population":0,
    "gn:timezone":"Asia/Karachi",
    "iso:country":"PK",
    "name:und_x_variant":[
        "Mori",
        "Mari"
    ],
    "wof:name":"Mari",
    "wof:placetype":"locality"
},
  "geometry": {"coordinates":[72.88221999999998,34.19306],"type":"Point"}
}