{
  "type": "Feature",
  "properties": {
    "gn:admin1_code":"2.0",
    "gn:asciiname":"Muhammad Baqa",
    "gn:country_code":"PK",
    "gn:dem":72,
    "gn:feature_class":"P",
    "gn:feature_code":"PPL",
    "gn:name":"Muhammad Baqa",
    "gn:population":0,
    "gn:timezone":"Asia/Karachi",
    "iso:country":"PK",
    "name:und_x_variant":[
        "Muhammad Baga"
    ],
    "wof:name":"Muhammad Baqa",
    "wof:placetype":"locality"
},
  "geometry": {"coordinates":[67.71954000000001,28.57162000000001],"type":"Point"}
}