{
  "type": "Feature",
  "properties": {
    "gn:admin1_code":"5",
    "gn:asciiname":"Ghulam Ali Laghari",
    "gn:country_code":"PK",
    "gn:dem":22,
    "gn:feature_class":"P",
    "gn:feature_code":"PPL",
    "gn:name":"Ghulam Ali Laghari",
    "gn:population":0,
    "gn:timezone":"Asia/Karachi",
    "iso:country":"PK",
    "wof:name":"Ghulam Ali Laghari",
    "wof:placetype":"locality"
},
  "geometry": {"coordinates":[68.88588,25.41481],"type":"Point"}
}