{
  "type": "Feature",
  "properties": {
    "gn:admin1_code":"3.0",
    "gn:asciiname":"Kuldeh",
    "gn:country_code":"PK",
    "gn:dem":1612,
    "gn:feature_class":"P",
    "gn:feature_code":"PPL",
    "gn:name":"Kuldeh",
    "gn:population":0,
    "gn:timezone":"Asia/Karachi",
    "iso:country":"PK",
    "wof:name":"Kuldeh",
    "wof:placetype":"locality"
},
  "geometry": {"coordinates":[71.79241999999998,35.75322],"type":"Point"}
}