{
  "type": "Feature",
  "properties": {
    "gn:admin1_code":"3.0",
    "gn:asciiname":"Sama Gol",
    "gn:country_code":"PK",
    "gn:dem":2048,
    "gn:feature_class":"P",
    "gn:feature_code":"PPL",
    "gn:name":"Sama Gol",
    "gn:population":0,
    "gn:timezone":"Asia/Karachi",
    "iso:country":"PK",
    "wof:name":"Sama Gol",
    "wof:placetype":"locality"
},
  "geometry": {"coordinates":[72.19383000000001,36.28408],"type":"Point"}
}