{
  "type": "Feature",
  "properties": {
    "gn:admin1_code":"4",
    "gn:asciiname":"Basti Ali Hasan Sojal",
    "gn:country_code":"PK",
    "gn:dem":78,
    "gn:feature_class":"P",
    "gn:feature_code":"PPL",
    "gn:name":"Basti Ali Hasan Sojal",
    "gn:population":0,
    "gn:timezone":"Asia/Karachi",
    "iso:country":"PK",
    "name:und_x_variant":[
        "Sojai"
    ],
    "wof:name":"Basti Ali Hasan Sojal",
    "wof:placetype":"locality"
},
  "geometry": {"coordinates":[69.93607,28.30121],"type":"Point"}
}