{
  "type": "Feature",
  "properties": {
    "gn:admin1_code":"04",
    "gn:asciiname":"Chak Seventy-four -Five Left",
    "gn:country_code":"PK",
    "gn:dem":130,
    "gn:feature_class":"P",
    "gn:feature_code":"PPL",
    "gn:name":"Chak Seventy-four -Five Left",
    "gn:population":0,
    "gn:timezone":"Asia/Karachi",
    "iso:country":"PK",
    "name:und_x_variant":[
        "L\u0101r\u0101nw\u0101la"
    ],
    "wof:name":"Chak Seventy-four -Five Left",
    "wof:placetype":"locality"
},
  "geometry": {"coordinates":[72.05759999999999,30.08938],"type":"Point"}
}