{
  "type": "Feature",
  "properties": {
    "gn:admin1_code":"2",
    "gn:asciiname":"Kili Masiti Landi",
    "gn:country_code":"PK",
    "gn:dem":818,
    "gn:feature_class":"P",
    "gn:feature_code":"PPL",
    "gn:name":"Kili Masiti Landi",
    "gn:population":0,
    "gn:timezone":"Asia/Karachi",
    "iso:country":"PK",
    "name:und_x_variant":[
        "Mas\u012bti L\u0101ndi"
    ],
    "wof:name":"Kili Masiti Landi",
    "wof:placetype":"locality"
},
  "geometry": {"coordinates":[65.26923000000001,29.1324],"type":"Point"}
}