{
  "type": "Feature",
  "properties": {
    "gn:admin1_code":"4.0",
    "gn:asciiname":"Lanath",
    "gn:country_code":"PK",
    "gn:dem":1232,
    "gn:feature_class":"P",
    "gn:feature_code":"PPL",
    "gn:name":"Lanath",
    "gn:population":0,
    "gn:timezone":"Asia/Karachi",
    "iso:country":"PK",
    "name:eng_x_preferred":[
        "Lah\u0101th"
    ],
    "wof:name":"Lanath",
    "wof:placetype":"locality"
},
  "geometry": {"coordinates":[73.32228000000001,33.86225],"type":"Point"}
}