{
  "type": "Feature",
  "properties": {
    "gn:admin1_code":"5",
    "gn:asciiname":"Goth Chibbhar Jat",
    "gn:country_code":"PK",
    "gn:dem":15,
    "gn:feature_class":"P",
    "gn:feature_code":"PPL",
    "gn:name":"Goth Chibbhar Jat",
    "gn:population":0,
    "gn:timezone":"Asia/Karachi",
    "iso:country":"PK",
    "wof:name":"Goth Chibbhar Jat",
    "wof:placetype":"locality"
},
  "geometry": {"coordinates":[68.94167,25.13611],"type":"Point"}
}