{
  "type": "Feature",
  "properties": {
    "gn:admin1_code":"4.0",
    "gn:asciiname":"Kangal",
    "gn:country_code":"PK",
    "gn:dem":261,
    "gn:feature_class":"P",
    "gn:feature_code":"PPL",
    "gn:name":"Kangal",
    "gn:population":0,
    "gn:timezone":"Asia/Karachi",
    "iso:country":"PK",
    "name:ceb_x_preferred":[
        "Kangal"
    ],
    "name:deu_x_preferred":[
        "Kangal"
    ],
    "name:diq_x_preferred":[
        "Qan\u011fal"
    ],
    "name:fas_x_preferred":[
        "\u06a9\u0646\u06af\u0644"
    ],
    "name:fra_x_preferred":[
        "Kangal"
    ],
    "name:ita_x_preferred":[
        "Kangal"
    ],
    "name:kur_x_preferred":[
        "Qenxal"
    ],
    "name:mrj_x_preferred":[
        "\u041a\u0430\u043d\u0433\u0430\u043b"
    ],
    "name:msa_x_preferred":[
        "Kangal"
    ],
    "name:nld_x_preferred":[
        "Kangal"
    ],
    "name:nno_x_preferred":[
        "Kangal"
    ],
    "name:nor_x_preferred":[
        "Kangal"
    ],
    "name:pnb_x_preferred":[
        "\u0636\u0644\u0639 \u06a9\u0646\u06af\u0627\u0644"
    ],
    "name:swa_x_preferred":[
        "Kangal"
    ],
    "name:tur_x_preferred":[
        "Kangal"
    ],
    "name:und_x_variant":[
        "Gangal"
    ],
    "name:vie_x_preferred":[
        "Kangal"
    ],
    "name:zho_x_preferred":[
        "\u574e\u52a0\u723e"
    ],
    "wof:name":"Kangal",
    "wof:placetype":"locality"
},
  "geometry": {"coordinates":[74.7402,32.4657],"type":"Point"}
}