{
  "type": "Feature",
  "properties": {
    "gn:admin1_code":"4.0",
    "gn:asciiname":"Kangal",
    "gn:country_code":"PK",
    "gn:dem":261,
    "gn:feature_class":"P",
    "gn:feature_code":"PPL",
    "gn:name":"Kangal",
    "gn:population":0,
    "gn:timezone":"Asia/Karachi",
    "iso:country":"PK",
    "name:und_x_variant":[
        "Gangal"
    ],
    "wof:name":"Kangal",
    "wof:placetype":"locality"
},
  "geometry": {"coordinates":[74.7402,32.4657],"type":"Point"}
}