{
  "type": "Feature",
  "properties": {
    "gn:admin1_code":"02",
    "gn:asciiname":"Sherghali",
    "gn:country_code":"PK",
    "gn:dem":2030,
    "gn:feature_class":"P",
    "gn:feature_code":"PPL",
    "gn:name":"Sherghali",
    "gn:population":0,
    "gn:timezone":"Asia/Karachi",
    "iso:country":"PK",
    "name:eng_x_preferred":[
        "Shahrgali"
    ],
    "name:und_x_variant":[
        "Sharghali",
        "Sherghali"
    ],
    "wof:name":"Sherghali",
    "wof:placetype":"locality"
},
  "geometry": {"coordinates":[67.32174000000001,30.87137],"type":"Point"}
}