{
  "type": "Feature",
  "properties": {
    "gn:admin1_code":"5",
    "gn:asciiname":"Wali Jo Miani",
    "gn:country_code":"PK",
    "gn:dem":39,
    "gn:feature_class":"P",
    "gn:feature_code":"PPL",
    "gn:name":"Wali Jo Miani",
    "gn:population":0,
    "gn:timezone":"Asia/Karachi",
    "iso:country":"PK",
    "name:und_x_variant":[
        "Wali ji Mi\u0101ni"
    ],
    "wof:name":"Wali Jo Miani",
    "wof:placetype":"locality"
},
  "geometry": {"coordinates":[67.70310000000001,26.71953],"type":"Point"}
}