{
  "type": "Feature",
  "properties": {
    "gn:admin1_code":"3",
    "gn:asciiname":"Siral",
    "gn:country_code":"PK",
    "gn:dem":1711,
    "gn:feature_class":"P",
    "gn:feature_code":"PPL",
    "gn:name":"Siral",
    "gn:population":0,
    "gn:timezone":"Asia/Karachi",
    "iso:country":"PK",
    "name:und_x_variant":[
        "Seral"
    ],
    "wof:name":"Siral",
    "wof:placetype":"locality"
},
  "geometry": {"coordinates":[73.05972,34.71684],"type":"Point"}
}