{
  "type": "Feature",
  "properties": {
    "gn:admin1_code":"5",
    "gn:asciiname":"Goth Angri",
    "gn:country_code":"PK",
    "gn:dem":39,
    "gn:feature_class":"P",
    "gn:feature_code":"PPL",
    "gn:name":"Goth Angri",
    "gn:population":0,
    "gn:timezone":"Asia/Karachi",
    "iso:country":"PK",
    "name:und_x_variant":[
        "Angri",
        "Goth Angri"
    ],
    "wof:name":"Goth Angri",
    "wof:placetype":"locality"
},
  "geometry": {"coordinates":[68.02749,26.53458],"type":"Point"}
}