{
  "type": "Feature",
  "properties": {
    "gn:admin1_code":"03",
    "gn:asciiname":"Wasm",
    "gn:country_code":"PK",
    "gn:dem":2707,
    "gn:feature_class":"P",
    "gn:feature_code":"PPL",
    "gn:name":"Wasm",
    "gn:population":0,
    "gn:timezone":"Asia/Karachi",
    "iso:country":"PK",
    "name:und_x_variant":[
        "Wasam",
        "Wasm"
    ],
    "name:urd_x_preferred":[
        "W\u0101sam"
    ],
    "name:urd_x_variant":[
        "\u0648\u064e\u0627\u0633\u064e\u0645"
    ],
    "wof:name":"Wasm",
    "wof:placetype":"locality"
},
  "geometry": {"coordinates":[72.88491999999999,36.5862],"type":"Point"}
}