{
  "type": "Feature",
  "properties": {
    "gn:admin1_code":"4.0",
    "gn:asciiname":"Bhaini Qutab Din Kheral",
    "gn:country_code":"PK",
    "gn:dem":168,
    "gn:feature_class":"P",
    "gn:feature_code":"PPL",
    "gn:name":"Bhaini Qutab Din Kheral",
    "gn:population":0,
    "gn:timezone":"Asia/Karachi",
    "iso:country":"PK",
    "wof:name":"Bhaini Qutab Din Kheral",
    "wof:placetype":"locality"
},
  "geometry": {"coordinates":[73.69126999999997,30.20461],"type":"Point"}
}