{
  "type": "Feature",
  "properties": {
    "gn:admin1_code":"3",
    "gn:asciiname":"Qadra",
    "gn:country_code":"PK",
    "gn:dem":605,
    "gn:feature_class":"P",
    "gn:feature_code":"PPL",
    "gn:name":"Qadra",
    "gn:population":0,
    "gn:timezone":"Asia/Karachi",
    "iso:country":"PK",
    "wof:name":"Qadra",
    "wof:placetype":"locality"
},
  "geometry": {"coordinates":[72.57183000000001,34.21641],"type":"Point"}
}