{
  "type": "Feature",
  "properties": {
    "gn:admin1_code":"2.0",
    "gn:asciiname":"Kaiba",
    "gn:country_code":"PK",
    "gn:dem":1597,
    "gn:feature_class":"P",
    "gn:feature_code":"PPL",
    "gn:name":"Kaiba",
    "gn:population":0,
    "gn:timezone":"Asia/Karachi",
    "iso:country":"PK",
    "name:deu_x_preferred":[
        "Kaiba"
    ],
    "name:eng_x_preferred":[
        "Katha"
    ],
    "name:eng_x_variant":[
        "Kaiha"
    ],
    "name:fas_x_preferred":[
        "\u06a9\u0627\u06cc\u0628\u0627"
    ],
    "name:fra_x_preferred":[
        "Kaiba"
    ],
    "name:ita_x_preferred":[
        "Kaiba"
    ],
    "name:jpn_x_preferred":[
        "\u30ab\u30a4\u30d0"
    ],
    "name:rus_x_preferred":[
        "Kaiba"
    ],
    "name:spa_x_preferred":[
        "Kaiba"
    ],
    "name:ukr_x_preferred":[
        "Kaiba"
    ],
    "name:und_x_variant":[
        "Kaiha",
        "Kaiba"
    ],
    "name:zho_x_preferred":[
        "\u6d77\u99ac"
    ],
    "wof:name":"Kaiba",
    "wof:placetype":"locality"
},
  "geometry": {"coordinates":[69.86043000000001,31.55463],"type":"Point"}
}