{
  "type": "Feature",
  "properties": {
    "gn:admin1_code":"4",
    "gn:asciiname":"Muhammadwala",
    "gn:country_code":"PK",
    "gn:dem":122,
    "gn:feature_class":"P",
    "gn:feature_code":"PPL",
    "gn:name":"Muhammadwala",
    "gn:population":0,
    "gn:timezone":"Asia/Karachi",
    "iso:country":"PK",
    "name:und_x_variant":[
        "Mahm\u016bdw\u0101la"
    ],
    "wof:name":"Muhammadwala",
    "wof:placetype":"locality"
},
  "geometry": {"coordinates":[70.99825,29.98523],"type":"Point"}
}