{
  "type": "Feature",
  "properties": {
    "gn:admin1_code":"5",
    "gn:asciiname":"Goth Lakho Rahu",
    "gn:country_code":"PK",
    "gn:dem":26,
    "gn:feature_class":"P",
    "gn:feature_code":"PPL",
    "gn:name":"Goth Lakho Rahu",
    "gn:population":0,
    "gn:timezone":"Asia/Karachi",
    "iso:country":"PK",
    "name:eng_x_preferred":[
        "Lakh R\u0101hu"
    ],
    "wof:name":"Goth Lakho Rahu",
    "wof:placetype":"locality"
},
  "geometry": {"coordinates":[68.44814000000001,25.7696],"type":"Point"}
}