{
  "type": "Feature",
  "properties": {
    "gn:admin1_code":"2.0",
    "gn:asciiname":"Madrosah Imam Abu Hanijah",
    "gn:country_code":"PK",
    "gn:dem":1538,
    "gn:feature_class":"P",
    "gn:feature_code":"PPL",
    "gn:name":"Madrosah Imam Abu Hanijah",
    "gn:population":0,
    "gn:timezone":"Asia/Karachi",
    "iso:country":"PK",
    "wof:name":"Madrosah Imam Abu Hanijah",
    "wof:placetype":"locality"
},
  "geometry": {"coordinates":[66.97583,30.55359],"type":"Point"}
}