{
  "type": "Feature",
  "properties": {
    "gn:admin1_code":"4.0",
    "gn:asciiname":"Pirwala",
    "gn:country_code":"PK",
    "gn:dem":124,
    "gn:feature_class":"P",
    "gn:feature_code":"PPL",
    "gn:name":"Pirwala",
    "gn:population":0,
    "gn:timezone":"Asia/Karachi",
    "iso:country":"PK",
    "wof:name":"Pirwala",
    "wof:placetype":"locality"
},
  "geometry": {"coordinates":[71.61474,30.32681],"type":"Point"}
}