{
  "type": "Feature",
  "properties": {
    "gn:admin1_code":"4.0",
    "gn:asciiname":"Bareka Khu",
    "gn:country_code":"PK",
    "gn:dem":177,
    "gn:feature_class":"P",
    "gn:feature_code":"PPL",
    "gn:name":"Bareka Khu",
    "gn:population":0,
    "gn:timezone":"Asia/Karachi",
    "iso:country":"PK",
    "name:und_x_variant":[
        "Kattianw\u0101la"
    ],
    "wof:name":"Bareka Khu",
    "wof:placetype":"locality"
},
  "geometry": {"coordinates":[73.94467,30.22115],"type":"Point"}
}