{
  "type": "Feature",
  "properties": {
    "gn:admin1_code":"3.0",
    "gn:asciiname":"Gashu Banal",
    "gn:country_code":"PK",
    "gn:dem":3054,
    "gn:feature_class":"P",
    "gn:feature_code":"PPL",
    "gn:name":"Gashu Banal",
    "gn:population":0,
    "gn:timezone":"Asia/Karachi",
    "iso:country":"PK",
    "wof:name":"Gashu Banal",
    "wof:placetype":"locality"
},
  "geometry": {"coordinates":[72.66001,35.71308],"type":"Point"}
}