{
  "type": "Feature",
  "properties": {
    "gn:admin1_code":"1.0",
    "gn:asciiname":"Nari",
    "gn:country_code":"PK",
    "gn:dem":2421,
    "gn:feature_class":"P",
    "gn:feature_code":"PPL",
    "gn:name":"Nari",
    "gn:population":0,
    "gn:timezone":"Asia/Karachi",
    "iso:country":"PK",
    "wof:name":"Nari",
    "wof:placetype":"locality"
},
  "geometry": {"coordinates":[69.97400999999999,33.97275],"type":"Point"}
}