{
  "type": "Feature",
  "properties": {
    "gn:admin1_code":"4.0",
    "gn:asciiname":"Chak Fifteen",
    "gn:country_code":"PK",
    "gn:dem":201,
    "gn:feature_class":"P",
    "gn:feature_code":"PPL",
    "gn:name":"Chak Fifteen",
    "gn:population":0,
    "gn:timezone":"Asia/Karachi",
    "iso:country":"PK",
    "name:und_x_variant":[
        "Rakh Dobli"
    ],
    "wof:name":"Chak Fifteen",
    "wof:placetype":"locality"
},
  "geometry": {"coordinates":[74.08816999999998,31.09222],"type":"Point"}
}