{
  "type": "Feature",
  "properties": {
    "gn:admin1_code":"3.0",
    "gn:asciiname":"Kharkai",
    "gn:country_code":"PK",
    "gn:dem":670,
    "gn:feature_class":"P",
    "gn:feature_code":"PPL",
    "gn:name":"Kharkai",
    "gn:population":0,
    "gn:timezone":"Asia/Karachi",
    "iso:country":"PK",
    "name:eng_x_preferred":[
        "Kharkay"
    ],
    "name:fas_x_preferred":[
        "\u062e\u0627\u0631\u06a9\u06cc\u06cc"
    ],
    "name:urd_x_preferred":[
        "\u062e\u0627\u0631\u06a9\u0626\u06cc"
    ],
    "wof:name":"Kharkai",
    "wof:placetype":"locality"
},
  "geometry": {"coordinates":[71.80419999999999,34.58225],"type":"Point"}
}