{
  "type": "Feature",
  "properties": {
    "gn:admin1_code":"4",
    "gn:asciiname":"Chatt",
    "gn:country_code":"PK",
    "gn:dem":247,
    "gn:feature_class":"P",
    "gn:feature_code":"PPL",
    "gn:name":"Chatt",
    "gn:population":0,
    "gn:timezone":"Asia/Karachi",
    "iso:country":"PK",
    "name:und_x_variant":[
        "Chatta"
    ],
    "wof:name":"Chatt",
    "wof:placetype":"locality"
},
  "geometry": {"coordinates":[73.90918000000001,32.70439],"type":"Point"}
}