{
  "type": "Feature",
  "properties": {
    "gn:admin1_code":"1.0",
    "gn:asciiname":"Haidar Ali Kalle",
    "gn:country_code":"PK",
    "gn:dem":1403,
    "gn:feature_class":"P",
    "gn:feature_code":"PPL",
    "gn:name":"Haidar Ali Kalle",
    "gn:population":0,
    "gn:timezone":"Asia/Karachi",
    "iso:country":"PK",
    "name:und_x_variant":[
        "Haider Ali Kali",
        "Haidar Ali Kili",
        "Haidar Ali Kalle",
        "Haider Ali Kila"
    ],
    "wof:name":"Haidar Ali Kalle",
    "wof:placetype":"locality"
},
  "geometry": {"coordinates":[70.18594,33.81142],"type":"Point"}
}