{
  "type": "Feature",
  "properties": {
    "gn:admin1_code":"4.0",
    "gn:asciiname":"Race Course Town",
    "gn:country_code":"PK",
    "gn:dem":210,
    "gn:feature_class":"P",
    "gn:feature_code":"PPL",
    "gn:name":"Race Course Town",
    "gn:population":0,
    "gn:timezone":"Asia/Karachi",
    "iso:country":"PK",
    "name:eng_x_preferred":[
        "Race Course Town"
    ],
    "wof:name":"Race Course Town",
    "wof:placetype":"locality"
},
  "geometry": {"coordinates":[74.33800000000002,31.4226],"type":"Point"}
}