{
  "type": "Feature",
  "properties": {
    "gn:admin1_code":"4.0",
    "gn:asciiname":"Chak Five Hundred Ten",
    "gn:country_code":"PK",
    "gn:dem":164,
    "gn:feature_class":"P",
    "gn:feature_code":"PPL",
    "gn:name":"Chak Five Hundred Ten",
    "gn:population":0,
    "gn:timezone":"Asia/Karachi",
    "iso:country":"PK",
    "name:und_x_variant":[
        "Jhok Kur\u0101i"
    ],
    "wof:name":"Chak Five Hundred Ten",
    "wof:placetype":"locality"
},
  "geometry": {"coordinates":[72.77394,30.81302],"type":"Point"}
}