{
  "type": "Feature",
  "properties": {
    "gn:admin1_code":"5",
    "gn:asciiname":"Choro Khan Rind",
    "gn:country_code":"PK",
    "gn:dem":29,
    "gn:feature_class":"P",
    "gn:feature_code":"PPL",
    "gn:name":"Choro Khan Rind",
    "gn:population":0,
    "gn:timezone":"Asia/Karachi",
    "iso:country":"PK",
    "name:und_x_variant":[
        "Jora Kh\u0101n"
    ],
    "wof:name":"Choro Khan Rind",
    "wof:placetype":"locality"
},
  "geometry": {"coordinates":[68.66345,26.31376],"type":"Point"}
}