{
  "type": "Feature",
  "properties": {
    "gn:admin1_code":"2.0",
    "gn:asciiname":"Buzurg Gaz",
    "gn:country_code":"PK",
    "gn:dem":935,
    "gn:feature_class":"P",
    "gn:feature_code":"PPL",
    "gn:name":"Buzurg Gaz",
    "gn:population":0,
    "gn:timezone":"Asia/Karachi",
    "iso:country":"PK",
    "wof:name":"Buzurg Gaz",
    "wof:placetype":"locality"
},
  "geometry": {"coordinates":[63.66667,27.15],"type":"Point"}
}