{
  "type": "Feature",
  "properties": {
    "gn:admin1_code":"3.0",
    "gn:asciiname":"Shagi Michan Khel",
    "gn:country_code":"PK",
    "gn:dem":314,
    "gn:feature_class":"P",
    "gn:feature_code":"PPL",
    "gn:name":"Shagi Michan Khel",
    "gn:population":0,
    "gn:timezone":"Asia/Karachi",
    "iso:country":"PK",
    "name:und_x_variant":[
        "Sulaim\u0101n Michan Khel",
        "Shagi Michan Khel"
    ],
    "wof:name":"Shagi Michan Khel",
    "wof:placetype":"locality"
},
  "geometry": {"coordinates":[70.72931,32.92504],"type":"Point"}
}