{
  "type": "Feature",
  "properties": {
    "gn:admin1_code":"2",
    "gn:asciiname":"Luhma Zerin",
    "gn:country_code":"PK",
    "gn:dem":1029,
    "gn:feature_class":"P",
    "gn:feature_code":"PPL",
    "gn:name":"Luhma Zerin",
    "gn:population":0,
    "gn:timezone":"Asia/Karachi",
    "iso:country":"PK",
    "wof:name":"Luhma Zerin",
    "wof:placetype":"locality"
},
  "geometry": {"coordinates":[69.49853,29.81336],"type":"Point"}
}