{
  "type": "Feature",
  "properties": {
    "gn:admin1_code":"01",
    "gn:asciiname":"Nundem",
    "gn:country_code":"PK",
    "gn:dem":1459,
    "gn:feature_class":"P",
    "gn:feature_code":"PPL",
    "gn:name":"Nundem",
    "gn:population":0,
    "gn:timezone":"Asia/Karachi",
    "iso:country":"PK",
    "name:und_x_variant":[
        "Kund\u012bm"
    ],
    "wof:name":"Nundem",
    "wof:placetype":"locality"
},
  "geometry": {"coordinates":[69.57764,32.88293],"type":"Point"}
}