{
  "type": "Feature",
  "properties": {
    "gn:admin1_code":"4",
    "gn:asciiname":"Basti Lar",
    "gn:country_code":"PK",
    "gn:dem":86,
    "gn:feature_class":"P",
    "gn:feature_code":"PPL",
    "gn:name":"Basti L\u0101r",
    "gn:population":0,
    "gn:timezone":"Asia/Karachi",
    "iso:country":"PK",
    "wof:name":"Basti Lar",
    "wof:placetype":"locality"
},
  "geometry": {"coordinates":[70.60833000000002,28.55694],"type":"Point"}
}