{
  "type": "Feature",
  "properties": {
    "gn:admin1_code":"2.0",
    "gn:asciiname":"Baghsani Kili",
    "gn:country_code":"PK",
    "gn:dem":1878,
    "gn:feature_class":"P",
    "gn:feature_code":"PPL",
    "gn:name":"Baghsani Kili",
    "gn:population":0,
    "gn:timezone":"Asia/Karachi",
    "iso:country":"PK",
    "wof:name":"Baghsani Kili",
    "wof:placetype":"locality"
},
  "geometry": {"coordinates":[69.20549,31.70135],"type":"Point"}
}