{
  "type": "Feature",
  "properties": {
    "gn:admin1_code":"4",
    "gn:asciiname":"Jan Muhammadwali",
    "gn:country_code":"PK",
    "gn:dem":124,
    "gn:feature_class":"P",
    "gn:feature_code":"PPL",
    "gn:name":"Jan Muhammadwali",
    "gn:population":0,
    "gn:timezone":"Asia/Karachi",
    "iso:country":"PK",
    "name:eng_x_preferred":[
        "J\u0101n Muhammadw\u0101la"
    ],
    "wof:name":"Jan Muhammadwali",
    "wof:placetype":"locality"
},
  "geometry": {"coordinates":[71.89269,29.44169],"type":"Point"}
}