{
  "type": "Feature",
  "properties": {
    "gn:admin1_code":"2.0",
    "gn:asciiname":"Zardalu",
    "gn:country_code":"PK",
    "gn:dem":1383,
    "gn:feature_class":"P",
    "gn:feature_code":"PPL",
    "gn:name":"Zardalu",
    "gn:population":0,
    "gn:timezone":"Asia/Karachi",
    "iso:country":"PK",
    "name:ceb_x_preferred":[
        "Zardalu"
    ],
    "name:swe_x_preferred":[
        "Zardalu"
    ],
    "wof:name":"Zardalu",
    "wof:placetype":"locality"
},
  "geometry": {"coordinates":[67.5284,30.27842],"type":"Point"}
}