{
  "type": "Feature",
  "properties": {
    "gn:admin1_code":"1.0",
    "gn:asciiname":"Ghulam Haidar Kalle",
    "gn:country_code":"PK",
    "gn:dem":1268,
    "gn:feature_class":"P",
    "gn:feature_code":"PPL",
    "gn:name":"Ghulam Haidar Kalle",
    "gn:population":0,
    "gn:timezone":"Asia/Karachi",
    "iso:country":"PK",
    "name:und_x_variant":[
        "Ghulam Haider Kali",
        "Ghul\u0101m Haidar Kili",
        "Ghulam Haidar Kalle",
        "Ghulam Haidar Kila"
    ],
    "wof:name":"Ghulam Haidar Kalle",
    "wof:placetype":"locality"
},
  "geometry": {"coordinates":[70.24786999999999,33.76124],"type":"Point"}
}