{
  "type": "Feature",
  "properties": {
    "gn:admin1_code":"01",
    "gn:asciiname":"Khandak",
    "gn:country_code":"PK",
    "gn:dem":744,
    "gn:feature_class":"P",
    "gn:feature_code":"PPL",
    "gn:name":"Khandak",
    "gn:population":0,
    "gn:timezone":"Asia/Karachi",
    "iso:country":"PK",
    "wof:name":"Khandak",
    "wof:placetype":"locality"
},
  "geometry": {"coordinates":[71.32117,34.58996],"type":"Point"}
}