{
  "type": "Feature",
  "properties": {
    "gn:admin1_code":"7.0",
    "gn:asciiname":"Gamosh",
    "gn:country_code":"PK",
    "gn:dem":2751,
    "gn:feature_class":"P",
    "gn:feature_code":"PPL",
    "gn:name":"Gamosh",
    "gn:population":0,
    "gn:timezone":"Asia/Karachi",
    "iso:country":"PK",
    "wof:name":"Gamosh",
    "wof:placetype":"locality"
},
  "geometry": {"coordinates":[75.6133,35.19376],"type":"Point"}
}