{
  "type": "Feature",
  "properties": {
    "gn:admin1_code":"3",
    "gn:asciiname":"Dangram",
    "gn:country_code":"PK",
    "gn:dem":1037,
    "gn:feature_class":"P",
    "gn:feature_code":"PPL",
    "gn:name":"Dangram",
    "gn:population":0,
    "gn:timezone":"Asia/Karachi",
    "iso:country":"PK",
    "name:fas_x_preferred":[
        "\u062f\u0646\u06af\u0631\u0627\u0645"
    ],
    "name:urd_x_preferred":[
        "\u062f\u0646\u06af\u0631\u0627\u0645"
    ],
    "wof:name":"Dangram",
    "wof:placetype":"locality"
},
  "geometry": {"coordinates":[72.40644,34.75537],"type":"Point"}
}