{
  "type": "Feature",
  "properties": {
    "gn:admin1_code":"3.0",
    "gn:asciiname":"Bain",
    "gn:country_code":"PK",
    "gn:dem":311,
    "gn:feature_class":"P",
    "gn:feature_code":"PPL",
    "gn:name":"Bain",
    "gn:population":0,
    "gn:timezone":"Asia/Karachi",
    "iso:country":"PK",
    "name:bre_x_preferred":[
        "Bain"
    ],
    "name:ceb_x_preferred":[
        "Bain"
    ],
    "name:ces_x_preferred":[
        "Bain"
    ],
    "name:deu_x_preferred":[
        "Bain"
    ],
    "name:fra_x_preferred":[
        "Bain"
    ],
    "name:heb_x_preferred":[
        "\u05d1\u05d9\u05d9\u05df"
    ],
    "name:ita_x_preferred":[
        "Bain"
    ],
    "name:nld_x_preferred":[
        "Bain"
    ],
    "name:pol_x_preferred":[
        "Bain"
    ],
    "name:rus_x_preferred":[
        "\u0411\u0435\u0439\u043d"
    ],
    "name:spa_x_preferred":[
        "Bain"
    ],
    "name:swe_x_preferred":[
        "Bain"
    ],
    "name:ukr_x_preferred":[
        "\u0411\u0435\u0439\u043d"
    ],
    "wof:name":"Bain",
    "wof:placetype":"locality"
},
  "geometry": {"coordinates":[70.55916999999999,32.45905],"type":"Point"}
}