{
  "type": "Feature",
  "properties": {
    "gn:admin1_code":"3.0",
    "gn:asciiname":"Bain",
    "gn:country_code":"PK",
    "gn:dem":311,
    "gn:feature_class":"P",
    "gn:feature_code":"PPL",
    "gn:name":"Bain",
    "gn:population":0,
    "gn:timezone":"Asia/Karachi",
    "iso:country":"PK",
    "wof:name":"Bain",
    "wof:placetype":"locality"
},
  "geometry": {"coordinates":[70.55916999999999,32.45905],"type":"Point"}
}