{
  "type": "Feature",
  "properties": {
    "gn:admin1_code":"5",
    "gn:asciiname":"Sumar Chaneh",
    "gn:country_code":"PK",
    "gn:dem":12,
    "gn:feature_class":"P",
    "gn:feature_code":"PPL",
    "gn:name":"Sumar Chaneh",
    "gn:population":0,
    "gn:timezone":"Asia/Karachi",
    "iso:country":"PK",
    "wof:name":"Sumar Chaneh",
    "wof:placetype":"locality"
},
  "geometry": {"coordinates":[69.40694000000001,25.75417],"type":"Point"}
}