{
  "type": "Feature",
  "properties": {
    "gn:admin1_code":"4.0",
    "gn:asciiname":"Dhana",
    "gn:country_code":"PK",
    "gn:dem":202,
    "gn:feature_class":"P",
    "gn:feature_code":"PPL",
    "gn:name":"Dhana",
    "gn:population":0,
    "gn:timezone":"Asia/Karachi",
    "iso:country":"PK",
    "name:ben_x_preferred":[
        "\u09a7\u09be\u09a8\u09be"
    ],
    "name:bpy_x_preferred":[
        "\u09a7\u09be\u09a8\u09be"
    ],
    "name:ceb_x_preferred":[
        "Dh\u0101na"
    ],
    "name:ita_x_preferred":[
        "Dhana"
    ],
    "name:msa_x_preferred":[
        "Dhana"
    ],
    "name:new_x_preferred":[
        "\u0927\u093e\u0928\u093e"
    ],
    "name:nld_x_preferred":[
        "Dhana"
    ],
    "name:por_x_preferred":[
        "Dhana"
    ],
    "name:spa_x_preferred":[
        "Dhana"
    ],
    "name:swe_x_preferred":[
        "Dh\u0101na"
    ],
    "name:vie_x_preferred":[
        "Dhana"
    ],
    "wof:name":"Dhana",
    "wof:placetype":"locality"
},
  "geometry": {"coordinates":[74.14203000000001,31.45633],"type":"Point"}
}