{
  "type": "Feature",
  "properties": {
    "gn:admin1_code":"6.0",
    "gn:asciiname":"Bazzar Kot",
    "gn:country_code":"PK",
    "gn:dem":1180,
    "gn:feature_class":"P",
    "gn:feature_code":"PPL",
    "gn:name":"Bazzar Kot",
    "gn:population":0,
    "gn:timezone":"Asia/Karachi",
    "iso:country":"PK",
    "wof:name":"Bazzar Kot",
    "wof:placetype":"locality"
},
  "geometry": {"coordinates":[73.56950999999999,33.97951],"type":"Point"}
}