{
  "type": "Feature",
  "properties": {
    "gn:admin1_code":"4.0",
    "gn:asciiname":"Kasran",
    "gn:country_code":"PK",
    "gn:dem":305,
    "gn:feature_class":"P",
    "gn:feature_code":"PPL",
    "gn:name":"Kasran",
    "gn:population":0,
    "gn:timezone":"Asia/Karachi",
    "iso:country":"PK",
    "name:azb_x_preferred":[
        "\u06a9\u0633\u0631\u0627\u0646"
    ],
    "name:ceb_x_preferred":[
        "Kasr\u0101n"
    ],
    "name:fas_x_preferred":[
        "\u06a9\u0633\u0631\u0627\u0646"
    ],
    "name:swe_x_preferred":[
        "Kasr\u0101n"
    ],
    "wof:name":"Kasran",
    "wof:placetype":"locality"
},
  "geometry": {"coordinates":[72.39790000000001,33.88439],"type":"Point"}
}