{
  "type": "Feature",
  "properties": {
    "gn:admin1_code":"5.0",
    "gn:asciiname":"Siddiq Mandhro",
    "gn:country_code":"PK",
    "gn:dem":2,
    "gn:feature_class":"P",
    "gn:feature_code":"PPL",
    "gn:name":"Siddiq Mandhro",
    "gn:population":0,
    "gn:timezone":"Asia/Karachi",
    "iso:country":"PK",
    "wof:name":"Siddiq Mandhro",
    "wof:placetype":"locality"
},
  "geometry": {"coordinates":[68.79163,24.33708],"type":"Point"}
}