{
  "type": "Feature",
  "properties": {
    "gn:admin1_code":"04",
    "gn:asciiname":"Radhan",
    "gn:country_code":"PK",
    "gn:dem":178,
    "gn:feature_class":"P",
    "gn:feature_code":"PPL",
    "gn:name":"Radhan",
    "gn:population":0,
    "gn:timezone":"Asia/Karachi",
    "iso:country":"PK",
    "wof:name":"Radhan",
    "wof:placetype":"locality"
},
  "geometry": {"coordinates":[72.43276999999998,32.02408],"type":"Point"}
}