{
  "type": "Feature",
  "properties": {
    "gn:admin1_code":"03",
    "gn:asciiname":"Daryab Kalle",
    "gn:country_code":"PK",
    "gn:dem":365,
    "gn:feature_class":"P",
    "gn:feature_code":"PPL",
    "gn:name":"Daryab Kalle",
    "gn:population":0,
    "gn:timezone":"Asia/Karachi",
    "iso:country":"PK",
    "name:eng_x_preferred":[
        "Dary\u0101b Kalle"
    ],
    "name:und_x_variant":[
        "Daryat Kor\u016bna",
        "Daryab Kalle",
        "Daryab Korona"
    ],
    "wof:name":"Daryab Kalle",
    "wof:placetype":"locality"
},
  "geometry": {"coordinates":[71.54755,34.26238],"type":"Point"}
}