{
  "type": "Feature",
  "properties": {
    "gn:admin1_code":"4.0",
    "gn:asciiname":"Qila Sardar Jawahar Singh",
    "gn:country_code":"PK",
    "gn:dem":201,
    "gn:feature_class":"P",
    "gn:feature_code":"PPL",
    "gn:name":"Qila Sardar Jawahar Singh",
    "gn:population":0,
    "gn:timezone":"Asia/Karachi",
    "iso:country":"PK",
    "name:und_x_variant":[
        "Kalas\u0101nw\u0101la"
    ],
    "wof:name":"Qila Sardar Jawahar Singh",
    "wof:placetype":"locality"
},
  "geometry": {"coordinates":[73.41327,32.18228],"type":"Point"}
}