{
  "type": "Feature",
  "properties": {
    "gn:admin1_code":"04",
    "gn:asciiname":"Prewar",
    "gn:country_code":"PK",
    "gn:dem":90,
    "gn:feature_class":"P",
    "gn:feature_code":"PPL",
    "gn:name":"Prewar",
    "gn:population":0,
    "gn:timezone":"Asia/Karachi",
    "iso:country":"PK",
    "name:und_x_variant":[
        "Parewar",
        "Parehwar"
    ],
    "wof:name":"Prewar",
    "wof:placetype":"locality"
},
  "geometry": {"coordinates":[70.17697,28.77217000000001],"type":"Point"}
}