{
  "type": "Feature",
  "properties": {
    "gn:admin1_code":"5",
    "gn:asciiname":"Goth Iso Mari",
    "gn:country_code":"PK",
    "gn:dem":43,
    "gn:feature_class":"P",
    "gn:feature_code":"PPL",
    "gn:name":"Goth Iso Mari",
    "gn:population":0,
    "gn:timezone":"Asia/Karachi",
    "iso:country":"PK",
    "name:und_x_variant":[
        "Khharak Singh"
    ],
    "wof:name":"Goth Iso Mari",
    "wof:placetype":"locality"
},
  "geometry": {"coordinates":[67.94201,26.77498],"type":"Point"}
}