{
  "type": "Feature",
  "properties": {
    "gn:admin1_code":"5.0",
    "gn:asciiname":"Dodapur",
    "gn:country_code":"PK",
    "gn:dem":55,
    "gn:feature_class":"P",
    "gn:feature_code":"PPL",
    "gn:name":"Dodapur",
    "gn:population":0,
    "gn:timezone":"Asia/Karachi",
    "iso:country":"PK",
    "wof:name":"Dodapur",
    "wof:placetype":"locality"
},
  "geometry": {"coordinates":[68.1705,28.05792000000001],"type":"Point"}
}