{
  "type": "Feature",
  "properties": {
    "gn:admin1_code":"01",
    "gn:asciiname":"Kharra",
    "gn:country_code":"PK",
    "gn:dem":1924,
    "gn:feature_class":"P",
    "gn:feature_code":"PPL",
    "gn:name":"Kharra",
    "gn:population":0,
    "gn:timezone":"Asia/Karachi",
    "iso:country":"PK",
    "name:und_x_variant":[
        "Khara"
    ],
    "wof:name":"Kharra",
    "wof:placetype":"locality"
},
  "geometry": {"coordinates":[69.52746999999999,32.98835],"type":"Point"}
}