{
  "type": "Feature",
  "properties": {
    "gn:admin1_code":"6.0",
    "gn:asciiname":"Bungawali Mohri",
    "gn:country_code":"PK",
    "gn:dem":2830,
    "gn:feature_class":"P",
    "gn:feature_code":"PPL",
    "gn:name":"Bungawali Mohri",
    "gn:population":0,
    "gn:timezone":"Asia/Karachi",
    "iso:country":"PK",
    "wof:name":"Bungawali Mohri",
    "wof:placetype":"locality"
},
  "geometry": {"coordinates":[73.99802,34.77328],"type":"Point"}
}