{
  "type": "Feature",
  "properties": {
    "gn:admin1_code":"2.0",
    "gn:asciiname":"Abdul Rashid Chholgri",
    "gn:country_code":"PK",
    "gn:dem":60,
    "gn:feature_class":"P",
    "gn:feature_code":"PPL",
    "gn:name":"Abdul Rashid Chholgri",
    "gn:population":0,
    "gn:timezone":"Asia/Karachi",
    "iso:country":"PK",
    "name:und_x_variant":[
        "Abdul Rash\u012bd Chhalgari"
    ],
    "wof:name":"Abdul Rashid Chholgri",
    "wof:placetype":"locality"
},
  "geometry": {"coordinates":[68.12918000000001,28.40658],"type":"Point"}
}