{
  "type": "Feature",
  "properties": {
    "gn:admin1_code":"3",
    "gn:asciiname":"Gujar Banr",
    "gn:country_code":"PK",
    "gn:dem":1691,
    "gn:feature_class":"P",
    "gn:feature_code":"PPL",
    "gn:name":"Gujar Banr",
    "gn:population":0,
    "gn:timezone":"Asia/Karachi",
    "iso:country":"PK",
    "name:eng_x_preferred":[
        "B\u016bjabanr"
    ],
    "wof:name":"Gujar Banr",
    "wof:placetype":"locality"
},
  "geometry": {"coordinates":[72.60158,35.24231],"type":"Point"}
}