{
  "type": "Feature",
  "properties": {
    "gn:admin1_code":"3.0",
    "gn:asciiname":"Shah Munir",
    "gn:country_code":"PK",
    "gn:dem":342,
    "gn:feature_class":"P",
    "gn:feature_code":"PPL",
    "gn:name":"Shah Munir",
    "gn:population":0,
    "gn:timezone":"Asia/Karachi",
    "iso:country":"PK",
    "name:eng_x_preferred":[
        "Shah Munir"
    ],
    "wof:name":"Shah Munir",
    "wof:placetype":"locality"
},
  "geometry": {"coordinates":[71.89735999999998,34.26069],"type":"Point"}
}