{
  "type": "Feature",
  "properties": {
    "gn:admin1_code":"2",
    "gn:asciiname":"Bash",
    "gn:country_code":"PK",
    "gn:dem":1690,
    "gn:feature_class":"P",
    "gn:feature_code":"PPL",
    "gn:name":"Bash",
    "gn:population":0,
    "gn:timezone":"Asia/Karachi",
    "iso:country":"PK",
    "name:ceb_x_preferred":[
        "Bash"
    ],
    "name:deu_x_preferred":[
        "Bash"
    ],
    "name:fra_x_preferred":[
        "Bash"
    ],
    "name:jpn_x_preferred":[
        "\u30d0\u30c3\u30b7\u30e5"
    ],
    "name:nds_x_preferred":[
        "Bash"
    ],
    "name:nld_x_preferred":[
        "The Bash"
    ],
    "name:por_x_preferred":[
        "Bash"
    ],
    "name:rus_x_preferred":[
        "Bash"
    ],
    "name:ukr_x_preferred":[
        "Bash"
    ],
    "name:und_x_variant":[
        "B\u0101she",
        "B\u0101che",
        "Bash"
    ],
    "wof:name":"Bash",
    "wof:placetype":"locality"
},
  "geometry": {"coordinates":[68.75876,30.52273],"type":"Point"}
}