{
  "type": "Feature",
  "properties": {
    "gn:admin1_code":"4.0",
    "gn:asciiname":"Bhedon Khan",
    "gn:country_code":"PK",
    "gn:dem":248,
    "gn:feature_class":"P",
    "gn:feature_code":"PPL",
    "gn:name":"Bhedon Khan",
    "gn:population":0,
    "gn:timezone":"Asia/Karachi",
    "iso:country":"PK",
    "wof:name":"Bhedon Khan",
    "wof:placetype":"locality"
},
  "geometry": {"coordinates":[74.8126,32.22877],"type":"Point"}
}