{
  "type": "Feature",
  "properties": {
    "gn:admin1_code":"04",
    "gn:asciiname":"Sherpur",
    "gn:country_code":"PK",
    "gn:dem":111,
    "gn:feature_class":"P",
    "gn:feature_code":"PPL",
    "gn:name":"Sherpur",
    "gn:population":0,
    "gn:timezone":"Asia/Karachi",
    "iso:country":"PK",
    "name:ceb_x_preferred":[
        "Sherpur"
    ],
    "name:nld_x_preferred":[
        "Sherpur"
    ],
    "name:rus_x_preferred":[
        "\u0428\u0435\u0440\u043f\u0443\u0440"
    ],
    "name:swe_x_preferred":[
        "Sherpur"
    ],
    "wof:name":"Sherpur",
    "wof:placetype":"locality"
},
  "geometry": {"coordinates":[71.43680000000001,29.579],"type":"Point"}
}