{
  "type": "Feature",
  "properties": {
    "gn:admin1_code":"4.0",
    "gn:asciiname":"Khu Haji Sardar Ali",
    "gn:country_code":"PK",
    "gn:dem":162,
    "gn:feature_class":"P",
    "gn:feature_code":"PPL",
    "gn:name":"Khu Haji Sardar Ali",
    "gn:population":0,
    "gn:timezone":"Asia/Karachi",
    "iso:country":"PK",
    "wof:name":"Khu Haji Sardar Ali",
    "wof:placetype":"locality"
},
  "geometry": {"coordinates":[73.4949,30.05411],"type":"Point"}
}