{
  "type": "Feature",
  "properties": {
    "gn:admin1_code":"2.0",
    "gn:asciiname":"Shadizai",
    "gn:country_code":"PK",
    "gn:dem":1161,
    "gn:feature_class":"P",
    "gn:feature_code":"PPL",
    "gn:name":"Shadizai",
    "gn:population":0,
    "gn:timezone":"Asia/Karachi",
    "iso:country":"PK",
    "name:und_x_variant":[
        "Sh\u0101di Zai"
    ],
    "wof:name":"Shadizai",
    "wof:placetype":"locality"
},
  "geometry": {"coordinates":[66.21082,27.64709],"type":"Point"}
}