{
  "type": "Feature",
  "properties": {
    "gn:admin1_code":"5",
    "gn:asciiname":"Nehal Tangar",
    "gn:country_code":"PK",
    "gn:dem":23,
    "gn:feature_class":"P",
    "gn:feature_code":"PPL",
    "gn:name":"Nehal Tangar",
    "gn:population":0,
    "gn:timezone":"Asia/Karachi",
    "iso:country":"PK",
    "name:eng_x_preferred":[
        "Nih\u0101l Tangar"
    ],
    "wof:name":"Nehal Tangar",
    "wof:placetype":"locality"
},
  "geometry": {"coordinates":[68.47530999999999,25.4489],"type":"Point"}
}