{
  "type": "Feature",
  "properties": {
    "gn:admin1_code":"6",
    "gn:asciiname":"Banni Langrial",
    "gn:country_code":"PK",
    "gn:dem":1988,
    "gn:feature_class":"P",
    "gn:feature_code":"PPL",
    "gn:name":"Banni Langrial",
    "gn:population":0,
    "gn:timezone":"Asia/Karachi",
    "iso:country":"PK",
    "name:und_x_variant":[
        "Bani Lungri\u0101l\u0101n"
    ],
    "wof:name":"Banni Langrial",
    "wof:placetype":"locality"
},
  "geometry": {"coordinates":[73.75936,34.11159],"type":"Point"}
}