{
  "type": "Feature",
  "properties": {
    "gn:admin1_code":"6",
    "gn:asciiname":"Mukhal",
    "gn:country_code":"PK",
    "gn:dem":380,
    "gn:feature_class":"P",
    "gn:feature_code":"PPL",
    "gn:name":"Mukhal",
    "gn:population":0,
    "gn:timezone":"Asia/Karachi",
    "iso:country":"PK",
    "name:und_x_variant":[
        "Makah\u0101l"
    ],
    "wof:name":"Mukhal",
    "wof:placetype":"locality"
},
  "geometry": {"coordinates":[74.07051,32.96252],"type":"Point"}
}