{
  "type": "Feature",
  "properties": {
    "gn:admin1_code":"4",
    "gn:asciiname":"Chak Number Eight",
    "gn:country_code":"PK",
    "gn:dem":97,
    "gn:feature_class":"P",
    "gn:feature_code":"PPL",
    "gn:name":"Chak Number Eight",
    "gn:population":0,
    "gn:timezone":"Asia/Karachi",
    "iso:country":"PK",
    "name:und_x_variant":[
        "Chak Eight"
    ],
    "wof:name":"Chak Number Eight",
    "wof:placetype":"locality"
},
  "geometry": {"coordinates":[71.01079,29.01675],"type":"Point"}
}