{
  "type": "Feature",
  "properties": {
    "gn:admin1_code":"3.0",
    "gn:asciiname":"Jabba Banda",
    "gn:country_code":"PK",
    "gn:dem":3138,
    "gn:feature_class":"P",
    "gn:feature_code":"PPL",
    "gn:name":"Jabba Banda",
    "gn:population":0,
    "gn:timezone":"Asia/Karachi",
    "iso:country":"PK",
    "wof:name":"Jabba Banda",
    "wof:placetype":"locality"
},
  "geometry": {"coordinates":[72.81198000000001,35.73913],"type":"Point"}
}