{
  "type": "Feature",
  "properties": {
    "gn:admin1_code":"4",
    "gn:asciiname":"Chak One Hundred Fifteen -Seven C Right",
    "gn:country_code":"PK",
    "gn:dem":160,
    "gn:feature_class":"P",
    "gn:feature_code":"PPL",
    "gn:name":"Chak One Hundred Fifteen -Seven C Right",
    "gn:population":0,
    "gn:timezone":"Asia/Karachi",
    "iso:country":"PK",
    "name:und_x_variant":[
        "Chak One Hundred Fifteen-Seven CR"
    ],
    "wof:name":"Chak One Hundred Fifteen -Seven C Right",
    "wof:placetype":"locality"
},
  "geometry": {"coordinates":[72.59405,30.56078],"type":"Point"}
}