{
  "type": "Feature",
  "properties": {
    "gn:admin1_code":"05",
    "gn:asciiname":"Rawatsar",
    "gn:country_code":"PK",
    "gn:dem":112,
    "gn:feature_class":"P",
    "gn:feature_code":"PPL",
    "gn:name":"Rawatsar",
    "gn:population":0,
    "gn:timezone":"Asia/Karachi",
    "iso:country":"PK",
    "name:ben_x_preferred":[
        "\u09b0\u09be\u0993\u09af\u09bc\u09be\u09a4\u09b8\u09b0"
    ],
    "name:bpy_x_preferred":[
        "\u09b0\u09be\u09f1\u09be\u09a4\u09b8\u09b0"
    ],
    "name:cat_x_preferred":[
        "Rawatsar"
    ],
    "name:ceb_x_preferred":[
        "R\u0101wats\u0101r"
    ],
    "name:hif_x_preferred":[
        "Rawatsar"
    ],
    "name:hin_x_preferred":[
        "\u0930\u093e\u0935\u0924\u0938\u0930"
    ],
    "name:ita_x_preferred":[
        "Rawatsar"
    ],
    "name:msa_x_preferred":[
        "Rawatsar"
    ],
    "name:ori_x_preferred":[
        "\u0b30\u0b3e\u0b71\u0b24\u0b38\u0b3e\u0b30"
    ],
    "name:por_x_preferred":[
        "Rawatsar"
    ],
    "name:swe_x_preferred":[
        "R\u0101wats\u0101r"
    ],
    "name:vie_x_preferred":[
        "Rawatsar"
    ],
    "name:zho_x_preferred":[
        "\u62c9\u74e6\u7279\u8428\u5c14"
    ],
    "wof:name":"Rawatsar",
    "wof:placetype":"locality"
},
  "geometry": {"coordinates":[70.76903,25.03959],"type":"Point"}
}