{
  "type": "Feature",
  "properties": {
    "gn:admin1_code":"4.0",
    "gn:asciiname":"Mehr Shah Khel",
    "gn:country_code":"PK",
    "gn:dem":273,
    "gn:feature_class":"P",
    "gn:feature_code":"PPL",
    "gn:name":"Mehr Shah Khel",
    "gn:population":0,
    "gn:timezone":"Asia/Karachi",
    "iso:country":"PK",
    "name:und_x_variant":[
        "Kh\u0101n Zam\u0101nw\u0101la"
    ],
    "wof:name":"Mehr Shah Khel",
    "wof:placetype":"locality"
},
  "geometry": {"coordinates":[71.75378000000001,32.61069000000001],"type":"Point"}
}