{
  "type": "Feature",
  "properties": {
    "gn:admin1_code":"1.0",
    "gn:asciiname":"Doran Kalle",
    "gn:country_code":"PK",
    "gn:dem":1116,
    "gn:feature_class":"P",
    "gn:feature_code":"PPL",
    "gn:name":"Doran Kalle",
    "gn:population":0,
    "gn:timezone":"Asia/Karachi",
    "iso:country":"PK",
    "wof:name":"Doran Kalle",
    "wof:placetype":"locality"
},
  "geometry": {"coordinates":[70.30282,33.64588],"type":"Point"}
}