{
  "type": "Feature",
  "properties": {
    "gn:admin1_code":"04",
    "gn:asciiname":"Wagal",
    "gn:country_code":"PK",
    "gn:dem":1404,
    "gn:feature_class":"P",
    "gn:feature_code":"PPL",
    "gn:name":"Wagal",
    "gn:population":0,
    "gn:timezone":"Asia/Karachi",
    "iso:country":"PK",
    "name:und_x_variant":[
        "Wahgal",
        "Waggal",
        "Wagal"
    ],
    "wof:name":"Wagal",
    "wof:placetype":"locality"
},
  "geometry": {"coordinates":[73.52074,33.88526],"type":"Point"}
}