{
  "type": "Feature",
  "properties": {
    "gn:admin1_code":"4.0",
    "gn:asciiname":"Dhok Munawar",
    "gn:country_code":"PK",
    "gn:dem":272,
    "gn:feature_class":"P",
    "gn:feature_code":"PPL",
    "gn:name":"Dhok Munawar",
    "gn:population":0,
    "gn:timezone":"Asia/Karachi",
    "iso:country":"PK",
    "name:und_x_variant":[
        "Dhok Munawwar"
    ],
    "wof:name":"Dhok Munawar",
    "wof:placetype":"locality"
},
  "geometry": {"coordinates":[73.63099,32.9666],"type":"Point"}
}