{
  "type": "Feature",
  "properties": {
    "gn:admin1_code":"5",
    "gn:asciiname":"Nia Zarkhel",
    "gn:country_code":"PK",
    "gn:dem":68,
    "gn:feature_class":"P",
    "gn:feature_code":"PPL",
    "gn:name":"Nia Zarkhel",
    "gn:population":0,
    "gn:timezone":"Asia/Karachi",
    "iso:country":"PK",
    "name:und_x_variant":[
        "Zarkhel Nawo"
    ],
    "wof:name":"Nia Zarkhel",
    "wof:placetype":"locality"
},
  "geometry": {"coordinates":[68.67803000000001,28.09453],"type":"Point"}
}