{
  "type": "Feature",
  "properties": {
    "gn:admin1_code":"5",
    "gn:asciiname":"Goth Jakhra",
    "gn:country_code":"PK",
    "gn:dem":50,
    "gn:feature_class":"P",
    "gn:feature_code":"PPL",
    "gn:name":"Goth Jakhra",
    "gn:population":0,
    "gn:timezone":"Asia/Karachi",
    "iso:country":"PK",
    "name:und_x_variant":[
        "J\u0101khra Goth",
        "Jakhra",
        "J\u0101khra Goto",
        "Goth Jakhra"
    ],
    "wof:name":"Goth Jakhra",
    "wof:placetype":"locality"
},
  "geometry": {"coordinates":[68.0658,27.28158],"type":"Point"}
}