{
  "type": "Feature",
  "properties": {
    "gn:admin1_code":"4",
    "gn:asciiname":"Chak Two Hundred Seventy-three",
    "gn:country_code":"PK",
    "gn:dem":182,
    "gn:feature_class":"P",
    "gn:feature_code":"PPL",
    "gn:name":"Chak Two Hundred Seventy-three",
    "gn:population":0,
    "gn:timezone":"Asia/Karachi",
    "iso:country":"PK",
    "name:und_x_variant":[
        "M\u0101la Gondi\u0101n",
        "Chak Five Hundred Seventy-Three",
        "Chak Two Hundred Seventy-three",
        "Mahla Gondi\u0101n"
    ],
    "wof:name":"Chak Two Hundred Seventy-three",
    "wof:placetype":"locality"
},
  "geometry": {"coordinates":[72.81390999999998,31.39511],"type":"Point"}
}