{
  "type": "Feature",
  "properties": {
    "gn:admin1_code":"5",
    "gn:asciiname":"Goth Ghazi Khan Shar",
    "gn:country_code":"PK",
    "gn:dem":50,
    "gn:feature_class":"P",
    "gn:feature_code":"PPL",
    "gn:name":"Goth Ghazi Khan Shar",
    "gn:population":0,
    "gn:timezone":"Asia/Karachi",
    "iso:country":"PK",
    "name:und_x_variant":[
        "Goth Gh\u0101zi Kh\u0101n",
        "Gh\u0101zi Kh\u0101n Jag\u012br\u0101ni",
        "Goth Ghazi Khan Shar"
    ],
    "wof:name":"Goth Ghazi Khan Shar",
    "wof:placetype":"locality"
},
  "geometry": {"coordinates":[68.20061,27.66936],"type":"Point"}
}