{
  "type": "Feature",
  "properties": {
    "gn:admin1_code":"4.0",
    "gn:asciiname":"Banth",
    "gn:country_code":"PK",
    "gn:dem":543,
    "gn:feature_class":"P",
    "gn:feature_code":"PPL",
    "gn:name":"Banth",
    "gn:population":0,
    "gn:timezone":"Asia/Karachi",
    "iso:country":"PK",
    "wof:name":"Banth",
    "wof:placetype":"locality"
},
  "geometry": {"coordinates":[73.22253000000001,33.4089],"type":"Point"}
}