{
  "type": "Feature",
  "properties": {
    "gn:admin1_code":"4",
    "gn:asciiname":"Khanra",
    "gn:country_code":"PK",
    "gn:dem":364,
    "gn:feature_class":"P",
    "gn:feature_code":"PPL",
    "gn:name":"Khanra",
    "gn:population":0,
    "gn:timezone":"Asia/Karachi",
    "iso:country":"PK",
    "wof:name":"Khanra",
    "wof:placetype":"locality"
},
  "geometry": {"coordinates":[71.87694,32.74525],"type":"Point"}
}