{
  "type": "Feature",
  "properties": {
    "gn:admin1_code":"4.0",
    "gn:asciiname":"Hastu Khelwala",
    "gn:country_code":"PK",
    "gn:dem":255,
    "gn:feature_class":"P",
    "gn:feature_code":"PPL",
    "gn:name":"Hastu Khelwala",
    "gn:population":0,
    "gn:timezone":"Asia/Karachi",
    "iso:country":"PK",
    "name:und_x_variant":[
        "Alitow\u0101la"
    ],
    "wof:name":"Hastu Khelwala",
    "wof:placetype":"locality"
},
  "geometry": {"coordinates":[71.69603000000002,32.66314000000001],"type":"Point"}
}