{
  "type": "Feature",
  "properties": {
    "gn:admin1_code":"4.0",
    "gn:asciiname":"Basti Haji Jamal Sultan",
    "gn:country_code":"PK",
    "gn:dem":80,
    "gn:feature_class":"P",
    "gn:feature_code":"PPL",
    "gn:name":"Basti Haji Jamal Sultan",
    "gn:population":0,
    "gn:timezone":"Asia/Karachi",
    "iso:country":"PK",
    "wof:name":"Basti Haji Jamal Sultan",
    "wof:placetype":"locality"
},
  "geometry": {"coordinates":[70.31379,28.33768],"type":"Point"}
}