{
  "type": "Feature",
  "properties": {
    "gn:admin1_code":"1",
    "gn:asciiname":"Manzal",
    "gn:country_code":"PK",
    "gn:dem":1966,
    "gn:feature_class":"P",
    "gn:feature_code":"PPL",
    "gn:name":"Manzal",
    "gn:population":0,
    "gn:timezone":"Asia/Karachi",
    "iso:country":"PK",
    "name:und_x_variant":[
        "Boi Khel",
        "Manzai",
        "Manzal"
    ],
    "wof:name":"Manzal",
    "wof:placetype":"locality"
},
  "geometry": {"coordinates":[69.7852,32.57109000000001],"type":"Point"}
}