{
  "type": "Feature",
  "properties": {
    "gn:admin1_code":"3.0",
    "gn:asciiname":"Kuch Ghari",
    "gn:country_code":"PK",
    "gn:dem":3290,
    "gn:feature_class":"P",
    "gn:feature_code":"PPL",
    "gn:name":"Kuch Ghari",
    "gn:population":0,
    "gn:timezone":"Asia/Karachi",
    "iso:country":"PK",
    "wof:name":"Kuch Ghari",
    "wof:placetype":"locality"
},
  "geometry": {"coordinates":[72.08110000000001,36.2439],"type":"Point"}
}