{
  "type": "Feature",
  "properties": {
    "gn:admin1_code":"4.0",
    "gn:asciiname":"Dhiyan",
    "gn:country_code":"PK",
    "gn:dem":208,
    "gn:feature_class":"P",
    "gn:feature_code":"PPL",
    "gn:name":"Dhiyan",
    "gn:population":0,
    "gn:timezone":"Asia/Karachi",
    "iso:country":"PK",
    "name:und_x_variant":[
        "Dhing\u0101n"
    ],
    "wof:name":"Dhiyan",
    "wof:placetype":"locality"
},
  "geometry": {"coordinates":[74.1258,31.60625],"type":"Point"}
}