{
  "type": "Feature",
  "properties": {
    "gn:admin1_code":"04",
    "gn:asciiname":"Chak Eighty-four -Fifteen Left",
    "gn:country_code":"PK",
    "gn:dem":137,
    "gn:feature_class":"P",
    "gn:feature_code":"PPL",
    "gn:name":"Chak Eighty-four -Fifteen Left",
    "gn:population":0,
    "gn:timezone":"Asia/Karachi",
    "iso:country":"PK",
    "name:und_x_variant":[
        "Muhammadw\u0101la"
    ],
    "wof:name":"Chak Eighty-four -Fifteen Left",
    "wof:placetype":"locality"
},
  "geometry": {"coordinates":[72.1853,30.23267],"type":"Point"}
}