{
  "type": "Feature",
  "properties": {
    "gn:admin1_code":"4.0",
    "gn:asciiname":"Chak Mauju",
    "gn:country_code":"PK",
    "gn:dem":222,
    "gn:feature_class":"P",
    "gn:feature_code":"PPL",
    "gn:name":"Chak Mauju",
    "gn:population":0,
    "gn:timezone":"Asia/Karachi",
    "iso:country":"PK",
    "name:und_x_variant":[
        "Chak Moju"
    ],
    "wof:name":"Chak Mauju",
    "wof:placetype":"locality"
},
  "geometry": {"coordinates":[73.54774,32.74241],"type":"Point"}
}