{
  "type": "Feature",
  "properties": {
    "gn:admin1_code":"02",
    "gn:asciiname":"Kangoro",
    "gn:country_code":"PK",
    "gn:dem":372,
    "gn:feature_class":"P",
    "gn:feature_code":"PPL",
    "gn:name":"Kangoro",
    "gn:population":0,
    "gn:timezone":"Asia/Karachi",
    "iso:country":"PK",
    "name:und_x_variant":[
        "Kongoro"
    ],
    "wof:name":"Kangoro",
    "wof:placetype":"locality"
},
  "geometry": {"coordinates":[67.00971,25.83642],"type":"Point"}
}