{
  "type": "Feature",
  "properties": {
    "gn:admin1_code":"5",
    "gn:asciiname":"Mir Bagan Khan Bijrani",
    "gn:country_code":"PK",
    "gn:dem":68,
    "gn:feature_class":"P",
    "gn:feature_code":"PPL",
    "gn:name":"Mir Bagan Khan Bijrani",
    "gn:population":0,
    "gn:timezone":"Asia/Karachi",
    "iso:country":"PK",
    "name:und_x_variant":[
        "H\u0101ji Abdul Ghaff\u016br"
    ],
    "wof:name":"Mir Bagan Khan Bijrani",
    "wof:placetype":"locality"
},
  "geometry": {"coordinates":[68.95894,28.10535],"type":"Point"}
}