{
  "type": "Feature",
  "properties": {
    "gn:admin1_code":"2.0",
    "gn:asciiname":"Kito",
    "gn:country_code":"PK",
    "gn:dem":685,
    "gn:feature_class":"P",
    "gn:feature_code":"PPL",
    "gn:name":"Kito",
    "gn:population":0,
    "gn:timezone":"Asia/Karachi",
    "iso:country":"PK",
    "name:ceb_x_preferred":[
        "Kito"
    ],
    "name:deu_x_preferred":[
        "Kito"
    ],
    "name:eus_x_preferred":[
        "Kito"
    ],
    "name:ita_x_preferred":[
        "Kito"
    ],
    "name:swa_x_preferred":[
        "Kito"
    ],
    "name:swe_x_preferred":[
        "Kito"
    ],
    "wof:name":"Kito",
    "wof:placetype":"locality"
},
  "geometry": {"coordinates":[65.39603000000001,28.36724],"type":"Point"}
}