{
  "type": "Feature",
  "properties": {
    "gn:admin1_code":"1.0",
    "gn:asciiname":"Subidar Ilyas Mandark Kalle",
    "gn:country_code":"PK",
    "gn:dem":1829,
    "gn:feature_class":"P",
    "gn:feature_code":"PPL",
    "gn:name":"Subidar Ilyas Mandark Kalle",
    "gn:population":0,
    "gn:timezone":"Asia/Karachi",
    "iso:country":"PK",
    "wof:name":"Subidar Ilyas Mandark Kalle",
    "wof:placetype":"locality"
},
  "geometry": {"coordinates":[69.5776,32.97219],"type":"Point"}
}