{
  "type": "Feature",
  "properties": {
    "gn:admin1_code":"4.0",
    "gn:asciiname":"Khyruwala",
    "gn:country_code":"PK",
    "gn:dem":164,
    "gn:feature_class":"P",
    "gn:feature_code":"PPL",
    "gn:name":"Khyruwala",
    "gn:population":0,
    "gn:timezone":"Asia/Karachi",
    "iso:country":"PK",
    "wof:name":"Khyruwala",
    "wof:placetype":"locality"
},
  "geometry": {"coordinates":[71.24538000000003,31.51888],"type":"Point"}
}