{
  "type": "Feature",
  "properties": {
    "gn:admin1_code":"2",
    "gn:asciiname":"Gandbo",
    "gn:country_code":"PK",
    "gn:dem":55,
    "gn:feature_class":"P",
    "gn:feature_code":"PPL",
    "gn:name":"Gandbo",
    "gn:population":0,
    "gn:timezone":"Asia/Karachi",
    "iso:country":"PK",
    "name:eng_x_preferred":[
        "Gandbo"
    ],
    "wof:name":"Gandbo",
    "wof:placetype":"locality"
},
  "geometry": {"coordinates":[66.85903,25.04933],"type":"Point"}
}