{
  "type": "Feature",
  "properties": {
    "gn:admin1_code":"2.0",
    "gn:asciiname":"Baz Barrad",
    "gn:country_code":"PK",
    "gn:dem":1419,
    "gn:feature_class":"P",
    "gn:feature_code":"PPL",
    "gn:name":"Baz Barrad",
    "gn:population":0,
    "gn:timezone":"Asia/Karachi",
    "iso:country":"PK",
    "wof:name":"Baz Barrad",
    "wof:placetype":"locality"
},
  "geometry": {"coordinates":[69.39261999999999,30.48833],"type":"Point"}
}