{
  "type": "Feature",
  "properties": {
    "gn:admin1_code":"2.0",
    "gn:asciiname":"Hussainzai",
    "gn:country_code":"PK",
    "gn:dem":1684,
    "gn:feature_class":"P",
    "gn:feature_code":"PPL",
    "gn:name":"Hussainzai",
    "gn:population":0,
    "gn:timezone":"Asia/Karachi",
    "iso:country":"PK",
    "wof:name":"Hussainzai",
    "wof:placetype":"locality"
},
  "geometry": {"coordinates":[66.19184,28.21678],"type":"Point"}
}