{
  "type": "Feature",
  "properties": {
    "gn:admin1_code":"01",
    "gn:asciiname":"Jala Din",
    "gn:country_code":"PK",
    "gn:dem":2521,
    "gn:feature_class":"P",
    "gn:feature_code":"PPL",
    "gn:name":"Jala Din",
    "gn:population":0,
    "gn:timezone":"Asia/Karachi",
    "iso:country":"PK",
    "name:und_x_variant":[
        "Jalad\u012bn"
    ],
    "wof:name":"Jala Din",
    "wof:placetype":"locality"
},
  "geometry": {"coordinates":[70.64090999999998,33.93501],"type":"Point"}
}