{
  "type": "Feature",
  "properties": {
    "gn:admin1_code":"05",
    "gn:asciiname":"Muhammad Usman",
    "gn:country_code":"PK",
    "gn:dem":3,
    "gn:feature_class":"P",
    "gn:feature_code":"PPL",
    "gn:name":"Muhammad Usman",
    "gn:population":0,
    "gn:timezone":"Asia/Karachi",
    "iso:country":"PK",
    "name:und_x_variant":[
        "Usm\u0101n B\u0101hra"
    ],
    "wof:name":"Muhammad Usman",
    "wof:placetype":"locality"
},
  "geometry": {"coordinates":[67.90631999999999,24.24166],"type":"Point"}
}