{
  "type": "Feature",
  "properties": {
    "gn:admin1_code":"4",
    "gn:asciiname":"Allah Bakhshwala",
    "gn:country_code":"PK",
    "gn:dem":141,
    "gn:feature_class":"P",
    "gn:feature_code":"PPL",
    "gn:name":"Allah Bakhshwala",
    "gn:population":0,
    "gn:timezone":"Asia/Karachi",
    "iso:country":"PK",
    "name:und_x_variant":[
        "All\u0101h Bakhsh",
        "Allah Bakhshwala"
    ],
    "wof:name":"Allah Bakhshwala",
    "wof:placetype":"locality"
},
  "geometry": {"coordinates":[70.71375999999999,30.55065],"type":"Point"}
}