{
  "type": "Feature",
  "properties": {
    "gn:admin1_code":"4",
    "gn:asciiname":"Chak One Hundred Forty-two Southern Branch",
    "gn:country_code":"PK",
    "gn:dem":186,
    "gn:feature_class":"P",
    "gn:feature_code":"PPL",
    "gn:name":"Chak One Hundred Forty-two Southern Branch",
    "gn:population":0,
    "gn:timezone":"Asia/Karachi",
    "iso:country":"PK",
    "name:und_x_variant":[
        "Chak One Hundred Forty-two SB"
    ],
    "wof:name":"Chak One Hundred Forty-two Southern Branch",
    "wof:placetype":"locality"
},
  "geometry": {"coordinates":[72.6589,31.94758],"type":"Point"}
}