{
  "type": "Feature",
  "properties": {
    "gn:admin1_code":"2",
    "gn:asciiname":"Goth Kora Hara",
    "gn:country_code":"PK",
    "gn:dem":122,
    "gn:feature_class":"P",
    "gn:feature_code":"PPL",
    "gn:name":"Goth Kora Hara",
    "gn:population":0,
    "gn:timezone":"Asia/Karachi",
    "iso:country":"PK",
    "wof:name":"Goth Kora Hara",
    "wof:placetype":"locality"
},
  "geometry": {"coordinates":[67.93235,29.41604],"type":"Point"}
}