{
  "type": "Feature",
  "properties": {
    "gn:admin1_code":"5.0",
    "gn:asciiname":"Umar Shidi",
    "gn:country_code":"PK",
    "gn:dem":11,
    "gn:feature_class":"P",
    "gn:feature_code":"PPL",
    "gn:name":"Umar Shidi",
    "gn:population":0,
    "gn:timezone":"Asia/Karachi",
    "iso:country":"PK",
    "name:eng_x_preferred":[
        "Umar Shidi"
    ],
    "wof:name":"Umar Shidi",
    "wof:placetype":"locality"
},
  "geometry": {"coordinates":[68.23739,24.70637],"type":"Point"}
}