{
  "type": "Feature",
  "properties": {
    "gn:admin1_code":"7.0",
    "gn:asciiname":"Salat",
    "gn:country_code":"PK",
    "gn:dem":2161,
    "gn:feature_class":"P",
    "gn:feature_code":"PPL",
    "gn:name":"Salat",
    "gn:population":0,
    "gn:timezone":"Asia/Karachi",
    "iso:country":"PK",
    "wof:name":"Salat",
    "wof:placetype":"locality"
},
  "geometry": {"coordinates":[74.53189999999999,35.66028],"type":"Point"}
}