{
  "type": "Feature",
  "properties": {
    "gn:admin1_code":"4",
    "gn:asciiname":"Mota Gharb",
    "gn:country_code":"PK",
    "gn:dem":274,
    "gn:feature_class":"P",
    "gn:feature_code":"PPL",
    "gn:name":"Mota Gharb",
    "gn:population":0,
    "gn:timezone":"Asia/Karachi",
    "iso:country":"PK",
    "name:und_x_variant":[
        "Mote"
    ],
    "wof:name":"Mota Gharb",
    "wof:placetype":"locality"
},
  "geometry": {"coordinates":[73.5248,32.98669],"type":"Point"}
}