{
  "type": "Feature",
  "properties": {
    "gn:admin1_code":"4.0",
    "gn:asciiname":"Mehran da Khu",
    "gn:country_code":"PK",
    "gn:dem":183,
    "gn:feature_class":"P",
    "gn:feature_code":"PPL",
    "gn:name":"Mehran da Khu",
    "gn:population":0,
    "gn:timezone":"Asia/Karachi",
    "iso:country":"PK",
    "wof:name":"Mehran da Khu",
    "wof:placetype":"locality"
},
  "geometry": {"coordinates":[73.49063000000002,30.98813],"type":"Point"}
}