{
  "type": "Feature",
  "properties": {
    "gn:admin1_code":"4",
    "gn:asciiname":"Chak Six Hundred Fifty -One",
    "gn:country_code":"PK",
    "gn:dem":193,
    "gn:feature_class":"P",
    "gn:feature_code":"PPL",
    "gn:name":"Chak Six Hundred Fifty -One",
    "gn:population":0,
    "gn:timezone":"Asia/Karachi",
    "iso:country":"PK",
    "name:und_x_variant":[
        "Nai\u0101b\u0101di"
    ],
    "wof:name":"Chak Six Hundred Fifty -One",
    "wof:placetype":"locality"
},
  "geometry": {"coordinates":[73.51519,31.33368],"type":"Point"}
}