{
  "type": "Feature",
  "properties": {
    "gn:admin1_code":"4",
    "gn:asciiname":"Guddar Singhwala",
    "gn:country_code":"PK",
    "gn:dem":129,
    "gn:feature_class":"P",
    "gn:feature_code":"PPL",
    "gn:name":"Guddar Singhwala",
    "gn:population":0,
    "gn:timezone":"Asia/Karachi",
    "iso:country":"PK",
    "wof:name":"Guddar Singhwala",
    "wof:placetype":"locality"
},
  "geometry": {"coordinates":[71.86733000000002,30.28704],"type":"Point"}
}