{
  "type": "Feature",
  "properties": {
    "gn:admin1_code":"4.0",
    "gn:asciiname":"Basti Shali Khan",
    "gn:country_code":"PK",
    "gn:dem":1527,
    "gn:feature_class":"P",
    "gn:feature_code":"PPL",
    "gn:name":"Basti Shali Khan",
    "gn:population":0,
    "gn:timezone":"Asia/Karachi",
    "iso:country":"PK",
    "wof:name":"Basti Shali Khan",
    "wof:placetype":"locality"
},
  "geometry": {"coordinates":[69.96545,29.96194],"type":"Point"}
}