{
  "type": "Feature",
  "properties": {
    "gn:admin1_code":"3.0",
    "gn:asciiname":"Pehmdi",
    "gn:country_code":"PK",
    "gn:dem":1805,
    "gn:feature_class":"P",
    "gn:feature_code":"PPL",
    "gn:name":"Pehmdi",
    "gn:population":0,
    "gn:timezone":"Asia/Karachi",
    "iso:country":"PK",
    "wof:name":"Pehmdi",
    "wof:placetype":"locality"
},
  "geometry": {"coordinates":[71.76106,35.41111],"type":"Point"}
}