{
  "type": "Feature",
  "properties": {
    "gn:admin1_code":"4.0",
    "gn:asciiname":"Chak Five Hundred Eighty-two Thal Development Authority",
    "gn:country_code":"PK",
    "gn:dem":132,
    "gn:feature_class":"P",
    "gn:feature_code":"PPL",
    "gn:name":"Chak Five Hundred Eighty-two Thal Development Authority",
    "gn:population":0,
    "gn:timezone":"Asia/Karachi",
    "iso:country":"PK",
    "wof:name":"Chak Five Hundred Eighty-two Thal Development Authority",
    "wof:placetype":"locality"
},
  "geometry": {"coordinates":[71.19665000000001,30.53174000000001],"type":"Point"}
}