{
  "type": "Feature",
  "properties": {
    "gn:admin1_code":"4",
    "gn:asciiname":"Wan Head",
    "gn:country_code":"PK",
    "gn:dem":187,
    "gn:feature_class":"P",
    "gn:feature_code":"PPL",
    "gn:name":"Wan Head",
    "gn:population":0,
    "gn:timezone":"Asia/Karachi",
    "iso:country":"PK",
    "name:und_x_variant":[
        "Khokhar Pull"
    ],
    "wof:name":"Wan Head",
    "wof:placetype":"locality"
},
  "geometry": {"coordinates":[73.68494,31.00264],"type":"Point"}
}