{
  "type": "Feature",
  "properties": {
    "gn:admin1_code":"5.0",
    "gn:asciiname":"Goth Umar Katiar",
    "gn:country_code":"PK",
    "gn:dem":25,
    "gn:feature_class":"P",
    "gn:feature_code":"PPL",
    "gn:name":"Goth Umar Katiar",
    "gn:population":0,
    "gn:timezone":"Asia/Karachi",
    "iso:country":"PK",
    "name:und_x_variant":[
        "Umar Kati\u0101r",
        "Goth Umar Katiar"
    ],
    "wof:name":"Goth Umar Katiar",
    "wof:placetype":"locality"
},
  "geometry": {"coordinates":[67.67031,24.7927],"type":"Point"}
}