{
  "type": "Feature",
  "properties": {
    "gn:admin1_code":"5",
    "gn:asciiname":"Goth Hiro Talpur",
    "gn:country_code":"PK",
    "gn:dem":17,
    "gn:feature_class":"P",
    "gn:feature_code":"PPL",
    "gn:name":"Goth Hiro Talpur",
    "gn:population":0,
    "gn:timezone":"Asia/Karachi",
    "iso:country":"PK",
    "name:und_x_variant":[
        "Haro T\u0101lpur"
    ],
    "wof:name":"Goth Hiro Talpur",
    "wof:placetype":"locality"
},
  "geometry": {"coordinates":[68.75017,25.01212],"type":"Point"}
}