{
  "type": "Feature",
  "properties": {
    "gn:admin1_code":"03",
    "gn:asciiname":"Rampatai",
    "gn:country_code":"PK",
    "gn:dem":1774,
    "gn:feature_class":"P",
    "gn:feature_code":"PPL",
    "gn:name":"Rampatai",
    "gn:population":0,
    "gn:timezone":"Asia/Karachi",
    "iso:country":"PK",
    "name:und_x_variant":[
        "Rang Patai",
        "Rampatai"
    ],
    "wof:name":"Rampatai",
    "wof:placetype":"locality"
},
  "geometry": {"coordinates":[72.29845999999998,34.99887],"type":"Point"}
}