{
  "type": "Feature",
  "properties": {
    "gn:admin1_code":"4.0",
    "gn:asciiname":"Shahwali Chhol",
    "gn:country_code":"PK",
    "gn:dem":644,
    "gn:feature_class":"P",
    "gn:feature_code":"PPL",
    "gn:name":"Shahwali Chhol",
    "gn:population":0,
    "gn:timezone":"Asia/Karachi",
    "iso:country":"PK",
    "wof:name":"Shahwali Chhol",
    "wof:placetype":"locality"
},
  "geometry": {"coordinates":[72.39368,32.74343],"type":"Point"}
}