{
  "type": "Feature",
  "properties": {
    "gn:admin1_code":"8.0",
    "gn:asciiname":"Jhangi Saiydan",
    "gn:country_code":"PK",
    "gn:dem":556,
    "gn:feature_class":"P",
    "gn:feature_code":"PPL",
    "gn:name":"Jhangi Saiydan",
    "gn:population":0,
    "gn:timezone":"Asia/Karachi",
    "iso:country":"PK",
    "name:und_x_variant":[
        "Jhangi Saiyid\u0101n"
    ],
    "wof:name":"Jhangi Saiydan",
    "wof:placetype":"locality"
},
  "geometry": {"coordinates":[72.94453,33.62531],"type":"Point"}
}