{
  "type": "Feature",
  "properties": {
    "gn:admin1_code":"01",
    "gn:asciiname":"Kharkai",
    "gn:country_code":"PK",
    "gn:dem":960,
    "gn:feature_class":"P",
    "gn:feature_code":"PPL",
    "gn:name":"Kharkai",
    "gn:population":0,
    "gn:timezone":"Asia/Karachi",
    "iso:country":"PK",
    "name:und_x_variant":[
        "Kharkanai",
        "Khar Kanai"
    ],
    "wof:name":"Kharkai",
    "wof:placetype":"locality"
},
  "geometry": {"coordinates":[71.48369,34.60057],"type":"Point"}
}