{
  "type": "Feature",
  "properties": {
    "gn:admin1_code":"3",
    "gn:asciiname":"Kharai",
    "gn:country_code":"PK",
    "gn:dem":1374,
    "gn:feature_class":"P",
    "gn:feature_code":"PPL",
    "gn:name":"Kharai",
    "gn:population":0,
    "gn:timezone":"Asia/Karachi",
    "iso:country":"PK",
    "name:und_x_variant":[
        "Kherai"
    ],
    "wof:name":"Kharai",
    "wof:placetype":"locality"
},
  "geometry": {"coordinates":[72.63763,34.76958],"type":"Point"}
}