{
  "type": "Feature",
  "properties": {
    "gn:admin1_code":"4",
    "gn:asciiname":"Chak Three Hundred Eighty Gogera Branch",
    "gn:country_code":"PK",
    "gn:dem":190,
    "gn:feature_class":"P",
    "gn:feature_code":"PPL",
    "gn:name":"Chak Three Hundred Eighty Gogera Branch",
    "gn:population":0,
    "gn:timezone":"Asia/Karachi",
    "iso:country":"PK",
    "name:und_x_variant":[
        "Lurkaw\u0101la",
        "Larki\u0101n da Chak"
    ],
    "wof:name":"Chak Three Hundred Eighty Gogera Branch",
    "wof:placetype":"locality"
},
  "geometry": {"coordinates":[73.42034,31.23935],"type":"Point"}
}