{
  "type": "Feature",
  "properties": {
    "gn:admin1_code":"2",
    "gn:asciiname":"Goth Ghulam Hussain",
    "gn:country_code":"PK",
    "gn:dem":92,
    "gn:feature_class":"P",
    "gn:feature_code":"PPL",
    "gn:name":"Goth Ghulam Hussain",
    "gn:population":0,
    "gn:timezone":"Asia/Karachi",
    "iso:country":"PK",
    "name:eng_x_preferred":[
        "Goth Ghulam Hussain"
    ],
    "wof:name":"Goth Ghulam Hussain",
    "wof:placetype":"locality"
},
  "geometry": {"coordinates":[66.82505999999999,25.10338],"type":"Point"}
}