{
  "type": "Feature",
  "properties": {
    "gn:admin1_code":"4.0",
    "gn:asciiname":"Dungi Kalan",
    "gn:country_code":"PK",
    "gn:dem":534,
    "gn:feature_class":"P",
    "gn:feature_code":"PPL",
    "gn:name":"Dungi Kalan",
    "gn:population":0,
    "gn:timezone":"Asia/Karachi",
    "iso:country":"PK",
    "name:und_x_variant":[
        "Daungi Kalan",
        "Dungi Kalan"
    ],
    "wof:name":"Dungi Kalan",
    "wof:placetype":"locality"
},
  "geometry": {"coordinates":[73.13606999999998,33.2108],"type":"Point"}
}