{
  "type": "Feature",
  "properties": {
    "gn:admin1_code":"3",
    "gn:asciiname":"Dak Stage",
    "gn:country_code":"PK",
    "gn:dem":203,
    "gn:feature_class":"P",
    "gn:feature_code":"PPL",
    "gn:name":"D\u0101k Stage",
    "gn:population":0,
    "gn:timezone":"Asia/Karachi",
    "iso:country":"PK",
    "wof:name":"Dak Stage",
    "wof:placetype":"locality"
},
  "geometry": {"coordinates":[70.67222,31.975],"type":"Point"}
}