{
  "type": "Feature",
  "properties": {
    "gn:admin1_code":"4",
    "gn:asciiname":"Maddoke",
    "gn:country_code":"PK",
    "gn:dem":231,
    "gn:feature_class":"P",
    "gn:feature_code":"PPL",
    "gn:name":"Maddoke",
    "gn:population":0,
    "gn:timezone":"Asia/Karachi",
    "iso:country":"PK",
    "name:pan_x_preferred":[
        "\u0a2e\u0a71\u0a26\u0a4b\u0a15\u0a47"
    ],
    "name:und_x_variant":[
        "Maddako"
    ],
    "name:urd_x_preferred":[
        "\u0645\u06cc\u0688\u0648\u06a9\u06cc"
    ],
    "wof:name":"Maddoke",
    "wof:placetype":"locality"
},
  "geometry": {"coordinates":[74.22447,32.52122],"type":"Point"}
}