{
  "type": "Feature",
  "properties": {
    "gn:admin1_code":"4",
    "gn:asciiname":"Maddoke",
    "gn:country_code":"PK",
    "gn:dem":231,
    "gn:feature_class":"P",
    "gn:feature_code":"PPL",
    "gn:name":"Maddoke",
    "gn:population":0,
    "gn:timezone":"Asia/Karachi",
    "iso:country":"PK",
    "name:und_x_variant":[
        "Maddako"
    ],
    "wof:name":"Maddoke",
    "wof:placetype":"locality"
},
  "geometry": {"coordinates":[74.22447,32.52122],"type":"Point"}
}