{
  "type": "Feature",
  "properties": {
    "gn:admin1_code":"3.0",
    "gn:asciiname":"Qayyumabad",
    "gn:country_code":"PK",
    "gn:dem":360,
    "gn:feature_class":"P",
    "gn:feature_code":"PPL",
    "gn:name":"Qayyumabad",
    "gn:population":0,
    "gn:timezone":"Asia/Karachi",
    "iso:country":"PK",
    "name:eng_x_preferred":[
        "Qayyumabad"
    ],
    "name:snd_x_preferred":[
        "\u0642\u064a\u0648\u0645 \u0622\u0628\u0627\u062f"
    ],
    "name:urd_x_preferred":[
        "\u0642\u06cc\u0648\u0645 \u0622\u0628\u0627\u062f"
    ],
    "wof:name":"Qayyumabad",
    "wof:placetype":"locality"
},
  "geometry": {"coordinates":[71.46337,34.03639],"type":"Point"}
}