{
  "type": "Feature",
  "properties": {
    "gn:admin1_code":"3.0",
    "gn:asciiname":"Qayyumabad",
    "gn:country_code":"PK",
    "gn:dem":360,
    "gn:feature_class":"P",
    "gn:feature_code":"PPL",
    "gn:name":"Qayyumabad",
    "gn:population":0,
    "gn:timezone":"Asia/Karachi",
    "iso:country":"PK",
    "wof:name":"Qayyumabad",
    "wof:placetype":"locality"
},
  "geometry": {"coordinates":[71.46337,34.03639],"type":"Point"}
}