{
  "type": "Feature",
  "properties": {
    "gn:admin1_code":"2",
    "gn:asciiname":"Hilalak Kach",
    "gn:country_code":"PK",
    "gn:dem":951,
    "gn:feature_class":"P",
    "gn:feature_code":"PPL",
    "gn:name":"Hilalak Kach",
    "gn:population":0,
    "gn:timezone":"Asia/Karachi",
    "iso:country":"PK",
    "name:eng_x_preferred":[
        "Halalk Kach"
    ],
    "name:und_x_variant":[
        "Halak Kach",
        "Hilalak Kach"
    ],
    "wof:name":"Hilalak Kach",
    "wof:placetype":"locality"
},
  "geometry": {"coordinates":[68.94868000000001,30.0205],"type":"Point"}
}