{
  "type": "Feature",
  "properties": {
    "gn:admin1_code":"2.0",
    "gn:asciiname":"Jawar Karoga",
    "gn:country_code":"PK",
    "gn:dem":1100,
    "gn:feature_class":"P",
    "gn:feature_code":"PPL",
    "gn:name":"Jawar Karoga",
    "gn:population":0,
    "gn:timezone":"Asia/Karachi",
    "iso:country":"PK",
    "wof:name":"Jawar Karoga",
    "wof:placetype":"locality"
},
  "geometry": {"coordinates":[70.12039,30.91851],"type":"Point"}
}