{
  "type": "Feature",
  "properties": {
    "gn:admin1_code":"5",
    "gn:asciiname":"Hashim Khan Dahri",
    "gn:country_code":"PK",
    "gn:dem":27,
    "gn:feature_class":"P",
    "gn:feature_code":"PPL",
    "gn:name":"Hashim Khan Dahri",
    "gn:population":0,
    "gn:timezone":"Asia/Karachi",
    "iso:country":"PK",
    "wof:name":"Hashim Khan Dahri",
    "wof:placetype":"locality"
},
  "geometry": {"coordinates":[68.63136,26.06607],"type":"Point"}
}