{
  "type": "Feature",
  "properties": {
    "gn:admin1_code":"3.0",
    "gn:asciiname":"Dogah Baihk",
    "gn:country_code":"PK",
    "gn:dem":3700,
    "gn:feature_class":"P",
    "gn:feature_code":"PPL",
    "gn:name":"Dogah Baihk",
    "gn:population":0,
    "gn:timezone":"Asia/Karachi",
    "iso:country":"PK",
    "wof:name":"Dogah Baihk",
    "wof:placetype":"locality"
},
  "geometry": {"coordinates":[73.82309000000002,35.20422],"type":"Point"}
}