{
  "type": "Feature",
  "properties": {
    "gn:admin1_code":"3.0",
    "gn:asciiname":"Suba Derai",
    "gn:country_code":"PK",
    "gn:dem":975,
    "gn:feature_class":"P",
    "gn:feature_code":"PPL",
    "gn:name":"Suba Derai",
    "gn:population":0,
    "gn:timezone":"Asia/Karachi",
    "iso:country":"PK",
    "wof:name":"Suba Derai",
    "wof:placetype":"locality"
},
  "geometry": {"coordinates":[72.96096999999997,34.72658],"type":"Point"}
}