{
  "type": "Feature",
  "properties": {
    "gn:admin1_code":"2.0",
    "gn:asciiname":"Lakra",
    "gn:country_code":"PK",
    "gn:dem":2050,
    "gn:feature_class":"P",
    "gn:feature_code":"PPL",
    "gn:name":"Lakra",
    "gn:population":0,
    "gn:timezone":"Asia/Karachi",
    "iso:country":"PK",
    "wof:name":"Lakra",
    "wof:placetype":"locality"
},
  "geometry": {"coordinates":[68.96788000000001,31.45886],"type":"Point"}
}