{
  "type": "Feature",
  "properties": {
    "gn:admin1_code":"1.0",
    "gn:asciiname":"Maare Kala",
    "gn:country_code":"PK",
    "gn:dem":2395,
    "gn:feature_class":"P",
    "gn:feature_code":"PPL",
    "gn:name":"Maare Kala",
    "gn:population":0,
    "gn:timezone":"Asia/Karachi",
    "iso:country":"PK",
    "wof:name":"Maare Kala",
    "wof:placetype":"locality"
},
  "geometry": {"coordinates":[69.66746999999999,32.70629],"type":"Point"}
}