{
  "type": "Feature",
  "properties": {
    "gn:admin1_code":"2.0",
    "gn:asciiname":"Kili Mula Khuda Bakhsh",
    "gn:country_code":"PK",
    "gn:dem":609,
    "gn:feature_class":"P",
    "gn:feature_code":"PPL",
    "gn:name":"Kili Mula Khuda Bakhsh",
    "gn:population":0,
    "gn:timezone":"Asia/Karachi",
    "iso:country":"PK",
    "wof:name":"Kili Mula Khuda Bakhsh",
    "wof:placetype":"locality"
},
  "geometry": {"coordinates":[64.37385999999999,28.34488],"type":"Point"}
}