{
  "type": "Feature",
  "properties": {
    "gn:admin1_code":"4.0",
    "gn:asciiname":"Habib di Kothi",
    "gn:country_code":"PK",
    "gn:dem":190,
    "gn:feature_class":"P",
    "gn:feature_code":"PPL",
    "gn:name":"Habib di Kothi",
    "gn:population":0,
    "gn:timezone":"Asia/Karachi",
    "iso:country":"PK",
    "wof:name":"Habib di Kothi",
    "wof:placetype":"locality"
},
  "geometry": {"coordinates":[72.85755999999998,31.86056],"type":"Point"}
}