{
  "type": "Feature",
  "properties": {
    "gn:admin1_code":"3.0",
    "gn:asciiname":"Abbas Kalle",
    "gn:country_code":"PK",
    "gn:dem":361,
    "gn:feature_class":"P",
    "gn:feature_code":"PPL",
    "gn:name":"Abbas Kalle",
    "gn:population":0,
    "gn:timezone":"Asia/Karachi",
    "iso:country":"PK",
    "name:und_x_variant":[
        "Abb\u0101s Kili",
        "Abbas Kalle"
    ],
    "wof:name":"Abbas Kalle",
    "wof:placetype":"locality"
},
  "geometry": {"coordinates":[70.61596,32.95937],"type":"Point"}
}