{
  "type": "Feature",
  "properties": {
    "gn:admin1_code":"2",
    "gn:asciiname":"Tamul",
    "gn:country_code":"PK",
    "gn:dem":1920,
    "gn:feature_class":"P",
    "gn:feature_code":"PPL",
    "gn:name":"Tamul",
    "gn:population":0,
    "gn:timezone":"Asia/Karachi",
    "iso:country":"PK",
    "wof:name":"Tamul",
    "wof:placetype":"locality"
},
  "geometry": {"coordinates":[66.91219,31.14419],"type":"Point"}
}