{
  "type": "Feature",
  "properties": {
    "gn:admin1_code":"3.0",
    "gn:asciiname":"Landi Shah",
    "gn:country_code":"PK",
    "gn:dem":920,
    "gn:feature_class":"P",
    "gn:feature_code":"PPL",
    "gn:name":"Landi Shah",
    "gn:population":0,
    "gn:timezone":"Asia/Karachi",
    "iso:country":"PK",
    "wof:name":"Landi Shah",
    "wof:placetype":"locality"
},
  "geometry": {"coordinates":[72.06355000000001,34.74754],"type":"Point"}
}