{
  "type": "Feature",
  "properties": {
    "gn:admin1_code":"04",
    "gn:asciiname":"Tindanwali Dahar",
    "gn:country_code":"PK",
    "gn:dem":97,
    "gn:feature_class":"P",
    "gn:feature_code":"PPL",
    "gn:name":"Tindanwali Dahar",
    "gn:population":0,
    "gn:timezone":"Asia/Karachi",
    "iso:country":"PK",
    "wof:name":"Tindanwali Dahar",
    "wof:placetype":"locality"
},
  "geometry": {"coordinates":[71.18893,28.1553],"type":"Point"}
}