{
  "type": "Feature",
  "properties": {
    "gn:admin1_code":"4",
    "gn:asciiname":"Basti Hatu Arain",
    "gn:country_code":"PK",
    "gn:dem":96,
    "gn:feature_class":"P",
    "gn:feature_code":"PPL",
    "gn:name":"Basti Hatu Arain",
    "gn:population":0,
    "gn:timezone":"Asia/Karachi",
    "iso:country":"PK",
    "name:und_x_variant":[
        "Basti Malik H\u0101tu Ar\u0101in"
    ],
    "wof:name":"Basti Hatu Arain",
    "wof:placetype":"locality"
},
  "geometry": {"coordinates":[70.55767,29.03938],"type":"Point"}
}