{
  "type": "Feature",
  "properties": {
    "gn:admin1_code":"2.0",
    "gn:asciiname":"Batar",
    "gn:country_code":"PK",
    "gn:dem":1504,
    "gn:feature_class":"P",
    "gn:feature_code":"PPL",
    "gn:name":"Batar",
    "gn:population":0,
    "gn:timezone":"Asia/Karachi",
    "iso:country":"PK",
    "name:ara_x_preferred":[
        "\u0627\u0644\u0628\u062a\u0627\u0631"
    ],
    "wof:name":"Batar",
    "wof:placetype":"locality"
},
  "geometry": {"coordinates":[66.20719,27.89744],"type":"Point"}
}