{
  "type": "Feature",
  "properties": {
    "gn:admin1_code":"2.0",
    "gn:asciiname":"Sorwan Kalat",
    "gn:country_code":"PK",
    "gn:dem":874,
    "gn:feature_class":"P",
    "gn:feature_code":"PPL",
    "gn:name":"Sorwan Kalat",
    "gn:population":0,
    "gn:timezone":"Asia/Karachi",
    "iso:country":"PK",
    "name:und_x_variant":[
        "Sarw\u0101n Camp"
    ],
    "wof:name":"Sorwan Kalat",
    "wof:placetype":"locality"
},
  "geometry": {"coordinates":[63.86323,26.86817000000001],"type":"Point"}
}