{
  "type": "Feature",
  "properties": {
    "gn:admin1_code":"3.0",
    "gn:asciiname":"Masti Khel",
    "gn:country_code":"PK",
    "gn:dem":976,
    "gn:feature_class":"P",
    "gn:feature_code":"PPL",
    "gn:name":"Masti Khel",
    "gn:population":0,
    "gn:timezone":"Asia/Karachi",
    "iso:country":"PK",
    "name:und_x_variant":[
        "Kimanai"
    ],
    "wof:name":"Masti Khel",
    "wof:placetype":"locality"
},
  "geometry": {"coordinates":[71.34375,33.13372],"type":"Point"}
}