{
  "type": "Feature",
  "properties": {
    "gn:admin1_code":"2.0",
    "gn:asciiname":"Uchkand Karez",
    "gn:country_code":"PK",
    "gn:dem":2187,
    "gn:feature_class":"P",
    "gn:feature_code":"PPL",
    "gn:name":"Uchkand Karez",
    "gn:population":0,
    "gn:timezone":"Asia/Karachi",
    "iso:country":"PK",
    "wof:name":"Uchkand Karez",
    "wof:placetype":"locality"
},
  "geometry": {"coordinates":[67.69037,31.26267],"type":"Point"}
}