{
  "type": "Feature",
  "properties": {
    "gn:admin1_code":"6",
    "gn:asciiname":"Qila Padhar",
    "gn:country_code":"PK",
    "gn:dem":325,
    "gn:feature_class":"P",
    "gn:feature_code":"PPL",
    "gn:name":"Qila Padhar",
    "gn:population":0,
    "gn:timezone":"Asia/Karachi",
    "iso:country":"PK",
    "name:und_x_variant":[
        "Padh\u0101r",
        "Qila Padh\u0101rr"
    ],
    "wof:name":"Qila Padhar",
    "wof:placetype":"locality"
},
  "geometry": {"coordinates":[74.27526999999998,32.86042],"type":"Point"}
}