{
  "type": "Feature",
  "properties": {
    "gn:admin1_code":"2.0",
    "gn:asciiname":"Safi",
    "gn:country_code":"PK",
    "gn:dem":1334,
    "gn:feature_class":"P",
    "gn:feature_code":"PPL",
    "gn:name":"Safi",
    "gn:population":0,
    "gn:timezone":"Asia/Karachi",
    "iso:country":"PK",
    "name:bul_x_preferred":[
        "\u0421\u0430\u0444\u0438"
    ],
    "name:ceb_x_preferred":[
        "Safi"
    ],
    "name:deu_x_preferred":[
        "Safi"
    ],
    "name:fra_x_preferred":[
        "Safi"
    ],
    "name:heb_x_preferred":[
        "\u05e1\u05d0\u05e4\u05d9"
    ],
    "name:hun_x_preferred":[
        "Safi"
    ],
    "name:isl_x_preferred":[
        "Safi"
    ],
    "name:ita_x_preferred":[
        "Safi"
    ],
    "name:nld_x_preferred":[
        "Safi"
    ],
    "name:pol_x_preferred":[
        "Safi"
    ],
    "name:por_x_preferred":[
        "Safi"
    ],
    "name:ron_x_preferred":[
        "Safi"
    ],
    "name:rus_x_preferred":[
        "\u0421\u0430\u0444\u0438"
    ],
    "name:swe_x_preferred":[
        "Safi"
    ],
    "name:tur_x_preferred":[
        "Safi"
    ],
    "wof:name":"Safi",
    "wof:placetype":"locality"
},
  "geometry": {"coordinates":[68.77537,30.4259],"type":"Point"}
}