{
  "type": "Feature",
  "properties": {
    "gn:admin1_code":"2.0",
    "gn:asciiname":"Safi",
    "gn:country_code":"PK",
    "gn:dem":1334,
    "gn:feature_class":"P",
    "gn:feature_code":"PPL",
    "gn:name":"Safi",
    "gn:population":0,
    "gn:timezone":"Asia/Karachi",
    "iso:country":"PK",
    "wof:name":"Safi",
    "wof:placetype":"locality"
},
  "geometry": {"coordinates":[68.77537,30.4259],"type":"Point"}
}