{
  "type": "Feature",
  "properties": {
    "gn:admin1_code":"1.0",
    "gn:asciiname":"Kaniguram",
    "gn:country_code":"PK",
    "gn:dem":1910,
    "gn:feature_class":"P",
    "gn:feature_code":"PPL",
    "gn:name":"Kaniguram",
    "gn:population":0,
    "gn:timezone":"Asia/Karachi",
    "iso:country":"PK",
    "name:und_x_variant":[
        "K\u0101nigurum",
        "Kaniguram"
    ],
    "wof:name":"Kaniguram",
    "wof:placetype":"locality"
},
  "geometry": {"coordinates":[69.78658,32.51888],"type":"Point"}
}