{
  "type": "Feature",
  "properties": {
    "gn:admin1_code":"01",
    "gn:asciiname":"Mulla Mir Dad Ziarat",
    "gn:country_code":"PK",
    "gn:dem":819,
    "gn:feature_class":"P",
    "gn:feature_code":"PPL",
    "gn:name":"Mulla Mir Dad Ziarat",
    "gn:population":0,
    "gn:timezone":"Asia/Karachi",
    "iso:country":"PK",
    "wof:name":"Mulla Mir Dad Ziarat",
    "wof:placetype":"locality"
},
  "geometry": {"coordinates":[71.61636,34.61405999999999],"type":"Point"}
}