{
  "type": "Feature",
  "properties": {
    "gn:admin1_code":"5",
    "gn:asciiname":"Goth Haji Laghari",
    "gn:country_code":"PK",
    "gn:dem":14,
    "gn:feature_class":"P",
    "gn:feature_code":"PPL",
    "gn:name":"Goth Haji Laghari",
    "gn:population":0,
    "gn:timezone":"Asia/Karachi",
    "iso:country":"PK",
    "name:und_x_variant":[
        "Goth H\u0101ji Lagh\u0101ri"
    ],
    "wof:name":"Goth Haji Laghari",
    "wof:placetype":"locality"
},
  "geometry": {"coordinates":[69.06188,25.45037],"type":"Point"}
}