{
  "type": "Feature",
  "properties": {
    "gn:admin1_code":"1.0",
    "gn:asciiname":"Ramo",
    "gn:country_code":"PK",
    "gn:dem":965,
    "gn:feature_class":"P",
    "gn:feature_code":"PPL",
    "gn:name":"Ramo",
    "gn:population":0,
    "gn:timezone":"Asia/Karachi",
    "iso:country":"PK",
    "wof:name":"Ramo",
    "wof:placetype":"locality"
},
  "geometry": {"coordinates":[71.54885,34.5874],"type":"Point"}
}