{
  "type": "Feature",
  "properties": {
    "gn:admin1_code":"7.0",
    "gn:asciiname":"Harengal",
    "gn:country_code":"PK",
    "gn:dem":3452,
    "gn:feature_class":"P",
    "gn:feature_code":"PPL",
    "gn:name":"Harengal",
    "gn:population":0,
    "gn:timezone":"Asia/Karachi",
    "iso:country":"PK",
    "name:und_x_variant":[
        "Haringal Sh\u0101l"
    ],
    "wof:name":"Harengal",
    "wof:placetype":"locality"
},
  "geometry": {"coordinates":[72.91330000000001,36.35108],"type":"Point"}
}