{
  "type": "Feature",
  "properties": {
    "gn:admin1_code":"5",
    "gn:asciiname":"Numberdar Panjabi",
    "gn:country_code":"PK",
    "gn:dem":26,
    "gn:feature_class":"P",
    "gn:feature_code":"PPL",
    "gn:name":"Numberdar Panjabi",
    "gn:population":0,
    "gn:timezone":"Asia/Karachi",
    "iso:country":"PK",
    "name:und_x_variant":[
        "Numberd\u0101r Punj\u0101bi"
    ],
    "wof:name":"Numberdar Panjabi",
    "wof:placetype":"locality"
},
  "geometry": {"coordinates":[68.56945999999999,26.02677000000001],"type":"Point"}
}