{
  "type": "Feature",
  "properties": {
    "gn:admin1_code":"4.0",
    "gn:asciiname":"Benke",
    "gn:country_code":"PK",
    "gn:dem":176,
    "gn:feature_class":"P",
    "gn:feature_code":"PPL",
    "gn:name":"Benke",
    "gn:population":0,
    "gn:timezone":"Asia/Karachi",
    "iso:country":"PK",
    "name:deu_x_preferred":[
        "Benke"
    ],
    "wof:name":"Benke",
    "wof:placetype":"locality"
},
  "geometry": {"coordinates":[73.87288000000002,30.36019000000001],"type":"Point"}
}