{
  "type": "Feature",
  "properties": {
    "gn:admin1_code":"04",
    "gn:asciiname":"Takhtmahal",
    "gn:country_code":"PK",
    "gn:dem":207,
    "gn:feature_class":"P",
    "gn:feature_code":"PPL",
    "gn:name":"Takhtmahal",
    "gn:population":0,
    "gn:timezone":"Asia/Karachi",
    "iso:country":"PK",
    "name:und_x_variant":[
        "Takhtma",
        "Takhtmal",
        "Takhtmahal"
    ],
    "wof:name":"Takhtmahal",
    "wof:placetype":"locality"
},
  "geometry": {"coordinates":[73.49701999999998,32.37472],"type":"Point"}
}