{
  "type": "Feature",
  "properties": {
    "gn:admin1_code":"4",
    "gn:asciiname":"Chak Thirty-one SP",
    "gn:country_code":"PK",
    "gn:dem":163,
    "gn:feature_class":"P",
    "gn:feature_code":"PPL",
    "gn:name":"Chak Thirty-one SP",
    "gn:population":0,
    "gn:timezone":"Asia/Karachi",
    "iso:country":"PK",
    "name:und_x_variant":[
        "Chak Thirty-one",
        "Gidarpur"
    ],
    "wof:name":"Chak Thirty-one SP",
    "wof:placetype":"locality"
},
  "geometry": {"coordinates":[73.3151,30.42554],"type":"Point"}
}