{
  "type": "Feature",
  "properties": {
    "gn:admin1_code":"4.0",
    "gn:asciiname":"Chak Two Hundred Thirty-nine Rakh Branch",
    "gn:country_code":"PK",
    "gn:dem":183,
    "gn:feature_class":"P",
    "gn:feature_code":"PPL",
    "gn:name":"Chak Two Hundred Thirty-nine Rakh Branch",
    "gn:population":0,
    "gn:timezone":"Asia/Karachi",
    "iso:country":"PK",
    "name:und_x_variant":[
        "Hari\u0101n",
        "Chak Two Hundred Thirty-Nine RB",
        "Chak Two Hundred Thirty-nine Rakh Branch",
        "Harni\u0101n"
    ],
    "wof:name":"Chak Two Hundred Thirty-nine Rakh Branch",
    "wof:placetype":"locality"
},
  "geometry": {"coordinates":[73.17511,31.33921],"type":"Point"}
}