{
  "type": "Feature",
  "properties": {
    "gn:admin1_code":"2.0",
    "gn:asciiname":"Dura Chat",
    "gn:country_code":"PK",
    "gn:dem":239,
    "gn:feature_class":"P",
    "gn:feature_code":"PPL",
    "gn:name":"Dura Chat",
    "gn:population":0,
    "gn:timezone":"Asia/Karachi",
    "iso:country":"PK",
    "wof:name":"Dura Chat",
    "wof:placetype":"locality"
},
  "geometry": {"coordinates":[61.93782,26.15778],"type":"Point"}
}