{
  "type": "Feature",
  "properties": {
    "gn:admin1_code":"4",
    "gn:asciiname":"Nawan Lak Kharoke",
    "gn:country_code":"PK",
    "gn:dem":171,
    "gn:feature_class":"P",
    "gn:feature_code":"PPL",
    "gn:name":"Nawan Lak Kharoke",
    "gn:population":0,
    "gn:timezone":"Asia/Karachi",
    "iso:country":"PK",
    "name:und_x_variant":[
        "Naw\u0101n Log"
    ],
    "wof:name":"Nawan Lak Kharoke",
    "wof:placetype":"locality"
},
  "geometry": {"coordinates":[72.43108000000002,31.94457],"type":"Point"}
}