{
  "type": "Feature",
  "properties": {
    "gn:admin1_code":"3.0",
    "gn:asciiname":"Multan Manjiwala",
    "gn:country_code":"PK",
    "gn:dem":281,
    "gn:feature_class":"P",
    "gn:feature_code":"PPL",
    "gn:name":"Multan Manjiwala",
    "gn:population":0,
    "gn:timezone":"Asia/Karachi",
    "iso:country":"PK",
    "name:und_x_variant":[
        "Pur\u0101na Manjiw\u0101la",
        "Mult\u0101n",
        "Mult\u0101n Manjiw\u0101la",
        "Multan Manjiwala"
    ],
    "wof:name":"Multan Manjiwala",
    "wof:placetype":"locality"
},
  "geometry": {"coordinates":[70.83409,32.75021],"type":"Point"}
}