{
  "type": "Feature",
  "properties": {
    "gn:admin1_code":"2",
    "gn:asciiname":"Hardozo Zrandah",
    "gn:country_code":"PK",
    "gn:dem":1863,
    "gn:feature_class":"P",
    "gn:feature_code":"PPL",
    "gn:name":"Hardozo Zrandah",
    "gn:population":0,
    "gn:timezone":"Asia/Karachi",
    "iso:country":"PK",
    "wof:name":"Hardozo Zrandah",
    "wof:placetype":"locality"
},
  "geometry": {"coordinates":[66.81961,31.15309],"type":"Point"}
}