{
  "type": "Feature",
  "properties": {
    "gn:admin1_code":"2.0",
    "gn:asciiname":"Gilwandai",
    "gn:country_code":"PK",
    "gn:dem":2219,
    "gn:feature_class":"P",
    "gn:feature_code":"PPL",
    "gn:name":"Gilwandai",
    "gn:population":0,
    "gn:timezone":"Asia/Karachi",
    "iso:country":"PK",
    "name:und_x_variant":[
        "Ghalwendi",
        "Gilwandai"
    ],
    "wof:name":"Gilwandai",
    "wof:placetype":"locality"
},
  "geometry": {"coordinates":[67.80291,31.07936],"type":"Point"}
}