{
  "type": "Feature",
  "properties": {
    "gn:admin1_code":"04",
    "gn:asciiname":"Wan Chatta",
    "gn:country_code":"PK",
    "gn:dem":121,
    "gn:feature_class":"P",
    "gn:feature_code":"PPL",
    "gn:name":"Wan Chatta",
    "gn:population":0,
    "gn:timezone":"Asia/Karachi",
    "iso:country":"PK",
    "name:und_x_variant":[
        "W\u0101nchatta",
        "W\u0101n Chhatta",
        "Wan Chatta"
    ],
    "wof:name":"Wan Chatta",
    "wof:placetype":"locality"
},
  "geometry": {"coordinates":[71.44008000000002,30.10736],"type":"Point"}
}