{
  "type": "Feature",
  "properties": {
    "gn:admin1_code":"2.0",
    "gn:asciiname":"Kili Wali Muhammad",
    "gn:country_code":"PK",
    "gn:dem":1508,
    "gn:feature_class":"P",
    "gn:feature_code":"PPL",
    "gn:name":"Kili Wali Muhammad",
    "gn:population":0,
    "gn:timezone":"Asia/Karachi",
    "iso:country":"PK",
    "wof:name":"Kili Wali Muhammad",
    "wof:placetype":"locality"
},
  "geometry": {"coordinates":[66.56386999999999,30.08175],"type":"Point"}
}