{
  "type": "Feature",
  "properties": {
    "gn:admin1_code":"3.0",
    "gn:asciiname":"Hariala",
    "gn:country_code":"PK",
    "gn:dem":1085,
    "gn:feature_class":"P",
    "gn:feature_code":"PPL",
    "gn:name":"Hariala",
    "gn:population":0,
    "gn:timezone":"Asia/Karachi",
    "iso:country":"PK",
    "wof:name":"Hariala",
    "wof:placetype":"locality"
},
  "geometry": {"coordinates":[73.16745,33.82709000000001],"type":"Point"}
}