{
  "type": "Feature",
  "properties": {
    "gn:admin1_code":"4.0",
    "gn:asciiname":"Chak Six Hundred Eight Thal Development Authority",
    "gn:country_code":"PK",
    "gn:dem":127,
    "gn:feature_class":"P",
    "gn:feature_code":"PPL",
    "gn:name":"Chak Six Hundred Eight Thal Development Authority",
    "gn:population":0,
    "gn:timezone":"Asia/Karachi",
    "iso:country":"PK",
    "wof:name":"Chak Six Hundred Eight Thal Development Authority",
    "wof:placetype":"locality"
},
  "geometry": {"coordinates":[71.22421,30.37803],"type":"Point"}
}