{
  "type": "Feature",
  "properties": {
    "gn:admin1_code":"2.0",
    "gn:asciiname":"Ghulam Nabi",
    "gn:country_code":"PK",
    "gn:dem":36,
    "gn:feature_class":"P",
    "gn:feature_code":"PPL",
    "gn:name":"Ghulam Nabi",
    "gn:population":0,
    "gn:timezone":"Asia/Karachi",
    "iso:country":"PK",
    "name:und_x_variant":[
        "Mujammad Ghul\u0101m Nabi"
    ],
    "name:urd_x_preferred":[
        "\u063a\u0644\u0627\u0645 \u0646\u0628\u06cc"
    ],
    "wof:name":"Ghulam Nabi",
    "wof:placetype":"locality"
},
  "geometry": {"coordinates":[62.40639,25.35438],"type":"Point"}
}