{
  "type": "Feature",
  "properties": {
    "gn:admin1_code":"2.0",
    "gn:asciiname":"Alroi",
    "gn:country_code":"PK",
    "gn:dem":2275,
    "gn:feature_class":"P",
    "gn:feature_code":"PPL",
    "gn:name":"Alroi",
    "gn:population":0,
    "gn:timezone":"Asia/Karachi",
    "iso:country":"PK",
    "wof:name":"Alroi",
    "wof:placetype":"locality"
},
  "geometry": {"coordinates":[66.87591999999999,29.2529],"type":"Point"}
}