{
  "type": "Feature",
  "properties": {
    "gn:admin1_code":"2",
    "gn:asciiname":"Goth Ghulam Muhammad",
    "gn:country_code":"PK",
    "gn:dem":51,
    "gn:feature_class":"P",
    "gn:feature_code":"PPL",
    "gn:name":"Goth Ghulam Muhammad",
    "gn:population":0,
    "gn:timezone":"Asia/Karachi",
    "iso:country":"PK",
    "name:und_x_variant":[
        "Ghul\u0101m Muhammad"
    ],
    "wof:name":"Goth Ghulam Muhammad",
    "wof:placetype":"locality"
},
  "geometry": {"coordinates":[67.80105999999999,28.05396],"type":"Point"}
}