{
  "type": "Feature",
  "properties": {
    "gn:admin1_code":"4",
    "gn:asciiname":"Udaniwala",
    "gn:country_code":"PK",
    "gn:dem":141,
    "gn:feature_class":"P",
    "gn:feature_code":"PPL",
    "gn:name":"Udaniwala",
    "gn:population":0,
    "gn:timezone":"Asia/Karachi",
    "iso:country":"PK",
    "name:und_x_variant":[
        "Darb\u0101nw\u0101la",
        "Darbanwala",
        "Udaniwala"
    ],
    "wof:name":"Udaniwala",
    "wof:placetype":"locality"
},
  "geometry": {"coordinates":[71.07429,30.75101],"type":"Point"}
}