{
  "type": "Feature",
  "properties": {
    "gn:admin1_code":"3.0",
    "gn:asciiname":"Raza Muhammad Koruna",
    "gn:country_code":"PK",
    "gn:dem":328,
    "gn:feature_class":"P",
    "gn:feature_code":"PPL",
    "gn:name":"Raza Muhammad Koruna",
    "gn:population":0,
    "gn:timezone":"Asia/Karachi",
    "iso:country":"PK",
    "wof:name":"Raza Muhammad Koruna",
    "wof:placetype":"locality"
},
  "geometry": {"coordinates":[71.86554,34.22123],"type":"Point"}
}