{
  "type": "Feature",
  "properties": {
    "gn:admin1_code":"5.0",
    "gn:asciiname":"Rais Muhammad Zardari",
    "gn:country_code":"PK",
    "gn:dem":27,
    "gn:feature_class":"P",
    "gn:feature_code":"PPL",
    "gn:name":"Rais Muhammad Zardari",
    "gn:population":0,
    "gn:timezone":"Asia/Karachi",
    "iso:country":"PK",
    "wof:name":"Rais Muhammad Zardari",
    "wof:placetype":"locality"
},
  "geometry": {"coordinates":[68.57953000000001,26.05218],"type":"Point"}
}