{
  "type": "Feature",
  "properties": {
    "gn:admin1_code":"3",
    "gn:asciiname":"Sarujal",
    "gn:country_code":"PK",
    "gn:dem":1965,
    "gn:feature_class":"P",
    "gn:feature_code":"PPL",
    "gn:name":"Sarujal",
    "gn:population":0,
    "gn:timezone":"Asia/Karachi",
    "iso:country":"PK",
    "name:eng_x_preferred":[
        "Saruzj\u0101l"
    ],
    "name:und_x_variant":[
        "Sarik J\u0101o",
        "Sarujal",
        "Sarik Jao"
    ],
    "wof:name":"Sarujal",
    "wof:placetype":"locality"
},
  "geometry": {"coordinates":[71.69596,35.69862],"type":"Point"}
}