{
  "type": "Feature",
  "properties": {
    "gn:admin1_code":"4.0",
    "gn:asciiname":"Basti Hadwar",
    "gn:country_code":"PK",
    "gn:dem":142,
    "gn:feature_class":"P",
    "gn:feature_code":"PPL",
    "gn:name":"Basti Hadwar",
    "gn:population":0,
    "gn:timezone":"Asia/Karachi",
    "iso:country":"PK",
    "name:eng_x_preferred":[
        "Hadw\u0101r"
    ],
    "wof:name":"Basti Hadwar",
    "wof:placetype":"locality"
},
  "geometry": {"coordinates":[70.75708,30.79807000000001],"type":"Point"}
}