{
  "type": "Feature",
  "properties": {
    "gn:admin1_code":"4.0",
    "gn:asciiname":"Goth Gathar",
    "gn:country_code":"PK",
    "gn:dem":317,
    "gn:feature_class":"P",
    "gn:feature_code":"PPL",
    "gn:name":"Goth Gathar",
    "gn:population":0,
    "gn:timezone":"Asia/Karachi",
    "iso:country":"PK",
    "name:und_x_variant":[
        "Dhok Gathar"
    ],
    "wof:name":"Goth Gathar",
    "wof:placetype":"locality"
},
  "geometry": {"coordinates":[72.0535,33.55595],"type":"Point"}
}