{
  "type": "Feature",
  "properties": {
    "gn:admin1_code":"4.0",
    "gn:asciiname":"Shanwal",
    "gn:country_code":"PK",
    "gn:dem":126,
    "gn:feature_class":"P",
    "gn:feature_code":"PPL",
    "gn:name":"Shanwal",
    "gn:population":0,
    "gn:timezone":"Asia/Karachi",
    "iso:country":"PK",
    "name:und_x_variant":[
        "Shahw\u0101la"
    ],
    "wof:name":"Shanwal",
    "wof:placetype":"locality"
},
  "geometry": {"coordinates":[71.11362,30.26924],"type":"Point"}
}