{
  "type": "Feature",
  "properties": {
    "gn:admin1_code":"01",
    "gn:asciiname":"Sara Khui",
    "gn:country_code":"PK",
    "gn:dem":2318,
    "gn:feature_class":"P",
    "gn:feature_code":"PPL",
    "gn:name":"Sara Khui",
    "gn:population":0,
    "gn:timezone":"Asia/Karachi",
    "iso:country":"PK",
    "name:und_x_variant":[
        "Sara Khwa"
    ],
    "wof:name":"Sara Khui",
    "wof:placetype":"locality"
},
  "geometry": {"coordinates":[70.74845000000001,33.71319],"type":"Point"}
}