{
  "type": "Feature",
  "properties": {
    "gn:admin1_code":"4",
    "gn:asciiname":"Zorwala",
    "gn:country_code":"PK",
    "gn:dem":107,
    "gn:feature_class":"P",
    "gn:feature_code":"PPL",
    "gn:name":"Zorwala",
    "gn:population":0,
    "gn:timezone":"Asia/Karachi",
    "iso:country":"PK",
    "wof:name":"Zorwala",
    "wof:placetype":"locality"
},
  "geometry": {"coordinates":[70.79843000000002,29.89511],"type":"Point"}
}