{
  "type": "Feature",
  "properties": {
    "gn:admin1_code":"3",
    "gn:asciiname":"Mairagai",
    "gn:country_code":"PK",
    "gn:dem":1254,
    "gn:feature_class":"P",
    "gn:feature_code":"PPL",
    "gn:name":"Mairagai",
    "gn:population":0,
    "gn:timezone":"Asia/Karachi",
    "iso:country":"PK",
    "wof:name":"Mairagai",
    "wof:placetype":"locality"
},
  "geometry": {"coordinates":[72.77824,34.79717],"type":"Point"}
}