{
  "type": "Feature",
  "properties": {
    "gn:admin1_code":"4.0",
    "gn:asciiname":"Salema Matta",
    "gn:country_code":"PK",
    "gn:dem":418,
    "gn:feature_class":"P",
    "gn:feature_code":"PPL",
    "gn:name":"Salema Matta",
    "gn:population":0,
    "gn:timezone":"Asia/Karachi",
    "iso:country":"PK",
    "wof:name":"Salema Matta",
    "wof:placetype":"locality"
},
  "geometry": {"coordinates":[74.2672,32.93523],"type":"Point"}
}