{
  "type": "Feature",
  "properties": {
    "gn:admin1_code":"6",
    "gn:asciiname":"Gitari",
    "gn:country_code":"PK",
    "gn:dem":765,
    "gn:feature_class":"P",
    "gn:feature_code":"PPL",
    "gn:name":"Gitari",
    "gn:population":0,
    "gn:timezone":"Asia/Karachi",
    "iso:country":"PK",
    "name:und_x_variant":[
        "Gu\u0101ri"
    ],
    "wof:name":"Gitari",
    "wof:placetype":"locality"
},
  "geometry": {"coordinates":[74.07590999999999,33.08509],"type":"Point"}
}