{
  "type": "Feature",
  "properties": {
    "gn:admin1_code":"3.0",
    "gn:asciiname":"Shakai",
    "gn:country_code":"PK",
    "gn:dem":3585,
    "gn:feature_class":"P",
    "gn:feature_code":"PPL",
    "gn:name":"Shakai",
    "gn:population":0,
    "gn:timezone":"Asia/Karachi",
    "iso:country":"PK",
    "wof:name":"Shakai",
    "wof:placetype":"locality"
},
  "geometry": {"coordinates":[72.91948000000002,35.535],"type":"Point"}
}