{
  "type": "Feature",
  "properties": {
    "gn:admin1_code":"3",
    "gn:asciiname":"Kotaranrai",
    "gn:country_code":"PK",
    "gn:dem":818,
    "gn:feature_class":"P",
    "gn:feature_code":"PPL",
    "gn:name":"Kot\u0101ranrai",
    "gn:population":0,
    "gn:timezone":"Asia/Karachi",
    "iso:country":"PK",
    "wof:name":"Kotaranrai",
    "wof:placetype":"locality"
},
  "geometry": {"coordinates":[72.36667,34.40417],"type":"Point"}
}