{
  "type": "Feature",
  "properties": {
    "gn:admin1_code":"4.0",
    "gn:asciiname":"Bhurchh",
    "gn:country_code":"PK",
    "gn:dem":282,
    "gn:feature_class":"P",
    "gn:feature_code":"PPL",
    "gn:name":"Bhurchh",
    "gn:population":0,
    "gn:timezone":"Asia/Karachi",
    "iso:country":"PK",
    "wof:name":"Bhurchh",
    "wof:placetype":"locality"
},
  "geometry": {"coordinates":[74.02154,32.81148],"type":"Point"}
}