{
  "type": "Feature",
  "properties": {
    "gn:admin1_code":"4.0",
    "gn:asciiname":"Achalwali",
    "gn:country_code":"PK",
    "gn:dem":244,
    "gn:feature_class":"P",
    "gn:feature_code":"PPL",
    "gn:name":"Achalwali",
    "gn:population":0,
    "gn:timezone":"Asia/Karachi",
    "iso:country":"PK",
    "wof:name":"Achalwali",
    "wof:placetype":"locality"
},
  "geometry": {"coordinates":[75.04188000000001,32.13624],"type":"Point"}
}