{
  "type": "Feature",
  "properties": {
    "gn:admin1_code":"4.0",
    "gn:asciiname":"Ganmumwala",
    "gn:country_code":"PK",
    "gn:dem":145,
    "gn:feature_class":"P",
    "gn:feature_code":"PPL",
    "gn:name":"Ganmumwala",
    "gn:population":0,
    "gn:timezone":"Asia/Karachi",
    "iso:country":"PK",
    "name:und_x_variant":[
        "G\u0101nm\u016bnw\u0101la",
        "G\u0101manw\u0101la",
        "Ganmumwala"
    ],
    "wof:name":"Ganmumwala",
    "wof:placetype":"locality"
},
  "geometry": {"coordinates":[70.90245999999998,30.91201],"type":"Point"}
}