{
  "type": "Feature",
  "properties": {
    "gn:admin1_code":"4",
    "gn:asciiname":"Basti Baluch",
    "gn:country_code":"PK",
    "gn:dem":202,
    "gn:feature_class":"P",
    "gn:feature_code":"PPL",
    "gn:name":"Basti Baluch",
    "gn:population":0,
    "gn:timezone":"Asia/Karachi",
    "iso:country":"PK",
    "name:und_x_variant":[
        "Basti Baloch"
    ],
    "wof:name":"Basti Baluch",
    "wof:placetype":"locality"
},
  "geometry": {"coordinates":[70.12475000000001,29.69562],"type":"Point"}
}