{
  "type": "Feature",
  "properties": {
    "gn:admin1_code":"04",
    "gn:asciiname":"Mandra",
    "gn:country_code":"PK",
    "gn:dem":516,
    "gn:feature_class":"P",
    "gn:feature_code":"PPL",
    "gn:name":"Mandra",
    "gn:population":0,
    "gn:timezone":"Asia/Karachi",
    "iso:country":"PK",
    "wof:name":"Mandra",
    "wof:placetype":"locality"
},
  "geometry": {"coordinates":[73.23859,33.36624],"type":"Point"}
}