{
  "type": "Feature",
  "properties": {
    "gn:admin1_code":"4.0",
    "gn:asciiname":"Dufli Kabir Khan",
    "gn:country_code":"PK",
    "gn:dem":98,
    "gn:feature_class":"P",
    "gn:feature_code":"PPL",
    "gn:name":"Dufli Kabir Khan",
    "gn:population":0,
    "gn:timezone":"Asia/Karachi",
    "iso:country":"PK",
    "name:und_x_variant":[
        "Dphli Kab\u012br Kh\u0101n",
        "Dufli Kabir Khan",
        "D\u0101khli Kabir Kh\u0101n"
    ],
    "wof:name":"Dufli Kabir Khan",
    "wof:placetype":"locality"
},
  "geometry": {"coordinates":[70.75714000000001,29.00986],"type":"Point"}
}