{
  "type": "Feature",
  "properties": {
    "gn:admin1_code":"5.0",
    "gn:asciiname":"Bhil jo Goth",
    "gn:country_code":"PK",
    "gn:dem":26,
    "gn:feature_class":"P",
    "gn:feature_code":"PPL",
    "gn:name":"Bhil jo Goth",
    "gn:population":0,
    "gn:timezone":"Asia/Karachi",
    "iso:country":"PK",
    "wof:name":"Bhil jo Goth",
    "wof:placetype":"locality"
},
  "geometry": {"coordinates":[70.70444999999999,24.52783],"type":"Point"}
}