{
  "type": "Feature",
  "properties": {
    "gn:admin1_code":"2.0",
    "gn:asciiname":"Marro",
    "gn:country_code":"PK",
    "gn:dem":1488,
    "gn:feature_class":"P",
    "gn:feature_code":"PPL",
    "gn:name":"Marro",
    "gn:population":0,
    "gn:timezone":"Asia/Karachi",
    "iso:country":"PK",
    "name:ceb_x_preferred":[
        "Torrente Marro"
    ],
    "wof:name":"Marro",
    "wof:placetype":"locality"
},
  "geometry": {"coordinates":[66.35419,28.01042],"type":"Point"}
}