{
  "type": "Feature",
  "properties": {
    "gn:admin1_code":"3.0",
    "gn:asciiname":"Haji Kalle",
    "gn:country_code":"PK",
    "gn:dem":327,
    "gn:feature_class":"P",
    "gn:feature_code":"PPL",
    "gn:name":"Haji Kalle",
    "gn:population":0,
    "gn:timezone":"Asia/Karachi",
    "iso:country":"PK",
    "name:eng_x_preferred":[
        "Kili H\u0101ji"
    ],
    "wof:name":"Haji Kalle",
    "wof:placetype":"locality"
},
  "geometry": {"coordinates":[71.73917,34.23427],"type":"Point"}
}