{
  "type": "Feature",
  "properties": {
    "gn:admin1_code":"6",
    "gn:asciiname":"Randiama ki Ker",
    "gn:country_code":"PK",
    "gn:dem":413,
    "gn:feature_class":"P",
    "gn:feature_code":"PPL",
    "gn:name":"Randiama ki Ker",
    "gn:population":0,
    "gn:timezone":"Asia/Karachi",
    "iso:country":"PK",
    "name:und_x_variant":[
        "Ranhi\u0101ma"
    ],
    "wof:name":"Randiama ki Ker",
    "wof:placetype":"locality"
},
  "geometry": {"coordinates":[74.06343000000003,33.0174],"type":"Point"}
}