{
  "type": "Feature",
  "properties": {
    "gn:admin1_code":"3.0",
    "gn:asciiname":"Chanda Khora",
    "gn:country_code":"PK",
    "gn:dem":838,
    "gn:feature_class":"P",
    "gn:feature_code":"PPL",
    "gn:name":"Chanda Khora",
    "gn:population":0,
    "gn:timezone":"Asia/Karachi",
    "iso:country":"PK",
    "name:eng_x_preferred":[
        "Chanda Khora"
    ],
    "wof:name":"Chanda Khora",
    "wof:placetype":"locality"
},
  "geometry": {"coordinates":[72.24868000000002,34.71623],"type":"Point"}
}