{
  "type": "Feature",
  "properties": {
    "gn:admin1_code":"04",
    "gn:asciiname":"Dhanda",
    "gn:country_code":"PK",
    "gn:dem":254,
    "gn:feature_class":"P",
    "gn:feature_code":"PPL",
    "gn:name":"Dhanda",
    "gn:population":0,
    "gn:timezone":"Asia/Karachi",
    "iso:country":"PK",
    "name:und_x_variant":[
        "Dhandal",
        "Tandal",
        "Dhanda"
    ],
    "wof:name":"Dhanda",
    "wof:placetype":"locality"
},
  "geometry": {"coordinates":[74.62834000000002,32.47375],"type":"Point"}
}