{
  "type": "Feature",
  "properties": {
    "gn:admin1_code":"2.0",
    "gn:asciiname":"Bahadur Bazar",
    "gn:country_code":"PK",
    "gn:dem":525,
    "gn:feature_class":"P",
    "gn:feature_code":"PPL",
    "gn:name":"Bahadur Bazar",
    "gn:population":0,
    "gn:timezone":"Asia/Karachi",
    "iso:country":"PK",
    "wof:name":"Bahadur Bazar",
    "wof:placetype":"locality"
},
  "geometry": {"coordinates":[63.03834000000001,26.24593],"type":"Point"}
}