{
  "type": "Feature",
  "properties": {
    "gn:admin1_code":"2",
    "gn:asciiname":"Mulla Majid",
    "gn:country_code":"PK",
    "gn:dem":1566,
    "gn:feature_class":"P",
    "gn:feature_code":"PPL",
    "gn:name":"Mulla Majid",
    "gn:population":0,
    "gn:timezone":"Asia/Karachi",
    "iso:country":"PK",
    "wof:name":"Mulla Majid",
    "wof:placetype":"locality"
},
  "geometry": {"coordinates":[68.28194000000001,30.76667],"type":"Point"}
}