{
  "type": "Feature",
  "properties": {
    "gn:admin1_code":"02",
    "gn:asciiname":"Goth Wazir Machhi",
    "gn:country_code":"PK",
    "gn:dem":117,
    "gn:feature_class":"P",
    "gn:feature_code":"PPL",
    "gn:name":"Goth Wazir Machhi",
    "gn:population":0,
    "gn:timezone":"Asia/Karachi",
    "iso:country":"PK",
    "name:und_x_variant":[
        "Wazir",
        "Goth M\u0101chhi Wazir",
        "Goth Wazir Machhi"
    ],
    "wof:name":"Goth Wazir Machhi",
    "wof:placetype":"locality"
},
  "geometry": {"coordinates":[68.11757,29.13371],"type":"Point"}
}