{
  "type": "Feature",
  "properties": {
    "gn:admin1_code":"2.0",
    "gn:asciiname":"Kili Ghulam Haider",
    "gn:country_code":"PK",
    "gn:dem":1785,
    "gn:feature_class":"P",
    "gn:feature_code":"PPL",
    "gn:name":"Kili Ghulam Haider",
    "gn:population":0,
    "gn:timezone":"Asia/Karachi",
    "iso:country":"PK",
    "wof:name":"Kili Ghulam Haider",
    "wof:placetype":"locality"
},
  "geometry": {"coordinates":[66.27996,29.11406],"type":"Point"}
}