{
  "type": "Feature",
  "properties": {
    "gn:admin1_code":"4",
    "gn:asciiname":"Qadru Chang",
    "gn:country_code":"PK",
    "gn:dem":94,
    "gn:feature_class":"P",
    "gn:feature_code":"PPL",
    "gn:name":"Qadru Chang",
    "gn:population":0,
    "gn:timezone":"Asia/Karachi",
    "iso:country":"PK",
    "wof:name":"Qadru Chang",
    "wof:placetype":"locality"
},
  "geometry": {"coordinates":[70.36944,29.27778],"type":"Point"}
}