{
  "type": "Feature",
  "properties": {
    "gn:admin1_code":"3.0",
    "gn:asciiname":"Karlan",
    "gn:country_code":"PK",
    "gn:dem":805,
    "gn:feature_class":"P",
    "gn:feature_code":"PPL",
    "gn:name":"Karlan",
    "gn:population":0,
    "gn:timezone":"Asia/Karachi",
    "iso:country":"PK",
    "wof:name":"Karlan",
    "wof:placetype":"locality"
},
  "geometry": {"coordinates":[73.08128000000001,34.11563],"type":"Point"}
}