{
  "type": "Feature",
  "properties": {
    "gn:admin1_code":"7.0",
    "gn:asciiname":"Chulung",
    "gn:country_code":"PK",
    "gn:dem":4306,
    "gn:feature_class":"P",
    "gn:feature_code":"PPL",
    "gn:name":"Chulung",
    "gn:population":0,
    "gn:timezone":"Asia/Karachi",
    "iso:country":"PK",
    "wof:name":"Chulung",
    "wof:placetype":"locality"
},
  "geometry": {"coordinates":[76.89113,35.09670999999999],"type":"Point"}
}