{
  "type": "Feature",
  "properties": {
    "gn:admin1_code":"4",
    "gn:asciiname":"Dudian",
    "gn:country_code":"PK",
    "gn:dem":476,
    "gn:feature_class":"P",
    "gn:feature_code":"PPL",
    "gn:name":"Dudian",
    "gn:population":0,
    "gn:timezone":"Asia/Karachi",
    "iso:country":"PK",
    "name:und_x_variant":[
        "Dudhi\u0101n"
    ],
    "wof:name":"Dudian",
    "wof:placetype":"locality"
},
  "geometry": {"coordinates":[73.29411999999998,33.1892],"type":"Point"}
}