{
  "type": "Feature",
  "properties": {
    "gn:admin1_code":"4.0",
    "gn:asciiname":"Kashmir Colony",
    "gn:country_code":"PK",
    "gn:dem":534,
    "gn:feature_class":"P",
    "gn:feature_code":"PPL",
    "gn:name":"Kashmir Colony",
    "gn:population":0,
    "gn:timezone":"Asia/Karachi",
    "iso:country":"PK",
    "name:eng_x_preferred":[
        "Kashmir Colony"
    ],
    "name:urd_x_preferred":[
        "\u06a9\u0634\u0645\u06cc\u0631 \u06a9\u0627\u0644\u0648\u0646\u06cc"
    ],
    "wof:name":"Kashmir Colony",
    "wof:placetype":"locality"
},
  "geometry": {"coordinates":[72.61366,33.40895],"type":"Point"}
}