{
  "type": "Feature",
  "properties": {
    "gn:admin1_code":"04",
    "gn:asciiname":"Pind Qammar",
    "gn:country_code":"PK",
    "gn:dem":205,
    "gn:feature_class":"P",
    "gn:feature_code":"PPL",
    "gn:name":"Pind Qammar",
    "gn:population":0,
    "gn:timezone":"Asia/Karachi",
    "iso:country":"PK",
    "name:und_x_variant":[
        "Qamar"
    ],
    "wof:name":"Pind Qammar",
    "wof:placetype":"locality"
},
  "geometry": {"coordinates":[73.11632,32.59384],"type":"Point"}
}