{
  "type": "Feature",
  "properties": {
    "gn:admin1_code":"03",
    "gn:asciiname":"Maini",
    "gn:country_code":"PK",
    "gn:dem":382,
    "gn:feature_class":"P",
    "gn:feature_code":"PPL",
    "gn:name":"Maini",
    "gn:population":0,
    "gn:timezone":"Asia/Karachi",
    "iso:country":"PK",
    "name:fas_x_preferred":[
        "\u0645\u0627\u0626\u0646\u06cc"
    ],
    "name:urd_x_preferred":[
        "\u0645\u0627\u0626\u0646\u06cc"
    ],
    "wof:name":"Maini",
    "wof:placetype":"locality"
},
  "geometry": {"coordinates":[72.60849,34.11758],"type":"Point"}
}