{
  "type": "Feature",
  "properties": {
    "gn:admin1_code":"3.0",
    "gn:asciiname":"Khwara Banda",
    "gn:country_code":"PK",
    "gn:dem":334,
    "gn:feature_class":"P",
    "gn:feature_code":"PPL",
    "gn:name":"Khwara Banda",
    "gn:population":0,
    "gn:timezone":"Asia/Karachi",
    "iso:country":"PK",
    "wof:name":"Khwara Banda",
    "wof:placetype":"locality"
},
  "geometry": {"coordinates":[72.19098000000002,34.1031],"type":"Point"}
}