{
  "type": "Feature",
  "properties": {
    "gn:admin1_code":"4",
    "gn:asciiname":"Qabulwala",
    "gn:country_code":"PK",
    "gn:dem":127,
    "gn:feature_class":"P",
    "gn:feature_code":"PPL",
    "gn:name":"Qab\u016blw\u0101la",
    "gn:population":0,
    "gn:timezone":"Asia/Karachi",
    "iso:country":"PK",
    "name:eng_x_preferred":[
        "Qab\u016blw\u0101la"
    ],
    "wof:name":"Qabulwala",
    "wof:placetype":"locality"
},
  "geometry": {"coordinates":[70.98848000000002,30.41479],"type":"Point"}
}