{
  "type": "Feature",
  "properties": {
    "gn:admin1_code":"4",
    "gn:asciiname":"Chak Two Hundred Forty Thal Development Authority",
    "gn:country_code":"PK",
    "gn:dem":158,
    "gn:feature_class":"P",
    "gn:feature_code":"PPL",
    "gn:name":"Chak Two Hundred Forty Thal Development Authority",
    "gn:population":0,
    "gn:timezone":"Asia/Karachi",
    "iso:country":"PK",
    "name:und_x_variant":[
        "Chak 240 TDA",
        "Chak Two Hundred Forty TDA",
        "Chak Two Hundred Forty Thal Development Authority"
    ],
    "wof:name":"Chak Two Hundred Forty Thal Development Authority",
    "wof:placetype":"locality"
},
  "geometry": {"coordinates":[71.24074,31.24265],"type":"Point"}
}