{
  "type": "Feature",
  "properties": {
    "gn:admin1_code":"4",
    "gn:asciiname":"Chak Ninety-five ML",
    "gn:country_code":"PK",
    "gn:dem":159,
    "gn:feature_class":"P",
    "gn:feature_code":"PPL",
    "gn:name":"Chak Ninety-five ML",
    "gn:population":0,
    "gn:timezone":"Asia/Karachi",
    "iso:country":"PK",
    "name:und_x_variant":[
        "Chak 95 ML"
    ],
    "wof:name":"Chak Ninety-five ML",
    "wof:placetype":"locality"
},
  "geometry": {"coordinates":[71.09560999999999,31.28163],"type":"Point"}
}