{
  "type": "Feature",
  "properties": {
    "gn:admin1_code":"2.0",
    "gn:asciiname":"Pir Bari",
    "gn:country_code":"PK",
    "gn:dem":1204,
    "gn:feature_class":"P",
    "gn:feature_code":"PPL",
    "gn:name":"Pir Bari",
    "gn:population":0,
    "gn:timezone":"Asia/Karachi",
    "iso:country":"PK",
    "wof:name":"Pir Bari",
    "wof:placetype":"locality"
},
  "geometry": {"coordinates":[67.16913000000001,27.57242],"type":"Point"}
}