{
  "type": "Feature",
  "properties": {
    "gn:admin1_code":"4",
    "gn:asciiname":"Dhupsari",
    "gn:country_code":"PK",
    "gn:dem":190,
    "gn:feature_class":"P",
    "gn:feature_code":"PPL",
    "gn:name":"Dhupsari",
    "gn:population":0,
    "gn:timezone":"Asia/Karachi",
    "iso:country":"PK",
    "name:und_x_variant":[
        "Khani\u0101na \u0100b\u0101di Chaudhri\u0101n"
    ],
    "wof:name":"Dhupsari",
    "wof:placetype":"locality"
},
  "geometry": {"coordinates":[74.19908000000002,30.87592],"type":"Point"}
}