{
  "type": "Feature",
  "properties": {
    "gn:admin1_code":"4",
    "gn:asciiname":"Garhuwala",
    "gn:country_code":"PK",
    "gn:dem":117,
    "gn:feature_class":"P",
    "gn:feature_code":"PPL",
    "gn:name":"Garhuwala",
    "gn:population":0,
    "gn:timezone":"Asia/Karachi",
    "iso:country":"PK",
    "wof:name":"Garhuwala",
    "wof:placetype":"locality"
},
  "geometry": {"coordinates":[70.69423,30.0104],"type":"Point"}
}