{
  "type": "Feature",
  "properties": {
    "gn:admin1_code":"6",
    "gn:asciiname":"Tallewali Mohri",
    "gn:country_code":"PK",
    "gn:dem":2598,
    "gn:feature_class":"P",
    "gn:feature_code":"PPL",
    "gn:name":"Tallewali Mohri",
    "gn:population":0,
    "gn:timezone":"Asia/Karachi",
    "iso:country":"PK",
    "wof:name":"Tallewali Mohri",
    "wof:placetype":"locality"
},
  "geometry": {"coordinates":[73.46844,34.55265],"type":"Point"}
}