{
  "type": "Feature",
  "properties": {
    "gn:admin1_code":"5",
    "gn:asciiname":"Hammanlo Goth",
    "gn:country_code":"PK",
    "gn:dem":55,
    "gn:feature_class":"P",
    "gn:feature_code":"PPL",
    "gn:name":"Hammanlo Goth",
    "gn:population":0,
    "gn:timezone":"Asia/Karachi",
    "iso:country":"PK",
    "name:und_x_variant":[
        "Hammanio Goth"
    ],
    "wof:name":"Hammanlo Goth",
    "wof:placetype":"locality"
},
  "geometry": {"coordinates":[68.89570000000001,27.55813],"type":"Point"}
}