{
  "type": "Feature",
  "properties": {
    "gn:admin1_code":"4",
    "gn:asciiname":"Loi",
    "gn:country_code":"PK",
    "gn:dem":784,
    "gn:feature_class":"P",
    "gn:feature_code":"PPL",
    "gn:name":"Loi",
    "gn:population":0,
    "gn:timezone":"Asia/Karachi",
    "iso:country":"PK",
    "wof:name":"Loi",
    "wof:placetype":"locality"
},
  "geometry": {"coordinates":[70.29430000000001,30.89905],"type":"Point"}
}