{
  "type": "Feature",
  "properties": {
    "gn:admin1_code":"2.0",
    "gn:asciiname":"Gharkai Kili",
    "gn:country_code":"PK",
    "gn:dem":1523,
    "gn:feature_class":"P",
    "gn:feature_code":"PPL",
    "gn:name":"Gharkai Kili",
    "gn:population":0,
    "gn:timezone":"Asia/Karachi",
    "iso:country":"PK",
    "wof:name":"Gharkai Kili",
    "wof:placetype":"locality"
},
  "geometry": {"coordinates":[68.80369,30.89484],"type":"Point"}
}