{
  "type": "Feature",
  "properties": {
    "gn:admin1_code":"2.0",
    "gn:asciiname":"Haji Wado",
    "gn:country_code":"PK",
    "gn:dem":17,
    "gn:feature_class":"P",
    "gn:feature_code":"PPL",
    "gn:name":"Haji Wado",
    "gn:population":0,
    "gn:timezone":"Asia/Karachi",
    "iso:country":"PK",
    "name:und_x_variant":[
        "H\u0101ji"
    ],
    "wof:name":"Haji Wado",
    "wof:placetype":"locality"
},
  "geometry": {"coordinates":[62.35623,25.28882],"type":"Point"}
}