{
  "type": "Feature",
  "properties": {
    "gn:admin1_code":"3",
    "gn:asciiname":"Chehl",
    "gn:country_code":"PK",
    "gn:dem":318,
    "gn:feature_class":"P",
    "gn:feature_code":"PPL",
    "gn:name":"Chehl",
    "gn:population":0,
    "gn:timezone":"Asia/Karachi",
    "iso:country":"PK",
    "name:eng_x_preferred":[
        "Chehl"
    ],
    "wof:name":"Chehl",
    "wof:placetype":"locality"
},
  "geometry": {"coordinates":[72.04923000000002,34.24404000000001],"type":"Point"}
}