{
  "type": "Feature",
  "properties": {
    "gn:admin1_code":"6",
    "gn:asciiname":"Saral",
    "gn:country_code":"PK",
    "gn:dem":612,
    "gn:feature_class":"P",
    "gn:feature_code":"PPL",
    "gn:name":"Saral",
    "gn:population":0,
    "gn:timezone":"Asia/Karachi",
    "iso:country":"PK",
    "name:aze_x_preferred":[
        "Saral"
    ],
    "name:fas_x_preferred":[
        "\u0633\u0627\u0631\u0627\u0644"
    ],
    "name:fra_x_preferred":[
        "Saral"
    ],
    "name:und_x_variant":[
        "Sarai"
    ],
    "wof:name":"Saral",
    "wof:placetype":"locality"
},
  "geometry": {"coordinates":[74.16504,33.07397],"type":"Point"}
}