{
  "type": "Feature",
  "properties": {
    "gn:admin1_code":"4",
    "gn:asciiname":"Chak Eighty-one ML",
    "gn:country_code":"PK",
    "gn:dem":165,
    "gn:feature_class":"P",
    "gn:feature_code":"PPL",
    "gn:name":"Chak Eighty-one ML",
    "gn:population":0,
    "gn:timezone":"Asia/Karachi",
    "iso:country":"PK",
    "name:und_x_variant":[
        "Chak 81 ML"
    ],
    "wof:name":"Chak Eighty-one ML",
    "wof:placetype":"locality"
},
  "geometry": {"coordinates":[71.03196,31.3922],"type":"Point"}
}