{
  "type": "Feature",
  "properties": {
    "gn:admin1_code":"04",
    "gn:asciiname":"Butt Kot",
    "gn:country_code":"PK",
    "gn:dem":133,
    "gn:feature_class":"P",
    "gn:feature_code":"PPL",
    "gn:name":"Butt Kot",
    "gn:population":0,
    "gn:timezone":"Asia/Karachi",
    "iso:country":"PK",
    "name:und_x_variant":[
        "Kot Bhutta"
    ],
    "wof:name":"Butt Kot",
    "wof:placetype":"locality"
},
  "geometry": {"coordinates":[71.81643000000003,30.44069],"type":"Point"}
}