{
  "type": "Feature",
  "properties": {
    "gn:admin1_code":"2",
    "gn:asciiname":"Goth Subhan",
    "gn:country_code":"PK",
    "gn:dem":47,
    "gn:feature_class":"P",
    "gn:feature_code":"PPL",
    "gn:name":"Goth Subhan",
    "gn:population":0,
    "gn:timezone":"Asia/Karachi",
    "iso:country":"PK",
    "name:eng_x_preferred":[
        "Subh\u0101n Goth"
    ],
    "wof:name":"Goth Subhan",
    "wof:placetype":"locality"
},
  "geometry": {"coordinates":[66.68924,25.65714],"type":"Point"}
}