{
  "type": "Feature",
  "properties": {
    "gn:admin1_code":"7.0",
    "gn:asciiname":"Mishekin",
    "gn:country_code":"PK",
    "gn:dem":3299,
    "gn:feature_class":"P",
    "gn:feature_code":"PPL",
    "gn:name":"Mishekin",
    "gn:population":0,
    "gn:timezone":"Asia/Karachi",
    "iso:country":"PK",
    "wof:name":"Mishekin",
    "wof:placetype":"locality"
},
  "geometry": {"coordinates":[74.74550000000001,35.5894],"type":"Point"}
}