{
  "type": "Feature",
  "properties": {
    "gn:admin1_code":"4",
    "gn:asciiname":"Chak Twenty-six Panjnad",
    "gn:country_code":"PK",
    "gn:dem":86,
    "gn:feature_class":"P",
    "gn:feature_code":"PPL",
    "gn:name":"Chak Twenty-six Panjnad",
    "gn:population":0,
    "gn:timezone":"Asia/Karachi",
    "iso:country":"PK",
    "name:und_x_variant":[
        "Chak Twenty-six P"
    ],
    "wof:name":"Chak Twenty-six Panjnad",
    "wof:placetype":"locality"
},
  "geometry": {"coordinates":[70.63474000000002,28.51278],"type":"Point"}
}