{
  "type": "Feature",
  "properties": {
    "gn:admin1_code":"5.0",
    "gn:asciiname":"Baledai",
    "gn:country_code":"PK",
    "gn:dem":46,
    "gn:feature_class":"P",
    "gn:feature_code":"PPL",
    "gn:name":"Baledai",
    "gn:population":0,
    "gn:timezone":"Asia/Karachi",
    "iso:country":"PK",
    "name:und_x_variant":[
        "Baled\u0101i"
    ],
    "wof:name":"Baledai",
    "wof:placetype":"locality"
},
  "geometry": {"coordinates":[67.81811,27.28962000000001],"type":"Point"}
}