{
  "type": "Feature",
  "properties": {
    "gn:admin1_code":"2",
    "gn:asciiname":"Chakarkheli",
    "gn:country_code":"PK",
    "gn:dem":1726,
    "gn:feature_class":"P",
    "gn:feature_code":"PPL",
    "gn:name":"Chakarkheli",
    "gn:population":0,
    "gn:timezone":"Asia/Karachi",
    "iso:country":"PK",
    "wof:name":"Chakarkheli",
    "wof:placetype":"locality"
},
  "geometry": {"coordinates":[66.57061999999999,29.50284000000001],"type":"Point"}
}