{
  "type": "Feature",
  "properties": {
    "gn:admin1_code":"3",
    "gn:asciiname":"Kuz Ghazni",
    "gn:country_code":"PK",
    "gn:dem":2295,
    "gn:feature_class":"P",
    "gn:feature_code":"PPL",
    "gn:name":"Kuz Ghazni",
    "gn:population":0,
    "gn:timezone":"Asia/Karachi",
    "iso:country":"PK",
    "name:und_x_variant":[
        "Kuz Ghuz\u0101n"
    ],
    "wof:name":"Kuz Ghazni",
    "wof:placetype":"locality"
},
  "geometry": {"coordinates":[72.51300000000001,34.73004],"type":"Point"}
}