{
  "type": "Feature",
  "properties": {
    "gn:admin1_code":"3.0",
    "gn:asciiname":"Dakorak",
    "gn:country_code":"PK",
    "gn:dem":1036,
    "gn:feature_class":"P",
    "gn:feature_code":"PPL",
    "gn:name":"Dakorak",
    "gn:population":0,
    "gn:timezone":"Asia/Karachi",
    "iso:country":"PK",
    "wof:name":"Dakorak",
    "wof:placetype":"locality"
},
  "geometry": {"coordinates":[72.43765,34.86057],"type":"Point"}
}