{
  "type": "Feature",
  "properties": {
    "gn:admin1_code":"5",
    "gn:asciiname":"Goth Jan Muhammad Dehr",
    "gn:country_code":"PK",
    "gn:dem":75,
    "gn:feature_class":"P",
    "gn:feature_code":"PPL",
    "gn:name":"Goth Jan Muhammad Dehr",
    "gn:population":0,
    "gn:timezone":"Asia/Karachi",
    "iso:country":"PK",
    "name:und_x_variant":[
        "Goth J\u0101n Muhammad"
    ],
    "wof:name":"Goth Jan Muhammad Dehr",
    "wof:placetype":"locality"
},
  "geometry": {"coordinates":[69.56699,28.14413],"type":"Point"}
}