{
  "type": "Feature",
  "properties": {
    "gn:admin1_code":"4.0",
    "gn:asciiname":"Basti Thadawala",
    "gn:country_code":"PK",
    "gn:dem":114,
    "gn:feature_class":"P",
    "gn:feature_code":"PPL",
    "gn:name":"Basti Thadawala",
    "gn:population":0,
    "gn:timezone":"Asia/Karachi",
    "iso:country":"PK",
    "name:und_x_variant":[
        "Allw\u0101la"
    ],
    "wof:name":"Basti Thadawala",
    "wof:placetype":"locality"
},
  "geometry": {"coordinates":[71.1623,29.95473],"type":"Point"}
}