{
  "type": "Feature",
  "properties": {
    "gn:admin1_code":"04",
    "gn:asciiname":"Thatta Qutba",
    "gn:country_code":"PK",
    "gn:dem":212,
    "gn:feature_class":"P",
    "gn:feature_code":"PPL",
    "gn:name":"Thatta Qutba",
    "gn:population":0,
    "gn:timezone":"Asia/Karachi",
    "iso:country":"PK",
    "name:und_x_variant":[
        "Thatta Kutba",
        "Thatta Qutba"
    ],
    "wof:name":"Thatta Qutba",
    "wof:placetype":"locality"
},
  "geometry": {"coordinates":[73.82939,32.10738],"type":"Point"}
}