{
  "type": "Feature",
  "properties": {
    "gn:admin1_code":"4.0",
    "gn:asciiname":"Dera Tahir Baluch",
    "gn:country_code":"PK",
    "gn:dem":184,
    "gn:feature_class":"P",
    "gn:feature_code":"PPL",
    "gn:name":"Dera Tahir Baluch",
    "gn:population":0,
    "gn:timezone":"Asia/Karachi",
    "iso:country":"PK",
    "name:und_x_variant":[
        "Tahirw\u0101la"
    ],
    "wof:name":"Dera Tahir Baluch",
    "wof:placetype":"locality"
},
  "geometry": {"coordinates":[72.04519000000001,31.77592000000001],"type":"Point"}
}