{
  "type": "Feature",
  "properties": {
    "gn:admin1_code":"4",
    "gn:asciiname":"Bostiwala",
    "gn:country_code":"PK",
    "gn:dem":171,
    "gn:feature_class":"P",
    "gn:feature_code":"PPL",
    "gn:name":"Bostiwala",
    "gn:population":0,
    "gn:timezone":"Asia/Karachi",
    "iso:country":"PK",
    "name:und_x_variant":[
        "Chhatt\u012bw\u0101la"
    ],
    "wof:name":"Bostiwala",
    "wof:placetype":"locality"
},
  "geometry": {"coordinates":[72.56019000000001,31.70168],"type":"Point"}
}