{
  "type": "Feature",
  "properties": {
    "gn:admin1_code":"4",
    "gn:asciiname":"Charaghdinwala",
    "gn:country_code":"PK",
    "gn:dem":199,
    "gn:feature_class":"P",
    "gn:feature_code":"PPL",
    "gn:name":"Charaghdinwala",
    "gn:population":0,
    "gn:timezone":"Asia/Karachi",
    "iso:country":"PK",
    "name:und_x_variant":[
        "Chir\u0101ghuddinw\u0101la"
    ],
    "wof:name":"Charaghdinwala",
    "wof:placetype":"locality"
},
  "geometry": {"coordinates":[74.24321999999999,31.10267],"type":"Point"}
}