{
  "type": "Feature",
  "properties": {
    "gn:admin1_code":"4.0",
    "gn:asciiname":"Chak Ghakkar",
    "gn:country_code":"PK",
    "gn:dem":519,
    "gn:feature_class":"P",
    "gn:feature_code":"PPL",
    "gn:name":"Chak Ghakkar",
    "gn:population":0,
    "gn:timezone":"Asia/Karachi",
    "iso:country":"PK",
    "name:und_x_variant":[
        "Chak Gakhar",
        "Chak Ghakkar"
    ],
    "wof:name":"Chak Ghakkar",
    "wof:placetype":"locality"
},
  "geometry": {"coordinates":[72.81947,33.00066],"type":"Point"}
}