{
  "type": "Feature",
  "properties": {
    "gn:admin1_code":"5",
    "gn:asciiname":"Sachu Sarki",
    "gn:country_code":"PK",
    "gn:dem":65,
    "gn:feature_class":"P",
    "gn:feature_code":"PPL",
    "gn:name":"Sachu Sarki",
    "gn:population":0,
    "gn:timezone":"Asia/Karachi",
    "iso:country":"PK",
    "wof:name":"Sachu Sarki",
    "wof:placetype":"locality"
},
  "geometry": {"coordinates":[68.58861999999999,28.21349],"type":"Point"}
}