{
  "type": "Feature",
  "properties": {
    "gn:admin1_code":"2.0",
    "gn:asciiname":"Pir Bakhsh",
    "gn:country_code":"PK",
    "gn:dem":2003,
    "gn:feature_class":"P",
    "gn:feature_code":"PPL",
    "gn:name":"Pir Bakhsh",
    "gn:population":0,
    "gn:timezone":"Asia/Karachi",
    "iso:country":"PK",
    "wof:name":"Pir Bakhsh",
    "wof:placetype":"locality"
},
  "geometry": {"coordinates":[66.226,28.8038],"type":"Point"}
}