{
  "type": "Feature",
  "properties": {
    "gn:admin1_code":"5",
    "gn:asciiname":"Rang",
    "gn:country_code":"PK",
    "gn:dem":37,
    "gn:feature_class":"P",
    "gn:feature_code":"PPL",
    "gn:name":"Rang",
    "gn:population":0,
    "gn:timezone":"Asia/Karachi",
    "iso:country":"PK",
    "wof:name":"Rang",
    "wof:placetype":"locality"
},
  "geometry": {"coordinates":[67.67551999999999,26.53703],"type":"Point"}
}