{
  "type": "Feature",
  "properties": {
    "gn:admin1_code":"3.0",
    "gn:asciiname":"Mairakr",
    "gn:country_code":"PK",
    "gn:dem":374,
    "gn:feature_class":"P",
    "gn:feature_code":"PPL",
    "gn:name":"Mairakr",
    "gn:population":0,
    "gn:timezone":"Asia/Karachi",
    "iso:country":"PK",
    "name:eng_x_preferred":[
        "Mairakr"
    ],
    "wof:name":"Mairakr",
    "wof:placetype":"locality"
},
  "geometry": {"coordinates":[72.06528,34.34056],"type":"Point"}
}