{
  "type": "Feature",
  "properties": {
    "gn:admin1_code":"5",
    "gn:asciiname":"Machar Gahu",
    "gn:country_code":"PK",
    "gn:dem":19,
    "gn:feature_class":"P",
    "gn:feature_code":"PPL",
    "gn:name":"Machar Gahu",
    "gn:population":0,
    "gn:timezone":"Asia/Karachi",
    "iso:country":"PK",
    "name:und_x_variant":[
        "Mochar G\u0101hu"
    ],
    "wof:name":"Machar Gahu",
    "wof:placetype":"locality"
},
  "geometry": {"coordinates":[69.14105000000001,25.83894],"type":"Point"}
}