{
  "type": "Feature",
  "properties": {
    "gn:admin1_code":"4.0",
    "gn:asciiname":"Kartarpur",
    "gn:country_code":"PK",
    "gn:dem":178,
    "gn:feature_class":"P",
    "gn:feature_code":"PPL",
    "gn:name":"Kart\u0101rpur",
    "gn:population":0,
    "gn:timezone":"Asia/Karachi",
    "iso:country":"PK",
    "name:fra_x_preferred":[
        "Kartarpur"
    ],
    "wof:name":"Kartarpur",
    "wof:placetype":"locality"
},
  "geometry": {"coordinates":[72.98333000000002,31.15],"type":"Point"}
}