{
  "type": "Feature",
  "properties": {
    "gn:admin1_code":"4.0",
    "gn:asciiname":"Gil",
    "gn:country_code":"PK",
    "gn:dem":236,
    "gn:feature_class":"P",
    "gn:feature_code":"PPL",
    "gn:name":"Gil",
    "gn:population":0,
    "gn:timezone":"Asia/Karachi",
    "iso:country":"PK",
    "name:ast_x_preferred":[
        "Gil"
    ],
    "name:cat_x_preferred":[
        "Gil"
    ],
    "name:ceb_x_preferred":[
        "Gil"
    ],
    "name:fin_x_preferred":[
        "Gil"
    ],
    "name:fra_x_preferred":[
        "Gil"
    ],
    "name:nld_x_preferred":[
        "Gil"
    ],
    "name:pol_x_preferred":[
        "Gil"
    ],
    "name:rus_x_preferred":[
        "\u0413\u0438\u043b\u044c"
    ],
    "name:spa_x_preferred":[
        "Gil"
    ],
    "name:swe_x_preferred":[
        "Gil"
    ],
    "name:ukr_x_preferred":[
        "\u0413\u0456\u043b\u044c"
    ],
    "wof:name":"Gil",
    "wof:placetype":"locality"
},
  "geometry": {"coordinates":[74.80627,32.10681],"type":"Point"}
}