{
  "type": "Feature",
  "properties": {
    "gn:admin1_code":"4.0",
    "gn:asciiname":"Gil",
    "gn:country_code":"PK",
    "gn:dem":236,
    "gn:feature_class":"P",
    "gn:feature_code":"PPL",
    "gn:name":"Gil",
    "gn:population":0,
    "gn:timezone":"Asia/Karachi",
    "iso:country":"PK",
    "wof:name":"Gil",
    "wof:placetype":"locality"
},
  "geometry": {"coordinates":[74.80627,32.10681],"type":"Point"}
}