{
  "type": "Feature",
  "properties": {
    "gn:admin1_code":"4.0",
    "gn:asciiname":"Basti Rasul Bakhsh",
    "gn:country_code":"PK",
    "gn:dem":84,
    "gn:feature_class":"P",
    "gn:feature_code":"PPL",
    "gn:name":"Basti Ras\u016bl Bakhsh",
    "gn:population":0,
    "gn:timezone":"Asia/Karachi",
    "iso:country":"PK",
    "wof:name":"Basti Rasul Bakhsh",
    "wof:placetype":"locality"
},
  "geometry": {"coordinates":[70.39721999999998,28.83611],"type":"Point"}
}