{
  "type": "Feature",
  "properties": {
    "gn:admin1_code":"4.0",
    "gn:asciiname":"Jind Pannu",
    "gn:country_code":"PK",
    "gn:dem":238,
    "gn:feature_class":"P",
    "gn:feature_code":"PPL",
    "gn:name":"Jind Pannu",
    "gn:population":0,
    "gn:timezone":"Asia/Karachi",
    "iso:country":"PK",
    "wof:name":"Jind Pannu",
    "wof:placetype":"locality"
},
  "geometry": {"coordinates":[74.75878,32.15963],"type":"Point"}
}