{
  "type": "Feature",
  "properties": {
    "gn:admin1_code":"4.0",
    "gn:asciiname":"Gujar Kotla",
    "gn:country_code":"PK",
    "gn:dem":279,
    "gn:feature_class":"P",
    "gn:feature_code":"PPL",
    "gn:name":"Gujar Kotla",
    "gn:population":0,
    "gn:timezone":"Asia/Karachi",
    "iso:country":"PK",
    "name:und_x_variant":[
        "Gojar Kotla",
        "Gujar Kotla"
    ],
    "wof:name":"Gujar Kotla",
    "wof:placetype":"locality"
},
  "geometry": {"coordinates":[73.99285999999999,32.8226],"type":"Point"}
}