{
  "type": "Feature",
  "properties": {
    "gn:admin1_code":"4.0",
    "gn:asciiname":"Amir Sangranwali Bhaini",
    "gn:country_code":"PK",
    "gn:dem":183,
    "gn:feature_class":"P",
    "gn:feature_code":"PPL",
    "gn:name":"Amir Sangranwali Bhaini",
    "gn:population":0,
    "gn:timezone":"Asia/Karachi",
    "iso:country":"PK",
    "wof:name":"Amir Sangranwali Bhaini",
    "wof:placetype":"locality"
},
  "geometry": {"coordinates":[74.05901,30.59041],"type":"Point"}
}