{
  "type": "Feature",
  "properties": {
    "gn:admin1_code":"4",
    "gn:asciiname":"Thatti Bakhsh Shan",
    "gn:country_code":"PK",
    "gn:dem":168,
    "gn:feature_class":"P",
    "gn:feature_code":"PPL",
    "gn:name":"Thatti Bakhsh Shan",
    "gn:population":0,
    "gn:timezone":"Asia/Karachi",
    "iso:country":"PK",
    "name:und_x_variant":[
        "Thatti Baksh Shan",
        "Thathi Bakhsh Sh\u0101h"
    ],
    "wof:name":"Thatti Bakhsh Shan",
    "wof:placetype":"locality"
},
  "geometry": {"coordinates":[72.21597,31.83483],"type":"Point"}
}