{
  "type": "Feature",
  "properties": {
    "gn:admin1_code":"5",
    "gn:asciiname":"Goth Abdullah",
    "gn:country_code":"PK",
    "gn:dem":34,
    "gn:feature_class":"P",
    "gn:feature_code":"PPL",
    "gn:name":"Goth Abdullah",
    "gn:population":0,
    "gn:timezone":"Asia/Karachi",
    "iso:country":"PK",
    "wof:name":"Goth Abdullah",
    "wof:placetype":"locality"
},
  "geometry": {"coordinates":[68.17220999999999,26.14698],"type":"Point"}
}