{
  "type": "Feature",
  "properties": {
    "gn:admin1_code":"04",
    "gn:asciiname":"Tatral Kalan",
    "gn:country_code":"PK",
    "gn:dem":363,
    "gn:feature_class":"P",
    "gn:feature_code":"PPL",
    "gn:name":"Tatral Kalan",
    "gn:population":0,
    "gn:timezone":"Asia/Karachi",
    "iso:country":"PK",
    "wof:name":"Tatral Kalan",
    "wof:placetype":"locality"
},
  "geometry": {"coordinates":[72.85191999999998,33.32241],"type":"Point"}
}