{
  "type": "Feature",
  "properties": {
    "gn:admin1_code":"3.0",
    "gn:asciiname":"Lamba Nakka",
    "gn:country_code":"PK",
    "gn:dem":3375,
    "gn:feature_class":"P",
    "gn:feature_code":"PPL",
    "gn:name":"Lamba Nakka",
    "gn:population":0,
    "gn:timezone":"Asia/Karachi",
    "iso:country":"PK",
    "wof:name":"Lamba Nakka",
    "wof:placetype":"locality"
},
  "geometry": {"coordinates":[73.59975,34.83912],"type":"Point"}
}