{
  "type": "Feature",
  "properties": {
    "gn:admin1_code":"3.0",
    "gn:asciiname":"Mir Alam Manjiwala",
    "gn:country_code":"PK",
    "gn:dem":278,
    "gn:feature_class":"P",
    "gn:feature_code":"PPL",
    "gn:name":"Mir Alam Manjiwala",
    "gn:population":0,
    "gn:timezone":"Asia/Karachi",
    "iso:country":"PK",
    "name:und_x_variant":[
        "Mir \u0100lam",
        "M\u012br \u0100lam Manj\u012bw\u0101la",
        "Mir Alam Manjiwala"
    ],
    "wof:name":"Mir Alam Manjiwala",
    "wof:placetype":"locality"
},
  "geometry": {"coordinates":[70.83914,32.73514],"type":"Point"}
}