{
  "type": "Feature",
  "properties": {
    "gn:admin1_code":"04",
    "gn:asciiname":"Nurpur",
    "gn:country_code":"PK",
    "gn:dem":277,
    "gn:feature_class":"P",
    "gn:feature_code":"PPL",
    "gn:name":"Nurpur",
    "gn:population":0,
    "gn:timezone":"Asia/Karachi",
    "iso:country":"PK",
    "wof:name":"Nurpur",
    "wof:placetype":"locality"
},
  "geometry": {"coordinates":[73.41826,32.7704],"type":"Point"}
}