{
  "type": "Feature",
  "properties": {
    "gn:admin1_code":"2.0",
    "gn:asciiname":"Mari Kan",
    "gn:country_code":"PK",
    "gn:dem":280,
    "gn:feature_class":"P",
    "gn:feature_code":"PPL",
    "gn:name":"Mari Kan",
    "gn:population":0,
    "gn:timezone":"Asia/Karachi",
    "iso:country":"PK",
    "wof:name":"Mari Kan",
    "wof:placetype":"locality"
},
  "geometry": {"coordinates":[63.39536,26.0378],"type":"Point"}
}