{
  "type": "Feature",
  "properties": {
    "gn:admin1_code":"2.0",
    "gn:asciiname":"Haji Muhammad Qalandari",
    "gn:country_code":"PK",
    "gn:dem":659,
    "gn:feature_class":"P",
    "gn:feature_code":"PPL",
    "gn:name":"Haji Muhammad Qalandari",
    "gn:population":0,
    "gn:timezone":"Asia/Karachi",
    "iso:country":"PK",
    "wof:name":"Haji Muhammad Qalandari",
    "wof:placetype":"locality"
},
  "geometry": {"coordinates":[66.80654,26.60784],"type":"Point"}
}