{
  "type": "Feature",
  "properties": {
    "gn:admin1_code":"7.0",
    "gn:asciiname":"Kanch",
    "gn:country_code":"PK",
    "gn:dem":1863,
    "gn:feature_class":"P",
    "gn:feature_code":"PPL",
    "gn:name":"Kanch",
    "gn:population":0,
    "gn:timezone":"Asia/Karachi",
    "iso:country":"PK",
    "wof:name":"Kanch",
    "wof:placetype":"locality"
},
  "geometry": {"coordinates":[73.80579,36.17648],"type":"Point"}
}