{
  "type": "Feature",
  "properties": {
    "gn:admin1_code":"7.0",
    "gn:asciiname":"Kanch",
    "gn:country_code":"PK",
    "gn:dem":1863,
    "gn:feature_class":"P",
    "gn:feature_code":"PPL",
    "gn:name":"Kanch",
    "gn:population":0,
    "gn:timezone":"Asia/Karachi",
    "iso:country":"PK",
    "name:ara_x_preferred":[
        "\u0643\u0627\u0646\u062a\u0634"
    ],
    "name:fas_x_preferred":[
        "\u06a9\u0627\u0646\u0686"
    ],
    "name:fra_x_preferred":[
        "Kanch"
    ],
    "name:hye_x_preferred":[
        "\u053f\u0561\u0576\u0579"
    ],
    "name:ita_x_preferred":[
        "Kanch"
    ],
    "name:kat_x_preferred":[
        "\u10d9\u10d0\u10dc\u10e9\u10d8"
    ],
    "name:msa_x_preferred":[
        "Gyalto"
    ],
    "name:spa_x_preferred":[
        "Kanch"
    ],
    "name:ukr_x_preferred":[
        "\u041a\u0430\u043d\u0447"
    ],
    "name:vie_x_preferred":[
        "Kanch"
    ],
    "wof:name":"Kanch",
    "wof:placetype":"locality"
},
  "geometry": {"coordinates":[73.80579,36.17648],"type":"Point"}
}