{
  "type": "Feature",
  "properties": {
    "gn:admin1_code":"04",
    "gn:asciiname":"Pira Jangla",
    "gn:country_code":"PK",
    "gn:dem":429,
    "gn:feature_class":"P",
    "gn:feature_code":"PPL",
    "gn:name":"Pira Jangla",
    "gn:population":0,
    "gn:timezone":"Asia/Karachi",
    "iso:country":"PK",
    "name:und_x_variant":[
        "Pihra Jangla",
        "Pira Jangla"
    ],
    "wof:name":"Pira Jangla",
    "wof:placetype":"locality"
},
  "geometry": {"coordinates":[72.45649,32.98992],"type":"Point"}
}