{
  "type": "Feature",
  "properties": {
    "gn:admin1_code":"2.0",
    "gn:asciiname":"Gul Muhammad Kili",
    "gn:country_code":"PK",
    "gn:dem":1157,
    "gn:feature_class":"P",
    "gn:feature_code":"PPL",
    "gn:name":"Gul Muhammad Kili",
    "gn:population":0,
    "gn:timezone":"Asia/Karachi",
    "iso:country":"PK",
    "wof:name":"Gul Muhammad Kili",
    "wof:placetype":"locality"
},
  "geometry": {"coordinates":[63.8187,29.11402],"type":"Point"}
}