{
  "type": "Feature",
  "properties": {
    "gn:admin1_code":"04",
    "gn:asciiname":"Wan Dil Singh",
    "gn:country_code":"PK",
    "gn:dem":162,
    "gn:feature_class":"P",
    "gn:feature_code":"PPL",
    "gn:name":"Wan Dil Singh",
    "gn:population":0,
    "gn:timezone":"Asia/Karachi",
    "iso:country":"PK",
    "name:und_x_variant":[
        "W\u0101n Dal Singh"
    ],
    "wof:name":"Wan Dil Singh",
    "wof:placetype":"locality"
},
  "geometry": {"coordinates":[73.29678,30.40443],"type":"Point"}
}