{
  "type": "Feature",
  "properties": {
    "gn:admin1_code":"2.0",
    "gn:asciiname":"Nasir Chah",
    "gn:country_code":"PK",
    "gn:dem":1472,
    "gn:feature_class":"P",
    "gn:feature_code":"PPL",
    "gn:name":"Nasir Chah",
    "gn:population":0,
    "gn:timezone":"Asia/Karachi",
    "iso:country":"PK",
    "name:und_x_variant":[
        "Nazar Tsah"
    ],
    "wof:name":"Nasir Chah",
    "wof:placetype":"locality"
},
  "geometry": {"coordinates":[69.88790999999999,30.55469],"type":"Point"}
}