{
  "type": "Feature",
  "properties": {
    "gn:admin1_code":"7.0",
    "gn:asciiname":"Boqpal",
    "gn:country_code":"PK",
    "gn:dem":2235,
    "gn:feature_class":"P",
    "gn:feature_code":"PPL",
    "gn:name":"Boqpal",
    "gn:population":0,
    "gn:timezone":"Asia/Karachi",
    "iso:country":"PK",
    "wof:name":"Boqpal",
    "wof:placetype":"locality"
},
  "geometry": {"coordinates":[75.46009000000002,35.42097000000001],"type":"Point"}
}