{
  "type": "Feature",
  "properties": {
    "gn:admin1_code":"5",
    "gn:asciiname":"Jinde Shah",
    "gn:country_code":"PK",
    "gn:dem":57,
    "gn:feature_class":"P",
    "gn:feature_code":"PPL",
    "gn:name":"Jinde Shah",
    "gn:population":0,
    "gn:timezone":"Asia/Karachi",
    "iso:country":"PK",
    "name:und_x_variant":[
        "J\u012bndel Sh\u0101h"
    ],
    "wof:name":"Jinde Shah",
    "wof:placetype":"locality"
},
  "geometry": {"coordinates":[69.0072,27.59143],"type":"Point"}
}