{
  "type": "Feature",
  "properties": {
    "gn:admin1_code":"4",
    "gn:asciiname":"Chak One Hundred Forty-one Southern Branch",
    "gn:country_code":"PK",
    "gn:dem":182,
    "gn:feature_class":"P",
    "gn:feature_code":"PPL",
    "gn:name":"Chak One Hundred Forty-one Southern Branch",
    "gn:population":0,
    "gn:timezone":"Asia/Karachi",
    "iso:country":"PK",
    "name:und_x_variant":[
        "Chak One Hundred Forty-one SB",
        "Andhera"
    ],
    "wof:name":"Chak One Hundred Forty-one Southern Branch",
    "wof:placetype":"locality"
},
  "geometry": {"coordinates":[72.56206999999998,31.78536],"type":"Point"}
}