{
  "type": "Feature",
  "properties": {
    "gn:admin1_code":"6",
    "gn:asciiname":"Dariyar",
    "gn:country_code":"PK",
    "gn:dem":406,
    "gn:feature_class":"P",
    "gn:feature_code":"PPL",
    "gn:name":"Dariyar",
    "gn:population":0,
    "gn:timezone":"Asia/Karachi",
    "iso:country":"PK",
    "name:und_x_variant":[
        "Dariy\u0101n"
    ],
    "wof:name":"Dariyar",
    "wof:placetype":"locality"
},
  "geometry": {"coordinates":[74.03431999999999,33.03572],"type":"Point"}
}