{
  "type": "Feature",
  "properties": {
    "gn:admin1_code":"5.0",
    "gn:asciiname":"Pandhi Khan Rind",
    "gn:country_code":"PK",
    "gn:dem":37,
    "gn:feature_class":"P",
    "gn:feature_code":"PPL",
    "gn:name":"Pandhi Khan Rind",
    "gn:population":0,
    "gn:timezone":"Asia/Karachi",
    "iso:country":"PK",
    "wof:name":"Pandhi Khan Rind",
    "wof:placetype":"locality"
},
  "geometry": {"coordinates":[68.25649,26.34063],"type":"Point"}
}