{
  "type": "Feature",
  "properties": {
    "gn:admin1_code":"5.0",
    "gn:asciiname":"Shah Muhammad Makrani",
    "gn:country_code":"PK",
    "gn:dem":20,
    "gn:feature_class":"P",
    "gn:feature_code":"PPL",
    "gn:name":"Shah Muhammad Makrani",
    "gn:population":0,
    "gn:timezone":"Asia/Karachi",
    "iso:country":"PK",
    "wof:name":"Shah Muhammad Makrani",
    "wof:placetype":"locality"
},
  "geometry": {"coordinates":[68.94708,25.83649],"type":"Point"}
}