{
  "type": "Feature",
  "properties": {
    "gn:admin1_code":"5.0",
    "gn:asciiname":"Darkhan",
    "gn:cc2":"PK",
    "gn:country_code":"PK",
    "gn:dem":66,
    "gn:feature_class":"P",
    "gn:feature_code":"PPL",
    "gn:name":"Darkhan",
    "gn:population":0,
    "gn:timezone":"Asia/Karachi",
    "iso:country":"PK",
    "name:ceb_x_preferred":[
        "Darkhan"
    ],
    "name:fra_x_preferred":[
        "Darkhan"
    ],
    "name:sco_x_preferred":[
        "Darkhan"
    ],
    "name:swe_x_preferred":[
        "Darkhan"
    ],
    "name:und_x_variant":[
        "Dakhan",
        "Darkhan"
    ],
    "wof:name":"Darkhan",
    "wof:placetype":"locality"
},
  "geometry": {"coordinates":[68.65000000000001,27.98333],"type":"Point"}
}