{
  "type": "Feature",
  "properties": {
    "gn:admin1_code":"5.0",
    "gn:asciiname":"Goth Murshadabad",
    "gn:country_code":"PK",
    "gn:dem":65,
    "gn:feature_class":"P",
    "gn:feature_code":"PPL",
    "gn:name":"Goth Murshadabad",
    "gn:population":0,
    "gn:timezone":"Asia/Karachi",
    "iso:country":"PK",
    "name:eng_x_preferred":[
        "Goth Murshadabad"
    ],
    "wof:name":"Goth Murshadabad",
    "wof:placetype":"locality"
},
  "geometry": {"coordinates":[68.67256999999999,27.98596],"type":"Point"}
}