{
  "type": "Feature",
  "properties": {
    "gn:admin1_code":"4.0",
    "gn:asciiname":"Chak Two Hundred Twenty-nine Thal Development Authority",
    "gn:country_code":"PK",
    "gn:dem":156,
    "gn:feature_class":"P",
    "gn:feature_code":"PPL",
    "gn:name":"Chak Two Hundred Twenty-nine Thal Development Authority",
    "gn:population":0,
    "gn:timezone":"Asia/Karachi",
    "iso:country":"PK",
    "name:und_x_variant":[
        "Chak 229 TDA",
        "Chak Two Hundred Twenty-Nine TDA",
        "Chak Two Hundred Twenty-nine Thal Development Authority"
    ],
    "wof:name":"Chak Two Hundred Twenty-nine Thal Development Authority",
    "wof:placetype":"locality"
},
  "geometry": {"coordinates":[71.19908000000002,31.2024],"type":"Point"}
}