{
  "type": "Feature",
  "properties": {
    "gn:admin1_code":"2.0",
    "gn:asciiname":"Barshor",
    "gn:country_code":"PK",
    "gn:dem":1840,
    "gn:feature_class":"P",
    "gn:feature_code":"PPL",
    "gn:name":"Barshor",
    "gn:population":0,
    "gn:timezone":"Asia/Karachi",
    "iso:country":"PK",
    "name:eng_x_preferred":[
        "Barshor"
    ],
    "wof:name":"Barshor",
    "wof:placetype":"locality"
},
  "geometry": {"coordinates":[67.28985,30.81479],"type":"Point"}
}