{
  "type": "Feature",
  "properties": {
    "gn:admin1_code":"04",
    "gn:asciiname":"Saintha",
    "gn:country_code":"PK",
    "gn:dem":635,
    "gn:feature_class":"P",
    "gn:feature_code":"PPL",
    "gn:name":"Saintha",
    "gn:population":0,
    "gn:timezone":"Asia/Karachi",
    "iso:country":"PK",
    "wof:name":"Saintha",
    "wof:placetype":"locality"
},
  "geometry": {"coordinates":[73.48084,33.47493],"type":"Point"}
}