{
  "type": "Feature",
  "properties": {
    "gn:admin1_code":"3",
    "gn:asciiname":"Kiririan",
    "gn:country_code":"PK",
    "gn:dem":522,
    "gn:feature_class":"P",
    "gn:feature_code":"PPL",
    "gn:name":"Kiririan",
    "gn:population":0,
    "gn:timezone":"Asia/Karachi",
    "iso:country":"PK",
    "name:und_x_variant":[
        "Kir\u0101rw\u0101la"
    ],
    "wof:name":"Kiririan",
    "wof:placetype":"locality"
},
  "geometry": {"coordinates":[71.14046999999999,32.38232],"type":"Point"}
}