{
  "type": "Feature",
  "properties": {
    "gn:admin1_code":"4",
    "gn:asciiname":"Waliwala",
    "gn:country_code":"PK",
    "gn:dem":128,
    "gn:feature_class":"P",
    "gn:feature_code":"PPL",
    "gn:name":"Waliwala",
    "gn:population":0,
    "gn:timezone":"Asia/Karachi",
    "iso:country":"PK",
    "name:eng_x_preferred":[
        "Wall\u016bw\u0101la"
    ],
    "wof:name":"Waliwala",
    "wof:placetype":"locality"
},
  "geometry": {"coordinates":[70.91148000000003,30.34617],"type":"Point"}
}