{
  "type": "Feature",
  "properties": {
    "gn:admin1_code":"3.0",
    "gn:asciiname":"Tikki Banda",
    "gn:country_code":"PK",
    "gn:dem":2587,
    "gn:feature_class":"P",
    "gn:feature_code":"PPL",
    "gn:name":"Tikki Banda",
    "gn:population":0,
    "gn:timezone":"Asia/Karachi",
    "iso:country":"PK",
    "wof:name":"Tikki Banda",
    "wof:placetype":"locality"
},
  "geometry": {"coordinates":[72.95471999999999,35.14968],"type":"Point"}
}