{
  "type": "Feature",
  "properties": {
    "gn:admin1_code":"4.0",
    "gn:asciiname":"Hakuwala",
    "gn:country_code":"PK",
    "gn:dem":197,
    "gn:feature_class":"P",
    "gn:feature_code":"PPL",
    "gn:name":"Hakuwala",
    "gn:population":0,
    "gn:timezone":"Asia/Karachi",
    "iso:country":"PK",
    "name:und_x_variant":[
        "Kot Hakuw\u0101la",
        "Haji Kot"
    ],
    "wof:name":"Hakuwala",
    "wof:placetype":"locality"
},
  "geometry": {"coordinates":[73.80462,31.53743],"type":"Point"}
}