{
  "type": "Feature",
  "properties": {
    "gn:admin1_code":"2",
    "gn:asciiname":"Garang War",
    "gn:country_code":"PK",
    "gn:dem":2044,
    "gn:feature_class":"P",
    "gn:feature_code":"PPL",
    "gn:name":"Garang War",
    "gn:population":0,
    "gn:timezone":"Asia/Karachi",
    "iso:country":"PK",
    "name:und_x_variant":[
        "Ganre Wune"
    ],
    "wof:name":"Garang War",
    "wof:placetype":"locality"
},
  "geometry": {"coordinates":[66.77065999999999,31.16097],"type":"Point"}
}