{
  "type": "Feature",
  "properties": {
    "gn:admin1_code":"4",
    "gn:asciiname":"Bangial",
    "gn:country_code":"PK",
    "gn:dem":303,
    "gn:feature_class":"P",
    "gn:feature_code":"PPL",
    "gn:name":"Bangial",
    "gn:population":0,
    "gn:timezone":"Asia/Karachi",
    "iso:country":"PK",
    "wof:name":"Bangial",
    "wof:placetype":"locality"
},
  "geometry": {"coordinates":[74.03803000000001,32.82638],"type":"Point"}
}