{
  "type": "Feature",
  "properties": {
    "gn:admin1_code":"4",
    "gn:asciiname":"Alihani",
    "gn:country_code":"PK",
    "gn:dem":279,
    "gn:feature_class":"P",
    "gn:feature_code":"PPL",
    "gn:name":"Alihani",
    "gn:population":0,
    "gn:timezone":"Asia/Karachi",
    "iso:country":"PK",
    "name:eng_x_preferred":[
        "Basti Bhurgura"
    ],
    "wof:name":"Alihani",
    "wof:placetype":"locality"
},
  "geometry": {"coordinates":[70.29304999999999,29.95052],"type":"Point"}
}