{
  "type": "Feature",
  "properties": {
    "gn:admin1_code":"5.0",
    "gn:asciiname":"Haji Ali Muhammad Kalro",
    "gn:country_code":"PK",
    "gn:dem":13,
    "gn:feature_class":"P",
    "gn:feature_code":"PPL",
    "gn:name":"Haji Ali Muhammad Kalro",
    "gn:population":0,
    "gn:timezone":"Asia/Karachi",
    "iso:country":"PK",
    "wof:name":"Haji Ali Muhammad Kalro",
    "wof:placetype":"locality"
},
  "geometry": {"coordinates":[69.383,25.39419],"type":"Point"}
}