{
  "type": "Feature",
  "properties": {
    "gn:admin1_code":"1.0",
    "gn:asciiname":"Shpela",
    "gn:country_code":"PK",
    "gn:dem":1271,
    "gn:feature_class":"P",
    "gn:feature_code":"PPL",
    "gn:name":"Shpela",
    "gn:population":0,
    "gn:timezone":"Asia/Karachi",
    "iso:country":"PK",
    "wof:name":"Shpela",
    "wof:placetype":"locality"
},
  "geometry": {"coordinates":[70.22239999999999,32.56899],"type":"Point"}
}