{
  "type": "Feature",
  "properties": {
    "gn:admin1_code":"2.0",
    "gn:asciiname":"Hurro",
    "gn:country_code":"PK",
    "gn:dem":707,
    "gn:feature_class":"P",
    "gn:feature_code":"PPL",
    "gn:name":"Hurro",
    "gn:population":0,
    "gn:timezone":"Asia/Karachi",
    "iso:country":"PK",
    "name:und_x_variant":[
        "Kili Ras\u016bl Bakhsh"
    ],
    "wof:name":"Hurro",
    "wof:placetype":"locality"
},
  "geometry": {"coordinates":[65.46343,28.50416],"type":"Point"}
}