{
  "type": "Feature",
  "properties": {
    "iso:country":"PK",
    "name:ara_x_preferred":[
        "\u0647\u0644\u0648"
    ],
    "name:ceb_x_preferred":[
        "H\u0101l\u016b"
    ],
    "name:ckb_x_preferred":[
        "\u06be\u06d5\u06b5\u06c6\u060c \u0628\u0627\u0646\u06d5"
    ],
    "name:ckb_x_variant":[
        "\u06be\u06d5\u06b5\u06c6"
    ],
    "name:fas_x_preferred":[
        "\u0647\u0644\u0648"
    ],
    "name:swe_x_preferred":[
        "H\u0101l\u016b"
    ],
    "qs:gn_pop":0,
    "qs:name":"Halu",
    "qs:name_adm0":"Pakistan",
    "qs:name_adm1":"Sindh",
    "qs:photos":79,
    "qs:photos_1k":16,
    "qs:photos_9k":1,
    "qs:photos_9r":3,
    "qs:photos_all":79,
    "qs:photos_sr":3,
    "qs:placetype":"Town",
    "qs:pop_sr":"0",
    "qs:woe_adm0":23424922,
    "wd:wordcount":95,
    "wof:name":"Halu",
    "wof:placetype":"neighbourhood"
},
  "geometry": {"coordinates":[68.422431,25.815036],"type":"Point"}
}