{
  "type": "Feature",
  "properties": {
    "gn:admin1_code":"6",
    "gn:asciiname":"Kainan",
    "gn:country_code":"PK",
    "gn:dem":1935,
    "gn:feature_class":"P",
    "gn:feature_code":"PPL",
    "gn:name":"Kainan",
    "gn:population":0,
    "gn:timezone":"Asia/Karachi",
    "iso:country":"PK",
    "name:und_x_variant":[
        "Kaian",
        "Kainan"
    ],
    "wof:name":"Kainan",
    "wof:placetype":"locality"
},
  "geometry": {"coordinates":[74.07778,34.0125],"type":"Point"}
}