{
  "type": "Feature",
  "properties": {
    "gn:admin1_code":"4.0",
    "gn:asciiname":"Dharor Hindu",
    "gn:country_code":"PK",
    "gn:dem":213,
    "gn:feature_class":"P",
    "gn:feature_code":"PPL",
    "gn:name":"Dharor Hindu",
    "gn:population":0,
    "gn:timezone":"Asia/Karachi",
    "iso:country":"PK",
    "name:und_x_variant":[
        "Dharor Hindu\u0101n",
        "Ras\u016blpuran"
    ],
    "wof:name":"Dharor Hindu",
    "wof:placetype":"locality"
},
  "geometry": {"coordinates":[74.36949,31.7955],"type":"Point"}
}