{
  "type": "Feature",
  "properties": {
    "gn:admin1_code":"4.0",
    "gn:asciiname":"Senipura",
    "gn:country_code":"PK",
    "gn:dem":165,
    "gn:feature_class":"P",
    "gn:feature_code":"PPL",
    "gn:name":"Senipura",
    "gn:population":0,
    "gn:timezone":"Asia/Karachi",
    "iso:country":"PK",
    "name:und_x_variant":[
        "Chak 44-5 L",
        "Chak Forty-four Five L"
    ],
    "wof:name":"Senipura",
    "wof:placetype":"locality"
},
  "geometry": {"coordinates":[73.28504000000002,30.58764],"type":"Point"}
}