{
  "type": "Feature",
  "properties": {
    "gn:admin1_code":"5.0",
    "gn:asciiname":"Sarwar Shah",
    "gn:country_code":"PK",
    "gn:dem":9,
    "gn:feature_class":"P",
    "gn:feature_code":"PPL",
    "gn:name":"Sarwar Shah",
    "gn:population":0,
    "gn:timezone":"Asia/Karachi",
    "iso:country":"PK",
    "name:eng_x_preferred":[
        "Sarwar Shah"
    ],
    "wof:name":"Sarwar Shah",
    "wof:placetype":"locality"
},
  "geometry": {"coordinates":[68.17249,24.55226],"type":"Point"}
}