{
  "type": "Feature",
  "properties": {
    "gn:admin1_code":"2.0",
    "gn:asciiname":"Salk Mills",
    "gn:country_code":"PK",
    "gn:dem":2092,
    "gn:feature_class":"P",
    "gn:feature_code":"PPL",
    "gn:name":"Salk Mills",
    "gn:population":0,
    "gn:timezone":"Asia/Karachi",
    "iso:country":"PK",
    "wof:name":"Salk Mills",
    "wof:placetype":"locality"
},
  "geometry": {"coordinates":[67.82531,31.04328],"type":"Point"}
}