{
  "type": "Feature",
  "properties": {
    "gn:admin1_code":"2",
    "gn:asciiname":"Azizullah",
    "gn:country_code":"PK",
    "gn:dem":1923,
    "gn:feature_class":"P",
    "gn:feature_code":"PPL",
    "gn:name":"Azizullah",
    "gn:population":0,
    "gn:timezone":"Asia/Karachi",
    "iso:country":"PK",
    "wof:name":"Azizullah",
    "wof:placetype":"locality"
},
  "geometry": {"coordinates":[66.80072,31.12361],"type":"Point"}
}