{
  "type": "Feature",
  "properties": {
    "gn:admin1_code":"4.0",
    "gn:asciiname":"Chuna Mor",
    "gn:country_code":"PK",
    "gn:dem":705,
    "gn:feature_class":"P",
    "gn:feature_code":"PPL",
    "gn:name":"Chuna Mor",
    "gn:population":0,
    "gn:timezone":"Asia/Karachi",
    "iso:country":"PK",
    "wof:name":"Chuna Mor",
    "wof:placetype":"locality"
},
  "geometry": {"coordinates":[73.56404000000001,33.7685],"type":"Point"}
}