{
  "type": "Feature",
  "properties": {
    "gn:admin1_code":"6",
    "gn:asciiname":"Kopri",
    "gn:country_code":"PK",
    "gn:dem":3010,
    "gn:feature_class":"P",
    "gn:feature_code":"PPL",
    "gn:name":"Kopri",
    "gn:population":0,
    "gn:timezone":"Asia/Karachi",
    "iso:country":"PK",
    "name:hin_x_preferred":[
        "\u0915\u094b\u092a\u0930\u0940"
    ],
    "name:mar_x_preferred":[
        "\u0915\u094b\u092a\u0930\u0940"
    ],
    "name:tam_x_preferred":[
        "\u0b95\u0bcb\u0baa\u0bcd\u0bb0\u0bbf"
    ],
    "name:und_x_variant":[
        "Kaori"
    ],
    "wof:name":"Kopri",
    "wof:placetype":"locality"
},
  "geometry": {"coordinates":[74.01375,33.97443],"type":"Point"}
}