{
  "type": "Feature",
  "properties": {
    "gn:admin1_code":"8.0",
    "gn:asciiname":"Jagiot",
    "gn:country_code":"PK",
    "gn:dem":555,
    "gn:feature_class":"P",
    "gn:feature_code":"PPL",
    "gn:name":"Jagiot",
    "gn:population":0,
    "gn:timezone":"Asia/Karachi",
    "iso:country":"PK",
    "name:und_x_variant":[
        "Jagyot",
        "Jagiot"
    ],
    "wof:name":"Jagiot",
    "wof:placetype":"locality"
},
  "geometry": {"coordinates":[73.21364,33.67355],"type":"Point"}
}