{
  "type": "Feature",
  "properties": {
    "gn:admin1_code":"1.0",
    "gn:asciiname":"Tapakai",
    "gn:country_code":"PK",
    "gn:dem":1090,
    "gn:feature_class":"P",
    "gn:feature_code":"PPL",
    "gn:name":"Tapakai",
    "gn:population":0,
    "gn:timezone":"Asia/Karachi",
    "iso:country":"PK",
    "wof:name":"Tapakai",
    "wof:placetype":"locality"
},
  "geometry": {"coordinates":[70.19771,33.16197],"type":"Point"}
}