{
  "type": "Feature",
  "properties": {
    "gn:admin1_code":"3",
    "gn:asciiname":"Lari",
    "gn:country_code":"PK",
    "gn:dem":3151,
    "gn:feature_class":"P",
    "gn:feature_code":"PPL",
    "gn:name":"Lari",
    "gn:population":0,
    "gn:timezone":"Asia/Karachi",
    "iso:country":"PK",
    "wof:name":"Lari",
    "wof:placetype":"locality"
},
  "geometry": {"coordinates":[73.44821,34.77098],"type":"Point"}
}