{
  "type": "Feature",
  "properties": {
    "gn:admin1_code":"5.0",
    "gn:asciiname":"Ali Muhammad Shah Jo Tar",
    "gn:country_code":"PK",
    "gn:dem":76,
    "gn:feature_class":"P",
    "gn:feature_code":"PPL",
    "gn:name":"Ali Muhammad Shah Jo Tar",
    "gn:population":0,
    "gn:timezone":"Asia/Karachi",
    "iso:country":"PK",
    "wof:name":"Ali Muhammad Shah Jo Tar",
    "wof:placetype":"locality"
},
  "geometry": {"coordinates":[70.32833000000001,24.62473],"type":"Point"}
}