{
  "type": "Feature",
  "properties": {
    "gn:admin1_code":"4",
    "gn:asciiname":"Chak Seventy- Ten Right",
    "gn:country_code":"PK",
    "gn:dem":139,
    "gn:feature_class":"P",
    "gn:feature_code":"PPL",
    "gn:name":"Chak Seventy- Ten Right",
    "gn:population":0,
    "gn:timezone":"Asia/Karachi",
    "iso:country":"PK",
    "name:und_x_variant":[
        "Chak Seventy-Ten R",
        "Ary\u0101nagar",
        "Chak Seventy- Ten Right"
    ],
    "wof:name":"Chak Seventy- Ten Right",
    "wof:placetype":"locality"
},
  "geometry": {"coordinates":[72.01916999999997,30.26846],"type":"Point"}
}