{
  "type": "Feature",
  "properties": {
    "gn:admin1_code":"3.0",
    "gn:asciiname":"Arandu",
    "gn:country_code":"PK",
    "gn:dem":1143,
    "gn:feature_class":"P",
    "gn:feature_code":"PPL",
    "gn:name":"Arandu",
    "gn:population":0,
    "gn:timezone":"Asia/Karachi",
    "iso:country":"PK",
    "name:eng_x_preferred":[
        "Arandu"
    ],
    "name:und_x_variant":[
        "Arnawai",
        "Arnawa"
    ],
    "name:urd_x_preferred":[
        "Arand\u016b"
    ],
    "name:urd_x_variant":[
        "\u0627\u064e\u0631\u0646\u0652\u062f\u0648"
    ],
    "wof:name":"Arandu",
    "wof:placetype":"locality"
},
  "geometry": {"coordinates":[71.54929,35.31025],"type":"Point"}
}