{
  "type": "Feature",
  "properties": {
    "gn:admin1_code":"5.0",
    "gn:asciiname":"Charnor",
    "gn:country_code":"PK",
    "gn:dem":142,
    "gn:feature_class":"P",
    "gn:feature_code":"PPL",
    "gn:name":"Charnor",
    "gn:population":0,
    "gn:timezone":"Asia/Karachi",
    "iso:country":"PK",
    "name:und_x_variant":[
        "Ch\u0101rnor"
    ],
    "wof:name":"Charnor",
    "wof:placetype":"locality"
},
  "geometry": {"coordinates":[70.65460999999998,25.11362],"type":"Point"}
}