{
  "type": "Feature",
  "properties": {
    "gn:admin1_code":"3",
    "gn:asciiname":"Kuz Aspair",
    "gn:country_code":"PK",
    "gn:dem":1075,
    "gn:feature_class":"P",
    "gn:feature_code":"PPL",
    "gn:name":"Kuz Aspair",
    "gn:population":0,
    "gn:timezone":"Asia/Karachi",
    "iso:country":"PK",
    "name:und_x_variant":[
        "Kuz Aspanr"
    ],
    "wof:name":"Kuz Aspair",
    "wof:placetype":"locality"
},
  "geometry": {"coordinates":[72.11763000000001,34.78872],"type":"Point"}
}