{
  "type": "Feature",
  "properties": {
    "gn:admin1_code":"4.0",
    "gn:asciiname":"Atar",
    "gn:country_code":"PK",
    "gn:dem":576,
    "gn:feature_class":"P",
    "gn:feature_code":"PPL",
    "gn:name":"Atar",
    "gn:population":0,
    "gn:timezone":"Asia/Karachi",
    "iso:country":"PK",
    "wof:name":"Atar",
    "wof:placetype":"locality"
},
  "geometry": {"coordinates":[73.41303000000001,33.45043],"type":"Point"}
}