{
  "type": "Feature",
  "properties": {
    "gn:admin1_code":"4.0",
    "gn:asciiname":"Atar",
    "gn:country_code":"PK",
    "gn:dem":576,
    "gn:feature_class":"P",
    "gn:feature_code":"PPL",
    "gn:name":"Atar",
    "gn:population":0,
    "gn:timezone":"Asia/Karachi",
    "iso:country":"PK",
    "name:cat_x_preferred":[
        "Atar"
    ],
    "name:diq_x_preferred":[
        "Atar"
    ],
    "name:fas_x_preferred":[
        "\u0622\u0630\u0631"
    ],
    "name:fra_x_preferred":[
        "Atar"
    ],
    "name:jpn_x_preferred":[
        "\u30a2\u30fc\u30bf\u30eb"
    ],
    "name:nld_x_preferred":[
        "\u00c2tash"
    ],
    "name:nno_x_preferred":[
        "Atar"
    ],
    "name:pol_x_preferred":[
        "Atar"
    ],
    "name:ron_x_preferred":[
        "Atar"
    ],
    "name:rus_x_preferred":[
        "\u0410\u0442\u0430\u0440"
    ],
    "name:swe_x_preferred":[
        "Atar"
    ],
    "name:tur_x_preferred":[
        "Atar"
    ],
    "wof:name":"Atar",
    "wof:placetype":"locality"
},
  "geometry": {"coordinates":[73.41303000000001,33.45043],"type":"Point"}
}