{
  "type": "Feature",
  "properties": {
    "gn:admin1_code":"4",
    "gn:asciiname":"Basti Billa Arain",
    "gn:country_code":"PK",
    "gn:dem":101,
    "gn:feature_class":"P",
    "gn:feature_code":"PPL",
    "gn:name":"Basti Billa Arain",
    "gn:population":0,
    "gn:timezone":"Asia/Karachi",
    "iso:country":"PK",
    "name:und_x_variant":[
        "Basti Ar\u0101in"
    ],
    "wof:name":"Basti Billa Arain",
    "wof:placetype":"locality"
},
  "geometry": {"coordinates":[70.51411999999998,29.36266],"type":"Point"}
}