{
  "type": "Feature",
  "properties": {
    "gn:admin1_code":"5",
    "gn:asciiname":"Haji Thado Amer",
    "gn:country_code":"PK",
    "gn:dem":48,
    "gn:feature_class":"P",
    "gn:feature_code":"PPL",
    "gn:name":"Haji Thado Amer",
    "gn:population":0,
    "gn:timezone":"Asia/Karachi",
    "iso:country":"PK",
    "name:und_x_variant":[
        "H\u0101ji Thada"
    ],
    "wof:name":"Haji Thado Amer",
    "wof:placetype":"locality"
},
  "geometry": {"coordinates":[68.50573,27.03686],"type":"Point"}
}