{
  "type": "Feature",
  "properties": {
    "gn:admin1_code":"4",
    "gn:asciiname":"Chak Ninety-nine -Twelve Left",
    "gn:country_code":"PK",
    "gn:dem":153,
    "gn:feature_class":"P",
    "gn:feature_code":"PPL",
    "gn:name":"Chak Ninety-nine -Twelve Left",
    "gn:population":0,
    "gn:timezone":"Asia/Karachi",
    "iso:country":"PK",
    "name:und_x_variant":[
        "N\u016br Ell\u0101hi"
    ],
    "wof:name":"Chak Ninety-nine -Twelve Left",
    "wof:placetype":"locality"
},
  "geometry": {"coordinates":[72.53596999999998,30.41088],"type":"Point"}
}