{
  "type": "Feature",
  "properties": {
    "gn:admin1_code":"4.0",
    "gn:asciiname":"Chak Bandi",
    "gn:country_code":"PK",
    "gn:dem":183,
    "gn:feature_class":"P",
    "gn:feature_code":"PPL",
    "gn:name":"Chak Bandi",
    "gn:population":0,
    "gn:timezone":"Asia/Karachi",
    "iso:country":"PK",
    "name:und_x_variant":[
        "Cham Kandi",
        "Chom Kandi"
    ],
    "wof:name":"Chak Bandi",
    "wof:placetype":"locality"
},
  "geometry": {"coordinates":[73.03148,31.64929],"type":"Point"}
}