{
  "type": "Feature",
  "properties": {
    "gn:admin1_code":"5.0",
    "gn:asciiname":"Heto Abupoto",
    "gn:country_code":"PK",
    "gn:dem":29,
    "gn:feature_class":"P",
    "gn:feature_code":"PPL",
    "gn:name":"Heto Abupoto",
    "gn:population":0,
    "gn:timezone":"Asia/Karachi",
    "iso:country":"PK",
    "wof:name":"Heto Abupoto",
    "wof:placetype":"locality"
},
  "geometry": {"coordinates":[69.05034000000001,26.26057],"type":"Point"}
}