{
  "type": "Feature",
  "properties": {
    "gn:admin1_code":"2",
    "gn:asciiname":"Aghbargai",
    "gn:country_code":"PK",
    "gn:dem":2194,
    "gn:feature_class":"P",
    "gn:feature_code":"PPL",
    "gn:name":"Aghbargai",
    "gn:population":0,
    "gn:timezone":"Asia/Karachi",
    "iso:country":"PK",
    "name:eng_x_preferred":[
        "Aghbargai"
    ],
    "wof:name":"Aghbargai",
    "wof:placetype":"locality"
},
  "geometry": {"coordinates":[67.43626,30.89128],"type":"Point"}
}