{
  "type": "Feature",
  "properties": {
    "gn:admin1_code":"2.0",
    "gn:asciiname":"Bharro",
    "gn:country_code":"PK",
    "gn:dem":2444,
    "gn:feature_class":"P",
    "gn:feature_code":"PPL",
    "gn:name":"Bharro",
    "gn:population":0,
    "gn:timezone":"Asia/Karachi",
    "iso:country":"PK",
    "wof:name":"Bharro",
    "wof:placetype":"locality"
},
  "geometry": {"coordinates":[66.58205,28.59238],"type":"Point"}
}