{
  "type": "Feature",
  "properties": {
    "gn:admin1_code":"3",
    "gn:asciiname":"Karin",
    "gn:country_code":"PK",
    "gn:dem":1602,
    "gn:feature_class":"P",
    "gn:feature_code":"PPL",
    "gn:name":"Karin",
    "gn:population":0,
    "gn:timezone":"Asia/Karachi",
    "iso:country":"PK",
    "wof:name":"Karin",
    "wof:placetype":"locality"
},
  "geometry": {"coordinates":[72.61310999999998,34.7354],"type":"Point"}
}