{
  "type": "Feature",
  "properties": {
    "gn:admin1_code":"2.0",
    "gn:asciiname":"Karim Jan Bazar",
    "gn:country_code":"PK",
    "gn:dem":553,
    "gn:feature_class":"P",
    "gn:feature_code":"PPL",
    "gn:name":"Karim Jan Bazar",
    "gn:population":0,
    "gn:timezone":"Asia/Karachi",
    "iso:country":"PK",
    "name:und_x_variant":[
        "Kar\u012bm J\u0101n"
    ],
    "wof:name":"Karim Jan Bazar",
    "wof:placetype":"locality"
},
  "geometry": {"coordinates":[64.71852,26.24143],"type":"Point"}
}