{
  "type": "Feature",
  "properties": {
    "gn:admin1_code":"3.0",
    "gn:asciiname":"Bazwani",
    "gn:country_code":"PK",
    "gn:dem":2231,
    "gn:feature_class":"P",
    "gn:feature_code":"PPL",
    "gn:name":"Bazwani",
    "gn:population":0,
    "gn:timezone":"Asia/Karachi",
    "iso:country":"PK",
    "wof:name":"Bazwani",
    "wof:placetype":"locality"
},
  "geometry": {"coordinates":[73.54236,34.68179],"type":"Point"}
}