{
  "type": "Feature",
  "properties": {
    "gn:admin1_code":"4.0",
    "gn:asciiname":"Bhogi Chak",
    "gn:country_code":"PK",
    "gn:dem":279,
    "gn:feature_class":"P",
    "gn:feature_code":"PPL",
    "gn:name":"Bhogi Chak",
    "gn:population":0,
    "gn:timezone":"Asia/Karachi",
    "iso:country":"PK",
    "wof:name":"Bhogi Chak",
    "wof:placetype":"locality"
},
  "geometry": {"coordinates":[73.45907,32.94874],"type":"Point"}
}