{
  "type": "Feature",
  "properties": {
    "gn:admin1_code":"6",
    "gn:asciiname":"Dandkiar",
    "gn:country_code":"PK",
    "gn:dem":2535,
    "gn:feature_class":"P",
    "gn:feature_code":"PPL",
    "gn:name":"Dandkiar",
    "gn:population":0,
    "gn:timezone":"Asia/Karachi",
    "iso:country":"PK",
    "name:und_x_variant":[
        "D\u0101ndkari"
    ],
    "wof:name":"Dandkiar",
    "wof:placetype":"locality"
},
  "geometry": {"coordinates":[73.85850000000001,34.27107],"type":"Point"}
}