{
  "type": "Feature",
  "properties": {
    "gn:admin1_code":"4.0",
    "gn:asciiname":"Qattal Khel",
    "gn:country_code":"PK",
    "gn:dem":326,
    "gn:feature_class":"P",
    "gn:feature_code":"PPL",
    "gn:name":"Qattal Khel",
    "gn:population":0,
    "gn:timezone":"Asia/Karachi",
    "iso:country":"PK",
    "wof:name":"Qattal Khel",
    "wof:placetype":"locality"
},
  "geometry": {"coordinates":[71.17975,32.87612],"type":"Point"}
}