{
  "type": "Feature",
  "properties": {
    "gn:admin1_code":"5.0",
    "gn:asciiname":"Goth Tur Khan Pathan",
    "gn:country_code":"PK",
    "gn:dem":7,
    "gn:feature_class":"P",
    "gn:feature_code":"PPL",
    "gn:name":"Goth Tur Khan Pathan",
    "gn:population":0,
    "gn:timezone":"Asia/Karachi",
    "iso:country":"PK",
    "wof:name":"Goth Tur Khan Pathan",
    "wof:placetype":"locality"
},
  "geometry": {"coordinates":[69.10123,24.62026],"type":"Point"}
}