{
  "type": "Feature",
  "properties": {
    "gn:admin1_code":"3.0",
    "gn:asciiname":"Kairo Godar",
    "gn:country_code":"PK",
    "gn:dem":431,
    "gn:feature_class":"P",
    "gn:feature_code":"PPL",
    "gn:name":"Kairo Godar",
    "gn:population":0,
    "gn:timezone":"Asia/Karachi",
    "iso:country":"PK",
    "wof:name":"Kairo Godar",
    "wof:placetype":"locality"
},
  "geometry": {"coordinates":[71.84576,34.44185],"type":"Point"}
}