{
  "type": "Feature",
  "properties": {
    "gn:admin1_code":"6.0",
    "gn:asciiname":"Sahna Mehra",
    "gn:country_code":"PK",
    "gn:dem":1298,
    "gn:feature_class":"P",
    "gn:feature_code":"PPL",
    "gn:name":"Sahna Mehra",
    "gn:population":0,
    "gn:timezone":"Asia/Karachi",
    "iso:country":"PK",
    "name:und_x_variant":[
        "S\u0101h na Mohra"
    ],
    "wof:name":"Sahna Mehra",
    "wof:placetype":"locality"
},
  "geometry": {"coordinates":[73.70554,33.80028],"type":"Point"}
}