{
  "type": "Feature",
  "properties": {
    "gn:admin1_code":"4.0",
    "gn:asciiname":"Jalalpur Jagir",
    "gn:country_code":"PK",
    "gn:dem":186,
    "gn:feature_class":"P",
    "gn:feature_code":"PPL",
    "gn:name":"Jalalpur Jagir",
    "gn:population":0,
    "gn:timezone":"Asia/Karachi",
    "iso:country":"PK",
    "name:und_x_variant":[
        "Jal\u0101lpur",
        "Bonga Ichhral",
        "Bunga Ichhr\u0101l",
        "Jalalpur Jagir"
    ],
    "wof:name":"Jalalpur Jagir",
    "wof:placetype":"locality"
},
  "geometry": {"coordinates":[72.44488,32.29577],"type":"Point"}
}