{
  "type": "Feature",
  "properties": {
    "gn:admin1_code":"4",
    "gn:asciiname":"Gulcha",
    "gn:country_code":"PK",
    "gn:dem":129,
    "gn:feature_class":"P",
    "gn:feature_code":"PPL",
    "gn:name":"Gulcha",
    "gn:population":0,
    "gn:timezone":"Asia/Karachi",
    "iso:country":"PK",
    "name:ckb_x_preferred":[
        "\u06af\u0648\u06cc\u0644\u0686\u0648\u06ce"
    ],
    "name:fas_x_preferred":[
        "\u06af\u0648\u0644\u0686\u0648"
    ],
    "name:fra_x_preferred":[
        "Gulcha"
    ],
    "name:ita_x_preferred":[
        "Gul\u010da"
    ],
    "name:kir_x_preferred":[
        "\u0413\u04af\u043b\u0447\u04e9"
    ],
    "name:pol_x_preferred":[
        "G\u00fclcz\u00f6"
    ],
    "name:rus_x_preferred":[
        "\u0413\u0443\u043b\u044c\u0447\u0430"
    ],
    "name:sco_x_preferred":[
        "Gulcha"
    ],
    "name:tur_x_preferred":[
        "G\u00fcl\u00e7a"
    ],
    "name:und_x_variant":[
        "Guleha"
    ],
    "name:uzb_x_preferred":[
        "Gulcha"
    ],
    "wof:name":"Gulcha",
    "wof:placetype":"locality"
},
  "geometry": {"coordinates":[71.09407,30.37325],"type":"Point"}
}