{
  "type": "Feature",
  "properties": {
    "gn:admin1_code":"4",
    "gn:asciiname":"Kot Kalranwala",
    "gn:country_code":"PK",
    "gn:dem":198,
    "gn:feature_class":"P",
    "gn:feature_code":"PPL",
    "gn:name":"Kot Kalranwala",
    "gn:population":0,
    "gn:timezone":"Asia/Karachi",
    "iso:country":"PK",
    "name:und_x_variant":[
        "Kot K\u0101lre"
    ],
    "wof:name":"Kot Kalranwala",
    "wof:placetype":"locality"
},
  "geometry": {"coordinates":[73.78589000000002,31.45043],"type":"Point"}
}