{
  "type": "Feature",
  "properties": {
    "gn:admin1_code":"4.0",
    "gn:asciiname":"Chak One Hundred Four NP",
    "gn:country_code":"PK",
    "gn:dem":90,
    "gn:feature_class":"P",
    "gn:feature_code":"PPL",
    "gn:name":"Chak One Hundred Four NP",
    "gn:population":0,
    "gn:timezone":"Asia/Karachi",
    "iso:country":"PK",
    "name:urd_x_preferred":[
        "Chak One Hundred - four"
    ],
    "wof:name":"Chak One Hundred Four NP",
    "wof:placetype":"locality"
},
  "geometry": {"coordinates":[70.71294,28.83749000000001],"type":"Point"}
}