{
  "type": "Feature",
  "properties": {
    "gn:admin1_code":"4",
    "gn:asciiname":"Ganeri",
    "gn:country_code":"PK",
    "gn:dem":348,
    "gn:feature_class":"P",
    "gn:feature_code":"PPL",
    "gn:name":"Ganeri",
    "gn:population":0,
    "gn:timezone":"Asia/Karachi",
    "iso:country":"PK",
    "wof:name":"Ganeri",
    "wof:placetype":"locality"
},
  "geometry": {"coordinates":[73.3396,32.90401],"type":"Point"}
}