{
  "type": "Feature",
  "properties": {
    "gn:admin1_code":"3.0",
    "gn:asciiname":"Amir Gul",
    "gn:country_code":"PK",
    "gn:dem":381,
    "gn:feature_class":"P",
    "gn:feature_code":"PPL",
    "gn:name":"Amir Gul",
    "gn:population":0,
    "gn:timezone":"Asia/Karachi",
    "iso:country":"PK",
    "name:eng_x_preferred":[
        "Amir Gul"
    ],
    "name:ind_x_preferred":[
        "Amir Gul"
    ],
    "wof:name":"Amir Gul",
    "wof:placetype":"locality"
},
  "geometry": {"coordinates":[71.81824,34.31832],"type":"Point"}
}