{
  "type": "Feature",
  "properties": {
    "gn:admin1_code":"5.0",
    "gn:asciiname":"Shafi Muhammad Jatoi",
    "gn:country_code":"PK",
    "gn:dem":35,
    "gn:feature_class":"P",
    "gn:feature_code":"PPL",
    "gn:name":"Shafi Muhammad Jatoi",
    "gn:population":0,
    "gn:timezone":"Asia/Karachi",
    "iso:country":"PK",
    "wof:name":"Shafi Muhammad Jatoi",
    "wof:placetype":"locality"
},
  "geometry": {"coordinates":[68.07808,26.29883],"type":"Point"}
}