{
  "type": "Feature",
  "properties": {
    "gn:admin1_code":"4.0",
    "gn:asciiname":"Langhar",
    "gn:country_code":"PK",
    "gn:dem":1572,
    "gn:feature_class":"P",
    "gn:feature_code":"PPL",
    "gn:name":"Langhar",
    "gn:population":0,
    "gn:timezone":"Asia/Karachi",
    "iso:country":"PK",
    "name:eng_x_preferred":[
        "Langhar"
    ],
    "wof:name":"Langhar",
    "wof:placetype":"locality"
},
  "geometry": {"coordinates":[73.45571,33.80871],"type":"Point"}
}