{
  "type": "Feature",
  "properties": {
    "gn:admin1_code":"5",
    "gn:asciiname":"Haji Yar Muhammad Kolachi",
    "gn:country_code":"PK",
    "gn:dem":61,
    "gn:feature_class":"P",
    "gn:feature_code":"PPL",
    "gn:name":"Haji Yar Muhammad Kolachi",
    "gn:population":0,
    "gn:timezone":"Asia/Karachi",
    "iso:country":"PK",
    "wof:name":"Haji Yar Muhammad Kolachi",
    "wof:placetype":"locality"
},
  "geometry": {"coordinates":[68.73494000000001,27.82117],"type":"Point"}
}