{
  "type": "Feature",
  "properties": {
    "gn:admin1_code":"3",
    "gn:asciiname":"Gura",
    "gn:country_code":"PK",
    "gn:dem":1773,
    "gn:feature_class":"P",
    "gn:feature_code":"PPL",
    "gn:name":"Gura",
    "gn:population":0,
    "gn:timezone":"Asia/Karachi",
    "iso:country":"PK",
    "name:bel_x_preferred":[
        "\u0413\u0443\u0440\u0430"
    ],
    "name:ceb_x_preferred":[
        "Gura"
    ],
    "name:deu_x_preferred":[
        "Gura"
    ],
    "name:eng_x_preferred":[
        "G\u016br\u016blodeh"
    ],
    "name:ita_x_preferred":[
        "Gura"
    ],
    "name:lit_x_preferred":[
        "Gura"
    ],
    "name:ron_x_preferred":[
        "Gura"
    ],
    "name:rus_x_preferred":[
        "\u0413\u0443\u0440\u0430"
    ],
    "name:swe_x_preferred":[
        "Gura"
    ],
    "name:szl_x_preferred":[
        "G\u016fra"
    ],
    "name:ukr_x_preferred":[
        "\u0413\u0443\u0440\u0430"
    ],
    "wof:name":"Gura",
    "wof:placetype":"locality"
},
  "geometry": {"coordinates":[71.70652,35.64608],"type":"Point"}
}