{
  "type": "Feature",
  "properties": {
    "gn:admin1_code":"3",
    "gn:asciiname":"Gura",
    "gn:country_code":"PK",
    "gn:dem":1773,
    "gn:feature_class":"P",
    "gn:feature_code":"PPL",
    "gn:name":"Gura",
    "gn:population":0,
    "gn:timezone":"Asia/Karachi",
    "iso:country":"PK",
    "name:eng_x_preferred":[
        "G\u016br\u016blodeh"
    ],
    "wof:name":"Gura",
    "wof:placetype":"locality"
},
  "geometry": {"coordinates":[71.70652,35.64608],"type":"Point"}
}