{
  "type": "Feature",
  "properties": {
    "gn:admin1_code":"5",
    "gn:asciiname":"Umar Rahu",
    "gn:country_code":"PK",
    "gn:dem":40,
    "gn:feature_class":"P",
    "gn:feature_code":"PPL",
    "gn:name":"Umar Rahu",
    "gn:population":0,
    "gn:timezone":"Asia/Karachi",
    "iso:country":"PK",
    "name:und_x_variant":[
        "Umar R\u0101ho"
    ],
    "wof:name":"Umar Rahu",
    "wof:placetype":"locality"
},
  "geometry": {"coordinates":[68.07129,26.45372],"type":"Point"}
}