{
  "type": "Feature",
  "properties": {
    "gn:admin1_code":"04",
    "gn:asciiname":"Bhaini Momeke",
    "gn:country_code":"PK",
    "gn:dem":154,
    "gn:feature_class":"P",
    "gn:feature_code":"PPL",
    "gn:name":"Bhaini Momeke",
    "gn:population":0,
    "gn:timezone":"Asia/Karachi",
    "iso:country":"PK",
    "name:und_x_variant":[
        "Momeka"
    ],
    "wof:name":"Bhaini Momeke",
    "wof:placetype":"locality"
},
  "geometry": {"coordinates":[73.21874,30.09165],"type":"Point"}
}