{
  "type": "Feature",
  "properties": {
    "gn:admin1_code":"2.0",
    "gn:asciiname":"Mozo Muhammad Hasan Jamot",
    "gn:country_code":"PK",
    "gn:dem":466,
    "gn:feature_class":"P",
    "gn:feature_code":"PPL",
    "gn:name":"Mozo Muhammad Hasan Jamot",
    "gn:population":0,
    "gn:timezone":"Asia/Karachi",
    "iso:country":"PK",
    "wof:name":"Mozo Muhammad Hasan Jamot",
    "wof:placetype":"locality"
},
  "geometry": {"coordinates":[67.27706999999999,27.93204],"type":"Point"}
}