{
  "type": "Feature",
  "properties": {
    "gn:admin1_code":"4.0",
    "gn:asciiname":"Thatta Bahadur",
    "gn:country_code":"PK",
    "gn:dem":207,
    "gn:feature_class":"P",
    "gn:feature_code":"PPL",
    "gn:name":"Thatta Bahadur",
    "gn:population":0,
    "gn:timezone":"Asia/Karachi",
    "iso:country":"PK",
    "name:und_x_variant":[
        "Thatta Bah\u0101dur Sh\u0101h"
    ],
    "wof:name":"Thatta Bahadur",
    "wof:placetype":"locality"
},
  "geometry": {"coordinates":[73.77772,31.79294],"type":"Point"}
}