{
  "type": "Feature",
  "properties": {
    "gn:admin1_code":"3.0",
    "gn:asciiname":"Yusufabad",
    "gn:country_code":"PK",
    "gn:dem":318,
    "gn:feature_class":"P",
    "gn:feature_code":"PPL",
    "gn:name":"Yusufabad",
    "gn:population":0,
    "gn:timezone":"Asia/Karachi",
    "iso:country":"PK",
    "wof:name":"Yusufabad",
    "wof:placetype":"locality"
},
  "geometry": {"coordinates":[71.59368000000001,34.02618],"type":"Point"}
}