{
  "type": "Feature",
  "properties": {
    "gn:admin1_code":"01",
    "gn:asciiname":"Cham Kani",
    "gn:country_code":"PK",
    "gn:dem":1776,
    "gn:feature_class":"P",
    "gn:feature_code":"PPL",
    "gn:name":"Cham Kani",
    "gn:population":0,
    "gn:timezone":"Asia/Karachi",
    "iso:country":"PK",
    "wof:name":"Cham Kani",
    "wof:placetype":"locality"
},
  "geometry": {"coordinates":[70.67248000000002,33.70609],"type":"Point"}
}