{
  "type": "Feature",
  "properties": {
    "gn:admin1_code":"03",
    "gn:asciiname":"Nabi",
    "gn:country_code":"PK",
    "gn:dem":299,
    "gn:feature_class":"P",
    "gn:feature_code":"PPL",
    "gn:name":"Nabi",
    "gn:population":0,
    "gn:timezone":"Asia/Karachi",
    "iso:country":"PK",
    "wof:name":"Nabi",
    "wof:placetype":"locality"
},
  "geometry": {"coordinates":[72.35779000000002,33.9958],"type":"Point"}
}