{
  "type": "Feature",
  "properties": {
    "gn:admin1_code":"3.0",
    "gn:asciiname":"Harbano",
    "gn:country_code":"PK",
    "gn:dem":3790,
    "gn:feature_class":"P",
    "gn:feature_code":"PPL",
    "gn:name":"Harbano",
    "gn:population":0,
    "gn:timezone":"Asia/Karachi",
    "iso:country":"PK",
    "wof:name":"Harbano",
    "wof:placetype":"locality"
},
  "geometry": {"coordinates":[73.63985,35.30653],"type":"Point"}
}