{
  "type": "Feature",
  "properties": {
    "gn:admin1_code":"7.0",
    "gn:asciiname":"Kachal",
    "gn:country_code":"PK",
    "gn:dem":3149,
    "gn:feature_class":"P",
    "gn:feature_code":"PPL",
    "gn:name":"Kachal",
    "gn:population":0,
    "gn:timezone":"Asia/Karachi",
    "iso:country":"PK",
    "name:ceb_x_preferred":[
        "Kachal"
    ],
    "name:hin_x_preferred":[
        "\u0915\u091a\u0932"
    ],
    "name:msa_x_preferred":[
        "Kachal"
    ],
    "name:nep_x_preferred":[
        "\u0915\u091a\u0932"
    ],
    "name:new_x_preferred":[
        "\u0915\u091a\u0932"
    ],
    "name:pol_x_preferred":[
        "Kachal"
    ],
    "wof:name":"Kachal",
    "wof:placetype":"locality"
},
  "geometry": {"coordinates":[74.42829999999999,35.2956],"type":"Point"}
}