{
  "type": "Feature",
  "properties": {
    "gn:admin1_code":"6.0",
    "gn:asciiname":"Paniali",
    "gn:country_code":"PK",
    "gn:dem":1199,
    "gn:feature_class":"P",
    "gn:feature_code":"PPL",
    "gn:name":"Paniali",
    "gn:population":0,
    "gn:timezone":"Asia/Karachi",
    "iso:country":"PK",
    "wof:name":"Paniali",
    "wof:placetype":"locality"
},
  "geometry": {"coordinates":[73.69719000000001,33.68376],"type":"Point"}
}