{
  "type": "Feature",
  "properties": {
    "gn:admin1_code":"5",
    "gn:asciiname":"Sanghar",
    "gn:country_code":"PK",
    "gn:dem":47,
    "gn:feature_class":"P",
    "gn:feature_code":"PPL",
    "gn:name":"Sanghar",
    "gn:population":0,
    "gn:timezone":"Asia/Karachi",
    "iso:country":"PK",
    "name:und_x_variant":[
        "Sang\u0101r"
    ],
    "wof:name":"Sanghar",
    "wof:placetype":"locality"
},
  "geometry": {"coordinates":[69.57334,24.76296],"type":"Point"}
}