{
  "type": "Feature",
  "properties": {
    "gn:admin1_code":"4.0",
    "gn:asciiname":"Chak Bandi Amir",
    "gn:country_code":"PK",
    "gn:dem":162,
    "gn:feature_class":"P",
    "gn:feature_code":"PPL",
    "gn:name":"Chak Bandi Amir",
    "gn:population":0,
    "gn:timezone":"Asia/Karachi",
    "iso:country":"PK",
    "name:und_x_variant":[
        "Chakbandi Am\u012br"
    ],
    "wof:name":"Chak Bandi Amir",
    "wof:placetype":"locality"
},
  "geometry": {"coordinates":[72.76817,30.63414],"type":"Point"}
}