{
  "type": "Feature",
  "properties": {
    "gn:admin1_code":"3",
    "gn:asciiname":"Chauda",
    "gn:country_code":"PK",
    "gn:dem":1594,
    "gn:feature_class":"P",
    "gn:feature_code":"PPL",
    "gn:name":"Chauda",
    "gn:population":0,
    "gn:timezone":"Asia/Karachi",
    "iso:country":"PK",
    "wof:name":"Chauda",
    "wof:placetype":"locality"
},
  "geometry": {"coordinates":[72.40118000000002,34.62377],"type":"Point"}
}