{
  "type": "Feature",
  "properties": {
    "gn:admin1_code":"1",
    "gn:asciiname":"Malik Mela",
    "gn:country_code":"PK",
    "gn:dem":1825,
    "gn:feature_class":"P",
    "gn:feature_code":"PPL",
    "gn:name":"Malik Mela",
    "gn:population":0,
    "gn:timezone":"Asia/Karachi",
    "iso:country":"PK",
    "wof:name":"Malik Mela",
    "wof:placetype":"locality"
},
  "geometry": {"coordinates":[69.85934,32.51635],"type":"Point"}
}