{
  "type": "Feature",
  "properties": {
    "gn:admin1_code":"4.0",
    "gn:asciiname":"Danna Nonathal",
    "gn:country_code":"PK",
    "gn:dem":1926,
    "gn:feature_class":"P",
    "gn:feature_code":"PPL",
    "gn:name":"Danna Nonathal",
    "gn:population":0,
    "gn:timezone":"Asia/Karachi",
    "iso:country":"PK",
    "name:eng_x_preferred":[
        "Danna Nonathal"
    ],
    "wof:name":"Danna Nonathal",
    "wof:placetype":"locality"
},
  "geometry": {"coordinates":[73.4336,33.8805],"type":"Point"}
}