{
  "type": "Feature",
  "properties": {
    "gn:admin1_code":"3",
    "gn:asciiname":"Gagar",
    "gn:country_code":"PK",
    "gn:dem":1340,
    "gn:feature_class":"P",
    "gn:feature_code":"PPL",
    "gn:name":"Gagar",
    "gn:population":0,
    "gn:timezone":"Asia/Karachi",
    "iso:country":"PK",
    "name:hin_x_preferred":[
        "\u0917\u093e\u0917\u0930"
    ],
    "wof:name":"Gagar",
    "wof:placetype":"locality"
},
  "geometry": {"coordinates":[72.64058,34.66390999999999],"type":"Point"}
}