{
  "type": "Feature",
  "properties": {
    "gn:admin1_code":"3.0",
    "gn:asciiname":"Manrai",
    "gn:country_code":"PK",
    "gn:dem":863,
    "gn:feature_class":"P",
    "gn:feature_code":"PPL",
    "gn:name":"Manrai",
    "gn:population":0,
    "gn:timezone":"Asia/Karachi",
    "iso:country":"PK",
    "wof:name":"Manrai",
    "wof:placetype":"locality"
},
  "geometry": {"coordinates":[71.92548000000002,34.66946],"type":"Point"}
}