{
  "type": "Feature",
  "properties": {
    "gn:admin1_code":"4",
    "gn:asciiname":"Rahimpur",
    "gn:country_code":"PK",
    "gn:dem":241,
    "gn:feature_class":"P",
    "gn:feature_code":"PPL",
    "gn:name":"Rahimpur",
    "gn:population":0,
    "gn:timezone":"Asia/Karachi",
    "iso:country":"PK",
    "wof:name":"Rahimpur",
    "wof:placetype":"locality"
},
  "geometry": {"coordinates":[74.43828000000001,32.48103],"type":"Point"}
}