{
  "type": "Feature",
  "properties": {
    "gn:admin1_code":"03",
    "gn:asciiname":"Punj Naddi",
    "gn:country_code":"PK",
    "gn:dem":3325,
    "gn:feature_class":"P",
    "gn:feature_code":"PPL",
    "gn:name":"Punj Naddi",
    "gn:population":0,
    "gn:timezone":"Asia/Karachi",
    "iso:country":"PK",
    "name:und_x_variant":[
        "Panjnadi"
    ],
    "wof:name":"Punj Naddi",
    "wof:placetype":"locality"
},
  "geometry": {"coordinates":[73.32403000000002,34.74752],"type":"Point"}
}