{
  "type": "Feature",
  "properties": {
    "gn:admin1_code":"5.0",
    "gn:asciiname":"Chak Number Thirteen",
    "gn:country_code":"PK",
    "gn:dem":6,
    "gn:feature_class":"P",
    "gn:feature_code":"PPL",
    "gn:name":"Chak Number Thirteen",
    "gn:population":0,
    "gn:timezone":"Asia/Karachi",
    "iso:country":"PK",
    "wof:name":"Chak Number Thirteen",
    "wof:placetype":"locality"
},
  "geometry": {"coordinates":[68.61396999999999,24.46708],"type":"Point"}
}