{
  "type": "Feature",
  "properties": {
    "gn:admin1_code":"2.0",
    "gn:asciiname":"Spalghun Kili",
    "gn:country_code":"PK",
    "gn:dem":1474,
    "gn:feature_class":"P",
    "gn:feature_code":"PPL",
    "gn:name":"Spalghun Kili",
    "gn:population":0,
    "gn:timezone":"Asia/Karachi",
    "iso:country":"PK",
    "wof:name":"Spalghun Kili",
    "wof:placetype":"locality"
},
  "geometry": {"coordinates":[68.96974,30.92537],"type":"Point"}
}