{
  "type": "Feature",
  "properties": {
    "gn:admin1_code":"04",
    "gn:asciiname":"Nurewala",
    "gn:country_code":"PK",
    "gn:dem":170,
    "gn:feature_class":"P",
    "gn:feature_code":"PPL",
    "gn:name":"Nurewala",
    "gn:population":0,
    "gn:timezone":"Asia/Karachi",
    "iso:country":"PK",
    "name:und_x_variant":[
        "Thatti Lang",
        "Nurewala",
        "Nurew\u0101la"
    ],
    "wof:name":"Nurewala",
    "wof:placetype":"locality"
},
  "geometry": {"coordinates":[72.31914,31.77406],"type":"Point"}
}