{
  "type": "Feature",
  "properties": {
    "gn:admin1_code":"05",
    "gn:asciiname":"Sinhori",
    "gn:cc2":"PK",
    "gn:country_code":"PK",
    "gn:dem":33,
    "gn:feature_class":"P",
    "gn:feature_code":"PPL",
    "gn:name":"Sinhori",
    "gn:population":0,
    "gn:timezone":"Asia/Karachi",
    "iso:country":"PK",
    "name:und_x_variant":[
        "Sihori",
        "Sinhori"
    ],
    "wof:name":"Sinhori",
    "wof:placetype":"locality"
},
  "geometry": {"coordinates":[68.91667,26.43333],"type":"Point"}
}