{
  "type": "Feature",
  "properties": {
    "gn:admin1_code":"4.0",
    "gn:asciiname":"Punarwala",
    "gn:country_code":"PK",
    "gn:dem":145,
    "gn:feature_class":"P",
    "gn:feature_code":"PPL",
    "gn:name":"Punarwala",
    "gn:population":0,
    "gn:timezone":"Asia/Karachi",
    "iso:country":"PK",
    "name:eng_x_preferred":[
        "Punarwala"
    ],
    "wof:name":"Punarwala",
    "wof:placetype":"locality"
},
  "geometry": {"coordinates":[70.87075,30.84118],"type":"Point"}
}