{
  "type": "Feature",
  "properties": {
    "gn:admin1_code":"1.0",
    "gn:asciiname":"Khairab Haji Kalle",
    "gn:country_code":"PK",
    "gn:dem":794,
    "gn:feature_class":"P",
    "gn:feature_code":"PPL",
    "gn:name":"Khairab Haji Kalle",
    "gn:population":0,
    "gn:timezone":"Asia/Karachi",
    "iso:country":"PK",
    "wof:name":"Khairab Haji Kalle",
    "wof:placetype":"locality"
},
  "geometry": {"coordinates":[71.2897,33.91586],"type":"Point"}
}