{
  "type": "Feature",
  "properties": {
    "gn:admin1_code":"1.0",
    "gn:asciiname":"Almas Haji",
    "gn:country_code":"PK",
    "gn:dem":862,
    "gn:feature_class":"P",
    "gn:feature_code":"PPL",
    "gn:name":"Almas Haji",
    "gn:population":0,
    "gn:timezone":"Asia/Karachi",
    "iso:country":"PK",
    "name:und_x_variant":[
        "Kagap\u0101n"
    ],
    "wof:name":"Almas Haji",
    "wof:placetype":"locality"
},
  "geometry": {"coordinates":[71.23338000000003,34.6261],"type":"Point"}
}