{
  "type": "Feature",
  "properties": {
    "gn:admin1_code":"01",
    "gn:asciiname":"Daman",
    "gn:country_code":"PK",
    "gn:dem":937,
    "gn:feature_class":"P",
    "gn:feature_code":"PPL",
    "gn:name":"Daman",
    "gn:population":0,
    "gn:timezone":"Asia/Karachi",
    "iso:country":"PK",
    "name:ben_x_preferred":[
        "\u09a6\u09ae\u09a8"
    ],
    "name:bpy_x_preferred":[
        "\u09a6\u09ae\u09a8"
    ],
    "name:cat_x_preferred":[
        "Daman"
    ],
    "name:ceb_x_preferred":[
        "Daman"
    ],
    "name:deu_x_preferred":[
        "Daman"
    ],
    "name:fra_x_preferred":[
        "Daman"
    ],
    "name:nld_x_preferred":[
        "Daman"
    ],
    "name:sat_x_preferred":[
        "\u1c70\u1c5f\u1c62\u1c5a\u1c71"
    ],
    "name:slk_x_preferred":[
        "Daman"
    ],
    "name:swe_x_preferred":[
        "Daman"
    ],
    "name:tur_x_preferred":[
        "Daman"
    ],
    "name:und_x_variant":[
        "Daman Shah"
    ],
    "wof:name":"Daman",
    "wof:placetype":"locality"
},
  "geometry": {"coordinates":[71.67264,34.73589],"type":"Point"}
}