{
  "type": "Feature",
  "properties": {
    "gn:admin1_code":"4",
    "gn:asciiname":"Chak Mullanwala",
    "gn:country_code":"PK",
    "gn:dem":120,
    "gn:feature_class":"P",
    "gn:feature_code":"PPL",
    "gn:name":"Chak Mullanwala",
    "gn:population":0,
    "gn:timezone":"Asia/Karachi",
    "iso:country":"PK",
    "name:und_x_variant":[
        "Chak Mulla",
        "Chak Maulv",
        "Chak Mullanwala"
    ],
    "wof:name":"Chak Mullanwala",
    "wof:placetype":"locality"
},
  "geometry": {"coordinates":[71.00838,29.96761],"type":"Point"}
}