{
  "type": "Feature",
  "properties": {
    "gn:admin1_code":"4.0",
    "gn:asciiname":"Chak Forty A - Four Left",
    "gn:country_code":"PK",
    "gn:dem":164,
    "gn:feature_class":"P",
    "gn:feature_code":"PPL",
    "gn:name":"Chak Forty A - Four Left",
    "gn:population":0,
    "gn:timezone":"Asia/Karachi",
    "iso:country":"PK",
    "name:und_x_variant":[
        "Nautheh",
        "Nathe Bodla"
    ],
    "wof:name":"Chak Forty A - Four Left",
    "wof:placetype":"locality"
},
  "geometry": {"coordinates":[73.32929,30.56577],"type":"Point"}
}