{
  "type": "Feature",
  "properties": {
    "gn:admin1_code":"2.0",
    "gn:asciiname":"Kili Shahabad",
    "gn:country_code":"PK",
    "gn:dem":1615,
    "gn:feature_class":"P",
    "gn:feature_code":"PPL",
    "gn:name":"Kili Shahabad",
    "gn:population":0,
    "gn:timezone":"Asia/Karachi",
    "iso:country":"PK",
    "wof:name":"Kili Shahabad",
    "wof:placetype":"locality"
},
  "geometry": {"coordinates":[66.74253,30.12884],"type":"Point"}
}