{
  "type": "Feature",
  "properties": {
    "gn:admin1_code":"4.0",
    "gn:asciiname":"Dhok Baloch",
    "gn:country_code":"PK",
    "gn:dem":421,
    "gn:feature_class":"P",
    "gn:feature_code":"PPL",
    "gn:name":"Dhok Baloch",
    "gn:population":0,
    "gn:timezone":"Asia/Karachi",
    "iso:country":"PK",
    "wof:name":"Dhok Baloch",
    "wof:placetype":"locality"
},
  "geometry": {"coordinates":[72.65448000000001,33.6407],"type":"Point"}
}