{
  "type": "Feature",
  "properties": {
    "gn:admin1_code":"5.0",
    "gn:asciiname":"Muhammad Khan",
    "gn:country_code":"PK",
    "gn:dem":55,
    "gn:feature_class":"P",
    "gn:feature_code":"PPL",
    "gn:name":"Muhammad Khan",
    "gn:population":0,
    "gn:timezone":"Asia/Karachi",
    "iso:country":"PK",
    "name:eng_x_preferred":[
        "Goth Mohmmed Kh\u0101n"
    ],
    "wof:name":"Muhammad Khan",
    "wof:placetype":"locality"
},
  "geometry": {"coordinates":[68.58024,27.49552000000001],"type":"Point"}
}