{
  "type": "Feature",
  "properties": {
    "gn:admin1_code":"5.0",
    "gn:asciiname":"Siddiq Jat",
    "gn:country_code":"PK",
    "gn:dem":9,
    "gn:feature_class":"P",
    "gn:feature_code":"PPL",
    "gn:name":"Siddiq Jat",
    "gn:population":0,
    "gn:timezone":"Asia/Karachi",
    "iso:country":"PK",
    "name:eng_x_preferred":[
        "Siddiq Jat"
    ],
    "wof:name":"Siddiq Jat",
    "wof:placetype":"locality"
},
  "geometry": {"coordinates":[68.25964999999999,24.63785],"type":"Point"}
}