{
  "type": "Feature",
  "properties": {
    "gn:admin1_code":"6",
    "gn:asciiname":"Parwali Mohri",
    "gn:country_code":"PK",
    "gn:dem":2379,
    "gn:feature_class":"P",
    "gn:feature_code":"PPL",
    "gn:name":"Parwali Mohri",
    "gn:population":0,
    "gn:timezone":"Asia/Karachi",
    "iso:country":"PK",
    "name:und_x_variant":[
        "Parnali Mohri"
    ],
    "wof:name":"Parwali Mohri",
    "wof:placetype":"locality"
},
  "geometry": {"coordinates":[73.46244,34.5356],"type":"Point"}
}