{
  "type": "Feature",
  "properties": {
    "gn:admin1_code":"2.0",
    "gn:asciiname":"Kili Jamadar Qadir Nuli",
    "gn:country_code":"PK",
    "gn:dem":788,
    "gn:feature_class":"P",
    "gn:feature_code":"PPL",
    "gn:name":"Kili Jamadar Qadir Nuli",
    "gn:population":0,
    "gn:timezone":"Asia/Karachi",
    "iso:country":"PK",
    "wof:name":"Kili Jamadar Qadir Nuli",
    "wof:placetype":"locality"
},
  "geometry": {"coordinates":[63.73116,28.82072],"type":"Point"}
}