{
  "type": "Feature",
  "properties": {
    "gn:admin1_code":"4.0",
    "gn:asciiname":"Dogah",
    "gn:country_code":"PK",
    "gn:dem":267,
    "gn:feature_class":"P",
    "gn:feature_code":"PPL",
    "gn:name":"Dogah",
    "gn:population":0,
    "gn:timezone":"Asia/Karachi",
    "iso:country":"PK",
    "name:und_x_variant":[
        "Doga",
        "Dogoh",
        "Dogah"
    ],
    "wof:name":"Dogah",
    "wof:placetype":"locality"
},
  "geometry": {"coordinates":[74.07889,32.7298],"type":"Point"}
}