{
  "type": "Feature",
  "properties": {
    "gn:admin1_code":"4.0",
    "gn:asciiname":"Mohra Tarla",
    "gn:country_code":"PK",
    "gn:dem":759,
    "gn:feature_class":"P",
    "gn:feature_code":"PPL",
    "gn:name":"Mohra Tarla",
    "gn:population":0,
    "gn:timezone":"Asia/Karachi",
    "iso:country":"PK",
    "wof:name":"Mohra Tarla",
    "wof:placetype":"locality"
},
  "geometry": {"coordinates":[73.16025999999999,32.80453],"type":"Point"}
}