{
  "type": "Feature",
  "properties": {
    "gn:admin1_code":"04",
    "gn:asciiname":"Mahmud Shahid",
    "gn:country_code":"PK",
    "gn:dem":190,
    "gn:feature_class":"P",
    "gn:feature_code":"PPL",
    "gn:name":"Mahmud Shahid",
    "gn:population":0,
    "gn:timezone":"Asia/Karachi",
    "iso:country":"PK",
    "name:und_x_variant":[
        "Mahmud Shadid",
        "Mahmud Shahid"
    ],
    "wof:name":"Mahmud Shahid",
    "wof:placetype":"locality"
},
  "geometry": {"coordinates":[71.71366999999999,31.90853],"type":"Point"}
}