{
  "type": "Feature",
  "properties": {
    "gn:admin1_code":"2.0",
    "gn:asciiname":"Khuddi Muhammad Rahim",
    "gn:country_code":"PK",
    "gn:dem":2730,
    "gn:feature_class":"P",
    "gn:feature_code":"PPL",
    "gn:name":"Khuddi Muhammad Rahim",
    "gn:population":0,
    "gn:timezone":"Asia/Karachi",
    "iso:country":"PK",
    "wof:name":"Khuddi Muhammad Rahim",
    "wof:placetype":"locality"
},
  "geometry": {"coordinates":[66.78278,28.94323],"type":"Point"}
}