{
  "type": "Feature",
  "properties": {
    "gn:admin1_code":"04",
    "gn:asciiname":"Randhir",
    "gn:country_code":"PK",
    "gn:dem":247,
    "gn:feature_class":"P",
    "gn:feature_code":"PPL",
    "gn:name":"Randhir",
    "gn:population":0,
    "gn:timezone":"Asia/Karachi",
    "iso:country":"PK",
    "wof:name":"Randhir",
    "wof:placetype":"locality"
},
  "geometry": {"coordinates":[74.39560999999998,32.65414000000001],"type":"Point"}
}