{
  "type": "Feature",
  "properties": {
    "gn:admin1_code":"3.0",
    "gn:asciiname":"Jhok Mangal",
    "gn:country_code":"PK",
    "gn:dem":238,
    "gn:feature_class":"P",
    "gn:feature_code":"PPL",
    "gn:name":"Jhok Mangal",
    "gn:population":0,
    "gn:timezone":"Asia/Karachi",
    "iso:country":"PK",
    "name:und_x_variant":[
        "Mangal",
        "Jhok Mangal"
    ],
    "wof:name":"Jhok Mangal",
    "wof:placetype":"locality"
},
  "geometry": {"coordinates":[70.40554,31.39924],"type":"Point"}
}