{
  "type": "Feature",
  "properties": {
    "gn:admin1_code":"7.0",
    "gn:asciiname":"Daras",
    "gn:country_code":"PK",
    "gn:dem":2286,
    "gn:feature_class":"P",
    "gn:feature_code":"PPL",
    "gn:name":"Daras",
    "gn:population":0,
    "gn:timezone":"Asia/Karachi",
    "iso:country":"PK",
    "wof:name":"Daras",
    "wof:placetype":"locality"
},
  "geometry": {"coordinates":[74.14205,36.03713],"type":"Point"}
}