{
  "type": "Feature",
  "properties": {
    "gn:admin1_code":"4",
    "gn:asciiname":"Chak One Hundred Thirty-eight Nine Left",
    "gn:country_code":"PK",
    "gn:dem":167,
    "gn:feature_class":"P",
    "gn:feature_code":"PPL",
    "gn:name":"Chak One Hundred Thirty-eight Nine Left",
    "gn:population":0,
    "gn:timezone":"Asia/Karachi",
    "iso:country":"PK",
    "name:und_x_variant":[
        "New Chak One Hundred Thirty-eight-Nine L"
    ],
    "wof:name":"Chak One Hundred Thirty-eight Nine Left",
    "wof:placetype":"locality"
},
  "geometry": {"coordinates":[72.98439999999999,30.5873],"type":"Point"}
}