{
  "type": "Feature",
  "properties": {
    "gn:admin1_code":"4",
    "gn:asciiname":"Chak Twenty-four Dara Nawab Branch",
    "gn:country_code":"PK",
    "gn:dem":109,
    "gn:feature_class":"P",
    "gn:feature_code":"PPL",
    "gn:name":"Chak Twenty-four Dara Nawab Branch",
    "gn:population":0,
    "gn:timezone":"Asia/Karachi",
    "iso:country":"PK",
    "name:und_x_variant":[
        "Chak 24 D N B"
    ],
    "wof:name":"Chak Twenty-four Dara Nawab Branch",
    "wof:placetype":"locality"
},
  "geometry": {"coordinates":[71.36395,29.11153],"type":"Point"}
}