{
  "type": "Feature",
  "properties": {
    "gn:admin1_code":"02",
    "gn:asciiname":"Yadgar",
    "gn:country_code":"PK",
    "gn:dem":824,
    "gn:feature_class":"P",
    "gn:feature_code":"PPL",
    "gn:name":"Yadgar",
    "gn:population":0,
    "gn:timezone":"Asia/Karachi",
    "iso:country":"PK",
    "name:und_x_variant":[
        "Y\u0101dg\u0101r Chauki",
        "Yadgar"
    ],
    "wof:name":"Yadgar",
    "wof:placetype":"locality"
},
  "geometry": {"coordinates":[64.93800999999999,28.96161],"type":"Point"}
}