{
  "type": "Feature",
  "properties": {
    "gn:admin1_code":"03",
    "gn:asciiname":"Qalagai",
    "gn:country_code":"PK",
    "gn:dem":1191,
    "gn:feature_class":"P",
    "gn:feature_code":"PPL",
    "gn:name":"Qalagai",
    "gn:population":0,
    "gn:timezone":"Asia/Karachi",
    "iso:country":"PK",
    "wof:name":"Qalagai",
    "wof:placetype":"locality"
},
  "geometry": {"coordinates":[71.83017,34.88212],"type":"Point"}
}