{
  "type": "Feature",
  "properties": {
    "gn:admin1_code":"2.0",
    "gn:asciiname":"Kili Nek Muhammad",
    "gn:country_code":"PK",
    "gn:dem":1094,
    "gn:feature_class":"P",
    "gn:feature_code":"PPL",
    "gn:name":"Kili Nek Muhammad",
    "gn:population":0,
    "gn:timezone":"Asia/Karachi",
    "iso:country":"PK",
    "name:und_x_variant":[
        "Honak"
    ],
    "wof:name":"Kili Nek Muhammad",
    "wof:placetype":"locality"
},
  "geometry": {"coordinates":[63.38715,29.19899],"type":"Point"}
}