{
  "type": "Feature",
  "properties": {
    "gn:admin1_code":"4.0",
    "gn:asciiname":"Wara Allahdad",
    "gn:country_code":"PK",
    "gn:dem":221,
    "gn:feature_class":"P",
    "gn:feature_code":"PPL",
    "gn:name":"Wara Allahdad",
    "gn:population":0,
    "gn:timezone":"Asia/Karachi",
    "iso:country":"PK",
    "name:und_x_variant":[
        "Umar D\u012bn de W\u0101ra"
    ],
    "wof:name":"Wara Allahdad",
    "wof:placetype":"locality"
},
  "geometry": {"coordinates":[74.50824,31.56681],"type":"Point"}
}