{
  "type": "Feature",
  "properties": {
    "gn:admin1_code":"3",
    "gn:asciiname":"Meragai",
    "gn:country_code":"PK",
    "gn:dem":476,
    "gn:elevation":"469.0",
    "gn:feature_class":"P",
    "gn:feature_code":"PPL",
    "gn:name":"Meragai",
    "gn:population":0,
    "gn:timezone":"Asia/Karachi",
    "iso:country":"PK",
    "wof:name":"Meragai",
    "wof:placetype":"locality"
},
  "geometry": {"coordinates":[72.59477,34.20759],"type":"Point"}
}