{
  "type": "Feature",
  "properties": {
    "gn:admin1_code":"6.0",
    "gn:asciiname":"Lawan Kot",
    "gn:country_code":"PK",
    "gn:dem":1444,
    "gn:feature_class":"P",
    "gn:feature_code":"PPL",
    "gn:name":"Lawan Kot",
    "gn:population":0,
    "gn:timezone":"Asia/Karachi",
    "iso:country":"PK",
    "name:und_x_variant":[
        "Lahaw\u0101n Kothi\u0101n"
    ],
    "wof:name":"Lawan Kot",
    "wof:placetype":"locality"
},
  "geometry": {"coordinates":[73.71717,33.79481],"type":"Point"}
}