{
  "type": "Feature",
  "properties": {
    "gn:admin1_code":"2.0",
    "gn:asciiname":"Awadan",
    "gn:country_code":"PK",
    "gn:dem":39,
    "gn:feature_class":"P",
    "gn:feature_code":"PPL",
    "gn:name":"Awadan",
    "gn:population":0,
    "gn:timezone":"Asia/Karachi",
    "iso:country":"PK",
    "wof:name":"Awadan",
    "wof:placetype":"locality"
},
  "geometry": {"coordinates":[66.63160999999999,25.78743],"type":"Point"}
}