{
  "type": "Feature",
  "properties": {
    "gn:admin1_code":"3",
    "gn:asciiname":"Urnian-da-Nakka",
    "gn:country_code":"PK",
    "gn:dem":2781,
    "gn:feature_class":"P",
    "gn:feature_code":"PPL",
    "gn:name":"Urnian-da-Nakka",
    "gn:population":0,
    "gn:timezone":"Asia/Karachi",
    "iso:country":"PK",
    "wof:name":"Urnian-da-Nakka",
    "wof:placetype":"locality"
},
  "geometry": {"coordinates":[73.66634000000001,34.73922],"type":"Point"}
}