{
  "type": "Feature",
  "properties": {
    "gn:admin1_code":"2.0",
    "gn:asciiname":"Kili Malik Roshan",
    "gn:country_code":"PK",
    "gn:dem":858,
    "gn:feature_class":"P",
    "gn:feature_code":"PPL",
    "gn:name":"Kili Malik Roshan",
    "gn:population":0,
    "gn:timezone":"Asia/Karachi",
    "iso:country":"PK",
    "wof:name":"Kili Malik Roshan",
    "wof:placetype":"locality"
},
  "geometry": {"coordinates":[64.67766,29.24341],"type":"Point"}
}