{
  "type": "Feature",
  "properties": {
    "gn:admin1_code":"4.0",
    "gn:asciiname":"Rustliwala",
    "gn:country_code":"PK",
    "gn:dem":169,
    "gn:feature_class":"P",
    "gn:feature_code":"PPL",
    "gn:name":"Rustliwala",
    "gn:population":0,
    "gn:timezone":"Asia/Karachi",
    "iso:country":"PK",
    "name:und_x_variant":[
        "Rastalwala",
        "Rustliwala"
    ],
    "wof:name":"Rustliwala",
    "wof:placetype":"locality"
},
  "geometry": {"coordinates":[72.47709999999999,31.60856],"type":"Point"}
}