{
  "type": "Feature",
  "properties": {
    "gn:admin1_code":"04",
    "gn:asciiname":"Chak Four Hundred Fourty-five Jhang Branch",
    "gn:country_code":"PK",
    "gn:dem":159,
    "gn:feature_class":"P",
    "gn:feature_code":"PPL",
    "gn:name":"Chak Four Hundred Fourty-five Jhang Branch",
    "gn:population":0,
    "gn:timezone":"Asia/Karachi",
    "iso:country":"PK",
    "name:und_x_variant":[
        "Patu\u0101na",
        "Chak 445",
        "Chak Four Hundred Fourty-Five",
        "Chak Four Hundred Fourty-five Jhang Branch",
        "Path\u0101n\u0101n"
    ],
    "wof:name":"Chak Four Hundred Fourty-five Jhang Branch",
    "wof:placetype":"locality"
},
  "geometry": {"coordinates":[72.46776,31.20662],"type":"Point"}
}