{
  "type": "Feature",
  "properties": {
    "gn:admin1_code":"2",
    "gn:asciiname":"Marki",
    "gn:country_code":"PK",
    "gn:dem":1142,
    "gn:feature_class":"P",
    "gn:feature_code":"PPL",
    "gn:name":"Marki",
    "gn:population":0,
    "gn:timezone":"Asia/Karachi",
    "iso:country":"PK",
    "wof:name":"Marki",
    "wof:placetype":"locality"
},
  "geometry": {"coordinates":[66.16473000000001,27.57288],"type":"Point"}
}