{
  "type": "Feature",
  "properties": {
    "gn:admin1_code":"2",
    "gn:asciiname":"Gul Sher Jhalwani",
    "gn:country_code":"PK",
    "gn:dem":1320,
    "gn:feature_class":"P",
    "gn:feature_code":"PPL",
    "gn:name":"Gul Sher Jhalwani",
    "gn:population":0,
    "gn:timezone":"Asia/Karachi",
    "iso:country":"PK",
    "name:und_x_variant":[
        "Jhalw\u0101ni Kili"
    ],
    "wof:name":"Gul Sher Jhalwani",
    "wof:placetype":"locality"
},
  "geometry": {"coordinates":[69.86389,30.28855],"type":"Point"}
}