{
  "type": "Feature",
  "properties": {
    "gn:admin1_code":"5",
    "gn:asciiname":"Mithrahu",
    "gn:country_code":"PK",
    "gn:dem":51,
    "gn:feature_class":"P",
    "gn:feature_code":"PPL",
    "gn:name":"Mithrahu",
    "gn:population":0,
    "gn:timezone":"Asia/Karachi",
    "iso:country":"PK",
    "name:und_x_variant":[
        "Mithr\u0101hu Tas"
    ],
    "wof:name":"Mithrahu",
    "wof:placetype":"locality"
},
  "geometry": {"coordinates":[69.46866999999999,26.59681],"type":"Point"}
}