{
  "type": "Feature",
  "properties": {
    "gn:admin1_code":"1.0",
    "gn:asciiname":"Maliano Kili",
    "gn:country_code":"PK",
    "gn:dem":2009,
    "gn:feature_class":"P",
    "gn:feature_code":"PPL",
    "gn:name":"Maliano Kili",
    "gn:population":0,
    "gn:timezone":"Asia/Karachi",
    "iso:country":"PK",
    "name:und_x_variant":[
        "Kulal\u0101no Kalai",
        "Kulal\u0101no Kili",
        "Maliano Kili"
    ],
    "wof:name":"Maliano Kili",
    "wof:placetype":"locality"
},
  "geometry": {"coordinates":[69.96316,33.94076],"type":"Point"}
}