{
  "type": "Feature",
  "properties": {
    "gn:admin1_code":"4.0",
    "gn:asciiname":"Dhok Nasirian",
    "gn:country_code":"PK",
    "gn:dem":400,
    "gn:feature_class":"P",
    "gn:feature_code":"PPL",
    "gn:name":"Dhok Nasirian",
    "gn:population":0,
    "gn:timezone":"Asia/Karachi",
    "iso:country":"PK",
    "wof:name":"Dhok Nasirian",
    "wof:placetype":"locality"
},
  "geometry": {"coordinates":[73.3381,32.88026],"type":"Point"}
}