{
  "type": "Feature",
  "properties": {
    "gn:admin1_code":"02",
    "gn:asciiname":"Manara Kalan",
    "gn:country_code":"PK",
    "gn:dem":1626,
    "gn:feature_class":"P",
    "gn:feature_code":"PPL",
    "gn:name":"Manara Kalan",
    "gn:population":0,
    "gn:timezone":"Asia/Karachi",
    "iso:country":"PK",
    "name:und_x_variant":[
        "Mun\u0101ra"
    ],
    "wof:name":"Manara Kalan",
    "wof:placetype":"locality"
},
  "geometry": {"coordinates":[68.4139,30.41509000000001],"type":"Point"}
}