{
  "type": "Feature",
  "properties": {
    "gn:admin1_code":"6.0",
    "gn:asciiname":"Jolanara",
    "gn:country_code":"PK",
    "gn:dem":1826,
    "gn:feature_class":"P",
    "gn:feature_code":"PPL",
    "gn:name":"Jolanara",
    "gn:population":0,
    "gn:timezone":"Asia/Karachi",
    "iso:country":"PK",
    "wof:name":"Jolanara",
    "wof:placetype":"locality"
},
  "geometry": {"coordinates":[73.67959,33.90573],"type":"Point"}
}