{
  "type": "Feature",
  "properties": {
    "gn:admin1_code":"2.0",
    "gn:asciiname":"New Hakimabad",
    "gn:country_code":"PK",
    "gn:dem":1483,
    "gn:feature_class":"P",
    "gn:feature_code":"PPL",
    "gn:name":"New Hakimabad",
    "gn:population":0,
    "gn:timezone":"Asia/Karachi",
    "iso:country":"PK",
    "wof:name":"New Hakimabad",
    "wof:placetype":"locality"
},
  "geometry": {"coordinates":[66.91696999999999,30.66783],"type":"Point"}
}