{
  "type": "Feature",
  "properties": {
    "gn:admin1_code":"03",
    "gn:asciiname":"Amal Khel",
    "gn:country_code":"PK",
    "gn:dem":342,
    "gn:feature_class":"P",
    "gn:feature_code":"PPL",
    "gn:name":"Amal Khel",
    "gn:population":0,
    "gn:timezone":"Asia/Karachi",
    "iso:country":"PK",
    "name:und_x_variant":[
        "M\u0101ma Khel",
        "Amal Khel"
    ],
    "wof:name":"Amal Khel",
    "wof:placetype":"locality"
},
  "geometry": {"coordinates":[70.78666,32.98799],"type":"Point"}
}