{
  "type": "Feature",
  "properties": {
    "gn:admin1_code":"1.0",
    "gn:asciiname":"Kazhikai",
    "gn:country_code":"PK",
    "gn:dem":1427,
    "gn:feature_class":"P",
    "gn:feature_code":"PPL",
    "gn:name":"Kazhikai",
    "gn:population":0,
    "gn:timezone":"Asia/Karachi",
    "iso:country":"PK",
    "name:und_x_variant":[
        "Kazn\u012bkai",
        "Kazhikai Iral Khel"
    ],
    "wof:name":"Kazhikai",
    "wof:placetype":"locality"
},
  "geometry": {"coordinates":[70.02497,32.56319000000001],"type":"Point"}
}