{
  "type": "Feature",
  "properties": {
    "gn:admin1_code":"2.0",
    "gn:asciiname":"Chehdai",
    "gn:country_code":"PK",
    "gn:dem":1419,
    "gn:feature_class":"P",
    "gn:feature_code":"PPL",
    "gn:name":"Chehdai",
    "gn:population":0,
    "gn:timezone":"Asia/Karachi",
    "iso:country":"PK",
    "name:eng_x_preferred":[
        "Chehdai"
    ],
    "wof:name":"Chehdai",
    "wof:placetype":"locality"
},
  "geometry": {"coordinates":[66.05996,29.0793],"type":"Point"}
}