{
  "type": "Feature",
  "properties": {
    "gn:admin1_code":"4",
    "gn:asciiname":"Gurha Burj",
    "gn:country_code":"PK",
    "gn:dem":278,
    "gn:feature_class":"P",
    "gn:feature_code":"PPL",
    "gn:name":"Gurha Burj",
    "gn:population":0,
    "gn:timezone":"Asia/Karachi",
    "iso:country":"PK",
    "name:und_x_variant":[
        "Gora Burj"
    ],
    "wof:name":"Gurha Burj",
    "wof:placetype":"locality"
},
  "geometry": {"coordinates":[73.90132,32.96969],"type":"Point"}
}