{
  "type": "Feature",
  "properties": {
    "gn:admin1_code":"3",
    "gn:asciiname":"Kabgani",
    "gn:country_code":"PK",
    "gn:dem":585,
    "gn:feature_class":"P",
    "gn:feature_code":"PPL",
    "gn:name":"Kabgani",
    "gn:population":0,
    "gn:timezone":"Asia/Karachi",
    "iso:country":"PK",
    "name:fas_x_preferred":[
        "\u06a9\u0628\u06af\u0646\u06cc"
    ],
    "name:und_x_variant":[
        "K\u0101gbanri"
    ],
    "name:urd_x_preferred":[
        "\u06a9\u0628\u06af\u0646\u06cc"
    ],
    "wof:name":"Kabgani",
    "wof:placetype":"locality"
},
  "geometry": {"coordinates":[72.68069,34.18314],"type":"Point"}
}