{
  "type": "Feature",
  "properties": {
    "gn:admin1_code":"2.0",
    "gn:asciiname":"Nawab Rabat",
    "gn:country_code":"PK",
    "gn:dem":1154,
    "gn:feature_class":"P",
    "gn:feature_code":"PPL",
    "gn:name":"Nawab Rabat",
    "gn:population":0,
    "gn:timezone":"Asia/Karachi",
    "iso:country":"PK",
    "name:und_x_variant":[
        "M\u012br J\u0101n Kili"
    ],
    "wof:name":"Nawab Rabat",
    "wof:placetype":"locality"
},
  "geometry": {"coordinates":[68.55877,30.21941],"type":"Point"}
}