{
  "type": "Feature",
  "properties": {
    "gn:admin1_code":"4.0",
    "gn:asciiname":"Chak Two Hundred Sixty-four",
    "gn:country_code":"PK",
    "gn:dem":82,
    "gn:feature_class":"P",
    "gn:feature_code":"PPL",
    "gn:name":"Chak Two Hundred Sixty-four",
    "gn:population":0,
    "gn:timezone":"Asia/Karachi",
    "iso:country":"PK",
    "wof:name":"Chak Two Hundred Sixty-four",
    "wof:placetype":"locality"
},
  "geometry": {"coordinates":[70.8002,28.70411],"type":"Point"}
}