{
  "type": "Feature",
  "properties": {
    "gn:admin1_code":"4.0",
    "gn:asciiname":"Dalip Singh",
    "gn:country_code":"PK",
    "gn:dem":133,
    "gn:feature_class":"P",
    "gn:feature_code":"PPL",
    "gn:name":"Dalip Singh",
    "gn:population":0,
    "gn:timezone":"Asia/Karachi",
    "iso:country":"PK",
    "name:deu_x_preferred":[
        "Dalip Singh"
    ],
    "name:hin_x_preferred":[
        "\u0926\u0932\u0940\u092a \u0938\u093f\u0902\u0939"
    ],
    "name:nld_x_preferred":[
        "Dalip Singh"
    ],
    "wof:name":"Dalip Singh",
    "wof:placetype":"locality"
},
  "geometry": {"coordinates":[71.83237,30.3432],"type":"Point"}
}