{
  "type": "Feature",
  "properties": {
    "gn:admin1_code":"3.0",
    "gn:asciiname":"Asman Banda",
    "gn:country_code":"PK",
    "gn:dem":3562,
    "gn:feature_class":"P",
    "gn:feature_code":"PPL",
    "gn:name":"Asman Banda",
    "gn:population":0,
    "gn:timezone":"Asia/Karachi",
    "iso:country":"PK",
    "wof:name":"Asman Banda",
    "wof:placetype":"locality"
},
  "geometry": {"coordinates":[72.61171,35.67554000000001],"type":"Point"}
}