{
  "type": "Feature",
  "properties": {
    "gn:admin1_code":"2.0",
    "gn:asciiname":"Goth Ghulam Rasul",
    "gn:country_code":"PK",
    "gn:dem":109,
    "gn:feature_class":"P",
    "gn:feature_code":"PPL",
    "gn:name":"Goth Ghulam Rasul",
    "gn:population":0,
    "gn:timezone":"Asia/Karachi",
    "iso:country":"PK",
    "name:und_x_variant":[
        "Goth Ghul\u0101m Rasul",
        "Goth Babry",
        "Goth Ghulam Rasul"
    ],
    "wof:name":"Goth Ghulam Rasul",
    "wof:placetype":"locality"
},
  "geometry": {"coordinates":[67.11794999999999,25.33092000000001],"type":"Point"}
}