{
  "type": "Feature",
  "properties": {
    "gn:admin1_code":"3",
    "gn:asciiname":"Banowali",
    "gn:country_code":"PK",
    "gn:dem":1548,
    "gn:feature_class":"P",
    "gn:feature_code":"PPL",
    "gn:name":"Banowali",
    "gn:population":0,
    "gn:timezone":"Asia/Karachi",
    "iso:country":"PK",
    "name:und_x_variant":[
        "Banrw\u0101li"
    ],
    "wof:name":"Banowali",
    "wof:placetype":"locality"
},
  "geometry": {"coordinates":[73.09662,34.61464],"type":"Point"}
}