{
  "type": "Feature",
  "properties": {
    "gn:admin1_code":"03",
    "gn:asciiname":"Shanggir",
    "gn:country_code":"PK",
    "gn:dem":1174,
    "gn:feature_class":"P",
    "gn:feature_code":"PPL",
    "gn:name":"Shanggir",
    "gn:population":0,
    "gn:timezone":"Asia/Karachi",
    "iso:country":"PK",
    "name:eng_x_preferred":[
        "Sangar"
    ],
    "wof:name":"Shanggir",
    "wof:placetype":"locality"
},
  "geometry": {"coordinates":[71.60002,34.94947],"type":"Point"}
}