{
  "type": "Feature",
  "properties": {
    "gn:admin1_code":"3",
    "gn:asciiname":"Bianga",
    "gn:country_code":"PK",
    "gn:dem":764,
    "gn:feature_class":"P",
    "gn:feature_code":"PPL",
    "gn:name":"Bianga",
    "gn:population":0,
    "gn:timezone":"Asia/Karachi",
    "iso:country":"PK",
    "wof:name":"Bianga",
    "wof:placetype":"locality"
},
  "geometry": {"coordinates":[72.65201999999999,34.52467],"type":"Point"}
}