{
  "type": "Feature",
  "properties": {
    "gn:admin1_code":"5",
    "gn:asciiname":"Gorhi",
    "gn:country_code":"PK",
    "gn:dem":52,
    "gn:feature_class":"P",
    "gn:feature_code":"PPL",
    "gn:name":"Gorhi",
    "gn:population":0,
    "gn:timezone":"Asia/Karachi",
    "iso:country":"PK",
    "name:und_x_variant":[
        "Garhi"
    ],
    "wof:name":"Gorhi",
    "wof:placetype":"locality"
},
  "geometry": {"coordinates":[68.12905000000001,27.67506],"type":"Point"}
}