{
  "type": "Feature",
  "properties": {
    "gn:admin1_code":"3",
    "gn:asciiname":"Batangi",
    "gn:country_code":"PK",
    "gn:dem":1538,
    "gn:feature_class":"P",
    "gn:feature_code":"PPL",
    "gn:name":"Batangi",
    "gn:population":0,
    "gn:timezone":"Asia/Karachi",
    "iso:country":"PK",
    "name:fas_x_preferred":[
        "\u0628\u062a\u0646\u06af\u06cc"
    ],
    "wof:name":"Batangi",
    "wof:placetype":"locality"
},
  "geometry": {"coordinates":[73.0878,34.5962],"type":"Point"}
}