{
  "type": "Feature",
  "properties": {
    "gn:admin1_code":"2.0",
    "gn:asciiname":"Thul i Darya Khan",
    "gn:country_code":"PK",
    "gn:dem":1647,
    "gn:feature_class":"P",
    "gn:feature_code":"PPL",
    "gn:name":"Thul i Darya Khan",
    "gn:population":0,
    "gn:timezone":"Asia/Karachi",
    "iso:country":"PK",
    "wof:name":"Thul i Darya Khan",
    "wof:placetype":"locality"
},
  "geometry": {"coordinates":[66.82518,29.80388],"type":"Point"}
}