{
  "type": "Feature",
  "properties": {
    "gn:admin1_code":"2",
    "gn:asciiname":"Karam Shehr",
    "gn:country_code":"PK",
    "gn:dem":1040,
    "gn:feature_class":"P",
    "gn:feature_code":"PPL",
    "gn:name":"Karam Shehr",
    "gn:population":0,
    "gn:timezone":"Asia/Karachi",
    "iso:country":"PK",
    "name:und_x_variant":[
        "Karam"
    ],
    "wof:name":"Karam Shehr",
    "wof:placetype":"locality"
},
  "geometry": {"coordinates":[69.53009,29.83255],"type":"Point"}
}