{
  "type": "Feature",
  "properties": {
    "gn:admin1_code":"4.0",
    "gn:asciiname":"Tolwanwala",
    "gn:country_code":"PK",
    "gn:dem":198,
    "gn:feature_class":"P",
    "gn:feature_code":"PPL",
    "gn:name":"Tolwanwala",
    "gn:population":0,
    "gn:timezone":"Asia/Karachi",
    "iso:country":"PK",
    "name:und_x_variant":[
        "Tolu"
    ],
    "wof:name":"Tolwanwala",
    "wof:placetype":"locality"
},
  "geometry": {"coordinates":[74.43663000000002,31.07873],"type":"Point"}
}