{
  "type": "Feature",
  "properties": {
    "gn:admin1_code":"2.0",
    "gn:asciiname":"Nare Dak",
    "gn:country_code":"PK",
    "gn:dem":1886,
    "gn:feature_class":"P",
    "gn:feature_code":"PPL",
    "gn:name":"Nare Dak",
    "gn:population":0,
    "gn:timezone":"Asia/Karachi",
    "iso:country":"PK",
    "wof:name":"Nare Dak",
    "wof:placetype":"locality"
},
  "geometry": {"coordinates":[68.19951,30.52108],"type":"Point"}
}