{
  "type": "Feature",
  "properties": {
    "gn:admin1_code":"2.0",
    "gn:asciiname":"Shahr Muhammad Bakhsh",
    "gn:country_code":"PK",
    "gn:dem":1937,
    "gn:feature_class":"P",
    "gn:feature_code":"PPL",
    "gn:name":"Shahr Muhammad Bakhsh",
    "gn:population":0,
    "gn:timezone":"Asia/Karachi",
    "iso:country":"PK",
    "wof:name":"Shahr Muhammad Bakhsh",
    "wof:placetype":"locality"
},
  "geometry": {"coordinates":[66.92254,29.60819],"type":"Point"}
}