{
  "type": "Feature",
  "properties": {
    "gn:admin1_code":"3.0",
    "gn:asciiname":"Flandra",
    "gn:country_code":"PK",
    "gn:dem":540,
    "gn:feature_class":"P",
    "gn:feature_code":"PPL",
    "gn:name":"Flandra",
    "gn:population":0,
    "gn:timezone":"Asia/Karachi",
    "iso:country":"PK",
    "wof:name":"Flandra",
    "wof:placetype":"locality"
},
  "geometry": {"coordinates":[71.98362,34.52577],"type":"Point"}
}