{
  "type": "Feature",
  "properties": {
    "gn:admin1_code":"3.0",
    "gn:asciiname":"Deuveshow",
    "gn:country_code":"PK",
    "gn:dem":1845,
    "gn:feature_class":"P",
    "gn:feature_code":"PPL",
    "gn:name":"Deuveshow",
    "gn:population":0,
    "gn:timezone":"Asia/Karachi",
    "iso:country":"PK",
    "wof:name":"Deuveshow",
    "wof:placetype":"locality"
},
  "geometry": {"coordinates":[73.16564,35.4282],"type":"Point"}
}