{
  "type": "Feature",
  "properties": {
    "gn:admin1_code":"4",
    "gn:asciiname":"Hamid",
    "gn:country_code":"PK",
    "gn:dem":191,
    "gn:feature_class":"P",
    "gn:feature_code":"PPL",
    "gn:name":"Hamid",
    "gn:population":0,
    "gn:timezone":"Asia/Karachi",
    "iso:country":"PK",
    "name:ara_x_preferred":[
        "\u062d\u0645\u064a\u062f"
    ],
    "name:cat_x_preferred":[
        "H\u00e0mid"
    ],
    "name:deu_x_preferred":[
        "Hamid"
    ],
    "name:rus_x_preferred":[
        "\u0425\u0430\u043c\u0438\u0434"
    ],
    "name:ukr_x_preferred":[
        "\u0425\u0430\u043c\u0435\u0434"
    ],
    "wof:name":"Hamid",
    "wof:placetype":"locality"
},
  "geometry": {"coordinates":[74.42222,30.80278],"type":"Point"}
}