{
  "type": "Feature",
  "properties": {
    "gn:admin1_code":"2.0",
    "gn:asciiname":"Murad Hasan",
    "gn:country_code":"PK",
    "gn:dem":506,
    "gn:feature_class":"P",
    "gn:feature_code":"PPL",
    "gn:name":"Murad Hasan",
    "gn:population":0,
    "gn:timezone":"Asia/Karachi",
    "iso:country":"PK",
    "name:ben_x_preferred":[
        "\u09ae\u09c1\u09b0\u09be\u09a6 \u09b9\u09be\u09b8\u09be\u09a8"
    ],
    "wof:name":"Murad Hasan",
    "wof:placetype":"locality"
},
  "geometry": {"coordinates":[66.52566,26.36003],"type":"Point"}
}