{
  "type": "Feature",
  "properties": {
    "gn:admin1_code":"2.0",
    "gn:asciiname":"Chukhur",
    "gn:country_code":"PK",
    "gn:dem":1546,
    "gn:feature_class":"P",
    "gn:feature_code":"PPL",
    "gn:name":"Chukhur",
    "gn:population":0,
    "gn:timezone":"Asia/Karachi",
    "iso:country":"PK",
    "wof:name":"Chukhur",
    "wof:placetype":"locality"
},
  "geometry": {"coordinates":[66.73775999999999,28.54841],"type":"Point"}
}