{
  "type": "Feature",
  "properties": {
    "gn:admin1_code":"5.0",
    "gn:asciiname":"Wadero Darya Khan Jawari",
    "gn:country_code":"PK",
    "gn:dem":7,
    "gn:feature_class":"P",
    "gn:feature_code":"PPL",
    "gn:name":"Wadero Darya Khan Jawari",
    "gn:population":0,
    "gn:timezone":"Asia/Karachi",
    "iso:country":"PK",
    "wof:name":"Wadero Darya Khan Jawari",
    "wof:placetype":"locality"
},
  "geometry": {"coordinates":[67.74469000000001,24.69521],"type":"Point"}
}