{
  "type": "Feature",
  "properties": {
    "gn:admin1_code":"4.0",
    "gn:asciiname":"Pana-de-Jhok",
    "gn:country_code":"PK",
    "gn:dem":129,
    "gn:feature_class":"P",
    "gn:feature_code":"PPL",
    "gn:name":"Pana-de-Jhok",
    "gn:population":0,
    "gn:timezone":"Asia/Karachi",
    "iso:country":"PK",
    "wof:name":"Pana-de-Jhok",
    "wof:placetype":"locality"
},
  "geometry": {"coordinates":[72.19304,29.66589],"type":"Point"}
}