{
  "type": "Feature",
  "properties": {
    "gn:admin1_code":"3",
    "gn:asciiname":"Kade",
    "gn:country_code":"PK",
    "gn:dem":352,
    "gn:feature_class":"P",
    "gn:feature_code":"PPL",
    "gn:name":"Kade",
    "gn:population":0,
    "gn:timezone":"Asia/Karachi",
    "iso:country":"PK",
    "name:ceb_x_preferred":[
        "Kade"
    ],
    "name:deu_x_preferred":[
        "Kade"
    ],
    "name:eng_x_preferred":[
        "Kadai"
    ],
    "name:epo_x_preferred":[
        "Kade"
    ],
    "name:fas_x_preferred":[
        "\u06a9\u0627\u062f\u0647"
    ],
    "name:ita_x_preferred":[
        "Kade"
    ],
    "name:kaz_x_preferred":[
        "\u041a\u0430\u0434\u0435"
    ],
    "name:mkd_x_preferred":[
        "\u041a\u0430\u0434\u0435"
    ],
    "name:nld_x_preferred":[
        "Kade"
    ],
    "name:ron_x_preferred":[
        "Kade"
    ],
    "name:rus_x_preferred":[
        "\u041a\u0430\u0434\u0435"
    ],
    "name:und_x_variant":[
        "Bar Kadai",
        "Kade"
    ],
    "name:uzb_x_preferred":[
        "Kade"
    ],
    "name:vol_x_preferred":[
        "Kade"
    ],
    "wof:name":"Kade",
    "wof:placetype":"locality"
},
  "geometry": {"coordinates":[72.35429999999999,34.14723],"type":"Point"}
}