{
  "type": "Feature",
  "properties": {
    "gn:admin1_code":"4.0",
    "gn:asciiname":"Dhok Chanwal",
    "gn:country_code":"PK",
    "gn:dem":364,
    "gn:feature_class":"P",
    "gn:feature_code":"PPL",
    "gn:name":"Dhok Chanwal",
    "gn:population":0,
    "gn:timezone":"Asia/Karachi",
    "iso:country":"PK",
    "name:und_x_variant":[
        "Dhok Janw\u0101l"
    ],
    "wof:name":"Dhok Chanwal",
    "wof:placetype":"locality"
},
  "geometry": {"coordinates":[71.84418000000002,32.67255],"type":"Point"}
}