{
  "type": "Feature",
  "properties": {
    "gn:admin1_code":"3",
    "gn:asciiname":"Mehmun Kor",
    "gn:country_code":"PK",
    "gn:dem":369,
    "gn:feature_class":"P",
    "gn:feature_code":"PPL",
    "gn:name":"Mehmun Kor",
    "gn:population":0,
    "gn:timezone":"Asia/Karachi",
    "iso:country":"PK",
    "wof:name":"Mehmun Kor",
    "wof:placetype":"locality"
},
  "geometry": {"coordinates":[70.78174,33.02221],"type":"Point"}
}