{
  "type": "Feature",
  "properties": {
    "gn:admin1_code":"4.0",
    "gn:asciiname":"Water and Power Development Authority Colony",
    "gn:country_code":"PK",
    "gn:dem":189,
    "gn:feature_class":"P",
    "gn:feature_code":"PPL",
    "gn:name":"Water and Power Development Authority Colony",
    "gn:population":0,
    "gn:timezone":"Asia/Karachi",
    "iso:country":"PK",
    "name:und_x_variant":[
        "Water and Power Development Authority Town"
    ],
    "wof:name":"Water and Power Development Authority Colony",
    "wof:placetype":"locality"
},
  "geometry": {"coordinates":[73.21691,31.50089],"type":"Point"}
}