{
  "type": "Feature",
  "properties": {
    "gn:admin1_code":"03",
    "gn:asciiname":"Warshand",
    "gn:country_code":"PK",
    "gn:dem":463,
    "gn:feature_class":"P",
    "gn:feature_code":"PPL",
    "gn:name":"Warshand",
    "gn:population":0,
    "gn:timezone":"Asia/Karachi",
    "iso:country":"PK",
    "wof:name":"Warshand",
    "wof:placetype":"locality"
},
  "geometry": {"coordinates":[71.49634,33.35483],"type":"Point"}
}