{
  "type": "Feature",
  "properties": {
    "gn:admin1_code":"4",
    "gn:asciiname":"Lot Forty-three",
    "gn:country_code":"PK",
    "gn:dem":181,
    "gn:feature_class":"P",
    "gn:feature_code":"PPL",
    "gn:name":"Lot Forty-three",
    "gn:population":0,
    "gn:timezone":"Asia/Karachi",
    "iso:country":"PK",
    "wof:name":"Lot Forty-three",
    "wof:placetype":"locality"
},
  "geometry": {"coordinates":[71.28055999999999,31.80139],"type":"Point"}
}