{
  "type": "Feature",
  "properties": {
    "gn:admin1_code":"4",
    "gn:asciiname":"Chak Forty-two M",
    "gn:country_code":"PK",
    "gn:dem":116,
    "gn:feature_class":"P",
    "gn:feature_code":"PPL",
    "gn:name":"Chak Forty-two M",
    "gn:population":0,
    "gn:timezone":"Asia/Karachi",
    "iso:country":"PK",
    "wof:name":"Chak Forty-two M",
    "wof:placetype":"locality"
},
  "geometry": {"coordinates":[71.65416999999999,29.72639],"type":"Point"}
}