{
  "type": "Feature",
  "properties": {
    "gn:admin1_code":"6",
    "gn:asciiname":"Tarla Sukar",
    "gn:country_code":"PK",
    "gn:dem":2492,
    "gn:feature_class":"P",
    "gn:feature_code":"PPL",
    "gn:name":"Tarla Sukar",
    "gn:population":0,
    "gn:timezone":"Asia/Karachi",
    "iso:country":"PK",
    "name:und_x_variant":[
        "Tarla Sokur"
    ],
    "wof:name":"Tarla Sukar",
    "wof:placetype":"locality"
},
  "geometry": {"coordinates":[73.54261,34.54692],"type":"Point"}
}