{
  "type": "Feature",
  "properties": {
    "gn:admin1_code":"2.0",
    "gn:asciiname":"Khoro",
    "gn:country_code":"PK",
    "gn:dem":576,
    "gn:feature_class":"P",
    "gn:feature_code":"PPL",
    "gn:name":"Khoro",
    "gn:population":0,
    "gn:timezone":"Asia/Karachi",
    "iso:country":"PK",
    "wof:name":"Khoro",
    "wof:placetype":"locality"
},
  "geometry": {"coordinates":[65.70238000000001,26.72869],"type":"Point"}
}