{
  "type": "Feature",
  "properties": {
    "gn:admin1_code":"5.0",
    "gn:asciiname":"Goth Baijat",
    "gn:country_code":"PK",
    "gn:dem":17,
    "gn:feature_class":"P",
    "gn:feature_code":"PPL",
    "gn:name":"Goth Baijat",
    "gn:population":0,
    "gn:timezone":"Asia/Karachi",
    "iso:country":"PK",
    "name:und_x_variant":[
        "Goth H\u0101ji Kh\u0101n"
    ],
    "wof:name":"Goth Baijat",
    "wof:placetype":"locality"
},
  "geometry": {"coordinates":[68.63961999999999,25.02542],"type":"Point"}
}