{
  "type": "Feature",
  "properties": {
    "gn:admin1_code":"5",
    "gn:asciiname":"Jam Dhando Chhato Dhado",
    "gn:country_code":"PK",
    "gn:dem":74,
    "gn:feature_class":"P",
    "gn:feature_code":"PPL",
    "gn:name":"Jam Dhando Chhato Dhado",
    "gn:population":0,
    "gn:timezone":"Asia/Karachi",
    "iso:country":"PK",
    "name:und_x_variant":[
        "Chato Daho"
    ],
    "wof:name":"Jam Dhando Chhato Dhado",
    "wof:placetype":"locality"
},
  "geometry": {"coordinates":[69.70829000000001,28.21025],"type":"Point"}
}