{
  "type": "Feature",
  "properties": {
    "gn:admin1_code":"4.0",
    "gn:asciiname":"Chhiant",
    "gn:country_code":"PK",
    "gn:dem":1039,
    "gn:feature_class":"P",
    "gn:feature_code":"PPL",
    "gn:name":"Chhiant",
    "gn:population":0,
    "gn:timezone":"Asia/Karachi",
    "iso:country":"PK",
    "name:und_x_variant":[
        "Chent"
    ],
    "wof:name":"Chhiant",
    "wof:placetype":"locality"
},
  "geometry": {"coordinates":[73.48068000000001,33.74374],"type":"Point"}
}