{
  "type": "Feature",
  "properties": {
    "gn:admin1_code":"4.0",
    "gn:asciiname":"Alamabad",
    "gn:country_code":"PK",
    "gn:dem":542,
    "gn:feature_class":"P",
    "gn:feature_code":"PPL",
    "gn:name":"Alamabad",
    "gn:population":0,
    "gn:timezone":"Asia/Karachi",
    "iso:country":"PK",
    "name:fas_x_preferred":[
        "\u0639\u0644\u0645\u200c\u0622\u0628\u0627\u062f"
    ],
    "wof:name":"Alamabad",
    "wof:placetype":"locality"
},
  "geometry": {"coordinates":[73.15954000000001,33.01456],"type":"Point"}
}