{
  "type": "Feature",
  "properties": {
    "gn:admin1_code":"2.0",
    "gn:asciiname":"Chah Haji Azim",
    "gn:country_code":"PK",
    "gn:dem":843,
    "gn:feature_class":"P",
    "gn:feature_code":"PPL",
    "gn:name":"Chah Haji Azim",
    "gn:population":0,
    "gn:timezone":"Asia/Karachi",
    "iso:country":"PK",
    "wof:name":"Chah Haji Azim",
    "wof:placetype":"locality"
},
  "geometry": {"coordinates":[64.63464,28.83481],"type":"Point"}
}