{
  "type": "Feature",
  "properties": {
    "gn:admin1_code":"4",
    "gn:asciiname":"Chak Four Hundred Eleven - Eastern Bar",
    "gn:country_code":"PK",
    "gn:dem":148,
    "gn:feature_class":"P",
    "gn:feature_code":"PPL",
    "gn:name":"Chak Four Hundred Eleven - Eastern Bar",
    "gn:population":0,
    "gn:timezone":"Asia/Karachi",
    "iso:country":"PK",
    "name:und_x_variant":[
        "Chak Four Hundred Eleven EB"
    ],
    "wof:name":"Chak Four Hundred Eleven - Eastern Bar",
    "wof:placetype":"locality"
},
  "geometry": {"coordinates":[72.74767,30.26571],"type":"Point"}
}