{
  "type": "Feature",
  "properties": {
    "gn:admin1_code":"04",
    "gn:asciiname":"Rattapur Bala",
    "gn:country_code":"PK",
    "gn:dem":189,
    "gn:feature_class":"P",
    "gn:feature_code":"PPL",
    "gn:name":"Rattapur Bala",
    "gn:population":0,
    "gn:timezone":"Asia/Karachi",
    "iso:country":"PK",
    "name:und_x_variant":[
        "Ratt\u0101pur"
    ],
    "wof:name":"Rattapur Bala",
    "wof:placetype":"locality"
},
  "geometry": {"coordinates":[73.0133,31.90876],"type":"Point"}
}