{
  "type": "Feature",
  "properties": {
    "gn:admin1_code":"4",
    "gn:asciiname":"Chak Karim",
    "gn:country_code":"PK",
    "gn:dem":243,
    "gn:feature_class":"P",
    "gn:feature_code":"PPL",
    "gn:name":"Chak Karim",
    "gn:population":0,
    "gn:timezone":"Asia/Karachi",
    "iso:country":"PK",
    "name:und_x_variant":[
        "Karim Chak",
        "Chak Kar\u012bm"
    ],
    "wof:name":"Chak Karim",
    "wof:placetype":"locality"
},
  "geometry": {"coordinates":[74.48835,32.61431],"type":"Point"}
}