{
  "type": "Feature",
  "properties": {
    "gn:admin1_code":"2.0",
    "gn:asciiname":"Amir Khan",
    "gn:country_code":"PK",
    "gn:dem":51,
    "gn:feature_class":"P",
    "gn:feature_code":"PPL",
    "gn:name":"Amir Khan",
    "gn:population":0,
    "gn:timezone":"Asia/Karachi",
    "iso:country":"PK",
    "name:ara_x_preferred":[
        "\u0623\u0645\u064a\u0631 \u062e\u0627\u0646"
    ],
    "name:ben_x_preferred":[
        "\u0986\u09ae\u09bf\u09b0 \u0996\u09be\u09a8"
    ],
    "name:fra_x_preferred":[
        "Amir Khan"
    ],
    "name:hin_x_preferred":[
        "\u0906\u092e\u093f\u0930 \u0916\u093c\u093e\u0928"
    ],
    "name:spa_x_preferred":[
        "Amir Khan"
    ],
    "name:urd_x_preferred":[
        "\u0639\u0627\u0645\u0631 \u062e\u0627\u0646"
    ],
    "wof:name":"Amir Khan",
    "wof:placetype":"locality"
},
  "geometry": {"coordinates":[67.8939,28.0539],"type":"Point"}
}