{
  "type": "Feature",
  "properties": {
    "gn:admin1_code":"5",
    "gn:asciiname":"Idan Shah",
    "gn:country_code":"PK",
    "gn:dem":71,
    "gn:feature_class":"P",
    "gn:feature_code":"PPL",
    "gn:name":"Idan Shah",
    "gn:population":0,
    "gn:timezone":"Asia/Karachi",
    "iso:country":"PK",
    "name:und_x_variant":[
        "Idan Sh\u0101h"
    ],
    "wof:name":"Idan Shah",
    "wof:placetype":"locality"
},
  "geometry": {"coordinates":[69.25513000000001,27.95451],"type":"Point"}
}