{
  "type": "Feature",
  "properties": {
    "gn:admin1_code":"4",
    "gn:asciiname":"Qila Tek Chand",
    "gn:country_code":"PK",
    "gn:dem":184,
    "gn:feature_class":"P",
    "gn:feature_code":"PPL",
    "gn:name":"Qila Tek Chand",
    "gn:population":0,
    "gn:timezone":"Asia/Karachi",
    "iso:country":"PK",
    "wof:name":"Qila Tek Chand",
    "wof:placetype":"locality"
},
  "geometry": {"coordinates":[73.74028,31.18611],"type":"Point"}
}