{
  "type": "Feature",
  "properties": {
    "gn:admin1_code":"5.0",
    "gn:asciiname":"Idu Chang",
    "gn:country_code":"PK",
    "gn:dem":8,
    "gn:feature_class":"P",
    "gn:feature_code":"PPL",
    "gn:name":"Idu Chang",
    "gn:population":0,
    "gn:timezone":"Asia/Karachi",
    "iso:country":"PK",
    "name:und_x_variant":[
        "\u012adu Ch\u0101ng"
    ],
    "wof:name":"Idu Chang",
    "wof:placetype":"locality"
},
  "geometry": {"coordinates":[68.81206,24.60654],"type":"Point"}
}