{
  "type": "Feature",
  "properties": {
    "gn:admin1_code":"3.0",
    "gn:asciiname":"Niyok",
    "gn:country_code":"PK",
    "gn:dem":2961,
    "gn:feature_class":"P",
    "gn:feature_code":"PPL",
    "gn:name":"Niyok",
    "gn:population":0,
    "gn:timezone":"Asia/Karachi",
    "iso:country":"PK",
    "wof:name":"Niyok",
    "wof:placetype":"locality"
},
  "geometry": {"coordinates":[72.3976,36.35477],"type":"Point"}
}