{
  "type": "Feature",
  "properties": {
    "gn:admin1_code":"7.0",
    "gn:asciiname":"Boihil",
    "gn:country_code":"PK",
    "gn:dem":4096,
    "gn:feature_class":"P",
    "gn:feature_code":"PPL",
    "gn:name":"Boihil",
    "gn:population":0,
    "gn:timezone":"Asia/Karachi",
    "iso:country":"PK",
    "wof:name":"Boihil",
    "wof:placetype":"locality"
},
  "geometry": {"coordinates":[74.75763000000001,36.95316],"type":"Point"}
}