{
  "type": "Feature",
  "properties": {
    "gn:admin1_code":"5.0",
    "gn:asciiname":"Goth Singari",
    "gn:country_code":"PK",
    "gn:dem":3,
    "gn:feature_class":"P",
    "gn:feature_code":"PPL",
    "gn:name":"Goth Singari",
    "gn:population":0,
    "gn:timezone":"Asia/Karachi",
    "iso:country":"PK",
    "name:und_x_variant":[
        "Sing\u0101ri"
    ],
    "wof:name":"Goth Singari",
    "wof:placetype":"locality"
},
  "geometry": {"coordinates":[69.01049,24.3965],"type":"Point"}
}