{
  "type": "Feature",
  "properties": {
    "gn:admin1_code":"7.0",
    "gn:asciiname":"Choapa",
    "gn:country_code":"PK",
    "gn:dem":2201,
    "gn:feature_class":"P",
    "gn:feature_code":"PPL",
    "gn:name":"Choapa",
    "gn:population":0,
    "gn:timezone":"Asia/Karachi",
    "iso:country":"PK",
    "name:ceb_x_preferred":[
        "Choapa"
    ],
    "name:heb_x_preferred":[
        "\u05e6'\u05d5\u05d0\u05e4\u05d4"
    ],
    "name:ron_x_preferred":[
        "Choapa"
    ],
    "name:spa_x_preferred":[
        "Choapa"
    ],
    "name:swe_x_preferred":[
        "Choapa"
    ],
    "wof:name":"Choapa",
    "wof:placetype":"locality"
},
  "geometry": {"coordinates":[75.64313,35.35999],"type":"Point"}
}