{
  "type": "Feature",
  "properties": {
    "gn:admin1_code":"4.0",
    "gn:asciiname":"Chak Eighty-two Gugera Branch",
    "gn:country_code":"PK",
    "gn:dem":181,
    "gn:feature_class":"P",
    "gn:feature_code":"PPL",
    "gn:name":"Chak Eighty-two Gugera Branch",
    "gn:population":0,
    "gn:timezone":"Asia/Karachi",
    "iso:country":"PK",
    "name:und_x_variant":[
        "Bl\u0101ki",
        "Chak Eighty-Two RB",
        "Chak Eighty-two Gugera Branch",
        "Billaki"
    ],
    "wof:name":"Chak Eighty-two Gugera Branch",
    "wof:placetype":"locality"
},
  "geometry": {"coordinates":[73.13134000000002,31.25689],"type":"Point"}
}