{
  "type": "Feature",
  "properties": {
    "gn:admin1_code":"04",
    "gn:asciiname":"Sau",
    "gn:country_code":"PK",
    "gn:dem":468,
    "gn:feature_class":"P",
    "gn:feature_code":"PPL",
    "gn:name":"Sau",
    "gn:population":0,
    "gn:timezone":"Asia/Karachi",
    "iso:country":"PK",
    "name:und_x_variant":[
        "Sao",
        "Sau",
        "S\u0101ur",
        "Dhok Maly\u0101r",
        "Dhok Naly\u0101r"
    ],
    "wof:name":"Sau",
    "wof:placetype":"locality"
},
  "geometry": {"coordinates":[73.14564,33.06834],"type":"Point"}
}