{
  "type": "Feature",
  "properties": {
    "gn:admin1_code":"2.0",
    "gn:asciiname":"Adosh Shishan",
    "gn:country_code":"PK",
    "gn:dem":2551,
    "gn:feature_class":"P",
    "gn:feature_code":"PPL",
    "gn:name":"Adosh Shishan",
    "gn:population":0,
    "gn:timezone":"Asia/Karachi",
    "iso:country":"PK",
    "wof:name":"Adosh Shishan",
    "wof:placetype":"locality"
},
  "geometry": {"coordinates":[66.95000999999999,30.92206],"type":"Point"}
}