{
  "type": "Feature",
  "properties": {
    "gn:admin1_code":"4",
    "gn:asciiname":"Chanhawranwala",
    "gn:country_code":"PK",
    "gn:dem":164,
    "gn:feature_class":"P",
    "gn:feature_code":"PPL",
    "gn:name":"Chanhawranwala",
    "gn:population":0,
    "gn:timezone":"Asia/Karachi",
    "iso:country":"PK",
    "name:und_x_variant":[
        "Chanhawaran"
    ],
    "wof:name":"Chanhawranwala",
    "wof:placetype":"locality"
},
  "geometry": {"coordinates":[71.01886999999998,31.61687],"type":"Point"}
}