{
  "type": "Feature",
  "properties": {
    "gn:admin1_code":"2",
    "gn:asciiname":"Shahr Kambrani",
    "gn:country_code":"PK",
    "gn:dem":1785,
    "gn:feature_class":"P",
    "gn:feature_code":"PPL",
    "gn:name":"Shahr Kambrani",
    "gn:population":0,
    "gn:timezone":"Asia/Karachi",
    "iso:country":"PK",
    "wof:name":"Shahr Kambrani",
    "wof:placetype":"locality"
},
  "geometry": {"coordinates":[66.28780999999999,29.12922],"type":"Point"}
}