{
  "type": "Feature",
  "properties": {
    "gn:admin1_code":"5",
    "gn:asciiname":"Haji Karam Ali Talpur",
    "gn:country_code":"PK",
    "gn:dem":16,
    "gn:feature_class":"P",
    "gn:feature_code":"PPL",
    "gn:name":"Haji Karam Ali Talpur",
    "gn:population":0,
    "gn:timezone":"Asia/Karachi",
    "iso:country":"PK",
    "name:und_x_variant":[
        "Goth H\u0101ji Kar\u012bm Ali T\u0101lpur",
        "H\u0101ji Karam Ali T\u0101lpur Goth",
        "Haji Karam Ali Talpur"
    ],
    "wof:name":"Haji Karam Ali Talpur",
    "wof:placetype":"locality"
},
  "geometry": {"coordinates":[68.76940999999999,25.04682],"type":"Point"}
}