{
  "type": "Feature",
  "properties": {
    "gn:admin1_code":"3.0",
    "gn:asciiname":"Mira Khel",
    "gn:country_code":"PK",
    "gn:dem":323,
    "gn:feature_class":"P",
    "gn:feature_code":"PPL",
    "gn:name":"M\u012bra Khel",
    "gn:population":0,
    "gn:timezone":"Asia/Karachi",
    "iso:country":"PK",
    "name:und_x_variant":[
        "M\u012bra Khel"
    ],
    "wof:name":"Mira Khel",
    "wof:placetype":"locality"
},
  "geometry": {"coordinates":[70.645,32.85472],"type":"Point"}
}