{
  "type": "Feature",
  "properties": {
    "gn:admin1_code":"2.0",
    "gn:asciiname":"Kili Haji Muhammad",
    "gn:country_code":"PK",
    "gn:dem":1456,
    "gn:feature_class":"P",
    "gn:feature_code":"PPL",
    "gn:name":"Kili Haji Muhammad",
    "gn:population":0,
    "gn:timezone":"Asia/Karachi",
    "iso:country":"PK",
    "wof:name":"Kili Haji Muhammad",
    "wof:placetype":"locality"
},
  "geometry": {"coordinates":[65.68729999999999,27.78286],"type":"Point"}
}