{
  "type": "Feature",
  "properties": {
    "gn:admin1_code":"5",
    "gn:asciiname":"Goth Murid Khan Khoso",
    "gn:country_code":"PK",
    "gn:dem":69,
    "gn:feature_class":"P",
    "gn:feature_code":"PPL",
    "gn:name":"Goth Murid Khan Khoso",
    "gn:population":0,
    "gn:timezone":"Asia/Karachi",
    "iso:country":"PK",
    "name:und_x_variant":[
        "Murid Kh\u0101n Khosa"
    ],
    "wof:name":"Goth Murid Khan Khoso",
    "wof:placetype":"locality"
},
  "geometry": {"coordinates":[69.14102,28.32659],"type":"Point"}
}