{
  "type": "Feature",
  "properties": {
    "gn:admin1_code":"4.0",
    "gn:asciiname":"Chak One Hundred Fifty-three ML",
    "gn:country_code":"PK",
    "gn:dem":133,
    "gn:feature_class":"P",
    "gn:feature_code":"PPL",
    "gn:name":"Chak One Hundred Fifty-three ML",
    "gn:population":0,
    "gn:timezone":"Asia/Karachi",
    "iso:country":"PK",
    "name:und_x_variant":[
        "Chak One Hundred Fifty-Three TDA",
        "Chak 153 TDA",
        "Chak One Hundred Fifty-three ML"
    ],
    "wof:name":"Chak One Hundred Fifty-three ML",
    "wof:placetype":"locality"
},
  "geometry": {"coordinates":[71.02374,30.49764],"type":"Point"}
}