{
  "type": "Feature",
  "properties": {
    "gn:admin1_code":"4",
    "gn:asciiname":"Chak One Hundred Forty-one Khokhar",
    "gn:country_code":"PK",
    "gn:dem":177,
    "gn:feature_class":"P",
    "gn:feature_code":"PPL",
    "gn:name":"Chak One Hundred Forty-one Khokhar",
    "gn:population":0,
    "gn:timezone":"Asia/Karachi",
    "iso:country":"PK",
    "name:und_x_variant":[
        "Khokhar"
    ],
    "wof:name":"Chak One Hundred Forty-one Khokhar",
    "wof:placetype":"locality"
},
  "geometry": {"coordinates":[72.88535,31.58132],"type":"Point"}
}