{
  "type": "Feature",
  "properties": {
    "gn:admin1_code":"4",
    "gn:asciiname":"Jorianwali",
    "gn:country_code":"PK",
    "gn:dem":120,
    "gn:feature_class":"P",
    "gn:feature_code":"PPL",
    "gn:name":"Jorianwali",
    "gn:population":0,
    "gn:timezone":"Asia/Karachi",
    "iso:country":"PK",
    "name:und_x_variant":[
        "Charhoi\u0101nw\u0101la"
    ],
    "wof:name":"Jorianwali",
    "wof:placetype":"locality"
},
  "geometry": {"coordinates":[72.05266999999998,29.49475],"type":"Point"}
}