{
  "type": "Feature",
  "properties": {
    "gn:admin1_code":"4",
    "gn:asciiname":"Chak Sixty-five Dera Nawab Branch Janubi",
    "gn:country_code":"PK",
    "gn:dem":114,
    "gn:feature_class":"P",
    "gn:feature_code":"PPL",
    "gn:name":"Chak Sixty-five Dera Nawab Branch Janubi",
    "gn:population":0,
    "gn:timezone":"Asia/Karachi",
    "iso:country":"PK",
    "name:eng_x_preferred":[
        "Chak Sixty-five DB Jan\u016bbi"
    ],
    "wof:name":"Chak Sixty-five Dera Nawab Branch Janubi",
    "wof:placetype":"locality"
},
  "geometry": {"coordinates":[71.59104000000001,29.15863],"type":"Point"}
}