{
  "type": "Feature",
  "properties": {
    "gn:admin1_code":"5",
    "gn:asciiname":"Goth Jafar Ali",
    "gn:country_code":"PK",
    "gn:dem":69,
    "gn:feature_class":"P",
    "gn:feature_code":"PPL",
    "gn:name":"Goth Jafar Ali",
    "gn:population":0,
    "gn:timezone":"Asia/Karachi",
    "iso:country":"PK",
    "name:und_x_variant":[
        "Goth J\u0101fer Ali"
    ],
    "wof:name":"Goth Jafar Ali",
    "wof:placetype":"locality"
},
  "geometry": {"coordinates":[69.44535,27.83451],"type":"Point"}
}