{
  "type": "Feature",
  "properties": {
    "gn:admin1_code":"4",
    "gn:asciiname":"Niraliwala",
    "gn:country_code":"PK",
    "gn:dem":99,
    "gn:feature_class":"P",
    "gn:feature_code":"PPL",
    "gn:name":"Niraliwala",
    "gn:population":0,
    "gn:timezone":"Asia/Karachi",
    "iso:country":"PK",
    "wof:name":"Niraliwala",
    "wof:placetype":"locality"
},
  "geometry": {"coordinates":[70.45,29.30833],"type":"Point"}
}