{
  "type": "Feature",
  "properties": {
    "gn:admin1_code":"5",
    "gn:asciiname":"Goth Bhuro Khan Marri",
    "gn:country_code":"PK",
    "gn:dem":19,
    "gn:feature_class":"P",
    "gn:feature_code":"PPL",
    "gn:name":"Goth Bhuro Khan Marri",
    "gn:population":0,
    "gn:timezone":"Asia/Karachi",
    "iso:country":"PK",
    "wof:name":"Goth Bhuro Khan Marri",
    "wof:placetype":"locality"
},
  "geometry": {"coordinates":[68.98636999999999,25.85286],"type":"Point"}
}