{
  "type": "Feature",
  "properties": {
    "gn:admin1_code":"3.0",
    "gn:asciiname":"Tongen",
    "gn:country_code":"PK",
    "gn:dem":2383,
    "gn:feature_class":"P",
    "gn:feature_code":"PPL",
    "gn:name":"Tongen",
    "gn:population":0,
    "gn:timezone":"Asia/Karachi",
    "iso:country":"PK",
    "wof:name":"Tongen",
    "wof:placetype":"locality"
},
  "geometry": {"coordinates":[72.36957,36.39002],"type":"Point"}
}