{
  "type": "Feature",
  "properties": {
    "gn:admin1_code":"3",
    "gn:asciiname":"Kandoli",
    "gn:country_code":"PK",
    "gn:dem":1166,
    "gn:feature_class":"P",
    "gn:feature_code":"PPL",
    "gn:name":"Kandoli",
    "gn:population":0,
    "gn:timezone":"Asia/Karachi",
    "iso:country":"PK",
    "name:und_x_variant":[
        "Kandolai"
    ],
    "wof:name":"Kandoli",
    "wof:placetype":"locality"
},
  "geometry": {"coordinates":[73.05754,34.65574],"type":"Point"}
}