{
  "type": "Feature",
  "properties": {
    "gn:admin1_code":"3.0",
    "gn:asciiname":"Kot Mehi Dil",
    "gn:country_code":"PK",
    "gn:dem":326,
    "gn:feature_class":"P",
    "gn:feature_code":"PPL",
    "gn:name":"Kot Mehi Dil",
    "gn:population":0,
    "gn:timezone":"Asia/Karachi",
    "iso:country":"PK",
    "wof:name":"Kot Mehi Dil",
    "wof:placetype":"locality"
},
  "geometry": {"coordinates":[70.15361,32.14849],"type":"Point"}
}