{
  "type": "Feature",
  "properties": {
    "gn:admin1_code":"6",
    "gn:asciiname":"Draik Pattar",
    "gn:country_code":"PK",
    "gn:dem":1365,
    "gn:feature_class":"P",
    "gn:feature_code":"PPL",
    "gn:name":"Draik Pattar",
    "gn:population":0,
    "gn:timezone":"Asia/Karachi",
    "iso:country":"PK",
    "name:und_x_variant":[
        "Drek Bar"
    ],
    "wof:name":"Draik Pattar",
    "wof:placetype":"locality"
},
  "geometry": {"coordinates":[73.60605,34.46735],"type":"Point"}
}