{
  "type": "Feature",
  "properties": {
    "gn:admin1_code":"6",
    "gn:asciiname":"Sindahaki",
    "gn:country_code":"PK",
    "gn:dem":2091,
    "gn:feature_class":"P",
    "gn:feature_code":"PPL",
    "gn:name":"Sindahaki",
    "gn:population":0,
    "gn:timezone":"Asia/Karachi",
    "iso:country":"PK",
    "name:und_x_variant":[
        "Sin Dhakki",
        "S\u012bn Dhakki"
    ],
    "wof:name":"Sindahaki",
    "wof:placetype":"locality"
},
  "geometry": {"coordinates":[73.77176,34.12182],"type":"Point"}
}