{
  "type": "Feature",
  "properties": {
    "gn:admin1_code":"4",
    "gn:asciiname":"Chak One Hundred Ten South Branch",
    "gn:country_code":"PK",
    "gn:dem":188,
    "gn:feature_class":"P",
    "gn:feature_code":"PPL",
    "gn:name":"Chak One Hundred Ten South Branch",
    "gn:population":0,
    "gn:timezone":"Asia/Karachi",
    "iso:country":"PK",
    "name:und_x_variant":[
        "Chak One Hundred Ten SB"
    ],
    "wof:name":"Chak One Hundred Ten South Branch",
    "wof:placetype":"locality"
},
  "geometry": {"coordinates":[72.76063000000001,31.92259],"type":"Point"}
}