{
  "type": "Feature",
  "properties": {
    "gn:admin1_code":"5.0",
    "gn:asciiname":"Harnaro",
    "gn:country_code":"PK",
    "gn:dem":18,
    "gn:feature_class":"P",
    "gn:feature_code":"PPL",
    "gn:name":"Harnaro",
    "gn:population":0,
    "gn:timezone":"Asia/Karachi",
    "iso:country":"PK",
    "name:und_x_variant":[
        "Harn\u0101ro Thar"
    ],
    "wof:name":"Harnaro",
    "wof:placetype":"locality"
},
  "geometry": {"coordinates":[69.34309,24.37564],"type":"Point"}
}