{
  "type": "Feature",
  "properties": {
    "gn:admin1_code":"2.0",
    "gn:asciiname":"Juma Khan",
    "gn:country_code":"PK",
    "gn:dem":1479,
    "gn:feature_class":"P",
    "gn:feature_code":"PPL",
    "gn:name":"Juma Khan",
    "gn:population":0,
    "gn:timezone":"Asia/Karachi",
    "iso:country":"PK",
    "wof:name":"Juma Khan",
    "wof:placetype":"locality"
},
  "geometry": {"coordinates":[65.21396999999999,27.43136],"type":"Point"}
}