{
  "type": "Feature",
  "properties": {
    "gn:admin1_code":"5",
    "gn:asciiname":"Kothi Kalhori",
    "gn:country_code":"PK",
    "gn:dem":55,
    "gn:feature_class":"P",
    "gn:feature_code":"PPL",
    "gn:name":"Kothi Kalhori",
    "gn:population":0,
    "gn:timezone":"Asia/Karachi",
    "iso:country":"PK",
    "name:und_x_variant":[
        "Kothi"
    ],
    "wof:name":"Kothi Kalhori",
    "wof:placetype":"locality"
},
  "geometry": {"coordinates":[68.12555999999999,27.67195],"type":"Point"}
}