{
  "type": "Feature",
  "properties": {
    "gn:admin1_code":"4.0",
    "gn:asciiname":"Abidabad",
    "gn:country_code":"PK",
    "gn:dem":213,
    "gn:feature_class":"P",
    "gn:feature_code":"PPL",
    "gn:name":"Abidabad",
    "gn:population":0,
    "gn:timezone":"Asia/Karachi",
    "iso:country":"PK",
    "name:eng_x_preferred":[
        "Abidabad"
    ],
    "name:snd_x_preferred":[
        "\u0639\u0627\u0628\u062f \u0622\u0628\u0627\u062f"
    ],
    "name:urd_x_preferred":[
        "\u0639\u0627\u0628\u062f \u0622\u0628\u0627\u062f"
    ],
    "wof:name":"Abidabad",
    "wof:placetype":"locality"
},
  "geometry": {"coordinates":[73.92601999999999,31.93898],"type":"Point"}
}