{
  "type": "Feature",
  "properties": {
    "gn:admin1_code":"6.0",
    "gn:asciiname":"Basuta",
    "gn:country_code":"PK",
    "gn:dem":653,
    "gn:feature_class":"P",
    "gn:feature_code":"PPL",
    "gn:name":"Basuta",
    "gn:population":0,
    "gn:timezone":"Asia/Karachi",
    "iso:country":"PK",
    "wof:name":"Basuta",
    "wof:placetype":"locality"
},
  "geometry": {"coordinates":[73.74337,33.55446],"type":"Point"}
}