{
  "type": "Feature",
  "properties": {
    "gn:admin1_code":"5",
    "gn:asciiname":"Goth Diwan Phulchand",
    "gn:country_code":"PK",
    "gn:dem":14,
    "gn:feature_class":"P",
    "gn:feature_code":"PPL",
    "gn:name":"Goth Diwan Phulchand",
    "gn:population":0,
    "gn:timezone":"Asia/Karachi",
    "iso:country":"PK",
    "name:und_x_variant":[
        "Goth Diw\u0101n Ph\u016blchand"
    ],
    "wof:name":"Goth Diwan Phulchand",
    "wof:placetype":"locality"
},
  "geometry": {"coordinates":[69.12958,25.26695],"type":"Point"}
}