{
  "type": "Feature",
  "properties": {
    "gn:admin1_code":"2.0",
    "gn:asciiname":"Kili Hamza",
    "gn:country_code":"PK",
    "gn:dem":1604,
    "gn:feature_class":"P",
    "gn:feature_code":"PPL",
    "gn:name":"Kili Hamza",
    "gn:population":0,
    "gn:timezone":"Asia/Karachi",
    "iso:country":"PK",
    "wof:name":"Kili Hamza",
    "wof:placetype":"locality"
},
  "geometry": {"coordinates":[66.72028,29.82556],"type":"Point"}
}