{
  "type": "Feature",
  "properties": {
    "gn:admin1_code":"4",
    "gn:asciiname":"Phaddiwala",
    "gn:country_code":"PK",
    "gn:dem":140,
    "gn:feature_class":"P",
    "gn:feature_code":"PPL",
    "gn:name":"Phaddiwala",
    "gn:population":0,
    "gn:timezone":"Asia/Karachi",
    "iso:country":"PK",
    "name:und_x_variant":[
        "Phad\u012bw\u0101la"
    ],
    "wof:name":"Phaddiwala",
    "wof:placetype":"locality"
},
  "geometry": {"coordinates":[71.16790999999998,30.69111],"type":"Point"}
}