{
  "type": "Feature",
  "properties": {
    "gn:admin1_code":"01",
    "gn:asciiname":"Shingi",
    "gn:country_code":"PK",
    "gn:dem":2288,
    "gn:feature_class":"P",
    "gn:feature_code":"PPL",
    "gn:name":"Shingi",
    "gn:population":0,
    "gn:timezone":"Asia/Karachi",
    "iso:country":"PK",
    "wof:name":"Shingi",
    "wof:placetype":"locality"
},
  "geometry": {"coordinates":[69.59724,32.53967],"type":"Point"}
}