{
  "type": "Feature",
  "properties": {
    "gn:admin1_code":"3",
    "gn:asciiname":"Shangashgol",
    "gn:country_code":"PK",
    "gn:dem":1458,
    "gn:feature_class":"P",
    "gn:feature_code":"PPL",
    "gn:name":"Shangashgol",
    "gn:population":0,
    "gn:timezone":"Asia/Karachi",
    "iso:country":"PK",
    "name:eng_x_preferred":[
        "Shangashgol"
    ],
    "wof:name":"Shangashgol",
    "wof:placetype":"locality"
},
  "geometry": {"coordinates":[71.78079,35.7645],"type":"Point"}
}