{
  "type": "Feature",
  "properties": {
    "gn:admin1_code":"4",
    "gn:asciiname":"Pauliwala",
    "gn:country_code":"PK",
    "gn:dem":130,
    "gn:feature_class":"P",
    "gn:feature_code":"PPL",
    "gn:name":"Paul\u012bw\u0101la",
    "gn:population":0,
    "gn:timezone":"Asia/Karachi",
    "iso:country":"PK",
    "wof:name":"Pauliwala",
    "wof:placetype":"locality"
},
  "geometry": {"coordinates":[71.08333,30.4125],"type":"Point"}
}