{
  "type": "Feature",
  "properties": {
    "gn:admin1_code":"4",
    "gn:asciiname":"Tangiani",
    "gn:country_code":"PK",
    "gn:dem":145,
    "gn:feature_class":"P",
    "gn:feature_code":"PPL",
    "gn:name":"Tangiani",
    "gn:population":0,
    "gn:timezone":"Asia/Karachi",
    "iso:country":"PK",
    "name:und_x_variant":[
        "Tagl\u0101ni Umr\u0101ni"
    ],
    "wof:name":"Tangiani",
    "wof:placetype":"locality"
},
  "geometry": {"coordinates":[70.54751,30.16136],"type":"Point"}
}