{
  "type": "Feature",
  "properties": {
    "gn:admin1_code":"3.0",
    "gn:asciiname":"Dhinda",
    "gn:country_code":"PK",
    "gn:dem":490,
    "gn:feature_class":"P",
    "gn:feature_code":"PPL",
    "gn:name":"Dhinda",
    "gn:population":0,
    "gn:timezone":"Asia/Karachi",
    "iso:country":"PK",
    "name:und_x_variant":[
        "Dhainda",
        "Dhinda"
    ],
    "wof:name":"Dhinda",
    "wof:placetype":"locality"
},
  "geometry": {"coordinates":[72.88847,34.00172],"type":"Point"}
}