{
  "type": "Feature",
  "properties": {
    "gn:admin1_code":"6.0",
    "gn:asciiname":"Bana",
    "gn:country_code":"PK",
    "gn:dem":795,
    "gn:feature_class":"P",
    "gn:feature_code":"PPL",
    "gn:name":"Bana",
    "gn:population":0,
    "gn:timezone":"Asia/Karachi",
    "iso:country":"PK",
    "wof:name":"Bana",
    "wof:placetype":"locality"
},
  "geometry": {"coordinates":[74.06258000000003,33.30924],"type":"Point"}
}