{
  "type": "Feature",
  "properties": {
    "gn:admin1_code":"04",
    "gn:asciiname":"Rajana Thatta",
    "gn:country_code":"PK",
    "gn:dem":157,
    "gn:feature_class":"P",
    "gn:feature_code":"PPL",
    "gn:name":"Rajana Thatta",
    "gn:population":0,
    "gn:timezone":"Asia/Karachi",
    "iso:country":"PK",
    "name:und_x_variant":[
        "Raj\u0101na",
        "Rajana Thatta"
    ],
    "name:urd_x_preferred":[
        "\u0631\u062c\u0627\u0646\u06c1"
    ],
    "wof:name":"Rajana Thatta",
    "wof:placetype":"locality"
},
  "geometry": {"coordinates":[72.15398,31.42204000000001],"type":"Point"}
}