{
  "type": "Feature",
  "properties": {
    "gn:admin1_code":"3.0",
    "gn:asciiname":"Maddi Talao",
    "gn:country_code":"PK",
    "gn:dem":320,
    "gn:feature_class":"P",
    "gn:feature_code":"PPL",
    "gn:name":"Maddi Talao",
    "gn:population":0,
    "gn:timezone":"Asia/Karachi",
    "iso:country":"PK",
    "wof:name":"Maddi Talao",
    "wof:placetype":"locality"
},
  "geometry": {"coordinates":[71.74128,33.96354],"type":"Point"}
}