{
  "type": "Feature",
  "properties": {
    "gn:admin1_code":"3.0",
    "gn:asciiname":"Chashmai Banda",
    "gn:country_code":"PK",
    "gn:dem":356,
    "gn:feature_class":"P",
    "gn:feature_code":"PPL",
    "gn:name":"Chashmai Banda",
    "gn:population":0,
    "gn:timezone":"Asia/Karachi",
    "iso:country":"PK",
    "wof:name":"Chashmai Banda",
    "wof:placetype":"locality"
},
  "geometry": {"coordinates":[71.67237,33.29834],"type":"Point"}
}