{
  "type": "Feature",
  "properties": {
    "gn:admin1_code":"5",
    "gn:asciiname":"Dalil Khan",
    "gn:country_code":"PK",
    "gn:dem":64,
    "gn:feature_class":"P",
    "gn:feature_code":"PPL",
    "gn:name":"Dalil Khan",
    "gn:population":0,
    "gn:timezone":"Asia/Karachi",
    "iso:country":"PK",
    "name:und_x_variant":[
        "Dalel Kh\u0101n"
    ],
    "wof:name":"Dalil Khan",
    "wof:placetype":"locality"
},
  "geometry": {"coordinates":[68.87649999999999,28.27788],"type":"Point"}
}