{
  "type": "Feature",
  "properties": {
    "gn:admin1_code":"3.0",
    "gn:asciiname":"Halli",
    "gn:country_code":"PK",
    "gn:dem":1077,
    "gn:feature_class":"P",
    "gn:feature_code":"PPL",
    "gn:name":"Halli",
    "gn:population":0,
    "gn:timezone":"Asia/Karachi",
    "iso:country":"PK",
    "wof:name":"Halli",
    "wof:placetype":"locality"
},
  "geometry": {"coordinates":[73.12576,35.4624],"type":"Point"}
}