{
  "type": "Feature",
  "properties": {
    "gn:admin1_code":"3",
    "gn:asciiname":"Banda Semu",
    "gn:country_code":"PK",
    "gn:dem":410,
    "gn:feature_class":"P",
    "gn:feature_code":"PPL",
    "gn:name":"Banda Semu",
    "gn:population":0,
    "gn:timezone":"Asia/Karachi",
    "iso:country":"PK",
    "name:und_x_variant":[
        "Semu Kili",
        "Al\u012bmad",
        "Banda Semu",
        "Alim\u0101d"
    ],
    "wof:name":"Banda Semu",
    "wof:placetype":"locality"
},
  "geometry": {"coordinates":[71.09244,32.50704],"type":"Point"}
}