{
  "type": "Feature",
  "properties": {
    "gn:admin1_code":"3.0",
    "gn:asciiname":"Manghal Danna",
    "gn:country_code":"PK",
    "gn:dem":2035,
    "gn:feature_class":"P",
    "gn:feature_code":"PPL",
    "gn:name":"Manghal Danna",
    "gn:population":0,
    "gn:timezone":"Asia/Karachi",
    "iso:country":"PK",
    "wof:name":"Manghal Danna",
    "wof:placetype":"locality"
},
  "geometry": {"coordinates":[73.49148000000002,34.6882],"type":"Point"}
}