{
  "type": "Feature",
  "properties": {
    "gn:admin1_code":"4.0",
    "gn:asciiname":"Dhok Bhakkar",
    "gn:country_code":"PK",
    "gn:dem":371,
    "gn:feature_class":"P",
    "gn:feature_code":"PPL",
    "gn:name":"Dhok Bhakkar",
    "gn:population":0,
    "gn:timezone":"Asia/Karachi",
    "iso:country":"PK",
    "wof:name":"Dhok Bhakkar",
    "wof:placetype":"locality"
},
  "geometry": {"coordinates":[71.86284000000001,32.69774],"type":"Point"}
}