{
  "type": "Feature",
  "properties": {
    "gn:admin1_code":"3",
    "gn:asciiname":"Banda Zarifwala",
    "gn:country_code":"PK",
    "gn:dem":490,
    "gn:feature_class":"P",
    "gn:feature_code":"PPL",
    "gn:name":"Banda Zarifwala",
    "gn:population":0,
    "gn:timezone":"Asia/Karachi",
    "iso:country":"PK",
    "name:und_x_variant":[
        "B\u0101nda Zar\u012bfw\u0101l"
    ],
    "wof:name":"Banda Zarifwala",
    "wof:placetype":"locality"
},
  "geometry": {"coordinates":[71.03479,32.43065],"type":"Point"}
}