{
  "type": "Feature",
  "properties": {
    "gn:admin1_code":"6",
    "gn:asciiname":"Khai Mera",
    "gn:country_code":"PK",
    "gn:dem":396,
    "gn:feature_class":"P",
    "gn:feature_code":"PPL",
    "gn:name":"Khai Mera",
    "gn:population":0,
    "gn:timezone":"Asia/Karachi",
    "iso:country":"PK",
    "name:und_x_variant":[
        "Kai Maira",
        "Khai Mera"
    ],
    "wof:name":"Khai Mera",
    "wof:placetype":"locality"
},
  "geometry": {"coordinates":[73.83841,33.17811],"type":"Point"}
}