{
  "type": "Feature",
  "properties": {
    "gn:admin1_code":"4.0",
    "gn:asciiname":"Chak Two Hundred Seventy-seven Jhang Branch",
    "gn:country_code":"PK",
    "gn:dem":177,
    "gn:feature_class":"P",
    "gn:feature_code":"PPL",
    "gn:name":"Chak Two Hundred Seventy-seven Jhang Branch",
    "gn:population":0,
    "gn:timezone":"Asia/Karachi",
    "iso:country":"PK",
    "name:und_x_variant":[
        "Nangal",
        "Budhi Nangal",
        "Budhi",
        "Chak Two Hundred Twenty-Seven",
        "Chak Two Hundred Seventy-seven Jhang Branch",
        "Budhi Pind"
    ],
    "wof:name":"Chak Two Hundred Seventy-seven Jhang Branch",
    "wof:placetype":"locality"
},
  "geometry": {"coordinates":[72.79184000000002,31.31929],"type":"Point"}
}