{
  "type": "Feature",
  "properties": {
    "gn:admin1_code":"3.0",
    "gn:asciiname":"Mir Khan Ji Camp",
    "gn:country_code":"PK",
    "gn:dem":1281,
    "gn:feature_class":"P",
    "gn:feature_code":"PPL",
    "gn:name":"Mir Khan Ji Camp",
    "gn:population":0,
    "gn:timezone":"Asia/Karachi",
    "iso:country":"PK",
    "wof:name":"Mir Khan Ji Camp",
    "wof:placetype":"locality"
},
  "geometry": {"coordinates":[71.73721999999999,35.51083],"type":"Point"}
}