{
  "type": "Feature",
  "properties": {
    "gn:admin1_code":"5.0",
    "gn:asciiname":"Mihrab Khan Gargaz",
    "gn:country_code":"PK",
    "gn:dem":13,
    "gn:feature_class":"P",
    "gn:feature_code":"PPL",
    "gn:name":"Mihrab Khan Gargaz",
    "gn:population":0,
    "gn:timezone":"Asia/Karachi",
    "iso:country":"PK",
    "wof:name":"Mihrab Khan Gargaz",
    "wof:placetype":"locality"
},
  "geometry": {"coordinates":[69.01210999999999,24.88179],"type":"Point"}
}