{
  "type": "Feature",
  "properties": {
    "gn:admin1_code":"2.0",
    "gn:asciiname":"Nur Bakhsh Kili",
    "gn:country_code":"PK",
    "gn:dem":1590,
    "gn:feature_class":"P",
    "gn:feature_code":"PPL",
    "gn:name":"Nur Bakhsh Kili",
    "gn:population":0,
    "gn:timezone":"Asia/Karachi",
    "iso:country":"PK",
    "wof:name":"Nur Bakhsh Kili",
    "wof:placetype":"locality"
},
  "geometry": {"coordinates":[66.37671999999999,30.00572],"type":"Point"}
}