{
  "type": "Feature",
  "properties": {
    "gn:admin1_code":"4",
    "gn:asciiname":"Iqbal Nager",
    "gn:country_code":"PK",
    "gn:dem":181,
    "gn:feature_class":"P",
    "gn:feature_code":"PPL",
    "gn:name":"Iqbal Nager",
    "gn:population":0,
    "gn:timezone":"Asia/Karachi",
    "iso:country":"PK",
    "name:und_x_variant":[
        "Thatta Gilotr\u0101n"
    ],
    "wof:name":"Iqbal Nager",
    "wof:placetype":"locality"
},
  "geometry": {"coordinates":[73.00359,31.6458],"type":"Point"}
}