{
  "type": "Feature",
  "properties": {
    "gn:admin1_code":"2.0",
    "gn:asciiname":"Mir Muhammad",
    "gn:country_code":"PK",
    "gn:dem":935,
    "gn:feature_class":"P",
    "gn:feature_code":"PPL",
    "gn:name":"Mir Muhammad",
    "gn:population":0,
    "gn:timezone":"Asia/Karachi",
    "iso:country":"PK",
    "wof:name":"Mir Muhammad",
    "wof:placetype":"locality"
},
  "geometry": {"coordinates":[67.03430999999999,27.73775],"type":"Point"}
}