{
  "type": "Feature",
  "properties": {
    "gn:admin1_code":"4",
    "gn:asciiname":"Shahbdin",
    "gn:country_code":"PK",
    "gn:dem":237,
    "gn:feature_class":"P",
    "gn:feature_code":"PPL",
    "gn:name":"Shahbdin",
    "gn:population":0,
    "gn:timezone":"Asia/Karachi",
    "iso:country":"PK",
    "name:eng_x_preferred":[
        "Shahbdin"
    ],
    "name:und_x_variant":[
        "Sh\u0101diw\u0101l"
    ],
    "wof:name":"Shahbdin",
    "wof:placetype":"locality"
},
  "geometry": {"coordinates":[74.02491999999999,32.59918],"type":"Point"}
}