{
  "type": "Feature",
  "properties": {
    "gn:admin1_code":"4.0",
    "gn:asciiname":"Khanpur Sehwan",
    "gn:country_code":"PK",
    "gn:dem":197,
    "gn:feature_class":"P",
    "gn:feature_code":"PPL",
    "gn:name":"Khanpur Sehwan",
    "gn:population":0,
    "gn:timezone":"Asia/Karachi",
    "iso:country":"PK",
    "name:und_x_variant":[
        "Kh\u0101npur"
    ],
    "wof:name":"Khanpur Sehwan",
    "wof:placetype":"locality"
},
  "geometry": {"coordinates":[73.66216,31.21859000000001],"type":"Point"}
}