{
  "type": "Feature",
  "properties": {
    "gn:admin1_code":"4.0",
    "gn:asciiname":"Jindu Shahwali",
    "gn:country_code":"PK",
    "gn:dem":109,
    "gn:feature_class":"P",
    "gn:feature_code":"PPL",
    "gn:name":"Jindu Shahwali",
    "gn:population":0,
    "gn:timezone":"Asia/Karachi",
    "iso:country":"PK",
    "name:und_x_variant":[
        "Jindu Sh\u0101hw\u0101la"
    ],
    "wof:name":"Jindu Shahwali",
    "wof:placetype":"locality"
},
  "geometry": {"coordinates":[71.18624,29.65976],"type":"Point"}
}