{
  "type": "Feature",
  "properties": {
    "gn:admin1_code":"5",
    "gn:asciiname":"Bahawat Khan Bajkani",
    "gn:country_code":"PK",
    "gn:dem":69,
    "gn:feature_class":"P",
    "gn:feature_code":"PPL",
    "gn:name":"Bahawat Khan Bajkani",
    "gn:population":0,
    "gn:timezone":"Asia/Karachi",
    "iso:country":"PK",
    "name:und_x_variant":[
        "Bah\u0101wal Kh\u0101n"
    ],
    "wof:name":"Bahawat Khan Bajkani",
    "wof:placetype":"locality"
},
  "geometry": {"coordinates":[69.02002,28.19092],"type":"Point"}
}