{
  "type": "Feature",
  "properties": {
    "gn:admin1_code":"5.0",
    "gn:asciiname":"Goth Fateh Muhammad Khundiaro",
    "gn:country_code":"PK",
    "gn:dem":44,
    "gn:feature_class":"P",
    "gn:feature_code":"PPL",
    "gn:name":"Goth Fateh Muhammad Khundiaro",
    "gn:population":0,
    "gn:timezone":"Asia/Karachi",
    "iso:country":"PK",
    "wof:name":"Goth Fateh Muhammad Khundiaro",
    "wof:placetype":"locality"
},
  "geometry": {"coordinates":[68.27519000000001,26.79234000000001],"type":"Point"}
}