{
  "type": "Feature",
  "properties": {
    "gn:admin1_code":"4",
    "gn:asciiname":"Nawin Basti",
    "gn:country_code":"PK",
    "gn:dem":111,
    "gn:feature_class":"P",
    "gn:feature_code":"PPL",
    "gn:name":"Nawin Basti",
    "gn:population":0,
    "gn:timezone":"Asia/Karachi",
    "iso:country":"PK",
    "wof:name":"Nawin Basti",
    "wof:placetype":"locality"
},
  "geometry": {"coordinates":[71.17777,29.63033],"type":"Point"}
}