{
  "type": "Feature",
  "properties": {
    "gn:admin1_code":"04",
    "gn:asciiname":"Kot Sauru",
    "gn:cc2":"PK",
    "gn:country_code":"PK",
    "gn:dem":137,
    "gn:feature_class":"P",
    "gn:feature_code":"PPL",
    "gn:name":"Kot Sauru",
    "gn:population":0,
    "gn:timezone":"Asia/Karachi",
    "iso:country":"PK",
    "name:und_x_variant":[
        "Kot Sauro",
        "Kot Sauru"
    ],
    "wof:name":"Kot Sauru",
    "wof:placetype":"locality"
},
  "geometry": {"coordinates":[72.32333,29.91972],"type":"Point"}
}