{
  "type": "Feature",
  "properties": {
    "gn:admin1_code":"4.0",
    "gn:asciiname":"Dhok Awan",
    "gn:country_code":"PK",
    "gn:dem":271,
    "gn:feature_class":"P",
    "gn:feature_code":"PPL",
    "gn:name":"Dhok Awan",
    "gn:population":0,
    "gn:timezone":"Asia/Karachi",
    "iso:country":"PK",
    "name:eng_x_preferred":[
        "Dhok Awan"
    ],
    "name:urd_x_preferred":[
        "\u0688\u06be\u0648\u06a9 \u0627\u0639\u0648\u0627\u0646"
    ],
    "wof:name":"Dhok Awan",
    "wof:placetype":"locality"
},
  "geometry": {"coordinates":[73.42756,32.82333],"type":"Point"}
}