{
  "type": "Feature",
  "properties": {
    "gn:admin1_code":"4.0",
    "gn:asciiname":"Rai Thaikar",
    "gn:country_code":"PK",
    "gn:dem":522,
    "gn:feature_class":"P",
    "gn:feature_code":"PPL",
    "gn:name":"Rai Thaikar",
    "gn:population":0,
    "gn:timezone":"Asia/Karachi",
    "iso:country":"PK",
    "wof:name":"Rai Thaikar",
    "wof:placetype":"locality"
},
  "geometry": {"coordinates":[70.31277,31.05869],"type":"Point"}
}