{
  "type": "Feature",
  "properties": {
    "gn:admin1_code":"4.0",
    "gn:asciiname":"Muhammadpur Garga",
    "gn:country_code":"PK",
    "gn:dem":88,
    "gn:feature_class":"P",
    "gn:feature_code":"PPL",
    "gn:name":"Muhammadpur Garga",
    "gn:population":0,
    "gn:timezone":"Asia/Karachi",
    "iso:country":"PK",
    "name:und_x_variant":[
        "Muhammadpur G\u0101nga"
    ],
    "wof:name":"Muhammadpur Garga",
    "wof:placetype":"locality"
},
  "geometry": {"coordinates":[70.36419000000001,28.64596],"type":"Point"}
}