{
  "type": "Feature",
  "properties": {
    "gn:admin1_code":"01",
    "gn:asciiname":"Tangai Banda",
    "gn:country_code":"PK",
    "gn:dem":1350,
    "gn:feature_class":"P",
    "gn:feature_code":"PPL",
    "gn:name":"Tangai Banda",
    "gn:population":0,
    "gn:timezone":"Asia/Karachi",
    "iso:country":"PK",
    "name:eng_x_preferred":[
        "Tangi B\u0101nda"
    ],
    "wof:name":"Tangai Banda",
    "wof:placetype":"locality"
},
  "geometry": {"coordinates":[71.57091,34.6392],"type":"Point"}
}