{
  "type": "Feature",
  "properties": {
    "gn:admin1_code":"2.0",
    "gn:asciiname":"Kili Mir Mengal Khan",
    "gn:country_code":"PK",
    "gn:dem":611,
    "gn:feature_class":"P",
    "gn:feature_code":"PPL",
    "gn:name":"Kili Mir Mengal Khan",
    "gn:population":0,
    "gn:timezone":"Asia/Karachi",
    "iso:country":"PK",
    "wof:name":"Kili Mir Mengal Khan",
    "wof:placetype":"locality"
},
  "geometry": {"coordinates":[64.5245,28.29666],"type":"Point"}
}