{
  "type": "Feature",
  "properties": {
    "gn:admin1_code":"5",
    "gn:asciiname":"Goth Dalu Ketti",
    "gn:country_code":"PK",
    "gn:dem":32,
    "gn:feature_class":"P",
    "gn:feature_code":"PPL",
    "gn:name":"Goth Dalu Ketti",
    "gn:population":0,
    "gn:timezone":"Asia/Karachi",
    "iso:country":"PK",
    "name:eng_x_preferred":[
        "Dalu Keti"
    ],
    "wof:name":"Goth Dalu Ketti",
    "wof:placetype":"locality"
},
  "geometry": {"coordinates":[68.3443,25.97206],"type":"Point"}
}