{
  "type": "Feature",
  "properties": {
    "gn:admin1_code":"4.0",
    "gn:asciiname":"Khorin Thal",
    "gn:country_code":"PK",
    "gn:dem":514,
    "gn:feature_class":"P",
    "gn:feature_code":"PPL",
    "gn:name":"Khorin Thal",
    "gn:population":0,
    "gn:timezone":"Asia/Karachi",
    "iso:country":"PK",
    "wof:name":"Khorin Thal",
    "wof:placetype":"locality"
},
  "geometry": {"coordinates":[70.36124000000001,30.93877],"type":"Point"}
}