{
  "type": "Feature",
  "properties": {
    "gn:admin1_code":"3.0",
    "gn:asciiname":"Beri",
    "gn:country_code":"PK",
    "gn:dem":840,
    "gn:feature_class":"P",
    "gn:feature_code":"PPL",
    "gn:name":"Beri",
    "gn:population":0,
    "gn:timezone":"Asia/Karachi",
    "iso:country":"PK",
    "name:bul_x_preferred":[
        "\u0411\u0435\u0440\u0438"
    ],
    "name:ceb_x_preferred":[
        "Beri"
    ],
    "name:deu_x_preferred":[
        "Beri"
    ],
    "name:fra_x_preferred":[
        "Beri"
    ],
    "name:hin_x_preferred":[
        "\u092c\u0947\u0930\u0940"
    ],
    "name:msa_x_preferred":[
        "Beri"
    ],
    "name:rus_x_preferred":[
        "\u0411\u0435\u0440\u0438"
    ],
    "name:srp_x_preferred":[
        "\u0411\u0435\u0440\u0438"
    ],
    "name:swe_x_preferred":[
        "Beri"
    ],
    "name:und_x_variant":[
        "Lakhanpur"
    ],
    "wof:name":"Beri",
    "wof:placetype":"locality"
},
  "geometry": {"coordinates":[73.07042,34.23046],"type":"Point"}
}