{
  "type": "Feature",
  "properties": {
    "gn:admin1_code":"5.0",
    "gn:asciiname":"Goth Machhi",
    "gn:country_code":"PK",
    "gn:dem":11,
    "gn:feature_class":"P",
    "gn:feature_code":"PPL",
    "gn:name":"Goth Machhi",
    "gn:population":0,
    "gn:timezone":"Asia/Karachi",
    "iso:country":"PK",
    "name:und_x_variant":[
        "Goth M\u0101cchi"
    ],
    "wof:name":"Goth Machhi",
    "wof:placetype":"locality"
},
  "geometry": {"coordinates":[68.25149,24.7809],"type":"Point"}
}