{
  "type": "Feature",
  "properties": {
    "gn:admin1_code":"5.0",
    "gn:asciiname":"Abdul Rahman Chachar",
    "gn:country_code":"PK",
    "gn:dem":69,
    "gn:feature_class":"P",
    "gn:feature_code":"PPL",
    "gn:name":"Abdul Rahman Chachar",
    "gn:population":0,
    "gn:timezone":"Asia/Karachi",
    "iso:country":"PK",
    "wof:name":"Abdul Rahman Chachar",
    "wof:placetype":"locality"
},
  "geometry": {"coordinates":[69.26984,28.07571],"type":"Point"}
}