{
  "type": "Feature",
  "properties": {
    "gn:admin1_code":"4.0",
    "gn:asciiname":"Rakh Machhi",
    "gn:country_code":"PK",
    "gn:dem":210,
    "gn:feature_class":"P",
    "gn:feature_code":"PPL",
    "gn:name":"Rakh Machhi",
    "gn:population":0,
    "gn:timezone":"Asia/Karachi",
    "iso:country":"PK",
    "name:und_x_variant":[
        "Rakh M\u0101chhike"
    ],
    "wof:name":"Rakh Machhi",
    "wof:placetype":"locality"
},
  "geometry": {"coordinates":[73.89950999999998,31.73643],"type":"Point"}
}