{
  "type": "Feature",
  "properties": {
    "gn:admin1_code":"4.0",
    "gn:asciiname":"Naginawala",
    "gn:country_code":"PK",
    "gn:dem":143,
    "gn:feature_class":"P",
    "gn:feature_code":"PPL",
    "gn:name":"Naginawala",
    "gn:population":0,
    "gn:timezone":"Asia/Karachi",
    "iso:country":"PK",
    "name:und_x_variant":[
        "Nag\u012bnew\u0101la"
    ],
    "wof:name":"Naginawala",
    "wof:placetype":"locality"
},
  "geometry": {"coordinates":[70.94740999999998,30.79256],"type":"Point"}
}