{
  "type": "Feature",
  "properties": {
    "gn:admin1_code":"4.0",
    "gn:asciiname":"Masra",
    "gn:country_code":"PK",
    "gn:dem":245,
    "gn:feature_class":"P",
    "gn:feature_code":"PPL",
    "gn:name":"Masra",
    "gn:population":0,
    "gn:timezone":"Asia/Karachi",
    "iso:country":"PK",
    "wof:name":"Masra",
    "wof:placetype":"locality"
},
  "geometry": {"coordinates":[75.03618,32.14077],"type":"Point"}
}