{
  "type": "Feature",
  "properties": {
    "gn:admin1_code":"2.0",
    "gn:asciiname":"Goth Sharbat Khan Lehri",
    "gn:country_code":"PK",
    "gn:dem":62,
    "gn:feature_class":"P",
    "gn:feature_code":"PPL",
    "gn:name":"Goth Sharbat Khan Lehri",
    "gn:population":0,
    "gn:timezone":"Asia/Karachi",
    "iso:country":"PK",
    "wof:name":"Goth Sharbat Khan Lehri",
    "wof:placetype":"locality"
},
  "geometry": {"coordinates":[67.93386,28.44126],"type":"Point"}
}