{
  "type": "Feature",
  "properties": {
    "gn:admin1_code":"5.0",
    "gn:asciiname":"Hamid Ali Sehto Jo Goth",
    "gn:country_code":"PK",
    "gn:dem":52,
    "gn:feature_class":"P",
    "gn:feature_code":"PPL",
    "gn:name":"Hamid Ali Sehto Jo Goth",
    "gn:population":0,
    "gn:timezone":"Asia/Karachi",
    "iso:country":"PK",
    "wof:name":"Hamid Ali Sehto Jo Goth",
    "wof:placetype":"locality"
},
  "geometry": {"coordinates":[68.46509,27.15464],"type":"Point"}
}