{
  "type": "Feature",
  "properties": {
    "gn:admin1_code":"5",
    "gn:asciiname":"Goth Gahot",
    "gn:country_code":"PK",
    "gn:dem":30,
    "gn:feature_class":"P",
    "gn:feature_code":"PPL",
    "gn:name":"Goth Gahot",
    "gn:population":0,
    "gn:timezone":"Asia/Karachi",
    "iso:country":"PK",
    "name:eng_x_preferred":[
        "G\u0101hot"
    ],
    "wof:name":"Goth Gahot",
    "wof:placetype":"locality"
},
  "geometry": {"coordinates":[68.34792,25.92886],"type":"Point"}
}