{
  "type": "Feature",
  "properties": {
    "gn:admin1_code":"4",
    "gn:asciiname":"Dhok Allahyar",
    "gn:country_code":"PK",
    "gn:dem":823,
    "gn:feature_class":"P",
    "gn:feature_code":"PPL",
    "gn:name":"Dhok Allahyar",
    "gn:population":0,
    "gn:timezone":"Asia/Karachi",
    "iso:country":"PK",
    "name:und_x_variant":[
        "All\u0101hyarw\u0101li"
    ],
    "wof:name":"Dhok Allahyar",
    "wof:placetype":"locality"
},
  "geometry": {"coordinates":[72.23999999999999,32.63909],"type":"Point"}
}