{
  "type": "Feature",
  "properties": {
    "gn:admin1_code":"03",
    "gn:asciiname":"Kot Jai",
    "gn:country_code":"PK",
    "gn:dem":183,
    "gn:feature_class":"P",
    "gn:feature_code":"PPL",
    "gn:name":"Kot Jai",
    "gn:population":0,
    "gn:timezone":"Asia/Karachi",
    "iso:country":"PK",
    "name:fas_x_preferred":[
        "\u06a9\u0648\u062a \u062c\u0627\u0626\u06cc"
    ],
    "name:urd_x_preferred":[
        "\u06a9\u0648\u0679 \u062c\u0627\u0626\u06cc"
    ],
    "wof:name":"Kot Jai",
    "wof:placetype":"locality"
},
  "geometry": {"coordinates":[71.0932,32.17039],"type":"Point"}
}