{
  "type": "Feature",
  "properties": {
    "gn:admin1_code":"4",
    "gn:asciiname":"Panuwala",
    "gn:country_code":"PK",
    "gn:dem":122,
    "gn:feature_class":"P",
    "gn:feature_code":"PPL",
    "gn:name":"Panuwala",
    "gn:population":0,
    "gn:timezone":"Asia/Karachi",
    "iso:country":"PK",
    "name:eng_x_preferred":[
        "Panuwala"
    ],
    "wof:name":"Panuwala",
    "wof:placetype":"locality"
},
  "geometry": {"coordinates":[71.85833000000002,29.41806],"type":"Point"}
}