{
  "type": "Feature",
  "properties": {
    "gn:admin1_code":"3.0",
    "gn:asciiname":"Takai Banda",
    "gn:country_code":"PK",
    "gn:dem":2689,
    "gn:feature_class":"P",
    "gn:feature_code":"PPL",
    "gn:name":"Takai Banda",
    "gn:population":0,
    "gn:timezone":"Asia/Karachi",
    "iso:country":"PK",
    "wof:name":"Takai Banda",
    "wof:placetype":"locality"
},
  "geometry": {"coordinates":[72.58561999999998,35.09571],"type":"Point"}
}