{
  "type": "Feature",
  "properties": {
    "gn:admin1_code":"4",
    "gn:asciiname":"Chak Twenty-nine Gogera Distributary",
    "gn:country_code":"PK",
    "gn:dem":181,
    "gn:feature_class":"P",
    "gn:feature_code":"PPL",
    "gn:name":"Chak Twenty-nine Gogera Distributary",
    "gn:population":0,
    "gn:timezone":"Asia/Karachi",
    "iso:country":"PK",
    "name:und_x_variant":[
        "Chak Twenty-nine GD",
        "Gogera"
    ],
    "wof:name":"Chak Twenty-nine Gogera Distributary",
    "wof:placetype":"locality"
},
  "geometry": {"coordinates":[73.39173000000002,31.00888],"type":"Point"}
}