{
  "type": "Feature",
  "properties": {
    "gn:admin1_code":"4.0",
    "gn:asciiname":"Dhandar",
    "gn:country_code":"PK",
    "gn:dem":426,
    "gn:feature_class":"P",
    "gn:feature_code":"PPL",
    "gn:name":"Dhandar",
    "gn:population":0,
    "gn:timezone":"Asia/Karachi",
    "iso:country":"PK",
    "name:und_x_variant":[
        "Wandh\u0101rew\u0101li"
    ],
    "wof:name":"Dhandar",
    "wof:placetype":"locality"
},
  "geometry": {"coordinates":[71.91611,32.64345],"type":"Point"}
}