{
  "type": "Feature",
  "properties": {
    "gn:admin1_code":"4.0",
    "gn:asciiname":"Ghungrila",
    "gn:country_code":"PK",
    "gn:dem":541,
    "gn:feature_class":"P",
    "gn:feature_code":"PPL",
    "gn:name":"Ghungrila",
    "gn:population":0,
    "gn:timezone":"Asia/Karachi",
    "iso:country":"PK",
    "name:und_x_variant":[
        "Ghungr\u012bla",
        "Ghungrila"
    ],
    "wof:name":"Ghungrila",
    "wof:placetype":"locality"
},
  "geometry": {"coordinates":[73.24649000000002,33.30109],"type":"Point"}
}