{
  "type": "Feature",
  "properties": {
    "gn:admin1_code":"2.0",
    "gn:asciiname":"Dand",
    "gn:country_code":"PK",
    "gn:dem":1563,
    "gn:feature_class":"P",
    "gn:feature_code":"PPL",
    "gn:name":"Dand",
    "gn:population":0,
    "gn:timezone":"Asia/Karachi",
    "iso:country":"PK",
    "wof:name":"Dand",
    "wof:placetype":"locality"
},
  "geometry": {"coordinates":[68.87699000000001,30.60325],"type":"Point"}
}