{
  "type": "Feature",
  "properties": {
    "gn:admin1_code":"4.0",
    "gn:asciiname":"Kalowala",
    "gn:country_code":"PK",
    "gn:dem":200,
    "gn:feature_class":"P",
    "gn:feature_code":"PPL",
    "gn:name":"Kalowala",
    "gn:population":0,
    "gn:timezone":"Asia/Kolkata",
    "iso:country":"PK",
    "name:und_x_variant":[
        "K\u0101luw\u0101ra Kh\u0101lsa"
    ],
    "wof:name":"Kalowala",
    "wof:placetype":"locality"
},
  "geometry": {"coordinates":[74.57042,31.05505],"type":"Point"}
}