{
  "type": "Feature",
  "properties": {
    "gn:admin1_code":"04",
    "gn:asciiname":"Lorhikki",
    "gn:country_code":"PK",
    "gn:dem":234,
    "gn:feature_class":"P",
    "gn:feature_code":"PPL",
    "gn:name":"Lorhikki",
    "gn:population":0,
    "gn:timezone":"Asia/Karachi",
    "iso:country":"PK",
    "name:und_x_variant":[
        "Lohrki",
        "Lorrikki",
        "Lorhikki"
    ],
    "wof:name":"Lorhikki",
    "wof:placetype":"locality"
},
  "geometry": {"coordinates":[74.39869,32.27744000000001],"type":"Point"}
}