{
  "type": "Feature",
  "properties": {
    "gn:admin1_code":"5.0",
    "gn:asciiname":"Muhammad Ramzan Mallah",
    "gn:country_code":"PK",
    "gn:dem":3,
    "gn:feature_class":"P",
    "gn:feature_code":"PPL",
    "gn:name":"Muhammad Ramzan Mallah",
    "gn:population":0,
    "gn:timezone":"Asia/Karachi",
    "iso:country":"PK",
    "wof:name":"Muhammad Ramzan Mallah",
    "wof:placetype":"locality"
},
  "geometry": {"coordinates":[69.0475,24.34979],"type":"Point"}
}