{
  "type": "Feature",
  "properties": {
    "gn:admin1_code":"3.0",
    "gn:asciiname":"Shahotar",
    "gn:country_code":"PK",
    "gn:dem":1039,
    "gn:feature_class":"P",
    "gn:feature_code":"PPL",
    "gn:name":"Shahotar",
    "gn:population":0,
    "gn:timezone":"Asia/Karachi",
    "iso:country":"PK",
    "wof:name":"Shahotar",
    "wof:placetype":"locality"
},
  "geometry": {"coordinates":[73.35738000000001,34.52147],"type":"Point"}
}