{
  "type": "Feature",
  "properties": {
    "gn:admin1_code":"3",
    "gn:asciiname":"Chindakot",
    "gn:country_code":"PK",
    "gn:dem":1592,
    "gn:feature_class":"P",
    "gn:feature_code":"PPL",
    "gn:name":"Chindakot",
    "gn:population":0,
    "gn:timezone":"Asia/Karachi",
    "iso:country":"PK",
    "name:eng_x_preferred":[
        "Chindakot"
    ],
    "wof:name":"Chindakot",
    "wof:placetype":"locality"
},
  "geometry": {"coordinates":[71.7779,35.08416],"type":"Point"}
}