{
  "type": "Feature",
  "properties": {
    "gn:admin1_code":"4",
    "gn:asciiname":"Basti Khokhran",
    "gn:country_code":"PK",
    "gn:dem":86,
    "gn:feature_class":"P",
    "gn:feature_code":"PPL",
    "gn:name":"Basti Khokhran",
    "gn:population":0,
    "gn:timezone":"Asia/Karachi",
    "iso:country":"PK",
    "name:und_x_variant":[
        "Mad Ily\u0101s",
        "Basti Khokhran"
    ],
    "wof:name":"Basti Khokhran",
    "wof:placetype":"locality"
},
  "geometry": {"coordinates":[70.60634,28.57992],"type":"Point"}
}