{
  "type": "Feature",
  "properties": {
    "gn:admin1_code":"4",
    "gn:asciiname":"Nangal Hashri",
    "gn:country_code":"PK",
    "gn:dem":239,
    "gn:feature_class":"P",
    "gn:feature_code":"PPL",
    "gn:name":"Nangal Hashri",
    "gn:population":0,
    "gn:timezone":"Asia/Karachi",
    "iso:country":"PK",
    "name:und_x_variant":[
        "Nangal"
    ],
    "wof:name":"Nangal Hashri",
    "wof:placetype":"locality"
},
  "geometry": {"coordinates":[74.61412,32.25083],"type":"Point"}
}