{
  "type": "Feature",
  "properties": {
    "gn:admin1_code":"4.0",
    "gn:asciiname":"Gul Qaim",
    "gn:country_code":"PK",
    "gn:dem":120,
    "gn:feature_class":"P",
    "gn:feature_code":"PPL",
    "gn:name":"Gul Qaim",
    "gn:population":0,
    "gn:timezone":"Asia/Karachi",
    "iso:country":"PK",
    "name:eng_x_preferred":[
        "Gul Q\u0101im Mastoi"
    ],
    "wof:name":"Gul Qaim",
    "wof:placetype":"locality"
},
  "geometry": {"coordinates":[70.96156999999999,30.03767],"type":"Point"}
}