{
  "type": "Feature",
  "properties": {
    "gn:admin1_code":"3.0",
    "gn:asciiname":"Shahbaz",
    "gn:country_code":"PK",
    "gn:dem":306,
    "gn:feature_class":"P",
    "gn:feature_code":"PPL",
    "gn:name":"Shahbaz",
    "gn:population":0,
    "gn:timezone":"Asia/Karachi",
    "iso:country":"PK",
    "name:deu_x_preferred":[
        "Shahbaz"
    ],
    "name:eng_x_preferred":[
        "Sh\u0101hb\u0101z Kili"
    ],
    "name:rus_x_preferred":[
        "\u0428\u0430\u0445\u0431\u0430\u0437"
    ],
    "wof:name":"Shahbaz",
    "wof:placetype":"locality"
},
  "geometry": {"coordinates":[71.85646,34.13142],"type":"Point"}
}