{
  "type": "Feature",
  "properties": {
    "gn:admin1_code":"4",
    "gn:asciiname":"Jharianwala",
    "gn:country_code":"PK",
    "gn:dem":140,
    "gn:feature_class":"P",
    "gn:feature_code":"PPL",
    "gn:name":"Jharianwala",
    "gn:population":0,
    "gn:timezone":"Asia/Karachi",
    "iso:country":"PK",
    "name:und_x_variant":[
        "Jarhw\u0101la"
    ],
    "wof:name":"Jharianwala",
    "wof:placetype":"locality"
},
  "geometry": {"coordinates":[70.89010999999998,30.67783],"type":"Point"}
}