{
  "type": "Feature",
  "properties": {
    "gn:admin1_code":"04",
    "gn:asciiname":"Nebwal",
    "gn:country_code":"PK",
    "gn:dem":165,
    "gn:feature_class":"P",
    "gn:feature_code":"PPL",
    "gn:name":"Nebwal",
    "gn:population":0,
    "gn:timezone":"Asia/Karachi",
    "iso:country":"PK",
    "name:und_x_variant":[
        "Naibwal",
        "Nebwal"
    ],
    "wof:name":"Nebwal",
    "wof:placetype":"locality"
},
  "geometry": {"coordinates":[73.32257,30.25878],"type":"Point"}
}