{
  "type": "Feature",
  "properties": {
    "gn:admin1_code":"3",
    "gn:asciiname":"Chamrasi",
    "gn:country_code":"PK",
    "gn:dem":1340,
    "gn:feature_class":"P",
    "gn:feature_code":"PPL",
    "gn:name":"Chamrasi",
    "gn:population":0,
    "gn:timezone":"Asia/Karachi",
    "iso:country":"PK",
    "name:und_x_variant":[
        "Chakli"
    ],
    "wof:name":"Chamrasi",
    "wof:placetype":"locality"
},
  "geometry": {"coordinates":[72.93074,34.47841],"type":"Point"}
}