{
  "type": "Feature",
  "properties": {
    "gn:admin1_code":"5",
    "gn:asciiname":"Goth Hulia",
    "gn:country_code":"PK",
    "gn:dem":53,
    "gn:feature_class":"P",
    "gn:feature_code":"PPL",
    "gn:name":"Goth Hulia",
    "gn:population":0,
    "gn:timezone":"Asia/Karachi",
    "iso:country":"PK",
    "name:und_x_variant":[
        "Hulli"
    ],
    "wof:name":"Goth Hulia",
    "wof:placetype":"locality"
},
  "geometry": {"coordinates":[68.42300999999999,27.44959],"type":"Point"}
}