{
  "type": "Feature",
  "properties": {
    "gn:admin1_code":"5.0",
    "gn:asciiname":"Saiyid Mir Ali Shah",
    "gn:country_code":"PK",
    "gn:dem":26,
    "gn:feature_class":"P",
    "gn:feature_code":"PPL",
    "gn:name":"Saiyid Mir Ali Shah",
    "gn:population":0,
    "gn:timezone":"Asia/Karachi",
    "iso:country":"PK",
    "wof:name":"Saiyid Mir Ali Shah",
    "wof:placetype":"locality"
},
  "geometry": {"coordinates":[68.70893000000001,26.08801],"type":"Point"}
}