{
  "type": "Feature",
  "properties": {
    "gn:admin1_code":"4.0",
    "gn:asciiname":"Ahir Sarkhro",
    "gn:country_code":"PK",
    "gn:dem":175,
    "gn:feature_class":"P",
    "gn:feature_code":"PPL",
    "gn:name":"Ahir Sarkhro",
    "gn:population":0,
    "gn:timezone":"Asia/Karachi",
    "iso:country":"PK",
    "name:und_x_variant":[
        "Ah\u012br Surkhru"
    ],
    "wof:name":"Ahir Sarkhro",
    "wof:placetype":"locality"
},
  "geometry": {"coordinates":[72.32859000000001,32.02970999999999],"type":"Point"}
}