{
  "type": "Feature",
  "properties": {
    "gn:admin1_code":"7.0",
    "gn:asciiname":"Chinar",
    "gn:country_code":"PK",
    "gn:dem":2057,
    "gn:feature_class":"P",
    "gn:feature_code":"PPL",
    "gn:name":"Chinar",
    "gn:population":0,
    "gn:timezone":"Asia/Karachi",
    "iso:country":"PK",
    "wof:name":"Chinar",
    "wof:placetype":"locality"
},
  "geometry": {"coordinates":[73.85024,36.36235],"type":"Point"}
}