{
  "type": "Feature",
  "properties": {
    "gn:admin1_code":"05",
    "gn:asciiname":"Labana",
    "gn:country_code":"PK",
    "gn:dem":41,
    "gn:feature_class":"P",
    "gn:feature_code":"PPL",
    "gn:name":"Lab\u0101na",
    "gn:population":0,
    "gn:timezone":"Asia/Karachi",
    "iso:country":"PK",
    "name:pan_x_preferred":[
        "\u0a32\u0a2c\u0a3e\u0a23\u0a3e \u0a2c\u0a3f\u0a30\u0a3e\u0a26\u0a30\u0a40"
    ],
    "name:pnb_x_preferred":[
        "\u0644\u0628\u0627\u0646\u06c1"
    ],
    "wof:name":"Labana",
    "wof:placetype":"locality"
},
  "geometry": {"coordinates":[68.15000000000001,26.76667],"type":"Point"}
}