{
  "type": "Feature",
  "properties": {
    "gn:admin1_code":"4",
    "gn:asciiname":"Basti Arain",
    "gn:country_code":"PK",
    "gn:dem":107,
    "gn:feature_class":"P",
    "gn:feature_code":"PPL",
    "gn:name":"Basti Arain",
    "gn:population":0,
    "gn:timezone":"Asia/Karachi",
    "iso:country":"PK",
    "name:und_x_variant":[
        "Ar\u0101\u012bnw\u0101la"
    ],
    "wof:name":"Basti Arain",
    "wof:placetype":"locality"
},
  "geometry": {"coordinates":[71.24581999999999,29.35686],"type":"Point"}
}