{
  "type": "Feature",
  "properties": {
    "gn:admin1_code":"4.0",
    "gn:asciiname":"Gharmala",
    "gn:country_code":"PK",
    "gn:dem":241,
    "gn:feature_class":"P",
    "gn:feature_code":"PPL",
    "gn:name":"Gharmala",
    "gn:population":0,
    "gn:timezone":"Asia/Karachi",
    "iso:country":"PK",
    "name:fas_x_preferred":[
        "\u06af\u0647\u0631\u0645\u0627\u0644\u0647"
    ],
    "name:und_x_variant":[
        "Gharmalah",
        "Garm\u0101la",
        "Gharmala"
    ],
    "name:urd_x_preferred":[
        "\u06af\u06be\u0631\u0645\u0627\u0644\u06c1"
    ],
    "wof:name":"Gharmala",
    "wof:placetype":"locality"
},
  "geometry": {"coordinates":[73.68101,32.95098],"type":"Point"}
}