{
  "type": "Feature",
  "properties": {
    "gn:admin1_code":"3.0",
    "gn:asciiname":"Ziarat Pir Mela",
    "gn:country_code":"PK",
    "gn:dem":291,
    "gn:feature_class":"P",
    "gn:feature_code":"PPL",
    "gn:name":"Ziarat Pir Mela",
    "gn:population":0,
    "gn:timezone":"Asia/Karachi",
    "iso:country":"PK",
    "name:und_x_variant":[
        "Pir Mela"
    ],
    "wof:name":"Ziarat Pir Mela",
    "wof:placetype":"locality"
},
  "geometry": {"coordinates":[72.06185000000001,33.78735],"type":"Point"}
}