{
  "type": "Feature",
  "properties": {
    "gn:admin1_code":"5.0",
    "gn:asciiname":"Chak Number Thirty-two",
    "gn:country_code":"PK",
    "gn:dem":6,
    "gn:feature_class":"P",
    "gn:feature_code":"PPL",
    "gn:name":"Chak Number Thirty-two",
    "gn:population":0,
    "gn:timezone":"Asia/Karachi",
    "iso:country":"PK",
    "wof:name":"Chak Number Thirty-two",
    "wof:placetype":"locality"
},
  "geometry": {"coordinates":[68.82129999999999,24.41171],"type":"Point"}
}