{
  "type": "Feature",
  "properties": {
    "gn:admin1_code":"2.0",
    "gn:asciiname":"Alandur",
    "gn:country_code":"PK",
    "gn:dem":623,
    "gn:feature_class":"P",
    "gn:feature_code":"PPL",
    "gn:name":"Alandur",
    "gn:population":0,
    "gn:timezone":"Asia/Karachi",
    "iso:country":"PK",
    "name:bih_x_preferred":[
        "\u0905\u0932\u093e\u0928\u094d\u0926\u0941\u0930"
    ],
    "name:bpy_x_preferred":[
        "\u0986\u09b2\u09be\u09a8\u09cd\u09a6\u09c1\u09b0"
    ],
    "name:ceb_x_preferred":[
        "Alandur"
    ],
    "name:deu_x_preferred":[
        "Alandur"
    ],
    "name:fas_x_preferred":[
        "\u0627\u0644\u0627\u0646\u062f\u0648\u0631"
    ],
    "name:ita_x_preferred":[
        "Alandur"
    ],
    "name:mai_x_preferred":[
        "\u0905\u0932\u0928\u094d\u0926\u0942\u0930"
    ],
    "name:min_x_preferred":[
        "Alandur"
    ],
    "name:mlg_x_preferred":[
        "Alandur"
    ],
    "name:msa_x_preferred":[
        "Alandur"
    ],
    "name:new_x_preferred":[
        "\u0905\u0932\u0926\u094d\u0917\u092a\u0941\u0930"
    ],
    "name:por_x_preferred":[
        "Alandur"
    ],
    "name:spa_x_preferred":[
        "Alandur"
    ],
    "name:swe_x_preferred":[
        "Alandur"
    ],
    "name:tam_x_preferred":[
        "\u0b86\u0bb2\u0ba8\u0bcd\u0ba4\u0bc2\u0bb0\u0bcd"
    ],
    "name:vie_x_preferred":[
        "Alandur"
    ],
    "name:zho_x_preferred":[
        "\u963f\u5170\u675c\u5c14"
    ],
    "wof:name":"Alandur",
    "wof:placetype":"locality"
},
  "geometry": {"coordinates":[63.00059,26.36717],"type":"Point"}
}