{
  "type": "Feature",
  "properties": {
    "gn:admin1_code":"3",
    "gn:asciiname":"Barjhali",
    "gn:country_code":"PK",
    "gn:dem":3121,
    "gn:feature_class":"P",
    "gn:feature_code":"PPL",
    "gn:name":"Barjhali",
    "gn:population":0,
    "gn:timezone":"Asia/Karachi",
    "iso:country":"PK",
    "wof:name":"Barjhali",
    "wof:placetype":"locality"
},
  "geometry": {"coordinates":[73.58605,34.7674],"type":"Point"}
}