{
  "type": "Feature",
  "properties": {
    "gn:admin1_code":"3",
    "gn:asciiname":"Chakli",
    "gn:country_code":"PK",
    "gn:dem":983,
    "gn:feature_class":"P",
    "gn:feature_code":"PPL",
    "gn:name":"Chakli",
    "gn:population":0,
    "gn:timezone":"Asia/Karachi",
    "iso:country":"PK",
    "wof:name":"Chakli",
    "wof:placetype":"locality"
},
  "geometry": {"coordinates":[72.88643,34.31241],"type":"Point"}
}