{
  "type": "Feature",
  "properties": {
    "gn:admin1_code":"3",
    "gn:asciiname":"Chakli",
    "gn:country_code":"PK",
    "gn:dem":983,
    "gn:feature_class":"P",
    "gn:feature_code":"PPL",
    "gn:name":"Chakli",
    "gn:population":0,
    "gn:timezone":"Asia/Karachi",
    "iso:country":"PK",
    "name:ben_x_preferred":[
        "\u099a\u0995\u09b2\u09bf"
    ],
    "name:guj_x_preferred":[
        "\u0a9a\u0a95\u0ab0\u0ac0"
    ],
    "name:hin_x_preferred":[
        "\u091a\u0915\u0932\u0940"
    ],
    "name:kan_x_preferred":[
        "\u0c9a\u0c95\u0ccd\u0c95\u0cc1\u0cb2\u0cbf"
    ],
    "name:mai_x_preferred":[
        "\u091a\u0915\u0932\u0940"
    ],
    "name:mar_x_preferred":[
        "\u091a\u0915\u0932\u0940"
    ],
    "wof:name":"Chakli",
    "wof:placetype":"locality"
},
  "geometry": {"coordinates":[72.88643,34.31241],"type":"Point"}
}