{
  "type": "Feature",
  "properties": {
    "gn:admin1_code":"2.0",
    "gn:asciiname":"Sarwakai Kili",
    "gn:country_code":"PK",
    "gn:dem":1723,
    "gn:feature_class":"P",
    "gn:feature_code":"PPL",
    "gn:name":"Sarwakai Kili",
    "gn:population":0,
    "gn:timezone":"Asia/Karachi",
    "iso:country":"PK",
    "wof:name":"Sarwakai Kili",
    "wof:placetype":"locality"
},
  "geometry": {"coordinates":[69.13349000000001,31.54647000000001],"type":"Point"}
}