{
  "type": "Feature",
  "properties": {
    "gn:admin1_code":"4.0",
    "gn:asciiname":"Kothi Khandagh",
    "gn:country_code":"PK",
    "gn:dem":643,
    "gn:feature_class":"P",
    "gn:feature_code":"PPL",
    "gn:name":"Kothi Khandagh",
    "gn:population":0,
    "gn:timezone":"Asia/Karachi",
    "iso:country":"PK",
    "name:eng_x_preferred":[
        "Kothi Khandagh"
    ],
    "wof:name":"Kothi Khandagh",
    "wof:placetype":"locality"
},
  "geometry": {"coordinates":[70.15846999999999,30.03053],"type":"Point"}
}