{
  "type": "Feature",
  "properties": {
    "gn:admin1_code":"2.0",
    "gn:asciiname":"Balalzai Kili",
    "gn:country_code":"PK",
    "gn:dem":1360,
    "gn:feature_class":"P",
    "gn:feature_code":"PPL",
    "gn:name":"Balalzai Kili",
    "gn:population":0,
    "gn:timezone":"Asia/Karachi",
    "iso:country":"PK",
    "wof:name":"Balalzai Kili",
    "wof:placetype":"locality"
},
  "geometry": {"coordinates":[69.55869,30.41081],"type":"Point"}
}