{
  "type": "Feature",
  "properties": {
    "gn:admin1_code":"07",
    "gn:asciiname":"Rushit",
    "gn:country_code":"PK",
    "gn:dem":3205,
    "gn:feature_class":"P",
    "gn:feature_code":"PPL",
    "gn:name":"Rushit",
    "gn:population":0,
    "gn:timezone":"Asia/Karachi",
    "iso:country":"PK",
    "name:und_x_variant":[
        "Reshit"
    ],
    "wof:name":"Rushit",
    "wof:placetype":"locality"
},
  "geometry": {"coordinates":[74.50189,36.82677],"type":"Point"}
}