{
  "type": "Feature",
  "properties": {
    "gn:admin1_code":"5",
    "gn:asciiname":"Goth Imam Bakhsh Panwari",
    "gn:country_code":"PK",
    "gn:dem":51,
    "gn:feature_class":"P",
    "gn:feature_code":"PPL",
    "gn:name":"Goth Imam Bakhsh Panwari",
    "gn:population":0,
    "gn:timezone":"Asia/Karachi",
    "iso:country":"PK",
    "name:und_x_variant":[
        "Goth Im\u0101m Bakhsh Panw\u0101ri"
    ],
    "wof:name":"Goth Imam Bakhsh Panwari",
    "wof:placetype":"locality"
},
  "geometry": {"coordinates":[68.1636,27.09134],"type":"Point"}
}