{
  "type": "Feature",
  "properties": {
    "gn:admin1_code":"4.0",
    "gn:asciiname":"Basti Phullo Khalti",
    "gn:country_code":"PK",
    "gn:dem":81,
    "gn:feature_class":"P",
    "gn:feature_code":"PPL",
    "gn:name":"Basti Phullo Khalti",
    "gn:population":0,
    "gn:timezone":"Asia/Karachi",
    "iso:country":"PK",
    "wof:name":"Basti Phullo Khalti",
    "wof:placetype":"locality"
},
  "geometry": {"coordinates":[69.82994000000001,28.69756],"type":"Point"}
}