{
  "type": "Feature",
  "properties": {
    "gn:admin1_code":"02",
    "gn:asciiname":"Baski Chah",
    "gn:country_code":"PK",
    "gn:dem":1120,
    "gn:feature_class":"P",
    "gn:feature_code":"PPL",
    "gn:name":"Baski Chah",
    "gn:population":0,
    "gn:timezone":"Asia/Karachi",
    "iso:country":"PK",
    "wof:name":"Baski Chah",
    "wof:placetype":"locality"
},
  "geometry": {"coordinates":[63.77953,29.11912],"type":"Point"}
}