{
  "type": "Feature",
  "properties": {
    "gn:admin1_code":"2.0",
    "gn:asciiname":"Sumar",
    "gn:country_code":"PK",
    "gn:dem":27,
    "gn:feature_class":"P",
    "gn:feature_code":"PPL",
    "gn:name":"Sumar",
    "gn:population":0,
    "gn:timezone":"Asia/Karachi",
    "iso:country":"PK",
    "name:ceb_x_preferred":[
        "Sumar"
    ],
    "name:deu_x_preferred":[
        "Sumar"
    ],
    "wof:name":"Sumar",
    "wof:placetype":"locality"
},
  "geometry": {"coordinates":[64.43055,25.29518],"type":"Point"}
}