{
  "type": "Feature",
  "properties": {
    "gn:admin1_code":"5.0",
    "gn:asciiname":"Goth Gul Muhammad Marri",
    "gn:country_code":"PK",
    "gn:dem":42,
    "gn:feature_class":"P",
    "gn:feature_code":"PPL",
    "gn:name":"Goth Gul Muhammad Marri",
    "gn:population":0,
    "gn:timezone":"Asia/Karachi",
    "iso:country":"PK",
    "name:und_x_variant":[
        "Gul Muhammad"
    ],
    "wof:name":"Goth Gul Muhammad Marri",
    "wof:placetype":"locality"
},
  "geometry": {"coordinates":[68.29897,26.69905],"type":"Point"}
}