{
  "type": "Feature",
  "properties": {
    "gn:admin1_code":"4.0",
    "gn:asciiname":"Basti Gulkhani",
    "gn:country_code":"PK",
    "gn:dem":92,
    "gn:feature_class":"P",
    "gn:feature_code":"PPL",
    "gn:name":"Basti Gulkhani",
    "gn:population":0,
    "gn:timezone":"Asia/Karachi",
    "iso:country":"PK",
    "name:und_x_variant":[
        "Gulkh\u0101ni"
    ],
    "wof:name":"Basti Gulkhani",
    "wof:placetype":"locality"
},
  "geometry": {"coordinates":[70.37179999999999,28.95592000000001],"type":"Point"}
}