{
  "type": "Feature",
  "properties": {
    "gn:admin1_code":"4.0",
    "gn:asciiname":"Daihri",
    "gn:country_code":"PK",
    "gn:dem":107,
    "gn:feature_class":"P",
    "gn:feature_code":"PPL",
    "gn:name":"Daihri",
    "gn:population":0,
    "gn:timezone":"Asia/Karachi",
    "iso:country":"PK",
    "name:und_x_variant":[
        "Dahri",
        "Daihri"
    ],
    "wof:name":"Daihri",
    "wof:placetype":"locality"
},
  "geometry": {"coordinates":[71.37251999999999,28.96579],"type":"Point"}
}