{
  "type": "Feature",
  "properties": {
    "gn:admin1_code":"4",
    "gn:asciiname":"Alipur Kanjun",
    "gn:country_code":"PK",
    "gn:dem":123,
    "gn:feature_class":"P",
    "gn:feature_code":"PPL",
    "gn:name":"Alipur Kanjun",
    "gn:population":0,
    "gn:timezone":"Asia/Karachi",
    "iso:country":"PK",
    "name:und_x_variant":[
        "Al\u012bpur K\u0101njun"
    ],
    "wof:name":"Alipur Kanjun",
    "wof:placetype":"locality"
},
  "geometry": {"coordinates":[71.87397,29.68311],"type":"Point"}
}