{
  "type": "Feature",
  "properties": {
    "gn:admin1_code":"5",
    "gn:asciiname":"Goth Daria Khan Shaikh",
    "gn:country_code":"PK",
    "gn:dem":62,
    "gn:feature_class":"P",
    "gn:feature_code":"PPL",
    "gn:name":"Goth Daria Khan Shaikh",
    "gn:population":0,
    "gn:timezone":"Asia/Karachi",
    "iso:country":"PK",
    "name:und_x_variant":[
        "Sheikhw\u0101li Goth"
    ],
    "wof:name":"Goth Daria Khan Shaikh",
    "wof:placetype":"locality"
},
  "geometry": {"coordinates":[68.61555,27.65061],"type":"Point"}
}