{
  "type": "Feature",
  "properties": {
    "gn:admin1_code":"4",
    "gn:asciiname":"Batwala",
    "gn:country_code":"PK",
    "gn:dem":108,
    "gn:feature_class":"P",
    "gn:feature_code":"PPL",
    "gn:name":"Batwala",
    "gn:population":0,
    "gn:timezone":"Asia/Karachi",
    "iso:country":"PK",
    "name:und_x_variant":[
        "Basti B\u0101t"
    ],
    "wof:name":"Batwala",
    "wof:placetype":"locality"
},
  "geometry": {"coordinates":[70.80127,29.56378],"type":"Point"}
}