{
  "type": "Feature",
  "properties": {
    "gn:admin1_code":"1.0",
    "gn:asciiname":"Chhar Khel",
    "gn:country_code":"PK",
    "gn:dem":2570,
    "gn:feature_class":"P",
    "gn:feature_code":"PPL",
    "gn:name":"Chhar Khel",
    "gn:population":0,
    "gn:timezone":"Asia/Karachi",
    "iso:country":"PK",
    "name:und_x_variant":[
        "Ch\u0101r Khel"
    ],
    "wof:name":"Chhar Khel",
    "wof:placetype":"locality"
},
  "geometry": {"coordinates":[69.58158,33.06116],"type":"Point"}
}