{
  "type": "Feature",
  "properties": {
    "gn:admin1_code":"4.0",
    "gn:asciiname":"Bissa",
    "gn:country_code":"PK",
    "gn:dem":832,
    "gn:feature_class":"P",
    "gn:feature_code":"PPL",
    "gn:name":"Bissa",
    "gn:population":0,
    "gn:timezone":"Asia/Karachi",
    "iso:country":"PK",
    "name:ceb_x_preferred":[
        "Bissa"
    ],
    "name:deu_x_preferred":[
        "Bissa"
    ],
    "name:fra_x_preferred":[
        "Bissa"
    ],
    "name:swe_x_preferred":[
        "Bissa"
    ],
    "wof:name":"Bissa",
    "wof:placetype":"locality"
},
  "geometry": {"coordinates":[73.37384,33.74289],"type":"Point"}
}