{
  "type": "Feature",
  "properties": {
    "gn:admin1_code":"4",
    "gn:asciiname":"Chak Sixty-one North Branch",
    "gn:country_code":"PK",
    "gn:dem":192,
    "gn:feature_class":"P",
    "gn:feature_code":"PPL",
    "gn:name":"Chak Sixty-one North Branch",
    "gn:population":0,
    "gn:timezone":"Asia/Karachi",
    "iso:country":"PK",
    "name:und_x_variant":[
        "Chak 61 NB"
    ],
    "wof:name":"Chak Sixty-one North Branch",
    "wof:placetype":"locality"
},
  "geometry": {"coordinates":[72.78425,32.25575],"type":"Point"}
}