{
  "type": "Feature",
  "properties": {
    "gn:admin1_code":"5",
    "gn:asciiname":"Muhammad Bakhsh Laghari",
    "gn:country_code":"PK",
    "gn:dem":57,
    "gn:feature_class":"P",
    "gn:feature_code":"PPL",
    "gn:name":"Muhammad Bakhsh Lagh\u0101ri",
    "gn:population":0,
    "gn:timezone":"Asia/Karachi",
    "iso:country":"PK",
    "wof:name":"Muhammad Bakhsh Laghari",
    "wof:placetype":"locality"
},
  "geometry": {"coordinates":[68.37361,27.92917000000001],"type":"Point"}
}