{
  "type": "Feature",
  "properties": {
    "gn:admin1_code":"4.0",
    "gn:asciiname":"Goth Bajan",
    "gn:country_code":"PK",
    "gn:dem":115,
    "gn:feature_class":"P",
    "gn:feature_code":"PPL",
    "gn:name":"Goth Bajan",
    "gn:population":0,
    "gn:timezone":"Asia/Karachi",
    "iso:country":"PK",
    "name:eng_x_preferred":[
        "Goth Bh\u0101jan"
    ],
    "name:eng_x_variant":[
        "Goth Bajan"
    ],
    "wof:name":"Goth Bajan",
    "wof:placetype":"locality"
},
  "geometry": {"coordinates":[71.64662,29.40828],"type":"Point"}
}