{
  "type": "Feature",
  "properties": {
    "gn:admin1_code":"4.0",
    "gn:asciiname":"Basti Buchcha",
    "gn:country_code":"PK",
    "gn:dem":103,
    "gn:feature_class":"P",
    "gn:feature_code":"PPL",
    "gn:name":"Basti Buchcha",
    "gn:population":0,
    "gn:timezone":"Asia/Karachi",
    "iso:country":"PK",
    "name:und_x_variant":[
        "Basti Bucha"
    ],
    "wof:name":"Basti Buchcha",
    "wof:placetype":"locality"
},
  "geometry": {"coordinates":[71.28993,29.11405],"type":"Point"}
}