{
  "type": "Feature",
  "properties": {
    "gn:admin1_code":"5.0",
    "gn:asciiname":"Goth Raho Gohram",
    "gn:country_code":"PK",
    "gn:dem":142,
    "gn:feature_class":"P",
    "gn:feature_code":"PPL",
    "gn:name":"Goth Raho Gohram",
    "gn:population":0,
    "gn:timezone":"Asia/Karachi",
    "iso:country":"PK",
    "name:und_x_variant":[
        "Goth Gohr\u0101m"
    ],
    "wof:name":"Goth Raho Gohram",
    "wof:placetype":"locality"
},
  "geometry": {"coordinates":[67.16838,25.15166],"type":"Point"}
}