{
  "type": "Feature",
  "properties": {
    "gn:admin1_code":"2.0",
    "gn:asciiname":"Muhammad Azim Dik",
    "gn:country_code":"PK",
    "gn:dem":987,
    "gn:feature_class":"P",
    "gn:feature_code":"PPL",
    "gn:name":"Muhammad Azim Dik",
    "gn:population":0,
    "gn:timezone":"Asia/Karachi",
    "iso:country":"PK",
    "wof:name":"Muhammad Azim Dik",
    "wof:placetype":"locality"
},
  "geometry": {"coordinates":[64.36841,28.69407],"type":"Point"}
}