{
  "type": "Feature",
  "properties": {
    "gn:admin1_code":"4",
    "gn:asciiname":"Chak Five Hundred Seventy-two Gugera Branch",
    "gn:country_code":"PK",
    "gn:dem":196,
    "gn:feature_class":"P",
    "gn:feature_code":"PPL",
    "gn:name":"Chak Five Hundred Seventy-two Gugera Branch",
    "gn:population":0,
    "gn:timezone":"Asia/Karachi",
    "iso:country":"PK",
    "name:und_x_variant":[
        "Isl\u0101m\u0101b\u0101d Gharbi",
        "Isl\u0101m\u0101bad"
    ],
    "wof:name":"Chak Five Hundred Seventy-two Gugera Branch",
    "wof:placetype":"locality"
},
  "geometry": {"coordinates":[73.70271,31.52206],"type":"Point"}
}