{
  "type": "Feature",
  "properties": {
    "gn:admin1_code":"4.0",
    "gn:asciiname":"Murade Khurd",
    "gn:country_code":"PK",
    "gn:dem":207,
    "gn:feature_class":"P",
    "gn:feature_code":"PPL",
    "gn:name":"Murade Khurd",
    "gn:population":0,
    "gn:timezone":"Asia/Karachi",
    "iso:country":"PK",
    "wof:name":"Murade Khurd",
    "wof:placetype":"locality"
},
  "geometry": {"coordinates":[74.01158000000002,31.67242],"type":"Point"}
}