{
  "type": "Feature",
  "properties": {
    "gn:admin1_code":"4.0",
    "gn:asciiname":"Chak Sohi",
    "gn:country_code":"PK",
    "gn:dem":156,
    "gn:feature_class":"P",
    "gn:feature_code":"PPL",
    "gn:name":"Chak Sohi",
    "gn:population":0,
    "gn:timezone":"Asia/Karachi",
    "iso:country":"PK",
    "name:und_x_variant":[
        "Chak 16",
        "Chak Sixteen",
        "Chak Sohi"
    ],
    "wof:name":"Chak Sohi",
    "wof:placetype":"locality"
},
  "geometry": {"coordinates":[70.85392,31.19086],"type":"Point"}
}