{
  "type": "Feature",
  "properties": {
    "gn:admin1_code":"4.0",
    "gn:asciiname":"Khairewal",
    "gn:country_code":"PK",
    "gn:dem":210,
    "gn:feature_class":"P",
    "gn:feature_code":"PPL",
    "gn:name":"Khairewal",
    "gn:population":0,
    "gn:timezone":"Asia/Karachi",
    "iso:country":"PK",
    "name:und_x_variant":[
        "Kherewal",
        "Khairewal"
    ],
    "wof:name":"Khairewal",
    "wof:placetype":"locality"
},
  "geometry": {"coordinates":[73.46295000000001,32.36575999999999],"type":"Point"}
}