{
  "type": "Feature",
  "properties": {
    "gn:admin1_code":"4.0",
    "gn:asciiname":"Mungawala",
    "gn:country_code":"PK",
    "gn:dem":200,
    "gn:feature_class":"P",
    "gn:feature_code":"PPL",
    "gn:name":"Mung\u0101w\u0101la",
    "gn:population":0,
    "gn:timezone":"Asia/Karachi",
    "iso:country":"PK",
    "wof:name":"Mungawala",
    "wof:placetype":"locality"
},
  "geometry": {"coordinates":[73.57222,31.88667],"type":"Point"}
}