{
  "type": "Feature",
  "properties": {
    "gn:admin1_code":"1.0",
    "gn:asciiname":"Mego Kate",
    "gn:country_code":"PK",
    "gn:dem":560,
    "gn:feature_class":"P",
    "gn:feature_code":"PPL",
    "gn:name":"Mego Kate",
    "gn:population":0,
    "gn:timezone":"Asia/Karachi",
    "iso:country":"PK",
    "name:und_x_variant":[
        "Mego Kats"
    ],
    "wof:name":"Mego Kate",
    "wof:placetype":"locality"
},
  "geometry": {"coordinates":[71.29267,34.24064],"type":"Point"}
}