{
  "type": "Feature",
  "properties": {
    "gn:admin1_code":"2.0",
    "gn:asciiname":"Basti Muhammad",
    "gn:country_code":"PK",
    "gn:dem":99,
    "gn:feature_class":"P",
    "gn:feature_code":"PPL",
    "gn:name":"Basti Muhammad",
    "gn:population":0,
    "gn:timezone":"Asia/Karachi",
    "iso:country":"PK",
    "name:und_x_variant":[
        "Basti Hamid",
        "Basti Muhammad",
        "Basti H\u0101mad"
    ],
    "wof:name":"Basti Muhammad",
    "wof:placetype":"locality"
},
  "geometry": {"coordinates":[67.84659000000001,29.03157],"type":"Point"}
}