{
  "type": "Feature",
  "properties": {
    "gn:admin1_code":"6.0",
    "gn:asciiname":"Dinguh",
    "gn:country_code":"PK",
    "gn:dem":525,
    "gn:feature_class":"P",
    "gn:feature_code":"PPL",
    "gn:name":"Dinguh",
    "gn:population":0,
    "gn:timezone":"Asia/Karachi",
    "iso:country":"PK",
    "name:und_x_variant":[
        "Dinga"
    ],
    "wof:name":"Dinguh",
    "wof:placetype":"locality"
},
  "geometry": {"coordinates":[73.68971999999999,33.54334],"type":"Point"}
}