{
  "type": "Feature",
  "properties": {
    "gn:admin1_code":"3",
    "gn:asciiname":"Seri",
    "gn:country_code":"PK",
    "gn:dem":538,
    "gn:feature_class":"P",
    "gn:feature_code":"PPL",
    "gn:name":"Seri",
    "gn:population":0,
    "gn:timezone":"Asia/Karachi",
    "iso:country":"PK",
    "wof:name":"Seri",
    "wof:placetype":"locality"
},
  "geometry": {"coordinates":[72.82592,34.02538],"type":"Point"}
}