{
  "type": "Feature",
  "properties": {
    "gn:admin1_code":"3.0",
    "gn:asciiname":"Biro",
    "gn:country_code":"PK",
    "gn:dem":1019,
    "gn:feature_class":"P",
    "gn:feature_code":"PPL",
    "gn:name":"Biro",
    "gn:population":0,
    "gn:timezone":"Asia/Karachi",
    "iso:country":"PK",
    "name:eng_x_preferred":[
        "B\u012br"
    ],
    "wof:name":"Biro",
    "wof:placetype":"locality"
},
  "geometry": {"coordinates":[71.70045,34.93360999999999],"type":"Point"}
}