{
  "type": "Feature",
  "properties": {
    "gn:admin1_code":"04",
    "gn:asciiname":"Mandka",
    "gn:country_code":"PK",
    "gn:dem":123,
    "gn:feature_class":"P",
    "gn:feature_code":"PPL",
    "gn:name":"Mandka",
    "gn:population":0,
    "gn:timezone":"Asia/Karachi",
    "iso:country":"PK",
    "name:und_x_variant":[
        "Mondka"
    ],
    "wof:name":"Mandka",
    "wof:placetype":"locality"
},
  "geometry": {"coordinates":[71.05724000000002,29.96178],"type":"Point"}
}