{
  "type": "Feature",
  "properties": {
    "gn:admin1_code":"4",
    "gn:asciiname":"Sharqi Hamalwali",
    "gn:country_code":"PK",
    "gn:dem":238,
    "gn:feature_class":"P",
    "gn:feature_code":"PPL",
    "gn:name":"Sharqi Hamalwali",
    "gn:population":0,
    "gn:timezone":"Asia/Karachi",
    "iso:country":"PK",
    "name:und_x_variant":[
        "Jhok Ham\u0101liw\u0101la"
    ],
    "wof:name":"Sharqi Hamalwali",
    "wof:placetype":"locality"
},
  "geometry": {"coordinates":[70.49585,30.91807],"type":"Point"}
}