{
  "type": "Feature",
  "properties": {
    "gn:admin1_code":"6",
    "gn:asciiname":"Akhruti",
    "gn:country_code":"PK",
    "gn:dem":1187,
    "gn:feature_class":"P",
    "gn:feature_code":"PPL",
    "gn:name":"Akhruti",
    "gn:population":0,
    "gn:timezone":"Asia/Karachi",
    "iso:country":"PK",
    "name:und_x_variant":[
        "Akruti"
    ],
    "wof:name":"Akhruti",
    "wof:placetype":"locality"
},
  "geometry": {"coordinates":[73.90864000000001,33.66374],"type":"Point"}
}