{
  "type": "Feature",
  "properties": {
    "gn:admin1_code":"7.0",
    "gn:asciiname":"Keno Kot",
    "gn:country_code":"PK",
    "gn:dem":1635,
    "gn:feature_class":"P",
    "gn:feature_code":"PPL",
    "gn:name":"Keno Kot",
    "gn:population":0,
    "gn:timezone":"Asia/Karachi",
    "iso:country":"PK",
    "wof:name":"Keno Kot",
    "wof:placetype":"locality"
},
  "geometry": {"coordinates":[74.13984000000001,35.49562],"type":"Point"}
}