{
  "type": "Feature",
  "properties": {
    "gn:admin1_code":"4",
    "gn:asciiname":"Mandrani",
    "gn:country_code":"PK",
    "gn:dem":134,
    "gn:feature_class":"P",
    "gn:feature_code":"PPL",
    "gn:name":"Mandrani",
    "gn:population":0,
    "gn:timezone":"Asia/Karachi",
    "iso:country":"PK",
    "name:und_x_variant":[
        "Mondr\u0101ni"
    ],
    "wof:name":"Mandrani",
    "wof:placetype":"locality"
},
  "geometry": {"coordinates":[70.59119,30.08607],"type":"Point"}
}