{
  "type": "Feature",
  "properties": {
    "gn:admin1_code":"3.0",
    "gn:asciiname":"Nangabad",
    "gn:country_code":"PK",
    "gn:dem":397,
    "gn:feature_class":"P",
    "gn:feature_code":"PPL",
    "gn:name":"Nangabad",
    "gn:population":0,
    "gn:timezone":"Asia/Karachi",
    "iso:country":"PK",
    "wof:name":"Nangabad",
    "wof:placetype":"locality"
},
  "geometry": {"coordinates":[72.1923,34.36599],"type":"Point"}
}