{
  "type": "Feature",
  "properties": {
    "gn:admin1_code":"3.0",
    "gn:asciiname":"Dab Banda",
    "gn:country_code":"PK",
    "gn:dem":301,
    "gn:feature_class":"P",
    "gn:feature_code":"PPL",
    "gn:name":"Dab Banda",
    "gn:population":0,
    "gn:timezone":"Asia/Karachi",
    "iso:country":"PK",
    "name:eng_x_preferred":[
        "B\u0101nda"
    ],
    "wof:name":"Dab Banda",
    "wof:placetype":"locality"
},
  "geometry": {"coordinates":[71.79448000000002,34.13252],"type":"Point"}
}