{
  "type": "Feature",
  "properties": {
    "gn:admin1_code":"3.0",
    "gn:asciiname":"Kelo",
    "gn:country_code":"PK",
    "gn:dem":1002,
    "gn:feature_class":"P",
    "gn:feature_code":"PPL",
    "gn:name":"Kelo",
    "gn:population":0,
    "gn:timezone":"Asia/Karachi",
    "iso:country":"PK",
    "name:ceb_x_preferred":[
        "Kelo"
    ],
    "name:fin_x_preferred":[
        "Kelo"
    ],
    "name:ita_x_preferred":[
        "Kelo"
    ],
    "name:nld_x_preferred":[
        "Kelo"
    ],
    "name:slk_x_preferred":[
        "Kelo"
    ],
    "name:swe_x_preferred":[
        "Kelo"
    ],
    "wof:name":"Kelo",
    "wof:placetype":"locality"
},
  "geometry": {"coordinates":[72.78140999999999,34.56401],"type":"Point"}
}