{
  "type": "Feature",
  "properties": {
    "gn:admin1_code":"4.0",
    "gn:asciiname":"Bahmaniwala",
    "gn:country_code":"PK",
    "gn:dem":204,
    "gn:feature_class":"P",
    "gn:feature_code":"PPL",
    "gn:name":"Bahmaniwala",
    "gn:population":0,
    "gn:timezone":"Asia/Karachi",
    "iso:country":"PK",
    "name:und_x_variant":[
        "Usm\u0101nw\u0101la"
    ],
    "wof:name":"Bahmaniwala",
    "wof:placetype":"locality"
},
  "geometry": {"coordinates":[74.2072,31.10769],"type":"Point"}
}