{
  "type": "Feature",
  "properties": {
    "gn:admin1_code":"3.0",
    "gn:asciiname":"Nishan Banda",
    "gn:country_code":"PK",
    "gn:dem":1902,
    "gn:feature_class":"P",
    "gn:feature_code":"PPL",
    "gn:name":"Nishan Banda",
    "gn:population":0,
    "gn:timezone":"Asia/Karachi",
    "iso:country":"PK",
    "wof:name":"Nishan Banda",
    "wof:placetype":"locality"
},
  "geometry": {"coordinates":[72.06874000000001,35.06899],"type":"Point"}
}