{
  "type": "Feature",
  "properties": {
    "gn:admin1_code":"8.0",
    "gn:asciiname":"Mari",
    "gn:country_code":"PK",
    "gn:dem":579,
    "gn:feature_class":"P",
    "gn:feature_code":"PPL",
    "gn:name":"Mari",
    "gn:population":0,
    "gn:timezone":"Asia/Karachi",
    "iso:country":"PK",
    "name:und_x_variant":[
        "M\u016bri"
    ],
    "wof:name":"Mari",
    "wof:placetype":"locality"
},
  "geometry": {"coordinates":[73.28021,33.6364],"type":"Point"}
}