{
  "type": "Feature",
  "properties": {
    "gn:admin1_code":"5",
    "gn:asciiname":"Goth Allahyar Kaloi",
    "gn:country_code":"PK",
    "gn:dem":25,
    "gn:feature_class":"P",
    "gn:feature_code":"PPL",
    "gn:name":"Goth Allahyar Kaloi",
    "gn:population":0,
    "gn:timezone":"Asia/Karachi",
    "iso:country":"PK",
    "name:und_x_variant":[
        "Goth All\u0101hy\u0101r Kaloi"
    ],
    "wof:name":"Goth Allahyar Kaloi",
    "wof:placetype":"locality"
},
  "geometry": {"coordinates":[68.80553,25.84519],"type":"Point"}
}