{
  "type": "Feature",
  "properties": {
    "gn:admin1_code":"5.0",
    "gn:asciiname":"Haji Ghulam Qadar",
    "gn:country_code":"PK",
    "gn:dem":42,
    "gn:feature_class":"P",
    "gn:feature_code":"PPL",
    "gn:name":"Haji Ghulam Qadar",
    "gn:population":0,
    "gn:timezone":"Asia/Karachi",
    "iso:country":"PK",
    "name:und_x_variant":[
        "Goth Ghul\u0101m Q\u0101dir"
    ],
    "wof:name":"Haji Ghulam Qadar",
    "wof:placetype":"locality"
},
  "geometry": {"coordinates":[67.00053,25.07454],"type":"Point"}
}