{
  "type": "Feature",
  "properties": {
    "gn:admin1_code":"4.0",
    "gn:asciiname":"Karam Husainwala",
    "gn:country_code":"PK",
    "gn:dem":138,
    "gn:feature_class":"P",
    "gn:feature_code":"PPL",
    "gn:name":"Karam Husainw\u0101la",
    "gn:population":0,
    "gn:timezone":"Asia/Karachi",
    "iso:country":"PK",
    "wof:name":"Karam Husainwala",
    "wof:placetype":"locality"
},
  "geometry": {"coordinates":[70.83544999999999,30.80042000000001],"type":"Point"}
}