{
  "type": "Feature",
  "properties": {
    "gn:admin1_code":"1.0",
    "gn:asciiname":"Nurjan Kala",
    "gn:country_code":"PK",
    "gn:dem":2478,
    "gn:feature_class":"P",
    "gn:feature_code":"PPL",
    "gn:name":"Nurjan Kala",
    "gn:population":0,
    "gn:timezone":"Asia/Karachi",
    "iso:country":"PK",
    "wof:name":"Nurjan Kala",
    "wof:placetype":"locality"
},
  "geometry": {"coordinates":[69.66589999999999,32.73862],"type":"Point"}
}