{
  "type": "Feature",
  "properties": {
    "gn:admin1_code":"5.0",
    "gn:asciiname":"Pachaio Weri",
    "gn:country_code":"PK",
    "gn:dem":32,
    "gn:feature_class":"P",
    "gn:feature_code":"PPL",
    "gn:name":"Pachaio Weri",
    "gn:population":0,
    "gn:timezone":"Asia/Karachi",
    "iso:country":"PK",
    "wof:name":"Pachaio Weri",
    "wof:placetype":"locality"
},
  "geometry": {"coordinates":[69.48878000000001,24.47947000000001],"type":"Point"}
}