{
  "type": "Feature",
  "properties": {
    "gn:admin1_code":"4",
    "gn:asciiname":"Janiwala",
    "gn:country_code":"PK",
    "gn:dem":198,
    "gn:feature_class":"P",
    "gn:feature_code":"PPL",
    "gn:name":"Janiwala",
    "gn:population":0,
    "gn:timezone":"Asia/Karachi",
    "iso:country":"PK",
    "wof:name":"Janiwala",
    "wof:placetype":"locality"
},
  "geometry": {"coordinates":[73.77229,31.46067],"type":"Point"}
}