{
  "type": "Feature",
  "properties": {
    "gn:admin1_code":"4",
    "gn:asciiname":"Basti Pir Bakhsh",
    "gn:country_code":"PK",
    "gn:dem":103,
    "gn:feature_class":"P",
    "gn:feature_code":"PPL",
    "gn:name":"Basti Pir Bakhsh",
    "gn:population":0,
    "gn:timezone":"Asia/Karachi",
    "iso:country":"PK",
    "name:und_x_variant":[
        "Basti P\u012br Bakhsh Khas",
        "P\u012br Pakhsh",
        "Basti Pir Bakhsh"
    ],
    "wof:name":"Basti Pir Bakhsh",
    "wof:placetype":"locality"
},
  "geometry": {"coordinates":[70.50456,29.37548],"type":"Point"}
}