{
  "type": "Feature",
  "properties": {
    "gn:admin1_code":"4.0",
    "gn:asciiname":"Badduki",
    "gn:country_code":"PK",
    "gn:dem":205,
    "gn:feature_class":"P",
    "gn:feature_code":"PPL",
    "gn:name":"Badduki",
    "gn:population":0,
    "gn:timezone":"Asia/Karachi",
    "iso:country":"PK",
    "name:und_x_variant":[
        "Budduke"
    ],
    "wof:name":"Badduki",
    "wof:placetype":"locality"
},
  "geometry": {"coordinates":[74.18281999999998,31.32411],"type":"Point"}
}