{
  "type": "Feature",
  "properties": {
    "gn:admin1_code":"2.0",
    "gn:asciiname":"Pan Malik Kili",
    "gn:country_code":"PK",
    "gn:dem":1204,
    "gn:feature_class":"P",
    "gn:feature_code":"PPL",
    "gn:name":"Pan Malik Kili",
    "gn:population":0,
    "gn:timezone":"Asia/Karachi",
    "iso:country":"PK",
    "wof:name":"Pan Malik Kili",
    "wof:placetype":"locality"
},
  "geometry": {"coordinates":[69.89768000000001,30.77838],"type":"Point"}
}