{
  "type": "Feature",
  "properties": {
    "gn:admin1_code":"4.0",
    "gn:asciiname":"Bauhti Pind",
    "gn:country_code":"PK",
    "gn:dem":447,
    "gn:feature_class":"P",
    "gn:feature_code":"PPL",
    "gn:name":"Bauhti Pind",
    "gn:population":0,
    "gn:timezone":"Asia/Karachi",
    "iso:country":"PK",
    "name:und_x_variant":[
        "Bahuti Pind",
        "Bauhti Pind"
    ],
    "wof:name":"Bauhti Pind",
    "wof:placetype":"locality"
},
  "geometry": {"coordinates":[72.75046999999998,33.83003],"type":"Point"}
}