{
  "type": "Feature",
  "properties": {
    "gn:admin1_code":"5.0",
    "gn:asciiname":"Khan Muhammad Shah",
    "gn:country_code":"PK",
    "gn:dem":12,
    "gn:feature_class":"P",
    "gn:feature_code":"PPL",
    "gn:name":"Khan Muhammad Shah",
    "gn:population":0,
    "gn:timezone":"Asia/Karachi",
    "iso:country":"PK",
    "name:eng_x_preferred":[
        "Khan Muhammad Shah"
    ],
    "wof:name":"Khan Muhammad Shah",
    "wof:placetype":"locality"
},
  "geometry": {"coordinates":[68.13514000000001,24.69073],"type":"Point"}
}