{
  "type": "Feature",
  "properties": {
    "gn:admin1_code":"4",
    "gn:asciiname":"Dholo Chahan",
    "gn:country_code":"PK",
    "gn:dem":238,
    "gn:feature_class":"P",
    "gn:feature_code":"PPL",
    "gn:name":"Dholo Chahan",
    "gn:population":0,
    "gn:timezone":"Asia/Karachi",
    "iso:country":"PK",
    "name:und_x_variant":[
        "Dhaluchan",
        "Dholo Chah\u0101n"
    ],
    "wof:name":"Dholo Chahan",
    "wof:placetype":"locality"
},
  "geometry": {"coordinates":[74.45278,32.61806],"type":"Point"}
}