{
  "type": "Feature",
  "properties": {
    "gn:admin1_code":"4.0",
    "gn:asciiname":"Khilri",
    "gn:country_code":"PK",
    "gn:dem":342,
    "gn:feature_class":"P",
    "gn:feature_code":"PPL",
    "gn:name":"Khilri",
    "gn:population":0,
    "gn:timezone":"Asia/Karachi",
    "iso:country":"PK",
    "wof:name":"Khilri",
    "wof:placetype":"locality"
},
  "geometry": {"coordinates":[72.68382,33.26015],"type":"Point"}
}