{
  "type": "Feature",
  "properties": {
    "gn:admin1_code":"3.0",
    "gn:asciiname":"Khal",
    "gn:country_code":"PK",
    "gn:dem":1450,
    "gn:feature_class":"P",
    "gn:feature_code":"PPL",
    "gn:name":"Khal",
    "gn:population":0,
    "gn:timezone":"Asia/Karachi",
    "iso:country":"PK",
    "wof:name":"Khal",
    "wof:placetype":"locality"
},
  "geometry": {"coordinates":[72.93494,35.01521],"type":"Point"}
}