{
  "type": "Feature",
  "properties": {
    "gn:admin1_code":"7.0",
    "gn:asciiname":"Shuinj",
    "gn:country_code":"PK",
    "gn:dem":3812,
    "gn:feature_class":"P",
    "gn:feature_code":"PPL",
    "gn:name":"Shuinj",
    "gn:population":0,
    "gn:timezone":"Asia/Karachi",
    "iso:country":"PK",
    "wof:name":"Shuinj",
    "wof:placetype":"locality"
},
  "geometry": {"coordinates":[73.86979000000002,36.85018],"type":"Point"}
}