{
  "type": "Feature",
  "properties": {
    "gn:admin1_code":"2.0",
    "gn:asciiname":"Kili Nali",
    "gn:country_code":"PK",
    "gn:dem":814,
    "gn:feature_class":"P",
    "gn:feature_code":"PPL",
    "gn:name":"Kili Nali",
    "gn:population":0,
    "gn:timezone":"Asia/Karachi",
    "iso:country":"PK",
    "wof:name":"Kili Nali",
    "wof:placetype":"locality"
},
  "geometry": {"coordinates":[63.7836,28.83027],"type":"Point"}
}