{
  "type": "Feature",
  "properties": {
    "gn:admin1_code":"03",
    "gn:asciiname":"Mugh",
    "gn:country_code":"PK",
    "gn:dem":2022,
    "gn:feature_class":"P",
    "gn:feature_code":"PPL",
    "gn:name":"Mugh",
    "gn:population":0,
    "gn:timezone":"Asia/Karachi",
    "iso:country":"PK",
    "name:und_x_variant":[
        "Mogh",
        "Mugh"
    ],
    "name:urd_x_preferred":[
        "\u0645\u0648\u063a"
    ],
    "wof:name":"Mugh",
    "wof:placetype":"locality"
},
  "geometry": {"coordinates":[71.65609000000001,36.01231],"type":"Point"}
}