{
  "type": "Feature",
  "properties": {
    "gn:admin1_code":"2.0",
    "gn:asciiname":"Girawali Kili",
    "gn:country_code":"PK",
    "gn:dem":1761,
    "gn:feature_class":"P",
    "gn:feature_code":"PPL",
    "gn:name":"Girawali Kili",
    "gn:population":0,
    "gn:timezone":"Asia/Karachi",
    "iso:country":"PK",
    "name:und_x_variant":[
        "Girdawai"
    ],
    "wof:name":"Girawali Kili",
    "wof:placetype":"locality"
},
  "geometry": {"coordinates":[69.34295999999999,30.85027],"type":"Point"}
}