{
  "type": "Feature",
  "properties": {
    "gn:admin1_code":"4.0",
    "gn:asciiname":"Khuri",
    "gn:country_code":"PK",
    "gn:dem":655,
    "gn:feature_class":"P",
    "gn:feature_code":"PPL",
    "gn:name":"Khuri",
    "gn:population":0,
    "gn:timezone":"Asia/Karachi",
    "iso:country":"PK",
    "name:eng_x_preferred":[
        "Khuri"
    ],
    "name:fra_x_preferred":[
        "Khuri"
    ],
    "name:hin_x_preferred":[
        "\u0916\u0941\u0930\u0908"
    ],
    "wof:name":"Khuri",
    "wof:placetype":"locality"
},
  "geometry": {"coordinates":[70.21873000000001,30.11366],"type":"Point"}
}