{
  "type": "Feature",
  "properties": {
    "gn:admin1_code":"04",
    "gn:asciiname":"Zahidwala",
    "gn:country_code":"PK",
    "gn:dem":120,
    "gn:feature_class":"P",
    "gn:feature_code":"PPL",
    "gn:name":"Zahidwala",
    "gn:population":0,
    "gn:timezone":"Asia/Karachi",
    "iso:country":"PK",
    "name:eng_x_preferred":[
        "Z\u0101idw\u0101li"
    ],
    "name:und_x_variant":[
        "Z\u0101hidw\u0101li",
        "Zahidwala"
    ],
    "wof:name":"Zahidwala",
    "wof:placetype":"locality"
},
  "geometry": {"coordinates":[70.91001,29.9974],"type":"Point"}
}