{
  "type": "Feature",
  "properties": {
    "gn:admin1_code":"6",
    "gn:asciiname":"Alam-da-Gura",
    "gn:country_code":"PK",
    "gn:dem":560,
    "gn:feature_class":"P",
    "gn:feature_code":"PPL",
    "gn:name":"Alam-da-Gura",
    "gn:population":0,
    "gn:timezone":"Asia/Karachi",
    "iso:country":"PK",
    "name:und_x_variant":[
        "\u0100lam ka Ker"
    ],
    "wof:name":"Alam-da-Gura",
    "wof:placetype":"locality"
},
  "geometry": {"coordinates":[74.22723000000001,32.98821],"type":"Point"}
}