{
  "type": "Feature",
  "properties": {
    "gn:admin1_code":"4.0",
    "gn:asciiname":"Mandar",
    "gn:country_code":"PK",
    "gn:dem":253,
    "gn:feature_class":"P",
    "gn:feature_code":"PPL",
    "gn:name":"Mandar",
    "gn:population":0,
    "gn:timezone":"Asia/Karachi",
    "iso:country":"PK",
    "name:ceb_x_preferred":[
        "Mandar"
    ],
    "name:deu_x_preferred":[
        "Mandar"
    ],
    "name:fra_x_preferred":[
        "Mandar"
    ],
    "name:ind_x_preferred":[
        "Mandar"
    ],
    "wof:name":"Mandar",
    "wof:placetype":"locality"
},
  "geometry": {"coordinates":[74.84952,32.27526],"type":"Point"}
}