{
  "type": "Feature",
  "properties": {
    "gn:admin1_code":"2.0",
    "gn:asciiname":"Kili Mahmuzna",
    "gn:country_code":"PK",
    "gn:dem":2047,
    "gn:feature_class":"P",
    "gn:feature_code":"PPL",
    "gn:name":"Kili Mahmuzna",
    "gn:population":0,
    "gn:timezone":"Asia/Karachi",
    "iso:country":"PK",
    "wof:name":"Kili Mahmuzna",
    "wof:placetype":"locality"
},
  "geometry": {"coordinates":[67.55951999999999,30.46687],"type":"Point"}
}