{
  "type": "Feature",
  "properties": {
    "gn:admin1_code":"2",
    "gn:asciiname":"Manzai Kili",
    "gn:country_code":"PK",
    "gn:dem":950,
    "gn:feature_class":"P",
    "gn:feature_code":"PPL",
    "gn:name":"Manzai Kili",
    "gn:population":0,
    "gn:timezone":"Asia/Karachi",
    "iso:country":"PK",
    "name:eng_x_preferred":[
        "\u0100lam Shaikh"
    ],
    "wof:name":"Manzai Kili",
    "wof:placetype":"locality"
},
  "geometry": {"coordinates":[68.90446999999999,30.08527],"type":"Point"}
}