{
  "type": "Feature",
  "properties": {
    "gn:admin1_code":"4",
    "gn:asciiname":"Farid Bakhshwala",
    "gn:country_code":"PK",
    "gn:dem":115,
    "gn:feature_class":"P",
    "gn:feature_code":"PPL",
    "gn:name":"Farid Bakhshwala",
    "gn:population":0,
    "gn:timezone":"Asia/Karachi",
    "iso:country":"PK",
    "wof:name":"Farid Bakhshwala",
    "wof:placetype":"locality"
},
  "geometry": {"coordinates":[71.30603000000001,30.0257],"type":"Point"}
}