{
  "type": "Feature",
  "properties": {
    "gn:admin1_code":"6",
    "gn:asciiname":"Pind Khurd",
    "gn:country_code":"PK",
    "gn:dem":449,
    "gn:feature_class":"P",
    "gn:feature_code":"PPL",
    "gn:name":"Pind Khurd",
    "gn:population":0,
    "gn:timezone":"Asia/Karachi",
    "iso:country":"PK",
    "wof:name":"Pind Khurd",
    "wof:placetype":"locality"
},
  "geometry": {"coordinates":[73.77916,33.28408],"type":"Point"}
}