{
  "type": "Feature",
  "properties": {
    "gn:admin1_code":"3",
    "gn:asciiname":"Hari Maira",
    "gn:country_code":"PK",
    "gn:dem":895,
    "gn:feature_class":"P",
    "gn:feature_code":"PPL",
    "gn:name":"Hari Maira",
    "gn:population":0,
    "gn:timezone":"Asia/Karachi",
    "iso:country":"PK",
    "wof:name":"Hari Maira",
    "wof:placetype":"locality"
},
  "geometry": {"coordinates":[73.11632,34.39475],"type":"Point"}
}