{
  "type": "Feature",
  "properties": {
    "gn:admin1_code":"02",
    "gn:asciiname":"Mahram",
    "gn:country_code":"PK",
    "gn:dem":87,
    "gn:feature_class":"P",
    "gn:feature_code":"PPL",
    "gn:name":"Mahram",
    "gn:population":0,
    "gn:timezone":"Asia/Karachi",
    "iso:country":"PK",
    "name:und_x_variant":[
        "Mehram",
        "Mahram"
    ],
    "wof:name":"Mahram",
    "wof:placetype":"locality"
},
  "geometry": {"coordinates":[67.81659000000001,28.85037],"type":"Point"}
}