{
  "type": "Feature",
  "properties": {
    "gn:admin1_code":"02",
    "gn:asciiname":"Mahram",
    "gn:country_code":"PK",
    "gn:dem":87,
    "gn:feature_class":"P",
    "gn:feature_code":"PPL",
    "gn:name":"Mahram",
    "gn:population":0,
    "gn:timezone":"Asia/Karachi",
    "iso:country":"PK",
    "name:ara_x_preferred":[
        "\u0645\u062d\u0631\u0645"
    ],
    "name:bak_x_preferred":[
        "\u041c\u04d9\u0445\u0440\u04d9\u043c"
    ],
    "name:ben_x_preferred":[
        "\u09ae\u09be\u09b9\u09b0\u09be\u09ae"
    ],
    "name:deu_x_preferred":[
        "Mahram"
    ],
    "name:fas_x_preferred":[
        "\u0645\u062d\u0631\u0645"
    ],
    "name:ind_x_preferred":[
        "Mahram"
    ],
    "name:jav_x_preferred":[
        "Muhrim"
    ],
    "name:msa_x_preferred":[
        "Muhrim"
    ],
    "name:rus_x_preferred":[
        "\u041c\u0430\u0445\u0440\u0430\u043c"
    ],
    "name:tam_x_preferred":[
        "\u0bae\u0bb9\u0bcd\u0bb1\u0bae\u0bcd"
    ],
    "name:tur_x_preferred":[
        "Mahrem"
    ],
    "name:und_x_variant":[
        "Mehram",
        "Mahram"
    ],
    "name:urd_x_preferred":[
        "\u0645\u062d\u0631\u0645"
    ],
    "wof:name":"Mahram",
    "wof:placetype":"locality"
},
  "geometry": {"coordinates":[67.81659000000001,28.85037],"type":"Point"}
}