{
  "type": "Feature",
  "properties": {
    "gn:admin1_code":"3.0",
    "gn:asciiname":"Jonkai",
    "gn:country_code":"PK",
    "gn:dem":2097,
    "gn:feature_class":"P",
    "gn:feature_code":"PPL",
    "gn:name":"Jonkai",
    "gn:population":0,
    "gn:timezone":"Asia/Karachi",
    "iso:country":"PK",
    "name:eng_x_preferred":[
        "Jonkai"
    ],
    "wof:name":"Jonkai",
    "wof:placetype":"locality"
},
  "geometry": {"coordinates":[72.17608,35.43777],"type":"Point"}
}