{
  "type": "Feature",
  "properties": {
    "gn:admin1_code":"5",
    "gn:asciiname":"Goth Wassi",
    "gn:country_code":"PK",
    "gn:dem":19,
    "gn:feature_class":"P",
    "gn:feature_code":"PPL",
    "gn:name":"Goth Wassi",
    "gn:population":0,
    "gn:timezone":"Asia/Karachi",
    "iso:country":"PK",
    "name:eng_x_preferred":[
        "Wassi"
    ],
    "wof:name":"Goth Wassi",
    "wof:placetype":"locality"
},
  "geometry": {"coordinates":[68.37203000000001,25.15816],"type":"Point"}
}