{
  "type": "Feature",
  "properties": {
    "gn:admin1_code":"5.0",
    "gn:asciiname":"Khadim Husain Zardari",
    "gn:country_code":"PK",
    "gn:dem":35,
    "gn:feature_class":"P",
    "gn:feature_code":"PPL",
    "gn:name":"Khadim Husain Zardari",
    "gn:population":0,
    "gn:timezone":"Asia/Karachi",
    "iso:country":"PK",
    "wof:name":"Khadim Husain Zardari",
    "wof:placetype":"locality"
},
  "geometry": {"coordinates":[68.41923,26.09159],"type":"Point"}
}