{
  "type": "Feature",
  "properties": {
    "gn:admin1_code":"5",
    "gn:asciiname":"Mubarak Dars jo Tar",
    "gn:country_code":"PK",
    "gn:dem":28,
    "gn:feature_class":"P",
    "gn:feature_code":"PPL",
    "gn:name":"Mubarak Dars jo Tar",
    "gn:population":0,
    "gn:timezone":"Asia/Karachi",
    "iso:country":"PK",
    "wof:name":"Mubarak Dars jo Tar",
    "wof:placetype":"locality"
},
  "geometry": {"coordinates":[69.71127,25.01033],"type":"Point"}
}