{
  "type": "Feature",
  "properties": {
    "gn:admin1_code":"2",
    "gn:asciiname":"Shah Namaz",
    "gn:country_code":"PK",
    "gn:dem":1522,
    "gn:feature_class":"P",
    "gn:feature_code":"PPL",
    "gn:name":"Shah Namaz",
    "gn:population":0,
    "gn:timezone":"Asia/Karachi",
    "iso:country":"PK",
    "name:und_x_variant":[
        "Sh\u0101h Naw\u0101z"
    ],
    "wof:name":"Shah Namaz",
    "wof:placetype":"locality"
},
  "geometry": {"coordinates":[66.4558,29.78279],"type":"Point"}
}