{
  "type": "Feature",
  "properties": {
    "gn:admin1_code":"3.0",
    "gn:asciiname":"Jhatta",
    "gn:country_code":"PK",
    "gn:dem":308,
    "gn:feature_class":"P",
    "gn:feature_code":"PPL",
    "gn:name":"Jhatta",
    "gn:population":0,
    "gn:timezone":"Asia/Karachi",
    "iso:country":"PK",
    "name:und_x_variant":[
        "Jatta"
    ],
    "wof:name":"Jhatta",
    "wof:placetype":"locality"
},
  "geometry": {"coordinates":[70.18695,32.13604],"type":"Point"}
}