{
  "type": "Feature",
  "properties": {
    "gn:admin1_code":"4",
    "gn:asciiname":"Dinga",
    "gn:country_code":"PK",
    "gn:dem":193,
    "gn:feature_class":"P",
    "gn:feature_code":"PPL",
    "gn:name":"Dinga",
    "gn:population":0,
    "gn:timezone":"Asia/Karachi",
    "iso:country":"PK",
    "name:ceb_x_preferred":[
        "Dinga"
    ],
    "name:fas_x_preferred":[
        "\u062f\u06cc\u0646\u06af\u0627"
    ],
    "name:fra_x_preferred":[
        "Dinga"
    ],
    "name:por_x_preferred":[
        "Dinga"
    ],
    "name:spa_x_preferred":[
        "Dinga"
    ],
    "name:und_x_variant":[
        "Danga"
    ],
    "name:urd_x_preferred":[
        "\u0688\u06cc\u0646\u06af\u0627"
    ],
    "wof:name":"Dinga",
    "wof:placetype":"locality"
},
  "geometry": {"coordinates":[72.92103,31.92236],"type":"Point"}
}