{
  "type": "Feature",
  "properties": {
    "gn:admin1_code":"3",
    "gn:asciiname":"Qila Shahid",
    "gn:country_code":"PK",
    "gn:dem":2090,
    "gn:feature_class":"P",
    "gn:feature_code":"PPL",
    "gn:name":"Qila Shahid",
    "gn:population":0,
    "gn:timezone":"Asia/Karachi",
    "iso:country":"PK",
    "name:und_x_variant":[
        "Qal\u0101 Shah\u012bd"
    ],
    "wof:name":"Qila Shahid",
    "wof:placetype":"locality"
},
  "geometry": {"coordinates":[72.73600999999999,34.55751],"type":"Point"}
}