{
  "type": "Feature",
  "properties": {
    "gn:admin1_code":"5",
    "gn:asciiname":"Goth Jumman Bhutto",
    "gn:country_code":"PK",
    "gn:dem":59,
    "gn:feature_class":"P",
    "gn:feature_code":"PPL",
    "gn:name":"Goth Jumman Bhutto",
    "gn:population":0,
    "gn:timezone":"Asia/Karachi",
    "iso:country":"PK",
    "name:und_x_variant":[
        "Goth Jiwan Bhutto"
    ],
    "wof:name":"Goth Jumman Bhutto",
    "wof:placetype":"locality"
},
  "geometry": {"coordinates":[68.26607,27.59577],"type":"Point"}
}