{
  "type": "Feature",
  "properties": {
    "gn:admin1_code":"4.0",
    "gn:asciiname":"Chak Four Hundred Forty-three",
    "gn:country_code":"PK",
    "gn:dem":155,
    "gn:feature_class":"P",
    "gn:feature_code":"PPL",
    "gn:name":"Chak Four Hundred Forty-three",
    "gn:population":0,
    "gn:timezone":"Asia/Karachi",
    "iso:country":"PK",
    "name:und_x_variant":[
        "Kh\u0101ndoha"
    ],
    "wof:name":"Chak Four Hundred Forty-three",
    "wof:placetype":"locality"
},
  "geometry": {"coordinates":[72.47281,31.17339],"type":"Point"}
}