{
  "type": "Feature",
  "properties": {
    "gn:admin1_code":"03",
    "gn:asciiname":"Taila Band",
    "gn:country_code":"PK",
    "gn:dem":393,
    "gn:feature_class":"P",
    "gn:feature_code":"PPL",
    "gn:name":"Taila Band",
    "gn:population":0,
    "gn:timezone":"Asia/Karachi",
    "iso:country":"PK",
    "name:und_x_variant":[
        "Taila Bond",
        "Taila Band"
    ],
    "wof:name":"Taila Band",
    "wof:placetype":"locality"
},
  "geometry": {"coordinates":[71.64614,33.87267],"type":"Point"}
}