{
  "type": "Feature",
  "properties": {
    "gn:admin1_code":"2.0",
    "gn:asciiname":"Kili Dur Muhammad",
    "gn:country_code":"PK",
    "gn:dem":1303,
    "gn:feature_class":"P",
    "gn:feature_code":"PPL",
    "gn:name":"Kili Dur Muhammad",
    "gn:population":0,
    "gn:timezone":"Asia/Karachi",
    "iso:country":"PK",
    "wof:name":"Kili Dur Muhammad",
    "wof:placetype":"locality"
},
  "geometry": {"coordinates":[66.42686999999999,27.44626],"type":"Point"}
}