{
  "type": "Feature",
  "properties": {
    "gn:admin1_code":"04",
    "gn:asciiname":"Kora",
    "gn:country_code":"PK",
    "gn:dem":203,
    "gn:feature_class":"P",
    "gn:feature_code":"PPL",
    "gn:name":"Kora",
    "gn:population":0,
    "gn:timezone":"Asia/Karachi",
    "iso:country":"PK",
    "name:ben_x_preferred":[
        "\u0995\u09cb\u09b0\u09be"
    ],
    "name:bre_x_preferred":[
        "Kora"
    ],
    "name:bul_x_preferred":[
        "\u041a\u043e\u0440\u0430"
    ],
    "name:cat_x_preferred":[
        "Kora"
    ],
    "name:ceb_x_preferred":[
        "Kora"
    ],
    "name:chv_x_preferred":[
        "\u041a\u043e\u0440\u0430"
    ],
    "name:deu_x_preferred":[
        "Kora"
    ],
    "name:fra_x_preferred":[
        "Kora"
    ],
    "name:hrv_x_preferred":[
        "Kora"
    ],
    "name:ita_x_preferred":[
        "Kora"
    ],
    "name:nld_x_preferred":[
        "Kora"
    ],
    "name:pol_x_preferred":[
        "Kora"
    ],
    "name:por_x_preferred":[
        "Kora"
    ],
    "name:rus_x_preferred":[
        "\u041a\u043e\u0440\u0430"
    ],
    "name:spa_x_preferred":[
        "Kora"
    ],
    "name:srp_x_preferred":[
        "\u041a\u043e\u0440\u0430"
    ],
    "name:swe_x_preferred":[
        "Kora"
    ],
    "name:ukr_x_preferred":[
        "\u041a\u043e\u0440\u0430"
    ],
    "wof:name":"Kora",
    "wof:placetype":"locality"
},
  "geometry": {"coordinates":[72.94334000000001,32.59404],"type":"Point"}
}