{
  "type": "Feature",
  "properties": {
    "gn:admin1_code":"3.0",
    "gn:asciiname":"Kot Banda",
    "gn:country_code":"PK",
    "gn:dem":2146,
    "gn:feature_class":"P",
    "gn:feature_code":"PPL",
    "gn:name":"Kot Banda",
    "gn:population":0,
    "gn:timezone":"Asia/Karachi",
    "iso:country":"PK",
    "wof:name":"Kot Banda",
    "wof:placetype":"locality"
},
  "geometry": {"coordinates":[73.04821,34.93573],"type":"Point"}
}