{
  "type": "Feature",
  "properties": {
    "gn:admin1_code":"5",
    "gn:asciiname":"Goth Sumar Khan Kakepoto",
    "gn:country_code":"PK",
    "gn:dem":57,
    "gn:feature_class":"P",
    "gn:feature_code":"PPL",
    "gn:name":"Goth Sumar Khan Kakepoto",
    "gn:population":0,
    "gn:timezone":"Asia/Karachi",
    "iso:country":"PK",
    "name:und_x_variant":[
        "Goth Sum\u0101r Kh\u0101n K\u0101kepato",
        "Maulvi Abdul Majid Sh\u0101h",
        "Goth Sumar Khan Kakepoto"
    ],
    "wof:name":"Goth Sumar Khan Kakepoto",
    "wof:placetype":"locality"
},
  "geometry": {"coordinates":[68.4607,27.93457],"type":"Point"}
}