{
  "type": "Feature",
  "properties": {
    "gn:gn_country":"PK",
    "gn:gn_fcode":"PPLX",
    "gn:gn_pop":0,
    "iso:country":"PK",
    "name:eng_x_preferred":[
        "Dhobi Mandi"
    ],
    "name:unk_x_variant":[
        "Dhobi Mandi"
    ],
    "qs_pg:aaroncc":"PK",
    "qs_pg:gn_country":"PK",
    "qs_pg:gn_fcode":"PPLX",
    "qs_pg:gn_pop":0,
    "qs_pg:name":"Dhobi Mandi",
    "qs_pg:name_adm0":"Pakistan",
    "qs_pg:name_adm1":"Punjab",
    "qs_pg:photos":147,
    "qs_pg:photos_1k":30,
    "qs_pg:photos_9k":1,
    "qs_pg:photos_9r":3,
    "qs_pg:photos_all":147,
    "qs_pg:photos_sr":3,
    "qs_pg:pop_sr":0,
    "qs_pg:qs_pg_placetype":"neighbourhood",
    "qs_pg:qs_pg_placetype_gp":"Suburb",
    "qs_pg:woe_adm0":23424922,
    "woe:adm0_id":23424922,
    "woe:name_adm0":"Pakistan",
    "woe:name_adm1":"Punjab",
    "woe:placetype":"Suburb",
    "wof:name":"Dhobi Mandi",
    "wof:placetype":"neighbourhood"
},
  "geometry": {"coordinates":[74.30167,31.56667],"type":"Point"}
}