{
  "type": "Feature",
  "properties": {
    "gn:admin1_code":"05",
    "gn:asciiname":"Sahta",
    "gn:country_code":"PK",
    "gn:dem":18,
    "gn:feature_class":"P",
    "gn:feature_code":"PPL",
    "gn:name":"Sahta",
    "gn:population":0,
    "gn:timezone":"Asia/Karachi",
    "iso:country":"PK",
    "wof:name":"Sahta",
    "wof:placetype":"locality"
},
  "geometry": {"coordinates":[68.51666999999999,25.21667],"type":"Point"}
}