{
  "type": "Feature",
  "properties": {
    "gn:admin1_code":"4",
    "gn:asciiname":"Umarabad",
    "gn:country_code":"PK",
    "gn:dem":189,
    "gn:feature_class":"P",
    "gn:feature_code":"PPL",
    "gn:name":"Umarabad",
    "gn:population":0,
    "gn:timezone":"Asia/Karachi",
    "iso:country":"PK",
    "name:und_x_variant":[
        "Umr\u0101b\u0101d"
    ],
    "wof:name":"Umarabad",
    "wof:placetype":"locality"
},
  "geometry": {"coordinates":[73.74361,30.94751],"type":"Point"}
}