{
  "type": "Feature",
  "properties": {
    "gn:admin1_code":"2.0",
    "gn:asciiname":"Molvi Abdul Wahid",
    "gn:country_code":"PK",
    "gn:dem":808,
    "gn:feature_class":"P",
    "gn:feature_code":"PPL",
    "gn:name":"Molvi Abdul Wahid",
    "gn:population":0,
    "gn:timezone":"Asia/Karachi",
    "iso:country":"PK",
    "wof:name":"Molvi Abdul Wahid",
    "wof:placetype":"locality"
},
  "geometry": {"coordinates":[66.76824000000001,26.73981],"type":"Point"}
}