{
  "type": "Feature",
  "properties": {
    "gn:admin1_code":"4.0",
    "gn:asciiname":"Chak One Hundred Forty-eight -One Hundred Forty-nine Northern Branch",
    "gn:country_code":"PK",
    "gn:dem":173,
    "gn:feature_class":"P",
    "gn:feature_code":"PPL",
    "gn:name":"Chak One Hundred Forty-eight -One Hundred Forty-nine Northern Branch",
    "gn:population":0,
    "gn:timezone":"Asia/Karachi",
    "iso:country":"PK",
    "name:und_x_variant":[
        "Chak One Hundred Forty-Nine/One Hundred Fifty NB",
        "Chak One Hundred Forty-Nine NB",
        "Chak One Hundred Forty-eight -One Hundred Forty-nine Northern Branch"
    ],
    "wof:name":"Chak One Hundred Forty-eight -One Hundred Forty-nine Northern Branch",
    "wof:placetype":"locality"
},
  "geometry": {"coordinates":[72.43626999999999,31.78396],"type":"Point"}
}