{
  "type": "Feature",
  "properties": {
    "gn:admin1_code":"2.0",
    "gn:asciiname":"Damb",
    "gn:country_code":"PK",
    "gn:dem":1307,
    "gn:feature_class":"P",
    "gn:feature_code":"PPL",
    "gn:name":"Damb",
    "gn:population":0,
    "gn:timezone":"Asia/Karachi",
    "iso:country":"PK",
    "wof:name":"Damb",
    "wof:placetype":"locality"
},
  "geometry": {"coordinates":[66.45846,27.78019],"type":"Point"}
}