{
  "type": "Feature",
  "properties": {
    "gn:admin1_code":"6.0",
    "gn:asciiname":"Goshan",
    "gn:country_code":"PK",
    "gn:dem":835,
    "gn:feature_class":"P",
    "gn:feature_code":"PPL",
    "gn:name":"Goshan",
    "gn:population":0,
    "gn:timezone":"Asia/Karachi",
    "iso:country":"PK",
    "wof:name":"Goshan",
    "wof:placetype":"locality"
},
  "geometry": {"coordinates":[73.73893000000002,33.61888],"type":"Point"}
}