{
  "type": "Feature",
  "properties": {
    "gn:admin1_code":"5.0",
    "gn:asciiname":"Yusuf Kalhoro",
    "gn:country_code":"PK",
    "gn:dem":47,
    "gn:feature_class":"P",
    "gn:feature_code":"PPL",
    "gn:name":"Yusuf Kalhoro",
    "gn:population":0,
    "gn:timezone":"Asia/Karachi",
    "iso:country":"PK",
    "wof:name":"Yusuf Kalhoro",
    "wof:placetype":"locality"
},
  "geometry": {"coordinates":[67.89062,27.45742000000001],"type":"Point"}
}