{
  "type": "Feature",
  "properties": {
    "gn:admin1_code":"2.0",
    "gn:asciiname":"Goth Kalra",
    "gn:country_code":"PK",
    "gn:dem":59,
    "gn:feature_class":"P",
    "gn:feature_code":"PPL",
    "gn:name":"Goth Kalra",
    "gn:population":0,
    "gn:timezone":"Asia/Karachi",
    "iso:country":"PK",
    "name:und_x_variant":[
        "Goth Kairo"
    ],
    "wof:name":"Goth Kalra",
    "wof:placetype":"locality"
},
  "geometry": {"coordinates":[67.57146999999999,28.58133],"type":"Point"}
}