{
  "type": "Feature",
  "properties": {
    "gn:admin1_code":"1.0",
    "gn:asciiname":"Saiyid Akbar Kalle",
    "gn:country_code":"PK",
    "gn:dem":1476,
    "gn:feature_class":"P",
    "gn:feature_code":"PPL",
    "gn:name":"Saiyid Akbar Kalle",
    "gn:population":0,
    "gn:timezone":"Asia/Karachi",
    "iso:country":"PK",
    "name:und_x_variant":[
        "Saiyid Akbar",
        "Saiyid Akbar Kili",
        "Saiyid Akbar Kalle"
    ],
    "wof:name":"Saiyid Akbar Kalle",
    "wof:placetype":"locality"
},
  "geometry": {"coordinates":[70.05459,33.8314],"type":"Point"}
}