{
  "type": "Feature",
  "properties": {
    "gn:admin1_code":"02",
    "gn:asciiname":"Goth Khan Muhammad",
    "gn:country_code":"PK",
    "gn:dem":244,
    "gn:feature_class":"P",
    "gn:feature_code":"PPL",
    "gn:name":"Goth Khan Muhammad",
    "gn:population":0,
    "gn:timezone":"Asia/Karachi",
    "iso:country":"PK",
    "name:und_x_variant":[
        "Goth Rahail",
        "Goth Khan Muhammad"
    ],
    "wof:name":"Goth Khan Muhammad",
    "wof:placetype":"locality"
},
  "geometry": {"coordinates":[67.0381,25.45661],"type":"Point"}
}