{
  "type": "Feature",
  "properties": {
    "gn:admin1_code":"1.0",
    "gn:asciiname":"Sherwane",
    "gn:country_code":"PK",
    "gn:dem":1054,
    "gn:feature_class":"P",
    "gn:feature_code":"PPL",
    "gn:name":"Sherwane",
    "gn:population":0,
    "gn:timezone":"Asia/Karachi",
    "iso:country":"PK",
    "wof:name":"Sherwane",
    "wof:placetype":"locality"
},
  "geometry": {"coordinates":[70.36466999999999,33.41718],"type":"Point"}
}