{
  "type": "Feature",
  "properties": {
    "gn:admin1_code":"02",
    "gn:asciiname":"Sardar Dinar Khan",
    "gn:country_code":"PK",
    "gn:dem":1832,
    "gn:feature_class":"P",
    "gn:feature_code":"PPL",
    "gn:name":"Sardar Dinar Khan",
    "gn:population":0,
    "gn:timezone":"Asia/Karachi",
    "iso:country":"PK",
    "name:und_x_variant":[
        "Mi\u0101n Kh\u0101n Goth",
        "Mi\u0101n Kh\u0101n Got",
        "Sardar Dinar Khan"
    ],
    "wof:name":"Sardar Dinar Khan",
    "wof:placetype":"locality"
},
  "geometry": {"coordinates":[67.09151999999999,29.8974],"type":"Point"}
}