{
  "type": "Feature",
  "properties": {
    "gn:admin1_code":"5.0",
    "gn:asciiname":"Maulvi Mir Muhammad Jatoi",
    "gn:country_code":"PK",
    "gn:dem":8,
    "gn:feature_class":"P",
    "gn:feature_code":"PPL",
    "gn:name":"Maulvi Mir Muhammad Jatoi",
    "gn:population":0,
    "gn:timezone":"Asia/Karachi",
    "iso:country":"PK",
    "wof:name":"Maulvi Mir Muhammad Jatoi",
    "wof:placetype":"locality"
},
  "geometry": {"coordinates":[68.104,24.42453],"type":"Point"}
}