{
  "type": "Feature",
  "properties": {
    "gn:admin1_code":"4.0",
    "gn:asciiname":"Hakimanwala",
    "gn:country_code":"PK",
    "gn:dem":192,
    "gn:feature_class":"P",
    "gn:feature_code":"PPL",
    "gn:name":"Hakimanwala",
    "gn:population":0,
    "gn:timezone":"Asia/Karachi",
    "iso:country":"PK",
    "wof:name":"Hakimanwala",
    "wof:placetype":"locality"
},
  "geometry": {"coordinates":[71.27396999999998,32.07015999999999],"type":"Point"}
}