{
  "type": "Feature",
  "properties": {
    "gn:admin1_code":"3.0",
    "gn:asciiname":"Mulla di Basti",
    "gn:country_code":"PK",
    "gn:dem":3720,
    "gn:feature_class":"P",
    "gn:feature_code":"PPL",
    "gn:name":"Mulla di Basti",
    "gn:population":0,
    "gn:timezone":"Asia/Karachi",
    "iso:country":"PK",
    "wof:name":"Mulla di Basti",
    "wof:placetype":"locality"
},
  "geometry": {"coordinates":[74.04484000000002,35.03273],"type":"Point"}
}