{
  "type": "Feature",
  "properties": {
    "gn:admin1_code":"4",
    "gn:asciiname":"Chanwala",
    "gn:country_code":"PK",
    "gn:dem":120,
    "gn:feature_class":"P",
    "gn:feature_code":"PPL",
    "gn:name":"Chanw\u0101la",
    "gn:population":0,
    "gn:timezone":"Asia/Karachi",
    "iso:country":"PK",
    "wof:name":"Chanwala",
    "wof:placetype":"locality"
},
  "geometry": {"coordinates":[70.72118,30.09338],"type":"Point"}
}