{
  "type": "Feature",
  "properties": {
    "gn:admin1_code":"4.0",
    "gn:asciiname":"Chak Four Hundred Five",
    "gn:country_code":"PK",
    "gn:dem":177,
    "gn:feature_class":"P",
    "gn:feature_code":"PPL",
    "gn:name":"Chak Four Hundred Five",
    "gn:population":0,
    "gn:timezone":"Asia/Karachi",
    "iso:country":"PK",
    "name:und_x_variant":[
        "Kami\u0101na"
    ],
    "wof:name":"Chak Four Hundred Five",
    "wof:placetype":"locality"
},
  "geometry": {"coordinates":[73.10301,30.97318],"type":"Point"}
}