{
  "type": "Feature",
  "properties": {
    "gn:admin1_code":"5",
    "gn:asciiname":"Goth Massu Sahar",
    "gn:country_code":"PK",
    "gn:dem":49,
    "gn:feature_class":"P",
    "gn:feature_code":"PPL",
    "gn:name":"Goth Massu Sahar",
    "gn:population":0,
    "gn:timezone":"Asia/Karachi",
    "iso:country":"PK",
    "name:und_x_variant":[
        "Goth S\u0101rh"
    ],
    "wof:name":"Goth Massu Sahar",
    "wof:placetype":"locality"
},
  "geometry": {"coordinates":[67.96451,27.13259],"type":"Point"}
}