{
  "type": "Feature",
  "properties": {
    "gn:admin1_code":"4",
    "gn:asciiname":"Bhonkiwala",
    "gn:country_code":"PK",
    "gn:dem":176,
    "gn:feature_class":"P",
    "gn:feature_code":"PPL",
    "gn:name":"Bhonkiwala",
    "gn:population":0,
    "gn:timezone":"Asia/Karachi",
    "iso:country":"PK",
    "name:und_x_variant":[
        "Pank\u012bw\u0101la"
    ],
    "wof:name":"Bhonkiwala",
    "wof:placetype":"locality"
},
  "geometry": {"coordinates":[71.12924,31.72364],"type":"Point"}
}