{
  "type": "Feature",
  "properties": {
    "gn:admin1_code":"4",
    "gn:asciiname":"Chak Bhukhewala",
    "gn:country_code":"PK",
    "gn:dem":121,
    "gn:feature_class":"P",
    "gn:feature_code":"PPL",
    "gn:name":"Chak Bhukhewala",
    "gn:population":0,
    "gn:timezone":"Asia/Karachi",
    "iso:country":"PK",
    "name:und_x_variant":[
        "Bakhkhew\u0101la"
    ],
    "wof:name":"Chak Bhukhewala",
    "wof:placetype":"locality"
},
  "geometry": {"coordinates":[71.05492,30.08689],"type":"Point"}
}