{
  "type": "Feature",
  "properties": {
    "gn:admin1_code":"3.0",
    "gn:asciiname":"Alizai",
    "gn:country_code":"PK",
    "gn:dem":371,
    "gn:feature_class":"P",
    "gn:feature_code":"PPL",
    "gn:name":"Alizai",
    "gn:population":0,
    "gn:timezone":"Asia/Karachi",
    "iso:country":"PK",
    "name:ceb_x_preferred":[
        "Alizai"
    ],
    "name:eng_x_preferred":[
        "Al\u012bzai"
    ],
    "name:und_x_variant":[
        "Al\u2018\u012bzai"
    ],
    "name:urd_x_preferred":[
        "\u0639\u0644\u06cc \u0632\u0626\u06cc"
    ],
    "wof:name":"Alizai",
    "wof:placetype":"locality"
},
  "geometry": {"coordinates":[71.54971999999999,33.94454],"type":"Point"}
}