{
  "type": "Feature",
  "properties": {
    "gn:admin1_code":"4.0",
    "gn:asciiname":"Gulial",
    "gn:country_code":"PK",
    "gn:dem":481,
    "gn:feature_class":"P",
    "gn:feature_code":"PPL",
    "gn:name":"Gulial",
    "gn:population":0,
    "gn:timezone":"Asia/Karachi",
    "iso:country":"PK",
    "wof:name":"Gulial",
    "wof:placetype":"locality"
},
  "geometry": {"coordinates":[72.52225,33.508],"type":"Point"}
}