{
  "type": "Feature",
  "properties": {
    "gn:admin1_code":"2",
    "gn:asciiname":"Mat Khetran",
    "gn:country_code":"PK",
    "gn:dem":943,
    "gn:elevation":"940.0",
    "gn:feature_class":"P",
    "gn:feature_code":"PPL",
    "gn:name":"Mat Khetran",
    "gn:population":0,
    "gn:timezone":"Asia/Karachi",
    "iso:country":"PK",
    "name:und_x_variant":[
        "Az\u012bm Khetr\u0101n"
    ],
    "wof:name":"Mat Khetran",
    "wof:placetype":"locality"
},
  "geometry": {"coordinates":[69.63478000000001,29.73491],"type":"Point"}
}