{
  "type": "Feature",
  "properties": {
    "gn:admin1_code":"03",
    "gn:asciiname":"Sadra Sharif",
    "gn:country_code":"PK",
    "gn:dem":208,
    "gn:feature_class":"P",
    "gn:feature_code":"PPL",
    "gn:name":"Sadra Sharif",
    "gn:population":0,
    "gn:timezone":"Asia/Karachi",
    "iso:country":"PK",
    "name:und_x_variant":[
        "Sadra",
        "Sadra Sharif"
    ],
    "wof:name":"Sadra Sharif",
    "wof:placetype":"locality"
},
  "geometry": {"coordinates":[70.71218,32.08452],"type":"Point"}
}