{
  "type": "Feature",
  "properties": {
    "gn:admin1_code":"4.0",
    "gn:asciiname":"Chak Four Hundred Ninety-Four Thal Development Authority",
    "gn:country_code":"PK",
    "gn:dem":136,
    "gn:feature_class":"P",
    "gn:feature_code":"PPL",
    "gn:name":"Chak Four Hundred Ninety-Four Thal Development Authority",
    "gn:population":0,
    "gn:timezone":"Asia/Karachi",
    "iso:country":"PK",
    "name:und_x_variant":[
        "Chak Four Hundred Ninety-Four TDA",
        "Chak 494 TDA"
    ],
    "wof:name":"Chak Four Hundred Ninety-Four Thal Development Authority",
    "wof:placetype":"locality"
},
  "geometry": {"coordinates":[71.42568,30.71895],"type":"Point"}
}