{
  "type": "Feature",
  "properties": {
    "gn:admin1_code":"2.0",
    "gn:asciiname":"Sheikhabad",
    "gn:country_code":"PK",
    "gn:dem":1779,
    "gn:feature_class":"P",
    "gn:feature_code":"PPL",
    "gn:name":"Sheikhabad",
    "gn:population":0,
    "gn:timezone":"Asia/Karachi",
    "iso:country":"PK",
    "name:und_x_variant":[
        "Gagra",
        "Sheikh \u0100b\u0101d"
    ],
    "wof:name":"Sheikhabad",
    "wof:placetype":"locality"
},
  "geometry": {"coordinates":[69.55365,31.16552],"type":"Point"}
}