{
  "type": "Feature",
  "properties": {
    "gn:admin1_code":"2.0",
    "gn:asciiname":"Chachobi",
    "gn:country_code":"PK",
    "gn:dem":1311,
    "gn:feature_class":"P",
    "gn:feature_code":"PPL",
    "gn:name":"Chachobi",
    "gn:population":0,
    "gn:timezone":"Asia/Karachi",
    "iso:country":"PK",
    "name:und_x_variant":[
        "\u012asatobai",
        "Tsatobai",
        "Tsatsobai",
        "Chachobi"
    ],
    "wof:name":"Chachobi",
    "wof:placetype":"locality"
},
  "geometry": {"coordinates":[69.73559,31.74304],"type":"Point"}
}