{
  "type": "Feature",
  "properties": {
    "gn:admin1_code":"03",
    "gn:asciiname":"Nawagai",
    "gn:country_code":"PK",
    "gn:dem":992,
    "gn:feature_class":"P",
    "gn:feature_code":"PPL",
    "gn:name":"Nawagai",
    "gn:population":0,
    "gn:timezone":"Asia/Karachi",
    "iso:country":"PK",
    "name:eng_x_preferred":[
        "Naw\u0101gai"
    ],
    "wof:name":"Nawagai",
    "wof:placetype":"locality"
},
  "geometry": {"coordinates":[71.96729000000001,34.86496],"type":"Point"}
}