{
  "type": "Feature",
  "properties": {
    "gn:admin1_code":"5",
    "gn:asciiname":"Fazal Muhammad Talpur",
    "gn:country_code":"PK",
    "gn:dem":21,
    "gn:feature_class":"P",
    "gn:feature_code":"PPL",
    "gn:name":"Fazal Muhammad Talpur",
    "gn:population":0,
    "gn:timezone":"Asia/Karachi",
    "iso:country":"PK",
    "wof:name":"Fazal Muhammad Talpur",
    "wof:placetype":"locality"
},
  "geometry": {"coordinates":[68.66464999999999,25.49234],"type":"Point"}
}