{
  "type": "Feature",
  "properties": {
    "gn:admin1_code":"3.0",
    "gn:asciiname":"Pisho Ghot",
    "gn:country_code":"PK",
    "gn:dem":801,
    "gn:feature_class":"P",
    "gn:feature_code":"PPL",
    "gn:name":"Pisho Ghot",
    "gn:population":0,
    "gn:timezone":"Asia/Karachi",
    "iso:country":"PK",
    "wof:name":"Pisho Ghot",
    "wof:placetype":"locality"
},
  "geometry": {"coordinates":[72.48066,34.54328],"type":"Point"}
}