{
  "type": "Feature",
  "properties": {
    "gn:admin1_code":"4.0",
    "gn:asciiname":"Lohavi",
    "gn:country_code":"PK",
    "gn:dem":79,
    "gn:feature_class":"P",
    "gn:feature_code":"PPL",
    "gn:name":"Lohavi",
    "gn:population":0,
    "gn:timezone":"Asia/Karachi",
    "iso:country":"PK",
    "wof:name":"Lohavi",
    "wof:placetype":"locality"
},
  "geometry": {"coordinates":[70.00520999999999,28.42855],"type":"Point"}
}