{
  "type": "Feature",
  "properties": {
    "gn:admin1_code":"4",
    "gn:asciiname":"Chak Fifty-six -Twelve Left",
    "gn:country_code":"PK",
    "gn:dem":149,
    "gn:feature_class":"P",
    "gn:feature_code":"PPL",
    "gn:name":"Chak Fifty-six -Twelve Left",
    "gn:population":0,
    "gn:timezone":"Asia/Karachi",
    "iso:country":"PK",
    "name:und_x_variant":[
        "Chak Fifty-six Twelve L"
    ],
    "wof:name":"Chak Fifty-six -Twelve Left",
    "wof:placetype":"locality"
},
  "geometry": {"coordinates":[72.63004000000002,30.32112],"type":"Point"}
}