{
  "type": "Feature",
  "properties": {
    "gn:admin1_code":"4.0",
    "gn:asciiname":"Ulmanwala",
    "gn:country_code":"PK",
    "gn:dem":637,
    "gn:feature_class":"P",
    "gn:feature_code":"PPL",
    "gn:name":"Ulmanwala",
    "gn:population":0,
    "gn:timezone":"Asia/Karachi",
    "iso:country":"PK",
    "wof:name":"Ulmanwala",
    "wof:placetype":"locality"
},
  "geometry": {"coordinates":[71.66549999999999,32.80102],"type":"Point"}
}