{
  "type": "Feature",
  "properties": {
    "gn:admin1_code":"7.0",
    "gn:asciiname":"Sher Ahmad Das Baikh",
    "gn:country_code":"PK",
    "gn:dem":3774,
    "gn:feature_class":"P",
    "gn:feature_code":"PPL",
    "gn:name":"Sher Ahmad Das Baikh",
    "gn:population":0,
    "gn:timezone":"Asia/Karachi",
    "iso:country":"PK",
    "wof:name":"Sher Ahmad Das Baikh",
    "wof:placetype":"locality"
},
  "geometry": {"coordinates":[74.6412,35.09293],"type":"Point"}
}