{
  "type": "Feature",
  "properties": {
    "gn:admin1_code":"2.0",
    "gn:asciiname":"Kallepari",
    "gn:country_code":"PK",
    "gn:dem":654,
    "gn:feature_class":"P",
    "gn:feature_code":"PPL",
    "gn:name":"Kallepari",
    "gn:population":0,
    "gn:timezone":"Asia/Karachi",
    "iso:country":"PK",
    "wof:name":"Kallepari",
    "wof:placetype":"locality"
},
  "geometry": {"coordinates":[65.72414000000001,26.83279000000001],"type":"Point"}
}