{
  "type": "Feature",
  "properties": {
    "gn:admin1_code":"3.0",
    "gn:asciiname":"Barontha",
    "gn:country_code":"PK",
    "gn:dem":2199,
    "gn:feature_class":"P",
    "gn:feature_code":"PPL",
    "gn:name":"Barontha",
    "gn:population":0,
    "gn:timezone":"Asia/Karachi",
    "iso:country":"PK",
    "wof:name":"Barontha",
    "wof:placetype":"locality"
},
  "geometry": {"coordinates":[73.63701,34.73968],"type":"Point"}
}