{
  "type": "Feature",
  "properties": {
    "gn:admin1_code":"5",
    "gn:asciiname":"Punnun Kishkori",
    "gn:country_code":"PK",
    "gn:dem":8,
    "gn:feature_class":"P",
    "gn:feature_code":"PPL",
    "gn:name":"Punnun Kishkori",
    "gn:population":0,
    "gn:timezone":"Asia/Karachi",
    "iso:country":"PK",
    "wof:name":"Punnun Kishkori",
    "wof:placetype":"locality"
},
  "geometry": {"coordinates":[69.39721999999999,24.97222],"type":"Point"}
}