{
  "type": "Feature",
  "properties": {
    "gn:admin1_code":"4.0",
    "gn:asciiname":"Ghatti Kalanjar",
    "gn:country_code":"PK",
    "gn:dem":200,
    "gn:feature_class":"P",
    "gn:feature_code":"PPL",
    "gn:name":"Ghatti Kalanjar",
    "gn:population":0,
    "gn:timezone":"Asia/Karachi",
    "iso:country":"PK",
    "wof:name":"Ghatti Kalanjar",
    "wof:placetype":"locality"
},
  "geometry": {"coordinates":[74.60154,31.06434],"type":"Point"}
}