{
  "type": "Feature",
  "properties": {
    "gn:admin1_code":"4.0",
    "gn:asciiname":"Goi",
    "gn:country_code":"PK",
    "gn:dem":1265,
    "gn:feature_class":"P",
    "gn:feature_code":"PPL",
    "gn:name":"Goi",
    "gn:population":0,
    "gn:timezone":"Asia/Karachi",
    "iso:country":"PK",
    "name:eng_x_preferred":[
        "Ghoi"
    ],
    "wof:name":"Goi",
    "wof:placetype":"locality"
},
  "geometry": {"coordinates":[73.48364000000002,33.92387],"type":"Point"}
}