{
  "type": "Feature",
  "properties": {
    "gn:admin1_code":"3.0",
    "gn:asciiname":"Isak Chuntra",
    "gn:country_code":"PK",
    "gn:dem":794,
    "gn:feature_class":"P",
    "gn:feature_code":"PPL",
    "gn:name":"Isak Chuntra",
    "gn:population":0,
    "gn:timezone":"Asia/Karachi",
    "iso:country":"PK",
    "name:und_x_variant":[
        "Isak Chauntra",
        "Is\u0101k",
        "Isak Chuntra"
    ],
    "wof:name":"Isak Chuntra",
    "wof:placetype":"locality"
},
  "geometry": {"coordinates":[71.2325,33.13511],"type":"Point"}
}