{
  "type": "Feature",
  "properties": {
    "gn:admin1_code":"3",
    "gn:asciiname":"Kundi da Maidan",
    "gn:country_code":"PK",
    "gn:dem":3503,
    "gn:feature_class":"P",
    "gn:feature_code":"PPL",
    "gn:name":"Kundi da Maidan",
    "gn:population":0,
    "gn:timezone":"Asia/Karachi",
    "iso:country":"PK",
    "name:und_x_variant":[
        "Kundi ka Maid\u0101n"
    ],
    "wof:name":"Kundi da Maidan",
    "wof:placetype":"locality"
},
  "geometry": {"coordinates":[73.50657,34.84608],"type":"Point"}
}