{
  "type": "Feature",
  "properties": {
    "gn:admin1_code":"4",
    "gn:asciiname":"Chak Forty- Ten Right",
    "gn:country_code":"PK",
    "gn:dem":140,
    "gn:feature_class":"P",
    "gn:feature_code":"PPL",
    "gn:name":"Chak Forty- Ten Right",
    "gn:population":0,
    "gn:timezone":"Asia/Karachi",
    "iso:country":"PK",
    "name:und_x_variant":[
        "Chak Forty-Ten R",
        "Maul\u0101b\u0101d",
        "Chak Forty- Ten Right"
    ],
    "wof:name":"Chak Forty- Ten Right",
    "wof:placetype":"locality"
},
  "geometry": {"coordinates":[72.06475999999998,30.29362],"type":"Point"}
}