{
  "type": "Feature",
  "properties": {
    "gn:admin1_code":"3.0",
    "gn:asciiname":"Pasum",
    "gn:country_code":"PK",
    "gn:dem":2456,
    "gn:feature_class":"P",
    "gn:feature_code":"PPL",
    "gn:name":"Pasum",
    "gn:population":0,
    "gn:timezone":"Asia/Karachi",
    "iso:country":"PK",
    "wof:name":"Pasum",
    "wof:placetype":"locality"
},
  "geometry": {"coordinates":[72.55493,36.30426],"type":"Point"}
}