{
  "type": "Feature",
  "properties": {
    "gn:admin1_code":"2.0",
    "gn:asciiname":"Kili Haji Rehmin",
    "gn:country_code":"PK",
    "gn:dem":1257,
    "gn:feature_class":"P",
    "gn:feature_code":"PPL",
    "gn:name":"Kili Haji Rehmin",
    "gn:population":0,
    "gn:timezone":"Asia/Karachi",
    "iso:country":"PK",
    "wof:name":"Kili Haji Rehmin",
    "wof:placetype":"locality"
},
  "geometry": {"coordinates":[65.93763,29.03562],"type":"Point"}
}