{
  "type": "Feature",
  "properties": {
    "gn:admin1_code":"4",
    "gn:asciiname":"Dhumbrewala",
    "gn:country_code":"PK",
    "gn:dem":113,
    "gn:feature_class":"P",
    "gn:feature_code":"PPL",
    "gn:name":"Dhumbrewala",
    "gn:population":0,
    "gn:timezone":"Asia/Karachi",
    "iso:country":"PK",
    "name:und_x_variant":[
        "Dumrew\u0101la"
    ],
    "wof:name":"Dhumbrewala",
    "wof:placetype":"locality"
},
  "geometry": {"coordinates":[70.62344,29.85063],"type":"Point"}
}