{
  "type": "Feature",
  "properties": {
    "gn:admin1_code":"4",
    "gn:asciiname":"Mehrewala",
    "gn:country_code":"PK",
    "gn:dem":140,
    "gn:feature_class":"P",
    "gn:feature_code":"PPL",
    "gn:name":"Mehrewala",
    "gn:population":0,
    "gn:timezone":"Asia/Karachi",
    "iso:country":"PK",
    "name:und_x_variant":[
        "M\u0101r\u016bw\u0101la"
    ],
    "wof:name":"Mehrewala",
    "wof:placetype":"locality"
},
  "geometry": {"coordinates":[71.13172,30.64338],"type":"Point"}
}