{
  "type": "Feature",
  "properties": {
    "gn:admin1_code":"4.0",
    "gn:asciiname":"Azankhani Ban",
    "gn:country_code":"PK",
    "gn:dem":653,
    "gn:feature_class":"P",
    "gn:feature_code":"PPL",
    "gn:name":"Azankhani Ban",
    "gn:population":0,
    "gn:timezone":"Asia/Karachi",
    "iso:country":"PK",
    "name:eng_x_preferred":[
        "Azan kh\u0101ni Ban"
    ],
    "wof:name":"Azankhani Ban",
    "wof:placetype":"locality"
},
  "geometry": {"coordinates":[70.33759000000001,30.47469],"type":"Point"}
}