{
  "type": "Feature",
  "properties": {
    "gn:admin1_code":"4.0",
    "gn:asciiname":"Khui",
    "gn:country_code":"PK",
    "gn:dem":142,
    "gn:feature_class":"P",
    "gn:feature_code":"PPL",
    "gn:name":"Khui",
    "gn:population":0,
    "gn:timezone":"Asia/Karachi",
    "iso:country":"PK",
    "name:cat_x_preferred":[
        "Khui"
    ],
    "name:deu_x_preferred":[
        "Chui"
    ],
    "name:fra_x_preferred":[
        "Khoui"
    ],
    "name:hun_x_preferred":[
        "Hui"
    ],
    "name:ita_x_preferred":[
        "Khui"
    ],
    "name:jpn_x_preferred":[
        "\u30af\u30a4"
    ],
    "name:kat_x_preferred":[
        "\u10ee\u10e3\u10d8"
    ],
    "name:spa_x_preferred":[
        "Jui"
    ],
    "name:swe_x_preferred":[
        "Khui"
    ],
    "name:und_x_variant":[
        "Kh\u016bi"
    ],
    "name:vie_x_preferred":[
        "Khui"
    ],
    "wof:name":"Khui",
    "wof:placetype":"locality"
},
  "geometry": {"coordinates":[72.14627,30.85308],"type":"Point"}
}