{
  "type": "Feature",
  "properties": {
    "gn:admin1_code":"04",
    "gn:asciiname":"Walla",
    "gn:country_code":"PK",
    "gn:dem":175,
    "gn:feature_class":"P",
    "gn:feature_code":"PPL",
    "gn:name":"Walla",
    "gn:population":0,
    "gn:timezone":"Asia/Karachi",
    "iso:country":"PK",
    "wof:name":"Walla",
    "wof:placetype":"locality"
},
  "geometry": {"coordinates":[72.72369999999999,31.77211],"type":"Point"}
}