{
  "type": "Feature",
  "properties": {
    "gn:admin1_code":"5",
    "gn:asciiname":"Fazel Muhammad Hajan",
    "gn:country_code":"PK",
    "gn:dem":68,
    "gn:feature_class":"P",
    "gn:feature_code":"PPL",
    "gn:name":"Fazel Muhammad Hajan",
    "gn:population":0,
    "gn:timezone":"Asia/Karachi",
    "iso:country":"PK",
    "name:und_x_variant":[
        "Goth Fazal Muhammad Hay\u0101t"
    ],
    "wof:name":"Fazel Muhammad Hajan",
    "wof:placetype":"locality"
},
  "geometry": {"coordinates":[69.03049,28.36271],"type":"Point"}
}