{
  "type": "Feature",
  "properties": {
    "gn:admin1_code":"4",
    "gn:asciiname":"Basti Palah Kosh",
    "gn:country_code":"PK",
    "gn:dem":77,
    "gn:feature_class":"P",
    "gn:feature_code":"PPL",
    "gn:name":"Basti Palah Kosh",
    "gn:population":0,
    "gn:timezone":"Asia/Karachi",
    "iso:country":"PK",
    "name:und_x_variant":[
        "Palah Kosh"
    ],
    "wof:name":"Basti Palah Kosh",
    "wof:placetype":"locality"
},
  "geometry": {"coordinates":[69.91351999999999,28.35841],"type":"Point"}
}