{
  "type": "Feature",
  "properties": {
    "gn:admin1_code":"3.0",
    "gn:asciiname":"Kawa",
    "gn:country_code":"PK",
    "gn:dem":281,
    "gn:feature_class":"P",
    "gn:feature_code":"PPL",
    "gn:name":"Kawa",
    "gn:population":0,
    "gn:timezone":"Asia/Karachi",
    "iso:country":"PK",
    "name:ceb_x_preferred":[
        "Kawa"
    ],
    "name:deu_x_preferred":[
        "Kawa"
    ],
    "name:fra_x_preferred":[
        "Kawa"
    ],
    "name:kur_x_preferred":[
        "Kawa"
    ],
    "name:pol_x_preferred":[
        "Kawa"
    ],
    "name:swe_x_preferred":[
        "Kawa"
    ],
    "wof:name":"Kawa",
    "wof:placetype":"locality"
},
  "geometry": {"coordinates":[72.20515999999998,33.76721],"type":"Point"}
}