{
  "type": "Feature",
  "properties": {
    "gn:admin1_code":"4.0",
    "gn:asciiname":"Dera Mauladad Tiwana",
    "gn:country_code":"PK",
    "gn:dem":187,
    "gn:feature_class":"P",
    "gn:feature_code":"PPL",
    "gn:name":"Dera Mauladad Tiwana",
    "gn:population":0,
    "gn:timezone":"Asia/Karachi",
    "iso:country":"PK",
    "wof:name":"Dera Mauladad Tiwana",
    "wof:placetype":"locality"
},
  "geometry": {"coordinates":[72.23831,32.19055],"type":"Point"}
}