{
  "type": "Feature",
  "properties": {
    "gn:admin1_code":"4",
    "gn:asciiname":"Basti Bokhariwali",
    "gn:country_code":"PK",
    "gn:dem":150,
    "gn:feature_class":"P",
    "gn:feature_code":"PPL",
    "gn:name":"Basti Bokhariwali",
    "gn:population":0,
    "gn:timezone":"Asia/Karachi",
    "iso:country":"PK",
    "name:und_x_variant":[
        "Bhokr\u012bw\u0101la",
        "Basti Bokharw\u0101la",
        "Basti Bokhariwali"
    ],
    "wof:name":"Basti Bokhariwali",
    "wof:placetype":"locality"
},
  "geometry": {"coordinates":[70.99009000000002,31.05239000000001],"type":"Point"}
}