{
  "type": "Feature",
  "properties": {
    "gn:admin1_code":"3.0",
    "gn:asciiname":"Kanpur",
    "gn:country_code":"PK",
    "gn:dem":339,
    "gn:feature_class":"P",
    "gn:feature_code":"PPL",
    "gn:name":"Kanpur",
    "gn:population":0,
    "gn:timezone":"Asia/Karachi",
    "iso:country":"PK",
    "name:eng_x_preferred":[
        "Kanyor"
    ],
    "name:und_x_variant":[
        "Kanr\u0101war",
        "Kanyar",
        "Kanpur"
    ],
    "wof:name":"Kanpur",
    "wof:placetype":"locality"
},
  "geometry": {"coordinates":[71.67896,34.28344],"type":"Point"}
}