{
  "type": "Feature",
  "properties": {
    "gn:admin1_code":"5",
    "gn:asciiname":"Goth Wali Dino Thebo",
    "gn:country_code":"PK",
    "gn:dem":22,
    "gn:feature_class":"P",
    "gn:feature_code":"PPL",
    "gn:name":"Goth Wali Dino Thebo",
    "gn:population":0,
    "gn:timezone":"Asia/Karachi",
    "iso:country":"PK",
    "name:und_x_variant":[
        "Goth Waled\u012bno Thebo"
    ],
    "wof:name":"Goth Wali Dino Thebo",
    "wof:placetype":"locality"
},
  "geometry": {"coordinates":[68.76994999999999,25.61419],"type":"Point"}
}