{
  "type": "Feature",
  "properties": {
    "gn:admin1_code":"5",
    "gn:asciiname":"Goth Jurio Babbar",
    "gn:country_code":"PK",
    "gn:dem":54,
    "gn:feature_class":"P",
    "gn:feature_code":"PPL",
    "gn:name":"Goth Jurio Babbar",
    "gn:population":0,
    "gn:timezone":"Asia/Karachi",
    "iso:country":"PK",
    "name:und_x_variant":[
        "Goth Jario Babbar"
    ],
    "wof:name":"Goth Jurio Babbar",
    "wof:placetype":"locality"
},
  "geometry": {"coordinates":[67.51955,26.86414000000001],"type":"Point"}
}