{
  "type": "Feature",
  "properties": {
    "gn:admin1_code":"2.0",
    "gn:asciiname":"Karkana",
    "gn:country_code":"PK",
    "gn:dem":763,
    "gn:feature_class":"P",
    "gn:feature_code":"PPL",
    "gn:name":"Karkana",
    "gn:population":0,
    "gn:timezone":"Asia/Karachi",
    "iso:country":"PK",
    "wof:name":"Karkana",
    "wof:placetype":"locality"
},
  "geometry": {"coordinates":[70.24021999999999,30.8357],"type":"Point"}
}