{
  "type": "Feature",
  "properties": {
    "gn:admin1_code":"2.0",
    "gn:asciiname":"Girvi Gudi",
    "gn:country_code":"PK",
    "gn:dem":2085,
    "gn:feature_class":"P",
    "gn:feature_code":"PPL",
    "gn:name":"Girvi Gudi",
    "gn:population":0,
    "gn:timezone":"Asia/Karachi",
    "iso:country":"PK",
    "wof:name":"Girvi Gudi",
    "wof:placetype":"locality"
},
  "geometry": {"coordinates":[68.12116,30.35872],"type":"Point"}
}