{
  "type": "Feature",
  "properties": {
    "gn:admin1_code":"4.0",
    "gn:asciiname":"Chhaprian",
    "gn:country_code":"PK",
    "gn:dem":1316,
    "gn:feature_class":"P",
    "gn:feature_code":"PPL",
    "gn:name":"Chhaprian",
    "gn:population":0,
    "gn:timezone":"Asia/Karachi",
    "iso:country":"PK",
    "name:eng_x_preferred":[
        "Chhaprian"
    ],
    "wof:name":"Chhaprian",
    "wof:placetype":"locality"
},
  "geometry": {"coordinates":[73.41866999999998,33.79790999999999],"type":"Point"}
}