{
  "type": "Feature",
  "properties": {
    "gn:admin1_code":"4",
    "gn:asciiname":"Chak Forty-seven Southern Branch",
    "gn:country_code":"PK",
    "gn:dem":184,
    "gn:feature_class":"P",
    "gn:feature_code":"PPL",
    "gn:name":"Chak Forty-seven Southern Branch",
    "gn:population":0,
    "gn:timezone":"Asia/Karachi",
    "iso:country":"PK",
    "name:und_x_variant":[
        "Ahale Malik Akram"
    ],
    "wof:name":"Chak Forty-seven Southern Branch",
    "wof:placetype":"locality"
},
  "geometry": {"coordinates":[72.74966999999999,31.86272],"type":"Point"}
}