{
  "type": "Feature",
  "properties": {
    "gn:admin1_code":"5",
    "gn:asciiname":"Tangio",
    "gn:country_code":"PK",
    "gn:dem":41,
    "gn:feature_class":"P",
    "gn:feature_code":"PPL",
    "gn:name":"Tangio",
    "gn:population":0,
    "gn:timezone":"Asia/Karachi",
    "iso:country":"PK",
    "name:und_x_variant":[
        "Fugchoro Faqir",
        "Tangio"
    ],
    "wof:name":"Tangio",
    "wof:placetype":"locality"
},
  "geometry": {"coordinates":[68.91389000000001,26.71389000000001],"type":"Point"}
}