{
  "type": "Feature",
  "properties": {
    "gn:admin1_code":"4",
    "gn:asciiname":"Basti Hajiwala",
    "gn:country_code":"PK",
    "gn:dem":152,
    "gn:feature_class":"P",
    "gn:feature_code":"PPL",
    "gn:name":"Basti Hajiwala",
    "gn:population":0,
    "gn:timezone":"Asia/Karachi",
    "iso:country":"PK",
    "name:und_x_variant":[
        "Basti H\u0101ji",
        "Basti H\u0101jiw\u0101li",
        "Basti Hajiwala"
    ],
    "wof:name":"Basti Hajiwala",
    "wof:placetype":"locality"
},
  "geometry": {"coordinates":[70.88202,31.15628],"type":"Point"}
}