{
  "type": "Feature",
  "properties": {
    "gn:admin1_code":"4.0",
    "gn:asciiname":"Awan Kalan",
    "gn:country_code":"PK",
    "gn:dem":177,
    "gn:feature_class":"P",
    "gn:feature_code":"PPL",
    "gn:name":"Awan Kalan",
    "gn:population":0,
    "gn:timezone":"Asia/Karachi",
    "iso:country":"PK",
    "name:fas_x_preferred":[
        "\u0627\u0648\u0627\u0646 \u06a9\u0644\u0627\u0646"
    ],
    "wof:name":"Awan Kalan",
    "wof:placetype":"locality"
},
  "geometry": {"coordinates":[73.77794,30.72997],"type":"Point"}
}