{
  "type": "Feature",
  "properties": {
    "gn:admin1_code":"5.0",
    "gn:asciiname":"Goth Behtur",
    "gn:country_code":"PK",
    "gn:dem":64,
    "gn:feature_class":"P",
    "gn:feature_code":"PPL",
    "gn:name":"Goth Behtur",
    "gn:population":0,
    "gn:timezone":"Asia/Karachi",
    "iso:country":"PK",
    "name:und_x_variant":[
        "Goth Beth\u016br"
    ],
    "wof:name":"Goth Behtur",
    "wof:placetype":"locality"
},
  "geometry": {"coordinates":[69.29134999999999,27.76799],"type":"Point"}
}