{
  "type": "Feature",
  "properties": {
    "gn:admin1_code":"5.0",
    "gn:asciiname":"Kusturi Bhil ji Dhani",
    "gn:country_code":"PK",
    "gn:dem":126,
    "gn:feature_class":"P",
    "gn:feature_code":"PPL",
    "gn:name":"Kusturi Bhil ji Dhani",
    "gn:population":0,
    "gn:timezone":"Asia/Karachi",
    "iso:country":"PK",
    "wof:name":"Kusturi Bhil ji Dhani",
    "wof:placetype":"locality"
},
  "geometry": {"coordinates":[70.55807,25.255],"type":"Point"}
}