{
  "type": "Feature",
  "properties": {
    "gn:admin1_code":"2.0",
    "gn:asciiname":"Mandar Khan Jat",
    "gn:country_code":"PK",
    "gn:dem":77,
    "gn:feature_class":"P",
    "gn:feature_code":"PPL",
    "gn:name":"Mandar Khan Jat",
    "gn:population":0,
    "gn:timezone":"Asia/Karachi",
    "iso:country":"PK",
    "name:und_x_variant":[
        "All\u0101h Rakhio"
    ],
    "wof:name":"Mandar Khan Jat",
    "wof:placetype":"locality"
},
  "geometry": {"coordinates":[67.47428000000001,28.17054000000001],"type":"Point"}
}