{
  "type": "Feature",
  "properties": {
    "gn:admin1_code":"6",
    "gn:asciiname":"Pagdam",
    "gn:country_code":"PK",
    "gn:dem":1456,
    "gn:feature_class":"P",
    "gn:feature_code":"PPL",
    "gn:name":"Pagdam",
    "gn:population":0,
    "gn:timezone":"Asia/Karachi",
    "iso:country":"PK",
    "name:und_x_variant":[
        "Pakdam"
    ],
    "wof:name":"Pagdam",
    "wof:placetype":"locality"
},
  "geometry": {"coordinates":[73.48286999999998,34.46552],"type":"Point"}
}