{
  "type": "Feature",
  "properties": {
    "gn:admin1_code":"4",
    "gn:asciiname":"Chak Two",
    "gn:country_code":"PK",
    "gn:dem":200,
    "gn:feature_class":"P",
    "gn:feature_code":"PPL",
    "gn:name":"Chak Two",
    "gn:population":0,
    "gn:timezone":"Asia/Karachi",
    "iso:country":"PK",
    "name:und_x_variant":[
        "Bage ka Chak",
        "Bagga Gharbi"
    ],
    "wof:name":"Chak Two",
    "wof:placetype":"locality"
},
  "geometry": {"coordinates":[73.67545,31.52361],"type":"Point"}
}