{
  "type": "Feature",
  "properties": {
    "gn:admin1_code":"1",
    "gn:asciiname":"Maidanakai",
    "gn:country_code":"PK",
    "gn:dem":912,
    "gn:feature_class":"P",
    "gn:feature_code":"PPL",
    "gn:name":"Maidanakai",
    "gn:population":0,
    "gn:timezone":"Asia/Karachi",
    "iso:country":"PK",
    "wof:name":"Maidanakai",
    "wof:placetype":"locality"
},
  "geometry": {"coordinates":[69.60278000000001,32.025],"type":"Point"}
}