{
  "type": "Feature",
  "properties": {
    "gn:admin1_code":"4.0",
    "gn:asciiname":"Kashmiri Mahalla",
    "gn:country_code":"PK",
    "gn:dem":1686,
    "gn:feature_class":"P",
    "gn:feature_code":"PPL",
    "gn:name":"Kashmiri Mahalla",
    "gn:population":0,
    "gn:timezone":"Asia/Karachi",
    "iso:country":"PK",
    "name:eng_x_preferred":[
        "Kashmiri Mahalla"
    ],
    "name:und_x_variant":[
        "Kashm\u012bri Mahalia"
    ],
    "wof:name":"Kashmiri Mahalla",
    "wof:placetype":"locality"
},
  "geometry": {"coordinates":[73.36551,33.8974],"type":"Point"}
}