{
  "type": "Feature",
  "properties": {
    "gn:admin1_code":"5",
    "gn:asciiname":"Khyber Wado",
    "gn:country_code":"PK",
    "gn:dem":28,
    "gn:feature_class":"P",
    "gn:feature_code":"PPL",
    "gn:name":"Khyber Wado",
    "gn:population":0,
    "gn:timezone":"Asia/Karachi",
    "iso:country":"PK",
    "name:eng_x_preferred":[
        "Khebar Wado"
    ],
    "name:und_x_variant":[
        "Khebar"
    ],
    "wof:name":"Khyber Wado",
    "wof:placetype":"locality"
},
  "geometry": {"coordinates":[68.50121999999999,25.67878],"type":"Point"}
}