{
  "type": "Feature",
  "properties": {
    "gn:admin1_code":"4.0",
    "gn:asciiname":"Rode da Khu",
    "gn:country_code":"PK",
    "gn:dem":88,
    "gn:feature_class":"P",
    "gn:feature_code":"PPL",
    "gn:name":"Rode da Khu",
    "gn:population":0,
    "gn:timezone":"Asia/Karachi",
    "iso:country":"PK",
    "wof:name":"Rode da Khu",
    "wof:placetype":"locality"
},
  "geometry": {"coordinates":[70.47606,28.58778],"type":"Point"}
}