{
  "type": "Feature",
  "properties": {
    "gn:admin1_code":"01",
    "gn:asciiname":"Mata Sangar Kili",
    "gn:country_code":"PK",
    "gn:dem":1733,
    "gn:feature_class":"P",
    "gn:feature_code":"PPL",
    "gn:name":"Mata Sangar Kili",
    "gn:population":0,
    "gn:timezone":"Asia/Karachi",
    "iso:country":"PK",
    "name:und_x_variant":[
        "Matasargar",
        "M\u0101ta Sangar",
        "Mata Sangar Kili"
    ],
    "wof:name":"Mata Sangar Kili",
    "wof:placetype":"locality"
},
  "geometry": {"coordinates":[69.98814,33.78716],"type":"Point"}
}