{
  "type": "Feature",
  "properties": {
    "gn:admin1_code":"2.0",
    "gn:asciiname":"Parkanda",
    "gn:country_code":"PK",
    "gn:dem":1781,
    "gn:feature_class":"P",
    "gn:feature_code":"PPL",
    "gn:name":"Parkanda",
    "gn:population":0,
    "gn:timezone":"Asia/Karachi",
    "iso:country":"PK",
    "wof:name":"Parkanda",
    "wof:placetype":"locality"
},
  "geometry": {"coordinates":[67.75568,30.82306],"type":"Point"}
}