{
  "type": "Feature",
  "properties": {
    "gn:admin1_code":"4",
    "gn:asciiname":"Dhok Rahm Ali",
    "gn:country_code":"PK",
    "gn:dem":292,
    "gn:feature_class":"P",
    "gn:feature_code":"PPL",
    "gn:name":"Dhok Rahm Ali",
    "gn:population":0,
    "gn:timezone":"Asia/Karachi",
    "iso:country":"PK",
    "wof:name":"Dhok Rahm Ali",
    "wof:placetype":"locality"
},
  "geometry": {"coordinates":[73.42702,32.95143],"type":"Point"}
}