{
  "type": "Feature",
  "properties": {
    "gn:admin1_code":"5.0",
    "gn:asciiname":"Yusuf ji Dhani",
    "gn:country_code":"PK",
    "gn:dem":97,
    "gn:feature_class":"P",
    "gn:feature_code":"PPL",
    "gn:name":"Yusuf ji Dhani",
    "gn:population":0,
    "gn:timezone":"Asia/Karachi",
    "iso:country":"PK",
    "wof:name":"Yusuf ji Dhani",
    "wof:placetype":"locality"
},
  "geometry": {"coordinates":[70.31730999999999,24.85503],"type":"Point"}
}