{
  "type": "Feature",
  "properties": {
    "gn:admin1_code":"2.0",
    "gn:asciiname":"Nokeen Kalag",
    "gn:country_code":"PK",
    "gn:dem":735,
    "gn:feature_class":"P",
    "gn:feature_code":"PPL",
    "gn:name":"Nokeen Kalag",
    "gn:population":0,
    "gn:timezone":"Asia/Karachi",
    "iso:country":"PK",
    "wof:name":"Nokeen Kalag",
    "wof:placetype":"locality"
},
  "geometry": {"coordinates":[62.51825,26.37663],"type":"Point"}
}