{
  "type": "Feature",
  "properties": {
    "gn:admin1_code":"4.0",
    "gn:asciiname":"Ziarat Abdul Ghafoor Chhisha",
    "gn:country_code":"PK",
    "gn:dem":206,
    "gn:feature_class":"P",
    "gn:feature_code":"PPL",
    "gn:name":"Ziarat Abdul Ghafoor Chhisha",
    "gn:population":0,
    "gn:timezone":"Asia/Karachi",
    "iso:country":"PK",
    "wof:name":"Ziarat Abdul Ghafoor Chhisha",
    "wof:placetype":"locality"
},
  "geometry": {"coordinates":[73.16500000000001,32.40489],"type":"Point"}
}