{
  "type": "Feature",
  "properties": {
    "gn:admin1_code":"5.0",
    "gn:asciiname":"Bartho",
    "gn:country_code":"PK",
    "gn:dem":63,
    "gn:feature_class":"P",
    "gn:feature_code":"PPL",
    "gn:name":"Bartho",
    "gn:population":0,
    "gn:timezone":"Asia/Karachi",
    "iso:country":"PK",
    "name:und_x_variant":[
        "Berth",
        "Barth",
        "Bartho"
    ],
    "wof:name":"Bartho",
    "wof:placetype":"locality"
},
  "geometry": {"coordinates":[69.16117,27.76507],"type":"Point"}
}