{
  "type": "Feature",
  "properties": {
    "gn:admin1_code":"5",
    "gn:asciiname":"Goth Sobhago Khaskheli",
    "gn:country_code":"PK",
    "gn:dem":15,
    "gn:feature_class":"P",
    "gn:feature_code":"PPL",
    "gn:name":"Goth Sobh\u0101go Kh\u0101skheli",
    "gn:population":0,
    "gn:timezone":"Asia/Karachi",
    "iso:country":"PK",
    "wof:name":"Goth Sobhago Khaskheli",
    "wof:placetype":"locality"
},
  "geometry": {"coordinates":[68.86111,25.24167000000001],"type":"Point"}
}