{
  "type": "Feature",
  "properties": {
    "gn:admin1_code":"3.0",
    "gn:asciiname":"Rechh",
    "gn:country_code":"PK",
    "gn:dem":2710,
    "gn:feature_class":"P",
    "gn:feature_code":"PPL",
    "gn:name":"Rechh",
    "gn:population":0,
    "gn:timezone":"Asia/Karachi",
    "iso:country":"PK",
    "wof:name":"Rechh",
    "wof:placetype":"locality"
},
  "geometry": {"coordinates":[72.88261999999997,36.59161],"type":"Point"}
}