{
  "type": "Feature",
  "properties": {
    "gn:admin1_code":"2.0",
    "gn:asciiname":"Abdul Salam",
    "gn:country_code":"PK",
    "gn:dem":1539,
    "gn:feature_class":"P",
    "gn:feature_code":"PPL",
    "gn:name":"Abdul Salam",
    "gn:population":0,
    "gn:timezone":"Asia/Karachi",
    "iso:country":"PK",
    "name:eng_x_preferred":[
        "Abdul Salam"
    ],
    "wof:name":"Abdul Salam",
    "wof:placetype":"locality"
},
  "geometry": {"coordinates":[67.0689,30.69028],"type":"Point"}
}