{
  "type": "Feature",
  "properties": {
    "gn:admin1_code":"4",
    "gn:asciiname":"Buraneka",
    "gn:country_code":"PK",
    "gn:dem":253,
    "gn:feature_class":"P",
    "gn:feature_code":"PPL",
    "gn:name":"Buraneka",
    "gn:population":0,
    "gn:timezone":"Asia/Karachi",
    "iso:country":"PK",
    "wof:name":"Buraneka",
    "wof:placetype":"locality"
},
  "geometry": {"coordinates":[74.54978,32.48487],"type":"Point"}
}