{
  "type": "Feature",
  "properties": {
    "gn:admin1_code":"4",
    "gn:asciiname":"Amlike Athar Shah",
    "gn:country_code":"PK",
    "gn:dem":183,
    "gn:feature_class":"P",
    "gn:feature_code":"PPL",
    "gn:name":"Amlike Athar Sh\u0101h",
    "gn:population":0,
    "gn:timezone":"Asia/Karachi",
    "iso:country":"PK",
    "wof:name":"Amlike Athar Shah",
    "wof:placetype":"locality"
},
  "geometry": {"coordinates":[73.99167,30.71528],"type":"Point"}
}