{
  "type": "Feature",
  "properties": {
    "gn:admin1_code":"2.0",
    "gn:asciiname":"Mauladad Kili",
    "gn:country_code":"PK",
    "gn:dem":2165,
    "gn:feature_class":"P",
    "gn:feature_code":"PPL",
    "gn:name":"Mauladad Kili",
    "gn:population":0,
    "gn:timezone":"Asia/Karachi",
    "iso:country":"PK",
    "wof:name":"Mauladad Kili",
    "wof:placetype":"locality"
},
  "geometry": {"coordinates":[66.75802,30.92806],"type":"Point"}
}