{
  "type": "Feature",
  "properties": {
    "gn:admin1_code":"4.0",
    "gn:asciiname":"Dera Haji Lal Baig",
    "gn:country_code":"PK",
    "gn:dem":193,
    "gn:feature_class":"P",
    "gn:feature_code":"PPL",
    "gn:name":"Dera Haji Lal Baig",
    "gn:population":0,
    "gn:timezone":"Asia/Karachi",
    "iso:country":"PK",
    "wof:name":"Dera Haji Lal Baig",
    "wof:placetype":"locality"
},
  "geometry": {"coordinates":[71.80793,32.25502],"type":"Point"}
}