{
  "type": "Feature",
  "properties": {
    "gn:admin1_code":"3.0",
    "gn:asciiname":"Muzaffar da Maira",
    "gn:country_code":"PK",
    "gn:dem":1201,
    "gn:feature_class":"P",
    "gn:feature_code":"PPL",
    "gn:name":"Muzaffar da Maira",
    "gn:population":0,
    "gn:timezone":"Asia/Karachi",
    "iso:country":"PK",
    "wof:name":"Muzaffar da Maira",
    "wof:placetype":"locality"
},
  "geometry": {"coordinates":[73.22884999999999,34.2306],"type":"Point"}
}