{
  "type": "Feature",
  "properties": {
    "gn:admin1_code":"3",
    "gn:asciiname":"Baroti",
    "gn:country_code":"PK",
    "gn:dem":485,
    "gn:feature_class":"P",
    "gn:feature_code":"PPL",
    "gn:name":"Baroti",
    "gn:population":0,
    "gn:timezone":"Asia/Karachi",
    "iso:country":"PK",
    "wof:name":"Baroti",
    "wof:placetype":"locality"
},
  "geometry": {"coordinates":[72.85505999999999,34.36521],"type":"Point"}
}