{
  "type": "Feature",
  "properties": {
    "gn:admin1_code":"6",
    "gn:asciiname":"Dhok Satpir",
    "gn:country_code":"PK",
    "gn:dem":2523,
    "gn:feature_class":"P",
    "gn:feature_code":"PPL",
    "gn:name":"Dhok Satpir",
    "gn:population":0,
    "gn:timezone":"Asia/Karachi",
    "iso:country":"PK",
    "name:und_x_variant":[
        "Sarw\u0101li Bani"
    ],
    "wof:name":"Dhok Satpir",
    "wof:placetype":"locality"
},
  "geometry": {"coordinates":[74.23189000000001,33.91149],"type":"Point"}
}