{
  "type": "Feature",
  "properties": {
    "gn:admin1_code":"05",
    "gn:asciiname":"Shadipali",
    "gn:country_code":"PK",
    "gn:dem":17,
    "gn:feature_class":"P",
    "gn:feature_code":"PPL",
    "gn:name":"Shadipali",
    "gn:population":0,
    "gn:timezone":"Asia/Karachi",
    "iso:country":"PK",
    "name:und_x_variant":[
        "Sh\u0101d\u012bpali"
    ],
    "wof:name":"Shadipali",
    "wof:placetype":"locality"
},
  "geometry": {"coordinates":[69.23232,25.52016],"type":"Point"}
}