{
  "type": "Feature",
  "properties": {
    "gn:admin1_code":"3.0",
    "gn:asciiname":"Khazani Kalle",
    "gn:country_code":"PK",
    "gn:dem":318,
    "gn:feature_class":"P",
    "gn:feature_code":"PPL",
    "gn:name":"Khazani Kalle",
    "gn:population":0,
    "gn:timezone":"Asia/Karachi",
    "iso:country":"PK",
    "wof:name":"Khazani Kalle",
    "wof:placetype":"locality"
},
  "geometry": {"coordinates":[70.44622,32.43582],"type":"Point"}
}