{
  "type": "Feature",
  "properties": {
    "gn:admin1_code":"4",
    "gn:asciiname":"Shamirwala",
    "gn:country_code":"PK",
    "gn:dem":152,
    "gn:feature_class":"P",
    "gn:feature_code":"PPL",
    "gn:name":"Shamirwala",
    "gn:population":0,
    "gn:timezone":"Asia/Karachi",
    "iso:country":"PK",
    "name:und_x_variant":[
        "Sh\u0101hm\u012brw\u0101la"
    ],
    "wof:name":"Shamirwala",
    "wof:placetype":"locality"
},
  "geometry": {"coordinates":[71.40111999999998,31.07195],"type":"Point"}
}