{
  "type": "Feature",
  "properties": {
    "gn:admin1_code":"2",
    "gn:asciiname":"Hamayun Kili",
    "gn:country_code":"PK",
    "gn:dem":1459,
    "gn:feature_class":"P",
    "gn:feature_code":"PPL",
    "gn:name":"Hamayun Kili",
    "gn:population":0,
    "gn:timezone":"Asia/Karachi",
    "iso:country":"PK",
    "name:und_x_variant":[
        "Hamai Kili"
    ],
    "wof:name":"Hamayun Kili",
    "wof:placetype":"locality"
},
  "geometry": {"coordinates":[69.08748,30.90664],"type":"Point"}
}