{
  "type": "Feature",
  "properties": {
    "gn:admin1_code":"4.0",
    "gn:asciiname":"Jam Khan Chandia",
    "gn:country_code":"PK",
    "gn:dem":91,
    "gn:feature_class":"P",
    "gn:feature_code":"PPL",
    "gn:name":"Jam Kh\u0101n Ch\u0101ndia",
    "gn:population":0,
    "gn:timezone":"Asia/Karachi",
    "iso:country":"PK",
    "name:und_x_variant":[
        "Jam Kh\u0101n Ch\u0101ndia",
        "Jam Kh\u0101n Ch\u0101ndin"
    ],
    "wof:name":"Jam Khan Chandia",
    "wof:placetype":"locality"
},
  "geometry": {"coordinates":[70.49415999999999,28.8482],"type":"Point"}
}