{
  "type": "Feature",
  "properties": {
    "gn:admin1_code":"3.0",
    "gn:asciiname":"Gedrao",
    "gn:country_code":"PK",
    "gn:dem":1758,
    "gn:feature_class":"P",
    "gn:feature_code":"PPL",
    "gn:name":"Gedrao",
    "gn:population":0,
    "gn:timezone":"Asia/Karachi",
    "iso:country":"PK",
    "wof:name":"Gedrao",
    "wof:placetype":"locality"
},
  "geometry": {"coordinates":[72.9427,35.42817],"type":"Point"}
}