{
  "type": "Feature",
  "properties": {
    "gn:admin1_code":"4.0",
    "gn:asciiname":"Basti Khan Muhammad Mian",
    "gn:country_code":"PK",
    "gn:dem":84,
    "gn:feature_class":"P",
    "gn:feature_code":"PPL",
    "gn:name":"Basti Khan Muhammad Mian",
    "gn:population":0,
    "gn:timezone":"Asia/Karachi",
    "iso:country":"PK",
    "wof:name":"Basti Khan Muhammad Mian",
    "wof:placetype":"locality"
},
  "geometry": {"coordinates":[69.95276,28.56362],"type":"Point"}
}