{
  "type": "Feature",
  "properties": {
    "gn:admin1_code":"4.0",
    "gn:asciiname":"Uttam Ghariali",
    "gn:country_code":"PK",
    "gn:dem":482,
    "gn:feature_class":"P",
    "gn:feature_code":"PPL",
    "gn:name":"Uttam Ghariali",
    "gn:population":0,
    "gn:timezone":"Asia/Karachi",
    "iso:country":"PK",
    "name:und_x_variant":[
        "Uttam Ghari\u0101li"
    ],
    "wof:name":"Uttam Ghariali",
    "wof:placetype":"locality"
},
  "geometry": {"coordinates":[73.08381999999997,33.38922],"type":"Point"}
}