{
  "type": "Feature",
  "properties": {
    "gn:admin1_code":"4",
    "gn:asciiname":"Qamar Ka Thatta",
    "gn:country_code":"PK",
    "gn:dem":175,
    "gn:feature_class":"P",
    "gn:feature_code":"PPL",
    "gn:name":"Qamar Ka Thatta",
    "gn:population":0,
    "gn:timezone":"Asia/Karachi",
    "iso:country":"PK",
    "wof:name":"Qamar Ka Thatta",
    "wof:placetype":"locality"
},
  "geometry": {"coordinates":[72.74970999999999,31.69777],"type":"Point"}
}