{
  "type": "Feature",
  "properties": {
    "gn:admin1_code":"3.0",
    "gn:asciiname":"Tarnao",
    "gn:country_code":"PK",
    "gn:dem":1012,
    "gn:feature_class":"P",
    "gn:feature_code":"PPL",
    "gn:name":"Tarnao",
    "gn:population":0,
    "gn:timezone":"Asia/Karachi",
    "iso:country":"PK",
    "wof:name":"Tarnao",
    "wof:placetype":"locality"
},
  "geometry": {"coordinates":[72.94086999999998,34.72054],"type":"Point"}
}