{
  "type": "Feature",
  "properties": {
    "gn:admin1_code":"5.0",
    "gn:asciiname":"Manthar Rajar",
    "gn:country_code":"PK",
    "gn:dem":26,
    "gn:feature_class":"P",
    "gn:feature_code":"PPL",
    "gn:name":"Manthar Rajar",
    "gn:population":0,
    "gn:timezone":"Asia/Karachi",
    "iso:country":"PK",
    "wof:name":"Manthar Rajar",
    "wof:placetype":"locality"
},
  "geometry": {"coordinates":[69.58868000000001,25.88103],"type":"Point"}
}