{
  "type": "Feature",
  "properties": {
    "gn:admin1_code":"4.0",
    "gn:asciiname":"Inayatpur Mahota",
    "gn:country_code":"PK",
    "gn:dem":126,
    "gn:feature_class":"P",
    "gn:feature_code":"PPL",
    "gn:name":"Inayatpur Mahota",
    "gn:population":0,
    "gn:timezone":"Asia/Karachi",
    "iso:country":"PK",
    "name:und_x_variant":[
        "Inayatpur Muhatta",
        "Inayatpur Mahota"
    ],
    "wof:name":"Inayatpur Mahota",
    "wof:placetype":"locality"
},
  "geometry": {"coordinates":[71.50360000000001,30.33602],"type":"Point"}
}