{
  "type": "Feature",
  "properties": {
    "gn:admin1_code":"5",
    "gn:asciiname":"Goth Shafi Muhammad Arain",
    "gn:country_code":"PK",
    "gn:dem":36,
    "gn:feature_class":"P",
    "gn:feature_code":"PPL",
    "gn:name":"Goth Shafi Muhammad Arain",
    "gn:population":0,
    "gn:timezone":"Asia/Karachi",
    "iso:country":"PK",
    "name:und_x_variant":[
        "Goth H\u0101ji Shafi Muhammad Mahr"
    ],
    "wof:name":"Goth Shafi Muhammad Arain",
    "wof:placetype":"locality"
},
  "geometry": {"coordinates":[68.1495,26.38744],"type":"Point"}
}