{
  "type": "Feature",
  "properties": {
    "gn:admin1_code":"5",
    "gn:asciiname":"Goth Rais Irshad Nizamani",
    "gn:country_code":"PK",
    "gn:dem":52,
    "gn:feature_class":"P",
    "gn:feature_code":"PPL",
    "gn:name":"Goth Rais Irshad Nizamani",
    "gn:population":0,
    "gn:timezone":"Asia/Karachi",
    "iso:country":"PK",
    "name:und_x_variant":[
        "Karam Kh\u0101n Niz\u0101m\u0101ni"
    ],
    "wof:name":"Goth Rais Irshad Nizamani",
    "wof:placetype":"locality"
},
  "geometry": {"coordinates":[68.41516999999999,27.11137],"type":"Point"}
}