{
  "type": "Feature",
  "properties": {
    "gn:admin1_code":"2.0",
    "gn:asciiname":"Leghai",
    "gn:country_code":"PK",
    "gn:dem":2410,
    "gn:feature_class":"P",
    "gn:feature_code":"PPL",
    "gn:name":"Leghai",
    "gn:population":0,
    "gn:timezone":"Asia/Karachi",
    "iso:country":"PK",
    "name:eng_x_preferred":[
        "Laghai"
    ],
    "wof:name":"Leghai",
    "wof:placetype":"locality"
},
  "geometry": {"coordinates":[67.30356999999999,30.97775],"type":"Point"}
}