{
  "type": "Feature",
  "properties": {
    "gn:admin1_code":"2.0",
    "gn:asciiname":"Buh Bent",
    "gn:country_code":"PK",
    "gn:dem":684,
    "gn:feature_class":"P",
    "gn:feature_code":"PPL",
    "gn:name":"Buh Bent",
    "gn:population":0,
    "gn:timezone":"Asia/Karachi",
    "iso:country":"PK",
    "wof:name":"Buh Bent",
    "wof:placetype":"locality"
},
  "geometry": {"coordinates":[66.92208000000001,27.24653],"type":"Point"}
}