{
  "type": "Feature",
  "properties": {
    "gn:admin1_code":"3.0",
    "gn:asciiname":"Chashmai Chanda",
    "gn:country_code":"PK",
    "gn:dem":569,
    "gn:feature_class":"P",
    "gn:feature_code":"PPL",
    "gn:name":"Chashmai Chanda",
    "gn:population":0,
    "gn:timezone":"Asia/Karachi",
    "iso:country":"PK",
    "wof:name":"Chashmai Chanda",
    "wof:placetype":"locality"
},
  "geometry": {"coordinates":[71.63186999999998,33.15879],"type":"Point"}
}