{
  "type": "Feature",
  "properties": {
    "gn:admin1_code":"3.0",
    "gn:asciiname":"Sun",
    "gn:country_code":"PK",
    "gn:dem":1126,
    "gn:feature_class":"P",
    "gn:feature_code":"PPL",
    "gn:name":"Sun",
    "gn:population":0,
    "gn:timezone":"Asia/Karachi",
    "iso:country":"PK",
    "wof:name":"Sun",
    "wof:placetype":"locality"
},
  "geometry": {"coordinates":[73.25024000000001,34.53867],"type":"Point"}
}