{
  "type": "Feature",
  "properties": {
    "gn:admin1_code":"3.0",
    "gn:asciiname":"Karwala",
    "gn:country_code":"PK",
    "gn:dem":1013,
    "gn:feature_class":"P",
    "gn:feature_code":"PPL",
    "gn:name":"Karwala",
    "gn:population":0,
    "gn:timezone":"Asia/Karachi",
    "iso:country":"PK",
    "name:eng_x_preferred":[
        "Karwala"
    ],
    "wof:name":"Karwala",
    "wof:placetype":"locality"
},
  "geometry": {"coordinates":[73.12238000000001,33.9608],"type":"Point"}
}