{
  "type": "Feature",
  "properties": {
    "gn:admin1_code":"4.0",
    "gn:asciiname":"Luniwala",
    "gn:country_code":"PK",
    "gn:dem":140,
    "gn:feature_class":"P",
    "gn:feature_code":"PPL",
    "gn:name":"Luniwala",
    "gn:population":0,
    "gn:timezone":"Asia/Karachi",
    "iso:country":"PK",
    "wof:name":"Luniwala",
    "wof:placetype":"locality"
},
  "geometry": {"coordinates":[71.23779999999999,30.62218],"type":"Point"}
}