{
  "type": "Feature",
  "properties": {
    "gn:admin1_code":"5.0",
    "gn:asciiname":"Sumrial",
    "gn:country_code":"PK",
    "gn:dem":37,
    "gn:feature_class":"P",
    "gn:feature_code":"PPL",
    "gn:name":"Sumrial",
    "gn:population":0,
    "gn:timezone":"Asia/Karachi",
    "iso:country":"PK",
    "name:und_x_variant":[
        "Sumrit"
    ],
    "wof:name":"Sumrial",
    "wof:placetype":"locality"
},
  "geometry": {"coordinates":[70.55315999999998,24.50878],"type":"Point"}
}