{
  "type": "Feature",
  "properties": {
    "gn:admin1_code":"1.0",
    "gn:asciiname":"Shakara",
    "gn:country_code":"PK",
    "gn:dem":1984,
    "gn:feature_class":"P",
    "gn:feature_code":"PPL",
    "gn:name":"Shakara",
    "gn:population":0,
    "gn:timezone":"Asia/Karachi",
    "iso:country":"PK",
    "wof:name":"Shakara",
    "wof:placetype":"locality"
},
  "geometry": {"coordinates":[70.79106999999998,33.7544],"type":"Point"}
}