{
  "type": "Feature",
  "properties": {
    "gn:admin1_code":"4",
    "gn:asciiname":"Basti Lal Shahwali",
    "gn:country_code":"PK",
    "gn:dem":150,
    "gn:feature_class":"P",
    "gn:feature_code":"PPL",
    "gn:name":"Basti Lal Shahwali",
    "gn:population":0,
    "gn:timezone":"Asia/Karachi",
    "iso:country":"PK",
    "name:und_x_variant":[
        "L\u0101l Sh\u0101hw\u0101la"
    ],
    "wof:name":"Basti Lal Shahwali",
    "wof:placetype":"locality"
},
  "geometry": {"coordinates":[72.15912,31.05297],"type":"Point"}
}