{
  "type": "Feature",
  "properties": {
    "gn:admin1_code":"7.0",
    "gn:asciiname":"Gorinjar",
    "gn:country_code":"PK",
    "gn:dem":1869,
    "gn:feature_class":"P",
    "gn:feature_code":"PPL",
    "gn:name":"Gorinjar",
    "gn:population":0,
    "gn:timezone":"Asia/Karachi",
    "iso:country":"PK",
    "wof:name":"Gorinjar",
    "wof:placetype":"locality"
},
  "geometry": {"coordinates":[73.84275,36.16331],"type":"Point"}
}