{
  "type": "Feature",
  "properties": {
    "gn:admin1_code":"3.0",
    "gn:asciiname":"Gharibabad",
    "gn:country_code":"PK",
    "gn:dem":291,
    "gn:feature_class":"P",
    "gn:feature_code":"PPL",
    "gn:name":"Gharibabad",
    "gn:population":0,
    "gn:timezone":"Asia/Karachi",
    "iso:country":"PK",
    "name:und_x_variant":[
        "Ghar\u012bbpura"
    ],
    "wof:name":"Gharibabad",
    "wof:placetype":"locality"
},
  "geometry": {"coordinates":[72.19504000000001,33.77639],"type":"Point"}
}