{
  "type": "Feature",
  "properties": {
    "gn:admin1_code":"4",
    "gn:asciiname":"Chak Thirteen South Branch",
    "gn:country_code":"PK",
    "gn:dem":195,
    "gn:feature_class":"P",
    "gn:feature_code":"PPL",
    "gn:name":"Chak Thirteen South Branch",
    "gn:population":0,
    "gn:timezone":"Asia/Karachi",
    "iso:country":"PK",
    "name:und_x_variant":[
        "Chak Thirteen SB"
    ],
    "wof:name":"Chak Thirteen South Branch",
    "wof:placetype":"locality"
},
  "geometry": {"coordinates":[72.84613,32.19134],"type":"Point"}
}