{
  "type": "Feature",
  "properties": {
    "gn:admin1_code":"2.0",
    "gn:asciiname":"Miro Kucho",
    "gn:country_code":"PK",
    "gn:dem":1486,
    "gn:feature_class":"P",
    "gn:feature_code":"PPL",
    "gn:name":"Miro Kucho",
    "gn:population":0,
    "gn:timezone":"Asia/Karachi",
    "iso:country":"PK",
    "wof:name":"Miro Kucho",
    "wof:placetype":"locality"
},
  "geometry": {"coordinates":[66.68656,28.47885],"type":"Point"}
}