{
  "type": "Feature",
  "properties": {
    "gn:admin1_code":"5.0",
    "gn:asciiname":"Chak Number Five",
    "gn:country_code":"PK",
    "gn:dem":9,
    "gn:feature_class":"P",
    "gn:feature_code":"PPL",
    "gn:name":"Chak Number Five",
    "gn:population":0,
    "gn:timezone":"Asia/Karachi",
    "iso:country":"PK",
    "name:eng_x_preferred":[
        "Chak Number Five"
    ],
    "wof:name":"Chak Number Five",
    "wof:placetype":"locality"
},
  "geometry": {"coordinates":[68.44238,24.58188],"type":"Point"}
}