{
  "type": "Feature",
  "properties": {
    "gn:admin1_code":"4",
    "gn:asciiname":"Dhoda",
    "gn:country_code":"PK",
    "gn:dem":317,
    "gn:feature_class":"P",
    "gn:feature_code":"PPL",
    "gn:name":"Dhoda",
    "gn:population":0,
    "gn:timezone":"Asia/Karachi",
    "iso:country":"PK",
    "wof:name":"Dhoda",
    "wof:placetype":"locality"
},
  "geometry": {"coordinates":[74.18969,32.84443],"type":"Point"}
}