{
  "type": "Feature",
  "properties": {
    "gn:admin1_code":"4",
    "gn:asciiname":"Chah Baghiwala",
    "gn:country_code":"PK",
    "gn:dem":170,
    "gn:feature_class":"P",
    "gn:feature_code":"PPL",
    "gn:name":"Chah Baghiwala",
    "gn:population":0,
    "gn:timezone":"Asia/Karachi",
    "iso:country":"PK",
    "name:und_x_variant":[
        "Ch\u0101h Bagw\u0101la"
    ],
    "wof:name":"Chah Baghiwala",
    "wof:placetype":"locality"
},
  "geometry": {"coordinates":[72.59428,31.51206],"type":"Point"}
}