{
  "type": "Feature",
  "properties": {
    "gn:admin1_code":"4.0",
    "gn:asciiname":"Chak Two Hundred Twenty",
    "gn:country_code":"PK",
    "gn:dem":159,
    "gn:feature_class":"P",
    "gn:feature_code":"PPL",
    "gn:name":"Chak Two Hundred Twenty",
    "gn:population":0,
    "gn:timezone":"Asia/Karachi",
    "iso:country":"PK",
    "name:und_x_variant":[
        "Ghanu\u0101n",
        "Chak 220",
        "Chak Two Hundred Twenty"
    ],
    "wof:name":"Chak Two Hundred Twenty",
    "wof:placetype":"locality"
},
  "geometry": {"coordinates":[72.46038,31.29585],"type":"Point"}
}