{
  "type": "Feature",
  "properties": {
    "gn:admin1_code":"5",
    "gn:asciiname":"Goth Lal Bakhsh",
    "gn:country_code":"PK",
    "gn:dem":51,
    "gn:feature_class":"P",
    "gn:feature_code":"PPL",
    "gn:name":"Goth Lal Bakhsh",
    "gn:population":0,
    "gn:timezone":"Asia/Karachi",
    "iso:country":"PK",
    "wof:name":"Goth Lal Bakhsh",
    "wof:placetype":"locality"
},
  "geometry": {"coordinates":[67.55275999999999,26.90872],"type":"Point"}
}