{
  "type": "Feature",
  "properties": {
    "gn:admin1_code":"03",
    "gn:asciiname":"Tutkai",
    "gn:country_code":"PK",
    "gn:dem":1087,
    "gn:feature_class":"P",
    "gn:feature_code":"PPL",
    "gn:name":"Tutkai",
    "gn:population":0,
    "gn:timezone":"Asia/Karachi",
    "iso:country":"PK",
    "name:und_x_variant":[
        "Totki",
        "Tutkai"
    ],
    "wof:name":"Tutkai",
    "wof:placetype":"locality"
},
  "geometry": {"coordinates":[72.41461,34.92281],"type":"Point"}
}