{
  "type": "Feature",
  "properties": {
    "gn:admin1_code":"03",
    "gn:asciiname":"Tutan Banda",
    "gn:country_code":"PK",
    "gn:dem":1154,
    "gn:feature_class":"P",
    "gn:feature_code":"PPL",
    "gn:name":"Tutan Banda",
    "gn:population":0,
    "gn:timezone":"Asia/Karachi",
    "iso:country":"PK",
    "name:und_x_variant":[
        "Tulan Banda",
        "Totan Banda",
        "Tutan Banda"
    ],
    "wof:name":"Tutan Banda",
    "wof:placetype":"locality"
},
  "geometry": {"coordinates":[72.22578,34.84616],"type":"Point"}
}