{
  "type": "Feature",
  "properties": {
    "gn:admin1_code":"4",
    "gn:asciiname":"Manjwala",
    "gn:country_code":"PK",
    "gn:dem":182,
    "gn:feature_class":"P",
    "gn:feature_code":"PPL",
    "gn:name":"Manjw\u0101la",
    "gn:population":0,
    "gn:timezone":"Asia/Karachi",
    "iso:country":"PK",
    "wof:name":"Manjwala",
    "wof:placetype":"locality"
},
  "geometry": {"coordinates":[73.57222,30.93333],"type":"Point"}
}