{
  "type": "Feature",
  "properties": {
    "gn:admin1_code":"4",
    "gn:asciiname":"Kot Umar Bakhsh Khan Mazari",
    "gn:country_code":"PK",
    "gn:dem":82,
    "gn:feature_class":"P",
    "gn:feature_code":"PPL",
    "gn:name":"Kot Umar Bakhsh Khan Mazari",
    "gn:population":0,
    "gn:timezone":"Asia/Karachi",
    "iso:country":"PK",
    "wof:name":"Kot Umar Bakhsh Khan Mazari",
    "wof:placetype":"locality"
},
  "geometry": {"coordinates":[69.95971999999999,28.50694],"type":"Point"}
}