{
  "type": "Feature",
  "properties": {
    "gn:admin1_code":"3",
    "gn:asciiname":"Nakka",
    "gn:country_code":"PK",
    "gn:dem":1909,
    "gn:feature_class":"P",
    "gn:feature_code":"PPL",
    "gn:name":"Nakka",
    "gn:population":0,
    "gn:timezone":"Asia/Karachi",
    "iso:country":"PK",
    "name:und_x_variant":[
        "Nalla"
    ],
    "wof:name":"Nakka",
    "wof:placetype":"locality"
},
  "geometry": {"coordinates":[73.21556,34.58415],"type":"Point"}
}