{
  "type": "Feature",
  "properties": {
    "gn:admin1_code":"2.0",
    "gn:asciiname":"Juma Khan Kili",
    "gn:country_code":"PK",
    "gn:dem":1303,
    "gn:feature_class":"P",
    "gn:feature_code":"PPL",
    "gn:name":"Juma Khan Kili",
    "gn:population":0,
    "gn:timezone":"Asia/Karachi",
    "iso:country":"PK",
    "wof:name":"Juma Khan Kili",
    "wof:placetype":"locality"
},
  "geometry": {"coordinates":[63.76445,29.22267],"type":"Point"}
}