{
  "type": "Feature",
  "properties": {
    "gn:admin1_code":"4.0",
    "gn:asciiname":"Khawaja Saleh",
    "gn:country_code":"PK",
    "gn:dem":198,
    "gn:feature_class":"P",
    "gn:feature_code":"PPL",
    "gn:name":"Khawaja Saleh",
    "gn:population":0,
    "gn:timezone":"Asia/Karachi",
    "iso:country":"PK",
    "name:und_x_variant":[
        "Khoja Salah",
        "Khoaja Sal\u0101h",
        "Khw\u0101ja Sal\u0101h",
        "Khawaja Saleh"
    ],
    "wof:name":"Khawaja Saleh",
    "wof:placetype":"locality"
},
  "geometry": {"coordinates":[72.93415999999998,32.40598],"type":"Point"}
}