{
  "type": "Feature",
  "properties": {
    "gn:admin1_code":"1.0",
    "gn:asciiname":"Pakhi",
    "gn:country_code":"PK",
    "gn:dem":756,
    "gn:feature_class":"P",
    "gn:feature_code":"PPL",
    "gn:name":"Pakhi",
    "gn:population":0,
    "gn:timezone":"Asia/Karachi",
    "iso:country":"PK",
    "wof:name":"Pakhi",
    "wof:placetype":"locality"
},
  "geometry": {"coordinates":[71.66162,33.72128],"type":"Point"}
}