{
  "type": "Feature",
  "properties": {
    "gn:admin1_code":"4.0",
    "gn:asciiname":"Bhati Afghanan",
    "gn:country_code":"PK",
    "gn:dem":266,
    "gn:feature_class":"P",
    "gn:feature_code":"PPL",
    "gn:name":"Bhati Afghanan",
    "gn:population":0,
    "gn:timezone":"Asia/Karachi",
    "iso:country":"PK",
    "wof:name":"Bhati Afghanan",
    "wof:placetype":"locality"
},
  "geometry": {"coordinates":[75.20376999999998,32.27551],"type":"Point"}
}