{
  "type": "Feature",
  "properties": {
    "gn:admin1_code":"4.0",
    "gn:asciiname":"Bara Maira",
    "gn:country_code":"PK",
    "gn:dem":551,
    "gn:feature_class":"P",
    "gn:feature_code":"PPL",
    "gn:name":"Bara Maira",
    "gn:population":0,
    "gn:timezone":"Asia/Karachi",
    "iso:country":"PK",
    "name:und_x_variant":[
        "Maira"
    ],
    "wof:name":"Bara Maira",
    "wof:placetype":"locality"
},
  "geometry": {"coordinates":[73.1741,33.4447],"type":"Point"}
}