{
  "type": "Feature",
  "properties": {
    "gn:admin1_code":"4.0",
    "gn:asciiname":"Chauntra Sargana",
    "gn:country_code":"PK",
    "gn:dem":147,
    "gn:feature_class":"P",
    "gn:feature_code":"PPL",
    "gn:name":"Chauntra Sargana",
    "gn:population":0,
    "gn:timezone":"Asia/Karachi",
    "iso:country":"PK",
    "name:und_x_variant":[
        "Chotra Sargana",
        "Chautra Sarg\u0101na",
        "Chauntra Sargana"
    ],
    "wof:name":"Chauntra Sargana",
    "wof:placetype":"locality"
},
  "geometry": {"coordinates":[72.29938,30.60453],"type":"Point"}
}