{
  "type": "Feature",
  "properties": {
    "gn:admin1_code":"5",
    "gn:asciiname":"Deh Two Hundred Five",
    "gn:country_code":"PK",
    "gn:dem":10,
    "gn:feature_class":"P",
    "gn:feature_code":"PPL",
    "gn:name":"Deh Two Hundred Five",
    "gn:population":0,
    "gn:timezone":"Asia/Karachi",
    "iso:country":"PK",
    "wof:name":"Deh Two Hundred Five",
    "wof:placetype":"locality"
},
  "geometry": {"coordinates":[69.28299,24.9908],"type":"Point"}
}