{
  "type": "Feature",
  "properties": {
    "gn:admin1_code":"5",
    "gn:asciiname":"Goth Jafar Rahu",
    "gn:country_code":"PK",
    "gn:dem":36,
    "gn:feature_class":"P",
    "gn:feature_code":"PPL",
    "gn:name":"Goth Jafar Rahu",
    "gn:population":0,
    "gn:timezone":"Asia/Karachi",
    "iso:country":"PK",
    "name:und_x_variant":[
        "Goth Jafar R\u0101ho"
    ],
    "wof:name":"Goth Jafar Rahu",
    "wof:placetype":"locality"
},
  "geometry": {"coordinates":[68.10964,26.34491],"type":"Point"}
}