{
  "type": "Feature",
  "properties": {
    "gn:admin1_code":"4.0",
    "gn:asciiname":"Chak One Hundred Eight -Nine Left",
    "gn:country_code":"PK",
    "gn:dem":166,
    "gn:feature_class":"P",
    "gn:feature_code":"PPL",
    "gn:name":"Chak One Hundred Eight -Nine Left",
    "gn:population":0,
    "gn:timezone":"Asia/Karachi",
    "iso:country":"PK",
    "name:und_x_variant":[
        "Budhaw\u0101la"
    ],
    "wof:name":"Chak One Hundred Eight -Nine Left",
    "wof:placetype":"locality"
},
  "geometry": {"coordinates":[73.09316,30.56043],"type":"Point"}
}