{
  "type": "Feature",
  "properties": {
    "gn:admin1_code":"2.0",
    "gn:asciiname":"Gird",
    "gn:country_code":"PK",
    "gn:dem":610,
    "gn:feature_class":"P",
    "gn:feature_code":"PPL",
    "gn:name":"Gird",
    "gn:population":0,
    "gn:timezone":"Asia/Karachi",
    "iso:country":"PK",
    "wof:name":"Gird",
    "wof:placetype":"locality"
},
  "geometry": {"coordinates":[63.46194000000001,27.63611],"type":"Point"}
}