{
  "type": "Feature",
  "properties": {
    "gn:admin1_code":"2.0",
    "gn:asciiname":"Syed Kalani",
    "gn:country_code":"PK",
    "gn:dem":1442,
    "gn:feature_class":"P",
    "gn:feature_code":"PPL",
    "gn:name":"Syed Kalani",
    "gn:population":0,
    "gn:timezone":"Asia/Karachi",
    "iso:country":"PK",
    "wof:name":"Syed Kalani",
    "wof:placetype":"locality"
},
  "geometry": {"coordinates":[66.53237,30.15796],"type":"Point"}
}