{
  "type": "Feature",
  "properties": {
    "gn:admin1_code":"5",
    "gn:asciiname":"Hot Jakhri",
    "gn:country_code":"PK",
    "gn:dem":24,
    "gn:feature_class":"P",
    "gn:feature_code":"PPL",
    "gn:name":"Hot Jakhri",
    "gn:population":0,
    "gn:timezone":"Asia/Karachi",
    "iso:country":"PK",
    "name:eng_x_preferred":[
        "Hot Jakhri"
    ],
    "wof:name":"Hot Jakhri",
    "wof:placetype":"locality"
},
  "geometry": {"coordinates":[68.49778000000001,25.49297],"type":"Point"}
}