{
  "type": "Feature",
  "properties": {
    "gn:admin1_code":"3.0",
    "gn:asciiname":"Dheri Rakhala",
    "gn:country_code":"PK",
    "gn:dem":1312,
    "gn:feature_class":"P",
    "gn:feature_code":"PPL",
    "gn:name":"Dheri Rakhala",
    "gn:population":0,
    "gn:timezone":"Asia/Karachi",
    "iso:country":"PK",
    "name:eng_x_preferred":[
        "Dheri Rakhala"
    ],
    "wof:name":"Dheri Rakhala",
    "wof:placetype":"locality"
},
  "geometry": {"coordinates":[73.23246999999998,33.84287],"type":"Point"}
}