{
  "type": "Feature",
  "properties": {
    "gn:admin1_code":"5",
    "gn:asciiname":"Goth Harun Sand",
    "gn:country_code":"PK",
    "gn:dem":22,
    "gn:feature_class":"P",
    "gn:feature_code":"PPL",
    "gn:name":"Goth Harun Sand",
    "gn:population":0,
    "gn:timezone":"Asia/Karachi",
    "iso:country":"PK",
    "name:und_x_variant":[
        "Goth H\u0101r\u016bn S\u0101nd"
    ],
    "wof:name":"Goth Harun Sand",
    "wof:placetype":"locality"
},
  "geometry": {"coordinates":[68.69932,25.61036],"type":"Point"}
}