{
  "type": "Feature",
  "properties": {
    "gn:admin1_code":"03",
    "gn:asciiname":"Guides Hill",
    "gn:country_code":"PK",
    "gn:dem":1141,
    "gn:feature_class":"P",
    "gn:feature_code":"PPL",
    "gn:name":"Guides Hill",
    "gn:population":0,
    "gn:timezone":"Asia/Karachi",
    "iso:country":"PK",
    "name:eng_x_preferred":[
        "Guides Hill"
    ],
    "wof:name":"Guides Hill",
    "wof:placetype":"locality"
},
  "geometry": {"coordinates":[71.91467,34.55793],"type":"Point"}
}