{
  "type": "Feature",
  "properties": {
    "gn:admin1_code":"4.0",
    "gn:asciiname":"Pilatan",
    "gn:country_code":"PK",
    "gn:dem":247,
    "gn:feature_class":"P",
    "gn:feature_code":"PPL",
    "gn:name":"Pilatan",
    "gn:population":0,
    "gn:timezone":"Asia/Karachi",
    "iso:country":"PK",
    "wof:name":"Pilatan",
    "wof:placetype":"locality"
},
  "geometry": {"coordinates":[74.98345,32.16947],"type":"Point"}
}