{
  "type": "Feature",
  "properties": {
    "gn:admin1_code":"4",
    "gn:asciiname":"Chak Rustamwala",
    "gn:country_code":"PK",
    "gn:dem":183,
    "gn:feature_class":"P",
    "gn:feature_code":"PPL",
    "gn:name":"Chak Rustamwala",
    "gn:population":0,
    "gn:timezone":"Asia/Karachi",
    "iso:country":"PK",
    "name:und_x_variant":[
        "Ch\u0101h \u0100b\u0101di Rustamw\u0101la"
    ],
    "wof:name":"Chak Rustamwala",
    "wof:placetype":"locality"
},
  "geometry": {"coordinates":[73.59439999999999,30.9661],"type":"Point"}
}