{
  "type": "Feature",
  "properties": {
    "gn:admin1_code":"6",
    "gn:asciiname":"Gulbahar",
    "gn:country_code":"PK",
    "gn:dem":274,
    "gn:feature_class":"P",
    "gn:feature_code":"PPL",
    "gn:name":"Gulbahar",
    "gn:population":0,
    "gn:timezone":"Asia/Karachi",
    "iso:country":"PK",
    "name:eng_x_preferred":[
        "Gulbahar"
    ],
    "name:urd_x_preferred":[
        "\u06af\u0644\u0628\u06c1\u0627\u0631"
    ],
    "wof:name":"Gulbahar",
    "wof:placetype":"locality"
},
  "geometry": {"coordinates":[73.88921000000001,33.0267],"type":"Point"}
}