{
  "type": "Feature",
  "properties": {
    "gn:admin1_code":"6",
    "gn:asciiname":"Gulbahar",
    "gn:country_code":"PK",
    "gn:dem":274,
    "gn:feature_class":"P",
    "gn:feature_code":"PPL",
    "gn:name":"Gulbahar",
    "gn:population":0,
    "gn:timezone":"Asia/Karachi",
    "iso:country":"PK",
    "wof:name":"Gulbahar",
    "wof:placetype":"locality"
},
  "geometry": {"coordinates":[73.88920999999998,33.0267],"type":"Point"}
}