{
  "type": "Feature",
  "properties": {
    "gn:admin1_code":"4.0",
    "gn:asciiname":"Cher Hardo",
    "gn:country_code":"PK",
    "gn:dem":530,
    "gn:feature_class":"P",
    "gn:feature_code":"PPL",
    "gn:name":"Cher Hardo",
    "gn:population":0,
    "gn:timezone":"Asia/Karachi",
    "iso:country":"PK",
    "wof:name":"Cher Hardo",
    "wof:placetype":"locality"
},
  "geometry": {"coordinates":[73.17789,33.32413],"type":"Point"}
}