{
  "type": "Feature",
  "properties": {
    "iso:country":"PK",
    "name:eng_x_preferred":[
        "Dulmial"
    ],
    "name:fas_x_preferred":[
        "\u062f\u0648\u0627\u0644\u0645\u06cc\u0627\u0644"
    ],
    "name:hin_x_preferred":[
        "\u0926\u0941\u0932\u094d\u092e\u093f\u092f\u093c\u093e\u0932"
    ],
    "name:nld_x_preferred":[
        "Dulmial"
    ],
    "name:unk_x_variant":[
        "Doalmial"
    ],
    "name:urd_x_preferred":[
        "\u062f\u0648\u0627\u0644\u0645\u06cc\u0627\u0644"
    ],
    "qs:gn_country":"PK",
    "qs:gn_fcode":"PPL",
    "qs:gn_pop":0,
    "qs:name":"Dulmian",
    "qs:name_adm0":"Pakistan",
    "qs:name_adm1":"Punjab",
    "qs:photos":10,
    "qs:photos_1k":2,
    "qs:photos_9k":1,
    "qs:photos_9r":1,
    "qs:photos_all":10,
    "qs:photos_sr":1,
    "qs:placetype":"Town",
    "qs:pop_sr":"0",
    "qs:woe_adm0":23424922,
    "wd:wordcount":218,
    "wof:name":"Dulmian",
    "wof:placetype":"locality"
},
  "geometry": {"coordinates":[72.92525999999999,32.73834],"type":"Point"}
}