{
  "type": "Feature",
  "properties": {
    "gn:admin1_code":"4.0",
    "gn:asciiname":"Chak Two Hundred Two",
    "gn:country_code":"PK",
    "gn:dem":178,
    "gn:feature_class":"P",
    "gn:feature_code":"PPL",
    "gn:name":"Chak Two Hundred Two",
    "gn:population":0,
    "gn:timezone":"Asia/Karachi",
    "iso:country":"PK",
    "name:und_x_variant":[
        "Gajjan",
        "Gaji\u0101ni",
        "Chak Two Hundred Seven",
        "Chak Two Hundred Two",
        "Salatke"
    ],
    "wof:name":"Chak Two Hundred Two",
    "wof:placetype":"locality"
},
  "geometry": {"coordinates":[72.76571,31.37953],"type":"Point"}
}