{
  "type": "Feature",
  "properties": {
    "gn:admin1_code":"2",
    "gn:asciiname":"Basti Haji Rehmatan",
    "gn:country_code":"PK",
    "gn:dem":1189,
    "gn:feature_class":"P",
    "gn:feature_code":"PPL",
    "gn:name":"Basti Haji Rehmatan",
    "gn:population":0,
    "gn:timezone":"Asia/Karachi",
    "iso:country":"PK",
    "name:und_x_variant":[
        "Basti Shaikh"
    ],
    "wof:name":"Basti Haji Rehmatan",
    "wof:placetype":"locality"
},
  "geometry": {"coordinates":[69.79031999999999,29.96434],"type":"Point"}
}