{
  "type": "Feature",
  "properties": {
    "gn:admin1_code":"4",
    "gn:asciiname":"Basti Ropri",
    "gn:country_code":"PK",
    "gn:dem":226,
    "gn:feature_class":"P",
    "gn:feature_code":"PPL",
    "gn:name":"Basti Ropri",
    "gn:population":0,
    "gn:timezone":"Asia/Karachi",
    "iso:country":"PK",
    "name:eng_x_preferred":[
        "Basti Ahmad"
    ],
    "name:und_x_variant":[
        "Basti Umr\u0101ni"
    ],
    "wof:name":"Basti Ropri",
    "wof:placetype":"locality"
},
  "geometry": {"coordinates":[70.35668000000001,29.94596],"type":"Point"}
}