{
  "type": "Feature",
  "properties": {
    "gn:admin1_code":"4.0",
    "gn:asciiname":"Dhar da Kulyan",
    "gn:country_code":"PK",
    "gn:dem":327,
    "gn:feature_class":"P",
    "gn:feature_code":"PPL",
    "gn:name":"Dhar da Kulyan",
    "gn:population":0,
    "gn:timezone":"Asia/Kolkata",
    "iso:country":"PK",
    "wof:name":"Dhar da Kulyan",
    "wof:placetype":"locality"
},
  "geometry": {"coordinates":[75.10630999999999,32.47312],"type":"Point"}
}