{
  "type": "Feature",
  "properties": {
    "gn:admin1_code":"2.0",
    "gn:asciiname":"Bangi Karez",
    "gn:country_code":"PK",
    "gn:dem":1661,
    "gn:feature_class":"P",
    "gn:feature_code":"PPL",
    "gn:name":"Bangi Karez",
    "gn:population":0,
    "gn:timezone":"Asia/Karachi",
    "iso:country":"PK",
    "wof:name":"Bangi Karez",
    "wof:placetype":"locality"
},
  "geometry": {"coordinates":[66.81905999999999,29.77459],"type":"Point"}
}