{
  "type": "Feature",
  "properties": {
    "gn:admin1_code":"4",
    "gn:asciiname":"Chak Five Hundred Sixty-seven",
    "gn:country_code":"PK",
    "gn:dem":191,
    "gn:feature_class":"P",
    "gn:feature_code":"PPL",
    "gn:name":"Chak Five Hundred Sixty-seven",
    "gn:population":0,
    "gn:timezone":"Asia/Karachi",
    "iso:country":"PK",
    "name:und_x_variant":[
        "Abb\u0101si",
        "B\u0101si"
    ],
    "wof:name":"Chak Five Hundred Sixty-seven",
    "wof:placetype":"locality"
},
  "geometry": {"coordinates":[73.61910999999998,31.35704],"type":"Point"}
}