{
  "type": "Feature",
  "properties": {
    "gn:admin1_code":"2.0",
    "gn:asciiname":"Safray",
    "gn:country_code":"PK",
    "gn:dem":1899,
    "gn:feature_class":"P",
    "gn:feature_code":"PPL",
    "gn:name":"Safray",
    "gn:population":0,
    "gn:timezone":"Asia/Karachi",
    "iso:country":"PK",
    "wof:name":"Safray",
    "wof:placetype":"locality"
},
  "geometry": {"coordinates":[68.62794,31.1248],"type":"Point"}
}