{
  "type": "Feature",
  "properties": {
    "gn:admin1_code":"04",
    "gn:asciiname":"Piara",
    "gn:country_code":"PK",
    "gn:dem":203,
    "gn:feature_class":"P",
    "gn:feature_code":"PPL",
    "gn:name":"Piara",
    "gn:population":0,
    "gn:timezone":"Asia/Karachi",
    "iso:country":"PK",
    "wof:name":"Piara",
    "wof:placetype":"locality"
},
  "geometry": {"coordinates":[74.06245,31.54563],"type":"Point"}
}