{
  "type": "Feature",
  "properties": {
    "gn:admin1_code":"3",
    "gn:asciiname":"Naura",
    "gn:country_code":"PK",
    "gn:dem":1371,
    "gn:feature_class":"P",
    "gn:feature_code":"PPL",
    "gn:name":"Naura",
    "gn:population":0,
    "gn:timezone":"Asia/Karachi",
    "iso:country":"PK",
    "name:deu_x_preferred":[
        "Naura"
    ],
    "name:eng_x_preferred":[
        "Naura"
    ],
    "wof:name":"Naura",
    "wof:placetype":"locality"
},
  "geometry": {"coordinates":[71.79930999999998,35.11749],"type":"Point"}
}