{
  "type": "Feature",
  "properties": {
    "gn:admin1_code":"2.0",
    "gn:asciiname":"Wali Dad Chah",
    "gn:country_code":"PK",
    "gn:dem":836,
    "gn:feature_class":"P",
    "gn:feature_code":"PPL",
    "gn:name":"Wali Dad Chah",
    "gn:population":0,
    "gn:timezone":"Asia/Karachi",
    "iso:country":"PK",
    "name:und_x_variant":[
        "Mirbor"
    ],
    "wof:name":"Wali Dad Chah",
    "wof:placetype":"locality"
},
  "geometry": {"coordinates":[64.31444999999999,28.82853],"type":"Point"}
}