{
  "type": "Feature",
  "properties": {
    "gn:admin1_code":"05",
    "gn:asciiname":"Bhit",
    "gn:country_code":"PK",
    "gn:dem":168,
    "gn:feature_class":"P",
    "gn:feature_code":"PPL",
    "gn:name":"Bhit",
    "gn:population":0,
    "gn:timezone":"Asia/Karachi",
    "iso:country":"PK",
    "name:ceb_x_preferred":[
        "Bhit"
    ],
    "name:fra_x_preferred":[
        "Bhit Shah"
    ],
    "name:snd_x_preferred":[
        "\u0680\u067d \u0634\u0627\u06be"
    ],
    "name:urd_x_preferred":[
        "\u0628\u06be\u0679 \u0634\u0627\u06c1"
    ],
    "wof:name":"Bhit",
    "wof:placetype":"locality"
},
  "geometry": {"coordinates":[67.75962,25.29543],"type":"Point"}
}