{
  "type": "Feature",
  "properties": {
    "gn:admin1_code":"03",
    "gn:asciiname":"Kuladano Sha",
    "gn:country_code":"PK",
    "gn:dem":1139,
    "gn:feature_class":"P",
    "gn:feature_code":"PPL",
    "gn:name":"Kuladano Sha",
    "gn:population":0,
    "gn:timezone":"Asia/Karachi",
    "iso:country":"PK",
    "wof:name":"Kuladano Sha",
    "wof:placetype":"locality"
},
  "geometry": {"coordinates":[71.78631999999998,34.96188],"type":"Point"}
}