{
  "type": "Feature",
  "properties": {
    "gn:admin1_code":"6",
    "gn:asciiname":"Fagir-e-Banar",
    "gn:country_code":"PK",
    "gn:dem":2789,
    "gn:feature_class":"P",
    "gn:feature_code":"PPL",
    "gn:name":"Fagir-e-Banar",
    "gn:population":0,
    "gn:timezone":"Asia/Karachi",
    "iso:country":"PK",
    "name:und_x_variant":[
        "Zargar Pari Baihk",
        "Fagir-e-Banar"
    ],
    "wof:name":"Fagir-e-Banar",
    "wof:placetype":"locality"
},
  "geometry": {"coordinates":[74.60556,34.82639],"type":"Point"}
}