{
  "type": "Feature",
  "properties": {
    "gn:admin1_code":"5.0",
    "gn:asciiname":"Goth Shahnawaz Marri",
    "gn:country_code":"PK",
    "gn:dem":39,
    "gn:feature_class":"P",
    "gn:feature_code":"PPL",
    "gn:name":"Goth Shahnawaz Marri",
    "gn:population":0,
    "gn:timezone":"Asia/Karachi",
    "iso:country":"PK",
    "name:und_x_variant":[
        "Goth M\u012br Hasan Marri"
    ],
    "wof:name":"Goth Shahnawaz Marri",
    "wof:placetype":"locality"
},
  "geometry": {"coordinates":[68.27934,26.54112000000001],"type":"Point"}
}