{
  "type": "Feature",
  "properties": {
    "gn:admin1_code":"4",
    "gn:asciiname":"Chachowal",
    "gn:country_code":"PK",
    "gn:dem":305,
    "gn:feature_class":"P",
    "gn:feature_code":"PPL",
    "gn:name":"Chachowal",
    "gn:population":0,
    "gn:timezone":"Asia/Karachi",
    "iso:country":"PK",
    "name:pan_x_preferred":[
        "\u0a1a\u0a3e\u0a1a\u0a4b\u0a35\u0a3e\u0a32"
    ],
    "name:und_x_variant":[
        "Ch\u0101ohow\u0101"
    ],
    "wof:name":"Chachowal",
    "wof:placetype":"locality"
},
  "geometry": {"coordinates":[74.17775999999998,32.82767],"type":"Point"}
}