{
  "type": "Feature",
  "properties": {
    "gn:admin1_code":"4",
    "gn:asciiname":"Awan da Jhangar",
    "gn:country_code":"PK",
    "gn:dem":185,
    "gn:feature_class":"P",
    "gn:feature_code":"PPL",
    "gn:name":"Awan da Jhangar",
    "gn:population":0,
    "gn:timezone":"Asia/Karachi",
    "iso:country":"PK",
    "name:und_x_variant":[
        "Jhangar"
    ],
    "wof:name":"Awan da Jhangar",
    "wof:placetype":"locality"
},
  "geometry": {"coordinates":[73.51894,31.215],"type":"Point"}
}