{
  "type": "Feature",
  "properties": {
    "gn:admin1_code":"4",
    "gn:asciiname":"Nurwahi",
    "gn:country_code":"PK",
    "gn:dem":109,
    "gn:feature_class":"P",
    "gn:feature_code":"PPL",
    "gn:name":"Nurwahi",
    "gn:population":0,
    "gn:timezone":"Asia/Karachi",
    "iso:country":"PK",
    "wof:name":"Nurwahi",
    "wof:placetype":"locality"
},
  "geometry": {"coordinates":[70.68789,29.75334],"type":"Point"}
}