{
  "type": "Feature",
  "properties": {
    "gn:admin1_code":"3.0",
    "gn:asciiname":"Banda Bozha",
    "gn:country_code":"PK",
    "gn:dem":502,
    "gn:feature_class":"P",
    "gn:feature_code":"PPL",
    "gn:name":"Banda Bozha",
    "gn:population":0,
    "gn:timezone":"Asia/Karachi",
    "iso:country":"PK",
    "wof:name":"Banda Bozha",
    "wof:placetype":"locality"
},
  "geometry": {"coordinates":[71.34124,33.30328],"type":"Point"}
}