{
  "type": "Feature",
  "properties": {
    "gn:admin1_code":"6.0",
    "gn:asciiname":"Bhatea",
    "gn:country_code":"PK",
    "gn:dem":960,
    "gn:feature_class":"P",
    "gn:feature_code":"PPL",
    "gn:name":"Bhatea",
    "gn:population":0,
    "gn:timezone":"Asia/Karachi",
    "iso:country":"PK",
    "wof:name":"Bhatea",
    "wof:placetype":"locality"
},
  "geometry": {"coordinates":[73.62209,33.74075999999999],"type":"Point"}
}