{
  "type": "Feature",
  "properties": {
    "gn:admin1_code":"2.0",
    "gn:asciiname":"Kili Haji Lal Bakhsh",
    "gn:country_code":"PK",
    "gn:dem":1811,
    "gn:feature_class":"P",
    "gn:feature_code":"PPL",
    "gn:name":"Kili Haji Lal Bakhsh",
    "gn:population":0,
    "gn:timezone":"Asia/Karachi",
    "iso:country":"PK",
    "wof:name":"Kili Haji Lal Bakhsh",
    "wof:placetype":"locality"
},
  "geometry": {"coordinates":[66.16457,28.56761],"type":"Point"}
}