{
  "type": "Feature",
  "properties": {
    "gn:admin1_code":"5.0",
    "gn:asciiname":"Bhilian Jo Moqam",
    "gn:country_code":"PK",
    "gn:dem":41,
    "gn:feature_class":"P",
    "gn:feature_code":"PPL",
    "gn:name":"Bhilian Jo Moqam",
    "gn:population":0,
    "gn:timezone":"Asia/Karachi",
    "iso:country":"PK",
    "wof:name":"Bhilian Jo Moqam",
    "wof:placetype":"locality"
},
  "geometry": {"coordinates":[69.81163000000001,25.86016],"type":"Point"}
}