{
  "type": "Feature",
  "properties": {
    "gn:admin1_code":"4",
    "gn:asciiname":"Chaudhri",
    "gn:country_code":"PK",
    "gn:dem":131,
    "gn:feature_class":"P",
    "gn:feature_code":"PPL",
    "gn:name":"Chaudhri",
    "gn:population":0,
    "gn:timezone":"Asia/Karachi",
    "iso:country":"PK",
    "name:eng_x_preferred":[
        "Chaudhri"
    ],
    "wof:name":"Chaudhri",
    "wof:placetype":"locality"
},
  "geometry": {"coordinates":[70.91145999999998,30.46692],"type":"Point"}
}