{
  "type": "Feature",
  "properties": {
    "gn:admin1_code":"4",
    "gn:asciiname":"Chhanni Bawara",
    "gn:country_code":"PK",
    "gn:dem":201,
    "gn:feature_class":"P",
    "gn:feature_code":"PPL",
    "gn:name":"Chhanni Bawara",
    "gn:population":0,
    "gn:timezone":"Asia/Karachi",
    "iso:country":"PK",
    "name:und_x_variant":[
        "Channi B\u0101wara",
        "Chiniot",
        "Chhanni Bawara"
    ],
    "wof:name":"Chhanni Bawara",
    "wof:placetype":"locality"
},
  "geometry": {"coordinates":[73.48095000000001,32.10172],"type":"Point"}
}