{
  "type": "Feature",
  "properties": {
    "gn:admin1_code":"3.0",
    "gn:asciiname":"Lowarai Kalle",
    "gn:country_code":"PK",
    "gn:dem":2091,
    "gn:feature_class":"P",
    "gn:feature_code":"PPL",
    "gn:name":"Lowarai Kalle",
    "gn:population":0,
    "gn:timezone":"Asia/Karachi",
    "iso:country":"PK",
    "wof:name":"Lowarai Kalle",
    "wof:placetype":"locality"
},
  "geometry": {"coordinates":[71.80726999999997,35.24033],"type":"Point"}
}