{
  "type": "Feature",
  "properties": {
    "gn:admin1_code":"2.0",
    "gn:asciiname":"Muhammad Harun",
    "gn:country_code":"PK",
    "gn:dem":856,
    "gn:feature_class":"P",
    "gn:feature_code":"PPL",
    "gn:name":"Muhammad Harun",
    "gn:population":0,
    "gn:timezone":"Asia/Karachi",
    "iso:country":"PK",
    "wof:name":"Muhammad Harun",
    "wof:placetype":"locality"
},
  "geometry": {"coordinates":[66.70905999999999,26.40786],"type":"Point"}
}