{
  "type": "Feature",
  "properties": {
    "gn:admin1_code":"3.0",
    "gn:asciiname":"Miangan Kili",
    "gn:country_code":"PK",
    "gn:dem":299,
    "gn:feature_class":"P",
    "gn:feature_code":"PPL",
    "gn:name":"Mi\u0101ng\u0101n Kili",
    "gn:population":0,
    "gn:timezone":"Asia/Karachi",
    "iso:country":"PK",
    "name:eng_x_preferred":[
        "Mi\u0101ng\u0101n Kili"
    ],
    "wof:name":"Miangan Kili",
    "wof:placetype":"locality"
},
  "geometry": {"coordinates":[71.96889,34.13694],"type":"Point"}
}