{
  "type": "Feature",
  "properties": {
    "gn:admin1_code":"5.0",
    "gn:asciiname":"Ilyas Panhwar",
    "gn:country_code":"PK",
    "gn:dem":47,
    "gn:feature_class":"P",
    "gn:feature_code":"PPL",
    "gn:name":"Ilyas Panhwar",
    "gn:population":0,
    "gn:timezone":"Asia/Karachi",
    "iso:country":"PK",
    "name:und_x_variant":[
        "Illy\u0101s Penhw\u0101r"
    ],
    "wof:name":"Ilyas Panhwar",
    "wof:placetype":"locality"
},
  "geometry": {"coordinates":[67.89575000000001,27.77928],"type":"Point"}
}