{
  "type": "Feature",
  "properties": {
    "gn:admin1_code":"1",
    "gn:asciiname":"Ghazikai",
    "gn:country_code":"PK",
    "gn:dem":2417,
    "gn:feature_class":"P",
    "gn:feature_code":"PPL",
    "gn:name":"Ghazikai",
    "gn:population":0,
    "gn:timezone":"Asia/Karachi",
    "iso:country":"PK",
    "wof:name":"Ghazikai",
    "wof:placetype":"locality"
},
  "geometry": {"coordinates":[69.76678000000001,32.72142],"type":"Point"}
}