{
  "type": "Feature",
  "properties": {
    "gn:admin1_code":"3",
    "gn:asciiname":"Dilasa Kalle",
    "gn:country_code":"PK",
    "gn:dem":390,
    "gn:feature_class":"P",
    "gn:feature_code":"PPL",
    "gn:name":"Dilasa Kalle",
    "gn:population":0,
    "gn:timezone":"Asia/Karachi",
    "iso:country":"PK",
    "name:und_x_variant":[
        "Dilasa Kili"
    ],
    "wof:name":"Dilasa Kalle",
    "wof:placetype":"locality"
},
  "geometry": {"coordinates":[70.90129,33.03705],"type":"Point"}
}