{
  "type": "Feature",
  "properties": {
    "gn:admin1_code":"3.0",
    "gn:asciiname":"Shal",
    "gn:country_code":"PK",
    "gn:dem":978,
    "gn:feature_class":"P",
    "gn:feature_code":"PPL",
    "gn:name":"Shal",
    "gn:population":0,
    "gn:timezone":"Asia/Karachi",
    "iso:country":"PK",
    "wof:name":"Shal",
    "wof:placetype":"locality"
},
  "geometry": {"coordinates":[73.22751,35.28374],"type":"Point"}
}