{
  "type": "Feature",
  "properties": {
    "gn:admin1_code":"5",
    "gn:asciiname":"Gul Hasan Khabar",
    "gn:country_code":"PK",
    "gn:dem":52,
    "gn:feature_class":"P",
    "gn:feature_code":"PPL",
    "gn:name":"Gul Hasan Khabar",
    "gn:population":0,
    "gn:timezone":"Asia/Karachi",
    "iso:country":"PK",
    "name:und_x_variant":[
        "Maka Khabar"
    ],
    "wof:name":"Gul Hasan Khabar",
    "wof:placetype":"locality"
},
  "geometry": {"coordinates":[68.55286,27.1473],"type":"Point"}
}