{
  "type": "Feature",
  "properties": {
    "iso:country":"PK",
    "name:ara_x_preferred":[
        "\u0645\u0646\u0637\u0642\u0629 \u062f\u064a\u0631"
    ],
    "name:cat_x_preferred":[
        "Dir"
    ],
    "name:eng_x_preferred":[
        "D\u012br"
    ],
    "name:eng_x_variant":[
        "Dir"
    ],
    "name:fas_x_preferred":[
        "\u062f\u06cc\u0631"
    ],
    "name:fra_x_preferred":[
        "Dir"
    ],
    "name:ita_x_preferred":[
        "Dir"
    ],
    "name:jpn_x_preferred":[
        "\u30c7\u30a3\u30fc\u30eb"
    ],
    "name:msa_x_preferred":[
        "Dir"
    ],
    "name:nld_x_preferred":[
        "Dir"
    ],
    "name:pol_x_preferred":[
        "Dir"
    ],
    "name:rus_x_preferred":[
        "\u0414\u0438\u0440"
    ],
    "name:swe_x_preferred":[
        "Dir"
    ],
    "name:und_x_variant":[
        "Upper Dir"
    ],
    "name:urd_x_preferred":[
        "\u062f\u06cc\u0631"
    ],
    "qs:gn_country":"PK",
    "qs:gn_fcode":"PPLA2",
    "qs:gn_pop":29869,
    "qs:name":"Dir",
    "qs:name_adm0":"Pakistan",
    "qs:name_adm1":"North-West Frontier",
    "qs:photos":0,
    "qs:photos_1k":0,
    "qs:photos_9k":1,
    "qs:photos_9r":1,
    "qs:photos_all":13,
    "qs:photos_sr":0,
    "qs:placetype":"Town",
    "qs:pop_sr":"7",
    "qs:woe_adm0":23424922,
    "wof:name":"Dir",
    "wof:placetype":"locality",
    "wof:population":29869
},
  "geometry": {"coordinates":[71.87555999999999,35.20583],"type":"Point"}
}