{
  "type": "Feature",
  "properties": {
    "gn:admin1_code":"3.0",
    "gn:asciiname":"Machhral",
    "gn:country_code":"PK",
    "gn:dem":500,
    "gn:feature_class":"P",
    "gn:feature_code":"PPL",
    "gn:name":"Machhral",
    "gn:population":0,
    "gn:timezone":"Asia/Karachi",
    "iso:country":"PK",
    "wof:name":"Machhral",
    "wof:placetype":"locality"
},
  "geometry": {"coordinates":[72.8678,34.36284000000001],"type":"Point"}
}