{
  "type": "Feature",
  "properties": {
    "gn:admin1_code":"5.0",
    "gn:asciiname":"Usman Hathiar",
    "gn:country_code":"PK",
    "gn:dem":9,
    "gn:feature_class":"P",
    "gn:feature_code":"PPL",
    "gn:name":"Usman Hathiar",
    "gn:population":0,
    "gn:timezone":"Asia/Karachi",
    "iso:country":"PK",
    "name:eng_x_preferred":[
        "Usman Hathiar"
    ],
    "wof:name":"Usman Hathiar",
    "wof:placetype":"locality"
},
  "geometry": {"coordinates":[68.12061,24.58178],"type":"Point"}
}