{
  "type": "Feature",
  "properties": {
    "gn:admin1_code":"6",
    "gn:asciiname":"Chhakarian",
    "gn:country_code":"PK",
    "gn:dem":1840,
    "gn:feature_class":"P",
    "gn:feature_code":"PPL",
    "gn:name":"Chhakarian",
    "gn:population":0,
    "gn:timezone":"Asia/Karachi",
    "iso:country":"PK",
    "name:und_x_variant":[
        "Chhakri\u0101n"
    ],
    "wof:name":"Chhakarian",
    "wof:placetype":"locality"
},
  "geometry": {"coordinates":[73.59577,34.51933],"type":"Point"}
}