{
  "type": "Feature",
  "properties": {
    "gn:admin1_code":"4",
    "gn:asciiname":"Rojewala",
    "gn:country_code":"PK",
    "gn:dem":125,
    "gn:feature_class":"P",
    "gn:feature_code":"PPL",
    "gn:name":"Rojewala",
    "gn:population":0,
    "gn:timezone":"Asia/Karachi",
    "iso:country":"PK",
    "name:eng_x_preferred":[
        "Rauzew\u0101la"
    ],
    "wof:name":"Rojewala",
    "wof:placetype":"locality"
},
  "geometry": {"coordinates":[70.95031999999998,30.27115],"type":"Point"}
}