{
  "type": "Feature",
  "properties": {
    "gn:admin1_code":"6.0",
    "gn:asciiname":"Islam Pura",
    "gn:country_code":"PK",
    "gn:dem":1138,
    "gn:feature_class":"P",
    "gn:feature_code":"PPL",
    "gn:name":"Islam Pura",
    "gn:population":0,
    "gn:timezone":"Asia/Karachi",
    "iso:country":"PK",
    "wof:name":"Islam Pura",
    "wof:placetype":"locality"
},
  "geometry": {"coordinates":[73.67884000000002,33.67463],"type":"Point"}
}