{
  "type": "Feature",
  "properties": {
    "gn:admin1_code":"4",
    "gn:asciiname":"Chah Kharola",
    "gn:country_code":"PK",
    "gn:dem":153,
    "gn:feature_class":"P",
    "gn:feature_code":"PPL",
    "gn:name":"Chah Kharola",
    "gn:population":0,
    "gn:timezone":"Asia/Karachi",
    "iso:country":"PK",
    "name:und_x_variant":[
        "Jhok G\u0101man Kasr\u0101niw\u0101li",
        "Jhok G\u0101man Qaisr\u0101niw\u0101li",
        "Chah Kharola"
    ],
    "wof:name":"Chah Kharola",
    "wof:placetype":"locality"
},
  "geometry": {"coordinates":[70.72274,31.04055],"type":"Point"}
}