{
  "type": "Feature",
  "properties": {
    "gn:admin1_code":"4",
    "gn:asciiname":"Mir Khar",
    "gn:country_code":"PK",
    "gn:dem":143,
    "gn:feature_class":"P",
    "gn:feature_code":"PPL",
    "gn:name":"Mir Khar",
    "gn:population":0,
    "gn:timezone":"Asia/Karachi",
    "iso:country":"PK",
    "name:und_x_variant":[
        "M\u012br Khar"
    ],
    "wof:name":"Mir Khar",
    "wof:placetype":"locality"
},
  "geometry": {"coordinates":[70.73532,30.85182],"type":"Point"}
}