{
  "type": "Feature",
  "properties": {
    "gn:admin1_code":"3.0",
    "gn:asciiname":"Ghazi Baba",
    "gn:country_code":"PK",
    "gn:dem":517,
    "gn:feature_class":"P",
    "gn:feature_code":"PPL",
    "gn:name":"Ghazi Baba",
    "gn:population":0,
    "gn:timezone":"Asia/Karachi",
    "iso:country":"PK",
    "name:eng_x_preferred":[
        "Ghazi Baba"
    ],
    "wof:name":"Ghazi Baba",
    "wof:placetype":"locality"
},
  "geometry": {"coordinates":[72.49446,34.28475],"type":"Point"}
}