{
  "type": "Feature",
  "properties": {
    "gn:admin1_code":"3",
    "gn:asciiname":"Kattawaz Kalle",
    "gn:country_code":"PK",
    "gn:dem":369,
    "gn:feature_class":"P",
    "gn:feature_code":"PPL",
    "gn:name":"Kattawaz Kalle",
    "gn:population":0,
    "gn:timezone":"Asia/Karachi",
    "iso:country":"PK",
    "name:und_x_variant":[
        "Kataw\u0101z Kili"
    ],
    "wof:name":"Kattawaz Kalle",
    "wof:placetype":"locality"
},
  "geometry": {"coordinates":[70.81041999999999,33.02945],"type":"Point"}
}