{
  "type": "Feature",
  "properties": {
    "gn:admin1_code":"4",
    "gn:asciiname":"Arewala",
    "gn:country_code":"PK",
    "gn:dem":130,
    "gn:feature_class":"P",
    "gn:feature_code":"PPL",
    "gn:name":"Arewala",
    "gn:population":0,
    "gn:timezone":"Asia/Karachi",
    "iso:country":"PK",
    "name:und_x_variant":[
        "\u0100row\u0101la"
    ],
    "wof:name":"Arewala",
    "wof:placetype":"locality"
},
  "geometry": {"coordinates":[71.79349000000001,30.28479],"type":"Point"}
}