{
  "type": "Feature",
  "properties": {
    "gn:admin1_code":"2.0",
    "gn:asciiname":"Kamal Khan",
    "gn:country_code":"PK",
    "gn:dem":1383,
    "gn:feature_class":"P",
    "gn:feature_code":"PPL",
    "gn:name":"Kamal Khan",
    "gn:population":0,
    "gn:timezone":"Asia/Karachi",
    "iso:country":"PK",
    "wof:name":"Kamal Khan",
    "wof:placetype":"locality"
},
  "geometry": {"coordinates":[66.52978,27.98182000000001],"type":"Point"}
}