{
  "type": "Feature",
  "properties": {
    "gn:admin1_code":"4",
    "gn:asciiname":"Basti Koro Shah",
    "gn:country_code":"PK",
    "gn:dem":163,
    "gn:feature_class":"P",
    "gn:feature_code":"PPL",
    "gn:name":"Basti Koro Shah",
    "gn:population":0,
    "gn:timezone":"Asia/Karachi",
    "iso:country":"PK",
    "wof:name":"Basti Koro Shah",
    "wof:placetype":"locality"
},
  "geometry": {"coordinates":[70.9507,31.50953],"type":"Point"}
}