{
  "type": "Feature",
  "properties": {
    "gn:admin1_code":"5",
    "gn:asciiname":"Kang Pir",
    "gn:country_code":"PK",
    "gn:dem":13,
    "gn:feature_class":"P",
    "gn:feature_code":"PPL",
    "gn:name":"Kang Pir",
    "gn:population":0,
    "gn:timezone":"Asia/Karachi",
    "iso:country":"PK",
    "name:und_x_variant":[
        "Kangper"
    ],
    "wof:name":"Kang Pir",
    "wof:placetype":"locality"
},
  "geometry": {"coordinates":[69.07281999999999,24.91897],"type":"Point"}
}