{
  "type": "Feature",
  "properties": {
    "gn:admin1_code":"4.0",
    "gn:asciiname":"Chak Three Hundred Thirty-seven",
    "gn:country_code":"PK",
    "gn:dem":160,
    "gn:feature_class":"P",
    "gn:feature_code":"PPL",
    "gn:name":"Chak Three Hundred Thirty-seven",
    "gn:population":0,
    "gn:timezone":"Asia/Karachi",
    "iso:country":"PK",
    "name:und_x_variant":[
        "Dholan"
    ],
    "wof:name":"Chak Three Hundred Thirty-seven",
    "wof:placetype":"locality"
},
  "geometry": {"coordinates":[72.50494999999999,30.89353],"type":"Point"}
}