{
  "type": "Feature",
  "properties": {
    "gn:admin1_code":"4.0",
    "gn:asciiname":"Chahiwali",
    "gn:country_code":"PK",
    "gn:dem":244,
    "gn:feature_class":"P",
    "gn:feature_code":"PPL",
    "gn:name":"Chahiwali",
    "gn:population":0,
    "gn:timezone":"Asia/Karachi",
    "iso:country":"PK",
    "name:und_x_variant":[
        "Chaewali",
        "Chahiwali"
    ],
    "wof:name":"Chahiwali",
    "wof:placetype":"locality"
},
  "geometry": {"coordinates":[74.69904,32.27938],"type":"Point"}
}