{
  "type": "Feature",
  "properties": {
    "gn:admin1_code":"2.0",
    "gn:asciiname":"Goth Damb",
    "gn:country_code":"PK",
    "gn:dem":4,
    "gn:feature_class":"P",
    "gn:feature_code":"PPL",
    "gn:name":"Goth Damb",
    "gn:population":0,
    "gn:timezone":"Asia/Karachi",
    "iso:country":"PK",
    "name:eng_x_preferred":[
        "D\u0101mb"
    ],
    "name:und_x_variant":[
        "Dam",
        "Kutto Damb",
        "D\u0101mbh",
        "Goth Damb"
    ],
    "wof:name":"Goth Damb",
    "wof:placetype":"locality"
},
  "geometry": {"coordinates":[66.56929000000001,25.44951],"type":"Point"}
}