{
  "type": "Feature",
  "properties": {
    "gn:admin1_code":"4",
    "gn:asciiname":"Tamachiwala",
    "gn:country_code":"PK",
    "gn:dem":125,
    "gn:feature_class":"P",
    "gn:feature_code":"PPL",
    "gn:name":"Tamachiwala",
    "gn:population":0,
    "gn:timezone":"Asia/Karachi",
    "iso:country":"PK",
    "name:und_x_variant":[
        "Tam\u0101chew\u0101la",
        "Tamachiwala"
    ],
    "wof:name":"Tamachiwala",
    "wof:placetype":"locality"
},
  "geometry": {"coordinates":[70.72856999999998,30.20433],"type":"Point"}
}