{
  "type": "Feature",
  "properties": {
    "gn:admin1_code":"3.0",
    "gn:asciiname":"Kandao",
    "gn:country_code":"PK",
    "gn:dem":845,
    "gn:feature_class":"P",
    "gn:feature_code":"PPL",
    "gn:name":"Kandao",
    "gn:population":0,
    "gn:timezone":"Asia/Karachi",
    "iso:country":"PK",
    "wof:name":"Kandao",
    "wof:placetype":"locality"
},
  "geometry": {"coordinates":[71.39740999999999,33.16981],"type":"Point"}
}