{
  "type": "Feature",
  "properties": {
    "gn:admin1_code":"3.0",
    "gn:asciiname":"Sardar Koruna",
    "gn:country_code":"PK",
    "gn:dem":378,
    "gn:feature_class":"P",
    "gn:feature_code":"PPL",
    "gn:name":"Sardar Koruna",
    "gn:population":0,
    "gn:timezone":"Asia/Karachi",
    "iso:country":"PK",
    "wof:name":"Sardar Koruna",
    "wof:placetype":"locality"
},
  "geometry": {"coordinates":[71.75246,34.32018],"type":"Point"}
}