{
  "type": "Feature",
  "properties": {
    "gn:admin1_code":"4.0",
    "gn:asciiname":"Fathwala",
    "gn:country_code":"PK",
    "gn:dem":109,
    "gn:feature_class":"P",
    "gn:feature_code":"PPL",
    "gn:name":"Fathwala",
    "gn:population":0,
    "gn:timezone":"Asia/Karachi",
    "iso:country":"PK",
    "name:und_x_variant":[
        "Fatehpur"
    ],
    "wof:name":"Fathwala",
    "wof:placetype":"locality"
},
  "geometry": {"coordinates":[71.30643000000001,29.43893],"type":"Point"}
}