{
  "type": "Feature",
  "properties": {
    "gn:admin1_code":"3",
    "gn:asciiname":"Daulat Kalle",
    "gn:country_code":"PK",
    "gn:dem":1804,
    "gn:feature_class":"P",
    "gn:feature_code":"PPL",
    "gn:name":"Daulat Kalle",
    "gn:population":0,
    "gn:timezone":"Asia/Karachi",
    "iso:country":"PK",
    "name:und_x_variant":[
        "Daulat Kili",
        "Daulat Kalle"
    ],
    "wof:name":"Daulat Kalle",
    "wof:placetype":"locality"
},
  "geometry": {"coordinates":[72.67409000000001,34.886],"type":"Point"}
}