{
  "type": "Feature",
  "properties": {
    "gn:admin1_code":"5",
    "gn:asciiname":"Piyaro Sakhani",
    "gn:country_code":"PK",
    "gn:dem":53,
    "gn:feature_class":"P",
    "gn:feature_code":"PPL",
    "gn:name":"Piyaro Sakhani",
    "gn:population":0,
    "gn:timezone":"Asia/Karachi",
    "iso:country":"PK",
    "name:und_x_variant":[
        "Sakh\u0101ni Baloch"
    ],
    "wof:name":"Piyaro Sakhani",
    "wof:placetype":"locality"
},
  "geometry": {"coordinates":[68.61373,27.19424],"type":"Point"}
}