{
  "type": "Feature",
  "properties": {
    "gn:admin1_code":"4.0",
    "gn:asciiname":"Chak One Hundred Five Gugera Branch",
    "gn:country_code":"PK",
    "gn:dem":190,
    "gn:feature_class":"P",
    "gn:feature_code":"PPL",
    "gn:name":"Chak One Hundred Five Gugera Branch",
    "gn:population":0,
    "gn:timezone":"Asia/Karachi",
    "iso:country":"PK",
    "name:und_x_variant":[
        "Bange Nan",
        "Banga",
        "Chak One Hundred Five Gugera Branch",
        "Wanga"
    ],
    "wof:name":"Chak One Hundred Five Gugera Branch",
    "wof:placetype":"locality"
},
  "geometry": {"coordinates":[73.29734000000001,31.40311],"type":"Point"}
}