{
  "type": "Feature",
  "properties": {
    "gn:admin1_code":"1.0",
    "gn:asciiname":"Sur Chakhai",
    "gn:country_code":"PK",
    "gn:dem":1289,
    "gn:feature_class":"P",
    "gn:feature_code":"PPL",
    "gn:name":"Sur Chakhai",
    "gn:population":0,
    "gn:timezone":"Asia/Karachi",
    "iso:country":"PK",
    "wof:name":"Sur Chakhai",
    "wof:placetype":"locality"
},
  "geometry": {"coordinates":[71.02603000000001,33.66393],"type":"Point"}
}