{
  "type": "Feature",
  "properties": {
    "gn:admin1_code":"4",
    "gn:asciiname":"Mansar",
    "gn:country_code":"PK",
    "gn:dem":186,
    "gn:feature_class":"P",
    "gn:feature_code":"PPL",
    "gn:name":"M\u0101nsar",
    "gn:population":0,
    "gn:timezone":"Asia/Karachi",
    "iso:country":"PK",
    "name:ceb_x_preferred":[
        "Mansar"
    ],
    "name:swe_x_preferred":[
        "Mansar"
    ],
    "wof:name":"Mansar",
    "wof:placetype":"locality"
},
  "geometry": {"coordinates":[73.59860999999999,30.91667],"type":"Point"}
}