{
  "type": "Feature",
  "properties": {
    "gn:admin1_code":"5",
    "gn:asciiname":"Goth Arz Muhammad Laghari",
    "gn:country_code":"PK",
    "gn:dem":22,
    "gn:feature_class":"P",
    "gn:feature_code":"PPL",
    "gn:name":"Goth Arz Muhammad Laghari",
    "gn:population":0,
    "gn:timezone":"Asia/Karachi",
    "iso:country":"PK",
    "wof:name":"Goth Arz Muhammad Laghari",
    "wof:placetype":"locality"
},
  "geometry": {"coordinates":[68.82222,25.94583],"type":"Point"}
}