{
  "type": "Feature",
  "properties": {
    "gn:admin1_code":"2.0",
    "gn:asciiname":"Baghisar",
    "gn:country_code":"PK",
    "gn:dem":1811,
    "gn:feature_class":"P",
    "gn:feature_code":"PPL",
    "gn:name":"Baghisar",
    "gn:population":0,
    "gn:timezone":"Asia/Karachi",
    "iso:country":"PK",
    "name:und_x_variant":[
        "B\u0101ghgai"
    ],
    "wof:name":"Baghisar",
    "wof:placetype":"locality"
},
  "geometry": {"coordinates":[66.88316,30.79354],"type":"Point"}
}