{
  "type": "Feature",
  "properties": {
    "gn:admin1_code":"3.0",
    "gn:asciiname":"Nar Hafizabad",
    "gn:country_code":"PK",
    "gn:dem":309,
    "gn:feature_class":"P",
    "gn:feature_code":"PPL",
    "gn:name":"Nar Hafizabad",
    "gn:population":0,
    "gn:timezone":"Asia/Karachi",
    "iso:country":"PK",
    "name:und_x_variant":[
        "H\u0101fiz Ab\u0101d",
        "Nar Hafizabad"
    ],
    "wof:name":"Nar Hafizabad",
    "wof:placetype":"locality"
},
  "geometry": {"coordinates":[70.75471999999998,32.84595],"type":"Point"}
}