{
  "type": "Feature",
  "properties": {
    "gn:admin1_code":"3.0",
    "gn:asciiname":"Methper",
    "gn:country_code":"PK",
    "gn:dem":1549,
    "gn:feature_class":"P",
    "gn:feature_code":"PPL",
    "gn:name":"Methper",
    "gn:population":0,
    "gn:timezone":"Asia/Karachi",
    "iso:country":"PK",
    "wof:name":"Methper",
    "wof:placetype":"locality"
},
  "geometry": {"coordinates":[73.02077,34.55747],"type":"Point"}
}