{
  "type": "Feature",
  "properties": {
    "gn:admin1_code":"2",
    "gn:asciiname":"Tlerai",
    "gn:country_code":"PK",
    "gn:dem":2363,
    "gn:feature_class":"P",
    "gn:feature_code":"PPL",
    "gn:name":"Tlerai",
    "gn:population":0,
    "gn:timezone":"Asia/Karachi",
    "iso:country":"PK",
    "wof:name":"Tlerai",
    "wof:placetype":"locality"
},
  "geometry": {"coordinates":[66.84634,31.00817],"type":"Point"}
}