{
  "type": "Feature",
  "properties": {
    "gn:admin1_code":"4.0",
    "gn:asciiname":"Sadhanwali",
    "gn:country_code":"PK",
    "gn:dem":217,
    "gn:feature_class":"P",
    "gn:feature_code":"PPL",
    "gn:name":"Sadhanwali",
    "gn:population":0,
    "gn:timezone":"Asia/Karachi",
    "iso:country":"PK",
    "name:und_x_variant":[
        "S\u0101dhw\u0101li"
    ],
    "wof:name":"Sadhanwali",
    "wof:placetype":"locality"
},
  "geometry": {"coordinates":[74.57817,31.56202],"type":"Point"}
}