{
  "type": "Feature",
  "properties": {
    "gn:admin1_code":"7.0",
    "gn:asciiname":"Sili Harang",
    "gn:country_code":"PK",
    "gn:dem":2190,
    "gn:feature_class":"P",
    "gn:feature_code":"PPL",
    "gn:name":"Sili Harang",
    "gn:population":0,
    "gn:timezone":"Asia/Karachi",
    "iso:country":"PK",
    "wof:name":"Sili Harang",
    "wof:placetype":"locality"
},
  "geometry": {"coordinates":[73.40786999999997,36.25338],"type":"Point"}
}