{
  "type": "Feature",
  "properties": {
    "gn:admin1_code":"5.0",
    "gn:asciiname":"Goth Hasan",
    "gn:country_code":"PK",
    "gn:dem":14,
    "gn:feature_class":"P",
    "gn:feature_code":"PPL",
    "gn:name":"Goth Hasan",
    "gn:population":0,
    "gn:timezone":"Asia/Karachi",
    "iso:country":"PK",
    "name:und_x_variant":[
        "Goth Hasan Ali",
        "Goth Hasan"
    ],
    "wof:name":"Goth Hasan",
    "wof:placetype":"locality"
},
  "geometry": {"coordinates":[66.72749,24.83833],"type":"Point"}
}