{
  "type": "Feature",
  "properties": {
    "gn:admin1_code":"3.0",
    "gn:asciiname":"Bazar Ahmad Khan",
    "gn:country_code":"PK",
    "gn:dem":367,
    "gn:feature_class":"P",
    "gn:feature_code":"PPL",
    "gn:name":"Bazar Ahmad Khan",
    "gn:population":0,
    "gn:timezone":"Asia/Karachi",
    "iso:country":"PK",
    "name:und_x_variant":[
        "Bazaar Ahmad Khan",
        "Bazar Ahmad Khan"
    ],
    "wof:name":"Bazar Ahmad Khan",
    "wof:placetype":"locality"
},
  "geometry": {"coordinates":[70.63278000000003,32.98313],"type":"Point"}
}