{
  "type": "Feature",
  "properties": {
    "gn:admin1_code":"4",
    "gn:asciiname":"Kot Nawab",
    "gn:country_code":"PK",
    "gn:dem":196,
    "gn:feature_class":"P",
    "gn:feature_code":"PPL",
    "gn:name":"Kot Naw\u0101b",
    "gn:population":0,
    "gn:timezone":"Asia/Karachi",
    "iso:country":"PK",
    "wof:name":"Kot Nawab",
    "wof:placetype":"locality"
},
  "geometry": {"coordinates":[73.87778,31.15694],"type":"Point"}
}