{
  "type": "Feature",
  "properties": {
    "gn:admin1_code":"4",
    "gn:asciiname":"Chah Jamewala",
    "gn:country_code":"PK",
    "gn:dem":137,
    "gn:feature_class":"P",
    "gn:feature_code":"PPL",
    "gn:name":"Chah Jamewala",
    "gn:population":0,
    "gn:timezone":"Asia/Karachi",
    "iso:country":"PK",
    "name:und_x_variant":[
        "J\u0101mew\u0101la"
    ],
    "wof:name":"Chah Jamewala",
    "wof:placetype":"locality"
},
  "geometry": {"coordinates":[71.31211999999999,30.6872],"type":"Point"}
}