{
  "type": "Feature",
  "properties": {
    "gn:admin1_code":"5.0",
    "gn:asciiname":"Korija",
    "gn:country_code":"PK",
    "gn:dem":52,
    "gn:feature_class":"P",
    "gn:feature_code":"PPL",
    "gn:name":"Korija",
    "gn:population":0,
    "gn:timezone":"Asia/Karachi",
    "iso:country":"PK",
    "name:bos_x_preferred":[
        "Korija"
    ],
    "name:fra_x_preferred":[
        "Korija"
    ],
    "name:hrv_x_preferred":[
        "Korija"
    ],
    "name:hun_x_preferred":[
        "Korija"
    ],
    "name:nld_x_preferred":[
        "Korija"
    ],
    "name:slv_x_preferred":[
        "Korija"
    ],
    "name:spa_x_preferred":[
        "Korija"
    ],
    "name:srp_x_preferred":[
        "\u041a\u043e\u0440\u0438\u0458\u0430"
    ],
    "name:ukr_x_preferred":[
        "\u041a\u043e\u0440\u0456\u044f"
    ],
    "wof:name":"Korija",
    "wof:placetype":"locality"
},
  "geometry": {"coordinates":[68.03967,27.61534],"type":"Point"}
}