{
  "type": "Feature",
  "properties": {
    "gn:admin1_code":"6",
    "gn:asciiname":"Pathra",
    "gn:country_code":"PK",
    "gn:dem":2486,
    "gn:feature_class":"P",
    "gn:feature_code":"PPL",
    "gn:name":"Pathra",
    "gn:population":0,
    "gn:timezone":"Asia/Karachi",
    "iso:country":"PK",
    "wof:name":"Pathra",
    "wof:placetype":"locality"
},
  "geometry": {"coordinates":[73.83875,34.28116],"type":"Point"}
}