{
  "type": "Feature",
  "properties": {
    "gn:admin1_code":"5.0",
    "gn:asciiname":"Goth Dorabi",
    "gn:country_code":"PK",
    "gn:dem":24,
    "gn:feature_class":"P",
    "gn:feature_code":"PPL",
    "gn:name":"Goth Dorabi",
    "gn:population":0,
    "gn:timezone":"Asia/Karachi",
    "iso:country":"PK",
    "name:und_x_variant":[
        "Dr\u0101bhi"
    ],
    "wof:name":"Goth Dorabi",
    "wof:placetype":"locality"
},
  "geometry": {"coordinates":[70.63216,24.56594],"type":"Point"}
}