{
  "type": "Feature",
  "properties": {
    "gn:admin1_code":"3.0",
    "gn:asciiname":"Nur Muhammad Khan Kalle",
    "gn:country_code":"PK",
    "gn:dem":306,
    "gn:feature_class":"P",
    "gn:feature_code":"PPL",
    "gn:name":"Nur Muhammad Khan Kalle",
    "gn:population":0,
    "gn:timezone":"Asia/Karachi",
    "iso:country":"PK",
    "wof:name":"Nur Muhammad Khan Kalle",
    "wof:placetype":"locality"
},
  "geometry": {"coordinates":[71.87644,34.08709],"type":"Point"}
}