{
  "type": "Feature",
  "properties": {
    "gn:admin1_code":"4",
    "gn:asciiname":"Chak Four Hundred Sixty-six",
    "gn:country_code":"PK",
    "gn:dem":175,
    "gn:feature_class":"P",
    "gn:feature_code":"PPL",
    "gn:name":"Chak Four Hundred Sixty-six",
    "gn:population":0,
    "gn:timezone":"Asia/Karachi",
    "iso:country":"PK",
    "name:und_x_variant":[
        "Chak Four Hundred Sixty-Six Deputyw\u0101la",
        "Chak Deputy",
        "Chak Four Hundred Sixty-six",
        "Deputyw\u0101la"
    ],
    "wof:name":"Chak Four Hundred Sixty-six",
    "wof:placetype":"locality"
},
  "geometry": {"coordinates":[72.69365000000001,31.54064],"type":"Point"}
}