{
  "type": "Feature",
  "properties": {
    "gn:admin1_code":"04",
    "gn:asciiname":"Shadman",
    "gn:country_code":"PK",
    "gn:dem":212,
    "gn:feature_class":"P",
    "gn:feature_code":"PPL",
    "gn:name":"Shadman",
    "gn:population":0,
    "gn:timezone":"Asia/Karachi",
    "iso:country":"PK",
    "name:ceb_x_preferred":[
        "Shadman"
    ],
    "name:fas_x_preferred":[
        "\u0634\u0627\u062f\u0645\u0627\u0646"
    ],
    "name:swe_x_preferred":[
        "Shadman"
    ],
    "wof:name":"Shadman",
    "wof:placetype":"locality"
},
  "geometry": {"coordinates":[74.06707,31.67047],"type":"Point"}
}