{
  "type": "Feature",
  "properties": {
    "gn:admin1_code":"4",
    "gn:asciiname":"Theri",
    "gn:country_code":"PK",
    "gn:dem":86,
    "gn:feature_class":"P",
    "gn:feature_code":"PPL",
    "gn:name":"Theri",
    "gn:population":0,
    "gn:timezone":"Asia/Karachi",
    "iso:country":"PK",
    "name:und_x_variant":[
        "\u016anchi Theri"
    ],
    "wof:name":"Theri",
    "wof:placetype":"locality"
},
  "geometry": {"coordinates":[70.60372,28.51957],"type":"Point"}
}