{
  "type": "Feature",
  "properties": {
    "gn:admin1_code":"7.0",
    "gn:asciiname":"Gomo",
    "gn:country_code":"PK",
    "gn:dem":2481,
    "gn:feature_class":"P",
    "gn:feature_code":"PPL",
    "gn:name":"Gomo",
    "gn:population":0,
    "gn:timezone":"Asia/Karachi",
    "iso:country":"PK",
    "name:und_x_variant":[
        "Gomo Tranzo"
    ],
    "wof:name":"Gomo",
    "wof:placetype":"locality"
},
  "geometry": {"coordinates":[76.21425000000001,35.25072],"type":"Point"}
}