{
  "type": "Feature",
  "properties": {
    "gn:admin1_code":"02",
    "gn:asciiname":"Piran Kili",
    "gn:country_code":"PK",
    "gn:dem":1578,
    "gn:feature_class":"P",
    "gn:feature_code":"PPL",
    "gn:name":"Piran Kili",
    "gn:population":0,
    "gn:timezone":"Asia/Karachi",
    "iso:country":"PK",
    "name:eng_x_preferred":[
        "Piran Kili"
    ],
    "name:und_x_variant":[
        "P\u012br\u0101n Kalai"
    ],
    "wof:name":"Piran Kili",
    "wof:placetype":"locality"
},
  "geometry": {"coordinates":[67.03294,30.59886],"type":"Point"}
}