{
  "type": "Feature",
  "properties": {
    "gn:admin1_code":"03",
    "gn:asciiname":"Nurangi",
    "gn:country_code":"PK",
    "gn:dem":241,
    "gn:feature_class":"P",
    "gn:feature_code":"PPL",
    "gn:name":"Nurangi",
    "gn:population":0,
    "gn:timezone":"Asia/Karachi",
    "iso:country":"PK",
    "name:und_x_variant":[
        "Naurang"
    ],
    "wof:name":"Nurangi",
    "wof:placetype":"locality"
},
  "geometry": {"coordinates":[70.50359,32.2236],"type":"Point"}
}