{
  "type": "Feature",
  "properties": {
    "gn:admin1_code":"3.0",
    "gn:asciiname":"Guhetan Colony",
    "gn:country_code":"PK",
    "gn:dem":300,
    "gn:feature_class":"P",
    "gn:feature_code":"PPL",
    "gn:name":"Guhetan Colony",
    "gn:population":0,
    "gn:timezone":"Asia/Karachi",
    "iso:country":"PK",
    "name:und_x_variant":[
        "Datare"
    ],
    "wof:name":"Guhetan Colony",
    "wof:placetype":"locality"
},
  "geometry": {"coordinates":[72.09836,34.119],"type":"Point"}
}