{
  "type": "Feature",
  "properties": {
    "gn:admin1_code":"3.0",
    "gn:asciiname":"Shahidan",
    "gn:country_code":"PK",
    "gn:dem":323,
    "gn:feature_class":"P",
    "gn:feature_code":"PPL",
    "gn:name":"Shahidan",
    "gn:population":0,
    "gn:timezone":"Asia/Karachi",
    "iso:country":"PK",
    "name:eng_x_preferred":[
        "Sult\u0101n Kili"
    ],
    "wof:name":"Shahidan",
    "wof:placetype":"locality"
},
  "geometry": {"coordinates":[71.81067,34.2147],"type":"Point"}
}