{
  "type": "Feature",
  "properties": {
    "gn:admin1_code":"3",
    "gn:asciiname":"Kuz Lalku",
    "gn:country_code":"PK",
    "gn:dem":1898,
    "gn:feature_class":"P",
    "gn:feature_code":"PPL",
    "gn:name":"Kuz Lalku",
    "gn:population":0,
    "gn:timezone":"Asia/Karachi",
    "iso:country":"PK",
    "name:und_x_variant":[
        "Kuz L\u0101lku",
        "Kil\u0101i"
    ],
    "wof:name":"Kuz Lalku",
    "wof:placetype":"locality"
},
  "geometry": {"coordinates":[72.39381999999998,35.13013],"type":"Point"}
}