{
  "type": "Feature",
  "properties": {
    "gn:admin1_code":"04",
    "gn:asciiname":"Sidhwala",
    "gn:country_code":"PK",
    "gn:dem":152,
    "gn:feature_class":"P",
    "gn:feature_code":"PPL",
    "gn:name":"Sidhwala",
    "gn:population":0,
    "gn:timezone":"Asia/Karachi",
    "iso:country":"PK",
    "name:und_x_variant":[
        "Sidha"
    ],
    "wof:name":"Sidhwala",
    "wof:placetype":"locality"
},
  "geometry": {"coordinates":[72.10354,31.20531],"type":"Point"}
}