{
  "type": "Feature",
  "properties": {
    "gn:admin1_code":"4.0",
    "gn:asciiname":"Chak Daud Ahloka",
    "gn:country_code":"PK",
    "gn:dem":166,
    "gn:feature_class":"P",
    "gn:feature_code":"PPL",
    "gn:name":"Chak Daud Ahloka",
    "gn:population":0,
    "gn:timezone":"Asia/Karachi",
    "iso:country":"PK",
    "name:und_x_variant":[
        "Dadu Ahluka",
        "D\u0101du Ahloka",
        "Chak Daud Ahloka"
    ],
    "wof:name":"Chak Daud Ahloka",
    "wof:placetype":"locality"
},
  "geometry": {"coordinates":[73.45026,30.29761],"type":"Point"}
}