{
  "type": "Feature",
  "properties": {
    "gn:admin1_code":"5",
    "gn:asciiname":"Mir Hasan",
    "gn:country_code":"PK",
    "gn:dem":52,
    "gn:feature_class":"P",
    "gn:feature_code":"PPL",
    "gn:name":"Mir Hasan",
    "gn:population":0,
    "gn:timezone":"Asia/Karachi",
    "iso:country":"PK",
    "name:und_x_variant":[
        "Mangar Kh\u0101n"
    ],
    "wof:name":"Mir Hasan",
    "wof:placetype":"locality"
},
  "geometry": {"coordinates":[68.13374,28.04343],"type":"Point"}
}