{
  "type": "Feature",
  "properties": {
    "gn:admin1_code":"3",
    "gn:asciiname":"Tippar",
    "gn:country_code":"PK",
    "gn:dem":1135,
    "gn:feature_class":"P",
    "gn:feature_code":"PPL",
    "gn:name":"Tippar",
    "gn:population":0,
    "gn:timezone":"Asia/Karachi",
    "iso:country":"PK",
    "wof:name":"Tippar",
    "wof:placetype":"locality"
},
  "geometry": {"coordinates":[73.24851,34.53843],"type":"Point"}
}