{
  "type": "Feature",
  "properties": {
    "gn:admin1_code":"4.0",
    "gn:asciiname":"Qasaiwala",
    "gn:country_code":"PK",
    "gn:dem":123,
    "gn:feature_class":"P",
    "gn:feature_code":"PPL",
    "gn:name":"Qasaiwala",
    "gn:population":0,
    "gn:timezone":"Asia/Karachi",
    "iso:country":"PK",
    "wof:name":"Qasaiwala",
    "wof:placetype":"locality"
},
  "geometry": {"coordinates":[71.23435000000001,30.07326],"type":"Point"}
}