{
  "type": "Feature",
  "properties": {
    "gn:admin1_code":"2",
    "gn:asciiname":"Dinar Khan",
    "gn:country_code":"PK",
    "gn:dem":60,
    "gn:feature_class":"P",
    "gn:feature_code":"PPL",
    "gn:name":"Dinar Khan",
    "gn:population":0,
    "gn:timezone":"Asia/Karachi",
    "iso:country":"PK",
    "name:und_x_variant":[
        "Din\u0101r"
    ],
    "wof:name":"Dinar Khan",
    "wof:placetype":"locality"
},
  "geometry": {"coordinates":[68.72939000000001,28.48651],"type":"Point"}
}