{
  "type": "Feature",
  "properties": {
    "gn:admin1_code":"4.0",
    "gn:asciiname":"Khaur City",
    "gn:country_code":"PK",
    "gn:dem":444,
    "gn:feature_class":"P",
    "gn:feature_code":"PPL",
    "gn:name":"Khaur City",
    "gn:population":0,
    "gn:timezone":"Asia/Karachi",
    "iso:country":"PK",
    "name:und_x_variant":[
        "Kaur",
        "Khaur",
        "Khaur City"
    ],
    "wof:name":"Khaur City",
    "wof:placetype":"locality"
},
  "geometry": {"coordinates":[72.45734,33.24985],"type":"Point"}
}