{
  "type": "Feature",
  "properties": {
    "gn:admin1_code":"4",
    "gn:asciiname":"Thul",
    "gn:country_code":"PK",
    "gn:dem":158,
    "gn:feature_class":"P",
    "gn:feature_code":"PPL",
    "gn:name":"Thul",
    "gn:population":0,
    "gn:timezone":"Asia/Karachi",
    "iso:country":"PK",
    "name:ceb_x_preferred":[
        "Thul"
    ],
    "name:eng_x_preferred":[
        "Thul Sobha"
    ],
    "name:fas_x_preferred":[
        "\u062a\u0647\u0648\u0644"
    ],
    "name:fra_x_preferred":[
        "Thul"
    ],
    "name:spa_x_preferred":[
        "Thul"
    ],
    "name:urd_x_preferred":[
        "\u062a\u06be\u0644"
    ],
    "wof:name":"Thul",
    "wof:placetype":"locality"
},
  "geometry": {"coordinates":[70.59856000000001,30.3507],"type":"Point"}
}