{
  "type": "Feature",
  "properties": {
    "gn:admin1_code":"5",
    "gn:asciiname":"Haji Allah Dino Machhi",
    "gn:country_code":"PK",
    "gn:dem":40,
    "gn:feature_class":"P",
    "gn:feature_code":"PPL",
    "gn:name":"Haji Allah Dino Machhi",
    "gn:population":0,
    "gn:timezone":"Asia/Karachi",
    "iso:country":"PK",
    "wof:name":"Haji Allah Dino Machhi",
    "wof:placetype":"locality"
},
  "geometry": {"coordinates":[68.00833,26.64028],"type":"Point"}
}