{
  "type": "Feature",
  "properties": {
    "gn:admin1_code":"4",
    "gn:asciiname":"Dadwala",
    "gn:country_code":"PK",
    "gn:dem":135,
    "gn:feature_class":"P",
    "gn:feature_code":"PPL",
    "gn:name":"Dadwala",
    "gn:population":0,
    "gn:timezone":"Asia/Karachi",
    "iso:country":"PK",
    "name:fas_x_preferred":[
        "\u062f\u062f\u0648\u0627\u0644\u0647"
    ],
    "name:urd_x_preferred":[
        "\u062f\u062f\u0648\u0627\u0644\u06c1"
    ],
    "wof:name":"Dadwala",
    "wof:placetype":"locality"
},
  "geometry": {"coordinates":[71.69761,30.72348],"type":"Point"}
}