{
  "type": "Feature",
  "properties": {
    "gn:admin1_code":"03",
    "gn:asciiname":"Saipal",
    "gn:cc2":"PK",
    "gn:country_code":"PK",
    "gn:dem":305,
    "gn:feature_class":"P",
    "gn:feature_code":"PPL",
    "gn:name":"Saipal",
    "gn:population":0,
    "gn:timezone":"Asia/Karachi",
    "iso:country":"PK",
    "name:ceb_x_preferred":[
        "S\u0101ip\u0101l"
    ],
    "name:ces_x_preferred":[
        "Saipal"
    ],
    "name:deu_x_preferred":[
        "Saipal"
    ],
    "name:dty_x_preferred":[
        "\u0938\u093e\u0907\u092a\u093e\u0932 \u0939\u093f\u092e\u093e\u0932"
    ],
    "name:nep_x_preferred":[
        "\u0938\u093e\u0907\u092a\u093e\u0932 \u0939\u093f\u092e\u093e\u0932"
    ],
    "name:nld_x_preferred":[
        "Saipal"
    ],
    "name:pnb_x_preferred":[
        "\u0633\u0627\u0626\u06cc\u067e\u0627\u0644"
    ],
    "name:und_x_variant":[
        "Satpal",
        "Saipal"
    ],
    "wof:name":"Saipal",
    "wof:placetype":"locality"
},
  "geometry": {"coordinates":[70.75,32.87361],"type":"Point"}
}