{
  "type": "Feature",
  "properties": {
    "gn:admin1_code":"6.0",
    "gn:asciiname":"Norhat",
    "gn:country_code":"PK",
    "gn:dem":925,
    "gn:feature_class":"P",
    "gn:feature_code":"PPL",
    "gn:name":"Norhat",
    "gn:population":0,
    "gn:timezone":"Asia/Karachi",
    "iso:country":"PK",
    "name:und_x_variant":[
        "Nara Ut"
    ],
    "wof:name":"Norhat",
    "wof:placetype":"locality"
},
  "geometry": {"coordinates":[73.67184,33.62353],"type":"Point"}
}