{
  "type": "Feature",
  "properties": {
    "gn:admin1_code":"3",
    "gn:asciiname":"Guchar Shal",
    "gn:country_code":"PK",
    "gn:dem":3323,
    "gn:feature_class":"P",
    "gn:feature_code":"PPL",
    "gn:name":"Guchar Shal",
    "gn:population":0,
    "gn:timezone":"Asia/Karachi",
    "iso:country":"PK",
    "name:eng_x_preferred":[
        "Ghuch\u0101r Sh\u0101l"
    ],
    "wof:name":"Guchar Shal",
    "wof:placetype":"locality"
},
  "geometry": {"coordinates":[71.84549,35.74078],"type":"Point"}
}