{
  "type": "Feature",
  "properties": {
    "gn:admin1_code":"4",
    "gn:asciiname":"Admani",
    "gn:country_code":"PK",
    "gn:dem":211,
    "gn:feature_class":"P",
    "gn:feature_code":"PPL",
    "gn:name":"Admani",
    "gn:population":0,
    "gn:timezone":"Asia/Karachi",
    "iso:country":"PK",
    "name:und_x_variant":[
        "Adm\u0101no"
    ],
    "wof:name":"Admani",
    "wof:placetype":"locality"
},
  "geometry": {"coordinates":[73.37234000000002,32.65426],"type":"Point"}
}