{
  "type": "Feature",
  "properties": {
    "gn:admin1_code":"6",
    "gn:asciiname":"Khawas",
    "gn:country_code":"PK",
    "gn:dem":729,
    "gn:feature_class":"P",
    "gn:feature_code":"PPL",
    "gn:name":"Khawas",
    "gn:population":0,
    "gn:timezone":"Asia/Karachi",
    "iso:country":"PK",
    "name:und_x_variant":[
        "Khow\u0101s"
    ],
    "wof:name":"Khawas",
    "wof:placetype":"locality"
},
  "geometry": {"coordinates":[73.90924,33.39748],"type":"Point"}
}