{
  "type": "Feature",
  "properties": {
    "gn:admin1_code":"2.0",
    "gn:asciiname":"Channal",
    "gn:country_code":"PK",
    "gn:dem":1151,
    "gn:feature_class":"P",
    "gn:feature_code":"PPL",
    "gn:name":"Channal",
    "gn:population":0,
    "gn:timezone":"Asia/Karachi",
    "iso:country":"PK",
    "wof:name":"Channal",
    "wof:placetype":"locality"
},
  "geometry": {"coordinates":[66.20928000000001,27.62116],"type":"Point"}
}