{
  "type": "Feature",
  "properties": {
    "gn:admin1_code":"04",
    "gn:asciiname":"Sainka Thatta",
    "gn:country_code":"PK",
    "gn:dem":181,
    "gn:feature_class":"P",
    "gn:feature_code":"PPL",
    "gn:name":"Sainka Thatta",
    "gn:population":0,
    "gn:timezone":"Asia/Karachi",
    "iso:country":"PK",
    "name:und_x_variant":[
        "Saike",
        "Saik",
        "Sainka Thatta"
    ],
    "wof:name":"Sainka Thatta",
    "wof:placetype":"locality"
},
  "geometry": {"coordinates":[73.29861,31.03272],"type":"Point"}
}