{
  "type": "Feature",
  "properties": {
    "gn:admin1_code":"5.0",
    "gn:asciiname":"Zaitun Mallah",
    "gn:country_code":"PK",
    "gn:dem":10,
    "gn:feature_class":"P",
    "gn:feature_code":"PPL",
    "gn:name":"Zaitun Mallah",
    "gn:population":0,
    "gn:timezone":"Asia/Karachi",
    "iso:country":"PK",
    "wof:name":"Zaitun Mallah",
    "wof:placetype":"locality"
},
  "geometry": {"coordinates":[68.34675,24.67219],"type":"Point"}
}