{
  "type": "Feature",
  "properties": {
    "gn:admin1_code":"1.0",
    "gn:asciiname":"Pitna",
    "gn:country_code":"PK",
    "gn:dem":1542,
    "gn:feature_class":"P",
    "gn:feature_code":"PPL",
    "gn:name":"Pitna",
    "gn:population":0,
    "gn:timezone":"Asia/Karachi",
    "iso:country":"PK",
    "wof:name":"Pitna",
    "wof:placetype":"locality"
},
  "geometry": {"coordinates":[69.49091,32.32169],"type":"Point"}
}