{
  "type": "Feature",
  "properties": {
    "gn:admin1_code":"4",
    "gn:asciiname":"Chak One",
    "gn:country_code":"PK",
    "gn:dem":132,
    "gn:feature_class":"P",
    "gn:feature_code":"PPL",
    "gn:name":"Chak One",
    "gn:population":0,
    "gn:timezone":"Asia/Karachi",
    "iso:country":"PK",
    "name:und_x_variant":[
        "Fauji\u0101nw\u0101la"
    ],
    "wof:name":"Chak One",
    "wof:placetype":"locality"
},
  "geometry": {"coordinates":[71.80244,30.26895],"type":"Point"}
}