{
  "type": "Feature",
  "properties": {
    "gn:admin1_code":"8.0",
    "gn:asciiname":"Giddar Kotha",
    "gn:country_code":"PK",
    "gn:dem":572,
    "gn:feature_class":"P",
    "gn:feature_code":"PPL",
    "gn:name":"Giddar Kotha",
    "gn:population":0,
    "gn:timezone":"Asia/Karachi",
    "iso:country":"PK",
    "name:und_x_variant":[
        "Gheder Kothah",
        "Giddar Kotha"
    ],
    "wof:name":"Giddar Kotha",
    "wof:placetype":"locality"
},
  "geometry": {"coordinates":[73.05,33.71667],"type":"Point"}
}