{
  "type": "Feature",
  "properties": {
    "gn:admin1_code":"4",
    "gn:asciiname":"Chak Three Hundred Three Eastern Bar",
    "gn:country_code":"PK",
    "gn:dem":149,
    "gn:feature_class":"P",
    "gn:feature_code":"PPL",
    "gn:name":"Chak Three Hundred Three Eastern Bar",
    "gn:population":0,
    "gn:timezone":"Asia/Karachi",
    "iso:country":"PK",
    "name:und_x_variant":[
        "Chopra",
        "Choupari"
    ],
    "wof:name":"Chak Three Hundred Three Eastern Bar",
    "wof:placetype":"locality"
},
  "geometry": {"coordinates":[72.76083,30.12611],"type":"Point"}
}