{
  "type": "Feature",
  "properties": {
    "gn:admin1_code":"2.0",
    "gn:asciiname":"Maula Dad Gis",
    "gn:country_code":"PK",
    "gn:dem":1369,
    "gn:feature_class":"P",
    "gn:feature_code":"PPL",
    "gn:name":"Maula Dad Gis",
    "gn:population":0,
    "gn:timezone":"Asia/Karachi",
    "iso:country":"PK",
    "wof:name":"Maula Dad Gis",
    "wof:placetype":"locality"
},
  "geometry": {"coordinates":[63.8299,29.25589],"type":"Point"}
}