{
  "type": "Feature",
  "properties": {
    "gn:admin1_code":"4.0",
    "gn:asciiname":"Khan Muhmmadwala",
    "gn:country_code":"PK",
    "gn:dem":110,
    "gn:feature_class":"P",
    "gn:feature_code":"PPL",
    "gn:name":"Khan Muhmmadwala",
    "gn:population":0,
    "gn:timezone":"Asia/Karachi",
    "iso:country":"PK",
    "name:und_x_variant":[
        "Kh\u0101n Muhammadw\u0101la"
    ],
    "wof:name":"Khan Muhmmadwala",
    "wof:placetype":"locality"
},
  "geometry": {"coordinates":[71.29339,29.64585],"type":"Point"}
}