{
  "type": "Feature",
  "properties": {
    "gn:admin1_code":"5.0",
    "gn:asciiname":"Gharo",
    "gn:country_code":"PK",
    "gn:dem":46,
    "gn:feature_class":"P",
    "gn:feature_code":"PPL",
    "gn:name":"Gharo",
    "gn:population":0,
    "gn:timezone":"Asia/Karachi",
    "iso:country":"PK",
    "name:ceb_x_preferred":[
        "Gh\u0101ro"
    ],
    "name:eng_x_preferred":[
        "Gharo"
    ],
    "name:pnb_x_preferred":[
        "\u06af\u06be\u0627\u0631\u0648"
    ],
    "name:urd_x_preferred":[
        "\u06af\u06be\u0627\u0631\u0648"
    ],
    "wof:name":"Gharo",
    "wof:placetype":"locality"
},
  "geometry": {"coordinates":[67.73363000000001,27.16951],"type":"Point"}
}