{
  "type": "Feature",
  "properties": {
    "gn:admin1_code":"4",
    "gn:asciiname":"Bhagiana Kalan",
    "gn:country_code":"PK",
    "gn:dem":201,
    "gn:feature_class":"P",
    "gn:feature_code":"PPL",
    "gn:name":"Bhagiana Kalan",
    "gn:population":0,
    "gn:timezone":"Asia/Karachi",
    "iso:country":"PK",
    "name:und_x_variant":[
        "Bhagi\u0101na Khurd"
    ],
    "wof:name":"Bhagiana Kalan",
    "wof:placetype":"locality"
},
  "geometry": {"coordinates":[73.99051999999998,31.18531],"type":"Point"}
}