{
  "type": "Feature",
  "properties": {
    "gn:admin1_code":"4.0",
    "gn:asciiname":"Kotha Hayat Jhammat",
    "gn:country_code":"PK",
    "gn:dem":182,
    "gn:feature_class":"P",
    "gn:feature_code":"PPL",
    "gn:name":"Kotha Hayat Jhammat",
    "gn:population":0,
    "gn:timezone":"Asia/Karachi",
    "iso:country":"PK",
    "wof:name":"Kotha Hayat Jhammat",
    "wof:placetype":"locality"
},
  "geometry": {"coordinates":[72.41638,32.21926],"type":"Point"}
}