{
  "type": "Feature",
  "properties": {
    "gn:admin1_code":"04",
    "gn:asciiname":"Chak Wasiran",
    "gn:country_code":"PK",
    "gn:dem":186,
    "gn:feature_class":"P",
    "gn:feature_code":"PPL",
    "gn:name":"Chak Wasiran",
    "gn:population":0,
    "gn:timezone":"Asia/Karachi",
    "iso:country":"PK",
    "name:und_x_variant":[
        "Wasir\u0101n"
    ],
    "wof:name":"Chak Wasiran",
    "wof:placetype":"locality"
},
  "geometry": {"coordinates":[73.34999999999999,31.21667],"type":"Point"}
}