{
  "type": "Feature",
  "properties": {
    "gn:admin1_code":"5.0",
    "gn:asciiname":"Goth Jadu",
    "gn:country_code":"PK",
    "gn:dem":59,
    "gn:feature_class":"P",
    "gn:feature_code":"PPL",
    "gn:name":"Goth Jadu",
    "gn:population":0,
    "gn:timezone":"Asia/Karachi",
    "iso:country":"PK",
    "wof:name":"Goth Jadu",
    "wof:placetype":"locality"
},
  "geometry": {"coordinates":[68.64578,27.85095],"type":"Point"}
}