{
  "type": "Feature",
  "properties": {
    "gn:admin1_code":"3.0",
    "gn:asciiname":"Dobandai",
    "gn:country_code":"PK",
    "gn:dem":3518,
    "gn:feature_class":"P",
    "gn:feature_code":"PPL",
    "gn:name":"Dobandai",
    "gn:population":0,
    "gn:timezone":"Asia/Karachi",
    "iso:country":"PK",
    "name:und_x_variant":[
        "Dabandai"
    ],
    "wof:name":"Dobandai",
    "wof:placetype":"locality"
},
  "geometry": {"coordinates":[72.68089999999999,35.08473],"type":"Point"}
}