{
  "type": "Feature",
  "properties": {
    "gn:admin1_code":"2.0",
    "gn:asciiname":"Kili Al Murad",
    "gn:country_code":"PK",
    "gn:dem":1621,
    "gn:feature_class":"P",
    "gn:feature_code":"PPL",
    "gn:name":"Kili Al Murad",
    "gn:population":0,
    "gn:timezone":"Asia/Karachi",
    "iso:country":"PK",
    "wof:name":"Kili Al Murad",
    "wof:placetype":"neighbourhood"
},
  "geometry": {"coordinates":[66.97279,30.23889],"type":"Point"}
}