{
  "type": "Feature",
  "properties": {
    "gn:admin1_code":"4",
    "gn:asciiname":"Mumdawala",
    "gn:country_code":"PK",
    "gn:dem":125,
    "gn:feature_class":"P",
    "gn:feature_code":"PPL",
    "gn:name":"Mumdawala",
    "gn:population":0,
    "gn:timezone":"Asia/Karachi",
    "iso:country":"PK",
    "name:eng_x_preferred":[
        "Mand\u016bw\u0101la"
    ],
    "wof:name":"Mumdawala",
    "wof:placetype":"locality"
},
  "geometry": {"coordinates":[70.94081,30.27048],"type":"Point"}
}