{
  "type": "Feature",
  "properties": {
    "gn:admin1_code":"3.0",
    "gn:asciiname":"Manduri",
    "gn:country_code":"PK",
    "gn:dem":315,
    "gn:feature_class":"P",
    "gn:feature_code":"PPL",
    "gn:name":"Manduri",
    "gn:population":0,
    "gn:timezone":"Asia/Karachi",
    "iso:country":"PK",
    "wof:name":"Manduri",
    "wof:placetype":"locality"
},
  "geometry": {"coordinates":[71.90884,34.19122],"type":"Point"}
}