{
  "type": "Feature",
  "properties": {
    "gn:admin1_code":"3.0",
    "gn:asciiname":"Manduri",
    "gn:country_code":"PK",
    "gn:dem":315,
    "gn:feature_class":"P",
    "gn:feature_code":"PPL",
    "gn:name":"Manduri",
    "gn:population":0,
    "gn:timezone":"Asia/Karachi",
    "iso:country":"PK",
    "name:bpy_x_preferred":[
        "\u09ae\u09be\u09a8\u09a1\u09c1\u09b0\u09bf"
    ],
    "name:ceb_x_preferred":[
        "Manduri"
    ],
    "name:epo_x_preferred":[
        "Manduri"
    ],
    "name:eus_x_preferred":[
        "Manduri"
    ],
    "name:fra_x_preferred":[
        "Manduri"
    ],
    "name:ita_x_preferred":[
        "Manduri"
    ],
    "name:kaz_x_preferred":[
        "\u041c\u0430\u043d\u0434\u0443\u0440\u0438"
    ],
    "name:mlg_x_preferred":[
        "Manduri"
    ],
    "name:nld_x_preferred":[
        "Manduri"
    ],
    "name:nor_x_preferred":[
        "Manduri"
    ],
    "name:pol_x_preferred":[
        "Manduri"
    ],
    "name:por_x_preferred":[
        "Manduri"
    ],
    "name:ron_x_preferred":[
        "Manduri"
    ],
    "name:rus_x_preferred":[
        "\u041c\u0430\u043d\u0434\u0443\u0440\u0438"
    ],
    "name:swe_x_preferred":[
        "Manduri"
    ],
    "name:vol_x_preferred":[
        "Manduri"
    ],
    "name:war_x_preferred":[
        "Manduri"
    ],
    "name:zho_x_preferred":[
        "\u66fc\u675c\u91cc"
    ],
    "wof:name":"Manduri",
    "wof:placetype":"locality"
},
  "geometry": {"coordinates":[71.90884,34.19122],"type":"Point"}
}