{
  "type": "Feature",
  "properties": {
    "gn:admin1_code":"4",
    "gn:asciiname":"Mangu",
    "gn:country_code":"PK",
    "gn:dem":187,
    "gn:feature_class":"P",
    "gn:feature_code":"PPL",
    "gn:name":"Mangu",
    "gn:population":0,
    "gn:timezone":"Asia/Karachi",
    "iso:country":"PK",
    "name:ceb_x_preferred":[
        "Mangu"
    ],
    "name:ita_x_preferred":[
        "Mangu"
    ],
    "name:swe_x_preferred":[
        "Mangu"
    ],
    "wof:name":"Mangu",
    "wof:placetype":"locality"
},
  "geometry": {"coordinates":[71.25086,31.96257],"type":"Point"}
}