{
  "type": "Feature",
  "properties": {
    "gn:admin1_code":"1.0",
    "gn:asciiname":"Manzari China",
    "gn:country_code":"PK",
    "gn:dem":1116,
    "gn:feature_class":"P",
    "gn:feature_code":"PPL",
    "gn:name":"Manzari China",
    "gn:population":0,
    "gn:timezone":"Asia/Karachi",
    "iso:country":"PK",
    "name:und_x_variant":[
        "Manzarai China"
    ],
    "wof:name":"Manzari China",
    "wof:placetype":"locality"
},
  "geometry": {"coordinates":[71.05497,34.48766],"type":"Point"}
}