{
  "type": "Feature",
  "properties": {
    "gn:admin1_code":"3",
    "gn:asciiname":"Kaskhwar",
    "gn:country_code":"PK",
    "gn:dem":3036,
    "gn:feature_class":"P",
    "gn:feature_code":"PPL",
    "gn:name":"Kaskhwar",
    "gn:population":0,
    "gn:timezone":"Asia/Karachi",
    "iso:country":"PK",
    "wof:name":"Kaskhwar",
    "wof:placetype":"locality"
},
  "geometry": {"coordinates":[73.19436999999998,34.91337],"type":"Point"}
}