{
  "type": "Feature",
  "properties": {
    "gn:admin1_code":"5",
    "gn:asciiname":"Goth Haji Mahar",
    "gn:country_code":"PK",
    "gn:dem":71,
    "gn:feature_class":"P",
    "gn:feature_code":"PPL",
    "gn:name":"Goth Haji Mahar",
    "gn:population":0,
    "gn:timezone":"Asia/Karachi",
    "iso:country":"PK",
    "name:und_x_variant":[
        "H\u0101ji Mahar"
    ],
    "wof:name":"Goth Haji Mahar",
    "wof:placetype":"locality"
},
  "geometry": {"coordinates":[69.42918,28.01234],"type":"Point"}
}