{
  "type": "Feature",
  "properties": {
    "gn:admin1_code":"2.0",
    "gn:asciiname":"Amir Wal",
    "gn:country_code":"PK",
    "gn:dem":892,
    "gn:feature_class":"P",
    "gn:feature_code":"PPL",
    "gn:name":"Amir Wal",
    "gn:population":0,
    "gn:timezone":"Asia/Karachi",
    "iso:country":"PK",
    "wof:name":"Amir Wal",
    "wof:placetype":"locality"
},
  "geometry": {"coordinates":[65.60823000000001,29.46149],"type":"Point"}
}