{
  "type": "Feature",
  "properties": {
    "gn:admin1_code":"3",
    "gn:asciiname":"Feroz Banda",
    "gn:country_code":"PK",
    "gn:dem":1175,
    "gn:feature_class":"P",
    "gn:feature_code":"PPL",
    "gn:name":"Feroz Banda",
    "gn:population":0,
    "gn:timezone":"Asia/Karachi",
    "iso:country":"PK",
    "name:und_x_variant":[
        "B\u0101nda F\u012broz Kh\u0101n"
    ],
    "wof:name":"Feroz Banda",
    "wof:placetype":"locality"
},
  "geometry": {"coordinates":[73.05346,34.50149],"type":"Point"}
}