{
  "type": "Feature",
  "properties": {
    "gn:admin1_code":"4.0",
    "gn:asciiname":"Ianuwali Basti",
    "gn:country_code":"PK",
    "gn:dem":112,
    "gn:feature_class":"P",
    "gn:feature_code":"PPL",
    "gn:name":"Ianuwali Basti",
    "gn:population":0,
    "gn:timezone":"Asia/Karachi",
    "iso:country":"PK",
    "name:und_x_variant":[
        "J\u0101now\u0101li Basti"
    ],
    "wof:name":"Ianuwali Basti",
    "wof:placetype":"locality"
},
  "geometry": {"coordinates":[71.25556,29.62945],"type":"Point"}
}