{
  "type": "Feature",
  "properties": {
    "gn:admin1_code":"4.0",
    "gn:asciiname":"Jorian",
    "gn:country_code":"PK",
    "gn:dem":404,
    "gn:feature_class":"P",
    "gn:feature_code":"PPL",
    "gn:name":"Jorian",
    "gn:population":0,
    "gn:timezone":"Asia/Karachi",
    "iso:country":"PK",
    "wof:name":"Jorian",
    "wof:placetype":"locality"
},
  "geometry": {"coordinates":[72.92326,33.30307],"type":"Point"}
}