{
  "type": "Feature",
  "properties": {
    "gn:admin1_code":"2",
    "gn:asciiname":"Isa Khan",
    "gn:country_code":"PK",
    "gn:dem":1770,
    "gn:feature_class":"P",
    "gn:feature_code":"PPL",
    "gn:name":"Isa Khan",
    "gn:population":0,
    "gn:timezone":"Asia/Karachi",
    "iso:country":"PK",
    "wof:name":"Isa Khan",
    "wof:placetype":"locality"
},
  "geometry": {"coordinates":[67.0057,29.84565],"type":"Point"}
}