{
  "type": "Feature",
  "properties": {
    "gn:admin1_code":"5",
    "gn:asciiname":"Chatal Mangria",
    "gn:country_code":"PK",
    "gn:dem":62,
    "gn:feature_class":"P",
    "gn:feature_code":"PPL",
    "gn:name":"Chatal Mangria",
    "gn:population":0,
    "gn:timezone":"Asia/Karachi",
    "iso:country":"PK",
    "wof:name":"Chatal Mangria",
    "wof:placetype":"locality"
},
  "geometry": {"coordinates":[69.14721999999999,27.68889],"type":"Point"}
}