{
  "type": "Feature",
  "properties": {
    "gn:admin1_code":"4.0",
    "gn:asciiname":"Pamp",
    "gn:country_code":"PK",
    "gn:dem":229,
    "gn:feature_class":"P",
    "gn:feature_code":"PPL",
    "gn:name":"Pamp",
    "gn:population":0,
    "gn:timezone":"Asia/Karachi",
    "iso:country":"PK",
    "name:und_x_variant":[
        "Ahmad\u0101b\u0101d"
    ],
    "wof:name":"Pamp",
    "wof:placetype":"locality"
},
  "geometry": {"coordinates":[74.77213,31.98368],"type":"Point"}
}