{
  "type": "Feature",
  "properties": {
    "gn:admin1_code":"4",
    "gn:asciiname":"Khandowala",
    "gn:country_code":"PK",
    "gn:dem":124,
    "gn:feature_class":"P",
    "gn:feature_code":"PPL",
    "gn:name":"Khandow\u0101la",
    "gn:population":0,
    "gn:timezone":"Asia/Karachi",
    "iso:country":"PK",
    "wof:name":"Khandowala",
    "wof:placetype":"locality"
},
  "geometry": {"coordinates":[71.15000000000001,30.29583],"type":"Point"}
}