{
  "type": "Feature",
  "properties": {
    "gn:admin1_code":"7.0",
    "gn:asciiname":"Lumar",
    "gn:country_code":"PK",
    "gn:dem":2230,
    "gn:feature_class":"P",
    "gn:feature_code":"PPL",
    "gn:name":"Lumar",
    "gn:population":0,
    "gn:timezone":"Asia/Karachi",
    "iso:country":"PK",
    "name:ara_x_preferred":[
        "\u0644\u064a\u0645\u0627\u0631"
    ],
    "name:aze_x_preferred":[
        "Lumar"
    ],
    "name:ceb_x_preferred":[
        "L\u016bm\u0101r"
    ],
    "name:fas_x_preferred":[
        "\u0644\u0648\u0645\u0627\u0631"
    ],
    "name:mlg_x_preferred":[
        "Lumar"
    ],
    "name:msa_x_preferred":[
        "Lumar"
    ],
    "name:swe_x_preferred":[
        "L\u016bm\u0101r"
    ],
    "name:tur_x_preferred":[
        "Lumar"
    ],
    "name:und_x_variant":[
        "Lomar"
    ],
    "wof:name":"Lumar",
    "wof:placetype":"locality"
},
  "geometry": {"coordinates":[74.18290999999998,35.26275],"type":"Point"}
}