{
  "type": "Feature",
  "properties": {
    "gn:admin1_code":"7.0",
    "gn:asciiname":"Lumar",
    "gn:country_code":"PK",
    "gn:dem":2230,
    "gn:feature_class":"P",
    "gn:feature_code":"PPL",
    "gn:name":"Lumar",
    "gn:population":0,
    "gn:timezone":"Asia/Karachi",
    "iso:country":"PK",
    "name:und_x_variant":[
        "Lomar"
    ],
    "wof:name":"Lumar",
    "wof:placetype":"locality"
},
  "geometry": {"coordinates":[74.18290999999998,35.26275],"type":"Point"}
}