{
  "type": "Feature",
  "properties": {
    "gn:admin1_code":"4",
    "gn:asciiname":"Jalil Mahteke",
    "gn:country_code":"PK",
    "gn:dem":172,
    "gn:feature_class":"P",
    "gn:feature_code":"PPL",
    "gn:name":"Jalil Mahteke",
    "gn:population":0,
    "gn:timezone":"Asia/Karachi",
    "iso:country":"PK",
    "wof:name":"Jalil Mahteke",
    "wof:placetype":"locality"
},
  "geometry": {"coordinates":[73.56981999999998,30.38011],"type":"Point"}
}