{
  "type": "Feature",
  "properties": {
    "gn:admin1_code":"5",
    "gn:asciiname":"Abdullah Junejo",
    "gn:country_code":"PK",
    "gn:dem":7,
    "gn:feature_class":"P",
    "gn:feature_code":"PPL",
    "gn:name":"Abdullah Junejo",
    "gn:population":0,
    "gn:timezone":"Asia/Karachi",
    "iso:country":"PK",
    "name:und_x_variant":[
        "Abdull\u0101h Juneja"
    ],
    "wof:name":"Abdullah Junejo",
    "wof:placetype":"locality"
},
  "geometry": {"coordinates":[69.19014,24.80095],"type":"Point"}
}