{
  "type": "Feature",
  "properties": {
    "gn:admin1_code":"4.0",
    "gn:asciiname":"Silwan",
    "gn:country_code":"PK",
    "gn:dem":193,
    "gn:feature_class":"P",
    "gn:feature_code":"PPL",
    "gn:name":"Silw\u0101n",
    "gn:population":0,
    "gn:timezone":"Asia/Karachi",
    "iso:country":"PK",
    "name:ara_x_preferred":[
        "\u0633\u0644\u0648\u0627\u0646"
    ],
    "name:ces_x_preferred":[
        "Silvan"
    ],
    "name:deu_x_preferred":[
        "Silwan"
    ],
    "name:fin_x_preferred":[
        "Silwan"
    ],
    "name:fra_x_preferred":[
        "Silwan"
    ],
    "name:heb_x_preferred":[
        "\u05e1\u05d9\u05dc\u05d5\u05d0\u05df"
    ],
    "name:ind_x_preferred":[
        "Silwan"
    ],
    "name:mkd_x_preferred":[
        "\u0421\u0438\u043b\u0432\u0430\u043d"
    ],
    "name:nld_x_preferred":[
        "Silwan"
    ],
    "name:rus_x_preferred":[
        "\u0421\u0438\u043b\u0443\u0430\u043d"
    ],
    "name:spa_x_preferred":[
        "Silwan"
    ],
    "name:swe_x_preferred":[
        "Silwan"
    ],
    "name:urd_x_preferred":[
        "\u0633\u0644\u0648\u0627\u0646"
    ],
    "wof:name":"Silwan",
    "wof:placetype":"locality"
},
  "geometry": {"coordinates":[71.39944,32.51333],"type":"Point"}
}