{
  "type": "Feature",
  "properties": {
    "gn:admin1_code":"7.0",
    "gn:asciiname":"Bisil",
    "gn:country_code":"PK",
    "gn:dem":2654,
    "gn:feature_class":"P",
    "gn:feature_code":"PPL",
    "gn:name":"Bisil",
    "gn:population":0,
    "gn:timezone":"Asia/Karachi",
    "iso:country":"PK",
    "wof:name":"Bisil",
    "wof:placetype":"locality"
},
  "geometry": {"coordinates":[75.41683,35.85588],"type":"Point"}
}