{
  "type": "Feature",
  "properties": {
    "gn:admin1_code":"2.0",
    "gn:asciiname":"Lal Khan Nambardi",
    "gn:country_code":"PK",
    "gn:dem":1550,
    "gn:feature_class":"P",
    "gn:feature_code":"PPL",
    "gn:name":"Lal Khan Nambardi",
    "gn:population":0,
    "gn:timezone":"Asia/Karachi",
    "iso:country":"PK",
    "wof:name":"Lal Khan Nambardi",
    "wof:placetype":"locality"
},
  "geometry": {"coordinates":[69.78234999999999,30.29565],"type":"Point"}
}