{
  "type": "Feature",
  "properties": {
    "gn:admin1_code":"4",
    "gn:asciiname":"Kalani",
    "gn:country_code":"PK",
    "gn:dem":134,
    "gn:feature_class":"P",
    "gn:feature_code":"PPL",
    "gn:name":"Kalani",
    "gn:population":0,
    "gn:timezone":"Asia/Karachi",
    "iso:country":"PK",
    "name:fas_x_preferred":[
        "\u06a9\u0644\u0627\u0646\u06cc"
    ],
    "name:und_x_variant":[
        "N\u016br Sh\u0101h",
        "Kal\u0101ni"
    ],
    "wof:name":"Kalani",
    "wof:placetype":"locality"
},
  "geometry": {"coordinates":[72.17305,29.86219],"type":"Point"}
}