{
  "type": "Feature",
  "properties": {
    "gn:admin1_code":"2.0",
    "gn:asciiname":"Fozi Kach Kili",
    "gn:country_code":"PK",
    "gn:dem":1552,
    "gn:feature_class":"P",
    "gn:feature_code":"PPL",
    "gn:name":"Fozi Kach Kili",
    "gn:population":0,
    "gn:timezone":"Asia/Karachi",
    "iso:country":"PK",
    "name:und_x_variant":[
        "Fozi Kach"
    ],
    "wof:name":"Fozi Kach Kili",
    "wof:placetype":"locality"
},
  "geometry": {"coordinates":[67.91721,30.25992],"type":"Point"}
}