{
  "type": "Feature",
  "properties": {
    "gn:admin1_code":"3.0",
    "gn:asciiname":"Khewan Baihk",
    "gn:country_code":"PK",
    "gn:dem":4032,
    "gn:feature_class":"P",
    "gn:feature_code":"PPL",
    "gn:name":"Khewan Baihk",
    "gn:population":0,
    "gn:timezone":"Asia/Karachi",
    "iso:country":"PK",
    "name:eng_x_preferred":[
        "Kheon Behk"
    ],
    "wof:name":"Khewan Baihk",
    "wof:placetype":"locality"
},
  "geometry": {"coordinates":[72.34803000000002,35.65965],"type":"Point"}
}