{
  "type": "Feature",
  "properties": {
    "gn:admin1_code":"04",
    "gn:asciiname":"Manchar Chatha",
    "gn:country_code":"PK",
    "gn:dem":215,
    "gn:feature_class":"P",
    "gn:feature_code":"PPL",
    "gn:name":"Manchar Chatha",
    "gn:population":0,
    "gn:timezone":"Asia/Karachi",
    "iso:country":"PK",
    "name:und_x_variant":[
        "Manchar",
        "Manchar Chatha",
        "Manchar Chattha"
    ],
    "wof:name":"Manchar Chatha",
    "wof:placetype":"locality"
},
  "geometry": {"coordinates":[73.85075000000001,32.30191],"type":"Point"}
}