{
  "type": "Feature",
  "properties": {
    "gn:admin1_code":"05",
    "gn:asciiname":"Seraj Kaka",
    "gn:country_code":"PK",
    "gn:dem":29,
    "gn:feature_class":"P",
    "gn:feature_code":"PPL",
    "gn:name":"Seraj Kaka",
    "gn:population":0,
    "gn:timezone":"Asia/Karachi",
    "iso:country":"PK",
    "name:und_x_variant":[
        "Seraeho",
        "Sar\u0101hio",
        "Sir\u0101ch",
        "Seraj Kaka"
    ],
    "wof:name":"Seraj Kaka",
    "wof:placetype":"locality"
},
  "geometry": {"coordinates":[68.37284,26.02341],"type":"Point"}
}