{
  "type": "Feature",
  "properties": {
    "gn:admin1_code":"4.0",
    "gn:asciiname":"Jiwanpura Khurd",
    "gn:country_code":"PK",
    "gn:dem":208,
    "gn:feature_class":"P",
    "gn:feature_code":"PPL",
    "gn:name":"Jiwanpura Khurd",
    "gn:population":0,
    "gn:timezone":"Asia/Karachi",
    "iso:country":"PK",
    "name:und_x_variant":[
        "J\u012bwanpur Khurd"
    ],
    "wof:name":"Jiwanpura Khurd",
    "wof:placetype":"locality"
},
  "geometry": {"coordinates":[73.985,31.69247],"type":"Point"}
}