{
  "type": "Feature",
  "properties": {
    "gn:admin1_code":"4",
    "gn:asciiname":"Chak Four Hundred-seven",
    "gn:country_code":"PK",
    "gn:dem":119,
    "gn:feature_class":"P",
    "gn:feature_code":"PPL",
    "gn:name":"Chak Four Hundred-seven",
    "gn:population":0,
    "gn:timezone":"Asia/Karachi",
    "iso:country":"PK",
    "name:und_x_variant":[
        "Chak Seven-Eight Faiz",
        "Faiz"
    ],
    "wof:name":"Chak Four Hundred-seven",
    "wof:placetype":"locality"
},
  "geometry": {"coordinates":[71.47176999999998,30.00668],"type":"Point"}
}