{
  "type": "Feature",
  "properties": {
    "gn:admin1_code":"5.0",
    "gn:asciiname":"Goth Muhammad Liaqat",
    "gn:country_code":"PK",
    "gn:dem":14,
    "gn:feature_class":"P",
    "gn:feature_code":"PPL",
    "gn:name":"Goth Muhammad Liaqat",
    "gn:population":0,
    "gn:timezone":"Asia/Karachi",
    "iso:country":"PK",
    "name:und_x_variant":[
        "Goth Muhammad Li\u0101gat"
    ],
    "wof:name":"Goth Muhammad Liaqat",
    "wof:placetype":"locality"
},
  "geometry": {"coordinates":[68.78928000000001,25.0865],"type":"Point"}
}