{
  "type": "Feature",
  "properties": {
    "gn:admin1_code":"5.0",
    "gn:asciiname":"Dil Murad",
    "gn:country_code":"PK",
    "gn:dem":61,
    "gn:feature_class":"P",
    "gn:feature_code":"PPL",
    "gn:name":"Dil Murad",
    "gn:population":0,
    "gn:timezone":"Asia/Karachi",
    "iso:country":"PK",
    "name:und_x_variant":[
        "Dilumurad",
        "Dil Murad"
    ],
    "wof:name":"Dil Murad",
    "wof:placetype":"locality"
},
  "geometry": {"coordinates":[68.58558000000001,28.28223],"type":"Point"}
}