{
  "type": "Feature",
  "properties": {
    "gn:admin1_code":"3.0",
    "gn:asciiname":"Darwaza",
    "gn:country_code":"PK",
    "gn:dem":363,
    "gn:feature_class":"P",
    "gn:feature_code":"PPL",
    "gn:name":"Darw\u0101za",
    "gn:population":0,
    "gn:timezone":"Asia/Karachi",
    "iso:country":"PK",
    "wof:name":"Darwaza",
    "wof:placetype":"locality"
},
  "geometry": {"coordinates":[72.21139000000002,33.84083],"type":"Point"}
}