{
  "type": "Feature",
  "properties": {
    "gn:admin1_code":"4.0",
    "gn:asciiname":"Dhok Mian Ahmad Khan",
    "gn:country_code":"PK",
    "gn:dem":538,
    "gn:feature_class":"P",
    "gn:feature_code":"PPL",
    "gn:name":"Dhok Mian Ahmad Khan",
    "gn:population":0,
    "gn:timezone":"Asia/Karachi",
    "iso:country":"PK",
    "name:und_x_variant":[
        "Dhok Maira Ahmad Kh\u0101n",
        "Dhok Miar Ahmad Khan",
        "Dhok Mian Ahmad Khan"
    ],
    "wof:name":"Dhok Mian Ahmad Khan",
    "wof:placetype":"locality"
},
  "geometry": {"coordinates":[72.69877,33.50479],"type":"Point"}
}