{
  "type": "Feature",
  "properties": {
    "gn:admin1_code":"5.0",
    "gn:asciiname":"Kulachi",
    "gn:country_code":"PK",
    "gn:dem":44,
    "gn:feature_class":"P",
    "gn:feature_code":"PPL",
    "gn:name":"Kulachi",
    "gn:population":0,
    "gn:timezone":"Asia/Karachi",
    "iso:country":"PK",
    "name:eng_x_preferred":[
        "Kulachi"
    ],
    "name:fas_x_preferred":[
        "\u06a9\u0648\u0644\u0627\u0686\u06cc"
    ],
    "name:por_x_preferred":[
        "Kulachi"
    ],
    "name:urd_x_preferred":[
        "\u06a9\u0644\u0627\u0686\u06cc"
    ],
    "wof:name":"Kulachi",
    "wof:placetype":"locality"
},
  "geometry": {"coordinates":[67.61938000000001,27.21695],"type":"Point"}
}