{
  "type": "Feature",
  "properties": {
    "gn:admin1_code":"5.0",
    "gn:asciiname":"Goth Haji Ahmad Baran",
    "gn:country_code":"PK",
    "gn:dem":13,
    "gn:feature_class":"P",
    "gn:feature_code":"PPL",
    "gn:name":"Goth Haji Ahmad Baran",
    "gn:population":0,
    "gn:timezone":"Asia/Karachi",
    "iso:country":"PK",
    "name:eng_x_preferred":[
        "Goth Haji Ahmad Baran"
    ],
    "wof:name":"Goth Haji Ahmad Baran",
    "wof:placetype":"locality"
},
  "geometry": {"coordinates":[68.21028000000001,24.67267],"type":"Point"}
}