{
  "type": "Feature",
  "properties": {
    "gn:admin1_code":"4",
    "gn:asciiname":"Chak Ten Western Bank",
    "gn:country_code":"PK",
    "gn:dem":141,
    "gn:feature_class":"P",
    "gn:feature_code":"PPL",
    "gn:name":"Chak Ten Western Bank",
    "gn:population":0,
    "gn:timezone":"Asia/Karachi",
    "iso:country":"PK",
    "name:und_x_variant":[
        "Chak Ten-Four R"
    ],
    "wof:name":"Chak Ten Western Bank",
    "wof:placetype":"locality"
},
  "geometry": {"coordinates":[72.43021,30.11847],"type":"Point"}
}