{
  "type": "Feature",
  "properties": {
    "gn:admin1_code":"2.0",
    "gn:asciiname":"Barghlai",
    "gn:country_code":"PK",
    "gn:dem":732,
    "gn:feature_class":"P",
    "gn:feature_code":"PPL",
    "gn:name":"Barghlai",
    "gn:population":0,
    "gn:timezone":"Asia/Karachi",
    "iso:country":"PK",
    "wof:name":"Barghlai",
    "wof:placetype":"locality"
},
  "geometry": {"coordinates":[70.15411999999999,31.35457],"type":"Point"}
}