{
  "type": "Feature",
  "properties": {
    "gn:admin1_code":"2.0",
    "gn:asciiname":"S.K.B. Colony",
    "gn:country_code":"PK",
    "gn:dem":76,
    "gn:feature_class":"P",
    "gn:feature_code":"PPL",
    "gn:name":"S.K.B. Colony",
    "gn:population":0,
    "gn:timezone":"Asia/Karachi",
    "iso:country":"PK",
    "wof:name":"S.K.B. Colony",
    "wof:placetype":"locality"
},
  "geometry": {"coordinates":[66.53605,26.0013],"type":"Point"}
}