{
  "type": "Feature",
  "properties": {
    "gn:admin1_code":"2",
    "gn:asciiname":"Kotwal",
    "gn:country_code":"PK",
    "gn:dem":1216,
    "gn:feature_class":"P",
    "gn:feature_code":"PPL",
    "gn:name":"Kotwal",
    "gn:population":0,
    "gn:timezone":"Asia/Karachi",
    "iso:country":"PK",
    "wof:name":"Kotwal",
    "wof:placetype":"locality"
},
  "geometry": {"coordinates":[68.93331999999999,30.38371],"type":"Point"}
}