{
  "type": "Feature",
  "properties": {
    "gn:admin1_code":"2",
    "gn:asciiname":"Kotwal",
    "gn:country_code":"PK",
    "gn:dem":1216,
    "gn:feature_class":"P",
    "gn:feature_code":"PPL",
    "gn:name":"Kotwal",
    "gn:population":0,
    "gn:timezone":"Asia/Karachi",
    "iso:country":"PK",
    "name:cat_x_preferred":[
        "Kotwal"
    ],
    "name:ita_x_preferred":[
        "Kotwal"
    ],
    "name:mal_x_preferred":[
        "\u0d15\u0d4b\u0d1f\u0d4d\u0d1f\u0d4d\u200c\u200c\u0d35\u0d3e\u0d7d"
    ],
    "name:pan_x_preferred":[
        "\u0a15\u0a4b\u0a24\u0a35\u0a3e\u0a32"
    ],
    "name:tam_x_preferred":[
        "\u0b95\u0bca\u0ba4\u0bcd\u0ba4\u0bb5\u0bbe\u0bb2\u0bcd"
    ],
    "name:urd_x_preferred":[
        "\u06a9\u0648\u062a\u0648\u0627\u0644"
    ],
    "wof:name":"Kotwal",
    "wof:placetype":"locality"
},
  "geometry": {"coordinates":[68.93331999999999,30.38371],"type":"Point"}
}