{
  "type": "Feature",
  "properties": {
    "gn:admin1_code":"4.0",
    "gn:asciiname":"Kohliyar",
    "gn:country_code":"PK",
    "gn:dem":261,
    "gn:feature_class":"P",
    "gn:feature_code":"PPL",
    "gn:name":"Kohliyar",
    "gn:population":0,
    "gn:timezone":"Asia/Karachi",
    "iso:country":"PK",
    "wof:name":"Kohliyar",
    "wof:placetype":"locality"
},
  "geometry": {"coordinates":[75.01364000000002,32.26663],"type":"Point"}
}