{
  "type": "Feature",
  "properties": {
    "gn:admin1_code":"5",
    "gn:asciiname":"Goth Saleh Muhammad",
    "gn:country_code":"PK",
    "gn:dem":18,
    "gn:feature_class":"P",
    "gn:feature_code":"PPL",
    "gn:name":"Goth Saleh Muhammad",
    "gn:population":0,
    "gn:timezone":"Asia/Karachi",
    "iso:country":"PK",
    "name:eng_x_preferred":[
        "Goth Saleh Muhammad"
    ],
    "wof:name":"Goth Saleh Muhammad",
    "wof:placetype":"locality"
},
  "geometry": {"coordinates":[68.42543000000001,25.13766],"type":"Point"}
}