{
  "type": "Feature",
  "properties": {
    "gn:admin1_code":"04",
    "gn:asciiname":"Susian",
    "gn:country_code":"PK",
    "gn:dem":442,
    "gn:feature_class":"P",
    "gn:feature_code":"PPL",
    "gn:name":"Susian",
    "gn:population":0,
    "gn:timezone":"Asia/Karachi",
    "iso:country":"PK",
    "name:und_x_variant":[
        "Sosi",
        "Susi",
        "Susian"
    ],
    "wof:name":"Susian",
    "wof:placetype":"locality"
},
  "geometry": {"coordinates":[73.10009000000002,32.93274],"type":"Point"}
}