{
  "type": "Feature",
  "properties": {
    "gn:admin1_code":"2.0",
    "gn:asciiname":"Madat Khan",
    "gn:country_code":"PK",
    "gn:dem":154,
    "gn:feature_class":"P",
    "gn:feature_code":"PPL",
    "gn:name":"Madat Khan",
    "gn:population":0,
    "gn:timezone":"Asia/Karachi",
    "iso:country":"PK",
    "wof:name":"Madat Khan",
    "wof:placetype":"locality"
},
  "geometry": {"coordinates":[68.11620000000001,29.54541],"type":"Point"}
}