{
  "type": "Feature",
  "properties": {
    "gn:admin1_code":"4.0",
    "gn:asciiname":"Burj Manchar",
    "gn:country_code":"PK",
    "gn:dem":217,
    "gn:feature_class":"P",
    "gn:feature_code":"PPL",
    "gn:name":"Burj Manchar",
    "gn:population":0,
    "gn:timezone":"Asia/Karachi",
    "iso:country":"PK",
    "name:und_x_variant":[
        "Mancher"
    ],
    "wof:name":"Burj Manchar",
    "wof:placetype":"locality"
},
  "geometry": {"coordinates":[73.83254000000002,32.31002],"type":"Point"}
}