{
  "type": "Feature",
  "properties": {
    "gn:admin1_code":"7.0",
    "gn:asciiname":"Nahango Chhat",
    "gn:country_code":"PK",
    "gn:dem":2965,
    "gn:feature_class":"P",
    "gn:feature_code":"PPL",
    "gn:name":"Nahango Chhat",
    "gn:population":0,
    "gn:timezone":"Asia/Karachi",
    "iso:country":"PK",
    "wof:name":"Nahango Chhat",
    "wof:placetype":"locality"
},
  "geometry": {"coordinates":[72.94683000000001,36.16861],"type":"Point"}
}