{
  "type": "Feature",
  "properties": {
    "gn:admin1_code":"4",
    "gn:asciiname":"Basti Tahlian",
    "gn:country_code":"PK",
    "gn:dem":128,
    "gn:feature_class":"P",
    "gn:feature_code":"PPL",
    "gn:name":"Basti Tahlian",
    "gn:population":0,
    "gn:timezone":"Asia/Karachi",
    "iso:country":"PK",
    "name:eng_x_preferred":[
        "T\u0101hl\u012b\u0101nw\u0101li"
    ],
    "wof:name":"Basti Tahlian",
    "wof:placetype":"locality"
},
  "geometry": {"coordinates":[70.90658000000001,30.27481],"type":"Point"}
}