{
  "type": "Feature",
  "properties": {
    "gn:admin1_code":"4.0",
    "gn:asciiname":"Jakalian",
    "gn:country_code":"PK",
    "gn:dem":217,
    "gn:feature_class":"P",
    "gn:feature_code":"PPL",
    "gn:name":"Jakalian",
    "gn:population":0,
    "gn:timezone":"Asia/Karachi",
    "iso:country":"PK",
    "name:und_x_variant":[
        "Jokalia",
        "Jakalian",
        "Jok\u0101li\u0101n"
    ],
    "wof:name":"Jakalian",
    "wof:placetype":"locality"
},
  "geometry": {"coordinates":[73.78716999999997,32.40073],"type":"Point"}
}