{
  "type": "Feature",
  "properties": {
    "gn:admin1_code":"5",
    "gn:asciiname":"Goth Torba",
    "gn:country_code":"PK",
    "gn:dem":43,
    "gn:feature_class":"P",
    "gn:feature_code":"PPL",
    "gn:name":"Goth Torba",
    "gn:population":0,
    "gn:timezone":"Asia/Karachi",
    "iso:country":"PK",
    "name:und_x_variant":[
        "Toro"
    ],
    "wof:name":"Goth Torba",
    "wof:placetype":"locality"
},
  "geometry": {"coordinates":[67.97366,26.80816],"type":"Point"}
}