{
  "type": "Feature",
  "properties": {
    "gn:admin1_code":"4.0",
    "gn:asciiname":"Kot Khokharanwala",
    "gn:country_code":"PK",
    "gn:dem":180,
    "gn:feature_class":"P",
    "gn:feature_code":"PPL",
    "gn:name":"Kot Khokharanwala",
    "gn:population":0,
    "gn:timezone":"Asia/Karachi",
    "iso:country":"PK",
    "wof:name":"Kot Khokharanwala",
    "wof:placetype":"locality"
},
  "geometry": {"coordinates":[73.50576,30.90888],"type":"Point"}
}