{
  "type": "Feature",
  "properties": {
    "gn:admin1_code":"3.0",
    "gn:asciiname":"Dotara",
    "gn:country_code":"PK",
    "gn:dem":847,
    "gn:feature_class":"P",
    "gn:feature_code":"PPL",
    "gn:name":"Dotara",
    "gn:population":0,
    "gn:timezone":"Asia/Karachi",
    "iso:country":"PK",
    "name:ben_x_preferred":[
        "\u09a6\u09cb\u09a4\u09be\u09b0\u09be"
    ],
    "name:ell_x_preferred":[
        "\u039d\u03c4\u03bf\u03c4\u03ac\u03c1\u03b1"
    ],
    "name:eng_x_preferred":[
        "Dotara"
    ],
    "name:epo_x_preferred":[
        "Dotaro"
    ],
    "name:ind_x_preferred":[
        "Dotara"
    ],
    "name:spa_x_preferred":[
        "Dotara"
    ],
    "wof:name":"Dotara",
    "wof:placetype":"locality"
},
  "geometry": {"coordinates":[73.18007,33.89348],"type":"Point"}
}