{
  "type": "Feature",
  "properties": {
    "gn:admin1_code":"5",
    "gn:asciiname":"Goth Umid Ali Rind",
    "gn:country_code":"PK",
    "gn:dem":20,
    "gn:feature_class":"P",
    "gn:feature_code":"PPL",
    "gn:name":"Goth Umid Ali Rind",
    "gn:population":0,
    "gn:timezone":"Asia/Karachi",
    "iso:country":"PK",
    "name:und_x_variant":[
        "Goth Umed Ali Rind"
    ],
    "wof:name":"Goth Umid Ali Rind",
    "wof:placetype":"locality"
},
  "geometry": {"coordinates":[68.52404,25.2303],"type":"Point"}
}