{
  "type": "Feature",
  "properties": {
    "gn:admin1_code":"04",
    "gn:asciiname":"Thatti Dhakwan",
    "gn:country_code":"PK",
    "gn:dem":175,
    "gn:feature_class":"P",
    "gn:feature_code":"PPL",
    "gn:name":"Thatti Dhakwan",
    "gn:population":0,
    "gn:timezone":"Asia/Karachi",
    "iso:country":"PK",
    "wof:name":"Thatti Dhakwan",
    "wof:placetype":"locality"
},
  "geometry": {"coordinates":[72.34698,32.1006],"type":"Point"}
}