{
  "type": "Feature",
  "properties": {
    "gn:admin1_code":"5.0",
    "gn:asciiname":"Asaf",
    "gn:country_code":"PK",
    "gn:dem":121,
    "gn:feature_class":"P",
    "gn:feature_code":"PPL",
    "gn:name":"Asaf",
    "gn:population":0,
    "gn:timezone":"Asia/Karachi",
    "iso:country":"PK",
    "name:pol_x_preferred":[
        "Asaf"
    ],
    "name:rus_x_preferred":[
        "\u0410\u0441\u0430\u0444"
    ],
    "wof:name":"Asaf",
    "wof:placetype":"locality"
},
  "geometry": {"coordinates":[70.47818000000002,25.66178],"type":"Point"}
}