{
  "type": "Feature",
  "properties": {
    "gn:admin1_code":"2.0",
    "gn:asciiname":"Ghawagi",
    "gn:country_code":"PK",
    "gn:dem":2420,
    "gn:feature_class":"P",
    "gn:feature_code":"PPL",
    "gn:name":"Ghawagi",
    "gn:population":0,
    "gn:timezone":"Asia/Karachi",
    "iso:country":"PK",
    "name:eng_x_preferred":[
        "Ghawagi"
    ],
    "wof:name":"Ghawagi",
    "wof:placetype":"locality"
},
  "geometry": {"coordinates":[67.47981,30.93693],"type":"Point"}
}