{
  "type": "Feature",
  "properties": {
    "gn:admin1_code":"3",
    "gn:asciiname":"Shahid Takai",
    "gn:country_code":"PK",
    "gn:dem":2879,
    "gn:feature_class":"P",
    "gn:feature_code":"PPL",
    "gn:name":"Shahid Takai",
    "gn:population":0,
    "gn:timezone":"Asia/Karachi",
    "iso:country":"PK",
    "name:eng_x_preferred":[
        "Shahid Takai"
    ],
    "wof:name":"Shahid Takai",
    "wof:placetype":"locality"
},
  "geometry": {"coordinates":[72.46305,35.20756],"type":"Point"}
}