{
  "type": "Feature",
  "properties": {
    "gn:admin1_code":"02",
    "gn:asciiname":"Pir Pahalwan Shah",
    "gn:country_code":"PK",
    "gn:dem":103,
    "gn:feature_class":"P",
    "gn:feature_code":"PPL",
    "gn:name":"Pir Pahalwan Shah",
    "gn:population":0,
    "gn:timezone":"Asia/Karachi",
    "iso:country":"PK",
    "name:und_x_variant":[
        "Pahalw\u0101n Sh\u0101h"
    ],
    "wof:name":"Pir Pahalwan Shah",
    "wof:placetype":"locality"
},
  "geometry": {"coordinates":[67.81142,29.16338],"type":"Point"}
}