{
  "type": "Feature",
  "properties": {
    "gn:admin1_code":"3",
    "gn:asciiname":"Begakot",
    "gn:country_code":"PK",
    "gn:dem":1384,
    "gn:feature_class":"P",
    "gn:feature_code":"PPL",
    "gn:name":"Begakot",
    "gn:population":0,
    "gn:timezone":"Asia/Karachi",
    "iso:country":"PK",
    "name:und_x_variant":[
        "Beg\u0101hkot"
    ],
    "wof:name":"Begakot",
    "wof:placetype":"locality"
},
  "geometry": {"coordinates":[73.13427,34.16293],"type":"Point"}
}