{
  "type": "Feature",
  "properties": {
    "gn:admin1_code":"4",
    "gn:asciiname":"Kamala",
    "gn:country_code":"PK",
    "gn:dem":239,
    "gn:feature_class":"P",
    "gn:feature_code":"PPL",
    "gn:name":"Kamala",
    "gn:population":0,
    "gn:timezone":"Asia/Karachi",
    "iso:country":"PK",
    "name:ceb_x_preferred":[
        "Kamala"
    ],
    "name:deu_x_preferred":[
        "Kamala"
    ],
    "name:fra_x_preferred":[
        "Kamala"
    ],
    "name:kor_x_preferred":[
        "\uce74\ub9d0\ub77c"
    ],
    "name:nld_x_preferred":[
        "Kamala"
    ],
    "name:por_x_preferred":[
        "Kamala"
    ],
    "name:swe_x_preferred":[
        "Kamala"
    ],
    "name:tel_x_preferred":[
        "\u0c15\u0c2e\u0c32"
    ],
    "wof:name":"Kamala",
    "wof:placetype":"locality"
},
  "geometry": {"coordinates":[74.05597,32.61968],"type":"Point"}
}