{
  "type": "Feature",
  "properties": {
    "gn:admin1_code":"6",
    "gn:asciiname":"Bola",
    "gn:country_code":"PK",
    "gn:dem":2423,
    "gn:feature_class":"P",
    "gn:feature_code":"PPL",
    "gn:name":"Bola",
    "gn:population":0,
    "gn:timezone":"Asia/Karachi",
    "iso:country":"PK",
    "name:cat_x_preferred":[
        "Bola"
    ],
    "name:ceb_x_preferred":[
        "Bola"
    ],
    "name:deu_x_preferred":[
        "Bola"
    ],
    "name:eus_x_preferred":[
        "Bola"
    ],
    "name:fra_x_preferred":[
        "Bola"
    ],
    "name:ind_x_preferred":[
        "Bola"
    ],
    "name:ita_x_preferred":[
        "Bola"
    ],
    "name:nld_x_preferred":[
        "Bola"
    ],
    "name:pol_x_preferred":[
        "Bola"
    ],
    "name:por_x_preferred":[
        "Bola"
    ],
    "name:spa_x_preferred":[
        "Bola"
    ],
    "name:sun_x_preferred":[
        "Bola"
    ],
    "name:swe_x_preferred":[
        "Bola"
    ],
    "name:und_x_variant":[
        "Bela",
        "B\u014dla"
    ],
    "wof:name":"Bola",
    "wof:placetype":"locality"
},
  "geometry": {"coordinates":[74.42639,34.9125],"type":"Point"}
}