{
  "type": "Feature",
  "properties": {
    "gn:admin1_code":"3.0",
    "gn:asciiname":"Darabri",
    "gn:country_code":"PK",
    "gn:dem":197,
    "gn:feature_class":"P",
    "gn:feature_code":"PPL",
    "gn:name":"Darabri",
    "gn:population":0,
    "gn:timezone":"Asia/Karachi",
    "iso:country":"PK",
    "name:und_x_variant":[
        "Darbari",
        "Dar\u0101bri",
        "Darabri"
    ],
    "wof:name":"Darabri",
    "wof:placetype":"locality"
},
  "geometry": {"coordinates":[70.67763000000002,31.91859],"type":"Point"}
}