{
  "type": "Feature",
  "properties": {
    "gn:admin1_code":"2.0",
    "gn:asciiname":"Kili Mangi",
    "gn:country_code":"PK",
    "gn:dem":1640,
    "gn:feature_class":"P",
    "gn:feature_code":"PPL",
    "gn:name":"Kili Mangi",
    "gn:population":0,
    "gn:timezone":"Asia/Karachi",
    "iso:country":"PK",
    "name:eng_x_preferred":[
        "M\u0101ngi Kach"
    ],
    "wof:name":"Kili Mangi",
    "wof:placetype":"locality"
},
  "geometry": {"coordinates":[67.46129999999999,30.3697],"type":"Point"}
}