{
  "type": "Feature",
  "properties": {
    "gn:admin1_code":"6",
    "gn:asciiname":"Phiari",
    "gn:country_code":"PK",
    "gn:dem":273,
    "gn:feature_class":"P",
    "gn:feature_code":"PPL",
    "gn:name":"Phiari",
    "gn:population":0,
    "gn:timezone":"Asia/Karachi",
    "iso:country":"PK",
    "wof:name":"Phiari",
    "wof:placetype":"locality"
},
  "geometry": {"coordinates":[73.87575,33.08801],"type":"Point"}
}