{
  "type": "Feature",
  "properties": {
    "gn:admin1_code":"3",
    "gn:asciiname":"Manerai Banda",
    "gn:country_code":"PK",
    "gn:dem":367,
    "gn:feature_class":"P",
    "gn:feature_code":"PPL",
    "gn:name":"Manerai Banda",
    "gn:population":0,
    "gn:timezone":"Asia/Karachi",
    "iso:country":"PK",
    "name:eng_x_preferred":[
        "Maneri B\u0101nda"
    ],
    "wof:name":"Manerai Banda",
    "wof:placetype":"locality"
},
  "geometry": {"coordinates":[72.40075,34.15736],"type":"Point"}
}