{
  "type": "Feature",
  "properties": {
    "gn:admin1_code":"1",
    "gn:asciiname":"Wospas Kalle",
    "gn:country_code":"PK",
    "gn:dem":1462,
    "gn:feature_class":"P",
    "gn:feature_code":"PPL",
    "gn:name":"Wospas Kalle",
    "gn:population":0,
    "gn:timezone":"Asia/Karachi",
    "iso:country":"PK",
    "name:und_x_variant":[
        "Michi Khel",
        "Wospas Kili",
        "Wospas Kalle"
    ],
    "wof:name":"Wospas Kalle",
    "wof:placetype":"locality"
},
  "geometry": {"coordinates":[69.78778,32.355],"type":"Point"}
}