{
  "type": "Feature",
  "properties": {
    "gn:admin1_code":"2",
    "gn:asciiname":"Giawan",
    "gn:country_code":"PK",
    "gn:dem":2009,
    "gn:feature_class":"P",
    "gn:feature_code":"PPL",
    "gn:name":"Giawan",
    "gn:population":0,
    "gn:timezone":"Asia/Karachi",
    "iso:country":"PK",
    "wof:name":"Giawan",
    "wof:placetype":"locality"
},
  "geometry": {"coordinates":[66.58896,29.03016],"type":"Point"}
}