{
  "type": "Feature",
  "properties": {
    "gn:admin1_code":"4.0",
    "gn:asciiname":"Sojan Singwala",
    "gn:country_code":"PK",
    "gn:dem":200,
    "gn:feature_class":"P",
    "gn:feature_code":"PPL",
    "gn:name":"Sojan Singwala",
    "gn:population":0,
    "gn:timezone":"Asia/Karachi",
    "iso:country":"PK",
    "name:und_x_variant":[
        "Suj\u0101n Singhw\u0101la"
    ],
    "wof:name":"Sojan Singwala",
    "wof:placetype":"locality"
},
  "geometry": {"coordinates":[74.00624999999999,31.14913],"type":"Point"}
}