{
  "type": "Feature",
  "properties": {
    "gn:admin1_code":"5.0",
    "gn:asciiname":"Iqbal Bhutto",
    "gn:country_code":"PK",
    "gn:dem":48,
    "gn:feature_class":"P",
    "gn:feature_code":"PPL",
    "gn:name":"Iqbal Bhutto",
    "gn:population":0,
    "gn:timezone":"Asia/Karachi",
    "iso:country":"PK",
    "wof:name":"Iqbal Bhutto",
    "wof:placetype":"locality"
},
  "geometry": {"coordinates":[68.58374000000001,27.06811],"type":"Point"}
}