{
  "type": "Feature",
  "properties": {
    "iso:country":"PK",
    "name:bul_x_preferred":[
        "\u0411\u0445\u0438\u0440\u0438\u0430"
    ],
    "name:dut_x_preferred":[
        "Bhiria"
    ],
    "name:eng_x_preferred":[
        "Bhiria"
    ],
    "qs:gn_country":"PK",
    "qs:gn_fcode":"PPL",
    "qs:gn_pop":12186,
    "qs:name":"Bhiria",
    "qs:name_adm0":"Pakistan",
    "qs:name_adm1":"Sindh",
    "qs:photos":0,
    "qs:photos_1k":0,
    "qs:photos_9k":0,
    "qs:photos_9r":0,
    "qs:photos_all":0,
    "qs:photos_sr":0,
    "qs:placetype":"Town",
    "qs:pop_sr":"6",
    "qs:woe_adm0":23424922,
    "wd:wordcount":353,
    "wof:name":"Bhiria",
    "wof:placetype":"locality",
    "wof:population":12186
},
  "geometry": {"coordinates":[68.19484,26.91067],"type":"Point"}
}