{
  "type": "Feature",
  "properties": {
    "gn:admin1_code":"5.0",
    "gn:asciiname":"Ghulam Shabbir",
    "gn:country_code":"PK",
    "gn:dem":54,
    "gn:feature_class":"P",
    "gn:feature_code":"PPL",
    "gn:name":"Ghul\u0101m Shabb\u012br",
    "gn:population":0,
    "gn:timezone":"Asia/Karachi",
    "iso:country":"PK",
    "wof:name":"Ghulam Shabbir",
    "wof:placetype":"locality"
},
  "geometry": {"coordinates":[68.67081999999999,27.30126],"type":"Point"}
}