{
  "type": "Feature",
  "properties": {
    "gn:admin1_code":"5",
    "gn:asciiname":"Goth Haji Darya Khan Dahri",
    "gn:country_code":"PK",
    "gn:dem":26,
    "gn:feature_class":"P",
    "gn:feature_code":"PPL",
    "gn:name":"Goth Haji Darya Khan Dahri",
    "gn:population":0,
    "gn:timezone":"Asia/Karachi",
    "iso:country":"PK",
    "name:und_x_variant":[
        "Goth Soh\u0101n"
    ],
    "wof:name":"Goth Haji Darya Khan Dahri",
    "wof:placetype":"locality"
},
  "geometry": {"coordinates":[68.55179,25.55311],"type":"Point"}
}