{
  "type": "Feature",
  "properties": {
    "gn:admin1_code":"4",
    "gn:asciiname":"Bahrwal",
    "gn:country_code":"PK",
    "gn:dem":183,
    "gn:feature_class":"P",
    "gn:feature_code":"PPL",
    "gn:name":"Bahrwal",
    "gn:population":0,
    "gn:timezone":"Asia/Karachi",
    "iso:country":"PK",
    "name:und_x_variant":[
        "Bahrw\u0101l Khurd"
    ],
    "wof:name":"Bahrwal",
    "wof:placetype":"locality"
},
  "geometry": {"coordinates":[73.91630000000001,30.90547],"type":"Point"}
}