{
  "type": "Feature",
  "properties": {
    "gn:admin1_code":"6.0",
    "gn:asciiname":"Dehri Baihk",
    "gn:country_code":"PK",
    "gn:dem":2195,
    "gn:feature_class":"P",
    "gn:feature_code":"PPL",
    "gn:name":"Dehri Baihk",
    "gn:population":0,
    "gn:timezone":"Asia/Karachi",
    "iso:country":"PK",
    "wof:name":"Dehri Baihk",
    "wof:placetype":"locality"
},
  "geometry": {"coordinates":[73.98748000000001,34.75252],"type":"Point"}
}