{
  "type": "Feature",
  "properties": {
    "gn:admin1_code":"2.0",
    "gn:asciiname":"Gadi Saring",
    "gn:country_code":"PK",
    "gn:dem":109,
    "gn:feature_class":"P",
    "gn:feature_code":"PPL",
    "gn:name":"Gadi Saring",
    "gn:population":0,
    "gn:timezone":"Asia/Karachi",
    "iso:country":"PK",
    "name:und_x_variant":[
        "G\u0101di S\u0101rang",
        "G\u0101di Aurangzeb"
    ],
    "wof:name":"Gadi Saring",
    "wof:placetype":"locality"
},
  "geometry": {"coordinates":[67.75397,29.24616],"type":"Point"}
}