{
  "type": "Feature",
  "properties": {
    "gn:admin1_code":"01",
    "gn:asciiname":"Rajab China",
    "gn:country_code":"PK",
    "gn:dem":985,
    "gn:feature_class":"P",
    "gn:feature_code":"PPL",
    "gn:name":"Rajab China",
    "gn:population":0,
    "gn:timezone":"Asia/Karachi",
    "iso:country":"PK",
    "wof:name":"Rajab China",
    "wof:placetype":"locality"
},
  "geometry": {"coordinates":[71.41636,34.67837],"type":"Point"}
}