{
  "type": "Feature",
  "properties": {
    "gn:admin1_code":"3",
    "gn:asciiname":"Seri Gharia",
    "gn:country_code":"PK",
    "gn:dem":1339,
    "gn:feature_class":"P",
    "gn:feature_code":"PPL",
    "gn:name":"Seri Gharia",
    "gn:population":0,
    "gn:timezone":"Asia/Karachi",
    "iso:country":"PK",
    "name:und_x_variant":[
        "Nari\u0101la"
    ],
    "wof:name":"Seri Gharia",
    "wof:placetype":"locality"
},
  "geometry": {"coordinates":[72.97286,34.42775],"type":"Point"}
}