{
  "type": "Feature",
  "properties": {
    "gn:admin1_code":"4.0",
    "gn:asciiname":"Basti Master Rasul Bakhah",
    "gn:country_code":"PK",
    "gn:dem":83,
    "gn:feature_class":"P",
    "gn:feature_code":"PPL",
    "gn:name":"Basti Master Rasul Bakhah",
    "gn:population":0,
    "gn:timezone":"Asia/Karachi",
    "iso:country":"PK",
    "wof:name":"Basti Master Rasul Bakhah",
    "wof:placetype":"locality"
},
  "geometry": {"coordinates":[69.98696,28.70841],"type":"Point"}
}