{
  "type": "Feature",
  "properties": {
    "gn:admin1_code":"5.0",
    "gn:asciiname":"Shadi Jat",
    "gn:country_code":"PK",
    "gn:dem":7,
    "gn:feature_class":"P",
    "gn:feature_code":"PPL",
    "gn:name":"Shadi Jat",
    "gn:population":0,
    "gn:timezone":"Asia/Karachi",
    "iso:country":"PK",
    "name:eng_x_preferred":[
        "Shadi Jat"
    ],
    "wof:name":"Shadi Jat",
    "wof:placetype":"locality"
},
  "geometry": {"coordinates":[68.30468,24.50675],"type":"Point"}
}