{
  "type": "Feature",
  "properties": {
    "gn:admin1_code":"5",
    "gn:asciiname":"Goth Mian Ahmad Walhari",
    "gn:country_code":"PK",
    "gn:dem":9,
    "gn:feature_class":"P",
    "gn:feature_code":"PPL",
    "gn:name":"Goth Mian Ahmad Walhari",
    "gn:population":0,
    "gn:timezone":"Asia/Karachi",
    "iso:country":"PK",
    "name:und_x_variant":[
        "Mi\u0101n Ahmad Walh\u0101ri"
    ],
    "wof:name":"Goth Mian Ahmad Walhari",
    "wof:placetype":"locality"
},
  "geometry": {"coordinates":[69.61433000000001,25.43437],"type":"Point"}
}