{
  "type": "Feature",
  "properties": {
    "gn:admin1_code":"6",
    "gn:asciiname":"Kuna",
    "gn:country_code":"PK",
    "gn:dem":1435,
    "gn:feature_class":"P",
    "gn:feature_code":"PPL",
    "gn:name":"Kuna",
    "gn:population":0,
    "gn:timezone":"Asia/Karachi",
    "iso:country":"PK",
    "name:und_x_variant":[
        "K\u016bnal",
        "K\u016bna"
    ],
    "wof:name":"Kuna",
    "wof:placetype":"locality"
},
  "geometry": {"coordinates":[73.85236999999999,34.17501],"type":"Point"}
}