{
  "type": "Feature",
  "properties": {
    "gn:admin1_code":"6",
    "gn:asciiname":"Kuna",
    "gn:country_code":"PK",
    "gn:dem":1435,
    "gn:feature_class":"P",
    "gn:feature_code":"PPL",
    "gn:name":"Kuna",
    "gn:population":0,
    "gn:timezone":"Asia/Karachi",
    "iso:country":"PK",
    "name:bos_x_preferred":[
        "Kuna"
    ],
    "name:cat_x_preferred":[
        "Kuna"
    ],
    "name:ceb_x_preferred":[
        "Kuna"
    ],
    "name:ces_x_preferred":[
        "Kuna"
    ],
    "name:deu_x_preferred":[
        "Kuna"
    ],
    "name:fas_x_preferred":[
        "\u06a9\u0648\u0646\u0627"
    ],
    "name:fra_x_preferred":[
        "Kuna"
    ],
    "name:hrv_x_preferred":[
        "Kuna"
    ],
    "name:hun_x_preferred":[
        "Kuna"
    ],
    "name:lit_x_preferred":[
        "Kuna"
    ],
    "name:nld_x_preferred":[
        "Kuna"
    ],
    "name:nno_x_preferred":[
        "Kuna"
    ],
    "name:nor_x_preferred":[
        "Kuna"
    ],
    "name:pol_x_preferred":[
        "Kuna"
    ],
    "name:por_x_preferred":[
        "Kuna"
    ],
    "name:ron_x_preferred":[
        "Kuna"
    ],
    "name:rus_x_preferred":[
        "\u041a\u0443\u043d\u0430"
    ],
    "name:slk_x_preferred":[
        "Kuna"
    ],
    "name:slv_x_preferred":[
        "Kuna"
    ],
    "name:spa_x_preferred":[
        "Kuna"
    ],
    "name:srp_x_preferred":[
        "\u041a\u0443\u043d\u0430"
    ],
    "name:swe_x_preferred":[
        "Kuna"
    ],
    "name:ukr_x_preferred":[
        "\u041a\u0443\u043d\u0430"
    ],
    "name:und_x_variant":[
        "K\u016bnal",
        "K\u016bna"
    ],
    "wof:name":"Kuna",
    "wof:placetype":"locality"
},
  "geometry": {"coordinates":[73.85236999999999,34.17501],"type":"Point"}
}