{
  "type": "Feature",
  "properties": {
    "gn:admin1_code":"4.0",
    "gn:asciiname":"Bal Shahan",
    "gn:country_code":"PK",
    "gn:dem":256,
    "gn:feature_class":"P",
    "gn:feature_code":"PPL",
    "gn:name":"Bal Shahan",
    "gn:population":0,
    "gn:timezone":"Asia/Karachi",
    "iso:country":"PK",
    "name:und_x_variant":[
        "B\u0101l"
    ],
    "wof:name":"Bal Shahan",
    "wof:placetype":"locality"
},
  "geometry": {"coordinates":[74.86145,32.25952],"type":"Point"}
}