{
  "type": "Feature",
  "properties": {
    "gn:admin1_code":"2.0",
    "gn:asciiname":"Ismail Shahr",
    "gn:country_code":"PK",
    "gn:dem":941,
    "gn:feature_class":"P",
    "gn:feature_code":"PPL",
    "gn:name":"Ismail Shahr",
    "gn:population":0,
    "gn:timezone":"Asia/Karachi",
    "iso:country":"PK",
    "wof:name":"Ismail Shahr",
    "wof:placetype":"locality"
},
  "geometry": {"coordinates":[68.70649,30.00218],"type":"Point"}
}