{
  "type": "Feature",
  "properties": {
    "gn:admin1_code":"5.0",
    "gn:asciiname":"Ghazi ji Dhani",
    "gn:country_code":"PK",
    "gn:dem":119,
    "gn:feature_class":"P",
    "gn:feature_code":"PPL",
    "gn:name":"Ghazi ji Dhani",
    "gn:population":0,
    "gn:timezone":"Asia/Karachi",
    "iso:country":"PK",
    "wof:name":"Ghazi ji Dhani",
    "wof:placetype":"locality"
},
  "geometry": {"coordinates":[70.35069,25.09607],"type":"Point"}
}