{
  "type": "Feature",
  "properties": {
    "gn:admin1_code":"04",
    "gn:asciiname":"Chak Twenty -Eleven Left",
    "gn:country_code":"PK",
    "gn:dem":152,
    "gn:feature_class":"P",
    "gn:feature_code":"PPL",
    "gn:name":"Chak Twenty -Eleven Left",
    "gn:population":0,
    "gn:timezone":"Asia/Karachi",
    "iso:country":"PK",
    "name:und_x_variant":[
        "Muhammad Nagar"
    ],
    "wof:name":"Chak Twenty -Eleven Left",
    "wof:placetype":"locality"
},
  "geometry": {"coordinates":[72.77995,30.41365],"type":"Point"}
}