{
  "type": "Feature",
  "properties": {
    "gn:admin1_code":"4",
    "gn:asciiname":"Chak Thirty-four -One A Left",
    "gn:country_code":"PK",
    "gn:dem":188,
    "gn:feature_class":"P",
    "gn:feature_code":"PPL",
    "gn:name":"Chak Thirty-four -One A Left",
    "gn:population":0,
    "gn:timezone":"Asia/Karachi",
    "iso:country":"PK",
    "name:und_x_variant":[
        "Chak Thirty-four-One A L"
    ],
    "wof:name":"Chak Thirty-four -One A Left",
    "wof:placetype":"locality"
},
  "geometry": {"coordinates":[73.68879,30.88227],"type":"Point"}
}