{
  "type": "Feature",
  "properties": {
    "gn:admin1_code":"6.0",
    "gn:asciiname":"Dehri Topi",
    "gn:country_code":"PK",
    "gn:dem":1541,
    "gn:feature_class":"P",
    "gn:feature_code":"PPL",
    "gn:name":"Dehri Topi",
    "gn:population":0,
    "gn:timezone":"Asia/Karachi",
    "iso:country":"PK",
    "wof:name":"Dehri Topi",
    "wof:placetype":"locality"
},
  "geometry": {"coordinates":[73.77719999999999,33.90127],"type":"Point"}
}