{
  "type": "Feature",
  "properties": {
    "gn:admin1_code":"02",
    "gn:asciiname":"Shah Alizai",
    "gn:country_code":"PK",
    "gn:dem":1739,
    "gn:feature_class":"P",
    "gn:feature_code":"PPL",
    "gn:name":"Shah Alizai",
    "gn:population":0,
    "gn:timezone":"Asia/Karachi",
    "iso:country":"PK",
    "wof:name":"Shah Alizai",
    "wof:placetype":"locality"
},
  "geometry": {"coordinates":[66.55176999999999,29.41048],"type":"Point"}
}