{
  "type": "Feature",
  "properties": {
    "gn:admin1_code":"02",
    "gn:asciiname":"Tagas",
    "gn:country_code":"PK",
    "gn:dem":1170,
    "gn:feature_class":"P",
    "gn:feature_code":"PPL",
    "gn:name":"Tagas",
    "gn:population":0,
    "gn:timezone":"Asia/Karachi",
    "iso:country":"PK",
    "wof:name":"Tagas",
    "wof:placetype":"locality"
},
  "geometry": {"coordinates":[64.53333000000001,27.11667000000001],"type":"Point"}
}