{
  "type": "Feature",
  "properties": {
    "gn:admin1_code":"2.0",
    "gn:asciiname":"Mirdabad Baluch Kili",
    "gn:country_code":"PK",
    "gn:dem":1516,
    "gn:feature_class":"P",
    "gn:feature_code":"PPL",
    "gn:name":"Mirdabad Baluch Kili",
    "gn:population":0,
    "gn:timezone":"Asia/Karachi",
    "iso:country":"PK",
    "wof:name":"Mirdabad Baluch Kili",
    "wof:placetype":"locality"
},
  "geometry": {"coordinates":[66.62569000000001,30.25127],"type":"Point"}
}