{
  "type": "Feature",
  "properties": {
    "gn:admin1_code":"7.0",
    "gn:asciiname":"Chaino",
    "gn:country_code":"PK",
    "gn:dem":3002,
    "gn:feature_class":"P",
    "gn:feature_code":"PPL",
    "gn:name":"Chaino",
    "gn:population":0,
    "gn:timezone":"Asia/Karachi",
    "iso:country":"PK",
    "wof:name":"Chaino",
    "wof:placetype":"locality"
},
  "geometry": {"coordinates":[75.3116,35.4616],"type":"Point"}
}