{
  "type": "Feature",
  "properties": {
    "gn:admin1_code":"5.0",
    "gn:asciiname":"Panjo",
    "gn:country_code":"PK",
    "gn:dem":5,
    "gn:feature_class":"P",
    "gn:feature_code":"PPL",
    "gn:name":"Panjo",
    "gn:population":0,
    "gn:timezone":"Asia/Karachi",
    "iso:country":"PK",
    "wof:name":"Panjo",
    "wof:placetype":"locality"
},
  "geometry": {"coordinates":[67.63583,24.56556],"type":"Point"}
}