{
  "type": "Feature",
  "properties": {
    "gn:admin1_code":"4.0",
    "gn:asciiname":"Basti Karim Bakhsh",
    "gn:country_code":"PK",
    "gn:dem":112,
    "gn:feature_class":"P",
    "gn:feature_code":"PPL",
    "gn:name":"Basti Karim Bakhsh",
    "gn:population":0,
    "gn:timezone":"Asia/Karachi",
    "iso:country":"PK",
    "name:eng_x_preferred":[
        "Basti Karim Bakhsh"
    ],
    "wof:name":"Basti Karim Bakhsh",
    "wof:placetype":"locality"
},
  "geometry": {"coordinates":[71.51309000000001,29.21773],"type":"Point"}
}