{
  "type": "Feature",
  "properties": {
    "gn:admin1_code":"5.0",
    "gn:asciiname":"Nikna",
    "gn:country_code":"PK",
    "gn:dem":43,
    "gn:feature_class":"P",
    "gn:feature_code":"PPL",
    "gn:name":"Nikna",
    "gn:population":0,
    "gn:timezone":"Asia/Karachi",
    "iso:country":"PK",
    "name:und_x_variant":[
        "Nikno"
    ],
    "wof:name":"Nikna",
    "wof:placetype":"locality"
},
  "geometry": {"coordinates":[69.96411999999999,24.63242],"type":"Point"}
}