{
  "type": "Feature",
  "properties": {
    "gn:admin1_code":"4.0",
    "gn:asciiname":"Mastiwala",
    "gn:country_code":"PK",
    "gn:dem":239,
    "gn:feature_class":"P",
    "gn:feature_code":"PPL",
    "gn:name":"Mastiwala",
    "gn:population":0,
    "gn:timezone":"Asia/Karachi",
    "iso:country":"PK",
    "name:und_x_variant":[
        "Masti Khel\u0101nw\u0101la"
    ],
    "wof:name":"Mastiwala",
    "wof:placetype":"locality"
},
  "geometry": {"coordinates":[71.64145000000001,32.65825],"type":"Point"}
}