{
  "type": "Feature",
  "properties": {
    "gn:admin1_code":"4",
    "gn:asciiname":"Attaabab",
    "gn:country_code":"PK",
    "gn:dem":191,
    "gn:feature_class":"P",
    "gn:feature_code":"PPL",
    "gn:name":"Attaabab",
    "gn:population":0,
    "gn:timezone":"Asia/Karachi",
    "iso:country":"PK",
    "name:und_x_variant":[
        "Ataabad Lohri",
        "Ata\u0101b\u0101d Noon",
        "Attaabab"
    ],
    "wof:name":"Attaabab",
    "wof:placetype":"locality"
},
  "geometry": {"coordinates":[72.76548000000003,32.29127],"type":"Point"}
}