{
  "type": "Feature",
  "properties": {
    "gn:admin1_code":"3.0",
    "gn:asciiname":"Paroha",
    "gn:country_code":"PK",
    "gn:dem":1468,
    "gn:feature_class":"P",
    "gn:feature_code":"PPL",
    "gn:name":"Paroha",
    "gn:population":0,
    "gn:timezone":"Asia/Karachi",
    "iso:country":"PK",
    "name:tam_x_preferred":[
        "\u0baa\u0bb0\u0bcb\u0b95\u0bbe"
    ],
    "wof:name":"Paroha",
    "wof:placetype":"locality"
},
  "geometry": {"coordinates":[73.1591,35.3714],"type":"Point"}
}