{
  "type": "Feature",
  "properties": {
    "gn:admin1_code":"4",
    "gn:asciiname":"Chah Anar",
    "gn:country_code":"PK",
    "gn:dem":150,
    "gn:feature_class":"P",
    "gn:feature_code":"PPL",
    "gn:name":"Chah Anar",
    "gn:population":0,
    "gn:timezone":"Asia/Karachi",
    "iso:country":"PK",
    "name:und_x_variant":[
        "Ch\u0101h Onar"
    ],
    "wof:name":"Chah Anar",
    "wof:placetype":"locality"
},
  "geometry": {"coordinates":[71.82748000000002,30.94636],"type":"Point"}
}