{
  "type": "Feature",
  "properties": {
    "gn:admin1_code":"3",
    "gn:asciiname":"Marchinai",
    "gn:country_code":"PK",
    "gn:dem":1486,
    "gn:feature_class":"P",
    "gn:feature_code":"PPL",
    "gn:name":"Marchinai",
    "gn:population":0,
    "gn:timezone":"Asia/Karachi",
    "iso:country":"PK",
    "wof:name":"Marchinai",
    "wof:placetype":"locality"
},
  "geometry": {"coordinates":[72.49423,35.10572],"type":"Point"}
}