{
  "type": "Feature",
  "properties": {
    "gn:admin1_code":"3.0",
    "gn:asciiname":"Sarbugai",
    "gn:country_code":"PK",
    "gn:dem":525,
    "gn:feature_class":"P",
    "gn:feature_code":"PPL",
    "gn:name":"Sarbugai",
    "gn:population":0,
    "gn:timezone":"Asia/Karachi",
    "iso:country":"PK",
    "wof:name":"Sarbugai",
    "wof:placetype":"locality"
},
  "geometry": {"coordinates":[72.82595999999999,34.5152],"type":"Point"}
}