{
  "type": "Feature",
  "properties": {
    "gn:admin1_code":"4",
    "gn:asciiname":"Chak Eighty-eight South Branch",
    "gn:country_code":"PK",
    "gn:dem":190,
    "gn:feature_class":"P",
    "gn:feature_code":"PPL",
    "gn:name":"Chak Eighty-eight South Branch",
    "gn:population":0,
    "gn:timezone":"Asia/Karachi",
    "iso:country":"PK",
    "name:und_x_variant":[
        "Chak Eighty-eight SB"
    ],
    "wof:name":"Chak Eighty-eight South Branch",
    "wof:placetype":"locality"
},
  "geometry": {"coordinates":[72.79713000000002,32.04229],"type":"Point"}
}