{
  "type": "Feature",
  "properties": {
    "gn:admin1_code":"5",
    "gn:asciiname":"Sunwara Laghari",
    "gn:country_code":"PK",
    "gn:dem":17,
    "gn:feature_class":"P",
    "gn:feature_code":"PPL",
    "gn:name":"Sunw\u0101ra Lagh\u0101ri",
    "gn:population":0,
    "gn:timezone":"Asia/Karachi",
    "iso:country":"PK",
    "wof:name":"Sunwara Laghari",
    "wof:placetype":"locality"
},
  "geometry": {"coordinates":[68.575,25.08889],"type":"Point"}
}