{
  "type": "Feature",
  "properties": {
    "gn:admin1_code":"1.0",
    "gn:asciiname":"Shalzara",
    "gn:country_code":"PK",
    "gn:dem":1941,
    "gn:feature_class":"P",
    "gn:feature_code":"PPL",
    "gn:name":"Shalzara",
    "gn:population":0,
    "gn:timezone":"Asia/Karachi",
    "iso:country":"PK",
    "wof:name":"Shalzara",
    "wof:placetype":"locality"
},
  "geometry": {"coordinates":[70.85514999999999,33.76976],"type":"Point"}
}