{
  "type": "Feature",
  "properties": {
    "gn:admin1_code":"6",
    "gn:asciiname":"Rohela",
    "gn:country_code":"PK",
    "gn:dem":288,
    "gn:feature_class":"P",
    "gn:feature_code":"PPL",
    "gn:name":"Rohela",
    "gn:population":0,
    "gn:timezone":"Asia/Karachi",
    "iso:country":"PK",
    "name:und_x_variant":[
        "Rehia"
    ],
    "wof:name":"Rohela",
    "wof:placetype":"locality"
},
  "geometry": {"coordinates":[74.33313000000003,32.79551],"type":"Point"}
}