{
  "type": "Feature",
  "properties": {
    "gn:admin1_code":"4.0",
    "gn:asciiname":"Chak Two Hundred Five Murad",
    "gn:country_code":"PK",
    "gn:dem":151,
    "gn:feature_class":"P",
    "gn:feature_code":"PPL",
    "gn:name":"Chak Two Hundred Five Murad",
    "gn:population":0,
    "gn:timezone":"Asia/Karachi",
    "iso:country":"PK",
    "wof:name":"Chak Two Hundred Five Murad",
    "wof:placetype":"locality"
},
  "geometry": {"coordinates":[72.79161999999999,29.48803],"type":"Point"}
}