{
  "type": "Feature",
  "properties": {
    "gn:admin1_code":"3.0",
    "gn:asciiname":"Habibullah Colony",
    "gn:country_code":"PK",
    "gn:dem":1226,
    "gn:feature_class":"P",
    "gn:feature_code":"PPL",
    "gn:name":"Habibullah Colony",
    "gn:population":0,
    "gn:timezone":"Asia/Karachi",
    "iso:country":"PK",
    "wof:name":"Habibullah Colony",
    "wof:placetype":"locality"
},
  "geometry": {"coordinates":[73.24566999999998,34.18697],"type":"Point"}
}