{
  "type": "Feature",
  "properties": {
    "gn:admin1_code":"4",
    "gn:asciiname":"Ratteki",
    "gn:country_code":"PK",
    "gn:dem":171,
    "gn:feature_class":"P",
    "gn:feature_code":"PPL",
    "gn:name":"Ratteki",
    "gn:population":0,
    "gn:timezone":"Asia/Karachi",
    "iso:country":"PK",
    "name:und_x_variant":[
        "T\u0101ruke Ratteke"
    ],
    "wof:name":"Ratteki",
    "wof:placetype":"locality"
},
  "geometry": {"coordinates":[73.61566999999999,30.28426],"type":"Point"}
}