{
  "type": "Feature",
  "properties": {
    "gn:admin1_code":"4.0",
    "gn:asciiname":"Dhok Tas",
    "gn:country_code":"PK",
    "gn:dem":401,
    "gn:feature_class":"P",
    "gn:feature_code":"PPL",
    "gn:name":"Dhok Tas",
    "gn:population":0,
    "gn:timezone":"Asia/Karachi",
    "iso:country":"PK",
    "wof:name":"Dhok Tas",
    "wof:placetype":"locality"
},
  "geometry": {"coordinates":[72.62378000000002,33.81662],"type":"Point"}
}