{
  "type": "Feature",
  "properties": {
    "gn:admin1_code":"3.0",
    "gn:asciiname":"Falan Dheri",
    "gn:country_code":"PK",
    "gn:dem":337,
    "gn:feature_class":"P",
    "gn:feature_code":"PPL",
    "gn:name":"Falan Dheri",
    "gn:population":0,
    "gn:timezone":"Asia/Karachi",
    "iso:country":"PK",
    "wof:name":"Falan Dheri",
    "wof:placetype":"locality"
},
  "geometry": {"coordinates":[71.45430999999998,34.12528],"type":"Point"}
}