{
  "type": "Feature",
  "properties": {
    "gn:admin1_code":"1.0",
    "gn:asciiname":"Mamadi",
    "gn:country_code":"PK",
    "gn:dem":695,
    "gn:feature_class":"P",
    "gn:feature_code":"PPL",
    "gn:name":"Mamadi",
    "gn:population":0,
    "gn:timezone":"Asia/Karachi",
    "iso:country":"PK",
    "wof:name":"Mamadi",
    "wof:placetype":"locality"
},
  "geometry": {"coordinates":[70.24005,32.95757],"type":"Point"}
}