{
  "type": "Feature",
  "properties": {
    "gn:admin1_code":"2.0",
    "gn:asciiname":"Ghaibizai Kili",
    "gn:country_code":"PK",
    "gn:dem":1555,
    "gn:feature_class":"P",
    "gn:feature_code":"PPL",
    "gn:name":"Ghaibizai Kili",
    "gn:population":0,
    "gn:timezone":"Asia/Karachi",
    "iso:country":"PK",
    "name:eng_x_preferred":[
        "Ghaibizai Kili"
    ],
    "name:und_x_variant":[
        "Ghaibb\u012bzi Kili"
    ],
    "wof:name":"Ghaibizai Kili",
    "wof:placetype":"locality"
},
  "geometry": {"coordinates":[68.64041,30.8475],"type":"Point"}
}