{
  "type": "Feature",
  "properties": {
    "gn:admin1_code":"7.0",
    "gn:asciiname":"Giriakhdo",
    "gn:country_code":"PK",
    "gn:dem":2509,
    "gn:feature_class":"P",
    "gn:feature_code":"PPL",
    "gn:name":"Giriakhdo",
    "gn:population":0,
    "gn:timezone":"Asia/Karachi",
    "iso:country":"PK",
    "name:und_x_variant":[
        "Ahmad\u0101b\u0101d"
    ],
    "wof:name":"Giriakhdo",
    "wof:placetype":"locality"
},
  "geometry": {"coordinates":[76.18621,34.86514],"type":"Point"}
}