{
  "type": "Feature",
  "properties": {
    "gn:admin1_code":"4.0",
    "gn:asciiname":"Amirpur",
    "gn:country_code":"PK",
    "gn:dem":173,
    "gn:feature_class":"P",
    "gn:feature_code":"PPL",
    "gn:name":"Amirpur",
    "gn:population":0,
    "gn:timezone":"Asia/Karachi",
    "iso:country":"PK",
    "name:und_x_variant":[
        "Jasrat"
    ],
    "wof:name":"Amirpur",
    "wof:placetype":"locality"
},
  "geometry": {"coordinates":[72.87735000000001,31.67667],"type":"Point"}
}