{
  "type": "Feature",
  "properties": {
    "gn:admin1_code":"04",
    "gn:asciiname":"Salai",
    "gn:country_code":"PK",
    "gn:dem":688,
    "gn:feature_class":"P",
    "gn:feature_code":"PPL",
    "gn:name":"Salai",
    "gn:population":0,
    "gn:timezone":"Asia/Karachi",
    "iso:country":"PK",
    "name:fas_x_preferred":[
        "\u0633\u0644\u0648\u06cc\u06cc"
    ],
    "name:und_x_variant":[
        "Salooi",
        "Saloi",
        "Salai"
    ],
    "name:urd_x_preferred":[
        "\u0633\u0644\u0648\u0626\u06cc"
    ],
    "wof:name":"Salai",
    "wof:placetype":"locality"
},
  "geometry": {"coordinates":[73.09609,32.74532],"type":"Point"}
}