{
  "type": "Feature",
  "properties": {
    "gn:admin1_code":"3.0",
    "gn:asciiname":"Qurki",
    "gn:country_code":"PK",
    "gn:dem":3609,
    "gn:feature_class":"P",
    "gn:feature_code":"PPL",
    "gn:name":"Qurki",
    "gn:population":0,
    "gn:timezone":"Asia/Karachi",
    "iso:country":"PK",
    "wof:name":"Qurki",
    "wof:placetype":"locality"
},
  "geometry": {"coordinates":[73.95789000000001,34.90201],"type":"Point"}
}