{
  "type": "Feature",
  "properties": {
    "gn:admin1_code":"4",
    "gn:asciiname":"Jhok Sangiwali",
    "gn:country_code":"PK",
    "gn:dem":183,
    "gn:feature_class":"P",
    "gn:feature_code":"PPL",
    "gn:name":"Jhok Sangiwali",
    "gn:population":0,
    "gn:timezone":"Asia/Karachi",
    "iso:country":"PK",
    "name:und_x_variant":[
        "Jhok M\u0101ng\u012bw\u0101li"
    ],
    "wof:name":"Jhok Sangiwali",
    "wof:placetype":"locality"
},
  "geometry": {"coordinates":[70.59406,30.68342],"type":"Point"}
}