{
  "type": "Feature",
  "properties": {
    "gn:admin1_code":"5.0",
    "gn:asciiname":"Goth Yusuf Sonharo",
    "gn:country_code":"PK",
    "gn:dem":153,
    "gn:feature_class":"P",
    "gn:feature_code":"PPL",
    "gn:name":"Goth Yusuf Sonharo",
    "gn:population":0,
    "gn:timezone":"Asia/Karachi",
    "iso:country":"PK",
    "name:und_x_variant":[
        "Goth M\u016bsa"
    ],
    "wof:name":"Goth Yusuf Sonharo",
    "wof:placetype":"locality"
},
  "geometry": {"coordinates":[67.82289,25.58898],"type":"Point"}
}