{
  "type": "Feature",
  "properties": {
    "gn:admin1_code":"05",
    "gn:asciiname":"Goth Soki",
    "gn:country_code":"PK",
    "gn:dem":1,
    "gn:feature_class":"P",
    "gn:feature_code":"PPL",
    "gn:name":"Goth Soki",
    "gn:population":0,
    "gn:timezone":"Asia/Karachi",
    "iso:country":"PK",
    "name:und_x_variant":[
        "Soki"
    ],
    "wof:name":"Goth Soki",
    "wof:placetype":"locality"
},
  "geometry": {"coordinates":[67.37137,24.22296],"type":"Point"}
}