{
  "type": "Feature",
  "properties": {
    "gn:admin1_code":"4",
    "gn:asciiname":"Gohar Khanwala",
    "gn:country_code":"PK",
    "gn:dem":190,
    "gn:feature_class":"P",
    "gn:feature_code":"PPL",
    "gn:name":"Gohar Khanwala",
    "gn:population":0,
    "gn:timezone":"Asia/Karachi",
    "iso:country":"PK",
    "name:und_x_variant":[
        "Gauhar Kh\u0101n"
    ],
    "wof:name":"Gohar Khanwala",
    "wof:placetype":"locality"
},
  "geometry": {"coordinates":[71.48239000000002,32.01674000000001],"type":"Point"}
}