{
  "type": "Feature",
  "properties": {
    "gn:admin1_code":"4",
    "gn:asciiname":"Shah Abbas",
    "gn:country_code":"PK",
    "gn:dem":142,
    "gn:feature_class":"P",
    "gn:feature_code":"PPL",
    "gn:name":"Shah Abbas",
    "gn:population":0,
    "gn:timezone":"Asia/Karachi",
    "iso:country":"PK",
    "name:ara_x_preferred":[
        "\u0634\u0627\u0647 \u0639\u0628\u0627\u0633"
    ],
    "name:ces_x_preferred":[
        "\u0160\u00e1h Abb\u00e1s"
    ],
    "name:nld_x_preferred":[
        "Shah Abbas"
    ],
    "name:spa_x_preferred":[
        "Shah Abbas"
    ],
    "name:und_x_variant":[
        "Ab\u0101d Sh\u0101h"
    ],
    "name:vie_x_preferred":[
        "Shah Abbas"
    ],
    "wof:name":"Shah Abbas",
    "wof:placetype":"locality"
},
  "geometry": {"coordinates":[72.67619000000001,29.78671],"type":"Point"}
}