{
  "type": "Feature",
  "properties": {
    "gn:admin1_code":"5.0",
    "gn:asciiname":"Goth Ahmad Khan Kalwati Baloch",
    "gn:country_code":"PK",
    "gn:dem":6,
    "gn:feature_class":"P",
    "gn:feature_code":"PPL",
    "gn:name":"Goth Ahmad Khan Kalwati Baloch",
    "gn:population":0,
    "gn:timezone":"Asia/Karachi",
    "iso:country":"PK",
    "name:und_x_variant":[
        "Ahmad Kh\u0101n Kalwati Baloch"
    ],
    "wof:name":"Goth Ahmad Khan Kalwati Baloch",
    "wof:placetype":"locality"
},
  "geometry": {"coordinates":[67.67452,24.53806],"type":"Point"}
}