{
  "type": "Feature",
  "properties": {
    "gn:admin1_code":"04",
    "gn:asciiname":"Chak One Hundred Four -Ten Right",
    "gn:country_code":"PK",
    "gn:dem":129,
    "gn:feature_class":"P",
    "gn:feature_code":"PPL",
    "gn:name":"Chak One Hundred Four -Ten Right",
    "gn:population":0,
    "gn:timezone":"Asia/Karachi",
    "iso:country":"PK",
    "name:und_x_variant":[
        "Chak One Hundred Four",
        "Mughalw\u0101la Araiy\u0101n",
        "Chak One Hundred Four -Ten Right"
    ],
    "wof:name":"Chak One Hundred Four -Ten Right",
    "wof:placetype":"locality"
},
  "geometry": {"coordinates":[71.89908,30.09024],"type":"Point"}
}