{
  "type": "Feature",
  "properties": {
    "gn:admin1_code":"5",
    "gn:asciiname":"Pir Mashaque",
    "gn:country_code":"PK",
    "gn:dem":38,
    "gn:feature_class":"P",
    "gn:feature_code":"PPL",
    "gn:name":"Pir Mashaque",
    "gn:population":0,
    "gn:timezone":"Asia/Karachi",
    "iso:country":"PK",
    "name:und_x_variant":[
        "P\u012br Shaf\u0101q"
    ],
    "wof:name":"Pir Mashaque",
    "wof:placetype":"locality"
},
  "geometry": {"coordinates":[67.68364,26.74636],"type":"Point"}
}