{
  "type": "Feature",
  "properties": {
    "gn:admin1_code":"5",
    "gn:asciiname":"Ghulam Qadir",
    "gn:country_code":"PK",
    "gn:dem":28,
    "gn:feature_class":"P",
    "gn:feature_code":"PPL",
    "gn:name":"Ghulam Qadir",
    "gn:population":0,
    "gn:timezone":"Asia/Karachi",
    "iso:country":"PK",
    "name:und_x_variant":[
        "Ghul\u0101m Q\u0101dir Zerd\u0101ri"
    ],
    "wof:name":"Ghulam Qadir",
    "wof:placetype":"locality"
},
  "geometry": {"coordinates":[68.53185000000001,26.00661],"type":"Point"}
}