{
  "type": "Feature",
  "properties": {
    "gn:admin1_code":"8.0",
    "gn:asciiname":"Humak",
    "gn:country_code":"PK",
    "gn:dem":439,
    "gn:feature_class":"P",
    "gn:feature_code":"PPL",
    "gn:name":"Humak",
    "gn:population":0,
    "gn:timezone":"Asia/Karachi",
    "iso:country":"PK",
    "name:eng_x_preferred":[
        "Humak"
    ],
    "name:urd_x_preferred":[
        "\u06c1\u0645\u06a9"
    ],
    "wof:name":"Humak",
    "wof:placetype":"locality"
},
  "geometry": {"coordinates":[73.12618000000001,33.53796],"type":"Point"}
}