{
  "type": "Feature",
  "properties": {
    "gn:admin1_code":"3.0",
    "gn:asciiname":"Mozo Parwak",
    "gn:country_code":"PK",
    "gn:dem":2231,
    "gn:feature_class":"P",
    "gn:feature_code":"PPL",
    "gn:name":"Mozo Parwak",
    "gn:population":0,
    "gn:timezone":"Asia/Karachi",
    "iso:country":"PK",
    "wof:name":"Mozo Parwak",
    "wof:placetype":"locality"
},
  "geometry": {"coordinates":[72.39202,36.27323],"type":"Point"}
}