{
  "type": "Feature",
  "properties": {
    "gn:admin1_code":"7.0",
    "gn:asciiname":"Buyun",
    "gn:country_code":"PK",
    "gn:dem":3873,
    "gn:feature_class":"P",
    "gn:feature_code":"PPL",
    "gn:name":"Buyun",
    "gn:population":0,
    "gn:timezone":"Asia/Karachi",
    "iso:country":"PK",
    "wof:name":"Buyun",
    "wof:placetype":"locality"
},
  "geometry": {"coordinates":[73.34775999999999,35.75203],"type":"Point"}
}