{
  "type": "Feature",
  "properties": {
    "gn:admin1_code":"4",
    "gn:asciiname":"Chak One Hundred Thirty-seven Southern Branch",
    "gn:country_code":"PK",
    "gn:dem":180,
    "gn:feature_class":"P",
    "gn:feature_code":"PPL",
    "gn:name":"Chak One Hundred Thirty-seven Southern Branch",
    "gn:population":0,
    "gn:timezone":"Asia/Karachi",
    "iso:country":"PK",
    "name:und_x_variant":[
        "Chak One Hundred Thirty-seven SB"
    ],
    "wof:name":"Chak One Hundred Thirty-seven Southern Branch",
    "wof:placetype":"locality"
},
  "geometry": {"coordinates":[72.58459000000001,31.81525],"type":"Point"}
}