{
  "type": "Feature",
  "properties": {
    "gn:admin1_code":"01",
    "gn:asciiname":"Akal Khel",
    "gn:country_code":"PK",
    "gn:dem":2106,
    "gn:feature_class":"P",
    "gn:feature_code":"PPL",
    "gn:name":"Akal Khel",
    "gn:population":0,
    "gn:timezone":"Asia/Karachi",
    "iso:country":"PK",
    "wof:name":"Akal Khel",
    "wof:placetype":"locality"
},
  "geometry": {"coordinates":[70.64490000000001,33.81742],"type":"Point"}
}