{
  "type": "Feature",
  "properties": {
    "gn:admin1_code":"4.0",
    "gn:asciiname":"Kot Dost Muhammad Yousafabad",
    "gn:country_code":"PK",
    "gn:dem":135,
    "gn:feature_class":"P",
    "gn:feature_code":"PPL",
    "gn:name":"Kot Dost Muhammad Yousafabad",
    "gn:population":0,
    "gn:timezone":"Asia/Karachi",
    "iso:country":"PK",
    "wof:name":"Kot Dost Muhammad Yousafabad",
    "wof:placetype":"locality"
},
  "geometry": {"coordinates":[71.93138,30.31283],"type":"Point"}
}