{
  "type": "Feature",
  "properties": {
    "gn:admin1_code":"4.0",
    "gn:asciiname":"Mohsinabad",
    "gn:country_code":"PK",
    "gn:dem":188,
    "gn:feature_class":"P",
    "gn:feature_code":"PPL",
    "gn:name":"Mohsinabad",
    "gn:population":0,
    "gn:timezone":"Asia/Karachi",
    "iso:country":"PK",
    "wof:name":"Mohsinabad",
    "wof:placetype":"locality"
},
  "geometry": {"coordinates":[72.85443000000002,31.85644000000001],"type":"Point"}
}