{
  "type": "Feature",
  "properties": {
    "gn:admin1_code":"04",
    "gn:asciiname":"Mandhon",
    "gn:cc2":"PK",
    "gn:country_code":"PK",
    "gn:dem":175,
    "gn:feature_class":"P",
    "gn:feature_code":"PPL",
    "gn:name":"Mandhon",
    "gn:population":0,
    "gn:timezone":"Asia/Karachi",
    "iso:country":"PK",
    "name:und_x_variant":[
        "Modhawa",
        "Mandhon"
    ],
    "wof:name":"Mandhon",
    "wof:placetype":"locality"
},
  "geometry": {"coordinates":[72.98333000000002,31.11667000000001],"type":"Point"}
}