{
  "type": "Feature",
  "properties": {
    "gn:admin1_code":"5.0",
    "gn:asciiname":"Goth Rohi Rind",
    "gn:country_code":"PK",
    "gn:dem":6,
    "gn:feature_class":"P",
    "gn:feature_code":"PPL",
    "gn:name":"Goth Rohi Rind",
    "gn:population":0,
    "gn:timezone":"Asia/Karachi",
    "iso:country":"PK",
    "name:und_x_variant":[
        "Goth Dh\u0101i",
        "Goth Dahi Rind",
        "Goth Rohi Rind"
    ],
    "wof:name":"Goth Rohi Rind",
    "wof:placetype":"locality"
},
  "geometry": {"coordinates":[67.53293000000001,24.59144],"type":"Point"}
}