{
  "type": "Feature",
  "properties": {
    "gn:admin1_code":"5.0",
    "gn:asciiname":"Gazi Khan Chandio",
    "gn:country_code":"PK",
    "gn:dem":54,
    "gn:feature_class":"P",
    "gn:feature_code":"PPL",
    "gn:name":"Gazi Khan Chandio",
    "gn:population":0,
    "gn:timezone":"Asia/Karachi",
    "iso:country":"PK",
    "name:und_x_variant":[
        "Ail\u0101ni Sh\u0101h",
        "Goth Gh\u0101zi Ch\u0101ndio"
    ],
    "wof:name":"Gazi Khan Chandio",
    "wof:placetype":"locality"
},
  "geometry": {"coordinates":[68.51671999999999,27.49803],"type":"Point"}
}