{
  "type": "Feature",
  "properties": {
    "gn:admin1_code":"4",
    "gn:asciiname":"Manewala",
    "gn:country_code":"PK",
    "gn:dem":168,
    "gn:feature_class":"P",
    "gn:feature_code":"PPL",
    "gn:name":"Manewala",
    "gn:population":0,
    "gn:timezone":"Asia/Karachi",
    "iso:country":"PK",
    "name:und_x_variant":[
        "M\u0101nakw\u0101la"
    ],
    "wof:name":"Manewala",
    "wof:placetype":"locality"
},
  "geometry": {"coordinates":[71.15529000000002,31.52158],"type":"Point"}
}