{
  "type": "Feature",
  "properties": {
    "gn:admin1_code":"2",
    "gn:asciiname":"Kalandar Khan",
    "gn:country_code":"PK",
    "gn:dem":1537,
    "gn:feature_class":"P",
    "gn:feature_code":"PPL",
    "gn:name":"Kalandar Khan",
    "gn:population":0,
    "gn:timezone":"Asia/Karachi",
    "iso:country":"PK",
    "wof:name":"Kalandar Khan",
    "wof:placetype":"locality"
},
  "geometry": {"coordinates":[68.41183000000001,30.72528],"type":"Point"}
}