{
  "type": "Feature",
  "properties": {
    "gn:admin1_code":"4.0",
    "gn:asciiname":"Bhdruthi",
    "gn:country_code":"PK",
    "gn:dem":708,
    "gn:feature_class":"P",
    "gn:feature_code":"PPL",
    "gn:name":"Bhdruthi",
    "gn:population":0,
    "gn:timezone":"Asia/Karachi",
    "iso:country":"PK",
    "wof:name":"Bhdruthi",
    "wof:placetype":"locality"
},
  "geometry": {"coordinates":[73.51088,33.54658],"type":"Point"}
}