{
  "type": "Feature",
  "properties": {
    "gn:admin1_code":"3.0",
    "gn:asciiname":"Kandari Shahi",
    "gn:country_code":"PK",
    "gn:dem":2670,
    "gn:feature_class":"P",
    "gn:feature_code":"PPL",
    "gn:name":"Kandari Shahi",
    "gn:population":0,
    "gn:timezone":"Asia/Karachi",
    "iso:country":"PK",
    "name:eng_x_preferred":[
        "Kundail Sh\u0101hi"
    ],
    "wof:name":"Kandari Shahi",
    "wof:placetype":"locality"
},
  "geometry": {"coordinates":[72.17883,35.6452],"type":"Point"}
}