{
  "type": "Feature",
  "properties": {
    "gn:admin1_code":"3.0",
    "gn:asciiname":"Uchhar",
    "gn:country_code":"PK",
    "gn:dem":1207,
    "gn:feature_class":"P",
    "gn:feature_code":"PPL",
    "gn:name":"Uchhar",
    "gn:population":0,
    "gn:timezone":"Asia/Karachi",
    "iso:country":"PK",
    "wof:name":"Uchhar",
    "wof:placetype":"locality"
},
  "geometry": {"coordinates":[73.18980999999999,34.12146],"type":"Point"}
}