{
  "type": "Feature",
  "properties": {
    "gn:admin1_code":"5.0",
    "gn:asciiname":"Goth Dhani Bakhsh Sargani",
    "gn:country_code":"PK",
    "gn:dem":52,
    "gn:feature_class":"P",
    "gn:feature_code":"PPL",
    "gn:name":"Goth Dhani Bakhsh Sargani",
    "gn:population":0,
    "gn:timezone":"Asia/Karachi",
    "iso:country":"PK",
    "wof:name":"Goth Dhani Bakhsh Sargani",
    "wof:placetype":"locality"
},
  "geometry": {"coordinates":[68.18888000000001,27.13158],"type":"Point"}
}