{
  "type": "Feature",
  "properties": {
    "gn:admin1_code":"3.0",
    "gn:asciiname":"Saidullah Talao",
    "gn:country_code":"PK",
    "gn:dem":370,
    "gn:feature_class":"P",
    "gn:feature_code":"PPL",
    "gn:name":"Saidullah Talao",
    "gn:population":0,
    "gn:timezone":"Asia/Karachi",
    "iso:country":"PK",
    "wof:name":"Saidullah Talao",
    "wof:placetype":"locality"
},
  "geometry": {"coordinates":[71.5873,33.91638],"type":"Point"}
}