{
  "type": "Feature",
  "properties": {
    "gn:admin1_code":"6",
    "gn:asciiname":"Dherian",
    "gn:country_code":"PK",
    "gn:dem":1666,
    "gn:feature_class":"P",
    "gn:feature_code":"PPL",
    "gn:name":"Dherian",
    "gn:population":0,
    "gn:timezone":"Asia/Karachi",
    "iso:country":"PK",
    "wof:name":"Dherian",
    "wof:placetype":"locality"
},
  "geometry": {"coordinates":[73.45957,34.45557],"type":"Point"}
}