{
  "type": "Feature",
  "properties": {
    "gn:admin1_code":"4.0",
    "gn:asciiname":"Abdal",
    "gn:country_code":"PK",
    "gn:dem":233,
    "gn:feature_class":"P",
    "gn:feature_code":"PPL",
    "gn:name":"Abdal",
    "gn:population":0,
    "gn:timezone":"Asia/Karachi",
    "iso:country":"PK",
    "wof:name":"Abdal",
    "wof:placetype":"locality"
},
  "geometry": {"coordinates":[74.26165,32.22407],"type":"Point"}
}