{
  "type": "Feature",
  "properties": {
    "gn:admin1_code":"4.0",
    "gn:asciiname":"Abdal",
    "gn:country_code":"PK",
    "gn:dem":233,
    "gn:feature_class":"P",
    "gn:feature_code":"PPL",
    "gn:name":"Abdal",
    "gn:population":0,
    "gn:timezone":"Asia/Karachi",
    "iso:country":"PK",
    "name:ara_x_preferred":[
        "\u0623\u0628\u062f\u0627\u0644"
    ],
    "name:cat_x_preferred":[
        "Abdal"
    ],
    "name:deu_x_preferred":[
        "Abd\u0101l"
    ],
    "name:est_x_preferred":[
        "Abdaalid"
    ],
    "name:snd_x_preferred":[
        "\u0627\u0628\u062f\u0627\u0644"
    ],
    "name:tgk_x_preferred":[
        "\u0410\u0431\u0434\u043e\u043b"
    ],
    "name:tur_x_preferred":[
        "Abdal"
    ],
    "name:ukr_x_preferred":[
        "\u0410\u0431\u0434\u0430\u043b"
    ],
    "name:urd_x_preferred":[
        "\u0627\u0628\u062f\u0627\u0644"
    ],
    "wof:name":"Abdal",
    "wof:placetype":"locality"
},
  "geometry": {"coordinates":[74.26165,32.22407],"type":"Point"}
}