{
  "type": "Feature",
  "properties": {
    "gn:admin1_code":"4.0",
    "gn:asciiname":"Chhim Baluchan",
    "gn:country_code":"PK",
    "gn:dem":83,
    "gn:feature_class":"P",
    "gn:feature_code":"PPL",
    "gn:name":"Chhim Baluchan",
    "gn:population":0,
    "gn:timezone":"Asia/Karachi",
    "iso:country":"PK",
    "wof:name":"Chhim Baluchan",
    "wof:placetype":"locality"
},
  "geometry": {"coordinates":[70.38458,28.53165],"type":"Point"}
}