{
  "type": "Feature",
  "properties": {
    "gn:admin1_code":"2.0",
    "gn:asciiname":"Kili Haji Ser Khan",
    "gn:country_code":"PK",
    "gn:dem":2116,
    "gn:feature_class":"P",
    "gn:feature_code":"PPL",
    "gn:name":"Kili Haji Ser Khan",
    "gn:population":0,
    "gn:timezone":"Asia/Karachi",
    "iso:country":"PK",
    "wof:name":"Kili Haji Ser Khan",
    "wof:placetype":"locality"
},
  "geometry": {"coordinates":[67.92681,31.50198],"type":"Point"}
}