{
  "type": "Feature",
  "properties": {
    "gn:admin1_code":"7.0",
    "gn:asciiname":"Sultanabad",
    "gn:country_code":"PK",
    "gn:dem":1495,
    "gn:feature_class":"P",
    "gn:feature_code":"PPL",
    "gn:name":"Sultanabad",
    "gn:population":0,
    "gn:timezone":"Asia/Karachi",
    "iso:country":"PK",
    "name:aze_x_preferred":[
        "Sultanabad"
    ],
    "name:cat_x_preferred":[
        "Sultanabad"
    ],
    "name:deu_x_preferred":[
        "Sultanabad"
    ],
    "name:eng_x_preferred":[
        "Sultanabad"
    ],
    "name:urd_x_preferred":[
        "\u0633\u0644\u0637\u0627\u0646 \u0622\u0628\u0627\u062f"
    ],
    "wof:name":"Sultanabad",
    "wof:placetype":"locality"
},
  "geometry": {"coordinates":[74.38079999999999,35.9396],"type":"Point"}
}