{
  "type": "Feature",
  "properties": {
    "gn:admin1_code":"3.0",
    "gn:asciiname":"Daggar",
    "gn:country_code":"PK",
    "gn:dem":719,
    "gn:feature_class":"P",
    "gn:feature_code":"PPLA2",
    "gn:name":"Daggar",
    "gn:population":0,
    "gn:timezone":"Asia/Karachi",
    "iso:country":"PK",
    "name:fas_x_preferred":[
        "\u062a\u062d\u0635\u06cc\u0644 \u062f\u06af\u0631"
    ],
    "name:fra_x_preferred":[
        "Daggar"
    ],
    "name:msa_x_preferred":[
        "Daggar"
    ],
    "name:pnb_x_preferred":[
        "\u0688\u06af\u0631"
    ],
    "name:rus_x_preferred":[
        "\u0414\u0430\u0433\u0433\u0430\u0440"
    ],
    "name:swe_x_preferred":[
        "Daggar"
    ],
    "name:und_x_variant":[
        "Dagar",
        "Daggar"
    ],
    "name:urd_x_preferred":[
        "\u0688\u06af\u0631"
    ],
    "wof:name":"Daggar",
    "wof:placetype":"locality"
},
  "geometry": {"coordinates":[72.48438,34.51106],"type":"Point"}
}