{
  "type": "Feature",
  "properties": {
    "gn:admin1_code":"4.0",
    "gn:asciiname":"Mar Ban",
    "gn:country_code":"PK",
    "gn:dem":1227,
    "gn:feature_class":"P",
    "gn:feature_code":"PPL",
    "gn:name":"Mar Ban",
    "gn:population":0,
    "gn:timezone":"Asia/Karachi",
    "iso:country":"PK",
    "wof:name":"Mar Ban",
    "wof:placetype":"locality"
},
  "geometry": {"coordinates":[70.00811999999999,30.25122],"type":"Point"}
}