{
  "type": "Feature",
  "properties": {
    "gn:admin1_code":"04",
    "gn:asciiname":"Mallian Khurd",
    "gn:country_code":"PK",
    "gn:dem":212,
    "gn:feature_class":"P",
    "gn:feature_code":"PPL",
    "gn:name":"Mallian Khurd",
    "gn:population":0,
    "gn:timezone":"Asia/Karachi",
    "iso:country":"PK",
    "name:und_x_variant":[
        "Malian",
        "Malli\u0101n",
        "Mallian Khurd"
    ],
    "wof:name":"Mallian Khurd",
    "wof:placetype":"locality"
},
  "geometry": {"coordinates":[74.46993000000001,31.38614],"type":"Point"}
}