{
  "type": "Feature",
  "properties": {
    "gn:admin1_code":"5",
    "gn:asciiname":"Goth Rahuti",
    "gn:country_code":"PK",
    "gn:dem":23,
    "gn:feature_class":"P",
    "gn:feature_code":"PPL",
    "gn:name":"Goth Rahuti",
    "gn:population":0,
    "gn:timezone":"Asia/Karachi",
    "iso:country":"PK",
    "name:eng_x_preferred":[
        "Rahuti"
    ],
    "wof:name":"Goth Rahuti",
    "wof:placetype":"locality"
},
  "geometry": {"coordinates":[68.30645,25.15764],"type":"Point"}
}