{
  "type": "Feature",
  "properties": {
    "gn:admin1_code":"2.0",
    "gn:asciiname":"Akha Kaul",
    "gn:country_code":"PK",
    "gn:dem":1511,
    "gn:feature_class":"P",
    "gn:feature_code":"PPL",
    "gn:name":"Akha Kaul",
    "gn:population":0,
    "gn:timezone":"Asia/Karachi",
    "iso:country":"PK",
    "wof:name":"Akha Kaul",
    "wof:placetype":"locality"
},
  "geometry": {"coordinates":[66.75506999999999,30.72181],"type":"Point"}
}