{
  "type": "Feature",
  "properties": {
    "gn:admin1_code":"5",
    "gn:asciiname":"Goth Abdul Razzaq",
    "gn:country_code":"PK",
    "gn:dem":57,
    "gn:feature_class":"P",
    "gn:feature_code":"PPL",
    "gn:name":"Goth Abdul Razzaq",
    "gn:population":0,
    "gn:timezone":"Asia/Karachi",
    "iso:country":"PK",
    "name:und_x_variant":[
        "Abdul Raz\u0101q"
    ],
    "wof:name":"Goth Abdul Razzaq",
    "wof:placetype":"locality"
},
  "geometry": {"coordinates":[68.44025000000001,28.40024],"type":"Point"}
}