{
  "type": "Feature",
  "properties": {
    "gn:admin1_code":"4",
    "gn:asciiname":"Jaki Jamke",
    "gn:country_code":"PK",
    "gn:dem":190,
    "gn:feature_class":"P",
    "gn:feature_code":"PPL",
    "gn:name":"Jaki Jamke",
    "gn:population":0,
    "gn:timezone":"Asia/Karachi",
    "iso:country":"PK",
    "name:und_x_variant":[
        "J\u0101mke",
        "Jogi J\u0101mke",
        "Jaki Jamke"
    ],
    "wof:name":"Jaki Jamke",
    "wof:placetype":"locality"
},
  "geometry": {"coordinates":[73.2415,31.88636],"type":"Point"}
}