{
  "type": "Feature",
  "properties": {
    "gn:admin1_code":"6",
    "gn:asciiname":"Kallar",
    "gn:country_code":"PK",
    "gn:dem":394,
    "gn:feature_class":"P",
    "gn:feature_code":"PPL",
    "gn:name":"Kallar",
    "gn:population":0,
    "gn:timezone":"Asia/Karachi",
    "iso:country":"PK",
    "name:und_x_variant":[
        "Kalren"
    ],
    "wof:name":"Kallar",
    "wof:placetype":"locality"
},
  "geometry": {"coordinates":[74.26727,32.90396],"type":"Point"}
}