{
  "type": "Feature",
  "properties": {
    "gn:admin1_code":"5.0",
    "gn:asciiname":"Haji Jaro Chutto",
    "gn:country_code":"PK",
    "gn:dem":29,
    "gn:feature_class":"P",
    "gn:feature_code":"PPL",
    "gn:name":"Haji Jaro Chutto",
    "gn:population":0,
    "gn:timezone":"Asia/Karachi",
    "iso:country":"PK",
    "wof:name":"Haji Jaro Chutto",
    "wof:placetype":"locality"
},
  "geometry": {"coordinates":[68.48444000000001,26.28678],"type":"Point"}
}