{
  "type": "Feature",
  "properties": {
    "gn:admin1_code":"6",
    "gn:asciiname":"Shikhara Baihk",
    "gn:country_code":"PK",
    "gn:dem":3068,
    "gn:feature_class":"P",
    "gn:feature_code":"PPL",
    "gn:name":"Shikhara Baihk",
    "gn:population":0,
    "gn:timezone":"Asia/Karachi",
    "iso:country":"PK",
    "name:und_x_variant":[
        "Shik\u0101r Baihk"
    ],
    "wof:name":"Shikhara Baihk",
    "wof:placetype":"locality"
},
  "geometry": {"coordinates":[73.77054,34.73232],"type":"Point"}
}