{
  "type": "Feature",
  "properties": {
    "gn:admin1_code":"4.0",
    "gn:asciiname":"Malot",
    "gn:country_code":"PK",
    "gn:dem":1422,
    "gn:feature_class":"P",
    "gn:feature_code":"PPL",
    "gn:name":"Malot",
    "gn:population":0,
    "gn:timezone":"Asia/Karachi",
    "iso:country":"PK",
    "name:eng_x_preferred":[
        "Malot"
    ],
    "name:pnb_x_preferred":[
        "\u0645\u0644\u0648\u0679"
    ],
    "name:urd_x_preferred":[
        "\u0645\u0644\u0648\u0679"
    ],
    "wof:name":"Malot",
    "wof:placetype":"locality"
},
  "geometry": {"coordinates":[73.33797,33.88476],"type":"Point"}
}