{
  "type": "Feature",
  "properties": {
    "gn:admin1_code":"4",
    "gn:asciiname":"Sirmuniwala",
    "gn:country_code":"PK",
    "gn:dem":145,
    "gn:feature_class":"P",
    "gn:feature_code":"PPL",
    "gn:name":"Sirmuniwala",
    "gn:population":0,
    "gn:timezone":"Asia/Karachi",
    "iso:country":"PK",
    "wof:name":"Sirmuniwala",
    "wof:placetype":"locality"
},
  "geometry": {"coordinates":[71.13584,30.8806],"type":"Point"}
}