{
  "type": "Feature",
  "properties": {
    "gn:admin1_code":"5.0",
    "gn:asciiname":"Goth Pandi Sama",
    "gn:country_code":"PK",
    "gn:dem":12,
    "gn:feature_class":"P",
    "gn:feature_code":"PPL",
    "gn:name":"Goth Pandi Sama",
    "gn:population":0,
    "gn:timezone":"Asia/Karachi",
    "iso:country":"PK",
    "name:und_x_variant":[
        "Goth Pandi Soma"
    ],
    "wof:name":"Goth Pandi Sama",
    "wof:placetype":"locality"
},
  "geometry": {"coordinates":[68.49175,24.80436],"type":"Point"}
}