{
  "type": "Feature",
  "properties": {
    "gn:admin1_code":"4.0",
    "gn:asciiname":"Basti Dhora Ghallwan",
    "gn:country_code":"PK",
    "gn:dem":106,
    "gn:feature_class":"P",
    "gn:feature_code":"PPL",
    "gn:name":"Basti Dhora Ghallwan",
    "gn:population":0,
    "gn:timezone":"Asia/Karachi",
    "iso:country":"PK",
    "name:und_x_variant":[
        "Basti Dora Ghulwan"
    ],
    "wof:name":"Basti Dhora Ghallwan",
    "wof:placetype":"locality"
},
  "geometry": {"coordinates":[71.26015,29.33645],"type":"Point"}
}