{
  "type": "Feature",
  "properties": {
    "gn:admin1_code":"5.0",
    "gn:asciiname":"Pho Jat",
    "gn:country_code":"PK",
    "gn:dem":10,
    "gn:feature_class":"P",
    "gn:feature_code":"PPL",
    "gn:name":"Pho Jat",
    "gn:population":0,
    "gn:timezone":"Asia/Karachi",
    "iso:country":"PK",
    "name:eng_x_preferred":[
        "Y\u0101q\u016bb Panhwar"
    ],
    "wof:name":"Pho Jat",
    "wof:placetype":"locality"
},
  "geometry": {"coordinates":[68.34183,24.69025],"type":"Point"}
}