{
  "type": "Feature",
  "properties": {
    "gn:admin1_code":"5.0",
    "gn:asciiname":"Erazi Saidki",
    "gn:country_code":"PK",
    "gn:dem":63,
    "gn:feature_class":"P",
    "gn:feature_code":"PPL",
    "gn:name":"Erazi Saidki",
    "gn:population":0,
    "gn:timezone":"Asia/Karachi",
    "iso:country":"PK",
    "name:und_x_variant":[
        "Ir\u0101zi Saidki"
    ],
    "wof:name":"Erazi Saidki",
    "wof:placetype":"locality"
},
  "geometry": {"coordinates":[69.08333,27.81667],"type":"Point"}
}