{
  "type": "Feature",
  "properties": {
    "gn:admin1_code":"4",
    "gn:asciiname":"Thatha Gondlan",
    "gn:country_code":"PK",
    "gn:dem":209,
    "gn:feature_class":"P",
    "gn:feature_code":"PPL",
    "gn:name":"Thatha Gondlan",
    "gn:population":0,
    "gn:timezone":"Asia/Karachi",
    "iso:country":"PK",
    "name:und_x_variant":[
        "Thatta Gondl\u0101n"
    ],
    "wof:name":"Thatha Gondlan",
    "wof:placetype":"locality"
},
  "geometry": {"coordinates":[73.72974000000001,32.01985],"type":"Point"}
}