{
  "type": "Feature",
  "properties": {
    "gn:admin1_code":"5.0",
    "gn:asciiname":"Lundo Amro",
    "gn:country_code":"PK",
    "gn:dem":9,
    "gn:feature_class":"P",
    "gn:feature_code":"PPL",
    "gn:name":"Lundo Amro",
    "gn:population":0,
    "gn:timezone":"Asia/Karachi",
    "iso:country":"PK",
    "name:eng_x_preferred":[
        "Bhatti"
    ],
    "wof:name":"Lundo Amro",
    "wof:placetype":"locality"
},
  "geometry": {"coordinates":[68.06398,24.64418],"type":"Point"}
}