{
  "type": "Feature",
  "properties": {
    "gn:admin1_code":"04",
    "gn:asciiname":"Wario",
    "gn:country_code":"PK",
    "gn:dem":247,
    "gn:feature_class":"P",
    "gn:feature_code":"PPL",
    "gn:name":"Wario",
    "gn:population":0,
    "gn:timezone":"Asia/Karachi",
    "iso:country":"PK",
    "name:ang_x_preferred":[
        "Wario"
    ],
    "name:ara_x_preferred":[
        "\u0648\u0627\u0631\u064a\u0648"
    ],
    "name:cat_x_preferred":[
        "Wario"
    ],
    "name:ces_x_preferred":[
        "Wario"
    ],
    "name:dan_x_preferred":[
        "Wario"
    ],
    "name:deu_x_preferred":[
        "Wario"
    ],
    "name:fin_x_preferred":[
        "Wario"
    ],
    "name:fra_x_preferred":[
        "Wario"
    ],
    "name:ita_x_preferred":[
        "Wario"
    ],
    "name:jpn_x_preferred":[
        "\u30ef\u30ea\u30aa"
    ],
    "name:kor_x_preferred":[
        "\uc640\ub9ac\uc624"
    ],
    "name:lat_x_preferred":[
        "Wario"
    ],
    "name:lit_x_preferred":[
        "Wario"
    ],
    "name:nld_x_preferred":[
        "Wario"
    ],
    "name:nno_x_preferred":[
        "Wario"
    ],
    "name:nor_x_preferred":[
        "Wario"
    ],
    "name:pol_x_preferred":[
        "Wario"
    ],
    "name:por_x_preferred":[
        "Wario"
    ],
    "name:rus_x_preferred":[
        "\u0412\u0430\u0440\u0438\u043e"
    ],
    "name:spa_x_preferred":[
        "Wario"
    ],
    "name:swe_x_preferred":[
        "Wario"
    ],
    "name:tgl_x_preferred":[
        "Wario"
    ],
    "name:tha_x_preferred":[
        "\u0e27\u0e32\u0e23\u0e34\u0e42\u0e2d"
    ],
    "name:und_x_variant":[
        "Waryu"
    ],
    "name:urd_x_preferred":[
        "\u0648\u0627\u0631\u06cc\u0648"
    ],
    "name:wuu_x_preferred":[
        "\u74e6\u91cc\u5965"
    ],
    "name:yid_x_preferred":[
        "\u05d5\u05d5\u05d0\u05e8\u05d9\u05d0"
    ],
    "name:zho_x_preferred":[
        "\u74e6\u91cc\u5965"
    ],
    "wof:name":"Wario",
    "wof:placetype":"locality"
},
  "geometry": {"coordinates":[74.58936,32.41023],"type":"Point"}
}