{
  "type": "Feature",
  "properties": {
    "gn:admin1_code":"04",
    "gn:asciiname":"Wario",
    "gn:country_code":"PK",
    "gn:dem":247,
    "gn:feature_class":"P",
    "gn:feature_code":"PPL",
    "gn:name":"Wario",
    "gn:population":0,
    "gn:timezone":"Asia/Karachi",
    "iso:country":"PK",
    "name:und_x_variant":[
        "Waryu",
        "Wario"
    ],
    "wof:name":"Wario",
    "wof:placetype":"locality"
},
  "geometry": {"coordinates":[74.58936,32.41023],"type":"Point"}
}