{
  "type": "Feature",
  "properties": {
    "gn:admin1_code":"4.0",
    "gn:asciiname":"Machhiwala",
    "gn:country_code":"PK",
    "gn:dem":132,
    "gn:feature_class":"P",
    "gn:feature_code":"PPL",
    "gn:name":"Machhiwala",
    "gn:population":0,
    "gn:timezone":"Asia/Karachi",
    "iso:country":"PK",
    "wof:name":"Machhiwala",
    "wof:placetype":"locality"
},
  "geometry": {"coordinates":[71.82939,30.40067],"type":"Point"}
}