{
  "type": "Feature",
  "properties": {
    "gn:admin1_code":"03",
    "gn:asciiname":"Gumbatai",
    "gn:country_code":"PK",
    "gn:dem":1072,
    "gn:feature_class":"P",
    "gn:feature_code":"PPL",
    "gn:name":"Gumbatai",
    "gn:population":0,
    "gn:timezone":"Asia/Karachi",
    "iso:country":"PK",
    "name:eng_x_preferred":[
        "Gumbatai"
    ],
    "wof:name":"Gumbatai",
    "wof:placetype":"locality"
},
  "geometry": {"coordinates":[71.82625999999998,34.95532],"type":"Point"}
}