{
  "type": "Feature",
  "properties": {
    "gn:admin1_code":"3.0",
    "gn:asciiname":"Nar Quli Khan",
    "gn:country_code":"PK",
    "gn:dem":307,
    "gn:feature_class":"P",
    "gn:feature_code":"PPL",
    "gn:name":"Nar Quli Khan",
    "gn:population":0,
    "gn:timezone":"Asia/Karachi",
    "iso:country":"PK",
    "name:und_x_variant":[
        "Kamalo",
        "Kam\u0101lona"
    ],
    "wof:name":"Nar Quli Khan",
    "wof:placetype":"locality"
},
  "geometry": {"coordinates":[70.75384,32.80243],"type":"Point"}
}