{
  "type": "Feature",
  "properties": {
    "gn:admin1_code":"7.0",
    "gn:asciiname":"Maujho",
    "gn:country_code":"PK",
    "gn:dem":2603,
    "gn:feature_class":"P",
    "gn:feature_code":"PPL",
    "gn:name":"Maujho",
    "gn:population":0,
    "gn:timezone":"Asia/Karachi",
    "iso:country":"PK",
    "wof:name":"Maujho",
    "wof:placetype":"locality"
},
  "geometry": {"coordinates":[76.39437,35.27391],"type":"Point"}
}