{
  "type": "Feature",
  "properties": {
    "gn:admin1_code":"6.0",
    "gn:asciiname":"Seegar Gala",
    "gn:country_code":"PK",
    "gn:dem":1357,
    "gn:feature_class":"P",
    "gn:feature_code":"PPL",
    "gn:name":"Seegar Gala",
    "gn:population":0,
    "gn:timezone":"Asia/Karachi",
    "iso:country":"PK",
    "wof:name":"Seegar Gala",
    "wof:placetype":"locality"
},
  "geometry": {"coordinates":[74.10273000000002,33.48913],"type":"Point"}
}