{
  "type": "Feature",
  "properties": {
    "gn:admin1_code":"6",
    "gn:asciiname":"Harnah",
    "gn:country_code":"PK",
    "gn:dem":542,
    "gn:feature_class":"P",
    "gn:feature_code":"PPL",
    "gn:name":"Harnah",
    "gn:population":0,
    "gn:timezone":"Asia/Karachi",
    "iso:country":"PK",
    "wof:name":"Harnah",
    "wof:placetype":"locality"
},
  "geometry": {"coordinates":[73.85382,33.45191],"type":"Point"}
}