{
  "type": "Feature",
  "properties": {
    "gn:admin1_code":"4",
    "gn:asciiname":"Chojniwala",
    "gn:country_code":"PK",
    "gn:dem":150,
    "gn:feature_class":"P",
    "gn:feature_code":"PPL",
    "gn:name":"Chojniwala",
    "gn:population":0,
    "gn:timezone":"Asia/Karachi",
    "iso:country":"PK",
    "name:und_x_variant":[
        "Chajn\u012bw\u0101la"
    ],
    "wof:name":"Chojniwala",
    "wof:placetype":"locality"
},
  "geometry": {"coordinates":[71.01369,31.07927],"type":"Point"}
}