{
  "type": "Feature",
  "properties": {
    "gn:admin1_code":"04",
    "gn:asciiname":"Tibbi Izzat",
    "gn:country_code":"PK",
    "gn:dem":106,
    "gn:feature_class":"P",
    "gn:feature_code":"PPL",
    "gn:name":"Tibbi Izzat",
    "gn:population":0,
    "gn:timezone":"Asia/Karachi",
    "iso:country":"PK",
    "wof:name":"Tibbi Izzat",
    "wof:placetype":"locality"
},
  "geometry": {"coordinates":[71.30599000000002,29.18537],"type":"Point"}
}