{
  "type": "Feature",
  "properties": {
    "gn:admin1_code":"5.0",
    "gn:asciiname":"Chaudhry Muhammad Ali",
    "gn:country_code":"PK",
    "gn:dem":8,
    "gn:feature_class":"P",
    "gn:feature_code":"PPL",
    "gn:name":"Chaudhry Muhammad Ali",
    "gn:population":0,
    "gn:timezone":"Asia/Karachi",
    "iso:country":"PK",
    "name:ara_x_preferred":[
        "\u062a\u0634\u0648\u062f\u0631\u064a \u0645\u062d\u0645\u062f \u0639\u0644\u064a"
    ],
    "name:bel_x_preferred":[
        "\u041c\u0443\u0445\u0430\u043c\u0430\u0434 \u0410\u043b\u0456 \u0427\u0430\u045e\u0434\u0445\u0443\u0440\u044b"
    ],
    "name:deu_x_preferred":[
        "Chaudhry Muhammad Ali"
    ],
    "name:eng_x_preferred":[
        "Chaudhary Muhammad Ali"
    ],
    "name:fas_x_preferred":[
        "\u0686\u0648\u062f\u0647\u0631\u06cc \u0645\u062d\u0645\u062f \u0639\u0644\u06cc"
    ],
    "name:fra_x_preferred":[
        "Chaudhry Muhammad Ali"
    ],
    "name:heb_x_preferred":[
        "\u05e6'\u05d0\u05d5\u05d3\u05d4\u05e8\u05d9 \u05de\u05d5\u05d7\u05de\u05d3 \u05e2\u05dc\u05d9"
    ],
    "name:ind_x_preferred":[
        "Chaudhry Mohammad Ali"
    ],
    "name:ita_x_preferred":[
        "Chaudhry Muhammad Ali"
    ],
    "name:kas_x_preferred":[
        "\u0686\u0648\u06c1\u062f\u0631\u06cc \u0645\u062d\u0645\u062f \u0639\u0644\u06cc"
    ],
    "name:mar_x_preferred":[
        "\u091a\u094c\u0927\u0930\u0940 \u092e\u0941\u0939\u092e\u094d\u092e\u0926 \u0905\u0932\u0940"
    ],
    "name:pnb_x_preferred":[
        "\u0686\u0648\u062f\u06be\u0631\u06cc \u0645\u062d\u0645\u062f \u0639\u0644\u06cc"
    ],
    "name:pol_x_preferred":[
        "Chaudhry Mohammad Ali"
    ],
    "name:por_x_preferred":[
        "Chaudhry Muhammad Ali"
    ],
    "name:rus_x_preferred":[
        "\u0427\u043e\u0443\u0434\u0445\u0443\u0440\u0438"
    ],
    "name:urd_x_preferred":[
        "\u0686\u0648\u062f\u06be\u0631\u06cc \u0645\u062d\u0645\u062f \u0639\u0644\u06cc"
    ],
    "name:yor_x_preferred":[
        "Chaudhry Muhammad Ali"
    ],
    "wof:name":"Chaudhry Muhammad Ali",
    "wof:placetype":"locality"
},
  "geometry": {"coordinates":[68.34323000000001,24.64459],"type":"Point"}
}