{
  "type": "Feature",
  "properties": {
    "gn:admin1_code":"4",
    "gn:asciiname":"Chak Six Hundred Fifty-two/Three Gugera Branch",
    "gn:country_code":"PK",
    "gn:dem":193,
    "gn:feature_class":"P",
    "gn:feature_code":"PPL",
    "gn:name":"Chak Six Hundred Fifty-two/Three Gugera Branch",
    "gn:population":0,
    "gn:timezone":"Asia/Karachi",
    "iso:country":"PK",
    "name:und_x_variant":[
        "Chak Three and Three Hundred Fifty-two"
    ],
    "wof:name":"Chak Six Hundred Fifty-two/Three Gugera Branch",
    "wof:placetype":"locality"
},
  "geometry": {"coordinates":[73.48959000000001,31.26981],"type":"Point"}
}