{
  "type": "Feature",
  "properties": {
    "gn:admin1_code":"5",
    "gn:asciiname":"Gharo",
    "gn:country_code":"PK",
    "gn:dem":38,
    "gn:feature_class":"P",
    "gn:feature_code":"PPL",
    "gn:name":"Gharo",
    "gn:population":0,
    "gn:timezone":"Asia/Karachi",
    "iso:country":"PK",
    "name:ceb_x_preferred":[
        "Gh\u0101ro"
    ],
    "name:pnb_x_preferred":[
        "\u06af\u06be\u0627\u0631\u0648"
    ],
    "name:und_x_variant":[
        "Ch\u0101ro"
    ],
    "wof:name":"Gharo",
    "wof:placetype":"locality"
},
  "geometry": {"coordinates":[67.60929,26.64042],"type":"Point"}
}