{
  "type": "Feature",
  "properties": {
    "gn:admin1_code":"3.0",
    "gn:asciiname":"Ucha",
    "gn:country_code":"PK",
    "gn:dem":2787,
    "gn:feature_class":"P",
    "gn:feature_code":"PPL",
    "gn:name":"Ucha",
    "gn:population":0,
    "gn:timezone":"Asia/Karachi",
    "iso:country":"PK",
    "name:eng_x_preferred":[
        "\u016ash"
    ],
    "wof:name":"Ucha",
    "wof:placetype":"locality"
},
  "geometry": {"coordinates":[72.00756,35.87632],"type":"Point"}
}