{
  "type": "Feature",
  "properties": {
    "gn:admin1_code":"2.0",
    "gn:asciiname":"Akbar Bazar",
    "gn:country_code":"PK",
    "gn:dem":566,
    "gn:feature_class":"P",
    "gn:feature_code":"PPL",
    "gn:name":"Akbar Bazar",
    "gn:population":0,
    "gn:timezone":"Asia/Karachi",
    "iso:country":"PK",
    "wof:name":"Akbar Bazar",
    "wof:placetype":"locality"
},
  "geometry": {"coordinates":[64.93245,26.22924],"type":"Point"}
}