{
  "type": "Feature",
  "properties": {
    "gn:admin1_code":"2.0",
    "gn:asciiname":"Kar Sultanzai",
    "gn:country_code":"PK",
    "gn:dem":2628,
    "gn:feature_class":"P",
    "gn:feature_code":"PPL",
    "gn:name":"Kar Sultanzai",
    "gn:population":0,
    "gn:timezone":"Asia/Karachi",
    "iso:country":"PK",
    "name:und_x_variant":[
        "K\u0101r"
    ],
    "wof:name":"Kar Sultanzai",
    "wof:placetype":"locality"
},
  "geometry": {"coordinates":[67.6307,30.94033],"type":"Point"}
}