{
  "type": "Feature",
  "properties": {
    "gn:admin1_code":"5",
    "gn:asciiname":"Garhi Mehrab",
    "gn:country_code":"PK",
    "gn:dem":65,
    "gn:feature_class":"P",
    "gn:feature_code":"PPL",
    "gn:name":"Garhi Mehrab",
    "gn:population":0,
    "gn:timezone":"Asia/Karachi",
    "iso:country":"PK",
    "name:und_x_variant":[
        "Gobind R\u0101m"
    ],
    "wof:name":"Garhi Mehrab",
    "wof:placetype":"locality"
},
  "geometry": {"coordinates":[68.53156,28.19059],"type":"Point"}
}