{
  "type": "Feature",
  "properties": {
    "gn:admin1_code":"3.0",
    "gn:asciiname":"Beri Dherakki",
    "gn:country_code":"PK",
    "gn:dem":603,
    "gn:feature_class":"P",
    "gn:feature_code":"PPL",
    "gn:name":"Beri Dherakki",
    "gn:population":0,
    "gn:timezone":"Asia/Karachi",
    "iso:country":"PK",
    "name:und_x_variant":[
        "Dherakki B\u0101nda"
    ],
    "wof:name":"Beri Dherakki",
    "wof:placetype":"locality"
},
  "geometry": {"coordinates":[71.16201,33.28592],"type":"Point"}
}