{
  "type": "Feature",
  "properties": {
    "gn:admin1_code":"4.0",
    "gn:asciiname":"Muftpura",
    "gn:country_code":"PK",
    "gn:dem":186,
    "gn:feature_class":"P",
    "gn:feature_code":"PPL",
    "gn:name":"Muftpura",
    "gn:population":0,
    "gn:timezone":"Asia/Karachi",
    "iso:country":"PK",
    "wof:name":"Muftpura",
    "wof:placetype":"locality"
},
  "geometry": {"coordinates":[74.13258,30.71831],"type":"Point"}
}