{
  "type": "Feature",
  "properties": {
    "gn:admin1_code":"4.0",
    "gn:asciiname":"Jamalwal",
    "gn:country_code":"PK",
    "gn:dem":459,
    "gn:feature_class":"P",
    "gn:feature_code":"PPL",
    "gn:name":"Jamalwal",
    "gn:population":0,
    "gn:timezone":"Asia/Karachi",
    "iso:country":"PK",
    "name:eng_x_preferred":[
        "Jamalwal"
    ],
    "wof:name":"Jamalwal",
    "wof:placetype":"locality"
},
  "geometry": {"coordinates":[72.79243000000002,33.06997],"type":"Point"}
}