{
  "type": "Feature",
  "properties": {
    "gn:admin1_code":"3",
    "gn:asciiname":"Jalgar Banda",
    "gn:country_code":"PK",
    "gn:dem":1507,
    "gn:feature_class":"P",
    "gn:feature_code":"PPL",
    "gn:name":"Jalgar Banda",
    "gn:population":0,
    "gn:timezone":"Asia/Karachi",
    "iso:country":"PK",
    "name:eng_x_preferred":[
        "Jalgar Banda"
    ],
    "wof:name":"Jalgar Banda",
    "wof:placetype":"locality"
},
  "geometry": {"coordinates":[72.23866,34.59643],"type":"Point"}
}