{
  "type": "Feature",
  "properties": {
    "gn:admin1_code":"2.0",
    "gn:asciiname":"Makhal Kaul",
    "gn:country_code":"PK",
    "gn:dem":1783,
    "gn:feature_class":"P",
    "gn:feature_code":"PPL",
    "gn:name":"Makhal Kaul",
    "gn:population":0,
    "gn:timezone":"Asia/Karachi",
    "iso:country":"PK",
    "wof:name":"Makhal Kaul",
    "wof:placetype":"locality"
},
  "geometry": {"coordinates":[66.76472,30.80549],"type":"Point"}
}