{
  "type": "Feature",
  "properties": {
    "gn:admin1_code":"5",
    "gn:asciiname":"Goth Alam Shah",
    "gn:country_code":"PK",
    "gn:dem":52,
    "gn:feature_class":"P",
    "gn:feature_code":"PPL",
    "gn:name":"Goth Alam Shah",
    "gn:population":0,
    "gn:timezone":"Asia/Karachi",
    "iso:country":"PK",
    "name:und_x_variant":[
        "\u0100lam Sh\u0101h"
    ],
    "wof:name":"Goth Alam Shah",
    "wof:placetype":"locality"
},
  "geometry": {"coordinates":[68.11485999999999,27.98427],"type":"Point"}
}