{
  "type": "Feature",
  "properties": {
    "gn:admin1_code":"4.0",
    "gn:asciiname":"Amingarh",
    "gn:country_code":"PK",
    "gn:dem":86,
    "gn:feature_class":"P",
    "gn:feature_code":"PPL",
    "gn:name":"Amingarh",
    "gn:population":0,
    "gn:timezone":"Asia/Karachi",
    "iso:country":"PK",
    "name:und_x_variant":[
        "Am\u012bngarh"
    ],
    "wof:name":"Amingarh",
    "wof:placetype":"locality"
},
  "geometry": {"coordinates":[70.30161,28.45763],"type":"Point"}
}