{
  "type": "Feature",
  "properties": {
    "gn:admin1_code":"4",
    "gn:asciiname":"Nurpur Dogran",
    "gn:country_code":"PK",
    "gn:dem":194,
    "gn:feature_class":"P",
    "gn:feature_code":"PPL",
    "gn:name":"Nurpur Dogran",
    "gn:population":0,
    "gn:timezone":"Asia/Karachi",
    "iso:country":"PK",
    "wof:name":"Nurpur Dogran",
    "wof:placetype":"locality"
},
  "geometry": {"coordinates":[74.26769,30.8958],"type":"Point"}
}