{
  "type": "Feature",
  "properties": {
    "gn:admin1_code":"4",
    "gn:asciiname":"Ghaneriwala",
    "gn:country_code":"PK",
    "gn:dem":126,
    "gn:feature_class":"P",
    "gn:feature_code":"PPL",
    "gn:name":"Ghaneriwala",
    "gn:population":0,
    "gn:timezone":"Asia/Karachi",
    "iso:country":"PK",
    "name:eng_x_preferred":[
        "Ghaneriwala"
    ],
    "wof:name":"Ghaneriwala",
    "wof:placetype":"locality"
},
  "geometry": {"coordinates":[70.95147,30.24615],"type":"Point"}
}