{
  "type": "Feature",
  "properties": {
    "gn:admin1_code":"7.0",
    "gn:asciiname":"Hussainabad",
    "gn:country_code":"PK",
    "gn:dem":3451,
    "gn:feature_class":"P",
    "gn:feature_code":"PPL",
    "gn:name":"Hussainabad",
    "gn:population":0,
    "gn:timezone":"Asia/Karachi",
    "iso:country":"PK",
    "name:eng_x_preferred":[
        "Hussainabad"
    ],
    "name:urd_x_preferred":[
        "\u062d\u0633\u06cc\u0646 \u0622\u0628\u0627\u062f"
    ],
    "wof:name":"Hussainabad",
    "wof:placetype":"locality"
},
  "geometry": {"coordinates":[75.71856,34.75905],"type":"Point"}
}