{
  "type": "Feature",
  "properties": {
    "gn:admin1_code":"05",
    "gn:asciiname":"Landhi",
    "gn:country_code":"PK",
    "gn:dem":24,
    "gn:feature_class":"P",
    "gn:feature_code":"PPL",
    "gn:name":"Landhi",
    "gn:population":0,
    "gn:timezone":"Asia/Karachi",
    "iso:country":"PK",
    "name:und_x_variant":[
        "Lanchi",
        "L\u0101ndhi",
        "Landhi"
    ],
    "wof:name":"Landhi",
    "wof:placetype":"locality"
},
  "geometry": {"coordinates":[68.72051999999999,25.93122],"type":"Point"}
}