{
  "type": "Feature",
  "properties": {
    "gn:admin1_code":"2.0",
    "gn:asciiname":"Tarati",
    "gn:country_code":"PK",
    "gn:dem":28,
    "gn:feature_class":"P",
    "gn:feature_code":"PPL",
    "gn:name":"Tarati",
    "gn:population":0,
    "gn:timezone":"Asia/Karachi",
    "iso:country":"PK",
    "name:fas_x_preferred":[
        "\u062a\u0631\u0627\u062a\u06cc"
    ],
    "name:und_x_variant":[
        "Gam\u0101ni B\u0101z\u0101r",
        "Tarati"
    ],
    "name:urd_x_preferred":[
        "\u062a\u0631\u0627\u0679\u06cc"
    ],
    "wof:name":"Tarati",
    "wof:placetype":"locality"
},
  "geometry": {"coordinates":[63.0018,25.5004],"type":"Point"}
}