{
  "type": "Feature",
  "properties": {
    "gn:admin1_code":"3",
    "gn:asciiname":"Ilagat",
    "gn:country_code":"PK",
    "gn:dem":892,
    "gn:feature_class":"P",
    "gn:feature_code":"PPL",
    "gn:name":"Ilagat",
    "gn:population":0,
    "gn:timezone":"Asia/Karachi",
    "iso:country":"PK",
    "wof:name":"Ilagat",
    "wof:placetype":"locality"
},
  "geometry": {"coordinates":[72.92478,34.90417],"type":"Point"}
}