{
  "type": "Feature",
  "properties": {
    "gn:admin1_code":"02",
    "gn:asciiname":"Salak",
    "gn:country_code":"PK",
    "gn:dem":2089,
    "gn:feature_class":"P",
    "gn:feature_code":"PPL",
    "gn:name":"Salak",
    "gn:population":0,
    "gn:timezone":"Asia/Karachi",
    "iso:country":"PK",
    "name:und_x_variant":[
        "Silak",
        "Salak"
    ],
    "wof:name":"Salak",
    "wof:placetype":"locality"
},
  "geometry": {"coordinates":[67.83214,31.03912],"type":"Point"}
}