{
  "type": "Feature",
  "properties": {
    "gn:admin1_code":"02",
    "gn:asciiname":"Salak",
    "gn:country_code":"PK",
    "gn:dem":2089,
    "gn:feature_class":"P",
    "gn:feature_code":"PPL",
    "gn:name":"Salak",
    "gn:population":0,
    "gn:timezone":"Asia/Karachi",
    "iso:country":"PK",
    "name:ara_x_preferred":[
        "\u0633\u0627\u0644\u0627\u0643\u0629 \u0645\u0623\u0644\u0648\u0641\u0629"
    ],
    "name:ceb_x_preferred":[
        "Salacca zalacca"
    ],
    "name:ces_x_preferred":[
        "Salak"
    ],
    "name:deu_x_preferred":[
        "Salakpalme"
    ],
    "name:epo_x_preferred":[
        "Salacca zalacca"
    ],
    "name:fas_x_preferred":[
        "\u0633\u0627\u0644\u0627\u06a9"
    ],
    "name:fin_x_preferred":[
        "Salaki"
    ],
    "name:fra_x_preferred":[
        "Salak"
    ],
    "name:ind_x_preferred":[
        "Salak"
    ],
    "name:ita_x_preferred":[
        "Salacca zalacca"
    ],
    "name:jav_x_preferred":[
        "Salak"
    ],
    "name:jpn_x_preferred":[
        "\u30b5\u30e9\u30af"
    ],
    "name:koi_x_preferred":[
        "\u0421\u0430\u043b\u0430\u043a"
    ],
    "name:kom_x_preferred":[
        "\u0421\u0430\u043b\u0430\u043a"
    ],
    "name:lbe_x_preferred":[
        "\u0421\u0430\u043b\u0430\u043a"
    ],
    "name:lit_x_preferred":[
        "Valgomoji salakpalm\u0117"
    ],
    "name:mal_x_preferred":[
        "\u0d38\u0d32\u0d3e\u0d15\u0d4d\u0d15\u0d3e \u0d38\u0d32\u0d3e\u0d15\u0d4d\u0d15\u0d3e"
    ],
    "name:mrj_x_preferred":[
        "\u0421\u0430\u043b\u0430\u043a"
    ],
    "name:msa_x_preferred":[
        "Pokok Salak"
    ],
    "name:nld_x_preferred":[
        "Salak"
    ],
    "name:pol_x_preferred":[
        "Oszpilna jadalna"
    ],
    "name:por_x_preferred":[
        "Salacca zalacca"
    ],
    "name:ron_x_preferred":[
        "Salak"
    ],
    "name:rus_x_preferred":[
        "\u0421\u0430\u043b\u0430\u043a"
    ],
    "name:slk_x_preferred":[
        "Salaka"
    ],
    "name:spa_x_preferred":[
        "Salacca zalacca"
    ],
    "name:sun_x_preferred":[
        "Salak"
    ],
    "name:swe_x_preferred":[
        "Salak"
    ],
    "name:tha_x_preferred":[
        "\u0e2a\u0e25\u0e30"
    ],
    "name:udm_x_preferred":[
        "\u0421\u0430\u043b\u0430\u043a"
    ],
    "name:ukr_x_preferred":[
        "\u0421\u0430\u043b\u0430\u043a"
    ],
    "name:und_x_variant":[
        "Silak",
        "Salak"
    ],
    "name:vie_x_preferred":[
        "Salacca zalacca"
    ],
    "name:war_x_preferred":[
        "Salacca zalacca"
    ],
    "name:zho_x_preferred":[
        "\u86c7\u76ae\u679c"
    ],
    "wof:name":"Salak",
    "wof:placetype":"locality"
},
  "geometry": {"coordinates":[67.83214,31.03912],"type":"Point"}
}