{
  "type": "Feature",
  "properties": {
    "gn:admin1_code":"05",
    "gn:asciiname":"Goth Pholri",
    "gn:country_code":"PK",
    "gn:dem":45,
    "gn:feature_class":"P",
    "gn:feature_code":"PPL",
    "gn:name":"Goth Pholri",
    "gn:population":0,
    "gn:timezone":"Asia/Karachi",
    "iso:country":"PK",
    "name:und_x_variant":[
        "Pholehri",
        "Goth Pholri",
        "Pholri"
    ],
    "wof:name":"Goth Pholri",
    "wof:placetype":"locality"
},
  "geometry": {"coordinates":[68.46963000000001,26.77847],"type":"Point"}
}