{
  "type": "Feature",
  "properties": {
    "gn:admin1_code":"1.0",
    "gn:asciiname":"Kandwalai",
    "gn:country_code":"PK",
    "gn:dem":1993,
    "gn:feature_class":"P",
    "gn:feature_code":"PPL",
    "gn:name":"Kandwalai",
    "gn:population":0,
    "gn:timezone":"Asia/Karachi",
    "iso:country":"PK",
    "wof:name":"Kandwalai",
    "wof:placetype":"locality"
},
  "geometry": {"coordinates":[71.07764,34.56169000000001],"type":"Point"}
}