{
  "type": "Feature",
  "properties": {
    "gn:admin1_code":"3.0",
    "gn:asciiname":"Khaddar Khel",
    "gn:country_code":"PK",
    "gn:dem":441,
    "gn:feature_class":"P",
    "gn:feature_code":"PPL",
    "gn:name":"Khaddar Khel",
    "gn:population":0,
    "gn:timezone":"Asia/Karachi",
    "iso:country":"PK",
    "name:und_x_variant":[
        "Khadar Khel",
        "Khaddar Khel"
    ],
    "wof:name":"Khaddar Khel",
    "wof:placetype":"locality"
},
  "geometry": {"coordinates":[71.41608000000002,33.4118],"type":"Point"}
}