{
  "type": "Feature",
  "properties": {
    "gn:admin1_code":"2.0",
    "gn:asciiname":"Bidrang",
    "gn:country_code":"PK",
    "gn:dem":1600,
    "gn:feature_class":"P",
    "gn:feature_code":"PPL",
    "gn:name":"Bidrang",
    "gn:population":0,
    "gn:timezone":"Asia/Karachi",
    "iso:country":"PK",
    "wof:name":"Bidrang",
    "wof:placetype":"locality"
},
  "geometry": {"coordinates":[65.96666,28.25042],"type":"Point"}
}