{
  "type": "Feature",
  "properties": {
    "gn:admin1_code":"2.0",
    "gn:asciiname":"Wazlun",
    "gn:country_code":"PK",
    "gn:dem":1784,
    "gn:feature_class":"P",
    "gn:feature_code":"PPL",
    "gn:name":"Wazlun",
    "gn:population":0,
    "gn:timezone":"Asia/Karachi",
    "iso:country":"PK",
    "wof:name":"Wazlun",
    "wof:placetype":"locality"
},
  "geometry": {"coordinates":[68.21467,30.23342],"type":"Point"}
}