{
  "type": "Feature",
  "properties": {
    "gn:admin1_code":"2.0",
    "gn:asciiname":"Taiwar",
    "gn:country_code":"PK",
    "gn:dem":1549,
    "gn:feature_class":"P",
    "gn:feature_code":"PPL",
    "gn:name":"Taiwar",
    "gn:population":0,
    "gn:timezone":"Asia/Karachi",
    "iso:country":"PK",
    "wof:name":"Taiwar",
    "wof:placetype":"locality"
},
  "geometry": {"coordinates":[68.74224,30.89804],"type":"Point"}
}