{
  "type": "Feature",
  "properties": {
    "gn:admin1_code":"04",
    "gn:asciiname":"Sunn",
    "gn:country_code":"PK",
    "gn:dem":207,
    "gn:feature_class":"P",
    "gn:feature_code":"PPL",
    "gn:name":"Sunn",
    "gn:population":0,
    "gn:timezone":"Asia/Karachi",
    "iso:country":"PK",
    "name:deu_x_preferred":[
        "Sunn"
    ],
    "wof:name":"Sunn",
    "wof:placetype":"locality"
},
  "geometry": {"coordinates":[73.19518000000002,32.52331],"type":"Point"}
}