{
  "type": "Feature",
  "properties": {
    "gn:admin1_code":"6.0",
    "gn:asciiname":"Godda",
    "gn:country_code":"PK",
    "gn:dem":800,
    "gn:feature_class":"P",
    "gn:feature_code":"PPL",
    "gn:name":"Godda",
    "gn:population":0,
    "gn:timezone":"Asia/Karachi",
    "iso:country":"PK",
    "name:und_x_variant":[
        "Gadot"
    ],
    "wof:name":"Godda",
    "wof:placetype":"locality"
},
  "geometry": {"coordinates":[73.66493,33.6119],"type":"Point"}
}