{
  "type": "Feature",
  "properties": {
    "gn:admin1_code":"2.0",
    "gn:asciiname":"Kili Ghazi Khan",
    "gn:country_code":"PK",
    "gn:dem":595,
    "gn:feature_class":"P",
    "gn:feature_code":"PPL",
    "gn:name":"Kili Ghazi Khan",
    "gn:population":0,
    "gn:timezone":"Asia/Karachi",
    "iso:country":"PK",
    "wof:name":"Kili Ghazi Khan",
    "wof:placetype":"locality"
},
  "geometry": {"coordinates":[64.30865,28.32601],"type":"Point"}
}