{
  "type": "Feature",
  "properties": {
    "gn:admin1_code":"03",
    "gn:asciiname":"Romen",
    "gn:country_code":"PK",
    "gn:dem":3031,
    "gn:feature_class":"P",
    "gn:feature_code":"PPL",
    "gn:name":"Romen",
    "gn:population":0,
    "gn:timezone":"Asia/Karachi",
    "iso:country":"PK",
    "name:ceb_x_preferred":[
        "Romen"
    ],
    "name:deu_x_preferred":[
        "Romen"
    ],
    "wof:name":"Romen",
    "wof:placetype":"locality"
},
  "geometry": {"coordinates":[72.0973,35.98599],"type":"Point"}
}