{
  "type": "Feature",
  "properties": {
    "gn:admin1_code":"4.0",
    "gn:asciiname":"Salt Chauk",
    "gn:country_code":"PK",
    "gn:dem":610,
    "gn:feature_class":"P",
    "gn:feature_code":"PPL",
    "gn:name":"Salt Chauk",
    "gn:population":0,
    "gn:timezone":"Asia/Karachi",
    "iso:country":"PK",
    "wof:name":"Salt Chauk",
    "wof:placetype":"locality"
},
  "geometry": {"coordinates":[72.72700999999998,32.6884],"type":"Point"}
}