{
  "type": "Feature",
  "properties": {
    "gn:admin1_code":"5",
    "gn:asciiname":"Pandhi Abupoto",
    "gn:country_code":"PK",
    "gn:dem":30,
    "gn:feature_class":"P",
    "gn:feature_code":"PPL",
    "gn:name":"Pandhi Abupoto",
    "gn:population":0,
    "gn:timezone":"Asia/Karachi",
    "iso:country":"PK",
    "wof:name":"Pandhi Abupoto",
    "wof:placetype":"locality"
},
  "geometry": {"coordinates":[69.07491999999999,26.27855],"type":"Point"}
}