{
  "type": "Feature",
  "properties": {
    "gn:admin1_code":"2.0",
    "gn:asciiname":"Kund Kili",
    "gn:country_code":"PK",
    "gn:dem":1911,
    "gn:feature_class":"P",
    "gn:feature_code":"PPL",
    "gn:name":"Kund Kili",
    "gn:population":0,
    "gn:timezone":"Asia/Karachi",
    "iso:country":"PK",
    "wof:name":"Kund Kili",
    "wof:placetype":"locality"
},
  "geometry": {"coordinates":[69.71613000000001,31.65161],"type":"Point"}
}