{
  "type": "Feature",
  "properties": {
    "gn:admin1_code":"4",
    "gn:asciiname":"Sadda Utar",
    "gn:country_code":"PK",
    "gn:dem":192,
    "gn:feature_class":"P",
    "gn:feature_code":"PPL",
    "gn:name":"Sadda Utar",
    "gn:population":0,
    "gn:timezone":"Asia/Karachi",
    "iso:country":"PK",
    "name:und_x_variant":[
        "Saddha Utt\u0101r",
        "Saddha Hith\u0101r"
    ],
    "wof:name":"Sadda Utar",
    "wof:placetype":"locality"
},
  "geometry": {"coordinates":[73.92999,30.95638],"type":"Point"}
}