{
  "type": "Feature",
  "properties": {
    "gn:admin1_code":"5",
    "gn:asciiname":"Haji Laung ji Wand",
    "gn:country_code":"PK",
    "gn:dem":74,
    "gn:feature_class":"P",
    "gn:feature_code":"PPL",
    "gn:name":"Haji Laung ji Wand",
    "gn:population":0,
    "gn:timezone":"Asia/Karachi",
    "iso:country":"PK",
    "wof:name":"Haji Laung ji Wand",
    "wof:placetype":"locality"
},
  "geometry": {"coordinates":[69.39618,26.72488],"type":"Point"}
}