{
  "type": "Feature",
  "properties": {
    "gn:admin1_code":"2.0",
    "gn:asciiname":"Zhwe Kili",
    "gn:country_code":"PK",
    "gn:dem":1655,
    "gn:feature_class":"P",
    "gn:feature_code":"PPL",
    "gn:name":"Zhwe Kili",
    "gn:population":0,
    "gn:timezone":"Asia/Karachi",
    "iso:country":"PK",
    "wof:name":"Zhwe Kili",
    "wof:placetype":"locality"
},
  "geometry": {"coordinates":[69.25421,31.63569],"type":"Point"}
}