{
  "type": "Feature",
  "properties": {
    "gn:admin1_code":"4.0",
    "gn:asciiname":"Chak Twenty Thal Development Authority",
    "gn:country_code":"PK",
    "gn:dem":175,
    "gn:feature_class":"P",
    "gn:feature_code":"PPL",
    "gn:name":"Chak Twenty Thal Development Authority",
    "gn:population":0,
    "gn:timezone":"Asia/Karachi",
    "iso:country":"PK",
    "name:und_x_variant":[
        "Chak 20 TDA"
    ],
    "wof:name":"Chak Twenty Thal Development Authority",
    "wof:placetype":"locality"
},
  "geometry": {"coordinates":[71.12737,31.76425],"type":"Point"}
}