{
  "type": "Feature",
  "properties": {
    "gn:admin1_code":"03",
    "gn:asciiname":"Pajagai",
    "gn:country_code":"PK",
    "gn:dem":317,
    "gn:feature_class":"P",
    "gn:feature_code":"PPL",
    "gn:name":"Pajagai",
    "gn:population":0,
    "gn:timezone":"Asia/Karachi",
    "iso:country":"PK",
    "name:eng_x_preferred":[
        "Pajaggi"
    ],
    "wof:name":"Pajagai",
    "wof:placetype":"locality"
},
  "geometry": {"coordinates":[71.54238000000002,34.0603],"type":"Point"}
}