{
  "type": "Feature",
  "properties": {
    "gn:admin1_code":"5.0",
    "gn:asciiname":"Goth Ahmad Mallah",
    "gn:country_code":"PK",
    "gn:dem":20,
    "gn:feature_class":"P",
    "gn:feature_code":"PPL",
    "gn:name":"Goth Ahmad Mallah",
    "gn:population":0,
    "gn:timezone":"Asia/Karachi",
    "iso:country":"PK",
    "name:und_x_variant":[
        "Goth Ahmed Mallah"
    ],
    "wof:name":"Goth Ahmad Mallah",
    "wof:placetype":"locality"
},
  "geometry": {"coordinates":[68.58,25.157],"type":"Point"}
}