{
  "type": "Feature",
  "properties": {
    "gn:admin1_code":"4.0",
    "gn:asciiname":"Chak Four Hundred Seventy-four Gugera Branch",
    "gn:country_code":"PK",
    "gn:dem":172,
    "gn:feature_class":"P",
    "gn:feature_code":"PPL",
    "gn:name":"Chak Four Hundred Seventy-four Gugera Branch",
    "gn:population":0,
    "gn:timezone":"Asia/Karachi",
    "iso:country":"PK",
    "name:und_x_variant":[
        "N\u0101ngli"
    ],
    "wof:name":"Chak Four Hundred Seventy-four Gugera Branch",
    "wof:placetype":"locality"
},
  "geometry": {"coordinates":[72.85088,31.04753],"type":"Point"}
}