{
  "type": "Feature",
  "properties": {
    "gn:admin1_code":"3.0",
    "gn:asciiname":"Maidan",
    "gn:country_code":"PK",
    "gn:dem":2268,
    "gn:feature_class":"P",
    "gn:feature_code":"PPL",
    "gn:name":"Maidan",
    "gn:population":0,
    "gn:timezone":"Asia/Karachi",
    "iso:country":"PK",
    "wof:name":"Maidan",
    "wof:placetype":"locality"
},
  "geometry": {"coordinates":[71.5797,36.00551],"type":"Point"}
}