{
  "type": "Feature",
  "properties": {
    "gn:admin1_code":"2.0",
    "gn:asciiname":"Chamber",
    "gn:country_code":"PK",
    "gn:dem":1387,
    "gn:feature_class":"P",
    "gn:feature_code":"PPL",
    "gn:name":"Chamber",
    "gn:population":0,
    "gn:timezone":"Asia/Karachi",
    "iso:country":"PK",
    "wof:name":"Chamber",
    "wof:placetype":"locality"
},
  "geometry": {"coordinates":[66.5275,27.98788],"type":"Point"}
}