{
  "type": "Feature",
  "properties": {
    "gn:admin1_code":"04",
    "gn:asciiname":"Rose",
    "gn:country_code":"PK",
    "gn:dem":206,
    "gn:feature_class":"P",
    "gn:feature_code":"PPL",
    "gn:name":"Rose",
    "gn:population":0,
    "gn:timezone":"Asia/Karachi",
    "iso:country":"PK",
    "name:und_x_variant":[
        "Rossa",
        "Rose"
    ],
    "wof:name":"Rose",
    "wof:placetype":"locality"
},
  "geometry": {"coordinates":[74.1254,31.26115],"type":"Point"}
}