{
  "type": "Feature",
  "properties": {
    "gn:admin1_code":"4",
    "gn:asciiname":"Bunga Kanwar Singh",
    "gn:country_code":"PK",
    "gn:dem":165,
    "gn:feature_class":"P",
    "gn:feature_code":"PPL",
    "gn:name":"Bunga Kanwar Singh",
    "gn:population":0,
    "gn:timezone":"Asia/Karachi",
    "iso:country":"PK",
    "wof:name":"Bunga Kanwar Singh",
    "wof:placetype":"locality"
},
  "geometry": {"coordinates":[73.34999999999999,30.45],"type":"Point"}
}