{
  "type": "Feature",
  "properties": {
    "gn:admin1_code":"4.0",
    "gn:asciiname":"Chak Nine -One Right",
    "gn:country_code":"PK",
    "gn:dem":182,
    "gn:feature_class":"P",
    "gn:feature_code":"PPL",
    "gn:name":"Chak Nine -One Right",
    "gn:population":0,
    "gn:timezone":"Asia/Karachi",
    "iso:country":"PK",
    "wof:name":"Chak Nine -One Right",
    "wof:placetype":"locality"
},
  "geometry": {"coordinates":[73.57923000000002,30.95269],"type":"Point"}
}