{
  "type": "Feature",
  "properties": {
    "gn:admin1_code":"5.0",
    "gn:asciiname":"Goth Allah Dino Marri",
    "gn:country_code":"PK",
    "gn:dem":44,
    "gn:feature_class":"P",
    "gn:feature_code":"PPL",
    "gn:name":"Goth Allah Dino Marri",
    "gn:population":0,
    "gn:timezone":"Asia/Karachi",
    "iso:country":"PK",
    "name:und_x_variant":[
        "J\u0101ni Marri"
    ],
    "wof:name":"Goth Allah Dino Marri",
    "wof:placetype":"locality"
},
  "geometry": {"coordinates":[68.25729,26.72663],"type":"Point"}
}