{
  "type": "Feature",
  "properties": {
    "gn:admin1_code":"4.0",
    "gn:asciiname":"Chirak Khelanwala",
    "gn:country_code":"PK",
    "gn:dem":193,
    "gn:feature_class":"P",
    "gn:feature_code":"PPL",
    "gn:name":"Chirak Khelanwala",
    "gn:population":0,
    "gn:timezone":"Asia/Karachi",
    "iso:country":"PK",
    "name:und_x_variant":[
        "Sam\u0101nw\u0101la",
        "Saminanwala"
    ],
    "wof:name":"Chirak Khelanwala",
    "wof:placetype":"locality"
},
  "geometry": {"coordinates":[71.58532,32.14759],"type":"Point"}
}