{
  "type": "Feature",
  "properties": {
    "gn:admin1_code":"4.0",
    "gn:asciiname":"Bhandar",
    "gn:country_code":"PK",
    "gn:dem":323,
    "gn:feature_class":"P",
    "gn:feature_code":"PPL",
    "gn:name":"Bhandar",
    "gn:population":0,
    "gn:timezone":"Asia/Karachi",
    "iso:country":"PK",
    "wof:name":"Bhandar",
    "wof:placetype":"locality"
},
  "geometry": {"coordinates":[73.3293,32.8369],"type":"Point"}
}