{
  "type": "Feature",
  "properties": {
    "gn:admin1_code":"1",
    "gn:asciiname":"Khine Punga",
    "gn:country_code":"PK",
    "gn:dem":1452,
    "gn:feature_class":"P",
    "gn:feature_code":"PPL",
    "gn:name":"Khine Punga",
    "gn:population":0,
    "gn:timezone":"Asia/Karachi",
    "iso:country":"PK",
    "wof:name":"Khine Punga",
    "wof:placetype":"locality"
},
  "geometry": {"coordinates":[69.84808000000001,32.3927],"type":"Point"}
}