{
  "type": "Feature",
  "properties": {
    "gn:admin1_code":"4",
    "gn:asciiname":"Sarianwala",
    "gn:country_code":"PK",
    "gn:dem":141,
    "gn:feature_class":"P",
    "gn:feature_code":"PPL",
    "gn:name":"Sarianwala",
    "gn:population":0,
    "gn:timezone":"Asia/Karachi",
    "iso:country":"PK",
    "name:und_x_variant":[
        "Sar\u012bnw\u0101la"
    ],
    "wof:name":"Sarianwala",
    "wof:placetype":"locality"
},
  "geometry": {"coordinates":[71.94158,30.85911],"type":"Point"}
}