{
  "type": "Feature",
  "properties": {
    "gn:admin1_code":"1.0",
    "gn:asciiname":"Lulai",
    "gn:country_code":"PK",
    "gn:dem":1959,
    "gn:feature_class":"P",
    "gn:feature_code":"PPL",
    "gn:name":"Lulai",
    "gn:population":0,
    "gn:timezone":"Asia/Karachi",
    "iso:country":"PK",
    "wof:name":"Lulai",
    "wof:placetype":"locality"
},
  "geometry": {"coordinates":[69.53969000000001,32.94405],"type":"Point"}
}