{
  "type": "Feature",
  "properties": {
    "gn:admin1_code":"4",
    "gn:asciiname":"Chah Jandwala",
    "gn:country_code":"PK",
    "gn:dem":140,
    "gn:feature_class":"P",
    "gn:feature_code":"PPL",
    "gn:name":"Chah Jandwala",
    "gn:population":0,
    "gn:timezone":"Asia/Karachi",
    "iso:country":"PK",
    "name:und_x_variant":[
        "Ch\u0101h\u0101t Jandw\u0101la"
    ],
    "wof:name":"Chah Jandwala",
    "wof:placetype":"locality"
},
  "geometry": {"coordinates":[72.15694999999999,30.60637],"type":"Point"}
}