{
  "type": "Feature",
  "properties": {
    "gn:admin1_code":"4",
    "gn:asciiname":"Muhammad Bakhshwala",
    "gn:country_code":"PK",
    "gn:dem":129,
    "gn:feature_class":"P",
    "gn:feature_code":"PPL",
    "gn:name":"Muhammad Bakhshwala",
    "gn:population":0,
    "gn:timezone":"Asia/Karachi",
    "iso:country":"PK",
    "name:und_x_variant":[
        "Bakhshew\u0101la"
    ],
    "wof:name":"Muhammad Bakhshwala",
    "wof:placetype":"locality"
},
  "geometry": {"coordinates":[71.02589,30.37397],"type":"Point"}
}