{
  "type": "Feature",
  "properties": {
    "gn:admin1_code":"5",
    "gn:asciiname":"Khair Muhammad",
    "gn:country_code":"PK",
    "gn:dem":46,
    "gn:feature_class":"P",
    "gn:feature_code":"PPL",
    "gn:name":"Khair Muhammad",
    "gn:population":0,
    "gn:timezone":"Asia/Karachi",
    "iso:country":"PK",
    "name:und_x_variant":[
        "Khair Muhammad Panhwar"
    ],
    "wof:name":"Khair Muhammad",
    "wof:placetype":"locality"
},
  "geometry": {"coordinates":[68.04425000000001,26.87093],"type":"Point"}
}