{
  "type": "Feature",
  "properties": {
    "iso:country":"PK",
    "name:afr_x_preferred":[
        "Kot Diji"
    ],
    "name:cat_x_preferred":[
        "Kot Diji"
    ],
    "name:ceb_x_preferred":[
        "Kot Diji"
    ],
    "name:ces_x_preferred":[
        "K\u00f3t D\u00edd\u017e\u00ed"
    ],
    "name:deu_x_preferred":[
        "Kot Diji"
    ],
    "name:eng_x_preferred":[
        "Kot Diji"
    ],
    "name:fas_x_preferred":[
        "\u06a9\u0648\u062a \u062f\u06cc\u062c\u06cc"
    ],
    "name:fin_x_preferred":[
        "Kot Diji"
    ],
    "name:jpn_x_preferred":[
        "\u30b3\u30c8\u30fb\u30c7\u30a3\u30b8"
    ],
    "name:nld_x_preferred":[
        "Kot Diji"
    ],
    "name:nno_x_preferred":[
        "Kot Diji"
    ],
    "name:pan_x_preferred":[
        "\u0a15\u0a4b\u0a1f \u0a21\u0a40\u0a1c\u0a40"
    ],
    "name:pnb_x_preferred":[
        "\u06a9\u0648\u0679 \u0688\u062c\u06cc"
    ],
    "name:rus_x_preferred":[
        "\u041a\u043e\u0442-\u0414\u0438\u0434\u0436\u0438"
    ],
    "name:snd_x_preferred":[
        "\u06aa\u0648\u067d \u068f\u064a\u062c\u064a"
    ],
    "name:tam_x_preferred":[
        "\u0b95\u0bcb\u0b9f\u0bcd \u0ba4\u0bbf\u0b9c\u0bbf"
    ],
    "name:und_x_variant":[
        "Diji"
    ],
    "name:urd_x_preferred":[
        "\u06a9\u0648\u0679 \u0688\u06cc\u062c\u06cc"
    ],
    "name:urd_x_variant":[
        "kot diji fort"
    ],
    "name:zho_x_preferred":[
        "\u679c\u5fb7\u8fea\u5409"
    ],
    "qs:gn_country":"PK",
    "qs:gn_fcode":"PPL",
    "qs:gn_pop":25616,
    "qs:name":"Kot Diji",
    "qs:name_adm0":"Pakistan",
    "qs:name_adm1":"Sindh",
    "qs:photos":22,
    "qs:photos_1k":4,
    "qs:photos_9k":1,
    "qs:photos_9r":1,
    "qs:photos_all":22,
    "qs:photos_sr":1,
    "qs:placetype":"Town",
    "qs:pop_sr":"7",
    "qs:woe_adm0":23424922,
    "wd:wordcount":832,
    "wof:name":"Kot Diji",
    "wof:placetype":"locality",
    "wof:population":25616
},
  "geometry": {"coordinates":[68.70834000000001,27.34272],"type":"Point"}
}