{
  "type": "Feature",
  "properties": {
    "gn:admin1_code":"2.0",
    "gn:asciiname":"Gaz Mar",
    "gn:country_code":"PK",
    "gn:dem":15,
    "gn:feature_class":"P",
    "gn:feature_code":"PPL",
    "gn:name":"Gaz Mar",
    "gn:population":0,
    "gn:timezone":"Asia/Karachi",
    "iso:country":"PK",
    "name:eng_x_preferred":[
        "Gaz Mar"
    ],
    "wof:name":"Gaz Mar",
    "wof:placetype":"locality"
},
  "geometry": {"coordinates":[62.19664,25.24943],"type":"Point"}
}