{
  "type": "Feature",
  "properties": {
    "gn:admin1_code":"5",
    "gn:asciiname":"Goth Qazi Azizabad Khabri",
    "gn:country_code":"PK",
    "gn:dem":67,
    "gn:feature_class":"P",
    "gn:feature_code":"PPL",
    "gn:name":"Goth Qazi Azizabad Khabri",
    "gn:population":0,
    "gn:timezone":"Asia/Karachi",
    "iso:country":"PK",
    "name:und_x_variant":[
        "Khabri"
    ],
    "wof:name":"Goth Qazi Azizabad Khabri",
    "wof:placetype":"locality"
},
  "geometry": {"coordinates":[68.72803,27.9587],"type":"Point"}
}