{
  "type": "Feature",
  "properties": {
    "gn:admin1_code":"4.0",
    "gn:asciiname":"Chautra",
    "gn:country_code":"PK",
    "gn:dem":789,
    "gn:feature_class":"P",
    "gn:feature_code":"PPL",
    "gn:name":"Chautra",
    "gn:population":0,
    "gn:timezone":"Asia/Karachi",
    "iso:country":"PK",
    "wof:name":"Chautra",
    "wof:placetype":"locality"
},
  "geometry": {"coordinates":[72.02162,32.53582],"type":"Point"}
}