{
  "type": "Feature",
  "properties": {
    "gn:admin1_code":"6",
    "gn:asciiname":"Chabrian Gujran",
    "gn:country_code":"PK",
    "gn:dem":247,
    "gn:feature_class":"P",
    "gn:feature_code":"PPL",
    "gn:name":"Chabrian Gujran",
    "gn:population":0,
    "gn:timezone":"Asia/Karachi",
    "iso:country":"PK",
    "name:und_x_variant":[
        "Chhabrian Gujran",
        "Chabrian Gujran"
    ],
    "wof:name":"Chabrian Gujran",
    "wof:placetype":"locality"
},
  "geometry": {"coordinates":[73.77512,33.06938],"type":"Point"}
}