{
  "type": "Feature",
  "properties": {
    "gn:admin1_code":"3.0",
    "gn:asciiname":"Nadamin",
    "gn:country_code":"PK",
    "gn:dem":403,
    "gn:feature_class":"P",
    "gn:feature_code":"PPL",
    "gn:name":"Nadamin",
    "gn:population":0,
    "gn:timezone":"Asia/Karachi",
    "iso:country":"PK",
    "name:und_x_variant":[
        "Nadam\u0101n"
    ],
    "wof:name":"Nadamin",
    "wof:placetype":"locality"
},
  "geometry": {"coordinates":[70.5502,32.99253],"type":"Point"}
}