{
  "type": "Feature",
  "properties": {
    "gn:admin1_code":"2.0",
    "gn:asciiname":"Ibrahim",
    "gn:country_code":"PK",
    "gn:dem":60,
    "gn:feature_class":"P",
    "gn:feature_code":"PPL",
    "gn:name":"Ibrahim",
    "gn:population":0,
    "gn:timezone":"Asia/Karachi",
    "iso:country":"PK",
    "name:und_x_variant":[
        "Ibr\u0101nim",
        "Ibrahim"
    ],
    "wof:name":"Ibrahim",
    "wof:placetype":"locality"
},
  "geometry": {"coordinates":[66.33920000000001,26.07424],"type":"Point"}
}