{
  "type": "Feature",
  "properties": {
    "gn:admin1_code":"6",
    "gn:asciiname":"Kotla",
    "gn:country_code":"PK",
    "gn:dem":581,
    "gn:feature_class":"P",
    "gn:feature_code":"PPL",
    "gn:name":"Kotla",
    "gn:population":0,
    "gn:timezone":"Asia/Karachi",
    "iso:country":"PK",
    "wof:name":"Kotla",
    "wof:placetype":"locality"
},
  "geometry": {"coordinates":[74.0176,33.12730999999999],"type":"Point"}
}