{
  "type": "Feature",
  "properties": {
    "gn:admin1_code":"3",
    "gn:asciiname":"Bhauraj",
    "gn:country_code":"PK",
    "gn:dem":975,
    "gn:feature_class":"P",
    "gn:feature_code":"PPL",
    "gn:name":"Bhauraj",
    "gn:population":0,
    "gn:timezone":"Asia/Karachi",
    "iso:country":"PK",
    "name:und_x_variant":[
        "Bhurj"
    ],
    "wof:name":"Bhauraj",
    "wof:placetype":"locality"
},
  "geometry": {"coordinates":[73.11313,34.30593],"type":"Point"}
}