{
  "type": "Feature",
  "properties": {
    "gn:admin1_code":"4.0",
    "gn:asciiname":"Mehr Gadi",
    "gn:country_code":"PK",
    "gn:dem":90,
    "gn:feature_class":"P",
    "gn:feature_code":"PPL",
    "gn:name":"Mehr Gadi",
    "gn:population":0,
    "gn:timezone":"Asia/Karachi",
    "iso:country":"PK",
    "name:und_x_variant":[
        "Mher Jatt\u0101n"
    ],
    "wof:name":"Mehr Gadi",
    "wof:placetype":"locality"
},
  "geometry": {"coordinates":[70.22754999999999,28.9397],"type":"Point"}
}