{
  "type": "Feature",
  "properties": {
    "gn:admin1_code":"3.0",
    "gn:asciiname":"Shin Darra",
    "gn:country_code":"PK",
    "gn:dem":1682,
    "gn:feature_class":"P",
    "gn:feature_code":"PPL",
    "gn:name":"Shin Darra",
    "gn:population":0,
    "gn:timezone":"Asia/Karachi",
    "iso:country":"PK",
    "wof:name":"Shin Darra",
    "wof:placetype":"locality"
},
  "geometry": {"coordinates":[72.09768000000003,34.87273],"type":"Point"}
}