{
  "type": "Feature",
  "properties": {
    "gn:admin1_code":"4",
    "gn:asciiname":"Longwala",
    "gn:country_code":"PK",
    "gn:dem":170,
    "gn:feature_class":"P",
    "gn:feature_code":"PPL",
    "gn:name":"Longwala",
    "gn:population":0,
    "gn:timezone":"Asia/Karachi",
    "iso:country":"PK",
    "name:und_x_variant":[
        "Laungw\u0101la"
    ],
    "wof:name":"Longwala",
    "wof:placetype":"locality"
},
  "geometry": {"coordinates":[73.64655,30.26041],"type":"Point"}
}