{
  "type": "Feature",
  "properties": {
    "gn:admin1_code":"4",
    "gn:asciiname":"Gilani Shah Ziarat",
    "gn:country_code":"PK",
    "gn:dem":130,
    "gn:feature_class":"P",
    "gn:feature_code":"PPL",
    "gn:name":"Gilani Shah Ziarat",
    "gn:population":0,
    "gn:timezone":"Asia/Karachi",
    "iso:country":"PK",
    "name:und_x_variant":[
        "Gil\u0101ni Sh\u0101h"
    ],
    "wof:name":"Gilani Shah Ziarat",
    "wof:placetype":"locality"
},
  "geometry": {"coordinates":[72.26975,29.68703],"type":"Point"}
}