{
  "type": "Feature",
  "properties": {
    "gn:admin1_code":"2.0",
    "gn:asciiname":"Hussain Sanjrani",
    "gn:country_code":"PK",
    "gn:dem":1680,
    "gn:feature_class":"P",
    "gn:feature_code":"PPL",
    "gn:name":"Hussain Sanjrani",
    "gn:population":0,
    "gn:timezone":"Asia/Karachi",
    "iso:country":"PK",
    "wof:name":"Hussain Sanjrani",
    "wof:placetype":"locality"
},
  "geometry": {"coordinates":[66.44905,28.28873],"type":"Point"}
}