{
  "type": "Feature",
  "properties": {
    "gn:admin1_code":"3.0",
    "gn:asciiname":"Kozi Khel",
    "gn:country_code":"PK",
    "gn:dem":428,
    "gn:feature_class":"P",
    "gn:feature_code":"PPL",
    "gn:name":"Kozi Khel",
    "gn:population":0,
    "gn:timezone":"Asia/Karachi",
    "iso:country":"PK",
    "wof:name":"Kozi Khel",
    "wof:placetype":"locality"
},
  "geometry": {"coordinates":[70.52625,33.02779],"type":"Point"}
}