{
  "type": "Feature",
  "properties": {
    "gn:admin1_code":"4.0",
    "gn:asciiname":"Tanaza Dam Colony",
    "gn:country_code":"PK",
    "gn:dem":572,
    "gn:feature_class":"P",
    "gn:feature_code":"PPL",
    "gn:name":"Tanaza Dam Colony",
    "gn:population":0,
    "gn:timezone":"Asia/Karachi",
    "iso:country":"PK",
    "wof:name":"Tanaza Dam Colony",
    "wof:placetype":"locality"
},
  "geometry": {"coordinates":[72.73745,33.46357],"type":"Point"}
}