{
  "type": "Feature",
  "properties": {
    "gn:admin1_code":"4.0",
    "gn:asciiname":"Kahirzai",
    "gn:country_code":"PK",
    "gn:dem":906,
    "gn:feature_class":"P",
    "gn:feature_code":"PPL",
    "gn:name":"Kahirzai",
    "gn:population":0,
    "gn:timezone":"Asia/Karachi",
    "iso:country":"PK",
    "wof:name":"Kahirzai",
    "wof:placetype":"locality"
},
  "geometry": {"coordinates":[70.1623,30.59536],"type":"Point"}
}