{
  "type": "Feature",
  "properties": {
    "gn:admin1_code":"3",
    "gn:asciiname":"Nati Banda",
    "gn:country_code":"PK",
    "gn:dem":1431,
    "gn:feature_class":"P",
    "gn:feature_code":"PPL",
    "gn:name":"Nati Banda",
    "gn:population":0,
    "gn:timezone":"Asia/Karachi",
    "iso:country":"PK",
    "wof:name":"Nati Banda",
    "wof:placetype":"locality"
},
  "geometry": {"coordinates":[72.78864,34.79979],"type":"Point"}
}