{
  "type": "Feature",
  "properties": {
    "gn:admin1_code":"5",
    "gn:asciiname":"Goth Senjer",
    "gn:country_code":"PK",
    "gn:dem":66,
    "gn:feature_class":"P",
    "gn:feature_code":"PPL",
    "gn:name":"Goth Senjer",
    "gn:population":0,
    "gn:timezone":"Asia/Karachi",
    "iso:country":"PK",
    "name:und_x_variant":[
        "Sanjar"
    ],
    "wof:name":"Goth Senjer",
    "wof:placetype":"locality"
},
  "geometry": {"coordinates":[68.76915,27.81695],"type":"Point"}
}