{
  "type": "Feature",
  "properties": {
    "gn:admin1_code":"07",
    "gn:asciiname":"Shimisto Shal",
    "gn:country_code":"PK",
    "gn:dem":3300,
    "gn:feature_class":"P",
    "gn:feature_code":"PPL",
    "gn:name":"Shimisto Shal",
    "gn:population":0,
    "gn:timezone":"Asia/Karachi",
    "iso:country":"PK",
    "name:und_x_variant":[
        "Shemist",
        "Shimisto Shal"
    ],
    "wof:name":"Shimisto Shal",
    "wof:placetype":"locality"
},
  "geometry": {"coordinates":[72.66649,36.14305],"type":"Point"}
}