{
  "type": "Feature",
  "properties": {
    "gn:admin1_code":"5.0",
    "gn:asciiname":"Ahmad Shah",
    "gn:country_code":"PK",
    "gn:dem":8,
    "gn:feature_class":"P",
    "gn:feature_code":"PPL",
    "gn:name":"Ahmad Shah",
    "gn:population":0,
    "gn:timezone":"Asia/Karachi",
    "iso:country":"PK",
    "name:eng_x_preferred":[
        "Goth H\u0101ji Ali Muhammad"
    ],
    "wof:name":"Ahmad Shah",
    "wof:placetype":"locality"
},
  "geometry": {"coordinates":[68.39171999999999,24.72767],"type":"Point"}
}