{
  "type": "Feature",
  "properties": {
    "gn:admin1_code":"5.0",
    "gn:asciiname":"Ahmad Shah",
    "gn:country_code":"PK",
    "gn:dem":8,
    "gn:feature_class":"P",
    "gn:feature_code":"PPL",
    "gn:name":"Ahmad Shah",
    "gn:population":0,
    "gn:timezone":"Asia/Karachi",
    "iso:country":"PK",
    "name:ara_x_preferred":[
        "\u0623\u062d\u0645\u062f \u0634\u0627\u0647"
    ],
    "name:cat_x_preferred":[
        "Ahmad Shah"
    ],
    "name:deu_x_preferred":[
        "Ahmad Schah"
    ],
    "name:eng_x_preferred":[
        "Goth H\u0101ji Ali Muhammad"
    ],
    "name:fas_x_preferred":[
        "\u0627\u062d\u0645\u062f\u0634\u0627\u0647"
    ],
    "name:fra_x_preferred":[
        "Ahmad Shah"
    ],
    "name:rus_x_preferred":[
        "\u0410\u0445\u043c\u0430\u0434 \u0428\u0430\u0445"
    ],
    "name:swe_x_preferred":[
        "Ahmad Shah"
    ],
    "name:urd_x_preferred":[
        "\u0627\u062d\u0645\u062f \u0634\u0627\u06c1"
    ],
    "wof:name":"Ahmad Shah",
    "wof:placetype":"locality"
},
  "geometry": {"coordinates":[68.39171999999999,24.72767],"type":"Point"}
}