{
  "type": "Feature",
  "properties": {
    "gn:admin1_code":"3.0",
    "gn:asciiname":"Abdul Haq Kili",
    "gn:country_code":"PK",
    "gn:dem":339,
    "gn:feature_class":"P",
    "gn:feature_code":"PPL",
    "gn:name":"Abdul Haq Kili",
    "gn:population":0,
    "gn:timezone":"Asia/Karachi",
    "iso:country":"PK",
    "name:eng_x_preferred":[
        "Abdul Haq Kili"
    ],
    "name:und_x_variant":[
        "Kal"
    ],
    "wof:name":"Abdul Haq Kili",
    "wof:placetype":"locality"
},
  "geometry": {"coordinates":[71.87949,34.2625],"type":"Point"}
}