{
  "type": "Feature",
  "properties": {
    "gn:admin1_code":"3.0",
    "gn:asciiname":"Sharifabad",
    "gn:country_code":"PK",
    "gn:dem":314,
    "gn:feature_class":"P",
    "gn:feature_code":"PPL",
    "gn:name":"Sharifabad",
    "gn:population":0,
    "gn:timezone":"Asia/Karachi",
    "iso:country":"PK",
    "wof:name":"Sharifabad",
    "wof:placetype":"locality"
},
  "geometry": {"coordinates":[72.01966,34.20754],"type":"Point"}
}