{
  "type": "Feature",
  "properties": {
    "gn:admin1_code":"6",
    "gn:asciiname":"Sardari",
    "gn:country_code":"PK",
    "gn:dem":309,
    "gn:feature_class":"P",
    "gn:feature_code":"PPL",
    "gn:name":"Sardari",
    "gn:population":0,
    "gn:timezone":"Asia/Karachi",
    "iso:country":"PK",
    "name:und_x_variant":[
        "Sard\u0101r"
    ],
    "wof:name":"Sardari",
    "wof:placetype":"locality"
},
  "geometry": {"coordinates":[74.35763,32.85792],"type":"Point"}
}