{
  "type": "Feature",
  "properties": {
    "gn:admin1_code":"5.0",
    "gn:asciiname":"Jhangal Khan Chana",
    "gn:country_code":"PK",
    "gn:dem":62,
    "gn:feature_class":"P",
    "gn:feature_code":"PPL",
    "gn:name":"Jhangal Khan Chana",
    "gn:population":0,
    "gn:timezone":"Asia/Karachi",
    "iso:country":"PK",
    "wof:name":"Jhangal Khan Chana",
    "wof:placetype":"locality"
},
  "geometry": {"coordinates":[68.81028000000001,28.29543],"type":"Point"}
}