{
  "type": "Feature",
  "properties": {
    "gn:admin1_code":"3",
    "gn:asciiname":"Mastiwala",
    "gn:country_code":"PK",
    "gn:dem":496,
    "gn:feature_class":"P",
    "gn:feature_code":"PPL",
    "gn:name":"Mastiwala",
    "gn:population":0,
    "gn:timezone":"Asia/Karachi",
    "iso:country":"PK",
    "wof:name":"Mastiwala",
    "wof:placetype":"locality"
},
  "geometry": {"coordinates":[71.22183000000003,32.37889000000001],"type":"Point"}
}