{
  "type": "Feature",
  "properties": {
    "gn:admin1_code":"5",
    "gn:asciiname":"Goth Hashim Dharejo",
    "gn:country_code":"PK",
    "gn:dem":38,
    "gn:feature_class":"P",
    "gn:feature_code":"PPL",
    "gn:name":"Goth Hashim Dharejo",
    "gn:population":0,
    "gn:timezone":"Asia/Karachi",
    "iso:country":"PK",
    "name:und_x_variant":[
        "Goth H\u0101sham Dh\u0101rejo"
    ],
    "wof:name":"Goth Hashim Dharejo",
    "wof:placetype":"locality"
},
  "geometry": {"coordinates":[68.11454000000001,26.36611],"type":"Point"}
}