{
  "type": "Feature",
  "properties": {
    "gn:admin1_code":"3",
    "gn:asciiname":"Khalian Reran",
    "gn:country_code":"PK",
    "gn:dem":837,
    "gn:feature_class":"P",
    "gn:feature_code":"PPL",
    "gn:name":"Khalian Reran",
    "gn:population":0,
    "gn:timezone":"Asia/Karachi",
    "iso:country":"PK",
    "name:und_x_variant":[
        "Khili\u0101n Haria"
    ],
    "wof:name":"Khalian Reran",
    "wof:placetype":"locality"
},
  "geometry": {"coordinates":[73.11334000000002,34.36819000000001],"type":"Point"}
}