{
  "type": "Feature",
  "properties": {
    "gn:admin1_code":"5",
    "gn:asciiname":"Sir Shah Nawaz Bhutto",
    "gn:country_code":"PK",
    "gn:dem":53,
    "gn:feature_class":"P",
    "gn:feature_code":"PPL",
    "gn:name":"Sir Shah Nawaz Bhutto",
    "gn:population":0,
    "gn:timezone":"Asia/Karachi",
    "iso:country":"PK",
    "wof:name":"Sir Shah Nawaz Bhutto",
    "wof:placetype":"locality"
},
  "geometry": {"coordinates":[68.09990999999999,27.83777000000001],"type":"Point"}
}