{
  "type": "Feature",
  "properties": {
    "gn:admin1_code":"01",
    "gn:asciiname":"Karim Masai",
    "gn:country_code":"PK",
    "gn:dem":1828,
    "gn:feature_class":"P",
    "gn:feature_code":"PPL",
    "gn:name":"Karim Masai",
    "gn:population":0,
    "gn:timezone":"Asia/Karachi",
    "iso:country":"PK",
    "name:und_x_variant":[
        "Kar\u012bm Nmasai"
    ],
    "wof:name":"Karim Masai",
    "wof:placetype":"locality"
},
  "geometry": {"coordinates":[70.67301999999999,33.72413],"type":"Point"}
}