{
  "type": "Feature",
  "properties": {
    "gn:admin1_code":"5",
    "gn:asciiname":"Goth Muhammad Ali Laghari",
    "gn:country_code":"PK",
    "gn:dem":15,
    "gn:feature_class":"P",
    "gn:feature_code":"PPL",
    "gn:name":"Goth Muhammad Ali Laghari",
    "gn:population":0,
    "gn:timezone":"Asia/Karachi",
    "iso:country":"PK",
    "name:und_x_variant":[
        "Goth Um\u012bd Ali Lagh\u0101ri"
    ],
    "wof:name":"Goth Muhammad Ali Laghari",
    "wof:placetype":"locality"
},
  "geometry": {"coordinates":[69.03309,25.32839],"type":"Point"}
}