{
  "type": "Feature",
  "properties": {
    "gn:admin1_code":"4.0",
    "gn:asciiname":"Jand Mali",
    "gn:country_code":"PK",
    "gn:dem":179,
    "gn:feature_class":"P",
    "gn:feature_code":"PPL",
    "gn:name":"Jand Mali",
    "gn:population":0,
    "gn:timezone":"Asia/Karachi",
    "iso:country":"PK",
    "name:und_x_variant":[
        "Jand M\u0101ll"
    ],
    "wof:name":"Jand Mali",
    "wof:placetype":"locality"
},
  "geometry": {"coordinates":[72.13744,31.66594000000001],"type":"Point"}
}