{
  "type": "Feature",
  "properties": {
    "gn:admin1_code":"04",
    "gn:asciiname":"Malowa",
    "gn:country_code":"PK",
    "gn:dem":243,
    "gn:feature_class":"P",
    "gn:feature_code":"PPL",
    "gn:name":"Malowa",
    "gn:population":0,
    "gn:timezone":"Asia/Karachi",
    "iso:country":"PK",
    "name:und_x_variant":[
        "Malowal",
        "Malluw\u0101l",
        "Malowa"
    ],
    "wof:name":"Malowa",
    "wof:placetype":"locality"
},
  "geometry": {"coordinates":[75.03355000000001,32.11272],"type":"Point"}
}