{
  "type": "Feature",
  "properties": {
    "gn:admin1_code":"4",
    "gn:asciiname":"Chak Four Hundred Forty-six",
    "gn:country_code":"PK",
    "gn:dem":173,
    "gn:feature_class":"P",
    "gn:feature_code":"PPL",
    "gn:name":"Chak Four Hundred Forty-six",
    "gn:population":0,
    "gn:timezone":"Asia/Karachi",
    "iso:country":"PK",
    "name:und_x_variant":[
        "K\u0101kew\u0101la"
    ],
    "wof:name":"Chak Four Hundred Forty-six",
    "wof:placetype":"locality"
},
  "geometry": {"coordinates":[72.97775,30.99386],"type":"Point"}
}