{
  "type": "Feature",
  "properties": {
    "gn:admin1_code":"5",
    "gn:asciiname":"Goth Muhammad Siddiq Kalhora",
    "gn:country_code":"PK",
    "gn:dem":71,
    "gn:feature_class":"P",
    "gn:feature_code":"PPL",
    "gn:name":"Goth Muhammad Siddiq Kalhora",
    "gn:population":0,
    "gn:timezone":"Asia/Karachi",
    "iso:country":"PK",
    "name:und_x_variant":[
        "Muhammad S\u0101diq Kalwar"
    ],
    "wof:name":"Goth Muhammad Siddiq Kalhora",
    "wof:placetype":"locality"
},
  "geometry": {"coordinates":[69.56413000000001,28.01227],"type":"Point"}
}