{
  "type": "Feature",
  "properties": {
    "gn:admin1_code":"1",
    "gn:asciiname":"Mina Khel Mela",
    "gn:country_code":"PK",
    "gn:dem":1887,
    "gn:feature_class":"P",
    "gn:feature_code":"PPL",
    "gn:name":"Mina Khel Mela",
    "gn:population":0,
    "gn:timezone":"Asia/Karachi",
    "iso:country":"PK",
    "name:und_x_variant":[
        "Mina Khel"
    ],
    "wof:name":"Mina Khel Mela",
    "wof:placetype":"locality"
},
  "geometry": {"coordinates":[69.98257,32.61713],"type":"Point"}
}