{
  "type": "Feature",
  "properties": {
    "gn:admin1_code":"4",
    "gn:asciiname":"L Plot",
    "gn:country_code":"PK",
    "gn:dem":190,
    "gn:feature_class":"P",
    "gn:feature_code":"PPL",
    "gn:name":"L Plot",
    "gn:population":0,
    "gn:timezone":"Asia/Karachi",
    "iso:country":"PK",
    "name:und_x_variant":[
        "Fauji\u0101nw\u0101la"
    ],
    "wof:name":"L Plot",
    "wof:placetype":"locality"
},
  "geometry": {"coordinates":[73.66349,31.04492],"type":"Point"}
}