{
  "type": "Feature",
  "properties": {
    "gn:admin1_code":"1.0",
    "gn:asciiname":"Sar Ghundai",
    "gn:country_code":"PK",
    "gn:dem":1473,
    "gn:feature_class":"P",
    "gn:feature_code":"PPL",
    "gn:name":"Sar Ghundai",
    "gn:population":0,
    "gn:timezone":"Asia/Karachi",
    "iso:country":"PK",
    "wof:name":"Sar Ghundai",
    "wof:placetype":"locality"
},
  "geometry": {"coordinates":[70.78801,33.62086],"type":"Point"}
}