{
  "type": "Feature",
  "properties": {
    "gn:admin1_code":"4.0",
    "gn:asciiname":"Kanjuanwala",
    "gn:country_code":"PK",
    "gn:dem":220,
    "gn:feature_class":"P",
    "gn:feature_code":"PPL",
    "gn:name":"Kanjuanwala",
    "gn:population":0,
    "gn:timezone":"Asia/Karachi",
    "iso:country":"PK",
    "name:und_x_variant":[
        "K\u0101nj\u016b\u0101nw\u0101la (upper)"
    ],
    "wof:name":"Kanjuanwala",
    "wof:placetype":"locality"
},
  "geometry": {"coordinates":[71.63736999999998,32.54825],"type":"Point"}
}