{
  "type": "Feature",
  "properties": {
    "gn:admin1_code":"5.0",
    "gn:asciiname":"Pir Muhammad",
    "gn:country_code":"PK",
    "gn:dem":45,
    "gn:feature_class":"P",
    "gn:feature_code":"PPL",
    "gn:name":"Pir Muhammad",
    "gn:population":0,
    "gn:timezone":"Asia/Karachi",
    "iso:country":"PK",
    "name:fra_x_preferred":[
        "Pir Muhammad"
    ],
    "name:jpn_x_preferred":[
        "\u30d4\u30fc\u30eb\u30fb\u30e0\u30cf\u30f3\u30de\u30c9"
    ],
    "wof:name":"Pir Muhammad",
    "wof:placetype":"locality"
},
  "geometry": {"coordinates":[67.86605,27.38499],"type":"Point"}
}