{
  "type": "Feature",
  "properties": {
    "gn:admin1_code":"3.0",
    "gn:asciiname":"Dagai",
    "gn:country_code":"PK",
    "gn:dem":867,
    "gn:feature_class":"P",
    "gn:feature_code":"PPL",
    "gn:name":"Dagai",
    "gn:population":0,
    "gn:timezone":"Asia/Karachi",
    "iso:country":"PK",
    "name:pnb_x_preferred":[
        "\u0688\u06af\u0627\u0626"
    ],
    "name:und_x_variant":[
        "Dagi",
        "Dagai"
    ],
    "name:urd_x_preferred":[
        "\u062f\u06af\u0626\u06cc"
    ],
    "wof:name":"Dagai",
    "wof:placetype":"locality"
},
  "geometry": {"coordinates":[72.27016999999999,34.76492],"type":"Point"}
}