{
  "type": "Feature",
  "properties": {
    "gn:admin1_code":"4",
    "gn:asciiname":"Jodheke",
    "gn:country_code":"PK",
    "gn:dem":170,
    "gn:feature_class":"P",
    "gn:feature_code":"PPL",
    "gn:name":"Jodheke",
    "gn:population":0,
    "gn:timezone":"Asia/Karachi",
    "iso:country":"PK",
    "name:und_x_variant":[
        "Jodh Singh"
    ],
    "wof:name":"Jodheke",
    "wof:placetype":"locality"
},
  "geometry": {"coordinates":[73.81975,30.31309000000001],"type":"Point"}
}