{
  "type": "Feature",
  "properties": {
    "gn:admin1_code":"4.0",
    "gn:asciiname":"Hardo Jeoki",
    "gn:cc2":"PK",
    "gn:country_code":"PK",
    "gn:dem":216,
    "gn:feature_class":"P",
    "gn:feature_code":"PPL",
    "gn:name":"Hardo Jeoki",
    "gn:population":0,
    "gn:timezone":"Asia/Karachi",
    "iso:country":"PK",
    "name:und_x_variant":[
        "Hardo Jioke",
        "Hardo Jeoke",
        "Hardo Jeoki"
    ],
    "wof:name":"Hardo Jeoki",
    "wof:placetype":"locality"
},
  "geometry": {"coordinates":[73.88333,32.35],"type":"Point"}
}