{
  "type": "Feature",
  "properties": {
    "gn:admin1_code":"5.0",
    "gn:asciiname":"Goth Hanif Laghari",
    "gn:country_code":"PK",
    "gn:dem":16,
    "gn:feature_class":"P",
    "gn:feature_code":"PPL",
    "gn:name":"Goth Hanif Laghari",
    "gn:population":0,
    "gn:timezone":"Asia/Karachi",
    "iso:country":"PK",
    "name:und_x_variant":[
        "Hanif Lagh\u0101ri"
    ],
    "wof:name":"Goth Hanif Laghari",
    "wof:placetype":"locality"
},
  "geometry": {"coordinates":[68.87183,25.3678],"type":"Point"}
}