{
  "type": "Feature",
  "properties": {
    "gn:admin1_code":"4.0",
    "gn:asciiname":"Sarahdre",
    "gn:country_code":"PK",
    "gn:dem":553,
    "gn:feature_class":"P",
    "gn:feature_code":"PPL",
    "gn:name":"Sarahdre",
    "gn:population":0,
    "gn:timezone":"Asia/Karachi",
    "iso:country":"PK",
    "name:und_x_variant":[
        "Sar\u0101hdre"
    ],
    "wof:name":"Sarahdre",
    "wof:placetype":"locality"
},
  "geometry": {"coordinates":[73.15281999999998,33.25216],"type":"Point"}
}