{
  "type": "Feature",
  "properties": {
    "gn:admin1_code":"5",
    "gn:asciiname":"Yaro Khosa",
    "gn:country_code":"PK",
    "gn:dem":65,
    "gn:feature_class":"P",
    "gn:feature_code":"PPL",
    "gn:name":"Y\u0101ro Khosa",
    "gn:population":0,
    "gn:timezone":"Asia/Karachi",
    "iso:country":"PK",
    "wof:name":"Yaro Khosa",
    "wof:placetype":"locality"
},
  "geometry": {"coordinates":[68.93194,28.40278],"type":"Point"}
}