{
  "type": "Feature",
  "properties": {
    "gn:admin1_code":"4.0",
    "gn:asciiname":"Pind",
    "gn:country_code":"PK",
    "gn:dem":464,
    "gn:feature_class":"P",
    "gn:feature_code":"PPL",
    "gn:name":"Pind",
    "gn:population":0,
    "gn:timezone":"Asia/Karachi",
    "iso:country":"PK",
    "wof:name":"Pind",
    "wof:placetype":"locality"
},
  "geometry": {"coordinates":[72.77356999999998,33.80565],"type":"Point"}
}