{
  "type": "Feature",
  "properties": {
    "gn:admin1_code":"6.0",
    "gn:asciiname":"Athmuqam",
    "gn:country_code":"PK",
    "gn:dem":1386,
    "gn:feature_class":"P",
    "gn:feature_code":"PPLA2",
    "gn:name":"Athmuqam",
    "gn:population":0,
    "gn:timezone":"Asia/Karachi",
    "iso:country":"PK",
    "name:fas_x_preferred":[
        "\u0627\u062a\u0647\u200c\u0645\u0642\u0627\u0645"
    ],
    "name:hin_x_preferred":[
        "\u0906\u0920\u092e\u0941\u0915\u093e\u092e"
    ],
    "name:pnb_x_preferred":[
        "\u0627\u0679\u06be\u0645\u0642\u0627\u0645"
    ],
    "name:urd_x_preferred":[
        "\u0622\u0679\u06be\u0645\u0642\u0627\u0645"
    ],
    "wof:name":"Athmuqam",
    "wof:placetype":"locality"
},
  "geometry": {"coordinates":[73.89724,34.57173],"type":"Point"}
}