{
  "type": "Feature",
  "properties": {
    "gn:admin1_code":"4",
    "gn:asciiname":"Buttar",
    "gn:country_code":"PK",
    "gn:dem":232,
    "gn:feature_class":"P",
    "gn:feature_code":"PPL",
    "gn:name":"Buttar",
    "gn:population":0,
    "gn:timezone":"Asia/Karachi",
    "iso:country":"PK",
    "name:hin_x_preferred":[
        "\u092c\u0941\u091f\u0930"
    ],
    "name:pan_x_preferred":[
        "\u0a2c\u0a41\u0a71\u0a1f\u0a30"
    ],
    "name:pnb_x_preferred":[
        "\u0628\u0679\u0651\u0631"
    ],
    "name:urd_x_preferred":[
        "\u0628\u0679\u0631"
    ],
    "wof:name":"Buttar",
    "wof:placetype":"locality"
},
  "geometry": {"coordinates":[74.67433,32.14467],"type":"Point"}
}