{
  "type": "Feature",
  "properties": {
    "gn:admin1_code":"3.0",
    "gn:asciiname":"Wanda Shirdil Khan",
    "gn:country_code":"PK",
    "gn:dem":295,
    "gn:feature_class":"P",
    "gn:feature_code":"PPL",
    "gn:name":"Wanda Shirdil Khan",
    "gn:population":0,
    "gn:timezone":"Asia/Karachi",
    "iso:country":"PK",
    "name:und_x_variant":[
        "Sherdil Kh\u0101n"
    ],
    "wof:name":"Wanda Shirdil Khan",
    "wof:placetype":"locality"
},
  "geometry": {"coordinates":[70.86521,32.82131],"type":"Point"}
}