{
  "type": "Feature",
  "properties": {
    "gn:admin1_code":"4",
    "gn:asciiname":"Karunta",
    "gn:country_code":"PK",
    "gn:dem":524,
    "gn:feature_class":"P",
    "gn:feature_code":"PPL",
    "gn:name":"Karunta",
    "gn:population":0,
    "gn:timezone":"Asia/Karachi",
    "iso:country":"PK",
    "name:und_x_variant":[
        "Uparla Kar\u016bnta"
    ],
    "wof:name":"Karunta",
    "wof:placetype":"locality"
},
  "geometry": {"coordinates":[73.49249,33.17005],"type":"Point"}
}