{
  "type": "Feature",
  "properties": {
    "gn:admin1_code":"4.0",
    "gn:asciiname":"Islam Nagar",
    "gn:country_code":"PK",
    "gn:dem":141,
    "gn:feature_class":"P",
    "gn:feature_code":"PPL",
    "gn:name":"Islam Nagar",
    "gn:population":0,
    "gn:timezone":"Asia/Karachi",
    "iso:country":"PK",
    "name:eng_x_preferred":[
        "Islam Nagar"
    ],
    "name:urd_x_preferred":[
        "\u0627\u0633\u0644\u0627\u0645 \u0646\u06af\u0631"
    ],
    "wof:name":"Islam Nagar",
    "wof:placetype":"locality"
},
  "geometry": {"coordinates":[72.82804,29.82279],"type":"Point"}
}