{
  "type": "Feature",
  "properties": {
    "gn:admin1_code":"4",
    "gn:asciiname":"Chak One Hundred Twenty-seven ML",
    "gn:country_code":"PK",
    "gn:dem":141,
    "gn:feature_class":"P",
    "gn:feature_code":"PPL",
    "gn:name":"Chak One Hundred Twenty-seven ML",
    "gn:population":0,
    "gn:timezone":"Asia/Karachi",
    "iso:country":"PK",
    "name:und_x_variant":[
        "Chak One Hundred Twenty-Seven ML",
        "Kheraw\u0101la",
        "Chak 127 ML",
        "Chak One Hundred Twenty-seven ML"
    ],
    "wof:name":"Chak One Hundred Twenty-seven ML",
    "wof:placetype":"locality"
},
  "geometry": {"coordinates":[71.39765,30.70548],"type":"Point"}
}