{
  "type": "Feature",
  "properties": {
    "gn:admin1_code":"2.0",
    "gn:asciiname":"Toruski",
    "gn:country_code":"PK",
    "gn:dem":1590,
    "gn:feature_class":"P",
    "gn:feature_code":"PPL",
    "gn:name":"Toruski",
    "gn:population":0,
    "gn:timezone":"Asia/Karachi",
    "iso:country":"PK",
    "wof:name":"Toruski",
    "wof:placetype":"locality"
},
  "geometry": {"coordinates":[68.17041999999999,30.76203],"type":"Point"}
}