{
  "type": "Feature",
  "properties": {
    "gn:admin1_code":"4",
    "gn:asciiname":"Khan Da Kot",
    "gn:country_code":"PK",
    "gn:dem":172,
    "gn:feature_class":"P",
    "gn:feature_code":"PPL",
    "gn:name":"Khan Da Kot",
    "gn:population":0,
    "gn:timezone":"Asia/Karachi",
    "iso:country":"PK",
    "name:und_x_variant":[
        "Thatta Warbi\u0101n"
    ],
    "wof:name":"Khan Da Kot",
    "wof:placetype":"locality"
},
  "geometry": {"coordinates":[72.75999,31.55339],"type":"Point"}
}