{
  "type": "Feature",
  "properties": {
    "gn:admin1_code":"03",
    "gn:asciiname":"Nar Sahibzada Khost",
    "gn:country_code":"PK",
    "gn:dem":301,
    "gn:feature_class":"P",
    "gn:feature_code":"PPL",
    "gn:name":"Nar Sahibzada Khost",
    "gn:population":0,
    "gn:timezone":"Asia/Karachi",
    "iso:country":"PK",
    "name:und_x_variant":[
        "Sahibz\u0101da Khost",
        "Nar Sahibzada Khost"
    ],
    "wof:name":"Nar Sahibzada Khost",
    "wof:placetype":"locality"
},
  "geometry": {"coordinates":[70.79034,32.83699],"type":"Point"}
}