{
  "type": "Feature",
  "properties": {
    "gn:admin1_code":"2.0",
    "gn:asciiname":"Akhruk",
    "gn:country_code":"PK",
    "gn:dem":2204,
    "gn:feature_class":"P",
    "gn:feature_code":"PPL",
    "gn:name":"Akhruk",
    "gn:population":0,
    "gn:timezone":"Asia/Karachi",
    "iso:country":"PK",
    "wof:name":"Akhruk",
    "wof:placetype":"locality"
},
  "geometry": {"coordinates":[66.56504,28.79026],"type":"Point"}
}