{
  "type": "Feature",
  "properties": {
    "gn:admin1_code":"1.0",
    "gn:asciiname":"Tabai Tangai",
    "gn:country_code":"PK",
    "gn:dem":2210,
    "gn:feature_class":"P",
    "gn:feature_code":"PPL",
    "gn:name":"Tabai Tangai",
    "gn:population":0,
    "gn:timezone":"Asia/Karachi",
    "iso:country":"PK",
    "name:und_x_variant":[
        "Tabai Tangi"
    ],
    "wof:name":"Tabai Tangai",
    "wof:placetype":"locality"
},
  "geometry": {"coordinates":[70.31953,33.90203],"type":"Point"}
}