{
  "type": "Feature",
  "properties": {
    "gn:admin1_code":"4",
    "gn:asciiname":"Madanianwala",
    "gn:country_code":"PK",
    "gn:dem":192,
    "gn:feature_class":"P",
    "gn:feature_code":"PPL",
    "gn:name":"Madanianwala",
    "gn:population":0,
    "gn:timezone":"Asia/Karachi",
    "iso:country":"PK",
    "wof:name":"Madanianwala",
    "wof:placetype":"locality"
},
  "geometry": {"coordinates":[71.95,32.27778],"type":"Point"}
}