{
  "type": "Feature",
  "properties": {
    "gn:admin1_code":"3.0",
    "gn:asciiname":"Dobandai",
    "gn:country_code":"PK",
    "gn:dem":407,
    "gn:feature_class":"P",
    "gn:feature_code":"PPL",
    "gn:name":"Dobandai",
    "gn:population":0,
    "gn:timezone":"Asia/Karachi",
    "iso:country":"PK",
    "wof:name":"Dobandai",
    "wof:placetype":"locality"
},
  "geometry": {"coordinates":[71.87997,34.43023],"type":"Point"}
}