{
  "type": "Feature",
  "properties": {
    "gn:admin1_code":"4",
    "gn:asciiname":"Naglial Umer Khan",
    "gn:country_code":"PK",
    "gn:dem":461,
    "gn:feature_class":"P",
    "gn:feature_code":"PPL",
    "gn:name":"Naglial Umer Khan",
    "gn:population":0,
    "gn:timezone":"Asia/Karachi",
    "iso:country":"PK",
    "name:und_x_variant":[
        "Nagail Umar Kh\u0101n"
    ],
    "wof:name":"Naglial Umer Khan",
    "wof:placetype":"locality"
},
  "geometry": {"coordinates":[73.32621999999998,33.24542],"type":"Point"}
}