{
  "type": "Feature",
  "properties": {
    "gn:admin1_code":"5",
    "gn:asciiname":"Mir Nasrullah Khan Bijarani",
    "gn:country_code":"PK",
    "gn:dem":65,
    "gn:feature_class":"P",
    "gn:feature_code":"PPL",
    "gn:name":"Mir Nasrullah Khan Bijarani",
    "gn:population":0,
    "gn:timezone":"Asia/Karachi",
    "iso:country":"PK",
    "name:und_x_variant":[
        "Khair Muhammad Ghani"
    ],
    "wof:name":"Mir Nasrullah Khan Bijarani",
    "wof:placetype":"locality"
},
  "geometry": {"coordinates":[68.95138,28.16012000000001],"type":"Point"}
}