{
  "type": "Feature",
  "properties": {
    "gn:admin1_code":"3.0",
    "gn:asciiname":"Harif Khan Kalle",
    "gn:country_code":"PK",
    "gn:dem":347,
    "gn:feature_class":"P",
    "gn:feature_code":"PPL",
    "gn:name":"Harif Khan Kalle",
    "gn:population":0,
    "gn:timezone":"Asia/Karachi",
    "iso:country":"PK",
    "name:eng_x_preferred":[
        "Harif Kalle"
    ],
    "wof:name":"Harif Khan Kalle",
    "wof:placetype":"locality"
},
  "geometry": {"coordinates":[72.28815999999998,34.11818],"type":"Point"}
}