{
  "type": "Feature",
  "properties": {
    "gn:admin1_code":"4.0",
    "gn:asciiname":"Basti Adam",
    "gn:country_code":"PK",
    "gn:dem":125,
    "gn:feature_class":"P",
    "gn:feature_code":"PPL",
    "gn:name":"Basti Adam",
    "gn:population":0,
    "gn:timezone":"Asia/Karachi",
    "iso:country":"PK",
    "name:eng_x_preferred":[
        "Basti Adam"
    ],
    "name:eng_x_variant":[
        "Khokhar"
    ],
    "wof:name":"Basti Adam",
    "wof:placetype":"locality"
},
  "geometry": {"coordinates":[70.97568000000003,30.22655],"type":"Point"}
}