{
  "type": "Feature",
  "properties": {
    "gn:admin1_code":"03",
    "gn:asciiname":"Nakhtar",
    "gn:country_code":"PK",
    "gn:dem":839,
    "gn:feature_class":"P",
    "gn:feature_code":"PPL",
    "gn:name":"Nakhtar",
    "gn:population":0,
    "gn:timezone":"Asia/Karachi",
    "iso:country":"PK",
    "name:und_x_variant":[
        "Nakhatar",
        "Nakhtar"
    ],
    "wof:name":"Nakhtar",
    "wof:placetype":"locality"
},
  "geometry": {"coordinates":[72.75426999999998,34.60117],"type":"Point"}
}