{
  "type": "Feature",
  "properties": {
    "gn:admin1_code":"7.0",
    "gn:asciiname":"Dogah",
    "gn:country_code":"PK",
    "gn:dem":1779,
    "gn:feature_class":"P",
    "gn:feature_code":"PPL",
    "gn:name":"Dogah",
    "gn:population":0,
    "gn:timezone":"Asia/Karachi",
    "iso:country":"PK",
    "wof:name":"Dogah",
    "wof:placetype":"locality"
},
  "geometry": {"coordinates":[74.35876,35.45674],"type":"Point"}
}