{
  "type": "Feature",
  "properties": {
    "gn:admin1_code":"2.0",
    "gn:asciiname":"Kishari",
    "gn:country_code":"PK",
    "gn:dem":1147,
    "gn:feature_class":"P",
    "gn:feature_code":"PPL",
    "gn:name":"Kishari",
    "gn:population":0,
    "gn:timezone":"Asia/Karachi",
    "iso:country":"PK",
    "wof:name":"Kishari",
    "wof:placetype":"locality"
},
  "geometry": {"coordinates":[64.92919000000001,26.91876],"type":"Point"}
}