{
  "type": "Feature",
  "properties": {
    "gn:admin1_code":"2.0",
    "gn:asciiname":"Badduzai",
    "gn:country_code":"PK",
    "gn:dem":1782,
    "gn:feature_class":"P",
    "gn:feature_code":"PPL",
    "gn:name":"Badduzai",
    "gn:population":0,
    "gn:timezone":"Asia/Karachi",
    "iso:country":"PK",
    "wof:name":"Badduzai",
    "wof:placetype":"locality"
},
  "geometry": {"coordinates":[67.0532,29.6187],"type":"Point"}
}