{
  "type": "Feature",
  "properties": {
    "gn:admin1_code":"4.0",
    "gn:asciiname":"Burare",
    "gn:country_code":"PK",
    "gn:dem":87,
    "gn:feature_class":"P",
    "gn:feature_code":"PPL",
    "gn:name":"Burare",
    "gn:population":0,
    "gn:timezone":"Asia/Karachi",
    "iso:country":"PK",
    "name:und_x_variant":[
        "Nurpur",
        "Burare"
    ],
    "wof:name":"Burare",
    "wof:placetype":"locality"
},
  "geometry": {"coordinates":[70.21958000000001,28.59394],"type":"Point"}
}