{
  "type": "Feature",
  "properties": {
    "gn:admin1_code":"2.0",
    "gn:asciiname":"Tikhoi",
    "gn:country_code":"PK",
    "gn:dem":2624,
    "gn:feature_class":"P",
    "gn:feature_code":"PPL",
    "gn:name":"Tikhoi",
    "gn:population":0,
    "gn:timezone":"Asia/Karachi",
    "iso:country":"PK",
    "wof:name":"Tikhoi",
    "wof:placetype":"locality"
},
  "geometry": {"coordinates":[67.58628,30.92952],"type":"Point"}
}