{
  "type": "Feature",
  "properties": {
    "gn:admin1_code":"3.0",
    "gn:asciiname":"Naji Ajoor",
    "gn:country_code":"PK",
    "gn:dem":382,
    "gn:feature_class":"P",
    "gn:feature_code":"PPL",
    "gn:name":"Naji Ajoor",
    "gn:population":0,
    "gn:timezone":"Asia/Karachi",
    "iso:country":"PK",
    "name:eng_x_preferred":[
        "Naji Ajoor"
    ],
    "wof:name":"Naji Ajoor",
    "wof:placetype":"locality"
},
  "geometry": {"coordinates":[71.88972,34.37083],"type":"Point"}
}