{
  "type": "Feature",
  "properties": {
    "gn:admin1_code":"4",
    "gn:asciiname":"Kudaiabadwala",
    "gn:country_code":"PK",
    "gn:dem":126,
    "gn:feature_class":"P",
    "gn:feature_code":"PPL",
    "gn:name":"Kudaiabadwala",
    "gn:population":0,
    "gn:timezone":"Asia/Karachi",
    "iso:country":"PK",
    "name:und_x_variant":[
        "Khud\u0101\u012b B\u0101dw\u0101la"
    ],
    "wof:name":"Kudaiabadwala",
    "wof:placetype":"locality"
},
  "geometry": {"coordinates":[71.95652,29.65492],"type":"Point"}
}