{
  "type": "Feature",
  "properties": {
    "gn:admin1_code":"7.0",
    "gn:asciiname":"Zaibring",
    "gn:country_code":"PK",
    "gn:dem":3882,
    "gn:feature_class":"P",
    "gn:feature_code":"PPL",
    "gn:name":"Zaibring",
    "gn:population":0,
    "gn:timezone":"Asia/Karachi",
    "iso:country":"PK",
    "wof:name":"Zaibring",
    "wof:placetype":"locality"
},
  "geometry": {"coordinates":[76.23364000000002,35.17869],"type":"Point"}
}