{
  "type": "Feature",
  "properties": {
    "gn:admin1_code":"3.0",
    "gn:asciiname":"Sarkandai",
    "gn:country_code":"PK",
    "gn:dem":1607,
    "gn:feature_class":"P",
    "gn:feature_code":"PPL",
    "gn:name":"Sarkandai",
    "gn:population":0,
    "gn:timezone":"Asia/Karachi",
    "iso:country":"PK",
    "wof:name":"Sarkandai",
    "wof:placetype":"locality"
},
  "geometry": {"coordinates":[73.10590000000001,34.83158],"type":"Point"}
}