{
  "type": "Feature",
  "properties": {
    "gn:admin1_code":"1.0",
    "gn:asciiname":"Dabran",
    "gn:country_code":"PK",
    "gn:dem":610,
    "gn:feature_class":"P",
    "gn:feature_code":"PPL",
    "gn:name":"Dabran",
    "gn:population":0,
    "gn:timezone":"Asia/Karachi",
    "iso:country":"PK",
    "name:und_x_variant":[
        "Dabarm"
    ],
    "wof:name":"Dabran",
    "wof:placetype":"locality"
},
  "geometry": {"coordinates":[70.42331999999998,32.5877],"type":"Point"}
}