{
  "type": "Feature",
  "properties": {
    "gn:admin1_code":"4",
    "gn:asciiname":"Chak Twenty Five",
    "gn:country_code":"PK",
    "gn:dem":210,
    "gn:feature_class":"P",
    "gn:feature_code":"PPL",
    "gn:name":"Chak Twenty Five",
    "gn:population":0,
    "gn:timezone":"Asia/Karachi",
    "iso:country":"PK",
    "name:und_x_variant":[
        "Chak Twenty-three"
    ],
    "wof:name":"Chak Twenty Five",
    "wof:placetype":"locality"
},
  "geometry": {"coordinates":[73.23662,32.41002],"type":"Point"}
}