{
  "type": "Feature",
  "properties": {
    "gn:admin1_code":"3",
    "gn:asciiname":"Pure Tikarai",
    "gn:country_code":"PK",
    "gn:dem":3227,
    "gn:feature_class":"P",
    "gn:feature_code":"PPL",
    "gn:name":"Pure Tikarai",
    "gn:population":0,
    "gn:timezone":"Asia/Karachi",
    "iso:country":"PK",
    "name:eng_x_preferred":[
        "Pure Tikarai"
    ],
    "wof:name":"Pure Tikarai",
    "wof:placetype":"locality"
},
  "geometry": {"coordinates":[71.98909999999999,35.51228],"type":"Point"}
}