{
  "type": "Feature",
  "properties": {
    "gn:admin1_code":"4",
    "gn:asciiname":"Basti Bobra",
    "gn:country_code":"PK",
    "gn:dem":99,
    "gn:feature_class":"P",
    "gn:feature_code":"PPL",
    "gn:name":"Basti Bobra",
    "gn:population":0,
    "gn:timezone":"Asia/Karachi",
    "iso:country":"PK",
    "name:und_x_variant":[
        "Basti Bohra"
    ],
    "wof:name":"Basti Bobra",
    "wof:placetype":"locality"
},
  "geometry": {"coordinates":[70.94611999999999,29.13202],"type":"Point"}
}