{
  "type": "Feature",
  "properties": {
    "gn:admin1_code":"4.0",
    "gn:asciiname":"Kariali",
    "gn:country_code":"PK",
    "gn:dem":211,
    "gn:feature_class":"P",
    "gn:feature_code":"PPL",
    "gn:name":"Kariali",
    "gn:population":0,
    "gn:timezone":"Asia/Karachi",
    "iso:country":"PK",
    "wof:name":"Kariali",
    "wof:placetype":"locality"
},
  "geometry": {"coordinates":[73.21978,32.68962],"type":"Point"}
}