{
  "type": "Feature",
  "properties": {
    "gn:admin1_code":"6.0",
    "gn:asciiname":"Bilian",
    "gn:country_code":"PK",
    "gn:dem":988,
    "gn:feature_class":"P",
    "gn:feature_code":"PPL",
    "gn:name":"Bilian",
    "gn:population":0,
    "gn:timezone":"Asia/Karachi",
    "iso:country":"PK",
    "name:und_x_variant":[
        "Bhiti\u0101n"
    ],
    "wof:name":"Bilian",
    "wof:placetype":"locality"
},
  "geometry": {"coordinates":[73.68031999999999,33.62769],"type":"Point"}
}