{
  "type": "Feature",
  "properties": {
    "gn:admin1_code":"6.0",
    "gn:asciiname":"Palang",
    "gn:country_code":"PK",
    "gn:dem":628,
    "gn:feature_class":"P",
    "gn:feature_code":"PPL",
    "gn:name":"Palang",
    "gn:population":0,
    "gn:timezone":"Asia/Karachi",
    "iso:country":"PK",
    "wof:name":"Palang",
    "wof:placetype":"locality"
},
  "geometry": {"coordinates":[73.63172,33.64041],"type":"Point"}
}