{
  "type": "Feature",
  "properties": {
    "gn:admin1_code":"4",
    "gn:asciiname":"Kairewala",
    "gn:country_code":"PK",
    "gn:dem":128,
    "gn:feature_class":"P",
    "gn:feature_code":"PPL",
    "gn:name":"Kairewala",
    "gn:population":0,
    "gn:timezone":"Asia/Karachi",
    "iso:country":"PK",
    "name:und_x_variant":[
        "Kaironw\u0101la"
    ],
    "wof:name":"Kairewala",
    "wof:placetype":"locality"
},
  "geometry": {"coordinates":[71.0367,30.36602],"type":"Point"}
}