{
  "type": "Feature",
  "properties": {
    "gn:admin1_code":"7.0",
    "gn:asciiname":"Muse Harai",
    "gn:country_code":"PK",
    "gn:dem":3313,
    "gn:feature_class":"P",
    "gn:feature_code":"PPL",
    "gn:name":"Muse Harai",
    "gn:population":0,
    "gn:timezone":"Asia/Karachi",
    "iso:country":"PK",
    "wof:name":"Muse Harai",
    "wof:placetype":"locality"
},
  "geometry": {"coordinates":[74.57524000000002,35.8948],"type":"Point"}
}