{
  "type": "Feature",
  "properties": {
    "gn:admin1_code":"4",
    "gn:asciiname":"Dholwala",
    "gn:country_code":"PK",
    "gn:dem":164,
    "gn:feature_class":"P",
    "gn:feature_code":"PPL",
    "gn:name":"Dholwala",
    "gn:population":0,
    "gn:timezone":"Asia/Karachi",
    "iso:country":"PK",
    "name:und_x_variant":[
        "Muhammad Y\u0101rw\u0101la"
    ],
    "wof:name":"Dholwala",
    "wof:placetype":"locality"
},
  "geometry": {"coordinates":[71.60453000000003,31.35019],"type":"Point"}
}