{
  "type": "Feature",
  "properties": {
    "gn:admin1_code":"2.0",
    "gn:asciiname":"Ahmad Bazar",
    "gn:country_code":"PK",
    "gn:dem":910,
    "gn:feature_class":"P",
    "gn:feature_code":"PPL",
    "gn:name":"Ahmad Bazar",
    "gn:population":0,
    "gn:timezone":"Asia/Karachi",
    "iso:country":"PK",
    "wof:name":"Ahmad Bazar",
    "wof:placetype":"locality"
},
  "geometry": {"coordinates":[63.24113000000001,26.64502],"type":"Point"}
}