{
  "type": "Feature",
  "properties": {
    "gn:admin1_code":"5",
    "gn:asciiname":"Meting Koh",
    "gn:country_code":"PK",
    "gn:dem":30,
    "gn:feature_class":"P",
    "gn:feature_code":"PPL",
    "gn:name":"Meting Koh",
    "gn:population":0,
    "gn:timezone":"Asia/Karachi",
    "iso:country":"PK",
    "name:eng_x_preferred":[
        "Meting Ku\u0101n"
    ],
    "wof:name":"Meting Koh",
    "wof:placetype":"locality"
},
  "geometry": {"coordinates":[68.19535999999999,25.13198],"type":"Point"}
}