{
  "type": "Feature",
  "properties": {
    "gn:admin1_code":"4.0",
    "gn:asciiname":"Jindhar",
    "gn:country_code":"PK",
    "gn:dem":270,
    "gn:feature_class":"P",
    "gn:feature_code":"PPL",
    "gn:name":"Jindhar",
    "gn:population":0,
    "gn:timezone":"Asia/Karachi",
    "iso:country":"PK",
    "wof:name":"Jindhar",
    "wof:placetype":"locality"
},
  "geometry": {"coordinates":[75.05383,32.33251],"type":"Point"}
}