{
  "type": "Feature",
  "properties": {
    "gn:admin1_code":"2.0",
    "gn:asciiname":"Kili Shahdinkor",
    "gn:country_code":"PK",
    "gn:dem":715,
    "gn:feature_class":"P",
    "gn:feature_code":"PPL",
    "gn:name":"Kili Shahdinkor",
    "gn:population":0,
    "gn:timezone":"Asia/Karachi",
    "iso:country":"PK",
    "name:und_x_variant":[
        "Sh\u0101h D\u012bn Kor"
    ],
    "wof:name":"Kili Shahdinkor",
    "wof:placetype":"locality"
},
  "geometry": {"coordinates":[65.50333000000001,28.46976],"type":"Point"}
}