{
  "type": "Feature",
  "properties": {
    "gn:admin1_code":"6",
    "gn:asciiname":"Pari",
    "gn:country_code":"PK",
    "gn:dem":2847,
    "gn:feature_class":"P",
    "gn:feature_code":"PPL",
    "gn:name":"Pari",
    "gn:population":0,
    "gn:timezone":"Asia/Karachi",
    "iso:country":"PK",
    "name:ceb_x_preferred":[
        "Pari"
    ],
    "name:deu_x_preferred":[
        "Pari"
    ],
    "name:fin_x_preferred":[
        "Pari"
    ],
    "name:fra_x_preferred":[
        "Pari"
    ],
    "name:hye_x_preferred":[
        "\u0533\u0580\u0561\u0566"
    ],
    "name:ita_x_preferred":[
        "Pari"
    ],
    "name:rus_x_preferred":[
        "\u041f\u0430\u0440\u0438"
    ],
    "name:sco_x_preferred":[
        "Pari"
    ],
    "name:swe_x_preferred":[
        "Pari"
    ],
    "name:tgl_x_preferred":[
        "Pari"
    ],
    "name:ukr_x_preferred":[
        "\u041f\u0430\u0440\u0456"
    ],
    "wof:name":"Pari",
    "wof:placetype":"locality"
},
  "geometry": {"coordinates":[73.79586999999999,34.60889],"type":"Point"}
}