{
  "type": "Feature",
  "properties": {
    "gn:admin1_code":"6",
    "gn:asciiname":"Pari",
    "gn:country_code":"PK",
    "gn:dem":2847,
    "gn:feature_class":"P",
    "gn:feature_code":"PPL",
    "gn:name":"Pari",
    "gn:population":0,
    "gn:timezone":"Asia/Karachi",
    "iso:country":"PK",
    "wof:name":"Pari",
    "wof:placetype":"locality"
},
  "geometry": {"coordinates":[73.79586999999999,34.60889],"type":"Point"}
}