{
  "type": "Feature",
  "properties": {
    "gn:admin1_code":"3",
    "gn:asciiname":"Biakara",
    "gn:country_code":"PK",
    "gn:dem":1318,
    "gn:feature_class":"P",
    "gn:feature_code":"PPL",
    "gn:name":"Biakara",
    "gn:population":0,
    "gn:timezone":"Asia/Karachi",
    "iso:country":"PK",
    "name:und_x_variant":[
        "Balk\u0101rai"
    ],
    "wof:name":"Biakara",
    "wof:placetype":"locality"
},
  "geometry": {"coordinates":[72.34666,35.00891],"type":"Point"}
}