{
  "type": "Feature",
  "properties": {
    "gn:admin1_code":"5",
    "gn:asciiname":"Goth Mian",
    "gn:country_code":"PK",
    "gn:dem":45,
    "gn:feature_class":"P",
    "gn:feature_code":"PPL",
    "gn:name":"Goth Mian",
    "gn:population":0,
    "gn:timezone":"Asia/Karachi",
    "iso:country":"PK",
    "name:und_x_variant":[
        "Goth Mi\u0101ni"
    ],
    "wof:name":"Goth Mian",
    "wof:placetype":"locality"
},
  "geometry": {"coordinates":[67.92959,27.13453],"type":"Point"}
}