{
  "type": "Feature",
  "properties": {
    "gn:admin1_code":"3.0",
    "gn:asciiname":"Kehian",
    "gn:country_code":"PK",
    "gn:dem":1268,
    "gn:feature_class":"P",
    "gn:feature_code":"PPL",
    "gn:name":"Kehian",
    "gn:population":0,
    "gn:timezone":"Asia/Karachi",
    "iso:country":"PK",
    "name:eng_x_preferred":[
        "Kihan"
    ],
    "wof:name":"Kehian",
    "wof:placetype":"locality"
},
  "geometry": {"coordinates":[73.04083,33.89643],"type":"Point"}
}