{
  "type": "Feature",
  "properties": {
    "gn:admin1_code":"01",
    "gn:asciiname":"Sur Kankhai",
    "gn:country_code":"PK",
    "gn:dem":1940,
    "gn:feature_class":"P",
    "gn:feature_code":"PPL",
    "gn:name":"Sur Kankhai",
    "gn:population":0,
    "gn:timezone":"Asia/Karachi",
    "iso:country":"PK",
    "name:und_x_variant":[
        "S\u012br Gh\u0101khai",
        "S\u016br Gh\u0101khai",
        "Sur Kankhai",
        "Soor Ghakai"
    ],
    "wof:name":"Sur Kankhai",
    "wof:placetype":"locality"
},
  "geometry": {"coordinates":[70.71594,33.67881],"type":"Point"}
}