{
  "type": "Feature",
  "properties": {
    "gn:admin1_code":"4",
    "gn:asciiname":"Mondanewali",
    "gn:country_code":"PK",
    "gn:dem":163,
    "gn:feature_class":"P",
    "gn:feature_code":"PPL",
    "gn:name":"Mondanewali",
    "gn:population":0,
    "gn:timezone":"Asia/Karachi",
    "iso:country":"PK",
    "name:und_x_variant":[
        "Basti Chhina",
        "Basti Mod\u0101n\u012bw\u0101li",
        "Mondanewali"
    ],
    "wof:name":"Mondanewali",
    "wof:placetype":"locality"
},
  "geometry": {"coordinates":[70.93245999999998,31.51622],"type":"Point"}
}