{
  "type": "Feature",
  "properties": {
    "gn:admin1_code":"4",
    "gn:asciiname":"Chak Five Hundred Sixty-three Gugera Branch",
    "gn:country_code":"PK",
    "gn:dem":193,
    "gn:feature_class":"P",
    "gn:feature_code":"PPL",
    "gn:name":"Chak Five Hundred Sixty-three Gugera Branch",
    "gn:population":0,
    "gn:timezone":"Asia/Karachi",
    "iso:country":"PK",
    "name:und_x_variant":[
        "Sharqi"
    ],
    "wof:name":"Chak Five Hundred Sixty-three Gugera Branch",
    "wof:placetype":"locality"
},
  "geometry": {"coordinates":[73.63309,31.41623],"type":"Point"}
}