{
  "type": "Feature",
  "properties": {
    "gn:admin1_code":"6",
    "gn:asciiname":"Telpatre",
    "gn:country_code":"PK",
    "gn:dem":2753,
    "gn:feature_class":"P",
    "gn:feature_code":"PPL",
    "gn:name":"Telpatre",
    "gn:population":0,
    "gn:timezone":"Asia/Karachi",
    "iso:country":"PK",
    "name:und_x_variant":[
        "Tilpatre"
    ],
    "wof:name":"Telpatre",
    "wof:placetype":"locality"
},
  "geometry": {"coordinates":[73.82411999999999,34.23019],"type":"Point"}
}