{
  "type": "Feature",
  "properties": {
    "gn:admin1_code":"3.0",
    "gn:asciiname":"Muslim Abad",
    "gn:country_code":"PK",
    "gn:dem":400,
    "gn:feature_class":"P",
    "gn:feature_code":"PPL",
    "gn:name":"Muslim Abad",
    "gn:population":0,
    "gn:timezone":"Asia/Karachi",
    "iso:country":"PK",
    "name:eng_x_preferred":[
        "Muslim Abad"
    ],
    "wof:name":"Muslim Abad",
    "wof:placetype":"locality"
},
  "geometry": {"coordinates":[71.90176,34.40023],"type":"Point"}
}