{
  "type": "Feature",
  "properties": {
    "gn:admin1_code":"2.0",
    "gn:asciiname":"Imam Bakhsh Takri",
    "gn:country_code":"PK",
    "gn:dem":67,
    "gn:feature_class":"P",
    "gn:feature_code":"PPL",
    "gn:name":"Imam Bakhsh Takri",
    "gn:population":0,
    "gn:timezone":"Asia/Karachi",
    "iso:country":"PK",
    "name:und_x_variant":[
        "Takri Im\u0101m Bakhsh",
        "Im\u0101m akhsh Takri",
        "Takri Im\u0101m Bakh",
        "Imam Bakhsh Takri"
    ],
    "wof:name":"Imam Bakhsh Takri",
    "wof:placetype":"locality"
},
  "geometry": {"coordinates":[67.99823000000001,28.43771],"type":"Point"}
}