{
  "type": "Feature",
  "properties": {
    "gn:admin1_code":"2.0",
    "gn:asciiname":"Lal Bakhsh",
    "gn:country_code":"PK",
    "gn:dem":366,
    "gn:feature_class":"P",
    "gn:feature_code":"PPL",
    "gn:name":"Lal Bakhsh",
    "gn:population":0,
    "gn:timezone":"Asia/Karachi",
    "iso:country":"PK",
    "wof:name":"Lal Bakhsh",
    "wof:placetype":"locality"
},
  "geometry": {"coordinates":[65.59696,26.37389000000001],"type":"Point"}
}