{
  "type": "Feature",
  "properties": {
    "gn:admin1_code":"4",
    "gn:asciiname":"Rattarwala",
    "gn:country_code":"PK",
    "gn:dem":100,
    "gn:feature_class":"P",
    "gn:feature_code":"PPL",
    "gn:name":"Rattarwala",
    "gn:population":0,
    "gn:timezone":"Asia/Karachi",
    "iso:country":"PK",
    "wof:name":"Rattarwala",
    "wof:placetype":"locality"
},
  "geometry": {"coordinates":[70.78953,29.33857],"type":"Point"}
}