{
  "type": "Feature",
  "properties": {
    "gn:admin1_code":"4.0",
    "gn:asciiname":"Chak One Hundred Forty-eight - Six B",
    "gn:country_code":"PK",
    "gn:dem":157,
    "gn:feature_class":"P",
    "gn:feature_code":"PPL",
    "gn:name":"Chak One Hundred Forty-eight - Six B",
    "gn:population":0,
    "gn:timezone":"Asia/Karachi",
    "iso:country":"PK",
    "wof:name":"Chak One Hundred Forty-eight - Six B",
    "wof:placetype":"locality"
},
  "geometry": {"coordinates":[73.15613,29.49426],"type":"Point"}
}