{
  "type": "Feature",
  "properties": {
    "gn:admin1_code":"5.0",
    "gn:asciiname":"Adam Dahri",
    "gn:country_code":"PK",
    "gn:dem":42,
    "gn:feature_class":"P",
    "gn:feature_code":"PPL",
    "gn:name":"Adam Dahri",
    "gn:population":0,
    "gn:timezone":"Asia/Karachi",
    "iso:country":"PK",
    "name:und_x_variant":[
        "\u0100dam Lash\u0101ri"
    ],
    "wof:name":"Adam Dahri",
    "wof:placetype":"locality"
},
  "geometry": {"coordinates":[68.17533,26.62543],"type":"Point"}
}