{
  "type": "Feature",
  "properties": {
    "gn:admin1_code":"4",
    "gn:asciiname":"Tibbi Lakwali",
    "gn:country_code":"PK",
    "gn:dem":127,
    "gn:feature_class":"P",
    "gn:feature_code":"PPL",
    "gn:name":"Tibbi Lakwali",
    "gn:population":0,
    "gn:timezone":"Asia/Karachi",
    "iso:country":"PK",
    "name:eng_x_preferred":[
        "Tibbi L\u0101khew\u0101li"
    ],
    "wof:name":"Tibbi Lakwali",
    "wof:placetype":"locality"
},
  "geometry": {"coordinates":[70.98721,30.38065],"type":"Point"}
}