{
  "type": "Feature",
  "properties": {
    "gn:admin1_code":"2",
    "gn:asciiname":"Ghulam Jan Kili",
    "gn:country_code":"PK",
    "gn:dem":919,
    "gn:feature_class":"P",
    "gn:feature_code":"PPL",
    "gn:name":"Ghulam Jan Kili",
    "gn:population":0,
    "gn:timezone":"Asia/Karachi",
    "iso:country":"PK",
    "wof:name":"Ghulam Jan Kili",
    "wof:placetype":"locality"
},
  "geometry": {"coordinates":[65.89202,29.63084000000001],"type":"Point"}
}