{
  "type": "Feature",
  "properties": {
    "gn:admin1_code":"4",
    "gn:asciiname":"Basti Parora",
    "gn:country_code":"PK",
    "gn:dem":96,
    "gn:feature_class":"P",
    "gn:feature_code":"PPL",
    "gn:name":"Basti Parora",
    "gn:population":0,
    "gn:timezone":"Asia/Karachi",
    "iso:country":"PK",
    "name:und_x_variant":[
        "Basti Thume Par\u0101ra"
    ],
    "wof:name":"Basti Parora",
    "wof:placetype":"locality"
},
  "geometry": {"coordinates":[70.70905,29.06337000000001],"type":"Point"}
}