{
  "type": "Feature",
  "properties": {
    "gn:admin1_code":"4.0",
    "gn:asciiname":"Dhok Chakian",
    "gn:country_code":"PK",
    "gn:dem":842,
    "gn:feature_class":"P",
    "gn:feature_code":"PPL",
    "gn:name":"Dhok Chakian",
    "gn:population":0,
    "gn:timezone":"Asia/Karachi",
    "iso:country":"PK",
    "name:und_x_variant":[
        "Dhok Chari\u0101n"
    ],
    "wof:name":"Dhok Chakian",
    "wof:placetype":"locality"
},
  "geometry": {"coordinates":[72.22917,32.58569],"type":"Point"}
}