{
  "type": "Feature",
  "properties": {
    "gn:admin1_code":"7.0",
    "gn:asciiname":"Lajonchi",
    "gn:country_code":"PK",
    "gn:dem":3062,
    "gn:feature_class":"P",
    "gn:feature_code":"PPL",
    "gn:name":"Lajonchi",
    "gn:population":0,
    "gn:timezone":"Asia/Karachi",
    "iso:country":"PK",
    "name:und_x_variant":[
        "Laiyozh"
    ],
    "wof:name":"Lajonchi",
    "wof:placetype":"locality"
},
  "geometry": {"coordinates":[74.71565,35.04238],"type":"Point"}
}