{
  "type": "Feature",
  "properties": {
    "gn:admin1_code":"4.0",
    "gn:asciiname":"Wara Jamita",
    "gn:country_code":"PK",
    "gn:dem":218,
    "gn:feature_class":"P",
    "gn:feature_code":"PPL",
    "gn:name":"Wara Jamita",
    "gn:population":0,
    "gn:timezone":"Asia/Karachi",
    "iso:country":"PK",
    "name:und_x_variant":[
        "Jamite de W\u0101ra"
    ],
    "wof:name":"Wara Jamita",
    "wof:placetype":"locality"
},
  "geometry": {"coordinates":[74.51214,31.57105],"type":"Point"}
}