{
  "type": "Feature",
  "properties": {
    "gn:admin1_code":"2.0",
    "gn:asciiname":"Goth Goro Khan Gola",
    "gn:country_code":"PK",
    "gn:dem":125,
    "gn:feature_class":"P",
    "gn:feature_code":"PPL",
    "gn:name":"Goth Goro Khan Gola",
    "gn:population":0,
    "gn:timezone":"Asia/Karachi",
    "iso:country":"PK",
    "wof:name":"Goth Goro Khan Gola",
    "wof:placetype":"locality"
},
  "geometry": {"coordinates":[68.31248000000001,28.92593],"type":"Point"}
}