{
  "type": "Feature",
  "properties": {
    "gn:admin1_code":"1.0",
    "gn:asciiname":"Jaghur Kili",
    "gn:country_code":"PK",
    "gn:dem":1038,
    "gn:feature_class":"P",
    "gn:feature_code":"PPL",
    "gn:name":"Jaghur Kili",
    "gn:population":0,
    "gn:timezone":"Asia/Karachi",
    "iso:country":"PK",
    "wof:name":"Jaghur Kili",
    "wof:placetype":"locality"
},
  "geometry": {"coordinates":[69.40384,31.93389],"type":"Point"}
}