{
  "type": "Feature",
  "properties": {
    "gn:admin1_code":"2.0",
    "gn:asciiname":"Zhroba",
    "gn:country_code":"PK",
    "gn:dem":1281,
    "gn:elevation":"1897.0",
    "gn:feature_class":"P",
    "gn:feature_code":"PPL",
    "gn:name":"Zhroba",
    "gn:population":0,
    "gn:timezone":"Asia/Karachi",
    "iso:country":"PK",
    "wof:name":"Zhroba",
    "wof:placetype":"locality"
},
  "geometry": {"coordinates":[68.85874,30.36325],"type":"Point"}
}