{
  "type": "Feature",
  "properties": {
    "gn:admin1_code":"3.0",
    "gn:asciiname":"Jhok Ata Muhammad Jhandair",
    "gn:country_code":"PK",
    "gn:dem":170,
    "gn:feature_class":"P",
    "gn:feature_code":"PPL",
    "gn:name":"Jhok Ata Muhammad Jhandair",
    "gn:population":0,
    "gn:timezone":"Asia/Karachi",
    "iso:country":"PK",
    "wof:name":"Jhok Ata Muhammad Jhandair",
    "wof:placetype":"locality"
},
  "geometry": {"coordinates":[70.70300999999998,31.56786],"type":"Point"}
}