{
  "type": "Feature",
  "properties": {
    "gn:admin1_code":"4.0",
    "gn:asciiname":"Thalil",
    "gn:country_code":"PK",
    "gn:dem":612,
    "gn:feature_class":"P",
    "gn:feature_code":"PPL",
    "gn:name":"Thalil",
    "gn:population":0,
    "gn:timezone":"Asia/Karachi",
    "iso:country":"PK",
    "wof:name":"Thalil",
    "wof:placetype":"locality"
},
  "geometry": {"coordinates":[70.29754,30.75941],"type":"Point"}
}