{
  "type": "Feature",
  "properties": {
    "gn:admin1_code":"2",
    "gn:asciiname":"Khuddi Haji",
    "gn:country_code":"PK",
    "gn:dem":1590,
    "gn:feature_class":"P",
    "gn:feature_code":"PPL",
    "gn:name":"Khuddi Haji",
    "gn:population":0,
    "gn:timezone":"Asia/Karachi",
    "iso:country":"PK",
    "wof:name":"Khuddi Haji",
    "wof:placetype":"locality"
},
  "geometry": {"coordinates":[66.13785,29.12467],"type":"Point"}
}