{
  "type": "Feature",
  "properties": {
    "gn:admin1_code":"1.0",
    "gn:asciiname":"Isa Khel",
    "gn:country_code":"PK",
    "gn:dem":827,
    "gn:feature_class":"P",
    "gn:feature_code":"PPL",
    "gn:name":"Isa Khel",
    "gn:population":0,
    "gn:timezone":"Asia/Karachi",
    "iso:country":"PK",
    "name:und_x_variant":[
        "\u012asa Khel"
    ],
    "wof:name":"Isa Khel",
    "wof:placetype":"locality"
},
  "geometry": {"coordinates":[71.38636,33.80645999999999],"type":"Point"}
}