{
  "type": "Feature",
  "properties": {
    "gn:admin1_code":"4.0",
    "gn:asciiname":"Mari",
    "gn:country_code":"PK",
    "gn:dem":498,
    "gn:feature_class":"P",
    "gn:feature_code":"PPL",
    "gn:name":"Mari",
    "gn:population":0,
    "gn:timezone":"Asia/Karachi",
    "iso:country":"PK",
    "name:und_x_variant":[
        "Chach\u0101r\u0101nw\u0101li"
    ],
    "wof:name":"Mari",
    "wof:placetype":"locality"
},
  "geometry": {"coordinates":[72.66670000000001,32.90815],"type":"Point"}
}