{
  "type": "Feature",
  "properties": {
    "gn:admin1_code":"1.0",
    "gn:asciiname":"Bagzai",
    "gn:country_code":"PK",
    "gn:dem":981,
    "gn:feature_class":"P",
    "gn:feature_code":"PPL",
    "gn:name":"Bagzai",
    "gn:population":0,
    "gn:timezone":"Asia/Karachi",
    "iso:country":"PK",
    "wof:name":"Bagzai",
    "wof:placetype":"locality"
},
  "geometry": {"coordinates":[70.33372,33.53014],"type":"Point"}
}