{
  "type": "Feature",
  "properties": {
    "gn:admin1_code":"5",
    "gn:asciiname":"Goth Nodha",
    "gn:country_code":"PK",
    "gn:dem":62,
    "gn:feature_class":"P",
    "gn:feature_code":"PPL",
    "gn:name":"Goth Nodha",
    "gn:population":0,
    "gn:timezone":"Asia/Karachi",
    "iso:country":"PK",
    "name:eng_x_preferred":[
        "Goth Nodha"
    ],
    "name:und_x_variant":[
        "Nundhanw\u0101ri"
    ],
    "wof:name":"Goth Nodha",
    "wof:placetype":"locality"
},
  "geometry": {"coordinates":[68.02973,25.23916],"type":"Point"}
}