{
  "type": "Feature",
  "properties": {
    "gn:admin1_code":"5.0",
    "gn:asciiname":"Tikka Baran",
    "gn:country_code":"PK",
    "gn:dem":317,
    "gn:feature_class":"P",
    "gn:feature_code":"PPL",
    "gn:name":"Tikka Baran",
    "gn:population":0,
    "gn:timezone":"Asia/Karachi",
    "iso:country":"PK",
    "name:und_x_variant":[
        "Goth Tikka B\u0101r\u0101n",
        "B\u0101r\u0101n",
        "Tikka Baran"
    ],
    "wof:name":"Tikka Baran",
    "wof:placetype":"locality"
},
  "geometry": {"coordinates":[67.49713,25.96026],"type":"Point"}
}