{
  "type": "Feature",
  "properties": {
    "gn:admin1_code":"3.0",
    "gn:asciiname":"Sultanabad",
    "gn:country_code":"PK",
    "gn:dem":331,
    "gn:feature_class":"P",
    "gn:feature_code":"PPL",
    "gn:name":"Sultanabad",
    "gn:population":0,
    "gn:timezone":"Asia/Karachi",
    "iso:country":"PK",
    "name:aze_x_preferred":[
        "Sultanabad"
    ],
    "name:cat_x_preferred":[
        "Sultanabad"
    ],
    "name:deu_x_preferred":[
        "Sultanabad"
    ],
    "wof:name":"Sultanabad",
    "wof:placetype":"locality"
},
  "geometry": {"coordinates":[70.66046,32.54079],"type":"Point"}
}