{
  "type": "Feature",
  "properties": {
    "gn:admin1_code":"5",
    "gn:asciiname":"Qasim Raho",
    "gn:country_code":"PK",
    "gn:dem":37,
    "gn:feature_class":"P",
    "gn:feature_code":"PPL",
    "gn:name":"Qasim Raho",
    "gn:population":0,
    "gn:timezone":"Asia/Karachi",
    "iso:country":"PK",
    "wof:name":"Qasim Raho",
    "wof:placetype":"locality"
},
  "geometry": {"coordinates":[68.10139000000001,26.30278],"type":"Point"}
}