{
  "type": "Feature",
  "properties": {
    "gn:admin1_code":"5.0",
    "gn:asciiname":"Goth Kambir Jaskani",
    "gn:country_code":"PK",
    "gn:dem":13,
    "gn:feature_class":"P",
    "gn:feature_code":"PPL",
    "gn:name":"Goth Kambir Jaskani",
    "gn:population":0,
    "gn:timezone":"Asia/Karachi",
    "iso:country":"PK",
    "wof:name":"Goth Kambir Jaskani",
    "wof:placetype":"locality"
},
  "geometry": {"coordinates":[69.35141999999999,25.06906],"type":"Point"}
}