{
  "type": "Feature",
  "properties": {
    "gn:admin1_code":"2.0",
    "gn:asciiname":"Abdullah Bazar",
    "gn:country_code":"PK",
    "gn:dem":923,
    "gn:feature_class":"P",
    "gn:feature_code":"PPL",
    "gn:name":"Abdullah Bazar",
    "gn:population":0,
    "gn:timezone":"Asia/Karachi",
    "iso:country":"PK",
    "wof:name":"Abdullah Bazar",
    "wof:placetype":"locality"
},
  "geometry": {"coordinates":[63.22231,26.62715],"type":"Point"}
}