{
  "type": "Feature",
  "properties": {
    "gn:admin1_code":"5",
    "gn:asciiname":"Goth Dhalu Kaskheli",
    "gn:country_code":"PK",
    "gn:dem":23,
    "gn:feature_class":"P",
    "gn:feature_code":"PPL",
    "gn:name":"Goth Dhalu Kaskheli",
    "gn:population":0,
    "gn:timezone":"Asia/Karachi",
    "iso:country":"PK",
    "name:und_x_variant":[
        "Goth Dh\u0101lu Kh\u0101skheli",
        "Abdull\u0101h Kh\u0101skheli",
        "Goth Dhalu Kaskheli"
    ],
    "wof:name":"Goth Dhalu Kaskheli",
    "wof:placetype":"locality"
},
  "geometry": {"coordinates":[68.67103,25.65925],"type":"Point"}
}