{
  "type": "Feature",
  "properties": {
    "gn:admin1_code":"3",
    "gn:asciiname":"Kuar Sar Banda",
    "gn:country_code":"PK",
    "gn:dem":2226,
    "gn:feature_class":"P",
    "gn:feature_code":"PPL",
    "gn:name":"Kuar Sar Banda",
    "gn:population":0,
    "gn:timezone":"Asia/Karachi",
    "iso:country":"PK",
    "wof:name":"Kuar Sar Banda",
    "wof:placetype":"locality"
},
  "geometry": {"coordinates":[72.43980000000001,34.67952],"type":"Point"}
}