{
  "type": "Feature",
  "properties": {
    "gn:admin1_code":"2.0",
    "gn:asciiname":"Kili Abdul Mali",
    "gn:country_code":"PK",
    "gn:dem":1640,
    "gn:feature_class":"P",
    "gn:feature_code":"PPL",
    "gn:name":"Kili Abdul Mali",
    "gn:population":0,
    "gn:timezone":"Asia/Karachi",
    "iso:country":"PK",
    "wof:name":"Kili Abdul Mali",
    "wof:placetype":"locality"
},
  "geometry": {"coordinates":[67.43281999999999,30.18072],"type":"Point"}
}