{
  "type": "Feature",
  "properties": {
    "gn:admin1_code":"04",
    "gn:asciiname":"Marakiwal",
    "gn:country_code":"PK",
    "gn:dem":252,
    "gn:feature_class":"P",
    "gn:feature_code":"PPL",
    "gn:name":"Marakiwal",
    "gn:population":0,
    "gn:timezone":"Asia/Karachi",
    "iso:country":"PK",
    "name:und_x_variant":[
        "Wada Markiwal",
        "Mar\u0101kiw\u0101l"
    ],
    "wof:name":"Marakiwal",
    "wof:placetype":"locality"
},
  "geometry": {"coordinates":[74.54765999999999,32.57362],"type":"Point"}
}