{
  "type": "Feature",
  "properties": {
    "gn:admin1_code":"4",
    "gn:asciiname":"Pindi Jattan",
    "gn:country_code":"PK",
    "gn:dem":183,
    "gn:feature_class":"P",
    "gn:feature_code":"PPL",
    "gn:name":"Pindi Jattan",
    "gn:population":0,
    "gn:timezone":"Asia/Karachi",
    "iso:country":"PK",
    "name:und_x_variant":[
        "Pindi"
    ],
    "wof:name":"Pindi Jattan",
    "wof:placetype":"locality"
},
  "geometry": {"coordinates":[74.02894000000001,30.80811],"type":"Point"}
}