{
  "type": "Feature",
  "properties": {
    "gn:admin1_code":"4",
    "gn:asciiname":"Chak Four Hundred Sixty-five",
    "gn:country_code":"PK",
    "gn:dem":196,
    "gn:feature_class":"P",
    "gn:feature_code":"PPL",
    "gn:name":"Chak Four Hundred Sixty-five",
    "gn:population":0,
    "gn:timezone":"Asia/Karachi",
    "iso:country":"PK",
    "name:und_x_variant":[
        "Jhal\u0101ri",
        "Jhal\u0101ri Gherhi",
        "Jhallan Gharbi"
    ],
    "wof:name":"Chak Four Hundred Sixty-five",
    "wof:placetype":"locality"
},
  "geometry": {"coordinates":[73.18438,31.77542],"type":"Point"}
}