{
  "type": "Feature",
  "properties": {
    "gn:admin1_code":"4",
    "gn:asciiname":"Basti Mir Hazar Khan",
    "gn:country_code":"PK",
    "gn:dem":97,
    "gn:feature_class":"P",
    "gn:feature_code":"PPL",
    "gn:name":"Basti Mir Hazar Khan",
    "gn:population":0,
    "gn:timezone":"Asia/Karachi",
    "iso:country":"PK",
    "name:und_x_variant":[
        "Bast\u012b Mir Haz\u0101r Kh\u0101n",
        "Basti Mir Hazr\u0101t Kh\u0101n",
        "Basti Mir Hazar Khan"
    ],
    "wof:name":"Basti Mir Hazar Khan",
    "wof:placetype":"locality"
},
  "geometry": {"coordinates":[70.47118,29.27205],"type":"Point"}
}