{
  "type": "Feature",
  "properties": {
    "gn:admin1_code":"2.0",
    "gn:asciiname":"Kili Ghulam Rasul",
    "gn:country_code":"PK",
    "gn:dem":702,
    "gn:feature_class":"P",
    "gn:feature_code":"PPL",
    "gn:name":"Kili Ghulam Rasul",
    "gn:population":0,
    "gn:timezone":"Asia/Karachi",
    "iso:country":"PK",
    "wof:name":"Kili Ghulam Rasul",
    "wof:placetype":"locality"
},
  "geometry": {"coordinates":[65.2587,28.5658],"type":"Point"}
}