{
  "type": "Feature",
  "properties": {
    "gn:admin1_code":"3.0",
    "gn:asciiname":"Adam Khan",
    "gn:country_code":"PK",
    "gn:dem":402,
    "gn:feature_class":"P",
    "gn:feature_code":"PPL",
    "gn:name":"Adam Khan",
    "gn:population":0,
    "gn:timezone":"Asia/Karachi",
    "iso:country":"PK",
    "name:eng_x_preferred":[
        "Adam Khan"
    ],
    "wof:name":"Adam Khan",
    "wof:placetype":"locality"
},
  "geometry": {"coordinates":[71.90753000000002,34.4114],"type":"Point"}
}