{
  "type": "Feature",
  "properties": {
    "gn:admin1_code":"3.0",
    "gn:asciiname":"Adam Khan",
    "gn:country_code":"PK",
    "gn:dem":402,
    "gn:feature_class":"P",
    "gn:feature_code":"PPL",
    "gn:name":"Adam Khan",
    "gn:population":0,
    "gn:timezone":"Asia/Karachi",
    "iso:country":"PK",
    "name:ara_x_preferred":[
        "\u0622\u062f\u0645 \u062e\u0627\u0646"
    ],
    "name:deu_x_preferred":[
        "Adam Khan"
    ],
    "name:eng_x_preferred":[
        "Adam Khan"
    ],
    "name:fin_x_preferred":[
        "Adam Khan"
    ],
    "name:fra_x_preferred":[
        "Adam Langley-Khan"
    ],
    "name:jpn_x_preferred":[
        "\u30a2\u30c0\u30e0\u30fb\u30ab\u30fc\u30f3"
    ],
    "name:nld_x_preferred":[
        "Adam Khan"
    ],
    "name:pol_x_preferred":[
        "Adam Khan"
    ],
    "name:rus_x_preferred":[
        "\u041a\u0430\u043d"
    ],
    "name:swe_x_preferred":[
        "Adam Khan"
    ],
    "wof:name":"Adam Khan",
    "wof:placetype":"locality"
},
  "geometry": {"coordinates":[71.90753000000002,34.4114],"type":"Point"}
}