{
  "type": "Feature",
  "properties": {
    "gn:admin1_code":"4",
    "gn:asciiname":"Fazalwala",
    "gn:country_code":"PK",
    "gn:dem":127,
    "gn:feature_class":"P",
    "gn:feature_code":"PPL",
    "gn:name":"Fazalwala",
    "gn:population":0,
    "gn:timezone":"Asia/Karachi",
    "iso:country":"PK",
    "name:und_x_variant":[
        "F\u0101zilw\u0101la"
    ],
    "wof:name":"Fazalwala",
    "wof:placetype":"locality"
},
  "geometry": {"coordinates":[71.03408,30.38088],"type":"Point"}
}