{
  "type": "Feature",
  "properties": {
    "gn:admin1_code":"6.0",
    "gn:asciiname":"Khani",
    "gn:country_code":"PK",
    "gn:dem":395,
    "gn:feature_class":"P",
    "gn:feature_code":"PPL",
    "gn:name":"Khani",
    "gn:population":0,
    "gn:timezone":"Asia/Karachi",
    "iso:country":"PK",
    "wof:name":"Khani",
    "wof:placetype":"locality"
},
  "geometry": {"coordinates":[73.73789000000002,33.15537],"type":"Point"}
}