{
  "type": "Feature",
  "properties": {
    "gn:admin1_code":"3.0",
    "gn:asciiname":"Siasan",
    "gn:country_code":"PK",
    "gn:dem":2093,
    "gn:feature_class":"P",
    "gn:feature_code":"PPL",
    "gn:name":"Siasan",
    "gn:population":0,
    "gn:timezone":"Asia/Karachi",
    "iso:country":"PK",
    "name:eng_x_preferred":[
        "Siasan"
    ],
    "name:fas_x_preferred":[
        "\u0633\u06cc\u0627\u0633\u0627\u0646"
    ],
    "wof:name":"Siasan",
    "wof:placetype":"locality"
},
  "geometry": {"coordinates":[72.0909,35.38321],"type":"Point"}
}