{
  "type": "Feature",
  "properties": {
    "gn:admin1_code":"2.0",
    "gn:asciiname":"Dashti",
    "gn:country_code":"PK",
    "gn:dem":1435,
    "gn:feature_class":"P",
    "gn:feature_code":"PPL",
    "gn:name":"Dashti",
    "gn:population":0,
    "gn:timezone":"Asia/Karachi",
    "iso:country":"PK",
    "name:eng_x_preferred":[
        "Dashu"
    ],
    "wof:name":"Dashti",
    "wof:placetype":"locality"
},
  "geometry": {"coordinates":[66.06299,29.12332],"type":"Point"}
}