{
  "type": "Feature",
  "properties": {
    "gn:admin1_code":"4.0",
    "gn:asciiname":"Karor",
    "gn:country_code":"PK",
    "gn:dem":155,
    "gn:feature_class":"P",
    "gn:feature_code":"PPL",
    "gn:name":"Karor",
    "gn:population":0,
    "gn:timezone":"Asia/Karachi",
    "iso:country":"PK",
    "name:eng_x_preferred":[
        "Karor"
    ],
    "name:urd_x_preferred":[
        "\u06a9\u0627\u0631\u0648\u0631"
    ],
    "wof:name":"Karor",
    "wof:placetype":"locality"
},
  "geometry": {"coordinates":[72.20516000000001,31.40944],"type":"Point"}
}