{
  "type": "Feature",
  "properties": {
    "gn:admin1_code":"5.0",
    "gn:asciiname":"Dara",
    "gn:country_code":"PK",
    "gn:dem":46,
    "gn:feature_class":"P",
    "gn:feature_code":"PPL",
    "gn:name":"Dara",
    "gn:population":0,
    "gn:timezone":"Asia/Karachi",
    "iso:country":"PK",
    "name:ces_x_preferred":[
        "Dara"
    ],
    "name:isl_x_preferred":[
        "Dara"
    ],
    "name:slv_x_preferred":[
        "Dara"
    ],
    "name:srp_x_preferred":[
        "\u0414\u0430\u0440\u0430"
    ],
    "wof:name":"Dara",
    "wof:placetype":"locality"
},
  "geometry": {"coordinates":[67.89489,27.31138],"type":"Point"}
}