{
  "type": "Feature",
  "properties": {
    "gn:admin1_code":"6",
    "gn:asciiname":"Sahib Than",
    "gn:country_code":"PK",
    "gn:dem":1296,
    "gn:feature_class":"P",
    "gn:feature_code":"PPL",
    "gn:name":"Sahib Than",
    "gn:population":0,
    "gn:timezone":"Asia/Karachi",
    "iso:country":"PK",
    "name:und_x_variant":[
        "S\u0101hibth\u0101n"
    ],
    "wof:name":"Sahib Than",
    "wof:placetype":"locality"
},
  "geometry": {"coordinates":[73.50671,34.26883],"type":"Point"}
}