{
  "type": "Feature",
  "properties": {
    "gn:admin1_code":"3",
    "gn:asciiname":"Churkhai",
    "gn:country_code":"PK",
    "gn:dem":839,
    "gn:feature_class":"P",
    "gn:feature_code":"PPL",
    "gn:name":"Churkhai",
    "gn:population":0,
    "gn:timezone":"Asia/Karachi",
    "iso:country":"PK",
    "name:eng_x_preferred":[
        "Churkhai"
    ],
    "wof:name":"Churkhai",
    "wof:placetype":"locality"
},
  "geometry": {"coordinates":[72.13746,34.61774],"type":"Point"}
}