{
  "type": "Feature",
  "properties": {
    "gn:admin1_code":"4.0",
    "gn:asciiname":"Ajarwala",
    "gn:country_code":"PK",
    "gn:dem":107,
    "gn:feature_class":"P",
    "gn:feature_code":"PPL",
    "gn:name":"Ajarwala",
    "gn:population":0,
    "gn:timezone":"Asia/Karachi",
    "iso:country":"PK",
    "name:und_x_variant":[
        "Sub\u0101niw\u0101la"
    ],
    "wof:name":"Ajarwala",
    "wof:placetype":"locality"
},
  "geometry": {"coordinates":[70.53783,29.69021],"type":"Point"}
}