{
  "type": "Feature",
  "properties": {
    "gn:admin1_code":"7.0",
    "gn:asciiname":"Brashki",
    "gn:country_code":"PK",
    "gn:dem":2888,
    "gn:feature_class":"P",
    "gn:feature_code":"PPL",
    "gn:name":"Brashki",
    "gn:population":0,
    "gn:timezone":"Asia/Karachi",
    "iso:country":"PK",
    "name:und_x_variant":[
        "Burishki"
    ],
    "wof:name":"Brashki",
    "wof:placetype":"locality"
},
  "geometry": {"coordinates":[74.2372,36.28179],"type":"Point"}
}