{
  "type": "Feature",
  "properties": {
    "gn:admin1_code":"4",
    "gn:asciiname":"Dera Buddhu",
    "gn:country_code":"PK",
    "gn:dem":123,
    "gn:feature_class":"P",
    "gn:feature_code":"PPL",
    "gn:name":"Dera Buddhu",
    "gn:population":0,
    "gn:timezone":"Asia/Karachi",
    "iso:country":"PK",
    "name:und_x_variant":[
        "R\u0101m Krisha",
        "Dera Buddhu"
    ],
    "wof:name":"Dera Buddhu",
    "wof:placetype":"locality"
},
  "geometry": {"coordinates":[71.48380999999998,30.14735],"type":"Point"}
}