{
  "type": "Feature",
  "properties": {
    "gn:admin1_code":"4.0",
    "gn:asciiname":"Chak Six Hundred Seventy-three -Fourteen Gugera Branch",
    "gn:country_code":"PK",
    "gn:dem":151,
    "gn:feature_class":"P",
    "gn:feature_code":"PPL",
    "gn:name":"Chak Six Hundred Seventy-three -Fourteen Gugera Branch",
    "gn:population":0,
    "gn:timezone":"Asia/Karachi",
    "iso:country":"PK",
    "name:und_x_variant":[
        "Chak One Hundred Seventy-Three-Fourteen",
        "Harisab\u0101d"
    ],
    "wof:name":"Chak Six Hundred Seventy-three -Fourteen Gugera Branch",
    "wof:placetype":"locality"
},
  "geometry": {"coordinates":[72.41504999999999,30.75012000000001],"type":"Point"}
}