{
  "type": "Feature",
  "properties": {
    "gn:admin1_code":"1",
    "gn:asciiname":"Hissar Katskai",
    "gn:country_code":"PK",
    "gn:dem":1359,
    "gn:feature_class":"P",
    "gn:feature_code":"PPL",
    "gn:name":"Hissar Katskai",
    "gn:population":0,
    "gn:timezone":"Asia/Karachi",
    "iso:country":"PK",
    "name:und_x_variant":[
        "Shran Wangai",
        "Hissar Katskai"
    ],
    "wof:name":"Hissar Katskai",
    "wof:placetype":"locality"
},
  "geometry": {"coordinates":[69.92944,32.46497],"type":"Point"}
}