{
  "type": "Feature",
  "properties": {
    "gn:admin1_code":"4.0",
    "gn:asciiname":"Raroti Dhok",
    "gn:country_code":"PK",
    "gn:dem":582,
    "gn:feature_class":"P",
    "gn:feature_code":"PPL",
    "gn:name":"Raroti Dhok",
    "gn:population":0,
    "gn:timezone":"Asia/Karachi",
    "iso:country":"PK",
    "wof:name":"Raroti Dhok",
    "wof:placetype":"locality"
},
  "geometry": {"coordinates":[72.33143000000003,32.79586],"type":"Point"}
}