{
  "type": "Feature",
  "properties": {
    "gn:admin1_code":"1.0",
    "gn:asciiname":"Kas Kizar Kalle",
    "gn:country_code":"PK",
    "gn:dem":1866,
    "gn:feature_class":"P",
    "gn:feature_code":"PPL",
    "gn:name":"Kas Kizar Kalle",
    "gn:population":0,
    "gn:timezone":"Asia/Karachi",
    "iso:country":"PK",
    "name:und_x_variant":[
        "Kaskiz\u0101r"
    ],
    "wof:name":"Kas Kizar Kalle",
    "wof:placetype":"locality"
},
  "geometry": {"coordinates":[70.82094000000002,33.72553],"type":"Point"}
}