{
  "type": "Feature",
  "properties": {
    "gn:admin1_code":"5",
    "gn:asciiname":"Kathor",
    "gn:country_code":"PK",
    "gn:dem":52,
    "gn:feature_class":"P",
    "gn:feature_code":"PPL",
    "gn:name":"Kathor",
    "gn:population":0,
    "gn:timezone":"Asia/Karachi",
    "iso:country":"PK",
    "name:ceb_x_preferred":[
        "K\u0101thor"
    ],
    "name:guj_x_preferred":[
        "\u0a95\u0aa0\u0acb\u0ab0"
    ],
    "name:swe_x_preferred":[
        "K\u0101thor"
    ],
    "wof:name":"Kathor",
    "wof:placetype":"locality"
},
  "geometry": {"coordinates":[68.90029,26.99582],"type":"Point"}
}