{
  "type": "Feature",
  "properties": {
    "gn:admin1_code":"4",
    "gn:asciiname":"Tharaianwala",
    "gn:country_code":"PK",
    "gn:dem":139,
    "gn:feature_class":"P",
    "gn:feature_code":"PPL",
    "gn:name":"Tharaianwala",
    "gn:population":0,
    "gn:timezone":"Asia/Karachi",
    "iso:country":"PK",
    "name:und_x_variant":[
        "Ch\u0101h Thor\u0101j\u0101nw\u0101la"
    ],
    "wof:name":"Tharaianwala",
    "wof:placetype":"locality"
},
  "geometry": {"coordinates":[71.95924000000002,30.55097],"type":"Point"}
}