{
  "type": "Feature",
  "properties": {
    "gn:admin1_code":"3.0",
    "gn:asciiname":"Panjoth",
    "gn:country_code":"PK",
    "gn:dem":1374,
    "gn:feature_class":"P",
    "gn:feature_code":"PPL",
    "gn:name":"Panjoth",
    "gn:population":0,
    "gn:timezone":"Asia/Karachi",
    "iso:country":"PK",
    "name:eng_x_preferred":[
        "Panjoth"
    ],
    "wof:name":"Panjoth",
    "wof:placetype":"locality"
},
  "geometry": {"coordinates":[73.30698000000002,33.9466],"type":"Point"}
}