{
  "type": "Feature",
  "properties": {
    "gn:admin1_code":"04",
    "gn:asciiname":"Nakka Khurd",
    "gn:country_code":"PK",
    "gn:dem":351,
    "gn:feature_class":"P",
    "gn:feature_code":"PPL",
    "gn:name":"Nakka Khurd",
    "gn:population":0,
    "gn:timezone":"Asia/Karachi",
    "iso:country":"PK",
    "name:fas_x_preferred":[
        "\u0646\u06a9\u0647 \u062e\u0648\u0631\u062f"
    ],
    "name:und_x_variant":[
        "Zara Nakka",
        "Nakka Khurd"
    ],
    "name:urd_x_preferred":[
        "\u0646\u06a9\u06c1 \u062e\u0648\u0631\u062f"
    ],
    "wof:name":"Nakka Khurd",
    "wof:placetype":"locality"
},
  "geometry": {"coordinates":[71.81701,33.15072],"type":"Point"}
}