{
  "type": "Feature",
  "properties": {
    "gn:admin1_code":"3.0",
    "gn:asciiname":"Saimal Baihk",
    "gn:country_code":"PK",
    "gn:dem":3493,
    "gn:feature_class":"P",
    "gn:feature_code":"PPL",
    "gn:name":"Saimal Baihk",
    "gn:population":0,
    "gn:timezone":"Asia/Karachi",
    "iso:country":"PK",
    "wof:name":"Saimal Baihk",
    "wof:placetype":"locality"
},
  "geometry": {"coordinates":[73.45365,35.39628],"type":"Point"}
}