{
  "type": "Feature",
  "properties": {
    "gn:admin1_code":"8.0",
    "gn:asciiname":"Dhok Chik",
    "gn:country_code":"PK",
    "gn:dem":568,
    "gn:feature_class":"P",
    "gn:feature_code":"PPL",
    "gn:name":"Dhok Chik",
    "gn:population":0,
    "gn:timezone":"Asia/Karachi",
    "iso:country":"PK",
    "wof:name":"Dhok Chik",
    "wof:placetype":"locality"
},
  "geometry": {"coordinates":[73.26479,33.67823],"type":"Point"}
}