{
  "type": "Feature",
  "properties": {
    "gn:admin1_code":"3.0",
    "gn:asciiname":"Dheri",
    "gn:country_code":"PK",
    "gn:dem":528,
    "gn:feature_class":"P",
    "gn:feature_code":"PPL",
    "gn:name":"Dheri",
    "gn:population":0,
    "gn:timezone":"Asia/Karachi",
    "iso:country":"PK",
    "wof:name":"Dheri",
    "wof:placetype":"locality"
},
  "geometry": {"coordinates":[72.9811,34.12918],"type":"Point"}
}