{
  "type": "Feature",
  "properties": {
    "gn:admin1_code":"2.0",
    "gn:asciiname":"Multanai",
    "gn:country_code":"PK",
    "gn:dem":2075,
    "gn:feature_class":"P",
    "gn:feature_code":"PPL",
    "gn:name":"Multanai",
    "gn:population":0,
    "gn:timezone":"Asia/Karachi",
    "iso:country":"PK",
    "wof:name":"Multanai",
    "wof:placetype":"locality"
},
  "geometry": {"coordinates":[68.16105,31.71153],"type":"Point"}
}