{
  "type": "Feature",
  "properties": {
    "gn:admin1_code":"3.0",
    "gn:asciiname":"Paluno",
    "gn:country_code":"PK",
    "gn:dem":433,
    "gn:feature_class":"P",
    "gn:feature_code":"PPL",
    "gn:name":"Paluno",
    "gn:population":0,
    "gn:timezone":"Asia/Karachi",
    "iso:country":"PK",
    "name:eng_x_preferred":[
        "Mulla Misri"
    ],
    "wof:name":"Paluno",
    "wof:placetype":"locality"
},
  "geometry": {"coordinates":[71.82445,34.42675],"type":"Point"}
}