{
  "type": "Feature",
  "properties": {
    "gn:admin1_code":"3.0",
    "gn:asciiname":"Arbi Banda",
    "gn:country_code":"PK",
    "gn:dem":324,
    "gn:feature_class":"P",
    "gn:feature_code":"PPL",
    "gn:name":"Arbi Banda",
    "gn:population":0,
    "gn:timezone":"Asia/Karachi",
    "iso:country":"PK",
    "name:eng_x_preferred":[
        "Arbi Kili"
    ],
    "wof:name":"Arbi Banda",
    "wof:placetype":"locality"
},
  "geometry": {"coordinates":[71.99947,34.27121],"type":"Point"}
}