{
  "type": "Feature",
  "properties": {
    "gn:admin1_code":"4",
    "gn:asciiname":"Mota Phalla",
    "gn:country_code":"PK",
    "gn:dem":388,
    "gn:feature_class":"P",
    "gn:feature_code":"PPL",
    "gn:name":"Mota Phalla",
    "gn:population":0,
    "gn:timezone":"Asia/Karachi",
    "iso:country":"PK",
    "wof:name":"Mota Phalla",
    "wof:placetype":"locality"
},
  "geometry": {"coordinates":[73.29545999999998,32.95761],"type":"Point"}
}