{
  "type": "Feature",
  "properties": {
    "gn:admin1_code":"3.0",
    "gn:asciiname":"Narin",
    "gn:country_code":"PK",
    "gn:dem":1933,
    "gn:feature_class":"P",
    "gn:feature_code":"PPL",
    "gn:name":"Narin",
    "gn:population":0,
    "gn:timezone":"Asia/Karachi",
    "iso:country":"PK",
    "wof:name":"Narin",
    "wof:placetype":"locality"
},
  "geometry": {"coordinates":[73.62224000000001,35.44688],"type":"Point"}
}