{
  "type": "Feature",
  "properties": {
    "gn:admin1_code":"3.0",
    "gn:asciiname":"Barah",
    "gn:country_code":"PK",
    "gn:dem":363,
    "gn:feature_class":"P",
    "gn:feature_code":"PPL",
    "gn:name":"Barah",
    "gn:population":0,
    "gn:timezone":"Asia/Karachi",
    "iso:country":"PK",
    "name:eng_x_preferred":[
        "Borah"
    ],
    "wof:name":"Barah",
    "wof:placetype":"locality"
},
  "geometry": {"coordinates":[72.30145,34.10185],"type":"Point"}
}