{
  "type": "Feature",
  "properties": {
    "gn:admin1_code":"4.0",
    "gn:asciiname":"Basti Haji Ghulam Muhammad",
    "gn:country_code":"PK",
    "gn:dem":115,
    "gn:feature_class":"P",
    "gn:feature_code":"PPL",
    "gn:name":"Basti Haji Ghulam Muhammad",
    "gn:population":0,
    "gn:timezone":"Asia/Karachi",
    "iso:country":"PK",
    "name:eng_x_preferred":[
        "Basti Haji Ghul\u0101m Muhammad"
    ],
    "wof:name":"Basti Haji Ghulam Muhammad",
    "wof:placetype":"locality"
},
  "geometry": {"coordinates":[71.56021,29.36597],"type":"Point"}
}