{
  "type": "Feature",
  "properties": {
    "gn:admin1_code":"2.0",
    "gn:asciiname":"Danna Sar",
    "gn:country_code":"PK",
    "gn:dem":286,
    "gn:feature_class":"P",
    "gn:feature_code":"PPL",
    "gn:name":"Danna Sar",
    "gn:population":0,
    "gn:timezone":"Asia/Karachi",
    "iso:country":"PK",
    "name:und_x_variant":[
        "Danne Sar"
    ],
    "wof:name":"Danna Sar",
    "wof:placetype":"locality"
},
  "geometry": {"coordinates":[63.35702,26.04257],"type":"Point"}
}