{
  "type": "Feature",
  "properties": {
    "gn:admin1_code":"5",
    "gn:asciiname":"Bando",
    "gn:country_code":"PK",
    "gn:dem":39,
    "gn:feature_class":"P",
    "gn:feature_code":"PPL",
    "gn:name":"Bando",
    "gn:population":0,
    "gn:timezone":"Asia/Karachi",
    "iso:country":"PK",
    "name:ast_x_preferred":[
        "Bando"
    ],
    "name:ben_x_preferred":[
        "\u09ac\u09c7\u09a8\u09a1\u09cb"
    ],
    "name:ces_x_preferred":[
        "Bando"
    ],
    "name:dan_x_preferred":[
        "Bando"
    ],
    "name:fra_x_preferred":[
        "Bando"
    ],
    "name:mya_x_preferred":[
        "\u1017\u1014\u103a\u1010\u102d\u102f"
    ],
    "name:por_x_preferred":[
        "Bando"
    ],
    "name:spa_x_preferred":[
        "Bando"
    ],
    "name:und_x_variant":[
        "B\u0101nda"
    ],
    "name:vie_x_preferred":[
        "Bando"
    ],
    "wof:name":"Bando",
    "wof:placetype":"locality"
},
  "geometry": {"coordinates":[69.58632,24.80174],"type":"Point"}
}