{
  "type": "Feature",
  "properties": {
    "gn:admin1_code":"4.0",
    "gn:asciiname":"Chak Four Hundred Twelve Thal Development Authority",
    "gn:country_code":"PK",
    "gn:dem":142,
    "gn:feature_class":"P",
    "gn:feature_code":"PPL",
    "gn:name":"Chak Four Hundred Twelve Thal Development Authority",
    "gn:population":0,
    "gn:timezone":"Asia/Karachi",
    "iso:country":"PK",
    "name:und_x_variant":[
        "Chak Four Hundred Twelve TDA"
    ],
    "wof:name":"Chak Four Hundred Twelve Thal Development Authority",
    "wof:placetype":"locality"
},
  "geometry": {"coordinates":[71.35445,30.86674],"type":"Point"}
}