{
  "type": "Feature",
  "properties": {
    "gn:admin1_code":"3.0",
    "gn:asciiname":"Gul Dheri",
    "gn:country_code":"PK",
    "gn:dem":1593,
    "gn:feature_class":"P",
    "gn:feature_code":"PPL",
    "gn:name":"Gul Dheri",
    "gn:population":0,
    "gn:timezone":"Asia/Karachi",
    "iso:country":"PK",
    "wof:name":"Gul Dheri",
    "wof:placetype":"locality"
},
  "geometry": {"coordinates":[72.97751,34.54407],"type":"Point"}
}