{
  "type": "Feature",
  "properties": {
    "gn:admin1_code":"4",
    "gn:asciiname":"Sultan Ka Baghela",
    "gn:country_code":"PK",
    "gn:dem":162,
    "gn:feature_class":"P",
    "gn:feature_code":"PPL",
    "gn:name":"Sultan Ka Baghela",
    "gn:population":0,
    "gn:timezone":"Asia/Karachi",
    "iso:country":"PK",
    "name:und_x_variant":[
        "Sult\u0101n ke Baghela"
    ],
    "wof:name":"Sultan Ka Baghela",
    "wof:placetype":"locality"
},
  "geometry": {"coordinates":[72.77784,30.74219],"type":"Point"}
}