{
  "type": "Feature",
  "properties": {
    "gn:admin1_code":"2.0",
    "gn:asciiname":"Malik Baluch Khan",
    "gn:country_code":"PK",
    "gn:dem":1370,
    "gn:feature_class":"P",
    "gn:feature_code":"PPL",
    "gn:name":"Malik Baluch Khan",
    "gn:population":0,
    "gn:timezone":"Asia/Karachi",
    "iso:country":"PK",
    "name:und_x_variant":[
        "Malik Baloch Kh\u0101n",
        "Malik Baluch Khan"
    ],
    "wof:name":"Malik Baluch Khan",
    "wof:placetype":"locality"
},
  "geometry": {"coordinates":[66.50803000000001,30.26078],"type":"Point"}
}