{
  "type": "Feature",
  "properties": {
    "gn:admin1_code":"4.0",
    "gn:asciiname":"Chak Forty-seven -Three Right",
    "gn:country_code":"PK",
    "gn:dem":179,
    "gn:feature_class":"P",
    "gn:feature_code":"PPL",
    "gn:name":"Chak Forty-seven -Three Right",
    "gn:population":0,
    "gn:timezone":"Asia/Karachi",
    "iso:country":"PK",
    "name:und_x_variant":[
        "Chak Forty-seven Three R"
    ],
    "wof:name":"Chak Forty-seven -Three Right",
    "wof:placetype":"locality"
},
  "geometry": {"coordinates":[73.32635999999999,30.79698],"type":"Point"}
}