{
  "type": "Feature",
  "properties": {
    "gn:admin1_code":"3.0",
    "gn:asciiname":"Dhok Mallawali",
    "gn:country_code":"PK",
    "gn:dem":237,
    "gn:feature_class":"P",
    "gn:feature_code":"PPL",
    "gn:name":"Dhok Mallawali",
    "gn:population":0,
    "gn:timezone":"Asia/Karachi",
    "iso:country":"PK",
    "wof:name":"Dhok Mallawali",
    "wof:placetype":"locality"
},
  "geometry": {"coordinates":[71.71231,33.06016],"type":"Point"}
}