{
  "type": "Feature",
  "properties": {
    "gn:admin1_code":"2.0",
    "gn:asciiname":"Matan",
    "gn:country_code":"PK",
    "gn:dem":508,
    "gn:feature_class":"P",
    "gn:feature_code":"PPL",
    "gn:name":"Matan",
    "gn:population":0,
    "gn:timezone":"Asia/Karachi",
    "iso:country":"PK",
    "name:ceb_x_preferred":[
        "Matan"
    ],
    "name:swe_x_preferred":[
        "Matan"
    ],
    "wof:name":"Matan",
    "wof:placetype":"locality"
},
  "geometry": {"coordinates":[63.22729,28.07859],"type":"Point"}
}