{
  "type": "Feature",
  "properties": {
    "gn:admin1_code":"4.0",
    "gn:asciiname":"Tibbi Mehr Shah",
    "gn:country_code":"PK",
    "gn:dem":178,
    "gn:feature_class":"P",
    "gn:feature_code":"PPL",
    "gn:name":"Tibbi Mehr Shah",
    "gn:population":0,
    "gn:timezone":"Asia/Karachi",
    "iso:country":"PK",
    "wof:name":"Tibbi Mehr Shah",
    "wof:placetype":"locality"
},
  "geometry": {"coordinates":[73.286,30.89301],"type":"Point"}
}