{
  "type": "Feature",
  "properties": {
    "gn:admin1_code":"4",
    "gn:asciiname":"Muradwali Bheni",
    "gn:country_code":"PK",
    "gn:dem":137,
    "gn:feature_class":"P",
    "gn:feature_code":"PPL",
    "gn:name":"Muradwali Bheni",
    "gn:population":0,
    "gn:timezone":"Asia/Karachi",
    "iso:country":"PK",
    "wof:name":"Muradwali Bheni",
    "wof:placetype":"locality"
},
  "geometry": {"coordinates":[72.21389000000001,30.10278],"type":"Point"}
}