{
  "type": "Feature",
  "properties": {
    "gn:admin1_code":"3",
    "gn:asciiname":"Garai",
    "gn:country_code":"PK",
    "gn:dem":1891,
    "gn:feature_class":"P",
    "gn:feature_code":"PPL",
    "gn:name":"Garai",
    "gn:population":0,
    "gn:timezone":"Asia/Karachi",
    "iso:country":"PK",
    "name:ceb_x_preferred":[
        "Garai"
    ],
    "name:deu_x_preferred":[
        "Garai"
    ],
    "name:eus_x_preferred":[
        "Garai"
    ],
    "name:fra_x_preferred":[
        "Garai"
    ],
    "name:hun_x_preferred":[
        "Garai"
    ],
    "name:rus_x_preferred":[
        "\u0413\u0430\u0440\u0430\u0438"
    ],
    "name:swe_x_preferred":[
        "Garai"
    ],
    "wof:name":"Garai",
    "wof:placetype":"locality"
},
  "geometry": {"coordinates":[72.39166999999998,35.13194],"type":"Point"}
}