{
  "type": "Feature",
  "properties": {
    "gn:admin1_code":"5.0",
    "gn:asciiname":"Goth Sumar Bhil",
    "gn:country_code":"PK",
    "gn:dem":55,
    "gn:feature_class":"P",
    "gn:feature_code":"PPL",
    "gn:name":"Goth Sumar Bhil",
    "gn:population":0,
    "gn:timezone":"Asia/Karachi",
    "iso:country":"PK",
    "wof:name":"Goth Sumar Bhil",
    "wof:placetype":"locality"
},
  "geometry": {"coordinates":[69.95402,25.40953],"type":"Point"}
}