{
  "type": "Feature",
  "properties": {
    "gn:admin1_code":"4.0",
    "gn:asciiname":"Dhok Naian",
    "gn:country_code":"PK",
    "gn:dem":524,
    "gn:feature_class":"P",
    "gn:feature_code":"PPL",
    "gn:name":"Dhok Naian",
    "gn:population":0,
    "gn:timezone":"Asia/Karachi",
    "iso:country":"PK",
    "wof:name":"Dhok Naian",
    "wof:placetype":"locality"
},
  "geometry": {"coordinates":[73.15049999999999,33.49149],"type":"Point"}
}