{
  "type": "Feature",
  "properties": {
    "gn:admin1_code":"04",
    "gn:asciiname":"Pakki",
    "gn:country_code":"PK",
    "gn:dem":125,
    "gn:feature_class":"P",
    "gn:feature_code":"PPL",
    "gn:name":"Pakki",
    "gn:population":0,
    "gn:timezone":"Asia/Karachi",
    "iso:country":"PK",
    "name:eng_x_preferred":[
        "Pakki"
    ],
    "wof:name":"Pakki",
    "wof:placetype":"locality"
},
  "geometry": {"coordinates":[70.75,30.26728],"type":"Point"}
}