{
  "type": "Feature",
  "properties": {
    "gn:admin1_code":"4.0",
    "gn:asciiname":"Basti Dastian",
    "gn:country_code":"PK",
    "gn:dem":85,
    "gn:feature_class":"P",
    "gn:feature_code":"PPL",
    "gn:name":"Basti Dasti\u0101n",
    "gn:population":0,
    "gn:timezone":"Asia/Karachi",
    "iso:country":"PK",
    "wof:name":"Basti Dastian",
    "wof:placetype":"locality"
},
  "geometry": {"coordinates":[70.51666999999998,28.65556],"type":"Point"}
}