{
  "type": "Feature",
  "properties": {
    "gn:admin1_code":"4.0",
    "gn:asciiname":"Dhirke Kalan",
    "gn:country_code":"PK",
    "gn:dem":227,
    "gn:feature_class":"P",
    "gn:feature_code":"PPL",
    "gn:name":"Dhirke Kalan",
    "gn:population":0,
    "gn:timezone":"Asia/Karachi",
    "iso:country":"PK",
    "name:und_x_variant":[
        "Dheerke",
        "Dhirk",
        "Dhirke Kalan"
    ],
    "wof:name":"Dhirke Kalan",
    "wof:placetype":"locality"
},
  "geometry": {"coordinates":[74.06856999999999,32.51315],"type":"Point"}
}