{
  "type": "Feature",
  "properties": {
    "gn:admin1_code":"3",
    "gn:asciiname":"Karandukai",
    "gn:country_code":"PK",
    "gn:dem":2043,
    "gn:feature_class":"P",
    "gn:feature_code":"PPL",
    "gn:name":"K\u0101rand\u016bkai",
    "gn:population":0,
    "gn:timezone":"Asia/Karachi",
    "iso:country":"PK",
    "wof:name":"Karandukai",
    "wof:placetype":"locality"
},
  "geometry": {"coordinates":[72.5925,35.46667],"type":"Point"}
}