{
  "type": "Feature",
  "properties": {
    "gn:admin1_code":"2.0",
    "gn:asciiname":"Khusa Kurram",
    "gn:country_code":"PK",
    "gn:dem":1292,
    "gn:feature_class":"P",
    "gn:feature_code":"PPL",
    "gn:name":"Khusa Kurram",
    "gn:population":0,
    "gn:timezone":"Asia/Karachi",
    "iso:country":"PK",
    "wof:name":"Khusa Kurram",
    "wof:placetype":"locality"
},
  "geometry": {"coordinates":[69.89648000000001,30.34657],"type":"Point"}
}