{
  "type": "Feature",
  "properties": {
    "gn:admin1_code":"7.0",
    "gn:asciiname":"Pathro",
    "gn:country_code":"PK",
    "gn:dem":3549,
    "gn:feature_class":"P",
    "gn:feature_code":"PPL",
    "gn:name":"Pathro",
    "gn:population":0,
    "gn:timezone":"Asia/Karachi",
    "iso:country":"PK",
    "wof:name":"Pathro",
    "wof:placetype":"locality"
},
  "geometry": {"coordinates":[73.78870999999999,35.94351],"type":"Point"}
}