{
  "type": "Feature",
  "properties": {
    "gn:admin1_code":"3.0",
    "gn:asciiname":"Taj Muhammad Garhi",
    "gn:country_code":"PK",
    "gn:dem":330,
    "gn:feature_class":"P",
    "gn:feature_code":"PPL",
    "gn:name":"Taj Muhammad Garhi",
    "gn:population":0,
    "gn:timezone":"Asia/Karachi",
    "iso:country":"PK",
    "wof:name":"Taj Muhammad Garhi",
    "wof:placetype":"locality"
},
  "geometry": {"coordinates":[71.47889000000001,34.08522],"type":"Point"}
}