{
  "type": "Feature",
  "properties": {
    "gn:admin1_code":"2.0",
    "gn:asciiname":"Tolgo",
    "gn:country_code":"PK",
    "gn:dem":49,
    "gn:feature_class":"P",
    "gn:feature_code":"PPL",
    "gn:name":"Tolgo",
    "gn:population":0,
    "gn:timezone":"Asia/Karachi",
    "iso:country":"PK",
    "name:und_x_variant":[
        "Kalch\u0101t",
        "Tolgo"
    ],
    "wof:name":"Tolgo",
    "wof:placetype":"locality"
},
  "geometry": {"coordinates":[63.2238,25.50503],"type":"Point"}
}