{
  "type": "Feature",
  "properties": {
    "gn:admin1_code":"5.0",
    "gn:asciiname":"Shah Latif Town",
    "gn:country_code":"PK",
    "gn:dem":46,
    "gn:feature_class":"P",
    "gn:feature_code":"PPL",
    "gn:name":"Shah Latif Town",
    "gn:population":0,
    "gn:timezone":"Asia/Karachi",
    "iso:country":"PK",
    "name:snd_x_preferred":[
        "\u0634\u0627\u0647 \u0644\u0637\u064a\u0641 \u067d\u0627\u0626\u0648\u0646"
    ],
    "wof:name":"Shah Latif Town",
    "wof:placetype":"locality"
},
  "geometry": {"coordinates":[67.28331999999999,24.85688],"type":"Point"}
}