{
  "type": "Feature",
  "properties": {
    "gn:admin1_code":"5",
    "gn:asciiname":"Shafi Muhammad",
    "gn:country_code":"PK",
    "gn:dem":50,
    "gn:feature_class":"P",
    "gn:feature_code":"PPL",
    "gn:name":"Shafi Muhammad",
    "gn:population":0,
    "gn:timezone":"Asia/Karachi",
    "iso:country":"PK",
    "name:und_x_variant":[
        "Shaffi Muhammad"
    ],
    "wof:name":"Shafi Muhammad",
    "wof:placetype":"locality"
},
  "geometry": {"coordinates":[68.01855,28.07742],"type":"Point"}
}