{
  "type": "Feature",
  "properties": {
    "gn:admin1_code":"5",
    "gn:asciiname":"Goth Taj Muhammad Junejo",
    "gn:country_code":"PK",
    "gn:dem":14,
    "gn:feature_class":"P",
    "gn:feature_code":"PPL",
    "gn:name":"Goth Taj Muhammad Junejo",
    "gn:population":0,
    "gn:timezone":"Asia/Karachi",
    "iso:country":"PK",
    "name:und_x_variant":[
        "Goth Ghanwar Junejo"
    ],
    "wof:name":"Goth Taj Muhammad Junejo",
    "wof:placetype":"locality"
},
  "geometry": {"coordinates":[69.04785,25.06881],"type":"Point"}
}