{
  "type": "Feature",
  "properties": {
    "gn:admin1_code":"03",
    "gn:asciiname":"Gumbat",
    "gn:country_code":"PK",
    "gn:dem":931,
    "gn:feature_class":"P",
    "gn:feature_code":"PPL",
    "gn:name":"Gumbat",
    "gn:population":0,
    "gn:timezone":"Asia/Karachi",
    "iso:country":"PK",
    "name:eng_x_preferred":[
        "Gumbat"
    ],
    "wof:name":"Gumbat",
    "wof:placetype":"locality"
},
  "geometry": {"coordinates":[71.86525,34.73114],"type":"Point"}
}