{
  "type": "Feature",
  "properties": {
    "gn:admin1_code":"4",
    "gn:asciiname":"Naiwaia",
    "gn:country_code":"PK",
    "gn:dem":108,
    "gn:feature_class":"P",
    "gn:feature_code":"PPL",
    "gn:name":"Naiwaia",
    "gn:population":0,
    "gn:timezone":"Asia/Karachi",
    "iso:country":"PK",
    "name:und_x_variant":[
        "N\u0101iw\u0101la"
    ],
    "wof:name":"Naiwaia",
    "wof:placetype":"locality"
},
  "geometry": {"coordinates":[70.56595,29.73441],"type":"Point"}
}