{
  "type": "Feature",
  "properties": {
    "gn:admin1_code":"3.0",
    "gn:asciiname":"Muhammad Ismail Koruna",
    "gn:country_code":"PK",
    "gn:dem":342,
    "gn:feature_class":"P",
    "gn:feature_code":"PPL",
    "gn:name":"Muhammad Ismail Koruna",
    "gn:population":0,
    "gn:timezone":"Asia/Karachi",
    "iso:country":"PK",
    "name:eng_x_preferred":[
        "Muhammad Ismail Koruna"
    ],
    "wof:name":"Muhammad Ismail Koruna",
    "wof:placetype":"locality"
},
  "geometry": {"coordinates":[71.90600000000001,34.25889],"type":"Point"}
}