{
  "type": "Feature",
  "properties": {
    "gn:admin1_code":"4",
    "gn:asciiname":"Mustaqim Mamunka",
    "gn:country_code":"PK",
    "gn:dem":163,
    "gn:feature_class":"P",
    "gn:feature_code":"PPL",
    "gn:name":"Mustaqim Mamunka",
    "gn:population":0,
    "gn:timezone":"Asia/Karachi",
    "iso:country":"PK",
    "name:und_x_variant":[
        "Mustaq\u012bm Mahm\u016bnka"
    ],
    "wof:name":"Mustaqim Mamunka",
    "wof:placetype":"locality"
},
  "geometry": {"coordinates":[73.4034,30.26631],"type":"Point"}
}