{
  "type": "Feature",
  "properties": {
    "gn:admin1_code":"5.0",
    "gn:asciiname":"Deputy Jamal-ud-Din",
    "gn:country_code":"PK",
    "gn:dem":9,
    "gn:feature_class":"P",
    "gn:feature_code":"PPL",
    "gn:name":"Deputy Jamal-ud-Din",
    "gn:population":0,
    "gn:timezone":"Asia/Karachi",
    "iso:country":"PK",
    "wof:name":"Deputy Jamal-ud-Din",
    "wof:placetype":"locality"
},
  "geometry": {"coordinates":[69.23869000000001,24.75428],"type":"Point"}
}