{
  "type": "Feature",
  "properties": {
    "gn:admin1_code":"4.0",
    "gn:asciiname":"Chak Twenty-five - Four Left",
    "gn:country_code":"PK",
    "gn:dem":180,
    "gn:feature_class":"P",
    "gn:feature_code":"PPL",
    "gn:name":"Chak Twenty-five - Four Left",
    "gn:population":0,
    "gn:timezone":"Asia/Karachi",
    "iso:country":"PK",
    "name:und_x_variant":[
        "Chak Twenty-five Four L"
    ],
    "wof:name":"Chak Twenty-five - Four Left",
    "wof:placetype":"locality"
},
  "geometry": {"coordinates":[73.37640999999998,30.71871],"type":"Point"}
}