{
  "type": "Feature",
  "properties": {
    "gn:admin1_code":"1.0",
    "gn:asciiname":"Mangal Tapo",
    "gn:country_code":"PK",
    "gn:dem":966,
    "gn:feature_class":"P",
    "gn:feature_code":"PPL",
    "gn:name":"Mangal Tapo",
    "gn:population":0,
    "gn:timezone":"Asia/Karachi",
    "iso:country":"PK",
    "wof:name":"Mangal Tapo",
    "wof:placetype":"locality"
},
  "geometry": {"coordinates":[70.3523,33.52826],"type":"Point"}
}