{
  "type": "Feature",
  "properties": {
    "gn:admin1_code":"3",
    "gn:asciiname":"Asharai Patai",
    "gn:country_code":"PK",
    "gn:dem":1806,
    "gn:feature_class":"P",
    "gn:feature_code":"PPL",
    "gn:name":"Asharai Patai",
    "gn:population":0,
    "gn:timezone":"Asia/Karachi",
    "iso:country":"PK",
    "name:und_x_variant":[
        "Ash\u0101raipatai"
    ],
    "wof:name":"Asharai Patai",
    "wof:placetype":"locality"
},
  "geometry": {"coordinates":[72.65796,34.65867],"type":"Point"}
}