{
  "type": "Feature",
  "properties": {
    "gn:admin1_code":"01",
    "gn:asciiname":"Topan Shah",
    "gn:country_code":"PK",
    "gn:dem":970,
    "gn:feature_class":"P",
    "gn:feature_code":"PPL",
    "gn:name":"Topan Shah",
    "gn:population":0,
    "gn:timezone":"Asia/Karachi",
    "iso:country":"PK",
    "name:eng_x_preferred":[
        "Topan Shah"
    ],
    "name:und_x_variant":[
        "Tofan Shah"
    ],
    "wof:name":"Topan Shah",
    "wof:placetype":"locality"
},
  "geometry": {"coordinates":[71.53064000000001,34.87472],"type":"Point"}
}