{
  "type": "Feature",
  "properties": {
    "gn:admin1_code":"2.0",
    "gn:asciiname":"Khumb",
    "gn:country_code":"PK",
    "gn:dem":1562,
    "gn:feature_class":"P",
    "gn:feature_code":"PPL",
    "gn:name":"Khumb",
    "gn:population":0,
    "gn:timezone":"Asia/Karachi",
    "iso:country":"PK",
    "wof:name":"Khumb",
    "wof:placetype":"locality"
},
  "geometry": {"coordinates":[66.79134999999999,27.92345],"type":"Point"}
}