{
  "type": "Feature",
  "properties": {
    "gn:admin1_code":"4",
    "gn:asciiname":"Muhammadwala",
    "gn:country_code":"PK",
    "gn:dem":148,
    "gn:feature_class":"P",
    "gn:feature_code":"PPL",
    "gn:name":"Muhammadwala",
    "gn:population":0,
    "gn:timezone":"Asia/Karachi",
    "iso:country":"PK",
    "name:eng_x_preferred":[
        "Muhammadw\u0101li"
    ],
    "wof:name":"Muhammadwala",
    "wof:placetype":"locality"
},
  "geometry": {"coordinates":[70.66407,30.47082],"type":"Point"}
}