{
  "type": "Feature",
  "properties": {
    "gn:admin1_code":"3.0",
    "gn:asciiname":"Faiz Darha",
    "gn:country_code":"PK",
    "gn:dem":1583,
    "gn:feature_class":"P",
    "gn:feature_code":"PPL",
    "gn:name":"Faiz Darha",
    "gn:population":0,
    "gn:timezone":"Asia/Karachi",
    "iso:country":"PK",
    "wof:name":"Faiz Darha",
    "wof:placetype":"locality"
},
  "geometry": {"coordinates":[72.74746,35.01744],"type":"Point"}
}