{
  "type": "Feature",
  "properties": {
    "gn:admin1_code":"3.0",
    "gn:asciiname":"Azimabad",
    "gn:country_code":"PK",
    "gn:dem":312,
    "gn:feature_class":"P",
    "gn:feature_code":"PPL",
    "gn:name":"Azimabad",
    "gn:population":0,
    "gn:timezone":"Asia/Karachi",
    "iso:country":"PK",
    "name:urd_x_preferred":[
        "\u0639\u0638\u06cc\u0645 \u0622\u0628\u0627\u062f"
    ],
    "wof:name":"Azimabad",
    "wof:placetype":"locality"
},
  "geometry": {"coordinates":[71.91056,34.08555],"type":"Point"}
}