{
  "type": "Feature",
  "properties": {
    "gn:admin1_code":"4.0",
    "gn:asciiname":"Basti Jhellan",
    "gn:country_code":"PK",
    "gn:dem":90,
    "gn:feature_class":"P",
    "gn:feature_code":"PPL",
    "gn:name":"Basti Jhellan",
    "gn:population":0,
    "gn:timezone":"Asia/Karachi",
    "iso:country":"PK",
    "name:und_x_variant":[
        "Basti Jhullan"
    ],
    "wof:name":"Basti Jhellan",
    "wof:placetype":"locality"
},
  "geometry": {"coordinates":[70.6951,28.72414],"type":"Point"}
}