{
  "type": "Feature",
  "properties": {
    "gn:admin1_code":"5",
    "gn:asciiname":"Goth Ghulam Jeho",
    "gn:country_code":"PK",
    "gn:dem":57,
    "gn:feature_class":"P",
    "gn:feature_code":"PPL",
    "gn:name":"Goth Ghulam Jeho",
    "gn:population":0,
    "gn:timezone":"Asia/Karachi",
    "iso:country":"PK",
    "name:und_x_variant":[
        "Goth Gullan"
    ],
    "wof:name":"Goth Ghulam Jeho",
    "wof:placetype":"locality"
},
  "geometry": {"coordinates":[68.37035999999999,27.73968],"type":"Point"}
}