{
  "type": "Feature",
  "properties": {
    "gn:admin1_code":"1.0",
    "gn:asciiname":"Zarik Mela",
    "gn:country_code":"PK",
    "gn:dem":1190,
    "gn:feature_class":"P",
    "gn:feature_code":"PPL",
    "gn:name":"Zarik Mela",
    "gn:population":0,
    "gn:timezone":"Asia/Karachi",
    "iso:country":"PK",
    "wof:name":"Zarik Mela",
    "wof:placetype":"locality"
},
  "geometry": {"coordinates":[70.28952,33.29542],"type":"Point"}
}