{
  "type": "Feature",
  "properties": {
    "gn:admin1_code":"3.0",
    "gn:asciiname":"Mitha Khan",
    "gn:country_code":"PK",
    "gn:dem":323,
    "gn:feature_class":"P",
    "gn:feature_code":"PPL",
    "gn:name":"Mitha Khan",
    "gn:population":0,
    "gn:timezone":"Asia/Karachi",
    "iso:country":"PK",
    "wof:name":"Mitha Khan",
    "wof:placetype":"locality"
},
  "geometry": {"coordinates":[70.74638,32.97139],"type":"Point"}
}