{
  "type": "Feature",
  "properties": {
    "gn:admin1_code":"4",
    "gn:asciiname":"Yaruwala",
    "gn:country_code":"PK",
    "gn:dem":194,
    "gn:feature_class":"P",
    "gn:feature_code":"PPL",
    "gn:name":"Yaruwala",
    "gn:population":0,
    "gn:timezone":"Asia/Karachi",
    "iso:country":"PK",
    "name:und_x_variant":[
        "Y\u0101riw\u0101la"
    ],
    "wof:name":"Yaruwala",
    "wof:placetype":"locality"
},
  "geometry": {"coordinates":[71.44249000000001,32.18679],"type":"Point"}
}