{
  "type": "Feature",
  "properties": {
    "gn:admin1_code":"7.0",
    "gn:asciiname":"Gungthawar",
    "gn:country_code":"PK",
    "gn:dem":2329,
    "gn:feature_class":"P",
    "gn:feature_code":"PPL",
    "gn:name":"Gungthawar",
    "gn:population":0,
    "gn:timezone":"Asia/Karachi",
    "iso:country":"PK",
    "wof:name":"Gungthawar",
    "wof:placetype":"locality"
},
  "geometry": {"coordinates":[75.19494,35.61089000000001],"type":"Point"}
}