{
  "type": "Feature",
  "properties": {
    "gn:admin1_code":"4",
    "gn:asciiname":"Basti Thapai",
    "gn:country_code":"PK",
    "gn:dem":96,
    "gn:feature_class":"P",
    "gn:feature_code":"PPL",
    "gn:name":"Basti Thapai",
    "gn:population":0,
    "gn:timezone":"Asia/Karachi",
    "iso:country":"PK",
    "name:und_x_variant":[
        "Basti Th\u0101p\u0101r",
        "Basti Thapan",
        "Basti Thapai"
    ],
    "wof:name":"Basti Thapai",
    "wof:placetype":"locality"
},
  "geometry": {"coordinates":[70.98366,29.05642000000001],"type":"Point"}
}