{
  "type": "Feature",
  "properties": {
    "gn:admin1_code":"4",
    "gn:asciiname":"Alam Sherwala",
    "gn:country_code":"PK",
    "gn:dem":196,
    "gn:feature_class":"P",
    "gn:feature_code":"PPL",
    "gn:name":"Alam Sherwala",
    "gn:population":0,
    "gn:timezone":"Asia/Karachi",
    "iso:country":"PK",
    "name:und_x_variant":[
        "\u0100lamsherw\u0101la"
    ],
    "wof:name":"Alam Sherwala",
    "wof:placetype":"locality"
},
  "geometry": {"coordinates":[71.58235999999999,32.11968],"type":"Point"}
}