{
  "type": "Feature",
  "properties": {
    "gn:admin1_code":"5.0",
    "gn:asciiname":"Baddo",
    "gn:country_code":"PK",
    "gn:dem":23,
    "gn:feature_class":"P",
    "gn:feature_code":"PPL",
    "gn:name":"Baddo",
    "gn:population":0,
    "gn:timezone":"Asia/Karachi",
    "iso:country":"PK",
    "wof:name":"Baddo",
    "wof:placetype":"locality"
},
  "geometry": {"coordinates":[70.37085,24.50391],"type":"Point"}
}