{
  "type": "Feature",
  "properties": {
    "gn:admin1_code":"3.0",
    "gn:asciiname":"Eid Gan",
    "gn:country_code":"PK",
    "gn:dem":319,
    "gn:feature_class":"P",
    "gn:feature_code":"PPL",
    "gn:name":"Eid Gan",
    "gn:population":0,
    "gn:timezone":"Asia/Karachi",
    "iso:country":"PK",
    "name:eng_x_preferred":[
        "Eid Gan"
    ],
    "wof:name":"Eid Gan",
    "wof:placetype":"locality"
},
  "geometry": {"coordinates":[71.58360999999999,34.03083],"type":"Point"}
}