{
  "type": "Feature",
  "properties": {
    "gn:admin1_code":"5",
    "gn:asciiname":"Goth Ferano Mahar",
    "gn:country_code":"PK",
    "gn:dem":65,
    "gn:feature_class":"P",
    "gn:feature_code":"PPL",
    "gn:name":"Goth Ferano Mahar",
    "gn:population":0,
    "gn:timezone":"Asia/Karachi",
    "iso:country":"PK",
    "name:und_x_variant":[
        "Goth Per\u0101no Mahar"
    ],
    "wof:name":"Goth Ferano Mahar",
    "wof:placetype":"locality"
},
  "geometry": {"coordinates":[69.33110000000001,27.84248],"type":"Point"}
}