{
  "type": "Feature",
  "properties": {
    "gn:admin1_code":"4.0",
    "gn:asciiname":"Ghaziwala",
    "gn:country_code":"PK",
    "gn:dem":143,
    "gn:feature_class":"P",
    "gn:feature_code":"PPL",
    "gn:name":"Ghaziwala",
    "gn:population":0,
    "gn:timezone":"Asia/Karachi",
    "iso:country":"PK",
    "name:eng_x_preferred":[
        "Ghaziwala"
    ],
    "name:urd_x_preferred":[
        "\u063a\u0627\u0632\u06cc \u0648\u0627\u0644\u0627"
    ],
    "wof:name":"Ghaziwala",
    "wof:placetype":"locality"
},
  "geometry": {"coordinates":[72.06153999999999,30.59654],"type":"Point"}
}