{
  "type": "Feature",
  "properties": {
    "gn:admin1_code":"5.0",
    "gn:asciiname":"Hamidwah",
    "gn:country_code":"PK",
    "gn:dem":45,
    "gn:feature_class":"P",
    "gn:feature_code":"PPL",
    "gn:name":"Hamidwah",
    "gn:population":0,
    "gn:timezone":"Asia/Karachi",
    "iso:country":"PK",
    "name:und_x_variant":[
        "Ham\u012bd"
    ],
    "wof:name":"Hamidwah",
    "wof:placetype":"locality"
},
  "geometry": {"coordinates":[67.71666999999999,27.43333],"type":"Point"}
}