{
  "type": "Feature",
  "properties": {
    "gn:admin1_code":"5",
    "gn:asciiname":"Muhib Jatoi",
    "gn:country_code":"PK",
    "gn:dem":63,
    "gn:feature_class":"P",
    "gn:feature_code":"PPL",
    "gn:name":"Muhib Jatoi",
    "gn:population":0,
    "gn:timezone":"Asia/Karachi",
    "iso:country":"PK",
    "name:und_x_variant":[
        "Mobel Kh\u0101n Jatoi"
    ],
    "wof:name":"Muhib Jatoi",
    "wof:placetype":"locality"
},
  "geometry": {"coordinates":[68.50793,28.17987],"type":"Point"}
}