{
  "type": "Feature",
  "properties": {
    "gn:admin1_code":"5",
    "gn:asciiname":"Basti Punnal Khan Mazari",
    "gn:country_code":"PK",
    "gn:dem":79,
    "gn:feature_class":"P",
    "gn:feature_code":"PPL",
    "gn:name":"Basti Punnal Khan Mazari",
    "gn:population":0,
    "gn:timezone":"Asia/Karachi",
    "iso:country":"PK",
    "name:und_x_variant":[
        "Basti Punnu Kh\u0101n"
    ],
    "wof:name":"Basti Punnal Khan Mazari",
    "wof:placetype":"locality"
},
  "geometry": {"coordinates":[69.76884,28.36495],"type":"Point"}
}