{
  "type": "Feature",
  "properties": {
    "gn:admin1_code":"4",
    "gn:asciiname":"Chah Tilla",
    "gn:country_code":"PK",
    "gn:dem":149,
    "gn:feature_class":"P",
    "gn:feature_code":"PPL",
    "gn:name":"Chah Tilla",
    "gn:population":0,
    "gn:timezone":"Asia/Karachi",
    "iso:country":"PK",
    "name:und_x_variant":[
        "Ch\u0101h Tillal"
    ],
    "wof:name":"Chah Tilla",
    "wof:placetype":"locality"
},
  "geometry": {"coordinates":[71.8075,30.91807],"type":"Point"}
}