{
  "type": "Feature",
  "properties": {
    "gn:admin1_code":"5.0",
    "gn:asciiname":"Allah Bakhsh Bhurgari",
    "gn:country_code":"PK",
    "gn:dem":8,
    "gn:feature_class":"P",
    "gn:feature_code":"PPL",
    "gn:name":"Allah Bakhsh Bhurgari",
    "gn:population":0,
    "gn:timezone":"Asia/Karachi",
    "iso:country":"PK",
    "wof:name":"Allah Bakhsh Bhurgari",
    "wof:placetype":"locality"
},
  "geometry": {"coordinates":[69.08199999999999,24.65819],"type":"Point"}
}