{
  "type": "Feature",
  "properties": {
    "gn:admin1_code":"7.0",
    "gn:asciiname":"Dassifoto",
    "gn:country_code":"PK",
    "gn:dem":3020,
    "gn:feature_class":"P",
    "gn:feature_code":"PPL",
    "gn:name":"Dassifoto",
    "gn:population":0,
    "gn:timezone":"Asia/Karachi",
    "iso:country":"PK",
    "wof:name":"Dassifoto",
    "wof:placetype":"locality"
},
  "geometry": {"coordinates":[75.86123000000001,35.18133],"type":"Point"}
}