{
  "type": "Feature",
  "properties": {
    "gn:admin1_code":"5",
    "gn:asciiname":"Rakhial Ji Wand",
    "gn:country_code":"PK",
    "gn:dem":57,
    "gn:feature_class":"P",
    "gn:feature_code":"PPL",
    "gn:name":"Rakhial Ji Wand",
    "gn:population":0,
    "gn:timezone":"Asia/Karachi",
    "iso:country":"PK",
    "name:und_x_variant":[
        "Rakhio W\u0101nd"
    ],
    "wof:name":"Rakhial Ji Wand",
    "wof:placetype":"locality"
},
  "geometry": {"coordinates":[68.50581,27.87023],"type":"Point"}
}