{
  "type": "Feature",
  "properties": {
    "gn:admin1_code":"3.0",
    "gn:asciiname":"Charchur",
    "gn:country_code":"PK",
    "gn:dem":407,
    "gn:feature_class":"P",
    "gn:feature_code":"PPL",
    "gn:name":"Charchur",
    "gn:population":0,
    "gn:timezone":"Asia/Karachi",
    "iso:country":"PK",
    "name:eng_x_preferred":[
        "Charchur"
    ],
    "name:und_x_variant":[
        "Char Chor"
    ],
    "wof:name":"Charchur",
    "wof:placetype":"locality"
},
  "geometry": {"coordinates":[72.06468000000002,34.4202],"type":"Point"}
}