{
  "type": "Feature",
  "properties": {
    "gn:admin1_code":"4.0",
    "gn:asciiname":"Jhijowali",
    "gn:country_code":"PK",
    "gn:dem":260,
    "gn:feature_class":"P",
    "gn:feature_code":"PPL",
    "gn:name":"Jhijowali",
    "gn:population":0,
    "gn:timezone":"Asia/Karachi",
    "iso:country":"PK",
    "name:und_x_variant":[
        "Jhiiow\u0101li"
    ],
    "wof:name":"Jhijowali",
    "wof:placetype":"locality"
},
  "geometry": {"coordinates":[75.07518,32.25036],"type":"Point"}
}