{
  "type": "Feature",
  "properties": {
    "gn:admin1_code":"4",
    "gn:asciiname":"Basti Mehrab Sontra",
    "gn:country_code":"PK",
    "gn:dem":97,
    "gn:feature_class":"P",
    "gn:feature_code":"PPL",
    "gn:name":"Basti Mehrab Sontra",
    "gn:population":0,
    "gn:timezone":"Asia/Karachi",
    "iso:country":"PK",
    "name:und_x_variant":[
        "Basti Mer\u0101b Nabkai",
        "Basti Miar\u0101b",
        "Basti Mehrab Sontra"
    ],
    "wof:name":"Basti Mehrab Sontra",
    "wof:placetype":"locality"
},
  "geometry": {"coordinates":[70.49605,29.09071],"type":"Point"}
}