{
  "type": "Feature",
  "properties": {
    "gn:admin1_code":"4.0",
    "gn:asciiname":"Chak Two Hundred Five Rakh Branch",
    "gn:country_code":"PK",
    "gn:dem":186,
    "gn:feature_class":"P",
    "gn:feature_code":"PPL",
    "gn:name":"Chak Two Hundred Five Rakh Branch",
    "gn:population":0,
    "gn:timezone":"Asia/Karachi",
    "iso:country":"PK",
    "name:und_x_variant":[
        "Di\u0101lw\u0101la",
        "Chak Two Hundred Five RB",
        "Chak Two Hundred Five Rakh Branch"
    ],
    "wof:name":"Chak Two Hundred Five Rakh Branch",
    "wof:placetype":"neighbourhood"
},
  "geometry": {"coordinates":[73.22854,31.43095],"type":"Point"}
}