{
  "type": "Feature",
  "properties": {
    "gn:admin1_code":"4.0",
    "gn:asciiname":"Bukhara Sharif",
    "gn:country_code":"PK",
    "gn:dem":105,
    "gn:feature_class":"P",
    "gn:feature_code":"PPL",
    "gn:name":"Bukhara Sharif",
    "gn:population":0,
    "gn:timezone":"Asia/Karachi",
    "iso:country":"PK",
    "name:und_x_variant":[
        "Bukh\u0101ra"
    ],
    "wof:name":"Bukhara Sharif",
    "wof:placetype":"locality"
},
  "geometry": {"coordinates":[70.49178000000001,29.44837],"type":"Point"}
}