{
  "type": "Feature",
  "properties": {
    "gn:admin1_code":"04",
    "gn:asciiname":"Khana Haveli",
    "gn:country_code":"PK",
    "gn:dem":208,
    "gn:feature_class":"P",
    "gn:feature_code":"PPL",
    "gn:name":"Khana Haveli",
    "gn:population":0,
    "gn:timezone":"Asia/Karachi",
    "iso:country":"PK",
    "name:und_x_variant":[
        "Kulleke",
        "Kullake",
        "Khana Haveli"
    ],
    "wof:name":"Khana Haveli",
    "wof:placetype":"locality"
},
  "geometry": {"coordinates":[74.42636,31.30619],"type":"Point"}
}