{
  "type": "Feature",
  "properties": {
    "gn:admin1_code":"4",
    "gn:asciiname":"Natha Singhwala",
    "gn:country_code":"PK",
    "gn:dem":201,
    "gn:feature_class":"P",
    "gn:feature_code":"PPL",
    "gn:name":"Natha Singhw\u0101la",
    "gn:population":0,
    "gn:timezone":"Asia/Karachi",
    "iso:country":"PK",
    "wof:name":"Natha Singhwala",
    "wof:placetype":"locality"
},
  "geometry": {"coordinates":[73.62275,31.77414000000001],"type":"Point"}
}