{
  "type": "Feature",
  "properties": {
    "gn:admin1_code":"4.0",
    "gn:asciiname":"Malkana",
    "gn:country_code":"PK",
    "gn:dem":146,
    "gn:feature_class":"P",
    "gn:feature_code":"PPL",
    "gn:name":"Malkana",
    "gn:population":0,
    "gn:timezone":"Asia/Karachi",
    "iso:country":"PK",
    "name:eng_x_preferred":[
        "Mallokand"
    ],
    "name:urd_x_preferred":[
        "\u0645\u0644\u06a9\u0627\u0646\u06c1"
    ],
    "wof:name":"Malkana",
    "wof:placetype":"locality"
},
  "geometry": {"coordinates":[70.99006999999997,30.80931],"type":"Point"}
}