{
  "type": "Feature",
  "properties": {
    "gn:admin1_code":"04",
    "gn:asciiname":"Naranjan",
    "gn:country_code":"PK",
    "gn:dem":206,
    "gn:feature_class":"P",
    "gn:feature_code":"PPL",
    "gn:name":"Naranjan",
    "gn:population":0,
    "gn:timezone":"Asia/Karachi",
    "iso:country":"PK",
    "name:und_x_variant":[
        "Narinjani",
        "Naranjani",
        "Naranjan"
    ],
    "wof:name":"Naranjan",
    "wof:placetype":"locality"
},
  "geometry": {"coordinates":[74.11039,31.50235],"type":"Point"}
}