{
  "type": "Feature",
  "properties": {
    "gn:admin1_code":"6",
    "gn:asciiname":"Chitta Katha Baihk",
    "gn:country_code":"PK",
    "gn:dem":3221,
    "gn:feature_class":"P",
    "gn:feature_code":"PPL",
    "gn:name":"Chitta Katha Baihk",
    "gn:population":0,
    "gn:timezone":"Asia/Karachi",
    "iso:country":"PK",
    "name:und_x_variant":[
        "Chatta Katha Baihk",
        "Chitta Katha Baihk"
    ],
    "wof:name":"Chitta Katha Baihk",
    "wof:placetype":"locality"
},
  "geometry": {"coordinates":[74.4875,34.94167],"type":"Point"}
}