{
  "type": "Feature",
  "properties": {
    "gn:admin1_code":"4",
    "gn:asciiname":"Dhatewala",
    "gn:country_code":"PK",
    "gn:dem":118,
    "gn:feature_class":"P",
    "gn:feature_code":"PPL",
    "gn:name":"Dhatewala",
    "gn:population":0,
    "gn:timezone":"Asia/Karachi",
    "iso:country":"PK",
    "name:und_x_variant":[
        "Datew\u0101la"
    ],
    "wof:name":"Dhatewala",
    "wof:placetype":"locality"
},
  "geometry": {"coordinates":[71.39324000000001,30.00794],"type":"Point"}
}