{
  "type": "Feature",
  "properties": {
    "gn:admin1_code":"06",
    "gn:asciiname":"Surgun",
    "gn:country_code":"PK",
    "gn:dem":2316,
    "gn:feature_class":"P",
    "gn:feature_code":"PPL",
    "gn:name":"Surgun",
    "gn:population":0,
    "gn:timezone":"Asia/Karachi",
    "iso:country":"PK",
    "name:und_x_variant":[
        "Surgan",
        "Surgun"
    ],
    "wof:name":"Surgun",
    "wof:placetype":"locality"
},
  "geometry": {"coordinates":[74.20289,34.86844],"type":"Point"}
}