{
  "type": "Feature",
  "properties": {
    "gn:admin1_code":"4.0",
    "gn:asciiname":"Jhakkarpur",
    "gn:country_code":"PK",
    "gn:dem":119,
    "gn:feature_class":"P",
    "gn:feature_code":"PPL",
    "gn:name":"Jhakkarpur",
    "gn:population":0,
    "gn:timezone":"Asia/Karachi",
    "iso:country":"PK",
    "name:und_x_variant":[
        "Jhakarpur",
        "Jhakkarpur"
    ],
    "wof:name":"Jhakkarpur",
    "wof:placetype":"locality"
},
  "geometry": {"coordinates":[71.36404,30.145],"type":"Point"}
}