{
  "type": "Feature",
  "properties": {
    "gn:admin1_code":"5",
    "gn:asciiname":"Goth Ghazi Shoro",
    "gn:country_code":"PK",
    "gn:dem":20,
    "gn:feature_class":"P",
    "gn:feature_code":"PPL",
    "gn:name":"Goth Ghazi Shoro",
    "gn:population":0,
    "gn:timezone":"Asia/Karachi",
    "iso:country":"PK",
    "name:eng_x_preferred":[
        "Goth All\u0101hy\u0101r Shoro"
    ],
    "wof:name":"Goth Ghazi Shoro",
    "wof:placetype":"locality"
},
  "geometry": {"coordinates":[68.44843,25.28742],"type":"Point"}
}