{
  "type": "Feature",
  "properties": {
    "gn:admin1_code":"3",
    "gn:asciiname":"Chir Banda",
    "gn:country_code":"PK",
    "gn:dem":1642,
    "gn:feature_class":"P",
    "gn:feature_code":"PPL",
    "gn:name":"Chir Banda",
    "gn:population":0,
    "gn:timezone":"Asia/Karachi",
    "iso:country":"PK",
    "name:und_x_variant":[
        "Sh\u012br B\u0101nda",
        "Chir Banda"
    ],
    "wof:name":"Chir Banda",
    "wof:placetype":"locality"
},
  "geometry": {"coordinates":[72.89416,34.82394],"type":"Point"}
}