{
  "type": "Feature",
  "properties": {
    "gn:admin1_code":"3",
    "gn:asciiname":"Palai",
    "gn:country_code":"PK",
    "gn:dem":3038,
    "gn:feature_class":"P",
    "gn:feature_code":"PPL",
    "gn:name":"Palai",
    "gn:population":0,
    "gn:timezone":"Asia/Karachi",
    "iso:country":"PK",
    "name:eng_x_preferred":[
        "P\u0101la\u012b"
    ],
    "wof:name":"Palai",
    "wof:placetype":"locality"
},
  "geometry": {"coordinates":[71.94582,35.65044],"type":"Point"}
}