{
  "type": "Feature",
  "properties": {
    "gn:admin1_code":"3",
    "gn:asciiname":"Shorkat",
    "gn:country_code":"PK",
    "gn:dem":1533,
    "gn:feature_class":"P",
    "gn:feature_code":"PPL",
    "gn:name":"Shorkat",
    "gn:population":0,
    "gn:timezone":"Asia/Karachi",
    "iso:country":"PK",
    "name:und_x_variant":[
        "Shorkad",
        "Shorkot",
        "Shorkat"
    ],
    "wof:name":"Shorkat",
    "wof:placetype":"locality"
},
  "geometry": {"coordinates":[72.55998000000002,35.14472],"type":"Point"}
}