{
  "type": "Feature",
  "properties": {
    "gn:admin1_code":"5.0",
    "gn:asciiname":"Dosi Muhammad Ujjan",
    "gn:country_code":"PK",
    "gn:dem":53,
    "gn:feature_class":"P",
    "gn:feature_code":"PPL",
    "gn:name":"Dosi Muhammad Ujjan",
    "gn:population":0,
    "gn:timezone":"Asia/Karachi",
    "iso:country":"PK",
    "wof:name":"Dosi Muhammad Ujjan",
    "wof:placetype":"locality"
},
  "geometry": {"coordinates":[68.64100000000001,27.18987000000001],"type":"Point"}
}