{
  "type": "Feature",
  "properties": {
    "gn:admin1_code":"4.0",
    "gn:asciiname":"Chakwal",
    "gn:country_code":"PK",
    "gn:dem":194,
    "gn:feature_class":"P",
    "gn:feature_code":"PPL",
    "gn:name":"Chakw\u0101l",
    "gn:population":0,
    "gn:timezone":"Asia/Karachi",
    "iso:country":"PK",
    "name:ara_x_preferred":[
        "\u062c\u0643\u0648\u0627\u0644"
    ],
    "name:azb_x_preferred":[
        "\u0686\u06a9\u0648\u0627\u0644"
    ],
    "name:bel_x_preferred":[
        "\u0427\u0430\u043a\u0432\u0430\u043b"
    ],
    "name:ben_x_preferred":[
        "\u099a\u0995\u0993\u09af\u09bc\u09be\u09b2"
    ],
    "name:fas_x_preferred":[
        "\u0686\u06a9\u0648\u0627\u0644"
    ],
    "name:fra_x_preferred":[
        "Chakwal"
    ],
    "name:hin_x_preferred":[
        "\u091a\u0915\u0935\u093e\u0932"
    ],
    "name:ita_x_preferred":[
        "Chakwal"
    ],
    "name:pan_x_preferred":[
        "\u0a1a\u0a15\u0a35\u0a3e\u0a32"
    ],
    "name:pnb_x_preferred":[
        "\u0686\u06a9\u0648\u0627\u0644"
    ],
    "name:pol_x_preferred":[
        "\u0106akwal"
    ],
    "name:por_x_preferred":[
        "Chakwal"
    ],
    "name:pus_x_preferred":[
        "\u0686\u06a9\u0648\u0627\u0644"
    ],
    "name:rus_x_preferred":[
        "\u0427\u0430\u043a\u0432\u0430\u043b"
    ],
    "name:snd_x_preferred":[
        "\u0686\u06aa\u0648\u0627\u0644"
    ],
    "name:spa_x_preferred":[
        "Chakwal"
    ],
    "name:srp_x_preferred":[
        "\u0427\u0430\u043a\u0432\u0430\u043b"
    ],
    "name:swe_x_preferred":[
        "Chakwal"
    ],
    "name:urd_x_preferred":[
        "\u0686\u06a9\u0648\u0627\u0644"
    ],
    "name:vie_x_preferred":[
        "Chakwal"
    ],
    "name:zho_x_preferred":[
        "\u5091\u683c\u74e6\u723e"
    ],
    "wof:name":"Chakwal",
    "wof:placetype":"locality"
},
  "geometry": {"coordinates":[72.91667,32.11333],"type":"Point"}
}