{
  "type": "Feature",
  "properties": {
    "gn:admin1_code":"4.0",
    "gn:asciiname":"Chakwal",
    "gn:country_code":"PK",
    "gn:dem":194,
    "gn:feature_class":"P",
    "gn:feature_code":"PPL",
    "gn:name":"Chakw\u0101l",
    "gn:population":0,
    "gn:timezone":"Asia/Karachi",
    "iso:country":"PK",
    "wof:name":"Chakwal",
    "wof:placetype":"locality"
},
  "geometry": {"coordinates":[72.91667,32.11333],"type":"Point"}
}