{
  "type": "Feature",
  "properties": {
    "gn:admin1_code":"4.0",
    "gn:asciiname":"Jandiala Purana",
    "gn:country_code":"PK",
    "gn:dem":222,
    "gn:feature_class":"P",
    "gn:feature_code":"PPL",
    "gn:name":"Jandiala Purana",
    "gn:population":0,
    "gn:timezone":"Asia/Karachi",
    "iso:country":"PK",
    "name:und_x_variant":[
        "Jandiala Kalsan",
        "Jandi\u0101la",
        "Jandiala Purana"
    ],
    "wof:name":"Jandiala Purana",
    "wof:placetype":"locality"
},
  "geometry": {"coordinates":[74.55122,31.84762000000001],"type":"Point"}
}