{
  "type": "Feature",
  "properties": {
    "gn:admin1_code":"4",
    "gn:asciiname":"Chak Thirty-six Shumali",
    "gn:country_code":"PK",
    "gn:dem":181,
    "gn:feature_class":"P",
    "gn:feature_code":"PPL",
    "gn:name":"Chak Thirty-six Shumali",
    "gn:population":0,
    "gn:timezone":"Asia/Karachi",
    "iso:country":"PK",
    "name:und_x_variant":[
        "Rattray\u0101b\u0101d",
        "Chak Eighty-Six",
        "Chak Thirty-six Shumali"
    ],
    "wof:name":"Chak Thirty-six Shumali",
    "wof:placetype":"locality"
},
  "geometry": {"coordinates":[72.88696999999998,31.42672],"type":"Point"}
}