{
  "type": "Feature",
  "properties": {
    "gn:admin1_code":"5.0",
    "gn:asciiname":"Piru Kaka",
    "gn:country_code":"PK",
    "gn:dem":29,
    "gn:feature_class":"P",
    "gn:feature_code":"PPL",
    "gn:name":"Piru Kaka",
    "gn:population":0,
    "gn:timezone":"Asia/Karachi",
    "iso:country":"PK",
    "name:und_x_variant":[
        "Piru K\u0101ka"
    ],
    "wof:name":"Piru Kaka",
    "wof:placetype":"locality"
},
  "geometry": {"coordinates":[68.41193,26.00595],"type":"Point"}
}