{
  "type": "Feature",
  "properties": {
    "gn:admin1_code":"3.0",
    "gn:asciiname":"Jalalpur",
    "gn:country_code":"PK",
    "gn:dem":1273,
    "gn:feature_class":"P",
    "gn:feature_code":"PPL",
    "gn:name":"Jalalpur",
    "gn:population":0,
    "gn:timezone":"Asia/Karachi",
    "iso:country":"PK",
    "name:und_x_variant":[
        "Jalalpura",
        "Juliapura",
        "Jalalpur"
    ],
    "wof:name":"Jalalpur",
    "wof:placetype":"locality"
},
  "geometry": {"coordinates":[73.24106,34.243],"type":"Point"}
}