{
  "type": "Feature",
  "properties": {
    "gn:admin1_code":"1.0",
    "gn:asciiname":"Zafar Kile",
    "gn:country_code":"PK",
    "gn:dem":702,
    "gn:feature_class":"P",
    "gn:feature_code":"PPL",
    "gn:name":"Zafar Kile",
    "gn:population":0,
    "gn:timezone":"Asia/Karachi",
    "iso:country":"PK",
    "wof:name":"Zafar Kile",
    "wof:placetype":"locality"
},
  "geometry": {"coordinates":[71.36464000000002,34.34728],"type":"Point"}
}