{
  "type": "Feature",
  "properties": {
    "gn:admin1_code":"3",
    "gn:asciiname":"Jhok Mamdu Gadi",
    "gn:country_code":"PK",
    "gn:dem":174,
    "gn:feature_class":"P",
    "gn:feature_code":"PPL",
    "gn:name":"Jhok Mamdu Gadi",
    "gn:population":0,
    "gn:timezone":"Asia/Karachi",
    "iso:country":"PK",
    "name:und_x_variant":[
        "Jhok Mamdu"
    ],
    "wof:name":"Jhok Mamdu Gadi",
    "wof:placetype":"locality"
},
  "geometry": {"coordinates":[70.68531,31.58428],"type":"Point"}
}