{
  "type": "Feature",
  "properties": {
    "gn:admin1_code":"4.0",
    "gn:asciiname":"Chak Twenty-three Twenty-four - Three Right",
    "gn:country_code":"PK",
    "gn:dem":157,
    "gn:feature_class":"P",
    "gn:feature_code":"PPL",
    "gn:name":"Chak Twenty-three Twenty-four - Three Right",
    "gn:population":0,
    "gn:timezone":"Asia/Karachi",
    "iso:country":"PK",
    "wof:name":"Chak Twenty-three Twenty-four - Three Right",
    "wof:placetype":"locality"
},
  "geometry": {"coordinates":[73.03860999999998,29.62647],"type":"Point"}
}