{
  "type": "Feature",
  "properties": {
    "gn:admin1_code":"7.0",
    "gn:asciiname":"Khapalu",
    "gn:country_code":"PK",
    "gn:dem":2600,
    "gn:feature_class":"P",
    "gn:feature_code":"PPL",
    "gn:name":"Khapalu",
    "gn:population":0,
    "gn:timezone":"Asia/Karachi",
    "iso:country":"PK",
    "wof:name":"Khapalu",
    "wof:placetype":"locality"
},
  "geometry": {"coordinates":[76.33381,35.16220999999999],"type":"Point"}
}