{
  "type": "Feature",
  "properties": {
    "gn:admin1_code":"4.0",
    "gn:asciiname":"Mohra Jummal",
    "gn:country_code":"PK",
    "gn:dem":528,
    "gn:feature_class":"P",
    "gn:feature_code":"PPL",
    "gn:name":"Mohra Jummal",
    "gn:population":0,
    "gn:timezone":"Asia/Karachi",
    "iso:country":"PK",
    "name:und_x_variant":[
        "Mohra Jumman"
    ],
    "wof:name":"Mohra Jummal",
    "wof:placetype":"locality"
},
  "geometry": {"coordinates":[73.24769999999999,33.49442],"type":"Point"}
}