{
  "type": "Feature",
  "properties": {
    "gn:admin1_code":"2",
    "gn:asciiname":"Chhapri",
    "gn:country_code":"PK",
    "gn:dem":1211,
    "gn:feature_class":"P",
    "gn:feature_code":"PPL",
    "gn:name":"Chhapri",
    "gn:population":0,
    "gn:timezone":"Asia/Karachi",
    "iso:country":"PK",
    "name:und_x_variant":[
        "Galak"
    ],
    "wof:name":"Chhapri",
    "wof:placetype":"locality"
},
  "geometry": {"coordinates":[69.04503000000001,30.42111],"type":"Point"}
}