{
  "type": "Feature",
  "properties": {
    "gn:admin1_code":"1.0",
    "gn:asciiname":"Latif Khan Kili",
    "gn:country_code":"PK",
    "gn:dem":948,
    "gn:feature_class":"P",
    "gn:feature_code":"PPL",
    "gn:name":"Latif Khan Kili",
    "gn:population":0,
    "gn:timezone":"Asia/Karachi",
    "iso:country":"PK",
    "name:und_x_variant":[
        "Lat\u012bf Kili"
    ],
    "wof:name":"Latif Khan Kili",
    "wof:placetype":"locality"
},
  "geometry": {"coordinates":[71.18855000000001,33.96599000000001],"type":"Point"}
}