{
  "type": "Feature",
  "properties": {
    "gn:admin1_code":"4.0",
    "gn:asciiname":"Muhammad Hayatwala Bhan",
    "gn:country_code":"PK",
    "gn:dem":185,
    "gn:feature_class":"P",
    "gn:feature_code":"PPL",
    "gn:name":"Muhammad Hayatwala Bhan",
    "gn:population":0,
    "gn:timezone":"Asia/Karachi",
    "iso:country":"PK",
    "name:und_x_variant":[
        "Muhammad Hayatw\u0101la Bh\u0101n"
    ],
    "wof:name":"Muhammad Hayatwala Bhan",
    "wof:placetype":"locality"
},
  "geometry": {"coordinates":[72.15701999999997,32.07319],"type":"Point"}
}