{
  "type": "Feature",
  "properties": {
    "gn:admin1_code":"1.0",
    "gn:asciiname":"Tangi Sar",
    "gn:country_code":"PK",
    "gn:dem":851,
    "gn:feature_class":"P",
    "gn:feature_code":"PPL",
    "gn:name":"Tangi Sar",
    "gn:population":0,
    "gn:timezone":"Asia/Karachi",
    "iso:country":"PK",
    "name:eng_x_preferred":[
        "Tangi Sar"
    ],
    "wof:name":"Tangi Sar",
    "wof:placetype":"locality"
},
  "geometry": {"coordinates":[69.99061,31.80941],"type":"Point"}
}