{
  "type": "Feature",
  "properties": {
    "gn:admin1_code":"2.0",
    "gn:asciiname":"Sarband",
    "gn:country_code":"PK",
    "gn:dem":1355,
    "gn:feature_class":"P",
    "gn:feature_code":"PPL",
    "gn:name":"Sarband",
    "gn:population":0,
    "gn:timezone":"Asia/Karachi",
    "iso:country":"PK",
    "wof:name":"Sarband",
    "wof:placetype":"locality"
},
  "geometry": {"coordinates":[69.51476,30.46965],"type":"Point"}
}