{
  "type": "Feature",
  "properties": {
    "gn:admin1_code":"4.0",
    "gn:asciiname":"Dera Chatha",
    "gn:country_code":"PK",
    "gn:dem":218,
    "gn:feature_class":"P",
    "gn:feature_code":"PPL",
    "gn:name":"Dera Chatha",
    "gn:population":0,
    "gn:timezone":"Asia/Karachi",
    "iso:country":"PK",
    "wof:name":"Dera Chatha",
    "wof:placetype":"locality"
},
  "geometry": {"coordinates":[73.52257,32.54545],"type":"Point"}
}