{
  "type": "Feature",
  "properties": {
    "gn:admin1_code":"4.0",
    "gn:asciiname":"Kahn Singh Khurkan",
    "gn:country_code":"PK",
    "gn:dem":170,
    "gn:feature_class":"P",
    "gn:feature_code":"PPL",
    "gn:name":"Kahn Singh Khurkan",
    "gn:population":0,
    "gn:timezone":"Asia/Karachi",
    "iso:country":"PK",
    "wof:name":"Kahn Singh Khurkan",
    "wof:placetype":"locality"
},
  "geometry": {"coordinates":[73.72398000000003,30.2139],"type":"Point"}
}