{
  "type": "Feature",
  "properties": {
    "gn:admin1_code":"4.0",
    "gn:asciiname":"Basti Shekhar",
    "gn:country_code":"PK",
    "gn:dem":108,
    "gn:feature_class":"P",
    "gn:feature_code":"PPL",
    "gn:name":"Basti Shekhar",
    "gn:population":0,
    "gn:timezone":"Asia/Karachi",
    "iso:country":"PK",
    "name:und_x_variant":[
        "Chhina Mal\u0101na"
    ],
    "wof:name":"Basti Shekhar",
    "wof:placetype":"locality"
},
  "geometry": {"coordinates":[70.82511,29.60583],"type":"Point"}
}