{
  "type": "Feature",
  "properties": {
    "gn:admin1_code":"1.0",
    "gn:asciiname":"Guda Trap",
    "gn:country_code":"PK",
    "gn:dem":797,
    "gn:feature_class":"P",
    "gn:feature_code":"PPL",
    "gn:name":"Guda Trap",
    "gn:population":0,
    "gn:timezone":"Asia/Karachi",
    "iso:country":"PK",
    "wof:name":"Guda Trap",
    "wof:placetype":"locality"
},
  "geometry": {"coordinates":[70.32848,33.20569],"type":"Point"}
}