{
  "type": "Feature",
  "properties": {
    "gn:admin1_code":"2",
    "gn:asciiname":"Goth Bachal",
    "gn:country_code":"PK",
    "gn:dem":64,
    "gn:feature_class":"P",
    "gn:feature_code":"PPL",
    "gn:name":"Goth Bachal",
    "gn:population":0,
    "gn:timezone":"Asia/Karachi",
    "iso:country":"PK",
    "name:eng_x_preferred":[
        "Goth Bachal"
    ],
    "wof:name":"Goth Bachal",
    "wof:placetype":"locality"
},
  "geometry": {"coordinates":[66.79119,25.15255],"type":"Point"}
}