{
  "type": "Feature",
  "properties": {
    "gn:admin1_code":"3",
    "gn:asciiname":"Sar China Banda",
    "gn:country_code":"PK",
    "gn:dem":2258,
    "gn:feature_class":"P",
    "gn:feature_code":"PPL",
    "gn:name":"Sar China Banda",
    "gn:population":0,
    "gn:timezone":"Asia/Karachi",
    "iso:country":"PK",
    "wof:name":"Sar China Banda",
    "wof:placetype":"locality"
},
  "geometry": {"coordinates":[72.40728,34.68273],"type":"Point"}
}