{
  "type": "Feature",
  "properties": {
    "gn:admin1_code":"3.0",
    "gn:asciiname":"Koto",
    "gn:country_code":"PK",
    "gn:dem":790,
    "gn:feature_class":"P",
    "gn:feature_code":"PPL",
    "gn:name":"Koto",
    "gn:population":0,
    "gn:timezone":"Asia/Karachi",
    "iso:country":"PK",
    "name:eng_x_preferred":[
        "Koto"
    ],
    "wof:name":"Koto",
    "wof:placetype":"locality"
},
  "geometry": {"coordinates":[71.861,34.86267],"type":"Point"}
}