{
  "type": "Feature",
  "properties": {
    "gn:admin1_code":"2.0",
    "gn:asciiname":"Sipachik",
    "gn:country_code":"PK",
    "gn:dem":1340,
    "gn:feature_class":"P",
    "gn:feature_code":"PPL",
    "gn:name":"Sipachik",
    "gn:population":0,
    "gn:timezone":"Asia/Karachi",
    "iso:country":"PK",
    "wof:name":"Sipachik",
    "wof:placetype":"locality"
},
  "geometry": {"coordinates":[66.5436,27.50851],"type":"Point"}
}