{
  "type": "Feature",
  "properties": {
    "gn:admin1_code":"4",
    "gn:asciiname":"Jawaya",
    "gn:country_code":"PK",
    "gn:dem":184,
    "gn:feature_class":"P",
    "gn:feature_code":"PPL",
    "gn:name":"Jawaya",
    "gn:population":0,
    "gn:timezone":"Asia/Karachi",
    "iso:country":"PK",
    "name:und_x_variant":[
        "Thatta H\u0101ji",
        "Jaw\u0101ia Khichi",
        "Jawaya",
        "H\u0101ji"
    ],
    "wof:name":"Jawaya",
    "wof:placetype":"locality"
},
  "geometry": {"coordinates":[73.47377,31.07013],"type":"Point"}
}