{
  "type": "Feature",
  "properties": {
    "gn:admin1_code":"4.0",
    "gn:asciiname":"Hathi Khelanwala",
    "gn:country_code":"PK",
    "gn:dem":216,
    "gn:feature_class":"P",
    "gn:feature_code":"PPL",
    "gn:name":"Hathi Khelanwala",
    "gn:population":0,
    "gn:timezone":"Asia/Karachi",
    "iso:country":"PK",
    "wof:name":"Hathi Khelanwala",
    "wof:placetype":"locality"
},
  "geometry": {"coordinates":[71.57073000000003,32.71258],"type":"Point"}
}