{
  "type": "Feature",
  "properties": {
    "gn:admin1_code":"4.0",
    "gn:asciiname":"Chak Umra",
    "gn:country_code":"PK",
    "gn:dem":553,
    "gn:feature_class":"P",
    "gn:feature_code":"PPL",
    "gn:name":"Chak Umra",
    "gn:population":0,
    "gn:timezone":"Asia/Karachi",
    "iso:country":"PK",
    "name:eng_x_preferred":[
        "Chak Mura"
    ],
    "name:eng_x_variant":[
        "Chak Umra"
    ],
    "wof:name":"Chak Umra",
    "wof:placetype":"locality"
},
  "geometry": {"coordinates":[72.95904,32.99876],"type":"Point"}
}