{
  "type": "Feature",
  "properties": {
    "gn:admin1_code":"5",
    "gn:asciiname":"Goth Sono Khatri",
    "gn:country_code":"PK",
    "gn:dem":56,
    "gn:feature_class":"P",
    "gn:feature_code":"PPL",
    "gn:name":"Goth Sono Khatri",
    "gn:population":0,
    "gn:timezone":"Asia/Karachi",
    "iso:country":"PK",
    "name:und_x_variant":[
        "Sono Kh\u0101tri"
    ],
    "wof:name":"Goth Sono Khatri",
    "wof:placetype":"locality"
},
  "geometry": {"coordinates":[68.38046,27.83536],"type":"Point"}
}