{
  "type": "Feature",
  "properties": {
    "gn:admin1_code":"4",
    "gn:asciiname":"Jhok Khichian",
    "gn:country_code":"PK",
    "gn:dem":172,
    "gn:feature_class":"P",
    "gn:feature_code":"PPL",
    "gn:name":"Jhok Khichian",
    "gn:population":0,
    "gn:timezone":"Asia/Karachi",
    "iso:country":"PK",
    "name:und_x_variant":[
        "Jhok Khichi\u0101nw\u0101li"
    ],
    "wof:name":"Jhok Khichian",
    "wof:placetype":"locality"
},
  "geometry": {"coordinates":[71.04276999999998,31.78519],"type":"Point"}
}