{
  "type": "Feature",
  "properties": {
    "gn:admin1_code":"3",
    "gn:asciiname":"Gandero Banda",
    "gn:country_code":"PK",
    "gn:dem":591,
    "gn:feature_class":"P",
    "gn:feature_code":"PPL",
    "gn:name":"Gandero Banda",
    "gn:population":0,
    "gn:timezone":"Asia/Karachi",
    "iso:country":"PK",
    "name:eng_x_preferred":[
        "Gandero B\u0101ba"
    ],
    "wof:name":"Gandero Banda",
    "wof:placetype":"locality"
},
  "geometry": {"coordinates":[72.19471999999998,34.53827],"type":"Point"}
}