{
  "type": "Feature",
  "properties": {
    "gn:admin1_code":"4",
    "gn:asciiname":"Basti Ghallu",
    "gn:country_code":"PK",
    "gn:dem":103,
    "gn:feature_class":"P",
    "gn:feature_code":"PPL",
    "gn:name":"Basti Ghallu",
    "gn:population":0,
    "gn:timezone":"Asia/Karachi",
    "iso:country":"PK",
    "wof:name":"Basti Ghallu",
    "wof:placetype":"locality"
},
  "geometry": {"coordinates":[71.00610999999998,29.42739000000001],"type":"Point"}
}