{
  "type": "Feature",
  "properties": {
    "gn:admin1_code":"3.0",
    "gn:asciiname":"Burj Dheri Kili",
    "gn:country_code":"PK",
    "gn:dem":343,
    "gn:feature_class":"P",
    "gn:feature_code":"PPL",
    "gn:name":"Burj Dheri Kili",
    "gn:population":0,
    "gn:timezone":"Asia/Karachi",
    "iso:country":"PK",
    "wof:name":"Burj Dheri Kili",
    "wof:placetype":"locality"
},
  "geometry": {"coordinates":[71.42806999999998,34.09786],"type":"Point"}
}