{
  "type": "Feature",
  "properties": {
    "gn:admin1_code":"1.0",
    "gn:asciiname":"Khar Warsak",
    "gn:country_code":"PK",
    "gn:dem":1038,
    "gn:feature_class":"P",
    "gn:feature_code":"PPL",
    "gn:name":"Khar Warsak",
    "gn:population":0,
    "gn:timezone":"Asia/Karachi",
    "iso:country":"PK",
    "wof:name":"Khar Warsak",
    "wof:placetype":"locality"
},
  "geometry": {"coordinates":[70.07951,33.06822],"type":"Point"}
}