{
  "type": "Feature",
  "properties": {
    "gn:admin1_code":"4",
    "gn:asciiname":"Chanan Brahminwala",
    "gn:country_code":"PK",
    "gn:dem":144,
    "gn:feature_class":"P",
    "gn:feature_code":"PPL",
    "gn:name":"Chanan Brahminw\u0101la",
    "gn:population":0,
    "gn:timezone":"Asia/Karachi",
    "iso:country":"PK",
    "wof:name":"Chanan Brahminwala",
    "wof:placetype":"locality"
},
  "geometry": {"coordinates":[71.39721999999998,30.90556],"type":"Point"}
}