{
  "type": "Feature",
  "properties": {
    "gn:admin1_code":"04",
    "gn:asciiname":"Uthwal Jagir",
    "gn:country_code":"PK",
    "gn:dem":183,
    "gn:feature_class":"P",
    "gn:feature_code":"PPL",
    "gn:name":"Uthwal Jagir",
    "gn:population":0,
    "gn:timezone":"Asia/Karachi",
    "iso:country":"PK",
    "wof:name":"Uthwal Jagir",
    "wof:placetype":"locality"
},
  "geometry": {"coordinates":[73.51649999999999,31.03396],"type":"Point"}
}