{
  "type": "Feature",
  "properties": {
    "gn:admin1_code":"04",
    "gn:asciiname":"Raikot",
    "gn:country_code":"PK",
    "gn:dem":145,
    "gn:feature_class":"P",
    "gn:feature_code":"PPL",
    "gn:name":"R\u0101ikot",
    "gn:population":0,
    "gn:timezone":"Asia/Karachi",
    "iso:country":"PK",
    "name:ben_x_preferred":[
        "\u09b0\u09be\u09af\u09bc\u0995\u09cb\u099f"
    ],
    "name:bpy_x_preferred":[
        "\u09b0\u09be\u09af\u09bc\u0995\u09cb\u099f"
    ],
    "name:cat_x_preferred":[
        "Raikot"
    ],
    "name:ceb_x_preferred":[
        "R\u0101ikot"
    ],
    "name:hin_x_preferred":[
        "\u0930\u093e\u092f\u0915\u094b\u091f"
    ],
    "name:ita_x_preferred":[
        "Raikot"
    ],
    "name:mlg_x_preferred":[
        "Raikot"
    ],
    "name:msa_x_preferred":[
        "Raikot"
    ],
    "name:nld_x_preferred":[
        "Raikot"
    ],
    "name:ori_x_preferred":[
        "\u0b30\u0b3e\u0b07\u0b15\u0b4b\u0b1f"
    ],
    "name:pan_x_preferred":[
        "\u0a30\u0a3e\u0a0f\u0a15\u0a4b\u0a1f"
    ],
    "name:pnb_x_preferred":[
        "\u0631\u0627\u0626\u06cc\u06a9\u0648\u0679"
    ],
    "name:por_x_preferred":[
        "Raikot"
    ],
    "name:spa_x_preferred":[
        "Raikot"
    ],
    "name:swe_x_preferred":[
        "R\u0101ikot"
    ],
    "name:vie_x_preferred":[
        "Raikot"
    ],
    "name:zho_x_preferred":[
        "\u8d56\u79d1\u7279"
    ],
    "wof:name":"Raikot",
    "wof:placetype":"locality"
},
  "geometry": {"coordinates":[72.40000000000001,30.28333],"type":"Point"}
}