{
  "type": "Feature",
  "properties": {
    "gn:admin1_code":"3",
    "gn:asciiname":"Badrocha",
    "gn:country_code":"PK",
    "gn:dem":1548,
    "gn:feature_class":"P",
    "gn:feature_code":"PPL",
    "gn:name":"Badrocha",
    "gn:population":0,
    "gn:timezone":"Asia/Karachi",
    "iso:country":"PK",
    "wof:name":"Badrocha",
    "wof:placetype":"locality"
},
  "geometry": {"coordinates":[73.21916999999998,34.52658],"type":"Point"}
}