{
  "type": "Feature",
  "properties": {
    "gn:admin1_code":"4.0",
    "gn:asciiname":"Chak Fifty-four - Four Right",
    "gn:country_code":"PK",
    "gn:dem":156,
    "gn:feature_class":"P",
    "gn:feature_code":"PPL",
    "gn:name":"Chak Fifty-four - Four Right",
    "gn:population":0,
    "gn:timezone":"Asia/Karachi",
    "iso:country":"PK",
    "wof:name":"Chak Fifty-four - Four Right",
    "wof:placetype":"locality"
},
  "geometry": {"coordinates":[73.08805,29.59049000000001],"type":"Point"}
}