{
  "type": "Feature",
  "properties": {
    "gn:admin1_code":"5",
    "gn:asciiname":"Abdul Khaliq",
    "gn:country_code":"PK",
    "gn:dem":59,
    "gn:feature_class":"P",
    "gn:feature_code":"PPL",
    "gn:name":"Abdul Khaliq",
    "gn:population":0,
    "gn:timezone":"Asia/Karachi",
    "iso:country":"PK",
    "wof:name":"Abdul Khaliq",
    "wof:placetype":"locality"
},
  "geometry": {"coordinates":[68.68685000000001,28.41679],"type":"Point"}
}