{
  "type": "Feature",
  "properties": {
    "gn:admin1_code":"5",
    "gn:asciiname":"Abdul Khaliq",
    "gn:country_code":"PK",
    "gn:dem":59,
    "gn:feature_class":"P",
    "gn:feature_code":"PPL",
    "gn:name":"Abdul Khaliq",
    "gn:population":0,
    "gn:timezone":"Asia/Karachi",
    "iso:country":"PK",
    "name:ara_x_preferred":[
        "\u0639\u0628\u062f \u0627\u0644\u062e\u0627\u0644\u0642"
    ],
    "name:ben_x_preferred":[
        "\u0986\u09ac\u09a6\u09c1\u09b2 \u0996\u09be\u09b2\u09c7\u0995"
    ],
    "name:cat_x_preferred":[
        "Abd-al-Kh\u00e0liq"
    ],
    "wof:name":"Abdul Khaliq",
    "wof:placetype":"locality"
},
  "geometry": {"coordinates":[68.68685000000001,28.41679],"type":"Point"}
}