{
  "type": "Feature",
  "properties": {
    "gn:admin1_code":"5",
    "gn:asciiname":"Chhutto Dal",
    "gn:country_code":"PK",
    "gn:dem":66,
    "gn:feature_class":"P",
    "gn:feature_code":"PPL",
    "gn:name":"Chhutto Dal",
    "gn:population":0,
    "gn:timezone":"Asia/Karachi",
    "iso:country":"PK",
    "name:und_x_variant":[
        "Chatha Dal"
    ],
    "wof:name":"Chhutto Dal",
    "wof:placetype":"locality"
},
  "geometry": {"coordinates":[68.80928,28.17513],"type":"Point"}
}