{
  "type": "Feature",
  "properties": {
    "gn:admin1_code":"3",
    "gn:asciiname":"Kinari",
    "gn:country_code":"PK",
    "gn:dem":2166,
    "gn:feature_class":"P",
    "gn:feature_code":"PPL",
    "gn:name":"Kinari",
    "gn:population":0,
    "gn:timezone":"Asia/Karachi",
    "iso:country":"PK",
    "wof:name":"Kinari",
    "wof:placetype":"locality"
},
  "geometry": {"coordinates":[73.50905,34.80562],"type":"Point"}
}