{
  "type": "Feature",
  "properties": {
    "gn:admin1_code":"7",
    "gn:asciiname":"Bielargo",
    "gn:country_code":"PK",
    "gn:dem":2587,
    "gn:feature_class":"P",
    "gn:feature_code":"PPL",
    "gn:name":"Bielargo",
    "gn:population":0,
    "gn:timezone":"Asia/Karachi",
    "iso:country":"PK",
    "wof:name":"Bielargo",
    "wof:placetype":"locality"
},
  "geometry": {"coordinates":[76.15816,34.6822],"type":"Point"}
}