{
  "type": "Feature",
  "properties": {
    "gn:admin1_code":"4.0",
    "gn:asciiname":"Basti Malik Pervaz",
    "gn:country_code":"PK",
    "gn:dem":97,
    "gn:feature_class":"P",
    "gn:feature_code":"PPL",
    "gn:name":"Basti Malik Pervaz",
    "gn:population":0,
    "gn:timezone":"Asia/Karachi",
    "iso:country":"PK",
    "name:und_x_variant":[
        "Basti Missan"
    ],
    "wof:name":"Basti Malik Pervaz",
    "wof:placetype":"locality"
},
  "geometry": {"coordinates":[70.93616,29.07089],"type":"Point"}
}