{
  "type": "Feature",
  "properties": {
    "gn:admin1_code":"05",
    "gn:asciiname":"Yusuf Barro",
    "gn:country_code":"PK",
    "gn:dem":250,
    "gn:feature_class":"P",
    "gn:feature_code":"PPL",
    "gn:name":"Yusuf Barro",
    "gn:population":0,
    "gn:timezone":"Asia/Karachi",
    "iso:country":"PK",
    "name:und_x_variant":[
        "Y\u016bsif Barro",
        "Yusuf Barro"
    ],
    "wof:name":"Yusuf Barro",
    "wof:placetype":"locality"
},
  "geometry": {"coordinates":[67.25818000000001,25.22677],"type":"Point"}
}