{
  "type": "Feature",
  "properties": {
    "gn:admin1_code":"4",
    "gn:asciiname":"Bhandgiran",
    "gn:country_code":"PK",
    "gn:dem":293,
    "gn:feature_class":"P",
    "gn:feature_code":"PPL",
    "gn:name":"Bhandgiran",
    "gn:population":0,
    "gn:timezone":"Asia/Karachi",
    "iso:country":"PK",
    "wof:name":"Bhandgiran",
    "wof:placetype":"locality"
},
  "geometry": {"coordinates":[74.02566,32.84389],"type":"Point"}
}