{
  "type": "Feature",
  "properties": {
    "gn:admin1_code":"4",
    "gn:asciiname":"Todowala Khu",
    "gn:country_code":"PK",
    "gn:dem":133,
    "gn:feature_class":"P",
    "gn:feature_code":"PPL",
    "gn:name":"Todowala Khu",
    "gn:population":0,
    "gn:timezone":"Asia/Karachi",
    "iso:country":"PK",
    "name:und_x_variant":[
        "Todow\u0101la Kh\u016bh"
    ],
    "wof:name":"Todowala Khu",
    "wof:placetype":"locality"
},
  "geometry": {"coordinates":[72.38076,29.66046],"type":"Point"}
}