{
  "type": "Feature",
  "properties": {
    "gn:admin1_code":"4.0",
    "gn:asciiname":"Wari",
    "gn:country_code":"PK",
    "gn:dem":484,
    "gn:feature_class":"P",
    "gn:feature_code":"PPL",
    "gn:name":"Wari",
    "gn:population":0,
    "gn:timezone":"Asia/Karachi",
    "iso:country":"PK",
    "name:eng_x_preferred":[
        "Wari"
    ],
    "wof:name":"Wari",
    "wof:placetype":"locality"
},
  "geometry": {"coordinates":[72.69237,33.01375],"type":"Point"}
}