{
  "type": "Feature",
  "properties": {
    "gn:admin1_code":"2.0",
    "gn:asciiname":"Zargun Ghar Kili Sardar Sawal Khan",
    "gn:country_code":"PK",
    "gn:dem":2174,
    "gn:feature_class":"P",
    "gn:feature_code":"PPL",
    "gn:name":"Zargun Ghar Kili Sardar Sawal Khan",
    "gn:population":0,
    "gn:timezone":"Asia/Karachi",
    "iso:country":"PK",
    "wof:name":"Zargun Ghar Kili Sardar Sawal Khan",
    "wof:placetype":"locality"
},
  "geometry": {"coordinates":[67.34966999999999,30.30474],"type":"Point"}
}