{
  "type": "Feature",
  "properties": {
    "gn:admin1_code":"1.0",
    "gn:asciiname":"Maikai Kalle",
    "gn:country_code":"PK",
    "gn:dem":2347,
    "gn:feature_class":"P",
    "gn:feature_code":"PPL",
    "gn:name":"Maikai Kalle",
    "gn:population":0,
    "gn:timezone":"Asia/Karachi",
    "iso:country":"PK",
    "name:und_x_variant":[
        "Maikai Kili"
    ],
    "wof:name":"Maikai Kalle",
    "wof:placetype":"locality"
},
  "geometry": {"coordinates":[70.10708000000001,33.95463],"type":"Point"}
}