{
  "type": "Feature",
  "properties": {
    "gn:admin1_code":"03",
    "gn:asciiname":"Samandi",
    "gn:country_code":"PK",
    "gn:dem":378,
    "gn:feature_class":"P",
    "gn:feature_code":"PPL",
    "gn:name":"Samandi",
    "gn:population":0,
    "gn:timezone":"Asia/Karachi",
    "iso:country":"PK",
    "name:fas_x_preferred":[
        "\u0633\u0645\u0646\u062f\u06cc"
    ],
    "name:urd_x_preferred":[
        "\u0633\u0645\u0646\u062f\u06cc"
    ],
    "wof:name":"Samandi",
    "wof:placetype":"locality"
},
  "geometry": {"coordinates":[70.52049,32.62116],"type":"Point"}
}