{
  "type": "Feature",
  "properties": {
    "gn:admin1_code":"4",
    "gn:asciiname":"Chak Six Hundred Thirty-seven Thal Development Authority",
    "gn:country_code":"PK",
    "gn:dem":136,
    "gn:feature_class":"P",
    "gn:feature_code":"PPL",
    "gn:name":"Chak Six Hundred Thirty-seven Thal Development Authority",
    "gn:population":0,
    "gn:timezone":"Asia/Karachi",
    "iso:country":"PK",
    "name:und_x_variant":[
        "Chak Six Hundred Thirty-Seven TDA",
        "Moh\u0101n\u0101w\u0101la",
        "Chak 637 TDA",
        "Chak Six Hundred Thirty-seven Thal Development Authority"
    ],
    "wof:name":"Chak Six Hundred Thirty-seven Thal Development Authority",
    "wof:placetype":"locality"
},
  "geometry": {"coordinates":[71.30249000000001,30.65693],"type":"Point"}
}