{
  "type": "Feature",
  "properties": {
    "gn:admin1_code":"4",
    "gn:asciiname":"Chak Kumhariwala",
    "gn:country_code":"PK",
    "gn:dem":170,
    "gn:feature_class":"P",
    "gn:feature_code":"PPL",
    "gn:name":"Chak Kumhariwala",
    "gn:population":0,
    "gn:timezone":"Asia/Karachi",
    "iso:country":"PK",
    "name:und_x_variant":[
        "Kumh\u0101r\u012bw\u0101la"
    ],
    "wof:name":"Chak Kumhariwala",
    "wof:placetype":"locality"
},
  "geometry": {"coordinates":[73.49603,30.37765],"type":"Point"}
}