{
  "type": "Feature",
  "properties": {
    "gn:admin1_code":"4",
    "gn:asciiname":"Sumandari",
    "gn:country_code":"PK",
    "gn:dem":117,
    "gn:feature_class":"P",
    "gn:feature_code":"PPL",
    "gn:name":"Sumandari",
    "gn:population":0,
    "gn:timezone":"Asia/Karachi",
    "iso:country":"PK",
    "name:und_x_variant":[
        "Bush\u0101ratpur",
        "Bush\u0101ratw\u0101la"
    ],
    "wof:name":"Sumandari",
    "wof:placetype":"locality"
},
  "geometry": {"coordinates":[70.74821999999998,29.88965],"type":"Point"}
}