{
  "type": "Feature",
  "properties": {
    "gn:admin1_code":"4.0",
    "gn:asciiname":"Thatta Salimka",
    "gn:country_code":"PK",
    "gn:dem":181,
    "gn:feature_class":"P",
    "gn:feature_code":"PPL",
    "gn:name":"Thatta Salimka",
    "gn:population":0,
    "gn:timezone":"Asia/Karachi",
    "iso:country":"PK",
    "name:und_x_variant":[
        "Sal\u012bmke"
    ],
    "wof:name":"Thatta Salimka",
    "wof:placetype":"locality"
},
  "geometry": {"coordinates":[73.40201999999999,30.98846],"type":"Point"}
}