{
  "type": "Feature",
  "properties": {
    "gn:admin1_code":"4",
    "gn:asciiname":"Malkan",
    "gn:country_code":"PK",
    "gn:dem":107,
    "gn:feature_class":"P",
    "gn:feature_code":"PPL",
    "gn:name":"Malkan",
    "gn:population":0,
    "gn:timezone":"Asia/Karachi",
    "iso:country":"PK",
    "name:und_x_variant":[
        "Malka"
    ],
    "wof:name":"Malkan",
    "wof:placetype":"locality"
},
  "geometry": {"coordinates":[71.10234,29.5022],"type":"Point"}
}