{
  "type": "Feature",
  "properties": {
    "gn:admin1_code":"2.0",
    "gn:asciiname":"Kili Takri Qadir Bakhsh",
    "gn:country_code":"PK",
    "gn:dem":1251,
    "gn:feature_class":"P",
    "gn:feature_code":"PPL",
    "gn:name":"Kili Takri Qadir Bakhsh",
    "gn:population":0,
    "gn:timezone":"Asia/Karachi",
    "iso:country":"PK",
    "wof:name":"Kili Takri Qadir Bakhsh",
    "wof:placetype":"locality"
},
  "geometry": {"coordinates":[66.23156,27.20083],"type":"Point"}
}