{
  "type": "Feature",
  "properties": {
    "gn:admin1_code":"5.0",
    "gn:asciiname":"Ghulam Hussain",
    "gn:country_code":"PK",
    "gn:dem":76,
    "gn:feature_class":"P",
    "gn:feature_code":"PPL",
    "gn:name":"Ghulam Hussain",
    "gn:population":0,
    "gn:timezone":"Asia/Karachi",
    "iso:country":"PK",
    "name:urd_x_preferred":[
        "\u063a\u0644\u0627\u0645 \u062d\u0633\u06cc\u0646"
    ],
    "wof:name":"Ghulam Hussain",
    "wof:placetype":"locality"
},
  "geometry": {"coordinates":[69.53368,28.49312],"type":"Point"}
}