{
  "type": "Feature",
  "properties": {
    "gn:admin1_code":"4.0",
    "gn:asciiname":"Damra Janubi",
    "gn:country_code":"PK",
    "gn:dem":159,
    "gn:feature_class":"P",
    "gn:feature_code":"PPL",
    "gn:name":"Damra Janubi",
    "gn:population":0,
    "gn:timezone":"Asia/Karachi",
    "iso:country":"PK",
    "name:und_x_variant":[
        "Domra Jan\u016bbi"
    ],
    "wof:name":"Damra Janubi",
    "wof:placetype":"locality"
},
  "geometry": {"coordinates":[70.68333,30.73333],"type":"Point"}
}