{
  "type": "Feature",
  "properties": {
    "gn:admin1_code":"1.0",
    "gn:asciiname":"Manduna Kai",
    "gn:country_code":"PK",
    "gn:dem":2473,
    "gn:feature_class":"P",
    "gn:feature_code":"PPL",
    "gn:name":"Manduna Kai",
    "gn:population":0,
    "gn:timezone":"Asia/Karachi",
    "iso:country":"PK",
    "wof:name":"Manduna Kai",
    "wof:placetype":"locality"
},
  "geometry": {"coordinates":[69.65436,32.66947],"type":"Point"}
}