{
  "type": "Feature",
  "properties": {
    "gn:admin1_code":"7.0",
    "gn:asciiname":"Darkali",
    "gn:country_code":"PK",
    "gn:dem":1882,
    "gn:feature_class":"P",
    "gn:feature_code":"PPL",
    "gn:name":"Darkali",
    "gn:population":0,
    "gn:timezone":"Asia/Karachi",
    "iso:country":"PK",
    "wof:name":"Darkali",
    "wof:placetype":"locality"
},
  "geometry": {"coordinates":[73.43989000000001,35.67427],"type":"Point"}
}