{
  "type": "Feature",
  "properties": {
    "gn:admin1_code":"2.0",
    "gn:asciiname":"Naya Karez",
    "gn:country_code":"PK",
    "gn:dem":1990,
    "gn:feature_class":"P",
    "gn:feature_code":"PPL",
    "gn:name":"Naya Karez",
    "gn:population":0,
    "gn:timezone":"Asia/Karachi",
    "iso:country":"PK",
    "wof:name":"Naya Karez",
    "wof:placetype":"locality"
},
  "geometry": {"coordinates":[67.35195,30.66464],"type":"Point"}
}