{
  "type": "Feature",
  "properties": {
    "gn:admin1_code":"2.0",
    "gn:asciiname":"Kili Khadim",
    "gn:country_code":"PK",
    "gn:dem":1873,
    "gn:feature_class":"P",
    "gn:feature_code":"PPL",
    "gn:name":"Kili Khadim",
    "gn:population":0,
    "gn:timezone":"Asia/Karachi",
    "iso:country":"PK",
    "wof:name":"Kili Khadim",
    "wof:placetype":"locality"
},
  "geometry": {"coordinates":[66.43725999999999,30.70237],"type":"Point"}
}