{
  "type": "Feature",
  "properties": {
    "gn:admin1_code":"2.0",
    "gn:asciiname":"Chibi",
    "gn:country_code":"PK",
    "gn:dem":29,
    "gn:feature_class":"P",
    "gn:feature_code":"PPL",
    "gn:name":"Chibi",
    "gn:population":0,
    "gn:timezone":"Asia/Karachi",
    "iso:country":"PK",
    "name:bar_x_preferred":[
        "Chibi"
    ],
    "name:ceb_x_preferred":[
        "Chibi Shi"
    ],
    "name:deu_x_preferred":[
        "Chibi"
    ],
    "name:fas_x_preferred":[
        "\u0686\u06cc\u0628\u06cc \u0633\u06cc\u062a\u06cc"
    ],
    "name:fra_x_preferred":[
        "Chibi"
    ],
    "name:ind_x_preferred":[
        "Kota Chibi"
    ],
    "name:ita_x_preferred":[
        "Chibi"
    ],
    "name:jpn_x_preferred":[
        "\u8d64\u58c1\u5e02"
    ],
    "name:kik_x_preferred":[
        "Chibi City"
    ],
    "name:kor_x_preferred":[
        "\uce20\ube44\uc2dc"
    ],
    "name:mlg_x_preferred":[
        "Chibi City"
    ],
    "name:nld_x_preferred":[
        "Chibi"
    ],
    "name:nor_x_preferred":[
        "Chibi"
    ],
    "name:pam_x_preferred":[
        "Chibi Lakanbalen"
    ],
    "name:rus_x_preferred":[
        "\u0427\u0438\u0431\u0438"
    ],
    "name:swe_x_preferred":[
        "Chibi"
    ],
    "name:tur_x_preferred":[
        "Chibi"
    ],
    "name:und_x_variant":[
        "Chib"
    ],
    "name:vie_x_preferred":[
        "X\u00edch B\u00edch"
    ],
    "name:war_x_preferred":[
        "Chibi"
    ],
    "name:zho_x_preferred":[
        "\u8d64\u58c1\u5e02"
    ],
    "wof:name":"Chibi",
    "wof:placetype":"locality"
},
  "geometry": {"coordinates":[62.4363,25.35046],"type":"Point"}
}