{
  "type": "Feature",
  "properties": {
    "iso:country":"PK",
    "name:ast_x_preferred":[
        "Radhan"
    ],
    "name:eng_x_preferred":[
        "Radhan"
    ],
    "name:nld_x_preferred":[
        "Radhan"
    ],
    "name:spa_x_preferred":[
        "Radhan"
    ],
    "name:und_x_variant":[
        "Goth R\u0101dhan"
    ],
    "qs:gn_country":"PK",
    "qs:gn_fcode":"PPL",
    "qs:gn_pop":16786,
    "qs:name":"Radhan",
    "qs:name_adm0":"Pakistan",
    "qs:name_adm1":"Sindh",
    "qs:photos":0,
    "qs:photos_1k":0,
    "qs:photos_9k":0,
    "qs:photos_9r":0,
    "qs:photos_all":0,
    "qs:photos_sr":0,
    "qs:placetype":"Town",
    "qs:pop_sr":"6",
    "qs:woe_adm0":23424922,
    "wd:wordcount":329,
    "wof:name":"Radhan",
    "wof:placetype":"locality",
    "wof:population":16786
},
  "geometry": {"coordinates":[67.95,27.18333],"type":"Point"}
}