{
  "type": "Feature",
  "properties": {
    "gn:admin1_code":"6",
    "gn:asciiname":"Palal Kalan",
    "gn:country_code":"PK",
    "gn:dem":784,
    "gn:feature_class":"P",
    "gn:feature_code":"PPL",
    "gn:name":"Palal Kalan",
    "gn:population":0,
    "gn:timezone":"Asia/Karachi",
    "iso:country":"PK",
    "name:und_x_variant":[
        "Pal\u0101hal Kal\u0101n"
    ],
    "wof:name":"Palal Kalan",
    "wof:placetype":"locality"
},
  "geometry": {"coordinates":[73.89831,33.25443],"type":"Point"}
}