{
  "type": "Feature",
  "properties": {
    "gn:admin1_code":"3.0",
    "gn:asciiname":"Lolgram",
    "gn:country_code":"PK",
    "gn:dem":2890,
    "gn:feature_class":"P",
    "gn:feature_code":"PPL",
    "gn:name":"Lolgram",
    "gn:population":0,
    "gn:timezone":"Asia/Karachi",
    "iso:country":"PK",
    "wof:name":"Lolgram",
    "wof:placetype":"locality"
},
  "geometry": {"coordinates":[71.82408000000002,36.07157],"type":"Point"}
}