{
  "type": "Feature",
  "properties": {
    "gn:admin1_code":"3.0",
    "gn:asciiname":"Birth Khel",
    "gn:country_code":"PK",
    "gn:dem":319,
    "gn:feature_class":"P",
    "gn:feature_code":"PPL",
    "gn:name":"Birth Khel",
    "gn:population":0,
    "gn:timezone":"Asia/Karachi",
    "iso:country":"PK",
    "name:und_x_variant":[
        "Barath Khel"
    ],
    "wof:name":"Birth Khel",
    "wof:placetype":"locality"
},
  "geometry": {"coordinates":[70.964,32.74029],"type":"Point"}
}