{
  "type": "Feature",
  "properties": {
    "gn:admin1_code":"1.0",
    "gn:asciiname":"Kajir Kot",
    "gn:country_code":"PK",
    "gn:dem":717,
    "gn:feature_class":"P",
    "gn:feature_code":"PPL",
    "gn:name":"Kajir Kot",
    "gn:population":0,
    "gn:timezone":"Asia/Karachi",
    "iso:country":"PK",
    "name:und_x_variant":[
        "Salai"
    ],
    "wof:name":"Kajir Kot",
    "wof:placetype":"locality"
},
  "geometry": {"coordinates":[70.24134000000001,32.97855999999999],"type":"Point"}
}