{
  "type": "Feature",
  "properties": {
    "gn:admin1_code":"2",
    "gn:asciiname":"Kili Sher Khan",
    "gn:country_code":"PK",
    "gn:dem":1180,
    "gn:feature_class":"P",
    "gn:feature_code":"PPL",
    "gn:name":"Kili Sher Khan",
    "gn:population":0,
    "gn:timezone":"Asia/Karachi",
    "iso:country":"PK",
    "name:und_x_variant":[
        "Mir Hasan"
    ],
    "wof:name":"Kili Sher Khan",
    "wof:placetype":"locality"
},
  "geometry": {"coordinates":[69.23923000000001,30.34679],"type":"Point"}
}