{
  "type": "Feature",
  "properties": {
    "gn:admin1_code":"4.0",
    "gn:asciiname":"Depoke",
    "gn:country_code":"PK",
    "gn:dem":253,
    "gn:feature_class":"P",
    "gn:feature_code":"PPL",
    "gn:name":"Depoke",
    "gn:population":0,
    "gn:timezone":"Asia/Karachi",
    "iso:country":"PK",
    "name:fas_x_preferred":[
        "\u062f\u06cc\u067e\u0648\u06a9\u0647"
    ],
    "name:und_x_variant":[
        "Dipu Ke",
        "Depoke"
    ],
    "wof:name":"Depoke",
    "wof:placetype":"locality"
},
  "geometry": {"coordinates":[74.83561999999998,32.25792],"type":"Point"}
}