{
  "type": "Feature",
  "properties": {
    "gn:admin1_code":"04",
    "gn:asciiname":"Kot Fazaldad Khan",
    "gn:cc2":"PK",
    "gn:country_code":"PK",
    "gn:dem":173,
    "gn:feature_class":"P",
    "gn:feature_code":"PPL",
    "gn:name":"Kot Fazald\u0101d Kh\u0101n",
    "gn:population":0,
    "gn:timezone":"Asia/Karachi",
    "iso:country":"PK",
    "name:und_x_variant":[
        "Kot Fazld\u0101d Kh\u0101n",
        "Kot Fazald\u0101d Kh\u0101n"
    ],
    "wof:name":"Kot Fazaldad Khan",
    "wof:placetype":"locality"
},
  "geometry": {"coordinates":[73.21666999999999,30.68333],"type":"Point"}
}