{
  "type": "Feature",
  "properties": {
    "gn:admin1_code":"4.0",
    "gn:asciiname":"Berera",
    "gn:country_code":"PK",
    "gn:dem":267,
    "gn:feature_class":"P",
    "gn:feature_code":"PPL",
    "gn:name":"Berera",
    "gn:population":0,
    "gn:timezone":"Asia/Karachi",
    "iso:country":"PK",
    "wof:name":"Berera",
    "wof:placetype":"locality"
},
  "geometry": {"coordinates":[71.81998,33.02114],"type":"Point"}
}