{
  "type": "Feature",
  "properties": {
    "gn:admin1_code":"4",
    "gn:asciiname":"Chak Forty-Four M",
    "gn:country_code":"PK",
    "gn:dem":120,
    "gn:feature_class":"P",
    "gn:feature_code":"PPL",
    "gn:name":"Chak Forty-Four M",
    "gn:population":0,
    "gn:timezone":"Asia/Karachi",
    "iso:country":"PK",
    "name:und_x_variant":[
        "Chak 44 M"
    ],
    "wof:name":"Chak Forty-Four M",
    "wof:placetype":"locality"
},
  "geometry": {"coordinates":[71.61306,29.71178],"type":"Point"}
}