{
  "type": "Feature",
  "properties": {
    "gn:admin1_code":"5",
    "gn:asciiname":"Manga jo Goth",
    "gn:country_code":"PK",
    "gn:dem":62,
    "gn:feature_class":"P",
    "gn:feature_code":"PPL",
    "gn:name":"Manga jo Goth",
    "gn:population":0,
    "gn:timezone":"Asia/Karachi",
    "iso:country":"PK",
    "name:und_x_variant":[
        "Manga jo"
    ],
    "wof:name":"Manga jo Goth",
    "wof:placetype":"locality"
},
  "geometry": {"coordinates":[68.79434000000001,27.6994],"type":"Point"}
}