{
  "type": "Feature",
  "properties": {
    "gn:admin1_code":"1",
    "gn:asciiname":"Ayip",
    "gn:country_code":"PK",
    "gn:dem":1452,
    "gn:feature_class":"P",
    "gn:feature_code":"PPL",
    "gn:name":"Ayip",
    "gn:population":0,
    "gn:timezone":"Asia/Karachi",
    "iso:country":"PK",
    "name:und_x_variant":[
        "Ay\u012bp Khel"
    ],
    "wof:name":"Ayip",
    "wof:placetype":"locality"
},
  "geometry": {"coordinates":[69.93316,32.50417],"type":"Point"}
}