{
  "type": "Feature",
  "properties": {
    "gn:admin1_code":"4",
    "gn:asciiname":"Khot Khurd",
    "gn:country_code":"PK",
    "gn:dem":220,
    "gn:feature_class":"P",
    "gn:feature_code":"PPL",
    "gn:name":"Khot Khurd",
    "gn:population":0,
    "gn:timezone":"Asia/Karachi",
    "iso:country":"PK",
    "name:und_x_variant":[
        "Hardo Khoth"
    ],
    "wof:name":"Khot Khurd",
    "wof:placetype":"locality"
},
  "geometry": {"coordinates":[74.212,32.00474000000001],"type":"Point"}
}