{
  "type": "Feature",
  "properties": {
    "gn:admin1_code":"3.0",
    "gn:asciiname":"Kohala Moolia",
    "gn:country_code":"PK",
    "gn:dem":948,
    "gn:feature_class":"P",
    "gn:feature_code":"PPL",
    "gn:name":"Kohala Moolia",
    "gn:population":0,
    "gn:timezone":"Asia/Karachi",
    "iso:country":"PK",
    "wof:name":"Kohala Moolia",
    "wof:placetype":"locality"
},
  "geometry": {"coordinates":[73.48198000000002,34.14823],"type":"Point"}
}