{
  "type": "Feature",
  "properties": {
    "gn:admin1_code":"4.0",
    "gn:asciiname":"Salikabad",
    "gn:country_code":"PK",
    "gn:dem":413,
    "gn:feature_class":"P",
    "gn:feature_code":"PPL",
    "gn:name":"Salikabad",
    "gn:population":0,
    "gn:timezone":"Asia/Karachi",
    "iso:country":"PK",
    "wof:name":"Salikabad",
    "wof:placetype":"locality"
},
  "geometry": {"coordinates":[72.71998000000001,33.86054],"type":"Point"}
}