{
  "type": "Feature",
  "properties": {
    "gn:admin1_code":"4",
    "gn:asciiname":"Khingrawala",
    "gn:country_code":"PK",
    "gn:dem":184,
    "gn:feature_class":"P",
    "gn:feature_code":"PPL",
    "gn:name":"Khingrawala",
    "gn:population":0,
    "gn:timezone":"Asia/Karachi",
    "iso:country":"PK",
    "name:und_x_variant":[
        "Khangr\u0101nw\u0101la",
        "Sodhiw\u0101la",
        "Khingrawala"
    ],
    "wof:name":"Khingrawala",
    "wof:placetype":"locality"
},
  "geometry": {"coordinates":[73.99722,30.72798],"type":"Point"}
}