{
  "type": "Feature",
  "properties": {
    "gn:admin1_code":"4",
    "gn:asciiname":"Partali Khurd",
    "gn:country_code":"PK",
    "gn:dem":532,
    "gn:feature_class":"P",
    "gn:feature_code":"PPL",
    "gn:name":"Partali Khurd",
    "gn:population":0,
    "gn:timezone":"Asia/Karachi",
    "iso:country":"PK",
    "name:und_x_variant":[
        "Part\u0101li Kal\u0101n"
    ],
    "wof:name":"Partali Khurd",
    "wof:placetype":"locality"
},
  "geometry": {"coordinates":[73.19331,33.20497],"type":"Point"}
}