{
  "type": "Feature",
  "properties": {
    "gn:admin1_code":"3.0",
    "gn:asciiname":"Sigel Kan",
    "gn:country_code":"PK",
    "gn:dem":1174,
    "gn:feature_class":"P",
    "gn:feature_code":"PPL",
    "gn:name":"Sigel Kan",
    "gn:population":0,
    "gn:timezone":"Asia/Karachi",
    "iso:country":"PK",
    "wof:name":"Sigel Kan",
    "wof:placetype":"locality"
},
  "geometry": {"coordinates":[73.05593,35.11498],"type":"Point"}
}