{
  "type": "Feature",
  "properties": {
    "gn:admin1_code":"4",
    "gn:asciiname":"Basti Jandwali",
    "gn:country_code":"PK",
    "gn:dem":143,
    "gn:feature_class":"P",
    "gn:feature_code":"PPL",
    "gn:name":"Basti Jandwali",
    "gn:population":0,
    "gn:timezone":"Asia/Karachi",
    "iso:country":"PK",
    "name:und_x_variant":[
        "Jandw\u0101la"
    ],
    "wof:name":"Basti Jandwali",
    "wof:placetype":"locality"
},
  "geometry": {"coordinates":[72.14353,30.90717],"type":"Point"}
}