{
  "type": "Feature",
  "properties": {
    "gn:admin1_code":"3",
    "gn:asciiname":"Karkabanj",
    "gn:country_code":"PK",
    "gn:dem":1747,
    "gn:feature_class":"P",
    "gn:feature_code":"PPL",
    "gn:name":"Karkabanj",
    "gn:population":0,
    "gn:timezone":"Asia/Karachi",
    "iso:country":"PK",
    "name:und_x_variant":[
        "K\u0101k\u0101banj"
    ],
    "wof:name":"Karkabanj",
    "wof:placetype":"locality"
},
  "geometry": {"coordinates":[72.09259,34.91372],"type":"Point"}
}