{
  "type": "Feature",
  "properties": {
    "gn:admin1_code":"2.0",
    "gn:asciiname":"Malik Amir Kili",
    "gn:country_code":"PK",
    "gn:dem":1569,
    "gn:feature_class":"P",
    "gn:feature_code":"PPL",
    "gn:name":"Malik Amir Kili",
    "gn:population":0,
    "gn:timezone":"Asia/Karachi",
    "iso:country":"PK",
    "wof:name":"Malik Amir Kili",
    "wof:placetype":"locality"
},
  "geometry": {"coordinates":[68.26109,30.77169],"type":"Point"}
}