{
  "type": "Feature",
  "properties": {
    "gn:admin1_code":"4.0",
    "gn:asciiname":"Dera Jutianwala",
    "gn:country_code":"PK",
    "gn:dem":153,
    "gn:feature_class":"P",
    "gn:feature_code":"PPL",
    "gn:name":"Dera Jutianwala",
    "gn:population":0,
    "gn:timezone":"Asia/Karachi",
    "iso:country":"PK",
    "name:und_x_variant":[
        "Bela Juti\u0101nw\u0101la"
    ],
    "wof:name":"Dera Jutianwala",
    "wof:placetype":"locality"
},
  "geometry": {"coordinates":[72.15183,31.20535],"type":"Point"}
}