{
  "type": "Feature",
  "properties": {
    "gn:admin1_code":"4.0",
    "gn:asciiname":"Chak Two Hundred Eight - Nine Right",
    "gn:country_code":"PK",
    "gn:dem":150,
    "gn:feature_class":"P",
    "gn:feature_code":"PPL",
    "gn:name":"Chak Two Hundred Eight - Nine Right",
    "gn:population":0,
    "gn:timezone":"Asia/Karachi",
    "iso:country":"PK",
    "name:und_x_variant":[
        "Shum\u0101li"
    ],
    "wof:name":"Chak Two Hundred Eight - Nine Right",
    "wof:placetype":"locality"
},
  "geometry": {"coordinates":[72.9979,29.30512],"type":"Point"}
}