{
  "type": "Feature",
  "properties": {
    "gn:admin1_code":"02",
    "gn:asciiname":"Nathwani",
    "gn:country_code":"PK",
    "gn:dem":1378,
    "gn:feature_class":"P",
    "gn:feature_code":"PPL",
    "gn:name":"Nathwani",
    "gn:population":0,
    "gn:timezone":"Asia/Karachi",
    "iso:country":"PK",
    "name:und_x_variant":[
        "Natwan",
        "Natw\u0101ni"
    ],
    "wof:name":"Nathwani",
    "wof:placetype":"locality"
},
  "geometry": {"coordinates":[66.58976,27.98492],"type":"Point"}
}