{
  "type": "Feature",
  "properties": {
    "gn:admin1_code":"4.0",
    "gn:asciiname":"Chak Twenty-nine Ghagh",
    "gn:country_code":"PK",
    "gn:dem":139,
    "gn:feature_class":"P",
    "gn:feature_code":"PPL",
    "gn:name":"Chak Twenty-nine Ghagh",
    "gn:population":0,
    "gn:timezone":"Asia/Karachi",
    "iso:country":"PK",
    "wof:name":"Chak Twenty-nine Ghagh",
    "wof:placetype":"locality"
},
  "geometry": {"coordinates":[72.14168000000002,30.72717],"type":"Point"}
}