{
  "type": "Feature",
  "properties": {
    "gn:admin1_code":"3",
    "gn:asciiname":"Narauk",
    "gn:country_code":"PK",
    "gn:dem":1972,
    "gn:feature_class":"P",
    "gn:feature_code":"PPL",
    "gn:name":"Narauk",
    "gn:population":0,
    "gn:timezone":"Asia/Karachi",
    "iso:country":"PK",
    "name:und_x_variant":[
        "Narsuk"
    ],
    "wof:name":"Narauk",
    "wof:placetype":"locality"
},
  "geometry": {"coordinates":[73.10420000000001,34.87016],"type":"Point"}
}