{
  "type": "Feature",
  "properties": {
    "gn:admin1_code":"2.0",
    "gn:asciiname":"Kili Anjuman",
    "gn:country_code":"PK",
    "gn:dem":2046,
    "gn:feature_class":"P",
    "gn:feature_code":"PPL",
    "gn:name":"Kili Anjuman",
    "gn:population":0,
    "gn:timezone":"Asia/Karachi",
    "iso:country":"PK",
    "wof:name":"Kili Anjuman",
    "wof:placetype":"locality"
},
  "geometry": {"coordinates":[67.22875000000001,30.05371],"type":"Point"}
}