{
  "type": "Feature",
  "properties": {
    "gn:admin1_code":"4.0",
    "gn:asciiname":"Hasseki",
    "gn:country_code":"PK",
    "gn:dem":197,
    "gn:feature_class":"P",
    "gn:feature_code":"PPL",
    "gn:name":"Hasseki",
    "gn:population":0,
    "gn:timezone":"Asia/Karachi",
    "iso:country":"PK",
    "name:und_x_variant":[
        "Huseke"
    ],
    "wof:name":"Hasseki",
    "wof:placetype":"locality"
},
  "geometry": {"coordinates":[73.38383,31.93219],"type":"Point"}
}