{
  "type": "Feature",
  "properties": {
    "gn:admin1_code":"2",
    "gn:asciiname":"Adhga Haidera",
    "gn:country_code":"PK",
    "gn:dem":1597,
    "gn:feature_class":"P",
    "gn:feature_code":"PPL",
    "gn:name":"Adhga Haidera",
    "gn:population":0,
    "gn:timezone":"Asia/Karachi",
    "iso:country":"PK",
    "name:und_x_variant":[
        "Adaga Hadira"
    ],
    "wof:name":"Adhga Haidera",
    "wof:placetype":"locality"
},
  "geometry": {"coordinates":[69.50553000000001,30.79248],"type":"Point"}
}