{
  "type": "Feature",
  "properties": {
    "gn:admin1_code":"6.0",
    "gn:asciiname":"Kuhi",
    "gn:country_code":"PK",
    "gn:dem":1085,
    "gn:feature_class":"P",
    "gn:feature_code":"PPL",
    "gn:name":"Kuhi",
    "gn:population":0,
    "gn:timezone":"Asia/Karachi",
    "iso:country":"PK",
    "wof:name":"Kuhi",
    "wof:placetype":"locality"
},
  "geometry": {"coordinates":[73.68847,33.79362],"type":"Point"}
}