{
  "type": "Feature",
  "properties": {
    "gn:admin1_code":"3",
    "gn:asciiname":"Sukaili",
    "gn:country_code":"PK",
    "gn:dem":813,
    "gn:feature_class":"P",
    "gn:feature_code":"PPL",
    "gn:name":"Sukaili",
    "gn:population":0,
    "gn:timezone":"Asia/Karachi",
    "iso:country":"PK",
    "wof:name":"Sukaili",
    "wof:placetype":"locality"
},
  "geometry": {"coordinates":[72.66873000000002,34.22119],"type":"Point"}
}