{
  "type": "Feature",
  "properties": {
    "gn:admin1_code":"4",
    "gn:asciiname":"Fathewala",
    "gn:country_code":"PK",
    "gn:dem":138,
    "gn:feature_class":"P",
    "gn:feature_code":"PPL",
    "gn:name":"Fathewala",
    "gn:population":0,
    "gn:timezone":"Asia/Karachi",
    "iso:country":"PK",
    "name:und_x_variant":[
        "Fatehw\u0101la"
    ],
    "wof:name":"Fathewala",
    "wof:placetype":"locality"
},
  "geometry": {"coordinates":[71.47065000000001,30.77984],"type":"Point"}
}