{
  "type": "Feature",
  "properties": {
    "gn:admin1_code":"3",
    "gn:asciiname":"Koliga",
    "gn:country_code":"PK",
    "gn:dem":1358,
    "gn:feature_class":"P",
    "gn:feature_code":"PPL",
    "gn:name":"Koliga",
    "gn:population":0,
    "gn:timezone":"Asia/Karachi",
    "iso:country":"PK",
    "name:eng_x_preferred":[
        "Koligol"
    ],
    "wof:name":"Koliga",
    "wof:placetype":"locality"
},
  "geometry": {"coordinates":[71.69145999999998,35.40521],"type":"Point"}
}