{
  "type": "Feature",
  "properties": {
    "gn:admin1_code":"4",
    "gn:asciiname":"Saide Khan Gopang",
    "gn:country_code":"PK",
    "gn:dem":88,
    "gn:feature_class":"P",
    "gn:feature_code":"PPL",
    "gn:name":"Saide Kh\u0101n Gop\u0101ng",
    "gn:population":0,
    "gn:timezone":"Asia/Karachi",
    "iso:country":"PK",
    "wof:name":"Saide Khan Gopang",
    "wof:placetype":"locality"
},
  "geometry": {"coordinates":[70.77083,28.8625],"type":"Point"}
}