{
  "type": "Feature",
  "properties": {
    "gn:admin1_code":"3",
    "gn:asciiname":"Kapla",
    "gn:country_code":"PK",
    "gn:dem":1415,
    "gn:feature_class":"P",
    "gn:feature_code":"PPL",
    "gn:name":"Kapla",
    "gn:population":0,
    "gn:timezone":"Asia/Karachi",
    "iso:country":"PK",
    "name:cat_x_preferred":[
        "Kapla"
    ],
    "name:deu_x_preferred":[
        "Kapla"
    ],
    "name:fra_x_preferred":[
        "Kapla"
    ],
    "name:heb_x_preferred":[
        "\u05e7\u05e4\u05dc\u05d4"
    ],
    "name:hun_x_preferred":[
        "Kapla"
    ],
    "name:ita_x_preferred":[
        "Kapla"
    ],
    "name:jpn_x_preferred":[
        "\u30ab\u30d7\u30e9"
    ],
    "name:nld_x_preferred":[
        "Kapla"
    ],
    "name:por_x_preferred":[
        "Kapla"
    ],
    "name:swe_x_preferred":[
        "Kapla"
    ],
    "name:und_x_variant":[
        "Kupla",
        "Kapla"
    ],
    "wof:name":"Kapla",
    "wof:placetype":"locality"
},
  "geometry": {"coordinates":[72.74276,34.30229],"type":"Point"}
}