{
  "type": "Feature",
  "properties": {
    "gn:admin1_code":"3",
    "gn:asciiname":"Qalagai Banda",
    "gn:country_code":"PK",
    "gn:dem":1900,
    "gn:feature_class":"P",
    "gn:feature_code":"PPL",
    "gn:name":"Qalagai Banda",
    "gn:population":0,
    "gn:timezone":"Asia/Karachi",
    "iso:country":"PK",
    "wof:name":"Qalagai Banda",
    "wof:placetype":"locality"
},
  "geometry": {"coordinates":[72.152,34.87832],"type":"Point"}
}