{
  "type": "Feature",
  "properties": {
    "gn:admin1_code":"2.0",
    "gn:asciiname":"Malokar Kili",
    "gn:country_code":"PK",
    "gn:dem":1767,
    "gn:feature_class":"P",
    "gn:feature_code":"PPL",
    "gn:name":"Malokar Kili",
    "gn:population":0,
    "gn:timezone":"Asia/Karachi",
    "iso:country":"PK",
    "name:eng_x_preferred":[
        "Malok\u0101i Kili"
    ],
    "name:und_x_variant":[
        "Malok\u0101i Kili",
        "Malokar Kili"
    ],
    "wof:name":"Malokar Kili",
    "wof:placetype":"locality"
},
  "geometry": {"coordinates":[69.79307,31.56504],"type":"Point"}
}