{
  "type": "Feature",
  "properties": {
    "gn:admin1_code":"07",
    "gn:asciiname":"Sassi",
    "gn:country_code":"PK",
    "gn:dem":1449,
    "gn:feature_class":"P",
    "gn:feature_code":"PPL",
    "gn:name":"Sassi",
    "gn:population":0,
    "gn:timezone":"Asia/Karachi",
    "iso:country":"PK",
    "name:und_x_variant":[
        "Sasli"
    ],
    "wof:name":"Sassi",
    "wof:placetype":"locality"
},
  "geometry": {"coordinates":[74.74072,35.8404],"type":"Point"}
}