{
  "type": "Feature",
  "properties": {
    "gn:admin1_code":"5",
    "gn:asciiname":"Thaba",
    "gn:country_code":"PK",
    "gn:dem":37,
    "gn:feature_class":"P",
    "gn:feature_code":"PPL",
    "gn:name":"Thaba",
    "gn:population":0,
    "gn:timezone":"Asia/Karachi",
    "iso:country":"PK",
    "name:und_x_variant":[
        "Theba"
    ],
    "wof:name":"Thaba",
    "wof:placetype":"locality"
},
  "geometry": {"coordinates":[67.65680999999999,26.5359],"type":"Point"}
}