{
  "type": "Feature",
  "properties": {
    "gn:admin1_code":"5",
    "gn:asciiname":"Nur Muhammad Khaskheli Goth",
    "gn:country_code":"PK",
    "gn:dem":17,
    "gn:feature_class":"P",
    "gn:feature_code":"PPL",
    "gn:name":"N\u016br Muhammad Kh\u0101skheli Goth",
    "gn:population":0,
    "gn:timezone":"Asia/Karachi",
    "iso:country":"PK",
    "wof:name":"Nur Muhammad Khaskheli Goth",
    "wof:placetype":"locality"
},
  "geometry": {"coordinates":[68.77778000000001,25.13611],"type":"Point"}
}