{
  "type": "Feature",
  "properties": {
    "gn:admin1_code":"01",
    "gn:asciiname":"Najim Kot",
    "gn:country_code":"PK",
    "gn:dem":1702,
    "gn:feature_class":"P",
    "gn:feature_code":"PPL",
    "gn:name":"Najim Kot",
    "gn:population":0,
    "gn:timezone":"Asia/Karachi",
    "iso:country":"PK",
    "wof:name":"Najim Kot",
    "wof:placetype":"locality"
},
  "geometry": {"coordinates":[69.68944,32.39444],"type":"Point"}
}