{
  "type": "Feature",
  "properties": {
    "gn:admin1_code":"3.0",
    "gn:asciiname":"Marushaig Goshti",
    "gn:country_code":"PK",
    "gn:dem":3706,
    "gn:feature_class":"P",
    "gn:feature_code":"PPL",
    "gn:name":"Marushaig Goshti",
    "gn:population":0,
    "gn:timezone":"Asia/Karachi",
    "iso:country":"PK",
    "wof:name":"Marushaig Goshti",
    "wof:placetype":"locality"
},
  "geometry": {"coordinates":[71.32695,36.11283],"type":"Point"}
}