{
  "type": "Feature",
  "properties": {
    "gn:admin1_code":"4",
    "gn:asciiname":"Chak Three Hundred Twenty-seven Gugera Branch",
    "gn:country_code":"PK",
    "gn:dem":144,
    "gn:feature_class":"P",
    "gn:feature_code":"PPL",
    "gn:name":"Chak Three Hundred Twenty-seven Gugera Branch",
    "gn:population":0,
    "gn:timezone":"Asia/Karachi",
    "iso:country":"PK",
    "name:und_x_variant":[
        "Chak Three Hundred Twenty-Seven GB",
        "Ladh\u0101i",
        "Chak Three Hundred Twenty-seven Gugera Branch"
    ],
    "wof:name":"Chak Three Hundred Twenty-seven Gugera Branch",
    "wof:placetype":"locality"
},
  "geometry": {"coordinates":[72.25435,30.79878],"type":"Point"}
}