{
  "type": "Feature",
  "properties": {
    "gn:admin1_code":"2.0",
    "gn:asciiname":"Malik Moeen Khan Gis",
    "gn:country_code":"PK",
    "gn:dem":1465,
    "gn:feature_class":"P",
    "gn:feature_code":"PPL",
    "gn:name":"Malik Moeen Khan Gis",
    "gn:population":0,
    "gn:timezone":"Asia/Karachi",
    "iso:country":"PK",
    "wof:name":"Malik Moeen Khan Gis",
    "wof:placetype":"locality"
},
  "geometry": {"coordinates":[63.82286,29.28625],"type":"Point"}
}