{
  "type": "Feature",
  "properties": {
    "gn:admin1_code":"5",
    "gn:asciiname":"Goth Pandhi Chachur",
    "gn:country_code":"PK",
    "gn:dem":10,
    "gn:feature_class":"P",
    "gn:feature_code":"PPL",
    "gn:name":"Goth Pandhi Chachur",
    "gn:population":0,
    "gn:timezone":"Asia/Karachi",
    "iso:country":"PK",
    "name:und_x_variant":[
        "P\u0101nhi Ch\u0101char"
    ],
    "wof:name":"Goth Pandhi Chachur",
    "wof:placetype":"locality"
},
  "geometry": {"coordinates":[69.63464999999999,25.26497],"type":"Point"}
}