{
  "type": "Feature",
  "properties": {
    "gn:admin1_code":"4.0",
    "gn:asciiname":"Chak One Hundred Sixty-eight - Seven Right",
    "gn:country_code":"PK",
    "gn:dem":150,
    "gn:feature_class":"P",
    "gn:feature_code":"PPL",
    "gn:name":"Chak One Hundred Sixty-eight - Seven Right",
    "gn:population":0,
    "gn:timezone":"Asia/Karachi",
    "iso:country":"PK",
    "name:und_x_variant":[
        "Baluch\u0101nw\u0101la"
    ],
    "wof:name":"Chak One Hundred Sixty-eight - Seven Right",
    "wof:placetype":"locality"
},
  "geometry": {"coordinates":[73.04122,29.38923],"type":"Point"}
}