{
  "type": "Feature",
  "properties": {
    "gn:admin1_code":"1.0",
    "gn:asciiname":"Chinarop Piquet",
    "gn:country_code":"PK",
    "gn:dem":723,
    "gn:feature_class":"P",
    "gn:feature_code":"PPL",
    "gn:name":"Chinarop Piquet",
    "gn:population":0,
    "gn:timezone":"Asia/Karachi",
    "iso:country":"PK",
    "wof:name":"Chinarop Piquet",
    "wof:placetype":"locality"
},
  "geometry": {"coordinates":[70.21948,32.98424],"type":"Point"}
}