{
  "type": "Feature",
  "properties": {
    "gn:admin1_code":"2.0",
    "gn:asciiname":"Kili Khair Muhammad",
    "gn:country_code":"PK",
    "gn:dem":1657,
    "gn:feature_class":"P",
    "gn:feature_code":"PPL",
    "gn:name":"Kili Khair Muhammad",
    "gn:population":0,
    "gn:timezone":"Asia/Karachi",
    "iso:country":"PK",
    "wof:name":"Kili Khair Muhammad",
    "wof:placetype":"locality"
},
  "geometry": {"coordinates":[66.46946,28.22162],"type":"Point"}
}