{
  "type": "Feature",
  "properties": {
    "gn:admin1_code":"4",
    "gn:asciiname":"Dhok Loharan",
    "gn:country_code":"PK",
    "gn:dem":651,
    "gn:feature_class":"P",
    "gn:feature_code":"PPL",
    "gn:name":"Dhok Loharan",
    "gn:population":0,
    "gn:timezone":"Asia/Karachi",
    "iso:country":"PK",
    "name:und_x_variant":[
        "Dhok Loh\u0101ra"
    ],
    "wof:name":"Dhok Loharan",
    "wof:placetype":"locality"
},
  "geometry": {"coordinates":[73.19944,32.76750999999999],"type":"Point"}
}