{
  "type": "Feature",
  "properties": {
    "gn:admin1_code":"4",
    "gn:asciiname":"Chak One Hundred Sixteen - Seven Right Western Branch",
    "gn:country_code":"PK",
    "gn:dem":129,
    "gn:feature_class":"P",
    "gn:feature_code":"PPL",
    "gn:name":"Chak One Hundred Sixteen - Seven Right Western Branch",
    "gn:population":0,
    "gn:timezone":"Asia/Karachi",
    "iso:country":"PK",
    "name:und_x_variant":[
        "Mujtab\u0101\u0101b\u0101d"
    ],
    "wof:name":"Chak One Hundred Sixteen - Seven Right Western Branch",
    "wof:placetype":"locality"
},
  "geometry": {"coordinates":[72.00064,30.02705],"type":"Point"}
}