{
  "type": "Feature",
  "properties": {
    "gn:admin1_code":"1.0",
    "gn:asciiname":"Shinesar",
    "gn:country_code":"PK",
    "gn:dem":2255,
    "gn:feature_class":"P",
    "gn:feature_code":"PPL",
    "gn:name":"Shinesar",
    "gn:population":0,
    "gn:timezone":"Asia/Karachi",
    "iso:country":"PK",
    "name:und_x_variant":[
        "Shinesah",
        "Shinesar"
    ],
    "wof:name":"Shinesar",
    "wof:placetype":"locality"
},
  "geometry": {"coordinates":[70.18228000000001,33.92857],"type":"Point"}
}