{
  "type": "Feature",
  "properties": {
    "gn:admin1_code":"04",
    "gn:asciiname":"Pindi Gujran",
    "gn:country_code":"PK",
    "gn:dem":484,
    "gn:feature_class":"P",
    "gn:feature_code":"PPL",
    "gn:name":"Pindi Gujran",
    "gn:population":0,
    "gn:timezone":"Asia/Karachi",
    "iso:country":"PK",
    "name:und_x_variant":[
        "Pindi G\u016bjar\u0101n"
    ],
    "wof:name":"Pindi Gujran",
    "wof:placetype":"locality"
},
  "geometry": {"coordinates":[73.12260999999999,32.95975],"type":"Point"}
}