{
  "type": "Feature",
  "properties": {
    "gn:admin1_code":"5",
    "gn:asciiname":"Lal Muhammad",
    "gn:country_code":"PK",
    "gn:dem":53,
    "gn:feature_class":"P",
    "gn:feature_code":"PPL",
    "gn:name":"Lal Muhammad",
    "gn:population":0,
    "gn:timezone":"Asia/Karachi",
    "iso:country":"PK",
    "name:und_x_variant":[
        "H\u0101ji Khosa",
        "Lal Muhammad"
    ],
    "wof:name":"Lal Muhammad",
    "wof:placetype":"locality"
},
  "geometry": {"coordinates":[68.18013000000001,28.16639],"type":"Point"}
}