{
  "type": "Feature",
  "properties": {
    "gn:admin1_code":"07",
    "gn:asciiname":"Mathu Barog",
    "gn:country_code":"PK",
    "gn:dem":4663,
    "gn:feature_class":"P",
    "gn:feature_code":"PPL",
    "gn:name":"Mathu Barog",
    "gn:population":0,
    "gn:timezone":"Asia/Karachi",
    "iso:country":"PK",
    "wof:name":"Mathu Barog",
    "wof:placetype":"locality"
},
  "geometry": {"coordinates":[75.91667,34.96667],"type":"Point"}
}