{
  "type": "Feature",
  "properties": {
    "gn:admin1_code":"6",
    "gn:asciiname":"Gajjan",
    "gn:country_code":"PK",
    "gn:dem":1667,
    "gn:feature_class":"P",
    "gn:feature_code":"PPL",
    "gn:name":"Gajjan",
    "gn:population":0,
    "gn:timezone":"Asia/Karachi",
    "iso:country":"PK",
    "wof:name":"Gajjan",
    "wof:placetype":"locality"
},
  "geometry": {"coordinates":[73.88535999999998,33.65987],"type":"Point"}
}