{
  "type": "Feature",
  "properties": {
    "gn:admin1_code":"7.0",
    "gn:asciiname":"Pendo",
    "gn:country_code":"PK",
    "gn:dem":2271,
    "gn:feature_class":"P",
    "gn:feature_code":"PPL",
    "gn:name":"Pendo",
    "gn:population":0,
    "gn:timezone":"Asia/Karachi",
    "iso:country":"PK",
    "wof:name":"Pendo",
    "wof:placetype":"locality"
},
  "geometry": {"coordinates":[75.64015000000001,35.49064],"type":"Point"}
}