{
  "type": "Feature",
  "properties": {
    "gn:admin1_code":"4",
    "gn:asciiname":"Dhok Samolas",
    "gn:country_code":"PK",
    "gn:dem":312,
    "gn:feature_class":"P",
    "gn:feature_code":"PPL",
    "gn:name":"Dhok Samolas",
    "gn:population":0,
    "gn:timezone":"Asia/Karachi",
    "iso:country":"PK",
    "name:und_x_variant":[
        "Dhok Sammu"
    ],
    "wof:name":"Dhok Samolas",
    "wof:placetype":"locality"
},
  "geometry": {"coordinates":[73.39623,32.90396],"type":"Point"}
}