{
  "type": "Feature",
  "properties": {
    "gn:admin1_code":"3.0",
    "gn:asciiname":"Bisao",
    "gn:country_code":"PK",
    "gn:dem":4052,
    "gn:feature_class":"P",
    "gn:feature_code":"PPL",
    "gn:name":"Bisao",
    "gn:population":0,
    "gn:timezone":"Asia/Karachi",
    "iso:country":"PK",
    "name:und_x_variant":[
        "Bi\u0101so"
    ],
    "wof:name":"Bisao",
    "wof:placetype":"locality"
},
  "geometry": {"coordinates":[72.86995,35.39628],"type":"Point"}
}