{
  "type": "Feature",
  "properties": {
    "gn:admin1_code":"2",
    "gn:asciiname":"Shah Mir",
    "gn:country_code":"PK",
    "gn:dem":1780,
    "gn:feature_class":"P",
    "gn:feature_code":"PPL",
    "gn:name":"Shah Mir",
    "gn:population":0,
    "gn:timezone":"Asia/Karachi",
    "iso:country":"PK",
    "name:azb_x_preferred":[
        "\u0634\u0645\u0633 \u0627\u0644\u062f\u06cc\u0646 \u0634\u0627\u0647\u0645\u06cc\u0631"
    ],
    "name:jpn_x_preferred":[
        "\u30b7\u30e3\u30fc\u30fb\u30df\u30fc\u30eb"
    ],
    "wof:name":"Shah Mir",
    "wof:placetype":"locality"
},
  "geometry": {"coordinates":[67.02960999999999,29.946],"type":"Point"}
}