{
  "type": "Feature",
  "properties": {
    "gn:admin1_code":"2",
    "gn:asciiname":"Shah Mir",
    "gn:country_code":"PK",
    "gn:dem":1780,
    "gn:feature_class":"P",
    "gn:feature_code":"PPL",
    "gn:name":"Shah Mir",
    "gn:population":0,
    "gn:timezone":"Asia/Karachi",
    "iso:country":"PK",
    "wof:name":"Shah Mir",
    "wof:placetype":"locality"
},
  "geometry": {"coordinates":[67.02960999999999,29.946],"type":"Point"}
}