{
  "type": "Feature",
  "properties": {
    "gn:admin1_code":"4.0",
    "gn:asciiname":"Nikka Sarria",
    "gn:country_code":"PK",
    "gn:dem":270,
    "gn:feature_class":"P",
    "gn:feature_code":"PPL",
    "gn:name":"Nikka Sarria",
    "gn:population":0,
    "gn:timezone":"Asia/Karachi",
    "iso:country":"PK",
    "wof:name":"Nikka Sarria",
    "wof:placetype":"locality"
},
  "geometry": {"coordinates":[75.05431999999998,32.3126],"type":"Point"}
}