{
  "type": "Feature",
  "properties": {
    "gn:admin1_code":"4.0",
    "gn:asciiname":"Chak Four Hundred Sixty-four",
    "gn:country_code":"PK",
    "gn:dem":166,
    "gn:feature_class":"P",
    "gn:feature_code":"PPL",
    "gn:name":"Chak Four Hundred Sixty-four",
    "gn:population":0,
    "gn:timezone":"Asia/Karachi",
    "iso:country":"PK",
    "name:eng_x_preferred":[
        "Chak Four Hundred Sixty-four"
    ],
    "name:und_x_variant":[
        "Sult\u0101n Lakha",
        "Jorew\u0101la",
        "Joriw\u0101la"
    ],
    "wof:name":"Chak Four Hundred Sixty-four",
    "wof:placetype":"locality"
},
  "geometry": {"coordinates":[72.51539,31.47223],"type":"Point"}
}