{
  "type": "Feature",
  "properties": {
    "gn:admin1_code":"4.0",
    "gn:asciiname":"Wan Mian Murad Bakhsh",
    "gn:country_code":"PK",
    "gn:dem":175,
    "gn:feature_class":"P",
    "gn:feature_code":"PPL",
    "gn:name":"Wan Mian Murad Bakhsh",
    "gn:population":0,
    "gn:timezone":"Asia/Karachi",
    "iso:country":"PK",
    "name:und_x_variant":[
        "W\u0101n Mian M\u016br\u0101d Baklish"
    ],
    "wof:name":"Wan Mian Murad Bakhsh",
    "wof:placetype":"locality"
},
  "geometry": {"coordinates":[73.26742,30.87257],"type":"Point"}
}