{
  "type": "Feature",
  "properties": {
    "gn:admin1_code":"4.0",
    "gn:asciiname":"Nawan Ghoga",
    "gn:country_code":"PK",
    "gn:dem":216,
    "gn:feature_class":"P",
    "gn:feature_code":"PPL",
    "gn:name":"Nawan Ghoga",
    "gn:population":0,
    "gn:timezone":"Asia/Karachi",
    "iso:country":"PK",
    "name:und_x_variant":[
        "Ghoga Naw\u0101n"
    ],
    "wof:name":"Nawan Ghoga",
    "wof:placetype":"locality"
},
  "geometry": {"coordinates":[74.14851,31.92554],"type":"Point"}
}