{
  "type": "Feature",
  "properties": {
    "gn:admin1_code":"3",
    "gn:asciiname":"Lalu Razzar",
    "gn:country_code":"PK",
    "gn:dem":1144,
    "gn:feature_class":"P",
    "gn:feature_code":"PPL",
    "gn:name":"Lalu Razzar",
    "gn:population":0,
    "gn:timezone":"Asia/Karachi",
    "iso:country":"PK",
    "name:eng_x_preferred":[
        "L\u0101lu"
    ],
    "name:und_x_variant":[
        "Razzar",
        "Lalu Razzar"
    ],
    "wof:name":"Lalu Razzar",
    "wof:placetype":"locality"
},
  "geometry": {"coordinates":[72.46564000000002,34.37253],"type":"Point"}
}