{
  "type": "Feature",
  "properties": {
    "gn:admin1_code":"04",
    "gn:asciiname":"Shinh Bagh Paria",
    "gn:country_code":"PK",
    "gn:dem":308,
    "gn:feature_class":"P",
    "gn:feature_code":"PPL",
    "gn:name":"Shinh Bagh Paria",
    "gn:population":0,
    "gn:timezone":"Asia/Karachi",
    "iso:country":"PK",
    "name:und_x_variant":[
        "Shinh Bagh",
        "Shinh B\u0101gh P\u0101rla",
        "Shinh Bagh Paria"
    ],
    "wof:name":"Shinh Bagh Paria",
    "wof:placetype":"locality"
},
  "geometry": {"coordinates":[72.32245999999998,33.73561],"type":"Point"}
}