{
  "type": "Feature",
  "properties": {
    "gn:admin1_code":"2.0",
    "gn:asciiname":"Chauter",
    "gn:country_code":"PK",
    "gn:dem":2297,
    "gn:feature_class":"P",
    "gn:feature_code":"PPL",
    "gn:name":"Chauter",
    "gn:population":0,
    "gn:timezone":"Asia/Karachi",
    "iso:country":"PK",
    "name:und_x_variant":[
        "Chotair",
        "Chauter"
    ],
    "wof:name":"Chauter",
    "wof:placetype":"locality"
},
  "geometry": {"coordinates":[67.95199000000001,30.35462],"type":"Point"}
}