{
  "type": "Feature",
  "properties": {
    "gn:admin1_code":"6",
    "gn:asciiname":"Retar",
    "gn:country_code":"PK",
    "gn:dem":1004,
    "gn:feature_class":"P",
    "gn:feature_code":"PPL",
    "gn:name":"Retar",
    "gn:population":0,
    "gn:timezone":"Asia/Karachi",
    "iso:country":"PK",
    "name:und_x_variant":[
        "Rethar"
    ],
    "wof:name":"Retar",
    "wof:placetype":"locality"
},
  "geometry": {"coordinates":[73.43655,34.33146],"type":"Point"}
}