{
  "type": "Feature",
  "properties": {
    "gn:admin1_code":"4",
    "gn:asciiname":"Chak Seventeen -Eleven Left",
    "gn:country_code":"PK",
    "gn:dem":160,
    "gn:feature_class":"P",
    "gn:feature_code":"PPL",
    "gn:name":"Chak Seventeen -Eleven Left",
    "gn:population":0,
    "gn:timezone":"Asia/Karachi",
    "iso:country":"PK",
    "name:und_x_variant":[
        "Chak Seventeen-Eleven L",
        "R\u0101ji\u0101nw\u0101la"
    ],
    "wof:name":"Chak Seventeen -Eleven Left",
    "wof:placetype":"locality"
},
  "geometry": {"coordinates":[72.76198000000002,30.46579],"type":"Point"}
}