{
  "type": "Feature",
  "properties": {
    "gn:admin1_code":"4",
    "gn:asciiname":"Chak Two Hundred Thirty-seven Gugera Branch",
    "gn:country_code":"PK",
    "gn:dem":194,
    "gn:feature_class":"P",
    "gn:feature_code":"PPL",
    "gn:name":"Chak Two Hundred Thirty-seven Gugera Branch",
    "gn:population":0,
    "gn:timezone":"Asia/Karachi",
    "iso:country":"PK",
    "name:und_x_variant":[
        "Brijdala",
        "Burjd\u0101la"
    ],
    "wof:name":"Chak Two Hundred Thirty-seven Gugera Branch",
    "wof:placetype":"locality"
},
  "geometry": {"coordinates":[73.46013000000001,31.37058],"type":"Point"}
}