{
  "type": "Feature",
  "properties": {
    "gn:admin1_code":"1",
    "gn:asciiname":"Umarzai Zhawar",
    "gn:country_code":"PK",
    "gn:dem":1833,
    "gn:feature_class":"P",
    "gn:feature_code":"PPL",
    "gn:name":"Umarzai Zhawar",
    "gn:population":0,
    "gn:timezone":"Asia/Karachi",
    "iso:country":"PK",
    "wof:name":"Umarzai Zhawar",
    "wof:placetype":"locality"
},
  "geometry": {"coordinates":[69.9718,32.6686],"type":"Point"}
}