{
  "type": "Feature",
  "properties": {
    "gn:admin1_code":"4",
    "gn:asciiname":"Akirianwala",
    "gn:country_code":"PK",
    "gn:dem":172,
    "gn:feature_class":"P",
    "gn:feature_code":"PPL",
    "gn:name":"Akirianwala",
    "gn:population":0,
    "gn:timezone":"Asia/Karachi",
    "iso:country":"PK",
    "name:und_x_variant":[
        "Akerew\u0101la"
    ],
    "wof:name":"Akirianwala",
    "wof:placetype":"locality"
},
  "geometry": {"coordinates":[72.01014000000001,31.55329],"type":"Point"}
}