{
  "type": "Feature",
  "properties": {
    "gn:admin1_code":"4.0",
    "gn:asciiname":"Chak Chetanwala",
    "gn:country_code":"PK",
    "gn:dem":141,
    "gn:feature_class":"P",
    "gn:feature_code":"PPL",
    "gn:name":"Chak Chetanwala",
    "gn:population":0,
    "gn:timezone":"Asia/Karachi",
    "iso:country":"PK",
    "name:und_x_variant":[
        "Chathi\u0101nw\u0101la"
    ],
    "wof:name":"Chak Chetanwala",
    "wof:placetype":"locality"
},
  "geometry": {"coordinates":[72.13143000000002,30.81309000000001],"type":"Point"}
}