{
  "type": "Feature",
  "properties": {
    "gn:admin1_code":"3.0",
    "gn:asciiname":"Tit Baware",
    "gn:country_code":"PK",
    "gn:dem":1233,
    "gn:feature_class":"P",
    "gn:feature_code":"PPL",
    "gn:name":"Tit Baware",
    "gn:population":0,
    "gn:timezone":"Asia/Karachi",
    "iso:country":"PK",
    "wof:name":"Tit Baware",
    "wof:placetype":"locality"
},
  "geometry": {"coordinates":[72.41963,34.60964],"type":"Point"}
}