{
  "type": "Feature",
  "properties": {
    "gn:admin1_code":"01",
    "gn:asciiname":"Shamkhi",
    "gn:country_code":"PK",
    "gn:dem":1662,
    "gn:feature_class":"P",
    "gn:feature_code":"PPL",
    "gn:name":"Shamkhi",
    "gn:population":0,
    "gn:timezone":"Asia/Karachi",
    "iso:country":"PK",
    "name:und_x_variant":[
        "Shamkikili"
    ],
    "wof:name":"Shamkhi",
    "wof:placetype":"locality"
},
  "geometry": {"coordinates":[70.51164,33.64176],"type":"Point"}
}