{
  "type": "Feature",
  "properties": {
    "gn:admin1_code":"4",
    "gn:asciiname":"Mundherwala",
    "gn:country_code":"PK",
    "gn:dem":110,
    "gn:feature_class":"P",
    "gn:feature_code":"PPL",
    "gn:name":"Mundherwala",
    "gn:population":0,
    "gn:timezone":"Asia/Karachi",
    "iso:country":"PK",
    "name:und_x_variant":[
        "Basti Mundheri\u0101n"
    ],
    "wof:name":"Mundherwala",
    "wof:placetype":"locality"
},
  "geometry": {"coordinates":[70.97927,29.77636],"type":"Point"}
}