{
  "type": "Feature",
  "properties": {
    "gn:admin1_code":"01",
    "gn:asciiname":"Chana Darra",
    "gn:country_code":"PK",
    "gn:dem":1680,
    "gn:feature_class":"P",
    "gn:feature_code":"PPL",
    "gn:name":"Chana Darra",
    "gn:population":0,
    "gn:timezone":"Asia/Karachi",
    "iso:country":"PK",
    "wof:name":"Chana Darra",
    "wof:placetype":"locality"
},
  "geometry": {"coordinates":[70.68119,33.6362],"type":"Point"}
}