{
  "type": "Feature",
  "properties": {
    "gn:admin1_code":"06",
    "gn:asciiname":"Tas",
    "gn:country_code":"PK",
    "gn:dem":244,
    "gn:feature_class":"P",
    "gn:feature_code":"PPL",
    "gn:name":"Tas",
    "gn:population":0,
    "gn:timezone":"Asia/Karachi",
    "iso:country":"PK",
    "name:und_x_variant":[
        "Tass",
        "Tas"
    ],
    "wof:name":"Tas",
    "wof:placetype":"locality"
},
  "geometry": {"coordinates":[73.73170999999998,33.01997],"type":"Point"}
}