{
  "type": "Feature",
  "properties": {
    "gn:admin1_code":"4",
    "gn:asciiname":"Wargal",
    "gn:country_code":"PK",
    "gn:dem":686,
    "gn:feature_class":"P",
    "gn:feature_code":"PPL",
    "gn:name":"Wargal",
    "gn:population":0,
    "gn:timezone":"Asia/Karachi",
    "iso:country":"PK",
    "name:und_x_variant":[
        "Warg\u0101l"
    ],
    "wof:name":"Wargal",
    "wof:placetype":"locality"
},
  "geometry": {"coordinates":[72.06035,32.45248],"type":"Point"}
}