{
  "type": "Feature",
  "properties": {
    "gn:admin1_code":"4.0",
    "gn:asciiname":"Dera Bashir Mehr",
    "gn:country_code":"PK",
    "gn:dem":213,
    "gn:feature_class":"P",
    "gn:feature_code":"PPL",
    "gn:name":"Dera Bashir Mehr",
    "gn:population":0,
    "gn:timezone":"Asia/Karachi",
    "iso:country":"PK",
    "wof:name":"Dera Bashir Mehr",
    "wof:placetype":"locality"
},
  "geometry": {"coordinates":[74.34319000000001,31.79525],"type":"Point"}
}