{
  "type": "Feature",
  "properties": {
    "gn:admin1_code":"4",
    "gn:asciiname":"Damrewala",
    "gn:country_code":"PK",
    "gn:dem":113,
    "gn:feature_class":"P",
    "gn:feature_code":"PPL",
    "gn:name":"Damrewala",
    "gn:population":0,
    "gn:timezone":"Asia/Karachi",
    "iso:country":"PK",
    "name:und_x_variant":[
        "Basti Ar\u0101\u012bn"
    ],
    "wof:name":"Damrewala",
    "wof:placetype":"locality"
},
  "geometry": {"coordinates":[70.7663,29.91582],"type":"Point"}
}