{
  "type": "Feature",
  "properties": {
    "gn:admin1_code":"4",
    "gn:asciiname":"Basti Lal Khan",
    "gn:country_code":"PK",
    "gn:dem":102,
    "gn:feature_class":"P",
    "gn:feature_code":"PPL",
    "gn:name":"Basti Lal Khan",
    "gn:population":0,
    "gn:timezone":"Asia/Karachi",
    "iso:country":"PK",
    "name:und_x_variant":[
        "Basti Bakhti\u0101ri"
    ],
    "wof:name":"Basti Lal Khan",
    "wof:placetype":"locality"
},
  "geometry": {"coordinates":[70.92218000000003,29.32878],"type":"Point"}
}