{
  "type": "Feature",
  "properties": {
    "gn:admin1_code":"3.0",
    "gn:asciiname":"Gangu Dheri",
    "gn:country_code":"PK",
    "gn:dem":364,
    "gn:feature_class":"P",
    "gn:feature_code":"PPL",
    "gn:name":"Gangu Dheri",
    "gn:population":0,
    "gn:timezone":"Asia/Karachi",
    "iso:country":"PK",
    "name:eng_x_preferred":[
        "Gangu Dheri"
    ],
    "name:und_x_variant":[
        "Gangudher",
        "G\u0101ng\u016bdhei"
    ],
    "wof:name":"Gangu Dheri",
    "wof:placetype":"locality"
},
  "geometry": {"coordinates":[72.37361,34.23797],"type":"Point"}
}