{
  "type": "Feature",
  "properties": {
    "gn:admin1_code":"5",
    "gn:asciiname":"Goth Haji Sawan Buraro",
    "gn:country_code":"PK",
    "gn:dem":26,
    "gn:feature_class":"P",
    "gn:feature_code":"PPL",
    "gn:name":"Goth Haji Sawan Buraro",
    "gn:population":0,
    "gn:timezone":"Asia/Karachi",
    "iso:country":"PK",
    "name:und_x_variant":[
        "Goth H\u0101ji S\u0101wan Buraro"
    ],
    "wof:name":"Goth Haji Sawan Buraro",
    "wof:placetype":"locality"
},
  "geometry": {"coordinates":[68.67801999999999,25.79254],"type":"Point"}
}