{
  "type": "Feature",
  "properties": {
    "gn:admin1_code":"3.0",
    "gn:asciiname":"Borring",
    "gn:country_code":"PK",
    "gn:dem":233,
    "gn:feature_class":"P",
    "gn:feature_code":"PPL",
    "gn:name":"Borring",
    "gn:population":0,
    "gn:timezone":"Asia/Karachi",
    "iso:country":"PK",
    "wof:name":"Borring",
    "wof:placetype":"locality"
},
  "geometry": {"coordinates":[70.34321,31.70641],"type":"Point"}
}