{
  "type": "Feature",
  "properties": {
    "gn:admin1_code":"4.0",
    "gn:asciiname":"Chak Seventy-nine South Branch",
    "gn:country_code":"PK",
    "gn:dem":191,
    "gn:feature_class":"P",
    "gn:feature_code":"PPL",
    "gn:name":"Chak Seventy-nine South Branch",
    "gn:population":0,
    "gn:timezone":"Asia/Karachi",
    "iso:country":"PK",
    "name:und_x_variant":[
        "Chokera",
        "Chaukera",
        "Chak Seventy-nine South Branch"
    ],
    "wof:name":"Chak Seventy-nine South Branch",
    "wof:placetype":"locality"
},
  "geometry": {"coordinates":[72.81211999999999,32.06755],"type":"Point"}
}