{
  "type": "Feature",
  "properties": {
    "gn:admin1_code":"4.0",
    "gn:asciiname":"Dumanwali",
    "gn:country_code":"PK",
    "gn:dem":244,
    "gn:feature_class":"P",
    "gn:feature_code":"PPL",
    "gn:name":"Dumanwali",
    "gn:population":0,
    "gn:timezone":"Asia/Karachi",
    "iso:country":"PK",
    "wof:name":"Dumanwali",
    "wof:placetype":"locality"
},
  "geometry": {"coordinates":[75.06667,32.15],"type":"Point"}
}