{
  "type": "Feature",
  "properties": {
    "gn:admin1_code":"5",
    "gn:asciiname":"Banipota",
    "gn:country_code":"PK",
    "gn:dem":21,
    "gn:feature_class":"P",
    "gn:feature_code":"PPL",
    "gn:name":"Banipota",
    "gn:population":0,
    "gn:timezone":"Asia/Karachi",
    "iso:country":"PK",
    "name:und_x_variant":[
        "Goth Banipota"
    ],
    "wof:name":"Banipota",
    "wof:placetype":"locality"
},
  "geometry": {"coordinates":[68.71756999999999,25.37258],"type":"Point"}
}