{
  "type": "Feature",
  "properties": {
    "gn:admin1_code":"3",
    "gn:asciiname":"Satketai",
    "gn:country_code":"PK",
    "gn:dem":1192,
    "gn:feature_class":"P",
    "gn:feature_code":"PPL",
    "gn:name":"Satketai",
    "gn:population":0,
    "gn:timezone":"Asia/Karachi",
    "iso:country":"PK",
    "name:und_x_variant":[
        "Satketar",
        "Salketai",
        "Satketai"
    ],
    "wof:name":"Satketai",
    "wof:placetype":"locality"
},
  "geometry": {"coordinates":[72.73805,34.26484],"type":"Point"}
}