{
  "type": "Feature",
  "properties": {
    "gn:admin1_code":"3.0",
    "gn:asciiname":"Bankhar Banda",
    "gn:country_code":"PK",
    "gn:dem":2486,
    "gn:feature_class":"P",
    "gn:feature_code":"PPL",
    "gn:name":"Bankhar Banda",
    "gn:population":0,
    "gn:timezone":"Asia/Karachi",
    "iso:country":"PK",
    "wof:name":"Bankhar Banda",
    "wof:placetype":"locality"
},
  "geometry": {"coordinates":[72.89829,35.2012],"type":"Point"}
}