{
  "type": "Feature",
  "properties": {
    "gn:admin1_code":"7.0",
    "gn:asciiname":"Matok",
    "gn:country_code":"PK",
    "gn:dem":2735,
    "gn:feature_class":"P",
    "gn:feature_code":"PPL",
    "gn:name":"Matok",
    "gn:population":0,
    "gn:timezone":"Asia/Karachi",
    "iso:country":"PK",
    "wof:name":"Matok",
    "wof:placetype":"locality"
},
  "geometry": {"coordinates":[76.14487,34.98651],"type":"Point"}
}