{
  "type": "Feature",
  "properties": {
    "gn:admin1_code":"2.0",
    "gn:asciiname":"Parag Bazar",
    "gn:country_code":"PK",
    "gn:dem":546,
    "gn:feature_class":"P",
    "gn:feature_code":"PPL",
    "gn:name":"Parag Bazar",
    "gn:population":0,
    "gn:timezone":"Asia/Karachi",
    "iso:country":"PK",
    "wof:name":"Parag Bazar",
    "wof:placetype":"locality"
},
  "geometry": {"coordinates":[64.57823,26.06991],"type":"Point"}
}