{
  "type": "Feature",
  "properties": {
    "gn:admin1_code":"4",
    "gn:asciiname":"Chak Three Hundred Twenty-eight Thal Development Authority",
    "gn:country_code":"PK",
    "gn:dem":148,
    "gn:feature_class":"P",
    "gn:feature_code":"PPL",
    "gn:name":"Chak Three Hundred Twenty-eight Thal Development Authority",
    "gn:population":0,
    "gn:timezone":"Asia/Karachi",
    "iso:country":"PK",
    "name:und_x_variant":[
        "Chak Three Hundred Twenty-eight TDA"
    ],
    "wof:name":"Chak Three Hundred Twenty-eight Thal Development Authority",
    "wof:placetype":"locality"
},
  "geometry": {"coordinates":[71.30498,31.02483],"type":"Point"}
}