{
  "type": "Feature",
  "properties": {
    "gn:admin1_code":"4.0",
    "gn:asciiname":"Bhaini Seraja Wattu",
    "gn:country_code":"PK",
    "gn:dem":171,
    "gn:feature_class":"P",
    "gn:feature_code":"PPL",
    "gn:name":"Bhaini Seraja Wattu",
    "gn:population":0,
    "gn:timezone":"Asia/Karachi",
    "iso:country":"PK",
    "wof:name":"Bhaini Seraja Wattu",
    "wof:placetype":"locality"
},
  "geometry": {"coordinates":[73.17543000000001,30.90882],"type":"Point"}
}