{
  "type": "Feature",
  "properties": {
    "gn:admin1_code":"3.0",
    "gn:asciiname":"Ot Khel Mela",
    "gn:country_code":"PK",
    "gn:dem":375,
    "gn:feature_class":"P",
    "gn:feature_code":"PPL",
    "gn:name":"Ot Khel Mela",
    "gn:population":0,
    "gn:timezone":"Asia/Karachi",
    "iso:country":"PK",
    "name:und_x_variant":[
        "Ut Mela"
    ],
    "wof:name":"Ot Khel Mela",
    "wof:placetype":"locality"
},
  "geometry": {"coordinates":[71.70858,33.16951],"type":"Point"}
}