{
  "type": "Feature",
  "properties": {
    "gn:admin1_code":"7.0",
    "gn:asciiname":"Sakwar",
    "gn:country_code":"PK",
    "gn:dem":1622,
    "gn:feature_class":"P",
    "gn:feature_code":"PPL",
    "gn:name":"Sakwar",
    "gn:population":0,
    "gn:timezone":"Asia/Karachi",
    "iso:country":"PK",
    "wof:name":"Sakwar",
    "wof:placetype":"locality"
},
  "geometry": {"coordinates":[74.38665999999998,35.88095999999999],"type":"Point"}
}