{
  "type": "Feature",
  "properties": {
    "gn:admin1_code":"6.0",
    "gn:asciiname":"Hajlan",
    "gn:country_code":"PK",
    "gn:dem":562,
    "gn:feature_class":"P",
    "gn:feature_code":"PPL",
    "gn:name":"Hajlan",
    "gn:population":0,
    "gn:timezone":"Asia/Karachi",
    "iso:country":"PK",
    "name:und_x_variant":[
        "Haij\u0101n"
    ],
    "wof:name":"Hajlan",
    "wof:placetype":"locality"
},
  "geometry": {"coordinates":[73.65558,33.51833],"type":"Point"}
}