{
  "type": "Feature",
  "properties": {
    "gn:admin1_code":"3.0",
    "gn:asciiname":"Galm Ghari",
    "gn:country_code":"PK",
    "gn:dem":3682,
    "gn:feature_class":"P",
    "gn:feature_code":"PPL",
    "gn:name":"Galm Ghari",
    "gn:population":0,
    "gn:timezone":"Asia/Karachi",
    "iso:country":"PK",
    "wof:name":"Galm Ghari",
    "wof:placetype":"locality"
},
  "geometry": {"coordinates":[72.89919999999999,36.6909],"type":"Point"}
}