{
  "type": "Feature",
  "properties": {
    "gn:admin1_code":"4.0",
    "gn:asciiname":"Basti Hajiwali",
    "gn:country_code":"PK",
    "gn:dem":161,
    "gn:feature_class":"P",
    "gn:feature_code":"PPL",
    "gn:name":"Basti Hajiwali",
    "gn:population":0,
    "gn:timezone":"Asia/Karachi",
    "iso:country":"PK",
    "name:und_x_variant":[
        "Basti H\u0101j\u012bw\u0101la"
    ],
    "wof:name":"Basti Hajiwali",
    "wof:placetype":"locality"
},
  "geometry": {"coordinates":[71.79303,31.30245],"type":"Point"}
}