{
  "type": "Feature",
  "properties": {
    "gn:admin1_code":"4",
    "gn:asciiname":"Salmhan Sharif",
    "gn:country_code":"PK",
    "gn:dem":528,
    "gn:feature_class":"P",
    "gn:feature_code":"PPL",
    "gn:name":"Salmhan Sharif",
    "gn:population":0,
    "gn:timezone":"Asia/Karachi",
    "iso:country":"PK",
    "name:und_x_variant":[
        "Sarmun"
    ],
    "wof:name":"Salmhan Sharif",
    "wof:placetype":"locality"
},
  "geometry": {"coordinates":[72.18403000000001,32.42645],"type":"Point"}
}