{
  "type": "Feature",
  "properties": {
    "gn:admin1_code":"4",
    "gn:asciiname":"Hariwala",
    "gn:country_code":"PK",
    "gn:dem":165,
    "gn:feature_class":"P",
    "gn:feature_code":"PPL",
    "gn:name":"Har\u012bw\u0101la",
    "gn:population":0,
    "gn:timezone":"Asia/Karachi",
    "iso:country":"PK",
    "wof:name":"Hariwala",
    "wof:placetype":"locality"
},
  "geometry": {"coordinates":[73.65000000000001,30.3625],"type":"Point"}
}