{
  "type": "Feature",
  "properties": {
    "gn:admin1_code":"2.0",
    "gn:asciiname":"Fateh Muhammad",
    "gn:country_code":"PK",
    "gn:dem":839,
    "gn:feature_class":"P",
    "gn:feature_code":"PPL",
    "gn:name":"Fateh Muhammad",
    "gn:population":0,
    "gn:timezone":"Asia/Karachi",
    "iso:country":"PK",
    "wof:name":"Fateh Muhammad",
    "wof:placetype":"locality"
},
  "geometry": {"coordinates":[66.72582,26.39934],"type":"Point"}
}