{
  "type": "Feature",
  "properties": {
    "gn:admin1_code":"03",
    "gn:asciiname":"Palosai Atozai",
    "gn:country_code":"PK",
    "gn:dem":352,
    "gn:feature_class":"P",
    "gn:feature_code":"PPL",
    "gn:name":"Palosai Atozai",
    "gn:population":0,
    "gn:timezone":"Asia/Karachi",
    "iso:country":"PK",
    "name:eng_x_preferred":[
        "Attozai"
    ],
    "name:eng_x_variant":[
        "Atozai",
        "Palosai Atozai"
    ],
    "name:und_x_variant":[
        "Palosai Attozai",
        "Palosi Atozai"
    ],
    "wof:name":"Palosai Atozai",
    "wof:placetype":"locality"
},
  "geometry": {"coordinates":[71.48879000000002,34.03579000000001],"type":"Point"}
}