{
  "type": "Feature",
  "properties": {
    "gn:admin1_code":"2.0",
    "gn:asciiname":"Kamran Kaul",
    "gn:country_code":"PK",
    "gn:dem":1734,
    "gn:feature_class":"P",
    "gn:feature_code":"PPL",
    "gn:name":"Kamran Kaul",
    "gn:population":0,
    "gn:timezone":"Asia/Karachi",
    "iso:country":"PK",
    "wof:name":"Kamran Kaul",
    "wof:placetype":"locality"
},
  "geometry": {"coordinates":[66.79389999999999,30.78977],"type":"Point"}
}