{
  "type": "Feature",
  "properties": {
    "gn:admin1_code":"4",
    "gn:asciiname":"Chak Dhamiana",
    "gn:country_code":"PK",
    "gn:dem":166,
    "gn:feature_class":"P",
    "gn:feature_code":"PPL",
    "gn:name":"Chak Dhamiana",
    "gn:population":0,
    "gn:timezone":"Asia/Karachi",
    "iso:country":"PK",
    "name:und_x_variant":[
        "Dhami\u0101na"
    ],
    "wof:name":"Chak Dhamiana",
    "wof:placetype":"locality"
},
  "geometry": {"coordinates":[73.39205,30.44188],"type":"Point"}
}