{
  "type": "Feature",
  "properties": {
    "gn:admin1_code":"2.0",
    "gn:asciiname":"Hansan Kili",
    "gn:country_code":"PK",
    "gn:dem":1567,
    "gn:feature_class":"P",
    "gn:feature_code":"PPL",
    "gn:name":"Hansan Kili",
    "gn:population":0,
    "gn:timezone":"Asia/Karachi",
    "iso:country":"PK",
    "wof:name":"Hansan Kili",
    "wof:placetype":"locality"
},
  "geometry": {"coordinates":[68.63463,30.86791],"type":"Point"}
}