{
  "type": "Feature",
  "properties": {
    "gn:admin1_code":"01",
    "gn:asciiname":"Mandan",
    "gn:country_code":"PK",
    "gn:dem":1421,
    "gn:feature_class":"P",
    "gn:feature_code":"PPL",
    "gn:name":"Mandan",
    "gn:population":0,
    "gn:timezone":"Asia/Karachi",
    "iso:country":"PK",
    "name:und_x_variant":[
        "Mandana",
        "Mandan"
    ],
    "wof:name":"Mandan",
    "wof:placetype":"locality"
},
  "geometry": {"coordinates":[70.53791,33.58402],"type":"Point"}
}