{
  "type": "Feature",
  "properties": {
    "gn:admin1_code":"01",
    "gn:asciiname":"Mandan",
    "gn:country_code":"PK",
    "gn:dem":1421,
    "gn:feature_class":"P",
    "gn:feature_code":"PPL",
    "gn:name":"Mandan",
    "gn:population":0,
    "gn:timezone":"Asia/Karachi",
    "iso:country":"PK",
    "name:ara_x_preferred":[
        "\u0645\u0627\u0646\u062f\u0627\u0646"
    ],
    "name:bel_x_preferred":[
        "\u041c\u0430\u043d\u0434\u0430\u043d"
    ],
    "name:cat_x_preferred":[
        "Mandans"
    ],
    "name:chy_x_preferred":[
        "Ts\u00e9-he\u0161e'\u00e9m\u00e2he\u00f3nese"
    ],
    "name:cym_x_preferred":[
        "Mandan"
    ],
    "name:deu_x_preferred":[
        "Mandan"
    ],
    "name:est_x_preferred":[
        "Mandanid"
    ],
    "name:fin_x_preferred":[
        "Mandanit"
    ],
    "name:fra_x_preferred":[
        "Mandans"
    ],
    "name:hrv_x_preferred":[
        "Mandan Indijanci"
    ],
    "name:ido_x_preferred":[
        "Mandan"
    ],
    "name:ind_x_preferred":[
        "Suku Mandan"
    ],
    "name:ita_x_preferred":[
        "Mandan"
    ],
    "name:jpn_x_preferred":[
        "\u30de\u30f3\u30c0\u30f3"
    ],
    "name:lav_x_preferred":[
        "Mandani"
    ],
    "name:lit_x_preferred":[
        "Mandanai"
    ],
    "name:mlg_x_preferred":[
        "Mandan"
    ],
    "name:nds_x_preferred":[
        "Mandan"
    ],
    "name:nld_x_preferred":[
        "Mandan"
    ],
    "name:nor_x_preferred":[
        "Mandan"
    ],
    "name:pol_x_preferred":[
        "Mandanowie"
    ],
    "name:por_x_preferred":[
        "Mandan"
    ],
    "name:rus_x_preferred":[
        "\u041c\u0430\u043d\u0434\u0430\u043d\u044b"
    ],
    "name:spa_x_preferred":[
        "Mandan"
    ],
    "name:swe_x_preferred":[
        "Mandan"
    ],
    "name:tur_x_preferred":[
        "Mandanlar"
    ],
    "name:ukr_x_preferred":[
        "\u041c\u0430\u043d\u0434\u0430\u043d\u0438"
    ],
    "name:und_x_variant":[
        "Mandana",
        "Mandan"
    ],
    "wof:name":"Mandan",
    "wof:placetype":"locality"
},
  "geometry": {"coordinates":[70.53791,33.58402],"type":"Point"}
}