{
  "type": "Feature",
  "properties": {
    "gn:admin1_code":"3.0",
    "gn:asciiname":"Daslor Pain",
    "gn:country_code":"PK",
    "gn:dem":1068,
    "gn:feature_class":"P",
    "gn:feature_code":"PPL",
    "gn:name":"Daslor Pain",
    "gn:population":0,
    "gn:timezone":"Asia/Karachi",
    "iso:country":"PK",
    "name:und_x_variant":[
        "Daslor"
    ],
    "wof:name":"Daslor Pain",
    "wof:placetype":"locality"
},
  "geometry": {"coordinates":[72.01168,35.03373],"type":"Point"}
}