{
  "type": "Feature",
  "properties": {
    "gn:admin1_code":"4.0",
    "gn:asciiname":"Darbar Mian Hassa",
    "gn:country_code":"PK",
    "gn:dem":135,
    "gn:feature_class":"P",
    "gn:feature_code":"PPL",
    "gn:name":"Darbar Mian Hassa",
    "gn:population":0,
    "gn:timezone":"Asia/Karachi",
    "iso:country":"PK",
    "wof:name":"Darbar Mian Hassa",
    "wof:placetype":"locality"
},
  "geometry": {"coordinates":[71.70815999999998,30.74758],"type":"Point"}
}