{
  "type": "Feature",
  "properties": {
    "gn:admin1_code":"2.0",
    "gn:asciiname":"Basti Khams",
    "gn:country_code":"PK",
    "gn:dem":1179,
    "gn:feature_class":"P",
    "gn:feature_code":"PPL",
    "gn:name":"Basti Khams",
    "gn:population":0,
    "gn:timezone":"Asia/Karachi",
    "iso:country":"PK",
    "wof:name":"Basti Khams",
    "wof:placetype":"locality"
},
  "geometry": {"coordinates":[69.79264000000001,29.96391],"type":"Point"}
}