{
  "type": "Feature",
  "properties": {
    "gn:admin1_code":"4.0",
    "gn:asciiname":"Rajoia",
    "gn:country_code":"PK",
    "gn:dem":435,
    "gn:feature_class":"P",
    "gn:feature_code":"PPL",
    "gn:name":"Rajoia",
    "gn:population":0,
    "gn:timezone":"Asia/Karachi",
    "iso:country":"PK",
    "name:und_x_variant":[
        "Rajoa",
        "Rajoia"
    ],
    "wof:name":"Rajoia",
    "wof:placetype":"locality"
},
  "geometry": {"coordinates":[73.04975999999998,33.30299],"type":"Point"}
}