{
  "type": "Feature",
  "properties": {
    "gn:admin1_code":"5",
    "gn:asciiname":"Ali Punjabi",
    "gn:country_code":"PK",
    "gn:dem":11,
    "gn:feature_class":"P",
    "gn:feature_code":"PPL",
    "gn:name":"Ali Punjabi",
    "gn:population":0,
    "gn:timezone":"Asia/Karachi",
    "iso:country":"PK",
    "name:und_x_variant":[
        "Goth Panj\u0101bi"
    ],
    "wof:name":"Ali Punjabi",
    "wof:placetype":"locality"
},
  "geometry": {"coordinates":[69.19714999999999,24.99938],"type":"Point"}
}