{
  "type": "Feature",
  "properties": {
    "gn:admin1_code":"3.0",
    "gn:asciiname":"Dorghosh",
    "gn:country_code":"PK",
    "gn:dem":2713,
    "gn:feature_class":"P",
    "gn:feature_code":"PPL",
    "gn:name":"Dorghosh",
    "gn:population":0,
    "gn:timezone":"Asia/Karachi",
    "iso:country":"PK",
    "wof:name":"Dorghosh",
    "wof:placetype":"locality"
},
  "geometry": {"coordinates":[71.56298000000002,35.94492],"type":"Point"}
}