{
  "type": "Feature",
  "properties": {
    "gn:admin1_code":"2.0",
    "gn:asciiname":"Malik Haji Ali Muhammad",
    "gn:country_code":"PK",
    "gn:dem":1026,
    "gn:feature_class":"P",
    "gn:feature_code":"PPL",
    "gn:name":"Malik Haji Ali Muhammad",
    "gn:population":0,
    "gn:timezone":"Asia/Karachi",
    "iso:country":"PK",
    "wof:name":"Malik Haji Ali Muhammad",
    "wof:placetype":"locality"
},
  "geometry": {"coordinates":[63.96405,29.05909],"type":"Point"}
}