{
  "type": "Feature",
  "properties": {
    "gn:admin1_code":"3.0",
    "gn:asciiname":"Bezogah",
    "gn:country_code":"PK",
    "gn:dem":2079,
    "gn:feature_class":"P",
    "gn:feature_code":"PPL",
    "gn:name":"Bezogah",
    "gn:population":0,
    "gn:timezone":"Asia/Karachi",
    "iso:country":"PK",
    "wof:name":"Bezogah",
    "wof:placetype":"locality"
},
  "geometry": {"coordinates":[71.77164,35.39092],"type":"Point"}
}