{
  "type": "Feature",
  "properties": {
    "gn:admin1_code":"5",
    "gn:asciiname":"Jhindi Goth",
    "gn:country_code":"PK",
    "gn:dem":47,
    "gn:feature_class":"P",
    "gn:feature_code":"PPL",
    "gn:name":"Jhindi Goth",
    "gn:population":0,
    "gn:timezone":"Asia/Karachi",
    "iso:country":"PK",
    "name:und_x_variant":[
        "Jhindi"
    ],
    "wof:name":"Jhindi Goth",
    "wof:placetype":"locality"
},
  "geometry": {"coordinates":[69.22713,27.19931],"type":"Point"}
}