{
  "type": "Feature",
  "properties": {
    "gn:admin1_code":"4.0",
    "gn:asciiname":"Kalas",
    "gn:country_code":"PK",
    "gn:dem":1293,
    "gn:feature_class":"P",
    "gn:feature_code":"PPL",
    "gn:name":"Kalas",
    "gn:population":0,
    "gn:timezone":"Asia/Karachi",
    "iso:country":"PK",
    "name:ceb_x_preferred":[
        "Kalas"
    ],
    "name:ces_x_preferred":[
        "Kala\u0161"
    ],
    "name:deu_x_preferred":[
        "Kalas"
    ],
    "name:eng_x_preferred":[
        "Kal\u0101la"
    ],
    "name:fin_x_preferred":[
        "Kalas"
    ],
    "name:pol_x_preferred":[
        "Kalas"
    ],
    "name:srp_x_preferred":[
        "\u041a\u0430\u043b\u0430\u0441"
    ],
    "name:swe_x_preferred":[
        "Kalas"
    ],
    "wof:name":"Kalas",
    "wof:placetype":"locality"
},
  "geometry": {"coordinates":[73.49309000000002,33.77844],"type":"Point"}
}