{
  "type": "Feature",
  "properties": {
    "gn:admin1_code":"4.0",
    "gn:asciiname":"Kalas",
    "gn:country_code":"PK",
    "gn:dem":1293,
    "gn:feature_class":"P",
    "gn:feature_code":"PPL",
    "gn:name":"Kalas",
    "gn:population":0,
    "gn:timezone":"Asia/Karachi",
    "iso:country":"PK",
    "name:eng_x_preferred":[
        "Kal\u0101la"
    ],
    "wof:name":"Kalas",
    "wof:placetype":"locality"
},
  "geometry": {"coordinates":[73.49309000000002,33.77844],"type":"Point"}
}