{
  "type": "Feature",
  "properties": {
    "gn:admin1_code":"4.0",
    "gn:asciiname":"Kerampura",
    "gn:country_code":"PK",
    "gn:dem":217,
    "gn:feature_class":"P",
    "gn:feature_code":"PPL",
    "gn:name":"Kerampura",
    "gn:population":0,
    "gn:timezone":"Asia/Karachi",
    "iso:country":"PK",
    "name:und_x_variant":[
        "Kairopura"
    ],
    "wof:name":"Kerampura",
    "wof:placetype":"locality"
},
  "geometry": {"coordinates":[74.57839,31.3978],"type":"Point"}
}