{
  "type": "Feature",
  "properties": {
    "gn:admin1_code":"05",
    "gn:asciiname":"Saiyidpur",
    "gn:country_code":"PK",
    "gn:dem":16,
    "gn:feature_class":"P",
    "gn:feature_code":"PPL",
    "gn:name":"Saiyidpur",
    "gn:population":0,
    "gn:timezone":"Asia/Karachi",
    "iso:country":"PK",
    "name:und_x_variant":[
        "Saidpur"
    ],
    "wof:name":"Saiyidpur",
    "wof:placetype":"locality"
},
  "geometry": {"coordinates":[68.86286,24.91087000000001],"type":"Point"}
}