{
  "type": "Feature",
  "properties": {
    "gn:admin1_code":"4.0",
    "gn:asciiname":"Mianwala",
    "gn:country_code":"PK",
    "gn:dem":143,
    "gn:feature_class":"P",
    "gn:feature_code":"PPL",
    "gn:name":"Mi\u0101nw\u0101la",
    "gn:population":0,
    "gn:timezone":"Asia/Karachi",
    "iso:country":"PK",
    "name:fas_x_preferred":[
        "\u0645\u06cc\u0627\u0646\u200c\u0648\u0627\u0644\u0627"
    ],
    "name:urd_x_preferred":[
        "\u0645\u06cc\u0627\u06ba \u0648\u0627\u0644\u0627"
    ],
    "wof:name":"Mianwala",
    "wof:placetype":"locality"
},
  "geometry": {"coordinates":[70.98650000000001,30.83456],"type":"Point"}
}