{
  "type": "Feature",
  "properties": {
    "gn:admin1_code":"2",
    "gn:asciiname":"Gulshan Doki",
    "gn:country_code":"PK",
    "gn:dem":1802,
    "gn:feature_class":"P",
    "gn:feature_code":"PPL",
    "gn:name":"Gulshan Doki",
    "gn:population":0,
    "gn:timezone":"Asia/Karachi",
    "iso:country":"PK",
    "name:und_x_variant":[
        "Doki"
    ],
    "wof:name":"Gulshan Doki",
    "wof:placetype":"locality"
},
  "geometry": {"coordinates":[66.31129,29.18146],"type":"Point"}
}