{
  "type": "Feature",
  "properties": {
    "gn:admin1_code":"4",
    "gn:asciiname":"Chak Pathan",
    "gn:country_code":"PK",
    "gn:dem":226,
    "gn:feature_class":"P",
    "gn:feature_code":"PPL",
    "gn:name":"Chak Pathan",
    "gn:population":0,
    "gn:timezone":"Asia/Karachi",
    "iso:country":"PK",
    "name:und_x_variant":[
        "Path\u0101n Chak"
    ],
    "wof:name":"Chak Pathan",
    "wof:placetype":"locality"
},
  "geometry": {"coordinates":[74.0792,32.31572],"type":"Point"}
}