{
  "type": "Feature",
  "properties": {
    "gn:admin1_code":"4",
    "gn:asciiname":"Firozwala",
    "gn:country_code":"PK",
    "gn:dem":108,
    "gn:feature_class":"P",
    "gn:feature_code":"PPL",
    "gn:name":"Firozwala",
    "gn:population":0,
    "gn:timezone":"Asia/Karachi",
    "iso:country":"PK",
    "name:und_x_variant":[
        "F\u012brozw\u0101la",
        "Firozew\u0101la",
        "Firozwala"
    ],
    "wof:name":"Firozwala",
    "wof:placetype":"locality"
},
  "geometry": {"coordinates":[70.63471,29.70595],"type":"Point"}
}