{
  "type": "Feature",
  "properties": {
    "gn:admin1_code":"01",
    "gn:asciiname":"Khado",
    "gn:country_code":"PK",
    "gn:dem":2160,
    "gn:feature_class":"P",
    "gn:feature_code":"PPL",
    "gn:name":"Khado",
    "gn:population":0,
    "gn:timezone":"Asia/Karachi",
    "iso:country":"PK",
    "wof:name":"Khado",
    "wof:placetype":"locality"
},
  "geometry": {"coordinates":[70.62824999999999,33.90117],"type":"Point"}
}