{
  "type": "Feature",
  "properties": {
    "gn:admin1_code":"3.0",
    "gn:asciiname":"Turen More",
    "gn:country_code":"PK",
    "gn:dem":1823,
    "gn:feature_class":"P",
    "gn:feature_code":"PPL",
    "gn:name":"Turen More",
    "gn:population":0,
    "gn:timezone":"Asia/Karachi",
    "iso:country":"PK",
    "name:eng_x_preferred":[
        "Turen More"
    ],
    "wof:name":"Turen More",
    "wof:placetype":"locality"
},
  "geometry": {"coordinates":[71.97986,36.00002999999999],"type":"Point"}
}