{
  "type": "Feature",
  "properties": {
    "gn:admin1_code":"3",
    "gn:asciiname":"Chhapra",
    "gn:country_code":"PK",
    "gn:dem":1145,
    "gn:feature_class":"P",
    "gn:feature_code":"PPL",
    "gn:name":"Chhapra",
    "gn:population":0,
    "gn:timezone":"Asia/Karachi",
    "iso:country":"PK",
    "name:und_x_variant":[
        "Chhaprai"
    ],
    "wof:name":"Chhapra",
    "wof:placetype":"locality"
},
  "geometry": {"coordinates":[73.19324,34.51989],"type":"Point"}
}