{
  "type": "Feature",
  "properties": {
    "gn:admin1_code":"3.0",
    "gn:asciiname":"Said Nurabad",
    "gn:country_code":"PK",
    "gn:dem":307,
    "gn:feature_class":"P",
    "gn:feature_code":"PPL",
    "gn:name":"Said Nurabad",
    "gn:population":0,
    "gn:timezone":"Asia/Karachi",
    "iso:country":"PK",
    "wof:name":"Said Nurabad",
    "wof:placetype":"locality"
},
  "geometry": {"coordinates":[71.82741,34.15616],"type":"Point"}
}