{
  "type": "Feature",
  "properties": {
    "gn:admin1_code":"4",
    "gn:asciiname":"Dheri",
    "gn:country_code":"PK",
    "gn:dem":316,
    "gn:feature_class":"P",
    "gn:feature_code":"PPL",
    "gn:name":"Dheri",
    "gn:population":0,
    "gn:timezone":"Asia/Karachi",
    "iso:country":"PK",
    "name:und_x_variant":[
        "Dher"
    ],
    "wof:name":"Dheri",
    "wof:placetype":"locality"
},
  "geometry": {"coordinates":[74.01283000000002,32.89994],"type":"Point"}
}