{
  "type": "Feature",
  "properties": {
    "gn:admin1_code":"4.0",
    "gn:asciiname":"Chah Jalalwala",
    "gn:country_code":"PK",
    "gn:dem":143,
    "gn:feature_class":"P",
    "gn:feature_code":"PPL",
    "gn:name":"Chah Jalalwala",
    "gn:population":0,
    "gn:timezone":"Asia/Karachi",
    "iso:country":"PK",
    "name:und_x_variant":[
        "Khu Jal\u0101lw\u0101la"
    ],
    "wof:name":"Chah Jalalwala",
    "wof:placetype":"locality"
},
  "geometry": {"coordinates":[72.04035999999998,30.98314],"type":"Point"}
}