{
  "type": "Feature",
  "properties": {
    "gn:admin1_code":"2.0",
    "gn:asciiname":"Sufi Muhammad Gis",
    "gn:country_code":"PK",
    "gn:dem":1411,
    "gn:feature_class":"P",
    "gn:feature_code":"PPL",
    "gn:name":"Sufi Muhammad Gis",
    "gn:population":0,
    "gn:timezone":"Asia/Karachi",
    "iso:country":"PK",
    "wof:name":"Sufi Muhammad Gis",
    "wof:placetype":"locality"
},
  "geometry": {"coordinates":[63.93266,29.29286],"type":"Point"}
}