{
  "type": "Feature",
  "properties": {
    "gn:admin1_code":"3",
    "gn:asciiname":"Begomar",
    "gn:country_code":"PK",
    "gn:dem":1488,
    "gn:feature_class":"P",
    "gn:feature_code":"PPL",
    "gn:name":"Begomar",
    "gn:population":0,
    "gn:timezone":"Asia/Karachi",
    "iso:country":"PK",
    "wof:name":"Begomar",
    "wof:placetype":"locality"
},
  "geometry": {"coordinates":[72.86014,34.96022],"type":"Point"}
}