{
  "type": "Feature",
  "properties": {
    "gn:admin1_code":"4.0",
    "gn:asciiname":"Chah Mithanwala",
    "gn:country_code":"PK",
    "gn:dem":109,
    "gn:feature_class":"P",
    "gn:feature_code":"PPL",
    "gn:name":"Chah Mithanwala",
    "gn:population":0,
    "gn:timezone":"Asia/Karachi",
    "iso:country":"PK",
    "name:und_x_variant":[
        "Ch\u0101h Mithaw\u0101la"
    ],
    "wof:name":"Chah Mithanwala",
    "wof:placetype":"locality"
},
  "geometry": {"coordinates":[71.04395,29.71188],"type":"Point"}
}