{
  "type": "Feature",
  "properties": {
    "gn:admin1_code":"4.0",
    "gn:asciiname":"Chak Seventy-eight Jhang Branch",
    "gn:country_code":"PK",
    "gn:dem":180,
    "gn:feature_class":"P",
    "gn:feature_code":"PPL",
    "gn:name":"Chak Seventy-eight Jhang Branch",
    "gn:population":0,
    "gn:timezone":"Asia/Karachi",
    "iso:country":"PK",
    "name:und_x_variant":[
        "Jawdi",
        "Jiwaddi",
        "Chak Seventy-Eight",
        "Chak Seventy-eight Jhang Branch",
        "Joddi"
    ],
    "wof:name":"Chak Seventy-eight Jhang Branch",
    "wof:placetype":"locality"
},
  "geometry": {"coordinates":[72.90958000000001,31.28849],"type":"Point"}
}