{
  "type": "Feature",
  "properties": {
    "gn:admin1_code":"2.0",
    "gn:asciiname":"Mangal",
    "gn:country_code":"PK",
    "gn:dem":2108,
    "gn:feature_class":"P",
    "gn:feature_code":"PPL",
    "gn:name":"Mangal",
    "gn:population":0,
    "gn:timezone":"Asia/Karachi",
    "iso:country":"PK",
    "name:und_x_variant":[
        "Mangala"
    ],
    "wof:name":"Mangal",
    "wof:placetype":"locality"
},
  "geometry": {"coordinates":[67.17454000000001,30.3774],"type":"Point"}
}