{
  "type": "Feature",
  "properties": {
    "gn:admin1_code":"5.0",
    "gn:asciiname":"Goth Talib Dablo",
    "gn:country_code":"PK",
    "gn:dem":0,
    "gn:feature_class":"P",
    "gn:feature_code":"PPL",
    "gn:name":"Goth Talib Dablo",
    "gn:population":0,
    "gn:timezone":"Asia/Karachi",
    "iso:country":"PK",
    "wof:name":"Goth Talib Dablo",
    "wof:placetype":"locality"
},
  "geometry": {"coordinates":[67.47279,24.45722],"type":"Point"}
}