{
  "type": "Feature",
  "properties": {
    "gn:admin1_code":"3",
    "gn:asciiname":"Langalot",
    "gn:country_code":"PK",
    "gn:dem":1826,
    "gn:feature_class":"P",
    "gn:feature_code":"PPL",
    "gn:name":"Langalot",
    "gn:population":0,
    "gn:timezone":"Asia/Karachi",
    "iso:country":"PK",
    "name:und_x_variant":[
        "Lag\u0101lu"
    ],
    "wof:name":"Langalot",
    "wof:placetype":"locality"
},
  "geometry": {"coordinates":[73.44329999999999,34.22045],"type":"Point"}
}