{
  "type": "Feature",
  "properties": {
    "gn:admin1_code":"2.0",
    "gn:asciiname":"Faiz Muhammad Kili",
    "gn:country_code":"PK",
    "gn:dem":1477,
    "gn:feature_class":"P",
    "gn:feature_code":"PPL",
    "gn:name":"Faiz Muhammad Kili",
    "gn:population":0,
    "gn:timezone":"Asia/Karachi",
    "iso:country":"PK",
    "wof:name":"Faiz Muhammad Kili",
    "wof:placetype":"locality"
},
  "geometry": {"coordinates":[68.54878000000001,30.33282],"type":"Point"}
}