{
  "type": "Feature",
  "properties": {
    "gn:admin1_code":"3",
    "gn:asciiname":"Dila",
    "gn:country_code":"PK",
    "gn:dem":944,
    "gn:feature_class":"P",
    "gn:feature_code":"PPL",
    "gn:name":"Dila",
    "gn:population":0,
    "gn:timezone":"Asia/Karachi",
    "iso:country":"PK",
    "name:ceb_x_preferred":[
        "Dila"
    ],
    "name:fra_x_preferred":[
        "Dila"
    ],
    "name:pol_x_preferred":[
        "Dila"
    ],
    "name:swe_x_preferred":[
        "Dila"
    ],
    "name:tgl_x_preferred":[
        "Dila"
    ],
    "wof:name":"Dila",
    "wof:placetype":"locality"
},
  "geometry": {"coordinates":[72.76235,34.21098],"type":"Point"}
}