{
  "type": "Feature",
  "properties": {
    "gn:admin1_code":"4.0",
    "gn:asciiname":"Wadhlanwala",
    "gn:country_code":"PK",
    "gn:dem":190,
    "gn:feature_class":"P",
    "gn:feature_code":"PPL",
    "gn:name":"Wadhlanwala",
    "gn:population":0,
    "gn:timezone":"Asia/Karachi",
    "iso:country":"PK",
    "name:und_x_variant":[
        "Wadhi\u0101nw\u0101la"
    ],
    "wof:name":"Wadhlanwala",
    "wof:placetype":"locality"
},
  "geometry": {"coordinates":[71.83336,31.99718],"type":"Point"}
}