{
  "type": "Feature",
  "properties": {
    "gn:admin1_code":"3",
    "gn:asciiname":"Ghundao",
    "gn:country_code":"PK",
    "gn:dem":2121,
    "gn:feature_class":"P",
    "gn:feature_code":"PPL",
    "gn:name":"Ghundao",
    "gn:population":0,
    "gn:timezone":"Asia/Karachi",
    "iso:country":"PK",
    "wof:name":"Ghundao",
    "wof:placetype":"locality"
},
  "geometry": {"coordinates":[72.60776,34.80645999999999],"type":"Point"}
}