{
  "type": "Feature",
  "properties": {
    "gn:admin1_code":"4.0",
    "gn:asciiname":"Gokhal",
    "gn:country_code":"PK",
    "gn:dem":495,
    "gn:feature_class":"P",
    "gn:feature_code":"PPL",
    "gn:name":"Gokhal",
    "gn:population":0,
    "gn:timezone":"Asia/Karachi",
    "iso:country":"PK",
    "name:und_x_variant":[
        "Ghokal",
        "Ghukkal",
        "Gokhal"
    ],
    "wof:name":"Gokhal",
    "wof:placetype":"locality"
},
  "geometry": {"coordinates":[72.97169,32.9438],"type":"Point"}
}