{
  "type": "Feature",
  "properties": {
    "gn:admin1_code":"3.0",
    "gn:asciiname":"Drasan",
    "gn:country_code":"PK",
    "gn:dem":2076,
    "gn:feature_class":"P",
    "gn:feature_code":"PPL",
    "gn:name":"Drasan",
    "gn:population":0,
    "gn:timezone":"Asia/Karachi",
    "iso:country":"PK",
    "name:und_x_variant":[
        "Kila Drasan",
        "Kala Drasan",
        "Darasan",
        "Drasan"
    ],
    "name:urd_x_preferred":[
        "\u062f\u0652\u0631\u064e\u0627\u0633\u064e\u0646"
    ],
    "wof:name":"Drasan",
    "wof:placetype":"locality"
},
  "geometry": {"coordinates":[72.23909999999999,36.30999],"type":"Point"}
}