{
  "type": "Feature",
  "properties": {
    "gn:admin1_code":"5",
    "gn:asciiname":"Goth Sono Pitafi",
    "gn:country_code":"PK",
    "gn:dem":66,
    "gn:feature_class":"P",
    "gn:feature_code":"PPL",
    "gn:name":"Goth Sono Pitafi",
    "gn:population":0,
    "gn:timezone":"Asia/Karachi",
    "iso:country":"PK",
    "name:und_x_variant":[
        "Goth Sona Pit\u0101fi"
    ],
    "wof:name":"Goth Sono Pitafi",
    "wof:placetype":"locality"
},
  "geometry": {"coordinates":[69.48161999999999,27.81925],"type":"Point"}
}