{
  "type": "Feature",
  "properties": {
    "gn:admin1_code":"4.0",
    "gn:asciiname":"Thatta Khokhar",
    "gn:country_code":"PK",
    "gn:dem":158,
    "gn:feature_class":"P",
    "gn:feature_code":"PPL",
    "gn:name":"Thatta Khokhar",
    "gn:population":0,
    "gn:timezone":"Asia/Karachi",
    "iso:country":"PK",
    "name:und_x_variant":[
        "Khokhar"
    ],
    "wof:name":"Thatta Khokhar",
    "wof:placetype":"locality"
},
  "geometry": {"coordinates":[72.10814999999999,31.49579],"type":"Point"}
}