{
  "type": "Feature",
  "properties": {
    "gn:admin1_code":"5.0",
    "gn:asciiname":"Laira",
    "gn:country_code":"PK",
    "gn:dem":41,
    "gn:feature_class":"P",
    "gn:feature_code":"PPL",
    "gn:name":"Laira",
    "gn:population":0,
    "gn:timezone":"Asia/Karachi",
    "iso:country":"PK",
    "name:gle_x_preferred":[
        "Laira"
    ],
    "wof:name":"Laira",
    "wof:placetype":"locality"
},
  "geometry": {"coordinates":[67.64926,27.06422],"type":"Point"}
}