{
  "type": "Feature",
  "properties": {
    "gn:admin1_code":"4.0",
    "gn:asciiname":"Basti Machhi",
    "gn:country_code":"PK",
    "gn:dem":79,
    "gn:feature_class":"P",
    "gn:feature_code":"PPL",
    "gn:name":"Basti M\u0101chhi",
    "gn:population":0,
    "gn:timezone":"Asia/Karachi",
    "iso:country":"PK",
    "wof:name":"Basti Machhi",
    "wof:placetype":"locality"
},
  "geometry": {"coordinates":[70.13333,28.68333],"type":"Point"}
}