{
  "type": "Feature",
  "properties": {
    "gn:admin1_code":"3",
    "gn:asciiname":"Ishtiwincho",
    "gn:country_code":"PK",
    "gn:dem":2767,
    "gn:feature_class":"P",
    "gn:feature_code":"PPL",
    "gn:name":"Ishtiwincho",
    "gn:population":0,
    "gn:timezone":"Asia/Karachi",
    "iso:country":"PK",
    "name:eng_x_preferred":[
        "Ishtiwincho"
    ],
    "wof:name":"Ishtiwincho",
    "wof:placetype":"locality"
},
  "geometry": {"coordinates":[71.60001,35.80842],"type":"Point"}
}