{
  "type": "Feature",
  "properties": {
    "gn:admin1_code":"1.0",
    "gn:asciiname":"Sultan Khel",
    "gn:country_code":"PK",
    "gn:dem":545,
    "gn:feature_class":"P",
    "gn:feature_code":"PPL",
    "gn:name":"Sultan Khel",
    "gn:population":0,
    "gn:timezone":"Asia/Karachi",
    "iso:country":"PK",
    "name:und_x_variant":[
        "Kandi Balias Khel"
    ],
    "wof:name":"Sultan Khel",
    "wof:placetype":"locality"
},
  "geometry": {"coordinates":[71.69873,33.58989],"type":"Point"}
}