{
  "type": "Feature",
  "properties": {
    "gn:admin1_code":"4",
    "gn:asciiname":"Chak One Hundred Fourteen Western Branch",
    "gn:country_code":"PK",
    "gn:dem":132,
    "gn:feature_class":"P",
    "gn:feature_code":"PPL",
    "gn:name":"Chak One Hundred Fourteen Western Branch",
    "gn:population":0,
    "gn:timezone":"Asia/Karachi",
    "iso:country":"PK",
    "name:und_x_variant":[
        "Kot J\u0101far"
    ],
    "wof:name":"Chak One Hundred Fourteen Western Branch",
    "wof:placetype":"locality"
},
  "geometry": {"coordinates":[72.03236,30.03872],"type":"Point"}
}