{
  "type": "Feature",
  "properties": {
    "gn:admin1_code":"4",
    "gn:asciiname":"Bhutta",
    "gn:country_code":"PK",
    "gn:dem":243,
    "gn:feature_class":"P",
    "gn:feature_code":"PPL",
    "gn:name":"Bhutta",
    "gn:population":0,
    "gn:timezone":"Asia/Karachi",
    "iso:country":"PK",
    "name:und_x_variant":[
        "Bhuttar",
        "Bhutta"
    ],
    "wof:name":"Bhutta",
    "wof:placetype":"locality"
},
  "geometry": {"coordinates":[74.74098000000002,32.22266],"type":"Point"}
}