{
  "type": "Feature",
  "properties": {
    "gn:admin1_code":"7.0",
    "gn:asciiname":"Kashipa",
    "gn:country_code":"PK",
    "gn:dem":2752,
    "gn:feature_class":"P",
    "gn:feature_code":"PPL",
    "gn:name":"Kashipa",
    "gn:population":0,
    "gn:timezone":"Asia/Karachi",
    "iso:country":"PK",
    "name:und_x_variant":[
        "Kushipa"
    ],
    "wof:name":"Kashipa",
    "wof:placetype":"locality"
},
  "geometry": {"coordinates":[75.30463,35.64136],"type":"Point"}
}