{
  "type": "Feature",
  "properties": {
    "gn:admin1_code":"01",
    "gn:asciiname":"Sulaiman Khel",
    "gn:country_code":"PK",
    "gn:dem":1440,
    "gn:feature_class":"P",
    "gn:feature_code":"PPL",
    "gn:name":"Sulaiman Khel",
    "gn:population":0,
    "gn:timezone":"Asia/Karachi",
    "iso:country":"PK",
    "wof:name":"Sulaiman Khel",
    "wof:placetype":"locality"
},
  "geometry": {"coordinates":[71.01736,33.68597],"type":"Point"}
}