{
  "type": "Feature",
  "properties": {
    "gn:admin1_code":"3.0",
    "gn:asciiname":"Shakh Number Six",
    "gn:country_code":"PK",
    "gn:dem":357,
    "gn:feature_class":"P",
    "gn:feature_code":"PPL",
    "gn:name":"Shakh Number Six",
    "gn:population":0,
    "gn:timezone":"Asia/Karachi",
    "iso:country":"PK",
    "name:eng_x_preferred":[
        "Shakh Number Six"
    ],
    "wof:name":"Shakh Number Six",
    "wof:placetype":"locality"
},
  "geometry": {"coordinates":[71.81197,34.28346],"type":"Point"}
}