{
  "type": "Feature",
  "properties": {
    "gn:admin1_code":"04",
    "gn:asciiname":"Kot Naju",
    "gn:country_code":"PK",
    "gn:dem":286,
    "gn:feature_class":"P",
    "gn:feature_code":"PPL",
    "gn:name":"Kot Naju",
    "gn:population":0,
    "gn:timezone":"Asia/Karachi",
    "iso:country":"PK",
    "wof:name":"Kot Naju",
    "wof:placetype":"locality"
},
  "geometry": {"coordinates":[74.96736,32.40643],"type":"Point"}
}