{
  "type": "Feature",
  "properties": {
    "gn:admin1_code":"4.0",
    "gn:asciiname":"Santa Sial di Bhaini",
    "gn:country_code":"PK",
    "gn:dem":146,
    "gn:feature_class":"P",
    "gn:feature_code":"PPL",
    "gn:name":"Santa Sial di Bhaini",
    "gn:population":0,
    "gn:timezone":"Asia/Karachi",
    "iso:country":"PK",
    "wof:name":"Santa Sial di Bhaini",
    "wof:placetype":"locality"
},
  "geometry": {"coordinates":[72.79774,29.89243],"type":"Point"}
}