{
  "type": "Feature",
  "properties": {
    "gn:admin1_code":"3.0",
    "gn:asciiname":"Chadhrar",
    "gn:country_code":"PK",
    "gn:dem":243,
    "gn:feature_class":"P",
    "gn:feature_code":"PPL",
    "gn:name":"Chadhrar",
    "gn:population":0,
    "gn:timezone":"Asia/Karachi",
    "iso:country":"PK",
    "name:und_x_variant":[
        "Chandar"
    ],
    "wof:name":"Chadhrar",
    "wof:placetype":"locality"
},
  "geometry": {"coordinates":[70.35287,32.15637],"type":"Point"}
}