{
  "type": "Feature",
  "properties": {
    "gn:admin1_code":"4",
    "gn:asciiname":"Basti Dost Muhammad Hulwani",
    "gn:country_code":"PK",
    "gn:dem":102,
    "gn:feature_class":"P",
    "gn:feature_code":"PPL",
    "gn:name":"Basti Dost Muhammad Hulwani",
    "gn:population":0,
    "gn:timezone":"Asia/Karachi",
    "iso:country":"PK",
    "name:und_x_variant":[
        "Dost Muhammad Kh\u0101n Hulw\u0101n"
    ],
    "wof:name":"Basti Dost Muhammad Hulwani",
    "wof:placetype":"locality"
},
  "geometry": {"coordinates":[70.34040999999999,29.28594],"type":"Point"}
}