{
  "type": "Feature",
  "properties": {
    "gn:admin1_code":"5",
    "gn:asciiname":"Sabhago Mughairi",
    "gn:country_code":"PK",
    "gn:dem":48,
    "gn:feature_class":"P",
    "gn:feature_code":"PPL",
    "gn:name":"Sabhago Mughairi",
    "gn:population":0,
    "gn:timezone":"Asia/Karachi",
    "iso:country":"PK",
    "name:und_x_variant":[
        "Sobh\u0101go Mughairi"
    ],
    "wof:name":"Sabhago Mughairi",
    "wof:placetype":"locality"
},
  "geometry": {"coordinates":[68.02108,27.50941],"type":"Point"}
}