{
  "type": "Feature",
  "properties": {
    "gn:admin1_code":"4.0",
    "gn:asciiname":"Progiapur",
    "gn:country_code":"PK",
    "gn:dem":211,
    "gn:feature_class":"P",
    "gn:feature_code":"PPL",
    "gn:name":"Progiapur",
    "gn:population":0,
    "gn:timezone":"Asia/Karachi",
    "iso:country":"PK",
    "name:und_x_variant":[
        "Mohammad Sult\u0101n\u0101b\u0101d"
    ],
    "wof:name":"Progiapur",
    "wof:placetype":"locality"
},
  "geometry": {"coordinates":[74.29277999999999,31.47056],"type":"Point"}
}