{
  "type": "Feature",
  "properties": {
    "gn:admin1_code":"5.0",
    "gn:asciiname":"Chattan Shah",
    "gn:country_code":"PK",
    "gn:dem":2,
    "gn:feature_class":"P",
    "gn:feature_code":"PPL",
    "gn:name":"Chattan Shah",
    "gn:population":0,
    "gn:timezone":"Asia/Karachi",
    "iso:country":"PK",
    "wof:name":"Chattan Shah",
    "wof:placetype":"locality"
},
  "geometry": {"coordinates":[67.89046999999999,24.17965],"type":"Point"}
}