{
  "type": "Feature",
  "properties": {
    "gn:admin1_code":"4.0",
    "gn:asciiname":"Chauki Kohna",
    "gn:country_code":"PK",
    "gn:dem":126,
    "gn:feature_class":"P",
    "gn:feature_code":"PPL",
    "gn:name":"Chauki Kohna",
    "gn:population":0,
    "gn:timezone":"Asia/Karachi",
    "iso:country":"PK",
    "name:und_x_variant":[
        "Chak Chauki Kohna",
        "Chauki Kohna"
    ],
    "wof:name":"Chauki Kohna",
    "wof:placetype":"locality"
},
  "geometry": {"coordinates":[71.91091999999998,29.73657],"type":"Point"}
}