{
  "type": "Feature",
  "properties": {
    "gn:admin1_code":"04",
    "gn:asciiname":"Ranjhai",
    "gn:country_code":"PK",
    "gn:dem":235,
    "gn:feature_class":"P",
    "gn:feature_code":"PPL",
    "gn:name":"Ranjhai",
    "gn:population":0,
    "gn:timezone":"Asia/Karachi",
    "iso:country":"PK",
    "wof:name":"Ranjhai",
    "wof:placetype":"locality"
},
  "geometry": {"coordinates":[74.32006,32.30857],"type":"Point"}
}