{
  "type": "Feature",
  "properties": {
    "gn:admin1_code":"05",
    "gn:asciiname":"Goth Sumra Rangai",
    "gn:country_code":"PK",
    "gn:dem":5,
    "gn:feature_class":"P",
    "gn:feature_code":"PPL",
    "gn:name":"Goth Sumra Rangai",
    "gn:population":0,
    "gn:timezone":"Asia/Karachi",
    "iso:country":"PK",
    "wof:name":"Goth Sumra Rangai",
    "wof:placetype":"locality"
},
  "geometry": {"coordinates":[67.96661,24.3211],"type":"Point"}
}