{
  "type": "Feature",
  "properties": {
    "gn:admin1_code":"3.0",
    "gn:asciiname":"Muhib Banda",
    "gn:country_code":"PK",
    "gn:dem":334,
    "gn:feature_class":"P",
    "gn:feature_code":"PPL",
    "gn:name":"Muhib Banda",
    "gn:population":0,
    "gn:timezone":"Asia/Karachi",
    "iso:country":"PK",
    "name:eng_x_preferred":[
        "Muhib Banda"
    ],
    "wof:name":"Muhib Banda",
    "wof:placetype":"locality"
},
  "geometry": {"coordinates":[72.32205,34.16098],"type":"Point"}
}