{
  "type": "Feature",
  "properties": {
    "gn:admin1_code":"4.0",
    "gn:asciiname":"Kalanwala Khu",
    "gn:country_code":"PK",
    "gn:dem":203,
    "gn:feature_class":"P",
    "gn:feature_code":"PPL",
    "gn:name":"Kalanwala Khu",
    "gn:population":0,
    "gn:timezone":"Asia/Karachi",
    "iso:country":"PK",
    "name:und_x_variant":[
        "Kal\u0101lw\u0101la"
    ],
    "wof:name":"Kalanwala Khu",
    "wof:placetype":"locality"
},
  "geometry": {"coordinates":[74.04921999999998,31.27518],"type":"Point"}
}