{
  "type": "Feature",
  "properties": {
    "gn:admin1_code":"5",
    "gn:asciiname":"Deh One Hundred Fifty",
    "gn:country_code":"PK",
    "gn:dem":16,
    "gn:feature_class":"P",
    "gn:feature_code":"PPL",
    "gn:name":"Deh One Hundred Fifty",
    "gn:population":0,
    "gn:timezone":"Asia/Karachi",
    "iso:country":"PK",
    "wof:name":"Deh One Hundred Fifty",
    "wof:placetype":"locality"
},
  "geometry": {"coordinates":[68.99150999999999,25.19045],"type":"Point"}
}