{
  "type": "Feature",
  "properties": {
    "gn:admin1_code":"5.0",
    "gn:asciiname":"Aru Soho",
    "gn:country_code":"PK",
    "gn:dem":8,
    "gn:feature_class":"P",
    "gn:feature_code":"PPL",
    "gn:name":"Aru Soho",
    "gn:population":0,
    "gn:timezone":"Asia/Karachi",
    "iso:country":"PK",
    "name:eng_x_preferred":[
        "Aru Soho"
    ],
    "wof:name":"Aru Soho",
    "wof:placetype":"locality"
},
  "geometry": {"coordinates":[68.28001999999999,24.62577000000001],"type":"Point"}
}