{
  "type": "Feature",
  "properties": {
    "gn:admin1_code":"4.0",
    "gn:asciiname":"Sambli Behranai",
    "gn:country_code":"PK",
    "gn:dem":1107,
    "gn:feature_class":"P",
    "gn:feature_code":"PPL",
    "gn:name":"Sambli Behranai",
    "gn:population":0,
    "gn:timezone":"Asia/Karachi",
    "iso:country":"PK",
    "name:eng_x_preferred":[
        "Sambli Behranai"
    ],
    "wof:name":"Sambli Behranai",
    "wof:placetype":"locality"
},
  "geometry": {"coordinates":[73.36496,33.83474],"type":"Point"}
}