{
  "type": "Feature",
  "properties": {
    "gn:admin1_code":"4.0",
    "gn:asciiname":"Arbiwala",
    "gn:country_code":"PK",
    "gn:dem":115,
    "gn:feature_class":"P",
    "gn:feature_code":"PPL",
    "gn:name":"Arbiwala",
    "gn:population":0,
    "gn:timezone":"Asia/Karachi",
    "iso:country":"PK",
    "name:und_x_variant":[
        "Qutab Abrind",
        "Abr\u012bnd",
        "Arbiwala"
    ],
    "wof:name":"Arbiwala",
    "wof:placetype":"locality"
},
  "geometry": {"coordinates":[70.92915000000001,29.92002],"type":"Point"}
}