{
  "type": "Feature",
  "properties": {
    "gn:admin1_code":"3",
    "gn:asciiname":"Magra",
    "gn:country_code":"PK",
    "gn:dem":2340,
    "gn:feature_class":"P",
    "gn:feature_code":"PPL",
    "gn:name":"Magra",
    "gn:population":0,
    "gn:timezone":"Asia/Karachi",
    "iso:country":"PK",
    "wof:name":"Magra",
    "wof:placetype":"locality"
},
  "geometry": {"coordinates":[73.27439,34.68194],"type":"Point"}
}