{
  "type": "Feature",
  "properties": {
    "gn:admin1_code":"3",
    "gn:asciiname":"Magra",
    "gn:country_code":"PK",
    "gn:dem":2340,
    "gn:feature_class":"P",
    "gn:feature_code":"PPL",
    "gn:name":"Magra",
    "gn:population":0,
    "gn:timezone":"Asia/Karachi",
    "iso:country":"PK",
    "name:cat_x_preferred":[
        "Magra"
    ],
    "name:ceb_x_preferred":[
        "Fiume Magra"
    ],
    "name:chv_x_preferred":[
        "\u041c\u0430\u0433\u0440\u0430"
    ],
    "name:deu_x_preferred":[
        "Magra"
    ],
    "name:fas_x_preferred":[
        "\u0645\u0627\u06af\u0631\u0627"
    ],
    "name:fra_x_preferred":[
        "Magra"
    ],
    "name:ita_x_preferred":[
        "Magra"
    ],
    "name:jpn_x_preferred":[
        "\u30de\u30b0\u30e9\u5ddd"
    ],
    "name:lat_x_preferred":[
        "Macra"
    ],
    "name:nld_x_preferred":[
        "Magra"
    ],
    "name:nno_x_preferred":[
        "Magra"
    ],
    "name:rus_x_preferred":[
        "\u041c\u0430\u0433\u0440\u0430"
    ],
    "name:spa_x_preferred":[
        "R\u00edo Magra"
    ],
    "name:swe_x_preferred":[
        "Magra"
    ],
    "name:tgk_x_preferred":[
        "\u041c\u0430\u0433\u0440\u0430"
    ],
    "name:zho_x_preferred":[
        "\u99ac\u683c\u62c9\u6cb3"
    ],
    "wof:name":"Magra",
    "wof:placetype":"locality"
},
  "geometry": {"coordinates":[73.27439,34.68194],"type":"Point"}
}