{
  "type": "Feature",
  "properties": {
    "gn:admin1_code":"2.0",
    "gn:asciiname":"Goth Hassan Bakhsh Umrani",
    "gn:country_code":"PK",
    "gn:dem":63,
    "gn:feature_class":"P",
    "gn:feature_code":"PPL",
    "gn:name":"Goth Hassan Bakhsh Umrani",
    "gn:population":0,
    "gn:timezone":"Asia/Karachi",
    "iso:country":"PK",
    "wof:name":"Goth Hassan Bakhsh Umrani",
    "wof:placetype":"locality"
},
  "geometry": {"coordinates":[67.86086999999999,28.45324],"type":"Point"}
}