{
  "type": "Feature",
  "properties": {
    "gn:admin1_code":"4",
    "gn:asciiname":"Ajja Bhutta",
    "gn:country_code":"PK",
    "gn:dem":175,
    "gn:feature_class":"P",
    "gn:feature_code":"PPL",
    "gn:name":"Ajja Bhutta",
    "gn:population":0,
    "gn:timezone":"Asia/Karachi",
    "iso:country":"PK",
    "name:und_x_variant":[
        "\u0100ija Bhuta"
    ],
    "wof:name":"Ajja Bhutta",
    "wof:placetype":"locality"
},
  "geometry": {"coordinates":[73.77916,30.71538],"type":"Point"}
}