{
  "type": "Feature",
  "properties": {
    "gn:admin1_code":"3.0",
    "gn:asciiname":"Chukara",
    "gn:country_code":"PK",
    "gn:dem":489,
    "gn:feature_class":"P",
    "gn:feature_code":"PPL",
    "gn:name":"Chukara",
    "gn:population":0,
    "gn:timezone":"Asia/Karachi",
    "iso:country":"PK",
    "name:und_x_variant":[
        "Chowkara",
        "Chukara"
    ],
    "wof:name":"Chukara",
    "wof:placetype":"locality"
},
  "geometry": {"coordinates":[71.03398,33.02863],"type":"Point"}
}