{
  "type": "Feature",
  "properties": {
    "gn:admin1_code":"7.0",
    "gn:asciiname":"Krabathung",
    "gn:country_code":"PK",
    "gn:dem":2531,
    "gn:feature_class":"P",
    "gn:feature_code":"PPL",
    "gn:name":"Krabathung",
    "gn:population":0,
    "gn:timezone":"Asia/Karachi",
    "iso:country":"PK",
    "wof:name":"Krabathung",
    "wof:placetype":"locality"
},
  "geometry": {"coordinates":[76.17804,35.25519],"type":"Point"}
}