{
  "type": "Feature",
  "properties": {
    "gn:admin1_code":"5",
    "gn:asciiname":"Mai Jannat",
    "gn:country_code":"PK",
    "gn:dem":54,
    "gn:feature_class":"P",
    "gn:feature_code":"PPL",
    "gn:name":"Mai Jannat",
    "gn:population":0,
    "gn:timezone":"Asia/Karachi",
    "iso:country":"PK",
    "name:und_x_variant":[
        "Jannaum\u0101i"
    ],
    "wof:name":"Mai Jannat",
    "wof:placetype":"locality"
},
  "geometry": {"coordinates":[68.2923,27.92656],"type":"Point"}
}