{
  "type": "Feature",
  "properties": {
    "gn:admin1_code":"1.0",
    "gn:asciiname":"Sirin",
    "gn:country_code":"PK",
    "gn:dem":622,
    "gn:feature_class":"P",
    "gn:feature_code":"PPL",
    "gn:name":"Sirin",
    "gn:population":0,
    "gn:timezone":"Asia/Karachi",
    "iso:country":"PK",
    "name:und_x_variant":[
        "Sir\u012bn"
    ],
    "wof:name":"Sirin",
    "wof:placetype":"locality"
},
  "geometry": {"coordinates":[70.42719,32.64942],"type":"Point"}
}