{
  "type": "Feature",
  "properties": {
    "gn:admin1_code":"1.0",
    "gn:asciiname":"Sirin",
    "gn:country_code":"PK",
    "gn:dem":622,
    "gn:feature_class":"P",
    "gn:feature_code":"PPL",
    "gn:name":"Sirin",
    "gn:population":0,
    "gn:timezone":"Asia/Karachi",
    "iso:country":"PK",
    "name:afr_x_preferred":[
        "Sirin"
    ],
    "name:ara_x_preferred":[
        "\u0633\u064a\u0631\u064a\u0646"
    ],
    "name:cat_x_preferred":[
        "Sirin"
    ],
    "name:ces_x_preferred":[
        "Sirin"
    ],
    "name:deu_x_preferred":[
        "Sirin"
    ],
    "name:ell_x_preferred":[
        "\u03a3\u03af\u03c1\u03b9\u03bd"
    ],
    "name:epo_x_preferred":[
        "Sirino"
    ],
    "name:eus_x_preferred":[
        "Sirin"
    ],
    "name:fin_x_preferred":[
        "Sirin"
    ],
    "name:fra_x_preferred":[
        "Sirin"
    ],
    "name:mkd_x_preferred":[
        "\u0421\u0438\u0440\u0438\u043d"
    ],
    "name:nld_x_preferred":[
        "Sirin"
    ],
    "name:pol_x_preferred":[
        "Sirin"
    ],
    "name:ron_x_preferred":[
        "Sirin"
    ],
    "name:rus_x_preferred":[
        "\u0421\u0438\u0440\u0438\u043d"
    ],
    "name:spa_x_preferred":[
        "Sirin"
    ],
    "name:srp_x_preferred":[
        "\u0421\u0438\u0440\u0438\u043d"
    ],
    "name:swe_x_preferred":[
        "Sirin"
    ],
    "name:ukr_x_preferred":[
        "\u0421\u0438\u0440\u0438\u043d"
    ],
    "name:und_x_variant":[
        "Sir\u012bn"
    ],
    "name:zho_x_preferred":[
        "\u897f\u7433\u9e1f"
    ],
    "wof:name":"Sirin",
    "wof:placetype":"locality"
},
  "geometry": {"coordinates":[70.42719,32.64942],"type":"Point"}
}