{
  "type": "Feature",
  "properties": {
    "gn:admin1_code":"6.0",
    "gn:asciiname":"Chalka",
    "gn:country_code":"PK",
    "gn:dem":867,
    "gn:feature_class":"P",
    "gn:feature_code":"PPL",
    "gn:name":"Chalka",
    "gn:population":0,
    "gn:timezone":"Asia/Karachi",
    "iso:country":"PK",
    "name:und_x_variant":[
        "Chahot"
    ],
    "wof:name":"Chalka",
    "wof:placetype":"locality"
},
  "geometry": {"coordinates":[73.67959,33.60159],"type":"Point"}
}