{
  "type": "Feature",
  "properties": {
    "gn:admin1_code":"4.0",
    "gn:asciiname":"Basti Karam Ilahi",
    "gn:country_code":"PK",
    "gn:dem":87,
    "gn:feature_class":"P",
    "gn:feature_code":"PPL",
    "gn:name":"Basti Karam Ilahi",
    "gn:population":0,
    "gn:timezone":"Asia/Karachi",
    "iso:country":"PK",
    "wof:name":"Basti Karam Ilahi",
    "wof:placetype":"locality"
},
  "geometry": {"coordinates":[70.69409,28.53873],"type":"Point"}
}