{
  "type": "Feature",
  "properties": {
    "gn:admin1_code":"04",
    "gn:asciiname":"Seoki",
    "gn:country_code":"PK",
    "gn:dem":212,
    "gn:feature_class":"P",
    "gn:feature_code":"PPL",
    "gn:name":"Seoki",
    "gn:population":0,
    "gn:timezone":"Asia/Karachi",
    "iso:country":"PK",
    "name:und_x_variant":[
        "Sioke",
        "Seoki"
    ],
    "wof:name":"Seoki",
    "wof:placetype":"locality"
},
  "geometry": {"coordinates":[73.79308,32.04594],"type":"Point"}
}