{
  "type": "Feature",
  "properties": {
    "gn:admin1_code":"5",
    "gn:asciiname":"Deh Two Hundred Thirty-three",
    "gn:country_code":"PK",
    "gn:dem":14,
    "gn:feature_class":"P",
    "gn:feature_code":"PPL",
    "gn:name":"Deh Two Hundred Thirty-three",
    "gn:population":0,
    "gn:timezone":"Asia/Karachi",
    "iso:country":"PK",
    "name:und_x_variant":[
        "Kaloi",
        "Deh Two Hundred Thirty-three"
    ],
    "wof:name":"Deh Two Hundred Thirty-three",
    "wof:placetype":"locality"
},
  "geometry": {"coordinates":[69.19374000000001,25.38601],"type":"Point"}
}