{
  "type": "Feature",
  "properties": {
    "gn:admin1_code":"5",
    "gn:asciiname":"Bhurgari",
    "gn:country_code":"PK",
    "gn:dem":43,
    "gn:feature_class":"P",
    "gn:feature_code":"PPL",
    "gn:name":"Bhurgari",
    "gn:population":0,
    "gn:timezone":"Asia/Karachi",
    "iso:country":"PK",
    "name:snd_x_preferred":[
        "\u0680\u0631\u06b3\u0699\u064a"
    ],
    "wof:name":"Bhurgari",
    "wof:placetype":"locality"
},
  "geometry": {"coordinates":[67.72096999999999,26.69081],"type":"Point"}
}