{
  "type": "Feature",
  "properties": {
    "iso:country":"PK",
    "name:und_x_variant":[
        "Durro"
    ],
    "qs:gn_country":"PK",
    "qs:gn_fcode":"PPL",
    "qs:gn_pop":10869,
    "qs:name":"Daro",
    "qs:name_adm0":"Pakistan",
    "qs:name_adm1":"Sindh",
    "qs:photos":0,
    "qs:photos_1k":0,
    "qs:photos_9k":0,
    "qs:photos_9r":0,
    "qs:photos_all":0,
    "qs:photos_sr":0,
    "qs:placetype":"Town",
    "qs:pop_sr":"6",
    "qs:woe_adm0":23424922,
    "wof:name":"Daro",
    "wof:placetype":"locality",
    "wof:population":10869
},
  "geometry": {"coordinates":[68.18052,24.79463],"type":"Point"}
}