{
  "type": "Feature",
  "properties": {
    "gn:admin1_code":"01",
    "gn:asciiname":"Tabai",
    "gn:country_code":"PK",
    "gn:dem":1958,
    "gn:feature_class":"P",
    "gn:feature_code":"PPL",
    "gn:name":"Tabai",
    "gn:population":0,
    "gn:timezone":"Asia/Karachi",
    "iso:country":"PK",
    "wof:name":"Tabai",
    "wof:placetype":"locality"
},
  "geometry": {"coordinates":[70.46476,33.83865],"type":"Point"}
}