{
  "type": "Feature",
  "properties": {
    "gn:admin1_code":"2.0",
    "gn:asciiname":"Sar Band",
    "gn:country_code":"PK",
    "gn:dem":1967,
    "gn:feature_class":"P",
    "gn:feature_code":"PPL",
    "gn:name":"Sar Band",
    "gn:population":0,
    "gn:timezone":"Asia/Karachi",
    "iso:country":"PK",
    "name:fas_x_preferred":[
        "\u0633\u0631 \u0628\u0646\u062f"
    ],
    "name:und_x_variant":[
        "Zhar Bah\u0101n",
        "Sar Band"
    ],
    "wof:name":"Sar Band",
    "wof:placetype":"locality"
},
  "geometry": {"coordinates":[69.68743000000001,31.19335],"type":"Point"}
}