{
  "type": "Feature",
  "properties": {
    "gn:admin1_code":"1.0",
    "gn:asciiname":"Isa Khan Maurai Kalle",
    "gn:country_code":"PK",
    "gn:dem":459,
    "gn:feature_class":"P",
    "gn:feature_code":"PPL",
    "gn:name":"Isa Khan Maurai Kalle",
    "gn:population":0,
    "gn:timezone":"Asia/Karachi",
    "iso:country":"PK",
    "name:und_x_variant":[
        "\u012asa Kh\u0101n Kili"
    ],
    "wof:name":"Isa Khan Maurai Kalle",
    "wof:placetype":"locality"
},
  "geometry": {"coordinates":[70.39258000000002,32.48062],"type":"Point"}
}