{
  "type": "Feature",
  "properties": {
    "gn:admin1_code":"05",
    "gn:asciiname":"Achar Dal",
    "gn:country_code":"PK",
    "gn:dem":5,
    "gn:feature_class":"P",
    "gn:feature_code":"PPL",
    "gn:name":"Achar Dal",
    "gn:population":0,
    "gn:timezone":"Asia/Karachi",
    "iso:country":"PK",
    "wof:name":"Achar Dal",
    "wof:placetype":"locality"
},
  "geometry": {"coordinates":[67.67585,24.23894],"type":"Point"}
}