{
  "type": "Feature",
  "properties": {
    "gn:admin1_code":"5.0",
    "gn:asciiname":"Goth Pir Bukhsh",
    "gn:country_code":"PK",
    "gn:dem":46,
    "gn:feature_class":"P",
    "gn:feature_code":"PPL",
    "gn:name":"Goth Pir Bukhsh",
    "gn:population":0,
    "gn:timezone":"Asia/Karachi",
    "iso:country":"PK",
    "name:und_x_variant":[
        "Goth P\u012br Bakhsh Chuli\u0101ni"
    ],
    "wof:name":"Goth Pir Bukhsh",
    "wof:placetype":"locality"
},
  "geometry": {"coordinates":[67.73133,27.45842],"type":"Point"}
}