{
  "type": "Feature",
  "properties": {
    "gn:admin1_code":"4.0",
    "gn:asciiname":"Lundipura",
    "gn:country_code":"PK",
    "gn:dem":164,
    "gn:feature_class":"P",
    "gn:feature_code":"PPL",
    "gn:name":"Lundipura",
    "gn:population":0,
    "gn:timezone":"Asia/Karachi",
    "iso:country":"PK",
    "name:und_x_variant":[
        "Landipur"
    ],
    "wof:name":"Lundipura",
    "wof:placetype":"locality"
},
  "geometry": {"coordinates":[73.49945,30.22761],"type":"Point"}
}