{
  "type": "Feature",
  "properties": {
    "gn:admin1_code":"2.0",
    "gn:asciiname":"Shahr Gumnar Khan",
    "gn:country_code":"PK",
    "gn:dem":1952,
    "gn:feature_class":"P",
    "gn:feature_code":"PPL",
    "gn:name":"Shahr Gumnar Khan",
    "gn:population":0,
    "gn:timezone":"Asia/Karachi",
    "iso:country":"PK",
    "name:und_x_variant":[
        "Shahr G\u0101manr Kh\u0101n"
    ],
    "wof:name":"Shahr Gumnar Khan",
    "wof:placetype":"locality"
},
  "geometry": {"coordinates":[66.9158,29.6012],"type":"Point"}
}