{
  "type": "Feature",
  "properties": {
    "gn:admin1_code":"5.0",
    "gn:asciiname":"Raja Abdul Aziz",
    "gn:country_code":"PK",
    "gn:dem":29,
    "gn:feature_class":"P",
    "gn:feature_code":"PPL",
    "gn:name":"Raja Abdul Aziz",
    "gn:population":0,
    "gn:timezone":"Asia/Karachi",
    "iso:country":"PK",
    "name:und_x_variant":[
        "Ali Kh\u0101n Jam\u0101li"
    ],
    "wof:name":"Raja Abdul Aziz",
    "wof:placetype":"locality"
},
  "geometry": {"coordinates":[68.37765999999999,26.05479],"type":"Point"}
}