{
  "type": "Feature",
  "properties": {
    "gn:admin1_code":"4.0",
    "gn:asciiname":"Bangardan",
    "gn:country_code":"PK",
    "gn:dem":756,
    "gn:feature_class":"P",
    "gn:feature_code":"PPL",
    "gn:name":"Bangardan",
    "gn:population":0,
    "gn:timezone":"Asia/Karachi",
    "iso:country":"PK",
    "name:eng_x_preferred":[
        "Bang\u0101rdan"
    ],
    "wof:name":"Bangardan",
    "wof:placetype":"locality"
},
  "geometry": {"coordinates":[70.1904,30.09524],"type":"Point"}
}