{
  "type": "Feature",
  "properties": {
    "gn:admin1_code":"4.0",
    "gn:asciiname":"Tharu Khelanwala",
    "gn:country_code":"PK",
    "gn:dem":212,
    "gn:feature_class":"P",
    "gn:feature_code":"PPL",
    "gn:name":"Tharu Khelanwala",
    "gn:population":0,
    "gn:timezone":"Asia/Karachi",
    "iso:country":"PK",
    "name:und_x_variant":[
        "Th\u0101ru Khel\u0101nw\u0101la"
    ],
    "wof:name":"Tharu Khelanwala",
    "wof:placetype":"locality"
},
  "geometry": {"coordinates":[71.67313,32.49877],"type":"Point"}
}