{
  "type": "Feature",
  "properties": {
    "gn:admin1_code":"4.0",
    "gn:asciiname":"Phingniwala",
    "gn:country_code":"PK",
    "gn:dem":119,
    "gn:feature_class":"P",
    "gn:feature_code":"PPL",
    "gn:name":"Phingniwala",
    "gn:population":0,
    "gn:timezone":"Asia/Karachi",
    "iso:country":"PK",
    "wof:name":"Phingniwala",
    "wof:placetype":"locality"
},
  "geometry": {"coordinates":[71.08100999999998,30.02198],"type":"Point"}
}