{
  "type": "Feature",
  "properties": {
    "gn:admin1_code":"4.0",
    "gn:asciiname":"Chak Two Hundred Sixteen Gugera Branch",
    "gn:country_code":"PK",
    "gn:dem":172,
    "gn:feature_class":"P",
    "gn:feature_code":"PPL",
    "gn:name":"Chak Two Hundred Sixteen Gugera Branch",
    "gn:population":0,
    "gn:timezone":"Asia/Karachi",
    "iso:country":"PK",
    "name:und_x_variant":[
        "Jaj\u0101l\u0101bad"
    ],
    "wof:name":"Chak Two Hundred Sixteen Gugera Branch",
    "wof:placetype":"locality"
},
  "geometry": {"coordinates":[72.83058,31.03521],"type":"Point"}
}