{
  "type": "Feature",
  "properties": {
    "gn:admin1_code":"7.0",
    "gn:asciiname":"Handarap",
    "gn:country_code":"PK",
    "gn:dem":2948,
    "gn:feature_class":"P",
    "gn:feature_code":"PPL",
    "gn:name":"Handarap",
    "gn:population":0,
    "gn:timezone":"Asia/Karachi",
    "iso:country":"PK",
    "name:und_x_variant":[
        "Handaran"
    ],
    "wof:name":"Handarap",
    "wof:placetype":"locality"
},
  "geometry": {"coordinates":[72.79911,36.16517],"type":"Point"}
}