{
  "type": "Feature",
  "properties": {
    "gn:admin1_code":"7.0",
    "gn:asciiname":"Nabolai Baihk",
    "gn:country_code":"PK",
    "gn:dem":3421,
    "gn:feature_class":"P",
    "gn:feature_code":"PPL",
    "gn:name":"Nabolai Baihk",
    "gn:population":0,
    "gn:timezone":"Asia/Karachi",
    "iso:country":"PK",
    "wof:name":"Nabolai Baihk",
    "wof:placetype":"locality"
},
  "geometry": {"coordinates":[74.90430000000001,35.20446],"type":"Point"}
}