{
  "type": "Feature",
  "properties": {
    "gn:admin1_code":"5.0",
    "gn:asciiname":"Nizamuddin Jarwar",
    "gn:country_code":"PK",
    "gn:dem":63,
    "gn:feature_class":"P",
    "gn:feature_code":"PPL",
    "gn:name":"Nizamuddin Jarwar",
    "gn:population":0,
    "gn:timezone":"Asia/Karachi",
    "iso:country":"PK",
    "wof:name":"Nizamuddin Jarwar",
    "wof:placetype":"locality"
},
  "geometry": {"coordinates":[68.88171,28.31563],"type":"Point"}
}