{
  "type": "Feature",
  "properties": {
    "gn:admin1_code":"2.0",
    "gn:asciiname":"Haj Rehmat Jakhrani",
    "gn:country_code":"PK",
    "gn:dem":66,
    "gn:feature_class":"P",
    "gn:feature_code":"PPL",
    "gn:name":"Haj Rehmat Jakhrani",
    "gn:population":0,
    "gn:timezone":"Asia/Karachi",
    "iso:country":"PK",
    "wof:name":"Haj Rehmat Jakhrani",
    "wof:placetype":"locality"
},
  "geometry": {"coordinates":[68.2779,28.5551],"type":"Point"}
}