{
  "type": "Feature",
  "properties": {
    "gn:admin1_code":"2.0",
    "gn:asciiname":"Goth Haji Shaikl",
    "gn:country_code":"PK",
    "gn:dem":5,
    "gn:feature_class":"P",
    "gn:feature_code":"PPL",
    "gn:name":"Goth Haji Shaikl",
    "gn:population":0,
    "gn:timezone":"Asia/Karachi",
    "iso:country":"PK",
    "name:eng_x_preferred":[
        "Goth Haji Shaikl"
    ],
    "wof:name":"Goth Haji Shaikl",
    "wof:placetype":"locality"
},
  "geometry": {"coordinates":[66.75389,25.17375],"type":"Point"}
}