{
  "type": "Feature",
  "properties": {
    "gn:admin1_code":"4.0",
    "gn:asciiname":"Manakwali",
    "gn:country_code":"PK",
    "gn:dem":89,
    "gn:feature_class":"P",
    "gn:feature_code":"PPL",
    "gn:name":"Manakwali",
    "gn:population":0,
    "gn:timezone":"Asia/Karachi",
    "iso:country":"PK",
    "name:und_x_variant":[
        "M\u0101nikw\u0101li"
    ],
    "wof:name":"Manakwali",
    "wof:placetype":"locality"
},
  "geometry": {"coordinates":[70.43678,28.67001],"type":"Point"}
}