{
  "type": "Feature",
  "properties": {
    "gn:admin1_code":"2.0",
    "gn:asciiname":"Surnar Kili",
    "gn:country_code":"PK",
    "gn:dem":1475,
    "gn:feature_class":"P",
    "gn:feature_code":"PPL",
    "gn:name":"Surnar Kili",
    "gn:population":0,
    "gn:timezone":"Asia/Karachi",
    "iso:country":"PK",
    "wof:name":"Surnar Kili",
    "wof:placetype":"locality"
},
  "geometry": {"coordinates":[69.0231,30.83815],"type":"Point"}
}