{
  "type": "Feature",
  "properties": {
    "gn:admin1_code":"2.0",
    "gn:asciiname":"Azam Khan Goth",
    "gn:country_code":"PK",
    "gn:dem":960,
    "gn:feature_class":"P",
    "gn:feature_code":"PPL",
    "gn:name":"Azam Khan Goth",
    "gn:population":0,
    "gn:timezone":"Asia/Karachi",
    "iso:country":"PK",
    "name:und_x_variant":[
        "\u0100zam Kh\u0101n Shahr"
    ],
    "wof:name":"Azam Khan Goth",
    "wof:placetype":"locality"
},
  "geometry": {"coordinates":[66.11693000000001,26.97627],"type":"Point"}
}