{
  "type": "Feature",
  "properties": {
    "gn:admin1_code":"4",
    "gn:asciiname":"Bhanriwala",
    "gn:country_code":"PK",
    "gn:dem":99,
    "gn:feature_class":"P",
    "gn:feature_code":"PPL",
    "gn:name":"Bhanriwala",
    "gn:population":0,
    "gn:timezone":"Asia/Karachi",
    "iso:country":"PK",
    "name:und_x_variant":[
        "Kathanw\u0101la"
    ],
    "wof:name":"Bhanriwala",
    "wof:placetype":"locality"
},
  "geometry": {"coordinates":[70.46663000000002,29.31647],"type":"Point"}
}