{
  "type": "Feature",
  "properties": {
    "gn:admin1_code":"1.0",
    "gn:asciiname":"Sarmad Khel",
    "gn:country_code":"PK",
    "gn:dem":702,
    "gn:feature_class":"P",
    "gn:feature_code":"PPL",
    "gn:name":"Sarmad Khel",
    "gn:population":0,
    "gn:timezone":"Asia/Karachi",
    "iso:country":"PK",
    "name:und_x_variant":[
        "Tsewdai"
    ],
    "wof:name":"Sarmad Khel",
    "wof:placetype":"locality"
},
  "geometry": {"coordinates":[70.24196999999999,32.98486],"type":"Point"}
}