{
  "type": "Feature",
  "properties": {
    "gn:admin1_code":"4",
    "gn:asciiname":"Chapriwala",
    "gn:country_code":"PK",
    "gn:dem":141,
    "gn:feature_class":"P",
    "gn:feature_code":"PPL",
    "gn:name":"Chapriwala",
    "gn:population":0,
    "gn:timezone":"Asia/Karachi",
    "iso:country":"PK",
    "name:und_x_variant":[
        "Chhappar\u012bw\u0101la"
    ],
    "wof:name":"Chapriwala",
    "wof:placetype":"locality"
},
  "geometry": {"coordinates":[71.12103,30.69156],"type":"Point"}
}