{
  "type": "Feature",
  "properties": {
    "gn:admin1_code":"4.0",
    "gn:asciiname":"Muhammad Nagar",
    "gn:country_code":"PK",
    "gn:dem":352,
    "gn:feature_class":"P",
    "gn:feature_code":"PPL",
    "gn:name":"Muhammad Nagar",
    "gn:population":0,
    "gn:timezone":"Asia/Karachi",
    "iso:country":"PK",
    "name:eng_x_preferred":[
        "Muhammad Nagar"
    ],
    "name:snd_x_preferred":[
        "\u0645\u062d\u0645\u062f \u0646\u06af\u0699"
    ],
    "name:urd_x_preferred":[
        "\u0645\u062d\u0645\u062f \u0646\u06af\u0631"
    ],
    "wof:name":"Muhammad Nagar",
    "wof:placetype":"neighbourhood"
},
  "geometry": {"coordinates":[72.38882,33.7727],"type":"Point"}
}