{
  "type": "Feature",
  "properties": {
    "gn:admin1_code":"2",
    "gn:asciiname":"Muradhan Kili",
    "gn:country_code":"PK",
    "gn:dem":1160,
    "gn:feature_class":"P",
    "gn:feature_code":"PPL",
    "gn:name":"Muradhan Kili",
    "gn:population":0,
    "gn:timezone":"Asia/Karachi",
    "iso:country":"PK",
    "wof:name":"Muradhan Kili",
    "wof:placetype":"locality"
},
  "geometry": {"coordinates":[69.05816,29.8085],"type":"Point"}
}