{
  "type": "Feature",
  "properties": {
    "gn:admin1_code":"1.0",
    "gn:asciiname":"Yardo Kalle",
    "gn:country_code":"PK",
    "gn:dem":1443,
    "gn:feature_class":"P",
    "gn:feature_code":"PPL",
    "gn:name":"Yardo Kalle",
    "gn:population":0,
    "gn:timezone":"Asia/Karachi",
    "iso:country":"PK",
    "name:und_x_variant":[
        "Yardah Kila"
    ],
    "wof:name":"Yardo Kalle",
    "wof:placetype":"locality"
},
  "geometry": {"coordinates":[70.10417,33.82497],"type":"Point"}
}