{
  "type": "Feature",
  "properties": {
    "gn:admin1_code":"3",
    "gn:asciiname":"Kotkai",
    "gn:country_code":"PK",
    "gn:dem":1087,
    "gn:feature_class":"P",
    "gn:feature_code":"PPL",
    "gn:name":"Kotkai",
    "gn:population":0,
    "gn:timezone":"Asia/Karachi",
    "iso:country":"PK",
    "name:eng_x_preferred":[
        "Kotkai"
    ],
    "wof:name":"Kotkai",
    "wof:placetype":"locality"
},
  "geometry": {"coordinates":[71.99799,35.04173],"type":"Point"}
}