{
  "type": "Feature",
  "properties": {
    "gn:admin1_code":"5.0",
    "gn:asciiname":"Badal Machhi",
    "gn:country_code":"PK",
    "gn:dem":25,
    "gn:feature_class":"P",
    "gn:feature_code":"PPL",
    "gn:name":"Badal Machhi",
    "gn:population":0,
    "gn:timezone":"Asia/Karachi",
    "iso:country":"PK",
    "wof:name":"Badal Machhi",
    "wof:placetype":"locality"
},
  "geometry": {"coordinates":[68.60793000000001,26.13896],"type":"Point"}
}