{
  "type": "Feature",
  "properties": {
    "gn:admin1_code":"5",
    "gn:asciiname":"Bangalow Naraindas",
    "gn:country_code":"PK",
    "gn:dem":20,
    "gn:feature_class":"P",
    "gn:feature_code":"PPL",
    "gn:name":"Bangalow Naraindas",
    "gn:population":0,
    "gn:timezone":"Asia/Karachi",
    "iso:country":"PK",
    "wof:name":"Bangalow Naraindas",
    "wof:placetype":"locality"
},
  "geometry": {"coordinates":[68.89444,25.79861],"type":"Point"}
}