{
  "type": "Feature",
  "properties": {
    "gn:admin1_code":"4.0",
    "gn:asciiname":"Metlawala",
    "gn:country_code":"PK",
    "gn:dem":146,
    "gn:feature_class":"P",
    "gn:feature_code":"PPL",
    "gn:name":"Metlawala",
    "gn:population":0,
    "gn:timezone":"Asia/Karachi",
    "iso:country":"PK",
    "name:fas_x_preferred":[
        "\u0645\u06cc\u062a\u0644\u0627 \u0648\u0627\u0644\u0627"
    ],
    "name:urd_x_preferred":[
        "\u0645\u06cc\u062a\u0644\u0627 \u0648\u0627\u0644\u0627"
    ],
    "wof:name":"Metlawala",
    "wof:placetype":"locality"
},
  "geometry": {"coordinates":[70.85779000000002,30.95682],"type":"Point"}
}