{
  "type": "Feature",
  "properties": {
    "gn:admin1_code":"5.0",
    "gn:asciiname":"Nohani",
    "gn:country_code":"PK",
    "gn:dem":7,
    "gn:feature_class":"P",
    "gn:feature_code":"PPL",
    "gn:name":"Nohani",
    "gn:population":0,
    "gn:timezone":"Asia/Karachi",
    "iso:country":"PK",
    "name:fas_x_preferred":[
        "\u0646\u0648\u0647\u0646\u06cc"
    ],
    "wof:name":"Nohani",
    "wof:placetype":"locality"
},
  "geometry": {"coordinates":[68.60064,24.74288],"type":"Point"}
}