{
  "type": "Feature",
  "properties": {
    "gn:admin1_code":"4",
    "gn:asciiname":"Hansawala",
    "gn:country_code":"PK",
    "gn:dem":171,
    "gn:feature_class":"P",
    "gn:feature_code":"PPL",
    "gn:name":"Hansawala",
    "gn:population":0,
    "gn:timezone":"Asia/Karachi",
    "iso:country":"PK",
    "name:und_x_variant":[
        "H\u0101nsew\u0101la"
    ],
    "wof:name":"Hansawala",
    "wof:placetype":"locality"
},
  "geometry": {"coordinates":[71.10616,31.63859],"type":"Point"}
}