{
  "type": "Feature",
  "properties": {
    "gn:admin1_code":"4",
    "gn:asciiname":"Khurampur",
    "gn:country_code":"PK",
    "gn:dem":106,
    "gn:feature_class":"P",
    "gn:feature_code":"PPL",
    "gn:name":"Khurampur",
    "gn:population":0,
    "gn:timezone":"Asia/Karachi",
    "iso:country":"PK",
    "name:und_x_variant":[
        "Karampur",
        "Mariamw\u0101la",
        "Khurampur"
    ],
    "wof:name":"Khurampur",
    "wof:placetype":"locality"
},
  "geometry": {"coordinates":[71.16466,29.3854],"type":"Point"}
}