{
  "type": "Feature",
  "properties": {
    "gn:admin1_code":"3",
    "gn:asciiname":"Phagna",
    "gn:country_code":"PK",
    "gn:dem":1839,
    "gn:feature_class":"P",
    "gn:feature_code":"PPL",
    "gn:name":"Phagna",
    "gn:population":0,
    "gn:timezone":"Asia/Karachi",
    "iso:country":"PK",
    "wof:name":"Phagna",
    "wof:placetype":"locality"
},
  "geometry": {"coordinates":[73.46850000000001,34.68326],"type":"Point"}
}