{
  "type": "Feature",
  "properties": {
    "gn:admin1_code":"4.0",
    "gn:asciiname":"Chak Four Hundred Seventy-six Gugera Branch",
    "gn:country_code":"PK",
    "gn:dem":170,
    "gn:feature_class":"P",
    "gn:feature_code":"PPL",
    "gn:name":"Chak Four Hundred Seventy-six Gugera Branch",
    "gn:population":0,
    "gn:timezone":"Asia/Karachi",
    "iso:country":"PK",
    "name:und_x_variant":[
        "Bazurgw\u0101l",
        "Bazargw\u0101la"
    ],
    "wof:name":"Chak Four Hundred Seventy-six Gugera Branch",
    "wof:placetype":"locality"
},
  "geometry": {"coordinates":[72.87094,30.98509],"type":"Point"}
}