{
  "type": "Feature",
  "properties": {
    "gn:admin1_code":"6.0",
    "gn:asciiname":"Jandar Thagai",
    "gn:country_code":"PK",
    "gn:dem":3409,
    "gn:feature_class":"P",
    "gn:feature_code":"PPL",
    "gn:name":"Jandar Thagai",
    "gn:population":0,
    "gn:timezone":"Asia/Karachi",
    "iso:country":"PK",
    "name:und_x_variant":[
        "Holewali",
        "Jandar Thagai"
    ],
    "wof:name":"Jandar Thagai",
    "wof:placetype":"locality"
},
  "geometry": {"coordinates":[74.15451999999998,35.00026],"type":"Point"}
}