{
  "type": "Feature",
  "properties": {
    "gn:admin1_code":"4.0",
    "gn:asciiname":"Dhok Darjal",
    "gn:country_code":"PK",
    "gn:dem":451,
    "gn:feature_class":"P",
    "gn:feature_code":"PPL",
    "gn:name":"Dhok Darjal",
    "gn:population":0,
    "gn:timezone":"Asia/Karachi",
    "iso:country":"PK",
    "wof:name":"Dhok Darjal",
    "wof:placetype":"locality"
},
  "geometry": {"coordinates":[72.74561,33.05606],"type":"Point"}
}