{
  "type": "Feature",
  "properties": {
    "gn:admin1_code":"04",
    "gn:asciiname":"Shahia",
    "gn:country_code":"PK",
    "gn:dem":443,
    "gn:feature_class":"P",
    "gn:feature_code":"PPL",
    "gn:name":"Shahia",
    "gn:population":0,
    "gn:timezone":"Asia/Karachi",
    "iso:country":"PK",
    "wof:name":"Shahia",
    "wof:placetype":"locality"
},
  "geometry": {"coordinates":[72.76133,33.87569000000001],"type":"Point"}
}