{
  "type": "Feature",
  "properties": {
    "gn:admin1_code":"01",
    "gn:asciiname":"Shahzan",
    "gn:country_code":"PK",
    "gn:dem":1344,
    "gn:feature_class":"P",
    "gn:feature_code":"PPL",
    "gn:name":"Sh\u0101hzan",
    "gn:population":0,
    "gn:timezone":"Asia/Karachi",
    "iso:country":"PK",
    "wof:name":"Shahzan",
    "wof:placetype":"locality"
},
  "geometry": {"coordinates":[69.88333,32.39667],"type":"Point"}
}