{
  "type": "Feature",
  "properties": {
    "gn:admin1_code":"4",
    "gn:asciiname":"Gopanga",
    "gn:country_code":"PK",
    "gn:dem":107,
    "gn:feature_class":"P",
    "gn:feature_code":"PPL",
    "gn:name":"Gopanga",
    "gn:population":0,
    "gn:timezone":"Asia/Karachi",
    "iso:country":"PK",
    "name:und_x_variant":[
        "Gop\u0101ng",
        "Gop\u0101ganka"
    ],
    "wof:name":"Gopanga",
    "wof:placetype":"locality"
},
  "geometry": {"coordinates":[70.51749000000002,29.70838],"type":"Point"}
}