{
  "type": "Feature",
  "properties": {
    "gn:admin1_code":"04",
    "gn:asciiname":"Chak Two Hundred Thirty-six Gugera Branch",
    "gn:country_code":"PK",
    "gn:dem":196,
    "gn:feature_class":"P",
    "gn:feature_code":"PPL",
    "gn:name":"Chak Two Hundred Thirty-six Gugera Branch",
    "gn:population":0,
    "gn:timezone":"Asia/Karachi",
    "iso:country":"PK",
    "name:und_x_variant":[
        "Kot Daya Kishen",
        "Kot Daya Kishan",
        "Chak Two Hundred Thirty-six Gugera Branch",
        "Kot R\u0101dha Kish\u0101n"
    ],
    "wof:name":"Chak Two Hundred Thirty-six Gugera Branch",
    "wof:placetype":"locality"
},
  "geometry": {"coordinates":[73.48048,31.38272000000001],"type":"Point"}
}