{
  "type": "Feature",
  "properties": {
    "gn:admin1_code":"3.0",
    "gn:asciiname":"Chak Taja",
    "gn:country_code":"PK",
    "gn:dem":374,
    "gn:feature_class":"P",
    "gn:feature_code":"PPL",
    "gn:name":"Chak Taja",
    "gn:population":0,
    "gn:timezone":"Asia/Karachi",
    "iso:country":"PK",
    "name:eng_x_preferred":[
        "B\u0101nda Zar\u012bn\u0101b\u0101d"
    ],
    "wof:name":"Chak Taja",
    "wof:placetype":"locality"
},
  "geometry": {"coordinates":[72.30209000000001,34.28897],"type":"Point"}
}