{
  "type": "Feature",
  "properties": {
    "gn:admin1_code":"04",
    "gn:asciiname":"Chak Thirty-seven North Branch",
    "gn:country_code":"PK",
    "gn:dem":193,
    "gn:feature_class":"P",
    "gn:feature_code":"PPL",
    "gn:name":"Chak Thirty-seven North Branch",
    "gn:population":0,
    "gn:timezone":"Asia/Karachi",
    "iso:country":"PK",
    "name:und_x_variant":[
        "Pindi Mi\u0101ha",
        "Chak 37 NB",
        "Pindi Mi\u0101na",
        "Chak Thirty-seven North Branch"
    ],
    "wof:name":"Chak Thirty-seven North Branch",
    "wof:placetype":"locality"
},
  "geometry": {"coordinates":[72.7064,32.14108],"type":"Point"}
}