{
  "type": "Feature",
  "properties": {
    "gn:admin1_code":"6.0",
    "gn:asciiname":"Tailian-di-Dhok",
    "gn:country_code":"PK",
    "gn:dem":411,
    "gn:feature_class":"P",
    "gn:feature_code":"PPL",
    "gn:name":"Tailian-di-Dhok",
    "gn:population":0,
    "gn:timezone":"Asia/Karachi",
    "iso:country":"PK",
    "wof:name":"Tailian-di-Dhok",
    "wof:placetype":"locality"
},
  "geometry": {"coordinates":[74.15094000000001,32.98709],"type":"Point"}
}