{
  "type": "Feature",
  "properties": {
    "gn:admin1_code":"4.0",
    "gn:asciiname":"Basti Salyia Rasul Shah",
    "gn:country_code":"PK",
    "gn:dem":88,
    "gn:feature_class":"P",
    "gn:feature_code":"PPL",
    "gn:name":"Basti Salyia Ras\u016bl Sh\u0101h",
    "gn:population":0,
    "gn:timezone":"Asia/Karachi",
    "iso:country":"PK",
    "name:urd_x_preferred":[
        "Basti Salyia Ras\u016bl Sh\u0101h"
    ],
    "wof:name":"Basti Salyia Rasul Shah",
    "wof:placetype":"locality"
},
  "geometry": {"coordinates":[70.71666999999999,28.77778],"type":"Point"}
}