{
  "type": "Feature",
  "properties": {
    "gn:admin1_code":"04",
    "gn:asciiname":"Mallian Kalan",
    "gn:country_code":"PK",
    "gn:dem":214,
    "gn:feature_class":"P",
    "gn:feature_code":"PPL",
    "gn:name":"Mallian Kalan",
    "gn:population":0,
    "gn:timezone":"Asia/Karachi",
    "iso:country":"PK",
    "name:und_x_variant":[
        "Mallian",
        "Mallian Kalan"
    ],
    "wof:name":"Mallian Kalan",
    "wof:placetype":"locality"
},
  "geometry": {"coordinates":[74.06733,31.7712],"type":"Point"}
}