{
  "type": "Feature",
  "properties": {
    "gn:admin1_code":"5.0",
    "gn:asciiname":"Goth Ismail",
    "gn:country_code":"PK",
    "gn:dem":250,
    "gn:feature_class":"P",
    "gn:feature_code":"PPL",
    "gn:name":"Goth Ismail",
    "gn:population":0,
    "gn:timezone":"Asia/Karachi",
    "iso:country":"PK",
    "wof:name":"Goth Ismail",
    "wof:placetype":"locality"
},
  "geometry": {"coordinates":[67.71153000000001,25.57073],"type":"Point"}
}