{
  "type": "Feature",
  "properties": {
    "gn:admin1_code":"4",
    "gn:asciiname":"Naurang da Thatta",
    "gn:country_code":"PK",
    "gn:dem":192,
    "gn:feature_class":"P",
    "gn:feature_code":"PPL",
    "gn:name":"Naurang da Thatta",
    "gn:population":0,
    "gn:timezone":"Asia/Karachi",
    "iso:country":"PK",
    "name:und_x_variant":[
        "Naurang ka Kot"
    ],
    "wof:name":"Naurang da Thatta",
    "wof:placetype":"locality"
},
  "geometry": {"coordinates":[73.70803000000002,31.39464000000001],"type":"Point"}
}