{
  "type": "Feature",
  "properties": {
    "gn:admin1_code":"5.0",
    "gn:asciiname":"Goth Kalwari Junejo",
    "gn:country_code":"PK",
    "gn:dem":61,
    "gn:feature_class":"P",
    "gn:feature_code":"PPL",
    "gn:name":"Goth Kalwari Junejo",
    "gn:population":0,
    "gn:timezone":"Asia/Karachi",
    "iso:country":"PK",
    "name:eng_x_preferred":[
        "Goth Kalw\u0101ri"
    ],
    "wof:name":"Goth Kalwari Junejo",
    "wof:placetype":"locality"
},
  "geometry": {"coordinates":[68.68913000000001,27.81364],"type":"Point"}
}