{
  "type": "Feature",
  "properties": {
    "gn:admin1_code":"2.0",
    "gn:asciiname":"Nasir Khan Jatoi",
    "gn:country_code":"PK",
    "gn:dem":65,
    "gn:feature_class":"P",
    "gn:feature_code":"PPL",
    "gn:name":"Nasir Khan Jatoi",
    "gn:population":0,
    "gn:timezone":"Asia/Karachi",
    "iso:country":"PK",
    "wof:name":"Nasir Khan Jatoi",
    "wof:placetype":"locality"
},
  "geometry": {"coordinates":[68.13093000000001,28.45636],"type":"Point"}
}