{
  "type": "Feature",
  "properties": {
    "gn:admin1_code":"5",
    "gn:asciiname":"Andar",
    "gn:country_code":"PK",
    "gn:dem":77,
    "gn:feature_class":"P",
    "gn:feature_code":"PPL",
    "gn:name":"Andar",
    "gn:population":0,
    "gn:timezone":"Asia/Karachi",
    "iso:country":"PK",
    "name:por_x_preferred":[
        "Andar"
    ],
    "wof:name":"Andar",
    "wof:placetype":"locality"
},
  "geometry": {"coordinates":[69.80999,28.32642],"type":"Point"}
}