{
  "type": "Feature",
  "properties": {
    "gn:admin1_code":"2",
    "gn:asciiname":"Parshagai",
    "gn:country_code":"PK",
    "gn:dem":2428,
    "gn:feature_class":"P",
    "gn:feature_code":"PPL",
    "gn:name":"Parshagai",
    "gn:population":0,
    "gn:timezone":"Asia/Karachi",
    "iso:country":"PK",
    "name:eng_x_preferred":[
        "Parshagai H\u0101bo"
    ],
    "wof:name":"Parshagai",
    "wof:placetype":"locality"
},
  "geometry": {"coordinates":[67.69126999999999,31.18107],"type":"Point"}
}