{
  "type": "Feature",
  "properties": {
    "gn:admin1_code":"4.0",
    "gn:asciiname":"Hassanabad",
    "gn:country_code":"PK",
    "gn:dem":208,
    "gn:feature_class":"P",
    "gn:feature_code":"PPL",
    "gn:name":"Hassanabad",
    "gn:population":0,
    "gn:timezone":"Asia/Karachi",
    "iso:country":"PK",
    "name:und_x_variant":[
        "Hasanab\u0101d"
    ],
    "wof:name":"Hassanabad",
    "wof:placetype":"locality"
},
  "geometry": {"coordinates":[74.23451,31.44237],"type":"Point"}
}