{
  "type": "Feature",
  "properties": {
    "gn:admin1_code":"2",
    "gn:asciiname":"Goth Jalal Khan",
    "gn:country_code":"PK",
    "gn:dem":104,
    "gn:feature_class":"P",
    "gn:feature_code":"PPL",
    "gn:name":"Goth Jalal Khan",
    "gn:population":0,
    "gn:timezone":"Asia/Karachi",
    "iso:country":"PK",
    "name:und_x_variant":[
        "Goth Jal\u0101l Kh\u0101n Khia"
    ],
    "wof:name":"Goth Jalal Khan",
    "wof:placetype":"locality"
},
  "geometry": {"coordinates":[68.22887,28.93878],"type":"Point"}
}