{
  "type": "Feature",
  "properties": {
    "gn:admin1_code":"4.0",
    "gn:asciiname":"Dhakwaia",
    "gn:country_code":"PK",
    "gn:dem":211,
    "gn:feature_class":"P",
    "gn:feature_code":"PPL",
    "gn:name":"Dhakwaia",
    "gn:population":0,
    "gn:timezone":"Asia/Karachi",
    "iso:country":"PK",
    "name:und_x_variant":[
        "Dhakw\u0101la"
    ],
    "wof:name":"Dhakwaia",
    "wof:placetype":"locality"
},
  "geometry": {"coordinates":[73.93914000000002,31.85405],"type":"Point"}
}