{
  "type": "Feature",
  "properties": {
    "gn:admin1_code":"1.0",
    "gn:asciiname":"Ban Kurman",
    "gn:country_code":"PK",
    "gn:dem":391,
    "gn:feature_class":"P",
    "gn:feature_code":"PPL",
    "gn:name":"Ban Kurman",
    "gn:population":0,
    "gn:timezone":"Asia/Karachi",
    "iso:country":"PK",
    "wof:name":"Ban Kurman",
    "wof:placetype":"locality"
},
  "geometry": {"coordinates":[73.74623000000003,33.12863],"type":"Point"}
}