{
  "type": "Feature",
  "properties": {
    "gn:admin1_code":"5.0",
    "gn:asciiname":"Chakar Mohana",
    "gn:country_code":"PK",
    "gn:dem":6,
    "gn:feature_class":"P",
    "gn:feature_code":"PPL",
    "gn:name":"Chakar Mohana",
    "gn:population":0,
    "gn:timezone":"Asia/Karachi",
    "iso:country":"PK",
    "name:eng_x_preferred":[
        "Chakar Mohana"
    ],
    "wof:name":"Chakar Mohana",
    "wof:placetype":"locality"
},
  "geometry": {"coordinates":[68.24995,24.51694],"type":"Point"}
}