{
  "type": "Feature",
  "properties": {
    "gn:admin1_code":"4",
    "gn:asciiname":"Lambor",
    "gn:country_code":"PK",
    "gn:dem":236,
    "gn:feature_class":"P",
    "gn:feature_code":"PPL",
    "gn:name":"Lambor",
    "gn:population":0,
    "gn:timezone":"Asia/Karachi",
    "iso:country":"PK",
    "name:und_x_variant":[
        "Lambhor"
    ],
    "wof:name":"Lambor",
    "wof:placetype":"locality"
},
  "geometry": {"coordinates":[73.87673000000002,32.65129],"type":"Point"}
}