{
  "type": "Feature",
  "properties": {
    "gn:admin1_code":"01",
    "gn:asciiname":"Bakirai",
    "gn:country_code":"PK",
    "gn:dem":2292,
    "gn:feature_class":"P",
    "gn:feature_code":"PPL",
    "gn:name":"Bakirai",
    "gn:population":0,
    "gn:timezone":"Asia/Karachi",
    "iso:country":"PK",
    "name:und_x_variant":[
        "Bekarai"
    ],
    "wof:name":"Bakirai",
    "wof:placetype":"locality"
},
  "geometry": {"coordinates":[69.51193000000001,32.72392],"type":"Point"}
}