{
  "type": "Feature",
  "properties": {
    "gn:admin1_code":"4.0",
    "gn:asciiname":"Jhar Sikkha",
    "gn:country_code":"PK",
    "gn:dem":209,
    "gn:feature_class":"P",
    "gn:feature_code":"PPL",
    "gn:name":"Jhar Sikkha",
    "gn:population":0,
    "gn:timezone":"Asia/Karachi",
    "iso:country":"PK",
    "name:und_x_variant":[
        "Jh\u0101r Sikkh\u0101n",
        "Jh\u0101i Kal\u0101n",
        "Jhar Sikkha"
    ],
    "wof:name":"Jhar Sikkha",
    "wof:placetype":"locality"
},
  "geometry": {"coordinates":[73.8365,31.94408],"type":"Point"}
}