{
  "type": "Feature",
  "properties": {
    "gn:admin1_code":"3.0",
    "gn:asciiname":"Sara Shah",
    "gn:country_code":"PK",
    "gn:dem":410,
    "gn:feature_class":"P",
    "gn:feature_code":"PPL",
    "gn:name":"Sara Shah",
    "gn:population":0,
    "gn:timezone":"Asia/Karachi",
    "iso:country":"PK",
    "wof:name":"Sara Shah",
    "wof:placetype":"locality"
},
  "geometry": {"coordinates":[71.63208,34.36372],"type":"Point"}
}