{
  "type": "Feature",
  "properties": {
    "gn:admin1_code":"7.0",
    "gn:asciiname":"Keh Hatun",
    "gn:country_code":"PK",
    "gn:dem":1978,
    "gn:feature_class":"P",
    "gn:feature_code":"PPL",
    "gn:name":"Keh Hatun",
    "gn:population":0,
    "gn:timezone":"Asia/Karachi",
    "iso:country":"PK",
    "wof:name":"Keh Hatun",
    "wof:placetype":"locality"
},
  "geometry": {"coordinates":[73.75194999999999,36.25928],"type":"Point"}
}