{
  "type": "Feature",
  "properties": {
    "gn:admin1_code":"3.0",
    "gn:asciiname":"Arakh",
    "gn:country_code":"PK",
    "gn:dem":1476,
    "gn:feature_class":"P",
    "gn:feature_code":"PPL",
    "gn:name":"Arakh",
    "gn:population":0,
    "gn:timezone":"Asia/Karachi",
    "iso:country":"PK",
    "wof:name":"Arakh",
    "wof:placetype":"locality"
},
  "geometry": {"coordinates":[71.93436,35.04603],"type":"Point"}
}