{
  "type": "Feature",
  "properties": {
    "gn:admin1_code":"4.0",
    "gn:asciiname":"Dodar",
    "gn:country_code":"PK",
    "gn:dem":711,
    "gn:feature_class":"P",
    "gn:feature_code":"PPL",
    "gn:name":"Dodar",
    "gn:population":0,
    "gn:timezone":"Asia/Karachi",
    "iso:country":"PK",
    "name:eng_x_preferred":[
        "Dodar"
    ],
    "wof:name":"Dodar",
    "wof:placetype":"locality"
},
  "geometry": {"coordinates":[70.19396,30.05505],"type":"Point"}
}