{
  "type": "Feature",
  "properties": {
    "gn:admin1_code":"3.0",
    "gn:asciiname":"Mian Isa",
    "gn:country_code":"PK",
    "gn:dem":343,
    "gn:feature_class":"P",
    "gn:feature_code":"PPL",
    "gn:name":"Mian Isa",
    "gn:population":0,
    "gn:timezone":"Asia/Karachi",
    "iso:country":"PK",
    "name:eng_x_preferred":[
        "Mi\u0101n \u012asa"
    ],
    "wof:name":"Mian Isa",
    "wof:placetype":"locality"
},
  "geometry": {"coordinates":[71.5724,34.24437],"type":"Point"}
}