{
  "type": "Feature",
  "properties": {
    "gn:admin1_code":"5",
    "gn:asciiname":"Goth Saleh Muhammad Dandu",
    "gn:country_code":"PK",
    "gn:dem":77,
    "gn:feature_class":"P",
    "gn:feature_code":"PPL",
    "gn:name":"Goth Saleh Muhammad Dandu",
    "gn:population":0,
    "gn:timezone":"Asia/Karachi",
    "iso:country":"PK",
    "name:und_x_variant":[
        "Sadi Kh\u0101n"
    ],
    "wof:name":"Goth Saleh Muhammad Dandu",
    "wof:placetype":"locality"
},
  "geometry": {"coordinates":[69.60098000000001,28.23591],"type":"Point"}
}