{
  "type": "Feature",
  "properties": {
    "gn:admin1_code":"5",
    "gn:asciiname":"Goth Allahyar",
    "gn:country_code":"PK",
    "gn:dem":51,
    "gn:feature_class":"P",
    "gn:feature_code":"PPL",
    "gn:name":"Goth Allahyar",
    "gn:population":0,
    "gn:timezone":"Asia/Karachi",
    "iso:country":"PK",
    "name:und_x_variant":[
        "Goth All\u0101hy\u0101r Kh\u0101n"
    ],
    "wof:name":"Goth Allahyar",
    "wof:placetype":"locality"
},
  "geometry": {"coordinates":[68.52599000000001,26.93999],"type":"Point"}
}