{
  "type": "Feature",
  "properties": {
    "gn:admin1_code":"5",
    "gn:asciiname":"Goth Butta",
    "gn:country_code":"PK",
    "gn:dem":14,
    "gn:feature_class":"P",
    "gn:feature_code":"PPL",
    "gn:name":"Goth Butta",
    "gn:population":0,
    "gn:timezone":"Asia/Karachi",
    "iso:country":"PK",
    "name:und_x_variant":[
        "Goth B\u016bta"
    ],
    "wof:name":"Goth Butta",
    "wof:placetype":"locality"
},
  "geometry": {"coordinates":[69.02526999999999,25.18007],"type":"Point"}
}