{
  "type": "Feature",
  "properties": {
    "gn:admin1_code":"4",
    "gn:asciiname":"Chah Nakpi",
    "gn:country_code":"PK",
    "gn:dem":150,
    "gn:feature_class":"P",
    "gn:feature_code":"PPL",
    "gn:name":"Chah Nakpi",
    "gn:population":0,
    "gn:timezone":"Asia/Karachi",
    "iso:country":"PK",
    "name:und_x_variant":[
        "Nakkappi",
        "Chah Nakpi"
    ],
    "wof:name":"Chah Nakpi",
    "wof:placetype":"locality"
},
  "geometry": {"coordinates":[70.97138000000002,31.03768],"type":"Point"}
}