{
  "type": "Feature",
  "properties": {
    "gn:admin1_code":"4.0",
    "gn:asciiname":"Dorewala",
    "gn:country_code":"PK",
    "gn:dem":113,
    "gn:feature_class":"P",
    "gn:feature_code":"PPL",
    "gn:name":"Dorewala",
    "gn:population":0,
    "gn:timezone":"Asia/Karachi",
    "iso:country":"PK",
    "name:und_x_variant":[
        "Dhoraw\u0101la"
    ],
    "wof:name":"Dorewala",
    "wof:placetype":"locality"
},
  "geometry": {"coordinates":[71.43307,29.6199],"type":"Point"}
}