{
  "type": "Feature",
  "properties": {
    "gn:admin1_code":"6",
    "gn:asciiname":"Bhurjali",
    "gn:country_code":"PK",
    "gn:dem":3002,
    "gn:feature_class":"P",
    "gn:feature_code":"PPL",
    "gn:name":"Bhurjali",
    "gn:population":0,
    "gn:timezone":"Asia/Karachi",
    "iso:country":"PK",
    "name:und_x_variant":[
        "Barjamiali",
        "Bhurj\u0101li"
    ],
    "wof:name":"Bhurjali",
    "wof:placetype":"locality"
},
  "geometry": {"coordinates":[74.1151,34.7323],"type":"Point"}
}