{
  "type": "Feature",
  "properties": {
    "gn:admin1_code":"2.0",
    "gn:asciiname":"Zia Qambrani",
    "gn:country_code":"PK",
    "gn:dem":1187,
    "gn:feature_class":"P",
    "gn:feature_code":"PPL",
    "gn:name":"Zia Qambrani",
    "gn:population":0,
    "gn:timezone":"Asia/Karachi",
    "iso:country":"PK",
    "wof:name":"Zia Qambrani",
    "wof:placetype":"locality"
},
  "geometry": {"coordinates":[66.25166999999999,27.66751],"type":"Point"}
}