{
  "type": "Feature",
  "properties": {
    "gn:admin1_code":"3",
    "gn:asciiname":"Lao Nisar",
    "gn:country_code":"PK",
    "gn:dem":1726,
    "gn:feature_class":"P",
    "gn:feature_code":"PPL",
    "gn:name":"Lao Nisar",
    "gn:population":0,
    "gn:timezone":"Asia/Karachi",
    "iso:country":"PK",
    "name:eng_x_preferred":[
        "Lao Nissar"
    ],
    "wof:name":"Lao Nisar",
    "wof:placetype":"locality"
},
  "geometry": {"coordinates":[71.92035,35.6584],"type":"Point"}
}