{
  "type": "Feature",
  "properties": {
    "gn:admin1_code":"1.0",
    "gn:asciiname":"Samundari Mela",
    "gn:country_code":"PK",
    "gn:dem":550,
    "gn:feature_class":"P",
    "gn:feature_code":"PPL",
    "gn:name":"Samundari Mela",
    "gn:population":0,
    "gn:timezone":"Asia/Karachi",
    "iso:country":"PK",
    "name:und_x_variant":[
        "Jabbe",
        "Jab\u0101"
    ],
    "wof:name":"Samundari Mela",
    "wof:placetype":"locality"
},
  "geometry": {"coordinates":[71.70132,33.59387],"type":"Point"}
}