{
  "type": "Feature",
  "properties": {
    "gn:admin1_code":"03",
    "gn:asciiname":"Narinjai",
    "gn:country_code":"PK",
    "gn:dem":918,
    "gn:feature_class":"P",
    "gn:feature_code":"PPL",
    "gn:name":"Narinjai",
    "gn:population":0,
    "gn:timezone":"Asia/Karachi",
    "iso:country":"PK",
    "name:eng_x_preferred":[
        "Narinjai"
    ],
    "wof:name":"Narinjai",
    "wof:placetype":"locality"
},
  "geometry": {"coordinates":[71.71919,34.62549],"type":"Point"}
}