{
  "type": "Feature",
  "properties": {
    "gn:admin1_code":"3.0",
    "gn:asciiname":"Gadbano Kalle",
    "gn:country_code":"PK",
    "gn:dem":335,
    "gn:feature_class":"P",
    "gn:feature_code":"PPL",
    "gn:name":"Gadbano Kalle",
    "gn:population":0,
    "gn:timezone":"Asia/Karachi",
    "iso:country":"PK",
    "wof:name":"Gadbano Kalle",
    "wof:placetype":"locality"
},
  "geometry": {"coordinates":[72.16701,34.09835],"type":"Point"}
}