{
  "type": "Feature",
  "properties": {
    "gn:admin1_code":"4.0",
    "gn:asciiname":"Dhok Moman",
    "gn:country_code":"PK",
    "gn:dem":690,
    "gn:feature_class":"P",
    "gn:feature_code":"PPL",
    "gn:name":"Dhok Moman",
    "gn:population":0,
    "gn:timezone":"Asia/Karachi",
    "iso:country":"PK",
    "name:und_x_variant":[
        "Moman"
    ],
    "wof:name":"Dhok Moman",
    "wof:placetype":"locality"
},
  "geometry": {"coordinates":[72.35389000000001,32.70396],"type":"Point"}
}