{
  "type": "Feature",
  "properties": {
    "gn:admin1_code":"5.0",
    "gn:asciiname":"Goth Haji Ahmad Setho",
    "gn:country_code":"PK",
    "gn:dem":4,
    "gn:feature_class":"P",
    "gn:feature_code":"PPL",
    "gn:name":"Goth Haji Ahmad Setho",
    "gn:population":0,
    "gn:timezone":"Asia/Karachi",
    "iso:country":"PK",
    "wof:name":"Goth Haji Ahmad Setho",
    "wof:placetype":"locality"
},
  "geometry": {"coordinates":[67.53024000000001,24.48034],"type":"Point"}
}