{
  "type": "Feature",
  "properties": {
    "gn:admin1_code":"3.0",
    "gn:asciiname":"Jehangirai",
    "gn:country_code":"PK",
    "gn:dem":3165,
    "gn:feature_class":"P",
    "gn:feature_code":"PPL",
    "gn:name":"Jehangirai",
    "gn:population":0,
    "gn:timezone":"Asia/Karachi",
    "iso:country":"PK",
    "wof:name":"Jehangirai",
    "wof:placetype":"locality"
},
  "geometry": {"coordinates":[72.69029999999999,35.05048],"type":"Point"}
}