{
  "type": "Feature",
  "properties": {
    "gn:admin1_code":"2.0",
    "gn:asciiname":"Channalkund",
    "gn:country_code":"PK",
    "gn:dem":1010,
    "gn:feature_class":"P",
    "gn:feature_code":"PPL",
    "gn:name":"Channalkund",
    "gn:population":0,
    "gn:timezone":"Asia/Karachi",
    "iso:country":"PK",
    "wof:name":"Channalkund",
    "wof:placetype":"locality"
},
  "geometry": {"coordinates":[66.17775999999999,27.06129],"type":"Point"}
}