{
  "type": "Feature",
  "properties": {
    "gn:admin1_code":"5",
    "gn:asciiname":"Haji Khan Kanjo",
    "gn:country_code":"PK",
    "gn:dem":74,
    "gn:feature_class":"P",
    "gn:feature_code":"PPL",
    "gn:name":"Haji Khan Kanjo",
    "gn:population":0,
    "gn:timezone":"Asia/Karachi",
    "iso:country":"PK",
    "name:und_x_variant":[
        "H\u0101ji K\u0101njo"
    ],
    "wof:name":"Haji Khan Kanjo",
    "wof:placetype":"locality"
},
  "geometry": {"coordinates":[69.72887,28.06056],"type":"Point"}
}