{
  "type": "Feature",
  "properties": {
    "gn:admin1_code":"4",
    "gn:asciiname":"Diwan Sahib",
    "gn:country_code":"PK",
    "gn:dem":164,
    "gn:feature_class":"P",
    "gn:feature_code":"PPL",
    "gn:name":"Diwan Sahib",
    "gn:population":0,
    "gn:timezone":"Asia/Karachi",
    "iso:country":"PK",
    "name:und_x_variant":[
        "Kot D\u012bw\u0101n S\u0101hib"
    ],
    "wof:name":"Diwan Sahib",
    "wof:placetype":"locality"
},
  "geometry": {"coordinates":[73.34458000000002,30.29853],"type":"Point"}
}