{
  "type": "Feature",
  "properties": {
    "gn:admin1_code":"4",
    "gn:asciiname":"Basti Murad Khan Chang",
    "gn:country_code":"PK",
    "gn:dem":78,
    "gn:feature_class":"P",
    "gn:feature_code":"PPL",
    "gn:name":"Basti Murad Khan Chang",
    "gn:population":0,
    "gn:timezone":"Asia/Karachi",
    "iso:country":"PK",
    "name:und_x_variant":[
        "Basti Mu\u0101d Kh\u0101n"
    ],
    "wof:name":"Basti Murad Khan Chang",
    "wof:placetype":"locality"
},
  "geometry": {"coordinates":[69.82669,28.35116],"type":"Point"}
}