{
  "type": "Feature",
  "properties": {
    "gn:admin1_code":"5.0",
    "gn:asciiname":"Bakhshu Faqir",
    "gn:country_code":"PK",
    "gn:dem":101,
    "gn:feature_class":"P",
    "gn:feature_code":"PPL",
    "gn:name":"Bakhshu Faqir",
    "gn:population":0,
    "gn:timezone":"Asia/Karachi",
    "iso:country":"PK",
    "wof:name":"Bakhshu Faqir",
    "wof:placetype":"locality"
},
  "geometry": {"coordinates":[67.61006999999999,24.92254],"type":"Point"}
}