{
  "type": "Feature",
  "properties": {
    "gn:admin1_code":"2.0",
    "gn:asciiname":"Fatihani",
    "gn:country_code":"PK",
    "gn:dem":1108,
    "gn:feature_class":"P",
    "gn:feature_code":"PPL",
    "gn:name":"Fatihani",
    "gn:population":0,
    "gn:timezone":"Asia/Karachi",
    "iso:country":"PK",
    "name:und_x_variant":[
        "Moza Rahmt\u0101ni"
    ],
    "wof:name":"Fatihani",
    "wof:placetype":"locality"
},
  "geometry": {"coordinates":[69.92204,30.06803],"type":"Point"}
}