{
  "type": "Feature",
  "properties": {
    "gn:admin1_code":"4",
    "gn:asciiname":"Basti Dina",
    "gn:country_code":"PK",
    "gn:dem":106,
    "gn:feature_class":"P",
    "gn:feature_code":"PPL",
    "gn:name":"Basti Dina",
    "gn:population":0,
    "gn:timezone":"Asia/Karachi",
    "iso:country":"PK",
    "name:und_x_variant":[
        "Basti D\u012bni\u0101n"
    ],
    "wof:name":"Basti Dina",
    "wof:placetype":"locality"
},
  "geometry": {"coordinates":[70.95612,29.50221],"type":"Point"}
}