{
  "type": "Feature",
  "properties": {
    "gn:admin1_code":"4",
    "gn:asciiname":"Eisan Maharwala",
    "gn:country_code":"PK",
    "gn:dem":121,
    "gn:feature_class":"P",
    "gn:feature_code":"PPL",
    "gn:name":"Eisan Maharwala",
    "gn:population":0,
    "gn:timezone":"Asia/Karachi",
    "iso:country":"PK",
    "name:und_x_variant":[
        "Mah\u0101rw\u0101la"
    ],
    "wof:name":"Eisan Maharwala",
    "wof:placetype":"locality"
},
  "geometry": {"coordinates":[71.03317,29.96161],"type":"Point"}
}