{
  "type": "Feature",
  "properties": {
    "gn:admin1_code":"5.0",
    "gn:asciiname":"Manghat",
    "gn:country_code":"PK",
    "gn:dem":42,
    "gn:feature_class":"P",
    "gn:feature_code":"PPL",
    "gn:name":"Manghat",
    "gn:population":0,
    "gn:timezone":"Asia/Karachi",
    "iso:country":"PK",
    "name:und_x_variant":[
        "Munghat"
    ],
    "wof:name":"Manghat",
    "wof:placetype":"locality"
},
  "geometry": {"coordinates":[69.96896,24.4568],"type":"Point"}
}