{
  "type": "Feature",
  "properties": {
    "gn:admin1_code":"4",
    "gn:asciiname":"Nawan Pir Bakhshwala",
    "gn:country_code":"PK",
    "gn:dem":126,
    "gn:feature_class":"P",
    "gn:feature_code":"PPL",
    "gn:name":"Naw\u0101n P\u012br Bakhshw\u0101la",
    "gn:population":0,
    "gn:timezone":"Asia/Karachi",
    "iso:country":"PK",
    "wof:name":"Nawan Pir Bakhshwala",
    "wof:placetype":"locality"
},
  "geometry": {"coordinates":[71.22083000000001,30.30417000000001],"type":"Point"}
}