{
  "type": "Feature",
  "properties": {
    "gn:admin1_code":"5.0",
    "gn:asciiname":"Goth Murad Ali Zaur",
    "gn:country_code":"PK",
    "gn:dem":13,
    "gn:feature_class":"P",
    "gn:feature_code":"PPL",
    "gn:name":"Goth Murad Ali Zaur",
    "gn:population":0,
    "gn:timezone":"Asia/Karachi",
    "iso:country":"PK",
    "wof:name":"Goth Murad Ali Zaur",
    "wof:placetype":"locality"
},
  "geometry": {"coordinates":[68.21904000000001,24.78131],"type":"Point"}
}