{
  "type": "Feature",
  "properties": {
    "gn:country":"PK",
    "gn:fcode":"PPL",
    "gn:population":67439,
    "iso:country":"PK",
    "name:und_x_variant":[
        "Shorkot"
    ],
    "qs:name":"Shorko",
    "qs:photos_9r":0,
    "qs:photos_sr":0,
    "qs:pop_sr":"8",
    "wof:name":"Shorko",
    "wof:placetype":"locality",
    "wof:population":67439
},
  "geometry": {"coordinates":[70.87741,31.90991],"type":"Point"}
}