{
  "type": "Feature",
  "properties": {
    "gn:admin1_code":"4.0",
    "gn:asciiname":"Khark",
    "gn:country_code":"PK",
    "gn:dem":222,
    "gn:feature_class":"P",
    "gn:feature_code":"PPL",
    "gn:name":"Khark",
    "gn:population":0,
    "gn:timezone":"Asia/Karachi",
    "iso:country":"PK",
    "name:und_x_variant":[
        "Kharak"
    ],
    "wof:name":"Khark",
    "wof:placetype":"locality"
},
  "geometry": {"coordinates":[74.59926,31.56701],"type":"Point"}
}