{
  "type": "Feature",
  "properties": {
    "gn:admin1_code":"2.0",
    "gn:asciiname":"Sorgazo",
    "gn:country_code":"PK",
    "gn:dem":655,
    "gn:feature_class":"P",
    "gn:feature_code":"PPL",
    "gn:name":"Sorgazo",
    "gn:population":0,
    "gn:timezone":"Asia/Karachi",
    "iso:country":"PK",
    "name:und_x_variant":[
        "Kili S\u016brgazo"
    ],
    "wof:name":"Sorgazo",
    "wof:placetype":"locality"
},
  "geometry": {"coordinates":[65.09119,28.24342],"type":"Point"}
}