{
  "type": "Feature",
  "properties": {
    "gn:admin1_code":"5.0",
    "gn:asciiname":"Goth Nabi Bakhsh Hajano",
    "gn:country_code":"PK",
    "gn:dem":52,
    "gn:feature_class":"P",
    "gn:feature_code":"PPL",
    "gn:name":"Goth Nabi Bakhsh Haj\u0101no",
    "gn:population":0,
    "gn:timezone":"Asia/Karachi",
    "iso:country":"PK",
    "wof:name":"Goth Nabi Bakhsh Hajano",
    "wof:placetype":"locality"
},
  "geometry": {"coordinates":[68.25228,27.93627],"type":"Point"}
}