{
  "type": "Feature",
  "properties": {
    "gn:admin1_code":"4.0",
    "gn:asciiname":"Pharphago",
    "gn:country_code":"PK",
    "gn:dem":1446,
    "gn:feature_class":"P",
    "gn:feature_code":"PPL",
    "gn:name":"Pharphago",
    "gn:population":0,
    "gn:timezone":"Asia/Karachi",
    "iso:country":"PK",
    "wof:name":"Pharphago",
    "wof:placetype":"locality"
},
  "geometry": {"coordinates":[70.15985999999999,30.43225],"type":"Point"}
}