{
  "type": "Feature",
  "properties": {
    "gn:admin1_code":"2.0",
    "gn:asciiname":"Kili Soro",
    "gn:country_code":"PK",
    "gn:dem":2029,
    "gn:feature_class":"P",
    "gn:feature_code":"PPL",
    "gn:name":"Kili Soro",
    "gn:population":0,
    "gn:timezone":"Asia/Karachi",
    "iso:country":"PK",
    "name:eng_x_preferred":[
        "Kili Soro"
    ],
    "wof:name":"Kili Soro",
    "wof:placetype":"locality"
},
  "geometry": {"coordinates":[67.39412,30.66832],"type":"Point"}
}