{
  "type": "Feature",
  "properties": {
    "gn:admin1_code":"4.0",
    "gn:asciiname":"Khairan-na-Maira",
    "gn:country_code":"PK",
    "gn:dem":695,
    "gn:feature_class":"P",
    "gn:feature_code":"PPL",
    "gn:name":"Khairan-na-Maira",
    "gn:population":0,
    "gn:timezone":"Asia/Karachi",
    "iso:country":"PK",
    "name:eng_x_preferred":[
        "Kharan na Maira"
    ],
    "wof:name":"Khairan-na-Maira",
    "wof:placetype":"locality"
},
  "geometry": {"coordinates":[73.25301999999998,33.78985],"type":"Point"}
}