{
  "type": "Feature",
  "properties": {
    "gn:admin1_code":"2",
    "gn:asciiname":"Amun Kor",
    "gn:country_code":"PK",
    "gn:dem":1237,
    "gn:feature_class":"P",
    "gn:feature_code":"PPL",
    "gn:name":"Amun Kor",
    "gn:population":0,
    "gn:timezone":"Asia/Karachi",
    "iso:country":"PK",
    "wof:name":"Amun Kor",
    "wof:placetype":"locality"
},
  "geometry": {"coordinates":[68.88333,30.38194],"type":"Point"}
}