{
  "type": "Feature",
  "properties": {
    "gn:admin1_code":"5.0",
    "gn:asciiname":"Allah Bakhsh Chandani",
    "gn:country_code":"PK",
    "gn:dem":9,
    "gn:feature_class":"P",
    "gn:feature_code":"PPL",
    "gn:name":"Allah Bakhsh Chandani",
    "gn:population":0,
    "gn:timezone":"Asia/Karachi",
    "iso:country":"PK",
    "name:eng_x_preferred":[
        "Allah Bakhsh Chandani"
    ],
    "wof:name":"Allah Bakhsh Chandani",
    "wof:placetype":"locality"
},
  "geometry": {"coordinates":[68.22505,24.6653],"type":"Point"}
}