{
  "type": "Feature",
  "properties": {
    "gn:admin1_code":"04",
    "gn:asciiname":"Kohar",
    "gn:country_code":"PK",
    "gn:dem":245,
    "gn:feature_class":"P",
    "gn:feature_code":"PPL",
    "gn:name":"Kohar",
    "gn:population":0,
    "gn:timezone":"Asia/Karachi",
    "iso:country":"PK",
    "name:tat_x_preferred":[
        "\u041a\u043e\u04bb\u0430\u0440"
    ],
    "wof:name":"Kohar",
    "wof:placetype":"locality"
},
  "geometry": {"coordinates":[70.48390000000001,30.80197],"type":"Point"}
}