{
  "type": "Feature",
  "properties": {
    "gn:admin1_code":"4",
    "gn:asciiname":"Chak Two Hundred Fifty-three Eastern Bar",
    "gn:country_code":"PK",
    "gn:dem":151,
    "gn:feature_class":"P",
    "gn:feature_code":"PPL",
    "gn:name":"Chak Two Hundred Fifty-three Eastern Bar",
    "gn:population":0,
    "gn:timezone":"Asia/Karachi",
    "iso:country":"PK",
    "name:und_x_variant":[
        "Chak Two Hundred Fifty-three",
        "Tufa\u012bl\u0101b\u0101d"
    ],
    "wof:name":"Chak Two Hundred Fifty-three Eastern Bar",
    "wof:placetype":"locality"
},
  "geometry": {"coordinates":[72.79519999999999,30.19138],"type":"Point"}
}