{
  "type": "Feature",
  "properties": {
    "gn:admin1_code":"7.0",
    "gn:asciiname":"Diyal Khan di Baihk",
    "gn:country_code":"PK",
    "gn:dem":3478,
    "gn:feature_class":"P",
    "gn:feature_code":"PPL",
    "gn:name":"Diyal Khan di Baihk",
    "gn:population":0,
    "gn:timezone":"Asia/Karachi",
    "iso:country":"PK",
    "wof:name":"Diyal Khan di Baihk",
    "wof:placetype":"locality"
},
  "geometry": {"coordinates":[73.83969,35.83122],"type":"Point"}
}