{
  "type": "Feature",
  "properties": {
    "gn:admin1_code":"04",
    "gn:asciiname":"Samina Gharbi",
    "gn:country_code":"PK",
    "gn:dem":116,
    "gn:feature_class":"P",
    "gn:feature_code":"PPL",
    "gn:name":"Samina Gharbi",
    "gn:population":0,
    "gn:timezone":"Asia/Karachi",
    "iso:country":"PK",
    "name:eng_x_preferred":[
        "Samina Gharbi"
    ],
    "name:eng_x_variant":[
        "Semin Gharbi"
    ],
    "wof:name":"Samina Gharbi",
    "wof:placetype":"locality"
},
  "geometry": {"coordinates":[70.75324999999999,30.00119],"type":"Point"}
}