{
  "type": "Feature",
  "properties": {
    "gn:admin1_code":"4",
    "gn:asciiname":"Sukhar Nahr",
    "gn:country_code":"PK",
    "gn:dem":232,
    "gn:feature_class":"P",
    "gn:feature_code":"PPL",
    "gn:name":"Sukhar Nahr",
    "gn:population":0,
    "gn:timezone":"Asia/Karachi",
    "iso:country":"PK",
    "name:und_x_variant":[
        "S\u016bkkho N\u0101h"
    ],
    "wof:name":"Sukhar Nahr",
    "wof:placetype":"locality"
},
  "geometry": {"coordinates":[74.23201999999998,32.37647],"type":"Point"}
}