{
  "type": "Feature",
  "properties": {
    "gn:admin1_code":"4",
    "gn:asciiname":"Chukhianwala",
    "gn:country_code":"PK",
    "gn:dem":195,
    "gn:feature_class":"P",
    "gn:feature_code":"PPL",
    "gn:name":"Chukhianwala",
    "gn:population":0,
    "gn:timezone":"Asia/Karachi",
    "iso:country":"PK",
    "name:und_x_variant":[
        "Chkhi\u0101nw\u0101la"
    ],
    "wof:name":"Chukhianwala",
    "wof:placetype":"locality"
},
  "geometry": {"coordinates":[73.82093,31.36026],"type":"Point"}
}