{
  "type": "Feature",
  "properties": {
    "gn:admin1_code":"02",
    "gn:asciiname":"Tutak",
    "gn:country_code":"PK",
    "gn:dem":1493,
    "gn:feature_class":"P",
    "gn:feature_code":"PPL",
    "gn:name":"Tutak",
    "gn:population":0,
    "gn:timezone":"Asia/Karachi",
    "iso:country":"PK",
    "wof:name":"Tutak",
    "wof:placetype":"locality"
},
  "geometry": {"coordinates":[66.35117,28.03582],"type":"Point"}
}