{
  "type": "Feature",
  "properties": {
    "gn:admin1_code":"3.0",
    "gn:asciiname":"Chehr",
    "gn:country_code":"PK",
    "gn:dem":1464,
    "gn:feature_class":"P",
    "gn:feature_code":"PPL",
    "gn:name":"Chehr",
    "gn:population":0,
    "gn:timezone":"Asia/Karachi",
    "iso:country":"PK",
    "name:fas_x_preferred":[
        "\u0686\u0647\u0627\u0631"
    ],
    "name:und_x_variant":[
        "Char",
        "Chhar",
        "Chehr"
    ],
    "wof:name":"Chehr",
    "wof:placetype":"locality"
},
  "geometry": {"coordinates":[73.14858000000002,34.11458],"type":"Point"}
}