{
  "type": "Feature",
  "properties": {
    "gn:admin1_code":"2.0",
    "gn:asciiname":"Goth Ali Jan",
    "gn:country_code":"PK",
    "gn:dem":66,
    "gn:feature_class":"P",
    "gn:feature_code":"PPL",
    "gn:name":"Goth Ali Jan",
    "gn:population":0,
    "gn:timezone":"Asia/Karachi",
    "iso:country":"PK",
    "name:und_x_variant":[
        "Muzaffar \u0100b\u0101d"
    ],
    "wof:name":"Goth Ali Jan",
    "wof:placetype":"locality"
},
  "geometry": {"coordinates":[67.9937,28.4484],"type":"Point"}
}