{
  "type": "Feature",
  "properties": {
    "gn:admin1_code":"7.0",
    "gn:asciiname":"Brapa",
    "gn:country_code":"PK",
    "gn:dem":2551,
    "gn:feature_class":"P",
    "gn:feature_code":"PPL",
    "gn:name":"Brapa",
    "gn:population":0,
    "gn:timezone":"Asia/Karachi",
    "iso:country":"PK",
    "wof:name":"Brapa",
    "wof:placetype":"locality"
},
  "geometry": {"coordinates":[75.03151,35.69922000000001],"type":"Point"}
}