{
  "type": "Feature",
  "properties": {
    "gn:admin1_code":"1.0",
    "gn:asciiname":"Aura Kor",
    "gn:country_code":"PK",
    "gn:dem":711,
    "gn:feature_class":"P",
    "gn:feature_code":"PPL",
    "gn:name":"Aura Kor",
    "gn:population":0,
    "gn:timezone":"Asia/Karachi",
    "iso:country":"PK",
    "wof:name":"Aura Kor",
    "wof:placetype":"locality"
},
  "geometry": {"coordinates":[71.43297,34.6212],"type":"Point"}
}