{
  "type": "Feature",
  "properties": {
    "gn:admin1_code":"3",
    "gn:asciiname":"Sakamodika",
    "gn:country_code":"PK",
    "gn:dem":3842,
    "gn:feature_class":"P",
    "gn:feature_code":"PPL",
    "gn:name":"Sakamodika",
    "gn:population":0,
    "gn:timezone":"Asia/Karachi",
    "iso:country":"PK",
    "wof:name":"Sakamodika",
    "wof:placetype":"locality"
},
  "geometry": {"coordinates":[71.45222,35.94194],"type":"Point"}
}