{
  "type": "Feature",
  "properties": {
    "gn:admin1_code":"2",
    "gn:asciiname":"Abdullah",
    "gn:country_code":"PK",
    "gn:dem":1525,
    "gn:feature_class":"P",
    "gn:feature_code":"PPL",
    "gn:name":"Abdullah",
    "gn:population":0,
    "gn:timezone":"Asia/Karachi",
    "iso:country":"PK",
    "name:eng_x_preferred":[
        "Abdullah"
    ],
    "wof:name":"Abdullah",
    "wof:placetype":"locality"
},
  "geometry": {"coordinates":[67.06083000000001,30.71306],"type":"Point"}
}