{
  "type": "Feature",
  "properties": {
    "gn:admin1_code":"05",
    "gn:asciiname":"Sandh",
    "gn:country_code":"PK",
    "gn:dem":81,
    "gn:feature_class":"P",
    "gn:feature_code":"PPL",
    "gn:name":"Sandh",
    "gn:population":0,
    "gn:timezone":"Asia/Karachi",
    "iso:country":"PK",
    "name:und_x_variant":[
        "Sandb",
        "Sandh"
    ],
    "wof:name":"Sandh",
    "wof:placetype":"locality"
},
  "geometry": {"coordinates":[70.03010999999999,27.88699],"type":"Point"}
}