{
  "type": "Feature",
  "properties": {
    "gn:admin1_code":"4.0",
    "gn:asciiname":"Manshian di Basti",
    "gn:country_code":"PK",
    "gn:dem":89,
    "gn:feature_class":"P",
    "gn:feature_code":"PPL",
    "gn:name":"Manshian di Basti",
    "gn:population":0,
    "gn:timezone":"Asia/Karachi",
    "iso:country":"PK",
    "wof:name":"Manshian di Basti",
    "wof:placetype":"locality"
},
  "geometry": {"coordinates":[70.67543000000001,28.61817000000001],"type":"Point"}
}