{
  "type": "Feature",
  "properties": {
    "gn:admin1_code":"5",
    "gn:asciiname":"Nar",
    "gn:country_code":"PK",
    "gn:dem":77,
    "gn:feature_class":"P",
    "gn:feature_code":"PPL",
    "gn:name":"Nar",
    "gn:population":0,
    "gn:timezone":"Asia/Karachi",
    "iso:country":"PK",
    "wof:name":"Nar",
    "wof:placetype":"locality"
},
  "geometry": {"coordinates":[68.02415999999999,25.43694],"type":"Point"}
}