{
  "type": "Feature",
  "properties": {
    "gn:admin1_code":"5.0",
    "gn:asciiname":"Goth Kari Tar",
    "gn:country_code":"PK",
    "gn:dem":21,
    "gn:feature_class":"P",
    "gn:feature_code":"PPL",
    "gn:name":"Goth Kari Tar",
    "gn:population":0,
    "gn:timezone":"Asia/Karachi",
    "iso:country":"PK",
    "name:und_x_variant":[
        "K\u0101ritar"
    ],
    "wof:name":"Goth Kari Tar",
    "wof:placetype":"locality"
},
  "geometry": {"coordinates":[70.72726,24.5567],"type":"Point"}
}