{
  "type": "Feature",
  "properties": {
    "gn:admin1_code":"04",
    "gn:asciiname":"Chak Thirty-six North Branch",
    "gn:country_code":"PK",
    "gn:dem":194,
    "gn:feature_class":"P",
    "gn:feature_code":"PPL",
    "gn:name":"Chak Thirty-six North Branch",
    "gn:population":0,
    "gn:timezone":"Asia/Karachi",
    "iso:country":"PK",
    "name:fas_x_preferred":[
        "\u0686\u06a9 \u06f3\u06f6 \u0627\u0646\u200c\u0628\u06cc"
    ],
    "name:und_x_variant":[
        "Zangoza",
        "Chak 36 NB",
        "Zangeza",
        "Chak Thirty-six North Branch"
    ],
    "wof:name":"Chak Thirty-six North Branch",
    "wof:placetype":"locality"
},
  "geometry": {"coordinates":[72.72929000000001,32.12541],"type":"Point"}
}