{
  "type": "Feature",
  "properties": {
    "gn:admin1_code":"3.0",
    "gn:asciiname":"Tarkan",
    "gn:country_code":"PK",
    "gn:dem":2042,
    "gn:feature_class":"P",
    "gn:feature_code":"PPL",
    "gn:name":"Tarkan",
    "gn:population":0,
    "gn:timezone":"Asia/Karachi",
    "iso:country":"PK",
    "name:bul_x_preferred":[
        "\u0422\u0430\u0440\u043a\u0430\u043d"
    ],
    "name:deu_x_preferred":[
        "Tarkan"
    ],
    "name:heb_x_preferred":[
        "\u05d8\u05d0\u05e8\u05e7\u05d0\u05df"
    ],
    "name:hun_x_preferred":[
        "Tarkan"
    ],
    "name:slk_x_preferred":[
        "Tarkan"
    ],
    "name:ukr_x_preferred":[
        "\u0422\u0430\u0440\u0445\u0430\u043d"
    ],
    "wof:name":"Tarkan",
    "wof:placetype":"locality"
},
  "geometry": {"coordinates":[73.1705,35.52641],"type":"Point"}
}