{
  "type": "Feature",
  "properties": {
    "gn:admin1_code":"3.0",
    "gn:asciiname":"Tarkan",
    "gn:country_code":"PK",
    "gn:dem":2042,
    "gn:feature_class":"P",
    "gn:feature_code":"PPL",
    "gn:name":"Tarkan",
    "gn:population":0,
    "gn:timezone":"Asia/Karachi",
    "iso:country":"PK",
    "wof:name":"Tarkan",
    "wof:placetype":"locality"
},
  "geometry": {"coordinates":[73.1705,35.52641],"type":"Point"}
}