{
  "type": "Feature",
  "properties": {
    "gn:admin1_code":"4",
    "gn:asciiname":"Barsalpur",
    "gn:country_code":"PK",
    "gn:dem":246,
    "gn:feature_class":"P",
    "gn:feature_code":"PPL",
    "gn:name":"Barsalpur",
    "gn:population":0,
    "gn:timezone":"Asia/Karachi",
    "iso:country":"PK",
    "name:und_x_variant":[
        "Wasalpur",
        "Bars\u0101lpur"
    ],
    "wof:name":"Barsalpur",
    "wof:placetype":"locality"
},
  "geometry": {"coordinates":[74.53716999999997,32.59754],"type":"Point"}
}