{
  "type": "Feature",
  "properties": {
    "gn:admin1_code":"4.0",
    "gn:asciiname":"Dharindian",
    "gn:country_code":"PK",
    "gn:dem":215,
    "gn:feature_class":"P",
    "gn:feature_code":"PPL",
    "gn:name":"Dharindian",
    "gn:population":0,
    "gn:timezone":"Asia/Karachi",
    "iso:country":"PK",
    "name:und_x_variant":[
        "Dharandian",
        "Dhirandi\u0101n",
        "Dhirindi\u0101n",
        "Dharindian"
    ],
    "wof:name":"Dharindian",
    "wof:placetype":"locality"
},
  "geometry": {"coordinates":[73.81131999999999,32.29377],"type":"Point"}
}