{
  "type": "Feature",
  "properties": {
    "gn:admin1_code":"4",
    "gn:asciiname":"Nawan Awanwala",
    "gn:country_code":"PK",
    "gn:dem":157,
    "gn:feature_class":"P",
    "gn:feature_code":"PPL",
    "gn:name":"Nawan Awanwala",
    "gn:population":0,
    "gn:timezone":"Asia/Karachi",
    "iso:country":"PK",
    "name:und_x_variant":[
        "Awanw\u0101la",
        "Kaharw\u0101la",
        "Nawan Awanwala"
    ],
    "wof:name":"Nawan Awanwala",
    "wof:placetype":"locality"
},
  "geometry": {"coordinates":[72.10139000000002,31.50443],"type":"Point"}
}