{
  "type": "Feature",
  "properties": {
    "gn:admin1_code":"2.0",
    "gn:asciiname":"Spin Ragheh",
    "gn:country_code":"PK",
    "gn:dem":1555,
    "gn:feature_class":"P",
    "gn:feature_code":"PPL",
    "gn:name":"Spin Ragheh",
    "gn:population":0,
    "gn:timezone":"Asia/Karachi",
    "iso:country":"PK",
    "name:und_x_variant":[
        "Sarwa Kanrah"
    ],
    "wof:name":"Spin Ragheh",
    "wof:placetype":"locality"
},
  "geometry": {"coordinates":[69.90923000000001,31.39075],"type":"Point"}
}