{
  "type": "Feature",
  "properties": {
    "gn:admin1_code":"4",
    "gn:asciiname":"Tau",
    "gn:country_code":"PK",
    "gn:dem":259,
    "gn:feature_class":"P",
    "gn:feature_code":"PPL",
    "gn:name":"Tau",
    "gn:population":0,
    "gn:timezone":"Asia/Karachi",
    "iso:country":"PK",
    "name:und_x_variant":[
        "Tahu",
        "T\u0101u"
    ],
    "wof:name":"Tau",
    "wof:placetype":"locality"
},
  "geometry": {"coordinates":[74.65966999999998,32.51785],"type":"Point"}
}