{
  "type": "Feature",
  "properties": {
    "gn:admin1_code":"4.0",
    "gn:asciiname":"Jatoiwala",
    "gn:country_code":"PK",
    "gn:dem":123,
    "gn:feature_class":"P",
    "gn:feature_code":"PPL",
    "gn:name":"Jatoiwala",
    "gn:population":0,
    "gn:timezone":"Asia/Karachi",
    "iso:country":"PK",
    "name:eng_x_preferred":[
        "Jatoiwala"
    ],
    "wof:name":"Jatoiwala",
    "wof:placetype":"locality"
},
  "geometry": {"coordinates":[70.71984999999999,30.13643],"type":"Point"}
}