{
  "type": "Feature",
  "properties": {
    "gn:admin1_code":"3.0",
    "gn:asciiname":"Bazida Kokal Khel",
    "gn:country_code":"PK",
    "gn:dem":389,
    "gn:feature_class":"P",
    "gn:feature_code":"PPL",
    "gn:name":"Bazida Kokal Khel",
    "gn:population":0,
    "gn:timezone":"Asia/Karachi",
    "iso:country":"PK",
    "wof:name":"Bazida Kokal Khel",
    "wof:placetype":"locality"
},
  "geometry": {"coordinates":[70.61145,33.01819],"type":"Point"}
}