{
  "type": "Feature",
  "properties": {
    "gn:admin1_code":"3.0",
    "gn:asciiname":"Khandia Baihk",
    "gn:country_code":"PK",
    "gn:dem":3809,
    "gn:feature_class":"P",
    "gn:feature_code":"PPL",
    "gn:name":"Khandia Baihk",
    "gn:population":0,
    "gn:timezone":"Asia/Karachi",
    "iso:country":"PK",
    "wof:name":"Khandia Baihk",
    "wof:placetype":"locality"
},
  "geometry": {"coordinates":[74.0458,35.1378],"type":"Point"}
}