{
  "type": "Feature",
  "properties": {
    "gn:admin1_code":"6",
    "gn:asciiname":"Sundarmar",
    "gn:country_code":"PK",
    "gn:dem":2361,
    "gn:feature_class":"P",
    "gn:feature_code":"PPL",
    "gn:name":"Sundarmar",
    "gn:population":0,
    "gn:timezone":"Asia/Karachi",
    "iso:country":"PK",
    "name:und_x_variant":[
        "Sundaim\u0101l"
    ],
    "wof:name":"Sundarmar",
    "wof:placetype":"locality"
},
  "geometry": {"coordinates":[74.07041,33.95244],"type":"Point"}
}