{
  "type": "Feature",
  "properties": {
    "gn:admin1_code":"4",
    "gn:asciiname":"Faqiranwali",
    "gn:country_code":"PK",
    "gn:dem":236,
    "gn:feature_class":"P",
    "gn:feature_code":"PPL",
    "gn:name":"Faqiranwali",
    "gn:population":0,
    "gn:timezone":"Asia/Karachi",
    "iso:country":"PK",
    "wof:name":"Faqiranwali",
    "wof:placetype":"locality"
},
  "geometry": {"coordinates":[74.58544000000001,32.2298],"type":"Point"}
}