{
  "type": "Feature",
  "properties": {
    "gn:admin1_code":"6.0",
    "gn:asciiname":"Rettili",
    "gn:country_code":"PK",
    "gn:dem":455,
    "gn:feature_class":"P",
    "gn:feature_code":"PPL",
    "gn:name":"Rettili",
    "gn:population":0,
    "gn:timezone":"Asia/Karachi",
    "iso:country":"PK",
    "wof:name":"Rettili",
    "wof:placetype":"locality"
},
  "geometry": {"coordinates":[73.54885999999998,33.1633],"type":"Point"}
}