{
  "type": "Feature",
  "properties": {
    "gn:admin1_code":"5",
    "gn:asciiname":"Wakyani Sangi",
    "gn:country_code":"PK",
    "gn:dem":56,
    "gn:feature_class":"P",
    "gn:feature_code":"PPL",
    "gn:name":"Wakyani Sangi",
    "gn:population":0,
    "gn:timezone":"Asia/Karachi",
    "iso:country":"PK",
    "name:und_x_variant":[
        "Goth Vikia S\u0101ng",
        "Vikia S\u0101ngi",
        "Wakyani Sangi"
    ],
    "wof:name":"Wakyani Sangi",
    "wof:placetype":"locality"
},
  "geometry": {"coordinates":[68.22129,27.66752],"type":"Point"}
}