{
  "type": "Feature",
  "properties": {
    "gn:admin1_code":"3.0",
    "gn:asciiname":"Kandona",
    "gn:country_code":"PK",
    "gn:dem":819,
    "gn:feature_class":"P",
    "gn:feature_code":"PPL",
    "gn:name":"Kandona",
    "gn:population":0,
    "gn:timezone":"Asia/Karachi",
    "iso:country":"PK",
    "wof:name":"Kandona",
    "wof:placetype":"locality"
},
  "geometry": {"coordinates":[72.81169,34.05125],"type":"Point"}
}