{
  "type": "Feature",
  "properties": {
    "gn:admin1_code":"4",
    "gn:asciiname":"Nowshera",
    "gn:country_code":"PK",
    "gn:dem":223,
    "gn:feature_class":"P",
    "gn:feature_code":"PPL",
    "gn:name":"Nowshera",
    "gn:population":0,
    "gn:timezone":"Asia/Karachi",
    "iso:country":"PK",
    "name:und_x_variant":[
        "Naushahra"
    ],
    "wof:name":"Nowshera",
    "wof:placetype":"locality"
},
  "geometry": {"coordinates":[73.86959,32.53454],"type":"Point"}
}