{
  "type": "Feature",
  "properties": {
    "gn:admin1_code":"4",
    "gn:asciiname":"Nowshera",
    "gn:country_code":"PK",
    "gn:dem":223,
    "gn:feature_class":"P",
    "gn:feature_code":"PPL",
    "gn:name":"Nowshera",
    "gn:population":0,
    "gn:timezone":"Asia/Karachi",
    "iso:country":"PK",
    "name:ceb_x_preferred":[
        "Nowshera"
    ],
    "name:hin_x_preferred":[
        "\u0928\u094c\u0936\u0947\u0930\u093e"
    ],
    "name:pus_x_preferred":[
        "\u0646\u0648\u069a\u0627\u0631"
    ],
    "name:spa_x_preferred":[
        "Nowshera"
    ],
    "name:und_x_variant":[
        "Naushahra"
    ],
    "wof:name":"Nowshera",
    "wof:placetype":"locality"
},
  "geometry": {"coordinates":[73.86959,32.53454],"type":"Point"}
}