{
  "type": "Feature",
  "properties": {
    "gn:admin1_code":"3.0",
    "gn:asciiname":"Barwar Dhok",
    "gn:country_code":"PK",
    "gn:dem":599,
    "gn:feature_class":"P",
    "gn:feature_code":"PPL",
    "gn:name":"Barwar Dhok",
    "gn:population":0,
    "gn:timezone":"Asia/Karachi",
    "iso:country":"PK",
    "wof:name":"Barwar Dhok",
    "wof:placetype":"locality"
},
  "geometry": {"coordinates":[72.89591999999998,33.75284],"type":"Point"}
}