{
  "type": "Feature",
  "properties": {
    "gn:admin1_code":"3.0",
    "gn:asciiname":"Kuz Laikot",
    "gn:country_code":"PK",
    "gn:dem":2278,
    "gn:feature_class":"P",
    "gn:feature_code":"PPL",
    "gn:name":"Kuz Laikot",
    "gn:population":0,
    "gn:timezone":"Asia/Karachi",
    "iso:country":"PK",
    "name:eng_x_preferred":[
        "Kuz Laikot"
    ],
    "wof:name":"Kuz Laikot",
    "wof:placetype":"locality"
},
  "geometry": {"coordinates":[72.59246999999998,35.4376],"type":"Point"}
}