{
  "type": "Feature",
  "properties": {
    "gn:admin1_code":"2.0",
    "gn:asciiname":"Goth Haji Kehar Khan",
    "gn:country_code":"PK",
    "gn:dem":48,
    "gn:feature_class":"P",
    "gn:feature_code":"PPL",
    "gn:name":"Goth Haji Kehar Khan",
    "gn:population":0,
    "gn:timezone":"Asia/Karachi",
    "iso:country":"PK",
    "name:und_x_variant":[
        "H\u0101ji Kor Kh\u0101n"
    ],
    "wof:name":"Goth Haji Kehar Khan",
    "wof:placetype":"locality"
},
  "geometry": {"coordinates":[67.90819999999999,28.03779],"type":"Point"}
}