{
  "type": "Feature",
  "properties": {
    "gn:admin1_code":"3",
    "gn:asciiname":"Chhatri",
    "gn:country_code":"PK",
    "gn:dem":1977,
    "gn:feature_class":"P",
    "gn:feature_code":"PPL",
    "gn:name":"Chhatri",
    "gn:population":0,
    "gn:timezone":"Asia/Karachi",
    "iso:country":"PK",
    "name:deu_x_preferred":[
        "Chhatri"
    ],
    "name:fra_x_preferred":[
        "Chhatri"
    ],
    "name:hin_x_preferred":[
        "\u091b\u0924\u0930\u0940"
    ],
    "name:ind_x_preferred":[
        "Chhatri"
    ],
    "name:ita_x_preferred":[
        "Chhatri"
    ],
    "name:lit_x_preferred":[
        "\u010chatris"
    ],
    "name:msa_x_preferred":[
        "Chhatri"
    ],
    "name:ori_x_preferred":[
        "\u0b1b\u0b24\u0b4d\u0b30\u0b40"
    ],
    "name:pol_x_preferred":[
        "\u0106hatri"
    ],
    "name:rus_x_preferred":[
        "\u0427\u0430\u0442\u0440\u0438"
    ],
    "name:spa_x_preferred":[
        "Chhatri"
    ],
    "name:sqi_x_preferred":[
        "\u00c7hatri"
    ],
    "name:urd_x_preferred":[
        "\u0686\u06be\u062a\u0631\u06cc"
    ],
    "wof:name":"Chhatri",
    "wof:placetype":"locality"
},
  "geometry": {"coordinates":[73.33490999999999,34.19914],"type":"Point"}
}