{
  "type": "Feature",
  "properties": {
    "gn:admin1_code":"3",
    "gn:asciiname":"Chhatri",
    "gn:country_code":"PK",
    "gn:dem":1977,
    "gn:feature_class":"P",
    "gn:feature_code":"PPL",
    "gn:name":"Chhatri",
    "gn:population":0,
    "gn:timezone":"Asia/Karachi",
    "iso:country":"PK",
    "wof:name":"Chhatri",
    "wof:placetype":"locality"
},
  "geometry": {"coordinates":[73.33490999999999,34.19914],"type":"Point"}
}