{
  "type": "Feature",
  "properties": {
    "gn:admin1_code":"1.0",
    "gn:asciiname":"Shodat Khel",
    "gn:country_code":"PK",
    "gn:dem":602,
    "gn:feature_class":"P",
    "gn:feature_code":"PPL",
    "gn:name":"Shodat Khel",
    "gn:population":0,
    "gn:timezone":"Asia/Karachi",
    "iso:country":"PK",
    "name:und_x_variant":[
        "Sil\u0101i Palosi"
    ],
    "wof:name":"Shodat Khel",
    "wof:placetype":"locality"
},
  "geometry": {"coordinates":[70.38678,33.06063],"type":"Point"}
}