{
  "type": "Feature",
  "properties": {
    "gn:admin1_code":"01",
    "gn:asciiname":"Kochak",
    "gn:country_code":"PK",
    "gn:dem":877,
    "gn:feature_class":"P",
    "gn:feature_code":"PPL",
    "gn:name":"Kochak",
    "gn:population":0,
    "gn:timezone":"Asia/Karachi",
    "iso:country":"PK",
    "name:eng_x_preferred":[
        "Kochak"
    ],
    "name:und_x_variant":[
        "Kochak Tangai"
    ],
    "wof:name":"Kochak",
    "wof:placetype":"locality"
},
  "geometry": {"coordinates":[71.71621999999998,34.73644],"type":"Point"}
}