{
  "type": "Feature",
  "properties": {
    "gn:admin1_code":"4.0",
    "gn:asciiname":"Dhok Bijwal",
    "gn:country_code":"PK",
    "gn:dem":396,
    "gn:feature_class":"P",
    "gn:feature_code":"PPL",
    "gn:name":"Dhok Bijwal",
    "gn:population":0,
    "gn:timezone":"Asia/Karachi",
    "iso:country":"PK",
    "wof:name":"Dhok Bijwal",
    "wof:placetype":"locality"
},
  "geometry": {"coordinates":[72.35008000000001,33.50554],"type":"Point"}
}