{
  "type": "Feature",
  "properties": {
    "gn:admin1_code":"5.0",
    "gn:asciiname":"Goth Mahir Mahar",
    "gn:country_code":"PK",
    "gn:dem":65,
    "gn:feature_class":"P",
    "gn:feature_code":"PPL",
    "gn:name":"Goth Mahir Mahar",
    "gn:population":0,
    "gn:timezone":"Asia/Karachi",
    "iso:country":"PK",
    "name:und_x_variant":[
        "Goth Meh\u012br Mahar"
    ],
    "wof:name":"Goth Mahir Mahar",
    "wof:placetype":"locality"
},
  "geometry": {"coordinates":[69.25974000000001,27.81453],"type":"Point"}
}