{
  "type": "Feature",
  "properties": {
    "gn:admin1_code":"6",
    "gn:asciiname":"Hakan Dongan",
    "gn:country_code":"PK",
    "gn:dem":2691,
    "gn:feature_class":"P",
    "gn:feature_code":"PPL",
    "gn:name":"Hakan Dongan",
    "gn:population":0,
    "gn:timezone":"Asia/Karachi",
    "iso:country":"PK",
    "name:und_x_variant":[
        "H\u0101nk\u0101nd\u016bng\u0101n"
    ],
    "wof:name":"Hakan Dongan",
    "wof:placetype":"locality"
},
  "geometry": {"coordinates":[73.88905,34.52703],"type":"Point"}
}