{
  "type": "Feature",
  "properties": {
    "gn:admin1_code":"1.0",
    "gn:asciiname":"Adam Khel Banda",
    "gn:country_code":"PK",
    "gn:dem":776,
    "gn:feature_class":"P",
    "gn:feature_code":"PPL",
    "gn:name":"Adam Khel Banda",
    "gn:population":0,
    "gn:timezone":"Asia/Karachi",
    "iso:country":"PK",
    "wof:name":"Adam Khel Banda",
    "wof:placetype":"locality"
},
  "geometry": {"coordinates":[71.11105000000001,33.5374],"type":"Point"}
}