{
  "type": "Feature",
  "properties": {
    "gn:admin1_code":"2.0",
    "gn:asciiname":"Bhaba Kaul",
    "gn:country_code":"PK",
    "gn:dem":1806,
    "gn:feature_class":"P",
    "gn:feature_code":"PPL",
    "gn:name":"Bhaba Kaul",
    "gn:population":0,
    "gn:timezone":"Asia/Karachi",
    "iso:country":"PK",
    "wof:name":"Bhaba Kaul",
    "wof:placetype":"locality"
},
  "geometry": {"coordinates":[66.81583000000001,30.81728],"type":"Point"}
}