{
  "type": "Feature",
  "properties": {
    "gn:admin1_code":"2.0",
    "gn:asciiname":"Kili Rahim",
    "gn:country_code":"PK",
    "gn:dem":1655,
    "gn:feature_class":"P",
    "gn:feature_code":"PPL",
    "gn:name":"Kili Rahim",
    "gn:population":0,
    "gn:timezone":"Asia/Karachi",
    "iso:country":"PK",
    "wof:name":"Kili Rahim",
    "wof:placetype":"locality"
},
  "geometry": {"coordinates":[66.1206,29.26801],"type":"Point"}
}