{
  "type": "Feature",
  "properties": {
    "gn:admin1_code":"3",
    "gn:asciiname":"Jhok Arwaranwali",
    "gn:country_code":"PK",
    "gn:dem":185,
    "gn:feature_class":"P",
    "gn:feature_code":"PPL",
    "gn:name":"Jhok Arwaranwali",
    "gn:population":0,
    "gn:timezone":"Asia/Karachi",
    "iso:country":"PK",
    "wof:name":"Jhok Arwaranwali",
    "wof:placetype":"locality"
},
  "geometry": {"coordinates":[71.18465999999999,32.27595],"type":"Point"}
}