{
  "type": "Feature",
  "properties": {
    "gn:admin1_code":"5.0",
    "gn:asciiname":"Goth Jano Kharak",
    "gn:country_code":"PK",
    "gn:dem":11,
    "gn:feature_class":"P",
    "gn:feature_code":"PPL",
    "gn:name":"Goth Jano Kharak",
    "gn:population":0,
    "gn:timezone":"Asia/Karachi",
    "iso:country":"PK",
    "name:eng_x_preferred":[
        "Goth Jano Kharak"
    ],
    "wof:name":"Goth Jano Kharak",
    "wof:placetype":"locality"
},
  "geometry": {"coordinates":[68.23903,24.73181],"type":"Point"}
}