{
  "type": "Feature",
  "properties": {
    "gn:admin1_code":"2.0",
    "gn:asciiname":"Gulzar",
    "gn:country_code":"PK",
    "gn:dem":536,
    "gn:feature_class":"P",
    "gn:feature_code":"PPL",
    "gn:name":"Gulz\u0101r",
    "gn:population":0,
    "gn:timezone":"Asia/Karachi",
    "iso:country":"PK",
    "name:ara_x_preferred":[
        "\u063a\u0648\u0644\u0632\u0627\u0631"
    ],
    "name:asm_x_preferred":[
        "\u0997\u09c1\u09b2\u099c\u09be\u09f0"
    ],
    "name:ben_x_preferred":[
        "\u0997\u09c1\u09b2\u099c\u09be\u09b0"
    ],
    "name:deu_x_preferred":[
        "Gulzar"
    ],
    "name:fas_x_preferred":[
        "\u06af\u0644\u0632\u0627\u0631"
    ],
    "name:fin_x_preferred":[
        "Gulzar"
    ],
    "name:fra_x_preferred":[
        "Gulzar"
    ],
    "name:hin_x_preferred":[
        "\u0917\u0941\u0932\u091c\u093c\u093e\u0930"
    ],
    "name:hye_x_preferred":[
        "\u0533\u0578\u0582\u056c\u0566\u0561\u0580"
    ],
    "name:ind_x_preferred":[
        "Gulzar"
    ],
    "name:kan_x_preferred":[
        "\u0c97\u0cc1\u0cb2\u0ccd\u0c9c\u0cbe\u0cb0\u0ccd"
    ],
    "name:kor_x_preferred":[
        "\uad74\uc790\ub974"
    ],
    "name:mai_x_preferred":[
        "\u0917\u0941\u0932\u091c\u093e\u0930"
    ],
    "name:mal_x_preferred":[
        "\u0d17\u0d41\u0d7d\u0d38\u0d3e\u0d7c"
    ],
    "name:mar_x_preferred":[
        "\u0917\u0941\u0932\u091c\u093e\u0930"
    ],
    "name:mlg_x_preferred":[
        "Gulzar"
    ],
    "name:nno_x_preferred":[
        "Gulzar"
    ],
    "name:ori_x_preferred":[
        "\u0b17\u0b41\u0b32\u0b1c\u0b3e\u0b30"
    ],
    "name:pan_x_preferred":[
        "\u0a17\u0a41\u0a32\u0a1c\u0a3c\u0a3e\u0a30"
    ],
    "name:pnb_x_preferred":[
        "\u06af\u0644\u0632\u0627\u0631"
    ],
    "name:por_x_preferred":[
        "Gulzar"
    ],
    "name:rus_x_preferred":[
        "\u0413\u0443\u043b\u0437\u0430\u0440"
    ],
    "name:sco_x_preferred":[
        "Gulzar"
    ],
    "name:spa_x_preferred":[
        "Gulzar"
    ],
    "name:tam_x_preferred":[
        "\u0b95\u0bc1\u0bb2\u0bcd\u0b9a\u0bbe\u0bb0\u0bcd"
    ],
    "name:tel_x_preferred":[
        "\u0c17\u0c41\u0c32\u0c4d\u0c1c\u0c3e\u0c30\u0c4d"
    ],
    "name:tur_x_preferred":[
        "Gulzar"
    ],
    "name:urd_x_preferred":[
        "\u06af\u0644\u0632\u0627\u0631"
    ],
    "wof:name":"Gulzar",
    "wof:placetype":"locality"
},
  "geometry": {"coordinates":[63.43333000000001,28.01667],"type":"Point"}
}