{
  "type": "Feature",
  "properties": {
    "gn:admin1_code":"2.0",
    "gn:asciiname":"Gulzar",
    "gn:country_code":"PK",
    "gn:dem":536,
    "gn:feature_class":"P",
    "gn:feature_code":"PPL",
    "gn:name":"Gulz\u0101r",
    "gn:population":0,
    "gn:timezone":"Asia/Karachi",
    "iso:country":"PK",
    "wof:name":"Gulzar",
    "wof:placetype":"locality"
},
  "geometry": {"coordinates":[63.43333000000001,28.01667],"type":"Point"}
}