{
  "type": "Feature",
  "properties": {
    "gn:admin1_code":"4",
    "gn:asciiname":"Fateh Shahwala",
    "gn:country_code":"PK",
    "gn:dem":122,
    "gn:feature_class":"P",
    "gn:feature_code":"PPL",
    "gn:name":"Fateh Shahwala",
    "gn:population":0,
    "gn:timezone":"Asia/Karachi",
    "iso:country":"PK",
    "name:eng_x_preferred":[
        "Fateh Shahwala"
    ],
    "wof:name":"Fateh Shahwala",
    "wof:placetype":"locality"
},
  "geometry": {"coordinates":[70.96361999999998,30.09604],"type":"Point"}
}