{
  "type": "Feature",
  "properties": {
    "gn:admin1_code":"4",
    "gn:asciiname":"Dhok Nathuwala",
    "gn:country_code":"PK",
    "gn:dem":265,
    "gn:feature_class":"P",
    "gn:feature_code":"PPL",
    "gn:name":"Dhok Nathuwala",
    "gn:population":0,
    "gn:timezone":"Asia/Karachi",
    "iso:country":"PK",
    "name:und_x_variant":[
        "Dhok Nathw\u0101la"
    ],
    "wof:name":"Dhok Nathuwala",
    "wof:placetype":"locality"
},
  "geometry": {"coordinates":[73.43859,32.77176],"type":"Point"}
}