{
  "type": "Feature",
  "properties": {
    "gn:admin1_code":"6.0",
    "gn:asciiname":"Bhimbar District",
    "gn:country_code":"PK",
    "gn:dem":320,
    "gn:feature_class":"P",
    "gn:feature_code":"PPL",
    "gn:name":"Bhimbar District",
    "gn:population":0,
    "gn:timezone":"Asia/Karachi",
    "iso:country":"PK",
    "wof:name":"Bhimbar District",
    "wof:placetype":"neighbourhood"
},
  "geometry": {"coordinates":[74.06999999999999,32.97],"type":"Point"}
}