{
  "type": "Feature",
  "properties": {
    "gn:admin1_code":"4.0",
    "gn:asciiname":"Chak Seven- Nine Right",
    "gn:country_code":"PK",
    "gn:dem":144,
    "gn:feature_class":"P",
    "gn:feature_code":"PPL",
    "gn:name":"Chak Seven- Nine Right",
    "gn:population":0,
    "gn:timezone":"Asia/Karachi",
    "iso:country":"PK",
    "name:und_x_variant":[
        "Hanunm\u0101ngarh",
        "Chak Seven-Nine R",
        "Han\u016bm\u0101ngarh",
        "Chak Seven- Nine Right"
    ],
    "wof:name":"Chak Seven- Nine Right",
    "wof:placetype":"locality"
},
  "geometry": {"coordinates":[72.12921999999998,30.42198],"type":"Point"}
}