{
  "type": "Feature",
  "properties": {
    "gn:admin1_code":"4.0",
    "gn:asciiname":"Chak One Hundred Thirty-one - Six Right / One Left",
    "gn:country_code":"PK",
    "gn:dem":147,
    "gn:feature_class":"P",
    "gn:feature_code":"PPL",
    "gn:name":"Chak One Hundred Thirty-one - Six Right / One Left",
    "gn:population":0,
    "gn:timezone":"Asia/Karachi",
    "iso:country":"PK",
    "wof:name":"Chak One Hundred Thirty-one - Six Right / One Left",
    "wof:placetype":"locality"
},
  "geometry": {"coordinates":[72.86128000000002,29.40149000000001],"type":"Point"}
}