{
  "type": "Feature",
  "properties": {
    "gn:admin1_code":"4",
    "gn:asciiname":"Sadiqabad",
    "gn:country_code":"PK",
    "gn:dem":122,
    "gn:feature_class":"P",
    "gn:feature_code":"PPL",
    "gn:name":"Sadiqabad",
    "gn:population":0,
    "gn:timezone":"Asia/Karachi",
    "iso:country":"PK",
    "name:und_x_variant":[
        "Kh\u0101liq\u0101b\u0101d"
    ],
    "wof:name":"Sadiqabad",
    "wof:placetype":"locality"
},
  "geometry": {"coordinates":[72.24708000000003,29.85571],"type":"Point"}
}