{
  "type": "Feature",
  "properties": {
    "gn:admin1_code":"5",
    "gn:asciiname":"Unar",
    "gn:country_code":"PK",
    "gn:dem":9,
    "gn:feature_class":"P",
    "gn:feature_code":"PPL",
    "gn:name":"Unar",
    "gn:population":0,
    "gn:timezone":"Asia/Karachi",
    "iso:country":"PK",
    "name:deu_x_preferred":[
        "Unar"
    ],
    "name:und_x_variant":[
        "Gh\u0101zi Unar"
    ],
    "wof:name":"Unar",
    "wof:placetype":"locality"
},
  "geometry": {"coordinates":[69.10191999999999,24.77513],"type":"Point"}
}