{
  "type": "Feature",
  "properties": {
    "gn:admin1_code":"1.0",
    "gn:asciiname":"Borkai Keye",
    "gn:country_code":"PK",
    "gn:dem":759,
    "gn:feature_class":"P",
    "gn:feature_code":"PPL",
    "gn:name":"Borkai Keye",
    "gn:population":0,
    "gn:timezone":"Asia/Karachi",
    "iso:country":"PK",
    "name:und_x_variant":[
        "Borkai"
    ],
    "wof:name":"Borkai Keye",
    "wof:placetype":"locality"
},
  "geometry": {"coordinates":[71.2647,33.84377],"type":"Point"}
}