{
  "type": "Feature",
  "properties": {
    "gn:admin1_code":"4",
    "gn:asciiname":"Darkhanwala",
    "gn:country_code":"PK",
    "gn:dem":127,
    "gn:feature_class":"P",
    "gn:feature_code":"PPL",
    "gn:name":"Darkhanwala",
    "gn:population":0,
    "gn:timezone":"Asia/Karachi",
    "iso:country":"PK",
    "name:eng_x_preferred":[
        "Tarkh\u0101nw\u0101la"
    ],
    "wof:name":"Darkhanwala",
    "wof:placetype":"locality"
},
  "geometry": {"coordinates":[70.98501,30.25199000000001],"type":"Point"}
}