{
  "type": "Feature",
  "properties": {
    "gn:admin1_code":"4.0",
    "gn:asciiname":"Bhinaka",
    "gn:country_code":"PK",
    "gn:dem":649,
    "gn:feature_class":"P",
    "gn:feature_code":"PPL",
    "gn:name":"Bhinaka",
    "gn:population":0,
    "gn:timezone":"Asia/Karachi",
    "iso:country":"PK",
    "wof:name":"Bhinaka",
    "wof:placetype":"locality"
},
  "geometry": {"coordinates":[72.31435,32.59384],"type":"Point"}
}