{
  "type": "Feature",
  "properties": {
    "gn:admin1_code":"03",
    "gn:asciiname":"Pind Munim",
    "gn:country_code":"PK",
    "gn:dem":580,
    "gn:feature_class":"P",
    "gn:feature_code":"PPL",
    "gn:name":"Pind Munim",
    "gn:population":0,
    "gn:timezone":"Asia/Karachi",
    "iso:country":"PK",
    "name:und_x_variant":[
        "Pind Mun\u012bm",
        "Pind Munim"
    ],
    "wof:name":"Pind Munim",
    "wof:placetype":"locality"
},
  "geometry": {"coordinates":[72.91082,33.87078],"type":"Point"}
}