{
  "type": "Feature",
  "properties": {
    "gn:admin1_code":"5.0",
    "gn:asciiname":"Goth Bahadur Lanjwani",
    "gn:country_code":"PK",
    "gn:dem":17,
    "gn:feature_class":"P",
    "gn:feature_code":"PPL",
    "gn:name":"Goth Bahadur Lanjwani",
    "gn:population":0,
    "gn:timezone":"Asia/Karachi",
    "iso:country":"PK",
    "name:und_x_variant":[
        "Goth Bahar Lanjw\u0101ni"
    ],
    "wof:name":"Goth Bahadur Lanjwani",
    "wof:placetype":"locality"
},
  "geometry": {"coordinates":[68.56215999999999,25.06782],"type":"Point"}
}