{
  "type": "Feature",
  "properties": {
    "gn:admin1_code":"04",
    "gn:asciiname":"Chak Two Hundred Seventy-eight Jhang Branch",
    "gn:country_code":"PK",
    "gn:dem":175,
    "gn:feature_class":"P",
    "gn:feature_code":"PPL",
    "gn:name":"Chak Two Hundred Seventy-eight Jhang Branch",
    "gn:population":0,
    "gn:timezone":"Asia/Karachi",
    "iso:country":"PK",
    "name:und_x_variant":[
        "Usm\u0101n Kot",
        "Chak Two Hundred Seventy-Eight",
        "Chak Two Hundred Seventy-eight Jhang Branch"
    ],
    "wof:name":"Chak Two Hundred Seventy-eight Jhang Branch",
    "wof:placetype":"locality"
},
  "geometry": {"coordinates":[72.79578000000002,31.29053],"type":"Point"}
}