{
  "type": "Feature",
  "properties": {
    "gn:admin1_code":"6",
    "gn:asciiname":"Dadra",
    "gn:country_code":"PK",
    "gn:dem":653,
    "gn:feature_class":"P",
    "gn:feature_code":"PPL",
    "gn:name":"Dadra",
    "gn:population":0,
    "gn:timezone":"Asia/Karachi",
    "iso:country":"PK",
    "wof:name":"Dadra",
    "wof:placetype":"locality"
},
  "geometry": {"coordinates":[74.05155999999999,33.1444],"type":"Point"}
}