{
  "type": "Feature",
  "properties": {
    "gn:admin1_code":"3.0",
    "gn:asciiname":"Pakona",
    "gn:country_code":"PK",
    "gn:dem":813,
    "gn:feature_class":"P",
    "gn:feature_code":"PPL",
    "gn:name":"Pakona",
    "gn:population":0,
    "gn:timezone":"Asia/Karachi",
    "iso:country":"PK",
    "wof:name":"Pakona",
    "wof:placetype":"locality"
},
  "geometry": {"coordinates":[73.09376999999998,34.35285],"type":"Point"}
}