{
  "type": "Feature",
  "properties": {
    "gn:admin1_code":"2.0",
    "gn:asciiname":"Gorich Categ",
    "gn:country_code":"PK",
    "gn:dem":1077,
    "gn:feature_class":"P",
    "gn:feature_code":"PPL",
    "gn:name":"Gorich Categ",
    "gn:population":0,
    "gn:timezone":"Asia/Karachi",
    "iso:country":"PK",
    "wof:name":"Gorich Categ",
    "wof:placetype":"locality"
},
  "geometry": {"coordinates":[63.2606,27.24207],"type":"Point"}
}