{
  "type": "Feature",
  "properties": {
    "gn:admin1_code":"5.0",
    "gn:asciiname":"Goth Ibrahim Khan Punjabi",
    "gn:country_code":"PK",
    "gn:dem":12,
    "gn:feature_class":"P",
    "gn:feature_code":"PPL",
    "gn:name":"Goth Ibrahim Khan Punjabi",
    "gn:population":0,
    "gn:timezone":"Asia/Karachi",
    "iso:country":"PK",
    "wof:name":"Goth Ibrahim Khan Punjabi",
    "wof:placetype":"locality"
},
  "geometry": {"coordinates":[68.34846999999999,24.90038],"type":"Point"}
}