{
  "type": "Feature",
  "properties": {
    "gn:admin1_code":"3",
    "gn:asciiname":"Niam",
    "gn:country_code":"PK",
    "gn:dem":1547,
    "gn:feature_class":"P",
    "gn:feature_code":"PPL",
    "gn:name":"Niam",
    "gn:population":0,
    "gn:timezone":"Asia/Karachi",
    "iso:country":"PK",
    "name:eng_x_preferred":[
        "Niam"
    ],
    "wof:name":"Niam",
    "wof:placetype":"locality"
},
  "geometry": {"coordinates":[72.54261,35.22056],"type":"Point"}
}