{
  "type": "Feature",
  "properties": {
    "gn:admin1_code":"1.0",
    "gn:asciiname":"Yazha",
    "gn:country_code":"PK",
    "gn:dem":2263,
    "gn:feature_class":"P",
    "gn:feature_code":"PPL",
    "gn:name":"Yazha",
    "gn:population":0,
    "gn:timezone":"Asia/Karachi",
    "iso:country":"PK",
    "name:und_x_variant":[
        "Rodnik Sulayman",
        "Sulaim\u0101n",
        "Yazha"
    ],
    "wof:name":"Yazha",
    "wof:placetype":"locality"
},
  "geometry": {"coordinates":[69.27970000000001,32.51211],"type":"Point"}
}