{
  "type": "Feature",
  "properties": {
    "gn:admin1_code":"4.0",
    "gn:asciiname":"Chak Ninety-nine Eastern Bar",
    "gn:country_code":"PK",
    "gn:dem":153,
    "gn:feature_class":"P",
    "gn:feature_code":"PPL",
    "gn:name":"Chak Ninety-nine Eastern Bar",
    "gn:population":0,
    "gn:timezone":"Asia/Karachi",
    "iso:country":"PK",
    "name:und_x_variant":[
        "Deputyw\u0101la"
    ],
    "wof:name":"Chak Ninety-nine Eastern Bar",
    "wof:placetype":"locality"
},
  "geometry": {"coordinates":[73.01873000000001,30.18977000000001],"type":"Point"}
}