{
  "type": "Feature",
  "properties": {
    "gn:admin1_code":"7.0",
    "gn:asciiname":"Lamarz-i-Kisht",
    "gn:country_code":"PK",
    "gn:dem":3759,
    "gn:feature_class":"P",
    "gn:feature_code":"PPL",
    "gn:name":"Lamarz-i-Kisht",
    "gn:population":0,
    "gn:timezone":"Asia/Karachi",
    "iso:country":"PK",
    "wof:name":"Lamarz-i-Kisht",
    "wof:placetype":"locality"
},
  "geometry": {"coordinates":[75.98886999999998,36.41363],"type":"Point"}
}