{
  "type": "Feature",
  "properties": {
    "gn:admin1_code":"4",
    "gn:asciiname":"Hussainwali",
    "gn:country_code":"PK",
    "gn:dem":141,
    "gn:feature_class":"P",
    "gn:feature_code":"PPL",
    "gn:name":"Hussainwali",
    "gn:population":0,
    "gn:timezone":"Asia/Karachi",
    "iso:country":"PK",
    "name:und_x_variant":[
        "Husan\u012bniw\u0101li"
    ],
    "wof:name":"Hussainwali",
    "wof:placetype":"locality"
},
  "geometry": {"coordinates":[72.51101,29.75939],"type":"Point"}
}