{
  "type": "Feature",
  "properties": {
    "gn:admin1_code":"5",
    "gn:asciiname":"Goth Lal Khan Laghari",
    "gn:country_code":"PK",
    "gn:dem":13,
    "gn:feature_class":"P",
    "gn:feature_code":"PPL",
    "gn:name":"Goth Lal Khan Laghari",
    "gn:population":0,
    "gn:timezone":"Asia/Karachi",
    "iso:country":"PK",
    "name:und_x_variant":[
        "Goth L\u0101l Kh\u0101n Lagh\u0101ri"
    ],
    "wof:name":"Goth Lal Khan Laghari",
    "wof:placetype":"locality"
},
  "geometry": {"coordinates":[69.09704000000001,25.37858],"type":"Point"}
}