{
  "type": "Feature",
  "properties": {
    "gn:admin1_code":"6",
    "gn:asciiname":"Balian Poth",
    "gn:country_code":"PK",
    "gn:dem":2127,
    "gn:feature_class":"P",
    "gn:feature_code":"PPL",
    "gn:name":"Balian Poth",
    "gn:population":0,
    "gn:timezone":"Asia/Karachi",
    "iso:country":"PK",
    "name:und_x_variant":[
        "Bali\u0101r Potha"
    ],
    "wof:name":"Balian Poth",
    "wof:placetype":"locality"
},
  "geometry": {"coordinates":[73.80213000000001,33.91222],"type":"Point"}
}