{
  "type": "Feature",
  "properties": {
    "gn:admin1_code":"3.0",
    "gn:asciiname":"Nar Muhammad Anwar",
    "gn:country_code":"PK",
    "gn:dem":313,
    "gn:feature_class":"P",
    "gn:feature_code":"PPL",
    "gn:name":"Nar Muhammad Anwar",
    "gn:population":0,
    "gn:timezone":"Asia/Karachi",
    "iso:country":"PK",
    "wof:name":"Nar Muhammad Anwar",
    "wof:placetype":"locality"
},
  "geometry": {"coordinates":[70.73204,32.86669000000001],"type":"Point"}
}