{
  "type": "Feature",
  "properties": {
    "gn:admin1_code":"2.0",
    "gn:asciiname":"Kili Habibullah Khan",
    "gn:country_code":"PK",
    "gn:dem":960,
    "gn:feature_class":"P",
    "gn:feature_code":"PPL",
    "gn:name":"Kili Habibullah Khan",
    "gn:population":0,
    "gn:timezone":"Asia/Karachi",
    "iso:country":"PK",
    "wof:name":"Kili Habibullah Khan",
    "wof:placetype":"locality"
},
  "geometry": {"coordinates":[64.46455999999999,29.11263],"type":"Point"}
}