{
  "type": "Feature",
  "properties": {
    "gn:admin1_code":"2.0",
    "gn:asciiname":"Kili Maji Abdul Majid",
    "gn:country_code":"PK",
    "gn:dem":1580,
    "gn:feature_class":"P",
    "gn:feature_code":"PPL",
    "gn:name":"Kili Maji Abdul Majid",
    "gn:population":0,
    "gn:timezone":"Asia/Karachi",
    "iso:country":"PK",
    "wof:name":"Kili Maji Abdul Majid",
    "wof:placetype":"locality"
},
  "geometry": {"coordinates":[66.36497,29.57537],"type":"Point"}
}