{
  "type": "Feature",
  "properties": {
    "gn:admin1_code":"5",
    "gn:asciiname":"Shaikhan jo Goth",
    "gn:country_code":"PK",
    "gn:dem":52,
    "gn:feature_class":"P",
    "gn:feature_code":"PPL",
    "gn:name":"Shaikhan jo Goth",
    "gn:population":0,
    "gn:timezone":"Asia/Karachi",
    "iso:country":"PK",
    "name:und_x_variant":[
        "Sheikh\u0101n jo Goth"
    ],
    "wof:name":"Shaikhan jo Goth",
    "wof:placetype":"locality"
},
  "geometry": {"coordinates":[68.31734,27.44669],"type":"Point"}
}