{
  "type": "Feature",
  "properties": {
    "gn:admin1_code":"2.0",
    "gn:asciiname":"Patak",
    "gn:country_code":"PK",
    "gn:dem":1489,
    "gn:feature_class":"P",
    "gn:feature_code":"PPL",
    "gn:name":"Patak",
    "gn:population":0,
    "gn:timezone":"Asia/Karachi",
    "iso:country":"PK",
    "name:hun_x_preferred":[
        "Patak"
    ],
    "wof:name":"Patak",
    "wof:placetype":"locality"
},
  "geometry": {"coordinates":[65.61598000000001,27.75381],"type":"Point"}
}