{
  "type": "Feature",
  "properties": {
    "gn:admin1_code":"4.0",
    "gn:asciiname":"Chak Five - One Right",
    "gn:country_code":"PK",
    "gn:dem":156,
    "gn:feature_class":"P",
    "gn:feature_code":"PPL",
    "gn:name":"Chak Five - One Right",
    "gn:population":0,
    "gn:timezone":"Asia/Karachi",
    "iso:country":"PK",
    "wof:name":"Chak Five - One Right",
    "wof:placetype":"locality"
},
  "geometry": {"coordinates":[73.07918000000002,29.67483],"type":"Point"}
}