{
  "type": "Feature",
  "properties": {
    "gn:admin1_code":"2.0",
    "gn:asciiname":"Khush",
    "gn:country_code":"PK",
    "gn:dem":1678,
    "gn:feature_class":"P",
    "gn:feature_code":"PPL",
    "gn:name":"Khush",
    "gn:population":0,
    "gn:timezone":"Asia/Karachi",
    "iso:country":"PK",
    "wof:name":"Khush",
    "wof:placetype":"locality"
},
  "geometry": {"coordinates":[66.85143000000001,29.91716],"type":"Point"}
}