{
  "type": "Feature",
  "properties": {
    "gn:admin1_code":"2.0",
    "gn:asciiname":"Khush",
    "gn:country_code":"PK",
    "gn:dem":1678,
    "gn:feature_class":"P",
    "gn:feature_code":"PPL",
    "gn:name":"Khush",
    "gn:population":0,
    "gn:timezone":"Asia/Karachi",
    "iso:country":"PK",
    "name:azb_x_preferred":[
        "\u062e\u0648\u0634"
    ],
    "name:ell_x_preferred":[
        "\u03a7\u03bf\u03c5\u03c2"
    ],
    "name:fas_x_preferred":[
        "\u062e\u0648\u0634"
    ],
    "name:ita_x_preferred":[
        "Khush"
    ],
    "name:msa_x_preferred":[
        "Khush"
    ],
    "wof:name":"Khush",
    "wof:placetype":"locality"
},
  "geometry": {"coordinates":[66.85143000000001,29.91716],"type":"Point"}
}