{
  "type": "Feature",
  "properties": {
    "gn:admin1_code":"2.0",
    "gn:asciiname":"Grishak Kili",
    "gn:country_code":"PK",
    "gn:dem":752,
    "gn:feature_class":"P",
    "gn:feature_code":"PPL",
    "gn:name":"Grishak Kili",
    "gn:population":0,
    "gn:timezone":"Asia/Karachi",
    "iso:country":"PK",
    "wof:name":"Grishak Kili",
    "wof:placetype":"locality"
},
  "geometry": {"coordinates":[64.23281,27.47491],"type":"Point"}
}