{
  "type": "Feature",
  "properties": {
    "gn:admin1_code":"2.0",
    "gn:asciiname":"Masit",
    "gn:country_code":"PK",
    "gn:dem":706,
    "gn:feature_class":"P",
    "gn:feature_code":"PPL",
    "gn:name":"Masit",
    "gn:population":0,
    "gn:timezone":"Asia/Karachi",
    "iso:country":"PK",
    "wof:name":"Masit",
    "wof:placetype":"locality"
},
  "geometry": {"coordinates":[65.47450000000001,28.47806],"type":"Point"}
}