{
  "type": "Feature",
  "properties": {
    "gn:admin1_code":"2.0",
    "gn:asciiname":"Gharkai",
    "gn:country_code":"PK",
    "gn:dem":951,
    "gn:feature_class":"P",
    "gn:feature_code":"PPL",
    "gn:name":"Gharkai",
    "gn:population":0,
    "gn:timezone":"Asia/Karachi",
    "iso:country":"PK",
    "name:und_x_variant":[
        "Guzai"
    ],
    "wof:name":"Gharkai",
    "wof:placetype":"locality"
},
  "geometry": {"coordinates":[70.10880999999999,31.25945],"type":"Point"}
}