{
  "type": "Feature",
  "properties": {
    "gn:admin1_code":"04",
    "gn:asciiname":"Wiroke",
    "gn:country_code":"PK",
    "gn:dem":232,
    "gn:feature_class":"P",
    "gn:feature_code":"PPL",
    "gn:name":"Wiroke",
    "gn:population":0,
    "gn:timezone":"Asia/Karachi",
    "iso:country":"PK",
    "name:und_x_variant":[
        "Wiru Ke",
        "Wiroke"
    ],
    "wof:name":"Wiroke",
    "wof:placetype":"locality"
},
  "geometry": {"coordinates":[74.82134000000001,32.03151],"type":"Point"}
}