{
  "type": "Feature",
  "properties": {
    "gn:admin1_code":"01",
    "gn:asciiname":"Abdur Rahman Khel",
    "gn:country_code":"PK",
    "gn:dem":2443,
    "gn:feature_class":"P",
    "gn:feature_code":"PPL",
    "gn:name":"Abdur Rahman Khel",
    "gn:population":0,
    "gn:timezone":"Asia/Karachi",
    "iso:country":"PK",
    "name:fas_x_preferred":[
        "\u0639\u0628\u062f\u0627\u0644\u0631\u062d\u0645\u0646 \u062e\u0644"
    ],
    "wof:name":"Abdur Rahman Khel",
    "wof:placetype":"locality"
},
  "geometry": {"coordinates":[69.65101,32.56155],"type":"Point"}
}