{
  "type": "Feature",
  "properties": {
    "gn:admin1_code":"04",
    "gn:asciiname":"Mangher Sharif",
    "gn:country_code":"PK",
    "gn:dem":145,
    "gn:feature_class":"P",
    "gn:feature_code":"PPL",
    "gn:name":"Mangher Sharif",
    "gn:population":0,
    "gn:timezone":"Asia/Karachi",
    "iso:country":"PK",
    "name:und_x_variant":[
        "Mangeran Sharif",
        "Mangher\u0101n",
        "Mangher Sharif"
    ],
    "wof:name":"Mangher Sharif",
    "wof:placetype":"locality"
},
  "geometry": {"coordinates":[72.79091,29.85627],"type":"Point"}
}