{
  "type": "Feature",
  "properties": {
    "gn:admin1_code":"4.0",
    "gn:asciiname":"Lahota",
    "gn:country_code":"PK",
    "gn:dem":850,
    "gn:feature_class":"P",
    "gn:feature_code":"PPL",
    "gn:name":"Lahota",
    "gn:population":0,
    "gn:timezone":"Asia/Karachi",
    "iso:country":"PK",
    "wof:name":"Lahota",
    "wof:placetype":"locality"
},
  "geometry": {"coordinates":[72.48358,32.65714000000001],"type":"Point"}
}