{
  "type": "Feature",
  "properties": {
    "gn:admin1_code":"2.0",
    "gn:asciiname":"Haji Anwar Kaul",
    "gn:country_code":"PK",
    "gn:dem":1752,
    "gn:feature_class":"P",
    "gn:feature_code":"PPL",
    "gn:name":"Haji Anwar Kaul",
    "gn:population":0,
    "gn:timezone":"Asia/Karachi",
    "iso:country":"PK",
    "wof:name":"Haji Anwar Kaul",
    "wof:placetype":"locality"
},
  "geometry": {"coordinates":[66.78794000000001,30.80278],"type":"Point"}
}