{
  "type": "Feature",
  "properties": {
    "gn:admin1_code":"5",
    "gn:asciiname":"Goth Qadir Bakhsh Sanghar",
    "gn:country_code":"PK",
    "gn:dem":71,
    "gn:feature_class":"P",
    "gn:feature_code":"PPL",
    "gn:name":"Goth Qadir Bakhsh Sanghar",
    "gn:population":0,
    "gn:timezone":"Asia/Karachi",
    "iso:country":"PK",
    "name:und_x_variant":[
        "Pareo Sanghar"
    ],
    "wof:name":"Goth Qadir Bakhsh Sanghar",
    "wof:placetype":"locality"
},
  "geometry": {"coordinates":[69.37321999999999,28.05564],"type":"Point"}
}