{
  "type": "Feature",
  "properties": {
    "gn:admin1_code":"4",
    "gn:asciiname":"Bhan",
    "gn:country_code":"PK",
    "gn:dem":856,
    "gn:feature_class":"P",
    "gn:feature_code":"PPL",
    "gn:name":"Bhan",
    "gn:population":0,
    "gn:timezone":"Asia/Karachi",
    "iso:country":"PK",
    "wof:name":"Bhan",
    "wof:placetype":"locality"
},
  "geometry": {"coordinates":[72.14726,32.62552],"type":"Point"}
}