{
  "type": "Feature",
  "properties": {
    "gn:admin1_code":"3.0",
    "gn:asciiname":"Khushal Khan Banda",
    "gn:country_code":"PK",
    "gn:dem":377,
    "gn:feature_class":"P",
    "gn:feature_code":"PPL",
    "gn:name":"Khushal Khan Banda",
    "gn:population":0,
    "gn:timezone":"Asia/Karachi",
    "iso:country":"PK",
    "wof:name":"Khushal Khan Banda",
    "wof:placetype":"locality"
},
  "geometry": {"coordinates":[71.84618,34.32917],"type":"Point"}
}