{
  "type": "Feature",
  "properties": {
    "gn:admin1_code":"4",
    "gn:asciiname":"Naiwala",
    "gn:country_code":"PK",
    "gn:dem":143,
    "gn:feature_class":"P",
    "gn:feature_code":"PPL",
    "gn:name":"N\u0101iw\u0101la",
    "gn:population":0,
    "gn:timezone":"Asia/Karachi",
    "iso:country":"PK",
    "wof:name":"Naiwala",
    "wof:placetype":"locality"
},
  "geometry": {"coordinates":[71.00417,30.86667000000001],"type":"Point"}
}