{
  "type": "Feature",
  "properties": {
    "gn:admin1_code":"3.0",
    "gn:asciiname":"Tami",
    "gn:country_code":"PK",
    "gn:dem":2158,
    "gn:feature_class":"P",
    "gn:feature_code":"PPL",
    "gn:name":"Tami",
    "gn:population":0,
    "gn:timezone":"Asia/Karachi",
    "iso:country":"PK",
    "wof:name":"Tami",
    "wof:placetype":"locality"
},
  "geometry": {"coordinates":[73.31631999999998,34.60053],"type":"Point"}
}