{
  "type": "Feature",
  "properties": {
    "gn:admin1_code":"4.0",
    "gn:asciiname":"Chairmanwala",
    "gn:country_code":"PK",
    "gn:dem":236,
    "gn:feature_class":"P",
    "gn:feature_code":"PPL",
    "gn:name":"Chairmanwala",
    "gn:population":0,
    "gn:timezone":"Asia/Karachi",
    "iso:country":"PK",
    "wof:name":"Chairmanwala",
    "wof:placetype":"locality"
},
  "geometry": {"coordinates":[71.64673000000001,32.59857],"type":"Point"}
}