{
  "type": "Feature",
  "properties": {
    "gn:admin1_code":"5.0",
    "gn:asciiname":"Goth Haji Abdul Ghani Rind",
    "gn:country_code":"PK",
    "gn:dem":39,
    "gn:feature_class":"P",
    "gn:feature_code":"PPL",
    "gn:name":"Goth Haji Abdul Ghani Rind",
    "gn:population":0,
    "gn:timezone":"Asia/Karachi",
    "iso:country":"PK",
    "name:und_x_variant":[
        "Goth H\u0101ji Abdul Gh\u0101i R\u012bnd"
    ],
    "wof:name":"Goth Haji Abdul Ghani Rind",
    "wof:placetype":"locality"
},
  "geometry": {"coordinates":[68.22313,26.36808],"type":"Point"}
}