{
  "type": "Feature",
  "properties": {
    "gn:admin1_code":"4.0",
    "gn:asciiname":"Gogial",
    "gn:country_code":"PK",
    "gn:dem":278,
    "gn:feature_class":"P",
    "gn:feature_code":"PPL",
    "gn:name":"Gogial",
    "gn:population":0,
    "gn:timezone":"Asia/Karachi",
    "iso:country":"PK",
    "name:und_x_variant":[
        "G\u0101ngi\u0101l"
    ],
    "wof:name":"Gogial",
    "wof:placetype":"locality"
},
  "geometry": {"coordinates":[74.86255,32.45397],"type":"Point"}
}