{
  "type": "Feature",
  "properties": {
    "gn:admin1_code":"2",
    "gn:asciiname":"Mitthi",
    "gn:country_code":"PK",
    "gn:dem":437,
    "gn:feature_class":"P",
    "gn:feature_code":"PPL",
    "gn:name":"Mitthi",
    "gn:population":0,
    "gn:timezone":"Asia/Karachi",
    "iso:country":"PK",
    "name:eng_x_preferred":[
        "Goth Meth"
    ],
    "wof:name":"Mitthi",
    "wof:placetype":"locality"
},
  "geometry": {"coordinates":[66.91292,25.93766],"type":"Point"}
}