{
  "type": "Feature",
  "properties": {
    "gn:admin1_code":"2.0",
    "gn:asciiname":"Umar Kili",
    "gn:country_code":"PK",
    "gn:dem":1478,
    "gn:feature_class":"P",
    "gn:feature_code":"PPL",
    "gn:name":"Umar Kili",
    "gn:population":0,
    "gn:timezone":"Asia/Karachi",
    "iso:country":"PK",
    "wof:name":"Umar Kili",
    "wof:placetype":"locality"
},
  "geometry": {"coordinates":[66.46935999999999,29.9796],"type":"Point"}
}