{
  "type": "Feature",
  "properties": {
    "gn:admin1_code":"2.0",
    "gn:asciiname":"Alizai",
    "gn:country_code":"PK",
    "gn:dem":1939,
    "gn:feature_class":"P",
    "gn:feature_code":"PPL",
    "gn:name":"Alizai",
    "gn:population":0,
    "gn:timezone":"Asia/Karachi",
    "iso:country":"PK",
    "name:ceb_x_preferred":[
        "Alizai"
    ],
    "wof:name":"Alizai",
    "wof:placetype":"locality"
},
  "geometry": {"coordinates":[67.32014000000001,30.62011],"type":"Point"}
}