{
  "type": "Feature",
  "properties": {
    "gn:admin1_code":"7.0",
    "gn:asciiname":"Dudishal",
    "gn:country_code":"PK",
    "gn:dem":1008,
    "gn:feature_class":"P",
    "gn:feature_code":"PPL",
    "gn:name":"Dudishal",
    "gn:population":0,
    "gn:timezone":"Asia/Karachi",
    "iso:country":"PK",
    "name:und_x_variant":[
        "Chold\u0101s"
    ],
    "wof:name":"Dudishal",
    "wof:placetype":"locality"
},
  "geometry": {"coordinates":[73.72454,35.53391],"type":"Point"}
}