{
  "type": "Feature",
  "properties": {
    "gn:admin1_code":"4.0",
    "gn:asciiname":"Khandam Gopang",
    "gn:country_code":"PK",
    "gn:dem":92,
    "gn:feature_class":"P",
    "gn:feature_code":"PPL",
    "gn:name":"Khandam Gopang",
    "gn:population":0,
    "gn:timezone":"Asia/Karachi",
    "iso:country":"PK",
    "name:und_x_variant":[
        "Basti Ghul\u0101m Qadir"
    ],
    "wof:name":"Khandam Gopang",
    "wof:placetype":"locality"
},
  "geometry": {"coordinates":[70.45413000000001,28.76759],"type":"Point"}
}