{
  "type": "Feature",
  "properties": {
    "gn:admin1_code":"3.0",
    "gn:asciiname":"Zomalogocho Ghari",
    "gn:country_code":"PK",
    "gn:dem":3402,
    "gn:feature_class":"P",
    "gn:feature_code":"PPL",
    "gn:name":"Zomalogocho Ghari",
    "gn:population":0,
    "gn:timezone":"Asia/Karachi",
    "iso:country":"PK",
    "wof:name":"Zomalogocho Ghari",
    "wof:placetype":"locality"
},
  "geometry": {"coordinates":[71.6084,35.97339],"type":"Point"}
}