{
  "type": "Feature",
  "properties": {
    "gn:admin1_code":"2.0",
    "gn:asciiname":"Ziarat Pir Umar",
    "gn:country_code":"PK",
    "gn:dem":1032,
    "gn:feature_class":"P",
    "gn:feature_code":"PPL",
    "gn:name":"Ziarat Pir Umar",
    "gn:population":0,
    "gn:timezone":"Asia/Karachi",
    "iso:country":"PK",
    "wof:name":"Ziarat Pir Umar",
    "wof:placetype":"locality"
},
  "geometry": {"coordinates":[64.19152,26.95585],"type":"Point"}
}