{
  "type": "Feature",
  "properties": {
    "gn:admin1_code":"2",
    "gn:asciiname":"Khwaja Maddud",
    "gn:country_code":"PK",
    "gn:dem":2425,
    "gn:feature_class":"P",
    "gn:feature_code":"PPL",
    "gn:name":"Khwaja Maddud",
    "gn:population":0,
    "gn:timezone":"Asia/Karachi",
    "iso:country":"PK",
    "name:eng_x_preferred":[
        "Khwaja Maddud"
    ],
    "wof:name":"Khwaja Maddud",
    "wof:placetype":"locality"
},
  "geometry": {"coordinates":[67.10035000000001,30.97494],"type":"Point"}
}