{
  "type": "Feature",
  "properties": {
    "gn:admin1_code":"4",
    "gn:asciiname":"Chohranwala",
    "gn:country_code":"PK",
    "gn:dem":100,
    "gn:feature_class":"P",
    "gn:feature_code":"PPL",
    "gn:name":"Chohranwala",
    "gn:population":0,
    "gn:timezone":"Asia/Karachi",
    "iso:country":"PK",
    "name:und_x_variant":[
        "Chohrw\u0101la"
    ],
    "wof:name":"Chohranwala",
    "wof:placetype":"locality"
},
  "geometry": {"coordinates":[70.71398000000001,29.20162],"type":"Point"}
}