{
  "type": "Feature",
  "properties": {
    "gn:admin1_code":"3.0",
    "gn:asciiname":"Mausum",
    "gn:country_code":"PK",
    "gn:dem":312,
    "gn:feature_class":"P",
    "gn:feature_code":"PPL",
    "gn:name":"Mausum",
    "gn:population":0,
    "gn:timezone":"Asia/Karachi",
    "iso:country":"PK",
    "name:und_x_variant":[
        "Faq\u012br Muhammad Mas\u016bm"
    ],
    "wof:name":"Mausum",
    "wof:placetype":"locality"
},
  "geometry": {"coordinates":[70.74024,32.81404000000001],"type":"Point"}
}