{
  "type": "Feature",
  "properties": {
    "gn:admin1_code":"4",
    "gn:asciiname":"Khanewal",
    "gn:country_code":"PK",
    "gn:dem":207,
    "gn:feature_class":"P",
    "gn:feature_code":"PPL",
    "gn:name":"Khanewal",
    "gn:population":0,
    "gn:timezone":"Asia/Karachi",
    "iso:country":"PK",
    "name:ara_x_preferred":[
        "\u062e\u0627\u0646\u064a\u0648\u0627\u0644"
    ],
    "name:ceb_x_preferred":[
        "Kh\u0101new\u0101l"
    ],
    "name:epo_x_preferred":[
        "\u0124aniual"
    ],
    "name:fas_x_preferred":[
        "\u062e\u0627\u0646\u06cc\u0648\u0627\u0644"
    ],
    "name:fra_x_preferred":[
        "Khanewal"
    ],
    "name:lit_x_preferred":[
        "Chanevalis"
    ],
    "name:pan_x_preferred":[
        "\u0a16\u0a3e\u0a28\u0a47\u0a35\u0a3e\u0a32"
    ],
    "name:pnb_x_preferred":[
        "\u062e\u0627\u0646\u06cc\u0648\u0627\u0644"
    ],
    "name:pol_x_preferred":[
        "Khanewal"
    ],
    "name:por_x_preferred":[
        "Khanewal"
    ],
    "name:pus_x_preferred":[
        "\u062e\u0627\u0646\u064a\u0648\u0627\u0644"
    ],
    "name:rus_x_preferred":[
        "\u0425\u0430\u043d\u0435\u0432\u0430\u043b"
    ],
    "name:srp_x_preferred":[
        "\u0425\u0430\u043d\u0435\u0432\u0430\u043b"
    ],
    "name:swe_x_preferred":[
        "Khanewal"
    ],
    "name:und_x_variant":[
        "Kh\u0101nw\u0101li"
    ],
    "name:urd_x_preferred":[
        "\u062e\u0627\u0646\u06cc\u0648\u0627\u0644"
    ],
    "name:war_x_preferred":[
        "Khanewal"
    ],
    "wof:name":"Khanewal",
    "wof:placetype":"locality"
},
  "geometry": {"coordinates":[74.15831,31.55605],"type":"Point"}
}