{
  "type": "Feature",
  "properties": {
    "gn:admin1_code":"4",
    "gn:asciiname":"Khanewal",
    "gn:country_code":"PK",
    "gn:dem":207,
    "gn:feature_class":"P",
    "gn:feature_code":"PPL",
    "gn:name":"Khanewal",
    "gn:population":0,
    "gn:timezone":"Asia/Karachi",
    "iso:country":"PK",
    "name:und_x_variant":[
        "Kh\u0101nw\u0101li"
    ],
    "wof:name":"Khanewal",
    "wof:placetype":"locality"
},
  "geometry": {"coordinates":[74.15831,31.55605],"type":"Point"}
}