{
  "type": "Feature",
  "properties": {
    "gn:admin1_code":"4.0",
    "gn:asciiname":"Taitlewala Dera",
    "gn:country_code":"PK",
    "gn:dem":212,
    "gn:feature_class":"P",
    "gn:feature_code":"PPL",
    "gn:name":"Taitlewala Dera",
    "gn:population":0,
    "gn:timezone":"Asia/Karachi",
    "iso:country":"PK",
    "wof:name":"Taitlewala Dera",
    "wof:placetype":"locality"
},
  "geometry": {"coordinates":[74.04756,31.84002000000001],"type":"Point"}
}