{
  "type": "Feature",
  "properties": {
    "gn:admin1_code":"4.0",
    "gn:asciiname":"Khundi Dheri",
    "gn:country_code":"PK",
    "gn:dem":450,
    "gn:feature_class":"P",
    "gn:feature_code":"PPL",
    "gn:name":"Khundi Dheri",
    "gn:population":0,
    "gn:timezone":"Asia/Karachi",
    "iso:country":"PK",
    "name:und_x_variant":[
        "Dhok Khundi Dheri",
        "Khundi Dheri"
    ],
    "wof:name":"Khundi Dheri",
    "wof:placetype":"locality"
},
  "geometry": {"coordinates":[72.39998,33.21143],"type":"Point"}
}