{
  "type": "Feature",
  "properties": {
    "gn:admin1_code":"3",
    "gn:asciiname":"Burj",
    "gn:country_code":"PK",
    "gn:dem":3270,
    "gn:feature_class":"P",
    "gn:feature_code":"PPL",
    "gn:name":"Burj",
    "gn:population":0,
    "gn:timezone":"Asia/Karachi",
    "iso:country":"PK",
    "wof:name":"Burj",
    "wof:placetype":"locality"
},
  "geometry": {"coordinates":[73.21389000000001,34.86528],"type":"Point"}
}