{
  "type": "Feature",
  "properties": {
    "gn:admin1_code":"2.0",
    "gn:asciiname":"Hud Zawar",
    "gn:country_code":"PK",
    "gn:dem":1446,
    "gn:feature_class":"P",
    "gn:feature_code":"PPL",
    "gn:name":"Hud Zawar",
    "gn:population":0,
    "gn:timezone":"Asia/Karachi",
    "iso:country":"PK",
    "wof:name":"Hud Zawar",
    "wof:placetype":"locality"
},
  "geometry": {"coordinates":[70.01899,31.16363],"type":"Point"}
}