{
  "type": "Feature",
  "properties": {
    "gn:admin1_code":"3",
    "gn:asciiname":"Phagla",
    "gn:country_code":"PK",
    "gn:dem":1344,
    "gn:feature_class":"P",
    "gn:feature_code":"PPL",
    "gn:name":"Phagla",
    "gn:population":0,
    "gn:timezone":"Asia/Karachi",
    "iso:country":"PK",
    "wof:name":"Phagla",
    "wof:placetype":"locality"
},
  "geometry": {"coordinates":[73.12645000000001,34.17665],"type":"Point"}
}