{
  "type": "Feature",
  "properties": {
    "gn:admin1_code":"4",
    "gn:asciiname":"Sahnwal",
    "gn:country_code":"PK",
    "gn:dem":234,
    "gn:feature_class":"P",
    "gn:feature_code":"PPL",
    "gn:name":"Sahnwal",
    "gn:population":0,
    "gn:timezone":"Asia/Karachi",
    "iso:country":"PK",
    "name:und_x_variant":[
        "S\u0101nw\u0101l"
    ],
    "wof:name":"Sahnwal",
    "wof:placetype":"locality"
},
  "geometry": {"coordinates":[74.03193,32.58407],"type":"Point"}
}