{
  "type": "Feature",
  "properties": {
    "gn:admin1_code":"3.0",
    "gn:asciiname":"Koday",
    "gn:country_code":"PK",
    "gn:dem":325,
    "gn:feature_class":"P",
    "gn:feature_code":"PPL",
    "gn:name":"Koday",
    "gn:population":0,
    "gn:timezone":"Asia/Karachi",
    "iso:country":"PK",
    "name:eng_x_preferred":[
        "Kadai"
    ],
    "name:und_x_variant":[
        "Kaddi",
        "Koday"
    ],
    "wof:name":"Koday",
    "wof:placetype":"locality"
},
  "geometry": {"coordinates":[72.48421999999999,34.0766],"type":"Point"}
}