{
  "type": "Feature",
  "properties": {
    "gn:admin1_code":"5.0",
    "gn:asciiname":"Goth Hakim Ali Mehr",
    "gn:country_code":"PK",
    "gn:dem":21,
    "gn:feature_class":"P",
    "gn:feature_code":"PPL",
    "gn:name":"Goth Hakim Ali Mehr",
    "gn:population":0,
    "gn:timezone":"Asia/Karachi",
    "iso:country":"PK",
    "name:und_x_variant":[
        "Goth Hakim Mehr"
    ],
    "wof:name":"Goth Hakim Ali Mehr",
    "wof:placetype":"locality"
},
  "geometry": {"coordinates":[68.93695,25.80179],"type":"Point"}
}