{
  "type": "Feature",
  "properties": {
    "gn:admin1_code":"2.0",
    "gn:asciiname":"Daru",
    "gn:country_code":"PK",
    "gn:dem":675,
    "gn:feature_class":"P",
    "gn:feature_code":"PPL",
    "gn:name":"Daru",
    "gn:population":0,
    "gn:timezone":"Asia/Karachi",
    "iso:country":"PK",
    "name:ceb_x_preferred":[
        "Daru"
    ],
    "name:deu_x_preferred":[
        "Daru"
    ],
    "name:fas_x_preferred":[
        "\u062f\u0627\u0631\u0648"
    ],
    "name:fij_x_preferred":[
        "Daru"
    ],
    "name:fin_x_preferred":[
        "Daru"
    ],
    "name:fra_x_preferred":[
        "Daru"
    ],
    "name:glg_x_preferred":[
        "Daru"
    ],
    "name:ita_x_preferred":[
        "Daru"
    ],
    "name:jpn_x_preferred":[
        "\u30c0\u30eb"
    ],
    "name:lit_x_preferred":[
        "Daru"
    ],
    "name:nld_x_preferred":[
        "Daru"
    ],
    "name:pol_x_preferred":[
        "Daru"
    ],
    "name:por_x_preferred":[
        "Daru"
    ],
    "name:rus_x_preferred":[
        "\u0414\u0430\u0440\u0443"
    ],
    "name:swe_x_preferred":[
        "Daru"
    ],
    "name:tpi_x_preferred":[
        "Daru"
    ],
    "name:ukr_x_preferred":[
        "\u0414\u0430\u0440\u0443"
    ],
    "name:urd_x_preferred":[
        "\u062f\u0627\u0631\u0648"
    ],
    "wof:name":"Daru",
    "wof:placetype":"locality"
},
  "geometry": {"coordinates":[65.2603,28.3759],"type":"Point"}
}