{
  "type": "Feature",
  "properties": {
    "gn:admin1_code":"5",
    "gn:asciiname":"Goth Sumar",
    "gn:country_code":"PK",
    "gn:dem":71,
    "gn:feature_class":"P",
    "gn:feature_code":"PPL",
    "gn:name":"Goth Sumar",
    "gn:population":0,
    "gn:timezone":"Asia/Karachi",
    "iso:country":"PK",
    "wof:name":"Goth Sumar",
    "wof:placetype":"locality"
},
  "geometry": {"coordinates":[69.30556,28.24861],"type":"Point"}
}