{
  "type": "Feature",
  "properties": {
    "gn:admin1_code":"4.0",
    "gn:asciiname":"Dera Loha",
    "gn:country_code":"PK",
    "gn:dem":283,
    "gn:feature_class":"P",
    "gn:feature_code":"PPL",
    "gn:name":"Dera Loha",
    "gn:population":0,
    "gn:timezone":"Asia/Karachi",
    "iso:country":"PK",
    "wof:name":"Dera Loha",
    "wof:placetype":"locality"
},
  "geometry": {"coordinates":[69.60689000000001,28.85429],"type":"Point"}
}