{
  "type": "Feature",
  "properties": {
    "gn:admin1_code":"3",
    "gn:asciiname":"Nimakai",
    "gn:country_code":"PK",
    "gn:dem":1773,
    "gn:feature_class":"P",
    "gn:feature_code":"PPL",
    "gn:name":"Nimakai",
    "gn:population":0,
    "gn:timezone":"Asia/Karachi",
    "iso:country":"PK",
    "wof:name":"Nimakai",
    "wof:placetype":"locality"
},
  "geometry": {"coordinates":[72.52406999999999,35.09968],"type":"Point"}
}