{
  "type": "Feature",
  "properties": {
    "gn:admin1_code":"5.0",
    "gn:asciiname":"Goth Jumman Shah",
    "gn:country_code":"PK",
    "gn:dem":25,
    "gn:feature_class":"P",
    "gn:feature_code":"PPL",
    "gn:name":"Goth Jumman Shah",
    "gn:population":0,
    "gn:timezone":"Asia/Karachi",
    "iso:country":"PK",
    "name:und_x_variant":[
        "Jumman Sh\u0101h"
    ],
    "wof:name":"Goth Jumman Shah",
    "wof:placetype":"locality"
},
  "geometry": {"coordinates":[68.52481999999999,25.58749],"type":"Point"}
}