{
  "type": "Feature",
  "properties": {
    "gn:admin1_code":"5.0",
    "gn:asciiname":"Seth Qadar Bakhsh",
    "gn:country_code":"PK",
    "gn:dem":25,
    "gn:feature_class":"P",
    "gn:feature_code":"PPL",
    "gn:name":"Seth Qadar Bakhsh",
    "gn:population":0,
    "gn:timezone":"Asia/Karachi",
    "iso:country":"PK",
    "wof:name":"Seth Qadar Bakhsh",
    "wof:placetype":"locality"
},
  "geometry": {"coordinates":[68.50709000000001,25.69823],"type":"Point"}
}