{
  "type": "Feature",
  "properties": {
    "gn:admin1_code":"04",
    "gn:asciiname":"Shekhupura",
    "gn:country_code":"PK",
    "gn:dem":217,
    "gn:feature_class":"P",
    "gn:feature_code":"PPL",
    "gn:name":"Shekhupura",
    "gn:population":0,
    "gn:timezone":"Asia/Karachi",
    "iso:country":"PK",
    "name:und_x_variant":[
        "Sheikhupura Bedad",
        "Shekh\u016bpura Bed\u0101d",
        "Shekhupura"
    ],
    "wof:name":"Shekhupura",
    "wof:placetype":"locality"
},
  "geometry": {"coordinates":[74.21463,31.87198],"type":"Point"}
}