{
  "type": "Feature",
  "properties": {
    "gn:admin1_code":"2.0",
    "gn:asciiname":"Muhamamd Ali Zahri",
    "gn:country_code":"PK",
    "gn:dem":1548,
    "gn:feature_class":"P",
    "gn:feature_code":"PPL",
    "gn:name":"Muhamamd Ali Zahri",
    "gn:population":0,
    "gn:timezone":"Asia/Karachi",
    "iso:country":"PK",
    "wof:name":"Muhamamd Ali Zahri",
    "wof:placetype":"locality"
},
  "geometry": {"coordinates":[66.30434,28.04064],"type":"Point"}
}