{
  "type": "Feature",
  "properties": {
    "gn:admin1_code":"3.0",
    "gn:asciiname":"Manak Bohri",
    "gn:country_code":"PK",
    "gn:dem":1910,
    "gn:feature_class":"P",
    "gn:feature_code":"PPL",
    "gn:name":"Manak Bohri",
    "gn:population":0,
    "gn:timezone":"Asia/Karachi",
    "iso:country":"PK",
    "wof:name":"Manak Bohri",
    "wof:placetype":"locality"
},
  "geometry": {"coordinates":[73.25744,34.65319],"type":"Point"}
}