{
  "type": "Feature",
  "properties": {
    "gn:admin1_code":"4.0",
    "gn:asciiname":"Dheri Mandai",
    "gn:country_code":"PK",
    "gn:dem":652,
    "gn:feature_class":"P",
    "gn:feature_code":"PPL",
    "gn:name":"Dheri Mandai",
    "gn:population":0,
    "gn:timezone":"Asia/Karachi",
    "iso:country":"PK",
    "wof:name":"Dheri Mandai",
    "wof:placetype":"locality"
},
  "geometry": {"coordinates":[73.39426,33.50145],"type":"Point"}
}