{
  "type": "Feature",
  "properties": {
    "iso:country":"PK",
    "name:bul_x_preferred":[
        "\u041f\u0430\u0441\u043d\u0438"
    ],
    "name:eng_x_preferred":[
        "Pasni"
    ],
    "name:ita_x_preferred":[
        "Pasni"
    ],
    "name:jpn_x_preferred":[
        "\u30d1\u30b9\u30cb"
    ],
    "name:kor_x_preferred":[
        "\ud30c\uc2a4\ub2c8"
    ],
    "name:nld_x_preferred":[
        "Pasni"
    ],
    "name:pnb_x_preferred":[
        "\u067e\u0633\u0646\u06cc"
    ],
    "name:por_x_preferred":[
        "Pasni"
    ],
    "name:rus_x_preferred":[
        "\u041f\u0430\u0441\u043d\u0438"
    ],
    "name:unk_x_variant":[
        "Pansi"
    ],
    "name:urd_x_preferred":[
        "\u067e\u0633\u0646\u06cc"
    ],
    "name:zho_x_preferred":[
        "\u4f2f\u65af\u5c3c"
    ],
    "qs:gn_country":"PK",
    "qs:gn_fcode":"PPL",
    "qs:gn_pop":33110,
    "qs:name":"Pasni",
    "qs:name_adm0":"Pakistan",
    "qs:name_adm1":"Balochistan",
    "qs:photos":0,
    "qs:photos_1k":0,
    "qs:photos_9k":1,
    "qs:photos_9r":2,
    "qs:photos_all":36,
    "qs:photos_sr":0,
    "qs:placetype":"Town",
    "qs:pop_sr":"7",
    "qs:woe_adm0":23424922,
    "wof:name":"Pasni",
    "wof:placetype":"locality",
    "wof:population":33110
},
  "geometry": {"coordinates":[63.47103,25.26311],"type":"Point"}
}