{
  "type": "Feature",
  "properties": {
    "gn:admin1_code":"4",
    "gn:asciiname":"Thathalwala Khu",
    "gn:country_code":"PK",
    "gn:dem":93,
    "gn:feature_class":"P",
    "gn:feature_code":"PPL",
    "gn:name":"Thathalwala Khu",
    "gn:population":0,
    "gn:timezone":"Asia/Karachi",
    "iso:country":"PK",
    "name:und_x_variant":[
        "Barew\u0101la"
    ],
    "wof:name":"Thathalwala Khu",
    "wof:placetype":"locality"
},
  "geometry": {"coordinates":[70.43819000000001,29.13255],"type":"Point"}
}