{
  "type": "Feature",
  "properties": {
    "gn:admin1_code":"2.0",
    "gn:asciiname":"Kili Faiz Muhammad",
    "gn:country_code":"PK",
    "gn:dem":2150,
    "gn:feature_class":"P",
    "gn:feature_code":"PPL",
    "gn:name":"Kili Faiz Muhammad",
    "gn:population":0,
    "gn:timezone":"Asia/Karachi",
    "iso:country":"PK",
    "wof:name":"Kili Faiz Muhammad",
    "wof:placetype":"locality"
},
  "geometry": {"coordinates":[66.90975999999999,31.10311],"type":"Point"}
}