{
  "type": "Feature",
  "properties": {
    "gn:admin1_code":"4",
    "gn:asciiname":"Basti Markand",
    "gn:country_code":"PK",
    "gn:dem":105,
    "gn:feature_class":"P",
    "gn:feature_code":"PPL",
    "gn:name":"Basti Markand",
    "gn:population":0,
    "gn:timezone":"Asia/Karachi",
    "iso:country":"PK",
    "wof:name":"Basti Markand",
    "wof:placetype":"locality"
},
  "geometry": {"coordinates":[70.95416999999998,29.50528],"type":"Point"}
}