{
  "type": "Feature",
  "properties": {
    "gn:admin1_code":"2.0",
    "gn:asciiname":"Gul Mir",
    "gn:country_code":"PK",
    "gn:dem":80,
    "gn:feature_class":"P",
    "gn:feature_code":"PPL",
    "gn:name":"Gul Mir",
    "gn:population":0,
    "gn:timezone":"Asia/Karachi",
    "iso:country":"PK",
    "wof:name":"Gul Mir",
    "wof:placetype":"locality"
},
  "geometry": {"coordinates":[67.82698000000001,28.84833],"type":"Point"}
}