{
  "type": "Feature",
  "properties": {
    "gn:admin1_code":"5",
    "gn:asciiname":"Ayub Khan",
    "gn:country_code":"PK",
    "gn:dem":11,
    "gn:feature_class":"P",
    "gn:feature_code":"PPL",
    "gn:name":"Ayub Khan",
    "gn:population":0,
    "gn:timezone":"Asia/Karachi",
    "iso:country":"PK",
    "name:deu_x_preferred":[
        "Ayub Khan"
    ],
    "name:hin_x_preferred":[
        "\u0905\u092f\u0942\u092c \u0916\u093c\u093e\u0928"
    ],
    "name:ind_x_preferred":[
        "Ayub Khan"
    ],
    "name:msa_x_preferred":[
        "Ayub Khan"
    ],
    "name:pol_x_preferred":[
        "Ayub Khan"
    ],
    "name:swe_x_preferred":[
        "Ayub Khan"
    ],
    "wof:name":"Ayub Khan",
    "wof:placetype":"locality"
},
  "geometry": {"coordinates":[69.44444,25.29028],"type":"Point"}
}