{
  "type": "Feature",
  "properties": {
    "gn:admin1_code":"3",
    "gn:asciiname":"Faqirabad",
    "gn:country_code":"PK",
    "gn:dem":293,
    "gn:feature_class":"P",
    "gn:feature_code":"PPL",
    "gn:name":"Faqirabad",
    "gn:population":0,
    "gn:timezone":"Asia/Karachi",
    "iso:country":"PK",
    "name:eng_x_preferred":[
        "B\u0101nda"
    ],
    "wof:name":"Faqirabad",
    "wof:placetype":"locality"
},
  "geometry": {"coordinates":[71.77110999999999,34.12611],"type":"Point"}
}