{
  "type": "Feature",
  "properties": {
    "gn:admin1_code":"3",
    "gn:asciiname":"Shandai",
    "gn:country_code":"PK",
    "gn:dem":2218,
    "gn:feature_class":"P",
    "gn:feature_code":"PPL",
    "gn:name":"Shandai",
    "gn:population":0,
    "gn:timezone":"Asia/Karachi",
    "iso:country":"PK",
    "name:eng_x_preferred":[
        "Shadal"
    ],
    "wof:name":"Shandai",
    "wof:placetype":"locality"
},
  "geometry": {"coordinates":[71.79456,35.2018],"type":"Point"}
}