{
  "type": "Feature",
  "properties": {
    "gn:admin1_code":"04",
    "gn:asciiname":"Chak Forty -Gogera Distributary",
    "gn:country_code":"PK",
    "gn:dem":178,
    "gn:feature_class":"P",
    "gn:feature_code":"PPL",
    "gn:name":"Chak Forty -Gogera Distributary",
    "gn:population":0,
    "gn:timezone":"Asia/Karachi",
    "iso:country":"PK",
    "name:und_x_variant":[
        "R\u0101ipur"
    ],
    "wof:name":"Chak Forty -Gogera Distributary",
    "wof:placetype":"locality"
},
  "geometry": {"coordinates":[73.35174000000001,30.90386],"type":"Point"}
}