{
  "type": "Feature",
  "properties": {
    "gn:admin1_code":"2.0",
    "gn:asciiname":"Kili Ibrahim Khan",
    "gn:country_code":"PK",
    "gn:dem":2174,
    "gn:feature_class":"P",
    "gn:feature_code":"PPL",
    "gn:name":"Kili Ibrahim Khan",
    "gn:population":0,
    "gn:timezone":"Asia/Karachi",
    "iso:country":"PK",
    "wof:name":"Kili Ibrahim Khan",
    "wof:placetype":"locality"
},
  "geometry": {"coordinates":[66.44499,30.66664],"type":"Point"}
}