{
  "type": "Feature",
  "properties": {
    "gn:admin1_code":"7.0",
    "gn:asciiname":"Saskun",
    "gn:country_code":"PK",
    "gn:dem":1456,
    "gn:feature_class":"P",
    "gn:feature_code":"PPL",
    "gn:name":"Saskun",
    "gn:population":0,
    "gn:timezone":"Asia/Karachi",
    "iso:country":"PK",
    "wof:name":"Saskun",
    "wof:placetype":"locality"
},
  "geometry": {"coordinates":[73.72048000000002,35.56808],"type":"Point"}
}