{
  "type": "Feature",
  "properties": {
    "gn:admin1_code":"2.0",
    "gn:asciiname":"Baran Mullazai",
    "gn:country_code":"PK",
    "gn:dem":2218,
    "gn:feature_class":"P",
    "gn:feature_code":"PPL",
    "gn:name":"Baran Mullazai",
    "gn:population":0,
    "gn:timezone":"Asia/Karachi",
    "iso:country":"PK",
    "wof:name":"Baran Mullazai",
    "wof:placetype":"locality"
},
  "geometry": {"coordinates":[67.63849,31.4178],"type":"Point"}
}