{
  "type": "Feature",
  "properties": {
    "gn:admin1_code":"3.0",
    "gn:asciiname":"Patura",
    "gn:country_code":"PK",
    "gn:dem":1055,
    "gn:feature_class":"P",
    "gn:feature_code":"PPL",
    "gn:name":"Patura",
    "gn:population":0,
    "gn:timezone":"Asia/Karachi",
    "iso:country":"PK",
    "wof:name":"Patura",
    "wof:placetype":"locality"
},
  "geometry": {"coordinates":[73.48081999999999,34.18283],"type":"Point"}
}