{
  "type": "Feature",
  "properties": {
    "gn:admin1_code":"5",
    "gn:asciiname":"Abdur Rahman Kalhora",
    "gn:country_code":"PK",
    "gn:dem":65,
    "gn:feature_class":"P",
    "gn:feature_code":"PPL",
    "gn:name":"Abdur Rahman Kalhora",
    "gn:population":0,
    "gn:timezone":"Asia/Karachi",
    "iso:country":"PK",
    "name:und_x_variant":[
        "Abdul Rehm\u0101n Kalhora"
    ],
    "wof:name":"Abdur Rahman Kalhora",
    "wof:placetype":"locality"
},
  "geometry": {"coordinates":[68.87191,28.03182],"type":"Point"}
}