{
  "type": "Feature",
  "properties": {
    "gn:admin1_code":"3.0",
    "gn:asciiname":"Gul Beli",
    "gn:country_code":"PK",
    "gn:dem":2524,
    "gn:feature_class":"P",
    "gn:feature_code":"PPL",
    "gn:name":"Gul Beli",
    "gn:population":0,
    "gn:timezone":"Asia/Karachi",
    "iso:country":"PK",
    "wof:name":"Gul Beli",
    "wof:placetype":"locality"
},
  "geometry": {"coordinates":[71.73683,35.98363],"type":"Point"}
}