{
  "type": "Feature",
  "properties": {
    "gn:admin1_code":"4.0",
    "gn:asciiname":"Chak Khido",
    "gn:country_code":"PK",
    "gn:dem":270,
    "gn:feature_class":"P",
    "gn:feature_code":"PPL",
    "gn:name":"Chak Khido",
    "gn:population":0,
    "gn:timezone":"Asia/Karachi",
    "iso:country":"PK",
    "wof:name":"Chak Khido",
    "wof:placetype":"locality"
},
  "geometry": {"coordinates":[74.85736,32.39481],"type":"Point"}
}