{
  "type": "Feature",
  "properties": {
    "gn:admin1_code":"4.0",
    "gn:asciiname":"Chak Three Hundred Thirty-five",
    "gn:country_code":"PK",
    "gn:dem":176,
    "gn:feature_class":"P",
    "gn:feature_code":"PPL",
    "gn:name":"Chak Three Hundred Thirty-five",
    "gn:population":0,
    "gn:timezone":"Asia/Karachi",
    "iso:country":"PK",
    "name:eng_x_preferred":[
        "Chak Three Hundred Thirty-five"
    ],
    "name:und_x_variant":[
        "Bedinpur",
        "Bad\u012bnpur",
        "Dostpur"
    ],
    "wof:name":"Chak Three Hundred Thirty-five",
    "wof:placetype":"locality"
},
  "geometry": {"coordinates":[72.7384,31.34392],"type":"Point"}
}