{
  "type": "Feature",
  "properties": {
    "gn:admin1_code":"3",
    "gn:asciiname":"Ucharn Lasht",
    "gn:country_code":"PK",
    "gn:dem":2662,
    "gn:feature_class":"P",
    "gn:feature_code":"PPL",
    "gn:name":"Ucharn Lasht",
    "gn:population":0,
    "gn:timezone":"Asia/Karachi",
    "iso:country":"PK",
    "name:eng_x_preferred":[
        "Uchsh\u012ba Lasht"
    ],
    "wof:name":"Ucharn Lasht",
    "wof:placetype":"locality"
},
  "geometry": {"coordinates":[71.56314,35.96803],"type":"Point"}
}