{
  "type": "Feature",
  "properties": {
    "gn:admin1_code":"3.0",
    "gn:asciiname":"Changla Gali",
    "gn:country_code":"PK",
    "gn:dem":2489,
    "gn:feature_class":"P",
    "gn:feature_code":"PPL",
    "gn:name":"Changla Gali",
    "gn:population":0,
    "gn:timezone":"Asia/Karachi",
    "iso:country":"PK",
    "name:fas_x_preferred":[
        "\u0686\u0647\u0627\u0646\u06af\u0644\u0647 \u06af\u0644\u06cc"
    ],
    "name:fra_x_preferred":[
        "Changla Gali"
    ],
    "name:und_x_variant":[
        "Chh\u0101ngla Gali"
    ],
    "name:urd_x_preferred":[
        "\u0686\u06be\u0627\u0646\u06af\u0644\u06c1 \u06af\u0644\u06cc"
    ],
    "wof:name":"Changla Gali",
    "wof:placetype":"locality"
},
  "geometry": {"coordinates":[73.37674,33.99558],"type":"Point"}
}