{
  "type": "Feature",
  "properties": {
    "gn:admin1_code":"2.0",
    "gn:asciiname":"Goth Ali Nawaz Khan",
    "gn:country_code":"PK",
    "gn:dem":68,
    "gn:feature_class":"P",
    "gn:feature_code":"PPL",
    "gn:name":"Goth Ali Nawaz Khan",
    "gn:population":0,
    "gn:timezone":"Asia/Karachi",
    "iso:country":"PK",
    "wof:name":"Goth Ali Nawaz Khan",
    "wof:placetype":"locality"
},
  "geometry": {"coordinates":[68.44879,28.65861],"type":"Point"}
}