{
  "type": "Feature",
  "properties": {
    "gn:admin1_code":"6",
    "gn:asciiname":"Dhoda",
    "gn:country_code":"PK",
    "gn:dem":2587,
    "gn:feature_class":"P",
    "gn:feature_code":"PPL",
    "gn:name":"Dhoda",
    "gn:population":0,
    "gn:timezone":"Asia/Karachi",
    "iso:country":"PK",
    "wof:name":"Dhoda",
    "wof:placetype":"locality"
},
  "geometry": {"coordinates":[73.58445,34.3866],"type":"Point"}
}