{
  "type": "Feature",
  "properties": {
    "gn:admin1_code":"4",
    "gn:asciiname":"Kheoti",
    "gn:country_code":"PK",
    "gn:dem":103,
    "gn:feature_class":"P",
    "gn:feature_code":"PPL",
    "gn:name":"Kheoti",
    "gn:population":0,
    "gn:timezone":"Asia/Karachi",
    "iso:country":"PK",
    "wof:name":"Kheoti",
    "wof:placetype":"locality"
},
  "geometry": {"coordinates":[71.24391999999997,29.13167],"type":"Point"}
}