{
  "type": "Feature",
  "properties": {
    "gn:admin1_code":"1.0",
    "gn:asciiname":"Sorai Mela",
    "gn:country_code":"PK",
    "gn:dem":1174,
    "gn:feature_class":"P",
    "gn:feature_code":"PPL",
    "gn:name":"Sorai Mela",
    "gn:population":0,
    "gn:timezone":"Asia/Karachi",
    "iso:country":"PK",
    "wof:name":"Sorai Mela",
    "wof:placetype":"locality"
},
  "geometry": {"coordinates":[70.23056,33.61806],"type":"Point"}
}