{
  "type": "Feature",
  "properties": {
    "gn:admin1_code":"3",
    "gn:asciiname":"Hal Saividan",
    "gn:country_code":"PK",
    "gn:dem":1343,
    "gn:feature_class":"P",
    "gn:feature_code":"PPL",
    "gn:name":"Hal Saividan",
    "gn:population":0,
    "gn:timezone":"Asia/Karachi",
    "iso:country":"PK",
    "name:und_x_variant":[
        "Hal"
    ],
    "wof:name":"Hal Saividan",
    "wof:placetype":"locality"
},
  "geometry": {"coordinates":[73.124,34.18236],"type":"Point"}
}