{
  "type": "Feature",
  "properties": {
    "gn:admin1_code":"4.0",
    "gn:asciiname":"Khaler Baragh",
    "gn:country_code":"PK",
    "gn:dem":735,
    "gn:feature_class":"P",
    "gn:feature_code":"PPL",
    "gn:name":"Khaler Baragh",
    "gn:population":0,
    "gn:timezone":"Asia/Karachi",
    "iso:country":"PK",
    "name:eng_x_preferred":[
        "Khaler Bar\u0101g"
    ],
    "wof:name":"Khaler Baragh",
    "wof:placetype":"locality"
},
  "geometry": {"coordinates":[70.19759999999999,30.14838],"type":"Point"}
}