{
  "type": "Feature",
  "properties": {
    "gn:admin1_code":"4.0",
    "gn:asciiname":"Allahabad Colony",
    "gn:country_code":"PK",
    "gn:dem":183,
    "gn:feature_class":"P",
    "gn:feature_code":"PPL",
    "gn:name":"Allahabad Colony",
    "gn:population":0,
    "gn:timezone":"Asia/Karachi",
    "iso:country":"PK",
    "name:eng_x_preferred":[
        "Allahabad Colony"
    ],
    "name:urd_x_preferred":[
        "\u0627\u0644\u0644\u06c1 \u0622\u0628\u0627\u062f \u06a9\u0627\u0644\u0648\u0646\u06cc"
    ],
    "wof:name":"Allahabad Colony",
    "wof:placetype":"locality"
},
  "geometry": {"coordinates":[72.22712,32.12822],"type":"Point"}
}