{
  "type": "Feature",
  "properties": {
    "gn:admin1_code":"5.0",
    "gn:asciiname":"Makarsi Mandhro",
    "gn:country_code":"PK",
    "gn:dem":5,
    "gn:feature_class":"P",
    "gn:feature_code":"PPL",
    "gn:name":"Makarsi Mandhro",
    "gn:population":0,
    "gn:timezone":"Asia/Karachi",
    "iso:country":"PK",
    "wof:name":"Makarsi Mandhro",
    "wof:placetype":"locality"
},
  "geometry": {"coordinates":[68.77605,24.45642],"type":"Point"}
}