{
  "type": "Feature",
  "properties": {
    "gn:admin1_code":"2.0",
    "gn:asciiname":"Goth Saleh",
    "gn:country_code":"PK",
    "gn:dem":18,
    "gn:feature_class":"P",
    "gn:feature_code":"PPL",
    "gn:name":"Goth Saleh",
    "gn:population":0,
    "gn:timezone":"Asia/Karachi",
    "iso:country":"PK",
    "name:eng_x_preferred":[
        "Goth Saleh"
    ],
    "wof:name":"Goth Saleh",
    "wof:placetype":"locality"
},
  "geometry": {"coordinates":[66.68564000000001,25.4316],"type":"Point"}
}