{
  "type": "Feature",
  "properties": {
    "gn:admin1_code":"4",
    "gn:asciiname":"Banda Shaikhan",
    "gn:country_code":"PK",
    "gn:dem":211,
    "gn:feature_class":"P",
    "gn:feature_code":"PPL",
    "gn:name":"B\u0101nda Shaikh\u0101n",
    "gn:population":0,
    "gn:timezone":"Asia/Karachi",
    "iso:country":"PK",
    "wof:name":"Banda Shaikhan",
    "wof:placetype":"locality"
},
  "geometry": {"coordinates":[71.24861,32.66667],"type":"Point"}
}