{
  "type": "Feature",
  "properties": {
    "gn:admin1_code":"6",
    "gn:asciiname":"Mera Kandi",
    "gn:country_code":"PK",
    "gn:dem":435,
    "gn:feature_class":"P",
    "gn:feature_code":"PPL",
    "gn:name":"Mera Kandi",
    "gn:population":0,
    "gn:timezone":"Asia/Karachi",
    "iso:country":"PK",
    "wof:name":"Mera Kandi",
    "wof:placetype":"locality"
},
  "geometry": {"coordinates":[73.82380000000001,33.26129],"type":"Point"}
}