{
  "type": "Feature",
  "properties": {
    "gn:admin1_code":"04",
    "gn:asciiname":"Kotli",
    "gn:country_code":"PK",
    "gn:dem":251,
    "gn:feature_class":"P",
    "gn:feature_code":"PPL",
    "gn:name":"Kotli",
    "gn:population":0,
    "gn:timezone":"Asia/Karachi",
    "iso:country":"PK",
    "name:und_x_variant":[
        "Kotli Qanungoi",
        "Kotli K\u0101nungo",
        "Kotli"
    ],
    "wof:name":"Kotli",
    "wof:placetype":"locality"
},
  "geometry": {"coordinates":[75.00824,32.20555],"type":"Point"}
}