{
  "type": "Feature",
  "properties": {
    "gn:admin1_code":"3.0",
    "gn:asciiname":"Giarh",
    "gn:country_code":"PK",
    "gn:dem":1679,
    "gn:feature_class":"P",
    "gn:feature_code":"PPL",
    "gn:name":"Giarh",
    "gn:population":0,
    "gn:timezone":"Asia/Karachi",
    "iso:country":"PK",
    "name:und_x_variant":[
        "Gi\u0101r"
    ],
    "wof:name":"Giarh",
    "wof:placetype":"locality"
},
  "geometry": {"coordinates":[73.34617,33.97722],"type":"Point"}
}