{
  "type": "Feature",
  "properties": {
    "gn:admin1_code":"3.0",
    "gn:asciiname":"Karin",
    "gn:country_code":"PK",
    "gn:dem":2164,
    "gn:feature_class":"P",
    "gn:feature_code":"PPL",
    "gn:name":"Karin",
    "gn:population":0,
    "gn:timezone":"Asia/Karachi",
    "iso:country":"PK",
    "wof:name":"Karin",
    "wof:placetype":"locality"
},
  "geometry": {"coordinates":[73.02965,35.09321],"type":"Point"}
}