{
  "type": "Feature",
  "properties": {
    "gn:admin1_code":"3.0",
    "gn:asciiname":"Karin",
    "gn:country_code":"PK",
    "gn:dem":2164,
    "gn:feature_class":"P",
    "gn:feature_code":"PPL",
    "gn:name":"Karin",
    "gn:population":0,
    "gn:timezone":"Asia/Karachi",
    "iso:country":"PK",
    "name:bos_x_preferred":[
        "Karin"
    ],
    "name:ceb_x_preferred":[
        "Karin"
    ],
    "name:deu_x_preferred":[
        "Karin"
    ],
    "name:fra_x_preferred":[
        "Karin"
    ],
    "name:hrv_x_preferred":[
        "Karin"
    ],
    "name:ita_x_preferred":[
        "Karin"
    ],
    "name:jpn_x_preferred":[
        "\u30ab\u30ea\u30f3"
    ],
    "name:nld_x_preferred":[
        "Karin"
    ],
    "name:pol_x_preferred":[
        "Karin"
    ],
    "name:rus_x_preferred":[
        "\u041a\u0430\u0440\u0438\u043d"
    ],
    "name:spa_x_preferred":[
        "Karin"
    ],
    "name:srp_x_preferred":[
        "\u041a\u0430\u0440\u0438\u043d"
    ],
    "name:ukr_x_preferred":[
        "\u041a\u0430\u0440\u0456\u043d"
    ],
    "wof:name":"Karin",
    "wof:placetype":"locality"
},
  "geometry": {"coordinates":[73.02965,35.09321],"type":"Point"}
}