{
  "type": "Feature",
  "properties": {
    "gn:admin1_code":"4",
    "gn:asciiname":"Tarsangi",
    "gn:country_code":"PK",
    "gn:dem":141,
    "gn:feature_class":"P",
    "gn:feature_code":"PPL",
    "gn:name":"Tarsangi",
    "gn:population":0,
    "gn:timezone":"Asia/Karachi",
    "iso:country":"PK",
    "name:und_x_variant":[
        "Tars\u0101ng\u012bw\u0101la"
    ],
    "wof:name":"Tarsangi",
    "wof:placetype":"locality"
},
  "geometry": {"coordinates":[72.46061999999998,30.14238],"type":"Point"}
}