{
  "type": "Feature",
  "properties": {
    "gn:admin1_code":"04",
    "gn:asciiname":"Chak Fifty-three -Three Right",
    "gn:country_code":"PK",
    "gn:dem":178,
    "gn:feature_class":"P",
    "gn:feature_code":"PPL",
    "gn:name":"Chak Fifty-three -Three Right",
    "gn:population":0,
    "gn:timezone":"Asia/Karachi",
    "iso:country":"PK",
    "name:und_x_variant":[
        "N\u0101lew\u0101la"
    ],
    "wof:name":"Chak Fifty-three -Three Right",
    "wof:placetype":"locality"
},
  "geometry": {"coordinates":[73.26572,30.79722000000001],"type":"Point"}
}