{
  "type": "Feature",
  "properties": {
    "gn:admin1_code":"5.0",
    "gn:asciiname":"Goth Ismail Maljo",
    "gn:country_code":"PK",
    "gn:dem":1,
    "gn:feature_class":"P",
    "gn:feature_code":"PPL",
    "gn:name":"Goth Ismail Maljo",
    "gn:population":0,
    "gn:timezone":"Asia/Karachi",
    "iso:country":"PK",
    "wof:name":"Goth Ismail Maljo",
    "wof:placetype":"locality"
},
  "geometry": {"coordinates":[67.55255,24.038],"type":"Point"}
}