{
  "type": "Feature",
  "properties": {
    "gn:admin1_code":"3.0",
    "gn:asciiname":"Mama Ji Kalle",
    "gn:country_code":"PK",
    "gn:dem":316,
    "gn:feature_class":"P",
    "gn:feature_code":"PPL",
    "gn:name":"Mama Ji Kalle",
    "gn:population":0,
    "gn:timezone":"Asia/Karachi",
    "iso:country":"PK",
    "wof:name":"Mama Ji Kalle",
    "wof:placetype":"locality"
},
  "geometry": {"coordinates":[72.11346999999998,34.10123],"type":"Point"}
}