{
  "type": "Feature",
  "properties": {
    "gn:admin1_code":"3.0",
    "gn:asciiname":"Kalawan",
    "gn:country_code":"PK",
    "gn:dem":3828,
    "gn:feature_class":"P",
    "gn:feature_code":"PPL",
    "gn:name":"Kalawan",
    "gn:population":0,
    "gn:timezone":"Asia/Karachi",
    "iso:country":"PK",
    "wof:name":"Kalawan",
    "wof:placetype":"locality"
},
  "geometry": {"coordinates":[73.98524999999999,35.15425],"type":"Point"}
}