{
  "type": "Feature",
  "properties": {
    "gn:admin1_code":"3.0",
    "gn:asciiname":"Multani Landidak",
    "gn:country_code":"PK",
    "gn:dem":321,
    "gn:feature_class":"P",
    "gn:feature_code":"PPL",
    "gn:name":"Multani Landidak",
    "gn:population":0,
    "gn:timezone":"Asia/Karachi",
    "iso:country":"PK",
    "name:und_x_variant":[
        "Mult\u0101ni"
    ],
    "wof:name":"Multani Landidak",
    "wof:placetype":"locality"
},
  "geometry": {"coordinates":[70.63330000000001,32.84145],"type":"Point"}
}