{
  "type": "Feature",
  "properties": {
    "gn:admin1_code":"2",
    "gn:asciiname":"Jogianie Selajh",
    "gn:country_code":"PK",
    "gn:dem":1245,
    "gn:feature_class":"P",
    "gn:feature_code":"PPL",
    "gn:name":"Jogianie Selajh",
    "gn:population":0,
    "gn:timezone":"Asia/Karachi",
    "iso:country":"PK",
    "name:und_x_variant":[
        "Selach",
        "Jogian",
        "Jogianie Selajh"
    ],
    "wof:name":"Jogianie Selajh",
    "wof:placetype":"locality"
},
  "geometry": {"coordinates":[69.77903000000001,30.00372],"type":"Point"}
}