{
  "type": "Feature",
  "properties": {
    "gn:admin1_code":"4",
    "gn:asciiname":"Purana Qita Bara",
    "gn:country_code":"PK",
    "gn:dem":126,
    "gn:feature_class":"P",
    "gn:feature_code":"PPL",
    "gn:name":"Purana Qita Bara",
    "gn:population":0,
    "gn:timezone":"Asia/Karachi",
    "iso:country":"PK",
    "name:und_x_variant":[
        "Qita B\u0101ra"
    ],
    "wof:name":"Purana Qita Bara",
    "wof:placetype":"locality"
},
  "geometry": {"coordinates":[71.84416999999998,30.36736],"type":"Point"}
}