{
  "type": "Feature",
  "properties": {
    "gn:admin1_code":"2.0",
    "gn:asciiname":"Mangalzai Kili",
    "gn:country_code":"PK",
    "gn:dem":2004,
    "gn:feature_class":"P",
    "gn:feature_code":"PPL",
    "gn:name":"Mangalzai Kili",
    "gn:population":0,
    "gn:timezone":"Asia/Karachi",
    "iso:country":"PK",
    "wof:name":"Mangalzai Kili",
    "wof:placetype":"locality"
},
  "geometry": {"coordinates":[69.74153000000001,31.47965],"type":"Point"}
}