{
  "type": "Feature",
  "properties": {
    "gn:admin1_code":"02",
    "gn:asciiname":"Nasozai",
    "gn:country_code":"PK",
    "gn:dem":1509,
    "gn:feature_class":"P",
    "gn:feature_code":"PPL",
    "gn:name":"Nasozai",
    "gn:population":0,
    "gn:timezone":"Asia/Karachi",
    "iso:country":"PK",
    "name:und_x_variant":[
        "Nassozai",
        "Nasozi",
        "Nasozai"
    ],
    "wof:name":"Nasozai",
    "wof:placetype":"locality"
},
  "geometry": {"coordinates":[66.94409,30.48261],"type":"Point"}
}