{
  "type": "Feature",
  "properties": {
    "gn:admin1_code":"3",
    "gn:asciiname":"Serai",
    "gn:country_code":"PK",
    "gn:dem":1839,
    "gn:feature_class":"P",
    "gn:feature_code":"PPL",
    "gn:name":"Serai",
    "gn:population":0,
    "gn:timezone":"Asia/Karachi",
    "iso:country":"PK",
    "wof:name":"Serai",
    "wof:placetype":"locality"
},
  "geometry": {"coordinates":[73.04418000000003,34.85219],"type":"Point"}
}