{
  "type": "Feature",
  "properties": {
    "gn:admin1_code":"6.0",
    "gn:asciiname":"Bat Kalli",
    "gn:country_code":"PK",
    "gn:dem":2167,
    "gn:feature_class":"P",
    "gn:feature_code":"PPL",
    "gn:name":"Bat Kalli",
    "gn:population":0,
    "gn:timezone":"Asia/Karachi",
    "iso:country":"PK",
    "wof:name":"Bat Kalli",
    "wof:placetype":"locality"
},
  "geometry": {"coordinates":[73.55556999999997,34.50574],"type":"Point"}
}