{
  "type": "Feature",
  "properties": {
    "gn:admin1_code":"1.0",
    "gn:asciiname":"Kaskai",
    "gn:country_code":"PK",
    "gn:dem":1944,
    "gn:feature_class":"P",
    "gn:feature_code":"PPL",
    "gn:name":"Kaskai",
    "gn:population":0,
    "gn:timezone":"Asia/Karachi",
    "iso:country":"PK",
    "wof:name":"Kaskai",
    "wof:placetype":"locality"
},
  "geometry": {"coordinates":[69.62579000000001,33.0463],"type":"Point"}
}