{
  "type": "Feature",
  "properties": {
    "gn:admin1_code":"6",
    "gn:asciiname":"Karshan",
    "gn:country_code":"PK",
    "gn:dem":1140,
    "gn:feature_class":"P",
    "gn:feature_code":"PPL",
    "gn:name":"Karshan",
    "gn:population":0,
    "gn:timezone":"Asia/Karachi",
    "iso:country":"PK",
    "wof:name":"Karshan",
    "wof:placetype":"locality"
},
  "geometry": {"coordinates":[73.49082,34.4766],"type":"Point"}
}