{
  "type": "Feature",
  "properties": {
    "gn:admin1_code":"03",
    "gn:asciiname":"Patai",
    "gn:country_code":"PK",
    "gn:dem":353,
    "gn:feature_class":"P",
    "gn:feature_code":"PPL",
    "gn:name":"Patai",
    "gn:population":0,
    "gn:timezone":"Asia/Karachi",
    "iso:country":"PK",
    "name:eng_x_preferred":[
        "Patai"
    ],
    "name:und_x_variant":[
        "P\u0101t\u0101l"
    ],
    "wof:name":"Patai",
    "wof:placetype":"locality"
},
  "geometry": {"coordinates":[71.91679000000001,34.28583],"type":"Point"}
}