{
  "type": "Feature",
  "properties": {
    "gn:admin1_code":"5.0",
    "gn:asciiname":"Goth Qaiser Khan Dasti",
    "gn:country_code":"PK",
    "gn:dem":24,
    "gn:feature_class":"P",
    "gn:feature_code":"PPL",
    "gn:name":"Goth Qaiser Khan Dasti",
    "gn:population":0,
    "gn:timezone":"Asia/Karachi",
    "iso:country":"PK",
    "name:eng_x_preferred":[
        "Goth Qaiser Khan Dasti"
    ],
    "wof:name":"Goth Qaiser Khan Dasti",
    "wof:placetype":"locality"
},
  "geometry": {"coordinates":[68.32694000000001,25.34463],"type":"Point"}
}