{
  "type": "Feature",
  "properties": {
    "gn:admin1_code":"7.0",
    "gn:asciiname":"Thurgon",
    "gn:country_code":"PK",
    "gn:dem":2241,
    "gn:feature_class":"P",
    "gn:feature_code":"PPL",
    "gn:name":"Thurgon",
    "gn:population":0,
    "gn:timezone":"Asia/Karachi",
    "iso:country":"PK",
    "name:und_x_variant":[
        "Gomba Thurgon"
    ],
    "wof:name":"Thurgon",
    "wof:placetype":"locality"
},
  "geometry": {"coordinates":[75.74308000000001,35.3014],"type":"Point"}
}