{
  "type": "Feature",
  "properties": {
    "gn:admin1_code":"5",
    "gn:asciiname":"Phojo Ghun",
    "gn:country_code":"PK",
    "gn:dem":32,
    "gn:feature_class":"P",
    "gn:feature_code":"PPL",
    "gn:name":"Phojo Ghun",
    "gn:population":0,
    "gn:timezone":"Asia/Karachi",
    "iso:country":"PK",
    "name:und_x_variant":[
        "Phajo Ghur"
    ],
    "wof:name":"Phojo Ghun",
    "wof:placetype":"locality"
},
  "geometry": {"coordinates":[68.52163,26.19626],"type":"Point"}
}