{
  "type": "Feature",
  "properties": {
    "gn:admin1_code":"4.0",
    "gn:asciiname":"Baghail Singwala",
    "gn:country_code":"PK",
    "gn:dem":205,
    "gn:feature_class":"P",
    "gn:feature_code":"PPL",
    "gn:name":"Baghail Singwala",
    "gn:population":0,
    "gn:timezone":"Asia/Karachi",
    "iso:country":"PK",
    "name:und_x_variant":[
        "Baghel Singhw\u0101la"
    ],
    "wof:name":"Baghail Singwala",
    "wof:placetype":"locality"
},
  "geometry": {"coordinates":[74.23220999999999,31.13894],"type":"Point"}
}