{
  "type": "Feature",
  "properties": {
    "gn:admin1_code":"4.0",
    "gn:asciiname":"Mansurian",
    "gn:country_code":"PK",
    "gn:dem":80,
    "gn:feature_class":"P",
    "gn:feature_code":"PPL",
    "gn:name":"Mansurian",
    "gn:population":0,
    "gn:timezone":"Asia/Karachi",
    "iso:country":"PK",
    "name:und_x_variant":[
        "Mash\u016br",
        "Mansurian"
    ],
    "wof:name":"Mansurian",
    "wof:placetype":"locality"
},
  "geometry": {"coordinates":[70.14524,28.33284],"type":"Point"}
}