{
  "type": "Feature",
  "properties": {
    "gn:admin1_code":"04",
    "gn:asciiname":"Chak One Hundred Twenty-Three RB",
    "gn:country_code":"PK",
    "gn:dem":185,
    "gn:feature_class":"P",
    "gn:feature_code":"PPL",
    "gn:name":"Chak One Hundred Twenty-Three RB",
    "gn:population":0,
    "gn:timezone":"Asia/Karachi",
    "iso:country":"PK",
    "name:und_x_variant":[
        "Sidhupur",
        "Chak One Hundred Twenty-Three RB"
    ],
    "wof:name":"Chak One Hundred Twenty-Three RB",
    "wof:placetype":"locality"
},
  "geometry": {"coordinates":[73.06520999999999,31.4545],"type":"Point"}
}