{
  "type": "Feature",
  "properties": {
    "gn:admin1_code":"5",
    "gn:asciiname":"Goth Haji Abdul Rehman Babar",
    "gn:country_code":"PK",
    "gn:dem":21,
    "gn:feature_class":"P",
    "gn:feature_code":"PPL",
    "gn:name":"Goth Haji Abdul Rehman Babar",
    "gn:population":0,
    "gn:timezone":"Asia/Karachi",
    "iso:country":"PK",
    "name:eng_x_preferred":[
        "Jorio Babar"
    ],
    "wof:name":"Goth Haji Abdul Rehman Babar",
    "wof:placetype":"locality"
},
  "geometry": {"coordinates":[68.22604,25.12114],"type":"Point"}
}