{
  "type": "Feature",
  "properties": {
    "gn:admin1_code":"5.0",
    "gn:asciiname":"Goth Bachal Sumro",
    "gn:country_code":"PK",
    "gn:dem":11,
    "gn:feature_class":"P",
    "gn:feature_code":"PPL",
    "gn:name":"Goth Bachal Sumro",
    "gn:population":0,
    "gn:timezone":"Asia/Karachi",
    "iso:country":"PK",
    "name:und_x_variant":[
        "Bacch\u0101i S\u016bmro"
    ],
    "wof:name":"Goth Bachal Sumro",
    "wof:placetype":"locality"
},
  "geometry": {"coordinates":[68.87966999999999,24.63894],"type":"Point"}
}