{
  "type": "Feature",
  "properties": {
    "gn:admin1_code":"5",
    "gn:asciiname":"Goth Mohabbat Lashari",
    "gn:country_code":"PK",
    "gn:dem":21,
    "gn:feature_class":"P",
    "gn:feature_code":"PPL",
    "gn:name":"Goth Mohabbat Lashari",
    "gn:population":0,
    "gn:timezone":"Asia/Karachi",
    "iso:country":"PK",
    "name:und_x_variant":[
        "Goth H\u0101ji Bachu"
    ],
    "wof:name":"Goth Mohabbat Lashari",
    "wof:placetype":"locality"
},
  "geometry": {"coordinates":[68.79424,25.55412],"type":"Point"}
}