{
  "type": "Feature",
  "properties": {
    "gn:admin1_code":"3",
    "gn:asciiname":"Khazana",
    "gn:country_code":"PK",
    "gn:dem":939,
    "gn:feature_class":"P",
    "gn:feature_code":"PPL",
    "gn:name":"Khazana",
    "gn:population":0,
    "gn:timezone":"Asia/Karachi",
    "iso:country":"PK",
    "name:eng_x_preferred":[
        "Khazana"
    ],
    "wof:name":"Khazana",
    "wof:placetype":"locality"
},
  "geometry": {"coordinates":[72.16889,34.72932],"type":"Point"}
}