{
  "type": "Feature",
  "properties": {
    "gn:admin1_code":"04",
    "gn:asciiname":"Ladha Langar",
    "gn:country_code":"PK",
    "gn:dem":131,
    "gn:feature_class":"P",
    "gn:feature_code":"PPL",
    "gn:name":"Ladha Langar",
    "gn:population":0,
    "gn:timezone":"Asia/Karachi",
    "iso:country":"PK",
    "name:eng_x_preferred":[
        "Laddha Langar"
    ],
    "name:eng_x_variant":[
        "Ladha Langhar"
    ],
    "name:und_x_variant":[
        "Ladha Langhar",
        "Ladha Langar"
    ],
    "wof:name":"Ladha Langar",
    "wof:placetype":"locality"
},
  "geometry": {"coordinates":[70.92915000000001,30.38356],"type":"Point"}
}