{
  "type": "Feature",
  "properties": {
    "gn:admin1_code":"01",
    "gn:asciiname":"Larimai Borinzai",
    "gn:country_code":"PK",
    "gn:dem":2378,
    "gn:feature_class":"P",
    "gn:feature_code":"PPL",
    "gn:name":"Larimai Borinzai",
    "gn:population":0,
    "gn:timezone":"Asia/Karachi",
    "iso:country":"PK",
    "name:und_x_variant":[
        "Kazhakai",
        "Larima"
    ],
    "wof:name":"Larimai Borinzai",
    "wof:placetype":"locality"
},
  "geometry": {"coordinates":[69.74831999999999,32.60604],"type":"Point"}
}