{
  "type": "Feature",
  "properties": {
    "gn:admin1_code":"5",
    "gn:asciiname":"Goth Hamza",
    "gn:country_code":"PK",
    "gn:dem":57,
    "gn:feature_class":"P",
    "gn:feature_code":"PPL",
    "gn:name":"Goth Hamza",
    "gn:population":0,
    "gn:timezone":"Asia/Karachi",
    "iso:country":"PK",
    "name:und_x_variant":[
        "Lahri Br\u0101hul"
    ],
    "wof:name":"Goth Hamza",
    "wof:placetype":"locality"
},
  "geometry": {"coordinates":[68.35641,28.07587],"type":"Point"}
}