{
  "type": "Feature",
  "properties": {
    "gn:admin1_code":"2.0",
    "gn:asciiname":"Sulaiman Khan Bazar",
    "gn:country_code":"PK",
    "gn:dem":335,
    "gn:feature_class":"P",
    "gn:feature_code":"PPL",
    "gn:name":"Sulaiman Khan Bazar",
    "gn:population":0,
    "gn:timezone":"Asia/Karachi",
    "iso:country":"PK",
    "name:und_x_variant":[
        "Sulaim\u0101n Kh\u0101n"
    ],
    "wof:name":"Sulaiman Khan Bazar",
    "wof:placetype":"locality"
},
  "geometry": {"coordinates":[65.48614999999999,26.26587],"type":"Point"}
}