{
  "type": "Feature",
  "properties": {
    "gn:admin1_code":"3.0",
    "gn:asciiname":"Boraka",
    "gn:country_code":"PK",
    "gn:dem":623,
    "gn:feature_class":"P",
    "gn:feature_code":"PPL",
    "gn:name":"Boraka",
    "gn:population":0,
    "gn:timezone":"Asia/Karachi",
    "iso:country":"PK",
    "wof:name":"Boraka",
    "wof:placetype":"locality"
},
  "geometry": {"coordinates":[71.23350000000001,33.53989],"type":"Point"}
}