{
  "type": "Feature",
  "properties": {
    "gn:admin1_code":"04",
    "gn:asciiname":"Lafi",
    "gn:country_code":"PK",
    "gn:dem":648,
    "gn:feature_class":"P",
    "gn:feature_code":"PPL",
    "gn:name":"Lafi",
    "gn:population":0,
    "gn:timezone":"Asia/Karachi",
    "iso:country":"PK",
    "name:und_x_variant":[
        "Laphi",
        "Lafi"
    ],
    "wof:name":"Lafi",
    "wof:placetype":"locality"
},
  "geometry": {"coordinates":[72.61843,32.63909],"type":"Point"}
}