{
  "type": "Feature",
  "properties": {
    "gn:admin1_code":"2",
    "gn:asciiname":"Moch",
    "gn:country_code":"PK",
    "gn:dem":106,
    "gn:feature_class":"P",
    "gn:feature_code":"PPL",
    "gn:name":"Moch",
    "gn:population":0,
    "gn:timezone":"Asia/Karachi",
    "iso:country":"PK",
    "name:und_x_variant":[
        "Shabkhor",
        "Moch"
    ],
    "wof:name":"Moch",
    "wof:placetype":"locality"
},
  "geometry": {"coordinates":[67.98747,29.17708],"type":"Point"}
}