{
  "type": "Feature",
  "properties": {
    "gn:admin1_code":"3.0",
    "gn:asciiname":"Shan Khel",
    "gn:country_code":"PK",
    "gn:dem":554,
    "gn:feature_class":"P",
    "gn:feature_code":"PPL",
    "gn:name":"Shan Khel",
    "gn:population":0,
    "gn:timezone":"Asia/Karachi",
    "iso:country":"PK",
    "wof:name":"Shan Khel",
    "wof:placetype":"locality"
},
  "geometry": {"coordinates":[70.22736999999999,32.29464],"type":"Point"}
}