{
  "type": "Feature",
  "properties": {
    "gn:admin1_code":"3",
    "gn:asciiname":"Jat",
    "gn:country_code":"PK",
    "gn:dem":1599,
    "gn:feature_class":"P",
    "gn:feature_code":"PPL",
    "gn:name":"Jat",
    "gn:population":0,
    "gn:timezone":"Asia/Karachi",
    "iso:country":"PK",
    "wof:name":"Jat",
    "wof:placetype":"locality"
},
  "geometry": {"coordinates":[72.95523,34.33483],"type":"Point"}
}