{
  "type": "Feature",
  "properties": {
    "gn:admin1_code":"4.0",
    "gn:asciiname":"Dhak Ghulam Kheli",
    "gn:country_code":"PK",
    "gn:dem":328,
    "gn:feature_class":"P",
    "gn:feature_code":"PPL",
    "gn:name":"Dhak Ghulam Kheli",
    "gn:population":0,
    "gn:timezone":"Asia/Karachi",
    "iso:country":"PK",
    "name:und_x_variant":[
        "Ghulamkheli Dhok"
    ],
    "wof:name":"Dhak Ghulam Kheli",
    "wof:placetype":"locality"
},
  "geometry": {"coordinates":[71.98773,33.46345],"type":"Point"}
}