{
  "type": "Feature",
  "properties": {
    "gn:admin1_code":"3",
    "gn:asciiname":"Khudu Khelo Derai",
    "gn:country_code":"PK",
    "gn:dem":640,
    "gn:feature_class":"P",
    "gn:feature_code":"PPL",
    "gn:name":"Khudu Khelo Derai",
    "gn:population":0,
    "gn:timezone":"Asia/Karachi",
    "iso:country":"PK",
    "wof:name":"Khudu Khelo Derai",
    "wof:placetype":"locality"
},
  "geometry": {"coordinates":[72.66511,34.43405],"type":"Point"}
}