{
  "type": "Feature",
  "properties": {
    "gn:admin1_code":"5.0",
    "gn:asciiname":"Hakim Ji Wand",
    "gn:country_code":"PK",
    "gn:dem":38,
    "gn:feature_class":"P",
    "gn:feature_code":"PPL",
    "gn:name":"Hakim Ji Wand",
    "gn:population":0,
    "gn:timezone":"Asia/Karachi",
    "iso:country":"PK",
    "wof:name":"Hakim Ji Wand",
    "wof:placetype":"locality"
},
  "geometry": {"coordinates":[69.69119999999999,25.91144],"type":"Point"}
}