{
  "type": "Feature",
  "properties": {
    "gn:admin1_code":"5.0",
    "gn:asciiname":"Shahdad Brahui",
    "gn:country_code":"PK",
    "gn:dem":37,
    "gn:feature_class":"P",
    "gn:feature_code":"PPL",
    "gn:name":"Shahdad Brahui",
    "gn:population":0,
    "gn:timezone":"Asia/Karachi",
    "iso:country":"PK",
    "name:eng_x_preferred":[
        "H\u0101ji Shahd\u0101d Brahui"
    ],
    "wof:name":"Shahdad Brahui",
    "wof:placetype":"locality"
},
  "geometry": {"coordinates":[68.05341,25.09012],"type":"Point"}
}