{
  "type": "Feature",
  "properties": {
    "gn:admin1_code":"4",
    "gn:asciiname":"Baluwala",
    "gn:country_code":"PK",
    "gn:dem":114,
    "gn:feature_class":"P",
    "gn:feature_code":"PPL",
    "gn:name":"Baluwala",
    "gn:population":0,
    "gn:timezone":"Asia/Karachi",
    "iso:country":"PK",
    "name:und_x_variant":[
        "B\u0101luw\u0101la",
        "B\u0101l\u016bw\u0101la"
    ],
    "wof:name":"Baluwala",
    "wof:placetype":"locality"
},
  "geometry": {"coordinates":[70.59739,29.91341],"type":"Point"}
}