{
  "type": "Feature",
  "properties": {
    "gn:admin1_code":"4",
    "gn:asciiname":"Noushehra",
    "gn:country_code":"PK",
    "gn:dem":111,
    "gn:feature_class":"P",
    "gn:feature_code":"PPL",
    "gn:name":"Noushehra",
    "gn:population":0,
    "gn:timezone":"Asia/Karachi",
    "iso:country":"PK",
    "name:eng_x_preferred":[
        "Naushera"
    ],
    "name:eng_x_variant":[
        "Naushahra"
    ],
    "wof:name":"Noushehra",
    "wof:placetype":"locality"
},
  "geometry": {"coordinates":[71.55148,29.20671],"type":"Point"}
}