{
  "type": "Feature",
  "properties": {
    "gn:admin1_code":"4.0",
    "gn:asciiname":"Saro",
    "gn:country_code":"PK",
    "gn:dem":211,
    "gn:feature_class":"P",
    "gn:feature_code":"PPL",
    "gn:name":"Saro",
    "gn:population":0,
    "gn:timezone":"Asia/Karachi",
    "iso:country":"PK",
    "name:ceb_x_preferred":[
        "Saro"
    ],
    "name:deu_x_preferred":[
        "Saro"
    ],
    "name:fra_x_preferred":[
        "Saro"
    ],
    "name:ita_x_preferred":[
        "Saro"
    ],
    "name:nld_x_preferred":[
        "Saro"
    ],
    "name:spa_x_preferred":[
        "Saro"
    ],
    "name:swe_x_preferred":[
        "Saro"
    ],
    "name:und_x_variant":[
        "Saroi"
    ],
    "wof:name":"Saro",
    "wof:placetype":"locality"
},
  "geometry": {"coordinates":[74.47726,31.29402],"type":"Point"}
}