{
  "type": "Feature",
  "properties": {
    "gn:admin1_code":"6",
    "gn:asciiname":"Khariala",
    "gn:country_code":"PK",
    "gn:dem":2299,
    "gn:feature_class":"P",
    "gn:feature_code":"PPL",
    "gn:name":"Khariala",
    "gn:population":0,
    "gn:timezone":"Asia/Karachi",
    "iso:country":"PK",
    "wof:name":"Khariala",
    "wof:placetype":"locality"
},
  "geometry": {"coordinates":[73.65241999999998,34.33942],"type":"Point"}
}