{
  "type": "Feature",
  "properties": {
    "gn:admin1_code":"6",
    "gn:asciiname":"Dhangri",
    "gn:country_code":"PK",
    "gn:dem":372,
    "gn:feature_class":"P",
    "gn:feature_code":"PPL",
    "gn:name":"Dhangri",
    "gn:population":0,
    "gn:timezone":"Asia/Karachi",
    "iso:country":"PK",
    "name:und_x_variant":[
        "Dhangri Bahadur"
    ],
    "wof:name":"Dhangri",
    "wof:placetype":"locality"
},
  "geometry": {"coordinates":[73.79214,33.22221],"type":"Point"}
}