{
  "type": "Feature",
  "properties": {
    "gn:admin1_code":"5.0",
    "gn:asciiname":"Goth Sufan Jakhro",
    "gn:country_code":"PK",
    "gn:dem":127,
    "gn:feature_class":"P",
    "gn:feature_code":"PPL",
    "gn:name":"Goth Sufan Jakhro",
    "gn:population":0,
    "gn:timezone":"Asia/Karachi",
    "iso:country":"PK",
    "name:eng_x_preferred":[
        "Goth Sufan J\u0101khro"
    ],
    "wof:name":"Goth Sufan Jakhro",
    "wof:placetype":"locality"
},
  "geometry": {"coordinates":[67.77491999999999,25.12598],"type":"Point"}
}