{
  "type": "Feature",
  "properties": {
    "gn:admin1_code":"4.0",
    "gn:asciiname":"Hazariwala",
    "gn:country_code":"PK",
    "gn:dem":108,
    "gn:feature_class":"P",
    "gn:feature_code":"PPL",
    "gn:name":"Hazariwala",
    "gn:population":0,
    "gn:timezone":"Asia/Karachi",
    "iso:country":"PK",
    "wof:name":"Hazariwala",
    "wof:placetype":"locality"
},
  "geometry": {"coordinates":[71.44476,29.25517],"type":"Point"}
}