{
  "type": "Feature",
  "properties": {
    "gn:admin1_code":"4",
    "gn:asciiname":"Chah Bambewala",
    "gn:country_code":"PK",
    "gn:dem":151,
    "gn:feature_class":"P",
    "gn:feature_code":"PPL",
    "gn:name":"Chah Bambewala",
    "gn:population":0,
    "gn:timezone":"Asia/Karachi",
    "iso:country":"PK",
    "name:und_x_variant":[
        "Basti Bambew\u0101la"
    ],
    "wof:name":"Chah Bambewala",
    "wof:placetype":"locality"
},
  "geometry": {"coordinates":[72.04881,31.10859],"type":"Point"}
}