{
  "type": "Feature",
  "properties": {
    "gn:admin1_code":"4.0",
    "gn:asciiname":"Yousaf Gil da Dera",
    "gn:country_code":"PK",
    "gn:dem":145,
    "gn:feature_class":"P",
    "gn:feature_code":"PPL",
    "gn:name":"Yousaf Gil da Dera",
    "gn:population":0,
    "gn:timezone":"Asia/Karachi",
    "iso:country":"PK",
    "wof:name":"Yousaf Gil da Dera",
    "wof:placetype":"locality"
},
  "geometry": {"coordinates":[72.85292,29.84455],"type":"Point"}
}