{
  "type": "Feature",
  "properties": {
    "gn:admin1_code":"2.0",
    "gn:asciiname":"Zarachi",
    "gn:country_code":"PK",
    "gn:dem":1890,
    "gn:feature_class":"P",
    "gn:feature_code":"PPL",
    "gn:name":"Zarachi",
    "gn:population":0,
    "gn:timezone":"Asia/Karachi",
    "iso:country":"PK",
    "wof:name":"Zarachi",
    "wof:placetype":"locality"
},
  "geometry": {"coordinates":[66.0615,28.6968],"type":"Point"}
}