{
  "type": "Feature",
  "properties": {
    "gn:admin1_code":"4",
    "gn:asciiname":"Tirhai",
    "gn:country_code":"PK",
    "gn:dem":131,
    "gn:feature_class":"P",
    "gn:feature_code":"PPL",
    "gn:name":"Tirh\u0101i",
    "gn:population":0,
    "gn:timezone":"Asia/Karachi",
    "iso:country":"PK",
    "name:eng_x_preferred":[
        "Tirh\u0101i"
    ],
    "wof:name":"Tirhai",
    "wof:placetype":"locality"
},
  "geometry": {"coordinates":[70.92901999999999,30.38375],"type":"Point"}
}