{
  "type": "Feature",
  "properties": {
    "gn:admin1_code":"2.0",
    "gn:asciiname":"Tando Gulab",
    "gn:country_code":"PK",
    "gn:dem":90,
    "gn:feature_class":"P",
    "gn:feature_code":"PPL",
    "gn:name":"Tando Gulab",
    "gn:population":0,
    "gn:timezone":"Asia/Karachi",
    "iso:country":"PK",
    "name:und_x_variant":[
        "Shahr Sobhd\u0101r"
    ],
    "wof:name":"Tando Gulab",
    "wof:placetype":"locality"
},
  "geometry": {"coordinates":[67.49664,28.80104],"type":"Point"}
}