{
  "type": "Feature",
  "properties": {
    "gn:admin1_code":"4",
    "gn:asciiname":"Khurshidabad",
    "gn:country_code":"PK",
    "gn:dem":146,
    "gn:feature_class":"P",
    "gn:feature_code":"PPL",
    "gn:name":"Khurshidabad",
    "gn:population":0,
    "gn:timezone":"Asia/Karachi",
    "iso:country":"PK",
    "name:und_x_variant":[
        "K\u0101nuw\u0101la"
    ],
    "wof:name":"Khurshidabad",
    "wof:placetype":"locality"
},
  "geometry": {"coordinates":[72.34492,30.64754000000001],"type":"Point"}
}