{
  "type": "Feature",
  "properties": {
    "gn:admin1_code":"4.0",
    "gn:asciiname":"Chah Chandwanwala",
    "gn:country_code":"PK",
    "gn:dem":156,
    "gn:feature_class":"P",
    "gn:feature_code":"PPL",
    "gn:name":"Chah Chandwanwala",
    "gn:population":0,
    "gn:timezone":"Asia/Karachi",
    "iso:country":"PK",
    "name:und_x_variant":[
        "Chanduw\u0101la"
    ],
    "wof:name":"Chah Chandwanwala",
    "wof:placetype":"locality"
},
  "geometry": {"coordinates":[72.41658000000002,31.11215],"type":"Point"}
}