{
  "type": "Feature",
  "properties": {
    "gn:admin1_code":"6",
    "gn:asciiname":"Bagnuwali Sari",
    "gn:country_code":"PK",
    "gn:dem":2166,
    "gn:feature_class":"P",
    "gn:feature_code":"PPL",
    "gn:name":"Bagnuwali Sari",
    "gn:population":0,
    "gn:timezone":"Asia/Karachi",
    "iso:country":"PK",
    "name:und_x_variant":[
        "Bagnuwala Seri",
        "Bagnuwali Sari"
    ],
    "wof:name":"Bagnuwali Sari",
    "wof:placetype":"locality"
},
  "geometry": {"coordinates":[74.39444,34.85972],"type":"Point"}
}