{
  "type": "Feature",
  "properties": {
    "gn:admin1_code":"4.0",
    "gn:asciiname":"Chah Rashidwala",
    "gn:country_code":"PK",
    "gn:dem":149,
    "gn:feature_class":"P",
    "gn:feature_code":"PPL",
    "gn:name":"Chah Rashidwala",
    "gn:population":0,
    "gn:timezone":"Asia/Karachi",
    "iso:country":"PK",
    "wof:name":"Chah Rashidwala",
    "wof:placetype":"locality"
},
  "geometry": {"coordinates":[72.20255,31.13498],"type":"Point"}
}