{
  "type": "Feature",
  "properties": {
    "gn:admin1_code":"5.0",
    "gn:asciiname":"Marn Nandhi",
    "gn:country_code":"PK",
    "gn:dem":55,
    "gn:feature_class":"P",
    "gn:feature_code":"PPL",
    "gn:name":"Marn Nandhi",
    "gn:population":0,
    "gn:timezone":"Asia/Karachi",
    "iso:country":"PK",
    "name:eng_x_preferred":[
        "Goth \u0100rab Kh\u0101n"
    ],
    "wof:name":"Marn Nandhi",
    "wof:placetype":"locality"
},
  "geometry": {"coordinates":[68.57276999999999,27.42999],"type":"Point"}
}