{
  "type": "Feature",
  "properties": {
    "gn:admin1_code":"2",
    "gn:asciiname":"Basti Kamalam Shah",
    "gn:country_code":"PK",
    "gn:dem":1013,
    "gn:feature_class":"P",
    "gn:feature_code":"PPL",
    "gn:name":"Basti Kamalam Shah",
    "gn:population":0,
    "gn:timezone":"Asia/Karachi",
    "iso:country":"PK",
    "name:und_x_variant":[
        "Kam\u0101l\u0101n Sh\u0101h"
    ],
    "wof:name":"Basti Kamalam Shah",
    "wof:placetype":"locality"
},
  "geometry": {"coordinates":[69.37053,29.77321],"type":"Point"}
}