{
  "type": "Feature",
  "properties": {
    "gn:admin1_code":"4",
    "gn:asciiname":"Chak Three Hundred Sixty-seven Gogera Branch",
    "gn:country_code":"PK",
    "gn:dem":185,
    "gn:feature_class":"P",
    "gn:feature_code":"PPL",
    "gn:name":"Chak Three Hundred Sixty-seven Gogera Branch",
    "gn:population":0,
    "gn:timezone":"Asia/Karachi",
    "iso:country":"PK",
    "name:und_x_variant":[
        "Jhok Bukhi",
        "Jhok Bhukhi"
    ],
    "wof:name":"Chak Three Hundred Sixty-seven Gogera Branch",
    "wof:placetype":"locality"
},
  "geometry": {"coordinates":[73.33481,31.10027],"type":"Point"}
}