{
  "type": "Feature",
  "properties": {
    "gn:admin1_code":"2.0",
    "gn:asciiname":"Azim Kor",
    "gn:country_code":"PK",
    "gn:dem":1242,
    "gn:feature_class":"P",
    "gn:feature_code":"PPL",
    "gn:name":"Azim Kor",
    "gn:population":0,
    "gn:timezone":"Asia/Karachi",
    "iso:country":"PK",
    "name:und_x_variant":[
        "Az\u012bim Kor"
    ],
    "wof:name":"Azim Kor",
    "wof:placetype":"locality"
},
  "geometry": {"coordinates":[69.30696999999999,30.16878],"type":"Point"}
}