{
  "type": "Feature",
  "properties": {
    "gn:admin1_code":"5.0",
    "gn:asciiname":"Goth Haji Muhammad Tark",
    "gn:country_code":"PK",
    "gn:dem":25,
    "gn:feature_class":"P",
    "gn:feature_code":"PPL",
    "gn:name":"Goth Haji Muhammad Tark",
    "gn:population":0,
    "gn:timezone":"Asia/Karachi",
    "iso:country":"PK",
    "name:und_x_variant":[
        "Goth H\u0101ji Muhammad Turk"
    ],
    "wof:name":"Goth Haji Muhammad Tark",
    "wof:placetype":"locality"
},
  "geometry": {"coordinates":[68.55004,25.50952],"type":"Point"}
}