{
  "type": "Feature",
  "properties": {
    "gn:admin1_code":"5.0",
    "gn:asciiname":"Ajbi Bhil Jo Tar",
    "gn:country_code":"PK",
    "gn:dem":57,
    "gn:feature_class":"P",
    "gn:feature_code":"PPL",
    "gn:name":"Ajbi Bhil Jo Tar",
    "gn:population":0,
    "gn:timezone":"Asia/Karachi",
    "iso:country":"PK",
    "wof:name":"Ajbi Bhil Jo Tar",
    "wof:placetype":"locality"
},
  "geometry": {"coordinates":[70.30383,24.61847],"type":"Point"}
}