{
  "type": "Feature",
  "properties": {
    "gn:admin1_code":"3.0",
    "gn:asciiname":"Kabal River",
    "gn:country_code":"PK",
    "gn:dem":288,
    "gn:feature_class":"P",
    "gn:feature_code":"PPL",
    "gn:name":"Kabal River",
    "gn:population":0,
    "gn:timezone":"Asia/Karachi",
    "iso:country":"PK",
    "wof:name":"Kabal River",
    "wof:placetype":"locality"
},
  "geometry": {"coordinates":[71.98976,34.01733],"type":"Point"}
}