{
  "type": "Feature",
  "properties": {
    "gn:admin1_code":"5.0",
    "gn:asciiname":"Sadoro Khaskheli",
    "gn:country_code":"PK",
    "gn:dem":12,
    "gn:feature_class":"P",
    "gn:feature_code":"PPL",
    "gn:name":"Sadoro Khaskheli",
    "gn:population":0,
    "gn:timezone":"Asia/Karachi",
    "iso:country":"PK",
    "name:eng_x_preferred":[
        "Sadoro Khaskheli"
    ],
    "wof:name":"Sadoro Khaskheli",
    "wof:placetype":"locality"
},
  "geometry": {"coordinates":[68.21117,24.74399],"type":"Point"}
}