{
  "type": "Feature",
  "properties": {
    "gn:admin1_code":"2",
    "gn:asciiname":"Taj Muhammad Khan Kandrani",
    "gn:country_code":"PK",
    "gn:dem":66,
    "gn:feature_class":"P",
    "gn:feature_code":"PPL",
    "gn:name":"Taj Muhammad Khan Kandrani",
    "gn:population":0,
    "gn:timezone":"Asia/Karachi",
    "iso:country":"PK",
    "name:und_x_variant":[
        "Taj Muhammad Karn\u0101ri"
    ],
    "wof:name":"Taj Muhammad Khan Kandrani",
    "wof:placetype":"locality"
},
  "geometry": {"coordinates":[68.86471,28.43382],"type":"Point"}
}