{
  "type": "Feature",
  "properties": {
    "gn:admin1_code":"4.0",
    "gn:asciiname":"Pir Kala",
    "gn:country_code":"PK",
    "gn:dem":264,
    "gn:feature_class":"P",
    "gn:feature_code":"PPL",
    "gn:name":"Pir Kala",
    "gn:population":0,
    "gn:timezone":"Asia/Karachi",
    "iso:country":"PK",
    "wof:name":"Pir Kala",
    "wof:placetype":"locality"
},
  "geometry": {"coordinates":[74.92168000000002,32.29882],"type":"Point"}
}