{
  "type": "Feature",
  "properties": {
    "gn:admin1_code":"5.0",
    "gn:asciiname":"Mehram Ji Tube Well",
    "gn:country_code":"PK",
    "gn:dem":44,
    "gn:feature_class":"P",
    "gn:feature_code":"PPL",
    "gn:name":"Mehram Ji Tube Well",
    "gn:population":0,
    "gn:timezone":"Asia/Karachi",
    "iso:country":"PK",
    "wof:name":"Mehram Ji Tube Well",
    "wof:placetype":"locality"
},
  "geometry": {"coordinates":[68.01059000000001,26.70498],"type":"Point"}
}