{
  "type": "Feature",
  "properties": {
    "gn:admin1_code":"2.0",
    "gn:asciiname":"Dost Muhammad Kili",
    "gn:country_code":"PK",
    "gn:dem":1735,
    "gn:feature_class":"P",
    "gn:feature_code":"PPL",
    "gn:name":"Dost Muhammad Kili",
    "gn:population":0,
    "gn:timezone":"Asia/Karachi",
    "iso:country":"PK",
    "wof:name":"Dost Muhammad Kili",
    "wof:placetype":"locality"
},
  "geometry": {"coordinates":[69.2616,31.6681],"type":"Point"}
}