{
  "type": "Feature",
  "properties": {
    "gn:admin1_code":"3.0",
    "gn:asciiname":"Lande Shah",
    "gn:country_code":"PK",
    "gn:dem":314,
    "gn:feature_class":"P",
    "gn:feature_code":"PPL",
    "gn:name":"Lande Shah",
    "gn:population":0,
    "gn:timezone":"Asia/Karachi",
    "iso:country":"PK",
    "name:eng_x_preferred":[
        "Mat\u012bull\u0101h Kor\u016bna"
    ],
    "wof:name":"Lande Shah",
    "wof:placetype":"locality"
},
  "geometry": {"coordinates":[71.84979,34.1781],"type":"Point"}
}