{
  "type": "Feature",
  "properties": {
    "gn:admin1_code":"4",
    "gn:asciiname":"Qabulanwala",
    "gn:country_code":"PK",
    "gn:dem":109,
    "gn:feature_class":"P",
    "gn:feature_code":"PPL",
    "gn:name":"Qabulanwala",
    "gn:population":0,
    "gn:timezone":"Asia/Karachi",
    "iso:country":"PK",
    "name:und_x_variant":[
        "B\u0101barw\u0101la"
    ],
    "wof:name":"Qabulanwala",
    "wof:placetype":"locality"
},
  "geometry": {"coordinates":[70.57094000000002,29.69137000000001],"type":"Point"}
}