{
  "type": "Feature",
  "properties": {
    "gn:admin1_code":"4.0",
    "gn:asciiname":"Bai",
    "gn:country_code":"PK",
    "gn:dem":425,
    "gn:feature_class":"P",
    "gn:feature_code":"PPL",
    "gn:name":"Bai",
    "gn:population":0,
    "gn:timezone":"Asia/Karachi",
    "iso:country":"PK",
    "wof:name":"Bai",
    "wof:placetype":"locality"
},
  "geometry": {"coordinates":[72.66105999999998,33.84183],"type":"Point"}
}