{
  "type": "Feature",
  "properties": {
    "gn:admin1_code":"5.0",
    "gn:asciiname":"Ali Muhammad Pothan",
    "gn:country_code":"PK",
    "gn:dem":10,
    "gn:feature_class":"P",
    "gn:feature_code":"PPL",
    "gn:name":"Ali Muhammad Pothan",
    "gn:population":0,
    "gn:timezone":"Asia/Karachi",
    "iso:country":"PK",
    "name:und_x_variant":[
        "Ali Muhammad Path\u0101n"
    ],
    "wof:name":"Ali Muhammad Pothan",
    "wof:placetype":"locality"
},
  "geometry": {"coordinates":[68.84681999999999,24.72307],"type":"Point"}
}