{
  "type": "Feature",
  "properties": {
    "gn:admin1_code":"2.0",
    "gn:asciiname":"Densar",
    "gn:country_code":"PK",
    "gn:dem":1174,
    "gn:feature_class":"P",
    "gn:feature_code":"PPL",
    "gn:name":"Densar",
    "gn:population":0,
    "gn:timezone":"Asia/Karachi",
    "iso:country":"PK",
    "name:und_x_variant":[
        "Den Sar"
    ],
    "wof:name":"Densar",
    "wof:placetype":"locality"
},
  "geometry": {"coordinates":[66.20678000000001,27.67729000000001],"type":"Point"}
}