{
  "type": "Feature",
  "properties": {
    "gn:admin1_code":"5.0",
    "gn:asciiname":"Ali Muhammad Shah",
    "gn:country_code":"PK",
    "gn:dem":4,
    "gn:feature_class":"P",
    "gn:feature_code":"PPL",
    "gn:name":"Ali Muhammad Shah",
    "gn:population":0,
    "gn:timezone":"Asia/Karachi",
    "iso:country":"PK",
    "wof:name":"Ali Muhammad Shah",
    "wof:placetype":"locality"
},
  "geometry": {"coordinates":[67.7787,24.20533],"type":"Point"}
}