{
  "type": "Feature",
  "properties": {
    "gn:admin1_code":"3",
    "gn:asciiname":"Sangu",
    "gn:country_code":"PK",
    "gn:dem":2315,
    "gn:feature_class":"P",
    "gn:feature_code":"PPL",
    "gn:name":"Sangu",
    "gn:population":0,
    "gn:timezone":"Asia/Karachi",
    "iso:country":"PK",
    "name:ben_x_preferred":[
        "\u09b8\u09be\u0999\u09cd\u0997\u09c1"
    ],
    "name:ceb_x_preferred":[
        "Sangu"
    ],
    "name:deu_x_preferred":[
        "Sangu"
    ],
    "name:fin_x_preferred":[
        "Sangu"
    ],
    "name:fra_x_preferred":[
        "Sangu"
    ],
    "name:new_x_preferred":[
        "\u0938\u093e\u0902\u0917\u0941"
    ],
    "name:pol_x_preferred":[
        "Sangu"
    ],
    "name:swe_x_preferred":[
        "Sangu"
    ],
    "wof:name":"Sangu",
    "wof:placetype":"locality"
},
  "geometry": {"coordinates":[73.06475,34.73499],"type":"Point"}
}