{
  "type": "Feature",
  "properties": {
    "gn:admin1_code":"3.0",
    "gn:asciiname":"Dant",
    "gn:country_code":"PK",
    "gn:dem":1352,
    "gn:feature_class":"P",
    "gn:feature_code":"PPL",
    "gn:name":"Dant",
    "gn:population":0,
    "gn:timezone":"Asia/Karachi",
    "iso:country":"PK",
    "wof:name":"Dant",
    "wof:placetype":"locality"
},
  "geometry": {"coordinates":[73.24961999999999,35.25648],"type":"Point"}
}