{
  "type": "Feature",
  "properties": {
    "gn:admin1_code":"2.0",
    "gn:asciiname":"Arz Muhammad Magsi",
    "gn:country_code":"PK",
    "gn:dem":56,
    "gn:feature_class":"P",
    "gn:feature_code":"PPL",
    "gn:name":"Arz Muhammad Magsi",
    "gn:population":0,
    "gn:timezone":"Asia/Karachi",
    "iso:country":"PK",
    "name:und_x_variant":[
        "Bal\u0101ch"
    ],
    "wof:name":"Arz Muhammad Magsi",
    "wof:placetype":"locality"
},
  "geometry": {"coordinates":[68.35786999999999,28.29331],"type":"Point"}
}