{
  "type": "Feature",
  "properties": {
    "gn:admin1_code":"5",
    "gn:asciiname":"Bhindki",
    "gn:country_code":"PK",
    "gn:dem":70,
    "gn:feature_class":"P",
    "gn:feature_code":"PPL",
    "gn:name":"Bhindki",
    "gn:population":0,
    "gn:timezone":"Asia/Karachi",
    "iso:country":"PK",
    "name:und_x_variant":[
        "Pindki"
    ],
    "wof:name":"Bhindki",
    "wof:placetype":"locality"
},
  "geometry": {"coordinates":[69.33337,28.03888],"type":"Point"}
}