{
  "type": "Feature",
  "properties": {
    "gn:admin1_code":"4",
    "gn:asciiname":"Chak Eleven -One A Left",
    "gn:country_code":"PK",
    "gn:dem":187,
    "gn:feature_class":"P",
    "gn:feature_code":"PPL",
    "gn:name":"Chak Eleven -One A Left",
    "gn:population":0,
    "gn:timezone":"Asia/Karachi",
    "iso:country":"PK",
    "name:und_x_variant":[
        "Chak Eleven-One A L"
    ],
    "wof:name":"Chak Eleven -One A Left",
    "wof:placetype":"locality"
},
  "geometry": {"coordinates":[73.63566,30.90587],"type":"Point"}
}