{
  "type": "Feature",
  "properties": {
    "gn:admin1_code":"4",
    "gn:asciiname":"Jhok Rahman",
    "gn:country_code":"PK",
    "gn:dem":131,
    "gn:feature_class":"P",
    "gn:feature_code":"PPL",
    "gn:name":"Jhok Rahman",
    "gn:population":0,
    "gn:timezone":"Asia/Karachi",
    "iso:country":"PK",
    "name:eng_x_preferred":[
        "Jhok Rahman"
    ],
    "wof:name":"Jhok Rahman",
    "wof:placetype":"locality"
},
  "geometry": {"coordinates":[70.74672,30.47284],"type":"Point"}
}