{
  "type": "Feature",
  "properties": {
    "gn:admin1_code":"3.0",
    "gn:asciiname":"Kamlori",
    "gn:country_code":"PK",
    "gn:dem":1323,
    "gn:feature_class":"P",
    "gn:feature_code":"PPL",
    "gn:name":"Kamlori",
    "gn:population":0,
    "gn:timezone":"Asia/Karachi",
    "iso:country":"PK",
    "wof:name":"Kamlori",
    "wof:placetype":"locality"
},
  "geometry": {"coordinates":[72.97355,34.49973],"type":"Point"}
}