{
  "type": "Feature",
  "properties": {
    "gn:admin1_code":"5.0",
    "gn:asciiname":"Ali Shah",
    "gn:country_code":"PK",
    "gn:dem":51,
    "gn:feature_class":"P",
    "gn:feature_code":"PPL",
    "gn:name":"Ali Shah",
    "gn:population":0,
    "gn:timezone":"Asia/Karachi",
    "iso:country":"PK",
    "name:ara_x_preferred":[
        "\u0639\u0644\u064a \u0634\u0627\u0647"
    ],
    "name:mar_x_preferred":[
        "\u0905\u0932\u0940 \u0936\u093e\u0939"
    ],
    "name:tam_x_preferred":[
        "\u0b85\u0bb2\u0bbf \u0bb7\u0bbe"
    ],
    "wof:name":"Ali Shah",
    "wof:placetype":"locality"
},
  "geometry": {"coordinates":[68.02261,27.51058],"type":"Point"}
}