{
  "type": "Feature",
  "properties": {
    "gn:admin1_code":"2.0",
    "gn:asciiname":"Maror Pur",
    "gn:country_code":"PK",
    "gn:dem":77,
    "gn:feature_class":"P",
    "gn:feature_code":"PPL",
    "gn:name":"Maror Pur",
    "gn:population":0,
    "gn:timezone":"Asia/Karachi",
    "iso:country":"PK",
    "name:und_x_variant":[
        "Mar\u0101rp\u016br"
    ],
    "wof:name":"Maror Pur",
    "wof:placetype":"locality"
},
  "geometry": {"coordinates":[67.81895,28.66952],"type":"Point"}
}