{
  "type": "Feature",
  "properties": {
    "gn:admin1_code":"02",
    "gn:asciiname":"Hambarg",
    "gn:country_code":"PK",
    "gn:dem":519,
    "gn:feature_class":"P",
    "gn:feature_code":"PPL",
    "gn:name":"Hambarg",
    "gn:population":0,
    "gn:timezone":"Asia/Karachi",
    "iso:country":"PK",
    "wof:name":"Hambarg",
    "wof:placetype":"locality"
},
  "geometry": {"coordinates":[62.4066,26.35441],"type":"Point"}
}