{
  "type": "Feature",
  "properties": {
    "gn:admin1_code":"3.0",
    "gn:asciiname":"Chhari",
    "gn:country_code":"PK",
    "gn:dem":2066,
    "gn:feature_class":"P",
    "gn:feature_code":"PPL",
    "gn:name":"Chhari",
    "gn:population":0,
    "gn:timezone":"Asia/Karachi",
    "iso:country":"PK",
    "wof:name":"Chhari",
    "wof:placetype":"locality"
},
  "geometry": {"coordinates":[73.30468,34.55032],"type":"Point"}
}