{
  "type": "Feature",
  "properties": {
    "gn:admin1_code":"4.0",
    "gn:asciiname":"Dhok Mora",
    "gn:country_code":"PK",
    "gn:dem":332,
    "gn:feature_class":"P",
    "gn:feature_code":"PPL",
    "gn:name":"Dhok Mora",
    "gn:population":0,
    "gn:timezone":"Asia/Karachi",
    "iso:country":"PK",
    "name:und_x_variant":[
        "Dhok Maly\u0101r\u0101"
    ],
    "wof:name":"Dhok Mora",
    "wof:placetype":"locality"
},
  "geometry": {"coordinates":[72.17931,33.25696],"type":"Point"}
}