{
  "type": "Feature",
  "properties": {
    "gn:admin1_code":"4.0",
    "gn:asciiname":"Lahori",
    "gn:country_code":"PK",
    "gn:dem":115,
    "gn:feature_class":"P",
    "gn:feature_code":"PPL",
    "gn:name":"Lahori",
    "gn:population":0,
    "gn:timezone":"Asia/Karachi",
    "iso:country":"PK",
    "wof:name":"Lahori",
    "wof:placetype":"locality"
},
  "geometry": {"coordinates":[71.44388000000002,29.75432],"type":"Point"}
}