{
  "type": "Feature",
  "properties": {
    "gn:admin1_code":"4.0",
    "gn:asciiname":"Basti Pirowali",
    "gn:country_code":"PK",
    "gn:dem":99,
    "gn:feature_class":"P",
    "gn:feature_code":"PPL",
    "gn:name":"Basti Pirowali",
    "gn:population":0,
    "gn:timezone":"Asia/Karachi",
    "iso:country":"PK",
    "name:und_x_variant":[
        "Basti Paroew\u0101li"
    ],
    "wof:name":"Basti Pirowali",
    "wof:placetype":"locality"
},
  "geometry": {"coordinates":[70.84945999999999,29.35423],"type":"Point"}
}