{
  "type": "Feature",
  "properties": {
    "gn:admin1_code":"4",
    "gn:asciiname":"Amir Ahloka",
    "gn:country_code":"PK",
    "gn:dem":163,
    "gn:feature_class":"P",
    "gn:feature_code":"PPL",
    "gn:name":"Amir Ahloka",
    "gn:population":0,
    "gn:timezone":"Asia/Karachi",
    "iso:country":"PK",
    "name:und_x_variant":[
        "Am\u012bra Ahloka"
    ],
    "wof:name":"Amir Ahloka",
    "wof:placetype":"locality"
},
  "geometry": {"coordinates":[73.45079,30.27759],"type":"Point"}
}