{
  "type": "Feature",
  "properties": {
    "gn:admin1_code":"3",
    "gn:asciiname":"Khamari",
    "gn:country_code":"PK",
    "gn:dem":1265,
    "gn:feature_class":"P",
    "gn:feature_code":"PPL",
    "gn:name":"Khamari",
    "gn:population":0,
    "gn:timezone":"Asia/Karachi",
    "iso:country":"PK",
    "wof:name":"Khamari",
    "wof:placetype":"locality"
},
  "geometry": {"coordinates":[72.91014,34.28342],"type":"Point"}
}