{
  "type": "Feature",
  "properties": {
    "gn:admin1_code":"2.0",
    "gn:asciiname":"Kili Hasham",
    "gn:country_code":"PK",
    "gn:dem":1267,
    "gn:feature_class":"P",
    "gn:feature_code":"PPL",
    "gn:name":"Kili Hasham",
    "gn:population":0,
    "gn:timezone":"Asia/Karachi",
    "iso:country":"PK",
    "wof:name":"Kili Hasham",
    "wof:placetype":"locality"
},
  "geometry": {"coordinates":[66.30648000000001,27.13503],"type":"Point"}
}