{
  "type": "Feature",
  "properties": {
    "gn:admin1_code":"5.0",
    "gn:asciiname":"Draza",
    "gn:country_code":"PK",
    "gn:dem":53,
    "gn:feature_class":"P",
    "gn:feature_code":"PPL",
    "gn:name":"Draza",
    "gn:population":0,
    "gn:timezone":"Asia/Karachi",
    "iso:country":"PK",
    "name:und_x_variant":[
        "Daraz",
        "Shah Daraz",
        "Dr\u0101za",
        "Draza"
    ],
    "wof:name":"Draza",
    "wof:placetype":"locality"
},
  "geometry": {"coordinates":[68.51139000000001,27.30517],"type":"Point"}
}