{
  "type": "Feature",
  "properties": {
    "gn:admin1_code":"3",
    "gn:asciiname":"Gal",
    "gn:country_code":"PK",
    "gn:dem":1642,
    "gn:feature_class":"P",
    "gn:feature_code":"PPL",
    "gn:name":"Gal",
    "gn:population":0,
    "gn:timezone":"Asia/Karachi",
    "iso:country":"PK",
    "name:cat_x_preferred":[
        "Gal"
    ],
    "name:ceb_x_preferred":[
        "Gal"
    ],
    "name:eus_x_preferred":[
        "Gal"
    ],
    "name:fin_x_preferred":[
        "Gal"
    ],
    "name:nds_x_preferred":[
        "Gal"
    ],
    "name:nld_x_preferred":[
        "Gal"
    ],
    "name:oci_x_preferred":[
        "Gal"
    ],
    "name:pol_x_preferred":[
        "Gal"
    ],
    "name:por_x_preferred":[
        "Gal"
    ],
    "name:rus_x_preferred":[
        "Gal"
    ],
    "name:slk_x_preferred":[
        "Gal"
    ],
    "name:spa_x_preferred":[
        "Gal"
    ],
    "name:srp_x_preferred":[
        "Gal"
    ],
    "name:swe_x_preferred":[
        "Gal"
    ],
    "wof:name":"Gal",
    "wof:placetype":"locality"
},
  "geometry": {"coordinates":[72.09016,34.95994],"type":"Point"}
}