{
  "type": "Feature",
  "properties": {
    "gn:admin1_code":"6",
    "gn:asciiname":"Nakka Shaikhan",
    "gn:country_code":"PK",
    "gn:dem":1760,
    "gn:feature_class":"P",
    "gn:feature_code":"PPL",
    "gn:name":"Nakka Shaikhan",
    "gn:population":0,
    "gn:timezone":"Asia/Karachi",
    "iso:country":"PK",
    "name:und_x_variant":[
        "Nakka"
    ],
    "wof:name":"Nakka Shaikhan",
    "wof:placetype":"locality"
},
  "geometry": {"coordinates":[73.61789,34.29416],"type":"Point"}
}