{
  "type": "Feature",
  "properties": {
    "gn:admin1_code":"03",
    "gn:asciiname":"Shagai Bala",
    "gn:country_code":"PK",
    "gn:dem":316,
    "gn:feature_class":"P",
    "gn:feature_code":"PPL",
    "gn:name":"Shagai Bala",
    "gn:population":0,
    "gn:timezone":"Asia/Karachi",
    "iso:country":"PK",
    "name:eng_x_preferred":[
        "Shiggi B\u0101la"
    ],
    "name:und_x_variant":[
        "Shagi Bala",
        "Shagai",
        "Shagai Bala"
    ],
    "wof:name":"Shagai Bala",
    "wof:placetype":"locality"
},
  "geometry": {"coordinates":[71.56155,34.14892],"type":"Point"}
}