{
  "type": "Feature",
  "properties": {
    "gn:admin1_code":"2",
    "gn:asciiname":"Chortu",
    "gn:country_code":"PK",
    "gn:dem":1587,
    "gn:feature_class":"P",
    "gn:feature_code":"PPL",
    "gn:name":"Chortu",
    "gn:population":0,
    "gn:timezone":"Asia/Karachi",
    "iso:country":"PK",
    "wof:name":"Chortu",
    "wof:placetype":"locality"
},
  "geometry": {"coordinates":[66.76806999999999,28.58173],"type":"Point"}
}