{
  "type": "Feature",
  "properties": {
    "gn:admin1_code":"4",
    "gn:asciiname":"Dhok Hajalwala",
    "gn:country_code":"PK",
    "gn:dem":406,
    "gn:feature_class":"P",
    "gn:feature_code":"PPL",
    "gn:name":"Dhok Hajalwala",
    "gn:population":0,
    "gn:timezone":"Asia/Karachi",
    "iso:country":"PK",
    "name:und_x_variant":[
        "Haji\u0101lw\u0101la",
        "Dhok Haji\u0101lw\u0101la",
        "Dhok Hajalwala"
    ],
    "wof:name":"Dhok Hajalwala",
    "wof:placetype":"locality"
},
  "geometry": {"coordinates":[72.08084000000002,32.89218],"type":"Point"}
}