{
  "type": "Feature",
  "properties": {
    "gn:admin1_code":"2.0",
    "gn:asciiname":"Ziaba Melan",
    "gn:country_code":"PK",
    "gn:dem":1847,
    "gn:feature_class":"P",
    "gn:feature_code":"PPL",
    "gn:name":"Ziaba Melan",
    "gn:population":0,
    "gn:timezone":"Asia/Karachi",
    "iso:country":"PK",
    "wof:name":"Ziaba Melan",
    "wof:placetype":"locality"
},
  "geometry": {"coordinates":[68.74929,31.07975],"type":"Point"}
}