{
  "type": "Feature",
  "properties": {
    "gn:admin1_code":"4.0",
    "gn:asciiname":"Basti Babal Khambra",
    "gn:country_code":"PK",
    "gn:dem":90,
    "gn:feature_class":"P",
    "gn:feature_code":"PPL",
    "gn:name":"Basti Babal Khambra",
    "gn:population":0,
    "gn:timezone":"Asia/Karachi",
    "iso:country":"PK",
    "name:und_x_variant":[
        "B\u0101bal"
    ],
    "wof:name":"Basti Babal Khambra",
    "wof:placetype":"locality"
},
  "geometry": {"coordinates":[70.30849000000001,28.70105],"type":"Point"}
}