{
  "type": "Feature",
  "properties": {
    "gn:admin1_code":"5",
    "gn:asciiname":"Vijuto",
    "gn:country_code":"PK",
    "gn:dem":35,
    "gn:feature_class":"P",
    "gn:feature_code":"PPL",
    "gn:name":"Vijuto",
    "gn:population":0,
    "gn:timezone":"Asia/Karachi",
    "iso:country":"PK",
    "wof:name":"Vijuto",
    "wof:placetype":"locality"
},
  "geometry": {"coordinates":[69.60011999999999,24.82652],"type":"Point"}
}