{
  "type": "Feature",
  "properties": {
    "gn:admin1_code":"04",
    "gn:asciiname":"Mansurwali",
    "gn:country_code":"PK",
    "gn:dem":219,
    "gn:feature_class":"P",
    "gn:feature_code":"PPL",
    "gn:name":"Mansurwali",
    "gn:population":0,
    "gn:timezone":"Asia/Karachi",
    "iso:country":"PK",
    "name:und_x_variant":[
        "Mansoorwali",
        "Mansurwali"
    ],
    "wof:name":"Mansurwali",
    "wof:placetype":"locality"
},
  "geometry": {"coordinates":[74.0072,32.3765],"type":"Point"}
}