{
  "type": "Feature",
  "properties": {
    "gn:admin1_code":"1",
    "gn:asciiname":"Mamit Khel",
    "gn:country_code":"PK",
    "gn:dem":1701,
    "gn:feature_class":"P",
    "gn:feature_code":"PPL",
    "gn:name":"Mamit Khel",
    "gn:population":0,
    "gn:timezone":"Asia/Karachi",
    "iso:country":"PK",
    "name:und_x_variant":[
        "Michi Khel",
        "Mamit Khel"
    ],
    "wof:name":"Mamit Khel",
    "wof:placetype":"locality"
},
  "geometry": {"coordinates":[69.79255999999999,32.41953],"type":"Point"}
}