{
  "type": "Feature",
  "properties": {
    "gn:admin1_code":"2.0",
    "gn:asciiname":"Raghzai",
    "gn:country_code":"PK",
    "gn:dem":1192,
    "gn:feature_class":"P",
    "gn:feature_code":"PPL",
    "gn:name":"Raghzai",
    "gn:population":0,
    "gn:timezone":"Asia/Karachi",
    "iso:country":"PK",
    "wof:name":"Raghzai",
    "wof:placetype":"locality"
},
  "geometry": {"coordinates":[70.07677,31.26192],"type":"Point"}
}