{
  "type": "Feature",
  "properties": {
    "gn:admin1_code":"04",
    "gn:asciiname":"Basti Lal Kathia",
    "gn:country_code":"PK",
    "gn:dem":155,
    "gn:feature_class":"P",
    "gn:feature_code":"PPL",
    "gn:name":"Basti Lal Kathia",
    "gn:population":0,
    "gn:timezone":"Asia/Karachi",
    "iso:country":"PK",
    "name:und_x_variant":[
        "L\u0101l K\u0101thia"
    ],
    "wof:name":"Basti Lal Kathia",
    "wof:placetype":"locality"
},
  "geometry": {"coordinates":[72.53789999999999,30.59431],"type":"Point"}
}