{
  "type": "Feature",
  "properties": {
    "gn:admin1_code":"4.0",
    "gn:asciiname":"Naiyanwala Bhan",
    "gn:country_code":"PK",
    "gn:dem":188,
    "gn:feature_class":"P",
    "gn:feature_code":"PPL",
    "gn:name":"Naiyanwala Bhan",
    "gn:population":0,
    "gn:timezone":"Asia/Karachi",
    "iso:country":"PK",
    "name:und_x_variant":[
        "Naiyanw\u0101la Bh\u0101n"
    ],
    "wof:name":"Naiyanwala Bhan",
    "wof:placetype":"locality"
},
  "geometry": {"coordinates":[72.15951,32.10669],"type":"Point"}
}