{
  "type": "Feature",
  "properties": {
    "gn:admin1_code":"3.0",
    "gn:asciiname":"Wanda Diwana",
    "gn:country_code":"PK",
    "gn:dem":363,
    "gn:feature_class":"P",
    "gn:feature_code":"PPL",
    "gn:name":"Wanda Diwana",
    "gn:population":0,
    "gn:timezone":"Asia/Karachi",
    "iso:country":"PK",
    "wof:name":"Wanda Diwana",
    "wof:placetype":"locality"
},
  "geometry": {"coordinates":[71.03945,32.51002],"type":"Point"}
}