{
  "type": "Feature",
  "properties": {
    "gn:admin1_code":"6",
    "gn:asciiname":"Uparli Ure",
    "gn:country_code":"PK",
    "gn:dem":2494,
    "gn:feature_class":"P",
    "gn:feature_code":"PPL",
    "gn:name":"Uparli Ure",
    "gn:population":0,
    "gn:timezone":"Asia/Karachi",
    "iso:country":"PK",
    "name:und_x_variant":[
        "Upari \u016are"
    ],
    "wof:name":"Uparli Ure",
    "wof:placetype":"locality"
},
  "geometry": {"coordinates":[74.2079,33.95188],"type":"Point"}
}