{
  "type": "Feature",
  "properties": {
    "gn:admin1_code":"2.0",
    "gn:asciiname":"Shakar Ab",
    "gn:country_code":"PK",
    "gn:dem":871,
    "gn:feature_class":"P",
    "gn:feature_code":"PPL",
    "gn:name":"Shakar Ab",
    "gn:population":0,
    "gn:timezone":"Asia/Karachi",
    "iso:country":"PK",
    "wof:name":"Shakar Ab",
    "wof:placetype":"locality"
},
  "geometry": {"coordinates":[64.62961,29.18091],"type":"Point"}
}