{
  "type": "Feature",
  "properties": {
    "gn:admin1_code":"2.0",
    "gn:asciiname":"Kili Shaikhan",
    "gn:country_code":"PK",
    "gn:dem":1678,
    "gn:feature_class":"P",
    "gn:feature_code":"PPL",
    "gn:name":"Kili Shaikhan",
    "gn:population":0,
    "gn:timezone":"Asia/Karachi",
    "iso:country":"PK",
    "name:und_x_variant":[
        "Shaikhan"
    ],
    "wof:name":"Kili Shaikhan",
    "wof:placetype":"locality"
},
  "geometry": {"coordinates":[66.84957,29.80653],"type":"Point"}
}