{
  "type": "Feature",
  "properties": {
    "gn:admin1_code":"2.0",
    "gn:asciiname":"Sakhidad Bazar Guzi",
    "gn:country_code":"PK",
    "gn:dem":552,
    "gn:feature_class":"P",
    "gn:feature_code":"PPL",
    "gn:name":"Sakhidad Bazar Guzi",
    "gn:population":0,
    "gn:timezone":"Asia/Karachi",
    "iso:country":"PK",
    "wof:name":"Sakhidad Bazar Guzi",
    "wof:placetype":"locality"
},
  "geometry": {"coordinates":[64.66683,26.21948],"type":"Point"}
}