{
  "type": "Feature",
  "properties": {
    "gn:admin1_code":"3.0",
    "gn:asciiname":"Julian",
    "gn:country_code":"PK",
    "gn:dem":546,
    "gn:feature_class":"P",
    "gn:feature_code":"PPL",
    "gn:name":"Julian",
    "gn:population":0,
    "gn:timezone":"Asia/Karachi",
    "iso:country":"PK",
    "wof:name":"Julian",
    "wof:placetype":"locality"
},
  "geometry": {"coordinates":[72.87985,33.7742],"type":"Point"}
}