{
  "type": "Feature",
  "properties": {
    "gn:admin1_code":"3.0",
    "gn:asciiname":"Julian",
    "gn:country_code":"PK",
    "gn:dem":546,
    "gn:feature_class":"P",
    "gn:feature_code":"PPL",
    "gn:name":"Julian",
    "gn:population":0,
    "gn:timezone":"Asia/Karachi",
    "iso:country":"PK",
    "name:bre_x_preferred":[
        "Julian"
    ],
    "name:bul_x_preferred":[
        "\u042e\u043b\u0438\u0430\u043d"
    ],
    "name:ceb_x_preferred":[
        "Julian"
    ],
    "name:ces_x_preferred":[
        "Julian"
    ],
    "name:fas_x_preferred":[
        "\u062c\u0648\u0644\u06cc\u0646"
    ],
    "name:fin_x_preferred":[
        "Julian"
    ],
    "name:fra_x_preferred":[
        "Julian"
    ],
    "name:ita_x_preferred":[
        "Julian"
    ],
    "name:jpn_x_preferred":[
        "\u30b8\u30e5\u30ea\u30a2\u30f3"
    ],
    "name:kor_x_preferred":[
        "\uc904\ub9ac\uc5b8"
    ],
    "name:nld_x_preferred":[
        "Julian"
    ],
    "name:pol_x_preferred":[
        "Julian"
    ],
    "name:por_x_preferred":[
        "Julian"
    ],
    "name:ron_x_preferred":[
        "Iulian"
    ],
    "name:rus_x_preferred":[
        "\u042e\u043b\u0438\u0430\u043d"
    ],
    "name:slk_x_preferred":[
        "Juli\u00e1n"
    ],
    "name:spa_x_preferred":[
        "Juli\u00e1n"
    ],
    "name:srp_x_preferred":[
        "\u040f\u0443\u043b\u0438\u0458\u0430\u043d"
    ],
    "name:ukr_x_preferred":[
        "\u042e\u043b\u0456\u0430\u043d"
    ],
    "name:vol_x_preferred":[
        "Julian"
    ],
    "wof:name":"Julian",
    "wof:placetype":"locality"
},
  "geometry": {"coordinates":[72.87985,33.7742],"type":"Point"}
}