{
  "type": "Feature",
  "properties": {
    "gn:admin1_code":"3.0",
    "gn:asciiname":"Koda Baihk",
    "gn:country_code":"PK",
    "gn:dem":3791,
    "gn:feature_class":"P",
    "gn:feature_code":"PPL",
    "gn:name":"Koda Baihk",
    "gn:population":0,
    "gn:timezone":"Asia/Karachi",
    "iso:country":"PK",
    "name:und_x_variant":[
        "Kh\u0101dia Baihk"
    ],
    "wof:name":"Koda Baihk",
    "wof:placetype":"locality"
},
  "geometry": {"coordinates":[74.04445,35.13001],"type":"Point"}
}