{
  "type": "Feature",
  "properties": {
    "gn:admin1_code":"1.0",
    "gn:asciiname":"Dokaya",
    "gn:country_code":"PK",
    "gn:dem":2114,
    "gn:feature_class":"P",
    "gn:feature_code":"PPL",
    "gn:name":"Dokaya",
    "gn:population":0,
    "gn:timezone":"Asia/Karachi",
    "iso:country":"PK",
    "wof:name":"Dokaya",
    "wof:placetype":"locality"
},
  "geometry": {"coordinates":[70.85760999999999,33.78183],"type":"Point"}
}