{
  "type": "Feature",
  "properties": {
    "gn:admin1_code":"4",
    "gn:asciiname":"Basti Jarian",
    "gn:country_code":"PK",
    "gn:dem":127,
    "gn:feature_class":"P",
    "gn:feature_code":"PPL",
    "gn:name":"Basti Jarian",
    "gn:population":0,
    "gn:timezone":"Asia/Karachi",
    "iso:country":"PK",
    "name:eng_x_preferred":[
        "Basti J\u012br\u0101n"
    ],
    "wof:name":"Basti Jarian",
    "wof:placetype":"locality"
},
  "geometry": {"coordinates":[70.98276,30.34826],"type":"Point"}
}