{
  "type": "Feature",
  "properties": {
    "gn:admin1_code":"4.0",
    "gn:asciiname":"Kotla Saiyid Kabir",
    "gn:country_code":"PK",
    "gn:dem":133,
    "gn:feature_class":"P",
    "gn:feature_code":"PPL",
    "gn:name":"Kotla Saiyid Kabir",
    "gn:population":0,
    "gn:timezone":"Asia/Karachi",
    "iso:country":"PK",
    "wof:name":"Kotla Saiyid Kabir",
    "wof:placetype":"locality"
},
  "geometry": {"coordinates":[71.71939999999999,30.32716],"type":"Point"}
}