{
  "type": "Feature",
  "properties": {
    "gn:admin1_code":"5",
    "gn:asciiname":"Otaq Haji Shams Din Jatoi",
    "gn:country_code":"PK",
    "gn:dem":44,
    "gn:feature_class":"P",
    "gn:feature_code":"PPL",
    "gn:name":"Otaq Haji Shams Din Jatoi",
    "gn:population":0,
    "gn:timezone":"Asia/Karachi",
    "iso:country":"PK",
    "wof:name":"Otaq Haji Shams Din Jatoi",
    "wof:placetype":"locality"
},
  "geometry": {"coordinates":[68.09166999999999,26.64028],"type":"Point"}
}