{
  "type": "Feature",
  "properties": {
    "gn:admin1_code":"4",
    "gn:asciiname":"Yazman Mandi",
    "gn:country_code":"PK",
    "gn:dem":120,
    "gn:feature_class":"P",
    "gn:feature_code":"PPL",
    "gn:name":"Yazm\u0101n Mandi",
    "gn:population":0,
    "gn:timezone":"Asia/Karachi",
    "iso:country":"PK",
    "wof:name":"Yazman Mandi",
    "wof:placetype":"locality"
},
  "geometry": {"coordinates":[71.74306,29.12639],"type":"Point"}
}