{
  "type": "Feature",
  "properties": {
    "gn:admin1_code":"5.0",
    "gn:asciiname":"Ibrahim Shoro",
    "gn:country_code":"PK",
    "gn:dem":20,
    "gn:feature_class":"P",
    "gn:feature_code":"PPL",
    "gn:name":"Ibrahim Shoro",
    "gn:population":0,
    "gn:timezone":"Asia/Karachi",
    "iso:country":"PK",
    "wof:name":"Ibrahim Shoro",
    "wof:placetype":"locality"
},
  "geometry": {"coordinates":[68.45999999999999,25.26741],"type":"Point"}
}