{
  "type": "Feature",
  "properties": {
    "gn:admin1_code":"4.0",
    "gn:asciiname":"Shafi di Haveli",
    "gn:country_code":"PK",
    "gn:dem":193,
    "gn:feature_class":"P",
    "gn:feature_code":"PPL",
    "gn:name":"Shafi di Haveli",
    "gn:population":0,
    "gn:timezone":"Asia/Karachi",
    "iso:country":"PK",
    "wof:name":"Shafi di Haveli",
    "wof:placetype":"locality"
},
  "geometry": {"coordinates":[74.28839000000001,31.06102000000001],"type":"Point"}
}