{
  "type": "Feature",
  "properties": {
    "gn:admin1_code":"4",
    "gn:asciiname":"Samandwala",
    "gn:country_code":"PK",
    "gn:dem":130,
    "gn:feature_class":"P",
    "gn:feature_code":"PPL",
    "gn:name":"Samandw\u0101la",
    "gn:population":0,
    "gn:timezone":"Asia/Karachi",
    "iso:country":"PK",
    "name:eng_x_preferred":[
        "Samandw\u0101la"
    ],
    "wof:name":"Samandwala",
    "wof:placetype":"locality"
},
  "geometry": {"coordinates":[70.93462,30.39128],"type":"Point"}
}