{
  "type": "Feature",
  "properties": {
    "gn:admin1_code":"4.0",
    "gn:asciiname":"Zabra",
    "gn:country_code":"PK",
    "gn:dem":258,
    "gn:feature_class":"P",
    "gn:feature_code":"PPL",
    "gn:name":"Zabra",
    "gn:population":0,
    "gn:timezone":"Asia/Karachi",
    "iso:country":"PK",
    "wof:name":"Zabra",
    "wof:placetype":"locality"
},
  "geometry": {"coordinates":[70.46776,30.80715],"type":"Point"}
}