{
  "type": "Feature",
  "properties": {
    "gn:admin1_code":"4.0",
    "gn:asciiname":"Behkan Bodla",
    "gn:country_code":"PK",
    "gn:dem":167,
    "gn:feature_class":"P",
    "gn:feature_code":"PPL",
    "gn:name":"Behkan Bodla",
    "gn:population":0,
    "gn:timezone":"Asia/Karachi",
    "iso:country":"PK",
    "name:und_x_variant":[
        "Chak Bodla"
    ],
    "wof:name":"Behkan Bodla",
    "wof:placetype":"locality"
},
  "geometry": {"coordinates":[73.60081,30.17686],"type":"Point"}
}