{
  "type": "Feature",
  "properties": {
    "gn:admin1_code":"4",
    "gn:asciiname":"Chak Twenty-five- Ten Right",
    "gn:country_code":"PK",
    "gn:dem":142,
    "gn:feature_class":"P",
    "gn:feature_code":"PPL",
    "gn:name":"Chak Twenty-five- Ten Right",
    "gn:population":0,
    "gn:timezone":"Asia/Karachi",
    "iso:country":"PK",
    "name:und_x_variant":[
        "Chak Twenty-Five-Ten R"
    ],
    "wof:name":"Chak Twenty-five- Ten Right",
    "wof:placetype":"locality"
},
  "geometry": {"coordinates":[72.17231,30.34146],"type":"Point"}
}