{
  "type": "Feature",
  "properties": {
    "gn:admin1_code":"5.0",
    "gn:asciiname":"Dhaklo",
    "gn:country_code":"PK",
    "gn:dem":81,
    "gn:feature_class":"P",
    "gn:feature_code":"PPL",
    "gn:name":"Dhaklo",
    "gn:population":0,
    "gn:timezone":"Asia/Karachi",
    "iso:country":"PK",
    "name:und_x_variant":[
        "Dh\u0101kla"
    ],
    "wof:name":"Dhaklo",
    "wof:placetype":"locality"
},
  "geometry": {"coordinates":[70.25433000000001,24.94015],"type":"Point"}
}