{
  "type": "Feature",
  "properties": {
    "gn:admin1_code":"4.0",
    "gn:asciiname":"Chak Eighteen Bahawal Canal",
    "gn:country_code":"PK",
    "gn:dem":112,
    "gn:feature_class":"P",
    "gn:feature_code":"PPL",
    "gn:name":"Chak Eighteen Bahawal Canal",
    "gn:population":0,
    "gn:timezone":"Asia/Karachi",
    "iso:country":"PK",
    "name:eng_x_preferred":[
        "Chak Eighteen BC"
    ],
    "wof:name":"Chak Eighteen Bahawal Canal",
    "wof:placetype":"locality"
},
  "geometry": {"coordinates":[71.58304,29.22395],"type":"Point"}
}