{
  "type": "Feature",
  "properties": {
    "gn:admin1_code":"3",
    "gn:asciiname":"Khoter",
    "gn:country_code":"PK",
    "gn:dem":3152,
    "gn:feature_class":"P",
    "gn:feature_code":"PPL",
    "gn:name":"Khoter",
    "gn:population":0,
    "gn:timezone":"Asia/Karachi",
    "iso:country":"PK",
    "wof:name":"Khoter",
    "wof:placetype":"locality"
},
  "geometry": {"coordinates":[71.4175,35.99556],"type":"Point"}
}