{
  "type": "Feature",
  "properties": {
    "gn:admin1_code":"4",
    "gn:asciiname":"Mani",
    "gn:country_code":"PK",
    "gn:dem":129,
    "gn:feature_class":"P",
    "gn:feature_code":"PPL",
    "gn:name":"Mani",
    "gn:population":0,
    "gn:timezone":"Asia/Karachi",
    "iso:country":"PK",
    "name:und_x_variant":[
        "Mi\u0101ni"
    ],
    "wof:name":"Mani",
    "wof:placetype":"locality"
},
  "geometry": {"coordinates":[72.2154,29.60904],"type":"Point"}
}