{
  "type": "Feature",
  "properties": {
    "gn:admin1_code":"5.0",
    "gn:asciiname":"Gulan Khan Lund",
    "gn:country_code":"PK",
    "gn:dem":33,
    "gn:feature_class":"P",
    "gn:feature_code":"PPL",
    "gn:name":"Gulan Khan Lund",
    "gn:population":0,
    "gn:timezone":"Asia/Karachi",
    "iso:country":"PK",
    "wof:name":"Gulan Khan Lund",
    "wof:placetype":"locality"
},
  "geometry": {"coordinates":[68.40420999999999,26.33693],"type":"Point"}
}