{
  "type": "Feature",
  "properties": {
    "gn:admin1_code":"1.0",
    "gn:asciiname":"Muhammad Gat",
    "gn:country_code":"PK",
    "gn:dem":836,
    "gn:feature_class":"P",
    "gn:feature_code":"PPL",
    "gn:name":"Muhammad Gat",
    "gn:population":0,
    "gn:timezone":"Asia/Karachi",
    "iso:country":"PK",
    "wof:name":"Muhammad Gat",
    "wof:placetype":"locality"
},
  "geometry": {"coordinates":[71.28286,34.61863],"type":"Point"}
}