{
  "type": "Feature",
  "properties": {
    "gn:admin1_code":"4.0",
    "gn:asciiname":"Chak One Hundred Ninety-six",
    "gn:country_code":"PK",
    "gn:dem":167,
    "gn:feature_class":"P",
    "gn:feature_code":"PPL",
    "gn:name":"Chak One Hundred Ninety-six",
    "gn:population":0,
    "gn:timezone":"Asia/Karachi",
    "iso:country":"PK",
    "name:und_x_variant":[
        "Bissmill\u0101hpur",
        "Chak One Hundred Ninety-Six GB",
        "Bismill\u0101hpur",
        "Chak One Hundred Ninety-six",
        "N\u0101iab\u0101d"
    ],
    "wof:name":"Chak One Hundred Ninety-six",
    "wof:placetype":"locality"
},
  "geometry": {"coordinates":[72.73219,30.88628],"type":"Point"}
}