{
  "type": "Feature",
  "properties": {
    "gn:admin1_code":"3.0",
    "gn:asciiname":"Jitur Sanek",
    "gn:country_code":"PK",
    "gn:dem":2550,
    "gn:feature_class":"P",
    "gn:feature_code":"PPL",
    "gn:name":"Jitur Sanek",
    "gn:population":0,
    "gn:timezone":"Asia/Karachi",
    "iso:country":"PK",
    "wof:name":"Jitur Sanek",
    "wof:placetype":"locality"
},
  "geometry": {"coordinates":[71.52441,35.9775],"type":"Point"}
}