{
  "type": "Feature",
  "properties": {
    "gn:admin1_code":"2.0",
    "gn:asciiname":"Zindaigar Kor",
    "gn:country_code":"PK",
    "gn:dem":1563,
    "gn:feature_class":"P",
    "gn:feature_code":"PPL",
    "gn:name":"Zindaigar Kor",
    "gn:population":0,
    "gn:timezone":"Asia/Karachi",
    "iso:country":"PK",
    "name:eng_x_preferred":[
        "Zindaigare Kor"
    ],
    "wof:name":"Zindaigar Kor",
    "wof:placetype":"locality"
},
  "geometry": {"coordinates":[68.50749,30.83539],"type":"Point"}
}