{
  "type": "Feature",
  "properties": {
    "gn:admin1_code":"2.0",
    "gn:asciiname":"Borang",
    "gn:country_code":"PK",
    "gn:dem":1446,
    "gn:feature_class":"P",
    "gn:feature_code":"PPL",
    "gn:name":"Borang",
    "gn:population":0,
    "gn:timezone":"Asia/Karachi",
    "iso:country":"PK",
    "wof:name":"Borang",
    "wof:placetype":"locality"
},
  "geometry": {"coordinates":[67.19084000000001,29.22755],"type":"Point"}
}