{
  "type": "Feature",
  "properties": {
    "gn:admin1_code":"7.0",
    "gn:asciiname":"Hamzigund",
    "gn:country_code":"PK",
    "gn:dem":2570,
    "gn:feature_class":"P",
    "gn:feature_code":"PPL",
    "gn:name":"Hamzigund",
    "gn:population":0,
    "gn:timezone":"Asia/Karachi",
    "iso:country":"PK",
    "wof:name":"Hamzigund",
    "wof:placetype":"locality"
},
  "geometry": {"coordinates":[76.19594000000002,34.8122],"type":"Point"}
}