{
  "type": "Feature",
  "properties": {
    "gn:admin1_code":"4.0",
    "gn:asciiname":"Hala",
    "gn:country_code":"PK",
    "gn:dem":129,
    "gn:feature_class":"P",
    "gn:feature_code":"PPL",
    "gn:name":"H\u0101la",
    "gn:population":0,
    "gn:timezone":"Asia/Karachi",
    "iso:country":"PK",
    "name:ceb_x_preferred":[
        "Hala"
    ],
    "name:deu_x_preferred":[
        "Hala"
    ],
    "name:eng_x_preferred":[
        "H\u0101la"
    ],
    "name:hsb_x_preferred":[
        "Hala"
    ],
    "name:jpn_x_preferred":[
        "\u30cf\u30fc\u30e9"
    ],
    "name:pol_x_preferred":[
        "Hala"
    ],
    "name:slk_x_preferred":[
        "Hala"
    ],
    "name:slv_x_preferred":[
        "Hala"
    ],
    "name:srp_x_preferred":[
        "\u0425\u0430\u043b\u0430"
    ],
    "name:swe_x_preferred":[
        "Hala"
    ],
    "wof:name":"Hala",
    "wof:placetype":"locality"
},
  "geometry": {"coordinates":[70.9482,30.4333],"type":"Point"}
}