{
  "type": "Feature",
  "properties": {
    "gn:admin1_code":"07",
    "gn:asciiname":"Mulungutti",
    "gn:country_code":"PK",
    "gn:dem":3297,
    "gn:feature_class":"P",
    "gn:feature_code":"PPL",
    "gn:name":"Mulungutti",
    "gn:population":0,
    "gn:timezone":"Asia/Karachi",
    "iso:country":"PK",
    "name:und_x_variant":[
        "Mulung\u016btti"
    ],
    "wof:name":"Mulungutti",
    "wof:placetype":"locality"
},
  "geometry": {"coordinates":[75.20674,36.47846],"type":"Point"}
}