{
  "type": "Feature",
  "properties": {
    "gn:admin1_code":"4.0",
    "gn:asciiname":"Buner Keswal",
    "gn:country_code":"PK",
    "gn:dem":474,
    "gn:feature_class":"P",
    "gn:feature_code":"PPL",
    "gn:name":"Buner Keswal",
    "gn:population":0,
    "gn:timezone":"Asia/Karachi",
    "iso:country":"PK",
    "name:und_x_variant":[
        "Baner Keswal",
        "Buner Keswal"
    ],
    "wof:name":"Buner Keswal",
    "wof:placetype":"locality"
},
  "geometry": {"coordinates":[73.46401,33.29392],"type":"Point"}
}