{
  "type": "Feature",
  "properties": {
    "gn:admin1_code":"2.0",
    "gn:asciiname":"Kili Dum Kach",
    "gn:country_code":"PK",
    "gn:dem":1319,
    "gn:feature_class":"P",
    "gn:feature_code":"PPL",
    "gn:name":"Kili Dum Kach",
    "gn:population":0,
    "gn:timezone":"Asia/Karachi",
    "iso:country":"PK",
    "name:und_x_variant":[
        "Dum Kach"
    ],
    "wof:name":"Kili Dum Kach",
    "wof:placetype":"locality"
},
  "geometry": {"coordinates":[67.78264,30.21817],"type":"Point"}
}