{
  "type": "Feature",
  "properties": {
    "gn:admin1_code":"4.0",
    "gn:asciiname":"Balani",
    "gn:country_code":"PK",
    "gn:dem":289,
    "gn:feature_class":"P",
    "gn:feature_code":"PPL",
    "gn:name":"Balani",
    "gn:population":0,
    "gn:timezone":"Asia/Karachi",
    "iso:country":"PK",
    "name:und_x_variant":[
        "Bulani",
        "Balani"
    ],
    "wof:name":"Balani",
    "wof:placetype":"locality"
},
  "geometry": {"coordinates":[73.94364,32.9222],"type":"Point"}
}