{
  "type": "Feature",
  "properties": {
    "gn:admin1_code":"3.0",
    "gn:asciiname":"Sonia",
    "gn:country_code":"PK",
    "gn:dem":875,
    "gn:feature_class":"P",
    "gn:feature_code":"PPL",
    "gn:name":"Sonia",
    "gn:population":0,
    "gn:timezone":"Asia/Karachi",
    "iso:country":"PK",
    "wof:name":"Sonia",
    "wof:placetype":"locality"
},
  "geometry": {"coordinates":[72.76906,34.40748],"type":"Point"}
}