{
  "type": "Feature",
  "properties": {
    "gn:admin1_code":"5.0",
    "gn:asciiname":"Dungri",
    "gn:country_code":"PK",
    "gn:dem":50,
    "gn:feature_class":"P",
    "gn:feature_code":"PPL",
    "gn:name":"Dungri",
    "gn:population":0,
    "gn:timezone":"Asia/Karachi",
    "iso:country":"PK",
    "name:und_x_variant":[
        "D\u016bngri"
    ],
    "wof:name":"Dungri",
    "wof:placetype":"locality"
},
  "geometry": {"coordinates":[70.78381999999998,24.37362000000001],"type":"Point"}
}