{
  "type": "Feature",
  "properties": {
    "gn:admin1_code":"5.0",
    "gn:asciiname":"Dungri",
    "gn:country_code":"PK",
    "gn:dem":50,
    "gn:feature_class":"P",
    "gn:feature_code":"PPL",
    "gn:name":"Dungri",
    "gn:population":0,
    "gn:timezone":"Asia/Karachi",
    "iso:country":"PK",
    "name:guj_x_preferred":[
        "\u0aa1\u0ac1\u0a82\u0a97\u0ab0\u0ac0"
    ],
    "name:tam_x_preferred":[
        "\u0b9f\u0bc1\u0b99\u0bcd\u0b95\u0bbf\u0bb0\u0bbf"
    ],
    "name:und_x_variant":[
        "D\u016bngri"
    ],
    "wof:name":"Dungri",
    "wof:placetype":"locality"
},
  "geometry": {"coordinates":[70.78381999999998,24.37362000000001],"type":"Point"}
}