{
  "type": "Feature",
  "properties": {
    "gn:admin1_code":"03",
    "gn:asciiname":"Shamilat",
    "gn:country_code":"PK",
    "gn:dem":336,
    "gn:feature_class":"P",
    "gn:feature_code":"PPL",
    "gn:name":"Shamilat",
    "gn:population":0,
    "gn:timezone":"Asia/Karachi",
    "iso:country":"PK",
    "name:eng_x_preferred":[
        "Sh\u0101ml\u0101t"
    ],
    "wof:name":"Shamilat",
    "wof:placetype":"locality"
},
  "geometry": {"coordinates":[71.93172,34.2455],"type":"Point"}
}