{
  "type": "Feature",
  "properties": {
    "gn:admin1_code":"04",
    "gn:asciiname":"Kotla Gamun",
    "gn:country_code":"PK",
    "gn:dem":92,
    "gn:feature_class":"P",
    "gn:feature_code":"PPL",
    "gn:name":"Kotla Gamun",
    "gn:population":0,
    "gn:timezone":"Asia/Karachi",
    "iso:country":"PK",
    "name:und_x_variant":[
        "Kotla G\u0101m\u016bn",
        "Kotla G\u0101nmun"
    ],
    "wof:name":"Kotla Gamun",
    "wof:placetype":"locality"
},
  "geometry": {"coordinates":[70.30108,29.03327],"type":"Point"}
}