{
  "type": "Feature",
  "properties": {
    "gn:admin1_code":"02",
    "gn:asciiname":"Pehri",
    "gn:country_code":"PK",
    "gn:dem":1558,
    "gn:feature_class":"P",
    "gn:feature_code":"PPL",
    "gn:name":"Pehri",
    "gn:population":0,
    "gn:timezone":"Asia/Karachi",
    "iso:country":"PK",
    "name:und_x_variant":[
        "Piri",
        "Per\u0101i",
        "Pehri"
    ],
    "wof:name":"Pehri",
    "wof:placetype":"locality"
},
  "geometry": {"coordinates":[67.77514000000001,30.26477],"type":"Point"}
}