{
  "type": "Feature",
  "properties": {
    "gn:admin1_code":"4",
    "gn:asciiname":"Wrachhwala",
    "gn:country_code":"PK",
    "gn:dem":127,
    "gn:feature_class":"P",
    "gn:feature_code":"PPL",
    "gn:name":"Wr\u0101chhw\u0101la",
    "gn:population":0,
    "gn:timezone":"Asia/Karachi",
    "iso:country":"PK",
    "name:eng_x_preferred":[
        "Wr\u0101chhw\u0101la"
    ],
    "wof:name":"Wrachhwala",
    "wof:placetype":"locality"
},
  "geometry": {"coordinates":[70.92809,30.2916],"type":"Point"}
}