{
  "type": "Feature",
  "properties": {
    "gn:admin1_code":"01",
    "gn:asciiname":"Landiwam",
    "gn:country_code":"PK",
    "gn:dem":2174,
    "gn:feature_class":"P",
    "gn:feature_code":"PPL",
    "gn:name":"Landiwam",
    "gn:population":0,
    "gn:timezone":"Asia/Karachi",
    "iso:country":"PK",
    "wof:name":"Landiwam",
    "wof:placetype":"locality"
},
  "geometry": {"coordinates":[69.74136999999999,32.5444],"type":"Point"}
}