{
  "type": "Feature",
  "properties": {
    "gn:admin1_code":"03",
    "gn:asciiname":"Dhal",
    "gn:country_code":"PK",
    "gn:dem":1955,
    "gn:feature_class":"P",
    "gn:feature_code":"PPL",
    "gn:name":"Dhal",
    "gn:population":0,
    "gn:timezone":"Asia/Karachi",
    "iso:country":"PK",
    "name:eng_x_preferred":[
        "Dal"
    ],
    "wof:name":"Dhal",
    "wof:placetype":"locality"
},
  "geometry": {"coordinates":[71.54903,34.97868],"type":"Point"}
}