{
  "type": "Feature",
  "properties": {
    "gn:admin1_code":"4.0",
    "gn:asciiname":"Morli Kalan",
    "gn:country_code":"PK",
    "gn:dem":279,
    "gn:feature_class":"P",
    "gn:feature_code":"PPL",
    "gn:name":"Morli Kalan",
    "gn:population":0,
    "gn:timezone":"Asia/Karachi",
    "iso:country":"PK",
    "wof:name":"Morli Kalan",
    "wof:placetype":"locality"
},
  "geometry": {"coordinates":[75.1576,32.33592],"type":"Point"}
}