{
  "type": "Feature",
  "properties": {
    "gn:admin1_code":"4",
    "gn:asciiname":"Majuhan",
    "gn:country_code":"PK",
    "gn:dem":267,
    "gn:feature_class":"P",
    "gn:feature_code":"PPL",
    "gn:name":"Majuhan",
    "gn:population":0,
    "gn:timezone":"Asia/Karachi",
    "iso:country":"PK",
    "name:und_x_variant":[
        "Mujh\u016bwa"
    ],
    "wof:name":"Majuhan",
    "wof:placetype":"locality"
},
  "geometry": {"coordinates":[73.88729000000002,32.99111],"type":"Point"}
}