{
  "type": "Feature",
  "properties": {
    "gn:admin1_code":"04",
    "gn:asciiname":"Purana Baghpur",
    "gn:country_code":"PK",
    "gn:dem":461,
    "gn:feature_class":"P",
    "gn:feature_code":"PPL",
    "gn:name":"Purana Baghpur",
    "gn:population":0,
    "gn:timezone":"Asia/Karachi",
    "iso:country":"PK",
    "name:und_x_variant":[
        "Porana Bh\u0101gpur",
        "Purana Bh\u0101gpur",
        "Purana Baghpur"
    ],
    "wof:name":"Purana Baghpur",
    "wof:placetype":"locality"
},
  "geometry": {"coordinates":[73.32884,33.30682],"type":"Point"}
}