{
  "type": "Feature",
  "properties": {
    "gn:admin1_code":"3",
    "gn:asciiname":"Jhand Bala",
    "gn:country_code":"PK",
    "gn:dem":1569,
    "gn:feature_class":"P",
    "gn:feature_code":"PPL",
    "gn:name":"Jhand Bala",
    "gn:population":0,
    "gn:timezone":"Asia/Karachi",
    "iso:country":"PK",
    "wof:name":"Jhand Bala",
    "wof:placetype":"locality"
},
  "geometry": {"coordinates":[72.94278,34.39416],"type":"Point"}
}