{
  "type": "Feature",
  "properties": {
    "gn:admin1_code":"3",
    "gn:asciiname":"Malkani",
    "gn:country_code":"PK",
    "gn:dem":822,
    "gn:feature_class":"P",
    "gn:feature_code":"PPL",
    "gn:name":"Malkani",
    "gn:population":0,
    "gn:timezone":"Asia/Karachi",
    "iso:country":"PK",
    "wof:name":"Malkani",
    "wof:placetype":"locality"
},
  "geometry": {"coordinates":[73.12302,34.36868],"type":"Point"}
}