{
  "type": "Feature",
  "properties": {
    "gn:admin1_code":"4.0",
    "gn:asciiname":"Chohdho Khunian di",
    "gn:country_code":"PK",
    "gn:dem":194,
    "gn:feature_class":"P",
    "gn:feature_code":"PPL",
    "gn:name":"Chohdho Khunian di",
    "gn:population":0,
    "gn:timezone":"Asia/Karachi",
    "iso:country":"PK",
    "name:und_x_variant":[
        "Chohdo Khuni"
    ],
    "wof:name":"Chohdho Khunian di",
    "wof:placetype":"locality"
},
  "geometry": {"coordinates":[73.30013000000002,31.97417],"type":"Point"}
}