{
  "type": "Feature",
  "properties": {
    "gn:admin1_code":"6",
    "gn:asciiname":"Kinis",
    "gn:country_code":"PK",
    "gn:dem":2396,
    "gn:feature_class":"P",
    "gn:feature_code":"PPL",
    "gn:name":"Kinis",
    "gn:population":0,
    "gn:timezone":"Asia/Karachi",
    "iso:country":"PK",
    "wof:name":"Kinis",
    "wof:placetype":"locality"
},
  "geometry": {"coordinates":[73.91655,34.31663],"type":"Point"}
}