{
  "type": "Feature",
  "properties": {
    "gn:admin1_code":"3.0",
    "gn:asciiname":"Jingai",
    "gn:country_code":"PK",
    "gn:dem":645,
    "gn:feature_class":"P",
    "gn:feature_code":"PPL",
    "gn:name":"Jingai",
    "gn:population":0,
    "gn:timezone":"Asia/Karachi",
    "iso:country":"PK",
    "wof:name":"Jingai",
    "wof:placetype":"locality"
},
  "geometry": {"coordinates":[72.60905,34.41339],"type":"Point"}
}