{
  "type": "Feature",
  "properties": {
    "gn:admin1_code":"3.0",
    "gn:asciiname":"Charuna",
    "gn:country_code":"PK",
    "gn:dem":1551,
    "gn:feature_class":"P",
    "gn:feature_code":"PPL",
    "gn:name":"Charuna",
    "gn:population":0,
    "gn:timezone":"Asia/Karachi",
    "iso:country":"PK",
    "wof:name":"Charuna",
    "wof:placetype":"locality"
},
  "geometry": {"coordinates":[72.8463,34.56603],"type":"Point"}
}