{
  "type": "Feature",
  "properties": {
    "gn:admin1_code":"1.0",
    "gn:asciiname":"Pasta Jara",
    "gn:country_code":"PK",
    "gn:dem":744,
    "gn:feature_class":"P",
    "gn:feature_code":"PPL",
    "gn:name":"Pasta Jara",
    "gn:population":0,
    "gn:timezone":"Asia/Karachi",
    "iso:country":"PK",
    "name:und_x_variant":[
        "Pasta Tarai"
    ],
    "wof:name":"Pasta Jara",
    "wof:placetype":"locality"
},
  "geometry": {"coordinates":[70.39867,32.65999],"type":"Point"}
}