{
  "type": "Feature",
  "properties": {
    "gn:admin1_code":"4.0",
    "gn:asciiname":"Chak Sixty-three/Ten Muhajir Branch",
    "gn:country_code":"PK",
    "gn:dem":186,
    "gn:feature_class":"P",
    "gn:feature_code":"PPL",
    "gn:name":"Chak Sixty-three/Ten Muhajir Branch",
    "gn:population":0,
    "gn:timezone":"Asia/Karachi",
    "iso:country":"PK",
    "name:und_x_variant":[
        "Chak MB 63/10"
    ],
    "wof:name":"Chak Sixty-three/Ten Muhajir Branch",
    "wof:placetype":"locality"
},
  "geometry": {"coordinates":[72.28676999999998,32.31633],"type":"Point"}
}