{
  "type": "Feature",
  "properties": {
    "gn:admin1_code":"2.0",
    "gn:asciiname":"Baranzai",
    "gn:country_code":"PK",
    "gn:dem":1654,
    "gn:feature_class":"P",
    "gn:feature_code":"PPL",
    "gn:name":"Baranzai",
    "gn:population":0,
    "gn:timezone":"Asia/Karachi",
    "iso:country":"PK",
    "wof:name":"Baranzai",
    "wof:placetype":"locality"
},
  "geometry": {"coordinates":[66.46579,28.23207],"type":"Point"}
}