{
  "type": "Feature",
  "properties": {
    "gn:admin1_code":"3.0",
    "gn:asciiname":"Khiyal Mir Garhi",
    "gn:country_code":"PK",
    "gn:dem":536,
    "gn:feature_class":"P",
    "gn:feature_code":"PPL",
    "gn:name":"Khiyal Mir Garhi",
    "gn:population":0,
    "gn:timezone":"Asia/Karachi",
    "iso:country":"PK",
    "name:und_x_variant":[
        "Khiy\u0101l M\u012br Garhi"
    ],
    "wof:name":"Khiyal Mir Garhi",
    "wof:placetype":"locality"
},
  "geometry": {"coordinates":[71.59063,33.74856],"type":"Point"}
}