{
  "type": "Feature",
  "properties": {
    "gn:admin1_code":"07",
    "gn:asciiname":"Nialthi",
    "gn:country_code":"PK",
    "gn:dem":2774,
    "gn:feature_class":"P",
    "gn:feature_code":"PPL",
    "gn:name":"Nialthi",
    "gn:population":0,
    "gn:timezone":"Asia/Karachi",
    "iso:country":"PK",
    "wof:name":"Nialthi",
    "wof:placetype":"locality"
},
  "geometry": {"coordinates":[73.24118,36.49894000000001],"type":"Point"}
}