{
  "type": "Feature",
  "properties": {
    "gn:admin1_code":"3.0",
    "gn:asciiname":"Manai Get Banda",
    "gn:country_code":"PK",
    "gn:dem":2643,
    "gn:feature_class":"P",
    "gn:feature_code":"PPL",
    "gn:name":"Manai Get Banda",
    "gn:population":0,
    "gn:timezone":"Asia/Karachi",
    "iso:country":"PK",
    "wof:name":"Manai Get Banda",
    "wof:placetype":"locality"
},
  "geometry": {"coordinates":[71.93477,35.34871],"type":"Point"}
}