{
  "type": "Feature",
  "properties": {
    "gn:admin1_code":"05",
    "gn:asciiname":"Musa Himayati",
    "gn:country_code":"PK",
    "gn:dem":6,
    "gn:feature_class":"P",
    "gn:feature_code":"PPL",
    "gn:name":"Musa Himayati",
    "gn:population":0,
    "gn:timezone":"Asia/Karachi",
    "iso:country":"PK",
    "wof:name":"Musa Himayati",
    "wof:placetype":"locality"
},
  "geometry": {"coordinates":[67.81838,24.36973],"type":"Point"}
}