{
  "type": "Feature",
  "properties": {
    "gn:admin1_code":"5",
    "gn:asciiname":"Kaisar Bhitt",
    "gn:country_code":"PK",
    "gn:dem":49,
    "gn:feature_class":"P",
    "gn:feature_code":"PPL",
    "gn:name":"Kaisar Bhitt",
    "gn:population":0,
    "gn:timezone":"Asia/Karachi",
    "iso:country":"PK",
    "name:und_x_variant":[
        "Kaisar Bhatti"
    ],
    "wof:name":"Kaisar Bhitt",
    "wof:placetype":"locality"
},
  "geometry": {"coordinates":[67.99624,28.05179],"type":"Point"}
}