{
  "type": "Feature",
  "properties": {
    "gn:admin1_code":"3",
    "gn:asciiname":"Kuza Banda",
    "gn:country_code":"PK",
    "gn:dem":3244,
    "gn:feature_class":"P",
    "gn:feature_code":"PPL",
    "gn:name":"Kuza Banda",
    "gn:population":0,
    "gn:timezone":"Asia/Karachi",
    "iso:country":"PK",
    "name:eng_x_preferred":[
        "K\u016bz B\u0101nda"
    ],
    "name:fas_x_preferred":[
        "\u06a9\u0648\u0632\u0647 \u0628\u0646\u062f\u0627"
    ],
    "wof:name":"Kuza Banda",
    "wof:placetype":"locality"
},
  "geometry": {"coordinates":[71.96696,35.51157],"type":"Point"}
}