{
  "type": "Feature",
  "properties": {
    "gn:admin1_code":"4.0",
    "gn:asciiname":"Khal Chhaprian",
    "gn:country_code":"PK",
    "gn:dem":827,
    "gn:feature_class":"P",
    "gn:feature_code":"PPL",
    "gn:name":"Khal Chhaprian",
    "gn:population":0,
    "gn:timezone":"Asia/Karachi",
    "iso:country":"PK",
    "wof:name":"Khal Chhaprian",
    "wof:placetype":"locality"
},
  "geometry": {"coordinates":[73.50639,33.65063],"type":"Point"}
}