{
  "type": "Feature",
  "properties": {
    "gn:admin1_code":"3",
    "gn:asciiname":"Khazanai Banda",
    "gn:country_code":"PK",
    "gn:dem":1303,
    "gn:feature_class":"P",
    "gn:feature_code":"PPL",
    "gn:name":"Khazanai Banda",
    "gn:population":0,
    "gn:timezone":"Asia/Karachi",
    "iso:country":"PK",
    "wof:name":"Khazanai Banda",
    "wof:placetype":"locality"
},
  "geometry": {"coordinates":[72.21419,34.86724],"type":"Point"}
}