{
  "type": "Feature",
  "properties": {
    "gn:admin1_code":"5",
    "gn:asciiname":"Muhammad Khan Halipota",
    "gn:country_code":"PK",
    "gn:dem":15,
    "gn:feature_class":"P",
    "gn:feature_code":"PPL",
    "gn:name":"Muhammad Khan Halipota",
    "gn:population":0,
    "gn:timezone":"Asia/Karachi",
    "iso:country":"PK",
    "name:und_x_variant":[
        "Mur\u012bd H\u0101l\u012bpota"
    ],
    "wof:name":"Muhammad Khan Halipota",
    "wof:placetype":"locality"
},
  "geometry": {"coordinates":[69.27691,25.3099],"type":"Point"}
}