{
  "type": "Feature",
  "properties": {
    "gn:admin1_code":"2.0",
    "gn:asciiname":"Kili Nadir Khan",
    "gn:country_code":"PK",
    "gn:dem":901,
    "gn:feature_class":"P",
    "gn:feature_code":"PPL",
    "gn:name":"Kili Nadir Khan",
    "gn:population":0,
    "gn:timezone":"Asia/Karachi",
    "iso:country":"PK",
    "wof:name":"Kili Nadir Khan",
    "wof:placetype":"locality"
},
  "geometry": {"coordinates":[65.56338000000001,29.61527],"type":"Point"}
}