{
  "type": "Feature",
  "properties": {
    "gn:admin1_code":"4.0",
    "gn:asciiname":"Jhalluna Rotha",
    "gn:country_code":"PK",
    "gn:dem":477,
    "gn:feature_class":"P",
    "gn:feature_code":"PPL",
    "gn:name":"Jhalluna Rotha",
    "gn:population":0,
    "gn:timezone":"Asia/Karachi",
    "iso:country":"PK",
    "name:eng_x_preferred":[
        "Jhalluna Rotha"
    ],
    "wof:name":"Jhalluna Rotha",
    "wof:placetype":"locality"
},
  "geometry": {"coordinates":[72.99913000000002,33.2312],"type":"Point"}
}