{
  "type": "Feature",
  "properties": {
    "gn:admin1_code":"5.0",
    "gn:asciiname":"Goth Rahim Charan",
    "gn:country_code":"PK",
    "gn:dem":9,
    "gn:feature_class":"P",
    "gn:feature_code":"PPL",
    "gn:name":"Goth Rahim Charan",
    "gn:population":0,
    "gn:timezone":"Asia/Karachi",
    "iso:country":"PK",
    "name:eng_x_preferred":[
        "Goth Rah\u012bm Ch\u0101ran"
    ],
    "wof:name":"Goth Rahim Charan",
    "wof:placetype":"locality"
},
  "geometry": {"coordinates":[68.06055000000001,24.73923],"type":"Point"}
}