{
  "type": "Feature",
  "properties": {
    "gn:admin1_code":"1.0",
    "gn:asciiname":"Kausar",
    "gn:country_code":"PK",
    "gn:dem":1041,
    "gn:feature_class":"P",
    "gn:feature_code":"PPL",
    "gn:name":"Kausar",
    "gn:population":0,
    "gn:timezone":"Asia/Karachi",
    "iso:country":"PK",
    "wof:name":"Kausar",
    "wof:placetype":"locality"
},
  "geometry": {"coordinates":[71.34844,34.69549],"type":"Point"}
}