{
  "type": "Feature",
  "properties": {
    "gn:admin1_code":"3.0",
    "gn:asciiname":"Kangar Bala",
    "gn:country_code":"PK",
    "gn:dem":863,
    "gn:feature_class":"P",
    "gn:feature_code":"PPL",
    "gn:name":"Kangar Bala",
    "gn:population":0,
    "gn:timezone":"Asia/Karachi",
    "iso:country":"PK",
    "name:und_x_variant":[
        "Kangar Utla"
    ],
    "wof:name":"Kangar Bala",
    "wof:placetype":"locality"
},
  "geometry": {"coordinates":[73.01898,34.21268],"type":"Point"}
}