{
  "type": "Feature",
  "properties": {
    "gn:admin1_code":"2.0",
    "gn:asciiname":"Laekar",
    "gn:country_code":"PK",
    "gn:dem":1050,
    "gn:feature_class":"P",
    "gn:feature_code":"PPL",
    "gn:name":"Laekar",
    "gn:population":0,
    "gn:timezone":"Asia/Karachi",
    "iso:country":"PK",
    "wof:name":"Laekar",
    "wof:placetype":"locality"
},
  "geometry": {"coordinates":[66.64706,27.06816],"type":"Point"}
}