{
  "type": "Feature",
  "properties": {
    "gn:admin1_code":"3.0",
    "gn:asciiname":"Siritu",
    "gn:country_code":"PK",
    "gn:dem":1448,
    "gn:feature_class":"P",
    "gn:feature_code":"PPL",
    "gn:name":"Siritu",
    "gn:population":0,
    "gn:timezone":"Asia/Karachi",
    "iso:country":"PK",
    "wof:name":"Siritu",
    "wof:placetype":"locality"
},
  "geometry": {"coordinates":[73.22824,35.46914],"type":"Point"}
}