{
  "type": "Feature",
  "properties": {
    "gn:admin1_code":"7.0",
    "gn:asciiname":"Triko",
    "gn:country_code":"PK",
    "gn:dem":1961,
    "gn:feature_class":"P",
    "gn:feature_code":"PPL",
    "gn:name":"Triko",
    "gn:population":0,
    "gn:timezone":"Asia/Karachi",
    "iso:country":"PK",
    "name:azb_x_preferred":[
        "\u062a\u0631\u06cc\u06a9\u0648"
    ],
    "name:fas_x_preferred":[
        "\u062a\u0631\u06cc\u06a9\u0648"
    ],
    "name:fra_x_preferred":[
        "Triko"
    ],
    "wof:name":"Triko",
    "wof:placetype":"locality"
},
  "geometry": {"coordinates":[75.13802,35.60409],"type":"Point"}
}