{
  "type": "Feature",
  "properties": {
    "gn:admin1_code":"2.0",
    "gn:asciiname":"Gazka Chah",
    "gn:country_code":"PK",
    "gn:dem":939,
    "gn:feature_class":"P",
    "gn:feature_code":"PPL",
    "gn:name":"Gazka Chah",
    "gn:population":0,
    "gn:timezone":"Asia/Karachi",
    "iso:country":"PK",
    "wof:name":"Gazka Chah",
    "wof:placetype":"locality"
},
  "geometry": {"coordinates":[63.22391999999999,27.41728],"type":"Point"}
}