{
  "type": "Feature",
  "properties": {
    "gn:admin1_code":"3.0",
    "gn:asciiname":"Bhittanni Kili",
    "gn:country_code":"PK",
    "gn:dem":378,
    "gn:feature_class":"P",
    "gn:feature_code":"PPL",
    "gn:name":"Bhittanni Kili",
    "gn:population":0,
    "gn:timezone":"Asia/Karachi",
    "iso:country":"PK",
    "wof:name":"Bhittanni Kili",
    "wof:placetype":"neighbourhood"
},
  "geometry": {"coordinates":[70.59860999999999,32.98722],"type":"Point"}
}