{
  "type": "Feature",
  "properties": {
    "gn:admin1_code":"7.0",
    "gn:asciiname":"Gumai",
    "gn:country_code":"PK",
    "gn:dem":2855,
    "gn:feature_class":"P",
    "gn:feature_code":"PPL",
    "gn:name":"Gumai",
    "gn:population":0,
    "gn:timezone":"Asia/Karachi",
    "iso:country":"PK",
    "wof:name":"Gumai",
    "wof:placetype":"locality"
},
  "geometry": {"coordinates":[74.85525,35.02983],"type":"Point"}
}