{
  "type": "Feature",
  "properties": {
    "gn:admin1_code":"5",
    "gn:asciiname":"Goth Muhabbat Khan Lakhiar",
    "gn:country_code":"PK",
    "gn:dem":47,
    "gn:feature_class":"P",
    "gn:feature_code":"PPL",
    "gn:name":"Goth Muhabbat Khan Lakhiar",
    "gn:population":0,
    "gn:timezone":"Asia/Karachi",
    "iso:country":"PK",
    "wof:name":"Goth Muhabbat Khan Lakhiar",
    "wof:placetype":"locality"
},
  "geometry": {"coordinates":[67.90438,27.04594],"type":"Point"}
}