{
  "type": "Feature",
  "properties": {
    "gn:admin1_code":"2.0",
    "gn:asciiname":"Sasuli",
    "gn:country_code":"PK",
    "gn:dem":1602,
    "gn:feature_class":"P",
    "gn:feature_code":"PPL",
    "gn:name":"Sasuli",
    "gn:population":0,
    "gn:timezone":"Asia/Karachi",
    "iso:country":"PK",
    "wof:name":"Sasuli",
    "wof:placetype":"locality"
},
  "geometry": {"coordinates":[66.29267,27.90592],"type":"Point"}
}