{
  "type": "Feature",
  "properties": {
    "gn:admin1_code":"03",
    "gn:asciiname":"Mandra Khel",
    "gn:country_code":"PK",
    "gn:dem":315,
    "gn:feature_class":"P",
    "gn:feature_code":"PPL",
    "gn:name":"Mandra Khel",
    "gn:population":0,
    "gn:timezone":"Asia/Karachi",
    "iso:country":"PK",
    "name:eng_x_preferred":[
        "Mandra Khel"
    ],
    "wof:name":"Mandra Khel",
    "wof:placetype":"locality"
},
  "geometry": {"coordinates":[71.55041999999997,34.06361],"type":"Point"}
}