{
  "type": "Feature",
  "properties": {
    "gn:admin1_code":"5",
    "gn:asciiname":"Goth Nur Muhammad Rind",
    "gn:country_code":"PK",
    "gn:dem":47,
    "gn:feature_class":"P",
    "gn:feature_code":"PPL",
    "gn:name":"Goth Nur Muhammad Rind",
    "gn:population":0,
    "gn:timezone":"Asia/Karachi",
    "iso:country":"PK",
    "name:und_x_variant":[
        "Goth N\u016br Muhammad Rind Baloch"
    ],
    "wof:name":"Goth Nur Muhammad Rind",
    "wof:placetype":"locality"
},
  "geometry": {"coordinates":[68.16551,27.02893],"type":"Point"}
}