{
  "type": "Feature",
  "properties": {
    "gn:admin1_code":"2.0",
    "gn:asciiname":"Janabad",
    "gn:country_code":"PK",
    "gn:dem":1415,
    "gn:feature_class":"P",
    "gn:feature_code":"PPL",
    "gn:name":"Janabad",
    "gn:population":0,
    "gn:timezone":"Asia/Karachi",
    "iso:country":"PK",
    "name:und_x_variant":[
        "J\u0101n \u0100b\u0101d"
    ],
    "wof:name":"Janabad",
    "wof:placetype":"locality"
},
  "geometry": {"coordinates":[69.27091999999999,31.13161],"type":"Point"}
}