{
  "type": "Feature",
  "properties": {
    "gn:admin1_code":"4",
    "gn:asciiname":"Gaz",
    "gn:country_code":"PK",
    "gn:dem":234,
    "gn:feature_class":"P",
    "gn:feature_code":"PPL",
    "gn:name":"Gaz",
    "gn:population":0,
    "gn:timezone":"Asia/Karachi",
    "iso:country":"PK",
    "name:aze_x_preferred":[
        "Qaz"
    ],
    "name:ceb_x_preferred":[
        "Gaz"
    ],
    "name:fra_x_preferred":[
        "Gaz"
    ],
    "name:hrv_x_preferred":[
        "Gaz"
    ],
    "name:pol_x_preferred":[
        "Gaz"
    ],
    "name:ron_x_preferred":[
        "Gaz"
    ],
    "name:slv_x_preferred":[
        "Gaz"
    ],
    "name:swe_x_preferred":[
        "Gaz"
    ],
    "name:uzb_x_preferred":[
        "Gaz"
    ],
    "name:vep_x_preferred":[
        "Gaz"
    ],
    "wof:name":"Gaz",
    "wof:placetype":"locality"
},
  "geometry": {"coordinates":[74.47789,32.24043],"type":"Point"}
}