{
  "type": "Feature",
  "properties": {
    "gn:admin1_code":"3.0",
    "gn:asciiname":"Namlai",
    "gn:country_code":"PK",
    "gn:dem":1799,
    "gn:feature_class":"P",
    "gn:feature_code":"PPL",
    "gn:name":"Namlai",
    "gn:population":0,
    "gn:timezone":"Asia/Karachi",
    "iso:country":"PK",
    "wof:name":"Namlai",
    "wof:placetype":"locality"
},
  "geometry": {"coordinates":[72.1683,35.17907],"type":"Point"}
}