{
  "type": "Feature",
  "properties": {
    "gn:admin1_code":"5.0",
    "gn:asciiname":"Hundi",
    "gn:country_code":"PK",
    "gn:dem":346,
    "gn:feature_class":"P",
    "gn:feature_code":"PPL",
    "gn:name":"Hundi",
    "gn:population":0,
    "gn:timezone":"Asia/Karachi",
    "iso:country":"PK",
    "name:deu_x_preferred":[
        "Hundi"
    ],
    "name:pan_x_preferred":[
        "\u0a39\u0a41\u0a70\u0a21\u0a40"
    ],
    "name:urd_x_preferred":[
        "\u06c1\u0646\u0688\u06cc"
    ],
    "wof:name":"Hundi",
    "wof:placetype":"locality"
},
  "geometry": {"coordinates":[67.67948,25.27154],"type":"Point"}
}