{
  "type": "Feature",
  "properties": {
    "gn:admin1_code":"4.0",
    "gn:asciiname":"Chak Eighty-six",
    "gn:country_code":"PK",
    "gn:dem":133,
    "gn:feature_class":"P",
    "gn:feature_code":"PPL",
    "gn:name":"Chak Eighty-six",
    "gn:population":0,
    "gn:timezone":"Asia/Karachi",
    "iso:country":"PK",
    "name:und_x_variant":[
        "Buzurgw\u0101l",
        "Chak Eighty-six"
    ],
    "wof:name":"Chak Eighty-six",
    "wof:placetype":"locality"
},
  "geometry": {"coordinates":[72.11579999999999,30.04988],"type":"Point"}
}