{
  "type": "Feature",
  "properties": {
    "gn:admin1_code":"3",
    "gn:asciiname":"Dulai",
    "gn:country_code":"PK",
    "gn:dem":1565,
    "gn:feature_class":"P",
    "gn:feature_code":"PPL",
    "gn:name":"Dulai",
    "gn:population":0,
    "gn:timezone":"Asia/Karachi",
    "iso:country":"PK",
    "wof:name":"Dulai",
    "wof:placetype":"locality"
},
  "geometry": {"coordinates":[72.84678000000002,34.89455],"type":"Point"}
}