{
  "type": "Feature",
  "properties": {
    "gn:admin1_code":"4",
    "gn:asciiname":"Chak Forty-eight",
    "gn:country_code":"PK",
    "gn:dem":116,
    "gn:feature_class":"P",
    "gn:feature_code":"PPL",
    "gn:name":"Chak Forty-eight",
    "gn:population":0,
    "gn:timezone":"Asia/Karachi",
    "iso:country":"PK",
    "name:und_x_variant":[
        "Chak Forty-Eight M",
        "Chak 48 M",
        "Chak Forty-eight"
    ],
    "wof:name":"Chak Forty-eight",
    "wof:placetype":"locality"
},
  "geometry": {"coordinates":[71.50176,29.67606],"type":"Point"}
}