{
  "type": "Feature",
  "properties": {
    "gn:admin1_code":"4.0",
    "gn:asciiname":"Budhewala",
    "gn:country_code":"PK",
    "gn:dem":135,
    "gn:feature_class":"P",
    "gn:feature_code":"PPL",
    "gn:name":"Budhewala",
    "gn:population":0,
    "gn:timezone":"Asia/Karachi",
    "iso:country":"PK",
    "name:und_x_variant":[
        "Buddhew\u0101la"
    ],
    "wof:name":"Budhewala",
    "wof:placetype":"locality"
},
  "geometry": {"coordinates":[72.20574000000001,30.1673],"type":"Point"}
}