{
  "type": "Feature",
  "properties": {
    "gn:admin1_code":"3",
    "gn:asciiname":"Khwarpalai",
    "gn:country_code":"PK",
    "gn:dem":1686,
    "gn:feature_class":"P",
    "gn:feature_code":"PPL",
    "gn:name":"Khw\u0101rpalai",
    "gn:population":0,
    "gn:timezone":"Asia/Karachi",
    "iso:country":"PK",
    "wof:name":"Khwarpalai",
    "wof:placetype":"locality"
},
  "geometry": {"coordinates":[72.53749999999999,34.81111],"type":"Point"}
}