{
  "type": "Feature",
  "properties": {
    "gn:admin1_code":"4",
    "gn:asciiname":"Kotli Manan",
    "gn:country_code":"PK",
    "gn:dem":251,
    "gn:feature_class":"P",
    "gn:feature_code":"PPL",
    "gn:name":"Kotli Manan",
    "gn:population":0,
    "gn:timezone":"Asia/Karachi",
    "iso:country":"PK",
    "name:und_x_variant":[
        "Kotli Manalian",
        "Kotli Manan"
    ],
    "wof:name":"Kotli Manan",
    "wof:placetype":"locality"
},
  "geometry": {"coordinates":[74.58901999999998,32.71331],"type":"Point"}
}