{
  "type": "Feature",
  "properties": {
    "gn:admin1_code":"5",
    "gn:asciiname":"Goth Abdullah Tunio",
    "gn:country_code":"PK",
    "gn:dem":54,
    "gn:feature_class":"P",
    "gn:feature_code":"PPL",
    "gn:name":"Goth Abdullah Tunio",
    "gn:population":0,
    "gn:timezone":"Asia/Karachi",
    "iso:country":"PK",
    "name:und_x_variant":[
        "Geru"
    ],
    "wof:name":"Goth Abdullah Tunio",
    "wof:placetype":"locality"
},
  "geometry": {"coordinates":[68.39498,27.3796],"type":"Point"}
}