{
  "type": "Feature",
  "properties": {
    "gn:admin1_code":"4.0",
    "gn:asciiname":"Sheru Khelanwala",
    "gn:country_code":"PK",
    "gn:dem":251,
    "gn:feature_class":"P",
    "gn:feature_code":"PPL",
    "gn:name":"Sheru Khelanwala",
    "gn:population":0,
    "gn:timezone":"Asia/Karachi",
    "iso:country":"PK",
    "name:und_x_variant":[
        "Sheru Khel\u0101w\u0101la",
        "Sherw\u0101la",
        "Sheru Khelanwala"
    ],
    "wof:name":"Sheru Khelanwala",
    "wof:placetype":"locality"
},
  "geometry": {"coordinates":[71.73186,32.59295],"type":"Point"}
}