{
  "type": "Feature",
  "properties": {
    "gn:admin1_code":"6.0",
    "gn:asciiname":"Darhal Gangan",
    "gn:country_code":"PK",
    "gn:dem":526,
    "gn:feature_class":"P",
    "gn:feature_code":"PPL",
    "gn:name":"Darhal Gangan",
    "gn:population":0,
    "gn:timezone":"Asia/Karachi",
    "iso:country":"PK",
    "wof:name":"Darhal Gangan",
    "wof:placetype":"locality"
},
  "geometry": {"coordinates":[73.9853,33.14782],"type":"Point"}
}