{
  "type": "Feature",
  "properties": {
    "gn:admin1_code":"5.0",
    "gn:asciiname":"Naik Muhammad Burro",
    "gn:country_code":"PK",
    "gn:dem":66,
    "gn:feature_class":"P",
    "gn:feature_code":"PPL",
    "gn:name":"Naik Muhammad Burro",
    "gn:population":0,
    "gn:timezone":"Asia/Karachi",
    "iso:country":"PK",
    "wof:name":"Naik Muhammad Burro",
    "wof:placetype":"locality"
},
  "geometry": {"coordinates":[68.72969999999999,28.26078],"type":"Point"}
}