{
  "type": "Feature",
  "properties": {
    "gn:admin1_code":"2.0",
    "gn:asciiname":"Sunt",
    "gn:country_code":"PK",
    "gn:dem":1388,
    "gn:feature_class":"P",
    "gn:feature_code":"PPL",
    "gn:name":"Sunt",
    "gn:population":0,
    "gn:timezone":"Asia/Karachi",
    "iso:country":"PK",
    "wof:name":"Sunt",
    "wof:placetype":"locality"
},
  "geometry": {"coordinates":[64.71092,27.3767],"type":"Point"}
}