{
  "type": "Feature",
  "properties": {
    "gn:admin1_code":"4.0",
    "gn:asciiname":"Basti Kansawaia",
    "gn:country_code":"PK",
    "gn:dem":113,
    "gn:feature_class":"P",
    "gn:feature_code":"PPL",
    "gn:name":"Basti Kansawaia",
    "gn:population":0,
    "gn:timezone":"Asia/Karachi",
    "iso:country":"PK",
    "wof:name":"Basti Kansawaia",
    "wof:placetype":"locality"
},
  "geometry": {"coordinates":[71.13853,29.84334],"type":"Point"}
}