{
  "type": "Feature",
  "properties": {
    "gn:admin1_code":"3",
    "gn:asciiname":"Jhok Khoja",
    "gn:country_code":"PK",
    "gn:dem":172,
    "gn:feature_class":"P",
    "gn:feature_code":"PPL",
    "gn:name":"Jhok Khoja",
    "gn:population":0,
    "gn:timezone":"Asia/Karachi",
    "iso:country":"PK",
    "name:und_x_variant":[
        "Basti Khojhi\u0101w\u0101li",
        "Basti Khojhi\u0101nw\u0101li",
        "Jhok Khoja"
    ],
    "wof:name":"Jhok Khoja",
    "wof:placetype":"locality"
},
  "geometry": {"coordinates":[70.64230000000001,31.50825],"type":"Point"}
}