{
  "type": "Feature",
  "properties": {
    "gn:admin1_code":"2.0",
    "gn:asciiname":"Darga",
    "gn:country_code":"PK",
    "gn:dem":2377,
    "gn:feature_class":"P",
    "gn:feature_code":"PPL",
    "gn:name":"Darga",
    "gn:population":0,
    "gn:timezone":"Asia/Karachi",
    "iso:country":"PK",
    "name:deu_x_preferred":[
        "Darga"
    ],
    "wof:name":"Darga",
    "wof:placetype":"locality"
},
  "geometry": {"coordinates":[67.59454000000001,30.82956],"type":"Point"}
}