{
  "type": "Feature",
  "properties": {
    "gn:admin1_code":"5",
    "gn:asciiname":"Goth Haji Waris Khan",
    "gn:country_code":"PK",
    "gn:dem":13,
    "gn:feature_class":"P",
    "gn:feature_code":"PPL",
    "gn:name":"Goth Haji Waris Khan",
    "gn:population":0,
    "gn:timezone":"Asia/Karachi",
    "iso:country":"PK",
    "name:und_x_variant":[
        "Goth H\u0101ji W\u0101ris Kh\u0101n Kh\u0101skheli"
    ],
    "wof:name":"Goth Haji Waris Khan",
    "wof:placetype":"locality"
},
  "geometry": {"coordinates":[69.09088,25.25954],"type":"Point"}
}