{
  "type": "Feature",
  "properties": {
    "gn:admin1_code":"4.0",
    "gn:asciiname":"Shau Ke Jhuge",
    "gn:country_code":"PK",
    "gn:dem":171,
    "gn:feature_class":"P",
    "gn:feature_code":"PPL",
    "gn:name":"Shau Ke Jhuge",
    "gn:population":0,
    "gn:timezone":"Asia/Karachi",
    "iso:country":"PK",
    "wof:name":"Shau Ke Jhuge",
    "wof:placetype":"locality"
},
  "geometry": {"coordinates":[73.01628000000002,30.95332],"type":"Point"}
}