{
  "type": "Feature",
  "properties": {
    "gn:admin1_code":"4.0",
    "gn:asciiname":"Bhopalpur Uparla",
    "gn:country_code":"PK",
    "gn:dem":298,
    "gn:feature_class":"P",
    "gn:feature_code":"PPL",
    "gn:name":"Bhopalpur Uparla",
    "gn:population":0,
    "gn:timezone":"Asia/Kolkata",
    "iso:country":"PK",
    "wof:name":"Bhopalpur Uparla",
    "wof:placetype":"locality"
},
  "geometry": {"coordinates":[75.1549,32.41613],"type":"Point"}
}