{
  "type": "Feature",
  "properties": {
    "gn:admin1_code":"5.0",
    "gn:asciiname":"Goth Mari Thal",
    "gn:country_code":"PK",
    "gn:dem":1539,
    "gn:feature_class":"P",
    "gn:feature_code":"PPL",
    "gn:name":"Goth Mari Thal",
    "gn:population":0,
    "gn:timezone":"Asia/Karachi",
    "iso:country":"PK",
    "wof:name":"Goth Mari Thal",
    "wof:placetype":"locality"
},
  "geometry": {"coordinates":[67.18755999999999,27.21016],"type":"Point"}
}