{
  "type": "Feature",
  "properties": {
    "gn:admin1_code":"2.0",
    "gn:asciiname":"Shin Khana",
    "gn:country_code":"PK",
    "gn:dem":2369,
    "gn:feature_class":"P",
    "gn:feature_code":"PPL",
    "gn:name":"Shin Khana",
    "gn:population":0,
    "gn:timezone":"Asia/Karachi",
    "iso:country":"PK",
    "name:eng_x_preferred":[
        "Shina K\u0101nr"
    ],
    "wof:name":"Shin Khana",
    "wof:placetype":"locality"
},
  "geometry": {"coordinates":[67.46594,30.85714],"type":"Point"}
}