{
  "type": "Feature",
  "properties": {
    "gn:admin1_code":"3.0",
    "gn:asciiname":"Chamhatti",
    "gn:country_code":"PK",
    "gn:dem":851,
    "gn:feature_class":"P",
    "gn:feature_code":"PPL",
    "gn:name":"Chamhatti",
    "gn:population":0,
    "gn:timezone":"Asia/Karachi",
    "iso:country":"PK",
    "name:und_x_variant":[
        "Chamhati",
        "Chamhatti"
    ],
    "wof:name":"Chamhatti",
    "wof:placetype":"locality"
},
  "geometry": {"coordinates":[73.03461,34.22666],"type":"Point"}
}