{
  "type": "Feature",
  "properties": {
    "gn:admin1_code":"4.0",
    "gn:asciiname":"Rahmataki",
    "gn:country_code":"PK",
    "gn:dem":657,
    "gn:feature_class":"P",
    "gn:feature_code":"PPL",
    "gn:name":"Rahmataki",
    "gn:population":0,
    "gn:timezone":"Asia/Karachi",
    "iso:country":"PK",
    "name:und_x_variant":[
        "Ramtaki"
    ],
    "wof:name":"Rahmataki",
    "wof:placetype":"locality"
},
  "geometry": {"coordinates":[72.31538,32.73386],"type":"Point"}
}