{
  "type": "Feature",
  "properties": {
    "gn:admin1_code":"3",
    "gn:asciiname":"Dand",
    "gn:country_code":"PK",
    "gn:dem":1712,
    "gn:feature_class":"P",
    "gn:feature_code":"PPL",
    "gn:name":"Dand",
    "gn:population":0,
    "gn:timezone":"Asia/Karachi",
    "iso:country":"PK",
    "wof:name":"Dand",
    "wof:placetype":"locality"
},
  "geometry": {"coordinates":[72.71471,34.7293],"type":"Point"}
}