{
  "type": "Feature",
  "properties": {
    "gn:admin1_code":"8.0",
    "gn:asciiname":"Ari Saiyidan",
    "gn:country_code":"PK",
    "gn:dem":547,
    "gn:feature_class":"P",
    "gn:feature_code":"PPL",
    "gn:name":"Ari Saiyidan",
    "gn:population":0,
    "gn:timezone":"Asia/Karachi",
    "iso:country":"PK",
    "name:und_x_variant":[
        "\u0100ri Saiyid\u0101n"
    ],
    "wof:name":"Ari Saiyidan",
    "wof:placetype":"locality"
},
  "geometry": {"coordinates":[73.28227,33.57432],"type":"Point"}
}