{
  "type": "Feature",
  "properties": {
    "gn:admin1_code":"7.0",
    "gn:asciiname":"Sumayar",
    "gn:country_code":"PK",
    "gn:dem":3165,
    "gn:feature_class":"P",
    "gn:feature_code":"PPL",
    "gn:name":"Sumayar",
    "gn:population":0,
    "gn:timezone":"Asia/Karachi",
    "iso:country":"PK",
    "wof:name":"Sumayar",
    "wof:placetype":"locality"
},
  "geometry": {"coordinates":[74.55540000000001,36.8208],"type":"Point"}
}