{
  "type": "Feature",
  "properties": {
    "gn:admin1_code":"1",
    "gn:asciiname":"Madak Khel Kili",
    "gn:country_code":"PK",
    "gn:dem":1507,
    "gn:feature_class":"P",
    "gn:feature_code":"PPL",
    "gn:name":"Madak Khel Kili",
    "gn:population":0,
    "gn:timezone":"Asia/Karachi",
    "iso:country":"PK",
    "wof:name":"Madak Khel Kili",
    "wof:placetype":"locality"
},
  "geometry": {"coordinates":[69.87274000000001,33.07813],"type":"Point"}
}