{
  "type": "Feature",
  "properties": {
    "gn:admin1_code":"4",
    "gn:asciiname":"Chak Four Dullewala Branch",
    "gn:country_code":"PK",
    "gn:dem":203,
    "gn:feature_class":"P",
    "gn:feature_code":"PPL",
    "gn:name":"Chak Four Dullewala Branch",
    "gn:population":0,
    "gn:timezone":"Asia/Karachi",
    "iso:country":"PK",
    "name:und_x_variant":[
        "Chak Four DB"
    ],
    "wof:name":"Chak Four Dullewala Branch",
    "wof:placetype":"locality"
},
  "geometry": {"coordinates":[71.53090999999998,32.40089],"type":"Point"}
}