{
  "type": "Feature",
  "properties": {
    "gn:admin1_code":"5.0",
    "gn:asciiname":"Muhammad Bakhsh Delwani",
    "gn:country_code":"PK",
    "gn:dem":13,
    "gn:feature_class":"P",
    "gn:feature_code":"PPL",
    "gn:name":"Muhammad Bakhsh Delwani",
    "gn:population":0,
    "gn:timezone":"Asia/Karachi",
    "iso:country":"PK",
    "wof:name":"Muhammad Bakhsh Delwani",
    "wof:placetype":"locality"
},
  "geometry": {"coordinates":[69.05996999999999,24.98065],"type":"Point"}
}