{
  "type": "Feature",
  "properties": {
    "gn:admin1_code":"4.0",
    "gn:asciiname":"Dhok Sabal",
    "gn:country_code":"PK",
    "gn:dem":402,
    "gn:feature_class":"P",
    "gn:feature_code":"PPL",
    "gn:name":"Dhok Sabal",
    "gn:population":0,
    "gn:timezone":"Asia/Karachi",
    "iso:country":"PK",
    "name:und_x_variant":[
        "Dhok Sab\u0101l\u0101nw\u0101li",
        "Dhok Sabal"
    ],
    "wof:name":"Dhok Sabal",
    "wof:placetype":"locality"
},
  "geometry": {"coordinates":[72.26483,33.0155],"type":"Point"}
}