{
  "type": "Feature",
  "properties": {
    "gn:admin1_code":"4.0",
    "gn:asciiname":"Dhanuae Kalan",
    "gn:country_code":"PK",
    "gn:dem":208,
    "gn:feature_class":"P",
    "gn:feature_code":"PPL",
    "gn:name":"Dhanuae Kalan",
    "gn:population":0,
    "gn:timezone":"Asia/Karachi",
    "iso:country":"PK",
    "name:und_x_variant":[
        "Dhaneye Kal\u0101n"
    ],
    "wof:name":"Dhanuae Kalan",
    "wof:placetype":"locality"
},
  "geometry": {"coordinates":[73.727,32.10273],"type":"Point"}
}