{
  "type": "Feature",
  "properties": {
    "gn:admin1_code":"2",
    "gn:asciiname":"Babek",
    "gn:country_code":"PK",
    "gn:dem":1327,
    "gn:feature_class":"P",
    "gn:feature_code":"PPL",
    "gn:name":"Babek",
    "gn:population":0,
    "gn:timezone":"Asia/Karachi",
    "iso:country":"PK",
    "wof:name":"Babek",
    "wof:placetype":"locality"
},
  "geometry": {"coordinates":[69.05144,30.5302],"type":"Point"}
}