{
  "type": "Feature",
  "properties": {
    "gn:admin1_code":"4.0",
    "gn:asciiname":"Khatwan",
    "gn:country_code":"PK",
    "gn:dem":179,
    "gn:feature_class":"P",
    "gn:feature_code":"PPL",
    "gn:name":"Khatwan",
    "gn:population":0,
    "gn:timezone":"Asia/Karachi",
    "iso:country":"PK",
    "name:fas_x_preferred":[
        "\u06a9\u0647\u062a\u0648\u0627\u0646"
    ],
    "name:urd_x_preferred":[
        "\u06a9\u06be\u0679\u0648\u0627\u06ba"
    ],
    "wof:name":"Khatwan",
    "wof:placetype":"locality"
},
  "geometry": {"coordinates":[72.06641999999999,31.76167],"type":"Point"}
}