{
  "type": "Feature",
  "properties": {
    "gn:admin1_code":"6",
    "gn:asciiname":"Dodwala Nala",
    "gn:country_code":"PK",
    "gn:dem":2678,
    "gn:feature_class":"P",
    "gn:feature_code":"PPL",
    "gn:name":"Dodwala Nala",
    "gn:population":0,
    "gn:timezone":"Asia/Karachi",
    "iso:country":"PK",
    "name:und_x_variant":[
        "Dodew\u0101la Nala"
    ],
    "wof:name":"Dodwala Nala",
    "wof:placetype":"locality"
},
  "geometry": {"coordinates":[73.87236999999998,34.26015],"type":"Point"}
}