{
  "type": "Feature",
  "properties": {
    "gn:admin1_code":"2.0",
    "gn:asciiname":"Mustafa Karez",
    "gn:country_code":"PK",
    "gn:dem":1488,
    "gn:feature_class":"P",
    "gn:feature_code":"PPL",
    "gn:name":"Mustafa Karez",
    "gn:population":0,
    "gn:timezone":"Asia/Karachi",
    "iso:country":"PK",
    "wof:name":"Mustafa Karez",
    "wof:placetype":"locality"
},
  "geometry": {"coordinates":[69.08653000000001,30.84626],"type":"Point"}
}