{
  "type": "Feature",
  "properties": {
    "gn:admin1_code":"6",
    "gn:asciiname":"Gurian",
    "gn:country_code":"PK",
    "gn:dem":1363,
    "gn:feature_class":"P",
    "gn:feature_code":"PPL",
    "gn:name":"Gurian",
    "gn:population":0,
    "gn:timezone":"Asia/Karachi",
    "iso:country":"PK",
    "name:deu_x_preferred":[
        "Gurian"
    ],
    "wof:name":"Gurian",
    "wof:placetype":"locality"
},
  "geometry": {"coordinates":[73.49074,34.491],"type":"Point"}
}