{
  "type": "Feature",
  "properties": {
    "gn:admin1_code":"05",
    "gn:asciiname":"Naushahro Abro Goth",
    "gn:country_code":"PK",
    "gn:dem":61,
    "gn:feature_class":"P",
    "gn:feature_code":"PPL",
    "gn:name":"Naushahro Abro Goth",
    "gn:population":0,
    "gn:timezone":"Asia/Karachi",
    "iso:country":"PK",
    "wof:name":"Naushahro Abro Goth",
    "wof:placetype":"locality"
},
  "geometry": {"coordinates":[68.55405999999999,27.87147],"type":"Point"}
}