{
  "type": "Feature",
  "properties": {
    "gn:admin1_code":"5",
    "gn:asciiname":"Ghulam Ahmad Brahul",
    "gn:country_code":"PK",
    "gn:dem":57,
    "gn:feature_class":"P",
    "gn:feature_code":"PPL",
    "gn:name":"Ghulam Ahmad Brahul",
    "gn:population":0,
    "gn:timezone":"Asia/Karachi",
    "iso:country":"PK",
    "name:und_x_variant":[
        "Ghu\u0101m Ahmad Br\u0101h\u016bl",
        "L\u0101lpur",
        "Ghulam Ahmad Brahul"
    ],
    "wof:name":"Ghulam Ahmad Brahul",
    "wof:placetype":"locality"
},
  "geometry": {"coordinates":[68.29235,27.99658],"type":"Point"}
}