{
  "type": "Feature",
  "properties": {
    "gn:admin1_code":"5",
    "gn:asciiname":"Yaqub Sehto",
    "gn:country_code":"PK",
    "gn:dem":7,
    "gn:feature_class":"P",
    "gn:feature_code":"PPL",
    "gn:name":"Yaqub Sehto",
    "gn:population":0,
    "gn:timezone":"Asia/Karachi",
    "iso:country":"PK",
    "name:und_x_variant":[
        "Goth Sehta"
    ],
    "wof:name":"Yaqub Sehto",
    "wof:placetype":"locality"
},
  "geometry": {"coordinates":[69.15640999999999,24.75962],"type":"Point"}
}