{
  "type": "Feature",
  "properties": {
    "gn:admin1_code":"4.0",
    "gn:asciiname":"Chak Sixty-four Rakh Branch",
    "gn:country_code":"PK",
    "gn:dem":191,
    "gn:feature_class":"P",
    "gn:feature_code":"PPL",
    "gn:name":"Chak Sixty-four Rakh Branch",
    "gn:population":0,
    "gn:timezone":"Asia/Karachi",
    "iso:country":"PK",
    "name:und_x_variant":[
        "Gur\u016bsar",
        "Bund\u0101la",
        "Chak Sixty-four Rakh Branch",
        "Band\u0101la"
    ],
    "wof:name":"Chak Sixty-four Rakh Branch",
    "wof:placetype":"locality"
},
  "geometry": {"coordinates":[73.35799,31.60265],"type":"Point"}
}