{
  "type": "Feature",
  "properties": {
    "gn:admin1_code":"6",
    "gn:asciiname":"Charangli",
    "gn:country_code":"PK",
    "gn:dem":652,
    "gn:feature_class":"P",
    "gn:feature_code":"PPL",
    "gn:name":"Charangli",
    "gn:population":0,
    "gn:timezone":"Asia/Karachi",
    "iso:country":"PK",
    "name:und_x_variant":[
        "Churangil"
    ],
    "wof:name":"Charangli",
    "wof:placetype":"locality"
},
  "geometry": {"coordinates":[73.86575000000001,33.47693],"type":"Point"}
}