{
  "type": "Feature",
  "properties": {
    "gn:admin1_code":"4.0",
    "gn:asciiname":"Kadawala Toba",
    "gn:country_code":"PK",
    "gn:dem":118,
    "gn:feature_class":"P",
    "gn:feature_code":"PPL",
    "gn:name":"Kadawala Toba",
    "gn:population":0,
    "gn:timezone":"Asia/Karachi",
    "iso:country":"PK",
    "name:und_x_variant":[
        "Kadaw\u0101la",
        "Kadawala Toba"
    ],
    "wof:name":"Kadawala Toba",
    "wof:placetype":"locality"
},
  "geometry": {"coordinates":[72.13333,28.61667000000001],"type":"Point"}
}