{
  "type": "Feature",
  "properties": {
    "gn:admin1_code":"2",
    "gn:asciiname":"Goth Murad Ali",
    "gn:country_code":"PK",
    "gn:dem":57,
    "gn:feature_class":"P",
    "gn:feature_code":"PPL",
    "gn:name":"Goth Murad Ali",
    "gn:population":0,
    "gn:timezone":"Asia/Karachi",
    "iso:country":"PK",
    "name:und_x_variant":[
        "Mur\u0101d Ali"
    ],
    "wof:name":"Goth Murad Ali",
    "wof:placetype":"locality"
},
  "geometry": {"coordinates":[68.49939000000001,28.43819],"type":"Point"}
}