{
  "type": "Feature",
  "properties": {
    "gn:admin1_code":"4.0",
    "gn:asciiname":"Shahwala Parara",
    "gn:country_code":"PK",
    "gn:dem":173,
    "gn:feature_class":"P",
    "gn:feature_code":"PPL",
    "gn:name":"Shahwala Parara",
    "gn:population":0,
    "gn:timezone":"Asia/Karachi",
    "iso:country":"PK",
    "wof:name":"Shahwala Parara",
    "wof:placetype":"locality"
},
  "geometry": {"coordinates":[72.47833,31.9262],"type":"Point"}
}