{
  "type": "Feature",
  "properties": {
    "gn:admin1_code":"3.0",
    "gn:asciiname":"Daran Banda",
    "gn:country_code":"PK",
    "gn:dem":3176,
    "gn:feature_class":"P",
    "gn:feature_code":"PPL",
    "gn:name":"Daran Banda",
    "gn:population":0,
    "gn:timezone":"Asia/Karachi",
    "iso:country":"PK",
    "wof:name":"Daran Banda",
    "wof:placetype":"locality"
},
  "geometry": {"coordinates":[71.72450000000001,35.28205999999999],"type":"Point"}
}