{
  "type": "Feature",
  "properties": {
    "gn:admin1_code":"4.0",
    "gn:asciiname":"Chak Milla",
    "gn:country_code":"PK",
    "gn:dem":911,
    "gn:feature_class":"P",
    "gn:feature_code":"PPL",
    "gn:name":"Chak Milla",
    "gn:population":0,
    "gn:timezone":"Asia/Karachi",
    "iso:country":"PK",
    "wof:name":"Chak Milla",
    "wof:placetype":"locality"
},
  "geometry": {"coordinates":[73.53763000000002,33.93518],"type":"Point"}
}