{
  "type": "Feature",
  "properties": {
    "gn:admin1_code":"4",
    "gn:asciiname":"Chah Khokharanwala",
    "gn:country_code":"PK",
    "gn:dem":155,
    "gn:feature_class":"P",
    "gn:feature_code":"PPL",
    "gn:name":"Chah Khokharanwala",
    "gn:population":0,
    "gn:timezone":"Asia/Karachi",
    "iso:country":"PK",
    "wof:name":"Chah Khokharanwala",
    "wof:placetype":"locality"
},
  "geometry": {"coordinates":[72.12566,31.30653],"type":"Point"}
}