{
  "type": "Feature",
  "properties": {
    "gn:admin1_code":"5.0",
    "gn:asciiname":"Deh Toba",
    "gn:country_code":"PK",
    "gn:dem":22,
    "gn:feature_class":"P",
    "gn:feature_code":"PPL",
    "gn:name":"Deh Toba",
    "gn:population":0,
    "gn:timezone":"Asia/Karachi",
    "iso:country":"PK",
    "name:und_x_variant":[
        "Dhedtobo"
    ],
    "wof:name":"Deh Toba",
    "wof:placetype":"locality"
},
  "geometry": {"coordinates":[70.63866999999998,24.55106],"type":"Point"}
}