{
  "type": "Feature",
  "properties": {
    "gn:admin1_code":"04",
    "gn:asciiname":"Kot Mahoi",
    "gn:country_code":"PK",
    "gn:dem":193,
    "gn:feature_class":"P",
    "gn:feature_code":"PPL",
    "gn:name":"Kot Mahoi",
    "gn:population":0,
    "gn:timezone":"Asia/Karachi",
    "iso:country":"PK",
    "name:und_x_variant":[
        "Kot Mohoi",
        "Kot Mahoi"
    ],
    "wof:name":"Kot Mahoi",
    "wof:placetype":"locality"
},
  "geometry": {"coordinates":[70.59954999999999,30.54981],"type":"Point"}
}