{
  "type": "Feature",
  "properties": {
    "gn:admin1_code":"3.0",
    "gn:asciiname":"Katan Banda",
    "gn:country_code":"PK",
    "gn:dem":3152,
    "gn:feature_class":"P",
    "gn:feature_code":"PPL",
    "gn:name":"Katan Banda",
    "gn:population":0,
    "gn:timezone":"Asia/Karachi",
    "iso:country":"PK",
    "name:eng_x_preferred":[
        "Margh\u0101t\u012br"
    ],
    "wof:name":"Katan Banda",
    "wof:placetype":"locality"
},
  "geometry": {"coordinates":[72.27449,35.60345],"type":"Point"}
}