{
  "type": "Feature",
  "properties": {
    "gn:admin1_code":"2.0",
    "gn:asciiname":"Khan Jan",
    "gn:country_code":"PK",
    "gn:dem":380,
    "gn:feature_class":"P",
    "gn:feature_code":"PPL",
    "gn:name":"Khan Jan",
    "gn:population":0,
    "gn:timezone":"Asia/Karachi",
    "iso:country":"PK",
    "wof:name":"Khan Jan",
    "wof:placetype":"locality"
},
  "geometry": {"coordinates":[65.66667,26.3974],"type":"Point"}
}