{
  "type": "Feature",
  "properties": {
    "gn:admin1_code":"4.0",
    "gn:asciiname":"Dhok Rai Neka",
    "gn:country_code":"PK",
    "gn:dem":470,
    "gn:feature_class":"P",
    "gn:feature_code":"PPL",
    "gn:name":"Dhok Rai Neka",
    "gn:population":0,
    "gn:timezone":"Asia/Karachi",
    "iso:country":"PK",
    "wof:name":"Dhok Rai Neka",
    "wof:placetype":"locality"
},
  "geometry": {"coordinates":[72.60462,33.50701],"type":"Point"}
}