{
  "type": "Feature",
  "properties": {
    "gn:admin1_code":"4.0",
    "gn:asciiname":"Mal Pind",
    "gn:country_code":"PK",
    "gn:dem":408,
    "gn:feature_class":"P",
    "gn:feature_code":"PPL",
    "gn:name":"Mal Pind",
    "gn:population":0,
    "gn:timezone":"Asia/Karachi",
    "iso:country":"PK",
    "wof:name":"Mal Pind",
    "wof:placetype":"locality"
},
  "geometry": {"coordinates":[72.67525000000001,33.85867],"type":"Point"}
}