{
  "type": "Feature",
  "properties": {
    "gn:admin1_code":"4",
    "gn:asciiname":"Kot Kalu",
    "gn:country_code":"PK",
    "gn:dem":222,
    "gn:feature_class":"P",
    "gn:feature_code":"PPL",
    "gn:name":"Kot Kalu",
    "gn:population":0,
    "gn:timezone":"Asia/Karachi",
    "iso:country":"PK",
    "wof:name":"Kot Kalu",
    "wof:placetype":"locality"
},
  "geometry": {"coordinates":[73.99840999999998,32.39996],"type":"Point"}
}