{
  "type": "Feature",
  "properties": {
    "gn:admin1_code":"03",
    "gn:asciiname":"Paras",
    "gn:country_code":"PK",
    "gn:dem":1301,
    "gn:feature_class":"P",
    "gn:feature_code":"PPL",
    "gn:name":"Paras",
    "gn:population":0,
    "gn:timezone":"Asia/Karachi",
    "iso:country":"PK",
    "name:und_x_variant":[
        "P\u0101ras"
    ],
    "wof:name":"Paras",
    "wof:placetype":"locality"
},
  "geometry": {"coordinates":[73.46120000000001,34.66231],"type":"Point"}
}