{
  "type": "Feature",
  "properties": {
    "gn:admin1_code":"5",
    "gn:asciiname":"Goth Haji Sawan",
    "gn:country_code":"PK",
    "gn:dem":13,
    "gn:feature_class":"P",
    "gn:feature_code":"PPL",
    "gn:name":"Goth Haji Sawan",
    "gn:population":0,
    "gn:timezone":"Asia/Karachi",
    "iso:country":"PK",
    "name:und_x_variant":[
        "H\u0101ji S\u0101wan"
    ],
    "wof:name":"Goth Haji Sawan",
    "wof:placetype":"locality"
},
  "geometry": {"coordinates":[69.51205,25.45089],"type":"Point"}
}