{
  "type": "Feature",
  "properties": {
    "gn:admin1_code":"5.0",
    "gn:asciiname":"Muhammad Bakhsh Rind",
    "gn:country_code":"PK",
    "gn:dem":54,
    "gn:feature_class":"P",
    "gn:feature_code":"PPL",
    "gn:name":"Muhammad Bakhsh Rind",
    "gn:population":0,
    "gn:timezone":"Asia/Karachi",
    "iso:country":"PK",
    "wof:name":"Muhammad Bakhsh Rind",
    "wof:placetype":"locality"
},
  "geometry": {"coordinates":[68.1464,28.18577],"type":"Point"}
}