{
  "type": "Feature",
  "properties": {
    "gn:admin1_code":"6",
    "gn:asciiname":"Kuhi",
    "gn:country_code":"PK",
    "gn:dem":288,
    "gn:feature_class":"P",
    "gn:feature_code":"PPL",
    "gn:name":"Kuhi",
    "gn:population":0,
    "gn:timezone":"Asia/Karachi",
    "iso:country":"PK",
    "name:ceb_x_preferred":[
        "K\u016bhi"
    ],
    "name:swe_x_preferred":[
        "K\u016bhi"
    ],
    "name:und_x_variant":[
        "Kuhl Zer",
        "Kuhi"
    ],
    "wof:name":"Kuhi",
    "wof:placetype":"locality"
},
  "geometry": {"coordinates":[73.93589,32.9971],"type":"Point"}
}