{
  "type": "Feature",
  "properties": {
    "gn:admin1_code":"4.0",
    "gn:asciiname":"Basti Dur Muhammad Sher",
    "gn:country_code":"PK",
    "gn:dem":104,
    "gn:feature_class":"P",
    "gn:feature_code":"PPL",
    "gn:name":"Basti Dur Muhammad Sher",
    "gn:population":0,
    "gn:timezone":"Asia/Karachi",
    "iso:country":"PK",
    "wof:name":"Basti Dur Muhammad Sher",
    "wof:placetype":"locality"
},
  "geometry": {"coordinates":[70.63511,29.46076],"type":"Point"}
}