{
  "type": "Feature",
  "properties": {
    "gn:admin1_code":"4",
    "gn:asciiname":"Kili Nasir Khel",
    "gn:country_code":"PK",
    "gn:dem":139,
    "gn:feature_class":"P",
    "gn:feature_code":"PPL",
    "gn:name":"Kili Nasir Khel",
    "gn:population":0,
    "gn:timezone":"Asia/Karachi",
    "iso:country":"PK",
    "name:und_x_variant":[
        "F\u0101zilw\u0101la"
    ],
    "wof:name":"Kili Nasir Khel",
    "wof:placetype":"locality"
},
  "geometry": {"coordinates":[71.1032,30.57627],"type":"Point"}
}