{
  "type": "Feature",
  "properties": {
    "gn:admin1_code":"3",
    "gn:asciiname":"Wahat",
    "gn:country_code":"PK",
    "gn:dem":2343,
    "gn:feature_class":"P",
    "gn:feature_code":"PPL",
    "gn:name":"Wahat",
    "gn:population":0,
    "gn:timezone":"Asia/Karachi",
    "iso:country":"PK",
    "name:eng_x_preferred":[
        "Warth"
    ],
    "name:urd_x_preferred":[
        "Waht"
    ],
    "name:urd_x_variant":[
        "\u0648\u064e\u06be\u0652\u062a"
    ],
    "wof:name":"Wahat",
    "wof:placetype":"locality"
},
  "geometry": {"coordinates":[71.51767,35.98468],"type":"Point"}
}