{
  "type": "Feature",
  "properties": {
    "gn:admin1_code":"4",
    "gn:asciiname":"Saduwala",
    "gn:country_code":"PK",
    "gn:dem":123,
    "gn:feature_class":"P",
    "gn:feature_code":"PPL",
    "gn:name":"Saduwala",
    "gn:population":0,
    "gn:timezone":"Asia/Karachi",
    "iso:country":"PK",
    "name:und_x_variant":[
        "Sadd\u016bw\u0101la"
    ],
    "wof:name":"Saduwala",
    "wof:placetype":"locality"
},
  "geometry": {"coordinates":[71.58378,30.28969],"type":"Point"}
}