{
  "type": "Feature",
  "properties": {
    "gn:admin1_code":"3.0",
    "gn:asciiname":"Kaskai",
    "gn:country_code":"PK",
    "gn:dem":2331,
    "gn:feature_class":"P",
    "gn:feature_code":"PPL",
    "gn:name":"Kaskai",
    "gn:population":0,
    "gn:timezone":"Asia/Karachi",
    "iso:country":"PK",
    "name:und_x_variant":[
        "Kaske"
    ],
    "wof:name":"Kaskai",
    "wof:placetype":"locality"
},
  "geometry": {"coordinates":[72.21173,35.16249000000001],"type":"Point"}
}