{
  "type": "Feature",
  "properties": {
    "gn:admin1_code":"03",
    "gn:asciiname":"Sarfaraz",
    "gn:country_code":"PK",
    "gn:dem":227,
    "gn:feature_class":"P",
    "gn:feature_code":"PPL",
    "gn:name":"Sarfar\u0101z",
    "gn:population":0,
    "gn:timezone":"Asia/Karachi",
    "iso:country":"PK",
    "wof:name":"Sarfaraz",
    "wof:placetype":"locality"
},
  "geometry": {"coordinates":[70.54472,32.18639],"type":"Point"}
}