{
  "type": "Feature",
  "properties": {
    "gn:admin1_code":"4",
    "gn:asciiname":"Khamisa Pakhiwar",
    "gn:country_code":"PK",
    "gn:dem":103,
    "gn:feature_class":"P",
    "gn:feature_code":"PPL",
    "gn:name":"Khamisa Pakhiwar",
    "gn:population":0,
    "gn:timezone":"Asia/Karachi",
    "iso:country":"PK",
    "name:und_x_variant":[
        "Kham\u012bsa Pakh\u012bwar"
    ],
    "wof:name":"Khamisa Pakhiwar",
    "wof:placetype":"locality"
},
  "geometry": {"coordinates":[71.17214,29.06665],"type":"Point"}
}