{
  "type": "Feature",
  "properties": {
    "gn:admin1_code":"4.0",
    "gn:asciiname":"Dajal",
    "gn:country_code":"PK",
    "gn:dem":141,
    "gn:feature_class":"P",
    "gn:feature_code":"PPL",
    "gn:name":"D\u0101jal",
    "gn:population":0,
    "gn:timezone":"Asia/Karachi",
    "iso:country":"PK",
    "name:eng_x_preferred":[
        "Dajal"
    ],
    "name:urd_x_preferred":[
        "\u062f\u0627\u062c\u0644"
    ],
    "wof:name":"Dajal",
    "wof:placetype":"locality"
},
  "geometry": {"coordinates":[70.81870000000001,30.79874],"type":"Point"}
}