{
  "type": "Feature",
  "properties": {
    "gn:admin1_code":"03",
    "gn:asciiname":"Rangpur Shamali",
    "gn:country_code":"PK",
    "gn:dem":181,
    "gn:feature_class":"P",
    "gn:feature_code":"PPL",
    "gn:name":"Rangpur Shamali",
    "gn:population":0,
    "gn:timezone":"Asia/Karachi",
    "iso:country":"PK",
    "name:und_x_variant":[
        "Rangpur-Shumali",
        "Rangpur Shamali",
        "Rangpur Shim\u0101li"
    ],
    "wof:name":"Rangpur Shamali",
    "wof:placetype":"locality"
},
  "geometry": {"coordinates":[71.0334,32.0644],"type":"Point"}
}