{
  "type": "Feature",
  "properties": {
    "gn:admin1_code":"1.0",
    "gn:asciiname":"Balana Pakhe",
    "gn:country_code":"PK",
    "gn:dem":1873,
    "gn:feature_class":"P",
    "gn:feature_code":"PPL",
    "gn:name":"Balana Pakhe",
    "gn:population":0,
    "gn:timezone":"Asia/Karachi",
    "iso:country":"PK",
    "name:und_x_variant":[
        "Plana Pakha"
    ],
    "wof:name":"Balana Pakhe",
    "wof:placetype":"locality"
},
  "geometry": {"coordinates":[70.76439000000001,33.78183],"type":"Point"}
}