{
  "type": "Feature",
  "properties": {
    "gn:admin1_code":"04",
    "gn:asciiname":"Sui Chimian",
    "gn:country_code":"PK",
    "gn:dem":523,
    "gn:feature_class":"P",
    "gn:feature_code":"PPL",
    "gn:name":"Sui Chimian",
    "gn:population":0,
    "gn:timezone":"Asia/Karachi",
    "iso:country":"PK",
    "name:und_x_variant":[
        "Soi Chemian",
        "Sui Chimian"
    ],
    "wof:name":"Sui Chimian",
    "wof:placetype":"locality"
},
  "geometry": {"coordinates":[73.42933000000002,33.37382],"type":"Point"}
}