{
  "type": "Feature",
  "properties": {
    "gn:admin1_code":"3.0",
    "gn:asciiname":"Dando",
    "gn:country_code":"PK",
    "gn:dem":368,
    "gn:feature_class":"P",
    "gn:feature_code":"PPL",
    "gn:name":"Dando",
    "gn:population":0,
    "gn:timezone":"Asia/Karachi",
    "iso:country":"PK",
    "name:eng_x_preferred":[
        "Dandao"
    ],
    "wof:name":"Dando",
    "wof:placetype":"locality"
},
  "geometry": {"coordinates":[71.8458,34.29837],"type":"Point"}
}