{
  "type": "Feature",
  "properties": {
    "gn:admin1_code":"04",
    "gn:asciiname":"Basti Thil Wazir",
    "gn:country_code":"PK",
    "gn:dem":89,
    "gn:feature_class":"P",
    "gn:feature_code":"PPL",
    "gn:name":"Basti Thil Wazir",
    "gn:population":0,
    "gn:timezone":"Asia/Karachi",
    "iso:country":"PK",
    "name:und_x_variant":[
        "Thul Waz\u012br"
    ],
    "wof:name":"Basti Thil Wazir",
    "wof:placetype":"locality"
},
  "geometry": {"coordinates":[70.21993000000001,28.63522],"type":"Point"}
}