{
  "type": "Feature",
  "properties": {
    "gn:admin1_code":"6",
    "gn:asciiname":"Kiran",
    "gn:country_code":"PK",
    "gn:dem":2539,
    "gn:feature_class":"P",
    "gn:feature_code":"PPL",
    "gn:name":"Kiran",
    "gn:population":0,
    "gn:timezone":"Asia/Karachi",
    "iso:country":"PK",
    "name:ceb_x_preferred":[
        "Kiran"
    ],
    "name:deu_x_preferred":[
        "Kiran"
    ],
    "name:hin_x_preferred":[
        "\u0915\u093f\u0930\u0923"
    ],
    "name:und_x_variant":[
        "Kirni"
    ],
    "wof:name":"Kiran",
    "wof:placetype":"locality"
},
  "geometry": {"coordinates":[74.06140000000001,33.92638],"type":"Point"}
}