{
  "type": "Feature",
  "properties": {
    "gn:admin1_code":"5.0",
    "gn:asciiname":"Dargahi Jakrani",
    "gn:country_code":"PK",
    "gn:dem":65,
    "gn:feature_class":"P",
    "gn:feature_code":"PPL",
    "gn:name":"Dargahi Jakrani",
    "gn:population":0,
    "gn:timezone":"Asia/Karachi",
    "iso:country":"PK",
    "wof:name":"Dargahi Jakrani",
    "wof:placetype":"locality"
},
  "geometry": {"coordinates":[68.92008,28.40487000000001],"type":"Point"}
}