{
  "type": "Feature",
  "properties": {
    "gn:admin1_code":"04",
    "gn:asciiname":"Manda Khel",
    "gn:country_code":"PK",
    "gn:dem":215,
    "gn:feature_class":"P",
    "gn:feature_code":"PPL",
    "gn:name":"Manda Khel",
    "gn:population":0,
    "gn:timezone":"Asia/Karachi",
    "iso:country":"PK",
    "wof:name":"Manda Khel",
    "wof:placetype":"locality"
},
  "geometry": {"coordinates":[71.4166,32.86234],"type":"Point"}
}