{
  "type": "Feature",
  "properties": {
    "gn:admin1_code":"05",
    "gn:asciiname":"Goth Saddar Ji Ujan",
    "gn:country_code":"PK",
    "gn:dem":57,
    "gn:feature_class":"P",
    "gn:feature_code":"PPL",
    "gn:name":"Goth Saddar Ji Ujan",
    "gn:population":0,
    "gn:timezone":"Asia/Karachi",
    "iso:country":"PK",
    "name:und_x_variant":[
        "Saderji",
        "Sadarji",
        "S\u0101darji Bhatti",
        "Goth Saddar Ji Ujan"
    ],
    "wof:name":"Goth Saddar Ji Ujan",
    "wof:placetype":"locality"
},
  "geometry": {"coordinates":[68.54125999999999,27.59038],"type":"Point"}
}