{
  "type": "Feature",
  "properties": {
    "gn:admin1_code":"6.0",
    "gn:asciiname":"Beri di Gal",
    "gn:country_code":"PK",
    "gn:dem":1129,
    "gn:feature_class":"P",
    "gn:feature_code":"PPL",
    "gn:name":"Beri di Gal",
    "gn:population":0,
    "gn:timezone":"Asia/Karachi",
    "iso:country":"PK",
    "wof:name":"Beri di Gal",
    "wof:placetype":"locality"
},
  "geometry": {"coordinates":[73.97754999999999,33.80019],"type":"Point"}
}