{
  "type": "Feature",
  "properties": {
    "gn:admin1_code":"2",
    "gn:asciiname":"Adamzai",
    "gn:country_code":"PK",
    "gn:dem":1725,
    "gn:feature_class":"P",
    "gn:feature_code":"PPL",
    "gn:name":"Adamzai",
    "gn:population":0,
    "gn:timezone":"Asia/Karachi",
    "iso:country":"PK",
    "wof:name":"Adamzai",
    "wof:placetype":"locality"
},
  "geometry": {"coordinates":[66.52226999999999,29.45622],"type":"Point"}
}