{
  "type": "Feature",
  "properties": {
    "gn:admin1_code":"1.0",
    "gn:asciiname":"Shaikh Karoz Ziarat",
    "gn:country_code":"PK",
    "gn:dem":807,
    "gn:feature_class":"P",
    "gn:feature_code":"PPL",
    "gn:name":"Shaikh Karoz Ziarat",
    "gn:population":0,
    "gn:timezone":"Asia/Karachi",
    "iso:country":"PK",
    "name:und_x_variant":[
        "Sheikh Karoz Zi\u0101rat"
    ],
    "wof:name":"Shaikh Karoz Ziarat",
    "wof:placetype":"locality"
},
  "geometry": {"coordinates":[70.22468000000001,32.95751],"type":"Point"}
}