{
  "type": "Feature",
  "properties": {
    "gn:admin1_code":"01",
    "gn:asciiname":"Dhilai",
    "gn:country_code":"PK",
    "gn:dem":931,
    "gn:feature_class":"P",
    "gn:feature_code":"PPL",
    "gn:name":"Dhilai",
    "gn:population":0,
    "gn:timezone":"Asia/Karachi",
    "iso:country":"PK",
    "name:und_x_variant":[
        "Dilai"
    ],
    "wof:name":"Dhilai",
    "wof:placetype":"locality"
},
  "geometry": {"coordinates":[71.43256,34.71474],"type":"Point"}
}