{
  "type": "Feature",
  "properties": {
    "gn:admin1_code":"3.0",
    "gn:asciiname":"Gariwali Banda",
    "gn:country_code":"PK",
    "gn:dem":1981,
    "gn:feature_class":"P",
    "gn:feature_code":"PPL",
    "gn:name":"Gariwali Banda",
    "gn:population":0,
    "gn:timezone":"Asia/Karachi",
    "iso:country":"PK",
    "wof:name":"Gariwali Banda",
    "wof:placetype":"locality"
},
  "geometry": {"coordinates":[73.14936999999998,34.81703],"type":"Point"}
}