{
  "type": "Feature",
  "properties": {
    "gn:admin1_code":"4",
    "gn:asciiname":"Summandriwala",
    "gn:country_code":"PK",
    "gn:dem":135,
    "gn:feature_class":"P",
    "gn:feature_code":"PPL",
    "gn:name":"Summandriwala",
    "gn:population":0,
    "gn:timezone":"Asia/Karachi",
    "iso:country":"PK",
    "name:und_x_variant":[
        "Sammundari"
    ],
    "wof:name":"Summandriwala",
    "wof:placetype":"locality"
},
  "geometry": {"coordinates":[70.93463,30.55013],"type":"Point"}
}