{
  "type": "Feature",
  "properties": {
    "gn:admin1_code":"4.0",
    "gn:asciiname":"Bhator",
    "gn:country_code":"PK",
    "gn:dem":264,
    "gn:feature_class":"P",
    "gn:feature_code":"PPL",
    "gn:name":"Bhator",
    "gn:population":0,
    "gn:timezone":"Asia/Karachi",
    "iso:country":"PK",
    "name:und_x_variant":[
        "Bataur",
        "Bator",
        "Bhator"
    ],
    "wof:name":"Bhator",
    "wof:placetype":"locality"
},
  "geometry": {"coordinates":[73.97866999999999,32.76785],"type":"Point"}
}