{
  "type": "Feature",
  "properties": {
    "gn:admin1_code":"4",
    "gn:asciiname":"Sher Gorh",
    "gn:country_code":"PK",
    "gn:dem":189,
    "gn:feature_class":"P",
    "gn:feature_code":"PPL",
    "gn:name":"Sher Gorh",
    "gn:population":0,
    "gn:timezone":"Asia/Karachi",
    "iso:country":"PK",
    "name:und_x_variant":[
        "Ch\u0101h Sher Bah\u0101dur"
    ],
    "wof:name":"Sher Gorh",
    "wof:placetype":"locality"
},
  "geometry": {"coordinates":[70.58493,30.79355],"type":"Point"}
}