{
  "type": "Feature",
  "properties": {
    "gn:admin1_code":"4",
    "gn:asciiname":"Ali da Dera",
    "gn:country_code":"PK",
    "gn:dem":196,
    "gn:feature_class":"P",
    "gn:feature_code":"PPL",
    "gn:name":"Ali da Dera",
    "gn:population":0,
    "gn:timezone":"Asia/Karachi",
    "iso:country":"PK",
    "name:und_x_variant":[
        "Sher Ali da Dera"
    ],
    "wof:name":"Ali da Dera",
    "wof:placetype":"locality"
},
  "geometry": {"coordinates":[72.92829999999999,32.19457],"type":"Point"}
}