{
  "type": "Feature",
  "properties": {
    "gn:admin1_code":"4.0",
    "gn:asciiname":"Chak Ten Tarpai",
    "gn:country_code":"PK",
    "gn:dem":129,
    "gn:feature_class":"P",
    "gn:feature_code":"PPL",
    "gn:name":"Chak Ten Tarpai",
    "gn:population":0,
    "gn:timezone":"Asia/Karachi",
    "iso:country":"PK",
    "name:und_x_variant":[
        "Am\u012br Kot"
    ],
    "wof:name":"Chak Ten Tarpai",
    "wof:placetype":"locality"
},
  "geometry": {"coordinates":[71.73567,30.1592],"type":"Point"}
}