{
  "type": "Feature",
  "properties": {
    "gn:admin1_code":"3",
    "gn:asciiname":"Tirel",
    "gn:country_code":"PK",
    "gn:dem":2723,
    "gn:feature_class":"P",
    "gn:feature_code":"PPL",
    "gn:name":"Tirel",
    "gn:population":0,
    "gn:timezone":"Asia/Karachi",
    "iso:country":"PK",
    "wof:name":"Tirel",
    "wof:placetype":"locality"
},
  "geometry": {"coordinates":[73.37345999999999,34.67841],"type":"Point"}
}