{
  "type": "Feature",
  "properties": {
    "gn:admin1_code":"2.0",
    "gn:asciiname":"Alangi",
    "gn:country_code":"PK",
    "gn:dem":831,
    "gn:feature_class":"P",
    "gn:feature_code":"PPL",
    "gn:name":"Alangi",
    "gn:population":0,
    "gn:timezone":"Asia/Karachi",
    "iso:country":"PK",
    "wof:name":"Alangi",
    "wof:placetype":"locality"
},
  "geometry": {"coordinates":[67.11587,27.68545],"type":"Point"}
}