{
  "type": "Feature",
  "properties": {
    "gn:admin1_code":"5",
    "gn:asciiname":"Goth Gulab Shaikh",
    "gn:country_code":"PK",
    "gn:dem":51,
    "gn:feature_class":"P",
    "gn:feature_code":"PPL",
    "gn:name":"Goth Gulab Shaikh",
    "gn:population":0,
    "gn:timezone":"Asia/Karachi",
    "iso:country":"PK",
    "name:und_x_variant":[
        "Gul\u0101b Shaikh"
    ],
    "wof:name":"Goth Gulab Shaikh",
    "wof:placetype":"locality"
},
  "geometry": {"coordinates":[68.22256999999999,27.53197],"type":"Point"}
}