{
  "type": "Feature",
  "properties": {
    "gn:admin1_code":"5.0",
    "gn:asciiname":"Gul Gaho",
    "gn:country_code":"PK",
    "gn:dem":16,
    "gn:feature_class":"P",
    "gn:feature_code":"PPL",
    "gn:name":"Gul Gaho",
    "gn:population":0,
    "gn:timezone":"Asia/Karachi",
    "iso:country":"PK",
    "name:und_x_variant":[
        "Gul Caho"
    ],
    "wof:name":"Gul Gaho",
    "wof:placetype":"locality"
},
  "geometry": {"coordinates":[68.18666999999999,24.81672],"type":"Point"}
}