{
  "type": "Feature",
  "properties": {
    "gn:admin1_code":"4.0",
    "gn:asciiname":"Bhiryunwala",
    "gn:country_code":"PK",
    "gn:dem":224,
    "gn:feature_class":"P",
    "gn:feature_code":"PPL",
    "gn:name":"Bhiryunwala",
    "gn:population":0,
    "gn:timezone":"Asia/Karachi",
    "iso:country":"PK",
    "name:und_x_variant":[
        "Birhunw\u0101la"
    ],
    "wof:name":"Bhiryunwala",
    "wof:placetype":"locality"
},
  "geometry": {"coordinates":[71.59611,32.66709],"type":"Point"}
}