{
  "type": "Feature",
  "properties": {
    "gn:admin1_code":"3.0",
    "gn:asciiname":"Qaziabad",
    "gn:country_code":"PK",
    "gn:dem":306,
    "gn:feature_class":"P",
    "gn:feature_code":"PPL",
    "gn:name":"Qaziabad",
    "gn:population":0,
    "gn:timezone":"Asia/Karachi",
    "iso:country":"PK",
    "name:eng_x_preferred":[
        "Qaziabad"
    ],
    "wof:name":"Qaziabad",
    "wof:placetype":"locality"
},
  "geometry": {"coordinates":[71.86546,34.14549],"type":"Point"}
}