{
  "type": "Feature",
  "properties": {
    "gn:admin1_code":"1.0",
    "gn:asciiname":"Girdghun",
    "gn:country_code":"PK",
    "gn:dem":720,
    "gn:feature_class":"P",
    "gn:feature_code":"PPL",
    "gn:name":"Girdghun",
    "gn:population":0,
    "gn:timezone":"Asia/Karachi",
    "iso:country":"PK",
    "wof:name":"Girdghun",
    "wof:placetype":"locality"
},
  "geometry": {"coordinates":[70.08986,31.63304],"type":"Point"}
}