{
  "type": "Feature",
  "properties": {
    "gn:admin1_code":"04",
    "gn:asciiname":"Yusafwala",
    "gn:country_code":"PK",
    "gn:dem":174,
    "gn:feature_class":"P",
    "gn:feature_code":"PPL",
    "gn:name":"Yusafwala",
    "gn:population":0,
    "gn:timezone":"Asia/Karachi",
    "iso:country":"PK",
    "name:und_x_variant":[
        "Y\u016bsufw\u0101la"
    ],
    "wof:name":"Yusafwala",
    "wof:placetype":"locality"
},
  "geometry": {"coordinates":[73.193,30.67998],"type":"Point"}
}