{
  "type": "Feature",
  "properties": {
    "gn:admin1_code":"3",
    "gn:asciiname":"Slaimanai",
    "gn:country_code":"PK",
    "gn:dem":546,
    "gn:feature_class":"P",
    "gn:feature_code":"PPL",
    "gn:name":"Slaimanai",
    "gn:population":0,
    "gn:timezone":"Asia/Karachi",
    "iso:country":"PK",
    "name:und_x_variant":[
        "Sulaim\u0101nai",
        "Silionai",
        "Slaimanai"
    ],
    "wof:name":"Slaimanai",
    "wof:placetype":"locality"
},
  "geometry": {"coordinates":[72.73488,34.43603],"type":"Point"}
}