{
  "type": "Feature",
  "properties": {
    "gn:admin1_code":"4.0",
    "gn:asciiname":"Dera Saiyid Mushir Shah",
    "gn:country_code":"PK",
    "gn:dem":84,
    "gn:feature_class":"P",
    "gn:feature_code":"PPL",
    "gn:name":"Dera Saiyid Mushir Shah",
    "gn:population":0,
    "gn:timezone":"Asia/Karachi",
    "iso:country":"PK",
    "wof:name":"Dera Saiyid Mushir Shah",
    "wof:placetype":"locality"
},
  "geometry": {"coordinates":[70.46691,28.36206],"type":"Point"}
}