{
  "type": "Feature",
  "properties": {
    "gn:admin1_code":"3.0",
    "gn:asciiname":"Noja Bandi",
    "gn:country_code":"PK",
    "gn:dem":1114,
    "gn:feature_class":"P",
    "gn:feature_code":"PPL",
    "gn:name":"Noja Bandi",
    "gn:population":0,
    "gn:timezone":"Asia/Karachi",
    "iso:country":"PK",
    "wof:name":"Noja Bandi",
    "wof:placetype":"locality"
},
  "geometry": {"coordinates":[73.18463,33.96774],"type":"Point"}
}