{
  "type": "Feature",
  "properties": {
    "gn:admin1_code":"4.0",
    "gn:asciiname":"Colony Chak Eighty-eight",
    "gn:country_code":"PK",
    "gn:dem":137,
    "gn:feature_class":"P",
    "gn:feature_code":"PPL",
    "gn:name":"Colony Chak Eighty-eight",
    "gn:population":0,
    "gn:timezone":"Asia/Karachi",
    "iso:country":"PK",
    "wof:name":"Colony Chak Eighty-eight",
    "wof:placetype":"locality"
},
  "geometry": {"coordinates":[71.96449,30.27837],"type":"Point"}
}