{
  "type": "Feature",
  "properties": {
    "gn:admin1_code":"5.0",
    "gn:asciiname":"Doctor Muhammad Alam",
    "gn:country_code":"PK",
    "gn:dem":59,
    "gn:feature_class":"P",
    "gn:feature_code":"PPL",
    "gn:name":"Doctor Muhammad Alam",
    "gn:population":0,
    "gn:timezone":"Asia/Karachi",
    "iso:country":"PK",
    "wof:name":"Doctor Muhammad Alam",
    "wof:placetype":"locality"
},
  "geometry": {"coordinates":[68.67274999999999,28.4023],"type":"Point"}
}