{
  "type": "Feature",
  "properties": {
    "gn:admin1_code":"4.0",
    "gn:asciiname":"Ibrahimabad",
    "gn:country_code":"PK",
    "gn:dem":212,
    "gn:feature_class":"P",
    "gn:feature_code":"PPL",
    "gn:name":"Ibrahimabad",
    "gn:population":0,
    "gn:timezone":"Asia/Karachi",
    "iso:country":"PK",
    "name:und_x_variant":[
        "Path\u0101nw\u0101la",
        "Ibr\u0101h\u012bm\u0101b\u0101d",
        "Ibrahimabad"
    ],
    "wof:name":"Ibrahimabad",
    "wof:placetype":"locality"
},
  "geometry": {"coordinates":[74.48363000000001,31.25486],"type":"Point"}
}