{
  "type": "Feature",
  "properties": {
    "gn:admin1_code":"3.0",
    "gn:asciiname":"Umarabad",
    "gn:country_code":"PK",
    "gn:dem":407,
    "gn:feature_class":"P",
    "gn:feature_code":"PPL",
    "gn:name":"Umarabad",
    "gn:population":0,
    "gn:timezone":"Asia/Karachi",
    "iso:country":"PK",
    "name:eng_x_preferred":[
        "Ghari\u0101b\u0101d"
    ],
    "wof:name":"Umarabad",
    "wof:placetype":"locality"
},
  "geometry": {"coordinates":[72.31161999999998,34.33573],"type":"Point"}
}