{
  "type": "Feature",
  "properties": {
    "gn:admin1_code":"2.0",
    "gn:asciiname":"Rozi",
    "gn:country_code":"PK",
    "gn:dem":983,
    "gn:feature_class":"P",
    "gn:feature_code":"PPL",
    "gn:name":"Rozi",
    "gn:population":0,
    "gn:timezone":"Asia/Karachi",
    "iso:country":"PK",
    "wof:name":"Rozi",
    "wof:placetype":"locality"
},
  "geometry": {"coordinates":[65.7197,28.811],"type":"Point"}
}