{
  "type": "Feature",
  "properties": {
    "gn:admin1_code":"3",
    "gn:asciiname":"Madhar",
    "gn:country_code":"PK",
    "gn:dem":2098,
    "gn:feature_class":"P",
    "gn:feature_code":"PPL",
    "gn:name":"Madhar",
    "gn:population":0,
    "gn:timezone":"Asia/Karachi",
    "iso:country":"PK",
    "name:und_x_variant":[
        "Madh\u0101r"
    ],
    "wof:name":"Madhar",
    "wof:placetype":"locality"
},
  "geometry": {"coordinates":[73.33726999999998,34.63629],"type":"Point"}
}