{
  "type": "Feature",
  "properties": {
    "gn:admin1_code":"4.0",
    "gn:asciiname":"Basti Dina",
    "gn:country_code":"PK",
    "gn:dem":901,
    "gn:feature_class":"P",
    "gn:feature_code":"PPL",
    "gn:name":"Basti Dina",
    "gn:population":0,
    "gn:timezone":"Asia/Karachi",
    "iso:country":"PK",
    "wof:name":"Basti Dina",
    "wof:placetype":"locality"
},
  "geometry": {"coordinates":[70.20914999999999,30.32595],"type":"Point"}
}