{
  "type": "Feature",
  "properties": {
    "gn:admin1_code":"4.0",
    "gn:asciiname":"Chak Bidia",
    "gn:country_code":"PK",
    "gn:dem":247,
    "gn:feature_class":"P",
    "gn:feature_code":"PPL",
    "gn:name":"Chak Bidia",
    "gn:population":0,
    "gn:timezone":"Asia/Karachi",
    "iso:country":"PK",
    "name:und_x_variant":[
        "Chak Baddia",
        "Chak Bidia"
    ],
    "wof:name":"Chak Bidia",
    "wof:placetype":"locality"
},
  "geometry": {"coordinates":[74.52658000000002,32.72975],"type":"Point"}
}