{
  "type": "Feature",
  "properties": {
    "gn:admin1_code":"3.0",
    "gn:asciiname":"Chhochang",
    "gn:country_code":"PK",
    "gn:dem":1060,
    "gn:feature_class":"P",
    "gn:feature_code":"PPL",
    "gn:name":"Chhochang",
    "gn:population":0,
    "gn:timezone":"Asia/Karachi",
    "iso:country":"PK",
    "wof:name":"Chhochang",
    "wof:placetype":"locality"
},
  "geometry": {"coordinates":[73.20434,35.29978],"type":"Point"}
}