{
  "type": "Feature",
  "properties": {
    "gn:admin1_code":"1.0",
    "gn:asciiname":"Tutki Mela",
    "gn:country_code":"PK",
    "gn:dem":2021,
    "gn:feature_class":"P",
    "gn:feature_code":"PPL",
    "gn:name":"Tutki Mela",
    "gn:population":0,
    "gn:timezone":"Asia/Karachi",
    "iso:country":"PK",
    "wof:name":"Tutki Mela",
    "wof:placetype":"locality"
},
  "geometry": {"coordinates":[70.01353,33.95847],"type":"Point"}
}