{
  "type": "Feature",
  "properties": {
    "gn:admin1_code":"5",
    "gn:asciiname":"Wazir Kerio",
    "gn:country_code":"PK",
    "gn:dem":50,
    "gn:feature_class":"P",
    "gn:feature_code":"PPL",
    "gn:name":"Wazir Kerio",
    "gn:population":0,
    "gn:timezone":"Asia/Karachi",
    "iso:country":"PK",
    "name:und_x_variant":[
        "Kab\u012br Kh\u0101n"
    ],
    "wof:name":"Wazir Kerio",
    "wof:placetype":"locality"
},
  "geometry": {"coordinates":[68.62130999999999,27.23973],"type":"Point"}
}