{
  "type": "Feature",
  "properties": {
    "gn:admin1_code":"4",
    "gn:asciiname":"Bunga Sudhiwala",
    "gn:country_code":"PK",
    "gn:dem":176,
    "gn:feature_class":"P",
    "gn:feature_code":"PPL",
    "gn:name":"Bunga Sudhiwala",
    "gn:population":0,
    "gn:timezone":"Asia/Karachi",
    "iso:country":"PK",
    "name:und_x_variant":[
        "Bonga Sodhiw\u0101la"
    ],
    "wof:name":"Bunga Sudhiwala",
    "wof:placetype":"locality"
},
  "geometry": {"coordinates":[73.78676,30.83229],"type":"Point"}
}