{
  "type": "Feature",
  "properties": {
    "gn:admin1_code":"4.0",
    "gn:asciiname":"Ali da Khu",
    "gn:country_code":"PK",
    "gn:dem":92,
    "gn:feature_class":"P",
    "gn:feature_code":"PPL",
    "gn:name":"Ali da Khu",
    "gn:population":0,
    "gn:timezone":"Asia/Karachi",
    "iso:country":"PK",
    "name:urd_x_preferred":[
        "Ali d\u0101 Khuh"
    ],
    "wof:name":"Ali da Khu",
    "wof:placetype":"locality"
},
  "geometry": {"coordinates":[70.62245,28.96025],"type":"Point"}
}