{
  "type": "Feature",
  "properties": {
    "gn:admin1_code":"4",
    "gn:asciiname":"Chakliyar",
    "gn:country_code":"PK",
    "gn:dem":129,
    "gn:feature_class":"P",
    "gn:feature_code":"PPL",
    "gn:name":"Chakliyar",
    "gn:population":0,
    "gn:timezone":"Asia/Karachi",
    "iso:country":"PK",
    "name:und_x_variant":[
        "Chak One Hundred Forty-two",
        "Chaklair",
        "Chakliyar"
    ],
    "wof:name":"Chakliyar",
    "wof:placetype":"locality"
},
  "geometry": {"coordinates":[71.99343,29.97583],"type":"Point"}
}