{
  "type": "Feature",
  "properties": {
    "gn:admin1_code":"6",
    "gn:asciiname":"Anhari",
    "gn:country_code":"PK",
    "gn:dem":1444,
    "gn:feature_class":"P",
    "gn:feature_code":"PPL",
    "gn:name":"Anhari",
    "gn:population":0,
    "gn:timezone":"Asia/Karachi",
    "iso:country":"PK",
    "name:und_x_variant":[
        "Nihari"
    ],
    "wof:name":"Anhari",
    "wof:placetype":"locality"
},
  "geometry": {"coordinates":[73.84065,33.75066],"type":"Point"}
}