{
  "type": "Feature",
  "properties": {
    "gn:admin1_code":"5.0",
    "gn:asciiname":"Goth Hisbani",
    "gn:country_code":"PK",
    "gn:dem":45,
    "gn:feature_class":"P",
    "gn:feature_code":"PPL",
    "gn:name":"Goth Hisbani",
    "gn:population":0,
    "gn:timezone":"Asia/Karachi",
    "iso:country":"PK",
    "name:und_x_variant":[
        "Goth Hisb\u0101n\u012b"
    ],
    "wof:name":"Goth Hisbani",
    "wof:placetype":"locality"
},
  "geometry": {"coordinates":[68.09796999999999,27.05775],"type":"Point"}
}