{
  "type": "Feature",
  "properties": {
    "gn:admin1_code":"4.0",
    "gn:asciiname":"Miro Khan Sangrani",
    "gn:country_code":"PK",
    "gn:dem":83,
    "gn:feature_class":"P",
    "gn:feature_code":"PPL",
    "gn:name":"Miro Khan Sangrani",
    "gn:population":0,
    "gn:timezone":"Asia/Karachi",
    "iso:country":"PK",
    "wof:name":"Miro Khan Sangrani",
    "wof:placetype":"locality"
},
  "geometry": {"coordinates":[69.9157,28.68545],"type":"Point"}
}