{
  "type": "Feature",
  "properties": {
    "gn:admin1_code":"3",
    "gn:asciiname":"Pumbazara",
    "gn:country_code":"PK",
    "gn:dem":1574,
    "gn:feature_class":"P",
    "gn:feature_code":"PPL",
    "gn:name":"Pumbazara",
    "gn:population":0,
    "gn:timezone":"Asia/Karachi",
    "iso:country":"PK",
    "wof:name":"Pumbazara",
    "wof:placetype":"locality"
},
  "geometry": {"coordinates":[72.01319000000002,34.87851],"type":"Point"}
}