{
  "type": "Feature",
  "properties": {
    "gn:admin1_code":"4.0",
    "gn:asciiname":"Dodhra",
    "gn:country_code":"PK",
    "gn:dem":219,
    "gn:feature_class":"P",
    "gn:feature_code":"PPL",
    "gn:name":"Dodhra",
    "gn:population":0,
    "gn:timezone":"Asia/Karachi",
    "iso:country":"PK",
    "name:und_x_variant":[
        "Dudrai"
    ],
    "wof:name":"Dodhra",
    "wof:placetype":"locality"
},
  "geometry": {"coordinates":[73.84215999999998,32.45434],"type":"Point"}
}