{
  "type": "Feature",
  "properties": {
    "gn:admin1_code":"01",
    "gn:asciiname":"Nawagai",
    "gn:country_code":"PK",
    "gn:dem":976,
    "gn:feature_class":"P",
    "gn:feature_code":"PPL",
    "gn:name":"Nawagai",
    "gn:population":0,
    "gn:timezone":"Asia/Karachi",
    "iso:country":"PK",
    "name:fas_x_preferred":[
        "\u0646\u0648\u0627\u06af\u0626\u06cc"
    ],
    "name:und_x_variant":[
        "Bara Nawagai"
    ],
    "wof:name":"Nawagai",
    "wof:placetype":"locality"
},
  "geometry": {"coordinates":[71.29156,34.66226],"type":"Point"}
}