{
  "type": "Feature",
  "properties": {
    "gn:admin1_code":"5.0",
    "gn:asciiname":"Bukhari",
    "gn:country_code":"PK",
    "gn:dem":24,
    "gn:feature_class":"P",
    "gn:feature_code":"PPL",
    "gn:name":"Bukhari",
    "gn:population":0,
    "gn:timezone":"Asia/Karachi",
    "iso:country":"PK",
    "name:ara_x_preferred":[
        "\u0628\u062e\u0627\u0631\u064a"
    ],
    "name:bak_x_preferred":[
        "\u0411\u043e\u0445\u0430\u0440\u0438"
    ],
    "name:rus_x_preferred":[
        "\u0411\u0443\u0445\u0430\u0440\u0438"
    ],
    "name:urd_x_preferred":[
        "\u0628\u062e\u0627\u0631\u06cc"
    ],
    "wof:name":"Bukhari",
    "wof:placetype":"locality"
},
  "geometry": {"coordinates":[68.56188,25.82657],"type":"Point"}
}