{
  "type": "Feature",
  "properties": {
    "gn:admin1_code":"3.0",
    "gn:asciiname":"Ghaligai",
    "gn:country_code":"PK",
    "gn:dem":832,
    "gn:feature_class":"P",
    "gn:feature_code":"PPL",
    "gn:name":"Ghaligai",
    "gn:population":0,
    "gn:timezone":"Asia/Karachi",
    "iso:country":"PK",
    "name:und_x_variant":[
        "Gh\u0101l\u012bgai"
    ],
    "wof:name":"Ghaligai",
    "wof:placetype":"locality"
},
  "geometry": {"coordinates":[72.25983000000002,34.6993],"type":"Point"}
}