{
  "type": "Feature",
  "properties": {
    "gn:admin1_code":"03",
    "gn:asciiname":"Muhammad Khel",
    "gn:cc2":"PK",
    "gn:country_code":"PK",
    "gn:dem":390,
    "gn:feature_class":"P",
    "gn:feature_code":"PPL",
    "gn:name":"Muhammad Khel",
    "gn:population":0,
    "gn:timezone":"Asia/Karachi",
    "iso:country":"PK",
    "name:und_x_variant":[
        "Mohammad Khel Wazir",
        "Sperka"
    ],
    "name:urd_x_preferred":[
        "\u0645\u062d\u0645\u062f \u062e\u06cc\u0644"
    ],
    "wof:name":"Muhammad Khel",
    "wof:placetype":"locality"
},
  "geometry": {"coordinates":[70.53333000000001,32.98333],"type":"Point"}
}