{
  "type": "Feature",
  "properties": {
    "gn:admin1_code":"03",
    "gn:asciiname":"Giro Banda",
    "gn:country_code":"PK",
    "gn:dem":728,
    "gn:feature_class":"P",
    "gn:feature_code":"PPL",
    "gn:name":"Giro Banda",
    "gn:population":0,
    "gn:timezone":"Asia/Karachi",
    "iso:country":"PK",
    "wof:name":"Giro Banda",
    "wof:placetype":"locality"
},
  "geometry": {"coordinates":[71.95111999999997,34.65373],"type":"Point"}
}