{
  "type": "Feature",
  "properties": {
    "gn:admin1_code":"05",
    "gn:asciiname":"Bale Khan Jamali",
    "gn:country_code":"PK",
    "gn:dem":6,
    "gn:feature_class":"P",
    "gn:feature_code":"PPL",
    "gn:name":"Bale Khan Jamali",
    "gn:population":0,
    "gn:timezone":"Asia/Karachi",
    "iso:country":"PK",
    "name:und_x_variant":[
        "Goth Baloch Kh\u0101n Jam\u0101li"
    ],
    "wof:name":"Bale Khan Jamali",
    "wof:placetype":"locality"
},
  "geometry": {"coordinates":[67.96533000000001,24.37887000000001],"type":"Point"}
}