{
  "type": "Feature",
  "properties": {
    "gn:admin1_code":"3.0",
    "gn:asciiname":"Dobash",
    "gn:country_code":"PK",
    "gn:dem":1636,
    "gn:feature_class":"P",
    "gn:feature_code":"PPL",
    "gn:name":"Dobash",
    "gn:population":0,
    "gn:timezone":"Asia/Karachi",
    "iso:country":"PK",
    "wof:name":"Dobash",
    "wof:placetype":"locality"
},
  "geometry": {"coordinates":[71.72799000000001,35.73932999999999],"type":"Point"}
}