{
  "type": "Feature",
  "properties": {
    "gn:admin1_code":"03",
    "gn:asciiname":"Sinpora",
    "gn:country_code":"PK",
    "gn:dem":1161,
    "gn:feature_class":"P",
    "gn:feature_code":"PPL",
    "gn:name":"Sinpora",
    "gn:population":0,
    "gn:timezone":"Asia/Karachi",
    "iso:country":"PK",
    "name:und_x_variant":[
        "Sinpura",
        "Sinpora"
    ],
    "wof:name":"Sinpora",
    "wof:placetype":"locality"
},
  "geometry": {"coordinates":[72.38198,34.94906],"type":"Point"}
}