{
  "type": "Feature",
  "properties": {
    "gn:admin1_code":"4.0",
    "gn:asciiname":"Kit",
    "gn:country_code":"PK",
    "gn:dem":210,
    "gn:feature_class":"P",
    "gn:feature_code":"PPL",
    "gn:name":"Kit",
    "gn:population":0,
    "gn:timezone":"Asia/Karachi",
    "iso:country":"PK",
    "name:ceb_x_preferred":[
        "Kit"
    ],
    "name:deu_x_preferred":[
        "Kit"
    ],
    "name:eus_x_preferred":[
        "Kit"
    ],
    "name:fra_x_preferred":[
        "Kit"
    ],
    "name:hrv_x_preferred":[
        "Kit"
    ],
    "name:nld_x_preferred":[
        "Kit"
    ],
    "name:spa_x_preferred":[
        "Kit"
    ],
    "name:swe_x_preferred":[
        "Kit"
    ],
    "name:und_x_variant":[
        "K\u012bt"
    ],
    "name:uzb_x_preferred":[
        "Kit"
    ],
    "wof:name":"Kit",
    "wof:placetype":"locality"
},
  "geometry": {"coordinates":[74.41216,31.29371],"type":"Point"}
}