{
  "type": "Feature",
  "properties": {
    "gn:admin1_code":"4",
    "gn:asciiname":"Chak One Hundred Thirty-four -Sixteen Left",
    "gn:country_code":"PK",
    "gn:dem":143,
    "gn:feature_class":"P",
    "gn:feature_code":"PPL",
    "gn:name":"Chak One Hundred Thirty-four -Sixteen Left",
    "gn:population":0,
    "gn:timezone":"Asia/Karachi",
    "iso:country":"PK",
    "name:und_x_variant":[
        "Chak One Hundred Thirty-Four-Sixteen L",
        "\u012as\u0101i\u0101n",
        "Piran Singh",
        "Chak One Hundred Thirty-four -Sixteen Left",
        "Issai\u0101nw\u0101la"
    ],
    "wof:name":"Chak One Hundred Thirty-four -Sixteen Left",
    "wof:placetype":"locality"
},
  "geometry": {"coordinates":[72.25034000000002,30.38629],"type":"Point"}
}