{
  "type": "Feature",
  "properties": {
    "gn:admin1_code":"3.0",
    "gn:asciiname":"Lilownai",
    "gn:country_code":"PK",
    "gn:dem":1610,
    "gn:feature_class":"P",
    "gn:feature_code":"PPL",
    "gn:name":"Lilownai",
    "gn:population":0,
    "gn:timezone":"Asia/Karachi",
    "iso:country":"PK",
    "wof:name":"Lilownai",
    "wof:placetype":"locality"
},
  "geometry": {"coordinates":[72.64390999999998,34.95630999999999],"type":"Point"}
}