{
  "type": "Feature",
  "properties": {
    "gn:admin1_code":"5.0",
    "gn:asciiname":"Muhammad Sumar",
    "gn:country_code":"PK",
    "gn:dem":10,
    "gn:feature_class":"P",
    "gn:feature_code":"PPL",
    "gn:name":"Muhammad Sumar",
    "gn:population":0,
    "gn:timezone":"Asia/Karachi",
    "iso:country":"PK",
    "name:eng_x_preferred":[
        "Muhammad Sumar"
    ],
    "wof:name":"Muhammad Sumar",
    "wof:placetype":"locality"
},
  "geometry": {"coordinates":[68.37919000000001,24.68188],"type":"Point"}
}