{
  "type": "Feature",
  "properties": {
    "gn:admin1_code":"4.0",
    "gn:asciiname":"Chak One Hundred Four Jhang Branch",
    "gn:country_code":"PK",
    "gn:dem":192,
    "gn:feature_class":"P",
    "gn:feature_code":"PPL",
    "gn:name":"Chak One Hundred Four Jhang Branch",
    "gn:population":0,
    "gn:timezone":"Asia/Karachi",
    "iso:country":"PK",
    "name:und_x_variant":[
        "Chak One Hundred Four",
        "Harmoha",
        "Chak One Hundred Four Jhang Branch",
        "Harmui\u0101n"
    ],
    "wof:name":"Chak One Hundred Four Jhang Branch",
    "wof:placetype":"locality"
},
  "geometry": {"coordinates":[73.08323,31.62375],"type":"Point"}
}