{
  "type": "Feature",
  "properties": {
    "gn:admin1_code":"4",
    "gn:asciiname":"Dhok Burj",
    "gn:country_code":"PK",
    "gn:dem":251,
    "gn:feature_class":"P",
    "gn:feature_code":"PPL",
    "gn:name":"Dhok Burj",
    "gn:population":0,
    "gn:timezone":"Asia/Karachi",
    "iso:country":"PK",
    "name:und_x_variant":[
        "Dhok Baruj"
    ],
    "wof:name":"Dhok Burj",
    "wof:placetype":"locality"
},
  "geometry": {"coordinates":[72.79281999999998,32.63786],"type":"Point"}
}