{
  "type": "Feature",
  "properties": {
    "gn:admin1_code":"2.0",
    "gn:asciiname":"Kili Khuda Bakhsh",
    "gn:country_code":"PK",
    "gn:dem":1201,
    "gn:feature_class":"P",
    "gn:feature_code":"PPL",
    "gn:name":"Kili Khuda Bakhsh",
    "gn:population":0,
    "gn:timezone":"Asia/Karachi",
    "iso:country":"PK",
    "wof:name":"Kili Khuda Bakhsh",
    "wof:placetype":"locality"
},
  "geometry": {"coordinates":[65.8412,29.09551],"type":"Point"}
}