{
  "type": "Feature",
  "properties": {
    "gn:admin1_code":"4.0",
    "gn:asciiname":"Basui",
    "gn:country_code":"PK",
    "gn:dem":776,
    "gn:feature_class":"P",
    "gn:feature_code":"PPL",
    "gn:name":"Basui",
    "gn:population":0,
    "gn:timezone":"Asia/Karachi",
    "iso:country":"PK",
    "name:eng_x_preferred":[
        "Basol"
    ],
    "wof:name":"Basui",
    "wof:placetype":"locality"
},
  "geometry": {"coordinates":[73.25537,33.81323],"type":"Point"}
}