{
  "type": "Feature",
  "properties": {
    "gn:admin1_code":"2.0",
    "gn:asciiname":"Goth Muhammad Khan",
    "gn:country_code":"PK",
    "gn:dem":266,
    "gn:feature_class":"P",
    "gn:feature_code":"PPL",
    "gn:name":"Goth Muhammad Khan",
    "gn:population":0,
    "gn:timezone":"Asia/Karachi",
    "iso:country":"PK",
    "wof:name":"Goth Muhammad Khan",
    "wof:placetype":"locality"
},
  "geometry": {"coordinates":[67.34515999999999,25.81521],"type":"Point"}
}