{
  "type": "Feature",
  "properties": {
    "gn:admin1_code":"3",
    "gn:asciiname":"Dhero Banda",
    "gn:country_code":"PK",
    "gn:dem":741,
    "gn:feature_class":"P",
    "gn:feature_code":"PPL",
    "gn:name":"Dhero Banda",
    "gn:population":0,
    "gn:timezone":"Asia/Karachi",
    "iso:country":"PK",
    "wof:name":"Dhero Banda",
    "wof:placetype":"locality"
},
  "geometry": {"coordinates":[72.65184000000001,34.21333],"type":"Point"}
}