{
  "type": "Feature",
  "properties": {
    "gn:admin1_code":"6",
    "gn:asciiname":"Hari Dhara",
    "gn:country_code":"PK",
    "gn:dem":1323,
    "gn:feature_class":"P",
    "gn:feature_code":"PPL",
    "gn:name":"Hari Dhara",
    "gn:population":0,
    "gn:timezone":"Asia/Karachi",
    "iso:country":"PK",
    "wof:name":"Hari Dhara",
    "wof:placetype":"locality"
},
  "geometry": {"coordinates":[74.05278,33.56111],"type":"Point"}
}