{
  "type": "Feature",
  "properties": {
    "gn:admin1_code":"05",
    "gn:asciiname":"Goth Mohana",
    "gn:country_code":"PK",
    "gn:dem":7,
    "gn:feature_class":"P",
    "gn:feature_code":"PPL",
    "gn:name":"Goth Mohana",
    "gn:population":0,
    "gn:timezone":"Asia/Karachi",
    "iso:country":"PK",
    "name:und_x_variant":[
        "Goth Mah\u0101na"
    ],
    "wof:name":"Goth Mohana",
    "wof:placetype":"locality"
},
  "geometry": {"coordinates":[67.98195,24.27423],"type":"Point"}
}