{
  "type": "Feature",
  "properties": {
    "gn:admin1_code":"4.0",
    "gn:asciiname":"Awanpur",
    "gn:country_code":"PK",
    "gn:dem":517,
    "gn:feature_class":"P",
    "gn:feature_code":"PPL",
    "gn:name":"Awanpur",
    "gn:population":0,
    "gn:timezone":"Asia/Karachi",
    "iso:country":"PK",
    "wof:name":"Awanpur",
    "wof:placetype":"locality"
},
  "geometry": {"coordinates":[72.61591,33.57080999999999],"type":"Point"}
}