{
  "type": "Feature",
  "properties": {
    "gn:admin1_code":"2.0",
    "gn:asciiname":"Ragho Sapna",
    "gn:country_code":"PK",
    "gn:dem":840,
    "gn:feature_class":"P",
    "gn:feature_code":"PPL",
    "gn:name":"Ragho Sapna",
    "gn:population":0,
    "gn:timezone":"Asia/Karachi",
    "iso:country":"PK",
    "wof:name":"Ragho Sapna",
    "wof:placetype":"locality"
},
  "geometry": {"coordinates":[70.15437,31.35924],"type":"Point"}
}