{
  "type": "Feature",
  "properties": {
    "gn:admin1_code":"05",
    "gn:asciiname":"Goth Tor",
    "gn:country_code":"PK",
    "gn:dem":54,
    "gn:feature_class":"P",
    "gn:feature_code":"PPL",
    "gn:name":"Goth Tor",
    "gn:population":0,
    "gn:timezone":"Asia/Karachi",
    "iso:country":"PK",
    "name:und_x_variant":[
        "To",
        "Tor",
        "Goth Tor"
    ],
    "wof:name":"Goth Tor",
    "wof:placetype":"locality"
},
  "geometry": {"coordinates":[67.42455,26.96165],"type":"Point"}
}