{
  "type": "Feature",
  "properties": {
    "gn:admin1_code":"4.0",
    "gn:asciiname":"Bhangi Khel",
    "gn:country_code":"PK",
    "gn:dem":506,
    "gn:feature_class":"P",
    "gn:feature_code":"PPL",
    "gn:name":"Bhangi Khel",
    "gn:population":0,
    "gn:timezone":"Asia/Karachi",
    "iso:country":"PK",
    "name:und_x_variant":[
        "Bangi Khel"
    ],
    "wof:name":"Bhangi Khel",
    "wof:placetype":"locality"
},
  "geometry": {"coordinates":[71.59153000000001,33.18548],"type":"Point"}
}