{
  "type": "Feature",
  "properties": {
    "gn:admin1_code":"4.0",
    "gn:asciiname":"Islampur",
    "gn:country_code":"PK",
    "gn:dem":164,
    "gn:feature_class":"P",
    "gn:feature_code":"PPL",
    "gn:name":"Islampur",
    "gn:population":0,
    "gn:timezone":"Asia/Karachi",
    "iso:country":"PK",
    "wof:name":"Islampur",
    "wof:placetype":"locality"
},
  "geometry": {"coordinates":[73.49795,30.18346],"type":"Point"}
}