{
  "type": "Feature",
  "properties": {
    "gn:admin1_code":"4",
    "gn:asciiname":"Chak Seven Hundred Fifty Gugera Branch",
    "gn:country_code":"PK",
    "gn:dem":146,
    "gn:feature_class":"P",
    "gn:feature_code":"PPL",
    "gn:name":"Chak Seven Hundred Fifty Gugera Branch",
    "gn:population":0,
    "gn:timezone":"Asia/Karachi",
    "iso:country":"PK",
    "name:und_x_variant":[
        "Chak Seven Hundred Fifty"
    ],
    "wof:name":"Chak Seven Hundred Fifty Gugera Branch",
    "wof:placetype":"locality"
},
  "geometry": {"coordinates":[72.39134,30.65492],"type":"Point"}
}