{
  "type": "Feature",
  "properties": {
    "gn:admin1_code":"5.0",
    "gn:asciiname":"Goth Kando Sumro",
    "gn:country_code":"PK",
    "gn:dem":31,
    "gn:feature_class":"P",
    "gn:feature_code":"PPL",
    "gn:name":"Goth Kando Sumro",
    "gn:population":0,
    "gn:timezone":"Asia/Karachi",
    "iso:country":"PK",
    "wof:name":"Goth Kando Sumro",
    "wof:placetype":"locality"
},
  "geometry": {"coordinates":[69.45126999999999,24.79134],"type":"Point"}
}