{
  "type": "Feature",
  "properties": {
    "gn:admin1_code":"1.0",
    "gn:asciiname":"Chamba",
    "gn:country_code":"PK",
    "gn:dem":383,
    "gn:feature_class":"P",
    "gn:feature_code":"PPL",
    "gn:name":"Chamba",
    "gn:population":0,
    "gn:timezone":"Asia/Karachi",
    "iso:country":"PK",
    "wof:name":"Chamba",
    "wof:placetype":"locality"
},
  "geometry": {"coordinates":[73.74236999999999,33.163],"type":"Point"}
}