{
  "type": "Feature",
  "properties": {
    "gn:admin1_code":"4",
    "gn:asciiname":"Bhuttewala",
    "gn:country_code":"PK",
    "gn:dem":129,
    "gn:feature_class":"P",
    "gn:feature_code":"PPL",
    "gn:name":"Bhuttew\u0101la",
    "gn:population":0,
    "gn:timezone":"Asia/Karachi",
    "iso:country":"PK",
    "name:eng_x_preferred":[
        "Bhuttew\u0101la"
    ],
    "wof:name":"Bhuttewala",
    "wof:placetype":"locality"
},
  "geometry": {"coordinates":[70.87921,30.2773],"type":"Point"}
}