{
  "type": "Feature",
  "properties": {
    "gn:admin1_code":"2.0",
    "gn:asciiname":"Srawate",
    "gn:country_code":"PK",
    "gn:dem":2194,
    "gn:feature_class":"P",
    "gn:feature_code":"PPL",
    "gn:name":"Srawate",
    "gn:population":0,
    "gn:timezone":"Asia/Karachi",
    "iso:country":"PK",
    "name:und_x_variant":[
        "Sraw\u0101te"
    ],
    "wof:name":"Srawate",
    "wof:placetype":"locality"
},
  "geometry": {"coordinates":[69.7206,31.59421],"type":"Point"}
}