{
  "type": "Feature",
  "properties": {
    "gn:admin1_code":"7.0",
    "gn:asciiname":"Ratul",
    "gn:country_code":"PK",
    "gn:dem":2744,
    "gn:feature_class":"P",
    "gn:feature_code":"PPL",
    "gn:name":"Ratul",
    "gn:population":0,
    "gn:timezone":"Asia/Karachi",
    "iso:country":"PK",
    "wof:name":"Ratul",
    "wof:placetype":"locality"
},
  "geometry": {"coordinates":[74.75723000000001,36.22724],"type":"Point"}
}