{
  "type": "Feature",
  "properties": {
    "gn:admin1_code":"2",
    "gn:asciiname":"Korachao",
    "gn:country_code":"PK",
    "gn:dem":1637,
    "gn:feature_class":"P",
    "gn:feature_code":"PPL",
    "gn:name":"Korachao",
    "gn:population":0,
    "gn:timezone":"Asia/Karachi",
    "iso:country":"PK",
    "wof:name":"Korachao",
    "wof:placetype":"locality"
},
  "geometry": {"coordinates":[66.23194000000001,28.06944],"type":"Point"}
}