{
  "type": "Feature",
  "properties": {
    "gn:admin1_code":"6",
    "gn:asciiname":"Paniali",
    "gn:country_code":"PK",
    "gn:dem":822,
    "gn:feature_class":"P",
    "gn:feature_code":"PPL",
    "gn:name":"Paniali",
    "gn:population":0,
    "gn:timezone":"Asia/Karachi",
    "iso:country":"PK",
    "wof:name":"Paniali",
    "wof:placetype":"locality"
},
  "geometry": {"coordinates":[73.49729000000001,34.17049],"type":"Point"}
}