{
  "type": "Feature",
  "properties": {
    "gn:admin1_code":"2.0",
    "gn:asciiname":"Goth Burra",
    "gn:country_code":"PK",
    "gn:dem":53,
    "gn:feature_class":"P",
    "gn:feature_code":"PPL",
    "gn:name":"Goth Burra",
    "gn:population":0,
    "gn:timezone":"Asia/Karachi",
    "iso:country":"PK",
    "wof:name":"Goth Burra",
    "wof:placetype":"locality"
},
  "geometry": {"coordinates":[67.68624,28.10047],"type":"Point"}
}