{
  "type": "Feature",
  "properties": {
    "gn:admin1_code":"01",
    "gn:asciiname":"Gido",
    "gn:country_code":"PK",
    "gn:dem":942,
    "gn:feature_class":"P",
    "gn:feature_code":"PPL",
    "gn:name":"Gido",
    "gn:population":0,
    "gn:timezone":"Asia/Karachi",
    "iso:country":"PK",
    "name:und_x_variant":[
        "Gidow"
    ],
    "wof:name":"Gido",
    "wof:placetype":"locality"
},
  "geometry": {"coordinates":[71.64579999999999,34.58045],"type":"Point"}
}