{
  "type": "Feature",
  "properties": {
    "gn:admin1_code":"3.0",
    "gn:asciiname":"Sirki Khel",
    "gn:country_code":"PK",
    "gn:dem":359,
    "gn:feature_class":"P",
    "gn:feature_code":"PPL",
    "gn:name":"Sirki Khel",
    "gn:population":0,
    "gn:timezone":"Asia/Karachi",
    "iso:country":"PK",
    "wof:name":"Sirki Khel",
    "wof:placetype":"locality"
},
  "geometry": {"coordinates":[70.89858000000002,32.89138],"type":"Point"}
}