{
  "type": "Feature",
  "properties": {
    "gn:admin1_code":"01",
    "gn:asciiname":"Zangai",
    "gn:country_code":"PK",
    "gn:dem":2117,
    "gn:feature_class":"P",
    "gn:feature_code":"PPL",
    "gn:name":"Zangai",
    "gn:population":0,
    "gn:timezone":"Asia/Karachi",
    "iso:country":"PK",
    "name:und_x_variant":[
        "Zangi"
    ],
    "wof:name":"Zangai",
    "wof:placetype":"locality"
},
  "geometry": {"coordinates":[70.59063,33.83169],"type":"Point"}
}