{
  "type": "Feature",
  "properties": {
    "gn:admin1_code":"7.0",
    "gn:asciiname":"Saralokhutu",
    "gn:country_code":"PK",
    "gn:dem":2451,
    "gn:feature_class":"P",
    "gn:feature_code":"PPL",
    "gn:name":"Saralokhutu",
    "gn:population":0,
    "gn:timezone":"Asia/Karachi",
    "iso:country":"PK",
    "name:und_x_variant":[
        "Bar\u0101lokhutu"
    ],
    "wof:name":"Saralokhutu",
    "wof:placetype":"locality"
},
  "geometry": {"coordinates":[73.20050999999999,36.18503],"type":"Point"}
}