{
  "type": "Feature",
  "properties": {
    "gn:admin1_code":"1.0",
    "gn:asciiname":"Saddique Koruna",
    "gn:country_code":"PK",
    "gn:dem":816,
    "gn:feature_class":"P",
    "gn:feature_code":"PPL",
    "gn:name":"Saddique Koruna",
    "gn:population":0,
    "gn:timezone":"Asia/Karachi",
    "iso:country":"PK",
    "wof:name":"Saddique Koruna",
    "wof:placetype":"locality"
},
  "geometry": {"coordinates":[71.50801,34.58458],"type":"Point"}
}