{
  "type": "Feature",
  "properties": {
    "gn:admin1_code":"2",
    "gn:asciiname":"Khadar China Kili",
    "gn:country_code":"PK",
    "gn:dem":1635,
    "gn:feature_class":"P",
    "gn:feature_code":"PPL",
    "gn:name":"Khadar China Kili",
    "gn:population":0,
    "gn:timezone":"Asia/Karachi",
    "iso:country":"PK",
    "wof:name":"Khadar China Kili",
    "wof:placetype":"locality"
},
  "geometry": {"coordinates":[69.20517,30.82435],"type":"Point"}
}