{
  "type": "Feature",
  "properties": {
    "gn:admin1_code":"3",
    "gn:asciiname":"Bahram Darra",
    "gn:country_code":"PK",
    "gn:dem":2225,
    "gn:feature_class":"P",
    "gn:feature_code":"PPL",
    "gn:name":"Bahram Darra",
    "gn:population":0,
    "gn:timezone":"Asia/Karachi",
    "iso:country":"PK",
    "wof:name":"Bahram Darra",
    "wof:placetype":"locality"
},
  "geometry": {"coordinates":[72.61866999999999,34.79705],"type":"Point"}
}