{
  "type": "Feature",
  "properties": {
    "gn:admin1_code":"3.0",
    "gn:asciiname":"Baja",
    "gn:country_code":"PK",
    "gn:dem":1433,
    "gn:feature_class":"P",
    "gn:feature_code":"PPL",
    "gn:name":"Baja",
    "gn:population":0,
    "gn:timezone":"Asia/Karachi",
    "iso:country":"PK",
    "wof:name":"Baja",
    "wof:placetype":"locality"
},
  "geometry": {"coordinates":[73.26414,35.17899],"type":"Point"}
}