{
  "type": "Feature",
  "properties": {
    "gn:admin1_code":"3.0",
    "gn:asciiname":"Thur",
    "gn:country_code":"PK",
    "gn:dem":1555,
    "gn:feature_class":"P",
    "gn:feature_code":"PPL",
    "gn:name":"Thur",
    "gn:population":0,
    "gn:timezone":"Asia/Karachi",
    "iso:country":"PK",
    "wof:name":"Thur",
    "wof:placetype":"locality"
},
  "geometry": {"coordinates":[73.13172,34.68881],"type":"Point"}
}