{
  "type": "Feature",
  "properties": {
    "gn:admin1_code":"05",
    "gn:asciiname":"Goth Shekhani",
    "gn:country_code":"PK",
    "gn:dem":52,
    "gn:feature_class":"P",
    "gn:feature_code":"PPL",
    "gn:name":"Goth Shekhani",
    "gn:population":0,
    "gn:timezone":"Asia/Karachi",
    "iso:country":"PK",
    "name:und_x_variant":[
        "Shaikhani",
        "Goth Shekhani",
        "Shekh\u0101ni"
    ],
    "wof:name":"Goth Shekhani",
    "wof:placetype":"locality"
},
  "geometry": {"coordinates":[68.2196,27.18483],"type":"Point"}
}