{
  "type": "Feature",
  "properties": {
    "gn:admin1_code":"4.0",
    "gn:asciiname":"Thatti Jaya",
    "gn:country_code":"PK",
    "gn:dem":184,
    "gn:feature_class":"P",
    "gn:feature_code":"PPL",
    "gn:name":"Thatti Jaya",
    "gn:population":0,
    "gn:timezone":"Asia/Karachi",
    "iso:country":"PK",
    "name:und_x_variant":[
        "Thatti Joya"
    ],
    "wof:name":"Thatti Jaya",
    "wof:placetype":"locality"
},
  "geometry": {"coordinates":[72.29406999999998,32.19742],"type":"Point"}
}