{
  "type": "Feature",
  "properties": {
    "gn:admin1_code":"5",
    "gn:asciiname":"Ghulam Haider Dumbki",
    "gn:country_code":"PK",
    "gn:dem":71,
    "gn:feature_class":"P",
    "gn:feature_code":"PPL",
    "gn:name":"Ghulam Haider Dumbki",
    "gn:population":0,
    "gn:timezone":"Asia/Karachi",
    "iso:country":"PK",
    "name:und_x_variant":[
        "Ghulam Hussain Domki"
    ],
    "wof:name":"Ghulam Haider Dumbki",
    "wof:placetype":"locality"
},
  "geometry": {"coordinates":[69.29299,28.39722],"type":"Point"}
}