{
  "type": "Feature",
  "properties": {
    "gn:admin1_code":"4",
    "gn:asciiname":"Khirkiwala",
    "gn:country_code":"PK",
    "gn:dem":131,
    "gn:feature_class":"P",
    "gn:feature_code":"PPL",
    "gn:name":"Khirkiwala",
    "gn:population":0,
    "gn:timezone":"Asia/Karachi",
    "iso:country":"PK",
    "name:eng_x_preferred":[
        "Khirk\u012bw\u0101la"
    ],
    "wof:name":"Khirkiwala",
    "wof:placetype":"locality"
},
  "geometry": {"coordinates":[70.94641,30.45081],"type":"Point"}
}