{
  "type": "Feature",
  "properties": {
    "gn:admin1_code":"5.0",
    "gn:asciiname":"Goth Allah Dina",
    "gn:country_code":"PK",
    "gn:dem":14,
    "gn:feature_class":"P",
    "gn:feature_code":"PPL",
    "gn:name":"Goth Allah Dina",
    "gn:population":0,
    "gn:timezone":"Asia/Karachi",
    "iso:country":"PK",
    "name:und_x_variant":[
        "K\u0101ndara"
    ],
    "wof:name":"Goth Allah Dina",
    "wof:placetype":"locality"
},
  "geometry": {"coordinates":[68.19319,24.77896],"type":"Point"}
}