{
  "type": "Feature",
  "properties": {
    "gn:admin1_code":"2",
    "gn:asciiname":"Chauki",
    "gn:country_code":"PK",
    "gn:dem":1523,
    "gn:feature_class":"P",
    "gn:feature_code":"PPL",
    "gn:name":"Chauki",
    "gn:population":0,
    "gn:timezone":"Asia/Karachi",
    "iso:country":"PK",
    "wof:name":"Chauki",
    "wof:placetype":"locality"
},
  "geometry": {"coordinates":[69.01666999999999,30.81667],"type":"Point"}
}