{
  "type": "Feature",
  "properties": {
    "gn:admin1_code":"4",
    "gn:asciiname":"Waddi Basti",
    "gn:country_code":"PK",
    "gn:dem":124,
    "gn:feature_class":"P",
    "gn:feature_code":"PPL",
    "gn:name":"Waddi Basti",
    "gn:population":0,
    "gn:timezone":"Asia/Karachi",
    "iso:country":"PK",
    "name:und_x_variant":[
        "Basti H\u0101du",
        "Basti K\u0101du",
        "Basti Malikw\u0101li",
        "Waddi Basti",
        "Basti Allu",
        "Malikw\u0101li"
    ],
    "wof:name":"Waddi Basti",
    "wof:placetype":"locality"
},
  "geometry": {"coordinates":[70.33965999999999,29.57639],"type":"Point"}
}