{
  "type": "Feature",
  "properties": {
    "gn:admin1_code":"4",
    "gn:asciiname":"Dhok Mohsin Ali",
    "gn:country_code":"PK",
    "gn:dem":532,
    "gn:feature_class":"P",
    "gn:feature_code":"PPL",
    "gn:name":"Dhok Mohsin Ali",
    "gn:population":0,
    "gn:timezone":"Asia/Karachi",
    "iso:country":"PK",
    "name:und_x_variant":[
        "Dhok B\u0101ba Mosa"
    ],
    "wof:name":"Dhok Mohsin Ali",
    "wof:placetype":"locality"
},
  "geometry": {"coordinates":[73.16275,33.03258],"type":"Point"}
}