{
  "type": "Feature",
  "properties": {
    "gn:admin1_code":"5",
    "gn:asciiname":"Goth Muhammad Lark",
    "gn:country_code":"PK",
    "gn:dem":60,
    "gn:feature_class":"P",
    "gn:feature_code":"PPL",
    "gn:name":"Goth Muhammad Lark",
    "gn:population":0,
    "gn:timezone":"Asia/Karachi",
    "iso:country":"PK",
    "name:und_x_variant":[
        "L\u0101rka"
    ],
    "wof:name":"Goth Muhammad Lark",
    "wof:placetype":"locality"
},
  "geometry": {"coordinates":[68.46389000000001,27.52063],"type":"Point"}
}