{
  "type": "Feature",
  "properties": {
    "gn:admin1_code":"3.0",
    "gn:asciiname":"Jal Baihk",
    "gn:country_code":"PK",
    "gn:dem":3843,
    "gn:feature_class":"P",
    "gn:feature_code":"PPL",
    "gn:name":"Jal Baihk",
    "gn:population":0,
    "gn:timezone":"Asia/Karachi",
    "iso:country":"PK",
    "wof:name":"Jal Baihk",
    "wof:placetype":"locality"
},
  "geometry": {"coordinates":[73.45753000000001,35.38405],"type":"Point"}
}