{
  "type": "Feature",
  "properties": {
    "gn:admin1_code":"3.0",
    "gn:asciiname":"Qazi Bela",
    "gn:country_code":"PK",
    "gn:dem":1060,
    "gn:feature_class":"P",
    "gn:feature_code":"PPL",
    "gn:name":"Qazi Bela",
    "gn:population":0,
    "gn:timezone":"Asia/Karachi",
    "iso:country":"PK",
    "wof:name":"Qazi Bela",
    "wof:placetype":"locality"
},
  "geometry": {"coordinates":[73.2928,34.45579],"type":"Point"}
}