{
  "type": "Feature",
  "properties": {
    "gn:admin1_code":"04",
    "gn:asciiname":"Surg",
    "gn:country_code":"PK",
    "gn:dem":386,
    "gn:feature_class":"P",
    "gn:feature_code":"PPL",
    "gn:name":"Surg",
    "gn:population":0,
    "gn:timezone":"Asia/Karachi",
    "iso:country":"PK",
    "name:und_x_variant":[
        "Surg Salar",
        "Surg"
    ],
    "wof:name":"Surg",
    "wof:placetype":"locality"
},
  "geometry": {"coordinates":[72.25969000000001,33.70666],"type":"Point"}
}