{
  "type": "Feature",
  "properties": {
    "gn:admin1_code":"5.0",
    "gn:asciiname":"Goth Muhammad Yusuf Chandio",
    "gn:country_code":"PK",
    "gn:dem":9,
    "gn:feature_class":"P",
    "gn:feature_code":"PPL",
    "gn:name":"Goth Muhammad Yusuf Chandio",
    "gn:population":0,
    "gn:timezone":"Asia/Karachi",
    "iso:country":"PK",
    "name:und_x_variant":[
        "Muhammad Y\u016bsuf Ch\u0101ndio"
    ],
    "wof:name":"Goth Muhammad Yusuf Chandio",
    "wof:placetype":"locality"
},
  "geometry": {"coordinates":[68.05806,24.32978],"type":"Point"}
}