{
  "type": "Feature",
  "properties": {
    "gn:admin1_code":"1.0",
    "gn:asciiname":"Gul Salam Kot",
    "gn:country_code":"PK",
    "gn:dem":2137,
    "gn:feature_class":"P",
    "gn:feature_code":"PPL",
    "gn:name":"Gul Salam Kot",
    "gn:population":0,
    "gn:timezone":"Asia/Karachi",
    "iso:country":"PK",
    "wof:name":"Gul Salam Kot",
    "wof:placetype":"locality"
},
  "geometry": {"coordinates":[69.43625,32.78015],"type":"Point"}
}