{
  "type": "Feature",
  "properties": {
    "gn:admin1_code":"5.0",
    "gn:asciiname":"Gujri Chak One",
    "gn:country_code":"PK",
    "gn:dem":25,
    "gn:feature_class":"P",
    "gn:feature_code":"PPL",
    "gn:name":"Gujri Chak One",
    "gn:population":0,
    "gn:timezone":"Asia/Karachi",
    "iso:country":"PK",
    "name:und_x_variant":[
        "Gujhri Bhit",
        "Gujri",
        "Gujri Chak One"
    ],
    "wof:name":"Gujri Chak One",
    "wof:placetype":"locality"
},
  "geometry": {"coordinates":[68.96696999999999,26.19114],"type":"Point"}
}