{
  "type": "Feature",
  "properties": {
    "gn:admin1_code":"3",
    "gn:asciiname":"Kalau",
    "gn:country_code":"PK",
    "gn:dem":2268,
    "gn:feature_class":"P",
    "gn:feature_code":"PPL",
    "gn:name":"Kalau",
    "gn:population":0,
    "gn:timezone":"Asia/Karachi",
    "iso:country":"PK",
    "name:und_x_variant":[
        "Kalaur",
        "Kalau"
    ],
    "wof:name":"Kalau",
    "wof:placetype":"locality"
},
  "geometry": {"coordinates":[72.60897,34.78237],"type":"Point"}
}