{
  "type": "Feature",
  "properties": {
    "gn:admin1_code":"5",
    "gn:asciiname":"Goth Haji Karim",
    "gn:country_code":"PK",
    "gn:dem":11,
    "gn:feature_class":"P",
    "gn:feature_code":"PPL",
    "gn:name":"Goth Haji Karim",
    "gn:population":0,
    "gn:timezone":"Asia/Karachi",
    "iso:country":"PK",
    "name:und_x_variant":[
        "Abdul Kar\u012bm Pali"
    ],
    "wof:name":"Goth Haji Karim",
    "wof:placetype":"locality"
},
  "geometry": {"coordinates":[69.59875,25.28561],"type":"Point"}
}