{
  "type": "Feature",
  "properties": {
    "gn:admin1_code":"2.0",
    "gn:asciiname":"Abdul Rahim Kili",
    "gn:country_code":"PK",
    "gn:dem":1805,
    "gn:feature_class":"P",
    "gn:feature_code":"PPL",
    "gn:name":"Abdul Rahim Kili",
    "gn:population":0,
    "gn:timezone":"Asia/Karachi",
    "iso:country":"PK",
    "name:und_x_variant":[
        "Abdur Rah\u012bm Kili"
    ],
    "wof:name":"Abdul Rahim Kili",
    "wof:placetype":"locality"
},
  "geometry": {"coordinates":[69.09321,31.51572],"type":"Point"}
}