{
  "type": "Feature",
  "properties": {
    "gn:admin1_code":"3.0",
    "gn:asciiname":"Dairuwaini",
    "gn:country_code":"PK",
    "gn:dem":3285,
    "gn:feature_class":"P",
    "gn:feature_code":"PPL",
    "gn:name":"Dairuwaini",
    "gn:population":0,
    "gn:timezone":"Asia/Karachi",
    "iso:country":"PK",
    "wof:name":"Dairuwaini",
    "wof:placetype":"locality"
},
  "geometry": {"coordinates":[71.57956,36.29125],"type":"Point"}
}