{
  "type": "Feature",
  "properties": {
    "gn:admin1_code":"3.0",
    "gn:asciiname":"Saghri Chashmai",
    "gn:country_code":"PK",
    "gn:dem":602,
    "gn:feature_class":"P",
    "gn:feature_code":"PPL",
    "gn:name":"Saghri Chashmai",
    "gn:population":0,
    "gn:timezone":"Asia/Karachi",
    "iso:country":"PK",
    "wof:name":"Saghri Chashmai",
    "wof:placetype":"locality"
},
  "geometry": {"coordinates":[71.61400999999999,33.15883],"type":"Point"}
}