{
  "type": "Feature",
  "properties": {
    "gn:country":"PK",
    "gn:fcode":"PPL",
    "gn:population":1111,
    "iso:country":"PK",
    "name:und_x_variant":[
        "Shinpokh"
    ],
    "qs:name":"Sh\u012bnpokh",
    "qs:photos_9r":0,
    "qs:photos_sr":0,
    "qs:pop_sr":"3",
    "wof:name":"Sh\u012bnpokh",
    "wof:placetype":"locality",
    "wof:population":1111
},
  "geometry": {"coordinates":[71.17821000000001,34.3292],"type":"Point"}
}