{
  "type": "Feature",
  "properties": {
    "gn:admin1_code":"3.0",
    "gn:asciiname":"Garah Budha",
    "gn:country_code":"PK",
    "gn:dem":268,
    "gn:feature_class":"P",
    "gn:feature_code":"PPL",
    "gn:name":"Garah Budha",
    "gn:population":0,
    "gn:timezone":"Asia/Karachi",
    "iso:country":"PK",
    "wof:name":"Garah Budha",
    "wof:placetype":"locality"
},
  "geometry": {"coordinates":[70.34585,32.22075],"type":"Point"}
}