{
  "type": "Feature",
  "properties": {
    "gn:admin1_code":"2",
    "gn:asciiname":"Karim Bakhsh",
    "gn:country_code":"PK",
    "gn:dem":1848,
    "gn:feature_class":"P",
    "gn:feature_code":"PPL",
    "gn:name":"Karim Bakhsh",
    "gn:population":0,
    "gn:timezone":"Asia/Karachi",
    "iso:country":"PK",
    "wof:name":"Karim Bakhsh",
    "wof:placetype":"locality"
},
  "geometry": {"coordinates":[67.09281999999999,29.98784],"type":"Point"}
}