{
  "type": "Feature",
  "properties": {
    "gn:admin1_code":"4.0",
    "gn:asciiname":"Khothian",
    "gn:country_code":"PK",
    "gn:dem":482,
    "gn:feature_class":"P",
    "gn:feature_code":"PPL",
    "gn:name":"Khothian",
    "gn:population":0,
    "gn:timezone":"Asia/Karachi",
    "iso:country":"PK",
    "name:und_x_variant":[
        "Khoti\u0101n"
    ],
    "wof:name":"Khothian",
    "wof:placetype":"locality"
},
  "geometry": {"coordinates":[73.00221999999999,32.88744000000001],"type":"Point"}
}