{
  "type": "Feature",
  "properties": {
    "gn:admin1_code":"04",
    "gn:asciiname":"Bagu Na Mohra",
    "gn:country_code":"PK",
    "gn:dem":467,
    "gn:feature_class":"P",
    "gn:feature_code":"PPL",
    "gn:name":"Bagu Na Mohra",
    "gn:population":0,
    "gn:timezone":"Asia/Karachi",
    "iso:country":"PK",
    "name:und_x_variant":[
        "Baggon\u0101l Mohra"
    ],
    "wof:name":"Bagu Na Mohra",
    "wof:placetype":"locality"
},
  "geometry": {"coordinates":[73.36031,33.35021],"type":"Point"}
}