{
  "type": "Feature",
  "properties": {
    "gn:admin1_code":"3",
    "gn:asciiname":"Anu Dap",
    "gn:country_code":"PK",
    "gn:dem":3234,
    "gn:feature_class":"P",
    "gn:feature_code":"PPL",
    "gn:name":"Anu Dap",
    "gn:population":0,
    "gn:timezone":"Asia/Karachi",
    "iso:country":"PK",
    "name:eng_x_preferred":[
        "Anu Dap"
    ],
    "wof:name":"Anu Dap",
    "wof:placetype":"locality"
},
  "geometry": {"coordinates":[71.97293000000001,35.6807],"type":"Point"}
}