{
  "type": "Feature",
  "properties": {
    "gn:admin1_code":"2",
    "gn:asciiname":"Mazarai",
    "gn:country_code":"PK",
    "gn:dem":1629,
    "gn:feature_class":"P",
    "gn:feature_code":"PPL",
    "gn:name":"Mazarai",
    "gn:population":0,
    "gn:timezone":"Asia/Karachi",
    "iso:country":"PK",
    "wof:name":"Mazarai",
    "wof:placetype":"locality"
},
  "geometry": {"coordinates":[66.97815,30.77126],"type":"Point"}
}