{
  "type": "Feature",
  "properties": {
    "gn:admin1_code":"5",
    "gn:asciiname":"Bakhsh Ali Rind",
    "gn:country_code":"PK",
    "gn:dem":28,
    "gn:feature_class":"P",
    "gn:feature_code":"PPL",
    "gn:name":"Bakhsh Ali Rind",
    "gn:population":0,
    "gn:timezone":"Asia/Karachi",
    "iso:country":"PK",
    "wof:name":"Bakhsh Ali Rind",
    "wof:placetype":"locality"
},
  "geometry": {"coordinates":[68.62801,26.08873],"type":"Point"}
}