{
  "type": "Feature",
  "properties": {
    "gn:admin1_code":"3",
    "gn:asciiname":"Lusu Baihk",
    "gn:country_code":"PK",
    "gn:dem":2605,
    "gn:feature_class":"P",
    "gn:feature_code":"PPL",
    "gn:name":"Lusu Baihk",
    "gn:population":0,
    "gn:timezone":"Asia/Karachi",
    "iso:country":"PK",
    "name:und_x_variant":[
        "Losu Baik"
    ],
    "wof:name":"Lusu Baihk",
    "wof:placetype":"locality"
},
  "geometry": {"coordinates":[73.41701999999999,34.18292],"type":"Point"}
}