{
  "type": "Feature",
  "properties": {
    "gn:admin1_code":"4.0",
    "gn:asciiname":"Khorian",
    "gn:country_code":"PK",
    "gn:dem":234,
    "gn:feature_class":"P",
    "gn:feature_code":"PPL",
    "gn:name":"Khorian",
    "gn:population":0,
    "gn:timezone":"Asia/Karachi",
    "iso:country":"PK",
    "name:und_x_variant":[
        "Khori"
    ],
    "wof:name":"Khorian",
    "wof:placetype":"locality"
},
  "geometry": {"coordinates":[73.68099000000002,32.71473],"type":"Point"}
}