{
  "type": "Feature",
  "properties": {
    "gn:admin1_code":"7.0",
    "gn:asciiname":"Domoi Baihk",
    "gn:country_code":"PK",
    "gn:dem":2993,
    "gn:feature_class":"P",
    "gn:feature_code":"PPL",
    "gn:name":"Domoi Baihk",
    "gn:population":0,
    "gn:timezone":"Asia/Karachi",
    "iso:country":"PK",
    "wof:name":"Domoi Baihk",
    "wof:placetype":"locality"
},
  "geometry": {"coordinates":[74.51258,35.39814000000001],"type":"Point"}
}