{
  "type": "Feature",
  "properties": {
    "gn:admin1_code":"5.0",
    "gn:asciiname":"Goth Mola Bakhsh Marri",
    "gn:country_code":"PK",
    "gn:dem":14,
    "gn:feature_class":"P",
    "gn:feature_code":"PPL",
    "gn:name":"Goth Mola Bakhsh Marri",
    "gn:population":0,
    "gn:timezone":"Asia/Karachi",
    "iso:country":"PK",
    "wof:name":"Goth Mola Bakhsh Marri",
    "wof:placetype":"locality"
},
  "geometry": {"coordinates":[69.23694,25.67427],"type":"Point"}
}