{
  "type": "Feature",
  "properties": {
    "gn:admin1_code":"5.0",
    "gn:asciiname":"Maula Bakhsh Sandelo",
    "gn:country_code":"PK",
    "gn:dem":41,
    "gn:feature_class":"P",
    "gn:feature_code":"PPL",
    "gn:name":"Maula Bakhsh Sandelo",
    "gn:population":0,
    "gn:timezone":"Asia/Karachi",
    "iso:country":"PK",
    "wof:name":"Maula Bakhsh Sandelo",
    "wof:placetype":"locality"
},
  "geometry": {"coordinates":[67.97929000000001,26.73517],"type":"Point"}
}