{
  "type": "Feature",
  "properties": {
    "gn:admin1_code":"6",
    "gn:asciiname":"Harkarrian",
    "gn:country_code":"PK",
    "gn:dem":1357,
    "gn:feature_class":"P",
    "gn:feature_code":"PPL",
    "gn:name":"Harkarrian",
    "gn:population":0,
    "gn:timezone":"Asia/Karachi",
    "iso:country":"PK",
    "name:und_x_variant":[
        "Kalar"
    ],
    "wof:name":"Harkarrian",
    "wof:placetype":"locality"
},
  "geometry": {"coordinates":[73.96115,33.82465],"type":"Point"}
}