{
  "type": "Feature",
  "properties": {
    "gn:admin1_code":"2.0",
    "gn:asciiname":"Kili Haji Hakim Kare",
    "gn:country_code":"PK",
    "gn:dem":1449,
    "gn:feature_class":"P",
    "gn:feature_code":"PPL",
    "gn:name":"Kili Haji Hakim Kare",
    "gn:population":0,
    "gn:timezone":"Asia/Karachi",
    "iso:country":"PK",
    "wof:name":"Kili Haji Hakim Kare",
    "wof:placetype":"locality"
},
  "geometry": {"coordinates":[66.51773,30.08947],"type":"Point"}
}