{
  "type": "Feature",
  "properties": {
    "gn:admin1_code":"2.0",
    "gn:asciiname":"Bar Kuhai",
    "gn:country_code":"PK",
    "gn:dem":983,
    "gn:feature_class":"P",
    "gn:feature_code":"PPL",
    "gn:name":"Bar Kuhai",
    "gn:population":0,
    "gn:timezone":"Asia/Karachi",
    "iso:country":"PK",
    "wof:name":"Bar Kuhai",
    "wof:placetype":"locality"
},
  "geometry": {"coordinates":[70.14339,30.95239],"type":"Point"}
}