{
  "type": "Feature",
  "properties": {
    "gn:admin1_code":"7.0",
    "gn:asciiname":"Togla",
    "gn:country_code":"PK",
    "gn:dem":2642,
    "gn:feature_class":"P",
    "gn:feature_code":"PPL",
    "gn:name":"Togla",
    "gn:population":0,
    "gn:timezone":"Asia/Karachi",
    "iso:country":"PK",
    "wof:name":"Togla",
    "wof:placetype":"locality"
},
  "geometry": {"coordinates":[75.04231,35.73008],"type":"Point"}
}