{
  "type": "Feature",
  "properties": {
    "gn:admin1_code":"3.0",
    "gn:asciiname":"Chhapri",
    "gn:country_code":"PK",
    "gn:dem":333,
    "gn:feature_class":"P",
    "gn:feature_code":"PPL",
    "gn:name":"Chhapri",
    "gn:population":0,
    "gn:timezone":"Asia/Karachi",
    "iso:country":"PK",
    "name:und_x_variant":[
        "Chapri"
    ],
    "wof:name":"Chhapri",
    "wof:placetype":"locality"
},
  "geometry": {"coordinates":[70.66224,32.92242],"type":"Point"}
}