{
  "type": "Feature",
  "properties": {
    "gn:admin1_code":"3.0",
    "gn:asciiname":"Sakar Kalle",
    "gn:country_code":"PK",
    "gn:dem":343,
    "gn:feature_class":"P",
    "gn:feature_code":"PPL",
    "gn:name":"Sakar Kalle",
    "gn:population":0,
    "gn:timezone":"Asia/Karachi",
    "iso:country":"PK",
    "name:eng_x_preferred":[
        "S\u0101k\u0101r Kalle"
    ],
    "name:und_x_variant":[
        "Sakar",
        "Sakar Kalle"
    ],
    "wof:name":"Sakar Kalle",
    "wof:placetype":"locality"
},
  "geometry": {"coordinates":[71.63164,34.282],"type":"Point"}
}