{
  "type": "Feature",
  "properties": {
    "gn:admin1_code":"4.0",
    "gn:asciiname":"Fatehpur Number Two",
    "gn:country_code":"PK",
    "gn:dem":420,
    "gn:feature_class":"P",
    "gn:feature_code":"PPL",
    "gn:name":"Fatehpur Number Two",
    "gn:population":0,
    "gn:timezone":"Asia/Karachi",
    "iso:country":"PK",
    "wof:name":"Fatehpur Number Two",
    "wof:placetype":"locality"
},
  "geometry": {"coordinates":[73.24511,32.85981],"type":"Point"}
}