{
  "type": "Feature",
  "properties": {
    "gn:admin1_code":"2.0",
    "gn:asciiname":"Goth Khara Haji Abdul Rehman",
    "gn:country_code":"PK",
    "gn:dem":128,
    "gn:feature_class":"P",
    "gn:feature_code":"PPL",
    "gn:name":"Goth Khara Haji Abdul Rehman",
    "gn:population":0,
    "gn:timezone":"Asia/Karachi",
    "iso:country":"PK",
    "name:und_x_variant":[
        "Kh\u0101ra"
    ],
    "wof:name":"Goth Khara Haji Abdul Rehman",
    "wof:placetype":"locality"
},
  "geometry": {"coordinates":[67.80608000000001,29.47957],"type":"Point"}
}