{
  "type": "Feature",
  "properties": {
    "gn:admin1_code":"04",
    "gn:asciiname":"Chak One Hundred Forty-five",
    "gn:country_code":"PK",
    "gn:dem":176,
    "gn:feature_class":"P",
    "gn:feature_code":"PPL",
    "gn:name":"Chak One Hundred Forty-five",
    "gn:population":0,
    "gn:timezone":"Asia/Karachi",
    "iso:country":"PK",
    "name:und_x_variant":[
        "Kot B\u0101habw\u0101la",
        "Kot Bhabwala",
        "Chak One Hundred Forty-five",
        "Sandanw\u0101la",
        "Sahwa"
    ],
    "wof:name":"Chak One Hundred Forty-five",
    "wof:placetype":"locality"
},
  "geometry": {"coordinates":[72.84356,31.54351],"type":"Point"}
}