{
  "type": "Feature",
  "properties": {
    "gn:admin1_code":"5.0",
    "gn:asciiname":"Denhari",
    "gn:country_code":"PK",
    "gn:dem":18,
    "gn:feature_class":"P",
    "gn:feature_code":"PPL",
    "gn:name":"Denhari",
    "gn:population":0,
    "gn:timezone":"Asia/Karachi",
    "iso:country":"PK",
    "name:und_x_variant":[
        "D\u0101in\u0101la"
    ],
    "wof:name":"Denhari",
    "wof:placetype":"locality"
},
  "geometry": {"coordinates":[70.42140000000001,24.39591],"type":"Point"}
}