{
  "type": "Feature",
  "properties": {
    "gn:admin1_code":"1.0",
    "gn:asciiname":"Dresara",
    "gn:country_code":"PK",
    "gn:dem":686,
    "gn:feature_class":"P",
    "gn:feature_code":"PPL",
    "gn:name":"Dresara",
    "gn:population":0,
    "gn:timezone":"Asia/Karachi",
    "iso:country":"PK",
    "wof:name":"Dresara",
    "wof:placetype":"locality"
},
  "geometry": {"coordinates":[71.27911999999998,34.49725],"type":"Point"}
}