{
  "type": "Feature",
  "properties": {
    "gn:admin1_code":"5.0",
    "gn:asciiname":"Goth Kamal Khan Magsi",
    "gn:country_code":"PK",
    "gn:dem":14,
    "gn:feature_class":"P",
    "gn:feature_code":"PPL",
    "gn:name":"Goth Kamal Khan Magsi",
    "gn:population":0,
    "gn:timezone":"Asia/Karachi",
    "iso:country":"PK",
    "name:und_x_variant":[
        "Goth Kam\u0101l Magsi"
    ],
    "wof:name":"Goth Kamal Khan Magsi",
    "wof:placetype":"locality"
},
  "geometry": {"coordinates":[68.20098,24.87428],"type":"Point"}
}