{
  "type": "Feature",
  "properties": {
    "gn:admin1_code":"4",
    "gn:asciiname":"Chak One Hundred Eighty-four Shumali",
    "gn:country_code":"PK",
    "gn:dem":179,
    "gn:feature_class":"P",
    "gn:feature_code":"PPL",
    "gn:name":"Chak One Hundred Eighty-four Shumali",
    "gn:population":0,
    "gn:timezone":"Asia/Karachi",
    "iso:country":"PK",
    "name:und_x_variant":[
        "Drawala",
        "Sipraw\u0101la",
        "Chak One Hundred Eighty-Four",
        "Chak One Hundred Eighty-four Shumali",
        "Komh\u0101r\u0101b\u0101d"
    ],
    "wof:name":"Chak One Hundred Eighty-four Shumali",
    "wof:placetype":"locality"
},
  "geometry": {"coordinates":[72.83941999999998,31.48828],"type":"Point"}
}