{
  "type": "Feature",
  "properties": {
    "gn:admin1_code":"5",
    "gn:asciiname":"Muhammad Palji Otaq",
    "gn:country_code":"PK",
    "gn:dem":19,
    "gn:feature_class":"P",
    "gn:feature_code":"PPL",
    "gn:name":"Muhammad Palji Ot\u0101q",
    "gn:population":0,
    "gn:timezone":"Asia/Karachi",
    "iso:country":"PK",
    "wof:name":"Muhammad Palji Otaq",
    "wof:placetype":"locality"
},
  "geometry": {"coordinates":[68.89721999999999,25.45139],"type":"Point"}
}