{
  "type": "Feature",
  "properties": {
    "gn:admin1_code":"4.0",
    "gn:asciiname":"Dhok Ahir",
    "gn:country_code":"PK",
    "gn:dem":522,
    "gn:feature_class":"P",
    "gn:feature_code":"PPL",
    "gn:name":"Dhok Ahir",
    "gn:population":0,
    "gn:timezone":"Asia/Karachi",
    "iso:country":"PK",
    "name:fas_x_preferred":[
        "\u0628\u0647\u06cc\u0631 \u0622\u0647\u06cc\u0631"
    ],
    "name:und_x_variant":[
        "Bher Ah\u012br",
        "Dhok Ahir"
    ],
    "name:urd_x_preferred":[
        "\u0628\u06be\u06cc\u0631 \u0622\u06c1\u06cc\u0631"
    ],
    "wof:name":"Dhok Ahir",
    "wof:placetype":"locality"
},
  "geometry": {"coordinates":[73.06961,33.21615],"type":"Point"}
}