{
  "type": "Feature",
  "properties": {
    "gn:admin1_code":"3.0",
    "gn:asciiname":"Jabbi",
    "gn:country_code":"PK",
    "gn:dem":632,
    "gn:feature_class":"P",
    "gn:feature_code":"PPL",
    "gn:name":"Jabbi",
    "gn:population":0,
    "gn:timezone":"Asia/Karachi",
    "iso:country":"PK",
    "wof:name":"Jabbi",
    "wof:placetype":"locality"
},
  "geometry": {"coordinates":[71.26045000000001,33.55984],"type":"Point"}
}