{
  "type": "Feature",
  "properties": {
    "gn:admin1_code":"4",
    "gn:asciiname":"Mian Hakim Ali",
    "gn:country_code":"PK",
    "gn:dem":146,
    "gn:feature_class":"P",
    "gn:feature_code":"PPL",
    "gn:name":"Mian Hakim Ali",
    "gn:population":0,
    "gn:timezone":"Asia/Karachi",
    "iso:country":"PK",
    "name:und_x_variant":[
        "Mi\u0101n H\u0101kim Ali"
    ],
    "wof:name":"Mian Hakim Ali",
    "wof:placetype":"locality"
},
  "geometry": {"coordinates":[72.66109,29.92183],"type":"Point"}
}