{
  "type": "Feature",
  "properties": {
    "gn:admin1_code":"3.0",
    "gn:asciiname":"Derai",
    "gn:country_code":"PK",
    "gn:dem":1117,
    "gn:feature_class":"P",
    "gn:feature_code":"PPL",
    "gn:name":"Derai",
    "gn:population":0,
    "gn:timezone":"Asia/Karachi",
    "iso:country":"PK",
    "wof:name":"Derai",
    "wof:placetype":"locality"
},
  "geometry": {"coordinates":[72.81683000000002,34.70458],"type":"Point"}
}