{
  "type": "Feature",
  "properties": {
    "gn:admin1_code":"03",
    "gn:asciiname":"Namazkot",
    "gn:country_code":"PK",
    "gn:dem":1386,
    "gn:feature_class":"P",
    "gn:feature_code":"PPL",
    "gn:name":"Namazkot",
    "gn:population":0,
    "gn:timezone":"Asia/Karachi",
    "iso:country":"PK",
    "name:eng_x_preferred":[
        "Bilm\u0101zkot"
    ],
    "name:und_x_variant":[
        "Am\u0101kot",
        "Namazkot"
    ],
    "wof:name":"Namazkot",
    "wof:placetype":"locality"
},
  "geometry": {"coordinates":[71.76344,34.96966],"type":"Point"}
}