{
  "type": "Feature",
  "properties": {
    "gn:admin1_code":"02",
    "gn:asciiname":"Shadizai",
    "gn:country_code":"PK",
    "gn:dem":1461,
    "gn:feature_class":"P",
    "gn:feature_code":"PPL",
    "gn:name":"Shadizai",
    "gn:population":0,
    "gn:timezone":"Asia/Karachi",
    "iso:country":"PK",
    "name:und_x_variant":[
        "Ajram Shadezai",
        "Shadizai"
    ],
    "wof:name":"Shadizai",
    "wof:placetype":"locality"
},
  "geometry": {"coordinates":[66.79964,30.55111],"type":"Point"}
}