{
  "type": "Feature",
  "properties": {
    "gn:admin1_code":"2.0",
    "gn:asciiname":"Aliabad",
    "gn:country_code":"PK",
    "gn:dem":50,
    "gn:feature_class":"P",
    "gn:feature_code":"PPL",
    "gn:name":"Aliabad",
    "gn:population":0,
    "gn:timezone":"Asia/Karachi",
    "iso:country":"PK",
    "name:und_x_variant":[
        "Chak Sixteen",
        "Chak 16"
    ],
    "wof:name":"Aliabad",
    "wof:placetype":"locality"
},
  "geometry": {"coordinates":[67.74594,28.04865],"type":"Point"}
}