{
  "type": "Feature",
  "properties": {
    "gn:admin1_code":"2.0",
    "gn:asciiname":"Aliabad",
    "gn:country_code":"PK",
    "gn:dem":50,
    "gn:feature_class":"P",
    "gn:feature_code":"PPL",
    "gn:name":"Aliabad",
    "gn:population":0,
    "gn:timezone":"Asia/Karachi",
    "iso:country":"PK",
    "name:azb_x_preferred":[
        "\u0639\u0644\u06cc\u200c\u0622\u0628\u0627\u062f"
    ],
    "name:aze_x_preferred":[
        "\u018fliabad"
    ],
    "name:fas_x_preferred":[
        "\u0639\u0644\u06cc\u200c\u0622\u0628\u0627\u062f"
    ],
    "name:hin_x_preferred":[
        "\u0906\u0932\u093f\u092f\u093e\u092c\u093e\u0926"
    ],
    "name:ita_x_preferred":[
        "Aliabad"
    ],
    "name:kat_x_preferred":[
        "\u10d0\u10da\u10d8\u10d0\u10d1\u10d0\u10d3\u10d8"
    ],
    "name:mzn_x_preferred":[
        "\u0639\u0644\u06cc\u200c\u0622\u0628\u0627\u062f"
    ],
    "name:nld_x_preferred":[
        "Aliabad"
    ],
    "name:pol_x_preferred":[
        "Aliabad"
    ],
    "name:tur_x_preferred":[
        "Aliabad"
    ],
    "name:und_x_variant":[
        "Chak Sixteen",
        "Chak 16"
    ],
    "wof:name":"Aliabad",
    "wof:placetype":"locality"
},
  "geometry": {"coordinates":[67.74594,28.04865],"type":"Point"}
}