{
  "type": "Feature",
  "properties": {
    "gn:admin1_code":"2.0",
    "gn:asciiname":"Saifullah Karaz",
    "gn:country_code":"PK",
    "gn:dem":1625,
    "gn:feature_class":"P",
    "gn:feature_code":"PPL",
    "gn:name":"Saifullah Karaz",
    "gn:population":0,
    "gn:timezone":"Asia/Karachi",
    "iso:country":"PK",
    "wof:name":"Saifullah Karaz",
    "wof:placetype":"locality"
},
  "geometry": {"coordinates":[66.82231,29.87553],"type":"Point"}
}