{
  "type": "Feature",
  "properties": {
    "gn:admin1_code":"4.0",
    "gn:asciiname":"Bhaini Manzurwali",
    "gn:country_code":"PK",
    "gn:dem":152,
    "gn:feature_class":"P",
    "gn:feature_code":"PPL",
    "gn:name":"Bhaini Manzurwali",
    "gn:population":0,
    "gn:timezone":"Asia/Karachi",
    "iso:country":"PK",
    "wof:name":"Bhaini Manzurwali",
    "wof:placetype":"locality"
},
  "geometry": {"coordinates":[73.01401,29.87509],"type":"Point"}
}