{
  "type": "Feature",
  "properties": {
    "gn:admin1_code":"04",
    "gn:asciiname":"Maraulianwala",
    "gn:country_code":"PK",
    "gn:dem":195,
    "gn:feature_class":"P",
    "gn:feature_code":"PPL",
    "gn:name":"Maraulianwala",
    "gn:population":0,
    "gn:timezone":"Asia/Karachi",
    "iso:country":"PK",
    "name:und_x_variant":[
        "Marulianwala",
        "Maraulianwala"
    ],
    "wof:name":"Maraulianwala",
    "wof:placetype":"locality"
},
  "geometry": {"coordinates":[72.91856999999997,32.15487],"type":"Point"}
}