{
  "type": "Feature",
  "properties": {
    "gn:admin1_code":"1.0",
    "gn:asciiname":"Gawa",
    "gn:country_code":"PK",
    "gn:dem":1181,
    "gn:feature_class":"P",
    "gn:feature_code":"PPL",
    "gn:name":"Gawa",
    "gn:population":0,
    "gn:timezone":"Asia/Karachi",
    "iso:country":"PK",
    "name:bar_x_preferred":[
        "Gawa"
    ],
    "name:ceb_x_preferred":[
        "Gawa"
    ],
    "name:eng_x_preferred":[
        "Gawa"
    ],
    "name:swe_x_preferred":[
        "Gawa"
    ],
    "wof:name":"Gawa",
    "wof:placetype":"locality"
},
  "geometry": {"coordinates":[71.53827,34.89494000000001],"type":"Point"}
}