{
  "type": "Feature",
  "properties": {
    "gn:admin1_code":"4.0",
    "gn:asciiname":"Chak Seventy-six -B -Fifteen Left",
    "gn:country_code":"PK",
    "gn:dem":133,
    "gn:feature_class":"P",
    "gn:feature_code":"PPL",
    "gn:name":"Chak Seventy-six -B -Fifteen Left",
    "gn:population":0,
    "gn:timezone":"Asia/Karachi",
    "iso:country":"PK",
    "name:und_x_variant":[
        "Haji Rahmatull\u0101h",
        "H\u0101ji Rehmatull\u0101h"
    ],
    "wof:name":"Chak Seventy-six -B -Fifteen Left",
    "wof:placetype":"locality"
},
  "geometry": {"coordinates":[72.08703,30.1505],"type":"Point"}
}