{
  "type": "Feature",
  "properties": {
    "gn:admin1_code":"3.0",
    "gn:asciiname":"Tala",
    "gn:country_code":"PK",
    "gn:dem":869,
    "gn:feature_class":"P",
    "gn:feature_code":"PPL",
    "gn:name":"Tala",
    "gn:population":0,
    "gn:timezone":"Asia/Karachi",
    "iso:country":"PK",
    "name:aze_x_preferred":[
        "Tala"
    ],
    "name:ceb_x_preferred":[
        "Tala"
    ],
    "name:deu_x_preferred":[
        "Tala"
    ],
    "name:ell_x_preferred":[
        "\u03a4\u03ac\u03bb\u03b1"
    ],
    "name:epo_x_preferred":[
        "Tala"
    ],
    "name:est_x_preferred":[
        "Tala"
    ],
    "name:fin_x_preferred":[
        "Tala"
    ],
    "name:fra_x_preferred":[
        "Tala"
    ],
    "name:ind_x_preferred":[
        "Tala"
    ],
    "name:isl_x_preferred":[
        "Tala"
    ],
    "name:ita_x_preferred":[
        "Tala"
    ],
    "name:lit_x_preferred":[
        "Tala"
    ],
    "name:nld_x_preferred":[
        "Tala"
    ],
    "name:por_x_preferred":[
        "Tala"
    ],
    "name:rus_x_preferred":[
        "\u0422\u0430\u043b\u0430"
    ],
    "name:spa_x_preferred":[
        "Tala"
    ],
    "name:srp_x_preferred":[
        "\u0422\u0430\u043b\u0430"
    ],
    "name:swe_x_preferred":[
        "Tala"
    ],
    "name:tgl_x_preferred":[
        "Tala"
    ],
    "wof:name":"Tala",
    "wof:placetype":"locality"
},
  "geometry": {"coordinates":[72.64716999999997,34.54632],"type":"Point"}
}