{
  "type": "Feature",
  "properties": {
    "gn:admin1_code":"2.0",
    "gn:asciiname":"Kili Muhammad Hassani",
    "gn:country_code":"PK",
    "gn:dem":1584,
    "gn:feature_class":"P",
    "gn:feature_code":"PPL",
    "gn:name":"Kili Muhammad Hassani",
    "gn:population":0,
    "gn:timezone":"Asia/Karachi",
    "iso:country":"PK",
    "name:und_x_variant":[
        "Zangl\u0101hi"
    ],
    "wof:name":"Kili Muhammad Hassani",
    "wof:placetype":"locality"
},
  "geometry": {"coordinates":[66.29349999999999,28.1353],"type":"Point"}
}