{
  "type": "Feature",
  "properties": {
    "gn:admin1_code":"6",
    "gn:asciiname":"Haji",
    "gn:country_code":"PK",
    "gn:dem":1826,
    "gn:feature_class":"P",
    "gn:feature_code":"PPL",
    "gn:name":"Haji",
    "gn:population":0,
    "gn:timezone":"Asia/Kolkata",
    "iso:country":"PK",
    "wof:name":"Haji",
    "wof:placetype":"locality"
},
  "geometry": {"coordinates":[73.84895,34.45054],"type":"Point"}
}