{
  "type": "Feature",
  "properties": {
    "gn:admin1_code":"2.0",
    "gn:asciiname":"Siagzi",
    "gn:country_code":"PK",
    "gn:dem":516,
    "gn:feature_class":"P",
    "gn:feature_code":"PPL",
    "gn:name":"Siagzi",
    "gn:population":0,
    "gn:timezone":"Asia/Karachi",
    "iso:country":"PK",
    "wof:name":"Siagzi",
    "wof:placetype":"locality"
},
  "geometry": {"coordinates":[65.1983,26.42342],"type":"Point"}
}