{
  "type": "Feature",
  "properties": {
    "gn:admin1_code":"4",
    "gn:asciiname":"Sajranwali",
    "gn:country_code":"PK",
    "gn:dem":102,
    "gn:feature_class":"P",
    "gn:feature_code":"PPL",
    "gn:name":"Sajranwali",
    "gn:population":0,
    "gn:timezone":"Asia/Karachi",
    "iso:country":"PK",
    "name:und_x_variant":[
        "Basti Shajr\u0101nw\u0101li",
        "Shajr\u0101nw\u0101li",
        "Sajranwali"
    ],
    "wof:name":"Sajranwali",
    "wof:placetype":"locality"
},
  "geometry": {"coordinates":[70.73634,29.35712],"type":"Point"}
}