{
  "type": "Feature",
  "properties": {
    "gn:admin1_code":"4",
    "gn:asciiname":"Dhok Munda",
    "gn:country_code":"PK",
    "gn:dem":476,
    "gn:feature_class":"P",
    "gn:feature_code":"PPL",
    "gn:name":"Dhok Munda",
    "gn:population":0,
    "gn:timezone":"Asia/Karachi",
    "iso:country":"PK",
    "name:und_x_variant":[
        "Dhok Mande"
    ],
    "wof:name":"Dhok Munda",
    "wof:placetype":"locality"
},
  "geometry": {"coordinates":[73.06374,32.85731],"type":"Point"}
}