{
  "type": "Feature",
  "properties": {
    "gn:admin1_code":"04",
    "gn:asciiname":"Matta",
    "gn:country_code":"PK",
    "gn:dem":165,
    "gn:feature_class":"P",
    "gn:feature_code":"PPL",
    "gn:name":"Matta",
    "gn:population":0,
    "gn:timezone":"Asia/Karachi",
    "iso:country":"PK",
    "name:ceb_x_preferred":[
        "Matta"
    ],
    "name:deu_x_preferred":[
        "Matta"
    ],
    "name:fra_x_preferred":[
        "Matta"
    ],
    "name:jpn_x_preferred":[
        "\u30de\u30c3\u30bf"
    ],
    "name:nld_x_preferred":[
        "Matta"
    ],
    "name:spa_x_preferred":[
        "Matta"
    ],
    "name:swe_x_preferred":[
        "Matta"
    ],
    "name:tur_x_preferred":[
        "Matta"
    ],
    "wof:name":"Matta",
    "wof:placetype":"locality"
},
  "geometry": {"coordinates":[72.39879000000001,31.59387000000001],"type":"Point"}
}