{
  "type": "Feature",
  "properties": {
    "gn:admin1_code":"4.0",
    "gn:asciiname":"Chak Fateh Khan",
    "gn:country_code":"PK",
    "gn:dem":468,
    "gn:feature_class":"P",
    "gn:feature_code":"PPL",
    "gn:name":"Chak Fateh Khan",
    "gn:population":0,
    "gn:timezone":"Asia/Karachi",
    "iso:country":"PK",
    "name:und_x_variant":[
        "Chak Fatek Kh\u0101n",
        "Chak Fateh Khan"
    ],
    "wof:name":"Chak Fateh Khan",
    "wof:placetype":"locality"
},
  "geometry": {"coordinates":[72.509,33.58784],"type":"Point"}
}