{
  "type": "Feature",
  "properties": {
    "gn:admin1_code":"5",
    "gn:asciiname":"Rasul Bukhsh",
    "gn:country_code":"PK",
    "gn:dem":30,
    "gn:feature_class":"P",
    "gn:feature_code":"PPL",
    "gn:name":"Rasul Bukhsh",
    "gn:population":0,
    "gn:timezone":"Asia/Karachi",
    "iso:country":"PK",
    "name:und_x_variant":[
        "Ras\u016bl Bakhsh"
    ],
    "wof:name":"Rasul Bukhsh",
    "wof:placetype":"locality"
},
  "geometry": {"coordinates":[68.62024,26.2762],"type":"Point"}
}