{
  "type": "Feature",
  "properties": {
    "gn:admin1_code":"4.0",
    "gn:asciiname":"Bhadre Banaras Khan Wali",
    "gn:country_code":"PK",
    "gn:dem":489,
    "gn:feature_class":"P",
    "gn:feature_code":"PPL",
    "gn:name":"Bhadre Banaras Khan Wali",
    "gn:population":0,
    "gn:timezone":"Asia/Karachi",
    "iso:country":"PK",
    "wof:name":"Bhadre Banaras Khan Wali",
    "wof:placetype":"locality"
},
  "geometry": {"coordinates":[72.67487,33.56466],"type":"Point"}
}