{
  "type": "Feature",
  "properties": {
    "gn:admin1_code":"04",
    "gn:asciiname":"Uppal",
    "gn:country_code":"PK",
    "gn:dem":219,
    "gn:feature_class":"P",
    "gn:feature_code":"PPL",
    "gn:name":"Uppal",
    "gn:population":0,
    "gn:timezone":"Asia/Karachi",
    "iso:country":"PK",
    "wof:name":"Uppal",
    "wof:placetype":"locality"
},
  "geometry": {"coordinates":[74.60519000000002,31.4526],"type":"Point"}
}