{
  "type": "Feature",
  "properties": {
    "gn:admin1_code":"02",
    "gn:asciiname":"Wurghur",
    "gn:country_code":"PK",
    "gn:dem":2206,
    "gn:feature_class":"P",
    "gn:feature_code":"PPL",
    "gn:name":"Wurghur",
    "gn:population":0,
    "gn:timezone":"Asia/Karachi",
    "iso:country":"PK",
    "name:und_x_variant":[
        "Wurghun",
        "Wurghur"
    ],
    "wof:name":"Wurghur",
    "wof:placetype":"locality"
},
  "geometry": {"coordinates":[66.97556,31.05],"type":"Point"}
}