{
  "type": "Feature",
  "properties": {
    "gn:admin1_code":"3.0",
    "gn:asciiname":"Kotkai",
    "gn:country_code":"PK",
    "gn:dem":1155,
    "gn:feature_class":"P",
    "gn:feature_code":"PPL",
    "gn:name":"Kotkai",
    "gn:population":0,
    "gn:timezone":"Asia/Karachi",
    "iso:country":"PK",
    "wof:name":"Kotkai",
    "wof:placetype":"locality"
},
  "geometry": {"coordinates":[72.85477,34.53866],"type":"Point"}
}