{
  "type": "Feature",
  "properties": {
    "gn:admin1_code":"1.0",
    "gn:asciiname":"Akashawa",
    "gn:country_code":"PK",
    "gn:dem":904,
    "gn:feature_class":"P",
    "gn:feature_code":"PPL",
    "gn:name":"Akashawa",
    "gn:population":0,
    "gn:timezone":"Asia/Karachi",
    "iso:country":"PK",
    "wof:name":"Akashawa",
    "wof:placetype":"locality"
},
  "geometry": {"coordinates":[70.45423000000002,33.44632],"type":"Point"}
}