{
  "type": "Feature",
  "properties": {
    "gn:admin1_code":"5.0",
    "gn:asciiname":"Goth Rahim Ali Chang",
    "gn:country_code":"PK",
    "gn:dem":16,
    "gn:feature_class":"P",
    "gn:feature_code":"PPL",
    "gn:name":"Goth Rahim Ali Chang",
    "gn:population":0,
    "gn:timezone":"Asia/Karachi",
    "iso:country":"PK",
    "name:und_x_variant":[
        "Goth Rahim Ali Chang Baloch"
    ],
    "wof:name":"Goth Rahim Ali Chang",
    "wof:placetype":"locality"
},
  "geometry": {"coordinates":[68.28187,24.99473],"type":"Point"}
}