{
  "type": "Feature",
  "properties": {
    "gn:admin1_code":"4",
    "gn:asciiname":"Chak Two Shamali",
    "gn:country_code":"PK",
    "gn:dem":218,
    "gn:feature_class":"P",
    "gn:feature_code":"PPL",
    "gn:name":"Chak Two Shamali",
    "gn:population":0,
    "gn:timezone":"Asia/Karachi",
    "iso:country":"PK",
    "name:und_x_variant":[
        "Chak Two North"
    ],
    "wof:name":"Chak Two Shamali",
    "wof:placetype":"locality"
},
  "geometry": {"coordinates":[73.52868000000002,32.57449],"type":"Point"}
}