{
  "type": "Feature",
  "properties": {
    "gn:admin1_code":"4",
    "gn:asciiname":"Basti Mulana",
    "gn:country_code":"PK",
    "gn:dem":112,
    "gn:feature_class":"P",
    "gn:feature_code":"PPL",
    "gn:name":"Basti Mulana",
    "gn:population":0,
    "gn:timezone":"Asia/Karachi",
    "iso:country":"PK",
    "name:und_x_variant":[
        "Mul\u0101na"
    ],
    "wof:name":"Basti Mulana",
    "wof:placetype":"locality"
},
  "geometry": {"coordinates":[71.0471,29.7963],"type":"Point"}
}