{
  "type": "Feature",
  "properties": {
    "gn:admin1_code":"1.0",
    "gn:asciiname":"Phonge",
    "gn:country_code":"PK",
    "gn:dem":739,
    "gn:feature_class":"P",
    "gn:feature_code":"PPL",
    "gn:name":"Phonge",
    "gn:population":0,
    "gn:timezone":"Asia/Karachi",
    "iso:country":"PK",
    "wof:name":"Phonge",
    "wof:placetype":"locality"
},
  "geometry": {"coordinates":[70.01311,31.85281],"type":"Point"}
}