{
  "type": "Feature",
  "properties": {
    "gn:admin1_code":"6",
    "gn:asciiname":"Nakar",
    "gn:country_code":"PK",
    "gn:dem":1684,
    "gn:feature_class":"P",
    "gn:feature_code":"PPL",
    "gn:name":"Nakar",
    "gn:population":0,
    "gn:timezone":"Asia/Karachi",
    "iso:country":"PK",
    "name:guj_x_preferred":[
        "\u0a95\u0ab5\u0abf \u0aa8\u0abe\u0a95\u0ab0"
    ],
    "name:hin_x_preferred":[
        "\u0928\u093e\u0915\u0930"
    ],
    "wof:name":"Nakar",
    "wof:placetype":"locality"
},
  "geometry": {"coordinates":[74.04323000000002,33.85557],"type":"Point"}
}