{
  "type": "Feature",
  "properties": {
    "gn:admin1_code":"3.0",
    "gn:asciiname":"Dhelan",
    "gn:country_code":"PK",
    "gn:dem":2834,
    "gn:feature_class":"P",
    "gn:feature_code":"PPL",
    "gn:name":"Dhelan",
    "gn:population":0,
    "gn:timezone":"Asia/Karachi",
    "iso:country":"PK",
    "wof:name":"Dhelan",
    "wof:placetype":"locality"
},
  "geometry": {"coordinates":[72.99146,35.28639000000001],"type":"Point"}
}