{
  "type": "Feature",
  "properties": {
    "gn:admin1_code":"3.0",
    "gn:asciiname":"Chhach",
    "gn:country_code":"PK",
    "gn:dem":562,
    "gn:feature_class":"P",
    "gn:feature_code":"PPL",
    "gn:name":"Chhach",
    "gn:population":0,
    "gn:timezone":"Asia/Karachi",
    "iso:country":"PK",
    "wof:name":"Chhach",
    "wof:placetype":"locality"
},
  "geometry": {"coordinates":[72.89697,33.8446],"type":"Point"}
}