{
  "type": "Feature",
  "properties": {
    "gn:admin1_code":"2.0",
    "gn:asciiname":"Dilmurad Khan",
    "gn:country_code":"PK",
    "gn:dem":73,
    "gn:feature_class":"P",
    "gn:feature_code":"PPL",
    "gn:name":"Dilmurad Khan",
    "gn:population":0,
    "gn:timezone":"Asia/Karachi",
    "iso:country":"PK",
    "wof:name":"Dilmurad Khan",
    "wof:placetype":"locality"
},
  "geometry": {"coordinates":[67.50185999999999,28.37153],"type":"Point"}
}