{
  "type": "Feature",
  "properties": {
    "gn:admin1_code":"5.0",
    "gn:asciiname":"Goth Ishaq Buzdar",
    "gn:country_code":"PK",
    "gn:dem":25,
    "gn:feature_class":"P",
    "gn:feature_code":"PPL",
    "gn:name":"Goth Ishaq Buzdar",
    "gn:population":0,
    "gn:timezone":"Asia/Karachi",
    "iso:country":"PK",
    "wof:name":"Goth Ishaq Buzdar",
    "wof:placetype":"locality"
},
  "geometry": {"coordinates":[68.69595,25.9837],"type":"Point"}
}