{
  "type": "Feature",
  "properties": {
    "gn:admin1_code":"2.0",
    "gn:asciiname":"Malik Abdul Rehman Kili",
    "gn:country_code":"PK",
    "gn:dem":1161,
    "gn:feature_class":"P",
    "gn:feature_code":"PPL",
    "gn:name":"Malik Abdul Rehman Kili",
    "gn:population":0,
    "gn:timezone":"Asia/Karachi",
    "iso:country":"PK",
    "wof:name":"Malik Abdul Rehman Kili",
    "wof:placetype":"locality"
},
  "geometry": {"coordinates":[63.93275,29.12893],"type":"Point"}
}