{
  "type": "Feature",
  "properties": {
    "gn:admin1_code":"5.0",
    "gn:asciiname":"Goth Karim Bakhsh Brahui",
    "gn:country_code":"PK",
    "gn:dem":68,
    "gn:feature_class":"P",
    "gn:feature_code":"PPL",
    "gn:name":"Goth Karim Bakhsh Brahui",
    "gn:population":0,
    "gn:timezone":"Asia/Karachi",
    "iso:country":"PK",
    "name:eng_x_preferred":[
        "Goth Karim Bakhsh Brahui"
    ],
    "wof:name":"Goth Karim Bakhsh Brahui",
    "wof:placetype":"locality"
},
  "geometry": {"coordinates":[68.53545,27.98779],"type":"Point"}
}