{
  "type": "Feature",
  "properties": {
    "gn:admin1_code":"6.0",
    "gn:asciiname":"Darwan",
    "gn:country_code":"PK",
    "gn:dem":1032,
    "gn:feature_class":"P",
    "gn:feature_code":"PPL",
    "gn:name":"Darwan",
    "gn:population":0,
    "gn:timezone":"Asia/Karachi",
    "iso:country":"PK",
    "wof:name":"Darwan",
    "wof:placetype":"locality"
},
  "geometry": {"coordinates":[73.55889000000001,34.46803],"type":"Point"}
}