{
  "type": "Feature",
  "properties": {
    "gn:admin1_code":"04",
    "gn:asciiname":"Kotla Faqir",
    "gn:country_code":"PK",
    "gn:dem":225,
    "gn:feature_class":"P",
    "gn:feature_code":"PPL",
    "gn:name":"Kotla Faqir",
    "gn:population":0,
    "gn:timezone":"Asia/Karachi",
    "iso:country":"PK",
    "name:fas_x_preferred":[
        "\u06a9\u0648\u062a\u0644\u0647 \u0641\u0642\u06cc\u0631"
    ],
    "name:urd_x_preferred":[
        "\u06a9\u0648\u0679\u0644\u06c1 \u0641\u0642\u06cc\u0631"
    ],
    "wof:name":"Kotla Faqir",
    "wof:placetype":"locality"
},
  "geometry": {"coordinates":[73.6893,32.90879],"type":"Point"}
}