{
  "type": "Feature",
  "properties": {
    "gn:admin1_code":"04",
    "gn:asciiname":"Naugran",
    "gn:country_code":"PK",
    "gn:dem":227,
    "gn:feature_class":"P",
    "gn:feature_code":"PPL",
    "gn:name":"Naugran",
    "gn:population":0,
    "gn:timezone":"Asia/Karachi",
    "iso:country":"PK",
    "name:und_x_variant":[
        "Naugir\u0101n"
    ],
    "wof:name":"Naugran",
    "wof:placetype":"locality"
},
  "geometry": {"coordinates":[73.65066,32.89798],"type":"Point"}
}