{
  "type": "Feature",
  "properties": {
    "gn:admin1_code":"4.0",
    "gn:asciiname":"Kanar",
    "gn:country_code":"PK",
    "gn:dem":1404,
    "gn:feature_class":"P",
    "gn:feature_code":"PPL",
    "gn:name":"Kanar",
    "gn:population":0,
    "gn:timezone":"Asia/Karachi",
    "iso:country":"PK",
    "name:eng_x_preferred":[
        "Kanar"
    ],
    "wof:name":"Kanar",
    "wof:placetype":"locality"
},
  "geometry": {"coordinates":[73.47686999999998,33.798],"type":"Point"}
}