{
  "type": "Feature",
  "properties": {
    "gn:admin1_code":"3.0",
    "gn:asciiname":"Teran Banda",
    "gn:country_code":"PK",
    "gn:dem":464,
    "gn:feature_class":"P",
    "gn:feature_code":"PPL",
    "gn:name":"Teran Banda",
    "gn:population":0,
    "gn:timezone":"Asia/Karachi",
    "iso:country":"PK",
    "name:und_x_variant":[
        "Teran B\u0101nda"
    ],
    "wof:name":"Teran Banda",
    "wof:placetype":"locality"
},
  "geometry": {"coordinates":[71.04120999999998,32.8645],"type":"Point"}
}