{
  "type": "Feature",
  "properties": {
    "gn:admin1_code":"4.0",
    "gn:asciiname":"Maindoha",
    "gn:country_code":"PK",
    "gn:dem":835,
    "gn:feature_class":"P",
    "gn:feature_code":"PPL",
    "gn:name":"Maindoha",
    "gn:population":0,
    "gn:timezone":"Asia/Karachi",
    "iso:country":"PK",
    "name:und_x_variant":[
        "Maidona"
    ],
    "wof:name":"Maindoha",
    "wof:placetype":"locality"
},
  "geometry": {"coordinates":[71.45189000000001,33.09216],"type":"Point"}
}