{
  "type": "Feature",
  "properties": {
    "gn:admin1_code":"4.0",
    "gn:asciiname":"Chak Twenty-three A - Four Left",
    "gn:country_code":"PK",
    "gn:dem":173,
    "gn:feature_class":"P",
    "gn:feature_code":"PPL",
    "gn:name":"Chak Twenty-three A - Four Left",
    "gn:population":0,
    "gn:timezone":"Asia/Karachi",
    "iso:country":"PK",
    "name:und_x_variant":[
        "Kot H\u0101shim",
        "Chak 23 A-4 L",
        "Kot H\u0101sham",
        "Chak Twenty-three A-Four L",
        "Chak Twenty-three A - Four Left"
    ],
    "wof:name":"Chak Twenty-three A - Four Left",
    "wof:placetype":"locality"
},
  "geometry": {"coordinates":[73.35585,30.69236],"type":"Point"}
}