{
  "type": "Feature",
  "properties": {
    "gn:admin1_code":"5",
    "gn:asciiname":"Goth Muhammad Saleh Bhambro",
    "gn:country_code":"PK",
    "gn:dem":13,
    "gn:feature_class":"P",
    "gn:feature_code":"PPL",
    "gn:name":"Goth Muhammad Saleh Bhambro",
    "gn:population":0,
    "gn:timezone":"Asia/Karachi",
    "iso:country":"PK",
    "name:und_x_variant":[
        "S\u0101eh Bhambro"
    ],
    "wof:name":"Goth Muhammad Saleh Bhambro",
    "wof:placetype":"locality"
},
  "geometry": {"coordinates":[69.39804000000001,25.39752],"type":"Point"}
}