{
  "type": "Feature",
  "properties": {
    "gn:admin1_code":"4",
    "gn:asciiname":"Sonagwala",
    "gn:country_code":"PK",
    "gn:dem":133,
    "gn:feature_class":"P",
    "gn:feature_code":"PPL",
    "gn:name":"Sonagwala",
    "gn:population":0,
    "gn:timezone":"Asia/Karachi",
    "iso:country":"PK",
    "name:und_x_variant":[
        "Soh\u0101gw\u0101la"
    ],
    "wof:name":"Sonagwala",
    "wof:placetype":"locality"
},
  "geometry": {"coordinates":[71.06113000000001,30.49012],"type":"Point"}
}