{
  "type": "Feature",
  "properties": {
    "gn:admin1_code":"04",
    "gn:asciiname":"Ladhewala",
    "gn:country_code":"PK",
    "gn:dem":249,
    "gn:feature_class":"P",
    "gn:feature_code":"PPL",
    "gn:name":"Ladhewala",
    "gn:population":0,
    "gn:timezone":"Asia/Karachi",
    "iso:country":"PK",
    "name:und_x_variant":[
        "Laddewala",
        "Ladew\u0101la",
        "Ladhewala"
    ],
    "wof:name":"Ladhewala",
    "wof:placetype":"locality"
},
  "geometry": {"coordinates":[74.95562,32.17486],"type":"Point"}
}