{
  "type": "Feature",
  "properties": {
    "gn:admin1_code":"4",
    "gn:asciiname":"Sanewali",
    "gn:country_code":"PK",
    "gn:dem":100,
    "gn:feature_class":"P",
    "gn:feature_code":"PPL",
    "gn:name":"Sanewali",
    "gn:population":0,
    "gn:timezone":"Asia/Karachi",
    "iso:country":"PK",
    "name:und_x_variant":[
        "Sonew\u0101li"
    ],
    "wof:name":"Sanewali",
    "wof:placetype":"locality"
},
  "geometry": {"coordinates":[70.86315,29.35604],"type":"Point"}
}