{
  "type": "Feature",
  "properties": {
    "gn:admin1_code":"5.0",
    "gn:asciiname":"Goth Ali Muhammad Amro",
    "gn:country_code":"PK",
    "gn:dem":11,
    "gn:feature_class":"P",
    "gn:feature_code":"PPL",
    "gn:name":"Goth Ali Muhammad Amro",
    "gn:population":0,
    "gn:timezone":"Asia/Karachi",
    "iso:country":"PK",
    "wof:name":"Goth Ali Muhammad Amro",
    "wof:placetype":"locality"
},
  "geometry": {"coordinates":[68.41159,24.81462],"type":"Point"}
}