{
  "type": "Feature",
  "properties": {
    "gn:admin1_code":"5",
    "gn:asciiname":"Goth Miani",
    "gn:country_code":"PK",
    "gn:dem":52,
    "gn:feature_class":"P",
    "gn:feature_code":"PPL",
    "gn:name":"Goth Miani",
    "gn:population":0,
    "gn:timezone":"Asia/Karachi",
    "iso:country":"PK",
    "name:und_x_variant":[
        "Mi\u0101ni"
    ],
    "wof:name":"Goth Miani",
    "wof:placetype":"locality"
},
  "geometry": {"coordinates":[68.34487,27.3194],"type":"Point"}
}