{
  "type": "Feature",
  "properties": {
    "gn:admin1_code":"4",
    "gn:asciiname":"Jlowali",
    "gn:country_code":"PK",
    "gn:dem":230,
    "gn:feature_class":"P",
    "gn:feature_code":"PPL",
    "gn:name":"Jlowali",
    "gn:population":0,
    "gn:timezone":"Asia/Karachi",
    "iso:country":"PK",
    "name:und_x_variant":[
        "Jalow\u0101li"
    ],
    "wof:name":"Jlowali",
    "wof:placetype":"locality"
},
  "geometry": {"coordinates":[74.59312,32.10811],"type":"Point"}
}