{
  "type": "Feature",
  "properties": {
    "gn:admin1_code":"2.0",
    "gn:asciiname":"Meti",
    "gn:country_code":"PK",
    "gn:dem":1403,
    "gn:feature_class":"P",
    "gn:feature_code":"PPL",
    "gn:name":"Meti",
    "gn:population":0,
    "gn:timezone":"Asia/Karachi",
    "iso:country":"PK",
    "wof:name":"Meti",
    "wof:placetype":"locality"
},
  "geometry": {"coordinates":[65.85361,27.70425],"type":"Point"}
}