{
  "type": "Feature",
  "properties": {
    "gn:admin1_code":"7.0",
    "gn:asciiname":"Baklit",
    "gn:country_code":"PK",
    "gn:dem":3081,
    "gn:feature_class":"P",
    "gn:feature_code":"PPL",
    "gn:name":"Baklit",
    "gn:population":0,
    "gn:timezone":"Asia/Karachi",
    "iso:country":"PK",
    "wof:name":"Baklit",
    "wof:placetype":"locality"
},
  "geometry": {"coordinates":[74.04411,35.1908],"type":"Point"}
}