{
  "type": "Feature",
  "properties": {
    "gn:admin1_code":"03",
    "gn:asciiname":"Muhammad Akbar",
    "gn:country_code":"PK",
    "gn:dem":255,
    "gn:feature_class":"P",
    "gn:feature_code":"PPL",
    "gn:name":"Muhammad Akbar",
    "gn:population":0,
    "gn:timezone":"Asia/Karachi",
    "iso:country":"PK",
    "name:und_x_variant":[
        "Mohammad Akbar",
        "Muhammad Akbar"
    ],
    "wof:name":"Muhammad Akbar",
    "wof:placetype":"locality"
},
  "geometry": {"coordinates":[70.54231999999998,32.3433],"type":"Point"}
}