{
  "type": "Feature",
  "properties": {
    "gn:admin1_code":"5.0",
    "gn:asciiname":"Ghendahu",
    "gn:country_code":"PK",
    "gn:dem":50,
    "gn:feature_class":"P",
    "gn:feature_code":"PPL",
    "gn:name":"Ghendahu",
    "gn:population":0,
    "gn:timezone":"Asia/Karachi",
    "iso:country":"PK",
    "name:und_x_variant":[
        "Gend\u0101hu"
    ],
    "wof:name":"Ghendahu",
    "wof:placetype":"locality"
},
  "geometry": {"coordinates":[69.09999999999999,27.18333],"type":"Point"}
}