{
  "type": "Feature",
  "properties": {
    "gn:admin1_code":"3.0",
    "gn:asciiname":"Behari",
    "gn:country_code":"PK",
    "gn:dem":2363,
    "gn:feature_class":"P",
    "gn:feature_code":"PPL",
    "gn:name":"Behari",
    "gn:population":0,
    "gn:timezone":"Asia/Karachi",
    "iso:country":"PK",
    "wof:name":"Behari",
    "wof:placetype":"locality"
},
  "geometry": {"coordinates":[73.63302,34.74566],"type":"Point"}
}