{
  "type": "Feature",
  "properties": {
    "gn:admin1_code":"3.0",
    "gn:asciiname":"Batgram",
    "gn:country_code":"PK",
    "gn:dem":927,
    "gn:feature_class":"P",
    "gn:feature_code":"PPL",
    "gn:name":"Batgram",
    "gn:population":0,
    "gn:timezone":"Asia/Karachi",
    "iso:country":"PK",
    "wof:name":"Batgram",
    "wof:placetype":"locality"
},
  "geometry": {"coordinates":[73.20081,34.44621],"type":"Point"}
}