{
  "type": "Feature",
  "properties": {
    "gn:admin1_code":"3",
    "gn:asciiname":"Biran Gali",
    "gn:country_code":"PK",
    "gn:dem":2144,
    "gn:feature_class":"P",
    "gn:feature_code":"PPL",
    "gn:name":"Biran Gali",
    "gn:population":0,
    "gn:timezone":"Asia/Karachi",
    "iso:country":"PK",
    "name:und_x_variant":[
        "Barnagiala"
    ],
    "wof:name":"Biran Gali",
    "wof:placetype":"locality"
},
  "geometry": {"coordinates":[73.36201,34.18141],"type":"Point"}
}