{
  "type": "Feature",
  "properties": {
    "gn:admin1_code":"4",
    "gn:asciiname":"Shahi Sherki Khangah",
    "gn:country_code":"PK",
    "gn:dem":115,
    "gn:feature_class":"P",
    "gn:feature_code":"PPL",
    "gn:name":"Shahi Sherki Khangah",
    "gn:population":0,
    "gn:timezone":"Asia/Karachi",
    "iso:country":"PK",
    "name:eng_x_preferred":[
        "Sh\u0101hni Sher ki Kh\u0101ng\u0101h"
    ],
    "wof:name":"Shahi Sherki Khangah",
    "wof:placetype":"locality"
},
  "geometry": {"coordinates":[71.68340000000001,29.50221],"type":"Point"}
}