{
  "type": "Feature",
  "properties": {
    "gn:admin1_code":"4.0",
    "gn:asciiname":"Bangrial",
    "gn:country_code":"PK",
    "gn:dem":555,
    "gn:feature_class":"P",
    "gn:feature_code":"PPL",
    "gn:name":"Bangrial",
    "gn:population":0,
    "gn:timezone":"Asia/Karachi",
    "iso:country":"PK",
    "wof:name":"Bangrial",
    "wof:placetype":"locality"
},
  "geometry": {"coordinates":[73.17525999999999,33.4977],"type":"Point"}
}