{
  "type": "Feature",
  "properties": {
    "gn:admin1_code":"5",
    "gn:asciiname":"Goth Bhuro Mangrio",
    "gn:country_code":"PK",
    "gn:dem":28,
    "gn:feature_class":"P",
    "gn:feature_code":"PPL",
    "gn:name":"Goth Bhuro Mangrio",
    "gn:population":0,
    "gn:timezone":"Asia/Karachi",
    "iso:country":"PK",
    "name:und_x_variant":[
        "Goth Bhuro Mangario"
    ],
    "wof:name":"Goth Bhuro Mangrio",
    "wof:placetype":"locality"
},
  "geometry": {"coordinates":[68.5104,25.95333],"type":"Point"}
}