{
  "type": "Feature",
  "properties": {
    "gn:admin1_code":"04",
    "gn:asciiname":"Pind Surial",
    "gn:country_code":"PK",
    "gn:dem":374,
    "gn:feature_class":"P",
    "gn:feature_code":"PPL",
    "gn:name":"Pind Surial",
    "gn:population":0,
    "gn:timezone":"Asia/Karachi",
    "iso:country":"PK",
    "name:und_x_variant":[
        "Pindi Sarhal",
        "Pindi Sir\u0101l",
        "Pind Surial"
    ],
    "wof:name":"Pind Surial",
    "wof:placetype":"locality"
},
  "geometry": {"coordinates":[72.17024000000001,33.58136],"type":"Point"}
}