{
  "type": "Feature",
  "properties": {
    "gn:admin1_code":"4",
    "gn:asciiname":"Ludhranwali Basti",
    "gn:country_code":"PK",
    "gn:dem":136,
    "gn:feature_class":"P",
    "gn:feature_code":"PPL",
    "gn:name":"Ludhranwali Basti",
    "gn:population":0,
    "gn:timezone":"Asia/Karachi",
    "iso:country":"PK",
    "name:und_x_variant":[
        "Luthrew\u0101li"
    ],
    "wof:name":"Ludhranwali Basti",
    "wof:placetype":"locality"
},
  "geometry": {"coordinates":[72.37253,29.66952],"type":"Point"}
}