{
  "type": "Feature",
  "properties": {
    "gn:admin1_code":"3",
    "gn:asciiname":"Banda Paik Kalle",
    "gn:country_code":"PK",
    "gn:dem":404,
    "gn:feature_class":"P",
    "gn:feature_code":"PPL",
    "gn:name":"Banda Paik Kalle",
    "gn:population":0,
    "gn:timezone":"Asia/Karachi",
    "iso:country":"PK",
    "name:und_x_variant":[
        "B\u0101nda Paik Kili"
    ],
    "wof:name":"Banda Paik Kalle",
    "wof:placetype":"locality"
},
  "geometry": {"coordinates":[70.92004,33.03397],"type":"Point"}
}