{
  "type": "Feature",
  "properties": {
    "gn:admin1_code":"3.0",
    "gn:asciiname":"Chamak Maira",
    "gn:country_code":"PK",
    "gn:dem":901,
    "gn:feature_class":"P",
    "gn:feature_code":"PPL",
    "gn:name":"Chamak Maira",
    "gn:population":0,
    "gn:timezone":"Asia/Karachi",
    "iso:country":"PK",
    "name:und_x_variant":[
        "Chamak Mera",
        "Chamak Maira"
    ],
    "wof:name":"Chamak Maira",
    "wof:placetype":"locality"
},
  "geometry": {"coordinates":[73.10096,34.11985],"type":"Point"}
}