{
  "type": "Feature",
  "properties": {
    "gn:admin1_code":"5",
    "gn:asciiname":"Goth Aryani",
    "gn:country_code":"PK",
    "gn:dem":68,
    "gn:feature_class":"P",
    "gn:feature_code":"PPL",
    "gn:name":"Goth Aryani",
    "gn:population":0,
    "gn:timezone":"Asia/Karachi",
    "iso:country":"PK",
    "name:und_x_variant":[
        "Goth Arb\u0101ni"
    ],
    "wof:name":"Goth Aryani",
    "wof:placetype":"locality"
},
  "geometry": {"coordinates":[69.34393,27.82667],"type":"Point"}
}