{
  "type": "Feature",
  "properties": {
    "gn:admin1_code":"3",
    "gn:asciiname":"Mian Band",
    "gn:country_code":"PK",
    "gn:dem":1075,
    "gn:feature_class":"P",
    "gn:feature_code":"PPL",
    "gn:name":"Mian Band",
    "gn:population":0,
    "gn:timezone":"Asia/Karachi",
    "iso:country":"PK",
    "name:und_x_variant":[
        "Dark\u0101la"
    ],
    "wof:name":"Mian Band",
    "wof:placetype":"locality"
},
  "geometry": {"coordinates":[72.94606,34.29771],"type":"Point"}
}