{
  "type": "Feature",
  "properties": {
    "gn:admin1_code":"3",
    "gn:asciiname":"Mian Band",
    "gn:country_code":"PK",
    "gn:dem":1075,
    "gn:feature_class":"P",
    "gn:feature_code":"PPL",
    "gn:name":"Mian Band",
    "gn:population":0,
    "gn:timezone":"Asia/Karachi",
    "iso:country":"PK",
    "name:ceb_x_preferred":[
        "M\u012b\u0101n Band"
    ],
    "name:fas_x_preferred":[
        "\u0645\u06cc\u0627\u0646 \u0628\u0646\u062f"
    ],
    "name:swe_x_preferred":[
        "M\u012b\u0101n Band"
    ],
    "name:und_x_variant":[
        "Dark\u0101la"
    ],
    "wof:name":"Mian Band",
    "wof:placetype":"locality"
},
  "geometry": {"coordinates":[72.94606,34.29771],"type":"Point"}
}