{
  "type": "Feature",
  "properties": {
    "gn:admin1_code":"4.0",
    "gn:asciiname":"Chak Eighty-three B Thal Development Authority",
    "gn:country_code":"PK",
    "gn:dem":159,
    "gn:feature_class":"P",
    "gn:feature_code":"PPL",
    "gn:name":"Chak Eighty-three B Thal Development Authority",
    "gn:population":0,
    "gn:timezone":"Asia/Karachi",
    "iso:country":"PK",
    "name:und_x_variant":[
        "Chak Eighty-Three TDA",
        "Chak 83 TDA",
        "Chak Eighty-three B Thal Development Authority"
    ],
    "wof:name":"Chak Eighty-three B Thal Development Authority",
    "wof:placetype":"locality"
},
  "geometry": {"coordinates":[71.0018,31.29337],"type":"Point"}
}