{
  "type": "Feature",
  "properties": {
    "gn:admin1_code":"2.0",
    "gn:asciiname":"Kili Haji Rashid Khan",
    "gn:country_code":"PK",
    "gn:dem":1477,
    "gn:feature_class":"P",
    "gn:feature_code":"PPL",
    "gn:name":"Kili Haji Rashid Khan",
    "gn:population":0,
    "gn:timezone":"Asia/Karachi",
    "iso:country":"PK",
    "wof:name":"Kili Haji Rashid Khan",
    "wof:placetype":"locality"
},
  "geometry": {"coordinates":[66.48143,30.47329],"type":"Point"}
}