{
  "type": "Feature",
  "properties": {
    "gn:admin1_code":"04",
    "gn:asciiname":"Kurelke",
    "gn:country_code":"PK",
    "gn:dem":215,
    "gn:feature_class":"P",
    "gn:feature_code":"PPL",
    "gn:name":"Kurelke",
    "gn:population":0,
    "gn:timezone":"Asia/Karachi",
    "iso:country":"PK",
    "name:und_x_variant":[
        "K\u016breike",
        "Kuralke",
        "Kurelke"
    ],
    "wof:name":"Kurelke",
    "wof:placetype":"locality"
},
  "geometry": {"coordinates":[73.89976,31.91252],"type":"Point"}
}