{
  "type": "Feature",
  "properties": {
    "gn:admin1_code":"4",
    "gn:asciiname":"Pirwala",
    "gn:country_code":"PK",
    "gn:dem":128,
    "gn:feature_class":"P",
    "gn:feature_code":"PPL",
    "gn:name":"Pirwala",
    "gn:population":0,
    "gn:timezone":"Asia/Karachi",
    "iso:country":"PK",
    "name:und_x_variant":[
        "Ch\u0101ndia",
        "Chandiah",
        "Pirwala"
    ],
    "wof:name":"Pirwala",
    "wof:placetype":"locality"
},
  "geometry": {"coordinates":[71.25360999999999,30.41171],"type":"Point"}
}