{
  "type": "Feature",
  "properties": {
    "gn:admin1_code":"7.0",
    "gn:asciiname":"Tarangzong Khoku",
    "gn:country_code":"PK",
    "gn:dem":2477,
    "gn:feature_class":"P",
    "gn:feature_code":"PPL",
    "gn:name":"Tarangzong Khoku",
    "gn:population":0,
    "gn:timezone":"Asia/Karachi",
    "iso:country":"PK",
    "wof:name":"Tarangzong Khoku",
    "wof:placetype":"locality"
},
  "geometry": {"coordinates":[76.22892,35.24673],"type":"Point"}
}