{
  "type": "Feature",
  "properties": {
    "gn:admin1_code":"4.0",
    "gn:asciiname":"Chah Shaikh Jiwand",
    "gn:country_code":"PK",
    "gn:dem":135,
    "gn:feature_class":"P",
    "gn:feature_code":"PPL",
    "gn:name":"Chah Shaikh Jiwand",
    "gn:population":0,
    "gn:timezone":"Asia/Karachi",
    "iso:country":"PK",
    "wof:name":"Chah Shaikh Jiwand",
    "wof:placetype":"locality"
},
  "geometry": {"coordinates":[70.78140999999999,30.63007],"type":"Point"}
}