{
  "type": "Feature",
  "properties": {
    "iso:country":"PK",
    "qs:gn_pop":0,
    "qs:name":"Goth-natkhe-khan",
    "qs:name_adm0":"Pakistan",
    "qs:name_adm1":"Sindh",
    "qs:photos":66,
    "qs:photos_1k":13,
    "qs:photos_9k":1,
    "qs:photos_9r":2,
    "qs:photos_all":66,
    "qs:photos_sr":2,
    "qs:placetype":"Town",
    "qs:pop_sr":"0",
    "qs:woe_adm0":23424922,
    "wof:name":"Goth-natkhe-khan",
    "wof:placetype":"locality"
},
  "geometry": {"coordinates":[67.123718,24.88519],"type":"Point"}
}