{
  "type": "Feature",
  "properties": {
    "gn:admin1_code":"4",
    "gn:asciiname":"Pipli Pahar",
    "gn:country_code":"PK",
    "gn:dem":169,
    "gn:feature_class":"P",
    "gn:feature_code":"PPL",
    "gn:name":"Pipli Pahar",
    "gn:population":0,
    "gn:timezone":"Asia/Karachi",
    "iso:country":"PK",
    "wof:name":"Pipli Pahar",
    "wof:placetype":"locality"
},
  "geometry": {"coordinates":[73.50782,30.64898],"type":"Point"}
}