{
  "type": "Feature",
  "properties": {
    "gn:admin1_code":"2.0",
    "gn:asciiname":"Goth Jumma Khan",
    "gn:country_code":"PK",
    "gn:dem":1624,
    "gn:feature_class":"P",
    "gn:feature_code":"PPL",
    "gn:name":"Goth Jumma Khan",
    "gn:population":0,
    "gn:timezone":"Asia/Karachi",
    "iso:country":"PK",
    "wof:name":"Goth Jumma Khan",
    "wof:placetype":"locality"
},
  "geometry": {"coordinates":[66.17506,28.10592],"type":"Point"}
}