{
  "type": "Feature",
  "properties": {
    "gn:admin1_code":"04",
    "gn:asciiname":"Sultan Thiraj",
    "gn:country_code":"PK",
    "gn:dem":142,
    "gn:feature_class":"P",
    "gn:feature_code":"PPL",
    "gn:name":"Sultan Thiraj",
    "gn:population":0,
    "gn:timezone":"Asia/Karachi",
    "iso:country":"PK",
    "name:und_x_variant":[
        "Sultan Tharoj",
        "Sultan Thiraj"
    ],
    "wof:name":"Sultan Thiraj",
    "wof:placetype":"locality"
},
  "geometry": {"coordinates":[72.07992,30.59104],"type":"Point"}
}