{
  "type": "Feature",
  "properties": {
    "gn:admin1_code":"5",
    "gn:asciiname":"Goth Khair Muhammad Sarawal",
    "gn:country_code":"PK",
    "gn:dem":24,
    "gn:feature_class":"P",
    "gn:feature_code":"PPL",
    "gn:name":"Goth Khair Muhammad Sarawal",
    "gn:population":0,
    "gn:timezone":"Asia/Karachi",
    "iso:country":"PK",
    "name:und_x_variant":[
        "Goth Khair Muhammad Sarew\u0101l",
        "Goth Buzd\u0101r Kh\u0101 Muhammad Sarew\u0101l"
    ],
    "wof:name":"Goth Khair Muhammad Sarawal",
    "wof:placetype":"locality"
},
  "geometry": {"coordinates":[68.70581,25.95194],"type":"Point"}
}