{
  "type": "Feature",
  "properties": {
    "gn:admin1_code":"3",
    "gn:asciiname":"Satal Cham",
    "gn:country_code":"PK",
    "gn:dem":1398,
    "gn:feature_class":"P",
    "gn:feature_code":"PPL",
    "gn:name":"Satal Cham",
    "gn:population":0,
    "gn:timezone":"Asia/Karachi",
    "iso:country":"PK",
    "name:und_x_variant":[
        "Sat\u0101ni Cham",
        "Satal Cham"
    ],
    "wof:name":"Satal Cham",
    "wof:placetype":"locality"
},
  "geometry": {"coordinates":[72.53048000000003,35.16992],"type":"Point"}
}