{
  "type": "Feature",
  "properties": {
    "gn:admin1_code":"5",
    "gn:asciiname":"Goth Chaudhry Ali Ahmad",
    "gn:country_code":"PK",
    "gn:dem":11,
    "gn:feature_class":"P",
    "gn:feature_code":"PPL",
    "gn:name":"Goth Chaudhry Ali Ahmad",
    "gn:population":0,
    "gn:timezone":"Asia/Karachi",
    "iso:country":"PK",
    "name:und_x_variant":[
        "Chaudhri Ali Muhammad"
    ],
    "wof:name":"Goth Chaudhry Ali Ahmad",
    "wof:placetype":"locality"
},
  "geometry": {"coordinates":[69.25869,24.77045],"type":"Point"}
}