{
  "type": "Feature",
  "properties": {
    "gn:admin1_code":"4",
    "gn:asciiname":"Chak Seventy-four/Two",
    "gn:country_code":"PK",
    "gn:dem":182,
    "gn:feature_class":"P",
    "gn:feature_code":"PPL",
    "gn:name":"Chak Seventy-four/Two",
    "gn:population":0,
    "gn:timezone":"Asia/Karachi",
    "iso:country":"PK",
    "name:und_x_variant":[
        "Baj\u0101z",
        "Baj\u0101j"
    ],
    "wof:name":"Chak Seventy-four/Two",
    "wof:placetype":"locality"
},
  "geometry": {"coordinates":[73.44683000000001,31.15436],"type":"Point"}
}