{
  "type": "Feature",
  "properties": {
    "gn:admin1_code":"5.0",
    "gn:asciiname":"Nurani",
    "gn:country_code":"PK",
    "gn:dem":117,
    "gn:feature_class":"P",
    "gn:feature_code":"PPL",
    "gn:name":"Nurani",
    "gn:population":0,
    "gn:timezone":"Asia/Karachi",
    "iso:country":"PK",
    "name:kan_x_preferred":[
        "\u0ca8\u0cc1\u0cb0\u0cbe\u0ca3\u0cbf"
    ],
    "wof:name":"Nurani",
    "wof:placetype":"locality"
},
  "geometry": {"coordinates":[70.45045999999998,25.40439],"type":"Point"}
}