{
  "type": "Feature",
  "properties": {
    "gn:admin1_code":"3",
    "gn:asciiname":"Lakai",
    "gn:country_code":"PK",
    "gn:dem":1154,
    "gn:feature_class":"P",
    "gn:feature_code":"PPL",
    "gn:name":"Lakai",
    "gn:population":0,
    "gn:timezone":"Asia/Karachi",
    "iso:country":"PK",
    "name:ceb_x_preferred":[
        "Lakai"
    ],
    "wof:name":"Lakai",
    "wof:placetype":"locality"
},
  "geometry": {"coordinates":[72.03896999999998,34.88235],"type":"Point"}
}