{
  "type": "Feature",
  "properties": {
    "gn:admin1_code":"5.0",
    "gn:asciiname":"Goth Mazar Brahui",
    "gn:country_code":"PK",
    "gn:dem":54,
    "gn:feature_class":"P",
    "gn:feature_code":"PPL",
    "gn:name":"Goth Mazar Brahui",
    "gn:population":0,
    "gn:timezone":"Asia/Karachi",
    "iso:country":"PK",
    "name:und_x_variant":[
        "Goth Maz\u0101r Brah\u016bl"
    ],
    "wof:name":"Goth Mazar Brahui",
    "wof:placetype":"locality"
},
  "geometry": {"coordinates":[68.29567,27.75572],"type":"Point"}
}