{
  "type": "Feature",
  "properties": {
    "gn:admin1_code":"6",
    "gn:asciiname":"Ghasitpur",
    "gn:country_code":"PK",
    "gn:dem":242,
    "gn:feature_class":"P",
    "gn:feature_code":"PPL",
    "gn:name":"Ghasitpur",
    "gn:population":0,
    "gn:timezone":"Asia/Karachi",
    "iso:country":"PK",
    "wof:name":"Ghasitpur",
    "wof:placetype":"locality"
},
  "geometry": {"coordinates":[73.78456,33.04482],"type":"Point"}
}