{
  "type": "Feature",
  "properties": {
    "gn:admin1_code":"4",
    "gn:asciiname":"Block Six",
    "gn:country_code":"PK",
    "gn:dem":155,
    "gn:feature_class":"P",
    "gn:feature_code":"PPL",
    "gn:name":"Block Six",
    "gn:population":0,
    "gn:timezone":"Asia/Karachi",
    "iso:country":"PK",
    "name:und_x_variant":[
        "Chak Nineteen-Thirteen L"
    ],
    "wof:name":"Block Six",
    "wof:placetype":"locality"
},
  "geometry": {"coordinates":[72.56093,30.50245],"type":"Point"}
}