{
  "type": "Feature",
  "properties": {
    "gn:admin1_code":"5",
    "gn:asciiname":"Goth Tarar",
    "gn:country_code":"PK",
    "gn:dem":68,
    "gn:feature_class":"P",
    "gn:feature_code":"PPL",
    "gn:name":"Goth Tarar",
    "gn:population":0,
    "gn:timezone":"Asia/Karachi",
    "iso:country":"PK",
    "name:und_x_variant":[
        "Goth Terar"
    ],
    "wof:name":"Goth Tarar",
    "wof:placetype":"locality"
},
  "geometry": {"coordinates":[69.42976,27.87789],"type":"Point"}
}