{
  "type": "Feature",
  "properties": {
    "gn:admin1_code":"01",
    "gn:asciiname":"Kinra Darra",
    "gn:country_code":"PK",
    "gn:dem":855,
    "gn:feature_class":"P",
    "gn:feature_code":"PPL",
    "gn:name":"Kinra Darra",
    "gn:population":0,
    "gn:timezone":"Asia/Karachi",
    "iso:country":"PK",
    "name:eng_x_preferred":[
        "Kinra Darra"
    ],
    "wof:name":"Kinra Darra",
    "wof:placetype":"locality"
},
  "geometry": {"coordinates":[71.58294000000002,34.58448],"type":"Point"}
}