{
  "type": "Feature",
  "properties": {
    "gn:admin1_code":"4.0",
    "gn:asciiname":"Basti Jam Sher Mand",
    "gn:country_code":"PK",
    "gn:dem":87,
    "gn:feature_class":"P",
    "gn:feature_code":"PPL",
    "gn:name":"Basti Jam Sher Mand",
    "gn:population":0,
    "gn:timezone":"Asia/Karachi",
    "iso:country":"PK",
    "name:und_x_variant":[
        "Basti J\u0101m Sher M\u0101nu"
    ],
    "wof:name":"Basti Jam Sher Mand",
    "wof:placetype":"locality"
},
  "geometry": {"coordinates":[70.48049,28.66071],"type":"Point"}
}