{
  "type": "Feature",
  "properties": {
    "gn:admin1_code":"5",
    "gn:asciiname":"Goth Lalhar",
    "gn:country_code":"PK",
    "gn:dem":53,
    "gn:feature_class":"P",
    "gn:feature_code":"PPL",
    "gn:name":"Goth Lalhar",
    "gn:population":0,
    "gn:timezone":"Asia/Karachi",
    "iso:country":"PK",
    "wof:name":"Goth Lalhar",
    "wof:placetype":"locality"
},
  "geometry": {"coordinates":[67.47589000000001,26.95488],"type":"Point"}
}