{
  "type": "Feature",
  "properties": {
    "gn:admin1_code":"5.0",
    "gn:asciiname":"Goth Shaji Khan Chandio",
    "gn:country_code":"PK",
    "gn:dem":45,
    "gn:feature_class":"P",
    "gn:feature_code":"PPL",
    "gn:name":"Goth Shaji Khan Chandio",
    "gn:population":0,
    "gn:timezone":"Asia/Karachi",
    "iso:country":"PK",
    "name:und_x_variant":[
        "Sh\u0101hi Kh\u0101n"
    ],
    "wof:name":"Goth Shaji Khan Chandio",
    "wof:placetype":"locality"
},
  "geometry": {"coordinates":[67.6846,27.05748],"type":"Point"}
}