{
  "type": "Feature",
  "properties": {
    "gn:admin1_code":"5.0",
    "gn:asciiname":"Waryam Khan Brahui",
    "gn:country_code":"PK",
    "gn:dem":64,
    "gn:feature_class":"P",
    "gn:feature_code":"PPL",
    "gn:name":"Waryam Khan Brahui",
    "gn:population":0,
    "gn:timezone":"Asia/Karachi",
    "iso:country":"PK",
    "name:und_x_variant":[
        "Wary\u0101m Kh\u0101n Brahul"
    ],
    "wof:name":"Waryam Khan Brahui",
    "wof:placetype":"locality"
},
  "geometry": {"coordinates":[68.93297,28.35365],"type":"Point"}
}