{
  "type": "Feature",
  "properties": {
    "gn:admin1_code":"2.0",
    "gn:asciiname":"Kili Karez",
    "gn:country_code":"PK",
    "gn:dem":1775,
    "gn:feature_class":"P",
    "gn:feature_code":"PPL",
    "gn:name":"Kili Karez",
    "gn:population":0,
    "gn:timezone":"Asia/Karachi",
    "iso:country":"PK",
    "name:und_x_variant":[
        "K\u0101rez Kili",
        "Kili Karez"
    ],
    "wof:name":"Kili Karez",
    "wof:placetype":"locality"
},
  "geometry": {"coordinates":[69.53228,31.15613],"type":"Point"}
}