{
  "type": "Feature",
  "properties": {
    "gn:admin1_code":"2.0",
    "gn:asciiname":"Gulzar",
    "gn:country_code":"PK",
    "gn:dem":1679,
    "gn:feature_class":"P",
    "gn:feature_code":"PPL",
    "gn:name":"Gulzar",
    "gn:population":0,
    "gn:timezone":"Asia/Karachi",
    "iso:country":"PK",
    "name:und_x_variant":[
        "Kili Gulz\u0101r",
        "Gulzar"
    ],
    "wof:name":"Gulzar",
    "wof:placetype":"locality"
},
  "geometry": {"coordinates":[66.95313,30.15657],"type":"Point"}
}