{
  "type": "Feature",
  "properties": {
    "gn:admin1_code":"5.0",
    "gn:asciiname":"Chang",
    "gn:country_code":"PK",
    "gn:dem":12,
    "gn:feature_class":"P",
    "gn:feature_code":"PPL",
    "gn:name":"Chang",
    "gn:population":0,
    "gn:timezone":"Asia/Karachi",
    "iso:country":"PK",
    "name:cat_x_preferred":[
        "Chang"
    ],
    "name:ceb_x_preferred":[
        "Chang"
    ],
    "name:ces_x_preferred":[
        "Chang"
    ],
    "name:deu_x_preferred":[
        "Chang"
    ],
    "name:fin_x_preferred":[
        "Chang"
    ],
    "name:fra_x_preferred":[
        "Chang"
    ],
    "name:hye_x_preferred":[
        "\u0536\u0561\u0576\u0563"
    ],
    "name:ita_x_preferred":[
        "Chang"
    ],
    "name:jpn_x_preferred":[
        "\u30c1\u30e3\u30f3"
    ],
    "name:nld_x_preferred":[
        "Chang"
    ],
    "name:pol_x_preferred":[
        "Chang"
    ],
    "name:rus_x_preferred":[
        "\u0427\u0430\u043d\u0433"
    ],
    "name:swe_x_preferred":[
        "Chang"
    ],
    "name:ukr_x_preferred":[
        "\u0427\u0430\u043d\u0433"
    ],
    "wof:name":"Chang",
    "wof:placetype":"locality"
},
  "geometry": {"coordinates":[68.67073000000001,24.93559],"type":"Point"}
}