{
  "type": "Feature",
  "properties": {
    "gn:admin1_code":"6",
    "gn:asciiname":"Kakota",
    "gn:country_code":"PK",
    "gn:dem":1464,
    "gn:feature_class":"P",
    "gn:feature_code":"PPL",
    "gn:name":"Kakota",
    "gn:population":0,
    "gn:timezone":"Asia/Karachi",
    "iso:country":"PK",
    "name:und_x_variant":[
        "Kagot",
        "Kag\u016bta"
    ],
    "wof:name":"Kakota",
    "wof:placetype":"locality"
},
  "geometry": {"coordinates":[74.03189999999999,33.80959],"type":"Point"}
}