{
  "type": "Feature",
  "properties": {
    "gn:admin1_code":"5.0",
    "gn:asciiname":"Ali Gul Junejo",
    "gn:country_code":"PK",
    "gn:dem":37,
    "gn:feature_class":"P",
    "gn:feature_code":"PPL",
    "gn:name":"Ali Gul Junejo",
    "gn:population":0,
    "gn:timezone":"Asia/Karachi",
    "iso:country":"PK",
    "name:und_x_variant":[
        "Ali Gul Juneja"
    ],
    "wof:name":"Ali Gul Junejo",
    "wof:placetype":"locality"
},
  "geometry": {"coordinates":[68.15375999999999,26.44177],"type":"Point"}
}