{
  "type": "Feature",
  "properties": {
    "gn:admin1_code":"4.0",
    "gn:asciiname":"Fatehpur Punjabian",
    "gn:country_code":"PK",
    "gn:dem":86,
    "gn:feature_class":"P",
    "gn:feature_code":"PPL",
    "gn:name":"Fatehpur Punjabian",
    "gn:population":0,
    "gn:timezone":"Asia/Karachi",
    "iso:country":"PK",
    "name:und_x_variant":[
        "Fatehpur Ar\u0101\u012b\u0101n",
        "Fatehpur"
    ],
    "wof:name":"Fatehpur Punjabian",
    "wof:placetype":"locality"
},
  "geometry": {"coordinates":[70.24984000000001,28.51165],"type":"Point"}
}