{
  "type": "Feature",
  "properties": {
    "gn:admin1_code":"3.0",
    "gn:asciiname":"Dheri Kalle",
    "gn:country_code":"PK",
    "gn:dem":301,
    "gn:feature_class":"P",
    "gn:feature_code":"PPL",
    "gn:name":"Dheri Kalle",
    "gn:population":0,
    "gn:timezone":"Asia/Karachi",
    "iso:country":"PK",
    "name:eng_x_preferred":[
        "Dheri Kili"
    ],
    "wof:name":"Dheri Kalle",
    "wof:placetype":"locality"
},
  "geometry": {"coordinates":[71.79586999999999,34.14215],"type":"Point"}
}