{
  "type": "Feature",
  "properties": {
    "gn:admin1_code":"4.0",
    "gn:asciiname":"Thanail Fathoi",
    "gn:country_code":"PK",
    "gn:dem":522,
    "gn:feature_class":"P",
    "gn:feature_code":"PPL",
    "gn:name":"Thanail Fathoi",
    "gn:population":0,
    "gn:timezone":"Asia/Karachi",
    "iso:country":"PK",
    "name:und_x_variant":[
        "Thanil Fathui"
    ],
    "wof:name":"Thanail Fathoi",
    "wof:placetype":"locality"
},
  "geometry": {"coordinates":[72.84799,32.97401],"type":"Point"}
}