{
  "type": "Feature",
  "properties": {
    "gn:admin1_code":"03",
    "gn:asciiname":"Panian",
    "gn:country_code":"PK",
    "gn:dem":470,
    "gn:feature_class":"P",
    "gn:feature_code":"PPL",
    "gn:name":"Panian",
    "gn:population":0,
    "gn:timezone":"Asia/Karachi",
    "iso:country":"PK",
    "name:und_x_variant":[
        "Panyan",
        "Panian"
    ],
    "wof:name":"Panian",
    "wof:placetype":"locality"
},
  "geometry": {"coordinates":[72.8511,33.9731],"type":"Point"}
}