{
  "type": "Feature",
  "properties": {
    "gn:admin1_code":"2.0",
    "gn:asciiname":"Jatkabad",
    "gn:country_code":"PK",
    "gn:dem":1926,
    "gn:feature_class":"P",
    "gn:feature_code":"PPL",
    "gn:name":"Jatkabad",
    "gn:population":0,
    "gn:timezone":"Asia/Karachi",
    "iso:country":"PK",
    "wof:name":"Jatkabad",
    "wof:placetype":"locality"
},
  "geometry": {"coordinates":[66.59198000000001,29.16552],"type":"Point"}
}