{
  "type": "Feature",
  "properties": {
    "gn:admin1_code":"5.0",
    "gn:asciiname":"Mithu Memon",
    "gn:country_code":"PK",
    "gn:dem":12,
    "gn:feature_class":"P",
    "gn:feature_code":"PPL",
    "gn:name":"Mithu Memon",
    "gn:population":0,
    "gn:timezone":"Asia/Karachi",
    "iso:country":"PK",
    "wof:name":"Mithu Memon",
    "wof:placetype":"locality"
},
  "geometry": {"coordinates":[68.64825,24.66755],"type":"Point"}
}