{
  "type": "Feature",
  "properties": {
    "gn:admin1_code":"5",
    "gn:asciiname":"Goth Haji Khan Talpur",
    "gn:country_code":"PK",
    "gn:dem":20,
    "gn:feature_class":"P",
    "gn:feature_code":"PPL",
    "gn:name":"Goth Haji Khan Talpur",
    "gn:population":0,
    "gn:timezone":"Asia/Karachi",
    "iso:country":"PK",
    "name:und_x_variant":[
        "Goth H\u0101ji T\u0101lpur"
    ],
    "wof:name":"Goth Haji Khan Talpur",
    "wof:placetype":"locality"
},
  "geometry": {"coordinates":[68.89391999999999,25.61366],"type":"Point"}
}