{
  "type": "Feature",
  "properties": {
    "gn:admin1_code":"4.0",
    "gn:asciiname":"Chhoi",
    "gn:country_code":"PK",
    "gn:dem":819,
    "gn:feature_class":"P",
    "gn:feature_code":"PPL",
    "gn:name":"Chhoi",
    "gn:population":0,
    "gn:timezone":"Asia/Karachi",
    "iso:country":"PK",
    "wof:name":"Chhoi",
    "wof:placetype":"locality"
},
  "geometry": {"coordinates":[72.23076999999998,32.52009],"type":"Point"}
}