{
  "type": "Feature",
  "properties": {
    "gn:admin1_code":"5.0",
    "gn:asciiname":"Goth Ghulam Rasul Babar",
    "gn:country_code":"PK",
    "gn:dem":21,
    "gn:feature_class":"P",
    "gn:feature_code":"PPL",
    "gn:name":"Goth Ghulam Rasul Babar",
    "gn:population":0,
    "gn:timezone":"Asia/Karachi",
    "iso:country":"PK",
    "wof:name":"Goth Ghulam Rasul Babar",
    "wof:placetype":"locality"
},
  "geometry": {"coordinates":[68.25249000000001,25.10388],"type":"Point"}
}