{
  "type": "Feature",
  "properties": {
    "gn:admin1_code":"3.0",
    "gn:asciiname":"Gidor",
    "gn:country_code":"PK",
    "gn:dem":2534,
    "gn:feature_class":"P",
    "gn:feature_code":"PPL",
    "gn:name":"Gidor",
    "gn:population":0,
    "gn:timezone":"Asia/Karachi",
    "iso:country":"PK",
    "wof:name":"Gidor",
    "wof:placetype":"locality"
},
  "geometry": {"coordinates":[73.06834000000001,35.096],"type":"Point"}
}