{
  "type": "Feature",
  "properties": {
    "gn:admin1_code":"1.0",
    "gn:asciiname":"Halalai",
    "gn:country_code":"PK",
    "gn:dem":779,
    "gn:feature_class":"P",
    "gn:feature_code":"PPL",
    "gn:name":"Halalai",
    "gn:population":0,
    "gn:timezone":"Asia/Karachi",
    "iso:country":"PK",
    "name:und_x_variant":[
        "Hil\u0101lai"
    ],
    "wof:name":"Halalai",
    "wof:placetype":"locality"
},
  "geometry": {"coordinates":[71.46616,34.39038],"type":"Point"}
}