{
  "type": "Feature",
  "properties": {
    "gn:admin1_code":"5.0",
    "gn:asciiname":"Sukhan ji Dhani",
    "gn:country_code":"PK",
    "gn:dem":72,
    "gn:feature_class":"P",
    "gn:feature_code":"PPL",
    "gn:name":"Sukhan ji Dhani",
    "gn:population":0,
    "gn:timezone":"Asia/Karachi",
    "iso:country":"PK",
    "wof:name":"Sukhan ji Dhani",
    "wof:placetype":"locality"
},
  "geometry": {"coordinates":[70.14978000000001,25.20306],"type":"Point"}
}