{
  "type": "Feature",
  "properties": {
    "gn:admin1_code":"4.0",
    "gn:asciiname":"Chak Two Hundred Eighty-eight Jhang Branch",
    "gn:country_code":"PK",
    "gn:dem":167,
    "gn:feature_class":"P",
    "gn:feature_code":"PPL",
    "gn:name":"Chak Two Hundred Eighty-eight Jhang Branch",
    "gn:population":0,
    "gn:timezone":"Asia/Karachi",
    "iso:country":"PK",
    "name:und_x_variant":[
        "Jaimal Singh Wala",
        "Jaimal Singh",
        "Chak Number Two Hundred Eighty-Eight",
        "Chak Two Hundred Eighty-eight Jhang Branch",
        "Ras\u016blpur"
    ],
    "wof:name":"Chak Two Hundred Eighty-eight Jhang Branch",
    "wof:placetype":"locality"
},
  "geometry": {"coordinates":[72.59896999999999,31.04275],"type":"Point"}
}