{
  "type": "Feature",
  "properties": {
    "gn:admin1_code":"3.0",
    "gn:asciiname":"Zidrat",
    "gn:country_code":"PK",
    "gn:dem":651,
    "gn:feature_class":"P",
    "gn:feature_code":"PPL",
    "gn:name":"Zidrat",
    "gn:population":0,
    "gn:timezone":"Asia/Karachi",
    "iso:country":"PK",
    "name:eng_x_preferred":[
        "Zidrat"
    ],
    "wof:name":"Zidrat",
    "wof:placetype":"locality"
},
  "geometry": {"coordinates":[73.0424,33.98988],"type":"Point"}
}