{
  "type": "Feature",
  "properties": {
    "gn:admin1_code":"03",
    "gn:asciiname":"Landai",
    "gn:country_code":"PK",
    "gn:dem":746,
    "gn:feature_class":"P",
    "gn:feature_code":"PPL",
    "gn:name":"Landai",
    "gn:population":0,
    "gn:timezone":"Asia/Karachi",
    "iso:country":"PK",
    "name:eng_x_preferred":[
        "Landai"
    ],
    "wof:name":"Landai",
    "wof:placetype":"locality"
},
  "geometry": {"coordinates":[71.84219,34.829],"type":"Point"}
}