{
  "type": "Feature",
  "properties": {
    "gn:admin1_code":"4",
    "gn:asciiname":"Mirza Lakkhoke",
    "gn:country_code":"PK",
    "gn:dem":189,
    "gn:feature_class":"P",
    "gn:feature_code":"PPL",
    "gn:name":"Mirza Lakkhoke",
    "gn:population":0,
    "gn:timezone":"Asia/Karachi",
    "iso:country":"PK",
    "wof:name":"Mirza Lakkhoke",
    "wof:placetype":"locality"
},
  "geometry": {"coordinates":[74.3875,30.80694],"type":"Point"}
}