{
  "type": "Feature",
  "properties": {
    "gn:admin1_code":"04",
    "gn:asciiname":"Mahabbat Surani",
    "gn:country_code":"PK",
    "gn:dem":120,
    "gn:feature_class":"P",
    "gn:feature_code":"PPL",
    "gn:name":"Mahabbat Surani",
    "gn:population":0,
    "gn:timezone":"Asia/Karachi",
    "iso:country":"PK",
    "name:eng_x_preferred":[
        "Muhabbat Sur\u0101ni"
    ],
    "name:eng_x_variant":[
        "Mokib Surani"
    ],
    "name:und_x_variant":[
        "Mokib Surani",
        "Mahabbat Surani"
    ],
    "wof:name":"Mahabbat Surani",
    "wof:placetype":"locality"
},
  "geometry": {"coordinates":[70.98383000000003,30.07162000000001],"type":"Point"}
}