{
  "type": "Feature",
  "properties": {
    "gn:admin1_code":"6",
    "gn:asciiname":"Ganji Gali",
    "gn:country_code":"PK",
    "gn:dem":1508,
    "gn:feature_class":"P",
    "gn:feature_code":"PPL",
    "gn:name":"Ganji Gali",
    "gn:population":0,
    "gn:timezone":"Asia/Karachi",
    "iso:country":"PK",
    "name:und_x_variant":[
        "Jok\u0101n"
    ],
    "wof:name":"Ganji Gali",
    "wof:placetype":"locality"
},
  "geometry": {"coordinates":[74.11839999999999,33.89023],"type":"Point"}
}