{
  "type": "Feature",
  "properties": {
    "gn:admin1_code":"1.0",
    "gn:asciiname":"Jalar Post",
    "gn:country_code":"PK",
    "gn:dem":787,
    "gn:feature_class":"P",
    "gn:feature_code":"PPL",
    "gn:name":"Jalar Post",
    "gn:population":0,
    "gn:timezone":"Asia/Karachi",
    "iso:country":"PK",
    "wof:name":"Jalar Post",
    "wof:placetype":"locality"
},
  "geometry": {"coordinates":[70.24029,32.84582],"type":"Point"}
}