{
  "type": "Feature",
  "properties": {
    "gn:admin1_code":"02",
    "gn:asciiname":"Korani",
    "gn:country_code":"PK",
    "gn:dem":94,
    "gn:feature_class":"P",
    "gn:feature_code":"PPL",
    "gn:name":"Korani",
    "gn:population":0,
    "gn:timezone":"Asia/Karachi",
    "iso:country":"PK",
    "wof:name":"Korani",
    "wof:placetype":"locality"
},
  "geometry": {"coordinates":[67.86402,29.09077000000001],"type":"Point"}
}