{
  "type": "Feature",
  "properties": {
    "gn:admin1_code":"3.0",
    "gn:asciiname":"Pitao",
    "gn:country_code":"PK",
    "gn:dem":391,
    "gn:feature_class":"P",
    "gn:feature_code":"PPL",
    "gn:name":"Pitao",
    "gn:population":0,
    "gn:timezone":"Asia/Karachi",
    "iso:country":"PK",
    "wof:name":"Pitao",
    "wof:placetype":"locality"
},
  "geometry": {"coordinates":[72.17738,33.9299],"type":"Point"}
}