{
  "type": "Feature",
  "properties": {
    "gn:admin1_code":"6.0",
    "gn:asciiname":"Guthria",
    "gn:country_code":"PK",
    "gn:dem":972,
    "gn:feature_class":"P",
    "gn:feature_code":"PPL",
    "gn:name":"Guthria",
    "gn:population":0,
    "gn:timezone":"Asia/Karachi",
    "iso:country":"PK",
    "wof:name":"Guthria",
    "wof:placetype":"locality"
},
  "geometry": {"coordinates":[73.59874000000001,33.76962],"type":"Point"}
}