{
  "type": "Feature",
  "properties": {
    "gn:admin1_code":"5",
    "gn:asciiname":"Goth Ghulam Qadir Mari",
    "gn:country_code":"PK",
    "gn:dem":42,
    "gn:feature_class":"P",
    "gn:feature_code":"PPL",
    "gn:name":"Goth Ghulam Qadir Mari",
    "gn:population":0,
    "gn:timezone":"Asia/Karachi",
    "iso:country":"PK",
    "name:und_x_variant":[
        "Goth Ghul\u0101m Q\u0101dir Mar",
        "Ghul\u0101m Muhammad Ar\u0101\u012bn",
        "Goth Ghulam Qadir Mari"
    ],
    "wof:name":"Goth Ghulam Qadir Mari",
    "wof:placetype":"locality"
},
  "geometry": {"coordinates":[68.12049,26.53495],"type":"Point"}
}