{
  "type": "Feature",
  "properties": {
    "gn:admin1_code":"4.0",
    "gn:asciiname":"Kacha Khokharwala",
    "gn:country_code":"PK",
    "gn:dem":139,
    "gn:feature_class":"P",
    "gn:feature_code":"PPL",
    "gn:name":"Kacha Khokharwala",
    "gn:population":0,
    "gn:timezone":"Asia/Karachi",
    "iso:country":"PK",
    "name:eng_x_preferred":[
        "Kacha Khokharwala"
    ],
    "wof:name":"Kacha Khokharwala",
    "wof:placetype":"locality"
},
  "geometry": {"coordinates":[70.80757,30.82417],"type":"Point"}
}