{
  "type": "Feature",
  "properties": {
    "gn:admin1_code":"4.0",
    "gn:asciiname":"Nawab Gulla Khelwala",
    "gn:country_code":"PK",
    "gn:dem":210,
    "gn:feature_class":"P",
    "gn:feature_code":"PPL",
    "gn:name":"Nawab Gulla Khelw\u0101la",
    "gn:population":0,
    "gn:timezone":"Asia/Karachi",
    "iso:country":"PK",
    "wof:name":"Nawab Gulla Khelwala",
    "wof:placetype":"locality"
},
  "geometry": {"coordinates":[71.58244999999999,32.52977],"type":"Point"}
}