{
  "type": "Feature",
  "properties": {
    "gn:admin1_code":"5.0",
    "gn:asciiname":"Ramsar",
    "gn:country_code":"PK",
    "gn:dem":60,
    "gn:feature_class":"P",
    "gn:feature_code":"PPL",
    "gn:name":"Ramsar",
    "gn:population":0,
    "gn:timezone":"Asia/Karachi",
    "iso:country":"PK",
    "name:ceb_x_preferred":[
        "Ramsar"
    ],
    "name:fas_x_preferred":[
        "\u0631\u0627\u0645\u0633\u0631"
    ],
    "name:fra_x_preferred":[
        "Ramsar"
    ],
    "name:pnb_x_preferred":[
        "\u0631\u0627\u0645\u0633\u0631"
    ],
    "name:spa_x_preferred":[
        "Ramsar"
    ],
    "name:swe_x_preferred":[
        "Ramsar"
    ],
    "wof:name":"Ramsar",
    "wof:placetype":"locality"
},
  "geometry": {"coordinates":[70.01325,26.19819],"type":"Point"}
}