{
  "type": "Feature",
  "properties": {
    "gn:admin1_code":"4",
    "gn:asciiname":"Bahawalwala",
    "gn:country_code":"PK",
    "gn:dem":138,
    "gn:feature_class":"P",
    "gn:feature_code":"PPL",
    "gn:name":"Bahawalwala",
    "gn:population":0,
    "gn:timezone":"Asia/Karachi",
    "iso:country":"PK",
    "name:und_x_variant":[
        "B\u0101na Ladhi\u0101w\u0101la"
    ],
    "wof:name":"Bahawalwala",
    "wof:placetype":"locality"
},
  "geometry": {"coordinates":[71.99129000000001,30.48992],"type":"Point"}
}