{
  "type": "Feature",
  "properties": {
    "gn:admin1_code":"1.0",
    "gn:asciiname":"Jawara",
    "gn:country_code":"PK",
    "gn:dem":2137,
    "gn:feature_class":"P",
    "gn:feature_code":"PPL",
    "gn:name":"Jawara",
    "gn:population":0,
    "gn:timezone":"Asia/Karachi",
    "iso:country":"PK",
    "name:und_x_variant":[
        "Jowara"
    ],
    "wof:name":"Jawara",
    "wof:placetype":"locality"
},
  "geometry": {"coordinates":[70.80105999999998,33.86186],"type":"Point"}
}