{
  "type": "Feature",
  "properties": {
    "gn:admin1_code":"5",
    "gn:asciiname":"Gharibo Bahan",
    "gn:country_code":"PK",
    "gn:dem":41,
    "gn:feature_class":"P",
    "gn:feature_code":"PPL",
    "gn:name":"Gharibo Bahan",
    "gn:population":0,
    "gn:timezone":"Asia/Karachi",
    "iso:country":"PK",
    "name:und_x_variant":[
        "Q\u0101sim Bahan",
        "Gharibo Bahan"
    ],
    "wof:name":"Gharibo Bahan",
    "wof:placetype":"locality"
},
  "geometry": {"coordinates":[68.00753,26.71368],"type":"Point"}
}