{
  "type": "Feature",
  "properties": {
    "gn:admin1_code":"3",
    "gn:asciiname":"Geri",
    "gn:country_code":"PK",
    "gn:dem":656,
    "gn:feature_class":"P",
    "gn:feature_code":"PPL",
    "gn:name":"Geri",
    "gn:population":0,
    "gn:timezone":"Asia/Karachi",
    "iso:country":"PK",
    "name:ceb_x_preferred":[
        "Geri"
    ],
    "name:deu_x_preferred":[
        "Geri"
    ],
    "name:fra_x_preferred":[
        "Geri"
    ],
    "name:kat_x_preferred":[
        "\u10d2\u10d4\u10e0\u10d8"
    ],
    "name:pol_x_preferred":[
        "Geri"
    ],
    "name:por_x_preferred":[
        "Geri"
    ],
    "name:swe_x_preferred":[
        "Geri"
    ],
    "wof:name":"Geri",
    "wof:placetype":"locality"
},
  "geometry": {"coordinates":[73.47564,34.2388],"type":"Point"}
}