{
  "type": "Feature",
  "properties": {
    "gn:admin1_code":"2.0",
    "gn:asciiname":"Kili Haji Taj Muhammad Badini",
    "gn:country_code":"PK",
    "gn:dem":985,
    "gn:feature_class":"P",
    "gn:feature_code":"PPL",
    "gn:name":"Kili Haji Taj Muhammad Badini",
    "gn:population":0,
    "gn:timezone":"Asia/Karachi",
    "iso:country":"PK",
    "wof:name":"Kili Haji Taj Muhammad Badini",
    "wof:placetype":"locality"
},
  "geometry": {"coordinates":[66.00769,29.62109],"type":"Point"}
}