{
  "type": "Feature",
  "properties": {
    "gn:admin1_code":"4",
    "gn:asciiname":"Chak Number One",
    "gn:country_code":"PK",
    "gn:dem":99,
    "gn:feature_class":"P",
    "gn:feature_code":"PPL",
    "gn:name":"Chak Number One",
    "gn:population":0,
    "gn:timezone":"Asia/Karachi",
    "iso:country":"PK",
    "name:und_x_variant":[
        "Chak One"
    ],
    "wof:name":"Chak Number One",
    "wof:placetype":"locality"
},
  "geometry": {"coordinates":[71.02415999999999,29.06037],"type":"Point"}
}