{
  "type": "Feature",
  "properties": {
    "gn:admin1_code":"5.0",
    "gn:asciiname":"Saleh Jhanjhi",
    "gn:country_code":"PK",
    "gn:dem":101,
    "gn:feature_class":"P",
    "gn:feature_code":"PPL",
    "gn:name":"Saleh Jhanjhi",
    "gn:population":0,
    "gn:timezone":"Asia/Karachi",
    "iso:country":"PK",
    "wof:name":"Saleh Jhanjhi",
    "wof:placetype":"locality"
},
  "geometry": {"coordinates":[70.41374999999999,24.85811],"type":"Point"}
}