{
  "type": "Feature",
  "properties": {
    "gn:admin1_code":"4",
    "gn:asciiname":"Minghanawala",
    "gn:country_code":"PK",
    "gn:dem":138,
    "gn:feature_class":"P",
    "gn:feature_code":"PPL",
    "gn:name":"Minghanawala",
    "gn:population":0,
    "gn:timezone":"Asia/Karachi",
    "iso:country":"PK",
    "wof:name":"Minghanawala",
    "wof:placetype":"locality"
},
  "geometry": {"coordinates":[70.93200999999998,30.6179],"type":"Point"}
}