{
  "type": "Feature",
  "properties": {
    "gn:admin1_code":"2",
    "gn:asciiname":"Nasran Kili",
    "gn:country_code":"PK",
    "gn:dem":1287,
    "gn:feature_class":"P",
    "gn:feature_code":"PPL",
    "gn:name":"Nasran Kili",
    "gn:population":0,
    "gn:timezone":"Asia/Karachi",
    "iso:country":"PK",
    "wof:name":"Nasran Kili",
    "wof:placetype":"locality"
},
  "geometry": {"coordinates":[68.85500999999999,30.40916],"type":"Point"}
}