{
  "type": "Feature",
  "properties": {
    "gn:admin1_code":"04",
    "gn:asciiname":"Sar Sarthokh",
    "gn:country_code":"PK",
    "gn:dem":774,
    "gn:feature_class":"P",
    "gn:feature_code":"PPL",
    "gn:name":"Sar Sarthokh",
    "gn:population":0,
    "gn:timezone":"Asia/Karachi",
    "iso:country":"PK",
    "name:und_x_variant":[
        "Surtuka",
        "Sartokh",
        "Sartok",
        "Sar Sarthokh"
    ],
    "wof:name":"Sar Sarthokh",
    "wof:placetype":"locality"
},
  "geometry": {"coordinates":[70.24135,30.38001],"type":"Point"}
}