{
  "type": "Feature",
  "properties": {
    "gn:admin1_code":"3",
    "gn:asciiname":"Garaonai",
    "gn:country_code":"PK",
    "gn:dem":1718,
    "gn:feature_class":"P",
    "gn:feature_code":"PPL",
    "gn:name":"Garaonai",
    "gn:population":0,
    "gn:timezone":"Asia/Karachi",
    "iso:country":"PK",
    "name:eng_x_preferred":[
        "Garaonai"
    ],
    "wof:name":"Garaonai",
    "wof:placetype":"locality"
},
  "geometry": {"coordinates":[71.65875,35.07862],"type":"Point"}
}