{
  "type": "Feature",
  "properties": {
    "gn:admin1_code":"4.0",
    "gn:asciiname":"Hasal",
    "gn:country_code":"PK",
    "gn:dem":331,
    "gn:feature_class":"P",
    "gn:feature_code":"PPL",
    "gn:name":"Hasal",
    "gn:population":0,
    "gn:timezone":"Asia/Karachi",
    "iso:country":"PK",
    "name:eng_x_preferred":[
        "Hasal"
    ],
    "name:eng_x_variant":[
        "Hasil"
    ],
    "name:und_x_variant":[
        "Hasil"
    ],
    "wof:name":"Hasal",
    "wof:placetype":"locality"
},
  "geometry": {"coordinates":[72.55303000000001,33.17099],"type":"Point"}
}