{
  "type": "Feature",
  "properties": {
    "gn:admin1_code":"1.0",
    "gn:asciiname":"Shapoabad",
    "gn:country_code":"PK",
    "gn:dem":2408,
    "gn:feature_class":"P",
    "gn:feature_code":"PPL",
    "gn:name":"Shapoabad",
    "gn:population":0,
    "gn:timezone":"Asia/Karachi",
    "iso:country":"PK",
    "name:und_x_variant":[
        "Shafu",
        "Shapoabad",
        "Sh\u0101fu",
        "Shafi Abad"
    ],
    "wof:name":"Shapoabad",
    "wof:placetype":"locality"
},
  "geometry": {"coordinates":[69.99566999999999,33.97671],"type":"Point"}
}