{
  "type": "Feature",
  "properties": {
    "gn:admin1_code":"06",
    "gn:asciiname":"Tain",
    "gn:country_code":"PK",
    "gn:dem":1124,
    "gn:feature_class":"P",
    "gn:feature_code":"PPL",
    "gn:name":"Tain",
    "gn:population":0,
    "gn:timezone":"Asia/Karachi",
    "iso:country":"PK",
    "name:azb_x_preferred":[
        "\u062a\u0627\u06cc\u0646"
    ],
    "name:cat_x_preferred":[
        "Tain"
    ],
    "name:ceb_x_preferred":[
        "Tain"
    ],
    "name:cym_x_preferred":[
        "Tain"
    ],
    "name:deu_x_preferred":[
        "Tain"
    ],
    "name:eus_x_preferred":[
        "Tain"
    ],
    "name:fas_x_preferred":[
        "\u062a\u0627\u06cc\u0646"
    ],
    "name:fra_x_preferred":[
        "Tain"
    ],
    "name:gla_x_preferred":[
        "Baile Dhubhthaich"
    ],
    "name:gle_x_preferred":[
        "Baile Dhubhthaich"
    ],
    "name:ita_x_preferred":[
        "Tain"
    ],
    "name:nld_x_preferred":[
        "Tain"
    ],
    "name:nno_x_preferred":[
        "Tain"
    ],
    "name:nor_x_preferred":[
        "Tain"
    ],
    "name:pol_x_preferred":[
        "Tain"
    ],
    "name:sco_x_preferred":[
        "Tain"
    ],
    "name:spa_x_preferred":[
        "Tain"
    ],
    "name:swe_x_preferred":[
        "Tain"
    ],
    "name:und_x_variant":[
        "T\u0101\u012bn"
    ],
    "wof:name":"Tain",
    "wof:placetype":"locality"
},
  "geometry": {"coordinates":[73.61859,33.90089],"type":"Point"}
}