{
  "type": "Feature",
  "properties": {
    "gn:admin1_code":"06",
    "gn:asciiname":"Tain",
    "gn:country_code":"PK",
    "gn:dem":1124,
    "gn:feature_class":"P",
    "gn:feature_code":"PPL",
    "gn:name":"Tain",
    "gn:population":0,
    "gn:timezone":"Asia/Karachi",
    "iso:country":"PK",
    "name:und_x_variant":[
        "T\u0101\u012bn"
    ],
    "wof:name":"Tain",
    "wof:placetype":"locality"
},
  "geometry": {"coordinates":[73.61859,33.90089],"type":"Point"}
}