{
  "type": "Feature",
  "properties": {
    "gn:admin1_code":"3.0",
    "gn:asciiname":"Bherwasa",
    "gn:country_code":"PK",
    "gn:dem":429,
    "gn:feature_class":"P",
    "gn:feature_code":"PPL",
    "gn:name":"Bherwasa",
    "gn:population":0,
    "gn:timezone":"Asia/Karachi",
    "iso:country":"PK",
    "name:und_x_variant":[
        "Bharw\u0101sa"
    ],
    "wof:name":"Bherwasa",
    "wof:placetype":"locality"
},
  "geometry": {"coordinates":[72.69147,34.01085],"type":"Point"}
}