{
  "type": "Feature",
  "properties": {
    "gn:admin1_code":"4.0",
    "gn:asciiname":"Basti Mehr Din",
    "gn:country_code":"PK",
    "gn:dem":83,
    "gn:feature_class":"P",
    "gn:feature_code":"PPL",
    "gn:name":"Basti Mehr Din",
    "gn:population":0,
    "gn:timezone":"Asia/Karachi",
    "iso:country":"PK",
    "name:und_x_variant":[
        "Basti Mahr D\u012bn"
    ],
    "wof:name":"Basti Mehr Din",
    "wof:placetype":"locality"
},
  "geometry": {"coordinates":[70.45394,28.50455],"type":"Point"}
}