{
  "type": "Feature",
  "properties": {
    "gn:admin1_code":"3.0",
    "gn:asciiname":"Cher",
    "gn:country_code":"PK",
    "gn:dem":3055,
    "gn:feature_class":"P",
    "gn:feature_code":"PPL",
    "gn:name":"Cher",
    "gn:population":0,
    "gn:timezone":"Asia/Karachi",
    "iso:country":"PK",
    "wof:name":"Cher",
    "wof:placetype":"locality"
},
  "geometry": {"coordinates":[73.11069000000001,35.56713],"type":"Point"}
}