{
  "type": "Feature",
  "properties": {
    "gn:admin1_code":"04",
    "gn:asciiname":"Mona Saiyidan",
    "gn:country_code":"PK",
    "gn:dem":203,
    "gn:feature_class":"P",
    "gn:feature_code":"PPL",
    "gn:name":"Mona Saiyidan",
    "gn:population":0,
    "gn:timezone":"Asia/Karachi",
    "iso:country":"PK",
    "name:und_x_variant":[
        "Mona"
    ],
    "wof:name":"Mona Saiyidan",
    "wof:placetype":"locality"
},
  "geometry": {"coordinates":[73.13329,32.45361],"type":"Point"}
}