{
  "type": "Feature",
  "properties": {
    "gn:admin1_code":"4.0",
    "gn:asciiname":"Chak One Hundred Ninety Shimali",
    "gn:country_code":"PK",
    "gn:dem":177,
    "gn:feature_class":"P",
    "gn:feature_code":"PPL",
    "gn:name":"Chak One Hundred Ninety Shimali",
    "gn:population":0,
    "gn:timezone":"Asia/Karachi",
    "iso:country":"PK",
    "name:und_x_variant":[
        "Chak 190 Shim\u0101li"
    ],
    "wof:name":"Chak One Hundred Ninety Shimali",
    "wof:placetype":"locality"
},
  "geometry": {"coordinates":[72.45215,32.0807],"type":"Point"}
}