{
  "type": "Feature",
  "properties": {
    "gn:admin1_code":"6",
    "gn:asciiname":"Rampur Bandala",
    "gn:country_code":"PK",
    "gn:dem":700,
    "gn:feature_class":"P",
    "gn:feature_code":"PPL",
    "gn:name":"Rampur Bandala",
    "gn:population":0,
    "gn:timezone":"Asia/Kolkata",
    "iso:country":"PK",
    "name:und_x_variant":[
        "Band\u0101la"
    ],
    "wof:name":"Rampur Bandala",
    "wof:placetype":"locality"
},
  "geometry": {"coordinates":[74.19405,33.05951],"type":"Point"}
}