{
  "type": "Feature",
  "properties": {
    "gn:admin1_code":"7.0",
    "gn:asciiname":"Thashing",
    "gn:country_code":"PK",
    "gn:dem":3668,
    "gn:feature_class":"P",
    "gn:feature_code":"PPL",
    "gn:name":"Thashing",
    "gn:population":0,
    "gn:timezone":"Asia/Karachi",
    "iso:country":"PK",
    "wof:name":"Thashing",
    "wof:placetype":"locality"
},
  "geometry": {"coordinates":[76.0741,34.88223],"type":"Point"}
}