{
  "type": "Feature",
  "properties": {
    "iso:country":"PK",
    "name:eng_x_preferred":[
        "Keti"
    ],
    "name:nld_x_preferred":[
        "Keti"
    ],
    "name:unk_x_variant":[
        "Ketibunder"
    ],
    "qs:gn_country":"PK",
    "qs:gn_fcode":"PPL",
    "qs:gn_pop":2934,
    "qs:name":"Keti Bandar",
    "qs:name_adm0":"Pakistan",
    "qs:name_adm1":"Sindh",
    "qs:photos":0,
    "qs:photos_1k":0,
    "qs:photos_9k":0,
    "qs:photos_9r":0,
    "qs:photos_all":0,
    "qs:photos_sr":0,
    "qs:placetype":"Town",
    "qs:pop_sr":"4",
    "qs:woe_adm0":23424922,
    "wof:name":"Keti Bandar",
    "wof:placetype":"locality",
    "wof:population":2934
},
  "geometry": {"coordinates":[67.44972,24.14472],"type":"Point"}
}