{
  "type": "Feature",
  "properties": {
    "gn:admin1_code":"5.0",
    "gn:asciiname":"Faqir Muhammad Mallah",
    "gn:country_code":"PK",
    "gn:dem":2,
    "gn:feature_class":"P",
    "gn:feature_code":"PPL",
    "gn:name":"Faqir Muhammad Mallah",
    "gn:population":0,
    "gn:timezone":"Asia/Karachi",
    "iso:country":"PK",
    "wof:name":"Faqir Muhammad Mallah",
    "wof:placetype":"locality"
},
  "geometry": {"coordinates":[68.84428,24.39889],"type":"Point"}
}