{
  "type": "Feature",
  "properties": {
    "gn:admin1_code":"04",
    "gn:asciiname":"Pind Aziz",
    "gn:country_code":"PK",
    "gn:dem":254,
    "gn:feature_class":"P",
    "gn:feature_code":"PPL",
    "gn:name":"Pind Aziz",
    "gn:population":0,
    "gn:timezone":"Asia/Karachi",
    "iso:country":"PK",
    "name:und_x_variant":[
        "Pindi Aziz",
        "Pind Az\u012bz",
        "Pind Aziz"
    ],
    "wof:name":"Pind Aziz",
    "wof:placetype":"locality"
},
  "geometry": {"coordinates":[73.87196,32.99849],"type":"Point"}
}