{
  "type": "Feature",
  "properties": {
    "gn:admin1_code":"3.0",
    "gn:asciiname":"Kalawan",
    "gn:country_code":"PK",
    "gn:dem":627,
    "gn:feature_class":"P",
    "gn:feature_code":"PPL",
    "gn:name":"Kalawan",
    "gn:population":0,
    "gn:timezone":"Asia/Karachi",
    "iso:country":"PK",
    "name:eng_x_preferred":[
        "Kal\u0101nw\u0101m"
    ],
    "wof:name":"Kalawan",
    "wof:placetype":"locality"
},
  "geometry": {"coordinates":[73.01878000000001,33.98951],"type":"Point"}
}