{
  "type": "Feature",
  "properties": {
    "gn:admin1_code":"04",
    "gn:asciiname":"Kalari",
    "gn:country_code":"PK",
    "gn:dem":575,
    "gn:feature_class":"P",
    "gn:feature_code":"PPL",
    "gn:name":"Kalari",
    "gn:population":0,
    "gn:timezone":"Asia/Karachi",
    "iso:country":"PK",
    "name:mal_x_preferred":[
        "\u0d15\u0d33\u0d30\u0d3f"
    ],
    "name:und_x_variant":[
        "Kal\u0101ri"
    ],
    "wof:name":"Kalari",
    "wof:placetype":"locality"
},
  "geometry": {"coordinates":[73.28035,33.46625],"type":"Point"}
}