{
  "type": "Feature",
  "properties": {
    "gn:admin1_code":"4.0",
    "gn:asciiname":"Kamalpura Nau",
    "gn:country_code":"PK",
    "gn:dem":199,
    "gn:feature_class":"P",
    "gn:feature_code":"PPL",
    "gn:name":"Kamalpura Nau",
    "gn:population":0,
    "gn:timezone":"Asia/Karachi",
    "iso:country":"PK",
    "name:und_x_variant":[
        "Kam\u0101lpura"
    ],
    "wof:name":"Kamalpura Nau",
    "wof:placetype":"locality"
},
  "geometry": {"coordinates":[74.58416,31.08259],"type":"Point"}
}