{
  "type": "Feature",
  "properties": {
    "gn:admin1_code":"4",
    "gn:asciiname":"Dera Hassan Shah",
    "gn:country_code":"PK",
    "gn:dem":153,
    "gn:feature_class":"P",
    "gn:feature_code":"PPL",
    "gn:name":"Dera Hassan Shah",
    "gn:population":0,
    "gn:timezone":"Asia/Karachi",
    "iso:country":"PK",
    "name:und_x_variant":[
        "Basti Hasan Sh\u0101h"
    ],
    "wof:name":"Dera Hassan Shah",
    "wof:placetype":"locality"
},
  "geometry": {"coordinates":[72.14842,31.24209],"type":"Point"}
}