{
  "type": "Feature",
  "properties": {
    "gn:admin1_code":"5",
    "gn:asciiname":"Karam Ali Chandio",
    "gn:country_code":"PK",
    "gn:dem":14,
    "gn:feature_class":"P",
    "gn:feature_code":"PPL",
    "gn:name":"Karam Ali Chandio",
    "gn:population":0,
    "gn:timezone":"Asia/Karachi",
    "iso:country":"PK",
    "name:und_x_variant":[
        "Karmun Ch\u0101ndia"
    ],
    "wof:name":"Karam Ali Chandio",
    "wof:placetype":"locality"
},
  "geometry": {"coordinates":[69.17269,24.89299],"type":"Point"}
}