{
  "type": "Feature",
  "properties": {
    "gn:admin1_code":"6",
    "gn:asciiname":"Haji Bal",
    "gn:country_code":"PK",
    "gn:dem":2289,
    "gn:feature_class":"P",
    "gn:feature_code":"PPL",
    "gn:name":"Haji Bal",
    "gn:population":0,
    "gn:timezone":"Asia/Karachi",
    "iso:country":"PK",
    "name:und_x_variant":[
        "Muhri"
    ],
    "wof:name":"Haji Bal",
    "wof:placetype":"locality"
},
  "geometry": {"coordinates":[74.17294,33.89095],"type":"Point"}
}