{
  "type": "Feature",
  "properties": {
    "gn:admin1_code":"2.0",
    "gn:asciiname":"Mohammad Hasni Churak",
    "gn:country_code":"PK",
    "gn:dem":1545,
    "gn:feature_class":"P",
    "gn:feature_code":"PPL",
    "gn:name":"Mohammad Hasni Churak",
    "gn:population":0,
    "gn:timezone":"Asia/Karachi",
    "iso:country":"PK",
    "wof:name":"Mohammad Hasni Churak",
    "wof:placetype":"locality"
},
  "geometry": {"coordinates":[66.12419,28.07834],"type":"Point"}
}