{
  "type": "Feature",
  "properties": {
    "gn:admin1_code":"4",
    "gn:asciiname":"Khu Rarhewala",
    "gn:country_code":"PK",
    "gn:dem":128,
    "gn:feature_class":"P",
    "gn:feature_code":"PPL",
    "gn:name":"Khu Rarhewala",
    "gn:population":0,
    "gn:timezone":"Asia/Karachi",
    "iso:country":"PK",
    "name:eng_x_preferred":[
        "R\u0101rew\u0101la"
    ],
    "wof:name":"Khu Rarhewala",
    "wof:placetype":"locality"
},
  "geometry": {"coordinates":[70.68669,30.29753],"type":"Point"}
}