{
  "type": "Feature",
  "properties": {
    "gn:admin1_code":"6.0",
    "gn:asciiname":"Lunjgran Bazar",
    "gn:country_code":"PK",
    "gn:dem":1666,
    "gn:feature_class":"P",
    "gn:feature_code":"PPL",
    "gn:name":"Lunjgran Bazar",
    "gn:population":0,
    "gn:timezone":"Asia/Karachi",
    "iso:country":"PK",
    "name:und_x_variant":[
        "Lunjgr\u0101n"
    ],
    "wof:name":"Lunjgran Bazar",
    "wof:placetype":"locality"
},
  "geometry": {"coordinates":[73.69773000000001,33.83139],"type":"Point"}
}