{
  "type": "Feature",
  "properties": {
    "gn:admin1_code":"3.0",
    "gn:asciiname":"Bar Shirial",
    "gn:country_code":"PK",
    "gn:dem":1975,
    "gn:feature_class":"P",
    "gn:feature_code":"PPL",
    "gn:name":"Bar Shirial",
    "gn:population":0,
    "gn:timezone":"Asia/Karachi",
    "iso:country":"PK",
    "wof:name":"Bar Shirial",
    "wof:placetype":"locality"
},
  "geometry": {"coordinates":[73.07767,35.00775],"type":"Point"}
}