{
  "type": "Feature",
  "properties": {
    "gn:admin1_code":"5.0",
    "gn:asciiname":"Haji Ismail Jokhio",
    "gn:country_code":"PK",
    "gn:dem":11,
    "gn:feature_class":"P",
    "gn:feature_code":"PPL",
    "gn:name":"H\u0101ji Ism\u0101\u012bl Jokhio",
    "gn:population":0,
    "gn:timezone":"Asia/Karachi",
    "iso:country":"PK",
    "wof:name":"Haji Ismail Jokhio",
    "wof:placetype":"locality"
},
  "geometry": {"coordinates":[67.78583,24.75472],"type":"Point"}
}