{
  "type": "Feature",
  "properties": {
    "gn:admin1_code":"02",
    "gn:asciiname":"Goth Haji Sulaiman Runjha",
    "gn:country_code":"PK",
    "gn:dem":130,
    "gn:feature_class":"P",
    "gn:feature_code":"PPL",
    "gn:name":"Goth Haji Sulaiman Runjha",
    "gn:population":0,
    "gn:timezone":"Asia/Karachi",
    "iso:country":"PK",
    "name:und_x_variant":[
        "Goth H\u0101ji Sulaim\u0101n"
    ],
    "wof:name":"Goth Haji Sulaiman Runjha",
    "wof:placetype":"locality"
},
  "geometry": {"coordinates":[66.24091,26.31577],"type":"Point"}
}