{
  "type": "Feature",
  "properties": {
    "gn:admin1_code":"1",
    "gn:asciiname":"Gurgura",
    "gn:country_code":"PK",
    "gn:dem":1717,
    "gn:feature_class":"P",
    "gn:feature_code":"PPL",
    "gn:name":"Gurgura",
    "gn:population":0,
    "gn:timezone":"Asia/Karachi",
    "iso:country":"PK",
    "name:som_x_preferred":[
        "Gurgura"
    ],
    "wof:name":"Gurgura",
    "wof:placetype":"locality"
},
  "geometry": {"coordinates":[69.90611,32.50872],"type":"Point"}
}