{
  "type": "Feature",
  "properties": {
    "gn:admin1_code":"2.0",
    "gn:asciiname":"Shin Kazha",
    "gn:country_code":"PK",
    "gn:dem":938,
    "gn:feature_class":"P",
    "gn:feature_code":"PPL",
    "gn:name":"Shin Kazha",
    "gn:population":0,
    "gn:timezone":"Asia/Karachi",
    "iso:country":"PK",
    "wof:name":"Shin Kazha",
    "wof:placetype":"locality"
},
  "geometry": {"coordinates":[70.11671,31.20436],"type":"Point"}
}