{
  "type": "Feature",
  "properties": {
    "gn:admin1_code":"4",
    "gn:asciiname":"Thalla Sharif",
    "gn:country_code":"PK",
    "gn:dem":79,
    "gn:feature_class":"P",
    "gn:feature_code":"PPL",
    "gn:name":"Thalla Sharif",
    "gn:population":0,
    "gn:timezone":"Asia/Karachi",
    "iso:country":"PK",
    "name:und_x_variant":[
        "Thallah Shar\u012bf"
    ],
    "wof:name":"Thalla Sharif",
    "wof:placetype":"locality"
},
  "geometry": {"coordinates":[69.97215,28.37546],"type":"Point"}
}