{
  "type": "Feature",
  "properties": {
    "gn:admin1_code":"5",
    "gn:asciiname":"Kharcho",
    "gn:country_code":"PK",
    "gn:dem":75,
    "gn:feature_class":"P",
    "gn:feature_code":"PPL",
    "gn:name":"Kharcho",
    "gn:population":0,
    "gn:timezone":"Asia/Karachi",
    "iso:country":"PK",
    "name:aze_x_preferred":[
        "Xar\u00e7o"
    ],
    "name:ces_x_preferred":[
        "Char\u010do"
    ],
    "name:ell_x_preferred":[
        "\u03a7\u03ac\u03c1\u03c4\u03c3\u03bf"
    ],
    "name:est_x_preferred":[
        "Hart\u0161oo"
    ],
    "name:fra_x_preferred":[
        "Khartcho"
    ],
    "name:heb_x_preferred":[
        "\u05d7\u05e8\u05e6'\u05d5"
    ],
    "name:hye_x_preferred":[
        "\u053d\u0561\u0580\u0579\u0578"
    ],
    "name:kaz_x_preferred":[
        "\u0425\u0430\u0440\u0447\u043e"
    ],
    "name:lit_x_preferred":[
        "Char\u010dio sriuba"
    ],
    "name:nld_x_preferred":[
        "Charsjo"
    ],
    "name:pol_x_preferred":[
        "Charczo"
    ],
    "name:por_x_preferred":[
        "Kharcho"
    ],
    "name:rue_x_preferred":[
        "\u0425\u0430\u0440\u0447\u043e"
    ],
    "name:rus_x_preferred":[
        "\u0425\u0430\u0440\u0447\u043e"
    ],
    "name:spa_x_preferred":[
        "Kharcho"
    ],
    "name:tur_x_preferred":[
        "Har\u00e7o"
    ],
    "name:ukr_x_preferred":[
        "\u0425\u0430\u0440\u0447\u043e"
    ],
    "name:und_x_variant":[
        "Kh\u0101rtia"
    ],
    "name:zho_x_preferred":[
        "\u5361\u723e\u55ac"
    ],
    "wof:name":"Kharcho",
    "wof:placetype":"locality"
},
  "geometry": {"coordinates":[69.03518000000001,26.90297],"type":"Point"}
}