{
  "type": "Feature",
  "properties": {
    "gn:admin1_code":"5",
    "gn:asciiname":"Kharcho",
    "gn:country_code":"PK",
    "gn:dem":75,
    "gn:feature_class":"P",
    "gn:feature_code":"PPL",
    "gn:name":"Kharcho",
    "gn:population":0,
    "gn:timezone":"Asia/Karachi",
    "iso:country":"PK",
    "name:und_x_variant":[
        "Kh\u0101rtia"
    ],
    "wof:name":"Kharcho",
    "wof:placetype":"locality"
},
  "geometry": {"coordinates":[69.03518000000001,26.90297],"type":"Point"}
}