{
  "type": "Feature",
  "properties": {
    "gn:admin1_code":"4.0",
    "gn:asciiname":"Basti Yaran Khanwali",
    "gn:country_code":"PK",
    "gn:dem":92,
    "gn:feature_class":"P",
    "gn:feature_code":"PPL",
    "gn:name":"Basti Y\u0101ran Kh\u0101nw\u0101li",
    "gn:population":0,
    "gn:timezone":"Asia/Karachi",
    "iso:country":"PK",
    "wof:name":"Basti Yaran Khanwali",
    "wof:placetype":"locality"
},
  "geometry": {"coordinates":[70.65694000000001,28.66944],"type":"Point"}
}