{
  "type": "Feature",
  "properties": {
    "gn:admin1_code":"04",
    "gn:asciiname":"Basti Salara",
    "gn:country_code":"PK",
    "gn:dem":184,
    "gn:feature_class":"P",
    "gn:feature_code":"PPL",
    "gn:name":"Basti Salara",
    "gn:population":0,
    "gn:timezone":"Asia/Karachi",
    "iso:country":"PK",
    "name:und_x_variant":[
        "Sal\u0101ra"
    ],
    "wof:name":"Basti Salara",
    "wof:placetype":"locality"
},
  "geometry": {"coordinates":[73.01483,31.74275],"type":"Point"}
}