{
  "type": "Feature",
  "properties": {
    "gn:admin1_code":"2.0",
    "gn:asciiname":"Goth Jamani Sakhhan",
    "gn:country_code":"PK",
    "gn:dem":56,
    "gn:feature_class":"P",
    "gn:feature_code":"PPL",
    "gn:name":"Goth Jamani Sakhhan",
    "gn:population":0,
    "gn:timezone":"Asia/Karachi",
    "iso:country":"PK",
    "wof:name":"Goth Jamani Sakhhan",
    "wof:placetype":"locality"
},
  "geometry": {"coordinates":[67.57406,28.26021],"type":"Point"}
}