{
  "type": "Feature",
  "properties": {
    "gn:admin1_code":"3",
    "gn:asciiname":"Laindi",
    "gn:country_code":"PK",
    "gn:dem":326,
    "gn:feature_class":"P",
    "gn:feature_code":"PPL",
    "gn:name":"Laindi",
    "gn:population":0,
    "gn:timezone":"Asia/Karachi",
    "iso:country":"PK",
    "name:eng_x_preferred":[
        "Landai"
    ],
    "wof:name":"Laindi",
    "wof:placetype":"locality"
},
  "geometry": {"coordinates":[72.16925000000001,34.27122],"type":"Point"}
}