{
  "type": "Feature",
  "properties": {
    "gn:admin1_code":"3",
    "gn:asciiname":"Shelang Shal",
    "gn:country_code":"PK",
    "gn:dem":3362,
    "gn:feature_class":"P",
    "gn:feature_code":"PPL",
    "gn:name":"Shelang Shal",
    "gn:population":0,
    "gn:timezone":"Asia/Karachi",
    "iso:country":"PK",
    "name:eng_x_preferred":[
        "Shelang Sh\u0101l"
    ],
    "wof:name":"Shelang Shal",
    "wof:placetype":"locality"
},
  "geometry": {"coordinates":[71.88339000000001,35.87067000000001],"type":"Point"}
}