{
  "type": "Feature",
  "properties": {
    "gn:admin1_code":"03",
    "gn:asciiname":"Muhammadzai",
    "gn:country_code":"PK",
    "gn:dem":720,
    "gn:feature_class":"P",
    "gn:feature_code":"PPL",
    "gn:name":"Muhammadzai",
    "gn:population":0,
    "gn:timezone":"Asia/Karachi",
    "iso:country":"PK",
    "name:und_x_variant":[
        "Mohammad Zai",
        "Muhammadzai"
    ],
    "wof:name":"Muhammadzai",
    "wof:placetype":"locality"
},
  "geometry": {"coordinates":[70.56570000000001,33.33103],"type":"Point"}
}