{
  "type": "Feature",
  "properties": {
    "gn:admin1_code":"3.0",
    "gn:asciiname":"Khadgol",
    "gn:country_code":"PK",
    "gn:dem":2192,
    "gn:feature_class":"P",
    "gn:feature_code":"PPL",
    "gn:name":"Khadgol",
    "gn:population":0,
    "gn:timezone":"Asia/Karachi",
    "iso:country":"PK",
    "name:eng_x_preferred":[
        "Khadgol"
    ],
    "wof:name":"Khadgol",
    "wof:placetype":"locality"
},
  "geometry": {"coordinates":[72.19303000000002,35.39396],"type":"Point"}
}