{
  "type": "Feature",
  "properties": {
    "gn:admin1_code":"5",
    "gn:asciiname":"Goth Waghargi",
    "gn:country_code":"PK",
    "gn:dem":18,
    "gn:feature_class":"P",
    "gn:feature_code":"PPL",
    "gn:name":"Goth Waghargi",
    "gn:population":0,
    "gn:timezone":"Asia/Karachi",
    "iso:country":"PK",
    "name:und_x_variant":[
        "W\u0101ghreji"
    ],
    "wof:name":"Goth Waghargi",
    "wof:placetype":"locality"
},
  "geometry": {"coordinates":[68.93038,25.10835],"type":"Point"}
}