{
  "type": "Feature",
  "properties": {
    "gn:admin1_code":"3",
    "gn:asciiname":"Jangrai",
    "gn:country_code":"PK",
    "gn:dem":1913,
    "gn:feature_class":"P",
    "gn:feature_code":"PPL",
    "gn:name":"Jangrai",
    "gn:population":0,
    "gn:timezone":"Asia/Karachi",
    "iso:country":"PK",
    "wof:name":"Jangrai",
    "wof:placetype":"locality"
},
  "geometry": {"coordinates":[73.03901999999999,34.91603],"type":"Point"}
}