{
  "type": "Feature",
  "properties": {
    "gn:admin1_code":"5",
    "gn:asciiname":"Mazari Kambrani",
    "gn:country_code":"PK",
    "gn:dem":64,
    "gn:feature_class":"P",
    "gn:feature_code":"PPL",
    "gn:name":"Mazari Kambrani",
    "gn:population":0,
    "gn:timezone":"Asia/Karachi",
    "iso:country":"PK",
    "wof:name":"Mazari Kambrani",
    "wof:placetype":"locality"
},
  "geometry": {"coordinates":[67.47156,26.83512],"type":"Point"}
}