{
  "type": "Feature",
  "properties": {
    "gn:admin1_code":"4",
    "gn:asciiname":"Mahajaranwala",
    "gn:country_code":"PK",
    "gn:dem":166,
    "gn:feature_class":"P",
    "gn:feature_code":"PPL",
    "gn:name":"Mahajaranwala",
    "gn:population":0,
    "gn:timezone":"Asia/Karachi",
    "iso:country":"PK",
    "name:und_x_variant":[
        "Muh\u0101j\u012br\u0101nw\u0101le"
    ],
    "wof:name":"Mahajaranwala",
    "wof:placetype":"locality"
},
  "geometry": {"coordinates":[72.90064,30.66852],"type":"Point"}
}