{
  "type": "Feature",
  "properties": {
    "gn:admin1_code":"1.0",
    "gn:asciiname":"Ghundi Khel",
    "gn:country_code":"PK",
    "gn:dem":2176,
    "gn:feature_class":"P",
    "gn:feature_code":"PPL",
    "gn:name":"Ghundi Khel",
    "gn:population":0,
    "gn:timezone":"Asia/Karachi",
    "iso:country":"PK",
    "wof:name":"Ghundi Khel",
    "wof:placetype":"locality"
},
  "geometry": {"coordinates":[69.94209000000001,33.95582],"type":"Point"}
}