{
  "type": "Feature",
  "properties": {
    "gn:admin1_code":"03",
    "gn:asciiname":"Pishai",
    "gn:country_code":"PK",
    "gn:dem":811,
    "gn:feature_class":"P",
    "gn:feature_code":"PPL",
    "gn:name":"Pishai",
    "gn:population":0,
    "gn:timezone":"Asia/Karachi",
    "iso:country":"PK",
    "wof:name":"Pishai",
    "wof:placetype":"locality"
},
  "geometry": {"coordinates":[71.83134,34.85015],"type":"Point"}
}