{
  "type": "Feature",
  "properties": {
    "gn:admin1_code":"4",
    "gn:asciiname":"Jam Sharif Lar",
    "gn:country_code":"PK",
    "gn:dem":88,
    "gn:feature_class":"P",
    "gn:feature_code":"PPL",
    "gn:name":"J\u0101m Shar\u012bf L\u0101r",
    "gn:population":0,
    "gn:timezone":"Asia/Karachi",
    "iso:country":"PK",
    "wof:name":"Jam Sharif Lar",
    "wof:placetype":"locality"
},
  "geometry": {"coordinates":[70.80694,28.7875],"type":"Point"}
}