{
  "type": "Feature",
  "properties": {
    "gn:admin1_code":"3.0",
    "gn:asciiname":"Lapkai",
    "gn:country_code":"PK",
    "gn:dem":1478,
    "gn:feature_class":"P",
    "gn:feature_code":"PPL",
    "gn:name":"Lapkai",
    "gn:population":0,
    "gn:timezone":"Asia/Karachi",
    "iso:country":"PK",
    "wof:name":"Lapkai",
    "wof:placetype":"locality"
},
  "geometry": {"coordinates":[71.75703,35.08865],"type":"Point"}
}