{
  "type": "Feature",
  "properties": {
    "gn:admin1_code":"7.0",
    "gn:asciiname":"Haji Muhammad di Baihk",
    "gn:country_code":"PK",
    "gn:dem":4139,
    "gn:feature_class":"P",
    "gn:feature_code":"PPL",
    "gn:name":"Haji Muhammad di Baihk",
    "gn:population":0,
    "gn:timezone":"Asia/Karachi",
    "iso:country":"PK",
    "wof:name":"Haji Muhammad di Baihk",
    "wof:placetype":"locality"
},
  "geometry": {"coordinates":[73.70618,35.9528],"type":"Point"}
}