{
  "type": "Feature",
  "properties": {
    "gn:admin1_code":"5.0",
    "gn:asciiname":"Sumar Khaskhali",
    "gn:country_code":"PK",
    "gn:dem":34,
    "gn:feature_class":"P",
    "gn:feature_code":"PPL",
    "gn:name":"Sumar Khaskhali",
    "gn:population":0,
    "gn:timezone":"Asia/Karachi",
    "iso:country":"PK",
    "wof:name":"Sumar Khaskhali",
    "wof:placetype":"locality"
},
  "geometry": {"coordinates":[66.86634000000001,24.97033],"type":"Point"}
}