{
  "type": "Feature",
  "properties": {
    "gn:admin1_code":"4.0",
    "gn:asciiname":"Nurabad",
    "gn:country_code":"PK",
    "gn:dem":247,
    "gn:feature_class":"P",
    "gn:feature_code":"PPL",
    "gn:name":"Nurabad",
    "gn:population":0,
    "gn:timezone":"Asia/Karachi",
    "iso:country":"PK",
    "name:aze_x_preferred":[
        "Nurabad"
    ],
    "name:deu_x_preferred":[
        "Nurabad"
    ],
    "name:fas_x_preferred":[
        "\u0646\u0648\u0631\u0622\u0628\u0627\u062f"
    ],
    "name:fra_x_preferred":[
        "Nourabad"
    ],
    "name:hin_x_preferred":[
        "\u0928\u0942\u0930\u093e\u092c\u093e\u0926"
    ],
    "name:pol_x_preferred":[
        "Nurabad"
    ],
    "name:rus_x_preferred":[
        "\u041d\u0443\u0440\u0430\u0431\u0430\u0434"
    ],
    "name:ukr_x_preferred":[
        "\u041d\u0443\u0440\u0430\u0431\u0430\u0434"
    ],
    "wof:name":"Nurabad",
    "wof:placetype":"locality"
},
  "geometry": {"coordinates":[74.51144000000002,32.47542],"type":"Point"}
}