{
  "type": "Feature",
  "properties": {
    "gn:admin1_code":"4.0",
    "gn:asciiname":"Chak Four Hundred Eighty-eight Thal Development Authority",
    "gn:country_code":"PK",
    "gn:dem":139,
    "gn:feature_class":"P",
    "gn:feature_code":"PPL",
    "gn:name":"Chak Four Hundred Eighty-eight Thal Development Authority",
    "gn:population":0,
    "gn:timezone":"Asia/Karachi",
    "iso:country":"PK",
    "name:und_x_variant":[
        "Chak Four Hundred Eighty-Eight TDA",
        "Chak 488 TDA",
        "Mashinw\u0101la",
        "Chak Four Hundred Eighty-eight Thal Development Authority"
    ],
    "wof:name":"Chak Four Hundred Eighty-eight Thal Development Authority",
    "wof:placetype":"locality"
},
  "geometry": {"coordinates":[71.45324000000002,30.72668],"type":"Point"}
}