{
  "type": "Feature",
  "properties": {
    "gn:admin1_code":"4",
    "gn:asciiname":"Chak Twenty-four -One A Left",
    "gn:country_code":"PK",
    "gn:dem":189,
    "gn:feature_class":"P",
    "gn:feature_code":"PPL",
    "gn:name":"Chak Twenty-four -One A Left",
    "gn:population":0,
    "gn:timezone":"Asia/Karachi",
    "iso:country":"PK",
    "name:und_x_variant":[
        "Chak Twenty-four-One A L"
    ],
    "wof:name":"Chak Twenty-four -One A Left",
    "wof:placetype":"locality"
},
  "geometry": {"coordinates":[73.74383,30.86526],"type":"Point"}
}