{
  "type": "Feature",
  "properties": {
    "gn:admin1_code":"4.0",
    "gn:asciiname":"Dera Bakhtawar Khel",
    "gn:country_code":"PK",
    "gn:dem":191,
    "gn:feature_class":"P",
    "gn:feature_code":"PPL",
    "gn:name":"Dera Bakhtawar Khel",
    "gn:population":0,
    "gn:timezone":"Asia/Karachi",
    "iso:country":"PK",
    "wof:name":"Dera Bakhtawar Khel",
    "wof:placetype":"locality"
},
  "geometry": {"coordinates":[71.80041999999997,32.15903],"type":"Point"}
}