{
  "type": "Feature",
  "properties": {
    "gn:admin1_code":"5.0",
    "gn:asciiname":"Goth Khaskheli",
    "gn:country_code":"PK",
    "gn:dem":11,
    "gn:feature_class":"P",
    "gn:feature_code":"PPL",
    "gn:name":"Goth Khaskheli",
    "gn:population":0,
    "gn:timezone":"Asia/Karachi",
    "iso:country":"PK",
    "name:und_x_variant":[
        "Goth Soda Baloch",
        "Goth Khaskheli"
    ],
    "wof:name":"Goth Khaskheli",
    "wof:placetype":"locality"
},
  "geometry": {"coordinates":[67.91441999999999,24.6227],"type":"Point"}
}