{
  "type": "Feature",
  "properties": {
    "gn:admin1_code":"4.0",
    "gn:asciiname":"Chah Beriwala",
    "gn:country_code":"PK",
    "gn:dem":117,
    "gn:feature_class":"P",
    "gn:feature_code":"PPL",
    "gn:name":"Chah Beriwala",
    "gn:population":0,
    "gn:timezone":"Asia/Karachi",
    "iso:country":"PK",
    "name:und_x_variant":[
        "Beriw\u0101la"
    ],
    "wof:name":"Chah Beriwala",
    "wof:placetype":"locality"
},
  "geometry": {"coordinates":[71.65783,29.60799],"type":"Point"}
}