{
  "type": "Feature",
  "properties": {
    "gn:admin1_code":"2.0",
    "gn:asciiname":"Kili Jangi Khan",
    "gn:country_code":"PK",
    "gn:dem":1572,
    "gn:feature_class":"P",
    "gn:feature_code":"PPL",
    "gn:name":"Kili Jangi Khan",
    "gn:population":0,
    "gn:timezone":"Asia/Karachi",
    "iso:country":"PK",
    "wof:name":"Kili Jangi Khan",
    "wof:placetype":"locality"
},
  "geometry": {"coordinates":[66.26774,29.80127],"type":"Point"}
}