{
  "type": "Feature",
  "properties": {
    "gn:admin1_code":"3.0",
    "gn:asciiname":"Hindu Talao",
    "gn:country_code":"PK",
    "gn:dem":399,
    "gn:feature_class":"P",
    "gn:feature_code":"PPL",
    "gn:name":"Hindu Talao",
    "gn:population":0,
    "gn:timezone":"Asia/Karachi",
    "iso:country":"PK",
    "wof:name":"Hindu Talao",
    "wof:placetype":"locality"
},
  "geometry": {"coordinates":[71.5493,33.88375],"type":"Point"}
}