{
  "type": "Feature",
  "properties": {
    "gn:admin1_code":"3",
    "gn:asciiname":"Bar Tiknai",
    "gn:country_code":"PK",
    "gn:dem":1107,
    "gn:feature_class":"P",
    "gn:feature_code":"PPL",
    "gn:name":"Bar Tiknai",
    "gn:population":0,
    "gn:timezone":"Asia/Karachi",
    "iso:country":"PK",
    "wof:name":"Bar Tiknai",
    "wof:placetype":"locality"
},
  "geometry": {"coordinates":[72.07013000000001,34.78981],"type":"Point"}
}