{
  "type": "Feature",
  "properties": {
    "gn:admin1_code":"6",
    "gn:asciiname":"Patheri",
    "gn:country_code":"PK",
    "gn:dem":765,
    "gn:feature_class":"P",
    "gn:feature_code":"PPL",
    "gn:name":"Patheri",
    "gn:population":0,
    "gn:timezone":"Asia/Karachi",
    "iso:country":"PK",
    "wof:name":"Patheri",
    "wof:placetype":"locality"
},
  "geometry": {"coordinates":[73.84589,33.36186],"type":"Point"}
}