{
  "type": "Feature",
  "properties": {
    "gn:admin1_code":"1",
    "gn:asciiname":"Barwan",
    "gn:country_code":"PK",
    "gn:dem":887,
    "gn:feature_class":"P",
    "gn:feature_code":"PPL",
    "gn:name":"Barwan",
    "gn:population":0,
    "gn:timezone":"Asia/Karachi",
    "iso:country":"PK",
    "name:und_x_variant":[
        "Barw\u0101nd"
    ],
    "wof:name":"Barwan",
    "wof:placetype":"locality"
},
  "geometry": {"coordinates":[71.15241,33.87921],"type":"Point"}
}