{
  "type": "Feature",
  "properties": {
    "gn:admin1_code":"3",
    "gn:asciiname":"Bar Karingal",
    "gn:country_code":"PK",
    "gn:dem":2342,
    "gn:feature_class":"P",
    "gn:feature_code":"PPL",
    "gn:name":"Bar Karingal",
    "gn:population":0,
    "gn:timezone":"Asia/Karachi",
    "iso:country":"PK",
    "wof:name":"Bar Karingal",
    "wof:placetype":"locality"
},
  "geometry": {"coordinates":[72.57368000000002,34.97303],"type":"Point"}
}