{
  "type": "Feature",
  "properties": {
    "gn:admin1_code":"2.0",
    "gn:asciiname":"Kili Muhammad Hassan",
    "gn:country_code":"PK",
    "gn:dem":1053,
    "gn:feature_class":"P",
    "gn:feature_code":"PPL",
    "gn:name":"Kili Muhammad Hassan",
    "gn:population":0,
    "gn:timezone":"Asia/Karachi",
    "iso:country":"PK",
    "wof:name":"Kili Muhammad Hassan",
    "wof:placetype":"locality"
},
  "geometry": {"coordinates":[63.8738,29.04873],"type":"Point"}
}