{
  "type": "Feature",
  "properties": {
    "gn:admin1_code":"4.0",
    "gn:asciiname":"Burheke",
    "gn:country_code":"PK",
    "gn:dem":241,
    "gn:feature_class":"P",
    "gn:feature_code":"PPL",
    "gn:name":"Burheke",
    "gn:population":0,
    "gn:timezone":"Asia/Karachi",
    "iso:country":"PK",
    "name:und_x_variant":[
        "Bureke",
        "Burheke"
    ],
    "wof:name":"Burheke",
    "wof:placetype":"locality"
},
  "geometry": {"coordinates":[74.64525999999999,32.2794],"type":"Point"}
}