{
  "type": "Feature",
  "properties": {
    "gn:admin1_code":"3.0",
    "gn:asciiname":"Abdullahabad",
    "gn:country_code":"PK",
    "gn:dem":316,
    "gn:feature_class":"P",
    "gn:feature_code":"PPL",
    "gn:name":"Abdullahabad",
    "gn:population":0,
    "gn:timezone":"Asia/Karachi",
    "iso:country":"PK",
    "name:eng_x_preferred":[
        "Abdullahabad"
    ],
    "wof:name":"Abdullahabad",
    "wof:placetype":"locality"
},
  "geometry": {"coordinates":[71.77164,34.20767],"type":"Point"}
}