{
  "type": "Feature",
  "properties": {
    "gn:admin1_code":"4.0",
    "gn:asciiname":"Basti Khushiwal",
    "gn:country_code":"PK",
    "gn:dem":195,
    "gn:feature_class":"P",
    "gn:feature_code":"PPL",
    "gn:name":"Basti Khushiwal",
    "gn:population":0,
    "gn:timezone":"Asia/Karachi",
    "iso:country":"PK",
    "name:und_x_variant":[
        "Kot Khushia"
    ],
    "wof:name":"Basti Khushiwal",
    "wof:placetype":"locality"
},
  "geometry": {"coordinates":[74.41113,31.05567000000001],"type":"Point"}
}