{
  "type": "Feature",
  "properties": {
    "gn:admin1_code":"5",
    "gn:asciiname":"Goth Jalal",
    "gn:country_code":"PK",
    "gn:dem":62,
    "gn:feature_class":"P",
    "gn:feature_code":"PPL",
    "gn:name":"Goth Jalal",
    "gn:population":0,
    "gn:timezone":"Asia/Karachi",
    "iso:country":"PK",
    "name:und_x_variant":[
        "Pannu Kehr"
    ],
    "wof:name":"Goth Jalal",
    "wof:placetype":"locality"
},
  "geometry": {"coordinates":[68.56323,28.20219],"type":"Point"}
}