{
  "type": "Feature",
  "properties": {
    "gn:admin1_code":"3",
    "gn:asciiname":"Langurbat Ba",
    "gn:country_code":"PK",
    "gn:dem":1343,
    "gn:feature_class":"P",
    "gn:feature_code":"PPL",
    "gn:name":"Langurbat Ba",
    "gn:population":0,
    "gn:timezone":"Asia/Karachi",
    "iso:country":"PK",
    "name:eng_x_preferred":[
        "Langurbat"
    ],
    "name:urd_x_preferred":[
        "Langarba\u1e6d"
    ],
    "name:urd_x_variant":[
        "\u0644\u064e\u0646\u0652\u06af\u064e\u0631\u0628\u064e\u0679"
    ],
    "wof:name":"Langurbat Ba",
    "wof:placetype":"locality"
},
  "geometry": {"coordinates":[71.60092,35.3286],"type":"Point"}
}