{
  "type": "Feature",
  "properties": {
    "gn:admin1_code":"4.0",
    "gn:asciiname":"Dulatpura",
    "gn:country_code":"PK",
    "gn:dem":205,
    "gn:feature_class":"P",
    "gn:feature_code":"PPL",
    "gn:name":"Dulatpura",
    "gn:population":0,
    "gn:timezone":"Asia/Karachi",
    "iso:country":"PK",
    "name:und_x_variant":[
        "Daulatpur",
        "Daulatpura",
        "Dulatpura"
    ],
    "wof:name":"Dulatpura",
    "wof:placetype":"locality"
},
  "geometry": {"coordinates":[73.84868,31.67441],"type":"Point"}
}