{
  "type": "Feature",
  "properties": {
    "gn:admin1_code":"2.0",
    "gn:asciiname":"Niam Loghur Zard",
    "gn:country_code":"PK",
    "gn:dem":1213,
    "gn:feature_class":"P",
    "gn:feature_code":"PPL",
    "gn:name":"Niam Loghur Zard",
    "gn:population":0,
    "gn:timezone":"Asia/Karachi",
    "iso:country":"PK",
    "wof:name":"Niam Loghur Zard",
    "wof:placetype":"locality"
},
  "geometry": {"coordinates":[66.2567,27.70892000000001],"type":"Point"}
}