{
  "type": "Feature",
  "properties": {
    "gn:admin1_code":"3",
    "gn:asciiname":"Gojra",
    "gn:country_code":"PK",
    "gn:dem":800,
    "gn:feature_class":"P",
    "gn:feature_code":"PPL",
    "gn:name":"Gojra",
    "gn:population":0,
    "gn:timezone":"Asia/Karachi",
    "iso:country":"PK",
    "name:ara_x_preferred":[
        "\u063a\u0648\u062c\u0631\u0627"
    ],
    "name:ceb_x_preferred":[
        "Ibbetson\u0101b\u0101d"
    ],
    "name:fas_x_preferred":[
        "\u06af\u0648\u062c\u0631\u0647"
    ],
    "name:fra_x_preferred":[
        "Gojra"
    ],
    "name:pnb_x_preferred":[
        "\u06af\u0648\u062c\u0631\u0627"
    ],
    "name:pol_x_preferred":[
        "Gojra"
    ],
    "name:por_x_preferred":[
        "Gojra"
    ],
    "name:pus_x_preferred":[
        "\u06af\u0648\u062c\u0631\u0627"
    ],
    "name:rus_x_preferred":[
        "\u0413\u043e\u0434\u0436\u0440\u0430"
    ],
    "name:srp_x_preferred":[
        "\u0413\u043e\u0458\u0440\u0430"
    ],
    "name:swe_x_preferred":[
        "Gojra"
    ],
    "name:und_x_variant":[
        "Gojr\u0101h"
    ],
    "name:urd_x_preferred":[
        "\u06af\u0648\u062c\u0631\u06c1"
    ],
    "name:war_x_preferred":[
        "Gojra"
    ],
    "wof:name":"Gojra",
    "wof:placetype":"locality"
},
  "geometry": {"coordinates":[73.06618,34.31838],"type":"Point"}
}