{
  "type": "Feature",
  "properties": {
    "gn:admin1_code":"3",
    "gn:asciiname":"Gojra",
    "gn:country_code":"PK",
    "gn:dem":800,
    "gn:feature_class":"P",
    "gn:feature_code":"PPL",
    "gn:name":"Gojra",
    "gn:population":0,
    "gn:timezone":"Asia/Karachi",
    "iso:country":"PK",
    "name:und_x_variant":[
        "Gojr\u0101h"
    ],
    "wof:name":"Gojra",
    "wof:placetype":"locality"
},
  "geometry": {"coordinates":[73.06618,34.31838],"type":"Point"}
}