{
  "type": "Feature",
  "properties": {
    "gn:admin1_code":"5.0",
    "gn:asciiname":"Mal Sario Samu",
    "gn:country_code":"PK",
    "gn:dem":17,
    "gn:feature_class":"P",
    "gn:feature_code":"PPL",
    "gn:name":"Mal Sario Samu",
    "gn:population":0,
    "gn:timezone":"Asia/Karachi",
    "iso:country":"PK",
    "name:und_x_variant":[
        "M\u0101lsario"
    ],
    "wof:name":"Mal Sario Samu",
    "wof:placetype":"locality"
},
  "geometry": {"coordinates":[70.58056999999999,24.54144],"type":"Point"}
}