{
  "type": "Feature",
  "properties": {
    "gn:admin1_code":"5",
    "gn:asciiname":"Goth Pir Ahmed Shah",
    "gn:country_code":"PK",
    "gn:dem":27,
    "gn:feature_class":"P",
    "gn:feature_code":"PPL",
    "gn:name":"Goth Pir Ahmed Shah",
    "gn:population":0,
    "gn:timezone":"Asia/Karachi",
    "iso:country":"PK",
    "name:und_x_variant":[
        "Goth P\u012br Ahmad Sh\u0101h"
    ],
    "wof:name":"Goth Pir Ahmed Shah",
    "wof:placetype":"locality"
},
  "geometry": {"coordinates":[68.51659000000001,26.25611],"type":"Point"}
}