{
  "type": "Feature",
  "properties": {
    "gn:admin1_code":"4",
    "gn:asciiname":"Poliwala",
    "gn:country_code":"PK",
    "gn:dem":125,
    "gn:feature_class":"P",
    "gn:feature_code":"PPL",
    "gn:name":"Poliwala",
    "gn:population":0,
    "gn:timezone":"Asia/Karachi",
    "iso:country":"PK",
    "name:und_x_variant":[
        "P\u0101oliw\u0101la"
    ],
    "wof:name":"Poliwala",
    "wof:placetype":"locality"
},
  "geometry": {"coordinates":[70.68865,30.23186],"type":"Point"}
}