{
  "type": "Feature",
  "properties": {
    "gn:admin1_code":"4",
    "gn:asciiname":"Dhok Qazian",
    "gn:country_code":"PK",
    "gn:dem":509,
    "gn:feature_class":"P",
    "gn:feature_code":"PPL",
    "gn:name":"Dhok Qazian",
    "gn:population":0,
    "gn:timezone":"Asia/Karachi",
    "iso:country":"PK",
    "name:und_x_variant":[
        "Sohlew\u0101li",
        "Dhok Qazian"
    ],
    "wof:name":"Dhok Qazian",
    "wof:placetype":"locality"
},
  "geometry": {"coordinates":[72.18040999999999,32.81442],"type":"Point"}
}