{
  "type": "Feature",
  "properties": {
    "gn:admin1_code":"5",
    "gn:asciiname":"Goth Mangon Khaskheli",
    "gn:country_code":"PK",
    "gn:dem":16,
    "gn:feature_class":"P",
    "gn:feature_code":"PPL",
    "gn:name":"Goth Mangon Kh\u0101skheli",
    "gn:population":0,
    "gn:timezone":"Asia/Karachi",
    "iso:country":"PK",
    "wof:name":"Goth Mangon Khaskheli",
    "wof:placetype":"locality"
},
  "geometry": {"coordinates":[68.89214,25.1862],"type":"Point"}
}