{
  "type": "Feature",
  "properties": {
    "gn:admin1_code":"3.0",
    "gn:asciiname":"Tarinabad",
    "gn:country_code":"PK",
    "gn:dem":328,
    "gn:feature_class":"P",
    "gn:feature_code":"PPL",
    "gn:name":"Tarinabad",
    "gn:population":0,
    "gn:timezone":"Asia/Karachi",
    "iso:country":"PK",
    "name:eng_x_preferred":[
        "Tarinabad"
    ],
    "wof:name":"Tarinabad",
    "wof:placetype":"locality"
},
  "geometry": {"coordinates":[72.28706,34.17125],"type":"Point"}
}