{
  "type": "Feature",
  "properties": {
    "gn:admin1_code":"5.0",
    "gn:asciiname":"Kharo Chan",
    "gn:country_code":"PK",
    "gn:dem":0,
    "gn:feature_class":"P",
    "gn:feature_code":"PPL",
    "gn:name":"Kharo Chan",
    "gn:population":0,
    "gn:timezone":"Asia/Karachi",
    "iso:country":"PK",
    "wof:name":"Kharo Chan",
    "wof:placetype":"locality"
},
  "geometry": {"coordinates":[67.57680999999999,24.05485],"type":"Point"}
}