{
  "type": "Feature",
  "properties": {
    "gn:admin1_code":"04",
    "gn:asciiname":"Nur Shah",
    "gn:country_code":"PK",
    "gn:dem":122,
    "gn:feature_class":"P",
    "gn:feature_code":"PPL",
    "gn:name":"Nur Shah",
    "gn:population":0,
    "gn:timezone":"Asia/Karachi",
    "iso:country":"PK",
    "name:und_x_variant":[
        "Noor Shah",
        "Nur Shah"
    ],
    "wof:name":"Nur Shah",
    "wof:placetype":"locality"
},
  "geometry": {"coordinates":[71.77628,29.65777000000001],"type":"Point"}
}