{
  "type": "Feature",
  "properties": {
    "iso:country":"PK",
    "name:eng_x_preferred":[
        "Little Attock"
    ],
    "name:eng_x_variant":[
        "Attock Khurd"
    ],
    "name:jpn_x_preferred":[
        "\u30a2\u30c8\u30c3\u30af\u30fb\u30af\u30eb\u30c9"
    ],
    "name:nld_x_preferred":[
        "Attock Khurd"
    ],
    "name:pnb_x_preferred":[
        "\u0627\u0679\u06a9 \u062e\u0631\u062f"
    ],
    "name:unk_x_variant":[
        "Attock"
    ],
    "name:urd_x_preferred":[
        "\u0627\u0679\u06a9 \u062e\u0648\u0631\u062f"
    ],
    "qs:gn_country":"PK",
    "qs:gn_fcode":"PPL",
    "qs:gn_pop":0,
    "qs:name":"Attock Khurd",
    "qs:name_adm0":"Pakistan",
    "qs:name_adm1":"Punjab",
    "qs:photos":18,
    "qs:photos_1k":4,
    "qs:photos_9k":1,
    "qs:photos_9r":1,
    "qs:photos_all":18,
    "qs:photos_sr":1,
    "qs:placetype":"Town",
    "qs:pop_sr":"0",
    "qs:woe_adm0":23424922,
    "wd:wordcount":1243,
    "wof:name":"Attock Khurd",
    "wof:placetype":"locality"
},
  "geometry": {"coordinates":[72.24074,33.89281],"type":"Point"}
}