{
  "type": "Feature",
  "properties": {
    "gn:admin1_code":"3.0",
    "gn:asciiname":"Shawani Khel",
    "gn:country_code":"PK",
    "gn:dem":333,
    "gn:feature_class":"P",
    "gn:feature_code":"PPL",
    "gn:name":"Shawani Khel",
    "gn:population":0,
    "gn:timezone":"Asia/Karachi",
    "iso:country":"PK",
    "name:und_x_variant":[
        "S\u0101w\u0101ni Khel",
        "Shawani Khel"
    ],
    "wof:name":"Shawani Khel",
    "wof:placetype":"locality"
},
  "geometry": {"coordinates":[70.66234,32.8798],"type":"Point"}
}