{
  "type": "Feature",
  "properties": {
    "gn:admin1_code":"4",
    "gn:asciiname":"Basti Lal Gopang",
    "gn:country_code":"PK",
    "gn:dem":96,
    "gn:feature_class":"P",
    "gn:feature_code":"PPL",
    "gn:name":"Basti Lal Gopang",
    "gn:population":0,
    "gn:timezone":"Asia/Karachi",
    "iso:country":"PK",
    "name:und_x_variant":[
        "Basti Gop\u0101ng"
    ],
    "wof:name":"Basti Lal Gopang",
    "wof:placetype":"locality"
},
  "geometry": {"coordinates":[70.56595,29.14671],"type":"Point"}
}