{
  "type": "Feature",
  "properties": {
    "gn:admin1_code":"5",
    "gn:asciiname":"Goth Mir Ghazi Khan",
    "gn:country_code":"PK",
    "gn:dem":23,
    "gn:feature_class":"P",
    "gn:feature_code":"PPL",
    "gn:name":"Goth Mir Ghazi Khan",
    "gn:population":0,
    "gn:timezone":"Asia/Karachi",
    "iso:country":"PK",
    "wof:name":"Goth Mir Ghazi Khan",
    "wof:placetype":"locality"
},
  "geometry": {"coordinates":[68.93533000000001,25.9645],"type":"Point"}
}