{
  "type": "Feature",
  "properties": {
    "gn:admin1_code":"2.0",
    "gn:asciiname":"Darj",
    "gn:country_code":"PK",
    "gn:dem":693,
    "gn:feature_class":"P",
    "gn:feature_code":"PPL",
    "gn:name":"Darj",
    "gn:population":0,
    "gn:timezone":"Asia/Karachi",
    "iso:country":"PK",
    "name:und_x_variant":[
        "Daraj"
    ],
    "wof:name":"Darj",
    "wof:placetype":"locality"
},
  "geometry": {"coordinates":[65.21080000000001,28.5467],"type":"Point"}
}