{
  "type": "Feature",
  "properties": {
    "gn:admin1_code":"4",
    "gn:asciiname":"Chah Faujianwala",
    "gn:country_code":"PK",
    "gn:dem":147,
    "gn:feature_class":"P",
    "gn:feature_code":"PPL",
    "gn:name":"Chah Faujianwala",
    "gn:population":0,
    "gn:timezone":"Asia/Karachi",
    "iso:country":"PK",
    "name:und_x_variant":[
        "Basti Fauji\u0101nw\u0101li"
    ],
    "wof:name":"Chah Faujianwala",
    "wof:placetype":"locality"
},
  "geometry": {"coordinates":[72.06317,31.08306],"type":"Point"}
}