{
  "type": "Feature",
  "properties": {
    "gn:admin1_code":"3.0",
    "gn:asciiname":"Mazanrin Kili",
    "gn:country_code":"PK",
    "gn:dem":302,
    "gn:feature_class":"P",
    "gn:feature_code":"PPL",
    "gn:name":"Mazanrin Kili",
    "gn:population":0,
    "gn:timezone":"Asia/Karachi",
    "iso:country":"PK",
    "wof:name":"Mazanrin Kili",
    "wof:placetype":"locality"
},
  "geometry": {"coordinates":[70.1939,32.15062],"type":"Point"}
}