{
  "type": "Feature",
  "properties": {
    "gn:admin1_code":"2.0",
    "gn:asciiname":"Goth Shambu",
    "gn:country_code":"PK",
    "gn:dem":97,
    "gn:feature_class":"P",
    "gn:feature_code":"PPL",
    "gn:name":"Goth Shambu",
    "gn:population":0,
    "gn:timezone":"Asia/Karachi",
    "iso:country":"PK",
    "wof:name":"Goth Shambu",
    "wof:placetype":"locality"
},
  "geometry": {"coordinates":[66.84076999999999,25.08113],"type":"Point"}
}