{
  "type": "Feature",
  "properties": {
    "gn:admin1_code":"2.0",
    "gn:asciiname":"Ry Chauki",
    "gn:country_code":"PK",
    "gn:dem":1460,
    "gn:feature_class":"P",
    "gn:feature_code":"PPL",
    "gn:name":"Ry Chauki",
    "gn:population":0,
    "gn:timezone":"Asia/Karachi",
    "iso:country":"PK",
    "wof:name":"Ry Chauki",
    "wof:placetype":"locality"
},
  "geometry": {"coordinates":[69.26373000000001,31.1023],"type":"Point"}
}