{
  "type": "Feature",
  "properties": {
    "gn:admin1_code":"3",
    "gn:asciiname":"Phulgaran",
    "gn:country_code":"PK",
    "gn:dem":1189,
    "gn:feature_class":"P",
    "gn:feature_code":"PPL",
    "gn:name":"Phulgaran",
    "gn:population":0,
    "gn:timezone":"Asia/Karachi",
    "iso:country":"PK",
    "name:und_x_variant":[
        "Phugiran"
    ],
    "wof:name":"Phulgaran",
    "wof:placetype":"locality"
},
  "geometry": {"coordinates":[73.25539999999999,34.05086],"type":"Point"}
}