{
  "type": "Feature",
  "properties": {
    "gn:admin1_code":"5.0",
    "gn:asciiname":"Goth Soniwaro",
    "gn:country_code":"PK",
    "gn:dem":72,
    "gn:feature_class":"P",
    "gn:feature_code":"PPL",
    "gn:name":"Goth Soniwaro",
    "gn:population":0,
    "gn:timezone":"Asia/Karachi",
    "iso:country":"PK",
    "wof:name":"Goth Soniwaro",
    "wof:placetype":"locality"
},
  "geometry": {"coordinates":[69.62163000000001,26.57782000000001],"type":"Point"}
}