{
  "type": "Feature",
  "properties": {
    "gn:admin1_code":"5",
    "gn:asciiname":"Goth Saiyid Shah Muhammad",
    "gn:country_code":"PK",
    "gn:dem":15,
    "gn:feature_class":"P",
    "gn:feature_code":"PPL",
    "gn:name":"Goth Saiyid Shah Muhammad",
    "gn:population":0,
    "gn:timezone":"Asia/Karachi",
    "iso:country":"PK",
    "name:eng_x_preferred":[
        "Goth Saiyid Shah Muhammad"
    ],
    "wof:name":"Goth Saiyid Shah Muhammad",
    "wof:placetype":"locality"
},
  "geometry": {"coordinates":[68.36412,25.04644],"type":"Point"}
}