{
  "type": "Feature",
  "properties": {
    "gn:admin1_code":"4.0",
    "gn:asciiname":"Darbar Pir Norang Lal",
    "gn:country_code":"PK",
    "gn:dem":80,
    "gn:feature_class":"P",
    "gn:feature_code":"PPL",
    "gn:name":"Darbar Pir Norang Lal",
    "gn:population":0,
    "gn:timezone":"Asia/Karachi",
    "iso:country":"PK",
    "wof:name":"Darbar Pir Norang Lal",
    "wof:placetype":"locality"
},
  "geometry": {"coordinates":[69.85943,28.39027],"type":"Point"}
}