{
  "type": "Feature",
  "properties": {
    "gn:admin1_code":"5.0",
    "gn:asciiname":"Goth Dhabo Samejo",
    "gn:country_code":"PK",
    "gn:dem":41,
    "gn:feature_class":"P",
    "gn:feature_code":"PPL",
    "gn:name":"Goth Dhabo Samejo",
    "gn:population":0,
    "gn:timezone":"Asia/Karachi",
    "iso:country":"PK",
    "wof:name":"Goth Dhabo Samejo",
    "wof:placetype":"locality"
},
  "geometry": {"coordinates":[69.48586,24.78692],"type":"Point"}
}