{
  "type": "Feature",
  "properties": {
    "gn:admin1_code":"3",
    "gn:asciiname":"Shotar",
    "gn:country_code":"PK",
    "gn:dem":498,
    "gn:feature_class":"P",
    "gn:feature_code":"PPL",
    "gn:name":"Shotar",
    "gn:population":0,
    "gn:timezone":"Asia/Karachi",
    "iso:country":"PK",
    "wof:name":"Shotar",
    "wof:placetype":"locality"
},
  "geometry": {"coordinates":[72.93298,34.7997],"type":"Point"}
}