{
  "type": "Feature",
  "properties": {
    "gn:admin1_code":"3.0",
    "gn:asciiname":"Bashgalian Deh",
    "gn:country_code":"PK",
    "gn:dem":2327,
    "gn:feature_class":"P",
    "gn:feature_code":"PPL",
    "gn:name":"Bashgalian Deh",
    "gn:population":0,
    "gn:timezone":"Asia/Karachi",
    "iso:country":"PK",
    "name:eng_x_preferred":[
        "Bashgalian Deh"
    ],
    "wof:name":"Bashgalian Deh",
    "wof:placetype":"locality"
},
  "geometry": {"coordinates":[71.65120999999998,35.80253],"type":"Point"}
}