{
  "type": "Feature",
  "properties": {
    "gn:admin1_code":"3.0",
    "gn:asciiname":"Chabino Banda",
    "gn:country_code":"PK",
    "gn:dem":1175,
    "gn:feature_class":"P",
    "gn:feature_code":"PPL",
    "gn:name":"Chabino Banda",
    "gn:population":0,
    "gn:timezone":"Asia/Karachi",
    "iso:country":"PK",
    "wof:name":"Chabino Banda",
    "wof:placetype":"locality"
},
  "geometry": {"coordinates":[70.83968,33.52572],"type":"Point"}
}