{
  "type": "Feature",
  "properties": {
    "gn:admin1_code":"5.0",
    "gn:asciiname":"Makhiaro Jat",
    "gn:country_code":"PK",
    "gn:dem":8,
    "gn:feature_class":"P",
    "gn:feature_code":"PPL",
    "gn:name":"Makhiaro Jat",
    "gn:population":0,
    "gn:timezone":"Asia/Karachi",
    "iso:country":"PK",
    "name:eng_x_preferred":[
        "Makhiaro Jat"
    ],
    "wof:name":"Makhiaro Jat",
    "wof:placetype":"locality"
},
  "geometry": {"coordinates":[68.38507,24.57911],"type":"Point"}
}