{
  "type": "Feature",
  "properties": {
    "gn:admin1_code":"2.0",
    "gn:asciiname":"Goth Khair Muhammad",
    "gn:country_code":"PK",
    "gn:dem":87,
    "gn:feature_class":"P",
    "gn:feature_code":"PPL",
    "gn:name":"Goth Khair Muhammad",
    "gn:population":0,
    "gn:timezone":"Asia/Karachi",
    "iso:country":"PK",
    "wof:name":"Goth Khair Muhammad",
    "wof:placetype":"locality"
},
  "geometry": {"coordinates":[66.8036,25.26823],"type":"Point"}
}