{
  "type": "Feature",
  "properties": {
    "gn:admin1_code":"4.0",
    "gn:asciiname":"Hajipur",
    "gn:country_code":"PK",
    "gn:dem":134,
    "gn:feature_class":"P",
    "gn:feature_code":"PPL",
    "gn:name":"Hajipur",
    "gn:population":0,
    "gn:timezone":"Asia/Karachi",
    "iso:country":"PK",
    "name:ara_x_preferred":[
        "\u062d\u0627\u062c\u064a \u0628\u0648\u0631"
    ],
    "name:ben_x_preferred":[
        "\u09b9\u09be\u099c\u09bf\u09aa\u09c1\u09b0"
    ],
    "name:bih_x_preferred":[
        "\u0939\u093e\u091c\u0940\u092a\u0941\u0930"
    ],
    "name:bpy_x_preferred":[
        "\u09b9\u09be\u099c\u09bf\u09aa\u09c1\u09b0"
    ],
    "name:cat_x_preferred":[
        "Hajipur"
    ],
    "name:ceb_x_preferred":[
        "H\u0101j\u012bpur"
    ],
    "name:epo_x_preferred":[
        "Ha\u011dipuro"
    ],
    "name:fas_x_preferred":[
        "\u062d\u0627\u062c\u06cc\u067e\u0648\u0631"
    ],
    "name:fra_x_preferred":[
        "Hajipur"
    ],
    "name:guj_x_preferred":[
        "\u0ab9\u0abe\u0a9c\u0ac0\u0aaa\u0ac1\u0ab0"
    ],
    "name:hin_x_preferred":[
        "\u0939\u093e\u091c\u0940\u092a\u0941\u0930"
    ],
    "name:ita_x_preferred":[
        "Hajipur"
    ],
    "name:mai_x_preferred":[
        "\u0939\u093e\u091c\u0940\u092a\u0941\u0930"
    ],
    "name:mar_x_preferred":[
        "\u0939\u093e\u091c\u0940\u092a\u0941\u0930"
    ],
    "name:mlg_x_preferred":[
        "Hajipur"
    ],
    "name:msa_x_preferred":[
        "Hajipur"
    ],
    "name:nep_x_preferred":[
        "\u0939\u093e\u091c\u0940\u092a\u0941\u0930"
    ],
    "name:new_x_preferred":[
        "\u0939\u093e\u091c\u093f\u092a\u0941\u0930"
    ],
    "name:ori_x_preferred":[
        "\u0b39\u0b3e\u0b1c\u0b3f\u0b2a\u0b41\u0b30"
    ],
    "name:pol_x_preferred":[
        "Hajipur"
    ],
    "name:por_x_preferred":[
        "Hajipur"
    ],
    "name:rus_x_preferred":[
        "\u0425\u0430\u0434\u0436\u0438\u043f\u0443\u0440"
    ],
    "name:san_x_preferred":[
        "\u0939\u093e\u091c\u0940\u092a\u0941\u0930\u092e\u094d"
    ],
    "name:spa_x_preferred":[
        "Hajipur"
    ],
    "name:swe_x_preferred":[
        "Hajipur"
    ],
    "name:tam_x_preferred":[
        "\u0bb9\u0bbe\u0b9c\u0bbf\u0baa\u0bcd\u0baa\u0bc2\u0bb0\u0bcd"
    ],
    "name:tgl_x_preferred":[
        "Hajipur"
    ],
    "name:ukr_x_preferred":[
        "\u0425\u0430\u0434\u0436\u0456\u043f\u0443\u0440"
    ],
    "name:urd_x_preferred":[
        "\u062d\u0627\u062c\u06cc \u067e\u0648\u0631"
    ],
    "name:vie_x_preferred":[
        "Hajipur"
    ],
    "name:war_x_preferred":[
        "Hajipur"
    ],
    "name:zho_x_preferred":[
        "\u54c8\u5409\u666e\u5c14"
    ],
    "wof:name":"Hajipur",
    "wof:placetype":"locality"
},
  "geometry": {"coordinates":[71.7253,30.34065],"type":"Point"}
}