{
  "type": "Feature",
  "properties": {
    "gn:admin1_code":"2.0",
    "gn:asciiname":"Rudkan Bazar",
    "gn:country_code":"PK",
    "gn:dem":559,
    "gn:feature_class":"P",
    "gn:feature_code":"PPL",
    "gn:name":"Rudkan Bazar",
    "gn:population":0,
    "gn:timezone":"Asia/Karachi",
    "iso:country":"PK",
    "name:und_x_variant":[
        "Rudk\u0101n"
    ],
    "wof:name":"Rudkan Bazar",
    "wof:placetype":"locality"
},
  "geometry": {"coordinates":[64.32129999999999,26.10807],"type":"Point"}
}