{
  "type": "Feature",
  "properties": {
    "gn:admin1_code":"1.0",
    "gn:asciiname":"Parad Kalle",
    "gn:country_code":"PK",
    "gn:dem":1596,
    "gn:feature_class":"P",
    "gn:feature_code":"PPL",
    "gn:name":"Parad Kalle",
    "gn:population":0,
    "gn:timezone":"Asia/Karachi",
    "iso:country":"PK",
    "name:und_x_variant":[
        "Parao Kili"
    ],
    "wof:name":"Parad Kalle",
    "wof:placetype":"locality"
},
  "geometry": {"coordinates":[70.1628,33.8745],"type":"Point"}
}