{
  "type": "Feature",
  "properties": {
    "gn:admin1_code":"4",
    "gn:asciiname":"Ghrabi",
    "gn:country_code":"PK",
    "gn:dem":134,
    "gn:feature_class":"P",
    "gn:feature_code":"PPL",
    "gn:name":"Ghrabi",
    "gn:population":0,
    "gn:timezone":"Asia/Karachi",
    "iso:country":"PK",
    "name:und_x_variant":[
        "Gul\u0101b\u0101d"
    ],
    "wof:name":"Ghrabi",
    "wof:placetype":"locality"
},
  "geometry": {"coordinates":[72.12990000000001,30.45811],"type":"Point"}
}