{
  "type": "Feature",
  "properties": {
    "gn:admin1_code":"3.0",
    "gn:asciiname":"Diwangol",
    "gn:country_code":"PK",
    "gn:dem":2466,
    "gn:feature_class":"P",
    "gn:feature_code":"PPL",
    "gn:name":"Diwangol",
    "gn:population":0,
    "gn:timezone":"Asia/Karachi",
    "iso:country":"PK",
    "name:und_x_variant":[
        "D\u012bw\u0101ngo"
    ],
    "wof:name":"Diwangol",
    "wof:placetype":"locality"
},
  "geometry": {"coordinates":[72.63901,36.41912],"type":"Point"}
}