{
  "type": "Feature",
  "properties": {
    "gn:admin1_code":"4.0",
    "gn:asciiname":"Basti Lohari",
    "gn:country_code":"PK",
    "gn:dem":106,
    "gn:feature_class":"P",
    "gn:feature_code":"PPL",
    "gn:name":"Basti Loh\u0101ri",
    "gn:population":0,
    "gn:timezone":"Asia/Karachi",
    "iso:country":"PK",
    "wof:name":"Basti Lohari",
    "wof:placetype":"locality"
},
  "geometry": {"coordinates":[71.17905,29.33553],"type":"Point"}
}