{
  "type": "Feature",
  "properties": {
    "gn:admin1_code":"05",
    "gn:asciiname":"Rukhul Shah",
    "gn:cc2":"PK",
    "gn:country_code":"PK",
    "gn:dem":24,
    "gn:feature_class":"P",
    "gn:feature_code":"PPL",
    "gn:name":"Rukhul Shah",
    "gn:population":0,
    "gn:timezone":"Asia/Karachi",
    "iso:country":"PK",
    "name:und_x_variant":[
        "Runhul Shah",
        "Runahul Shah",
        "Runhul Shah Paksiri",
        "Rukhul Shah"
    ],
    "wof:name":"Rukhul Shah",
    "wof:placetype":"locality"
},
  "geometry": {"coordinates":[69.01666999999999,26.13333],"type":"Point"}
}