{
  "type": "Feature",
  "properties": {
    "gn:admin1_code":"4.0",
    "gn:asciiname":"Qaisarpur",
    "gn:country_code":"PK",
    "gn:dem":114,
    "gn:feature_class":"P",
    "gn:feature_code":"PPL",
    "gn:name":"Qaisarpur",
    "gn:population":0,
    "gn:timezone":"Asia/Karachi",
    "iso:country":"PK",
    "name:und_x_variant":[
        "Qesarpur"
    ],
    "wof:name":"Qaisarpur",
    "wof:placetype":"locality"
},
  "geometry": {"coordinates":[71.31883000000001,29.76418],"type":"Point"}
}