{
  "type": "Feature",
  "properties": {
    "gn:admin1_code":"04",
    "gn:asciiname":"Kot Shah Muhammad",
    "gn:country_code":"PK",
    "gn:dem":220,
    "gn:feature_class":"P",
    "gn:feature_code":"PPL",
    "gn:name":"Kot Shah Muhammad",
    "gn:population":0,
    "gn:timezone":"Asia/Karachi",
    "iso:country":"PK",
    "wof:name":"Kot Shah Muhammad",
    "wof:placetype":"locality"
},
  "geometry": {"coordinates":[73.99486,32.15776],"type":"Point"}
}