{
  "type": "Feature",
  "properties": {
    "gn:admin1_code":"04",
    "gn:asciiname":"Miani Ichha",
    "gn:country_code":"PK",
    "gn:dem":98,
    "gn:feature_class":"P",
    "gn:feature_code":"PPL",
    "gn:name":"Miani Ichha",
    "gn:population":0,
    "gn:timezone":"Asia/Karachi",
    "iso:country":"PK",
    "name:und_x_variant":[
        "Miani Achhia",
        "Miani Ichha"
    ],
    "wof:name":"Miani Ichha",
    "wof:placetype":"locality"
},
  "geometry": {"coordinates":[70.82354000000002,29.08701],"type":"Point"}
}