{
  "type": "Feature",
  "properties": {
    "gn:admin1_code":"2.0",
    "gn:asciiname":"Goth Abdul Jabbar",
    "gn:country_code":"PK",
    "gn:dem":51,
    "gn:feature_class":"P",
    "gn:feature_code":"PPL",
    "gn:name":"Goth Abdul Jabbar",
    "gn:population":0,
    "gn:timezone":"Asia/Karachi",
    "iso:country":"PK",
    "wof:name":"Goth Abdul Jabbar",
    "wof:placetype":"locality"
},
  "geometry": {"coordinates":[67.89744,28.12527],"type":"Point"}
}