{
  "type": "Feature",
  "properties": {
    "gn:admin1_code":"4",
    "gn:asciiname":"Khuda Bakhsh Dabe",
    "gn:country_code":"PK",
    "gn:dem":102,
    "gn:feature_class":"P",
    "gn:feature_code":"PPL",
    "gn:name":"Khuda Bakhsh Dabe",
    "gn:population":0,
    "gn:timezone":"Asia/Karachi",
    "iso:country":"PK",
    "wof:name":"Khuda Bakhsh Dabe",
    "wof:placetype":"locality"
},
  "geometry": {"coordinates":[70.38916999999999,29.34027],"type":"Point"}
}