{
  "type": "Feature",
  "properties": {
    "gn:admin1_code":"5",
    "gn:asciiname":"Goth Haji Khan Rind",
    "gn:country_code":"PK",
    "gn:dem":16,
    "gn:feature_class":"P",
    "gn:feature_code":"PPL",
    "gn:name":"Goth Haji Khan Rind",
    "gn:population":0,
    "gn:timezone":"Asia/Karachi",
    "iso:country":"PK",
    "name:und_x_variant":[
        "Goth H\u0101ji Ali Hasan"
    ],
    "wof:name":"Goth Haji Khan Rind",
    "wof:placetype":"locality"
},
  "geometry": {"coordinates":[69.16331,25.55938],"type":"Point"}
}