{
  "type": "Feature",
  "properties": {
    "gn:admin1_code":"4.0",
    "gn:asciiname":"Budhwar",
    "gn:country_code":"PK",
    "gn:dem":216,
    "gn:feature_class":"P",
    "gn:feature_code":"PPL",
    "gn:name":"Budhwar",
    "gn:population":0,
    "gn:timezone":"Asia/Karachi",
    "iso:country":"PK",
    "name:hin_x_preferred":[
        "\u092c\u0941\u0927\u0935\u093e\u0930 \u0917\u094b\u0924\u094d\u0930"
    ],
    "name:und_x_variant":[
        "Badhw\u0101r"
    ],
    "wof:name":"Budhwar",
    "wof:placetype":"locality"
},
  "geometry": {"coordinates":[74.45829000000001,31.33839],"type":"Point"}
}