{
  "type": "Feature",
  "properties": {
    "gn:admin1_code":"04",
    "gn:asciiname":"Chak Seventy-eight -Five Left",
    "gn:country_code":"PK",
    "gn:dem":171,
    "gn:feature_class":"P",
    "gn:feature_code":"PPL",
    "gn:name":"Chak Seventy-eight -Five Left",
    "gn:population":0,
    "gn:timezone":"Asia/Karachi",
    "iso:country":"PK",
    "name:und_x_variant":[
        "Shamspura"
    ],
    "wof:name":"Chak Seventy-eight -Five Left",
    "wof:placetype":"locality"
},
  "geometry": {"coordinates":[73.19603000000002,30.58656],"type":"Point"}
}