{
  "type": "Feature",
  "properties": {
    "gn:admin1_code":"04",
    "gn:asciiname":"Salmun",
    "gn:country_code":"PK",
    "gn:dem":382,
    "gn:feature_class":"P",
    "gn:feature_code":"PPL",
    "gn:name":"Salmun",
    "gn:population":0,
    "gn:timezone":"Asia/Karachi",
    "iso:country":"PK",
    "wof:name":"Salmun",
    "wof:placetype":"locality"
},
  "geometry": {"coordinates":[72.91216999999997,33.30848],"type":"Point"}
}