{
  "type": "Feature",
  "properties": {
    "gn:admin1_code":"4.0",
    "gn:asciiname":"Kot Sher Singh",
    "gn:country_code":"PK",
    "gn:dem":203,
    "gn:feature_class":"P",
    "gn:feature_code":"PPL",
    "gn:name":"Kot Sher Singh",
    "gn:population":0,
    "gn:timezone":"Asia/Karachi",
    "iso:country":"PK",
    "name:und_x_variant":[
        "Kot Sard\u0101r Sher Singh",
        "Naiyeke",
        "Kot Sher Singh"
    ],
    "wof:name":"Kot Sher Singh",
    "wof:placetype":"locality"
},
  "geometry": {"coordinates":[74.08381,31.17233],"type":"Point"}
}