{
  "type": "Feature",
  "properties": {
    "gn:admin1_code":"3.0",
    "gn:asciiname":"Dok",
    "gn:country_code":"PK",
    "gn:dem":3254,
    "gn:feature_class":"P",
    "gn:feature_code":"PPL",
    "gn:name":"Dok",
    "gn:population":0,
    "gn:timezone":"Asia/Karachi",
    "iso:country":"PK",
    "wof:name":"Dok",
    "wof:placetype":"locality"
},
  "geometry": {"coordinates":[72.3222,36.35859],"type":"Point"}
}