{
  "type": "Feature",
  "properties": {
    "gn:admin1_code":"5",
    "gn:asciiname":"Goth Mal Mahr",
    "gn:country_code":"PK",
    "gn:dem":36,
    "gn:feature_class":"P",
    "gn:feature_code":"PPL",
    "gn:name":"Goth Mal Mahr",
    "gn:population":0,
    "gn:timezone":"Asia/Karachi",
    "iso:country":"PK",
    "name:und_x_variant":[
        "M\u0101l Mahr"
    ],
    "wof:name":"Goth Mal Mahr",
    "wof:placetype":"locality"
},
  "geometry": {"coordinates":[68.06416999999999,26.29351],"type":"Point"}
}