{
  "type": "Feature",
  "properties": {
    "gn:admin1_code":"02",
    "gn:asciiname":"Kili Muhammad Khel",
    "gn:country_code":"PK",
    "gn:dem":1480,
    "gn:feature_class":"P",
    "gn:feature_code":"PPL",
    "gn:name":"Kili Muhammad Khel",
    "gn:population":0,
    "gn:timezone":"Asia/Karachi",
    "iso:country":"PK",
    "name:und_x_variant":[
        "Mohammad Khail",
        "Muhammad Kheli",
        "Kili Muhammad Khel"
    ],
    "wof:name":"Kili Muhammad Khel",
    "wof:placetype":"locality"
},
  "geometry": {"coordinates":[66.57284,30.00476],"type":"Point"}
}