{
  "type": "Feature",
  "properties": {
    "gn:admin1_code":"6",
    "gn:asciiname":"Ram Singh ka Talab",
    "gn:country_code":"PK",
    "gn:dem":405,
    "gn:feature_class":"P",
    "gn:feature_code":"PPL",
    "gn:name":"Ram Singh ka Talab",
    "gn:population":0,
    "gn:timezone":"Asia/Karachi",
    "iso:country":"PK",
    "wof:name":"Ram Singh ka Talab",
    "wof:placetype":"locality"
},
  "geometry": {"coordinates":[73.87090999999999,33.18996],"type":"Point"}
}