{
  "type": "Feature",
  "properties": {
    "gn:admin1_code":"4",
    "gn:asciiname":"Nasirpur",
    "gn:country_code":"PK",
    "gn:dem":171,
    "gn:feature_class":"P",
    "gn:feature_code":"PPL",
    "gn:name":"Nasirpur",
    "gn:population":0,
    "gn:timezone":"Asia/Karachi",
    "iso:country":"PK",
    "name:fas_x_preferred":[
        "\u0646\u0635\u06cc\u0631\u067e\u0648\u0631"
    ],
    "name:fra_x_preferred":[
        "Nasirpur"
    ],
    "name:pan_x_preferred":[
        "\u0a28\u0a38\u0a30\u0a2a\u0a41\u0a30"
    ],
    "name:snd_x_preferred":[
        "\u0646\u0635\u0631 \u067e\u0648\u0631"
    ],
    "wof:name":"Nasirpur",
    "wof:placetype":"locality"
},
  "geometry": {"coordinates":[73.76124,30.30139],"type":"Point"}
}