{
  "type": "Feature",
  "properties": {
    "gn:admin1_code":"4",
    "gn:asciiname":"Palwaniwala",
    "gn:country_code":"PK",
    "gn:dem":169,
    "gn:feature_class":"P",
    "gn:feature_code":"PPL",
    "gn:name":"Palwaniwala",
    "gn:population":0,
    "gn:timezone":"Asia/Karachi",
    "iso:country":"PK",
    "name:und_x_variant":[
        "Ch\u0101h Pahalw\u0101niw\u0101la"
    ],
    "wof:name":"Palwaniwala",
    "wof:placetype":"locality"
},
  "geometry": {"coordinates":[71.12777,31.57567],"type":"Point"}
}