{
  "type": "Feature",
  "properties": {
    "gn:admin1_code":"4",
    "gn:asciiname":"Kotli Kohala",
    "gn:country_code":"PK",
    "gn:dem":262,
    "gn:feature_class":"P",
    "gn:feature_code":"PPL",
    "gn:name":"Kotli Kohala",
    "gn:population":0,
    "gn:timezone":"Asia/Karachi",
    "iso:country":"PK",
    "name:und_x_variant":[
        "Kotla Koh\u0101ta"
    ],
    "wof:name":"Kotli Kohala",
    "wof:placetype":"locality"
},
  "geometry": {"coordinates":[74.24590000000001,32.69526],"type":"Point"}
}