{
  "type": "Feature",
  "properties": {
    "gn:admin1_code":"3.0",
    "gn:asciiname":"Bela",
    "gn:country_code":"PK",
    "gn:dem":1070,
    "gn:feature_class":"P",
    "gn:feature_code":"PPL",
    "gn:name":"Bela",
    "gn:population":0,
    "gn:timezone":"Asia/Karachi",
    "iso:country":"PK",
    "name:bos_x_preferred":[
        "Bela"
    ],
    "name:cat_x_preferred":[
        "Bela"
    ],
    "name:ceb_x_preferred":[
        "Bela"
    ],
    "name:deu_x_preferred":[
        "Bela"
    ],
    "name:eng_x_preferred":[
        "Bela"
    ],
    "name:eus_x_preferred":[
        "Bela"
    ],
    "name:fra_x_preferred":[
        "Bela"
    ],
    "name:heb_x_preferred":[
        "\u05d1\u05dc\u05e2"
    ],
    "name:hrv_x_preferred":[
        "Bela"
    ],
    "name:ita_x_preferred":[
        "Bela"
    ],
    "name:nld_x_preferred":[
        "Bela"
    ],
    "name:pol_x_preferred":[
        "Bela"
    ],
    "name:por_x_preferred":[
        "Bela"
    ],
    "name:slv_x_preferred":[
        "Bela"
    ],
    "name:srp_x_preferred":[
        "\u0411\u0435\u043b\u0430"
    ],
    "name:swe_x_preferred":[
        "Bela"
    ],
    "name:tgl_x_preferred":[
        "Bela"
    ],
    "name:urd_x_preferred":[
        "\u0628\u06cc\u0644\u0627"
    ],
    "wof:name":"Bela",
    "wof:placetype":"locality"
},
  "geometry": {"coordinates":[73.24767,35.27296],"type":"Point"}
}