{
  "type": "Feature",
  "properties": {
    "gn:admin1_code":"2.0",
    "gn:asciiname":"Shahbaz Kili",
    "gn:country_code":"PK",
    "gn:dem":1241,
    "gn:feature_class":"P",
    "gn:feature_code":"PPL",
    "gn:name":"Shahbaz Kili",
    "gn:population":0,
    "gn:timezone":"Asia/Karachi",
    "iso:country":"PK",
    "name:rus_x_preferred":[
        "\u0428\u0430\u0445\u0431\u0430\u0437-\u041a\u0438\u043b\u0438"
    ],
    "name:und_x_variant":[
        "Shakhbaz-Kili",
        "Shahbaz Kili"
    ],
    "wof:name":"Shahbaz Kili",
    "wof:placetype":"locality"
},
  "geometry": {"coordinates":[66.40137,30.92924],"type":"Point"}
}