{
  "type": "Feature",
  "properties": {
    "gn:admin1_code":"3.0",
    "gn:asciiname":"Sunitz",
    "gn:country_code":"PK",
    "gn:dem":2701,
    "gn:feature_class":"P",
    "gn:feature_code":"PPL",
    "gn:name":"Sunitz",
    "gn:population":0,
    "gn:timezone":"Asia/Karachi",
    "iso:country":"PK",
    "wof:name":"Sunitz",
    "wof:placetype":"locality"
},
  "geometry": {"coordinates":[71.76429,36.0629],"type":"Point"}
}