{
  "type": "Feature",
  "properties": {
    "gn:admin1_code":"3",
    "gn:asciiname":"Bagnar",
    "gn:country_code":"PK",
    "gn:dem":2573,
    "gn:feature_class":"P",
    "gn:feature_code":"PPL",
    "gn:name":"Bagnar",
    "gn:population":0,
    "gn:timezone":"Asia/Karachi",
    "iso:country":"PK",
    "wof:name":"Bagnar",
    "wof:placetype":"locality"
},
  "geometry": {"coordinates":[73.6925,34.94102],"type":"Point"}
}