{
  "type": "Feature",
  "properties": {
    "gn:admin1_code":"4",
    "gn:asciiname":"Qabwali Shumali",
    "gn:country_code":"PK",
    "gn:dem":201,
    "gn:feature_class":"P",
    "gn:feature_code":"PPL",
    "gn:name":"Qabwali Shumali",
    "gn:population":0,
    "gn:timezone":"Asia/Karachi",
    "iso:country":"PK",
    "name:und_x_variant":[
        "Nay Qabarw\u0101li"
    ],
    "wof:name":"Qabwali Shumali",
    "wof:placetype":"locality"
},
  "geometry": {"coordinates":[73.66091,31.57984],"type":"Point"}
}