{
  "type": "Feature",
  "properties": {
    "gn:admin1_code":"2.0",
    "gn:asciiname":"Mullayan Kili",
    "gn:country_code":"PK",
    "gn:dem":1810,
    "gn:feature_class":"P",
    "gn:feature_code":"PPL",
    "gn:name":"Mullayan Kili",
    "gn:population":0,
    "gn:timezone":"Asia/Karachi",
    "iso:country":"PK",
    "wof:name":"Mullayan Kili",
    "wof:placetype":"locality"
},
  "geometry": {"coordinates":[69.0598,31.43604],"type":"Point"}
}