{
  "type": "Feature",
  "properties": {
    "gn:admin1_code":"4",
    "gn:asciiname":"Massuwala",
    "gn:country_code":"PK",
    "gn:dem":134,
    "gn:feature_class":"P",
    "gn:feature_code":"PPL",
    "gn:name":"Massuwala",
    "gn:population":0,
    "gn:timezone":"Asia/Karachi",
    "iso:country":"PK",
    "name:eng_x_preferred":[
        "Massuw\u0101la"
    ],
    "wof:name":"Massuwala",
    "wof:placetype":"locality"
},
  "geometry": {"coordinates":[70.72821,30.38674],"type":"Point"}
}