{
  "type": "Feature",
  "properties": {
    "gn:admin1_code":"3.0",
    "gn:asciiname":"Malkot",
    "gn:country_code":"PK",
    "gn:dem":1354,
    "gn:feature_class":"P",
    "gn:feature_code":"PPL",
    "gn:name":"Malkot",
    "gn:population":0,
    "gn:timezone":"Asia/Karachi",
    "iso:country":"PK",
    "name:eng_x_preferred":[
        "Malkot"
    ],
    "wof:name":"Malkot",
    "wof:placetype":"locality"
},
  "geometry": {"coordinates":[73.44575,33.99462],"type":"Point"}
}