{
  "type": "Feature",
  "properties": {
    "gn:admin1_code":"04",
    "gn:asciiname":"Kot Rahm Shah",
    "gn:country_code":"PK",
    "gn:dem":213,
    "gn:feature_class":"P",
    "gn:feature_code":"PPL",
    "gn:name":"Kot Rahm Shah",
    "gn:population":0,
    "gn:timezone":"Asia/Karachi",
    "iso:country":"PK",
    "name:und_x_variant":[
        "Kot Rehm Shah",
        "Kot Rah\u012bm Sh\u0101h",
        "Kot Rahm Shah"
    ],
    "wof:name":"Kot Rahm Shah",
    "wof:placetype":"locality"
},
  "geometry": {"coordinates":[73.64615000000001,32.47470999999999],"type":"Point"}
}