{
  "type": "Feature",
  "properties": {
    "gn:admin1_code":"2.0",
    "gn:asciiname":"Manro",
    "gn:country_code":"PK",
    "gn:dem":1034,
    "gn:feature_class":"P",
    "gn:feature_code":"PPL",
    "gn:name":"Manro",
    "gn:population":0,
    "gn:timezone":"Asia/Karachi",
    "iso:country":"PK",
    "name:und_x_variant":[
        "M\u0101nrun"
    ],
    "wof:name":"Manro",
    "wof:placetype":"locality"
},
  "geometry": {"coordinates":[66.79666,27.64013],"type":"Point"}
}