{
  "type": "Feature",
  "properties": {
    "gn:admin1_code":"3",
    "gn:asciiname":"Danda Banda",
    "gn:country_code":"PK",
    "gn:dem":2359,
    "gn:feature_class":"P",
    "gn:feature_code":"PPL",
    "gn:name":"Danda Banda",
    "gn:population":0,
    "gn:timezone":"Asia/Karachi",
    "iso:country":"PK",
    "name:eng_x_preferred":[
        "Dand B\u0101nda"
    ],
    "wof:name":"Danda Banda",
    "wof:placetype":"locality"
},
  "geometry": {"coordinates":[71.76586999999998,35.14966],"type":"Point"}
}