{
  "type": "Feature",
  "properties": {
    "gn:admin1_code":"5.0",
    "gn:asciiname":"Ganghirko",
    "gn:country_code":"PK",
    "gn:dem":49,
    "gn:feature_class":"P",
    "gn:feature_code":"PPL",
    "gn:name":"Ganghirko",
    "gn:population":0,
    "gn:timezone":"Asia/Karachi",
    "iso:country":"PK",
    "name:und_x_variant":[
        "Changharko",
        "Ganghirko"
    ],
    "wof:name":"Ganghirko",
    "wof:placetype":"locality"
},
  "geometry": {"coordinates":[68.0504,27.31623],"type":"Point"}
}