{
  "type": "Feature",
  "properties": {
    "gn:admin1_code":"3.0",
    "gn:asciiname":"Khal",
    "gn:country_code":"PK",
    "gn:dem":866,
    "gn:feature_class":"P",
    "gn:feature_code":"PPL",
    "gn:name":"Khal",
    "gn:population":0,
    "gn:timezone":"Asia/Karachi",
    "iso:country":"PK",
    "name:eng_x_preferred":[
        "Khal"
    ],
    "wof:name":"Khal",
    "wof:placetype":"locality"
},
  "geometry": {"coordinates":[71.97551999999997,34.89668],"type":"Point"}
}