{
  "type": "Feature",
  "properties": {
    "gn:admin1_code":"4.0",
    "gn:asciiname":"Chhurke",
    "gn:country_code":"PK",
    "gn:dem":241,
    "gn:feature_class":"P",
    "gn:feature_code":"PPL",
    "gn:name":"Chhurke",
    "gn:population":0,
    "gn:timezone":"Asia/Karachi",
    "iso:country":"PK",
    "wof:name":"Chhurke",
    "wof:placetype":"locality"
},
  "geometry": {"coordinates":[74.67555,32.28738],"type":"Point"}
}