{
  "type": "Feature",
  "properties": {
    "gn:admin1_code":"4.0",
    "gn:asciiname":"Jhugian Shaikhawal",
    "gn:country_code":"PK",
    "gn:dem":176,
    "gn:feature_class":"P",
    "gn:feature_code":"PPL",
    "gn:name":"Jhugian Shaikhawal",
    "gn:population":0,
    "gn:timezone":"Asia/Karachi",
    "iso:country":"PK",
    "name:und_x_variant":[
        "Jhungi\u0101n Shaikhow\u0101l"
    ],
    "wof:name":"Jhugian Shaikhawal",
    "wof:placetype":"locality"
},
  "geometry": {"coordinates":[72.32046,32.1268],"type":"Point"}
}