{
  "type": "Feature",
  "properties": {
    "gn:admin1_code":"5",
    "gn:asciiname":"Goth Muhammad Naro",
    "gn:country_code":"PK",
    "gn:dem":17,
    "gn:feature_class":"P",
    "gn:feature_code":"PPL",
    "gn:name":"Goth Muhammad Naro",
    "gn:population":0,
    "gn:timezone":"Asia/Karachi",
    "iso:country":"PK",
    "name:eng_x_preferred":[
        "Goth Muhammad Naro"
    ],
    "wof:name":"Goth Muhammad Naro",
    "wof:placetype":"locality"
},
  "geometry": {"coordinates":[68.41744,25.04128],"type":"Point"}
}