{
  "type": "Feature",
  "properties": {
    "gn:admin1_code":"3.0",
    "gn:asciiname":"Fatehabad",
    "gn:country_code":"PK",
    "gn:dem":344,
    "gn:feature_class":"P",
    "gn:feature_code":"PPL",
    "gn:name":"Fatehabad",
    "gn:population":0,
    "gn:timezone":"Asia/Karachi",
    "iso:country":"PK",
    "name:ara_x_preferred":[
        "\u0641\u0627\u062a\u062d \u0623\u0628\u0627\u062f"
    ],
    "name:ben_x_preferred":[
        "\u09ab\u09a4\u09c7\u09b9\u09be\u09ac\u09be\u09a6"
    ],
    "name:deu_x_preferred":[
        "Fatehabad"
    ],
    "name:eng_x_preferred":[
        "Fatehabad"
    ],
    "name:ita_x_preferred":[
        "Fatehabad"
    ],
    "name:msa_x_preferred":[
        "Fatehabad"
    ],
    "name:nld_x_preferred":[
        "Fatehabad"
    ],
    "name:pol_x_preferred":[
        "Fatehabad"
    ],
    "wof:name":"Fatehabad",
    "wof:placetype":"locality"
},
  "geometry": {"coordinates":[71.90035,34.26782],"type":"Point"}
}