{
  "type": "Feature",
  "properties": {
    "gn:admin1_code":"2.0",
    "gn:asciiname":"Dudazai",
    "gn:country_code":"PK",
    "gn:dem":1507,
    "gn:feature_class":"P",
    "gn:feature_code":"PPL",
    "gn:name":"Dudazai",
    "gn:population":0,
    "gn:timezone":"Asia/Karachi",
    "iso:country":"PK",
    "name:und_x_variant":[
        "Dur Muhammad"
    ],
    "wof:name":"Dudazai",
    "wof:placetype":"locality"
},
  "geometry": {"coordinates":[66.37899,28.04192],"type":"Point"}
}