{
  "type": "Feature",
  "properties": {
    "gn:admin1_code":"4",
    "gn:asciiname":"Basti Waja Chah",
    "gn:country_code":"PK",
    "gn:dem":108,
    "gn:feature_class":"P",
    "gn:feature_code":"PPL",
    "gn:name":"Basti Waja Chah",
    "gn:population":0,
    "gn:timezone":"Asia/Karachi",
    "iso:country":"PK",
    "name:und_x_variant":[
        "Basti S\u012b\u0101lw\u0101la"
    ],
    "wof:name":"Basti Waja Chah",
    "wof:placetype":"locality"
},
  "geometry": {"coordinates":[70.60959,29.68095],"type":"Point"}
}