{
  "type": "Feature",
  "properties": {
    "gn:admin1_code":"4",
    "gn:asciiname":"Gujratianwala",
    "gn:country_code":"PK",
    "gn:dem":162,
    "gn:feature_class":"P",
    "gn:feature_code":"PPL",
    "gn:name":"Gujratianwala",
    "gn:population":0,
    "gn:timezone":"Asia/Karachi",
    "iso:country":"PK",
    "name:und_x_variant":[
        "Dera Gujr\u0101ti\u0101n"
    ],
    "wof:name":"Gujratianwala",
    "wof:placetype":"locality"
},
  "geometry": {"coordinates":[71.28543000000001,31.41043],"type":"Point"}
}