{
  "type": "Feature",
  "properties": {
    "gn:admin1_code":"07",
    "gn:asciiname":"Matiyal",
    "gn:country_code":"PK",
    "gn:dem":3369,
    "gn:feature_class":"P",
    "gn:feature_code":"PPL",
    "gn:name":"Matiyal",
    "gn:population":0,
    "gn:timezone":"Asia/Karachi",
    "iso:country":"PK",
    "wof:name":"Matiyal",
    "wof:placetype":"locality"
},
  "geometry": {"coordinates":[75.75412,34.69712],"type":"Point"}
}