{
  "type": "Feature",
  "properties": {
    "gn:admin1_code":"4",
    "gn:asciiname":"Taltakka",
    "gn:country_code":"PK",
    "gn:dem":300,
    "gn:feature_class":"P",
    "gn:feature_code":"PPL",
    "gn:name":"Taltakka",
    "gn:population":0,
    "gn:timezone":"Asia/Karachi",
    "iso:country":"PK",
    "name:und_x_variant":[
        "Dhok Nis\u0101r Kh\u0101n"
    ],
    "wof:name":"Taltakka",
    "wof:placetype":"locality"
},
  "geometry": {"coordinates":[73.38969,32.91361],"type":"Point"}
}