{
  "type": "Feature",
  "properties": {
    "gn:admin1_code":"04",
    "gn:asciiname":"Nathia",
    "gn:country_code":"PK",
    "gn:dem":315,
    "gn:feature_class":"P",
    "gn:feature_code":"PPL",
    "gn:name":"Nathia",
    "gn:population":0,
    "gn:timezone":"Asia/Karachi",
    "iso:country":"PK",
    "name:und_x_variant":[
        "Nautheh",
        "Nothi\u0101n",
        "Nathi\u0101n",
        "Nathia"
    ],
    "wof:name":"Nathia",
    "wof:placetype":"locality"
},
  "geometry": {"coordinates":[73.94368,32.86446],"type":"Point"}
}