{
  "type": "Feature",
  "properties": {
    "gn:admin1_code":"04",
    "gn:asciiname":"Chak Three Hundred Fifty-eight",
    "gn:country_code":"PK",
    "gn:dem":163,
    "gn:feature_class":"P",
    "gn:feature_code":"PPL",
    "gn:name":"Chak Three Hundred Fifty-eight",
    "gn:population":0,
    "gn:timezone":"Asia/Karachi",
    "iso:country":"PK",
    "name:und_x_variant":[
        "Mughi Shum\u0101li",
        "Chak Three Hundred Fifty-eight",
        "Mughli Shum\u0101li",
        "Mughali Shim\u0101li"
    ],
    "wof:name":"Chak Three Hundred Fifty-eight",
    "wof:placetype":"locality"
},
  "geometry": {"coordinates":[72.60167,30.93029000000001],"type":"Point"}
}