{
  "type": "Feature",
  "properties": {
    "gn:admin1_code":"5.0",
    "gn:asciiname":"Goth Abdul Hakim",
    "gn:country_code":"PK",
    "gn:dem":41,
    "gn:feature_class":"P",
    "gn:feature_code":"PPL",
    "gn:name":"Goth Abdul Hakim",
    "gn:population":0,
    "gn:timezone":"Asia/Karachi",
    "iso:country":"PK",
    "name:und_x_variant":[
        "Hakim Mangan"
    ],
    "wof:name":"Goth Abdul Hakim",
    "wof:placetype":"locality"
},
  "geometry": {"coordinates":[68.32300000000001,26.67201],"type":"Point"}
}