{
  "type": "Feature",
  "properties": {
    "gn:admin1_code":"4.0",
    "gn:asciiname":"Chak Forty Dara Nawab Branch",
    "gn:country_code":"PK",
    "gn:dem":109,
    "gn:feature_class":"P",
    "gn:feature_code":"PPL",
    "gn:name":"Chak Forty Dara Nawab Branch",
    "gn:population":0,
    "gn:timezone":"Asia/Karachi",
    "iso:country":"PK",
    "name:und_x_variant":[
        "Chak 40 D N B"
    ],
    "wof:name":"Chak Forty Dara Nawab Branch",
    "wof:placetype":"locality"
},
  "geometry": {"coordinates":[71.40094000000001,29.10349],"type":"Point"}
}