{
  "type": "Feature",
  "properties": {
    "gn:admin1_code":"4.0",
    "gn:asciiname":"Lai Khan Wala",
    "gn:country_code":"PK",
    "gn:dem":177,
    "gn:feature_class":"P",
    "gn:feature_code":"PPL",
    "gn:name":"Lai Khan Wala",
    "gn:population":0,
    "gn:timezone":"Asia/Karachi",
    "iso:country":"PK",
    "name:und_x_variant":[
        "L\u0101l Kh\u0101nw\u0101la"
    ],
    "wof:name":"Lai Khan Wala",
    "wof:placetype":"locality"
},
  "geometry": {"coordinates":[72.43553,32.08727],"type":"Point"}
}