{
  "type": "Feature",
  "properties": {
    "gn:admin1_code":"2.0",
    "gn:asciiname":"Kili Dost Muhammad",
    "gn:country_code":"PK",
    "gn:dem":1513,
    "gn:feature_class":"P",
    "gn:feature_code":"PPL",
    "gn:name":"Kili Dost Muhammad",
    "gn:population":0,
    "gn:timezone":"Asia/Karachi",
    "iso:country":"PK",
    "wof:name":"Kili Dost Muhammad",
    "wof:placetype":"locality"
},
  "geometry": {"coordinates":[66.23009999999999,27.13306],"type":"Point"}
}