{
  "type": "Feature",
  "properties": {
    "gn:admin1_code":"2",
    "gn:asciiname":"Manzake",
    "gn:country_code":"PK",
    "gn:dem":2281,
    "gn:feature_class":"P",
    "gn:feature_code":"PPL",
    "gn:name":"Manzake",
    "gn:population":0,
    "gn:timezone":"Asia/Karachi",
    "iso:country":"PK",
    "wof:name":"Manzake",
    "wof:placetype":"locality"
},
  "geometry": {"coordinates":[67.44468000000001,31.05559],"type":"Point"}
}