{
  "type": "Feature",
  "properties": {
    "gn:admin1_code":"4.0",
    "gn:asciiname":"Kanduwala Kalan",
    "gn:country_code":"PK",
    "gn:dem":177,
    "gn:feature_class":"P",
    "gn:feature_code":"PPL",
    "gn:name":"Kanduwala Kalan",
    "gn:population":0,
    "gn:timezone":"Asia/Karachi",
    "iso:country":"PK",
    "name:und_x_variant":[
        "Kanduw\u0101la Sar\u0101i"
    ],
    "wof:name":"Kanduwala Kalan",
    "wof:placetype":"locality"
},
  "geometry": {"coordinates":[73.75434,30.68659],"type":"Point"}
}