{
  "type": "Feature",
  "properties": {
    "gn:admin1_code":"1",
    "gn:asciiname":"Siga",
    "gn:country_code":"PK",
    "gn:dem":1765,
    "gn:feature_class":"P",
    "gn:feature_code":"PPL",
    "gn:name":"Siga",
    "gn:population":0,
    "gn:timezone":"Asia/Karachi",
    "iso:country":"PK",
    "name:ara_x_preferred":[
        "\u0633\u064a\u0642\u0627"
    ],
    "name:fra_x_preferred":[
        "Siga"
    ],
    "wof:name":"Siga",
    "wof:placetype":"locality"
},
  "geometry": {"coordinates":[69.81926999999999,32.57158],"type":"Point"}
}