{
  "type": "Feature",
  "properties": {
    "gn:admin1_code":"4.0",
    "gn:asciiname":"Basti Jallo Tarkhar",
    "gn:country_code":"PK",
    "gn:dem":83,
    "gn:feature_class":"P",
    "gn:feature_code":"PPL",
    "gn:name":"Basti Jallo Tarkhar",
    "gn:population":0,
    "gn:timezone":"Asia/Karachi",
    "iso:country":"PK",
    "name:und_x_variant":[
        "Basti Jalio Tark\u0101n"
    ],
    "wof:name":"Basti Jallo Tarkhar",
    "wof:placetype":"locality"
},
  "geometry": {"coordinates":[69.85415999999999,28.56526],"type":"Point"}
}