{
  "type": "Feature",
  "properties": {
    "gn:admin1_code":"1.0",
    "gn:asciiname":"Zakir Khel Chhota",
    "gn:country_code":"PK",
    "gn:dem":623,
    "gn:feature_class":"P",
    "gn:feature_code":"PPL",
    "gn:name":"Zakir Khel Chhota",
    "gn:population":0,
    "gn:timezone":"Asia/Karachi",
    "iso:country":"PK",
    "name:und_x_variant":[
        "Kot Zairoz"
    ],
    "wof:name":"Zakir Khel Chhota",
    "wof:placetype":"locality"
},
  "geometry": {"coordinates":[70.32762,32.95011],"type":"Point"}
}