{
  "type": "Feature",
  "properties": {
    "gn:admin1_code":"3.0",
    "gn:asciiname":"Ziarat Koruna",
    "gn:country_code":"PK",
    "gn:dem":333,
    "gn:feature_class":"P",
    "gn:feature_code":"PPL",
    "gn:name":"Ziarat Koruna",
    "gn:population":0,
    "gn:timezone":"Asia/Karachi",
    "iso:country":"PK",
    "name:eng_x_preferred":[
        "Ziarat Koruna"
    ],
    "wof:name":"Ziarat Koruna",
    "wof:placetype":"locality"
},
  "geometry": {"coordinates":[71.96298,34.26254],"type":"Point"}
}