{
  "type": "Feature",
  "properties": {
    "gn:admin1_code":"08",
    "gn:asciiname":"Niazian",
    "gn:country_code":"PK",
    "gn:dem":454,
    "gn:feature_class":"P",
    "gn:feature_code":"PPL",
    "gn:name":"Niazian",
    "gn:population":0,
    "gn:timezone":"Asia/Karachi",
    "iso:country":"PK",
    "wof:name":"Niazian",
    "wof:placetype":"locality"
},
  "geometry": {"coordinates":[73.16723,33.54129],"type":"Point"}
}