{
  "type": "Feature",
  "properties": {
    "gn:admin1_code":"5",
    "gn:asciiname":"Goth Mir Mullo",
    "gn:country_code":"PK",
    "gn:dem":51,
    "gn:feature_class":"P",
    "gn:feature_code":"PPL",
    "gn:name":"Goth Mir Mullo",
    "gn:population":0,
    "gn:timezone":"Asia/Karachi",
    "iso:country":"PK",
    "name:und_x_variant":[
        "Mir Mulla"
    ],
    "wof:name":"Goth Mir Mullo",
    "wof:placetype":"locality"
},
  "geometry": {"coordinates":[68.97561999999999,26.78011],"type":"Point"}
}