{
  "type": "Feature",
  "properties": {
    "gn:admin1_code":"4",
    "gn:asciiname":"Basti Sakhani",
    "gn:country_code":"PK",
    "gn:dem":130,
    "gn:feature_class":"P",
    "gn:feature_code":"PPL",
    "gn:name":"Basti Sakhani",
    "gn:population":0,
    "gn:timezone":"Asia/Karachi",
    "iso:country":"PK",
    "name:eng_x_preferred":[
        "Basti Shaikh\u0101ni"
    ],
    "wof:name":"Basti Sakhani",
    "wof:placetype":"locality"
},
  "geometry": {"coordinates":[70.86371,30.39868],"type":"Point"}
}