{
  "type": "Feature",
  "properties": {
    "gn:admin1_code":"4",
    "gn:asciiname":"Basti Mithuwali",
    "gn:country_code":"PK",
    "gn:dem":100,
    "gn:feature_class":"P",
    "gn:feature_code":"PPL",
    "gn:name":"Basti Mithuwali",
    "gn:population":0,
    "gn:timezone":"Asia/Karachi",
    "iso:country":"PK",
    "name:und_x_variant":[
        "Basti Mahanwali",
        "Basti Charraw\u0101li"
    ],
    "wof:name":"Basti Mithuwali",
    "wof:placetype":"locality"
},
  "geometry": {"coordinates":[70.88264000000002,29.34114000000001],"type":"Point"}
}