{
  "type": "Feature",
  "properties": {
    "gn:admin1_code":"7.0",
    "gn:asciiname":"Laher Khoku",
    "gn:country_code":"PK",
    "gn:dem":2489,
    "gn:feature_class":"P",
    "gn:feature_code":"PPL",
    "gn:name":"Laher Khoku",
    "gn:population":0,
    "gn:timezone":"Asia/Karachi",
    "iso:country":"PK",
    "wof:name":"Laher Khoku",
    "wof:placetype":"locality"
},
  "geometry": {"coordinates":[76.24208,35.24148],"type":"Point"}
}