{
  "type": "Feature",
  "properties": {
    "gn:admin1_code":"4",
    "gn:asciiname":"Bamwala",
    "gn:country_code":"PK",
    "gn:dem":123,
    "gn:feature_class":"P",
    "gn:feature_code":"PPL",
    "gn:name":"Bamwala",
    "gn:population":0,
    "gn:timezone":"Asia/Karachi",
    "iso:country":"PK",
    "name:eng_x_preferred":[
        "Bamwala"
    ],
    "wof:name":"Bamwala",
    "wof:placetype":"locality"
},
  "geometry": {"coordinates":[70.89660000000001,30.12224],"type":"Point"}
}