{
  "type": "Feature",
  "properties": {
    "gn:admin1_code":"4",
    "gn:asciiname":"Basti Allah Dad La",
    "gn:country_code":"PK",
    "gn:dem":79,
    "gn:feature_class":"P",
    "gn:feature_code":"PPL",
    "gn:name":"Basti Allah Dad La",
    "gn:population":0,
    "gn:timezone":"Asia/Karachi",
    "iso:country":"PK",
    "name:und_x_variant":[
        "H\u0101ji All\u0101h D\u0101d Lath\u0101ni"
    ],
    "wof:name":"Basti Allah Dad La",
    "wof:placetype":"locality"
},
  "geometry": {"coordinates":[69.78990999999999,28.4473],"type":"Point"}
}