{
  "type": "Feature",
  "properties": {
    "gn:admin1_code":"1.0",
    "gn:asciiname":"Sub Khel",
    "gn:country_code":"PK",
    "gn:dem":957,
    "gn:feature_class":"P",
    "gn:feature_code":"PPL",
    "gn:name":"Sub Khel",
    "gn:population":0,
    "gn:timezone":"Asia/Karachi",
    "iso:country":"PK",
    "wof:name":"Sub Khel",
    "wof:placetype":"locality"
},
  "geometry": {"coordinates":[70.67935,33.16956],"type":"Point"}
}