{
  "type": "Feature",
  "properties": {
    "gn:admin1_code":"03",
    "gn:asciiname":"Sikandarpur",
    "gn:country_code":"PK",
    "gn:dem":537,
    "gn:feature_class":"P",
    "gn:feature_code":"PPL",
    "gn:name":"Sikandarpur",
    "gn:population":0,
    "gn:timezone":"Asia/Karachi",
    "iso:country":"PK",
    "name:und_x_variant":[
        "Chh\u0101oni\u0101n"
    ],
    "wof:name":"Sikandarpur",
    "wof:placetype":"locality"
},
  "geometry": {"coordinates":[72.94481,34.00524],"type":"Point"}
}