{
  "type": "Feature",
  "properties": {
    "gn:admin1_code":"2.0",
    "gn:asciiname":"Kili Khan Muhammad",
    "gn:country_code":"PK",
    "gn:dem":1273,
    "gn:feature_class":"P",
    "gn:feature_code":"PPL",
    "gn:name":"Kili Khan Muhammad",
    "gn:population":0,
    "gn:timezone":"Asia/Karachi",
    "iso:country":"PK",
    "wof:name":"Kili Khan Muhammad",
    "wof:placetype":"locality"
},
  "geometry": {"coordinates":[66.33610999999999,27.20615],"type":"Point"}
}