{
  "type": "Feature",
  "properties": {
    "gn:admin1_code":"5.0",
    "gn:asciiname":"Diam Solangi",
    "gn:country_code":"PK",
    "gn:dem":44,
    "gn:feature_class":"P",
    "gn:feature_code":"PPL",
    "gn:name":"Diam Solangi",
    "gn:population":0,
    "gn:timezone":"Asia/Karachi",
    "iso:country":"PK",
    "wof:name":"Diam Solangi",
    "wof:placetype":"locality"
},
  "geometry": {"coordinates":[68.05242,26.91948],"type":"Point"}
}