{
  "type": "Feature",
  "properties": {
    "gn:admin1_code":"4.0",
    "gn:asciiname":"Yusafabad",
    "gn:country_code":"PK",
    "gn:dem":88,
    "gn:feature_class":"P",
    "gn:feature_code":"PPL",
    "gn:name":"Yusafabad",
    "gn:population":0,
    "gn:timezone":"Asia/Karachi",
    "iso:country":"PK",
    "name:und_x_variant":[
        "Yousaf\u0101b\u0101d",
        "Adda Y\u016bsuf\u0101b\u0101d",
        "Yusafabad"
    ],
    "wof:name":"Yusafabad",
    "wof:placetype":"locality"
},
  "geometry": {"coordinates":[70.35557,28.6317],"type":"Point"}
}