{
  "type": "Feature",
  "properties": {
    "gn:admin1_code":"3.0",
    "gn:asciiname":"Kagiar",
    "gn:country_code":"PK",
    "gn:dem":1448,
    "gn:feature_class":"P",
    "gn:feature_code":"PPL",
    "gn:name":"Kagiar",
    "gn:population":0,
    "gn:timezone":"Asia/Karachi",
    "iso:country":"PK",
    "name:und_x_variant":[
        "K\u0101gl\u0101n"
    ],
    "wof:name":"Kagiar",
    "wof:placetype":"locality"
},
  "geometry": {"coordinates":[73.31093,33.99767],"type":"Point"}
}