{
  "type": "Feature",
  "properties": {
    "gn:admin1_code":"4",
    "gn:asciiname":"Jangal Arjaniwala",
    "gn:country_code":"PK",
    "gn:dem":139,
    "gn:feature_class":"P",
    "gn:feature_code":"PPL",
    "gn:name":"Jangal Arjaniwala",
    "gn:population":0,
    "gn:timezone":"Asia/Karachi",
    "iso:country":"PK",
    "wof:name":"Jangal Arjaniwala",
    "wof:placetype":"locality"
},
  "geometry": {"coordinates":[71.94809000000002,30.57679000000001],"type":"Point"}
}