{
  "type": "Feature",
  "properties": {
    "gn:admin1_code":"2.0",
    "gn:asciiname":"Goth Lakhu",
    "gn:country_code":"PK",
    "gn:dem":206,
    "gn:feature_class":"P",
    "gn:feature_code":"PPL",
    "gn:name":"Goth Lakhu",
    "gn:population":0,
    "gn:timezone":"Asia/Karachi",
    "iso:country":"PK",
    "name:eng_x_preferred":[
        "Goth Lakhu"
    ],
    "wof:name":"Goth Lakhu",
    "wof:placetype":"locality"
},
  "geometry": {"coordinates":[66.80461,25.76935],"type":"Point"}
}