{
  "type": "Feature",
  "properties": {
    "gn:admin1_code":"6.0",
    "gn:asciiname":"Nalian",
    "gn:country_code":"PK",
    "gn:dem":1064,
    "gn:feature_class":"P",
    "gn:feature_code":"PPL",
    "gn:name":"Nalian",
    "gn:population":0,
    "gn:timezone":"Asia/Karachi",
    "iso:country":"PK",
    "wof:name":"Nalian",
    "wof:placetype":"locality"
},
  "geometry": {"coordinates":[73.75128000000002,33.68236],"type":"Point"}
}