{
  "type": "Feature",
  "properties": {
    "gn:admin1_code":"4",
    "gn:asciiname":"Basti Mahniwala",
    "gn:country_code":"PK",
    "gn:dem":147,
    "gn:feature_class":"P",
    "gn:feature_code":"PPL",
    "gn:name":"Basti Mahniwala",
    "gn:population":0,
    "gn:timezone":"Asia/Karachi",
    "iso:country":"PK",
    "name:und_x_variant":[
        "Basti M\u0101hn\u012bw\u0101la"
    ],
    "wof:name":"Basti Mahniwala",
    "wof:placetype":"locality"
},
  "geometry": {"coordinates":[72.07841999999999,31.08931],"type":"Point"}
}