{
  "type": "Feature",
  "properties": {
    "gn:admin1_code":"1.0",
    "gn:asciiname":"Injriwam Kili",
    "gn:country_code":"PK",
    "gn:dem":476,
    "gn:feature_class":"P",
    "gn:feature_code":"PPL",
    "gn:name":"Injriwam Kili",
    "gn:population":0,
    "gn:timezone":"Asia/Karachi",
    "iso:country":"PK",
    "wof:name":"Injriwam Kili",
    "wof:placetype":"locality"
},
  "geometry": {"coordinates":[70.25452,31.59357],"type":"Point"}
}