{
  "type": "Feature",
  "properties": {
    "gn:admin1_code":"7.0",
    "gn:asciiname":"Chator Bari",
    "gn:country_code":"PK",
    "gn:dem":2814,
    "gn:feature_class":"P",
    "gn:feature_code":"PPL",
    "gn:name":"Chator Bari",
    "gn:population":0,
    "gn:timezone":"Asia/Karachi",
    "iso:country":"PK",
    "wof:name":"Chator Bari",
    "wof:placetype":"locality"
},
  "geometry": {"coordinates":[74.46783000000001,35.80204000000001],"type":"Point"}
}