{
  "type": "Feature",
  "properties": {
    "gn:admin1_code":"2.0",
    "gn:asciiname":"Kili Hazar Juft",
    "gn:country_code":"PK",
    "gn:dem":905,
    "gn:feature_class":"P",
    "gn:feature_code":"PPL",
    "gn:name":"Kili Hazar Juft",
    "gn:population":0,
    "gn:timezone":"Asia/Karachi",
    "iso:country":"PK",
    "wof:name":"Kili Hazar Juft",
    "wof:placetype":"locality"
},
  "geometry": {"coordinates":[65.78532,29.51897],"type":"Point"}
}