{
  "type": "Feature",
  "properties": {
    "gn:admin1_code":"04",
    "gn:asciiname":"Qasba Karial",
    "gn:country_code":"PK",
    "gn:dem":249,
    "gn:feature_class":"P",
    "gn:feature_code":"PPL",
    "gn:name":"Qasba Karial",
    "gn:population":0,
    "gn:timezone":"Asia/Karachi",
    "iso:country":"PK",
    "name:und_x_variant":[
        "Qasbah",
        "Qasba Karial"
    ],
    "wof:name":"Qasba Karial",
    "wof:placetype":"locality"
},
  "geometry": {"coordinates":[73.79914000000002,32.91458],"type":"Point"}
}