{
  "type": "Feature",
  "properties": {
    "gn:admin1_code":"5.0",
    "gn:asciiname":"Kojhe ki Dhane",
    "gn:country_code":"PK",
    "gn:dem":156,
    "gn:feature_class":"P",
    "gn:feature_code":"PPL",
    "gn:name":"Kojhe ki Dhane",
    "gn:population":0,
    "gn:timezone":"Asia/Karachi",
    "iso:country":"PK",
    "wof:name":"Kojhe ki Dhane",
    "wof:placetype":"locality"
},
  "geometry": {"coordinates":[70.61537,25.62263],"type":"Point"}
}