{
  "type": "Feature",
  "properties": {
    "gn:admin1_code":"7.0",
    "gn:asciiname":"Thurmik",
    "gn:country_code":"PK",
    "gn:dem":3092,
    "gn:feature_class":"P",
    "gn:feature_code":"PPL",
    "gn:name":"Thurmik",
    "gn:population":0,
    "gn:timezone":"Asia/Karachi",
    "iso:country":"PK",
    "name:und_x_variant":[
        "T\u016brmik"
    ],
    "wof:name":"Thurmik",
    "wof:placetype":"locality"
},
  "geometry": {"coordinates":[75.30358000000003,35.45066],"type":"Point"}
}