{
  "type": "Feature",
  "properties": {
    "gn:admin1_code":"4",
    "gn:asciiname":"Kobo Pura",
    "gn:country_code":"PK",
    "gn:dem":221,
    "gn:feature_class":"P",
    "gn:feature_code":"PPL",
    "gn:name":"Kobo Pura",
    "gn:population":0,
    "gn:timezone":"Asia/Karachi",
    "iso:country":"PK",
    "name:und_x_variant":[
        "Kobopura"
    ],
    "wof:name":"Kobo Pura",
    "wof:placetype":"locality"
},
  "geometry": {"coordinates":[73.95674,32.32867],"type":"Point"}
}