{
  "type": "Feature",
  "properties": {
    "gn:admin1_code":"4",
    "gn:asciiname":"Chhijrian-di-Basti",
    "gn:country_code":"PK",
    "gn:dem":108,
    "gn:feature_class":"P",
    "gn:feature_code":"PPL",
    "gn:name":"Chhijrian-di-Basti",
    "gn:population":0,
    "gn:timezone":"Asia/Karachi",
    "iso:country":"PK",
    "name:und_x_variant":[
        "Basti Mandw\u0101nrin",
        "Moch\u012bw\u0101la",
        "Chhijrian-di-Basti"
    ],
    "wof:name":"Chhijrian-di-Basti",
    "wof:placetype":"locality"
},
  "geometry": {"coordinates":[70.8545,29.57644],"type":"Point"}
}