{
  "type": "Feature",
  "properties": {
    "gn:admin1_code":"6",
    "gn:asciiname":"Maneah",
    "gn:country_code":"PK",
    "gn:dem":2720,
    "gn:feature_class":"P",
    "gn:feature_code":"PPL",
    "gn:name":"Maneah",
    "gn:population":0,
    "gn:timezone":"Asia/Karachi",
    "iso:country":"PK",
    "wof:name":"Maneah",
    "wof:placetype":"locality"
},
  "geometry": {"coordinates":[73.6375,34.33889],"type":"Point"}
}