{
  "type": "Feature",
  "properties": {
    "gn:admin1_code":"5",
    "gn:asciiname":"Goth Yaqub Nundani",
    "gn:country_code":"PK",
    "gn:dem":17,
    "gn:feature_class":"P",
    "gn:feature_code":"PPL",
    "gn:name":"Goth Yaqub Nundani",
    "gn:population":0,
    "gn:timezone":"Asia/Karachi",
    "iso:country":"PK",
    "name:und_x_variant":[
        "Y\u0101q\u016bb Nund\u0101ni"
    ],
    "wof:name":"Goth Yaqub Nundani",
    "wof:placetype":"locality"
},
  "geometry": {"coordinates":[68.97069999999999,25.29866],"type":"Point"}
}