{
  "type": "Feature",
  "properties": {
    "gn:admin1_code":"4",
    "gn:asciiname":"Kumharwali",
    "gn:country_code":"PK",
    "gn:dem":117,
    "gn:feature_class":"P",
    "gn:feature_code":"PPL",
    "gn:name":"Kumharwali",
    "gn:population":0,
    "gn:timezone":"Asia/Karachi",
    "iso:country":"PK",
    "name:und_x_variant":[
        "Kumh\u0101r\u0101nw\u0101li"
    ],
    "wof:name":"Kumharwali",
    "wof:placetype":"locality"
},
  "geometry": {"coordinates":[70.92934,29.85855],"type":"Point"}
}