{
  "type": "Feature",
  "properties": {
    "gn:admin1_code":"2",
    "gn:asciiname":"Goth Gul Muhammad",
    "gn:country_code":"PK",
    "gn:dem":98,
    "gn:feature_class":"P",
    "gn:feature_code":"PPL",
    "gn:name":"Goth Gul Muhammad",
    "gn:population":0,
    "gn:timezone":"Asia/Karachi",
    "iso:country":"PK",
    "name:eng_x_preferred":[
        "Goth Gul Muhammad"
    ],
    "wof:name":"Goth Gul Muhammad",
    "wof:placetype":"locality"
},
  "geometry": {"coordinates":[66.83698000000001,25.09209],"type":"Point"}
}