{
  "type": "Feature",
  "properties": {
    "gn:admin1_code":"3.0",
    "gn:asciiname":"Polo Dhand Pul",
    "gn:country_code":"PK",
    "gn:dem":368,
    "gn:feature_class":"P",
    "gn:feature_code":"PPL",
    "gn:name":"Polo Dhand Pul",
    "gn:population":0,
    "gn:timezone":"Asia/Karachi",
    "iso:country":"PK",
    "name:eng_x_preferred":[
        "Plo Dhand"
    ],
    "wof:name":"Polo Dhand Pul",
    "wof:placetype":"locality"
},
  "geometry": {"coordinates":[72.43666999999998,34.18113],"type":"Point"}
}