{
  "type": "Feature",
  "properties": {
    "gn:admin1_code":"2.0",
    "gn:asciiname":"Kach Hasanzai",
    "gn:country_code":"PK",
    "gn:dem":2090,
    "gn:feature_class":"P",
    "gn:feature_code":"PPL",
    "gn:name":"Kach Hasanzai",
    "gn:population":0,
    "gn:timezone":"Asia/Karachi",
    "iso:country":"PK",
    "name:eng_x_preferred":[
        "Kach Hasan Zai"
    ],
    "name:und_x_variant":[
        "Kach",
        "Kats",
        "Kach Hasanzai"
    ],
    "wof:name":"Kach Hasanzai",
    "wof:placetype":"locality"
},
  "geometry": {"coordinates":[67.30826,30.88361],"type":"Point"}
}