{
  "type": "Feature",
  "properties": {
    "gn:admin1_code":"2",
    "gn:asciiname":"Aludo",
    "gn:country_code":"PK",
    "gn:dem":64,
    "gn:feature_class":"P",
    "gn:feature_code":"PPL",
    "gn:name":"Aludo",
    "gn:population":0,
    "gn:timezone":"Asia/Karachi",
    "iso:country":"PK",
    "name:und_x_variant":[
        "Al\u016bda"
    ],
    "wof:name":"Aludo",
    "wof:placetype":"locality"
},
  "geometry": {"coordinates":[67.79864999999999,28.43145],"type":"Point"}
}