{
  "type": "Feature",
  "properties": {
    "gn:admin1_code":"3.0",
    "gn:asciiname":"Kuz Koi",
    "gn:country_code":"PK",
    "gn:dem":2799,
    "gn:feature_class":"P",
    "gn:feature_code":"PPL",
    "gn:name":"Kuz Koi",
    "gn:population":0,
    "gn:timezone":"Asia/Karachi",
    "iso:country":"PK",
    "wof:name":"Kuz Koi",
    "wof:placetype":"locality"
},
  "geometry": {"coordinates":[73.19062,35.54506],"type":"Point"}
}