{
  "type": "Feature",
  "properties": {
    "gn:admin1_code":"3.0",
    "gn:asciiname":"Sefan Koruna",
    "gn:country_code":"PK",
    "gn:dem":344,
    "gn:feature_class":"P",
    "gn:feature_code":"PPL",
    "gn:name":"Sefan Koruna",
    "gn:population":0,
    "gn:timezone":"Asia/Karachi",
    "iso:country":"PK",
    "name:und_x_variant":[
        "Naw\u0101b S\u0101hib Kili"
    ],
    "wof:name":"Sefan Koruna",
    "wof:placetype":"locality"
},
  "geometry": {"coordinates":[71.42613,34.15858],"type":"Point"}
}