{
  "type": "Feature",
  "properties": {
    "gn:admin1_code":"1.0",
    "gn:asciiname":"Shakar Tangai",
    "gn:country_code":"PK",
    "gn:dem":973,
    "gn:feature_class":"P",
    "gn:feature_code":"PPL",
    "gn:name":"Shakar Tangai",
    "gn:population":0,
    "gn:timezone":"Asia/Karachi",
    "iso:country":"PK",
    "name:und_x_variant":[
        "Shakar Tangi"
    ],
    "wof:name":"Shakar Tangai",
    "wof:placetype":"locality"
},
  "geometry": {"coordinates":[71.02803,33.57541],"type":"Point"}
}