{
  "type": "Feature",
  "properties": {
    "gn:admin1_code":"5",
    "gn:asciiname":"Goth Murid Bagrani",
    "gn:country_code":"PK",
    "gn:dem":16,
    "gn:feature_class":"P",
    "gn:feature_code":"PPL",
    "gn:name":"Goth Murid Bagrani",
    "gn:population":0,
    "gn:timezone":"Asia/Karachi",
    "iso:country":"PK",
    "name:und_x_variant":[
        "Goth Fazal B\u0101gr\u0101ni"
    ],
    "wof:name":"Goth Murid Bagrani",
    "wof:placetype":"locality"
},
  "geometry": {"coordinates":[68.83804000000001,25.05368],"type":"Point"}
}