{
  "type": "Feature",
  "properties": {
    "gn:admin1_code":"4",
    "gn:asciiname":"Bhagoke Tibbi",
    "gn:country_code":"PK",
    "gn:dem":205,
    "gn:feature_class":"P",
    "gn:feature_code":"PPL",
    "gn:name":"Bhagoke Tibbi",
    "gn:population":0,
    "gn:timezone":"Asia/Karachi",
    "iso:country":"PK",
    "name:und_x_variant":[
        "Bhaguke"
    ],
    "wof:name":"Bhagoke Tibbi",
    "wof:placetype":"locality"
},
  "geometry": {"coordinates":[73.56092,31.87615],"type":"Point"}
}