{
  "type": "Feature",
  "properties": {
    "gn:admin1_code":"2.0",
    "gn:asciiname":"Abdul Rahman Gis",
    "gn:country_code":"PK",
    "gn:dem":1409,
    "gn:feature_class":"P",
    "gn:feature_code":"PPL",
    "gn:name":"Abdul Rahman Gis",
    "gn:population":0,
    "gn:timezone":"Asia/Karachi",
    "iso:country":"PK",
    "wof:name":"Abdul Rahman Gis",
    "wof:placetype":"locality"
},
  "geometry": {"coordinates":[64.06541,29.28374],"type":"Point"}
}