{
  "type": "Feature",
  "properties": {
    "gn:admin1_code":"5",
    "gn:asciiname":"Goth Shar",
    "gn:country_code":"PK",
    "gn:dem":65,
    "gn:feature_class":"P",
    "gn:feature_code":"PPL",
    "gn:name":"Goth Shar",
    "gn:population":0,
    "gn:timezone":"Asia/Karachi",
    "iso:country":"PK",
    "name:und_x_variant":[
        "Per\u0101r"
    ],
    "wof:name":"Goth Shar",
    "wof:placetype":"locality"
},
  "geometry": {"coordinates":[68.80334999999999,27.86406],"type":"Point"}
}