{
  "type": "Feature",
  "properties": {
    "gn:admin1_code":"4.0",
    "gn:asciiname":"Ganja Mend",
    "gn:country_code":"PK",
    "gn:dem":100,
    "gn:feature_class":"P",
    "gn:feature_code":"PPL",
    "gn:name":"Ganja Mend",
    "gn:population":0,
    "gn:timezone":"Asia/Karachi",
    "iso:country":"PK",
    "name:und_x_variant":[
        "Gunja Mend"
    ],
    "wof:name":"Ganja Mend",
    "wof:placetype":"locality"
},
  "geometry": {"coordinates":[70.75148,29.31511],"type":"Point"}
}