{
  "type": "Feature",
  "properties": {
    "gn:admin1_code":"1.0",
    "gn:asciiname":"Kharchaper",
    "gn:country_code":"PK",
    "gn:dem":3036,
    "gn:feature_class":"P",
    "gn:feature_code":"PPL",
    "gn:name":"Kharchaper",
    "gn:population":0,
    "gn:timezone":"Asia/Karachi",
    "iso:country":"PK",
    "name:und_x_variant":[
        "Rekhmin Dhand"
    ],
    "wof:name":"Kharchaper",
    "wof:placetype":"locality"
},
  "geometry": {"coordinates":[70.00971,34.01014],"type":"Point"}
}