{
  "type": "Feature",
  "properties": {
    "gn:admin1_code":"4.0",
    "gn:asciiname":"Jhalar Wahab",
    "gn:country_code":"PK",
    "gn:dem":178,
    "gn:feature_class":"P",
    "gn:feature_code":"PPL",
    "gn:name":"Jhalar Wahab",
    "gn:population":0,
    "gn:timezone":"Asia/Karachi",
    "iso:country":"PK",
    "name:und_x_variant":[
        "Jalhar Whab"
    ],
    "wof:name":"Jhalar Wahab",
    "wof:placetype":"locality"
},
  "geometry": {"coordinates":[72.8974,31.72898],"type":"Point"}
}