{
  "type": "Feature",
  "properties": {
    "gn:admin1_code":"7.0",
    "gn:asciiname":"Loga Brok",
    "gn:country_code":"PK",
    "gn:dem":3801,
    "gn:feature_class":"P",
    "gn:feature_code":"PPL",
    "gn:name":"Loga Brok",
    "gn:population":0,
    "gn:timezone":"Asia/Karachi",
    "iso:country":"PK",
    "wof:name":"Loga Brok",
    "wof:placetype":"locality"
},
  "geometry": {"coordinates":[75.40814,35.67493],"type":"Point"}
}