{
  "type": "Feature",
  "properties": {
    "gn:admin1_code":"2",
    "gn:asciiname":"Hudak Mirzai",
    "gn:country_code":"PK",
    "gn:dem":2220,
    "gn:feature_class":"P",
    "gn:feature_code":"PPL",
    "gn:name":"Hudak Mirzai",
    "gn:population":0,
    "gn:timezone":"Asia/Karachi",
    "iso:country":"PK",
    "name:eng_x_preferred":[
        "Haodak"
    ],
    "wof:name":"Hudak Mirzai",
    "wof:placetype":"locality"
},
  "geometry": {"coordinates":[67.70855,31.24338],"type":"Point"}
}