{
  "type": "Feature",
  "properties": {
    "gn:admin1_code":"4",
    "gn:asciiname":"Wagran",
    "gn:country_code":"PK",
    "gn:dem":257,
    "gn:feature_class":"P",
    "gn:feature_code":"PPL",
    "gn:name":"Wagran",
    "gn:population":0,
    "gn:timezone":"Asia/Karachi",
    "iso:country":"PK",
    "wof:name":"Wagran",
    "wof:placetype":"locality"
},
  "geometry": {"coordinates":[74.64912,32.49369],"type":"Point"}
}