{
  "type": "Feature",
  "properties": {
    "gn:admin1_code":"3",
    "gn:asciiname":"Shahi",
    "gn:country_code":"PK",
    "gn:dem":2259,
    "gn:feature_class":"P",
    "gn:feature_code":"PPL",
    "gn:name":"Shahi",
    "gn:population":0,
    "gn:timezone":"Asia/Karachi",
    "iso:country":"PK",
    "name:eng_x_preferred":[
        "Shahi"
    ],
    "wof:name":"Shahi",
    "wof:placetype":"locality"
},
  "geometry": {"coordinates":[71.68234,35.1597],"type":"Point"}
}