{
  "type": "Feature",
  "properties": {
    "gn:admin1_code":"3.0",
    "gn:asciiname":"Shilmanai Banda",
    "gn:country_code":"PK",
    "gn:dem":1054,
    "gn:feature_class":"P",
    "gn:feature_code":"PPL",
    "gn:name":"Shilmanai Banda",
    "gn:population":0,
    "gn:timezone":"Asia/Karachi",
    "iso:country":"PK",
    "wof:name":"Shilmanai Banda",
    "wof:placetype":"locality"
},
  "geometry": {"coordinates":[72.78623,34.67197],"type":"Point"}
}