{
  "type": "Feature",
  "properties": {
    "gn:admin1_code":"3",
    "gn:asciiname":"Malkan",
    "gn:country_code":"PK",
    "gn:dem":1525,
    "gn:feature_class":"P",
    "gn:feature_code":"PPL",
    "gn:name":"Malkan",
    "gn:population":0,
    "gn:timezone":"Asia/Karachi",
    "iso:country":"PK",
    "wof:name":"Malkan",
    "wof:placetype":"locality"
},
  "geometry": {"coordinates":[73.16315999999998,34.59861],"type":"Point"}
}