{
  "type": "Feature",
  "properties": {
    "gn:admin1_code":"7.0",
    "gn:asciiname":"Kunting",
    "gn:country_code":"PK",
    "gn:dem":3256,
    "gn:feature_class":"P",
    "gn:feature_code":"PPL",
    "gn:name":"Kunting",
    "gn:population":0,
    "gn:timezone":"Asia/Karachi",
    "iso:country":"PK",
    "wof:name":"Kunting",
    "wof:placetype":"locality"
},
  "geometry": {"coordinates":[75.95199000000002,34.98185],"type":"Point"}
}