{
  "type": "Feature",
  "properties": {
    "gn:admin1_code":"4",
    "gn:asciiname":"Kharal",
    "gn:country_code":"PK",
    "gn:dem":230,
    "gn:feature_class":"P",
    "gn:feature_code":"PPL",
    "gn:name":"Kharal",
    "gn:population":0,
    "gn:timezone":"Asia/Karachi",
    "iso:country":"PK",
    "name:und_x_variant":[
        "Kurl",
        "Kuri",
        "Kharal"
    ],
    "wof:name":"Kharal",
    "wof:placetype":"locality"
},
  "geometry": {"coordinates":[74.20950999999999,32.51949],"type":"Point"}
}