{
  "type": "Feature",
  "properties": {
    "gn:admin1_code":"4",
    "gn:asciiname":"Tabqara",
    "gn:country_code":"PK",
    "gn:dem":171,
    "gn:feature_class":"P",
    "gn:feature_code":"PPL",
    "gn:name":"Tabqara",
    "gn:population":0,
    "gn:timezone":"Asia/Karachi",
    "iso:country":"PK",
    "name:und_x_variant":[
        "Tebqara"
    ],
    "wof:name":"Tabqara",
    "wof:placetype":"locality"
},
  "geometry": {"coordinates":[73.76742,30.1676],"type":"Point"}
}