{
  "type": "Feature",
  "properties": {
    "gn:admin1_code":"3.0",
    "gn:asciiname":"Watan Khan",
    "gn:country_code":"PK",
    "gn:dem":304,
    "gn:feature_class":"P",
    "gn:feature_code":"PPL",
    "gn:name":"Watan Khan",
    "gn:population":0,
    "gn:timezone":"Asia/Karachi",
    "iso:country":"PK",
    "wof:name":"Watan Khan",
    "wof:placetype":"locality"
},
  "geometry": {"coordinates":[70.75798,32.91402],"type":"Point"}
}