{
  "type": "Feature",
  "properties": {
    "gn:admin1_code":"1.0",
    "gn:asciiname":"Lahanda",
    "gn:country_code":"PK",
    "gn:dem":498,
    "gn:feature_class":"P",
    "gn:feature_code":"PPL",
    "gn:name":"Lahanda",
    "gn:population":0,
    "gn:timezone":"Asia/Karachi",
    "iso:country":"PK",
    "wof:name":"Lahanda",
    "wof:placetype":"locality"
},
  "geometry": {"coordinates":[73.65134999999999,33.42539],"type":"Point"}
}