{
  "type": "Feature",
  "properties": {
    "gn:admin1_code":"4",
    "gn:asciiname":"Basti Mehrwala",
    "gn:country_code":"PK",
    "gn:dem":120,
    "gn:feature_class":"P",
    "gn:feature_code":"PPL",
    "gn:name":"Basti Mehrwala",
    "gn:population":0,
    "gn:timezone":"Asia/Karachi",
    "iso:country":"PK",
    "name:und_x_variant":[
        "Mir\u0101nw\u0101li Basti"
    ],
    "wof:name":"Basti Mehrwala",
    "wof:placetype":"locality"
},
  "geometry": {"coordinates":[72.18961,29.7877],"type":"Point"}
}