{
  "type": "Feature",
  "properties": {
    "gn:admin1_code":"4.0",
    "gn:asciiname":"Dalowal",
    "gn:country_code":"PK",
    "gn:dem":173,
    "gn:feature_class":"P",
    "gn:feature_code":"PPL",
    "gn:name":"Dalowal",
    "gn:population":0,
    "gn:timezone":"Asia/Karachi",
    "iso:country":"PK",
    "name:und_x_variant":[
        "Dolowal",
        "Daulow\u0101l",
        "Dalowal"
    ],
    "wof:name":"Dalowal",
    "wof:placetype":"locality"
},
  "geometry": {"coordinates":[73.51555999999999,30.6823],"type":"Point"}
}