{
  "type": "Feature",
  "properties": {
    "gn:admin1_code":"7.0",
    "gn:asciiname":"Said Afzal di Baihk",
    "gn:country_code":"PK",
    "gn:dem":3717,
    "gn:feature_class":"P",
    "gn:feature_code":"PPL",
    "gn:name":"Said Afzal di Baihk",
    "gn:population":0,
    "gn:timezone":"Asia/Karachi",
    "iso:country":"PK",
    "wof:name":"Said Afzal di Baihk",
    "wof:placetype":"locality"
},
  "geometry": {"coordinates":[73.89214,35.88948],"type":"Point"}
}