{
  "type": "Feature",
  "properties": {
    "gn:admin1_code":"05",
    "gn:asciiname":"Goth Saiyid Ahmad Shah",
    "gn:country_code":"PK",
    "gn:dem":2,
    "gn:feature_class":"P",
    "gn:feature_code":"PPL",
    "gn:name":"Goth Saiyid Ahmad Shah",
    "gn:population":0,
    "gn:timezone":"Asia/Karachi",
    "iso:country":"PK",
    "wof:name":"Goth Saiyid Ahmad Shah",
    "wof:placetype":"locality"
},
  "geometry": {"coordinates":[67.55553,24.26219],"type":"Point"}
}