{
  "type": "Feature",
  "properties": {
    "gn:admin1_code":"03",
    "gn:asciiname":"Sura",
    "gn:country_code":"PK",
    "gn:dem":676,
    "gn:feature_class":"P",
    "gn:feature_code":"PPL",
    "gn:name":"Sura",
    "gn:population":0,
    "gn:timezone":"Asia/Karachi",
    "iso:country":"PK",
    "wof:name":"Sura",
    "wof:placetype":"locality"
},
  "geometry": {"coordinates":[72.54846999999999,34.38791],"type":"Point"}
}