{
  "type": "Feature",
  "properties": {
    "gn:admin1_code":"01",
    "gn:asciiname":"Torwani",
    "gn:country_code":"PK",
    "gn:dem":1284,
    "gn:feature_class":"P",
    "gn:feature_code":"PPL",
    "gn:name":"Torwani",
    "gn:population":0,
    "gn:timezone":"Asia/Karachi",
    "iso:country":"PK",
    "wof:name":"Torwani",
    "wof:placetype":"locality"
},
  "geometry": {"coordinates":[69.62666999999999,32.27917],"type":"Point"}
}