{
  "type": "Feature",
  "properties": {
    "gn:admin1_code":"4.0",
    "gn:asciiname":"Kakowal",
    "gn:country_code":"PK",
    "gn:dem":218,
    "gn:feature_class":"P",
    "gn:feature_code":"PPL",
    "gn:name":"Kakowal",
    "gn:population":0,
    "gn:timezone":"Asia/Karachi",
    "iso:country":"PK",
    "name:und_x_variant":[
        "K\u0101kow\u0101",
        "Kakowal"
    ],
    "wof:name":"Kakowal",
    "wof:placetype":"locality"
},
  "geometry": {"coordinates":[73.42825999999999,32.51803],"type":"Point"}
}