{
  "type": "Feature",
  "properties": {
    "gn:admin1_code":"4",
    "gn:asciiname":"Dosewala",
    "gn:country_code":"PK",
    "gn:dem":163,
    "gn:feature_class":"P",
    "gn:feature_code":"PPL",
    "gn:name":"Dosewala",
    "gn:population":0,
    "gn:timezone":"Asia/Karachi",
    "iso:country":"PK",
    "name:und_x_variant":[
        "Dost Muhammadw\u0101la"
    ],
    "wof:name":"Dosewala",
    "wof:placetype":"locality"
},
  "geometry": {"coordinates":[71.26379,31.49043],"type":"Point"}
}