{
  "type": "Feature",
  "properties": {
    "gn:admin1_code":"3.0",
    "gn:asciiname":"Qala",
    "gn:country_code":"PK",
    "gn:dem":331,
    "gn:feature_class":"P",
    "gn:feature_code":"PPL",
    "gn:name":"Qala",
    "gn:population":0,
    "gn:timezone":"Asia/Karachi",
    "iso:country":"PK",
    "name:eng_x_preferred":[
        "Ghar\u012bb\u0101b\u0101d Sh\u0101h Qila"
    ],
    "wof:name":"Qala",
    "wof:placetype":"locality"
},
  "geometry": {"coordinates":[71.70701,34.25586],"type":"Point"}
}