{
  "type": "Feature",
  "properties": {
    "gn:admin1_code":"03",
    "gn:asciiname":"Sangar",
    "gn:country_code":"PK",
    "gn:dem":941,
    "gn:feature_class":"P",
    "gn:feature_code":"PPL",
    "gn:name":"Sangar",
    "gn:population":0,
    "gn:timezone":"Asia/Karachi",
    "iso:country":"PK",
    "name:eng_x_preferred":[
        "Sangar"
    ],
    "wof:name":"Sangar",
    "wof:placetype":"locality"
},
  "geometry": {"coordinates":[71.92931999999998,34.85164],"type":"Point"}
}