{
  "type": "Feature",
  "properties": {
    "gn:admin1_code":"03",
    "gn:asciiname":"Sangar",
    "gn:country_code":"PK",
    "gn:dem":941,
    "gn:feature_class":"P",
    "gn:feature_code":"PPL",
    "gn:name":"Sangar",
    "gn:population":0,
    "gn:timezone":"Asia/Karachi",
    "iso:country":"PK",
    "name:ben_x_preferred":[
        "\u09b8\u09be\u0999\u09cd\u0997\u09be\u09b0"
    ],
    "name:ell_x_preferred":[
        "\u03a3\u03b1\u03bd\u03b3\u03ba\u03ac\u03c1"
    ],
    "name:eng_x_preferred":[
        "Sangar"
    ],
    "name:fas_x_preferred":[
        "\u0633\u0627\u0646\u06af\u0627\u0631"
    ],
    "name:fra_x_preferred":[
        "Sangar"
    ],
    "name:heb_x_preferred":[
        "\u05e1\u05e0\u05d2\u05e8"
    ],
    "name:hin_x_preferred":[
        "\u0938\u0902\u0917\u0930"
    ],
    "name:ind_x_preferred":[
        "Sangar"
    ],
    "name:jpn_x_preferred":[
        "\u30b5\u30f3\u30ac\u30fc"
    ],
    "name:kor_x_preferred":[
        "\uc0c1\uac00\ub974"
    ],
    "name:nld_x_preferred":[
        "Sangar"
    ],
    "name:spa_x_preferred":[
        "Sangar"
    ],
    "name:swe_x_preferred":[
        "Sangar"
    ],
    "name:tur_x_preferred":[
        "Sangar"
    ],
    "name:urd_x_preferred":[
        "\u0633\u0627\u0646\u06af\u0627\u0631"
    ],
    "name:vie_x_preferred":[
        "Sangar"
    ],
    "name:zho_cn_x_preferred":[
        "\u6851\u52a0\u5c14"
    ],
    "name:zho_tw_x_preferred":[
        "\u6851\u52a0\u723e"
    ],
    "wof:name":"Sangar",
    "wof:placetype":"locality"
},
  "geometry": {"coordinates":[71.92932,34.85164],"type":"Point"}
}