{
  "type": "Feature",
  "properties": {
    "gn:admin1_code":"6",
    "gn:asciiname":"Tang Mahli",
    "gn:country_code":"PK",
    "gn:dem":2746,
    "gn:feature_class":"P",
    "gn:feature_code":"PPL",
    "gn:name":"Tang Mahli",
    "gn:population":0,
    "gn:timezone":"Asia/Karachi",
    "iso:country":"PK",
    "name:und_x_variant":[
        "Tungw\u0101li"
    ],
    "wof:name":"Tang Mahli",
    "wof:placetype":"locality"
},
  "geometry": {"coordinates":[73.55020999999998,34.55649],"type":"Point"}
}