{
  "type": "Feature",
  "properties": {
    "gn:admin1_code":"2.0",
    "gn:asciiname":"Goth Sawali",
    "gn:country_code":"PK",
    "gn:dem":347,
    "gn:feature_class":"P",
    "gn:feature_code":"PPL",
    "gn:name":"Goth Sawali",
    "gn:population":0,
    "gn:timezone":"Asia/Karachi",
    "iso:country":"PK",
    "name:und_x_variant":[
        "Goth Saw\u0101li"
    ],
    "wof:name":"Goth Sawali",
    "wof:placetype":"locality"
},
  "geometry": {"coordinates":[67.13956,25.61591],"type":"Point"}
}