{
  "type": "Feature",
  "properties": {
    "gn:admin1_code":"4",
    "gn:asciiname":"Mochi",
    "gn:country_code":"PK",
    "gn:dem":167,
    "gn:feature_class":"P",
    "gn:feature_code":"PPL",
    "gn:name":"Mochi",
    "gn:population":0,
    "gn:timezone":"Asia/Karachi",
    "iso:country":"PK",
    "name:ara_x_preferred":[
        "\u0645\u0648\u062a\u0634\u064a"
    ],
    "name:cat_x_preferred":[
        "Mochi"
    ],
    "name:ces_x_preferred":[
        "Mo\u010di"
    ],
    "name:dan_x_preferred":[
        "Mochi"
    ],
    "name:deu_x_preferred":[
        "Mochi"
    ],
    "name:epo_x_preferred":[
        "Mo\u0109io"
    ],
    "name:fas_x_preferred":[
        "\u0645\u0648\u0686\u06cc"
    ],
    "name:fin_x_preferred":[
        "Mochi"
    ],
    "name:fra_x_preferred":[
        "Mochi"
    ],
    "name:gla_x_preferred":[
        "Mochi"
    ],
    "name:glg_x_preferred":[
        "Mochi"
    ],
    "name:heb_x_preferred":[
        "\u05de\u05d5\u05e6'\u05d9"
    ],
    "name:hun_x_preferred":[
        "Mocsi"
    ],
    "name:hye_x_preferred":[
        "\u0544\u0578\u0579\u056b"
    ],
    "name:ind_x_preferred":[
        "Moci"
    ],
    "name:ita_x_preferred":[
        "Mochi"
    ],
    "name:jav_x_preferred":[
        "Mochi"
    ],
    "name:msa_x_preferred":[
        "Mochi"
    ],
    "name:nld_x_preferred":[
        "Mochi"
    ],
    "name:nor_x_preferred":[
        "Mochi"
    ],
    "name:pan_x_preferred":[
        "\u0a2e\u0a4b\u0a1a\u0a40"
    ],
    "name:pol_x_preferred":[
        "Mochi"
    ],
    "name:por_x_preferred":[
        "Mochi"
    ],
    "name:rus_x_preferred":[
        "\u041c\u043e\u0442\u0438"
    ],
    "name:slv_x_preferred":[
        "Mo\u010di"
    ],
    "name:spa_x_preferred":[
        "Mochi"
    ],
    "name:sun_x_preferred":[
        "Moci"
    ],
    "name:swe_x_preferred":[
        "Mochi"
    ],
    "name:tha_x_preferred":[
        "\u0e42\u0e21\u0e08\u0e34"
    ],
    "name:tur_x_preferred":[
        "Mochi"
    ],
    "name:ukr_x_preferred":[
        "\u0420\u0438\u0441\u0456\u0432'\u044f\u043d\u0438\u043a"
    ],
    "name:und_x_variant":[
        "Moch\u012bw\u0101la"
    ],
    "name:vie_x_preferred":[
        "Mochi"
    ],
    "wof:name":"Mochi",
    "wof:placetype":"locality"
},
  "geometry": {"coordinates":[71.07095,31.71441],"type":"Point"}
}