{
  "type": "Feature",
  "properties": {
    "gn:admin1_code":"2.0",
    "gn:asciiname":"Goth Urs",
    "gn:country_code":"PK",
    "gn:dem":53,
    "gn:feature_class":"P",
    "gn:feature_code":"PPL",
    "gn:name":"Goth Urs",
    "gn:population":0,
    "gn:timezone":"Asia/Karachi",
    "iso:country":"PK",
    "name:und_x_variant":[
        "Goth Una"
    ],
    "wof:name":"Goth Urs",
    "wof:placetype":"locality"
},
  "geometry": {"coordinates":[67.74321999999999,28.07762],"type":"Point"}
}