{
  "type": "Feature",
  "properties": {
    "gn:admin1_code":"6",
    "gn:asciiname":"Nagri",
    "gn:country_code":"PK",
    "gn:dem":1580,
    "gn:feature_class":"P",
    "gn:feature_code":"PPL",
    "gn:name":"Nagri",
    "gn:population":0,
    "gn:timezone":"Asia/Karachi",
    "iso:country":"PK",
    "name:ind_x_preferred":[
        "Negeri"
    ],
    "name:sun_x_preferred":[
        "Nagri"
    ],
    "wof:name":"Nagri",
    "wof:placetype":"locality"
},
  "geometry": {"coordinates":[73.66239,34.15254],"type":"Point"}
}