{
  "type": "Feature",
  "properties": {
    "gn:admin1_code":"3",
    "gn:asciiname":"Atsar",
    "gn:country_code":"PK",
    "gn:dem":2463,
    "gn:feature_class":"P",
    "gn:feature_code":"PPL",
    "gn:name":"Atsar",
    "gn:population":0,
    "gn:timezone":"Asia/Karachi",
    "iso:country":"PK",
    "wof:name":"Atsar",
    "wof:placetype":"locality"
},
  "geometry": {"coordinates":[72.45194000000002,35.23722],"type":"Point"}
}