{
  "type": "Feature",
  "properties": {
    "gn:admin1_code":"2.0",
    "gn:asciiname":"Sap Mena",
    "gn:country_code":"PK",
    "gn:dem":1020,
    "gn:feature_class":"P",
    "gn:feature_code":"PPL",
    "gn:name":"Sap Mena",
    "gn:population":0,
    "gn:timezone":"Asia/Karachi",
    "iso:country":"PK",
    "wof:name":"Sap Mena",
    "wof:placetype":"locality"
},
  "geometry": {"coordinates":[70.14431999999999,31.0343],"type":"Point"}
}