{
  "type": "Feature",
  "properties": {
    "gn:admin1_code":"2.0",
    "gn:asciiname":"Kili Mir Nur Mahammad",
    "gn:country_code":"PK",
    "gn:dem":1197,
    "gn:feature_class":"P",
    "gn:feature_code":"PPL",
    "gn:name":"Kili Mir Nur Mahammad",
    "gn:population":0,
    "gn:timezone":"Asia/Karachi",
    "iso:country":"PK",
    "wof:name":"Kili Mir Nur Mahammad",
    "wof:placetype":"locality"
},
  "geometry": {"coordinates":[65.26145,28.84254],"type":"Point"}
}