{
  "type": "Feature",
  "properties": {
    "gn:admin1_code":"2.0",
    "gn:asciiname":"Yar Sakhar",
    "gn:country_code":"PK",
    "gn:dem":1298,
    "gn:feature_class":"P",
    "gn:feature_code":"PPL",
    "gn:name":"Yar Sakhar",
    "gn:population":0,
    "gn:timezone":"Asia/Karachi",
    "iso:country":"PK",
    "wof:name":"Yar Sakhar",
    "wof:placetype":"locality"
},
  "geometry": {"coordinates":[69.24165000000001,30.49187],"type":"Point"}
}