{
  "type": "Feature",
  "properties": {
    "gn:admin1_code":"3.0",
    "gn:asciiname":"Bachaklana",
    "gn:country_code":"PK",
    "gn:dem":1924,
    "gn:feature_class":"P",
    "gn:feature_code":"PPL",
    "gn:name":"Bachaklana",
    "gn:population":0,
    "gn:timezone":"Asia/Karachi",
    "iso:country":"PK",
    "wof:name":"Bachaklana",
    "wof:placetype":"locality"
},
  "geometry": {"coordinates":[71.90103000000001,35.61047],"type":"Point"}
}