{
  "type": "Feature",
  "properties": {
    "gn:admin1_code":"5.0",
    "gn:asciiname":"Wanjaro Wario",
    "gn:country_code":"PK",
    "gn:dem":6,
    "gn:feature_class":"P",
    "gn:feature_code":"PPL",
    "gn:name":"Wanj\u0101ro W\u0101rio",
    "gn:population":0,
    "gn:timezone":"Asia/Karachi",
    "iso:country":"PK",
    "wof:name":"Wanjaro Wario",
    "wof:placetype":"locality"
},
  "geometry": {"coordinates":[67.64972,24.52611],"type":"Point"}
}