{
  "type": "Feature",
  "properties": {
    "gn:admin1_code":"5",
    "gn:asciiname":"Habibwari Tar",
    "gn:country_code":"PK",
    "gn:dem":37,
    "gn:feature_class":"P",
    "gn:feature_code":"PPL",
    "gn:name":"Habibwari Tar",
    "gn:population":0,
    "gn:timezone":"Asia/Karachi",
    "iso:country":"PK",
    "name:und_x_variant":[
        "Hab\u012bbw\u0101ri Kh\u016bi"
    ],
    "wof:name":"Habibwari Tar",
    "wof:placetype":"locality"
},
  "geometry": {"coordinates":[69.28536,26.12728],"type":"Point"}
}