{
  "type": "Feature",
  "properties": {
    "gn:admin1_code":"3",
    "gn:asciiname":"Kuz Garhai",
    "gn:country_code":"PK",
    "gn:dem":1402,
    "gn:feature_class":"P",
    "gn:feature_code":"PPL",
    "gn:name":"Kuz Garhai",
    "gn:population":0,
    "gn:timezone":"Asia/Karachi",
    "iso:country":"PK",
    "name:und_x_variant":[
        "Kuz Garai",
        "Kuz Garhai"
    ],
    "wof:name":"Kuz Garhai",
    "wof:placetype":"locality"
},
  "geometry": {"coordinates":[72.53673000000001,35.17989],"type":"Point"}
}