{
  "type": "Feature",
  "properties": {
    "gn:admin1_code":"5.0",
    "gn:asciiname":"Pir Mohiuddin",
    "gn:country_code":"PK",
    "gn:dem":5,
    "gn:feature_class":"P",
    "gn:feature_code":"PPL",
    "gn:name":"P\u012br Mohiuddin",
    "gn:population":0,
    "gn:timezone":"Asia/Karachi",
    "iso:country":"PK",
    "wof:name":"Pir Mohiuddin",
    "wof:placetype":"locality"
},
  "geometry": {"coordinates":[67.55916999999999,24.64556],"type":"Point"}
}