{
  "type": "Feature",
  "properties": {
    "gn:admin1_code":"4.0",
    "gn:asciiname":"Lasura",
    "gn:country_code":"PK",
    "gn:dem":750,
    "gn:feature_class":"P",
    "gn:feature_code":"PPL",
    "gn:name":"Lasura",
    "gn:population":0,
    "gn:timezone":"Asia/Karachi",
    "iso:country":"PK",
    "name:eng_x_preferred":[
        "Lesura"
    ],
    "name:und_x_variant":[
        "Lesure",
        "Lasura"
    ],
    "wof:name":"Lasura",
    "wof:placetype":"locality"
},
  "geometry": {"coordinates":[70.17735,30.11932],"type":"Point"}
}