{
  "type": "Feature",
  "properties": {
    "gn:admin1_code":"04",
    "gn:asciiname":"Malleke",
    "gn:country_code":"PK",
    "gn:dem":165,
    "gn:feature_class":"P",
    "gn:feature_code":"PPL",
    "gn:name":"Malleke",
    "gn:population":0,
    "gn:timezone":"Asia/Karachi",
    "iso:country":"PK",
    "name:und_x_variant":[
        "Malleke T\u0101r\u016bke",
        "Malleke"
    ],
    "wof:name":"Malleke",
    "wof:placetype":"locality"
},
  "geometry": {"coordinates":[73.508,30.32049],"type":"Point"}
}