{
  "type": "Feature",
  "properties": {
    "gn:admin1_code":"4.0",
    "gn:asciiname":"Dera Jan Khelwala",
    "gn:country_code":"PK",
    "gn:dem":190,
    "gn:feature_class":"P",
    "gn:feature_code":"PPL",
    "gn:name":"Dera Jan Khelwala",
    "gn:population":0,
    "gn:timezone":"Asia/Karachi",
    "iso:country":"PK",
    "name:und_x_variant":[
        "H\u0101ji Muhammad Sherw\u0101la Dera"
    ],
    "wof:name":"Dera Jan Khelwala",
    "wof:placetype":"locality"
},
  "geometry": {"coordinates":[71.87823,31.99002],"type":"Point"}
}