{
  "type": "Feature",
  "properties": {
    "gn:admin1_code":"4.0",
    "gn:asciiname":"Chak Thirty-four - Four Left",
    "gn:country_code":"PK",
    "gn:dem":168,
    "gn:feature_class":"P",
    "gn:feature_code":"PPL",
    "gn:name":"Chak Thirty-four - Four Left",
    "gn:population":0,
    "gn:timezone":"Asia/Karachi",
    "iso:country":"PK",
    "name:und_x_variant":[
        "Chak Thirty-four Four L",
        "Th\u0101kro"
    ],
    "wof:name":"Chak Thirty-four - Four Left",
    "wof:placetype":"locality"
},
  "geometry": {"coordinates":[73.36341999999998,30.6353],"type":"Point"}
}