{
  "type": "Feature",
  "properties": {
    "gn:admin1_code":"3",
    "gn:asciiname":"Narai",
    "gn:country_code":"PK",
    "gn:dem":355,
    "gn:feature_class":"P",
    "gn:feature_code":"PPL",
    "gn:name":"Narai",
    "gn:population":0,
    "gn:timezone":"Asia/Karachi",
    "iso:country":"PK",
    "name:eng_x_preferred":[
        "Narai"
    ],
    "wof:name":"Narai",
    "wof:placetype":"locality"
},
  "geometry": {"coordinates":[72.17559,34.32826],"type":"Point"}
}