{
  "type": "Feature",
  "properties": {
    "gn:admin1_code":"1.0",
    "gn:asciiname":"Landukal",
    "gn:country_code":"PK",
    "gn:dem":2259,
    "gn:feature_class":"P",
    "gn:feature_code":"PPL",
    "gn:name":"Landukal",
    "gn:population":0,
    "gn:timezone":"Asia/Karachi",
    "iso:country":"PK",
    "name:und_x_variant":[
        "Land\u016bkai"
    ],
    "wof:name":"Landukal",
    "wof:placetype":"locality"
},
  "geometry": {"coordinates":[70.99804,33.7055],"type":"Point"}
}