{
  "type": "Feature",
  "properties": {
    "gn:admin1_code":"4.0",
    "gn:asciiname":"Khora Baqar",
    "gn:country_code":"PK",
    "gn:dem":164,
    "gn:feature_class":"P",
    "gn:feature_code":"PPL",
    "gn:name":"Khora Baqar",
    "gn:population":0,
    "gn:timezone":"Asia/Karachi",
    "iso:country":"PK",
    "name:und_x_variant":[
        "Thatta Bharw\u0101na"
    ],
    "wof:name":"Khora Baqar",
    "wof:placetype":"locality"
},
  "geometry": {"coordinates":[72.44549000000001,31.4963],"type":"Point"}
}