{
  "type": "Feature",
  "properties": {
    "gn:admin1_code":"3.0",
    "gn:asciiname":"Surwahrth",
    "gn:country_code":"PK",
    "gn:dem":2749,
    "gn:feature_class":"P",
    "gn:feature_code":"PPL",
    "gn:name":"Surwahrth",
    "gn:population":0,
    "gn:timezone":"Asia/Karachi",
    "iso:country":"PK",
    "wof:name":"Surwahrth",
    "wof:placetype":"locality"
},
  "geometry": {"coordinates":[72.3563,36.4229],"type":"Point"}
}