{
  "type": "Feature",
  "properties": {
    "gn:admin1_code":"3.0",
    "gn:asciiname":"Mithu",
    "gn:country_code":"PK",
    "gn:dem":252,
    "gn:feature_class":"P",
    "gn:feature_code":"PPL",
    "gn:name":"Mithu",
    "gn:population":0,
    "gn:timezone":"Asia/Karachi",
    "iso:country":"PK",
    "wof:name":"Mithu",
    "wof:placetype":"locality"
},
  "geometry": {"coordinates":[70.36253000000001,32.18275],"type":"Point"}
}