{
  "type": "Feature",
  "properties": {
    "gn:admin1_code":"6",
    "gn:asciiname":"Doda Dhok",
    "gn:country_code":"PK",
    "gn:dem":2382,
    "gn:feature_class":"P",
    "gn:feature_code":"PPL",
    "gn:name":"Doda Dhok",
    "gn:population":0,
    "gn:timezone":"Asia/Karachi",
    "iso:country":"PK",
    "name:und_x_variant":[
        "Dowa Dhok"
    ],
    "wof:name":"Doda Dhok",
    "wof:placetype":"locality"
},
  "geometry": {"coordinates":[73.90852,33.99589],"type":"Point"}
}