{
  "type": "Feature",
  "properties": {
    "gn:admin1_code":"4",
    "gn:asciiname":"Naushahra Bhattian",
    "gn:country_code":"PK",
    "gn:dem":204,
    "gn:feature_class":"P",
    "gn:feature_code":"PPL",
    "gn:name":"Naushahra Bhattian",
    "gn:population":0,
    "gn:timezone":"Asia/Karachi",
    "iso:country":"PK",
    "name:und_x_variant":[
        "Naushahra"
    ],
    "wof:name":"Naushahra Bhattian",
    "wof:placetype":"locality"
},
  "geometry": {"coordinates":[73.45614999999999,32.26178],"type":"Point"}
}