{
  "type": "Feature",
  "properties": {
    "gn:admin1_code":"4.0",
    "gn:asciiname":"Wara",
    "gn:country_code":"PK",
    "gn:dem":206,
    "gn:feature_class":"P",
    "gn:feature_code":"PPL",
    "gn:name":"Wara",
    "gn:population":0,
    "gn:timezone":"Asia/Karachi",
    "iso:country":"PK",
    "name:ceb_x_preferred":[
        "Wara"
    ],
    "name:deu_x_preferred":[
        "Wara"
    ],
    "name:fra_x_preferred":[
        "Wara"
    ],
    "name:swe_x_preferred":[
        "Wara"
    ],
    "wof:name":"Wara",
    "wof:placetype":"locality"
},
  "geometry": {"coordinates":[74.25315000000001,31.37712],"type":"Point"}
}