{
  "type": "Feature",
  "properties": {
    "gn:admin1_code":"2.0",
    "gn:asciiname":"Kili Fateh Muhammad",
    "gn:country_code":"PK",
    "gn:dem":1238,
    "gn:feature_class":"P",
    "gn:feature_code":"PPL",
    "gn:name":"Kili Fateh Muhammad",
    "gn:population":0,
    "gn:timezone":"Asia/Karachi",
    "iso:country":"PK",
    "wof:name":"Kili Fateh Muhammad",
    "wof:placetype":"locality"
},
  "geometry": {"coordinates":[66.27642,27.18888],"type":"Point"}
}