{
  "type": "Feature",
  "properties": {
    "gn:admin1_code":"5.0",
    "gn:asciiname":"Raja Anaras Punjabi",
    "gn:country_code":"PK",
    "gn:dem":8,
    "gn:feature_class":"P",
    "gn:feature_code":"PPL",
    "gn:name":"Raja Anaras Punjabi",
    "gn:population":0,
    "gn:timezone":"Asia/Karachi",
    "iso:country":"PK",
    "wof:name":"Raja Anaras Punjabi",
    "wof:placetype":"locality"
},
  "geometry": {"coordinates":[68.18786999999999,24.38437],"type":"Point"}
}