{
  "type": "Feature",
  "properties": {
    "gn:admin1_code":"03",
    "gn:asciiname":"Kalo Mahrai",
    "gn:country_code":"PK",
    "gn:dem":1022,
    "gn:feature_class":"P",
    "gn:feature_code":"PPL",
    "gn:name":"Kalo Mahrai",
    "gn:population":0,
    "gn:timezone":"Asia/Karachi",
    "iso:country":"PK",
    "wof:name":"Kalo Mahrai",
    "wof:placetype":"locality"
},
  "geometry": {"coordinates":[71.93335999999999,34.72532],"type":"Point"}
}