{
  "type": "Feature",
  "properties": {
    "gn:admin1_code":"4",
    "gn:asciiname":"Bhattiwala",
    "gn:country_code":"PK",
    "gn:dem":171,
    "gn:feature_class":"P",
    "gn:feature_code":"PPL",
    "gn:name":"Bhattiwala",
    "gn:population":0,
    "gn:timezone":"Asia/Karachi",
    "iso:country":"PK",
    "name:und_x_variant":[
        "Bhatt\u012bw\u0101la"
    ],
    "wof:name":"Bhattiwala",
    "wof:placetype":"locality"
},
  "geometry": {"coordinates":[73.71581999999999,30.25185],"type":"Point"}
}