{
  "type": "Feature",
  "properties": {
    "gn:admin1_code":"4",
    "gn:asciiname":"Dhok Basakki",
    "gn:country_code":"PK",
    "gn:dem":489,
    "gn:feature_class":"P",
    "gn:feature_code":"PPL",
    "gn:name":"Dhok Basakki",
    "gn:population":0,
    "gn:timezone":"Asia/Karachi",
    "iso:country":"PK",
    "name:und_x_variant":[
        "Dhok Baski"
    ],
    "wof:name":"Dhok Basakki",
    "wof:placetype":"locality"
},
  "geometry": {"coordinates":[73.32108000000002,33.06583],"type":"Point"}
}