{
  "type": "Feature",
  "properties": {
    "gn:admin1_code":"2.0",
    "gn:asciiname":"Karm",
    "gn:country_code":"PK",
    "gn:dem":2371,
    "gn:feature_class":"P",
    "gn:feature_code":"PPL",
    "gn:name":"Karm",
    "gn:population":0,
    "gn:timezone":"Asia/Karachi",
    "iso:country":"PK",
    "wof:name":"Karm",
    "wof:placetype":"locality"
},
  "geometry": {"coordinates":[66.42841,30.64523],"type":"Point"}
}