{
  "type": "Feature",
  "properties": {
    "gn:admin1_code":"4.0",
    "gn:asciiname":"Diwanwala",
    "gn:country_code":"PK",
    "gn:dem":103,
    "gn:feature_class":"P",
    "gn:feature_code":"PPL",
    "gn:name":"Diwanwala",
    "gn:population":0,
    "gn:timezone":"Asia/Karachi",
    "iso:country":"PK",
    "name:und_x_variant":[
        "Dirw\u0101nw\u0101la"
    ],
    "wof:name":"Diwanwala",
    "wof:placetype":"locality"
},
  "geometry": {"coordinates":[70.58336,29.44063],"type":"Point"}
}