{
  "type": "Feature",
  "properties": {
    "gn:admin1_code":"2.0",
    "gn:asciiname":"Sarkiri Bazar",
    "gn:country_code":"PK",
    "gn:dem":917,
    "gn:feature_class":"P",
    "gn:feature_code":"PPL",
    "gn:name":"Sarkiri Bazar",
    "gn:population":0,
    "gn:timezone":"Asia/Karachi",
    "iso:country":"PK",
    "wof:name":"Sarkiri Bazar",
    "wof:placetype":"locality"
},
  "geometry": {"coordinates":[63.54171,27.1515],"type":"Point"}
}