{
  "type": "Feature",
  "properties": {
    "gn:admin1_code":"2.0",
    "gn:asciiname":"Kunarkul",
    "gn:country_code":"PK",
    "gn:dem":1022,
    "gn:feature_class":"P",
    "gn:feature_code":"PPL",
    "gn:name":"Kunarkul",
    "gn:population":0,
    "gn:timezone":"Asia/Karachi",
    "iso:country":"PK",
    "wof:name":"Kunarkul",
    "wof:placetype":"locality"
},
  "geometry": {"coordinates":[66.19943000000001,27.0129],"type":"Point"}
}