{
  "type": "Feature",
  "properties": {
    "gn:admin1_code":"2",
    "gn:asciiname":"Kuchhari",
    "gn:country_code":"PK",
    "gn:dem":1101,
    "gn:feature_class":"P",
    "gn:feature_code":"PPL",
    "gn:name":"Kuchhari",
    "gn:population":0,
    "gn:timezone":"Asia/Karachi",
    "iso:country":"PK",
    "name:und_x_variant":[
        "Kuchhar"
    ],
    "wof:name":"Kuchhari",
    "wof:placetype":"locality"
},
  "geometry": {"coordinates":[69.51000999999999,29.89983],"type":"Point"}
}