{
  "type": "Feature",
  "properties": {
    "gn:admin1_code":"3.0",
    "gn:asciiname":"Majid Kalle",
    "gn:country_code":"PK",
    "gn:dem":392,
    "gn:feature_class":"P",
    "gn:feature_code":"PPL",
    "gn:name":"Majid Kalle",
    "gn:population":0,
    "gn:timezone":"Asia/Karachi",
    "iso:country":"PK",
    "wof:name":"Majid Kalle",
    "wof:placetype":"locality"
},
  "geometry": {"coordinates":[71.77573000000002,34.33862],"type":"Point"}
}