{
  "type": "Feature",
  "properties": {
    "gn:admin1_code":"1.0",
    "gn:asciiname":"Tindore Kalle",
    "gn:country_code":"PK",
    "gn:dem":1451,
    "gn:feature_class":"P",
    "gn:feature_code":"PPL",
    "gn:name":"Tindore Kalle",
    "gn:population":0,
    "gn:timezone":"Asia/Karachi",
    "iso:country":"PK",
    "wof:name":"Tindore Kalle",
    "wof:placetype":"locality"
},
  "geometry": {"coordinates":[70.42219,33.68247],"type":"Point"}
}