{
  "type": "Feature",
  "properties": {
    "gn:admin1_code":"04",
    "gn:asciiname":"Kotla Shaikhan da",
    "gn:country_code":"PK",
    "gn:dem":107,
    "gn:feature_class":"P",
    "gn:feature_code":"PPL",
    "gn:name":"Kotla Shaikhan da",
    "gn:population":0,
    "gn:timezone":"Asia/Karachi",
    "iso:country":"PK",
    "name:und_x_variant":[
        "Kotla Sheikhan",
        "Kotla Shaikh\u0101n",
        "Kotla Shaikhan da"
    ],
    "wof:name":"Kotla Shaikhan da",
    "wof:placetype":"locality"
},
  "geometry": {"coordinates":[71.11598000000002,29.28225],"type":"Point"}
}