{
  "type": "Feature",
  "properties": {
    "gn:admin1_code":"2.0",
    "gn:asciiname":"Muragh Kili",
    "gn:country_code":"PK",
    "gn:dem":2083,
    "gn:feature_class":"P",
    "gn:feature_code":"PPL",
    "gn:name":"Muragh Kili",
    "gn:population":0,
    "gn:timezone":"Asia/Karachi",
    "iso:country":"PK",
    "name:und_x_variant":[
        "Maragh"
    ],
    "wof:name":"Muragh Kili",
    "wof:placetype":"locality"
},
  "geometry": {"coordinates":[68.21732,31.31791],"type":"Point"}
}