{
  "type": "Feature",
  "properties": {
    "gn:admin1_code":"02",
    "gn:asciiname":"Sapar",
    "gn:country_code":"PK",
    "gn:dem":92,
    "gn:feature_class":"P",
    "gn:feature_code":"PPL",
    "gn:name":"Sapar",
    "gn:population":0,
    "gn:timezone":"Asia/Karachi",
    "iso:country":"PK",
    "wof:name":"Sapar",
    "wof:placetype":"locality"
},
  "geometry": {"coordinates":[68.21666999999999,28.81667],"type":"Point"}
}