{
  "type": "Feature",
  "properties": {
    "gn:admin1_code":"3.0",
    "gn:asciiname":"Hassan Khel Dagar Kalle",
    "gn:country_code":"PK",
    "gn:dem":501,
    "gn:feature_class":"P",
    "gn:feature_code":"PPLL",
    "gn:name":"Hassan Khel Dagar Kalle",
    "gn:population":0,
    "gn:timezone":"Asia/Karachi",
    "iso:country":"PK",
    "wof:name":"Hassan Khel Dagar Kalle",
    "wof:placetype":"locality"
},
  "geometry": {"coordinates":[70.46684999999999,32.60348],"type":"Point"}
}