{
  "type": "Feature",
  "properties": {
    "gn:admin1_code":"4",
    "gn:asciiname":"Basti Bukhsh Khan Chang",
    "gn:country_code":"PK",
    "gn:dem":76,
    "gn:feature_class":"P",
    "gn:feature_code":"PPL",
    "gn:name":"Basti Bukhsh Khan Chang",
    "gn:population":0,
    "gn:timezone":"Asia/Karachi",
    "iso:country":"PK",
    "name:und_x_variant":[
        "Bh\u0101i Kh\u0101n Chang"
    ],
    "wof:name":"Basti Bukhsh Khan Chang",
    "wof:placetype":"locality"
},
  "geometry": {"coordinates":[69.83803,28.36669],"type":"Point"}
}