{
  "type": "Feature",
  "properties": {
    "gn:admin1_code":"4.0",
    "gn:asciiname":"Nathe Jagir",
    "gn:country_code":"PK",
    "gn:dem":204,
    "gn:feature_class":"P",
    "gn:feature_code":"PPL",
    "gn:name":"Nathe Jagir",
    "gn:population":0,
    "gn:timezone":"Asia/Karachi",
    "iso:country":"PK",
    "name:und_x_variant":[
        "Nauthe J\u0101g\u012br",
        "Nathie Jag\u012br"
    ],
    "wof:name":"Nathe Jagir",
    "wof:placetype":"locality"
},
  "geometry": {"coordinates":[74.00046,31.27472],"type":"Point"}
}