{
  "type": "Feature",
  "properties": {
    "gn:admin1_code":"4.0",
    "gn:asciiname":"Saidpura",
    "gn:country_code":"PK",
    "gn:dem":161,
    "gn:feature_class":"P",
    "gn:feature_code":"PPL",
    "gn:name":"Saidpura",
    "gn:population":0,
    "gn:timezone":"Asia/Karachi",
    "iso:country":"PK",
    "name:urd_x_preferred":[
        "\u0633\u06cc\u062f\u067e\u0648\u0631"
    ],
    "wof:name":"Saidpura",
    "wof:placetype":"locality"
},
  "geometry": {"coordinates":[73.30989,30.27081],"type":"Point"}
}