{
  "type": "Feature",
  "properties": {
    "gn:admin1_code":"4.0",
    "gn:asciiname":"Piran-di-Lanri",
    "gn:country_code":"PK",
    "gn:dem":1548,
    "gn:feature_class":"P",
    "gn:feature_code":"PPL",
    "gn:name":"Piran-di-Lanri",
    "gn:population":0,
    "gn:timezone":"Asia/Karachi",
    "iso:country":"PK",
    "wof:name":"Piran-di-Lanri",
    "wof:placetype":"locality"
},
  "geometry": {"coordinates":[73.51668000000002,33.84592],"type":"Point"}
}