{
  "type": "Feature",
  "properties": {
    "gn:admin1_code":"4.0",
    "gn:asciiname":"Alam Khanwala",
    "gn:country_code":"PK",
    "gn:dem":231,
    "gn:feature_class":"P",
    "gn:feature_code":"PPL",
    "gn:name":"\u0100lam Kh\u0101nw\u0101la",
    "gn:population":0,
    "gn:timezone":"Asia/Karachi",
    "iso:country":"PK",
    "wof:name":"Alam Khanwala",
    "wof:placetype":"locality"
},
  "geometry": {"coordinates":[71.67946999999999,32.54960999999999],"type":"Point"}
}