{
  "type": "Feature",
  "properties": {
    "gn:admin1_code":"4.0",
    "gn:asciiname":"Tayyibwala",
    "gn:country_code":"PK",
    "gn:dem":173,
    "gn:feature_class":"P",
    "gn:feature_code":"PPL",
    "gn:name":"Tayyibwala",
    "gn:population":0,
    "gn:timezone":"Asia/Karachi",
    "iso:country":"PK",
    "name:und_x_variant":[
        "Rab Naw\u0101z Tegarw\u0101la"
    ],
    "wof:name":"Tayyibwala",
    "wof:placetype":"locality"
},
  "geometry": {"coordinates":[71.26796,31.6486],"type":"Point"}
}