{
  "type": "Feature",
  "properties": {
    "gn:admin1_code":"3.0",
    "gn:asciiname":"Balola",
    "gn:country_code":"PK",
    "gn:dem":928,
    "gn:feature_class":"P",
    "gn:feature_code":"PPL",
    "gn:name":"Balola",
    "gn:population":0,
    "gn:timezone":"Asia/Karachi",
    "iso:country":"PK",
    "wof:name":"Balola",
    "wof:placetype":"locality"
},
  "geometry": {"coordinates":[73.35513,34.44406],"type":"Point"}
}