{
  "type": "Feature",
  "properties": {
    "gn:admin1_code":"6.0",
    "gn:asciiname":"Bisian",
    "gn:country_code":"PK",
    "gn:dem":2010,
    "gn:feature_class":"P",
    "gn:feature_code":"PPL",
    "gn:name":"Bisian",
    "gn:population":0,
    "gn:timezone":"Asia/Karachi",
    "iso:country":"PK",
    "wof:name":"Bisian",
    "wof:placetype":"locality"
},
  "geometry": {"coordinates":[73.99169999999999,34.73518],"type":"Point"}
}