{
  "type": "Feature",
  "properties": {
    "gn:admin1_code":"2",
    "gn:asciiname":"Badini",
    "gn:country_code":"PK",
    "gn:dem":944,
    "gn:feature_class":"P",
    "gn:feature_code":"PPL",
    "gn:name":"Badini",
    "gn:population":0,
    "gn:timezone":"Asia/Karachi",
    "iso:country":"PK",
    "wof:name":"Badini",
    "wof:placetype":"locality"
},
  "geometry": {"coordinates":[65.98223,29.5841],"type":"Point"}
}