{
  "type": "Feature",
  "properties": {
    "gn:admin1_code":"3.0",
    "gn:asciiname":"Jani Khel Kirri Toti",
    "gn:country_code":"PK",
    "gn:dem":339,
    "gn:feature_class":"P",
    "gn:feature_code":"PPL",
    "gn:name":"Jani Khel Kirri Toti",
    "gn:population":0,
    "gn:timezone":"Asia/Karachi",
    "iso:country":"PK",
    "name:und_x_variant":[
        "Kirri Toti"
    ],
    "wof:name":"Jani Khel Kirri Toti",
    "wof:placetype":"locality"
},
  "geometry": {"coordinates":[70.45981,32.47066],"type":"Point"}
}