{
  "type": "Feature",
  "properties": {
    "gn:admin1_code":"5",
    "gn:asciiname":"Goth Dino Maku",
    "gn:country_code":"PK",
    "gn:dem":73,
    "gn:feature_class":"P",
    "gn:feature_code":"PPL",
    "gn:name":"Goth Dino Maku",
    "gn:population":0,
    "gn:timezone":"Asia/Karachi",
    "iso:country":"PK",
    "name:und_x_variant":[
        "Dino Maku"
    ],
    "wof:name":"Goth Dino Maku",
    "wof:placetype":"locality"
},
  "geometry": {"coordinates":[69.60619,28.01975],"type":"Point"}
}