{
  "type": "Feature",
  "properties": {
    "gn:admin1_code":"4.0",
    "gn:asciiname":"Kund",
    "gn:country_code":"PK",
    "gn:dem":1134,
    "gn:feature_class":"P",
    "gn:feature_code":"PPL",
    "gn:name":"Kund",
    "gn:population":0,
    "gn:timezone":"Asia/Karachi",
    "iso:country":"PK",
    "name:eng_x_preferred":[
        "Kund"
    ],
    "name:fas_x_preferred":[
        "\u06a9\u0646\u062f"
    ],
    "name:urd_x_preferred":[
        "\u06a9\u0646\u0688"
    ],
    "wof:name":"Kund",
    "wof:placetype":"locality"
},
  "geometry": {"coordinates":[73.43303,33.76177],"type":"Point"}
}