{
  "type": "Feature",
  "properties": {
    "gn:admin1_code":"3",
    "gn:asciiname":"Haidar Banda",
    "gn:country_code":"PK",
    "gn:dem":1836,
    "gn:feature_class":"P",
    "gn:feature_code":"PPL",
    "gn:name":"Haidar Banda",
    "gn:population":0,
    "gn:timezone":"Asia/Karachi",
    "iso:country":"PK",
    "wof:name":"Haidar Banda",
    "wof:placetype":"locality"
},
  "geometry": {"coordinates":[72.0223,34.80704],"type":"Point"}
}