{
  "type": "Feature",
  "properties": {
    "gn:admin1_code":"4.0",
    "gn:asciiname":"Block Number Five",
    "gn:country_code":"PK",
    "gn:dem":198,
    "gn:feature_class":"P",
    "gn:feature_code":"PPL",
    "gn:name":"Block Number Five",
    "gn:population":0,
    "gn:timezone":"Asia/Karachi",
    "iso:country":"PK",
    "name:und_x_variant":[
        "K\u0101mbu",
        "Kampu"
    ],
    "wof:name":"Block Number Five",
    "wof:placetype":"locality"
},
  "geometry": {"coordinates":[74.00402,31.07178],"type":"Point"}
}