{
  "type": "Feature",
  "properties": {
    "gn:admin1_code":"6",
    "gn:asciiname":"Gundi Garan",
    "gn:country_code":"PK",
    "gn:dem":2219,
    "gn:feature_class":"P",
    "gn:feature_code":"PPL",
    "gn:name":"Gundi Garan",
    "gn:population":0,
    "gn:timezone":"Asia/Kolkata",
    "iso:country":"PK",
    "name:und_x_variant":[
        "Gundigir\u0101h"
    ],
    "wof:name":"Gundi Garan",
    "wof:placetype":"locality"
},
  "geometry": {"coordinates":[73.92870000000001,34.14863],"type":"Point"}
}