{
  "type": "Feature",
  "properties": {
    "gn:admin1_code":"6",
    "gn:asciiname":"Dhamak",
    "gn:country_code":"PK",
    "gn:dem":366,
    "gn:feature_class":"P",
    "gn:feature_code":"PPL",
    "gn:name":"Dhamak",
    "gn:population":0,
    "gn:timezone":"Asia/Karachi",
    "iso:country":"PK",
    "name:und_x_variant":[
        "Dhammak"
    ],
    "wof:name":"Dhamak",
    "wof:placetype":"locality"
},
  "geometry": {"coordinates":[74.19147,32.93009],"type":"Point"}
}