{
  "type": "Feature",
  "properties": {
    "gn:admin1_code":"2.0",
    "gn:asciiname":"Ghunz",
    "gn:country_code":"PK",
    "gn:dem":2574,
    "gn:feature_class":"P",
    "gn:feature_code":"PPL",
    "gn:name":"Ghunz",
    "gn:population":0,
    "gn:timezone":"Asia/Karachi",
    "iso:country":"PK",
    "name:und_x_variant":[
        "Gunz",
        "Ghunz"
    ],
    "wof:name":"Ghunz",
    "wof:placetype":"locality"
},
  "geometry": {"coordinates":[67.89078000000001,30.45128],"type":"Point"}
}