{
  "type": "Feature",
  "properties": {
    "gn:admin1_code":"1.0",
    "gn:asciiname":"Alam Kili",
    "gn:country_code":"PK",
    "gn:dem":722,
    "gn:feature_class":"P",
    "gn:feature_code":"PPL",
    "gn:name":"Alam Kili",
    "gn:population":0,
    "gn:timezone":"Asia/Karachi",
    "iso:country":"PK",
    "name:und_x_variant":[
        "\u0100lam Kili",
        "Alam Khel"
    ],
    "wof:name":"Alam Kili",
    "wof:placetype":"locality"
},
  "geometry": {"coordinates":[71.38609,33.81938],"type":"Point"}
}