{
  "type": "Feature",
  "properties": {
    "gn:admin1_code":"1.0",
    "gn:asciiname":"Niaran Ziarat",
    "gn:country_code":"PK",
    "gn:dem":1203,
    "gn:feature_class":"P",
    "gn:feature_code":"PPL",
    "gn:name":"Niaran Ziarat",
    "gn:population":0,
    "gn:timezone":"Asia/Karachi",
    "iso:country":"PK",
    "wof:name":"Niaran Ziarat",
    "wof:placetype":"locality"
},
  "geometry": {"coordinates":[71.16845000000001,34.13949],"type":"Point"}
}