{
  "type": "Feature",
  "properties": {
    "gn:admin1_code":"2.0",
    "gn:asciiname":"Kili Chail",
    "gn:country_code":"PK",
    "gn:dem":1285,
    "gn:feature_class":"P",
    "gn:feature_code":"PPL",
    "gn:name":"Kili Chail",
    "gn:population":0,
    "gn:timezone":"Asia/Karachi",
    "iso:country":"PK",
    "wof:name":"Kili Chail",
    "wof:placetype":"locality"
},
  "geometry": {"coordinates":[64.86861999999999,27.28932],"type":"Point"}
}