{
  "type": "Feature",
  "properties": {
    "gn:admin1_code":"4",
    "gn:asciiname":"Dhok Raja Abdullah",
    "gn:country_code":"PK",
    "gn:dem":256,
    "gn:feature_class":"P",
    "gn:feature_code":"PPL",
    "gn:name":"Dhok Raja Abdullah",
    "gn:population":0,
    "gn:timezone":"Asia/Karachi",
    "iso:country":"PK",
    "wof:name":"Dhok Raja Abdullah",
    "wof:placetype":"locality"
},
  "geometry": {"coordinates":[72.81248000000002,32.64136],"type":"Point"}
}