{
  "type": "Feature",
  "properties": {
    "gn:admin1_code":"3",
    "gn:asciiname":"Sarhan",
    "gn:country_code":"PK",
    "gn:dem":2006,
    "gn:feature_class":"P",
    "gn:feature_code":"PPL",
    "gn:name":"Sarhan",
    "gn:population":0,
    "gn:timezone":"Asia/Karachi",
    "iso:country":"PK",
    "name:und_x_variant":[
        "Sahr\u0101n"
    ],
    "wof:name":"Sarhan",
    "wof:placetype":"locality"
},
  "geometry": {"coordinates":[73.20726999999999,34.65228],"type":"Point"}
}