{
  "type": "Feature",
  "properties": {
    "gn:admin1_code":"4",
    "gn:asciiname":"Muhammadwala",
    "gn:country_code":"PK",
    "gn:dem":98,
    "gn:feature_class":"P",
    "gn:feature_code":"PPL",
    "gn:name":"Muhammadwala",
    "gn:population":0,
    "gn:timezone":"Asia/Karachi",
    "iso:country":"PK",
    "wof:name":"Muhammadwala",
    "wof:placetype":"locality"
},
  "geometry": {"coordinates":[70.43831999999998,29.26345],"type":"Point"}
}