{
  "type": "Feature",
  "properties": {
    "gn:admin1_code":"3",
    "gn:asciiname":"Magri Janguan",
    "gn:country_code":"PK",
    "gn:dem":1282,
    "gn:feature_class":"P",
    "gn:feature_code":"PPL",
    "gn:name":"Magri Janguan",
    "gn:population":0,
    "gn:timezone":"Asia/Karachi",
    "iso:country":"PK",
    "name:und_x_variant":[
        "Magri Gujjar"
    ],
    "wof:name":"Magri Janguan",
    "wof:placetype":"locality"
},
  "geometry": {"coordinates":[73.12623000000001,34.07544],"type":"Point"}
}