{
  "type": "Feature",
  "properties": {
    "gn:admin1_code":"4.0",
    "gn:asciiname":"Khanowali",
    "gn:country_code":"PK",
    "gn:dem":256,
    "gn:feature_class":"P",
    "gn:feature_code":"PPL",
    "gn:name":"Khanowali",
    "gn:population":0,
    "gn:timezone":"Asia/Karachi",
    "iso:country":"PK",
    "name:und_x_variant":[
        "Kh\u0101n\u0101nw\u0101li"
    ],
    "wof:name":"Khanowali",
    "wof:placetype":"locality"
},
  "geometry": {"coordinates":[74.71217,32.38654],"type":"Point"}
}