{
  "type": "Feature",
  "properties": {
    "gn:admin1_code":"3",
    "gn:asciiname":"Nakhtar",
    "gn:country_code":"PK",
    "gn:dem":1757,
    "gn:feature_class":"P",
    "gn:feature_code":"PPL",
    "gn:name":"Nakhtar",
    "gn:population":0,
    "gn:timezone":"Asia/Karachi",
    "iso:country":"PK",
    "wof:name":"Nakhtar",
    "wof:placetype":"locality"
},
  "geometry": {"coordinates":[72.31766,34.90996],"type":"Point"}
}