{
  "type": "Feature",
  "properties": {
    "gn:admin1_code":"5",
    "gn:asciiname":"Goth Alam Chhachhar",
    "gn:country_code":"PK",
    "gn:dem":32,
    "gn:feature_class":"P",
    "gn:feature_code":"PPL",
    "gn:name":"Goth Alam Chhachhar",
    "gn:population":0,
    "gn:timezone":"Asia/Karachi",
    "iso:country":"PK",
    "name:und_x_variant":[
        "Wahan Chhachhar"
    ],
    "wof:name":"Goth Alam Chhachhar",
    "wof:placetype":"locality"
},
  "geometry": {"coordinates":[68.06419,26.12794],"type":"Point"}
}