{
  "type": "Feature",
  "properties": {
    "gn:admin1_code":"8.0",
    "gn:asciiname":"Ban",
    "gn:country_code":"PK",
    "gn:dem":569,
    "gn:feature_class":"P",
    "gn:feature_code":"PPL",
    "gn:name":"Ban",
    "gn:population":0,
    "gn:timezone":"Asia/Karachi",
    "iso:country":"PK",
    "wof:name":"Ban",
    "wof:placetype":"locality"
},
  "geometry": {"coordinates":[73.25667,33.60666],"type":"Point"}
}