{
  "type": "Feature",
  "properties": {
    "gn:admin1_code":"4.0",
    "gn:asciiname":"Losar",
    "gn:country_code":"PK",
    "gn:dem":511,
    "gn:feature_class":"P",
    "gn:feature_code":"PPL",
    "gn:name":"Losar",
    "gn:population":0,
    "gn:timezone":"Asia/Karachi",
    "iso:country":"PK",
    "wof:name":"Losar",
    "wof:placetype":"locality"
},
  "geometry": {"coordinates":[73.18343,33.41989],"type":"Point"}
}