{
  "type": "Feature",
  "properties": {
    "gn:admin1_code":"4.0",
    "gn:asciiname":"Losar",
    "gn:country_code":"PK",
    "gn:dem":511,
    "gn:feature_class":"P",
    "gn:feature_code":"PPL",
    "gn:name":"Losar",
    "gn:population":0,
    "gn:timezone":"Asia/Karachi",
    "iso:country":"PK",
    "name:ara_x_preferred":[
        "\u0644\u0648\u0633\u0627\u0631"
    ],
    "name:bod_x_preferred":[
        "\u0f56\u0f7c\u0f51\u0f0b\u0f40\u0fb1\u0f72\u0f0b\u0f63\u0f7c\u0f0b\u0f42\u0f66\u0f62\u0f0d"
    ],
    "name:ces_x_preferred":[
        "Losar"
    ],
    "name:deu_x_preferred":[
        "Losar"
    ],
    "name:fra_x_preferred":[
        "Losar"
    ],
    "name:hin_x_preferred":[
        "\u0932\u094b\u0938\u0930"
    ],
    "name:hun_x_preferred":[
        "Losz\u00e1r"
    ],
    "name:hye_x_preferred":[
        "\u053c\u0578\u057d\u0561\u0580"
    ],
    "name:ita_x_preferred":[
        "Losar"
    ],
    "name:mai_x_preferred":[
        "\u0932\u094b\u0938\u093e\u0930"
    ],
    "name:mar_x_preferred":[
        "\u0932\u094b\u0938\u0930"
    ],
    "name:msa_x_preferred":[
        "Losar"
    ],
    "name:nep_x_preferred":[
        "\u0932\u094b\u0938\u093e\u0930"
    ],
    "name:nld_x_preferred":[
        "Losar"
    ],
    "name:nno_x_preferred":[
        "Losar"
    ],
    "name:pol_x_preferred":[
        "Losar"
    ],
    "name:rus_x_preferred":[
        "\u041b\u043e\u0441\u0430\u0440"
    ],
    "name:spa_x_preferred":[
        "Losar"
    ],
    "name:swe_x_preferred":[
        "Losar"
    ],
    "name:ukr_x_preferred":[
        "\u041b\u043e\u0441\u0430\u0440"
    ],
    "name:vie_x_preferred":[
        "Losar"
    ],
    "name:zho_x_preferred":[
        "\u85cf\u5386\u65b0\u5e74"
    ],
    "wof:name":"Losar",
    "wof:placetype":"locality"
},
  "geometry": {"coordinates":[73.18343,33.41989],"type":"Point"}
}