{
  "type": "Feature",
  "properties": {
    "gn:admin1_code":"2.0",
    "gn:asciiname":"Toranzai",
    "gn:country_code":"PK",
    "gn:dem":1463,
    "gn:feature_class":"P",
    "gn:feature_code":"PPL",
    "gn:name":"Toranzai",
    "gn:population":0,
    "gn:timezone":"Asia/Karachi",
    "iso:country":"PK",
    "wof:name":"Toranzai",
    "wof:placetype":"locality"
},
  "geometry": {"coordinates":[69.22166999999999,31.01833],"type":"Point"}
}