{
  "type": "Feature",
  "properties": {
    "gn:admin1_code":"5",
    "gn:asciiname":"Goth Chutto Shar Baloch",
    "gn:country_code":"PK",
    "gn:dem":61,
    "gn:feature_class":"P",
    "gn:feature_code":"PPL",
    "gn:name":"Goth Chutto Shar Baloch",
    "gn:population":0,
    "gn:timezone":"Asia/Karachi",
    "iso:country":"PK",
    "name:eng_x_preferred":[
        "Goth Chutto Shar Baloch"
    ],
    "name:und_x_variant":[
        "K\u0101sm\u0101ni"
    ],
    "wof:name":"Goth Chutto Shar Baloch",
    "wof:placetype":"locality"
},
  "geometry": {"coordinates":[68.74204,27.79078],"type":"Point"}
}