{
  "type": "Feature",
  "properties": {
    "gn:admin1_code":"3",
    "gn:asciiname":"Maslun",
    "gn:country_code":"PK",
    "gn:dem":2479,
    "gn:feature_class":"P",
    "gn:feature_code":"PPL",
    "gn:name":"Maslun",
    "gn:population":0,
    "gn:timezone":"Asia/Karachi",
    "iso:country":"PK",
    "wof:name":"Maslun",
    "wof:placetype":"locality"
},
  "geometry": {"coordinates":[73.28234999999999,34.64964000000001],"type":"Point"}
}