{
  "type": "Feature",
  "properties": {
    "gn:admin1_code":"1",
    "gn:asciiname":"Bazam",
    "gn:country_code":"PK",
    "gn:dem":1833,
    "gn:feature_class":"P",
    "gn:feature_code":"PPL",
    "gn:name":"Bazam",
    "gn:population":0,
    "gn:timezone":"Asia/Karachi",
    "iso:country":"PK",
    "wof:name":"Bazam",
    "wof:placetype":"locality"
},
  "geometry": {"coordinates":[69.8104,32.6265],"type":"Point"}
}