{
  "type": "Feature",
  "properties": {
    "gn:admin1_code":"6",
    "gn:asciiname":"Manihal",
    "gn:country_code":"PK",
    "gn:dem":346,
    "gn:feature_class":"P",
    "gn:feature_code":"PPL",
    "gn:name":"Manihal",
    "gn:population":0,
    "gn:timezone":"Asia/Karachi",
    "iso:country":"PK",
    "name:und_x_variant":[
        "Maj\u0101l"
    ],
    "wof:name":"Manihal",
    "wof:placetype":"locality"
},
  "geometry": {"coordinates":[74.00624000000001,32.98108],"type":"Point"}
}