{
  "type": "Feature",
  "properties": {
    "gn:admin1_code":"4.0",
    "gn:asciiname":"Kund",
    "gn:country_code":"PK",
    "gn:dem":443,
    "gn:feature_class":"P",
    "gn:feature_code":"PPL",
    "gn:name":"Kund",
    "gn:population":0,
    "gn:timezone":"Asia/Karachi",
    "iso:country":"PK",
    "wof:name":"Kund",
    "wof:placetype":"locality"
},
  "geometry": {"coordinates":[73.40904999999999,33.10546],"type":"Point"}
}