{
  "type": "Feature",
  "properties": {
    "gn:admin1_code":"04",
    "gn:asciiname":"Thapla",
    "gn:country_code":"PK",
    "gn:dem":304,
    "gn:feature_class":"P",
    "gn:feature_code":"PPL",
    "gn:name":"Thapla",
    "gn:population":0,
    "gn:timezone":"Asia/Karachi",
    "iso:country":"PK",
    "wof:name":"Thapla",
    "wof:placetype":"locality"
},
  "geometry": {"coordinates":[73.84934,32.82273],"type":"Point"}
}