{
  "type": "Feature",
  "properties": {
    "gn:admin1_code":"6",
    "gn:asciiname":"Barsala",
    "gn:country_code":"PK",
    "gn:dem":281,
    "gn:feature_class":"P",
    "gn:feature_code":"PPL",
    "gn:name":"Barsala",
    "gn:population":0,
    "gn:timezone":"Asia/Karachi",
    "iso:country":"PK",
    "wof:name":"Barsala",
    "wof:placetype":"locality"
},
  "geometry": {"coordinates":[74.37735000000001,32.8203],"type":"Point"}
}