{
  "type": "Feature",
  "properties": {
    "gn:admin1_code":"2.0",
    "gn:asciiname":"Tirkha",
    "gn:country_code":"PK",
    "gn:dem":1580,
    "gn:feature_class":"P",
    "gn:feature_code":"PPL",
    "gn:name":"Tirkha",
    "gn:population":0,
    "gn:timezone":"Asia/Karachi",
    "iso:country":"PK",
    "name:eng_x_preferred":[
        "Tirkha"
    ],
    "wof:name":"Tirkha",
    "wof:placetype":"locality"
},
  "geometry": {"coordinates":[68.58240000000001,30.84082],"type":"Point"}
}