{
  "type": "Feature",
  "properties": {
    "gn:admin1_code":"4",
    "gn:asciiname":"Khu Bakhuwala",
    "gn:country_code":"PK",
    "gn:dem":143,
    "gn:feature_class":"P",
    "gn:feature_code":"PPL",
    "gn:name":"Khu Bakhuwala",
    "gn:population":0,
    "gn:timezone":"Asia/Karachi",
    "iso:country":"PK",
    "name:eng_x_preferred":[
        "Bakh\u016bw\u0101la"
    ],
    "wof:name":"Khu Bakhuwala",
    "wof:placetype":"locality"
},
  "geometry": {"coordinates":[70.64997,30.35756],"type":"Point"}
}