{
  "type": "Feature",
  "properties": {
    "gn:admin1_code":"5",
    "gn:asciiname":"Goth Daud Samtio",
    "gn:country_code":"PK",
    "gn:dem":49,
    "gn:feature_class":"P",
    "gn:feature_code":"PPL",
    "gn:name":"Goth Daud Samtio",
    "gn:population":0,
    "gn:timezone":"Asia/Karachi",
    "iso:country":"PK",
    "name:und_x_variant":[
        "Goth D\u0101\u016bd Samtia"
    ],
    "wof:name":"Goth Daud Samtio",
    "wof:placetype":"locality"
},
  "geometry": {"coordinates":[68.12897,27.15571],"type":"Point"}
}