{
  "type": "Feature",
  "properties": {
    "gn:admin1_code":"3",
    "gn:asciiname":"Rehmat Kotkai",
    "gn:country_code":"PK",
    "gn:dem":376,
    "gn:feature_class":"P",
    "gn:feature_code":"PPL",
    "gn:name":"Rehmat Kotkai",
    "gn:population":0,
    "gn:timezone":"Asia/Karachi",
    "iso:country":"PK",
    "name:und_x_variant":[
        "Rehmai Kili"
    ],
    "wof:name":"Rehmat Kotkai",
    "wof:placetype":"locality"
},
  "geometry": {"coordinates":[70.62820000000001,33.0062],"type":"Point"}
}