{
  "type": "Feature",
  "properties": {
    "gn:admin1_code":"5.0",
    "gn:asciiname":"Goth Panhwar Palafi",
    "gn:country_code":"PK",
    "gn:dem":9,
    "gn:feature_class":"P",
    "gn:feature_code":"PPL",
    "gn:name":"Goth Panhwar Palafi",
    "gn:population":0,
    "gn:timezone":"Asia/Karachi",
    "iso:country":"PK",
    "name:und_x_variant":[
        "Goth Panhwar P\u0101l\u0101ri"
    ],
    "wof:name":"Goth Panhwar Palafi",
    "wof:placetype":"locality"
},
  "geometry": {"coordinates":[67.76165,24.63539],"type":"Point"}
}