{
  "type": "Feature",
  "properties": {
    "gn:admin1_code":"7.0",
    "gn:asciiname":"Harzazgung Brok",
    "gn:country_code":"PK",
    "gn:dem":2971,
    "gn:feature_class":"P",
    "gn:feature_code":"PPL",
    "gn:name":"Harzazgung Brok",
    "gn:population":0,
    "gn:timezone":"Asia/Karachi",
    "iso:country":"PK",
    "wof:name":"Harzazgung Brok",
    "wof:placetype":"locality"
},
  "geometry": {"coordinates":[75.94866,35.01566],"type":"Point"}
}