{
  "type": "Feature",
  "properties": {
    "gn:admin1_code":"3",
    "gn:asciiname":"Bilalzai",
    "gn:country_code":"PK",
    "gn:dem":2027,
    "gn:feature_class":"P",
    "gn:feature_code":"PPL",
    "gn:name":"Bilalzai",
    "gn:population":0,
    "gn:timezone":"Asia/Karachi",
    "iso:country":"PK",
    "name:eng_x_preferred":[
        "Belanzai"
    ],
    "wof:name":"Bilalzai",
    "wof:placetype":"locality"
},
  "geometry": {"coordinates":[71.84886,35.28604],"type":"Point"}
}