{
  "type": "Feature",
  "properties": {
    "gn:admin1_code":"3.0",
    "gn:asciiname":"Anpholi",
    "gn:country_code":"PK",
    "gn:dem":1722,
    "gn:feature_class":"P",
    "gn:feature_code":"PPL",
    "gn:name":"Anpholi",
    "gn:population":0,
    "gn:timezone":"Asia/Karachi",
    "iso:country":"PK",
    "wof:name":"Anpholi",
    "wof:placetype":"locality"
},
  "geometry": {"coordinates":[73.16053000000002,35.29659],"type":"Point"}
}