{
  "type": "Feature",
  "properties": {
    "gn:admin1_code":"6",
    "gn:asciiname":"Sangal",
    "gn:country_code":"PK",
    "gn:dem":1671,
    "gn:feature_class":"P",
    "gn:feature_code":"PPL",
    "gn:name":"Sangal",
    "gn:population":0,
    "gn:timezone":"Asia/Karachi",
    "iso:country":"PK",
    "name:und_x_variant":[
        "Sangai"
    ],
    "wof:name":"Sangal",
    "wof:placetype":"locality"
},
  "geometry": {"coordinates":[74.04885999999998,33.88859],"type":"Point"}
}