{
  "type": "Feature",
  "properties": {
    "gn:admin1_code":"04",
    "gn:asciiname":"Chak Forty-four- Gogera Distributary",
    "gn:country_code":"PK",
    "gn:dem":177,
    "gn:feature_class":"P",
    "gn:feature_code":"PPL",
    "gn:name":"Chak Forty-four- Gogera Distributary",
    "gn:population":0,
    "gn:timezone":"Asia/Karachi",
    "iso:country":"PK",
    "name:und_x_variant":[
        "Bakhti\u0101r Singhw\u0101la",
        "Kot H\u0101kim R\u0101i",
        "Chak Forty-four- Gogera Distributary",
        "Bakht\u0101warw\u0101la"
    ],
    "wof:name":"Chak Forty-four- Gogera Distributary",
    "wof:placetype":"locality"
},
  "geometry": {"coordinates":[73.34231,30.85874],"type":"Point"}
}