{
  "type": "Feature",
  "properties": {
    "gn:admin1_code":"3",
    "gn:asciiname":"Badalgran",
    "gn:country_code":"PK",
    "gn:dem":2189,
    "gn:feature_class":"P",
    "gn:feature_code":"PPL",
    "gn:name":"Badalgran",
    "gn:population":0,
    "gn:timezone":"Asia/Karachi",
    "iso:country":"PK",
    "wof:name":"Badalgran",
    "wof:placetype":"locality"
},
  "geometry": {"coordinates":[73.63093000000001,34.7244],"type":"Point"}
}