{
  "type": "Feature",
  "properties": {
    "gn:admin1_code":"7.0",
    "gn:asciiname":"Ringali",
    "gn:country_code":"PK",
    "gn:dem":2322,
    "gn:feature_class":"P",
    "gn:feature_code":"PPL",
    "gn:name":"Ringali",
    "gn:population":0,
    "gn:timezone":"Asia/Karachi",
    "iso:country":"PK",
    "wof:name":"Ringali",
    "wof:placetype":"locality"
},
  "geometry": {"coordinates":[73.28191,36.21356],"type":"Point"}
}