{
  "type": "Feature",
  "properties": {
    "gn:admin1_code":"5.0",
    "gn:asciiname":"Hurri",
    "gn:country_code":"PK",
    "gn:dem":45,
    "gn:feature_class":"P",
    "gn:feature_code":"PPL",
    "gn:name":"Hurri",
    "gn:population":0,
    "gn:timezone":"Asia/Karachi",
    "iso:country":"PK",
    "name:cat_x_preferred":[
        "Khurri"
    ],
    "wof:name":"Hurri",
    "wof:placetype":"locality"
},
  "geometry": {"coordinates":[67.69360999999999,27.14691],"type":"Point"}
}