{
  "type": "Feature",
  "properties": {
    "gn:admin1_code":"3.0",
    "gn:asciiname":"Jalsi",
    "gn:country_code":"PK",
    "gn:dem":1575,
    "gn:feature_class":"P",
    "gn:feature_code":"PPL",
    "gn:name":"Jalsi",
    "gn:population":0,
    "gn:timezone":"Asia/Karachi",
    "iso:country":"PK",
    "wof:name":"Jalsi",
    "wof:placetype":"locality"
},
  "geometry": {"coordinates":[73.34121,34.00867],"type":"Point"}
}