{
  "type": "Feature",
  "properties": {
    "gn:admin1_code":"4.0",
    "gn:asciiname":"Basti Faiz Bakhsh",
    "gn:country_code":"PK",
    "gn:dem":122,
    "gn:feature_class":"P",
    "gn:feature_code":"PPL",
    "gn:name":"Basti Faiz Bakhsh",
    "gn:population":0,
    "gn:timezone":"Asia/Karachi",
    "iso:country":"PK",
    "name:eng_x_preferred":[
        "Basti Faiz Bakhsh"
    ],
    "wof:name":"Basti Faiz Bakhsh",
    "wof:placetype":"locality"
},
  "geometry": {"coordinates":[71.88138000000002,29.49622],"type":"Point"}
}