{
  "type": "Feature",
  "properties": {
    "gn:admin1_code":"2.0",
    "gn:asciiname":"Mursal",
    "gn:country_code":"PK",
    "gn:dem":1728,
    "gn:feature_class":"P",
    "gn:feature_code":"PPL",
    "gn:name":"Mursal",
    "gn:population":0,
    "gn:timezone":"Asia/Karachi",
    "iso:country":"PK",
    "name:aze_x_preferred":[
        "M\u00fcrs\u0259l"
    ],
    "wof:name":"Mursal",
    "wof:placetype":"locality"
},
  "geometry": {"coordinates":[66.74576999999999,29.68015],"type":"Point"}
}