{
  "type": "Feature",
  "properties": {
    "gn:admin1_code":"4",
    "gn:asciiname":"Chak Twenty Dolewala Branch",
    "gn:country_code":"PK",
    "gn:dem":199,
    "gn:feature_class":"P",
    "gn:feature_code":"PPL",
    "gn:name":"Chak Twenty Dolewala Branch",
    "gn:population":0,
    "gn:timezone":"Asia/Karachi",
    "iso:country":"PK",
    "name:und_x_variant":[
        "Chak Twenty DB"
    ],
    "wof:name":"Chak Twenty Dolewala Branch",
    "wof:placetype":"locality"
},
  "geometry": {"coordinates":[71.6234,32.22891],"type":"Point"}
}