{
  "type": "Feature",
  "properties": {
    "gn:admin1_code":"3.0",
    "gn:asciiname":"Dubran More",
    "gn:country_code":"PK",
    "gn:dem":1127,
    "gn:feature_class":"P",
    "gn:feature_code":"PPL",
    "gn:name":"Dubran More",
    "gn:population":0,
    "gn:timezone":"Asia/Karachi",
    "iso:country":"PK",
    "wof:name":"Dubran More",
    "wof:placetype":"locality"
},
  "geometry": {"coordinates":[73.13101,33.93128],"type":"Point"}
}