{
  "type": "Feature",
  "properties": {
    "gn:admin1_code":"01",
    "gn:asciiname":"Sperkai Narai",
    "gn:country_code":"PK",
    "gn:dem":1948,
    "gn:feature_class":"P",
    "gn:feature_code":"PPL",
    "gn:name":"Sperkai Narai",
    "gn:population":0,
    "gn:timezone":"Asia/Karachi",
    "iso:country":"PK",
    "wof:name":"Sperkai Narai",
    "wof:placetype":"locality"
},
  "geometry": {"coordinates":[69.51139999999999,32.80635],"type":"Point"}
}