{
  "type": "Feature",
  "properties": {
    "gn:admin1_code":"3",
    "gn:asciiname":"Tangai Banda",
    "gn:country_code":"PK",
    "gn:dem":2194,
    "gn:feature_class":"P",
    "gn:feature_code":"PPL",
    "gn:name":"Tangai Banda",
    "gn:population":0,
    "gn:timezone":"Asia/Karachi",
    "iso:country":"PK",
    "wof:name":"Tangai Banda",
    "wof:placetype":"locality"
},
  "geometry": {"coordinates":[72.64787,35.14608],"type":"Point"}
}