{
  "type": "Feature",
  "properties": {
    "gn:admin1_code":"05",
    "gn:asciiname":"Ali Muhammad Ferozani",
    "gn:country_code":"PK",
    "gn:dem":-1,
    "gn:feature_class":"P",
    "gn:feature_code":"PPL",
    "gn:name":"Ali Muhammad Ferozani",
    "gn:population":0,
    "gn:timezone":"Asia/Karachi",
    "iso:country":"PK",
    "wof:name":"Ali Muhammad Ferozani",
    "wof:placetype":"locality"
},
  "geometry": {"coordinates":[67.49745,24.09575],"type":"Point"}
}