{
  "type": "Feature",
  "properties": {
    "gn:admin1_code":"3.0",
    "gn:asciiname":"Kalo Shah",
    "gn:country_code":"PK",
    "gn:dem":437,
    "gn:feature_class":"P",
    "gn:feature_code":"PPL",
    "gn:name":"Kalo Shah",
    "gn:population":0,
    "gn:timezone":"Asia/Karachi",
    "iso:country":"PK",
    "wof:name":"Kalo Shah",
    "wof:placetype":"locality"
},
  "geometry": {"coordinates":[71.97986,34.45339],"type":"Point"}
}