{
  "type": "Feature",
  "properties": {
    "gn:admin1_code":"4",
    "gn:asciiname":"Dhok Kharala",
    "gn:country_code":"PK",
    "gn:dem":288,
    "gn:feature_class":"P",
    "gn:feature_code":"PPL",
    "gn:name":"Dhok Kharala",
    "gn:population":0,
    "gn:timezone":"Asia/Karachi",
    "iso:country":"PK",
    "name:und_x_variant":[
        "Dhok Khar\u0101l"
    ],
    "wof:name":"Dhok Kharala",
    "wof:placetype":"locality"
},
  "geometry": {"coordinates":[73.40000000000001,32.93549],"type":"Point"}
}