{
  "type": "Feature",
  "properties": {
    "gn:admin1_code":"5.0",
    "gn:asciiname":"Chandria",
    "gn:country_code":"PK",
    "gn:dem":66,
    "gn:feature_class":"P",
    "gn:feature_code":"PPL",
    "gn:name":"Chandria",
    "gn:population":0,
    "gn:timezone":"Asia/Karachi",
    "iso:country":"PK",
    "name:bul_x_preferred":[
        "\u0425\u0430\u043d\u0434\u0440\u0438\u044f"
    ],
    "name:ceb_x_preferred":[
        "Chandri\u00e1"
    ],
    "name:ell_x_preferred":[
        "\u03a7\u03b1\u03bd\u03b4\u03c1\u03b9\u03ac"
    ],
    "name:fra_x_preferred":[
        "Chandri\u00e1"
    ],
    "name:pol_x_preferred":[
        "Chandria"
    ],
    "name:swe_x_preferred":[
        "Chandria"
    ],
    "name:und_x_variant":[
        "Ch\u0101nd\u0101n"
    ],
    "wof:name":"Chandria",
    "wof:placetype":"locality"
},
  "geometry": {"coordinates":[68.73696,28.1915],"type":"Point"}
}