{
  "type": "Feature",
  "properties": {
    "gn:admin1_code":"2.0",
    "gn:asciiname":"Dinar Shahr",
    "gn:country_code":"PK",
    "gn:dem":502,
    "gn:feature_class":"P",
    "gn:feature_code":"PPL",
    "gn:name":"Dinar Shahr",
    "gn:population":0,
    "gn:timezone":"Asia/Karachi",
    "iso:country":"PK",
    "wof:name":"Dinar Shahr",
    "wof:placetype":"locality"
},
  "geometry": {"coordinates":[62.79718,28.04917],"type":"Point"}
}