{
  "type": "Feature",
  "properties": {
    "gn:admin1_code":"2.0",
    "gn:asciiname":"Marv",
    "gn:country_code":"PK",
    "gn:dem":1428,
    "gn:feature_class":"P",
    "gn:feature_code":"PPL",
    "gn:name":"Marv",
    "gn:population":0,
    "gn:timezone":"Asia/Karachi",
    "iso:country":"PK",
    "name:dan_x_preferred":[
        "Marv"
    ],
    "name:deu_x_preferred":[
        "Marv"
    ],
    "name:fra_x_preferred":[
        "Marv"
    ],
    "wof:name":"Marv",
    "wof:placetype":"locality"
},
  "geometry": {"coordinates":[66.5791,27.2089],"type":"Point"}
}