{
  "type": "Feature",
  "properties": {
    "gn:admin1_code":"5.0",
    "gn:asciiname":"Jan Muhammad Chandio",
    "gn:country_code":"PK",
    "gn:dem":35,
    "gn:feature_class":"P",
    "gn:feature_code":"PPL",
    "gn:name":"Jan Muhammad Chandio",
    "gn:population":0,
    "gn:timezone":"Asia/Karachi",
    "iso:country":"PK",
    "wof:name":"Jan Muhammad Chandio",
    "wof:placetype":"locality"
},
  "geometry": {"coordinates":[68.46375,26.42217],"type":"Point"}
}