{
  "type": "Feature",
  "properties": {
    "iso:country":"PK",
    "name:deu_x_preferred":[
        "Hangu"
    ],
    "name:dut_x_preferred":[
        "Hangu"
    ],
    "name:eng_x_preferred":[
        "Hangu"
    ],
    "name:fra_x_preferred":[
        "Hangu"
    ],
    "name:fre_x_preferred":[
        "Hangu"
    ],
    "name:ger_x_preferred":[
        "Hangu"
    ],
    "name:may_x_preferred":[
        "Hangu"
    ],
    "name:msa_x_preferred":[
        "Hangu"
    ],
    "name:pnb_x_preferred":[
        "\u06c1\u0646\u06af\u0648"
    ],
    "name:por_x_preferred":[
        "Hangu"
    ],
    "name:rus_x_preferred":[
        "\u0425\u0430\u043d\u0433\u0443"
    ],
    "name:spa_x_preferred":[
        "Hangu"
    ],
    "name:urd_x_preferred":[
        "\u06c1\u0646\u06af\u0648"
    ],
    "qs:gn_country":"PK",
    "qs:gn_fcode":"PPLA2",
    "qs:gn_pop":36150,
    "qs:name":"Hangu",
    "qs:name_adm0":"Pakistan",
    "qs:name_adm1":"North-West Frontier",
    "qs:photos":0,
    "qs:photos_1k":0,
    "qs:photos_9k":1,
    "qs:photos_9r":1,
    "qs:photos_all":3,
    "qs:photos_sr":0,
    "qs:placetype":"Town",
    "qs:pop_sr":"7",
    "qs:woe_adm0":23424922,
    "wd:wordcount":837,
    "wof:name":"Hangu",
    "wof:placetype":"locality",
    "wof:population":36150
},
  "geometry": {"coordinates":[71.05934000000001,33.53108],"type":"Point"}
}