{
  "type": "Feature",
  "properties": {
    "gn:admin1_code":"3.0",
    "gn:asciiname":"Gandi Khan Khel",
    "gn:country_code":"PK",
    "gn:dem":287,
    "gn:feature_class":"P",
    "gn:feature_code":"PPL",
    "gn:name":"Gandi Khan Khel",
    "gn:population":0,
    "gn:timezone":"Asia/Karachi",
    "iso:country":"PK",
    "wof:name":"Gandi Khan Khel",
    "wof:placetype":"locality"
},
  "geometry": {"coordinates":[70.76793000000001,32.74695],"type":"Point"}
}