{
  "type": "Feature",
  "properties": {
    "gn:admin1_code":"5.0",
    "gn:asciiname":"Suhrab Muhammad Jafri",
    "gn:country_code":"PK",
    "gn:dem":66,
    "gn:feature_class":"P",
    "gn:feature_code":"PPL",
    "gn:name":"Suhrab Muhammad Jafri",
    "gn:population":0,
    "gn:timezone":"Asia/Karachi",
    "iso:country":"PK",
    "name:und_x_variant":[
        "Sohrab Muhammad Jafri"
    ],
    "wof:name":"Suhrab Muhammad Jafri",
    "wof:placetype":"locality"
},
  "geometry": {"coordinates":[68.93995,28.26475],"type":"Point"}
}