{
  "type": "Feature",
  "properties": {
    "gn:admin1_code":"1.0",
    "gn:asciiname":"Pasalkot",
    "gn:country_code":"PK",
    "gn:dem":1454,
    "gn:feature_class":"P",
    "gn:feature_code":"PPL",
    "gn:name":"Pasalkot",
    "gn:population":0,
    "gn:timezone":"Asia/Karachi",
    "iso:country":"PK",
    "name:und_x_variant":[
        "Matw\u0101m",
        "Pasalkot",
        "Matwam Madi Khel"
    ],
    "wof:name":"Pasalkot",
    "wof:placetype":"locality"
},
  "geometry": {"coordinates":[70.06820999999999,32.69224000000001],"type":"Point"}
}