{
  "type": "Feature",
  "properties": {
    "gn:admin1_code":"4",
    "gn:asciiname":"Babara",
    "gn:country_code":"PK",
    "gn:dem":263,
    "gn:feature_class":"P",
    "gn:feature_code":"PPL",
    "gn:name":"Babara",
    "gn:population":0,
    "gn:timezone":"Asia/Karachi",
    "iso:country":"PK",
    "name:und_x_variant":[
        "Pamrah"
    ],
    "wof:name":"Babara",
    "wof:placetype":"locality"
},
  "geometry": {"coordinates":[74.2362,32.71815],"type":"Point"}
}