{
  "type": "Feature",
  "properties": {
    "gn:admin1_code":"2.0",
    "gn:asciiname":"Killi Malik Abdul Ghani Pirkani",
    "gn:country_code":"PK",
    "gn:dem":1552,
    "gn:feature_class":"P",
    "gn:feature_code":"PPL",
    "gn:name":"Killi Malik Abdul Ghani Pirkani",
    "gn:population":0,
    "gn:timezone":"Asia/Karachi",
    "iso:country":"PK",
    "wof:name":"Killi Malik Abdul Ghani Pirkani",
    "wof:placetype":"locality"
},
  "geometry": {"coordinates":[66.40694999999999,30.07426],"type":"Point"}
}