{
  "type": "Feature",
  "properties": {
    "gn:admin1_code":"4.0",
    "gn:asciiname":"Ishparalwali",
    "gn:country_code":"PK",
    "gn:dem":347,
    "gn:feature_class":"P",
    "gn:feature_code":"PPL",
    "gn:name":"Ishparalwali",
    "gn:population":0,
    "gn:timezone":"Asia/Karachi",
    "iso:country":"PK",
    "name:und_x_variant":[
        "Ishpral\u0101nw\u0101li"
    ],
    "wof:name":"Ishparalwali",
    "wof:placetype":"locality"
},
  "geometry": {"coordinates":[71.94528000000003,32.97984],"type":"Point"}
}