{
  "type": "Feature",
  "properties": {
    "gn:admin1_code":"1",
    "gn:asciiname":"Pir Kas",
    "gn:country_code":"PK",
    "gn:dem":766,
    "gn:feature_class":"P",
    "gn:feature_code":"PPL",
    "gn:name":"Pir Kas",
    "gn:population":0,
    "gn:timezone":"Asia/Karachi",
    "iso:country":"PK",
    "name:und_x_variant":[
        "P\u012br Kas"
    ],
    "wof:name":"Pir Kas",
    "wof:placetype":"locality"
},
  "geometry": {"coordinates":[70.51929,33.37335],"type":"Point"}
}