{
  "type": "Feature",
  "properties": {
    "gn:admin1_code":"3.0",
    "gn:asciiname":"Landidak Shadi",
    "gn:country_code":"PK",
    "gn:dem":326,
    "gn:feature_class":"P",
    "gn:feature_code":"PPL",
    "gn:name":"Landidak Shadi",
    "gn:population":0,
    "gn:timezone":"Asia/Karachi",
    "iso:country":"PK",
    "name:und_x_variant":[
        "Sh\u0101di Kh\u0101n"
    ],
    "wof:name":"Landidak Shadi",
    "wof:placetype":"locality"
},
  "geometry": {"coordinates":[70.63606999999998,32.8597],"type":"Point"}
}