{
  "type": "Feature",
  "properties": {
    "gn:admin1_code":"01",
    "gn:asciiname":"Tra Konr",
    "gn:country_code":"PK",
    "gn:dem":2355,
    "gn:feature_class":"P",
    "gn:feature_code":"PPL",
    "gn:name":"Tra Konr",
    "gn:population":0,
    "gn:timezone":"Asia/Karachi",
    "iso:country":"PK",
    "wof:name":"Tra Konr",
    "wof:placetype":"locality"
},
  "geometry": {"coordinates":[69.70175999999999,32.55477],"type":"Point"}
}