{
  "type": "Feature",
  "properties": {
    "gn:admin1_code":"4.0",
    "gn:asciiname":"Chak Two Hundred Two Gugera Branch",
    "gn:country_code":"PK",
    "gn:dem":166,
    "gn:feature_class":"P",
    "gn:feature_code":"PPL",
    "gn:name":"Chak Two Hundred Two Gugera Branch",
    "gn:population":0,
    "gn:timezone":"Asia/Karachi",
    "iso:country":"PK",
    "name:und_x_variant":[
        "Gobindarh",
        "Gobindgarh",
        "Chak Two Hundred Two Gugera Branch",
        "Gabindgurh"
    ],
    "wof:name":"Chak Two Hundred Two Gugera Branch",
    "wof:placetype":"locality"
},
  "geometry": {"coordinates":[72.80750999999999,30.9257],"type":"Point"}
}