{
  "type": "Feature",
  "properties": {
    "gn:admin1_code":"4.0",
    "gn:asciiname":"Chahi Kuhna",
    "gn:country_code":"PK",
    "gn:dem":217,
    "gn:feature_class":"P",
    "gn:feature_code":"PPL",
    "gn:name":"Chahi Kuhna",
    "gn:population":0,
    "gn:timezone":"Asia/Karachi",
    "iso:country":"PK",
    "name:und_x_variant":[
        "Chahal Kohna",
        "Chahil Kuhna",
        "Chahi Kuhna"
    ],
    "wof:name":"Chahi Kuhna",
    "wof:placetype":"locality"
},
  "geometry": {"coordinates":[73.98206999999999,32.12174],"type":"Point"}
}