{
  "type": "Feature",
  "properties": {
    "gn:admin1_code":"3.0",
    "gn:asciiname":"Kharmatu",
    "gn:country_code":"PK",
    "gn:dem":445,
    "gn:feature_class":"P",
    "gn:feature_code":"PPL",
    "gn:name":"Kharmatu",
    "gn:population":0,
    "gn:timezone":"Asia/Karachi",
    "iso:country":"PK",
    "name:und_x_variant":[
        "Kharm\u0101tu"
    ],
    "wof:name":"Kharmatu",
    "wof:placetype":"locality"
},
  "geometry": {"coordinates":[71.51291999999999,33.51423],"type":"Point"}
}