{
  "type": "Feature",
  "properties": {
    "gn:admin1_code":"3.0",
    "gn:asciiname":"Haji Koruna",
    "gn:country_code":"PK",
    "gn:dem":402,
    "gn:feature_class":"P",
    "gn:feature_code":"PPL",
    "gn:name":"Haji Koruna",
    "gn:population":0,
    "gn:timezone":"Asia/Karachi",
    "iso:country":"PK",
    "name:eng_x_preferred":[
        "Haji Koruna"
    ],
    "wof:name":"Haji Koruna",
    "wof:placetype":"locality"
},
  "geometry": {"coordinates":[71.77078,34.34682],"type":"Point"}
}