{
  "type": "Feature",
  "properties": {
    "gn:admin1_code":"4.0",
    "gn:asciiname":"Goth Gullan Machhi",
    "gn:country_code":"PK",
    "gn:dem":78,
    "gn:feature_class":"P",
    "gn:feature_code":"PPL",
    "gn:name":"Goth Gullan Machhi",
    "gn:population":0,
    "gn:timezone":"Asia/Karachi",
    "iso:country":"PK",
    "wof:name":"Goth Gullan Machhi",
    "wof:placetype":"locality"
},
  "geometry": {"coordinates":[69.73477,28.3065],"type":"Point"}
}