{
  "type": "Feature",
  "properties": {
    "gn:admin1_code":"4",
    "gn:asciiname":"Chak Pilowal Saiyidan",
    "gn:country_code":"PK",
    "gn:dem":180,
    "gn:feature_class":"P",
    "gn:feature_code":"PPL",
    "gn:name":"Chak Pilowal Saiyidan",
    "gn:population":0,
    "gn:timezone":"Asia/Karachi",
    "iso:country":"PK",
    "wof:name":"Chak Pilowal Saiyidan",
    "wof:placetype":"locality"
},
  "geometry": {"coordinates":[72.87,31.77326],"type":"Point"}
}