{
  "type": "Feature",
  "properties": {
    "gn:admin1_code":"2.0",
    "gn:asciiname":"Shahdlan",
    "gn:country_code":"PK",
    "gn:dem":597,
    "gn:feature_class":"P",
    "gn:feature_code":"PPL",
    "gn:name":"Shahdlan",
    "gn:population":0,
    "gn:timezone":"Asia/Karachi",
    "iso:country":"PK",
    "wof:name":"Shahdlan",
    "wof:placetype":"locality"
},
  "geometry": {"coordinates":[64.45487,28.12357],"type":"Point"}
}