{
  "type": "Feature",
  "properties": {
    "gn:admin1_code":"4",
    "gn:asciiname":"Chak Twenty-six Rakh Branch",
    "gn:country_code":"PK",
    "gn:dem":201,
    "gn:feature_class":"P",
    "gn:feature_code":"PPL",
    "gn:name":"Chak Twenty-six Rakh Branch",
    "gn:population":0,
    "gn:timezone":"Asia/Karachi",
    "iso:country":"PK",
    "name:und_x_variant":[
        "Moga Ghomy\u0101rw\u0101la",
        "Muj\u0101war\u0101nw\u0101la"
    ],
    "wof:name":"Chak Twenty-six Rakh Branch",
    "wof:placetype":"locality"
},
  "geometry": {"coordinates":[73.58230999999998,31.68688],"type":"Point"}
}