{
  "type": "Feature",
  "properties": {
    "gn:admin1_code":"5.0",
    "gn:asciiname":"Goth Mir Muhammad Jakhro",
    "gn:country_code":"PK",
    "gn:dem":26,
    "gn:feature_class":"P",
    "gn:feature_code":"PPL",
    "gn:name":"Goth Mir Muhammad Jakhro",
    "gn:population":0,
    "gn:timezone":"Asia/Karachi",
    "iso:country":"PK",
    "wof:name":"Goth Mir Muhammad Jakhro",
    "wof:placetype":"locality"
},
  "geometry": {"coordinates":[68.57510000000001,25.99889],"type":"Point"}
}