{
  "type": "Feature",
  "properties": {
    "gn:admin1_code":"1.0",
    "gn:asciiname":"Shinkai",
    "gn:country_code":"PK",
    "gn:dem":2093,
    "gn:feature_class":"P",
    "gn:feature_code":"PPL",
    "gn:name":"Shinkai",
    "gn:population":0,
    "gn:timezone":"Asia/Karachi",
    "iso:country":"PK",
    "wof:name":"Shinkai",
    "wof:placetype":"locality"
},
  "geometry": {"coordinates":[70.38011,33.84609],"type":"Point"}
}