{
  "type": "Feature",
  "properties": {
    "gn:admin1_code":"2.0",
    "gn:asciiname":"Karnongi",
    "gn:country_code":"PK",
    "gn:dem":978,
    "gn:feature_class":"P",
    "gn:feature_code":"PPL",
    "gn:name":"Karnongi",
    "gn:population":0,
    "gn:timezone":"Asia/Karachi",
    "iso:country":"PK",
    "wof:name":"Karnongi",
    "wof:placetype":"locality"
},
  "geometry": {"coordinates":[67.88308000000001,30.11813],"type":"Point"}
}