{
  "type": "Feature",
  "properties": {
    "gn:admin1_code":"5.0",
    "gn:asciiname":"Limun Khan Lashari",
    "gn:country_code":"PK",
    "gn:dem":62,
    "gn:feature_class":"P",
    "gn:feature_code":"PPL",
    "gn:name":"Limun Khan Lashari",
    "gn:population":0,
    "gn:timezone":"Asia/Karachi",
    "iso:country":"PK",
    "wof:name":"Limun Khan Lashari",
    "wof:placetype":"locality"
},
  "geometry": {"coordinates":[68.67307,28.28295],"type":"Point"}
}