{
  "type": "Feature",
  "properties": {
    "gn:admin1_code":"5",
    "gn:asciiname":"Goth Bachhal Channa",
    "gn:country_code":"PK",
    "gn:dem":39,
    "gn:feature_class":"P",
    "gn:feature_code":"PPL",
    "gn:name":"Goth Bachhal Channa",
    "gn:population":0,
    "gn:timezone":"Asia/Karachi",
    "iso:country":"PK",
    "name:und_x_variant":[
        "Kando Channa"
    ],
    "wof:name":"Goth Bachhal Channa",
    "wof:placetype":"locality"
},
  "geometry": {"coordinates":[67.82713000000001,26.44599],"type":"Point"}
}