{
  "type": "Feature",
  "properties": {
    "gn:admin1_code":"5.0",
    "gn:asciiname":"Lune Jat",
    "gn:country_code":"PK",
    "gn:dem":7,
    "gn:feature_class":"P",
    "gn:feature_code":"PPL",
    "gn:name":"Lune Jat",
    "gn:population":0,
    "gn:timezone":"Asia/Karachi",
    "iso:country":"PK",
    "name:eng_x_preferred":[
        "Luna"
    ],
    "wof:name":"Lune Jat",
    "wof:placetype":"locality"
},
  "geometry": {"coordinates":[68.26844,24.52174],"type":"Point"}
}