{
  "type": "Feature",
  "properties": {
    "gn:admin1_code":"3",
    "gn:asciiname":"Samchelai",
    "gn:country_code":"PK",
    "gn:dem":2340,
    "gn:feature_class":"P",
    "gn:feature_code":"PPL",
    "gn:name":"Samchelai",
    "gn:population":0,
    "gn:timezone":"Asia/Karachi",
    "iso:country":"PK",
    "wof:name":"Samchelai",
    "wof:placetype":"locality"
},
  "geometry": {"coordinates":[72.63889,34.83611],"type":"Point"}
}