{
  "type": "Feature",
  "properties": {
    "gn:admin1_code":"3",
    "gn:asciiname":"Ujjar Baffa",
    "gn:country_code":"PK",
    "gn:dem":1729,
    "gn:feature_class":"P",
    "gn:feature_code":"PPL",
    "gn:name":"Ujjar Baffa",
    "gn:population":0,
    "gn:timezone":"Asia/Karachi",
    "iso:country":"PK",
    "wof:name":"Ujjar Baffa",
    "wof:placetype":"locality"
},
  "geometry": {"coordinates":[72.90992,34.46668],"type":"Point"}
}