{
  "type": "Feature",
  "properties": {
    "gn:admin1_code":"3.0",
    "gn:asciiname":"Abdarra",
    "gn:country_code":"PK",
    "gn:dem":369,
    "gn:feature_class":"P",
    "gn:feature_code":"PPL",
    "gn:name":"Abdarra",
    "gn:population":0,
    "gn:timezone":"Asia/Karachi",
    "iso:country":"PK",
    "name:und_x_variant":[
        "Abdara",
        "Abdarra"
    ],
    "wof:name":"Abdarra",
    "wof:placetype":"locality"
},
  "geometry": {"coordinates":[71.51181,33.98403],"type":"Point"}
}