{
  "type": "Feature",
  "properties": {
    "gn:admin1_code":"3.0",
    "gn:asciiname":"Gala Khel",
    "gn:country_code":"PK",
    "gn:dem":418,
    "gn:feature_class":"P",
    "gn:feature_code":"PPL",
    "gn:name":"Gala Khel",
    "gn:population":0,
    "gn:timezone":"Asia/Karachi",
    "iso:country":"PK",
    "wof:name":"Gala Khel",
    "wof:placetype":"locality"
},
  "geometry": {"coordinates":[70.55014,33.01538],"type":"Point"}
}