{
  "type": "Feature",
  "properties": {
    "gn:admin1_code":"2.0",
    "gn:asciiname":"Khudadad Bazar",
    "gn:country_code":"PK",
    "gn:dem":28,
    "gn:feature_class":"P",
    "gn:feature_code":"PPL",
    "gn:name":"Khudadad Bazar",
    "gn:population":0,
    "gn:timezone":"Asia/Karachi",
    "iso:country":"PK",
    "wof:name":"Khudadad Bazar",
    "wof:placetype":"locality"
},
  "geometry": {"coordinates":[62.41676999999999,25.33167000000001],"type":"Point"}
}