{
  "type": "Feature",
  "properties": {
    "gn:admin1_code":"7.0",
    "gn:asciiname":"Rupli",
    "gn:country_code":"PK",
    "gn:dem":2186,
    "gn:feature_class":"P",
    "gn:feature_code":"PPL",
    "gn:name":"Rupli",
    "gn:population":0,
    "gn:timezone":"Asia/Karachi",
    "iso:country":"PK",
    "wof:name":"Rupli",
    "wof:placetype":"locality"
},
  "geometry": {"coordinates":[74.42278,35.46959000000001],"type":"Point"}
}