{
  "type": "Feature",
  "properties": {
    "gn:admin1_code":"4.0",
    "gn:asciiname":"Shahanwali",
    "gn:country_code":"PK",
    "gn:dem":125,
    "gn:feature_class":"P",
    "gn:feature_code":"PPL",
    "gn:name":"Shahanwali",
    "gn:population":0,
    "gn:timezone":"Asia/Karachi",
    "iso:country":"PK",
    "name:eng_x_preferred":[
        "Shahanwali"
    ],
    "wof:name":"Shahanwali",
    "wof:placetype":"locality"
},
  "geometry": {"coordinates":[71.97086,29.46742],"type":"Point"}
}