{
  "type": "Feature",
  "properties": {
    "gn:admin1_code":"2",
    "gn:asciiname":"Gandherai Sadu Kili",
    "gn:country_code":"PK",
    "gn:dem":1309,
    "gn:feature_class":"P",
    "gn:feature_code":"PPL",
    "gn:name":"Gandherai Sadu Kili",
    "gn:population":0,
    "gn:timezone":"Asia/Karachi",
    "iso:country":"PK",
    "wof:name":"Gandherai Sadu Kili",
    "wof:placetype":"locality"
},
  "geometry": {"coordinates":[69.54033000000001,31.84377000000001],"type":"Point"}
}