{
  "type": "Feature",
  "properties": {
    "gn:admin1_code":"3",
    "gn:asciiname":"Shakharan",
    "gn:country_code":"PK",
    "gn:dem":1805,
    "gn:feature_class":"P",
    "gn:feature_code":"PPL",
    "gn:name":"Shakharan",
    "gn:population":0,
    "gn:timezone":"Asia/Karachi",
    "iso:country":"PK",
    "name:und_x_variant":[
        "Shukhra"
    ],
    "wof:name":"Shakharan",
    "wof:placetype":"locality"
},
  "geometry": {"coordinates":[73.50657,34.66768],"type":"Point"}
}