{
  "type": "Feature",
  "properties": {
    "gn:admin1_code":"4.0",
    "gn:asciiname":"Rachand",
    "gn:country_code":"PK",
    "gn:dem":208,
    "gn:feature_class":"P",
    "gn:feature_code":"PPL",
    "gn:name":"Rachand",
    "gn:population":0,
    "gn:timezone":"Asia/Karachi",
    "iso:country":"PK",
    "name:und_x_variant":[
        "Har Chand",
        "Rachand"
    ],
    "wof:name":"Rachand",
    "wof:placetype":"locality"
},
  "geometry": {"coordinates":[73.73484999999999,31.79627],"type":"Point"}
}