{
  "type": "Feature",
  "properties": {
    "gn:admin1_code":"5.0",
    "gn:asciiname":"Goth Haji Umar Jamali",
    "gn:country_code":"PK",
    "gn:dem":17,
    "gn:feature_class":"P",
    "gn:feature_code":"PPL",
    "gn:name":"Goth Haji Umar Jamali",
    "gn:population":0,
    "gn:timezone":"Asia/Karachi",
    "iso:country":"PK",
    "wof:name":"Goth Haji Umar Jamali",
    "wof:placetype":"locality"
},
  "geometry": {"coordinates":[68.56390999999999,25.19842],"type":"Point"}
}