{
  "type": "Feature",
  "properties": {
    "gn:admin1_code":"4",
    "gn:asciiname":"Dhok Tahli",
    "gn:country_code":"PK",
    "gn:dem":370,
    "gn:feature_class":"P",
    "gn:feature_code":"PPL",
    "gn:name":"Dhok Tahli",
    "gn:population":0,
    "gn:timezone":"Asia/Karachi",
    "iso:country":"PK",
    "name:und_x_variant":[
        "Dhok Bakhsh"
    ],
    "wof:name":"Dhok Tahli",
    "wof:placetype":"locality"
},
  "geometry": {"coordinates":[73.33413,32.93742],"type":"Point"}
}