{
  "type": "Feature",
  "properties": {
    "gn:admin1_code":"5.0",
    "gn:asciiname":"Goth Hamal",
    "gn:country_code":"PK",
    "gn:dem":117,
    "gn:feature_class":"P",
    "gn:feature_code":"PPL",
    "gn:name":"Goth Hamal",
    "gn:population":0,
    "gn:timezone":"Asia/Karachi",
    "iso:country":"PK",
    "wof:name":"Goth Hamal",
    "wof:placetype":"locality"
},
  "geometry": {"coordinates":[67.17206,25.11275],"type":"Point"}
}