{
  "type": "Feature",
  "properties": {
    "gn:admin1_code":"5",
    "gn:asciiname":"Saiyid Muhammad Shah",
    "gn:country_code":"PK",
    "gn:dem":16,
    "gn:feature_class":"P",
    "gn:feature_code":"PPL",
    "gn:name":"Saiyid Muhammad Shah",
    "gn:population":0,
    "gn:timezone":"Asia/Karachi",
    "iso:country":"PK",
    "name:eng_x_preferred":[
        "Saiyid Muhammad Shah"
    ],
    "wof:name":"Saiyid Muhammad Shah",
    "wof:placetype":"locality"
},
  "geometry": {"coordinates":[68.20031999999999,25.01852],"type":"Point"}
}