{
  "type": "Feature",
  "properties": {
    "gn:admin1_code":"5",
    "gn:asciiname":"Dub jo Goth",
    "gn:country_code":"PK",
    "gn:dem":54,
    "gn:feature_class":"P",
    "gn:feature_code":"PPL",
    "gn:name":"Dub jo Goth",
    "gn:population":0,
    "gn:timezone":"Asia/Karachi",
    "iso:country":"PK",
    "name:und_x_variant":[
        "Dub"
    ],
    "wof:name":"Dub jo Goth",
    "wof:placetype":"locality"
},
  "geometry": {"coordinates":[69.05664,27.07219000000001],"type":"Point"}
}