{
  "type": "Feature",
  "properties": {
    "gn:admin1_code":"4.0",
    "gn:asciiname":"Sarto Chhaw",
    "gn:country_code":"PK",
    "gn:dem":1099,
    "gn:feature_class":"P",
    "gn:feature_code":"PPL",
    "gn:name":"Sarto Chhaw",
    "gn:population":0,
    "gn:timezone":"Asia/Karachi",
    "iso:country":"PK",
    "wof:name":"Sarto Chhaw",
    "wof:placetype":"locality"
},
  "geometry": {"coordinates":[70.1504,30.47621],"type":"Point"}
}