{
  "type": "Feature",
  "properties": {
    "gn:admin1_code":"3",
    "gn:asciiname":"Hazirah",
    "gn:country_code":"PK",
    "gn:dem":1294,
    "gn:feature_class":"P",
    "gn:feature_code":"PPL",
    "gn:name":"Hazirah",
    "gn:population":0,
    "gn:timezone":"Asia/Karachi",
    "iso:country":"PK",
    "name:und_x_variant":[
        "Haz\u012bra"
    ],
    "wof:name":"Hazirah",
    "wof:placetype":"locality"
},
  "geometry": {"coordinates":[73.31216999999999,34.30519],"type":"Point"}
}