{
  "type": "Feature",
  "properties": {
    "gn:admin1_code":"5",
    "gn:asciiname":"Goth Yaqub Khoso",
    "gn:country_code":"PK",
    "gn:dem":38,
    "gn:feature_class":"P",
    "gn:feature_code":"PPL",
    "gn:name":"Goth Yaqub Khoso",
    "gn:population":0,
    "gn:timezone":"Asia/Karachi",
    "iso:country":"PK",
    "name:und_x_variant":[
        "Jal\u0101l Khoso"
    ],
    "wof:name":"Goth Yaqub Khoso",
    "wof:placetype":"locality"
},
  "geometry": {"coordinates":[68.04423,26.28995],"type":"Point"}
}