{
  "type": "Feature",
  "properties": {
    "gn:admin1_code":"3.0",
    "gn:asciiname":"Kandali",
    "gn:country_code":"PK",
    "gn:dem":1369,
    "gn:feature_class":"P",
    "gn:feature_code":"PPL",
    "gn:name":"Kandali",
    "gn:population":0,
    "gn:timezone":"Asia/Karachi",
    "iso:country":"PK",
    "name:und_x_variant":[
        "B\u0101nda Kanduli"
    ],
    "wof:name":"Kandali",
    "wof:placetype":"locality"
},
  "geometry": {"coordinates":[70.95855,33.54501],"type":"Point"}
}