{
  "type": "Feature",
  "properties": {
    "gn:admin1_code":"7.0",
    "gn:asciiname":"Mano Tasti",
    "gn:country_code":"PK",
    "gn:dem":3379,
    "gn:feature_class":"P",
    "gn:feature_code":"PPL",
    "gn:name":"Mano Tasti",
    "gn:population":0,
    "gn:timezone":"Asia/Karachi",
    "iso:country":"PK",
    "wof:name":"Mano Tasti",
    "wof:placetype":"locality"
},
  "geometry": {"coordinates":[74.17648,35.14658],"type":"Point"}
}