{
  "type": "Feature",
  "properties": {
    "gn:admin1_code":"2.0",
    "gn:asciiname":"Saindak Colony",
    "gn:country_code":"PK",
    "gn:dem":1030,
    "gn:feature_class":"P",
    "gn:feature_code":"PPL",
    "gn:name":"Saindak Colony",
    "gn:population":0,
    "gn:timezone":"Asia/Karachi",
    "iso:country":"PK",
    "wof:name":"Saindak Colony",
    "wof:placetype":"locality"
},
  "geometry": {"coordinates":[61.58453000000001,29.23802],"type":"Point"}
}