{
  "type": "Feature",
  "properties": {
    "gn:admin1_code":"4",
    "gn:asciiname":"Khokharwala",
    "gn:country_code":"PK",
    "gn:dem":141,
    "gn:feature_class":"P",
    "gn:feature_code":"PPL",
    "gn:name":"Khokharwala",
    "gn:population":0,
    "gn:timezone":"Asia/Karachi",
    "iso:country":"PK",
    "name:und_x_variant":[
        "Loh\u0101rw\u0101la"
    ],
    "wof:name":"Khokharwala",
    "wof:placetype":"locality"
},
  "geometry": {"coordinates":[70.94175,30.72444],"type":"Point"}
}