{
  "type": "Feature",
  "properties": {
    "gn:admin1_code":"5",
    "gn:asciiname":"Goth Mir Muhammad Kaloi",
    "gn:country_code":"PK",
    "gn:dem":23,
    "gn:feature_class":"P",
    "gn:feature_code":"PPL",
    "gn:name":"Goth Mir Muhammad Kaloi",
    "gn:population":0,
    "gn:timezone":"Asia/Karachi",
    "iso:country":"PK",
    "name:und_x_variant":[
        "Goth Am\u012br Muhammad"
    ],
    "wof:name":"Goth Mir Muhammad Kaloi",
    "wof:placetype":"locality"
},
  "geometry": {"coordinates":[68.68314000000001,25.94382],"type":"Point"}
}