{
  "type": "Feature",
  "properties": {
    "gn:admin1_code":"04",
    "gn:asciiname":"Lang Shimali",
    "gn:country_code":"PK",
    "gn:dem":165,
    "gn:feature_class":"P",
    "gn:feature_code":"PPL",
    "gn:name":"Lang Shimali",
    "gn:population":0,
    "gn:timezone":"Asia/Karachi",
    "iso:country":"PK",
    "name:und_x_variant":[
        "Lang Shumali",
        "Lang Shimali"
    ],
    "wof:name":"Lang Shimali",
    "wof:placetype":"locality"
},
  "geometry": {"coordinates":[72.27524,31.69362000000001],"type":"Point"}
}