{
  "type": "Feature",
  "properties": {
    "gn:admin1_code":"4",
    "gn:asciiname":"Gandpur",
    "gn:country_code":"PK",
    "gn:dem":115,
    "gn:feature_class":"P",
    "gn:feature_code":"PPL",
    "gn:name":"Gandpur",
    "gn:population":0,
    "gn:timezone":"Asia/Karachi",
    "iso:country":"PK",
    "name:und_x_variant":[
        "D\u012bnpur"
    ],
    "wof:name":"Gandpur",
    "wof:placetype":"locality"
},
  "geometry": {"coordinates":[70.95631,29.86358],"type":"Point"}
}