{
  "type": "Feature",
  "properties": {
    "gn:admin1_code":"6.0",
    "gn:asciiname":"Band",
    "gn:country_code":"PK",
    "gn:dem":1629,
    "gn:feature_class":"P",
    "gn:feature_code":"PPL",
    "gn:name":"Band",
    "gn:population":0,
    "gn:timezone":"Asia/Karachi",
    "iso:country":"PK",
    "name:und_x_variant":[
        "P\u0101nd"
    ],
    "wof:name":"Band",
    "wof:placetype":"locality"
},
  "geometry": {"coordinates":[73.73499,33.84591],"type":"Point"}
}