{
  "type": "Feature",
  "properties": {
    "gn:admin1_code":"6.0",
    "gn:asciiname":"Band",
    "gn:country_code":"PK",
    "gn:dem":1629,
    "gn:feature_class":"P",
    "gn:feature_code":"PPL",
    "gn:name":"Band",
    "gn:population":0,
    "gn:timezone":"Asia/Karachi",
    "iso:country":"PK",
    "name:ceb_x_preferred":[
        "Band"
    ],
    "name:ces_x_preferred":[
        "Band"
    ],
    "name:dan_x_preferred":[
        "B\u00e5nd"
    ],
    "name:deu_x_preferred":[
        "Band"
    ],
    "name:epo_x_preferred":[
        "Band"
    ],
    "name:heb_x_preferred":[
        "\u05d1\u05e0\u05d3"
    ],
    "name:ind_x_preferred":[
        "Band"
    ],
    "name:ita_x_preferred":[
        "Band"
    ],
    "name:jpn_x_preferred":[
        "\u30d0\u30f3\u30c9"
    ],
    "name:nds_x_preferred":[
        "Band"
    ],
    "name:nld_x_preferred":[
        "Band"
    ],
    "name:nor_x_preferred":[
        "B\u00e5nd"
    ],
    "name:por_x_preferred":[
        "Band"
    ],
    "name:swe_x_preferred":[
        "Band"
    ],
    "name:und_x_variant":[
        "P\u0101nd"
    ],
    "name:uzb_x_preferred":[
        "Band"
    ],
    "name:vie_x_preferred":[
        "Band"
    ],
    "name:zho_x_preferred":[
        "Band"
    ],
    "wof:name":"Band",
    "wof:placetype":"locality"
},
  "geometry": {"coordinates":[73.73499,33.84591],"type":"Point"}
}