{
  "type": "Feature",
  "properties": {
    "gn:admin1_code":"03",
    "gn:asciiname":"Nalki",
    "gn:country_code":"PK",
    "gn:dem":578,
    "gn:feature_class":"P",
    "gn:feature_code":"PPL",
    "gn:name":"Nalki",
    "gn:population":0,
    "gn:timezone":"Asia/Karachi",
    "iso:country":"PK",
    "name:und_x_variant":[
        "Nalaki",
        "Nalakki",
        "Nalki"
    ],
    "wof:name":"Nalki",
    "wof:placetype":"locality"
},
  "geometry": {"coordinates":[73.00258000000002,34.13175],"type":"Point"}
}