{
  "type": "Feature",
  "properties": {
    "gn:admin1_code":"4.0",
    "gn:asciiname":"Supwal",
    "gn:country_code":"PK",
    "gn:dem":286,
    "gn:feature_class":"P",
    "gn:feature_code":"PPL",
    "gn:name":"Supwal",
    "gn:population":0,
    "gn:timezone":"Asia/Karachi",
    "iso:country":"PK",
    "wof:name":"Supwal",
    "wof:placetype":"locality"
},
  "geometry": {"coordinates":[74.95496999999997,32.41755999999999],"type":"Point"}
}