{
  "type": "Feature",
  "properties": {
    "gn:admin1_code":"2.0",
    "gn:asciiname":"Kili Mulla Alam Gul",
    "gn:country_code":"PK",
    "gn:dem":1909,
    "gn:feature_class":"P",
    "gn:feature_code":"PPL",
    "gn:name":"Kili Mulla Alam Gul",
    "gn:population":0,
    "gn:timezone":"Asia/Karachi",
    "iso:country":"PK",
    "wof:name":"Kili Mulla Alam Gul",
    "wof:placetype":"locality"
},
  "geometry": {"coordinates":[68.68365,31.55291],"type":"Point"}
}