{
  "type": "Feature",
  "properties": {
    "gn:admin1_code":"2.0",
    "gn:asciiname":"Naghari",
    "gn:country_code":"PK",
    "gn:dem":149,
    "gn:feature_class":"P",
    "gn:feature_code":"PPL",
    "gn:name":"Naghari",
    "gn:population":0,
    "gn:timezone":"Asia/Karachi",
    "iso:country":"PK",
    "name:und_x_variant":[
        "Goth Nagh\u0101ri"
    ],
    "wof:name":"Naghari",
    "wof:placetype":"locality"
},
  "geometry": {"coordinates":[67.63085,29.40512],"type":"Point"}
}