{
  "type": "Feature",
  "properties": {
    "gn:admin1_code":"2.0",
    "gn:asciiname":"Mandi",
    "gn:country_code":"PK",
    "gn:dem":2084,
    "gn:feature_class":"P",
    "gn:feature_code":"PPL",
    "gn:name":"Mandi",
    "gn:population":0,
    "gn:timezone":"Asia/Karachi",
    "iso:country":"PK",
    "name:ara_x_preferred":[
        "\u0645\u0627\u0646\u062f\u064a"
    ],
    "name:ceb_x_preferred":[
        "Mandi"
    ],
    "name:deu_x_preferred":[
        "Mandi"
    ],
    "name:fin_x_preferred":[
        "Mandi"
    ],
    "name:ita_x_preferred":[
        "Mandi"
    ],
    "name:nld_x_preferred":[
        "Mandi"
    ],
    "name:pol_x_preferred":[
        "Mandi"
    ],
    "name:rus_x_preferred":[
        "\u041c\u0430\u043d\u0434\u0438"
    ],
    "name:spa_x_preferred":[
        "Mandi"
    ],
    "name:swe_x_preferred":[
        "Mandi"
    ],
    "name:ukr_x_preferred":[
        "\u041c\u0430\u043d\u0434\u0456"
    ],
    "wof:name":"Mandi",
    "wof:placetype":"locality"
},
  "geometry": {"coordinates":[66.68485,28.7012],"type":"Point"}
}