{
  "type": "Feature",
  "properties": {
    "gn:admin1_code":"5.0",
    "gn:asciiname":"Goth Nazir Ahmed Hamlani",
    "gn:country_code":"PK",
    "gn:dem":62,
    "gn:feature_class":"P",
    "gn:feature_code":"PPL",
    "gn:name":"Goth Nazir Ahmed Hamlani",
    "gn:population":0,
    "gn:timezone":"Asia/Karachi",
    "iso:country":"PK",
    "wof:name":"Goth Nazir Ahmed Hamlani",
    "wof:placetype":"locality"
},
  "geometry": {"coordinates":[67.54125000000001,27.53718],"type":"Point"}
}