{
  "type": "Feature",
  "properties": {
    "gn:admin1_code":"4.0",
    "gn:asciiname":"Chhappar",
    "gn:country_code":"PK",
    "gn:dem":473,
    "gn:feature_class":"P",
    "gn:feature_code":"PPL",
    "gn:name":"Chhappar",
    "gn:population":0,
    "gn:timezone":"Asia/Karachi",
    "iso:country":"PK",
    "name:und_x_variant":[
        "Chhaper",
        "Chhappar"
    ],
    "wof:name":"Chhappar",
    "wof:placetype":"locality"
},
  "geometry": {"coordinates":[73.03863,33.40854],"type":"Point"}
}