{
  "type": "Feature",
  "properties": {
    "gn:admin1_code":"4",
    "gn:asciiname":"Nawan Kot",
    "gn:country_code":"PK",
    "gn:dem":231,
    "gn:feature_class":"P",
    "gn:feature_code":"PPL",
    "gn:name":"Nawan Kot",
    "gn:population":0,
    "gn:timezone":"Asia/Karachi",
    "iso:country":"PK",
    "name:und_x_variant":[
        "Naw\u0101nkot"
    ],
    "wof:name":"Nawan Kot",
    "wof:placetype":"locality"
},
  "geometry": {"coordinates":[74.40544,32.23988],"type":"Point"}
}