{
  "type": "Feature",
  "properties": {
    "gn:admin1_code":"5.0",
    "gn:asciiname":"Nabban Bhambhro",
    "gn:country_code":"PK",
    "gn:dem":61,
    "gn:feature_class":"P",
    "gn:feature_code":"PPL",
    "gn:name":"Nabban Bhambhro",
    "gn:population":0,
    "gn:timezone":"Asia/Karachi",
    "iso:country":"PK",
    "wof:name":"Nabban Bhambhro",
    "wof:placetype":"locality"
},
  "geometry": {"coordinates":[69.14723000000001,27.26272],"type":"Point"}
}