{
  "type": "Feature",
  "properties": {
    "gn:admin1_code":"04",
    "gn:asciiname":"Samthi",
    "gn:country_code":"PK",
    "gn:dem":750,
    "gn:feature_class":"P",
    "gn:feature_code":"PPL",
    "gn:name":"Samthi",
    "gn:population":0,
    "gn:timezone":"Asia/Karachi",
    "iso:country":"PK",
    "wof:name":"Samthi",
    "wof:placetype":"locality"
},
  "geometry": {"coordinates":[73.45696,33.49669],"type":"Point"}
}