{
  "type": "Feature",
  "properties": {
    "gn:admin1_code":"2.0",
    "gn:asciiname":"Mitha",
    "gn:country_code":"PK",
    "gn:dem":914,
    "gn:feature_class":"P",
    "gn:feature_code":"PPL",
    "gn:name":"Mitha",
    "gn:population":0,
    "gn:timezone":"Asia/Karachi",
    "iso:country":"PK",
    "wof:name":"Mitha",
    "wof:placetype":"locality"
},
  "geometry": {"coordinates":[69.38157,29.21868],"type":"Point"}
}