{
  "type": "Feature",
  "properties": {
    "gn:admin1_code":"7.0",
    "gn:asciiname":"Shu Das",
    "gn:country_code":"PK",
    "gn:dem":3199,
    "gn:feature_class":"P",
    "gn:feature_code":"PPL",
    "gn:name":"Shu Das",
    "gn:population":0,
    "gn:timezone":"Asia/Karachi",
    "iso:country":"PK",
    "wof:name":"Shu Das",
    "wof:placetype":"locality"
},
  "geometry": {"coordinates":[74.67725,35.00235],"type":"Point"}
}