{
  "type": "Feature",
  "properties": {
    "gn:admin1_code":"04",
    "gn:asciiname":"Mari Wasran",
    "gn:country_code":"PK",
    "gn:dem":137,
    "gn:feature_class":"P",
    "gn:feature_code":"PPL",
    "gn:name":"Mari Wasran",
    "gn:population":0,
    "gn:timezone":"Asia/Karachi",
    "iso:country":"PK",
    "name:und_x_variant":[
        "M\u0101ri Wasin\u0101nw\u0101li",
        "M\u0101ri Was\u012br\u0101nw\u0101li",
        "Mari Wasran"
    ],
    "wof:name":"Mari Wasran",
    "wof:placetype":"locality"
},
  "geometry": {"coordinates":[72.27798,30.06936],"type":"Point"}
}