{
  "type": "Feature",
  "properties": {
    "gn:admin1_code":"04",
    "gn:asciiname":"Basti Rahman",
    "gn:country_code":"PK",
    "gn:dem":137,
    "gn:feature_class":"P",
    "gn:feature_code":"PPL",
    "gn:name":"Basti Rahman",
    "gn:population":0,
    "gn:timezone":"Asia/Karachi",
    "iso:country":"PK",
    "name:eng_x_preferred":[
        "R\u0101man"
    ],
    "name:eng_x_variant":[
        "Ranman"
    ],
    "name:und_x_variant":[
        "Basti Rahman"
    ],
    "wof:name":"Basti Rahman",
    "wof:placetype":"locality"
},
  "geometry": {"coordinates":[70.70591999999998,30.37737000000001],"type":"Point"}
}