{
  "type": "Feature",
  "properties": {
    "gn:admin1_code":"5",
    "gn:asciiname":"Goth Miano",
    "gn:country_code":"PK",
    "gn:dem":57,
    "gn:feature_class":"P",
    "gn:feature_code":"PPL",
    "gn:name":"Goth Miano",
    "gn:population":0,
    "gn:timezone":"Asia/Karachi",
    "iso:country":"PK",
    "name:und_x_variant":[
        "Ra\u012bsw\u0101ro Kh\u016bh",
        "Ra\u012bsw\u0101ra Kh\u016bh",
        "Goth Miano"
    ],
    "wof:name":"Goth Miano",
    "wof:placetype":"locality"
},
  "geometry": {"coordinates":[68.56413000000001,27.5047],"type":"Point"}
}