{
  "type": "Feature",
  "properties": {
    "gn:admin1_code":"2.0",
    "gn:asciiname":"Kili Ali Muhammad",
    "gn:country_code":"PK",
    "gn:dem":1282,
    "gn:feature_class":"P",
    "gn:feature_code":"PPL",
    "gn:name":"Kili Ali Muhammad",
    "gn:population":0,
    "gn:timezone":"Asia/Karachi",
    "iso:country":"PK",
    "wof:name":"Kili Ali Muhammad",
    "wof:placetype":"locality"
},
  "geometry": {"coordinates":[66.47835000000001,27.34921],"type":"Point"}
}