{
  "type": "Feature",
  "properties": {
    "gn:admin1_code":"03",
    "gn:asciiname":"Kuria",
    "gn:country_code":"PK",
    "gn:dem":675,
    "gn:feature_class":"P",
    "gn:feature_code":"PPL",
    "gn:name":"Kuria",
    "gn:population":0,
    "gn:timezone":"Asia/Karachi",
    "iso:country":"PK",
    "name:ceb_x_preferred":[
        "Kuria"
    ],
    "name:deu_x_preferred":[
        "Kuria"
    ],
    "name:fra_x_preferred":[
        "Kuria"
    ],
    "name:nld_x_preferred":[
        "Kuria"
    ],
    "name:pol_x_preferred":[
        "Kuria"
    ],
    "name:por_x_preferred":[
        "Kuria"
    ],
    "name:swe_x_preferred":[
        "Kuria"
    ],
    "name:und_x_variant":[
        "Korea"
    ],
    "wof:name":"Kuria",
    "wof:placetype":"locality"
},
  "geometry": {"coordinates":[72.6172,34.41226],"type":"Point"}
}