{
  "type": "Feature",
  "properties": {
    "gn:admin1_code":"4",
    "gn:asciiname":"Mohra Mothan",
    "gn:country_code":"PK",
    "gn:dem":410,
    "gn:feature_class":"P",
    "gn:feature_code":"PPL",
    "gn:name":"Mohra Mothan",
    "gn:population":0,
    "gn:timezone":"Asia/Karachi",
    "iso:country":"PK",
    "name:und_x_variant":[
        "Mohri Mothan"
    ],
    "wof:name":"Mohra Mothan",
    "wof:placetype":"locality"
},
  "geometry": {"coordinates":[73.28870999999999,32.86057],"type":"Point"}
}