{
  "type": "Feature",
  "properties": {
    "gn:admin1_code":"4.0",
    "gn:asciiname":"Ihata Kanjriwala",
    "gn:country_code":"PK",
    "gn:dem":176,
    "gn:feature_class":"P",
    "gn:feature_code":"PPL",
    "gn:name":"Ihata Kanjriwala",
    "gn:population":0,
    "gn:timezone":"Asia/Karachi",
    "iso:country":"PK",
    "name:und_x_variant":[
        "Kaniriw\u0101la Ah\u0101ta"
    ],
    "wof:name":"Ihata Kanjriwala",
    "wof:placetype":"locality"
},
  "geometry": {"coordinates":[73.36740999999998,30.8877],"type":"Point"}
}