{
  "type": "Feature",
  "properties": {
    "gn:admin1_code":"4",
    "gn:asciiname":"Chambal",
    "gn:country_code":"PK",
    "gn:dem":456,
    "gn:feature_class":"P",
    "gn:feature_code":"PPL",
    "gn:name":"Chambal",
    "gn:population":0,
    "gn:timezone":"Asia/Karachi",
    "iso:country":"PK",
    "name:ceb_x_preferred":[
        "Chambal"
    ],
    "name:nld_x_preferred":[
        "Chambal"
    ],
    "name:swe_x_preferred":[
        "Chambal"
    ],
    "wof:name":"Chambal",
    "wof:placetype":"locality"
},
  "geometry": {"coordinates":[73.41566,32.70776],"type":"Point"}
}