{
  "type": "Feature",
  "properties": {
    "gn:admin1_code":"4",
    "gn:asciiname":"Chambal",
    "gn:country_code":"PK",
    "gn:dem":456,
    "gn:feature_class":"P",
    "gn:feature_code":"PPL",
    "gn:name":"Chambal",
    "gn:population":0,
    "gn:timezone":"Asia/Karachi",
    "iso:country":"PK",
    "name:ara_x_preferred":[
        "\u062a\u0634\u0627\u0645\u0628\u0627\u0644"
    ],
    "name:ceb_x_preferred":[
        "Chambal"
    ],
    "name:ell_x_preferred":[
        "\u03a4\u03c3\u03b1\u03bc\u03c0\u03ac\u03bb"
    ],
    "name:heb_x_preferred":[
        "\u05e6'\u05d0\u05de\u05d1\u05d0\u05dc"
    ],
    "name:hun_x_preferred":[
        "Chambal"
    ],
    "name:ind_x_preferred":[
        "Chambal"
    ],
    "name:ita_x_preferred":[
        "Chambal"
    ],
    "name:kor_x_preferred":[
        "\ucc38\ubc1c"
    ],
    "name:nld_x_preferred":[
        "Chambal"
    ],
    "name:por_x_preferred":[
        "Chambal"
    ],
    "name:swe_x_preferred":[
        "Chambal"
    ],
    "name:tur_x_preferred":[
        "Chambal"
    ],
    "name:ukr_x_preferred":[
        "\u0427\u0430\u043c\u0431\u0430\u043b"
    ],
    "name:vie_x_preferred":[
        "S\u00f4ng Chambal"
    ],
    "wof:name":"Chambal",
    "wof:placetype":"locality"
},
  "geometry": {"coordinates":[73.41566,32.70776],"type":"Point"}
}