{
  "type": "Feature",
  "properties": {
    "gn:admin1_code":"6",
    "gn:asciiname":"Suman",
    "gn:country_code":"PK",
    "gn:dem":1926,
    "gn:feature_class":"P",
    "gn:feature_code":"PPL",
    "gn:name":"Suman",
    "gn:population":0,
    "gn:timezone":"Asia/Karachi",
    "iso:country":"PK",
    "name:deu_x_preferred":[
        "Suman"
    ],
    "name:ukr_x_preferred":[
        "\u0421\u0443\u043c\u0430\u043d"
    ],
    "wof:name":"Suman",
    "wof:placetype":"locality"
},
  "geometry": {"coordinates":[74.25694,34.81667],"type":"Point"}
}