{
  "type": "Feature",
  "properties": {
    "gn:admin1_code":"4.0",
    "gn:asciiname":"Chah Tahliwala",
    "gn:country_code":"PK",
    "gn:dem":154,
    "gn:feature_class":"P",
    "gn:feature_code":"PPL",
    "gn:name":"Chah Tahliwala",
    "gn:population":0,
    "gn:timezone":"Asia/Karachi",
    "iso:country":"PK",
    "name:und_x_variant":[
        "Tahliw\u0101la"
    ],
    "wof:name":"Chah Tahliwala",
    "wof:placetype":"locality"
},
  "geometry": {"coordinates":[72.36308000000002,31.09782],"type":"Point"}
}