{
  "type": "Feature",
  "properties": {
    "gn:admin1_code":"01",
    "gn:asciiname":"Dando Kor",
    "gn:country_code":"PK",
    "gn:dem":668,
    "gn:feature_class":"P",
    "gn:feature_code":"PPL",
    "gn:name":"Dando Kor",
    "gn:population":0,
    "gn:timezone":"Asia/Karachi",
    "iso:country":"PK",
    "name:und_x_variant":[
        "Dand Nawar",
        "Danoo Nawar"
    ],
    "wof:name":"Dando Kor",
    "wof:placetype":"locality"
},
  "geometry": {"coordinates":[71.4115,34.59031],"type":"Point"}
}