{
  "type": "Feature",
  "properties": {
    "gn:admin1_code":"4.0",
    "gn:asciiname":"Kari",
    "gn:country_code":"PK",
    "gn:dem":522,
    "gn:feature_class":"P",
    "gn:feature_code":"PPL",
    "gn:name":"Kari",
    "gn:population":0,
    "gn:timezone":"Asia/Karachi",
    "iso:country":"PK",
    "wof:name":"Kari",
    "wof:placetype":"locality"
},
  "geometry": {"coordinates":[73.20309,33.33635],"type":"Point"}
}