{
  "type": "Feature",
  "properties": {
    "gn:admin1_code":"4",
    "gn:asciiname":"Galiakh",
    "gn:country_code":"PK",
    "gn:dem":736,
    "gn:feature_class":"P",
    "gn:feature_code":"PPL",
    "gn:name":"Galiakh",
    "gn:population":0,
    "gn:timezone":"Asia/Karachi",
    "iso:country":"PK",
    "name:und_x_variant":[
        "Gailak",
        "Galiakh"
    ],
    "wof:name":"Galiakh",
    "wof:placetype":"locality"
},
  "geometry": {"coordinates":[72.07840999999998,32.45604],"type":"Point"}
}