{
  "type": "Feature",
  "properties": {
    "gn:admin1_code":"3",
    "gn:asciiname":"Lamai Larai",
    "gn:country_code":"PK",
    "gn:dem":2082,
    "gn:feature_class":"P",
    "gn:feature_code":"PPL",
    "gn:name":"Lamai Larai",
    "gn:population":0,
    "gn:timezone":"Asia/Karachi",
    "iso:country":"PK",
    "wof:name":"Lamai Larai",
    "wof:placetype":"locality"
},
  "geometry": {"coordinates":[72.58266,34.86088],"type":"Point"}
}