{
  "type": "Feature",
  "properties": {
    "gn:admin1_code":"5.0",
    "gn:asciiname":"Goth Ghulam Haidar Khasu",
    "gn:country_code":"PK",
    "gn:dem":63,
    "gn:feature_class":"P",
    "gn:feature_code":"PPL",
    "gn:name":"Goth Ghulam Haidar Khasu",
    "gn:population":0,
    "gn:timezone":"Asia/Karachi",
    "iso:country":"PK",
    "wof:name":"Goth Ghulam Haidar Khasu",
    "wof:placetype":"locality"
},
  "geometry": {"coordinates":[69.00409999999999,27.68499000000001],"type":"Point"}
}