{
  "type": "Feature",
  "properties": {
    "gn:admin1_code":"4.0",
    "gn:asciiname":"Balkasar",
    "gn:country_code":"PK",
    "gn:dem":528,
    "gn:feature_class":"P",
    "gn:feature_code":"PPL",
    "gn:name":"Balkasar",
    "gn:population":0,
    "gn:timezone":"Asia/Karachi",
    "iso:country":"PK",
    "name:fas_x_preferred":[
        "\u0628\u0644\u06a9\u0633\u0631"
    ],
    "name:hin_x_preferred":[
        "\u092c\u0932\u0915\u0938\u094d\u0938\u0930"
    ],
    "name:und_x_variant":[
        "Balkassar"
    ],
    "name:urd_x_preferred":[
        "\u0628\u0644\u06a9\u0633\u0631"
    ],
    "wof:name":"Balkasar",
    "wof:placetype":"locality"
},
  "geometry": {"coordinates":[72.64439,32.93737],"type":"Point"}
}