{
  "type": "Feature",
  "properties": {
    "gn:admin1_code":"4.0",
    "gn:asciiname":"Balkasar",
    "gn:country_code":"PK",
    "gn:dem":528,
    "gn:feature_class":"P",
    "gn:feature_code":"PPL",
    "gn:name":"Balkasar",
    "gn:population":0,
    "gn:timezone":"Asia/Karachi",
    "iso:country":"PK",
    "name:und_x_variant":[
        "Balkassar"
    ],
    "wof:name":"Balkasar",
    "wof:placetype":"locality"
},
  "geometry": {"coordinates":[72.64439,32.93737],"type":"Point"}
}