{
  "type": "Feature",
  "properties": {
    "gn:admin1_code":"1.0",
    "gn:asciiname":"Gaz Baba China",
    "gn:country_code":"PK",
    "gn:dem":1173,
    "gn:feature_class":"P",
    "gn:feature_code":"PPL",
    "gn:name":"Gaz Baba China",
    "gn:population":0,
    "gn:timezone":"Asia/Karachi",
    "iso:country":"PK",
    "name:und_x_variant":[
        "Gazb\u0101ba Ch\u012bna"
    ],
    "wof:name":"Gaz Baba China",
    "wof:placetype":"locality"
},
  "geometry": {"coordinates":[70.34040999999999,32.62857],"type":"Point"}
}