{
  "type": "Feature",
  "properties": {
    "gn:admin1_code":"6",
    "gn:asciiname":"Seps",
    "gn:country_code":"PK",
    "gn:dem":291,
    "gn:feature_class":"P",
    "gn:feature_code":"PPL",
    "gn:name":"Seps",
    "gn:population":0,
    "gn:timezone":"Asia/Karachi",
    "iso:country":"PK",
    "name:und_x_variant":[
        "Sens",
        "Seps"
    ],
    "wof:name":"Seps",
    "wof:placetype":"locality"
},
  "geometry": {"coordinates":[73.85209999999999,33.09036],"type":"Point"}
}