{
  "type": "Feature",
  "properties": {
    "gn:admin1_code":"2",
    "gn:asciiname":"Akhtar Shah",
    "gn:country_code":"PK",
    "gn:dem":945,
    "gn:feature_class":"P",
    "gn:feature_code":"PPL",
    "gn:name":"Akhtar Shah",
    "gn:population":0,
    "gn:timezone":"Asia/Karachi",
    "iso:country":"PK",
    "name:eng_x_preferred":[
        "Akhtar Shah"
    ],
    "name:fas_x_preferred":[
        "\u0627\u062e\u062a\u0631\u0634\u0627\u0647"
    ],
    "wof:name":"Akhtar Shah",
    "wof:placetype":"locality"
},
  "geometry": {"coordinates":[68.97001,30.01787],"type":"Point"}
}