{
  "type": "Feature",
  "properties": {
    "gn:admin1_code":"3",
    "gn:asciiname":"Maira Qazian",
    "gn:country_code":"PK",
    "gn:dem":878,
    "gn:feature_class":"P",
    "gn:feature_code":"PPL",
    "gn:name":"Maira Qazian",
    "gn:population":0,
    "gn:timezone":"Asia/Karachi",
    "iso:country":"PK",
    "wof:name":"Maira Qazian",
    "wof:placetype":"locality"
},
  "geometry": {"coordinates":[73.14211999999998,34.00595],"type":"Point"}
}