{
  "type": "Feature",
  "properties": {
    "gn:admin1_code":"2.0",
    "gn:asciiname":"Sol Chakar",
    "gn:country_code":"PK",
    "gn:dem":1332,
    "gn:feature_class":"P",
    "gn:feature_code":"PPL",
    "gn:name":"Sol Chakar",
    "gn:population":0,
    "gn:timezone":"Asia/Karachi",
    "iso:country":"PK",
    "name:und_x_variant":[
        "Shahr Ch\u0101kar"
    ],
    "wof:name":"Sol Chakar",
    "wof:placetype":"locality"
},
  "geometry": {"coordinates":[65.77424999999999,28.01692],"type":"Point"}
}