{
  "type": "Feature",
  "properties": {
    "gn:admin1_code":"2.0",
    "gn:asciiname":"Goth Ghulam Rasul",
    "gn:country_code":"PK",
    "gn:dem":298,
    "gn:feature_class":"P",
    "gn:feature_code":"PPL",
    "gn:name":"Goth Ghulam Rasul",
    "gn:population":0,
    "gn:timezone":"Asia/Karachi",
    "iso:country":"PK",
    "wof:name":"Goth Ghulam Rasul",
    "wof:placetype":"locality"
},
  "geometry": {"coordinates":[67.1118,26.21847],"type":"Point"}
}