{
  "type": "Feature",
  "properties": {
    "gn:admin1_code":"2.0",
    "gn:asciiname":"Goth Abdul Hamid",
    "gn:country_code":"PK",
    "gn:dem":61,
    "gn:feature_class":"P",
    "gn:feature_code":"PPL",
    "gn:name":"Goth Abdul Hamid",
    "gn:population":0,
    "gn:timezone":"Asia/Karachi",
    "iso:country":"PK",
    "name:und_x_variant":[
        "Abdul Ham\u012bd"
    ],
    "wof:name":"Goth Abdul Hamid",
    "wof:placetype":"locality"
},
  "geometry": {"coordinates":[67.91086,28.35917],"type":"Point"}
}