{
  "type": "Feature",
  "properties": {
    "gn:admin1_code":"4",
    "gn:asciiname":"Shahbil Shah ka Khu",
    "gn:country_code":"PK",
    "gn:dem":178,
    "gn:feature_class":"P",
    "gn:feature_code":"PPL",
    "gn:name":"Shahbil Shah ka Khu",
    "gn:population":0,
    "gn:timezone":"Asia/Karachi",
    "iso:country":"PK",
    "wof:name":"Shahbil Shah ka Khu",
    "wof:placetype":"locality"
},
  "geometry": {"coordinates":[72.80608000000002,31.75834],"type":"Point"}
}