{
  "type": "Feature",
  "properties": {
    "gn:admin1_code":"3",
    "gn:asciiname":"Phuldar",
    "gn:country_code":"PK",
    "gn:dem":749,
    "gn:feature_class":"P",
    "gn:feature_code":"PPL",
    "gn:name":"Phuldar",
    "gn:population":0,
    "gn:timezone":"Asia/Karachi",
    "iso:country":"PK",
    "name:und_x_variant":[
        "Phuldh\u0101r"
    ],
    "wof:name":"Phuldar",
    "wof:placetype":"locality"
},
  "geometry": {"coordinates":[72.84824999999999,34.40687],"type":"Point"}
}