{
  "type": "Feature",
  "properties": {
    "gn:admin1_code":"2.0",
    "gn:asciiname":"Chashma Dolai",
    "gn:country_code":"PK",
    "gn:dem":1626,
    "gn:feature_class":"P",
    "gn:feature_code":"PPL",
    "gn:name":"Chashma Dolai",
    "gn:population":0,
    "gn:timezone":"Asia/Karachi",
    "iso:country":"PK",
    "name:und_x_variant":[
        "Dolai",
        "Dulai",
        "Chashma Dolai"
    ],
    "wof:name":"Chashma Dolai",
    "wof:placetype":"locality"
},
  "geometry": {"coordinates":[66.71568000000001,30.06537],"type":"Point"}
}