{
  "type": "Feature",
  "properties": {
    "gn:admin1_code":"4",
    "gn:asciiname":"Baulian",
    "gn:country_code":"PK",
    "gn:dem":456,
    "gn:feature_class":"P",
    "gn:feature_code":"PPL",
    "gn:name":"Baulian",
    "gn:population":0,
    "gn:timezone":"Asia/Karachi",
    "iso:country":"PK",
    "name:und_x_variant":[
        "B\u0101wali\u0101l"
    ],
    "wof:name":"Baulian",
    "wof:placetype":"locality"
},
  "geometry": {"coordinates":[73.2938,33.22419],"type":"Point"}
}