{
  "type": "Feature",
  "properties": {
    "gn:admin1_code":"04",
    "gn:asciiname":"Rajewala",
    "gn:country_code":"PK",
    "gn:dem":224,
    "gn:feature_class":"P",
    "gn:feature_code":"PPL",
    "gn:name":"Rajewala",
    "gn:population":0,
    "gn:timezone":"Asia/Karachi",
    "iso:country":"PK",
    "name:und_x_variant":[
        "Ragewala",
        "Rajewala"
    ],
    "wof:name":"Rajewala",
    "wof:placetype":"locality"
},
  "geometry": {"coordinates":[74.3312,32.04855],"type":"Point"}
}