{
  "type": "Feature",
  "properties": {
    "gn:admin1_code":"4.0",
    "gn:asciiname":"Dhok Sultan",
    "gn:country_code":"PK",
    "gn:dem":361,
    "gn:feature_class":"P",
    "gn:feature_code":"PPL",
    "gn:name":"Dhok Sultan",
    "gn:population":0,
    "gn:timezone":"Asia/Karachi",
    "iso:country":"PK",
    "name:und_x_variant":[
        "Sult\u0101n Ki Dhok"
    ],
    "wof:name":"Dhok Sultan",
    "wof:placetype":"locality"
},
  "geometry": {"coordinates":[72.16546,33.13972],"type":"Point"}
}