{
  "type": "Feature",
  "properties": {
    "gn:admin1_code":"4",
    "gn:asciiname":"Fateh Khan",
    "gn:country_code":"PK",
    "gn:dem":823,
    "gn:feature_class":"P",
    "gn:feature_code":"PPL",
    "gn:name":"Fateh Khan",
    "gn:population":0,
    "gn:timezone":"Asia/Karachi",
    "iso:country":"PK",
    "name:fas_x_preferred":[
        "\u0641\u0627\u062a\u062d\u200c\u062e\u0627\u0646"
    ],
    "name:hin_x_preferred":[
        "\u092b\u093c\u0924\u0939 \u0916\u093e\u0928"
    ],
    "name:und_x_variant":[
        "Fateh Khanw\u0101li"
    ],
    "name:urd_x_preferred":[
        "\u0641\u0627\u062a\u062d \u062e\u0627\u0646"
    ],
    "wof:name":"Fateh Khan",
    "wof:placetype":"locality"
},
  "geometry": {"coordinates":[72.23815,32.63197],"type":"Point"}
}