{
  "type": "Feature",
  "properties": {
    "gn:admin1_code":"3.0",
    "gn:asciiname":"New Malang Adda",
    "gn:country_code":"PK",
    "gn:dem":271,
    "gn:feature_class":"P",
    "gn:feature_code":"PPL",
    "gn:name":"New Malang Adda",
    "gn:population":0,
    "gn:timezone":"Asia/Karachi",
    "iso:country":"PK",
    "wof:name":"New Malang Adda",
    "wof:placetype":"locality"
},
  "geometry": {"coordinates":[70.77539,32.67757],"type":"Point"}
}