{
  "type": "Feature",
  "properties": {
    "gn:admin1_code":"4.0",
    "gn:asciiname":"Kakrala Kalan",
    "gn:country_code":"PK",
    "gn:dem":398,
    "gn:feature_class":"P",
    "gn:feature_code":"PPL",
    "gn:name":"Kakrala Kalan",
    "gn:population":0,
    "gn:timezone":"Asia/Karachi",
    "iso:country":"PK",
    "name:und_x_variant":[
        "Hardo Kakrala",
        "Kakr\u0101la",
        "Kakrala Kalan"
    ],
    "wof:name":"Kakrala Kalan",
    "wof:placetype":"locality"
},
  "geometry": {"coordinates":[73.36294000000002,32.86964],"type":"Point"}
}