{
  "type": "Feature",
  "properties": {
    "gn:admin1_code":"3",
    "gn:asciiname":"Utli Dali",
    "gn:country_code":"PK",
    "gn:dem":2453,
    "gn:feature_class":"P",
    "gn:feature_code":"PPL",
    "gn:name":"Utli Dali",
    "gn:population":0,
    "gn:timezone":"Asia/Karachi",
    "iso:country":"PK",
    "name:und_x_variant":[
        "Dali"
    ],
    "wof:name":"Utli Dali",
    "wof:placetype":"locality"
},
  "geometry": {"coordinates":[73.47909,34.69244],"type":"Point"}
}