{
  "type": "Feature",
  "properties": {
    "iso:country":"PK",
    "name:unk_x_variant":[
        "Kh\u0101npur"
    ],
    "qs:gn_country":"PK",
    "qs:gn_fcode":"PPL",
    "qs:gn_pop":22273,
    "qs:name":"Khanpoor",
    "qs:name_adm0":"Pakistan",
    "qs:name_adm1":"Sindh",
    "qs:photos":0,
    "qs:photos_1k":0,
    "qs:photos_9k":0,
    "qs:photos_9r":0,
    "qs:photos_all":0,
    "qs:photos_sr":0,
    "qs:placetype":"Town",
    "qs:pop_sr":"7",
    "qs:woe_adm0":23424922,
    "wof:name":"Khanpoor",
    "wof:placetype":"locality",
    "wof:population":22273
},
  "geometry": {"coordinates":[69.41373,27.84358],"type":"Point"}
}