{
  "type": "Feature",
  "properties": {
    "gn:admin1_code":"1.0",
    "gn:asciiname":"Kuz Chamarkand",
    "gn:country_code":"PK",
    "gn:dem":1093,
    "gn:feature_class":"P",
    "gn:feature_code":"PPL",
    "gn:name":"Kuz Chamarkand",
    "gn:population":0,
    "gn:timezone":"Asia/Karachi",
    "iso:country":"PK",
    "name:und_x_variant":[
        "K\u016bz Chamarkand",
        "Chamarkand Farooq Killi"
    ],
    "wof:name":"Kuz Chamarkand",
    "wof:placetype":"locality"
},
  "geometry": {"coordinates":[71.22153,34.68997],"type":"Point"}
}