{
  "type": "Feature",
  "properties": {
    "gn:admin1_code":"2.0",
    "gn:asciiname":"Takai",
    "gn:country_code":"PK",
    "gn:dem":1255,
    "gn:feature_class":"P",
    "gn:feature_code":"PPL",
    "gn:name":"Takai",
    "gn:population":0,
    "gn:timezone":"Asia/Karachi",
    "iso:country":"PK",
    "name:ceb_x_preferred":[
        "Takai"
    ],
    "name:fra_x_preferred":[
        "Takai"
    ],
    "name:hau_x_preferred":[
        "Takai"
    ],
    "name:ita_x_preferred":[
        "Takai"
    ],
    "name:spa_x_preferred":[
        "Takai"
    ],
    "wof:name":"Takai",
    "wof:placetype":"locality"
},
  "geometry": {"coordinates":[69.90172,31.14339],"type":"Point"}
}