{
  "type": "Feature",
  "properties": {
    "gn:admin1_code":"4.0",
    "gn:asciiname":"Gangiah Kachhi",
    "gn:country_code":"PK",
    "gn:dem":536,
    "gn:feature_class":"P",
    "gn:feature_code":"PPL",
    "gn:name":"Gangiah Kachhi",
    "gn:population":0,
    "gn:timezone":"Asia/Karachi",
    "iso:country":"PK",
    "name:und_x_variant":[
        "Gangl\u0101h Kachhi"
    ],
    "wof:name":"Gangiah Kachhi",
    "wof:placetype":"locality"
},
  "geometry": {"coordinates":[70.36442,30.74649],"type":"Point"}
}