{
  "type": "Feature",
  "properties": {
    "gn:admin1_code":"5",
    "gn:asciiname":"Goth Sharifabad",
    "gn:country_code":"PK",
    "gn:dem":18,
    "gn:feature_class":"P",
    "gn:feature_code":"PPL",
    "gn:name":"Goth Sharifabad",
    "gn:population":0,
    "gn:timezone":"Asia/Karachi",
    "iso:country":"PK",
    "name:und_x_variant":[
        "Shar\u012bf\u0101b\u0101d"
    ],
    "wof:name":"Goth Sharifabad",
    "wof:placetype":"locality"
},
  "geometry": {"coordinates":[68.87854,25.28055],"type":"Point"}
}