{
  "type": "Feature",
  "properties": {
    "gn:admin1_code":"4.0",
    "gn:asciiname":"Sil Khetar",
    "gn:country_code":"PK",
    "gn:dem":689,
    "gn:feature_class":"P",
    "gn:feature_code":"PPL",
    "gn:name":"Sil Khetar",
    "gn:population":0,
    "gn:timezone":"Asia/Karachi",
    "iso:country":"PK",
    "name:eng_x_preferred":[
        "S\u0101l Khetar"
    ],
    "wof:name":"Sil Khetar",
    "wof:placetype":"locality"
},
  "geometry": {"coordinates":[73.27418,33.78503],"type":"Point"}
}