{
  "type": "Feature",
  "properties": {
    "gn:admin1_code":"2.0",
    "gn:asciiname":"Muhammad Siddique Lohari",
    "gn:country_code":"PK",
    "gn:dem":725,
    "gn:feature_class":"P",
    "gn:feature_code":"PPL",
    "gn:name":"Muhammad Siddique Lohari",
    "gn:population":0,
    "gn:timezone":"Asia/Karachi",
    "iso:country":"PK",
    "wof:name":"Muhammad Siddique Lohari",
    "wof:placetype":"locality"
},
  "geometry": {"coordinates":[66.85285,26.68466],"type":"Point"}
}