{
  "type": "Feature",
  "properties": {
    "gn:admin1_code":"3.0",
    "gn:asciiname":"Gariala",
    "gn:country_code":"PK",
    "gn:dem":340,
    "gn:feature_class":"P",
    "gn:feature_code":"PPL",
    "gn:name":"Gariala",
    "gn:population":0,
    "gn:timezone":"Asia/Karachi",
    "iso:country":"PK",
    "name:eng_x_preferred":[
        "Gariala"
    ],
    "name:und_x_variant":[
        "Giryala"
    ],
    "wof:name":"Gariala",
    "wof:placetype":"locality"
},
  "geometry": {"coordinates":[72.21958000000002,34.26851],"type":"Point"}
}