{
  "type": "Feature",
  "properties": {
    "gn:admin1_code":"4.0",
    "gn:asciiname":"Dhok Fateh Sher",
    "gn:country_code":"PK",
    "gn:dem":393,
    "gn:feature_class":"P",
    "gn:feature_code":"PPL",
    "gn:name":"Dhok Fateh Sher",
    "gn:population":0,
    "gn:timezone":"Asia/Karachi",
    "iso:country":"PK",
    "wof:name":"Dhok Fateh Sher",
    "wof:placetype":"locality"
},
  "geometry": {"coordinates":[71.93984,33.29594],"type":"Point"}
}