{
  "type": "Feature",
  "properties": {
    "gn:admin1_code":"6",
    "gn:asciiname":"Sangar Seri",
    "gn:country_code":"PK",
    "gn:dem":2652,
    "gn:feature_class":"P",
    "gn:feature_code":"PPL",
    "gn:name":"Sangar Seri",
    "gn:population":0,
    "gn:timezone":"Asia/Karachi",
    "iso:country":"PK",
    "wof:name":"Sangar Seri",
    "wof:placetype":"locality"
},
  "geometry": {"coordinates":[74.26623000000002,34.77114],"type":"Point"}
}