{
  "type": "Feature",
  "properties": {
    "gn:admin1_code":"3.0",
    "gn:asciiname":"Abezari",
    "gn:country_code":"PK",
    "gn:dem":375,
    "gn:feature_class":"P",
    "gn:feature_code":"PPL",
    "gn:name":"Abezari",
    "gn:population":0,
    "gn:timezone":"Asia/Karachi",
    "iso:country":"PK",
    "wof:name":"Abezari",
    "wof:placetype":"locality"
},
  "geometry": {"coordinates":[70.57726,32.9671],"type":"Point"}
}