{
  "type": "Feature",
  "properties": {
    "gn:admin1_code":"7.0",
    "gn:asciiname":"Bulandi",
    "gn:country_code":"PK",
    "gn:dem":3015,
    "gn:feature_class":"P",
    "gn:feature_code":"PPL",
    "gn:name":"Bulandi",
    "gn:population":0,
    "gn:timezone":"Asia/Karachi",
    "iso:country":"PK",
    "wof:name":"Bulandi",
    "wof:placetype":"locality"
},
  "geometry": {"coordinates":[73.96723,36.50582],"type":"Point"}
}