{
  "type": "Feature",
  "properties": {
    "gn:admin1_code":"4.0",
    "gn:asciiname":"Utra Kalan",
    "gn:country_code":"PK",
    "gn:dem":206,
    "gn:feature_class":"P",
    "gn:feature_code":"PPL",
    "gn:name":"Utra Kalan",
    "gn:population":0,
    "gn:timezone":"Asia/Karachi",
    "iso:country":"PK",
    "wof:name":"Utra Kalan",
    "wof:placetype":"locality"
},
  "geometry": {"coordinates":[71.47055999999998,32.79028],"type":"Point"}
}