{
  "type": "Feature",
  "properties": {
    "gn:admin1_code":"4.0",
    "gn:asciiname":"Kala Khotai",
    "gn:country_code":"PK",
    "gn:dem":222,
    "gn:feature_class":"P",
    "gn:feature_code":"PPL",
    "gn:name":"K\u0101la Khot\u0101i",
    "gn:population":0,
    "gn:timezone":"Asia/Karachi",
    "iso:country":"PK",
    "wof:name":"Kala Khotai",
    "wof:placetype":"locality"
},
  "geometry": {"coordinates":[74.50185,31.8237],"type":"Point"}
}