{
  "type": "Feature",
  "properties": {
    "gn:admin1_code":"6.0",
    "gn:asciiname":"Dolman",
    "gn:country_code":"PK",
    "gn:dem":1411,
    "gn:feature_class":"P",
    "gn:feature_code":"PPL",
    "gn:name":"Dolman",
    "gn:population":0,
    "gn:timezone":"Asia/Karachi",
    "iso:country":"PK",
    "name:cat_x_preferred":[
        "D\u00f2lman"
    ],
    "name:deu_x_preferred":[
        "Dolman"
    ],
    "name:fin_x_preferred":[
        "Dolmaani"
    ],
    "name:fra_x_preferred":[
        "Dolman"
    ],
    "name:hun_x_preferred":[
        "Dolm\u00e1ny"
    ],
    "name:ido_x_preferred":[
        "Dolmano"
    ],
    "name:nor_x_preferred":[
        "Dolman"
    ],
    "name:pol_x_preferred":[
        "Dolman"
    ],
    "name:por_x_preferred":[
        "D\u00f3lm\u00e3"
    ],
    "name:rus_x_preferred":[
        "\u0414\u043e\u043b\u043e\u043c\u0430\u043d"
    ],
    "name:spa_x_preferred":[
        "Dolm\u00e1n"
    ],
    "name:swe_x_preferred":[
        "Dolman"
    ],
    "name:ukr_x_preferred":[
        "\u0414\u043e\u043b\u043e\u043c\u0430\u043d"
    ],
    "wof:name":"Dolman",
    "wof:placetype":"locality"
},
  "geometry": {"coordinates":[73.6812,33.98415],"type":"Point"}
}