{
  "type": "Feature",
  "properties": {
    "gn:admin1_code":"2.0",
    "gn:asciiname":"Gambola",
    "gn:country_code":"PK",
    "gn:dem":1253,
    "gn:feature_class":"P",
    "gn:feature_code":"PPL",
    "gn:name":"Gambola",
    "gn:population":0,
    "gn:timezone":"Asia/Karachi",
    "iso:country":"PK",
    "wof:name":"Gambola",
    "wof:placetype":"locality"
},
  "geometry": {"coordinates":[65.91908000000001,27.47843],"type":"Point"}
}