{
  "type": "Feature",
  "properties": {
    "gn:admin1_code":"6.0",
    "gn:asciiname":"Chappar",
    "gn:country_code":"PK",
    "gn:dem":477,
    "gn:feature_class":"P",
    "gn:feature_code":"PPL",
    "gn:name":"Chappar",
    "gn:population":0,
    "gn:timezone":"Asia/Karachi",
    "iso:country":"PK",
    "name:und_x_variant":[
        "Chaper"
    ],
    "wof:name":"Chappar",
    "wof:placetype":"locality"
},
  "geometry": {"coordinates":[73.58710000000001,33.373],"type":"Point"}
}