{
  "type": "Feature",
  "properties": {
    "gn:admin1_code":"3",
    "gn:asciiname":"Mehr Din Kalle",
    "gn:country_code":"PK",
    "gn:dem":301,
    "gn:feature_class":"P",
    "gn:feature_code":"PPL",
    "gn:name":"Mehr Din Kalle",
    "gn:population":0,
    "gn:timezone":"Asia/Karachi",
    "iso:country":"PK",
    "name:eng_x_preferred":[
        "Umard\u012bn Kalle"
    ],
    "name:und_x_variant":[
        "Umard\u012bn Kili",
        "Mehr Din Kalle"
    ],
    "wof:name":"Mehr Din Kalle",
    "wof:placetype":"locality"
},
  "geometry": {"coordinates":[72.37503000000002,34.01955],"type":"Point"}
}