{
  "type": "Feature",
  "properties": {
    "gn:admin1_code":"4",
    "gn:asciiname":"Qadirpur",
    "gn:country_code":"PK",
    "gn:dem":295,
    "gn:feature_class":"P",
    "gn:feature_code":"PPL",
    "gn:name":"Qadirpur",
    "gn:population":0,
    "gn:timezone":"Asia/Karachi",
    "iso:country":"PK",
    "name:ceb_x_preferred":[
        "Qad\u012brp\u016br"
    ],
    "name:fas_x_preferred":[
        "\u0642\u062f\u06cc\u0631\u067e\u0648\u0631"
    ],
    "name:swe_x_preferred":[
        "Qad\u012brp\u016br"
    ],
    "name:und_x_variant":[
        "Dhok Q\u0101dirpur"
    ],
    "wof:name":"Qadirpur",
    "wof:placetype":"locality"
},
  "geometry": {"coordinates":[73.28793,32.77258],"type":"Point"}
}