{
  "type": "Feature",
  "properties": {
    "gn:admin1_code":"4",
    "gn:asciiname":"Chak Eleven Bahawal Canal",
    "gn:country_code":"PK",
    "gn:dem":118,
    "gn:feature_class":"P",
    "gn:feature_code":"PPL",
    "gn:name":"Chak Eleven Bahawal Canal",
    "gn:population":0,
    "gn:timezone":"Asia/Karachi",
    "iso:country":"PK",
    "name:eng_x_preferred":[
        "Chak Eleven"
    ],
    "wof:name":"Chak Eleven Bahawal Canal",
    "wof:placetype":"locality"
},
  "geometry": {"coordinates":[71.661,29.33867],"type":"Point"}
}