{
  "type": "Feature",
  "properties": {
    "gn:admin1_code":"2.0",
    "gn:asciiname":"Goth Murid Khan Brahui",
    "gn:country_code":"PK",
    "gn:dem":63,
    "gn:feature_class":"P",
    "gn:feature_code":"PPL",
    "gn:name":"Goth Murid Khan Brahui",
    "gn:population":0,
    "gn:timezone":"Asia/Karachi",
    "iso:country":"PK",
    "name:und_x_variant":[
        "Goth Mur\u012bd Kh\u0101n Brahul"
    ],
    "wof:name":"Goth Murid Khan Brahui",
    "wof:placetype":"locality"
},
  "geometry": {"coordinates":[68.75320000000001,28.42971],"type":"Point"}
}