{
  "type": "Feature",
  "properties": {
    "gn:admin1_code":"4.0",
    "gn:asciiname":"Chak Two Hundred Six",
    "gn:country_code":"PK",
    "gn:dem":181,
    "gn:feature_class":"P",
    "gn:feature_code":"PPL",
    "gn:name":"Chak Two Hundred Six",
    "gn:population":0,
    "gn:timezone":"Asia/Karachi",
    "iso:country":"PK",
    "name:und_x_variant":[
        "Bus\u0101lw\u0101li",
        "Chak Two Hundred Six",
        "Si\u0101lw\u0101la"
    ],
    "wof:name":"Chak Two Hundred Six",
    "wof:placetype":"locality"
},
  "geometry": {"coordinates":[72.80875999999998,31.46273],"type":"Point"}
}