{
  "type": "Feature",
  "properties": {
    "gn:admin1_code":"5",
    "gn:asciiname":"Haji Motia Jagirani",
    "gn:country_code":"PK",
    "gn:dem":56,
    "gn:feature_class":"P",
    "gn:feature_code":"PPL",
    "gn:name":"Haji Motia Jagirani",
    "gn:population":0,
    "gn:timezone":"Asia/Karachi",
    "iso:country":"PK",
    "name:und_x_variant":[
        "J\u0101g\u012br\u0101ni"
    ],
    "wof:name":"Haji Motia Jagirani",
    "wof:placetype":"locality"
},
  "geometry": {"coordinates":[68.2517,27.62397],"type":"Point"}
}