{
  "type": "Feature",
  "properties": {
    "gn:admin1_code":"4.0",
    "gn:asciiname":"Mohra Bakhtan",
    "gn:country_code":"PK",
    "gn:dem":577,
    "gn:feature_class":"P",
    "gn:feature_code":"PPL",
    "gn:name":"Mohra Bakhtan",
    "gn:population":0,
    "gn:timezone":"Asia/Karachi",
    "iso:country":"PK",
    "wof:name":"Mohra Bakhtan",
    "wof:placetype":"locality"
},
  "geometry": {"coordinates":[73.29203000000003,33.51235],"type":"Point"}
}