{
  "type": "Feature",
  "properties": {
    "gn:admin1_code":"3",
    "gn:asciiname":"Darra",
    "gn:country_code":"PK",
    "gn:dem":1237,
    "gn:feature_class":"P",
    "gn:feature_code":"PPL",
    "gn:name":"Darra",
    "gn:population":0,
    "gn:timezone":"Asia/Karachi",
    "iso:country":"PK",
    "name:ceb_x_preferred":[
        "Darra"
    ],
    "name:swe_x_preferred":[
        "Darra"
    ],
    "wof:name":"Darra",
    "wof:placetype":"locality"
},
  "geometry": {"coordinates":[72.61284000000001,34.62745],"type":"Point"}
}