{
  "type": "Feature",
  "properties": {
    "gn:admin1_code":"5",
    "gn:asciiname":"Goth Bakhar Khan Jamali",
    "gn:country_code":"PK",
    "gn:dem":73,
    "gn:feature_class":"P",
    "gn:feature_code":"PPL",
    "gn:name":"Goth Bakhar Khan Jamali",
    "gn:population":0,
    "gn:timezone":"Asia/Karachi",
    "iso:country":"PK",
    "name:und_x_variant":[
        "Goth Bhai Kh\u0101n"
    ],
    "wof:name":"Goth Bakhar Khan Jamali",
    "wof:placetype":"locality"
},
  "geometry": {"coordinates":[67.34699999999999,26.74667],"type":"Point"}
}