{
  "type": "Feature",
  "properties": {
    "gn:admin1_code":"4",
    "gn:asciiname":"Lumbri",
    "gn:country_code":"PK",
    "gn:dem":174,
    "gn:feature_class":"P",
    "gn:feature_code":"PPL",
    "gn:name":"Lumbri",
    "gn:population":0,
    "gn:timezone":"Asia/Karachi",
    "iso:country":"PK",
    "name:fas_x_preferred":[
        "\u0644\u0648\u0645\u0628\u0631\u06cc"
    ],
    "name:urd_x_preferred":[
        "\u0644\u0645\u0628\u0631\u06cc"
    ],
    "wof:name":"Lumbri",
    "wof:placetype":"locality"
},
  "geometry": {"coordinates":[73.77507,30.66131],"type":"Point"}
}