{
  "type": "Feature",
  "properties": {
    "gn:admin1_code":"3.0",
    "gn:asciiname":"Zarabin",
    "gn:country_code":"PK",
    "gn:dem":1003,
    "gn:feature_class":"P",
    "gn:feature_code":"PPL",
    "gn:name":"Zarabin",
    "gn:population":0,
    "gn:timezone":"Asia/Karachi",
    "iso:country":"PK",
    "wof:name":"Zarabin",
    "wof:placetype":"locality"
},
  "geometry": {"coordinates":[70.66779,33.16304],"type":"Point"}
}