{
  "type": "Feature",
  "properties": {
    "gn:admin1_code":"4.0",
    "gn:asciiname":"Chak Two Hundred Thirty-six Rakh Branch",
    "gn:country_code":"PK",
    "gn:dem":182,
    "gn:feature_class":"P",
    "gn:feature_code":"PPL",
    "gn:name":"Chak Two Hundred Thirty-six Rakh Branch",
    "gn:population":0,
    "gn:timezone":"Asia/Karachi",
    "iso:country":"PK",
    "name:und_x_variant":[
        "Khudi Japi\u0101n",
        "Chak Two Hundred Thirty-Six RB",
        "Chak Two Hundred Thirty-six Rakh Branch",
        "Jappi\u0101n"
    ],
    "wof:name":"Chak Two Hundred Thirty-six Rakh Branch",
    "wof:placetype":"locality"
},
  "geometry": {"coordinates":[73.11048000000002,31.33569],"type":"Point"}
}