{
  "type": "Feature",
  "properties": {
    "gn:admin1_code":"4",
    "gn:asciiname":"Dhok Jara",
    "gn:country_code":"PK",
    "gn:dem":508,
    "gn:feature_class":"P",
    "gn:feature_code":"PPL",
    "gn:name":"Dhok Jara",
    "gn:population":0,
    "gn:timezone":"Asia/Karachi",
    "iso:country":"PK",
    "wof:name":"Dhok Jara",
    "wof:placetype":"locality"
},
  "geometry": {"coordinates":[73.27359,33.10906],"type":"Point"}
}