{
  "type": "Feature",
  "properties": {
    "gn:admin1_code":"2.0",
    "gn:asciiname":"Nishpar",
    "gn:country_code":"PK",
    "gn:dem":1757,
    "gn:feature_class":"P",
    "gn:feature_code":"PPL",
    "gn:name":"Nishpar",
    "gn:population":0,
    "gn:timezone":"Asia/Karachi",
    "iso:country":"PK",
    "wof:name":"Nishpar",
    "wof:placetype":"locality"
},
  "geometry": {"coordinates":[69.61086,31.23438],"type":"Point"}
}