{
  "type": "Feature",
  "properties": {
    "gn:admin1_code":"3",
    "gn:asciiname":"Sarbala Banda",
    "gn:country_code":"PK",
    "gn:dem":1788,
    "gn:feature_class":"P",
    "gn:feature_code":"PPL",
    "gn:name":"Sarbala Banda",
    "gn:population":0,
    "gn:timezone":"Asia/Karachi",
    "iso:country":"PK",
    "wof:name":"Sarbala Banda",
    "wof:placetype":"locality"
},
  "geometry": {"coordinates":[72.17619999999999,34.82565],"type":"Point"}
}