{
  "type": "Feature",
  "properties": {
    "gn:admin1_code":"4",
    "gn:asciiname":"Jhoutiauwala",
    "gn:country_code":"PK",
    "gn:dem":189,
    "gn:feature_class":"P",
    "gn:feature_code":"PPL",
    "gn:name":"Jhoutiauwala",
    "gn:population":0,
    "gn:timezone":"Asia/Karachi",
    "iso:country":"PK",
    "name:und_x_variant":[
        "Jhoi\u0101nw\u0101la",
        "Jah\u0101ni\u0101n",
        "Jhoutiauwala"
    ],
    "wof:name":"Jhoutiauwala",
    "wof:placetype":"locality"
},
  "geometry": {"coordinates":[73.21576999999998,31.83598],"type":"Point"}
}