{
  "type": "Feature",
  "properties": {
    "gn:admin1_code":"3.0",
    "gn:asciiname":"Banwar",
    "gn:country_code":"PK",
    "gn:dem":1339,
    "gn:feature_class":"P",
    "gn:feature_code":"PPL",
    "gn:name":"Banwar",
    "gn:population":0,
    "gn:timezone":"Asia/Karachi",
    "iso:country":"PK",
    "name:eng_x_preferred":[
        "Banwar"
    ],
    "wof:name":"Banwar",
    "wof:placetype":"locality"
},
  "geometry": {"coordinates":[73.32684,33.87959],"type":"Point"}
}