{
  "type": "Feature",
  "properties": {
    "gn:admin1_code":"3",
    "gn:asciiname":"Sarpatai",
    "gn:country_code":"PK",
    "gn:dem":880,
    "gn:feature_class":"P",
    "gn:feature_code":"PPL",
    "gn:name":"Sarpatai",
    "gn:population":0,
    "gn:timezone":"Asia/Karachi",
    "iso:country":"PK",
    "wof:name":"Sarpatai",
    "wof:placetype":"locality"
},
  "geometry": {"coordinates":[72.61681999999998,34.55453],"type":"Point"}
}