{
  "type": "Feature",
  "properties": {
    "gn:admin1_code":"4.0",
    "gn:asciiname":"Bhaku Sanpal",
    "gn:country_code":"PK",
    "gn:dem":155,
    "gn:feature_class":"P",
    "gn:feature_code":"PPL",
    "gn:name":"Bhaku Sanpal",
    "gn:population":0,
    "gn:timezone":"Asia/Karachi",
    "iso:country":"PK",
    "name:und_x_variant":[
        "Bakhu Sanp\u0101l"
    ],
    "wof:name":"Bhaku Sanpal",
    "wof:placetype":"locality"
},
  "geometry": {"coordinates":[72.61667,30.61667000000001],"type":"Point"}
}