{
  "type": "Feature",
  "properties": {
    "gn:admin1_code":"5",
    "gn:asciiname":"Goth Sobho Rind",
    "gn:country_code":"PK",
    "gn:dem":19,
    "gn:feature_class":"P",
    "gn:feature_code":"PPL",
    "gn:name":"Goth Sobho Rind",
    "gn:population":0,
    "gn:timezone":"Asia/Karachi",
    "iso:country":"PK",
    "name:und_x_variant":[
        "Ichhra Rind"
    ],
    "wof:name":"Goth Sobho Rind",
    "wof:placetype":"locality"
},
  "geometry": {"coordinates":[68.87311,25.3083],"type":"Point"}
}