{
  "type": "Feature",
  "properties": {
    "gn:admin1_code":"5",
    "gn:asciiname":"Ghulam Mustafa Khosa",
    "gn:country_code":"PK",
    "gn:dem":61,
    "gn:feature_class":"P",
    "gn:feature_code":"PPL",
    "gn:name":"Ghulam Mustafa Khosa",
    "gn:population":0,
    "gn:timezone":"Asia/Karachi",
    "iso:country":"PK",
    "name:und_x_variant":[
        "W\u0101hid Bakhsh Khosa"
    ],
    "wof:name":"Ghulam Mustafa Khosa",
    "wof:placetype":"locality"
},
  "geometry": {"coordinates":[68.65149,28.31286],"type":"Point"}
}