{
  "type": "Feature",
  "properties": {
    "gn:admin1_code":"7.0",
    "gn:asciiname":"Monkhur",
    "gn:country_code":"PK",
    "gn:dem":2340,
    "gn:feature_class":"P",
    "gn:feature_code":"PPL",
    "gn:name":"Monkhur",
    "gn:population":0,
    "gn:timezone":"Asia/Karachi",
    "iso:country":"PK",
    "wof:name":"Monkhur",
    "wof:placetype":"locality"
},
  "geometry": {"coordinates":[75.95050999999999,35.2283],"type":"Point"}
}