{
  "type": "Feature",
  "properties": {
    "gn:admin1_code":"1.0",
    "gn:asciiname":"Patia Gam",
    "gn:country_code":"PK",
    "gn:dem":963,
    "gn:feature_class":"P",
    "gn:feature_code":"PPL",
    "gn:name":"Patia Gam",
    "gn:population":0,
    "gn:timezone":"Asia/Karachi",
    "iso:country":"PK",
    "wof:name":"Patia Gam",
    "wof:placetype":"locality"
},
  "geometry": {"coordinates":[71.30891,33.76589],"type":"Point"}
}