{
  "type": "Feature",
  "properties": {
    "gn:admin1_code":"5.0",
    "gn:asciiname":"Jan Muhammad Jamali",
    "gn:country_code":"PK",
    "gn:dem":29,
    "gn:feature_class":"P",
    "gn:feature_code":"PPL",
    "gn:name":"Jan Muhammad Jamali",
    "gn:population":0,
    "gn:timezone":"Asia/Karachi",
    "iso:country":"PK",
    "name:und_x_variant":[
        "J\u0101n Muhammad Kam\u0101li"
    ],
    "wof:name":"Jan Muhammad Jamali",
    "wof:placetype":"locality"
},
  "geometry": {"coordinates":[68.41556,26.07247000000001],"type":"Point"}
}