{
  "type": "Feature",
  "properties": {
    "gn:admin1_code":"4.0",
    "gn:asciiname":"Chirohianwali Theri",
    "gn:country_code":"PK",
    "gn:dem":101,
    "gn:feature_class":"P",
    "gn:feature_code":"PPL",
    "gn:name":"Chirohianwali Theri",
    "gn:population":0,
    "gn:timezone":"Asia/Karachi",
    "iso:country":"PK",
    "wof:name":"Chirohianwali Theri",
    "wof:placetype":"locality"
},
  "geometry": {"coordinates":[71.27409,28.79641],"type":"Point"}
}