{
  "type": "Feature",
  "properties": {
    "gn:admin1_code":"4.0",
    "gn:asciiname":"Kashmir Point",
    "gn:country_code":"PK",
    "gn:dem":2239,
    "gn:feature_class":"P",
    "gn:feature_code":"PPL",
    "gn:name":"Kashmir Point",
    "gn:population":0,
    "gn:timezone":"Asia/Karachi",
    "iso:country":"PK",
    "name:eng_x_preferred":[
        "Kashmir Point"
    ],
    "wof:name":"Kashmir Point",
    "wof:placetype":"locality"
},
  "geometry": {"coordinates":[73.40043,33.91181],"type":"Point"}
}