{
  "type": "Feature",
  "properties": {
    "gn:admin1_code":"5.0",
    "gn:asciiname":"Goth Imam Bakhsh Zardari",
    "gn:country_code":"PK",
    "gn:dem":35,
    "gn:feature_class":"P",
    "gn:feature_code":"PPL",
    "gn:name":"Goth Imam Bakhsh Zardari",
    "gn:population":0,
    "gn:timezone":"Asia/Karachi",
    "iso:country":"PK",
    "wof:name":"Goth Imam Bakhsh Zardari",
    "wof:placetype":"locality"
},
  "geometry": {"coordinates":[68.13046999999999,26.339],"type":"Point"}
}