{
  "type": "Feature",
  "properties": {
    "gn:admin1_code":"3",
    "gn:asciiname":"Chiran",
    "gn:country_code":"PK",
    "gn:dem":906,
    "gn:feature_class":"P",
    "gn:feature_code":"PPL",
    "gn:name":"Chiran",
    "gn:population":0,
    "gn:timezone":"Asia/Karachi",
    "iso:country":"PK",
    "name:ara_x_preferred":[
        "\u062a\u0634\u064a\u0631\u0627\u0646"
    ],
    "name:fas_x_preferred":[
        "\u0686\u06cc\u0631\u0627\u0646"
    ],
    "name:msa_x_preferred":[
        "Chiran"
    ],
    "name:ukr_x_preferred":[
        "\u0427\u0456\u0440\u0430\u043d"
    ],
    "wof:name":"Chiran",
    "wof:placetype":"locality"
},
  "geometry": {"coordinates":[72.90688,34.89932],"type":"Point"}
}