{
  "type": "Feature",
  "properties": {
    "gn:admin1_code":"3",
    "gn:asciiname":"Sandho Gali",
    "gn:country_code":"PK",
    "gn:dem":1585,
    "gn:feature_class":"P",
    "gn:feature_code":"PPL",
    "gn:name":"Sandho Gali",
    "gn:population":0,
    "gn:timezone":"Asia/Karachi",
    "iso:country":"PK",
    "name:und_x_variant":[
        "Sandho"
    ],
    "wof:name":"Sandho Gali",
    "wof:placetype":"locality"
},
  "geometry": {"coordinates":[73.0916,34.16968],"type":"Point"}
}