{
  "type": "Feature",
  "properties": {
    "gn:admin1_code":"7.0",
    "gn:asciiname":"Chithar",
    "gn:country_code":"PK",
    "gn:dem":2029,
    "gn:feature_class":"P",
    "gn:feature_code":"PPL",
    "gn:name":"Chithar",
    "gn:population":0,
    "gn:timezone":"Asia/Karachi",
    "iso:country":"PK",
    "wof:name":"Chithar",
    "wof:placetype":"locality"
},
  "geometry": {"coordinates":[73.86816,35.64324000000001],"type":"Point"}
}