{
  "type": "Feature",
  "properties": {
    "gn:admin1_code":"4.0",
    "gn:asciiname":"Military Colony",
    "gn:country_code":"PK",
    "gn:dem":240,
    "gn:feature_class":"P",
    "gn:feature_code":"PPL",
    "gn:name":"Military Colony",
    "gn:population":0,
    "gn:timezone":"Asia/Karachi",
    "iso:country":"PK",
    "wof:name":"Military Colony",
    "wof:placetype":"locality"
},
  "geometry": {"coordinates":[74.43841,32.47098],"type":"Point"}
}