{
  "type": "Feature",
  "properties": {
    "gn:admin1_code":"4.0",
    "gn:asciiname":"Chak Two Hundred Seventy-nine Gogera Branch",
    "gn:country_code":"PK",
    "gn:dem":182,
    "gn:feature_class":"P",
    "gn:feature_code":"PPL",
    "gn:name":"Chak Two Hundred Seventy-nine Gogera Branch",
    "gn:population":0,
    "gn:timezone":"Asia/Karachi",
    "iso:country":"PK",
    "name:und_x_variant":[
        "Jasu\u0101na",
        "W\u0101ga"
    ],
    "wof:name":"Chak Two Hundred Seventy-nine Gogera Branch",
    "wof:placetype":"locality"
},
  "geometry": {"coordinates":[73.26616999999997,31.18536],"type":"Point"}
}