{
  "type": "Feature",
  "properties": {
    "gn:admin1_code":"04",
    "gn:asciiname":"Mujahad",
    "gn:country_code":"PK",
    "gn:dem":375,
    "gn:feature_class":"P",
    "gn:feature_code":"PPL",
    "gn:name":"Mujahad",
    "gn:population":0,
    "gn:timezone":"Asia/Karachi",
    "iso:country":"PK",
    "name:und_x_variant":[
        "Mujahid",
        "Mujahad"
    ],
    "wof:name":"Mujahad",
    "wof:placetype":"locality"
},
  "geometry": {"coordinates":[72.78114000000002,33.36828],"type":"Point"}
}