{
  "type": "Feature",
  "properties": {
    "gn:admin1_code":"2",
    "gn:asciiname":"Kili Makan Tuk",
    "gn:country_code":"PK",
    "gn:dem":1090,
    "gn:feature_class":"P",
    "gn:feature_code":"PPL",
    "gn:name":"Kili Makan Tuk",
    "gn:population":0,
    "gn:timezone":"Asia/Karachi",
    "iso:country":"PK",
    "name:und_x_variant":[
        "Makan Tuk"
    ],
    "wof:name":"Kili Makan Tuk",
    "wof:placetype":"locality"
},
  "geometry": {"coordinates":[64.31995999999999,29.14882],"type":"Point"}
}