{
  "type": "Feature",
  "properties": {
    "gn:admin1_code":"2.0",
    "gn:asciiname":"Goth Bahadur Khan Jhalawani",
    "gn:country_code":"PK",
    "gn:dem":86,
    "gn:feature_class":"P",
    "gn:feature_code":"PPL",
    "gn:name":"Goth Bahadur Khan Jhalawani",
    "gn:population":0,
    "gn:timezone":"Asia/Karachi",
    "iso:country":"PK",
    "wof:name":"Goth Bahadur Khan Jhalawani",
    "wof:placetype":"locality"
},
  "geometry": {"coordinates":[68.16509000000001,28.81939],"type":"Point"}
}