{
  "type": "Feature",
  "properties": {
    "gn:admin1_code":"7.0",
    "gn:asciiname":"Goin",
    "gn:country_code":"PK",
    "gn:dem":1490,
    "gn:feature_class":"P",
    "gn:feature_code":"PPL",
    "gn:name":"Goin",
    "gn:population":0,
    "gn:timezone":"Asia/Karachi",
    "iso:country":"PK",
    "name:deu_x_preferred":[
        "Goin"
    ],
    "name:fra_x_preferred":[
        "Goin"
    ],
    "name:pol_x_preferred":[
        "Goin"
    ],
    "name:swe_x_preferred":[
        "Goin"
    ],
    "name:ukr_x_preferred":[
        "\u0413\u0443\u0435\u043d"
    ],
    "wof:name":"Goin",
    "wof:placetype":"locality"
},
  "geometry": {"coordinates":[73.83006999999998,35.41315],"type":"Point"}
}