{
  "type": "Feature",
  "properties": {
    "gn:admin1_code":"4.0",
    "gn:asciiname":"Chung",
    "gn:country_code":"PK",
    "gn:dem":209,
    "gn:feature_class":"P",
    "gn:feature_code":"PPL",
    "gn:name":"Chung",
    "gn:population":0,
    "gn:timezone":"Asia/Karachi",
    "iso:country":"PK",
    "name:ceb_x_preferred":[
        "Chung"
    ],
    "name:deu_x_preferred":[
        "Chung"
    ],
    "name:fra_x_preferred":[
        "Chung"
    ],
    "name:rus_x_preferred":[
        "\u0427\u0436\u0443\u043d"
    ],
    "name:swe_x_preferred":[
        "Chung"
    ],
    "name:und_x_variant":[
        "Chung Panjgarian",
        "Chung"
    ],
    "wof:name":"Chung",
    "wof:placetype":"locality"
},
  "geometry": {"coordinates":[74.17373000000001,31.43139],"type":"Point"}
}