{
  "type": "Feature",
  "properties": {
    "gn:admin1_code":"4.0",
    "gn:asciiname":"Dhok Kunjala",
    "gn:country_code":"PK",
    "gn:dem":315,
    "gn:feature_class":"P",
    "gn:feature_code":"PPL",
    "gn:name":"Dhok Kunjala",
    "gn:population":0,
    "gn:timezone":"Asia/Karachi",
    "iso:country":"PK",
    "name:und_x_variant":[
        "Kunj\u0101la"
    ],
    "wof:name":"Dhok Kunjala",
    "wof:placetype":"locality"
},
  "geometry": {"coordinates":[72.14461999999997,33.06647],"type":"Point"}
}