{
  "type": "Feature",
  "properties": {
    "gn:admin1_code":"4.0",
    "gn:asciiname":"Ahmad Khanwala",
    "gn:country_code":"PK",
    "gn:dem":316,
    "gn:feature_class":"P",
    "gn:feature_code":"PPL",
    "gn:name":"Ahmad Khanwala",
    "gn:population":0,
    "gn:timezone":"Asia/Karachi",
    "iso:country":"PK",
    "wof:name":"Ahmad Khanwala",
    "wof:placetype":"locality"
},
  "geometry": {"coordinates":[71.79219999999999,32.62244],"type":"Point"}
}