{
  "type": "Feature",
  "properties": {
    "gn:admin1_code":"3",
    "gn:asciiname":"Panj Khuian",
    "gn:country_code":"PK",
    "gn:dem":1077,
    "gn:feature_class":"P",
    "gn:feature_code":"PPL",
    "gn:name":"Panj Khuian",
    "gn:population":0,
    "gn:timezone":"Asia/Karachi",
    "iso:country":"PK",
    "name:und_x_variant":[
        "Panj Kuri\u0101n",
        "Panj Kui\u0101n",
        "Panj Khuian"
    ],
    "wof:name":"Panj Khuian",
    "wof:placetype":"locality"
},
  "geometry": {"coordinates":[73.05144,34.15974],"type":"Point"}
}