{
  "type": "Feature",
  "properties": {
    "gn:admin1_code":"4.0",
    "gn:asciiname":"Pari Rajian",
    "gn:country_code":"PK",
    "gn:dem":566,
    "gn:feature_class":"P",
    "gn:feature_code":"PPL",
    "gn:name":"Pari Rajian",
    "gn:population":0,
    "gn:timezone":"Asia/Karachi",
    "iso:country":"PK",
    "wof:name":"Pari Rajian",
    "wof:placetype":"locality"
},
  "geometry": {"coordinates":[73.20792,33.29137],"type":"Point"}
}