{
  "type": "Feature",
  "properties": {
    "gn:admin1_code":"04",
    "gn:asciiname":"Chak Four Hundred Fifteen Jhang Branch",
    "gn:country_code":"PK",
    "gn:dem":171,
    "gn:feature_class":"P",
    "gn:feature_code":"PPL",
    "gn:name":"Chak Four Hundred Fifteen Jhang Branch",
    "gn:population":0,
    "gn:timezone":"Asia/Karachi",
    "iso:country":"PK",
    "name:und_x_variant":[
        "Kot Chanderke",
        "Kot Chandarke",
        "Chak Number Four Hundred Fifteen",
        "Chak Four Hundred Fifteen Jhang Branch",
        "Kot Sand\u0101rak"
    ],
    "wof:name":"Chak Four Hundred Fifteen Jhang Branch",
    "wof:placetype":"locality"
},
  "geometry": {"coordinates":[72.65935999999998,31.23865],"type":"Point"}
}