{
  "type": "Feature",
  "properties": {
    "gn:admin1_code":"4.0",
    "gn:asciiname":"Chah Nikkewala",
    "gn:country_code":"PK",
    "gn:dem":143,
    "gn:feature_class":"P",
    "gn:feature_code":"PPL",
    "gn:name":"Chah Nikkewala",
    "gn:population":0,
    "gn:timezone":"Asia/Karachi",
    "iso:country":"PK",
    "name:eng_x_preferred":[
        "Chah Nikkewala"
    ],
    "wof:name":"Chah Nikkewala",
    "wof:placetype":"locality"
},
  "geometry": {"coordinates":[70.9933,30.88742],"type":"Point"}
}