{
  "type": "Feature",
  "properties": {
    "gn:admin1_code":"3.0",
    "gn:asciiname":"Mus",
    "gn:country_code":"PK",
    "gn:dem":1111,
    "gn:feature_class":"P",
    "gn:feature_code":"PPL",
    "gn:name":"Mus",
    "gn:population":0,
    "gn:timezone":"Asia/Karachi",
    "iso:country":"PK",
    "name:cat_x_preferred":[
        "Mus"
    ],
    "name:ceb_x_preferred":[
        "Mus"
    ],
    "name:ces_x_preferred":[
        "Mus"
    ],
    "name:dan_x_preferred":[
        "Mus"
    ],
    "name:deu_x_preferred":[
        "Mus"
    ],
    "name:fin_x_preferred":[
        "Mus"
    ],
    "name:fra_x_preferred":[
        "Mus"
    ],
    "name:isl_x_preferred":[
        "M\u00fas"
    ],
    "name:lat_x_preferred":[
        "Mus"
    ],
    "name:ltz_x_preferred":[
        "Mus"
    ],
    "name:nld_x_preferred":[
        "Mus"
    ],
    "name:nno_x_preferred":[
        "Mus"
    ],
    "name:nor_x_preferred":[
        "Mus"
    ],
    "name:pol_x_preferred":[
        "Mus"
    ],
    "name:slk_x_preferred":[
        "Mus"
    ],
    "name:spa_x_preferred":[
        "Mus"
    ],
    "name:swe_x_preferred":[
        "Mus"
    ],
    "name:vie_x_preferred":[
        "Mus"
    ],
    "wof:name":"Mus",
    "wof:placetype":"locality"
},
  "geometry": {"coordinates":[73.2542,35.27429],"type":"Point"}
}