{
  "type": "Feature",
  "properties": {
    "gn:admin1_code":"3.0",
    "gn:asciiname":"Mangan Kalle",
    "gn:country_code":"PK",
    "gn:dem":1353,
    "gn:feature_class":"P",
    "gn:feature_code":"PPL",
    "gn:name":"Mangan Kalle",
    "gn:population":0,
    "gn:timezone":"Asia/Karachi",
    "iso:country":"PK",
    "wof:name":"Mangan Kalle",
    "wof:placetype":"locality"
},
  "geometry": {"coordinates":[73.0592,34.83695],"type":"Point"}
}