{
  "type": "Feature",
  "properties": {
    "gn:admin1_code":"2.0",
    "gn:asciiname":"Zafar Khan Khosa",
    "gn:country_code":"PK",
    "gn:dem":60,
    "gn:feature_class":"P",
    "gn:feature_code":"PPL",
    "gn:name":"Zafar Khan Khosa",
    "gn:population":0,
    "gn:timezone":"Asia/Karachi",
    "iso:country":"PK",
    "wof:name":"Zafar Khan Khosa",
    "wof:placetype":"locality"
},
  "geometry": {"coordinates":[68.29464,28.38235],"type":"Point"}
}