{
  "type": "Feature",
  "properties": {
    "gn:admin1_code":"4.0",
    "gn:asciiname":"Jhungawala",
    "gn:country_code":"PK",
    "gn:dem":845,
    "gn:feature_class":"P",
    "gn:feature_code":"PPL",
    "gn:name":"Jhungaw\u0101la",
    "gn:population":0,
    "gn:timezone":"Asia/Karachi",
    "iso:country":"PK",
    "wof:name":"Jhungawala",
    "wof:placetype":"locality"
},
  "geometry": {"coordinates":[72.32847,32.62368],"type":"Point"}
}