{
  "type": "Feature",
  "properties": {
    "gn:admin1_code":"3.0",
    "gn:asciiname":"Boveri",
    "gn:country_code":"PK",
    "gn:dem":1048,
    "gn:feature_class":"P",
    "gn:feature_code":"PPL",
    "gn:name":"Boveri",
    "gn:population":0,
    "gn:timezone":"Asia/Karachi",
    "iso:country":"PK",
    "wof:name":"Boveri",
    "wof:placetype":"locality"
},
  "geometry": {"coordinates":[73.22083000000001,33.84803],"type":"Point"}
}