{
  "type": "Feature",
  "properties": {
    "gn:admin1_code":"3.0",
    "gn:asciiname":"Chagharugh",
    "gn:country_code":"PK",
    "gn:dem":2963,
    "gn:feature_class":"P",
    "gn:feature_code":"PPL",
    "gn:name":"Chagharugh",
    "gn:population":0,
    "gn:timezone":"Asia/Karachi",
    "iso:country":"PK",
    "wof:name":"Chagharugh",
    "wof:placetype":"locality"
},
  "geometry": {"coordinates":[71.68141999999997,36.29784],"type":"Point"}
}