{
  "type": "Feature",
  "properties": {
    "gn:admin1_code":"4",
    "gn:asciiname":"Alpa Sudhari",
    "gn:country_code":"PK",
    "gn:dem":192,
    "gn:feature_class":"P",
    "gn:feature_code":"PPL",
    "gn:name":"Alpa Sudhari",
    "gn:population":0,
    "gn:timezone":"Asia/Karachi",
    "iso:country":"PK",
    "name:und_x_variant":[
        "Alpa Sudn\u0101ri"
    ],
    "wof:name":"Alpa Sudhari",
    "wof:placetype":"locality"
},
  "geometry": {"coordinates":[73.66813,31.13882000000001],"type":"Point"}
}