{
  "type": "Feature",
  "properties": {
    "gn:admin1_code":"3",
    "gn:asciiname":"Bankla",
    "gn:country_code":"PK",
    "gn:dem":2273,
    "gn:feature_class":"P",
    "gn:feature_code":"PPL",
    "gn:name":"Bankla",
    "gn:population":0,
    "gn:timezone":"Asia/Karachi",
    "iso:country":"PK",
    "wof:name":"Bankla",
    "wof:placetype":"locality"
},
  "geometry": {"coordinates":[73.61788,34.71614],"type":"Point"}
}