{
  "type": "Feature",
  "properties": {
    "gn:admin1_code":"5.0",
    "gn:asciiname":"Goth Koro Jamali",
    "gn:country_code":"PK",
    "gn:dem":50,
    "gn:feature_class":"P",
    "gn:feature_code":"PPL",
    "gn:name":"Goth Koro Jamali",
    "gn:population":0,
    "gn:timezone":"Asia/Karachi",
    "iso:country":"PK",
    "name:und_x_variant":[
        "Goth Kero Jamal"
    ],
    "wof:name":"Goth Koro Jamali",
    "wof:placetype":"locality"
},
  "geometry": {"coordinates":[68.1756,27.68361],"type":"Point"}
}