{
  "type": "Feature",
  "properties": {
    "gn:admin1_code":"4",
    "gn:asciiname":"Tappa Khakkhan",
    "gn:country_code":"PK",
    "gn:dem":125,
    "gn:feature_class":"P",
    "gn:feature_code":"PPL",
    "gn:name":"Tappa Khakkh\u0101n",
    "gn:population":0,
    "gn:timezone":"Asia/Karachi",
    "iso:country":"PK",
    "wof:name":"Tappa Khakkhan",
    "wof:placetype":"locality"
},
  "geometry": {"coordinates":[71.05,30.34583],"type":"Point"}
}