{
  "type": "Feature",
  "properties": {
    "gn:admin1_code":"3.0",
    "gn:asciiname":"Chittian Qabran",
    "gn:country_code":"PK",
    "gn:dem":948,
    "gn:feature_class":"P",
    "gn:feature_code":"PPL",
    "gn:name":"Chittian Qabran",
    "gn:population":0,
    "gn:timezone":"Asia/Karachi",
    "iso:country":"PK",
    "name:eng_x_preferred":[
        "Qabr\u0101n"
    ],
    "name:eng_x_variant":[
        "Chitti"
    ],
    "name:und_x_variant":[
        "Chitti Qabr\u0101n"
    ],
    "wof:name":"Chittian Qabran",
    "wof:placetype":"locality"
},
  "geometry": {"coordinates":[73.21191999999998,33.88616],"type":"Point"}
}