{
  "type": "Feature",
  "properties": {
    "gn:admin1_code":"4.0",
    "gn:asciiname":"Arki Dogran",
    "gn:country_code":"PK",
    "gn:dem":246,
    "gn:feature_class":"P",
    "gn:feature_code":"PPL",
    "gn:name":"Arki Dogran",
    "gn:population":0,
    "gn:timezone":"Asia/Karachi",
    "iso:country":"PK",
    "name:und_x_variant":[
        "Arki",
        "Arki Dogran"
    ],
    "wof:name":"Arki Dogran",
    "wof:placetype":"locality"
},
  "geometry": {"coordinates":[74.70211999999999,32.2911],"type":"Point"}
}