{
  "type": "Feature",
  "properties": {
    "gn:admin1_code":"2.0",
    "gn:asciiname":"Kauro Khan",
    "gn:country_code":"PK",
    "gn:dem":602,
    "gn:feature_class":"P",
    "gn:feature_code":"PPL",
    "gn:name":"Kauro Khan",
    "gn:population":0,
    "gn:timezone":"Asia/Karachi",
    "iso:country":"PK",
    "name:und_x_variant":[
        "Kauru Kh\u0101n"
    ],
    "wof:name":"Kauro Khan",
    "wof:placetype":"locality"
},
  "geometry": {"coordinates":[65.71051,26.76246],"type":"Point"}
}