{
  "type": "Feature",
  "properties": {
    "gn:admin1_code":"5",
    "gn:asciiname":"Goth Anb Khoso",
    "gn:country_code":"PK",
    "gn:dem":8,
    "gn:feature_class":"P",
    "gn:feature_code":"PPL",
    "gn:name":"Goth Anb Khoso",
    "gn:population":0,
    "gn:timezone":"Asia/Karachi",
    "iso:country":"PK",
    "name:und_x_variant":[
        "Goth S\u0101wan M\u0101chhi"
    ],
    "wof:name":"Goth Anb Khoso",
    "wof:placetype":"locality"
},
  "geometry": {"coordinates":[69.28237,24.9313],"type":"Point"}
}