{
  "type": "Feature",
  "properties": {
    "gn:admin1_code":"5",
    "gn:asciiname":"Bakhshal Lashari",
    "gn:country_code":"PK",
    "gn:dem":39,
    "gn:feature_class":"P",
    "gn:feature_code":"PPL",
    "gn:name":"Bakhshal Lashari",
    "gn:population":0,
    "gn:timezone":"Asia/Karachi",
    "iso:country":"PK",
    "name:und_x_variant":[
        "Rah\u012bm Bakhsh Lashk\u0101ri"
    ],
    "wof:name":"Bakhshal Lashari",
    "wof:placetype":"locality"
},
  "geometry": {"coordinates":[68.26706999999999,26.48562],"type":"Point"}
}