{
  "type": "Feature",
  "properties": {
    "gn:admin1_code":"3",
    "gn:asciiname":"Khetar",
    "gn:country_code":"PK",
    "gn:dem":1996,
    "gn:feature_class":"P",
    "gn:feature_code":"PPL",
    "gn:name":"Khetar",
    "gn:population":0,
    "gn:timezone":"Asia/Karachi",
    "iso:country":"PK",
    "wof:name":"Khetar",
    "wof:placetype":"locality"
},
  "geometry": {"coordinates":[73.38785,34.17598],"type":"Point"}
}