{
  "type": "Feature",
  "properties": {
    "gn:admin1_code":"4",
    "gn:asciiname":"Nathiwala",
    "gn:country_code":"PK",
    "gn:dem":128,
    "gn:feature_class":"P",
    "gn:feature_code":"PPL",
    "gn:name":"Nathiwala",
    "gn:population":0,
    "gn:timezone":"Asia/Karachi",
    "iso:country":"PK",
    "name:und_x_variant":[
        "Nathew\u0101la"
    ],
    "wof:name":"Nathiwala",
    "wof:placetype":"locality"
},
  "geometry": {"coordinates":[70.62945000000001,30.20973],"type":"Point"}
}