{
  "type": "Feature",
  "properties": {
    "gn:admin1_code":"5",
    "gn:asciiname":"Deh Three Hundred Seventy-three A",
    "gn:country_code":"PK",
    "gn:dem":10,
    "gn:feature_class":"P",
    "gn:feature_code":"PPL",
    "gn:name":"Deh Three Hundred Seventy-three A",
    "gn:population":0,
    "gn:timezone":"Asia/Karachi",
    "iso:country":"PK",
    "name:und_x_variant":[
        "Deh Three Hundred Seventy-three"
    ],
    "wof:name":"Deh Three Hundred Seventy-three A",
    "wof:placetype":"locality"
},
  "geometry": {"coordinates":[69.35013000000001,24.93607],"type":"Point"}
}