{
  "type": "Feature",
  "properties": {
    "gn:admin1_code":"3.0",
    "gn:asciiname":"Rawark Ghari",
    "gn:country_code":"PK",
    "gn:dem":3275,
    "gn:feature_class":"P",
    "gn:feature_code":"PPL",
    "gn:name":"Rawark Ghari",
    "gn:population":0,
    "gn:timezone":"Asia/Karachi",
    "iso:country":"PK",
    "wof:name":"Rawark Ghari",
    "wof:placetype":"locality"
},
  "geometry": {"coordinates":[72.93977,36.73213],"type":"Point"}
}