{
  "type": "Feature",
  "properties": {
    "gn:admin1_code":"1",
    "gn:asciiname":"Shaikh Mansir Kili",
    "gn:country_code":"PK",
    "gn:dem":2084,
    "gn:feature_class":"P",
    "gn:feature_code":"PPL",
    "gn:name":"Shaikh Mansir Kili",
    "gn:population":0,
    "gn:timezone":"Asia/Karachi",
    "iso:country":"PK",
    "wof:name":"Shaikh Mansir Kili",
    "wof:placetype":"locality"
},
  "geometry": {"coordinates":[69.85698000000001,32.71734],"type":"Point"}
}