{
  "type": "Feature",
  "properties": {
    "gn:admin1_code":"7.0",
    "gn:asciiname":"Bachicha",
    "gn:country_code":"PK",
    "gn:dem":1975,
    "gn:feature_class":"P",
    "gn:feature_code":"PPL",
    "gn:name":"Bachicha",
    "gn:population":0,
    "gn:timezone":"Asia/Karachi",
    "iso:country":"PK",
    "name:und_x_variant":[
        "Byicha"
    ],
    "wof:name":"Bachicha",
    "wof:placetype":"locality"
},
  "geometry": {"coordinates":[75.3329,35.59],"type":"Point"}
}