{
  "type": "Feature",
  "properties": {
    "gn:admin1_code":"04",
    "gn:asciiname":"Kot Mian Khan",
    "gn:country_code":"PK",
    "gn:dem":209,
    "gn:feature_class":"P",
    "gn:feature_code":"PPL",
    "gn:name":"Kot Mian Khan",
    "gn:population":0,
    "gn:timezone":"Asia/Karachi",
    "iso:country":"PK",
    "wof:name":"Kot Mian Khan",
    "wof:placetype":"locality"
},
  "geometry": {"coordinates":[73.63564000000002,32.27176],"type":"Point"}
}