{
  "type": "Feature",
  "properties": {
    "gn:admin1_code":"6.0",
    "gn:asciiname":"Gadiwali",
    "gn:country_code":"PK",
    "gn:dem":1941,
    "gn:feature_class":"P",
    "gn:feature_code":"PPL",
    "gn:name":"Gadiwali",
    "gn:population":0,
    "gn:timezone":"Asia/Karachi",
    "iso:country":"PK",
    "wof:name":"Gadiwali",
    "wof:placetype":"locality"
},
  "geometry": {"coordinates":[74.00371,33.91925],"type":"Point"}
}