{
  "type": "Feature",
  "properties": {
    "gn:admin1_code":"04",
    "gn:asciiname":"Rapal",
    "gn:country_code":"PK",
    "gn:dem":183,
    "gn:feature_class":"P",
    "gn:feature_code":"PPL",
    "gn:name":"Rapal",
    "gn:population":0,
    "gn:timezone":"Asia/Karachi",
    "iso:country":"PK",
    "name:gla_x_preferred":[
        "Rapal"
    ],
    "name:und_x_variant":[
        "Rup\u0101l"
    ],
    "wof:name":"Rapal",
    "wof:placetype":"locality"
},
  "geometry": {"coordinates":[74.16053000000002,30.66718],"type":"Point"}
}