{
  "type": "Feature",
  "properties": {
    "gn:admin1_code":"4.0",
    "gn:asciiname":"Ghorewala",
    "gn:country_code":"PK",
    "gn:dem":92,
    "gn:feature_class":"P",
    "gn:feature_code":"PPL",
    "gn:name":"Ghorew\u0101la",
    "gn:population":0,
    "gn:timezone":"Asia/Karachi",
    "iso:country":"PK",
    "wof:name":"Ghorewala",
    "wof:placetype":"locality"
},
  "geometry": {"coordinates":[70.81586999999998,28.79859],"type":"Point"}
}