{
  "type": "Feature",
  "properties": {
    "gn:admin1_code":"4.0",
    "gn:asciiname":"Jharkal",
    "gn:country_code":"PK",
    "gn:dem":163,
    "gn:feature_class":"P",
    "gn:feature_code":"PPL",
    "gn:name":"Jharkal",
    "gn:population":0,
    "gn:timezone":"Asia/Karachi",
    "iso:country":"PK",
    "name:fas_x_preferred":[
        "\u062c\u0647\u0631\u06a9\u0627\u0644"
    ],
    "name:und_x_variant":[
        "Jharkil Nasheb",
        "Jharrkil",
        "Jharkil",
        "Jharkal"
    ],
    "name:urd_x_preferred":[
        "\u062c\u06be\u0631\u06a9\u0627\u0644"
    ],
    "wof:name":"Jharkal",
    "wof:placetype":"locality"
},
  "geometry": {"coordinates":[70.99733000000001,31.35504],"type":"Point"}
}