{
  "type": "Feature",
  "properties": {
    "gn:admin1_code":"4.0",
    "gn:asciiname":"Jharkal",
    "gn:country_code":"PK",
    "gn:dem":163,
    "gn:feature_class":"P",
    "gn:feature_code":"PPL",
    "gn:name":"Jharkal",
    "gn:population":0,
    "gn:timezone":"Asia/Karachi",
    "iso:country":"PK",
    "name:und_x_variant":[
        "Jharkil Nasheb",
        "Jharrkil",
        "Jharkil",
        "Jharkal"
    ],
    "wof:name":"Jharkal",
    "wof:placetype":"locality"
},
  "geometry": {"coordinates":[70.99733000000001,31.35504],"type":"Point"}
}