{
  "type": "Feature",
  "properties": {
    "gn:admin1_code":"4.0",
    "gn:asciiname":"Jehangir da Tube Well",
    "gn:country_code":"PK",
    "gn:dem":176,
    "gn:feature_class":"P",
    "gn:feature_code":"PPL",
    "gn:name":"Jehangir da Tube Well",
    "gn:population":0,
    "gn:timezone":"Asia/Karachi",
    "iso:country":"PK",
    "wof:name":"Jehangir da Tube Well",
    "wof:placetype":"locality"
},
  "geometry": {"coordinates":[73.89599,30.46023],"type":"Point"}
}