{
  "type": "Feature",
  "properties": {
    "gn:admin1_code":"3",
    "gn:asciiname":"Batgram",
    "gn:country_code":"PK",
    "gn:dem":1358,
    "gn:feature_class":"P",
    "gn:feature_code":"PPL",
    "gn:name":"Batgram",
    "gn:population":0,
    "gn:timezone":"Asia/Karachi",
    "iso:country":"PK",
    "wof:name":"Batgram",
    "wof:placetype":"locality"
},
  "geometry": {"coordinates":[72.8135,34.94965999999999],"type":"Point"}
}