{
  "type": "Feature",
  "properties": {
    "gn:admin1_code":"3",
    "gn:asciiname":"Batilai",
    "gn:country_code":"PK",
    "gn:dem":629,
    "gn:feature_class":"P",
    "gn:feature_code":"PPL",
    "gn:name":"Batilai",
    "gn:population":0,
    "gn:timezone":"Asia/Karachi",
    "iso:country":"PK",
    "wof:name":"Batilai",
    "wof:placetype":"locality"
},
  "geometry": {"coordinates":[72.89875000000001,34.87607],"type":"Point"}
}