{
  "type": "Feature",
  "properties": {
    "gn:admin1_code":"03",
    "gn:asciiname":"Gir Gat",
    "gn:country_code":"PK",
    "gn:dem":834,
    "gn:feature_class":"P",
    "gn:feature_code":"PPL",
    "gn:name":"Gir Gat",
    "gn:population":0,
    "gn:timezone":"Asia/Karachi",
    "iso:country":"PK",
    "name:eng_x_preferred":[
        "Gurgia"
    ],
    "wof:name":"Gir Gat",
    "wof:placetype":"locality"
},
  "geometry": {"coordinates":[71.87272,34.84637],"type":"Point"}
}