{
  "type": "Feature",
  "properties": {
    "gn:admin1_code":"05",
    "gn:asciiname":"Goth Jhal",
    "gn:country_code":"PK",
    "gn:dem":0,
    "gn:feature_class":"P",
    "gn:feature_code":"PPL",
    "gn:name":"Goth Jhal",
    "gn:population":0,
    "gn:timezone":"Asia/Karachi",
    "iso:country":"PK",
    "name:und_x_variant":[
        "Goth Jhab"
    ],
    "wof:name":"Goth Jhal",
    "wof:placetype":"locality"
},
  "geometry": {"coordinates":[67.43321,24.12944],"type":"Point"}
}