{
  "type": "Feature",
  "properties": {
    "gn:admin1_code":"2.0",
    "gn:asciiname":"Karezgai",
    "gn:country_code":"PK",
    "gn:dem":2191,
    "gn:feature_class":"P",
    "gn:feature_code":"PPL",
    "gn:name":"Karezgai",
    "gn:population":0,
    "gn:timezone":"Asia/Karachi",
    "iso:country":"PK",
    "wof:name":"Karezgai",
    "wof:placetype":"locality"
},
  "geometry": {"coordinates":[66.69215,30.98365],"type":"Point"}
}