{
  "type": "Feature",
  "properties": {
    "gn:admin1_code":"2.0",
    "gn:asciiname":"Badai Khel Kili",
    "gn:country_code":"PK",
    "gn:dem":1610,
    "gn:feature_class":"P",
    "gn:feature_code":"PPL",
    "gn:name":"Badai Khel Kili",
    "gn:population":0,
    "gn:timezone":"Asia/Karachi",
    "iso:country":"PK",
    "name:und_x_variant":[
        "Gadai Khel Kili"
    ],
    "wof:name":"Badai Khel Kili",
    "wof:placetype":"locality"
},
  "geometry": {"coordinates":[69.3642,31.52759],"type":"Point"}
}