{
  "type": "Feature",
  "properties": {
    "gn:admin1_code":"4",
    "gn:asciiname":"Kikarwala",
    "gn:country_code":"PK",
    "gn:dem":123,
    "gn:feature_class":"P",
    "gn:feature_code":"PPL",
    "gn:name":"Kikarwala",
    "gn:population":0,
    "gn:timezone":"Asia/Karachi",
    "iso:country":"PK",
    "wof:name":"Kikarwala",
    "wof:placetype":"locality"
},
  "geometry": {"coordinates":[71.68482,30.02813],"type":"Point"}
}