{
  "type": "Feature",
  "properties": {
    "gn:admin1_code":"6",
    "gn:asciiname":"Sangot",
    "gn:country_code":"PK",
    "gn:dem":375,
    "gn:feature_class":"P",
    "gn:feature_code":"PPL",
    "gn:name":"Sangot",
    "gn:population":0,
    "gn:timezone":"Asia/Karachi",
    "iso:country":"PK",
    "name:und_x_variant":[
        "Sanghot",
        "Sangot"
    ],
    "wof:name":"Sangot",
    "wof:placetype":"locality"
},
  "geometry": {"coordinates":[73.76199,33.16341],"type":"Point"}
}