{
  "type": "Feature",
  "properties": {
    "gn:admin1_code":"4.0",
    "gn:asciiname":"Barakpur",
    "gn:country_code":"PK",
    "gn:dem":200,
    "gn:feature_class":"P",
    "gn:feature_code":"PPL",
    "gn:name":"Barakpur",
    "gn:population":0,
    "gn:timezone":"Asia/Karachi",
    "iso:country":"PK",
    "name:und_x_variant":[
        "Barkpur"
    ],
    "wof:name":"Barakpur",
    "wof:placetype":"locality"
},
  "geometry": {"coordinates":[73.38500999999999,31.91752],"type":"Point"}
}