{
  "type": "Feature",
  "properties": {
    "gn:admin1_code":"1.0",
    "gn:asciiname":"Shinak Kili",
    "gn:country_code":"PK",
    "gn:dem":1061,
    "gn:feature_class":"P",
    "gn:feature_code":"PPL",
    "gn:name":"Shinak Kili",
    "gn:population":0,
    "gn:timezone":"Asia/Karachi",
    "iso:country":"PK",
    "wof:name":"Shinak Kili",
    "wof:placetype":"locality"
},
  "geometry": {"coordinates":[70.31581,33.60944],"type":"Point"}
}