{
  "type": "Feature",
  "properties": {
    "gn:admin1_code":"3.0",
    "gn:asciiname":"Basak",
    "gn:country_code":"PK",
    "gn:dem":742,
    "gn:feature_class":"P",
    "gn:feature_code":"PPL",
    "gn:name":"Basak",
    "gn:population":0,
    "gn:timezone":"Asia/Karachi",
    "iso:country":"PK",
    "name:ceb_x_preferred":[
        "Basak"
    ],
    "name:ita_x_preferred":[
        "Basak"
    ],
    "name:swe_x_preferred":[
        "Basak"
    ],
    "wof:name":"Basak",
    "wof:placetype":"locality"
},
  "geometry": {"coordinates":[71.76448000000001,34.65096],"type":"Point"}
}