{
  "type": "Feature",
  "properties": {
    "gn:admin1_code":"7.0",
    "gn:asciiname":"Balti",
    "gn:country_code":"PK",
    "gn:dem":2809,
    "gn:feature_class":"P",
    "gn:feature_code":"PPL",
    "gn:name":"Balti",
    "gn:population":0,
    "gn:timezone":"Asia/Karachi",
    "iso:country":"PK",
    "name:ara_x_preferred":[
        "\u0628\u0627\u0644\u062a\u064a"
    ],
    "name:ces_x_preferred":[
        "Balti"
    ],
    "name:deu_x_preferred":[
        "Balti"
    ],
    "name:fra_x_preferred":[
        "Balti"
    ],
    "name:hrv_x_preferred":[
        "Balti"
    ],
    "name:ita_x_preferred":[
        "Balti"
    ],
    "name:nds_x_preferred":[
        "Balti"
    ],
    "name:nld_x_preferred":[
        "Balti"
    ],
    "name:nno_x_preferred":[
        "Balti"
    ],
    "name:nor_x_preferred":[
        "Balti"
    ],
    "name:rus_x_preferred":[
        "\u0411\u0430\u043b\u0442\u0438"
    ],
    "name:slk_x_preferred":[
        "Balti"
    ],
    "name:srp_x_preferred":[
        "\u0411\u0430\u043b\u0442\u0438"
    ],
    "name:urd_x_preferred":[
        "\u0628\u0644\u062a\u06cc(\u0636\u062f \u0627\u0628\u06c1\u0627\u0645)"
    ],
    "wof:name":"Balti",
    "wof:placetype":"locality"
},
  "geometry": {"coordinates":[73.3186,36.11003],"type":"Point"}
}