{
  "type": "Feature",
  "properties": {
    "gn:admin1_code":"7.0",
    "gn:asciiname":"Balti",
    "gn:country_code":"PK",
    "gn:dem":2809,
    "gn:feature_class":"P",
    "gn:feature_code":"PPL",
    "gn:name":"Balti",
    "gn:population":0,
    "gn:timezone":"Asia/Karachi",
    "iso:country":"PK",
    "wof:name":"Balti",
    "wof:placetype":"locality"
},
  "geometry": {"coordinates":[73.3186,36.11003],"type":"Point"}
}