{
  "type": "Feature",
  "properties": {
    "gn:admin1_code":"3.0",
    "gn:asciiname":"Mohammadabad",
    "gn:country_code":"PK",
    "gn:dem":366,
    "gn:feature_class":"P",
    "gn:feature_code":"PPL",
    "gn:name":"Mohammadabad",
    "gn:population":0,
    "gn:timezone":"Asia/Karachi",
    "iso:country":"PK",
    "name:und_x_variant":[
        "Purdu Tal\u0101o"
    ],
    "wof:name":"Mohammadabad",
    "wof:placetype":"locality"
},
  "geometry": {"coordinates":[71.72138000000002,33.92072],"type":"Point"}
}