{
  "type": "Feature",
  "properties": {
    "gn:admin1_code":"3.0",
    "gn:asciiname":"Mohammadabad",
    "gn:country_code":"PK",
    "gn:dem":366,
    "gn:feature_class":"P",
    "gn:feature_code":"PPL",
    "gn:name":"Mohammadabad",
    "gn:population":0,
    "gn:timezone":"Asia/Karachi",
    "iso:country":"PK",
    "name:aze_x_preferred":[
        "M\u0259h\u0259mm\u0259dabad"
    ],
    "name:bpy_x_preferred":[
        "\u09ae\u09cb\u09b9\u09be\u09ae\u09cd\u09ae\u09a6\u09be\u09ac\u09be\u09a6"
    ],
    "name:ceb_x_preferred":[
        "Mohammadabad"
    ],
    "name:new_x_preferred":[
        "\u092e\u094b\u0939\u092e\u094d\u092e\u0926\u093e\u092c\u093e\u0926"
    ],
    "name:nld_x_preferred":[
        "Mohammadabad"
    ],
    "name:pol_x_preferred":[
        "Mohammadabad"
    ],
    "name:swe_x_preferred":[
        "Mohammadabad"
    ],
    "name:und_x_variant":[
        "Purdu Tal\u0101o"
    ],
    "wof:name":"Mohammadabad",
    "wof:placetype":"locality"
},
  "geometry": {"coordinates":[71.72138000000002,33.92072],"type":"Point"}
}