{
  "type": "Feature",
  "properties": {
    "gn:admin1_code":"04",
    "gn:asciiname":"Sohawara",
    "gn:country_code":"PK",
    "gn:dem":273,
    "gn:feature_class":"P",
    "gn:feature_code":"PPL",
    "gn:name":"Sohawara",
    "gn:population":0,
    "gn:timezone":"Asia/Karachi",
    "iso:country":"PK",
    "name:und_x_variant":[
        "Sohawera",
        "Sohawara"
    ],
    "wof:name":"Sohawara",
    "wof:placetype":"locality"
},
  "geometry": {"coordinates":[75.10415,32.3089],"type":"Point"}
}