{
  "type": "Feature",
  "properties": {
    "gn:admin1_code":"3.0",
    "gn:asciiname":"Bher",
    "gn:country_code":"PK",
    "gn:dem":549,
    "gn:feature_class":"P",
    "gn:feature_code":"PPL",
    "gn:name":"Bher",
    "gn:population":0,
    "gn:timezone":"Asia/Karachi",
    "iso:country":"PK",
    "name:und_x_variant":[
        "Bhar",
        "Bher"
    ],
    "wof:name":"Bher",
    "wof:placetype":"locality"
},
  "geometry": {"coordinates":[72.79987,34.5834],"type":"Point"}
}