{
  "type": "Feature",
  "properties": {
    "gn:admin1_code":"4.0",
    "gn:asciiname":"Dhok Mohri",
    "gn:country_code":"PK",
    "gn:dem":453,
    "gn:feature_class":"P",
    "gn:feature_code":"PPL",
    "gn:name":"Dhok Mohri",
    "gn:population":0,
    "gn:timezone":"Asia/Karachi",
    "iso:country":"PK",
    "wof:name":"Dhok Mohri",
    "wof:placetype":"locality"
},
  "geometry": {"coordinates":[73.40954000000001,33.28612],"type":"Point"}
}