{
  "type": "Feature",
  "properties": {
    "gn:admin1_code":"2.0",
    "gn:asciiname":"Tara Khula",
    "gn:country_code":"PK",
    "gn:dem":1886,
    "gn:feature_class":"P",
    "gn:feature_code":"PPL",
    "gn:name":"Tara Khula",
    "gn:population":0,
    "gn:timezone":"Asia/Karachi",
    "iso:country":"PK",
    "wof:name":"Tara Khula",
    "wof:placetype":"locality"
},
  "geometry": {"coordinates":[69.07044999999999,31.39064],"type":"Point"}
}