{
  "type": "Feature",
  "properties": {
    "gn:admin1_code":"3",
    "gn:asciiname":"Ubari",
    "gn:country_code":"PK",
    "gn:dem":1585,
    "gn:feature_class":"P",
    "gn:feature_code":"PPL",
    "gn:name":"Ubari",
    "gn:population":0,
    "gn:timezone":"Asia/Karachi",
    "iso:country":"PK",
    "name:ara_x_preferred":[
        "\u0623\u0648\u0628\u0627\u0631\u064a"
    ],
    "name:azb_x_preferred":[
        "\u0627\u0648\u0628\u0627\u0631\u06cc"
    ],
    "name:bel_x_preferred":[
        "\u0410\u045e\u0431\u0430\u0440\u044b"
    ],
    "name:bul_x_preferred":[
        "\u0410\u0443\u0431\u0430\u0440\u0438"
    ],
    "name:cat_x_preferred":[
        "Ubari"
    ],
    "name:deu_x_preferred":[
        "Ubari"
    ],
    "name:epo_x_preferred":[
        "A\u016dbari"
    ],
    "name:fas_x_preferred":[
        "\u0627\u0648\u0628\u0627\u0631\u06cc"
    ],
    "name:fra_x_preferred":[
        "Oubari"
    ],
    "name:hun_x_preferred":[
        "Aub\u00e1ri"
    ],
    "name:ita_x_preferred":[
        "Ubari"
    ],
    "name:jpn_x_preferred":[
        "\u30a6\u30d0\u30ea"
    ],
    "name:kat_x_preferred":[
        "\u10d0\u10d5\u10d1\u10d0\u10e0\u10d8"
    ],
    "name:kor_x_preferred":[
        "\uc6b0\ubc14\ub9ac"
    ],
    "name:lit_x_preferred":[
        "Ubaris"
    ],
    "name:pol_x_preferred":[
        "Aubari"
    ],
    "name:por_x_preferred":[
        "Ubari"
    ],
    "name:ron_x_preferred":[
        "Ubari"
    ],
    "name:rus_x_preferred":[
        "\u0410\u0443\u0431\u0430\u0440\u0438"
    ],
    "name:sco_x_preferred":[
        "Awbari"
    ],
    "name:spa_x_preferred":[
        "Ubari"
    ],
    "name:tur_x_preferred":[
        "Ubari"
    ],
    "name:ukr_x_preferred":[
        "\u0410\u0443\u0431\u0430\u0440\u0456"
    ],
    "name:urd_x_preferred":[
        "\u0627\u0648\u0628\u0627\u0631\u06cc"
    ],
    "name:vie_x_preferred":[
        "Ubari"
    ],
    "name:vol_x_preferred":[
        "\u00c4ubari"
    ],
    "wof:name":"Ubari",
    "wof:placetype":"locality"
},
  "geometry": {"coordinates":[73.39291999999998,34.58051],"type":"Point"}
}