{
  "type": "Feature",
  "properties": {
    "gn:admin1_code":"2.0",
    "gn:asciiname":"Kili Nur Bakhsh",
    "gn:country_code":"PK",
    "gn:dem":1049,
    "gn:feature_class":"P",
    "gn:feature_code":"PPL",
    "gn:name":"Kili Nur Bakhsh",
    "gn:population":0,
    "gn:timezone":"Asia/Karachi",
    "iso:country":"PK",
    "wof:name":"Kili Nur Bakhsh",
    "wof:placetype":"locality"
},
  "geometry": {"coordinates":[64.2253,28.58524],"type":"Point"}
}