{
  "type": "Feature",
  "properties": {
    "gn:admin1_code":"3.0",
    "gn:asciiname":"Kushi Kot",
    "gn:country_code":"PK",
    "gn:dem":1971,
    "gn:feature_class":"P",
    "gn:feature_code":"PPL",
    "gn:name":"Kushi Kot",
    "gn:population":0,
    "gn:timezone":"Asia/Karachi",
    "iso:country":"PK",
    "name:eng_x_preferred":[
        "Khushikot"
    ],
    "wof:name":"Kushi Kot",
    "wof:placetype":"locality"
},
  "geometry": {"coordinates":[73.41311999999998,33.97644],"type":"Point"}
}