{
  "type": "Feature",
  "properties": {
    "gn:admin1_code":"5",
    "gn:asciiname":"Damranwari Takri",
    "gn:country_code":"PK",
    "gn:dem":83,
    "gn:feature_class":"P",
    "gn:feature_code":"PPL",
    "gn:name":"Damranwari Takri",
    "gn:population":0,
    "gn:timezone":"Asia/Karachi",
    "iso:country":"PK",
    "wof:name":"Damranwari Takri",
    "wof:placetype":"locality"
},
  "geometry": {"coordinates":[68.77338,27.16009],"type":"Point"}
}