{
  "type": "Feature",
  "properties": {
    "gn:admin1_code":"2.0",
    "gn:asciiname":"Gonga",
    "gn:country_code":"PK",
    "gn:dem":1305,
    "gn:feature_class":"P",
    "gn:feature_code":"PPL",
    "gn:name":"Gonga",
    "gn:population":0,
    "gn:timezone":"Asia/Karachi",
    "iso:country":"PK",
    "name:ceb_x_preferred":[
        "Gonga"
    ],
    "name:fra_x_preferred":[
        "Gonga"
    ],
    "name:swe_x_preferred":[
        "Gonga"
    ],
    "name:und_x_variant":[
        "G\u016bnga"
    ],
    "wof:name":"Gonga",
    "wof:placetype":"locality"
},
  "geometry": {"coordinates":[66.5217,27.77008],"type":"Point"}
}