{
  "type": "Feature",
  "properties": {
    "gn:admin1_code":"2",
    "gn:asciiname":"Phullemasi",
    "gn:country_code":"PK",
    "gn:dem":1921,
    "gn:feature_class":"P",
    "gn:feature_code":"PPL",
    "gn:name":"Phullemasi",
    "gn:population":0,
    "gn:timezone":"Asia/Karachi",
    "iso:country":"PK",
    "name:und_x_variant":[
        "Phullemaser"
    ],
    "wof:name":"Phullemasi",
    "wof:placetype":"locality"
},
  "geometry": {"coordinates":[66.55580999999999,29.09576],"type":"Point"}
}