{
  "type": "Feature",
  "properties": {
    "gn:admin1_code":"1.0",
    "gn:asciiname":"Jalal Kor",
    "gn:country_code":"PK",
    "gn:dem":362,
    "gn:feature_class":"P",
    "gn:feature_code":"PPL",
    "gn:name":"Jalal Kor",
    "gn:population":0,
    "gn:timezone":"Asia/Karachi",
    "iso:country":"PK",
    "wof:name":"Jalal Kor",
    "wof:placetype":"locality"
},
  "geometry": {"coordinates":[71.44471999999998,34.2125],"type":"Point"}
}