{
  "type": "Feature",
  "properties": {
    "gn:admin1_code":"4.0",
    "gn:asciiname":"Kamra",
    "gn:country_code":"PK",
    "gn:dem":486,
    "gn:feature_class":"P",
    "gn:feature_code":"PPL",
    "gn:name":"Kamra",
    "gn:population":0,
    "gn:timezone":"Asia/Karachi",
    "iso:country":"PK",
    "name:ara_x_preferred":[
        "\u0643\u0627\u0645\u0631\u0647"
    ],
    "name:fas_x_preferred":[
        "\u06a9\u0627\u0645\u0631\u0647"
    ],
    "name:fra_x_preferred":[
        "Kamra"
    ],
    "name:pnb_x_preferred":[
        "\u06a9\u0627\u0645\u0631\u0627"
    ],
    "name:por_x_preferred":[
        "Kamra"
    ],
    "name:rus_x_preferred":[
        "\u041a\u0430\u043c\u0440\u0430"
    ],
    "name:spa_x_preferred":[
        "Kamra"
    ],
    "name:und_x_variant":[
        "K\u0101mra"
    ],
    "name:urd_x_preferred":[
        "\u06a9\u0627\u0645\u0631\u06c1"
    ],
    "wof:name":"Kamra",
    "wof:placetype":"locality"
},
  "geometry": {"coordinates":[72.80757,33.81012],"type":"Point"}
}