{
  "type": "Feature",
  "properties": {
    "gn:admin1_code":"4.0",
    "gn:asciiname":"Kamra",
    "gn:country_code":"PK",
    "gn:dem":486,
    "gn:feature_class":"P",
    "gn:feature_code":"PPL",
    "gn:name":"Kamra",
    "gn:population":0,
    "gn:timezone":"Asia/Karachi",
    "iso:country":"PK",
    "name:und_x_variant":[
        "K\u0101mra"
    ],
    "wof:name":"Kamra",
    "wof:placetype":"locality"
},
  "geometry": {"coordinates":[72.80757,33.81012],"type":"Point"}
}