{
  "type": "Feature",
  "properties": {
    "gn:admin1_code":"4",
    "gn:asciiname":"Chah Adduwala",
    "gn:country_code":"PK",
    "gn:dem":120,
    "gn:feature_class":"P",
    "gn:feature_code":"PPL",
    "gn:name":"Chah Adduwala",
    "gn:population":0,
    "gn:timezone":"Asia/Karachi",
    "iso:country":"PK",
    "name:und_x_variant":[
        "Adduw\u0101la",
        "\u0100dow\u0101la",
        "Chah Adduwala"
    ],
    "wof:name":"Chah Adduwala",
    "wof:placetype":"locality"
},
  "geometry": {"coordinates":[71.56943000000003,29.74285],"type":"Point"}
}