{
  "type": "Feature",
  "properties": {
    "gn:admin1_code":"7.0",
    "gn:asciiname":"Ghachar",
    "gn:country_code":"PK",
    "gn:dem":2286,
    "gn:feature_class":"P",
    "gn:feature_code":"PPL",
    "gn:name":"Ghachar",
    "gn:population":0,
    "gn:timezone":"Asia/Karachi",
    "iso:country":"PK",
    "wof:name":"Ghachar",
    "wof:placetype":"locality"
},
  "geometry": {"coordinates":[73.96639999999999,35.32488],"type":"Point"}
}