{
  "type": "Feature",
  "properties": {
    "gn:admin1_code":"5.0",
    "gn:asciiname":"Bagdao Tar",
    "gn:country_code":"PK",
    "gn:dem":55,
    "gn:feature_class":"P",
    "gn:feature_code":"PPL",
    "gn:name":"Bagdao Tar",
    "gn:population":0,
    "gn:timezone":"Asia/Karachi",
    "iso:country":"PK",
    "wof:name":"Bagdao Tar",
    "wof:placetype":"locality"
},
  "geometry": {"coordinates":[69.67917,26.27949000000001],"type":"Point"}
}