{
  "type": "Feature",
  "properties": {
    "gn:admin1_code":"6",
    "gn:asciiname":"Hil Khurd",
    "gn:country_code":"PK",
    "gn:dem":540,
    "gn:feature_class":"P",
    "gn:feature_code":"PPL",
    "gn:name":"Hil Khurd",
    "gn:population":0,
    "gn:timezone":"Asia/Karachi",
    "iso:country":"PK",
    "wof:name":"Hil Khurd",
    "wof:placetype":"locality"
},
  "geometry": {"coordinates":[73.8776,33.51146],"type":"Point"}
}