{
  "type": "Feature",
  "properties": {
    "gn:admin1_code":"4",
    "gn:asciiname":"Sawanewala Khu",
    "gn:country_code":"PK",
    "gn:dem":171,
    "gn:feature_class":"P",
    "gn:feature_code":"PPL",
    "gn:name":"Sawanewala Khu",
    "gn:population":0,
    "gn:timezone":"Asia/Karachi",
    "iso:country":"PK",
    "name:und_x_variant":[
        "Wary\u0101mw\u0101la Khu",
        "Bary\u0101mw\u0101la Khu",
        "Sawanewala Khu"
    ],
    "wof:name":"Sawanewala Khu",
    "wof:placetype":"locality"
},
  "geometry": {"coordinates":[72.06286999999998,31.55535],"type":"Point"}
}