{
  "type": "Feature",
  "properties": {
    "gn:admin1_code":"3.0",
    "gn:asciiname":"Garah Ahmad",
    "gn:country_code":"PK",
    "gn:dem":218,
    "gn:feature_class":"P",
    "gn:feature_code":"PPL",
    "gn:name":"Garah Ahmad",
    "gn:population":0,
    "gn:timezone":"Asia/Karachi",
    "iso:country":"PK",
    "name:und_x_variant":[
        "Gara Ahmad"
    ],
    "wof:name":"Garah Ahmad",
    "wof:placetype":"locality"
},
  "geometry": {"coordinates":[70.4318,31.56798],"type":"Point"}
}