{
  "type": "Feature",
  "properties": {
    "gn:admin1_code":"2.0",
    "gn:asciiname":"Goth Haji Ahmad",
    "gn:country_code":"PK",
    "gn:dem":21,
    "gn:feature_class":"P",
    "gn:feature_code":"PPL",
    "gn:name":"Goth Haji Ahmad",
    "gn:population":0,
    "gn:timezone":"Asia/Karachi",
    "iso:country":"PK",
    "name:eng_x_preferred":[
        "Goth H\u0101ji Ahmed"
    ],
    "wof:name":"Goth Haji Ahmad",
    "wof:placetype":"locality"
},
  "geometry": {"coordinates":[66.63785,25.40897],"type":"Point"}
}