{
  "type": "Feature",
  "properties": {
    "gn:admin1_code":"2.0",
    "gn:asciiname":"Sergi",
    "gn:country_code":"PK",
    "gn:dem":514,
    "gn:feature_class":"P",
    "gn:feature_code":"PPL",
    "gn:name":"Sergi",
    "gn:population":0,
    "gn:timezone":"Asia/Karachi",
    "iso:country":"PK",
    "wof:name":"Sergi",
    "wof:placetype":"locality"
},
  "geometry": {"coordinates":[63.31177,27.99701],"type":"Point"}
}