{
  "type": "Feature",
  "properties": {
    "gn:admin1_code":"2.0",
    "gn:asciiname":"Kili Shomozai",
    "gn:country_code":"PK",
    "gn:dem":2091,
    "gn:feature_class":"P",
    "gn:feature_code":"PPL",
    "gn:name":"Kili Shomozai",
    "gn:population":0,
    "gn:timezone":"Asia/Karachi",
    "iso:country":"PK",
    "wof:name":"Kili Shomozai",
    "wof:placetype":"locality"
},
  "geometry": {"coordinates":[67.17703,30.2736],"type":"Point"}
}