{
  "type": "Feature",
  "properties": {
    "gn:admin1_code":"1.0",
    "gn:asciiname":"Tauda China",
    "gn:country_code":"PK",
    "gn:dem":941,
    "gn:feature_class":"P",
    "gn:feature_code":"PPL",
    "gn:name":"Tauda China",
    "gn:population":0,
    "gn:timezone":"Asia/Karachi",
    "iso:country":"PK",
    "name:und_x_variant":[
        "Talo Kunj",
        "T\u0101lo Kunj Kili"
    ],
    "wof:name":"Tauda China",
    "wof:placetype":"locality"
},
  "geometry": {"coordinates":[70.36636,33.49355],"type":"Point"}
}