{
  "type": "Feature",
  "properties": {
    "gn:admin1_code":"4",
    "gn:asciiname":"Lahorian",
    "gn:country_code":"PK",
    "gn:dem":263,
    "gn:feature_class":"P",
    "gn:feature_code":"PPL",
    "gn:name":"Lahorian",
    "gn:population":0,
    "gn:timezone":"Asia/Karachi",
    "iso:country":"PK",
    "wof:name":"Lahorian",
    "wof:placetype":"locality"
},
  "geometry": {"coordinates":[74.12724,32.74584],"type":"Point"}
}