{
  "type": "Feature",
  "properties": {
    "gn:admin1_code":"04",
    "gn:asciiname":"Lalial",
    "gn:country_code":"PK",
    "gn:dem":535,
    "gn:feature_class":"P",
    "gn:feature_code":"PPL",
    "gn:name":"Lalial",
    "gn:population":0,
    "gn:timezone":"Asia/Karachi",
    "iso:country":"PK",
    "name:und_x_variant":[
        "Lalh\u0101l"
    ],
    "wof:name":"Lalial",
    "wof:placetype":"locality"
},
  "geometry": {"coordinates":[73.19424000000002,33.22521],"type":"Point"}
}