{
  "type": "Feature",
  "properties": {
    "gn:admin1_code":"4.0",
    "gn:asciiname":"Tibbi Dahkawan",
    "gn:country_code":"PK",
    "gn:dem":104,
    "gn:feature_class":"P",
    "gn:feature_code":"PPL",
    "gn:name":"Tibbi Dahkawan",
    "gn:population":0,
    "gn:timezone":"Asia/Karachi",
    "iso:country":"PK",
    "name:und_x_variant":[
        "Tibba Dahkawan"
    ],
    "wof:name":"Tibbi Dahkawan",
    "wof:placetype":"locality"
},
  "geometry": {"coordinates":[71.28307,29.17522],"type":"Point"}
}