{
  "type": "Feature",
  "properties": {
    "gn:admin1_code":"7.0",
    "gn:asciiname":"Karambar Ilaq",
    "gn:country_code":"PK",
    "gn:dem":3307,
    "gn:feature_class":"P",
    "gn:feature_code":"PPL",
    "gn:name":"Karambar Ilaq",
    "gn:population":0,
    "gn:timezone":"Asia/Karachi",
    "iso:country":"PK",
    "wof:name":"Karambar Ilaq",
    "wof:placetype":"locality"
},
  "geometry": {"coordinates":[74.13339999999999,36.6368],"type":"Point"}
}