{
  "type": "Feature",
  "properties": {
    "gn:admin1_code":"4.0",
    "gn:asciiname":"Tibba Chak One Hundred Two - Six Right",
    "gn:country_code":"PK",
    "gn:dem":155,
    "gn:feature_class":"P",
    "gn:feature_code":"PPL",
    "gn:name":"Tibba Chak One Hundred Two - Six Right",
    "gn:population":0,
    "gn:timezone":"Asia/Karachi",
    "iso:country":"PK",
    "wof:name":"Tibba Chak One Hundred Two - Six Right",
    "wof:placetype":"locality"
},
  "geometry": {"coordinates":[73.03726999999998,29.51756],"type":"Point"}
}