{
  "type": "Feature",
  "properties": {
    "gn:admin1_code":"4.0",
    "gn:asciiname":"Kartarpur Malhian",
    "gn:country_code":"PK",
    "gn:dem":215,
    "gn:feature_class":"P",
    "gn:feature_code":"PPL",
    "gn:name":"Kartarpur Malhian",
    "gn:population":0,
    "gn:timezone":"Asia/Karachi",
    "iso:country":"PK",
    "name:und_x_variant":[
        "Gad\u0101nw\u0101la"
    ],
    "wof:name":"Kartarpur Malhian",
    "wof:placetype":"locality"
},
  "geometry": {"coordinates":[73.93316999999998,31.94002],"type":"Point"}
}