{
  "type": "Feature",
  "properties": {
    "gn:admin1_code":"2.0",
    "gn:asciiname":"Kili Atta Muhammad",
    "gn:country_code":"PK",
    "gn:dem":1317,
    "gn:feature_class":"P",
    "gn:feature_code":"PPL",
    "gn:name":"Kili Atta Muhammad",
    "gn:population":0,
    "gn:timezone":"Asia/Karachi",
    "iso:country":"PK",
    "name:und_x_variant":[
        "Kili H\u0101ji Atta Muhammad"
    ],
    "wof:name":"Kili Atta Muhammad",
    "wof:placetype":"locality"
},
  "geometry": {"coordinates":[66.47776999999999,27.28235],"type":"Point"}
}