{
  "type": "Feature",
  "properties": {
    "gn:admin1_code":"04",
    "gn:asciiname":"Thatta Kamira",
    "gn:country_code":"PK",
    "gn:dem":163,
    "gn:feature_class":"P",
    "gn:feature_code":"PPL",
    "gn:name":"Thatta Kamira",
    "gn:population":0,
    "gn:timezone":"Asia/Karachi",
    "iso:country":"PK",
    "name:und_x_variant":[
        "Thatta Kam\u012bra"
    ],
    "wof:name":"Thatta Kamira",
    "wof:placetype":"locality"
},
  "geometry": {"coordinates":[72.22532,31.64294000000001],"type":"Point"}
}