{
  "type": "Feature",
  "properties": {
    "gn:admin1_code":"3",
    "gn:asciiname":"Kanadaogai",
    "gn:country_code":"PK",
    "gn:dem":1351,
    "gn:feature_class":"P",
    "gn:feature_code":"PPL",
    "gn:name":"Kanadaogai",
    "gn:population":0,
    "gn:timezone":"Asia/Karachi",
    "iso:country":"PK",
    "name:und_x_variant":[
        "Kandaogai"
    ],
    "wof:name":"Kanadaogai",
    "wof:placetype":"locality"
},
  "geometry": {"coordinates":[72.31855999999998,34.98475],"type":"Point"}
}