{
  "type": "Feature",
  "properties": {
    "gn:admin1_code":"5.0",
    "gn:asciiname":"Haji Jind Kachelo",
    "gn:country_code":"PK",
    "gn:dem":9,
    "gn:feature_class":"P",
    "gn:feature_code":"PPL",
    "gn:name":"Haji Jind Kachelo",
    "gn:population":0,
    "gn:timezone":"Asia/Karachi",
    "iso:country":"PK",
    "wof:name":"Haji Jind Kachelo",
    "wof:placetype":"locality"
},
  "geometry": {"coordinates":[68.93179000000001,24.45213],"type":"Point"}
}