{
  "type": "Feature",
  "properties": {
    "iso:country":"PK",
    "name:eng_x_preferred":[
        "Vehari"
    ],
    "name:epo_x_preferred":[
        "Vehario"
    ],
    "name:fas_x_preferred":[
        "\u0648\u0647\u0627\u0631\u06cc\u060c \u067e\u0627\u06a9\u0633\u062a\u0627\u0646"
    ],
    "name:fra_x_preferred":[
        "Vehari"
    ],
    "name:pnb_x_preferred":[
        "\u0648\u06cc\u06c1\u0627\u0691\u06cc"
    ],
    "name:pus_x_preferred":[
        "\u0648\u0647\u0627\u0693\u064a"
    ],
    "name:rus_x_preferred":[
        "\u0412\u0438\u0445\u0430\u0440\u0438"
    ],
    "name:spa_x_preferred":[
        "Vehari"
    ],
    "name:srp_x_preferred":[
        "\u0412\u0435\u0445\u0430\u0440\u0438"
    ],
    "name:unk_x_variant":[
        "Vih\u0101ri"
    ],
    "name:urd_x_preferred":[
        "\u0648\u06c1\u0627\u0691\u06cc"
    ],
    "qs:gn_country":"PK",
    "qs:gn_fcode":"PPLA2",
    "qs:gn_pop":112840,
    "qs:name":"Vehari",
    "qs:name_adm0":"Pakistan",
    "qs:name_adm1":"Punjab",
    "qs:photos":8,
    "qs:photos_1k":2,
    "qs:photos_9k":1,
    "qs:photos_9r":1,
    "qs:photos_all":8,
    "qs:photos_sr":1,
    "qs:placetype":"Town",
    "qs:pop_sr":"9",
    "qs:woe_adm0":23424922,
    "wd:wordcount":1208,
    "wof:name":"Vehari",
    "wof:placetype":"locality",
    "wof:population":112840
},
  "geometry": {"coordinates":[72.34999999999999,30.03333],"type":"Point"}
}