{
  "type": "Feature",
  "properties": {
    "gn:admin1_code":"4.0",
    "gn:asciiname":"Basti Nohani",
    "gn:country_code":"PK",
    "gn:dem":85,
    "gn:feature_class":"P",
    "gn:feature_code":"PPL",
    "gn:name":"Basti Nohani",
    "gn:population":0,
    "gn:timezone":"Asia/Karachi",
    "iso:country":"PK",
    "name:und_x_variant":[
        "Noh\u0101ni"
    ],
    "wof:name":"Basti Nohani",
    "wof:placetype":"locality"
},
  "geometry": {"coordinates":[70.14265,28.54652],"type":"Point"}
}