{
  "type": "Feature",
  "properties": {
    "gn:admin1_code":"2.0",
    "gn:asciiname":"Adilabad",
    "gn:country_code":"PK",
    "gn:dem":1682,
    "gn:feature_class":"P",
    "gn:feature_code":"PPL",
    "gn:name":"Adilabad",
    "gn:population":0,
    "gn:timezone":"Asia/Karachi",
    "iso:country":"PK",
    "name:ara_x_preferred":[
        "\u0639\u0627\u062f\u0644 \u0623\u0628\u0627\u062f"
    ],
    "name:aze_x_preferred":[
        "Adilabad"
    ],
    "name:ben_x_preferred":[
        "\u0986\u09a6\u09bf\u09b2\u09be\u09ac\u09be\u09a6"
    ],
    "name:bih_x_preferred":[
        "\u0906\u0926\u093f\u0932\u093e\u092c\u093e\u0926"
    ],
    "name:bpy_x_preferred":[
        "\u0986\u09a6\u09bf\u09b2\u09be\u09ac\u09be\u09a6"
    ],
    "name:cat_x_preferred":[
        "Adilabad"
    ],
    "name:ceb_x_preferred":[
        "\u0100dil\u0101b\u0101d"
    ],
    "name:deu_x_preferred":[
        "Adilabad"
    ],
    "name:ell_x_preferred":[
        "\u0391\u03bd\u03c4\u03b9\u03bb\u03b1\u03bc\u03c0\u03ac\u03bd\u03c4"
    ],
    "name:est_x_preferred":[
        "\u0100dil\u0101b\u0101d"
    ],
    "name:fas_x_preferred":[
        "\u0639\u0627\u062f\u0644\u200c\u0622\u0628\u0627\u062f"
    ],
    "name:fin_x_preferred":[
        "Adilabad"
    ],
    "name:fra_x_preferred":[
        "Adilabad"
    ],
    "name:guj_x_preferred":[
        "\u0a86\u0aa6\u0abf\u0ab2\u0abe\u0aac\u0abe\u0aa6"
    ],
    "name:hin_x_preferred":[
        "\u0906\u0926\u093f\u0932\u093e\u092c\u093e\u0926"
    ],
    "name:ind_x_preferred":[
        "Adilabad"
    ],
    "name:ita_x_preferred":[
        "Adilabad"
    ],
    "name:jpn_x_preferred":[
        "\u30a2\u30fc\u30c7\u30a3\u30e9\u30fc\u30d0\u30fc\u30c9"
    ],
    "name:kat_x_preferred":[
        "\u10d0\u10d3\u10d8\u10da\u10d0\u10d1\u10d0\u10d3\u10d8"
    ],
    "name:mar_x_preferred":[
        "\u0906\u0926\u093f\u0932\u093e\u092c\u093e\u0926"
    ],
    "name:min_x_preferred":[
        "Adilabad"
    ],
    "name:mlg_x_preferred":[
        "Adilabad"
    ],
    "name:msa_x_preferred":[
        "Adilabad"
    ],
    "name:nep_x_preferred":[
        "\u0906\u0926\u093f\u0932\u093e\u092c\u093e\u0926"
    ],
    "name:new_x_preferred":[
        "\u0905\u0926\u093f\u0932\u092c\u093e\u0926"
    ],
    "name:nor_x_preferred":[
        "Adilabad"
    ],
    "name:ori_x_preferred":[
        "\u0b06\u0b26\u0b3f\u0b32\u0b3e\u0b2c\u0b3e\u0b26"
    ],
    "name:pam_x_preferred":[
        "Adilabad"
    ],
    "name:pnb_x_preferred":[
        "\u0639\u0627\u062f\u0644 \u0622\u0628\u0627\u062f"
    ],
    "name:pol_x_preferred":[
        "Adilabad"
    ],
    "name:por_x_preferred":[
        "Adilabad"
    ],
    "name:rus_x_preferred":[
        "\u0410\u0434\u0438\u043b\u0430\u0431\u0430\u0434"
    ],
    "name:san_x_preferred":[
        "\u0905\u0926\u093f\u0932\u093e\u092c\u093e\u0926\u094d-\u0928\u0917\u0930\u092e\u094d"
    ],
    "name:spa_x_preferred":[
        "Adilabad"
    ],
    "name:swe_x_preferred":[
        "Adilabad"
    ],
    "name:tam_x_preferred":[
        "\u0b86\u0ba4\u0bbf\u0bb2\u0bbe\u0baa\u0bbe\u0ba4\u0bcd"
    ],
    "name:tel_x_preferred":[
        "\u0c06\u0c26\u0c3f\u0c32\u0c3e\u0c2c\u0c3e\u0c26\u0c4d"
    ],
    "name:tur_x_preferred":[
        "Adilabad"
    ],
    "name:urd_x_preferred":[
        "\u0639\u0627\u062f\u0644 \u0622\u0628\u0627\u062f"
    ],
    "name:vie_x_preferred":[
        "Adilabad"
    ],
    "name:zho_x_preferred":[
        "\u963f\u8fea\u62c9\u5df4\u5fb7"
    ],
    "wof:name":"Adilabad",
    "wof:placetype":"locality"
},
  "geometry": {"coordinates":[69.84904,31.50984],"type":"Point"}
}