{
  "type": "Feature",
  "properties": {
    "gn:admin1_code":"2.0",
    "gn:asciiname":"Adilabad",
    "gn:country_code":"PK",
    "gn:dem":1682,
    "gn:feature_class":"P",
    "gn:feature_code":"PPL",
    "gn:name":"Adilabad",
    "gn:population":0,
    "gn:timezone":"Asia/Karachi",
    "iso:country":"PK",
    "wof:name":"Adilabad",
    "wof:placetype":"locality"
},
  "geometry": {"coordinates":[69.84904,31.50984],"type":"Point"}
}