{
  "type": "Feature",
  "properties": {
    "gn:admin1_code":"5.0",
    "gn:asciiname":"Bevata",
    "gn:country_code":"PK",
    "gn:dem":43,
    "gn:feature_class":"P",
    "gn:feature_code":"PPL",
    "gn:name":"Bevata",
    "gn:population":0,
    "gn:timezone":"Asia/Karachi",
    "iso:country":"PK",
    "name:fra_x_preferred":[
        "Bevata"
    ],
    "name:ita_x_preferred":[
        "Bevata"
    ],
    "name:mlg_x_preferred":[
        "Bevata"
    ],
    "name:nld_x_preferred":[
        "Bevata"
    ],
    "name:und_x_variant":[
        "Bev\u0101to"
    ],
    "wof:name":"Bevata",
    "wof:placetype":"locality"
},
  "geometry": {"coordinates":[69.69792,24.71023],"type":"Point"}
}