{
  "type": "Feature",
  "properties": {
    "gn:admin1_code":"4.0",
    "gn:asciiname":"Nadhandh",
    "gn:country_code":"PK",
    "gn:dem":126,
    "gn:feature_class":"P",
    "gn:feature_code":"PPL",
    "gn:name":"Nadhandh",
    "gn:population":0,
    "gn:timezone":"Asia/Karachi",
    "iso:country":"PK",
    "name:und_x_variant":[
        "Basti Nau Dhand"
    ],
    "wof:name":"Nadhandh",
    "wof:placetype":"locality"
},
  "geometry": {"coordinates":[71.5933,30.29963],"type":"Point"}
}