{
  "type": "Feature",
  "properties": {
    "gn:admin1_code":"4.0",
    "gn:asciiname":"Bara Giran",
    "gn:country_code":"PK",
    "gn:dem":269,
    "gn:feature_class":"P",
    "gn:feature_code":"PPL",
    "gn:name":"Bara Giran",
    "gn:population":0,
    "gn:timezone":"Asia/Karachi",
    "iso:country":"PK",
    "name:und_x_variant":[
        "Bada Gir\u0101n"
    ],
    "wof:name":"Bara Giran",
    "wof:placetype":"locality"
},
  "geometry": {"coordinates":[73.53437,32.94157],"type":"Point"}
}