{
  "type": "Feature",
  "properties": {
    "gn:admin1_code":"4.0",
    "gn:asciiname":"Chak Godar",
    "gn:country_code":"PK",
    "gn:dem":120,
    "gn:feature_class":"P",
    "gn:feature_code":"PPL",
    "gn:name":"Chak Godar",
    "gn:population":0,
    "gn:timezone":"Asia/Karachi",
    "iso:country":"PK",
    "name:und_x_variant":[
        "Godar",
        "Chak Godar"
    ],
    "wof:name":"Chak Godar",
    "wof:placetype":"locality"
},
  "geometry": {"coordinates":[71.02981,30.08173],"type":"Point"}
}