{
  "type": "Feature",
  "properties": {
    "gn:admin1_code":"4",
    "gn:asciiname":"Basti Sikhani",
    "gn:country_code":"PK",
    "gn:dem":130,
    "gn:feature_class":"P",
    "gn:feature_code":"PPL",
    "gn:name":"Basti Sikh\u0101ni",
    "gn:population":0,
    "gn:timezone":"Asia/Karachi",
    "iso:country":"PK",
    "name:eng_x_preferred":[
        "Basti Sikh\u0101ni"
    ],
    "wof:name":"Basti Sikhani",
    "wof:placetype":"neighbourhood"
},
  "geometry": {"coordinates":[70.97261,30.45685],"type":"Point"}
}