{
  "type": "Feature",
  "properties": {
    "gn:admin1_code":"5.0",
    "gn:asciiname":"Kalher",
    "gn:country_code":"PK",
    "gn:dem":12,
    "gn:feature_class":"P",
    "gn:feature_code":"PPL",
    "gn:name":"Kalher",
    "gn:population":0,
    "gn:timezone":"Asia/Karachi",
    "iso:country":"PK",
    "name:new_x_preferred":[
        "\u0915\u0932\u094d\u0939\u0947\u0930\u0941 \u092e\u0923\u094d\u0921\u0932"
    ],
    "name:tel_x_preferred":[
        "\u0c15\u0c32\u0c4d\u0c39\u0c47\u0c30\u0c41 \u0c2e\u0c02\u0c21\u0c32\u0c02"
    ],
    "wof:name":"Kalher",
    "wof:placetype":"locality"
},
  "geometry": {"coordinates":[68.68554,24.79399],"type":"Point"}
}