{
  "type": "Feature",
  "properties": {
    "gn:admin1_code":"4",
    "gn:asciiname":"Sangrasiwala",
    "gn:country_code":"PK",
    "gn:dem":114,
    "gn:feature_class":"P",
    "gn:feature_code":"PPL",
    "gn:name":"Sangrasiwala",
    "gn:population":0,
    "gn:timezone":"Asia/Karachi",
    "iso:country":"PK",
    "name:und_x_variant":[
        "Sangraaw\u0101la",
        "Sangr\u0101s\u012bw\u0101la",
        "Sangrasiwala"
    ],
    "wof:name":"Sangrasiwala",
    "wof:placetype":"locality"
},
  "geometry": {"coordinates":[71.49113,29.14707000000001],"type":"Point"}
}