{
  "type": "Feature",
  "properties": {
    "gn:admin1_code":"2.0",
    "gn:asciiname":"Goth Karim Bakshsh Gunga",
    "gn:country_code":"PK",
    "gn:dem":31,
    "gn:feature_class":"P",
    "gn:feature_code":"PPL",
    "gn:name":"Goth Karim Bakshsh Gunga",
    "gn:population":0,
    "gn:timezone":"Asia/Karachi",
    "iso:country":"PK",
    "wof:name":"Goth Karim Bakshsh Gunga",
    "wof:placetype":"locality"
},
  "geometry": {"coordinates":[66.45335,25.8515],"type":"Point"}
}