{
  "type": "Feature",
  "properties": {
    "gn:admin1_code":"3",
    "gn:asciiname":"Ghanesh",
    "gn:country_code":"PK",
    "gn:dem":2107,
    "gn:feature_class":"P",
    "gn:feature_code":"PPL",
    "gn:name":"Ghanesh",
    "gn:population":0,
    "gn:timezone":"Asia/Karachi",
    "iso:country":"PK",
    "name:eng_x_preferred":[
        "Ghanesh"
    ],
    "wof:name":"Ghanesh",
    "wof:placetype":"locality"
},
  "geometry": {"coordinates":[72.5744,35.21391],"type":"Point"}
}