{
  "type": "Feature",
  "properties": {
    "gn:admin1_code":"3",
    "gn:asciiname":"Yakh",
    "gn:country_code":"PK",
    "gn:dem":1555,
    "gn:feature_class":"P",
    "gn:feature_code":"PPL",
    "gn:name":"Yakh",
    "gn:population":0,
    "gn:timezone":"Asia/Karachi",
    "iso:country":"PK",
    "name:fas_x_preferred":[
        "\u06cc\u062e"
    ],
    "name:msa_x_preferred":[
        "Yakh"
    ],
    "name:und_x_variant":[
        "Yakh Ch\u012bna Darra"
    ],
    "name:urd_x_preferred":[
        "\u06cc\u06a9\u06be"
    ],
    "wof:name":"Yakh",
    "wof:placetype":"locality"
},
  "geometry": {"coordinates":[72.5027,34.87253],"type":"Point"}
}