{
  "type": "Feature",
  "properties": {
    "gn:admin1_code":"4",
    "gn:asciiname":"Dhok Rajgan",
    "gn:country_code":"PK",
    "gn:dem":327,
    "gn:feature_class":"P",
    "gn:feature_code":"PPL",
    "gn:name":"Dhok Rajgan",
    "gn:population":0,
    "gn:timezone":"Asia/Karachi",
    "iso:country":"PK",
    "name:und_x_variant":[
        "Dhok Bangrot"
    ],
    "wof:name":"Dhok Rajgan",
    "wof:placetype":"locality"
},
  "geometry": {"coordinates":[73.38516,32.93019],"type":"Point"}
}