{
  "type": "Feature",
  "properties": {
    "gn:admin1_code":"7.0",
    "gn:asciiname":"Samitta",
    "gn:country_code":"PK",
    "gn:dem":2465,
    "gn:feature_class":"P",
    "gn:feature_code":"PPL",
    "gn:name":"Samitta",
    "gn:population":0,
    "gn:timezone":"Asia/Karachi",
    "iso:country":"PK",
    "wof:name":"Samitta",
    "wof:placetype":"locality"
},
  "geometry": {"coordinates":[73.98564,35.71164],"type":"Point"}
}