{
  "type": "Feature",
  "properties": {
    "gn:admin1_code":"3.0",
    "gn:asciiname":"Chatha",
    "gn:country_code":"PK",
    "gn:dem":598,
    "gn:feature_class":"P",
    "gn:feature_code":"PPL",
    "gn:name":"Chatha",
    "gn:population":0,
    "gn:timezone":"Asia/Karachi",
    "iso:country":"PK",
    "wof:name":"Chatha",
    "wof:placetype":"locality"
},
  "geometry": {"coordinates":[73.003,34.18926],"type":"Point"}
}