{
  "type": "Feature",
  "properties": {
    "gn:admin1_code":"5.0",
    "gn:asciiname":"Darya Khan Zardari",
    "gn:country_code":"PK",
    "gn:dem":30,
    "gn:feature_class":"P",
    "gn:feature_code":"PPL",
    "gn:name":"Darya Khan Zardari",
    "gn:population":0,
    "gn:timezone":"Asia/Karachi",
    "iso:country":"PK",
    "wof:name":"Darya Khan Zardari",
    "wof:placetype":"locality"
},
  "geometry": {"coordinates":[68.47265,26.24964000000001],"type":"Point"}
}