{
  "type": "Feature",
  "properties": {
    "gn:admin1_code":"2",
    "gn:asciiname":"Kili Bolanzai",
    "gn:country_code":"PK",
    "gn:dem":1693,
    "gn:feature_class":"P",
    "gn:feature_code":"PPL",
    "gn:name":"Kili Bolanzai",
    "gn:population":0,
    "gn:timezone":"Asia/Karachi",
    "iso:country":"PK",
    "wof:name":"Kili Bolanzai",
    "wof:placetype":"locality"
},
  "geometry": {"coordinates":[66.11515,28.40691],"type":"Point"}
}