{
  "type": "Feature",
  "properties": {
    "gn:admin1_code":"4.0",
    "gn:asciiname":"Thattiwala",
    "gn:country_code":"PK",
    "gn:dem":123,
    "gn:feature_class":"P",
    "gn:feature_code":"PPL",
    "gn:name":"Thattiwala",
    "gn:population":0,
    "gn:timezone":"Asia/Karachi",
    "iso:country":"PK",
    "name:und_x_variant":[
        "Thathi Senjial"
    ],
    "wof:name":"Thattiwala",
    "wof:placetype":"neighbourhood"
},
  "geometry": {"coordinates":[71.43904000000001,30.23742],"type":"Point"}
}