{
  "type": "Feature",
  "properties": {
    "gn:admin1_code":"5",
    "gn:asciiname":"Goth Blund Notkani",
    "gn:country_code":"PK",
    "gn:dem":16,
    "gn:feature_class":"P",
    "gn:feature_code":"PPL",
    "gn:name":"Goth Blund Notkani",
    "gn:population":0,
    "gn:timezone":"Asia/Karachi",
    "iso:country":"PK",
    "name:und_x_variant":[
        "Goth Buland Notk\u0101ni"
    ],
    "wof:name":"Goth Blund Notkani",
    "wof:placetype":"locality"
},
  "geometry": {"coordinates":[68.78818000000001,25.01453],"type":"Point"}
}