{
  "type": "Feature",
  "properties": {
    "gn:admin1_code":"4",
    "gn:asciiname":"Chariala Khurd",
    "gn:country_code":"PK",
    "gn:dem":220,
    "gn:feature_class":"P",
    "gn:feature_code":"PPL",
    "gn:name":"Chariala Khurd",
    "gn:population":0,
    "gn:timezone":"Asia/Karachi",
    "iso:country":"PK",
    "name:und_x_variant":[
        "Charl\u0101la Khurd"
    ],
    "wof:name":"Chariala Khurd",
    "wof:placetype":"locality"
},
  "geometry": {"coordinates":[74.17675,32.03564],"type":"Point"}
}