{
  "type": "Feature",
  "properties": {
    "gn:admin1_code":"3",
    "gn:asciiname":"Patti Gali",
    "gn:country_code":"PK",
    "gn:dem":1443,
    "gn:feature_class":"P",
    "gn:feature_code":"PPL",
    "gn:name":"Patti Gali",
    "gn:population":0,
    "gn:timezone":"Asia/Karachi",
    "iso:country":"PK",
    "name:und_x_variant":[
        "Patthe Gali"
    ],
    "wof:name":"Patti Gali",
    "wof:placetype":"locality"
},
  "geometry": {"coordinates":[73.41481999999998,34.27663],"type":"Point"}
}