{
  "type": "Feature",
  "properties": {
    "gn:admin1_code":"2",
    "gn:asciiname":"Kabir",
    "gn:country_code":"PK",
    "gn:dem":1534,
    "gn:feature_class":"P",
    "gn:feature_code":"PPL",
    "gn:name":"Kabir",
    "gn:population":0,
    "gn:timezone":"Asia/Karachi",
    "iso:country":"PK",
    "wof:name":"Kabir",
    "wof:placetype":"locality"
},
  "geometry": {"coordinates":[68.40397,30.7467],"type":"Point"}
}