{
  "type": "Feature",
  "properties": {
    "gn:admin1_code":"02",
    "gn:asciiname":"Goth Ahmad Jamot",
    "gn:country_code":"PK",
    "gn:dem":169,
    "gn:feature_class":"P",
    "gn:feature_code":"PPL",
    "gn:name":"Goth Ahmad Jamot",
    "gn:population":0,
    "gn:timezone":"Asia/Karachi",
    "iso:country":"PK",
    "name:und_x_variant":[
        "Goth Ahmad J\u0101met"
    ],
    "wof:name":"Goth Ahmad Jamot",
    "wof:placetype":"locality"
},
  "geometry": {"coordinates":[66.33799,26.34483],"type":"Point"}
}