{
  "type": "Feature",
  "properties": {
    "gn:admin1_code":"5.0",
    "gn:asciiname":"Pathan Colony",
    "gn:country_code":"PK",
    "gn:dem":32,
    "gn:feature_class":"P",
    "gn:feature_code":"PPL",
    "gn:name":"Pathan Colony",
    "gn:population":0,
    "gn:timezone":"Asia/Karachi",
    "iso:country":"PK",
    "name:eng_x_preferred":[
        "Pathan Colony"
    ],
    "wof:name":"Pathan Colony",
    "wof:placetype":"locality"
},
  "geometry": {"coordinates":[68.36426,25.4063],"type":"Point"}
}