{
  "type": "Feature",
  "properties": {
    "gn:admin1_code":"1.0",
    "gn:asciiname":"Khadi Nawasi",
    "gn:country_code":"PK",
    "gn:dem":2056,
    "gn:feature_class":"P",
    "gn:feature_code":"PPL",
    "gn:name":"Khadi Nawasi",
    "gn:population":0,
    "gn:timezone":"Asia/Karachi",
    "iso:country":"PK",
    "wof:name":"Khadi Nawasi",
    "wof:placetype":"locality"
},
  "geometry": {"coordinates":[70.62900999999999,33.77372],"type":"Point"}
}