{
  "type": "Feature",
  "properties": {
    "gn:admin1_code":"4.0",
    "gn:asciiname":"Bandea",
    "gn:country_code":"PK",
    "gn:dem":680,
    "gn:feature_class":"P",
    "gn:feature_code":"PPL",
    "gn:name":"Bandea",
    "gn:population":0,
    "gn:timezone":"Asia/Karachi",
    "iso:country":"PK",
    "wof:name":"Bandea",
    "wof:placetype":"locality"
},
  "geometry": {"coordinates":[73.46956,33.62179],"type":"Point"}
}