{
  "type": "Feature",
  "properties": {
    "gn:admin1_code":"1.0",
    "gn:asciiname":"Lalbaz Garah",
    "gn:country_code":"PK",
    "gn:dem":866,
    "gn:feature_class":"P",
    "gn:feature_code":"PPL",
    "gn:name":"Lalbaz Garah",
    "gn:population":0,
    "gn:timezone":"Asia/Karachi",
    "iso:country":"PK",
    "name:und_x_variant":[
        "L\u0101lb\u0101z Gareh"
    ],
    "wof:name":"Lalbaz Garah",
    "wof:placetype":"locality"
},
  "geometry": {"coordinates":[71.09565000000001,33.59517],"type":"Point"}
}