{
  "type": "Feature",
  "properties": {
    "gn:admin1_code":"05",
    "gn:asciiname":"Goth Imam Bakhsh",
    "gn:country_code":"PK",
    "gn:dem":110,
    "gn:feature_class":"P",
    "gn:feature_code":"PPL",
    "gn:name":"Goth Imam Bakhsh",
    "gn:population":0,
    "gn:timezone":"Asia/Karachi",
    "iso:country":"PK",
    "name:und_x_variant":[
        "Goth Im\u0101m Bukhsh"
    ],
    "wof:name":"Goth Imam Bakhsh",
    "wof:placetype":"locality"
},
  "geometry": {"coordinates":[67.34361,25.03972000000001],"type":"Point"}
}