{
  "type": "Feature",
  "properties": {
    "gn:admin1_code":"2.0",
    "gn:asciiname":"Sorange",
    "gn:country_code":"PK",
    "gn:dem":1925,
    "gn:feature_class":"P",
    "gn:feature_code":"PPL",
    "gn:name":"Sorange",
    "gn:population":0,
    "gn:timezone":"Asia/Karachi",
    "iso:country":"PK",
    "wof:name":"Sorange",
    "wof:placetype":"locality"
},
  "geometry": {"coordinates":[67.22048000000001,30.16666],"type":"Point"}
}