{
  "type": "Feature",
  "properties": {
    "gn:admin1_code":"2.0",
    "gn:asciiname":"Kili Ali Murad",
    "gn:country_code":"PK",
    "gn:dem":228,
    "gn:feature_class":"P",
    "gn:feature_code":"PPL",
    "gn:name":"Kili Ali Murad",
    "gn:population":0,
    "gn:timezone":"Asia/Karachi",
    "iso:country":"PK",
    "wof:name":"Kili Ali Murad",
    "wof:placetype":"locality"
},
  "geometry": {"coordinates":[69.24463,28.75902],"type":"Point"}
}