{
  "type": "Feature",
  "properties": {
    "gn:admin1_code":"3.0",
    "gn:asciiname":"Achini Bala",
    "gn:country_code":"PK",
    "gn:dem":415,
    "gn:feature_class":"P",
    "gn:feature_code":"PPL",
    "gn:name":"Achini Bala",
    "gn:population":0,
    "gn:timezone":"Asia/Karachi",
    "iso:country":"PK",
    "name:eng_x_preferred":[
        "Achini Bala"
    ],
    "name:und_x_variant":[
        "Achini B\u0101la"
    ],
    "wof:name":"Achini Bala",
    "wof:placetype":"locality"
},
  "geometry": {"coordinates":[71.46633,33.96109000000001],"type":"Point"}
}