{
  "type": "Feature",
  "properties": {
    "gn:admin1_code":"04",
    "gn:asciiname":"Shadi Khan",
    "gn:country_code":"PK",
    "gn:dem":300,
    "gn:feature_class":"P",
    "gn:feature_code":"PPL",
    "gn:name":"Shadi Khan",
    "gn:population":0,
    "gn:timezone":"Asia/Karachi",
    "iso:country":"PK",
    "wof:name":"Shadi Khan",
    "wof:placetype":"locality"
},
  "geometry": {"coordinates":[72.37756999999998,33.92268],"type":"Point"}
}