{
  "type": "Feature",
  "properties": {
    "gn:admin1_code":"2.0",
    "gn:asciiname":"Kablo",
    "gn:country_code":"PK",
    "gn:dem":1211,
    "gn:feature_class":"P",
    "gn:feature_code":"PPL",
    "gn:name":"Kablo",
    "gn:population":0,
    "gn:timezone":"Asia/Karachi",
    "iso:country":"PK",
    "wof:name":"Kablo",
    "wof:placetype":"locality"
},
  "geometry": {"coordinates":[65.72583,27.20162],"type":"Point"}
}