{
  "type": "Feature",
  "properties": {
    "gn:admin1_code":"4",
    "gn:asciiname":"Nau Qabilwah",
    "gn:country_code":"PK",
    "gn:dem":128,
    "gn:feature_class":"P",
    "gn:feature_code":"PPL",
    "gn:name":"Nau Qabilwah",
    "gn:population":0,
    "gn:timezone":"Asia/Karachi",
    "iso:country":"PK",
    "name:und_x_variant":[
        "Mas\u012btw\u0101la"
    ],
    "wof:name":"Nau Qabilwah",
    "wof:placetype":"locality"
},
  "geometry": {"coordinates":[72.02504,29.66604],"type":"Point"}
}