{
  "type": "Feature",
  "properties": {
    "gn:admin1_code":"3.0",
    "gn:asciiname":"Sorwil",
    "gn:country_code":"PK",
    "gn:dem":2284,
    "gn:feature_class":"P",
    "gn:feature_code":"PPL",
    "gn:name":"Sorwil",
    "gn:population":0,
    "gn:timezone":"Asia/Karachi",
    "iso:country":"PK",
    "wof:name":"Sorwil",
    "wof:placetype":"locality"
},
  "geometry": {"coordinates":[72.38068,36.42163],"type":"Point"}
}