{
  "type": "Feature",
  "properties": {
    "gn:admin1_code":"2.0",
    "gn:asciiname":"Nusro Kaul Panazai",
    "gn:country_code":"PK",
    "gn:dem":2639,
    "gn:feature_class":"P",
    "gn:feature_code":"PPL",
    "gn:name":"Nusro Kaul Panazai",
    "gn:population":0,
    "gn:timezone":"Asia/Karachi",
    "iso:country":"PK",
    "wof:name":"Nusro Kaul Panazai",
    "wof:placetype":"locality"
},
  "geometry": {"coordinates":[66.98829000000001,30.92823],"type":"Point"}
}