{
  "type": "Feature",
  "properties": {
    "gn:admin1_code":"3",
    "gn:asciiname":"Shoshanka",
    "gn:country_code":"PK",
    "gn:dem":2044,
    "gn:feature_class":"P",
    "gn:feature_code":"PPL",
    "gn:name":"Shoshanka",
    "gn:population":0,
    "gn:timezone":"Asia/Karachi",
    "iso:country":"PK",
    "name:eng_x_preferred":[
        "Shoshanka"
    ],
    "wof:name":"Shoshanka",
    "wof:placetype":"locality"
},
  "geometry": {"coordinates":[71.69681,35.34364],"type":"Point"}
}