{
  "type": "Feature",
  "properties": {
    "gn:admin1_code":"5.0",
    "gn:asciiname":"Shurkandi",
    "gn:country_code":"PK",
    "gn:dem":122,
    "gn:feature_class":"P",
    "gn:feature_code":"PPL",
    "gn:name":"Shurkandi",
    "gn:population":0,
    "gn:timezone":"Asia/Karachi",
    "iso:country":"PK",
    "name:und_x_variant":[
        "Goth Shurkanai"
    ],
    "wof:name":"Shurkandi",
    "wof:placetype":"locality"
},
  "geometry": {"coordinates":[67.25055999999999,25.51381],"type":"Point"}
}