{
  "type": "Feature",
  "properties": {
    "gn:admin1_code":"5",
    "gn:asciiname":"Goth Boto Makan",
    "gn:country_code":"PK",
    "gn:dem":29,
    "gn:feature_class":"P",
    "gn:feature_code":"PPL",
    "gn:name":"Goth Boto Makan",
    "gn:population":0,
    "gn:timezone":"Asia/Karachi",
    "iso:country":"PK",
    "name:eng_x_preferred":[
        "Boto Mak\u0101n"
    ],
    "name:und_x_variant":[
        "Bota Mak\u0101n",
        "Goth Boto Makan"
    ],
    "wof:name":"Goth Boto Makan",
    "wof:placetype":"locality"
},
  "geometry": {"coordinates":[68.25305,25.26592],"type":"Point"}
}