{
  "type": "Feature",
  "properties": {
    "gn:admin1_code":"4.0",
    "gn:asciiname":"Hakim Chandawala",
    "gn:country_code":"PK",
    "gn:dem":124,
    "gn:feature_class":"P",
    "gn:feature_code":"PPL",
    "gn:name":"Hakim Chandawala",
    "gn:population":0,
    "gn:timezone":"Asia/Karachi",
    "iso:country":"PK",
    "name:eng_x_preferred":[
        "Hukam Chandaw\u0101la"
    ],
    "wof:name":"Hakim Chandawala",
    "wof:placetype":"locality"
},
  "geometry": {"coordinates":[70.70578,30.15922],"type":"Point"}
}