{
  "type": "Feature",
  "properties": {
    "gn:admin1_code":"3.0",
    "gn:asciiname":"Madagusht",
    "gn:country_code":"PK",
    "gn:dem":2904,
    "gn:feature_class":"P",
    "gn:feature_code":"PPL",
    "gn:name":"Madagusht",
    "gn:population":0,
    "gn:timezone":"Asia/Karachi",
    "iso:country":"PK",
    "name:eng_x_preferred":[
        "Madagusht"
    ],
    "wof:name":"Madagusht",
    "wof:placetype":"locality"
},
  "geometry": {"coordinates":[71.61400999999999,35.73102],"type":"Point"}
}