{
  "type": "Feature",
  "properties": {
    "gn:admin1_code":"4.0",
    "gn:asciiname":"Dhok Par",
    "gn:country_code":"PK",
    "gn:dem":516,
    "gn:feature_class":"P",
    "gn:feature_code":"PPL",
    "gn:name":"Dhok Par",
    "gn:population":0,
    "gn:timezone":"Asia/Karachi",
    "iso:country":"PK",
    "name:und_x_variant":[
        "Dhok Sap\u0101r\u0101sw\u0101li"
    ],
    "wof:name":"Dhok Par",
    "wof:placetype":"locality"
},
  "geometry": {"coordinates":[72.97423000000001,33.51542],"type":"Point"}
}