{
  "type": "Feature",
  "properties": {
    "gn:admin1_code":"4",
    "gn:asciiname":"Milkhi",
    "gn:country_code":"PK",
    "gn:dem":135,
    "gn:feature_class":"P",
    "gn:feature_code":"PPL",
    "gn:name":"Milkhi",
    "gn:population":0,
    "gn:timezone":"Asia/Karachi",
    "iso:country":"PK",
    "name:und_x_variant":[
        "Milkhiw\u0101la"
    ],
    "wof:name":"Milkhi",
    "wof:placetype":"locality"
},
  "geometry": {"coordinates":[71.04178,30.60275],"type":"Point"}
}