{
  "type": "Feature",
  "properties": {
    "gn:admin1_code":"07",
    "gn:asciiname":"Topkhana",
    "gn:country_code":"PK",
    "gn:dem":3662,
    "gn:feature_class":"P",
    "gn:feature_code":"PPL",
    "gn:name":"Topkhana",
    "gn:population":0,
    "gn:timezone":"Asia/Karachi",
    "iso:country":"PK",
    "wof:name":"Topkhana",
    "wof:placetype":"locality"
},
  "geometry": {"coordinates":[74.71666999999999,36.83333],"type":"Point"}
}