{
  "type": "Feature",
  "properties": {
    "gn:admin1_code":"3",
    "gn:asciiname":"Tarha Pain",
    "gn:country_code":"PK",
    "gn:dem":857,
    "gn:feature_class":"P",
    "gn:feature_code":"PPL",
    "gn:name":"Tarha Pain",
    "gn:population":0,
    "gn:timezone":"Asia/Karachi",
    "iso:country":"PK",
    "name:und_x_variant":[
        "Tarha Tarla"
    ],
    "wof:name":"Tarha Pain",
    "wof:placetype":"locality"
},
  "geometry": {"coordinates":[73.15774,34.41621],"type":"Point"}
}