{
  "type": "Feature",
  "properties": {
    "gn:admin1_code":"3",
    "gn:asciiname":"Bela",
    "gn:country_code":"PK",
    "gn:dem":1597,
    "gn:feature_class":"P",
    "gn:feature_code":"PPL",
    "gn:name":"Bela",
    "gn:population":0,
    "gn:timezone":"Asia/Karachi",
    "iso:country":"PK",
    "wof:name":"Bela",
    "wof:placetype":"locality"
},
  "geometry": {"coordinates":[72.62073000000002,34.73066],"type":"Point"}
}