{
  "type": "Feature",
  "properties": {
    "gn:admin1_code":"1",
    "gn:asciiname":"Gul Almar Kili",
    "gn:country_code":"PK",
    "gn:dem":1015,
    "gn:feature_class":"P",
    "gn:feature_code":"PPL",
    "gn:name":"Gul Almar Kili",
    "gn:population":0,
    "gn:timezone":"Asia/Karachi",
    "iso:country":"PK",
    "wof:name":"Gul Almar Kili",
    "wof:placetype":"locality"
},
  "geometry": {"coordinates":[71.07504,33.90675],"type":"Point"}
}