{
  "type": "Feature",
  "properties": {
    "gn:admin1_code":"2.0",
    "gn:asciiname":"Kili Saiyid Faqirdad",
    "gn:country_code":"PK",
    "gn:dem":1025,
    "gn:feature_class":"P",
    "gn:feature_code":"PPL",
    "gn:name":"Kili Saiyid Faqirdad",
    "gn:population":0,
    "gn:timezone":"Asia/Karachi",
    "iso:country":"PK",
    "wof:name":"Kili Saiyid Faqirdad",
    "wof:placetype":"locality"
},
  "geometry": {"coordinates":[64.46873000000001,29.27998],"type":"Point"}
}