{
  "type": "Feature",
  "properties": {
    "gn:admin1_code":"3.0",
    "gn:asciiname":"Bandi Dhundan",
    "gn:country_code":"PK",
    "gn:dem":1382,
    "gn:feature_class":"P",
    "gn:feature_code":"PPL",
    "gn:name":"Bandi Dhundan",
    "gn:population":0,
    "gn:timezone":"Asia/Karachi",
    "iso:country":"PK",
    "name:fas_x_preferred":[
        "\u0628\u0646\u062f\u06cc \u062f\u0647\u0648\u0646\u062f\u0627\u0646"
    ],
    "name:und_x_variant":[
        "B\u0101ndi Dh\u016bnd\u0101n"
    ],
    "wof:name":"Bandi Dhundan",
    "wof:placetype":"locality"
},
  "geometry": {"coordinates":[73.25768000000002,34.26442],"type":"Point"}
}