{
  "type": "Feature",
  "properties": {
    "gn:admin1_code":"4.0",
    "gn:asciiname":"Jahar",
    "gn:country_code":"PK",
    "gn:dem":416,
    "gn:feature_class":"P",
    "gn:feature_code":"PPL",
    "gn:name":"Jahar",
    "gn:population":0,
    "gn:timezone":"Asia/Karachi",
    "iso:country":"PK",
    "wof:name":"Jahar",
    "wof:placetype":"locality"
},
  "geometry": {"coordinates":[72.77275999999998,33.91347],"type":"Point"}
}