{
  "type": "Feature",
  "properties": {
    "gn:admin1_code":"2.0",
    "gn:asciiname":"Kharara Tezhi Coy L Ors",
    "gn:country_code":"PK",
    "gn:dem":2169,
    "gn:feature_class":"P",
    "gn:feature_code":"PPL",
    "gn:name":"Kharara Tezhi Coy L Ors",
    "gn:population":0,
    "gn:timezone":"Asia/Karachi",
    "iso:country":"PK",
    "name:und_x_variant":[
        "Khar\u0101ra Tezhi"
    ],
    "wof:name":"Kharara Tezhi Coy L Ors",
    "wof:placetype":"locality"
},
  "geometry": {"coordinates":[67.99906,30.72297],"type":"Point"}
}