{
  "type": "Feature",
  "properties": {
    "gn:admin1_code":"7.0",
    "gn:asciiname":"Newchu",
    "gn:country_code":"PK",
    "gn:dem":2907,
    "gn:feature_class":"P",
    "gn:feature_code":"PPL",
    "gn:name":"Newchu",
    "gn:population":0,
    "gn:timezone":"Asia/Karachi",
    "iso:country":"PK",
    "wof:name":"Newchu",
    "wof:placetype":"locality"
},
  "geometry": {"coordinates":[75.32523,35.6252],"type":"Point"}
}