{
  "type": "Feature",
  "properties": {
    "gn:admin1_code":"04",
    "gn:asciiname":"Chak Six -Four Left",
    "gn:country_code":"PK",
    "gn:dem":183,
    "gn:feature_class":"P",
    "gn:feature_code":"PPL",
    "gn:name":"Chak Six -Four Left",
    "gn:population":0,
    "gn:timezone":"Asia/Karachi",
    "iso:country":"PK",
    "name:und_x_variant":[
        "Rahmpur",
        "Chak Six Four L",
        "Chak 6-4 L"
    ],
    "wof:name":"Chak Six -Four Left",
    "wof:placetype":"locality"
},
  "geometry": {"coordinates":[73.45256999999999,30.7615],"type":"Point"}
}