{
  "type": "Feature",
  "properties": {
    "gn:admin1_code":"4",
    "gn:asciiname":"Khandanwala",
    "gn:country_code":"PK",
    "gn:dem":127,
    "gn:feature_class":"P",
    "gn:feature_code":"PPL",
    "gn:name":"Khandanwala",
    "gn:population":0,
    "gn:timezone":"Asia/Karachi",
    "iso:country":"PK",
    "wof:name":"Khandanwala",
    "wof:placetype":"locality"
},
  "geometry": {"coordinates":[71.23605000000001,30.25454],"type":"Point"}
}