{
  "type": "Feature",
  "properties": {
    "gn:admin1_code":"6.0",
    "gn:asciiname":"Maili",
    "gn:country_code":"PK",
    "gn:dem":1840,
    "gn:feature_class":"P",
    "gn:feature_code":"PPL",
    "gn:name":"Maili",
    "gn:population":0,
    "gn:timezone":"Asia/Karachi",
    "iso:country":"PK",
    "name:und_x_variant":[
        "Maill"
    ],
    "wof:name":"Maili",
    "wof:placetype":"locality"
},
  "geometry": {"coordinates":[74.18276,33.9285],"type":"Point"}
}