{
  "type": "Feature",
  "properties": {
    "gn:admin1_code":"4.0",
    "gn:asciiname":"Chak Manan",
    "gn:country_code":"PK",
    "gn:dem":210,
    "gn:feature_class":"P",
    "gn:feature_code":"PPL",
    "gn:name":"Chak Manan",
    "gn:population":0,
    "gn:timezone":"Asia/Karachi",
    "iso:country":"PK",
    "name:und_x_variant":[
        "Chak M\u0101n\u0101h",
        "K\u0101hlw\u0101n",
        "Kot Hari Chand",
        "Chak Manan"
    ],
    "wof:name":"Chak Manan",
    "wof:placetype":"locality"
},
  "geometry": {"coordinates":[73.86944,31.90655],"type":"Point"}
}