{
  "type": "Feature",
  "properties": {
    "gn:admin1_code":"4.0",
    "gn:asciiname":"Kahli",
    "gn:country_code":"PK",
    "gn:dem":826,
    "gn:feature_class":"P",
    "gn:feature_code":"PPL",
    "gn:name":"Kahli",
    "gn:population":0,
    "gn:timezone":"Asia/Karachi",
    "iso:country":"PK",
    "wof:name":"Kahli",
    "wof:placetype":"locality"
},
  "geometry": {"coordinates":[73.51608,33.96023],"type":"Point"}
}