{
  "type": "Feature",
  "properties": {
    "gn:admin1_code":"5.0",
    "gn:asciiname":"Haji Fateh Muhammad Abro",
    "gn:country_code":"PK",
    "gn:dem":16,
    "gn:feature_class":"P",
    "gn:feature_code":"PPL",
    "gn:name":"Haji Fateh Muhammad Abro",
    "gn:population":0,
    "gn:timezone":"Asia/Karachi",
    "iso:country":"PK",
    "wof:name":"Haji Fateh Muhammad Abro",
    "wof:placetype":"locality"
},
  "geometry": {"coordinates":[68.51170999999999,24.8789],"type":"Point"}
}