{
  "type": "Feature",
  "properties": {
    "gn:admin1_code":"6",
    "gn:asciiname":"Gawan",
    "gn:country_code":"PK",
    "gn:dem":1225,
    "gn:feature_class":"P",
    "gn:feature_code":"PPL",
    "gn:name":"Gawan",
    "gn:population":0,
    "gn:timezone":"Asia/Karachi",
    "iso:country":"PK",
    "wof:name":"Gawan",
    "wof:placetype":"locality"
},
  "geometry": {"coordinates":[73.96904000000001,33.50706],"type":"Point"}
}