{
  "type": "Feature",
  "properties": {
    "gn:admin1_code":"3.0",
    "gn:asciiname":"Labodai Banda",
    "gn:country_code":"PK",
    "gn:dem":2966,
    "gn:feature_class":"P",
    "gn:feature_code":"PPL",
    "gn:name":"Labodai Banda",
    "gn:population":0,
    "gn:timezone":"Asia/Karachi",
    "iso:country":"PK",
    "name:eng_x_preferred":[
        "Labodai Banda"
    ],
    "wof:name":"Labodai Banda",
    "wof:placetype":"locality"
},
  "geometry": {"coordinates":[72.40075,35.69656],"type":"Point"}
}