{
  "type": "Feature",
  "properties": {
    "gn:admin1_code":"2.0",
    "gn:asciiname":"Ranak",
    "gn:country_code":"PK",
    "gn:dem":776,
    "gn:feature_class":"P",
    "gn:feature_code":"PPL",
    "gn:name":"Ranak",
    "gn:population":0,
    "gn:timezone":"Asia/Karachi",
    "iso:country":"PK",
    "name:und_x_variant":[
        "Ramak"
    ],
    "wof:name":"Ranak",
    "wof:placetype":"locality"
},
  "geometry": {"coordinates":[70.13724000000001,31.33453],"type":"Point"}
}