{
  "type": "Feature",
  "properties": {
    "gn:admin1_code":"5.0",
    "gn:asciiname":"Goth Qabulo",
    "gn:country_code":"PK",
    "gn:dem":50,
    "gn:feature_class":"P",
    "gn:feature_code":"PPL",
    "gn:name":"Goth Qabulo",
    "gn:population":0,
    "gn:timezone":"Asia/Karachi",
    "iso:country":"PK",
    "name:und_x_variant":[
        "Qab\u016blo",
        "Kabulo",
        "Goth Qab\u016blo",
        "Goth Qabulo"
    ],
    "wof:name":"Goth Qabulo",
    "wof:placetype":"locality"
},
  "geometry": {"coordinates":[68.03279000000001,27.2282],"type":"Point"}
}