{
  "type": "Feature",
  "properties": {
    "gn:admin1_code":"3.0",
    "gn:asciiname":"Jamra",
    "gn:country_code":"PK",
    "gn:dem":307,
    "gn:feature_class":"P",
    "gn:feature_code":"PPL",
    "gn:name":"Jamra",
    "gn:population":0,
    "gn:timezone":"Asia/Karachi",
    "iso:country":"PK",
    "name:eng_x_preferred":[
        "Jh\u0101mra"
    ],
    "name:und_x_variant":[
        "Jamrah",
        "Jamra"
    ],
    "wof:name":"Jamra",
    "wof:placetype":"locality"
},
  "geometry": {"coordinates":[71.98765,34.17604],"type":"Point"}
}