{
  "type": "Feature",
  "properties": {
    "gn:admin1_code":"3",
    "gn:asciiname":"Kashora",
    "gn:country_code":"PK",
    "gn:dem":1497,
    "gn:feature_class":"P",
    "gn:feature_code":"PPL",
    "gn:name":"K\u0101shora",
    "gn:population":0,
    "gn:timezone":"Asia/Karachi",
    "iso:country":"PK",
    "wof:name":"Kashora",
    "wof:placetype":"locality"
},
  "geometry": {"coordinates":[72.97499999999999,34.775],"type":"Point"}
}