{
  "type": "Feature",
  "properties": {
    "gn:admin1_code":"7.0",
    "gn:asciiname":"Belangah",
    "gn:country_code":"PK",
    "gn:dem":2257,
    "gn:feature_class":"P",
    "gn:feature_code":"PPL",
    "gn:name":"Belangah",
    "gn:population":0,
    "gn:timezone":"Asia/Karachi",
    "iso:country":"PK",
    "wof:name":"Belangah",
    "wof:placetype":"locality"
},
  "geometry": {"coordinates":[73.82684999999999,35.32898],"type":"Point"}
}