{
  "type": "Feature",
  "properties": {
    "gn:admin1_code":"4",
    "gn:asciiname":"Basti Balwani",
    "gn:country_code":"PK",
    "gn:dem":175,
    "gn:feature_class":"P",
    "gn:feature_code":"PPL",
    "gn:name":"Basti Balwani",
    "gn:population":0,
    "gn:timezone":"Asia/Karachi",
    "iso:country":"PK",
    "name:und_x_variant":[
        "Balw\u0101ni\u0101n",
        "Basti Balwani"
    ],
    "wof:name":"Basti Balwani",
    "wof:placetype":"locality"
},
  "geometry": {"coordinates":[70.64480999999998,31.16136],"type":"Point"}
}