{
  "type": "Feature",
  "properties": {
    "gn:admin1_code":"4.0",
    "gn:asciiname":"Jahur",
    "gn:country_code":"PK",
    "gn:dem":263,
    "gn:feature_class":"P",
    "gn:feature_code":"PPL",
    "gn:name":"Jahur",
    "gn:population":0,
    "gn:timezone":"Asia/Karachi",
    "iso:country":"PK",
    "wof:name":"Jahur",
    "wof:placetype":"locality"
},
  "geometry": {"coordinates":[74.831,32.32199],"type":"Point"}
}