{
  "type": "Feature",
  "properties": {
    "gn:admin1_code":"5.0",
    "gn:asciiname":"Ghulam Nabi",
    "gn:country_code":"PK",
    "gn:dem":42,
    "gn:feature_class":"P",
    "gn:feature_code":"PPL",
    "gn:name":"Ghulam Nabi",
    "gn:population":0,
    "gn:timezone":"Asia/Karachi",
    "iso:country":"PK",
    "name:urd_x_preferred":[
        "\u063a\u0644\u0627\u0645 \u0646\u0628\u06cc"
    ],
    "wof:name":"Ghulam Nabi",
    "wof:placetype":"locality"
},
  "geometry": {"coordinates":[68.30824,26.68915],"type":"Point"}
}