{
  "type": "Feature",
  "properties": {
    "gn:admin1_code":"5",
    "gn:asciiname":"Bachal Khan Hangora",
    "gn:country_code":"PK",
    "gn:dem":27,
    "gn:feature_class":"P",
    "gn:feature_code":"PPL",
    "gn:name":"Bachal Khan Hangora",
    "gn:population":0,
    "gn:timezone":"Asia/Karachi",
    "iso:country":"PK",
    "wof:name":"Bachal Khan Hangora",
    "wof:placetype":"locality"
},
  "geometry": {"coordinates":[68.67055000000001,26.02839],"type":"Point"}
}