{
  "type": "Feature",
  "properties": {
    "gn:admin1_code":"5",
    "gn:asciiname":"Goth Talib",
    "gn:country_code":"PK",
    "gn:dem":36,
    "gn:feature_class":"P",
    "gn:feature_code":"PPL",
    "gn:name":"Goth Talib",
    "gn:population":0,
    "gn:timezone":"Asia/Karachi",
    "iso:country":"PK",
    "name:und_x_variant":[
        "Goth T\u0101lab Ja",
        "Goth Talib"
    ],
    "wof:name":"Goth Talib",
    "wof:placetype":"locality"
},
  "geometry": {"coordinates":[68.14073,26.36041],"type":"Point"}
}