{
  "type": "Feature",
  "properties": {
    "gn:admin1_code":"3.0",
    "gn:asciiname":"Rohtas Pahari",
    "gn:country_code":"PK",
    "gn:dem":1330,
    "gn:feature_class":"P",
    "gn:feature_code":"PPL",
    "gn:name":"Rohtas Pahari",
    "gn:population":0,
    "gn:timezone":"Asia/Karachi",
    "iso:country":"PK",
    "name:eng_x_preferred":[
        "Rohtas Pahari"
    ],
    "wof:name":"Rohtas Pahari",
    "wof:placetype":"locality"
},
  "geometry": {"coordinates":[73.10043,33.84105],"type":"Point"}
}