{
  "type": "Feature",
  "properties": {
    "gn:admin1_code":"5",
    "gn:asciiname":"Bahram Mughairi",
    "gn:country_code":"PK",
    "gn:dem":54,
    "gn:feature_class":"P",
    "gn:feature_code":"PPL",
    "gn:name":"Bahram Mughairi",
    "gn:population":0,
    "gn:timezone":"Asia/Karachi",
    "iso:country":"PK",
    "name:und_x_variant":[
        "B\u0101hr\u0101m Mughairi",
        "Bironi Mughairi",
        "Bahram Mughairi"
    ],
    "wof:name":"Bahram Mughairi",
    "wof:placetype":"locality"
},
  "geometry": {"coordinates":[68.20465,27.63711],"type":"Point"}
}