{
  "type": "Feature",
  "properties": {
    "gn:admin1_code":"4.0",
    "gn:asciiname":"Thathi Bakhsh Shah",
    "gn:country_code":"PK",
    "gn:dem":168,
    "gn:feature_class":"P",
    "gn:feature_code":"PPL",
    "gn:name":"Thathi Bakhsh Sh\u0101h",
    "gn:population":0,
    "gn:timezone":"Asia/Karachi",
    "iso:country":"PK",
    "wof:name":"Thathi Bakhsh Shah",
    "wof:placetype":"locality"
},
  "geometry": {"coordinates":[72.21606,31.83498],"type":"Point"}
}