{
  "type": "Feature",
  "properties": {
    "gn:admin1_code":"1.0",
    "gn:asciiname":"Shamiri",
    "gn:country_code":"PK",
    "gn:dem":668,
    "gn:feature_class":"P",
    "gn:feature_code":"PPL",
    "gn:name":"Shamiri",
    "gn:population":0,
    "gn:timezone":"Asia/Karachi",
    "iso:country":"PK",
    "name:und_x_variant":[
        "Shamiri Tori Khel"
    ],
    "wof:name":"Shamiri",
    "wof:placetype":"locality"
},
  "geometry": {"coordinates":[70.34415,33.11713],"type":"Point"}
}