{
  "type": "Feature",
  "properties": {
    "gn:admin1_code":"3.0",
    "gn:asciiname":"Solai",
    "gn:country_code":"PK",
    "gn:dem":749,
    "gn:feature_class":"P",
    "gn:feature_code":"PPL",
    "gn:name":"Solai",
    "gn:population":0,
    "gn:timezone":"Asia/Karachi",
    "iso:country":"PK",
    "wof:name":"Solai",
    "wof:placetype":"locality"
},
  "geometry": {"coordinates":[72.46734000000002,34.5172],"type":"Point"}
}