{
  "type": "Feature",
  "properties": {
    "gn:admin1_code":"4",
    "gn:asciiname":"Dhiranke Lalke",
    "gn:country_code":"PK",
    "gn:dem":207,
    "gn:feature_class":"P",
    "gn:feature_code":"PPL",
    "gn:name":"Dhiranke Lalke",
    "gn:population":0,
    "gn:timezone":"Asia/Karachi",
    "iso:country":"PK",
    "name:und_x_variant":[
        "L\u0101lki"
    ],
    "wof:name":"Dhiranke Lalke",
    "wof:placetype":"locality"
},
  "geometry": {"coordinates":[73.63529,32.14919],"type":"Point"}
}