{
  "type": "Feature",
  "properties": {
    "gn:admin1_code":"1.0",
    "gn:asciiname":"Garigal",
    "gn:country_code":"PK",
    "gn:dem":1156,
    "gn:feature_class":"P",
    "gn:feature_code":"PPL",
    "gn:name":"Garigal",
    "gn:population":0,
    "gn:timezone":"Asia/Karachi",
    "iso:country":"PK",
    "wof:name":"Garigal",
    "wof:placetype":"locality"
},
  "geometry": {"coordinates":[71.36973,34.77994],"type":"Point"}
}