{
  "type": "Feature",
  "properties": {
    "gn:admin1_code":"5.0",
    "gn:asciiname":"Muhammadi Bohri",
    "gn:country_code":"PK",
    "gn:dem":15,
    "gn:feature_class":"P",
    "gn:feature_code":"PPL",
    "gn:name":"Muhammadi Bohri",
    "gn:population":0,
    "gn:timezone":"Asia/Karachi",
    "iso:country":"PK",
    "name:eng_x_preferred":[
        "Muhammadi Bohri"
    ],
    "wof:name":"Muhammadi Bohri",
    "wof:placetype":"locality"
},
  "geometry": {"coordinates":[68.24515,25.0789],"type":"Point"}
}