{
  "type": "Feature",
  "properties": {
    "gn:admin1_code":"1.0",
    "gn:asciiname":"Aba Khel",
    "gn:country_code":"PK",
    "gn:dem":753,
    "gn:feature_class":"P",
    "gn:feature_code":"PPL",
    "gn:name":"Aba Khel",
    "gn:population":0,
    "gn:timezone":"Asia/Karachi",
    "iso:country":"PK",
    "name:ceb_x_preferred":[
        "Aba Khel"
    ],
    "name:und_x_variant":[
        "Abba Khel"
    ],
    "wof:name":"Aba Khel",
    "wof:placetype":"locality"
},
  "geometry": {"coordinates":[70.38429000000002,33.19443],"type":"Point"}
}