{
  "type": "Feature",
  "properties": {
    "gn:admin1_code":"01",
    "gn:asciiname":"Kalao",
    "gn:country_code":"PK",
    "gn:dem":711,
    "gn:feature_class":"P",
    "gn:feature_code":"PPL",
    "gn:name":"Kalao",
    "gn:population":0,
    "gn:timezone":"Asia/Karachi",
    "iso:country":"PK",
    "name:und_x_variant":[
        "Kal\u0101o"
    ],
    "wof:name":"Kalao",
    "wof:placetype":"locality"
},
  "geometry": {"coordinates":[71.4568,34.60331],"type":"Point"}
}