{
  "type": "Feature",
  "properties": {
    "gn:admin1_code":"3",
    "gn:asciiname":"Ali Khan",
    "gn:country_code":"PK",
    "gn:dem":1788,
    "gn:feature_class":"P",
    "gn:feature_code":"PPL",
    "gn:name":"Ali Khan",
    "gn:population":0,
    "gn:timezone":"Asia/Karachi",
    "iso:country":"PK",
    "name:deu_x_preferred":[
        "Ali Khan"
    ],
    "wof:name":"Ali Khan",
    "wof:placetype":"locality"
},
  "geometry": {"coordinates":[72.60234,34.61638],"type":"Point"}
}