{
  "type": "Feature",
  "properties": {
    "gn:admin1_code":"4",
    "gn:asciiname":"Qureshianwala",
    "gn:country_code":"PK",
    "gn:dem":176,
    "gn:feature_class":"P",
    "gn:feature_code":"PPL",
    "gn:name":"Qureshianwala",
    "gn:population":0,
    "gn:timezone":"Asia/Karachi",
    "iso:country":"PK",
    "name:und_x_variant":[
        "Quraishi\u0101nw\u0101la",
        "Quraish\u012bw\u0101la",
        "Qureshianwala"
    ],
    "wof:name":"Qureshianwala",
    "wof:placetype":"locality"
},
  "geometry": {"coordinates":[72.73178,31.64605],"type":"Point"}
}