{
  "type": "Feature",
  "properties": {
    "gn:admin1_code":"5.0",
    "gn:asciiname":"Ghulam Rasul Chacha",
    "gn:country_code":"PK",
    "gn:dem":50,
    "gn:feature_class":"P",
    "gn:feature_code":"PPL",
    "gn:name":"Ghulam Rasul Chacha",
    "gn:population":0,
    "gn:timezone":"Asia/Karachi",
    "iso:country":"PK",
    "name:und_x_variant":[
        "Chacha",
        "Ghul\u0101m Bas\u016b Chacha",
        "Ghulam Rasul Chacha"
    ],
    "wof:name":"Ghulam Rasul Chacha",
    "wof:placetype":"locality"
},
  "geometry": {"coordinates":[67.93414,27.65772],"type":"Point"}
}