{
  "type": "Feature",
  "properties": {
    "gn:admin1_code":"7.0",
    "gn:asciiname":"Dunsa",
    "gn:country_code":"PK",
    "gn:dem":3437,
    "gn:feature_class":"P",
    "gn:feature_code":"PPL",
    "gn:name":"Dunsa",
    "gn:population":0,
    "gn:timezone":"Asia/Karachi",
    "iso:country":"PK",
    "wof:name":"Dunsa",
    "wof:placetype":"locality"
},
  "geometry": {"coordinates":[76.08826999999999,35.41101],"type":"Point"}
}