{
  "type": "Feature",
  "properties": {
    "gn:admin1_code":"7.0",
    "gn:asciiname":"Akhot",
    "gn:country_code":"PK",
    "gn:dem":2122,
    "gn:feature_class":"P",
    "gn:feature_code":"PPL",
    "gn:name":"Akhot",
    "gn:population":0,
    "gn:timezone":"Asia/Karachi",
    "iso:country":"PK",
    "wof:name":"Akhot",
    "wof:placetype":"locality"
},
  "geometry": {"coordinates":[73.81695999999999,35.65249],"type":"Point"}
}