{
  "type": "Feature",
  "properties": {
    "gn:admin1_code":"5.0",
    "gn:asciiname":"Karira",
    "gn:country_code":"PK",
    "gn:dem":50,
    "gn:feature_class":"P",
    "gn:feature_code":"PPL",
    "gn:name":"Karira",
    "gn:population":0,
    "gn:timezone":"Asia/Karachi",
    "iso:country":"PK",
    "name:und_x_variant":[
        "Karria",
        "Karira"
    ],
    "wof:name":"Karira",
    "wof:placetype":"locality"
},
  "geometry": {"coordinates":[67.92851999999999,27.79996],"type":"Point"}
}