{
  "type": "Feature",
  "properties": {
    "gn:admin1_code":"3",
    "gn:asciiname":"Khalu",
    "gn:country_code":"PK",
    "gn:dem":335,
    "gn:feature_class":"P",
    "gn:feature_code":"PPL",
    "gn:name":"Khalu",
    "gn:population":0,
    "gn:timezone":"Asia/Karachi",
    "iso:country":"PK",
    "wof:name":"Khalu",
    "wof:placetype":"locality"
},
  "geometry": {"coordinates":[72.65069,34.01551],"type":"Point"}
}