{
  "type": "Feature",
  "properties": {
    "gn:admin1_code":"4.0",
    "gn:asciiname":"Godal Shahid",
    "gn:country_code":"PK",
    "gn:dem":210,
    "gn:feature_class":"P",
    "gn:feature_code":"PPL",
    "gn:name":"Godal Shah\u012bd",
    "gn:population":0,
    "gn:timezone":"Asia/Karachi",
    "iso:country":"PK",
    "wof:name":"Godal Shahid",
    "wof:placetype":"locality"
},
  "geometry": {"coordinates":[74.22778000000002,31.78083],"type":"Point"}
}