{
  "type": "Feature",
  "properties": {
    "gn:admin1_code":"2.0",
    "gn:asciiname":"Goth Nuruddin",
    "gn:country_code":"PK",
    "gn:dem":8,
    "gn:feature_class":"P",
    "gn:feature_code":"PPL",
    "gn:name":"Goth Nuruddin",
    "gn:population":0,
    "gn:timezone":"Asia/Karachi",
    "iso:country":"PK",
    "name:eng_x_preferred":[
        "Goth Nuruddin"
    ],
    "wof:name":"Goth Nuruddin",
    "wof:placetype":"locality"
},
  "geometry": {"coordinates":[66.72114999999999,25.04708],"type":"Point"}
}