{
  "type": "Feature",
  "properties": {
    "gn:admin1_code":"5",
    "gn:asciiname":"Goth Banglani",
    "gn:country_code":"PK",
    "gn:dem":62,
    "gn:feature_class":"P",
    "gn:feature_code":"PPL",
    "gn:name":"Goth Banglani",
    "gn:population":0,
    "gn:timezone":"Asia/Karachi",
    "iso:country":"PK",
    "name:und_x_variant":[
        "P\u012bral Qamr\u0101ni jo Goth"
    ],
    "wof:name":"Goth Banglani",
    "wof:placetype":"locality"
},
  "geometry": {"coordinates":[68.55792,28.11929],"type":"Point"}
}