{
  "type": "Feature",
  "properties": {
    "gn:admin1_code":"5.0",
    "gn:asciiname":"Goth Karam Khan",
    "gn:country_code":"PK",
    "gn:dem":85,
    "gn:feature_class":"P",
    "gn:feature_code":"PPL",
    "gn:name":"Goth Karam Khan",
    "gn:population":0,
    "gn:timezone":"Asia/Karachi",
    "iso:country":"PK",
    "wof:name":"Goth Karam Khan",
    "wof:placetype":"locality"
},
  "geometry": {"coordinates":[67.08360999999999,25.09556],"type":"Point"}
}