{
  "type": "Feature",
  "properties": {
    "gn:admin1_code":"3.0",
    "gn:asciiname":"Salima Sikandar Khel",
    "gn:country_code":"PK",
    "gn:dem":344,
    "gn:feature_class":"P",
    "gn:feature_code":"PPL",
    "gn:name":"Salima Sikandar Khel",
    "gn:population":0,
    "gn:timezone":"Asia/Karachi",
    "iso:country":"PK",
    "name:und_x_variant":[
        "Salma Sikandar Khel"
    ],
    "wof:name":"Salima Sikandar Khel",
    "wof:placetype":"locality"
},
  "geometry": {"coordinates":[70.66489,32.96932],"type":"Point"}
}