{
  "type": "Feature",
  "properties": {
    "gn:admin1_code":"4",
    "gn:asciiname":"Wani",
    "gn:country_code":"PK",
    "gn:dem":174,
    "gn:feature_class":"P",
    "gn:feature_code":"PPL",
    "gn:name":"Wani",
    "gn:population":0,
    "gn:timezone":"Asia/Karachi",
    "iso:country":"PK",
    "name:ceb_x_preferred":[
        "Wani"
    ],
    "name:deu_x_preferred":[
        "Wani"
    ],
    "name:kat_x_preferred":[
        "\u10d5\u10d0\u10dc\u10d8"
    ],
    "name:pol_x_preferred":[
        "Wani"
    ],
    "name:swe_x_preferred":[
        "Wani"
    ],
    "name:und_x_variant":[
        "Wanni"
    ],
    "name:xmf_x_preferred":[
        "\u10d5\u10d0\u10dc\u10d8"
    ],
    "wof:name":"Wani",
    "wof:placetype":"locality"
},
  "geometry": {"coordinates":[71.12045000000001,31.9102],"type":"Point"}
}