{
  "type": "Feature",
  "properties": {
    "gn:admin1_code":"2",
    "gn:asciiname":"Lewanai Kawar",
    "gn:country_code":"PK",
    "gn:dem":1365,
    "gn:feature_class":"P",
    "gn:feature_code":"PPL",
    "gn:name":"Lewanai Kawar",
    "gn:population":0,
    "gn:timezone":"Asia/Karachi",
    "iso:country":"PK",
    "wof:name":"Lewanai Kawar",
    "wof:placetype":"locality"
},
  "geometry": {"coordinates":[69.02848,30.54758],"type":"Point"}
}