{
  "type": "Feature",
  "properties": {
    "gn:admin1_code":"2.0",
    "gn:asciiname":"Shaikhan",
    "gn:country_code":"PK",
    "gn:dem":1859,
    "gn:feature_class":"P",
    "gn:feature_code":"PPL",
    "gn:name":"Shaikhan",
    "gn:population":0,
    "gn:timezone":"Asia/Karachi",
    "iso:country":"PK",
    "wof:name":"Shaikhan",
    "wof:placetype":"locality"
},
  "geometry": {"coordinates":[66.83478000000001,28.72417],"type":"Point"}
}