{
  "type": "Feature",
  "properties": {
    "gn:admin1_code":"4.0",
    "gn:asciiname":"Nurpur Baghan",
    "gn:country_code":"PK",
    "gn:dem":235,
    "gn:feature_class":"P",
    "gn:feature_code":"PPL",
    "gn:name":"Nurpur Baghan",
    "gn:population":0,
    "gn:timezone":"Asia/Karachi",
    "iso:country":"PK",
    "wof:name":"Nurpur Baghan",
    "wof:placetype":"locality"
},
  "geometry": {"coordinates":[73.57814,32.85544],"type":"Point"}
}