{
  "type": "Feature",
  "properties": {
    "gn:admin1_code":"4",
    "gn:asciiname":"Khu Jurwarwala",
    "gn:country_code":"PK",
    "gn:dem":137,
    "gn:feature_class":"P",
    "gn:feature_code":"PPL",
    "gn:name":"Khu Jurwarwala",
    "gn:population":0,
    "gn:timezone":"Asia/Karachi",
    "iso:country":"PK",
    "name:eng_x_preferred":[
        "Jarw\u0101rw\u0101la"
    ],
    "wof:name":"Khu Jurwarwala",
    "wof:placetype":"locality"
},
  "geometry": {"coordinates":[70.62615,30.34603],"type":"Point"}
}