{
  "type": "Feature",
  "properties": {
    "gn:admin1_code":"4.0",
    "gn:asciiname":"Chak Chuhor",
    "gn:country_code":"PK",
    "gn:dem":213,
    "gn:feature_class":"P",
    "gn:feature_code":"PPL",
    "gn:name":"Chak Chuhor",
    "gn:population":0,
    "gn:timezone":"Asia/Karachi",
    "iso:country":"PK",
    "name:und_x_variant":[
        "Chak Ch\u016bhar"
    ],
    "wof:name":"Chak Chuhor",
    "wof:placetype":"locality"
},
  "geometry": {"coordinates":[73.94229,32.02898],"type":"Point"}
}