{
  "type": "Feature",
  "properties": {
    "gn:admin1_code":"04",
    "gn:asciiname":"Mohra Maliaran",
    "gn:country_code":"PK",
    "gn:dem":425,
    "gn:feature_class":"P",
    "gn:feature_code":"PPL",
    "gn:name":"Mohra Maliaran",
    "gn:population":0,
    "gn:timezone":"Asia/Karachi",
    "iso:country":"PK",
    "name:und_x_variant":[
        "Mohra Malli\u0101r\u0101n",
        "Mohra Maliaran"
    ],
    "wof:name":"Mohra Maliaran",
    "wof:placetype":"locality"
},
  "geometry": {"coordinates":[73.08313000000003,32.89718],"type":"Point"}
}