{
  "type": "Feature",
  "properties": {
    "gn:admin1_code":"3",
    "gn:asciiname":"Kishna Gali",
    "gn:country_code":"PK",
    "gn:dem":1271,
    "gn:feature_class":"P",
    "gn:feature_code":"PPL",
    "gn:name":"Kishna Gali",
    "gn:population":0,
    "gn:timezone":"Asia/Karachi",
    "iso:country":"PK",
    "name:und_x_variant":[
        "Kishna Gal",
        "Kishna Gali"
    ],
    "wof:name":"Kishna Gali",
    "wof:placetype":"locality"
},
  "geometry": {"coordinates":[73.19139,34.2189],"type":"Point"}
}