{
  "type": "Feature",
  "properties": {
    "gn:admin1_code":"4.0",
    "gn:asciiname":"Dhok Shahbaz",
    "gn:country_code":"PK",
    "gn:dem":384,
    "gn:feature_class":"P",
    "gn:feature_code":"PPL",
    "gn:name":"Dhok Shahbaz",
    "gn:population":0,
    "gn:timezone":"Asia/Karachi",
    "iso:country":"PK",
    "wof:name":"Dhok Shahbaz",
    "wof:placetype":"locality"
},
  "geometry": {"coordinates":[71.81253000000002,33.27399],"type":"Point"}
}