{
  "type": "Feature",
  "properties": {
    "gn:admin1_code":"4.0",
    "gn:asciiname":"Hassuwali",
    "gn:country_code":"PK",
    "gn:dem":146,
    "gn:feature_class":"P",
    "gn:feature_code":"PPL",
    "gn:name":"Hass\u016bw\u0101li",
    "gn:population":0,
    "gn:timezone":"Asia/Karachi",
    "iso:country":"PK",
    "wof:name":"Hassuwali",
    "wof:placetype":"locality"
},
  "geometry": {"coordinates":[70.78995,30.91654],"type":"Point"}
}