{
  "type": "Feature",
  "properties": {
    "gn:admin1_code":"2.0",
    "gn:asciiname":"Goth Miran",
    "gn:country_code":"PK",
    "gn:dem":41,
    "gn:feature_class":"P",
    "gn:feature_code":"PPL",
    "gn:name":"Goth Miran",
    "gn:population":0,
    "gn:timezone":"Asia/Karachi",
    "iso:country":"PK",
    "name:und_x_variant":[
        "Marhi"
    ],
    "wof:name":"Goth Miran",
    "wof:placetype":"locality"
},
  "geometry": {"coordinates":[66.61139,25.81694],"type":"Point"}
}