{
  "type": "Feature",
  "properties": {
    "gn:admin1_code":"4.0",
    "gn:asciiname":"Mahoiji",
    "gn:country_code":"PK",
    "gn:dem":721,
    "gn:feature_class":"P",
    "gn:feature_code":"PPLL",
    "gn:name":"Mahoiji",
    "gn:population":0,
    "gn:timezone":"Asia/Karachi",
    "iso:country":"PK",
    "wof:name":"Mahoiji",
    "wof:placetype":"locality"
},
  "geometry": {"coordinates":[70.21084999999999,30.70985],"type":"Point"}
}