{
  "type": "Feature",
  "properties": {
    "gn:admin1_code":"4",
    "gn:asciiname":"Basti Qutab Isran",
    "gn:country_code":"PK",
    "gn:dem":110,
    "gn:feature_class":"P",
    "gn:feature_code":"PPL",
    "gn:name":"Basti Qutab Isran",
    "gn:population":0,
    "gn:timezone":"Asia/Karachi",
    "iso:country":"PK",
    "name:und_x_variant":[
        "Basti Ar\u0101inw\u0101la",
        "Ar\u0101inw\u0101la",
        "Basti Qutab Isran"
    ],
    "wof:name":"Basti Qutab Isran",
    "wof:placetype":"locality"
},
  "geometry": {"coordinates":[70.43031999999999,29.56875],"type":"Point"}
}