{
  "type": "Feature",
  "properties": {
    "gn:admin1_code":"2.0",
    "gn:asciiname":"Ishaq Jhuggi",
    "gn:country_code":"PK",
    "gn:dem":972,
    "gn:feature_class":"P",
    "gn:feature_code":"PPL",
    "gn:name":"Ishaq Jhuggi",
    "gn:population":0,
    "gn:timezone":"Asia/Karachi",
    "iso:country":"PK",
    "wof:name":"Ishaq Jhuggi",
    "wof:placetype":"locality"
},
  "geometry": {"coordinates":[64.88999,26.51083],"type":"Point"}
}