{
  "type": "Feature",
  "properties": {
    "gn:admin1_code":"04",
    "gn:asciiname":"Malik",
    "gn:country_code":"PK",
    "gn:dem":534,
    "gn:feature_class":"P",
    "gn:feature_code":"PPL",
    "gn:name":"Malik",
    "gn:population":0,
    "gn:timezone":"Asia/Karachi",
    "iso:country":"PK",
    "name:und_x_variant":[
        "Malakpur",
        "Malikpur",
        "Malik"
    ],
    "wof:name":"Malik",
    "wof:placetype":"locality"
},
  "geometry": {"coordinates":[72.70494000000002,33.47424],"type":"Point"}
}