{
  "type": "Feature",
  "properties": {
    "gn:admin1_code":"04",
    "gn:asciiname":"Malik",
    "gn:country_code":"PK",
    "gn:dem":534,
    "gn:feature_class":"P",
    "gn:feature_code":"PPL",
    "gn:name":"Malik",
    "gn:population":0,
    "gn:timezone":"Asia/Karachi",
    "iso:country":"PK",
    "name:aze_x_preferred":[
        "M\u0259lik"
    ],
    "name:bel_x_preferred":[
        "\u041c\u0430\u043b\u0456\u043a"
    ],
    "name:cat_x_preferred":[
        "M\u00e0lik"
    ],
    "name:deu_x_preferred":[
        "Malki"
    ],
    "name:epo_x_preferred":[
        "Maliko"
    ],
    "name:fra_x_preferred":[
        "Malik"
    ],
    "name:hun_x_preferred":[
        "Malik"
    ],
    "name:hye_x_preferred":[
        "\u0544\u0578\u0582\u056c\u0584"
    ],
    "name:isl_x_preferred":[
        "Malik"
    ],
    "name:ita_x_preferred":[
        "Malik"
    ],
    "name:jpn_x_preferred":[
        "\u30de\u30ea\u30af"
    ],
    "name:pol_x_preferred":[
        "Malik"
    ],
    "name:por_x_preferred":[
        "Malique"
    ],
    "name:rus_x_preferred":[
        "\u041c\u0430\u043b\u0438\u043a"
    ],
    "name:spa_x_preferred":[
        "Malik"
    ],
    "name:ukr_x_preferred":[
        "\u041c\u0430\u043b\u0456\u043a"
    ],
    "name:und_x_variant":[
        "Malakpur",
        "Malikpur",
        "Malik"
    ],
    "name:urd_x_preferred":[
        "\u0645\u0627\u0644\u06a9"
    ],
    "name:zho_x_preferred":[
        "\u99ac\u5229\u514b"
    ],
    "wof:name":"Malik",
    "wof:placetype":"locality"
},
  "geometry": {"coordinates":[72.70494000000002,33.47424],"type":"Point"}
}