{
  "type": "Feature",
  "properties": {
    "gn:admin1_code":"5",
    "gn:asciiname":"Goth Bangal Lashari",
    "gn:country_code":"PK",
    "gn:dem":24,
    "gn:feature_class":"P",
    "gn:feature_code":"PPL",
    "gn:name":"Goth Bangal Lashari",
    "gn:population":0,
    "gn:timezone":"Asia/Karachi",
    "iso:country":"PK",
    "name:eng_x_preferred":[
        "Bangal Lash\u0101ri"
    ],
    "wof:name":"Goth Bangal Lashari",
    "wof:placetype":"locality"
},
  "geometry": {"coordinates":[68.44455000000001,25.53883],"type":"Point"}
}