{
  "type": "Feature",
  "properties": {
    "gn:admin1_code":"3",
    "gn:asciiname":"Ghora Dakka Cantonment",
    "gn:country_code":"PK",
    "gn:dem":2360,
    "gn:feature_class":"P",
    "gn:feature_code":"PPL",
    "gn:name":"Ghora Dakka Cantonment",
    "gn:population":0,
    "gn:timezone":"Asia/Karachi",
    "iso:country":"PK",
    "name:fas_x_preferred":[
        "\u06af\u0648\u0631\u0627 \u062f\u0627\u06a9\u0627"
    ],
    "name:sco_x_preferred":[
        "Ghora Dhaka"
    ],
    "wof:name":"Ghora Dakka Cantonment",
    "wof:placetype":"locality"
},
  "geometry": {"coordinates":[73.40959000000002,34.0283],"type":"Point"}
}