{
  "type": "Feature",
  "properties": {
    "gn:admin1_code":"3",
    "gn:asciiname":"Ghora Dakka Cantonment",
    "gn:country_code":"PK",
    "gn:dem":2360,
    "gn:feature_class":"P",
    "gn:feature_code":"PPL",
    "gn:name":"Ghora Dakka Cantonment",
    "gn:population":0,
    "gn:timezone":"Asia/Karachi",
    "iso:country":"PK",
    "wof:name":"Ghora Dakka Cantonment",
    "wof:placetype":"locality"
},
  "geometry": {"coordinates":[73.40959000000002,34.0283],"type":"Point"}
}