{
  "type": "Feature",
  "properties": {
    "gn:admin1_code":"2.0",
    "gn:asciiname":"Mandazai",
    "gn:country_code":"PK",
    "gn:dem":1566,
    "gn:feature_class":"P",
    "gn:feature_code":"PPL",
    "gn:name":"Mandazai",
    "gn:population":0,
    "gn:timezone":"Asia/Karachi",
    "iso:country":"PK",
    "wof:name":"Mandazai",
    "wof:placetype":"locality"
},
  "geometry": {"coordinates":[70.08756,31.28708],"type":"Point"}
}