{
  "type": "Feature",
  "properties": {
    "gn:admin1_code":"4",
    "gn:asciiname":"Chak Allauddin",
    "gn:country_code":"PK",
    "gn:dem":225,
    "gn:feature_class":"P",
    "gn:feature_code":"PPL",
    "gn:name":"Chak Allauddin",
    "gn:population":0,
    "gn:timezone":"Asia/Karachi",
    "iso:country":"PK",
    "name:und_x_variant":[
        "Chak All\u0101uadin"
    ],
    "wof:name":"Chak Allauddin",
    "wof:placetype":"locality"
},
  "geometry": {"coordinates":[74.53201,32.05985],"type":"Point"}
}