{
  "type": "Feature",
  "properties": {
    "gn:admin1_code":"5",
    "gn:asciiname":"Goth Kundan Singh",
    "gn:country_code":"PK",
    "gn:dem":50,
    "gn:feature_class":"P",
    "gn:feature_code":"PPL",
    "gn:name":"Goth Kundan Singh",
    "gn:population":0,
    "gn:timezone":"Asia/Karachi",
    "iso:country":"PK",
    "name:und_x_variant":[
        "Goth Kandan Singh",
        "Kunan Jatoi",
        "Goth Kundan Singh"
    ],
    "wof:name":"Goth Kundan Singh",
    "wof:placetype":"locality"
},
  "geometry": {"coordinates":[68.00376999999999,27.35826],"type":"Point"}
}