{
  "type": "Feature",
  "properties": {
    "gn:admin1_code":"1",
    "gn:asciiname":"Adam Burj",
    "gn:country_code":"PK",
    "gn:dem":1310,
    "gn:feature_class":"P",
    "gn:feature_code":"PPL",
    "gn:name":"Adam Burj",
    "gn:population":0,
    "gn:timezone":"Asia/Karachi",
    "iso:country":"PK",
    "name:fas_x_preferred":[
        "\u0627\u062f\u0645 \u0628\u0631\u062c"
    ],
    "wof:name":"Adam Burj",
    "wof:placetype":"locality"
},
  "geometry": {"coordinates":[69.83111,32.36611],"type":"Point"}
}