{
  "type": "Feature",
  "properties": {
    "gn:admin1_code":"5.0",
    "gn:asciiname":"Muhammad Hasan Shah",
    "gn:country_code":"PK",
    "gn:dem":61,
    "gn:feature_class":"P",
    "gn:feature_code":"PPL",
    "gn:name":"Muhammad Hasan Shah",
    "gn:population":0,
    "gn:timezone":"Asia/Karachi",
    "iso:country":"PK",
    "name:und_x_variant":[
        "Muhammad Hasan Sh\u0101n"
    ],
    "wof:name":"Muhammad Hasan Shah",
    "wof:placetype":"locality"
},
  "geometry": {"coordinates":[68.76229000000001,28.33791],"type":"Point"}
}