{
  "type": "Feature",
  "properties": {
    "gn:admin1_code":"5.0",
    "gn:asciiname":"Loh",
    "gn:country_code":"PK",
    "gn:dem":9,
    "gn:feature_class":"P",
    "gn:feature_code":"PPL",
    "gn:name":"Loh",
    "gn:population":0,
    "gn:timezone":"Asia/Karachi",
    "iso:country":"PK",
    "name:ceb_x_preferred":[
        "Loh"
    ],
    "name:deu_x_preferred":[
        "Loh"
    ],
    "name:nds_x_preferred":[
        "Loh"
    ],
    "name:swe_x_preferred":[
        "Loh"
    ],
    "wof:name":"Loh",
    "wof:placetype":"locality"
},
  "geometry": {"coordinates":[69.16904,24.48294],"type":"Point"}
}