{
  "type": "Feature",
  "properties": {
    "gn:admin1_code":"5",
    "gn:asciiname":"Goth Ghulam Muhammad Laghari",
    "gn:country_code":"PK",
    "gn:dem":28,
    "gn:feature_class":"P",
    "gn:feature_code":"PPL",
    "gn:name":"Goth Ghulam Muhammad Laghari",
    "gn:population":0,
    "gn:timezone":"Asia/Karachi",
    "iso:country":"PK",
    "name:eng_x_preferred":[
        "Gholam Muhammad Lagh\u0101ri"
    ],
    "wof:name":"Goth Ghulam Muhammad Laghari",
    "wof:placetype":"locality"
},
  "geometry": {"coordinates":[68.49585999999999,25.89242],"type":"Point"}
}