{
  "type": "Feature",
  "properties": {
    "gn:admin1_code":"7",
    "gn:asciiname":"Chathatang",
    "gn:country_code":"PK",
    "gn:dem":2705,
    "gn:feature_class":"P",
    "gn:feature_code":"PPL",
    "gn:name":"Chathatang",
    "gn:population":0,
    "gn:timezone":"Asia/Karachi",
    "iso:country":"PK",
    "wof:name":"Chathatang",
    "wof:placetype":"locality"
},
  "geometry": {"coordinates":[76.23205,34.73597],"type":"Point"}
}