{
  "type": "Feature",
  "properties": {
    "gn:admin1_code":"4.0",
    "gn:asciiname":"Basti Ali Dost Zamkani",
    "gn:country_code":"PK",
    "gn:dem":83,
    "gn:feature_class":"P",
    "gn:feature_code":"PPL",
    "gn:name":"Basti Ali Dost Zamkani",
    "gn:population":0,
    "gn:timezone":"Asia/Karachi",
    "iso:country":"PK",
    "name:und_x_variant":[
        "Basti Zamk\u0101ni"
    ],
    "wof:name":"Basti Ali Dost Zamkani",
    "wof:placetype":"locality"
},
  "geometry": {"coordinates":[70.03785999999999,28.7105],"type":"Point"}
}