{
  "type": "Feature",
  "properties": {
    "gn:admin1_code":"2.0",
    "gn:asciiname":"Nau Karbala",
    "gn:country_code":"PK",
    "gn:dem":1481,
    "gn:feature_class":"P",
    "gn:feature_code":"PPL",
    "gn:name":"Nau Karbala",
    "gn:population":0,
    "gn:timezone":"Asia/Karachi",
    "iso:country":"PK",
    "wof:name":"Nau Karbala",
    "wof:placetype":"locality"
},
  "geometry": {"coordinates":[66.8947,30.67785],"type":"Point"}
}