{
  "type": "Feature",
  "properties": {
    "gn:admin1_code":"7.0",
    "gn:asciiname":"Baskomal",
    "gn:country_code":"PK",
    "gn:dem":1875,
    "gn:feature_class":"P",
    "gn:feature_code":"PPL",
    "gn:name":"Baskomal",
    "gn:population":0,
    "gn:timezone":"Asia/Karachi",
    "iso:country":"PK",
    "wof:name":"Baskomal",
    "wof:placetype":"locality"
},
  "geometry": {"coordinates":[73.43535,35.68084],"type":"Point"}
}