{
  "type": "Feature",
  "properties": {
    "gn:admin1_code":"2",
    "gn:asciiname":"Sheikhan",
    "gn:country_code":"PK",
    "gn:dem":1573,
    "gn:feature_class":"P",
    "gn:feature_code":"PPL",
    "gn:name":"Sheikhan",
    "gn:population":0,
    "gn:timezone":"Asia/Karachi",
    "iso:country":"PK",
    "name:fas_x_preferred":[
        "\u0634\u06cc\u062e\u0646"
    ],
    "name:und_x_variant":[
        "Shailkh\u0101n Kile",
        "Shaikh\u0101n Kile",
        "Sheikhan"
    ],
    "name:urd_x_preferred":[
        "\u0634\u06cc\u062e\u0646"
    ],
    "wof:name":"Sheikhan",
    "wof:placetype":"locality"
},
  "geometry": {"coordinates":[67.02383,30.44289],"type":"Point"}
}