{
  "type": "Feature",
  "properties": {
    "gn:admin1_code":"4",
    "gn:asciiname":"Tarewala",
    "gn:country_code":"PK",
    "gn:dem":200,
    "gn:feature_class":"P",
    "gn:feature_code":"PPL",
    "gn:name":"Tarewala",
    "gn:population":0,
    "gn:timezone":"Asia/Karachi",
    "iso:country":"PK",
    "name:und_x_variant":[
        "T\u0101r\u0101garh"
    ],
    "wof:name":"Tarewala",
    "wof:placetype":"locality"
},
  "geometry": {"coordinates":[73.53496,31.78411],"type":"Point"}
}