{
  "type": "Feature",
  "properties": {
    "gn:admin1_code":"3.0",
    "gn:asciiname":"Bachakai",
    "gn:country_code":"PK",
    "gn:dem":382,
    "gn:feature_class":"P",
    "gn:feature_code":"PPL",
    "gn:name":"Bachakai",
    "gn:population":0,
    "gn:timezone":"Asia/Karachi",
    "iso:country":"PK",
    "name:und_x_variant":[
        "Bachaki",
        "Backaki",
        "Bachki",
        "Bachkl",
        "Bachakai"
    ],
    "wof:name":"Bachakai",
    "wof:placetype":"locality"
},
  "geometry": {"coordinates":[70.50248000000001,32.81134],"type":"Point"}
}