{
  "type": "Feature",
  "properties": {
    "gn:admin1_code":"2.0",
    "gn:asciiname":"Abdul Ghafur",
    "gn:country_code":"PK",
    "gn:dem":1315,
    "gn:feature_class":"P",
    "gn:feature_code":"PPL",
    "gn:name":"Abdul Ghafur",
    "gn:population":0,
    "gn:timezone":"Asia/Karachi",
    "iso:country":"PK",
    "wof:name":"Abdul Ghafur",
    "wof:placetype":"locality"
},
  "geometry": {"coordinates":[66.52428,27.61576],"type":"Point"}
}