{
  "type": "Feature",
  "properties": {
    "gn:admin1_code":"3",
    "gn:asciiname":"Tanai",
    "gn:country_code":"PK",
    "gn:dem":1687,
    "gn:feature_class":"P",
    "gn:feature_code":"PPL",
    "gn:name":"Tanai",
    "gn:population":0,
    "gn:timezone":"Asia/Karachi",
    "iso:country":"PK",
    "name:eng_x_preferred":[
        "Tanrai"
    ],
    "name:mya_x_preferred":[
        "\u1010\u1014\u102d\u102f\u1004\u103a\u1038\u1019\u103c\u102d\u102f\u1037"
    ],
    "name:pol_x_preferred":[
        "Tanai"
    ],
    "name:shn_x_preferred":[
        "\u1010\u1083\u1088\u107c\u1062\u1086\u1038\u104a \u101d\u1035\u1004\u103a\u1038"
    ],
    "wof:name":"Tanai",
    "wof:placetype":"locality"
},
  "geometry": {"coordinates":[71.84613,35.11005],"type":"Point"}
}