{
  "type": "Feature",
  "properties": {
    "gn:admin1_code":"5",
    "gn:asciiname":"Goth Muhammad Siddique",
    "gn:country_code":"PK",
    "gn:dem":47,
    "gn:feature_class":"P",
    "gn:feature_code":"PPL",
    "gn:name":"Goth Muhammad Siddique",
    "gn:population":0,
    "gn:timezone":"Asia/Karachi",
    "iso:country":"PK",
    "name:und_x_variant":[
        "Goth Muhammad Siddiane Gun"
    ],
    "wof:name":"Goth Muhammad Siddique",
    "wof:placetype":"locality"
},
  "geometry": {"coordinates":[67.90469,27.18348],"type":"Point"}
}