{
  "type": "Feature",
  "properties": {
    "gn:admin1_code":"5.0",
    "gn:asciiname":"Panan Jo Goth",
    "gn:country_code":"PK",
    "gn:dem":54,
    "gn:feature_class":"P",
    "gn:feature_code":"PPL",
    "gn:name":"Panan Jo Goth",
    "gn:population":0,
    "gn:timezone":"Asia/Karachi",
    "iso:country":"PK",
    "name:und_x_variant":[
        "P\u0101nian Jo Goth"
    ],
    "wof:name":"Panan Jo Goth",
    "wof:placetype":"locality"
},
  "geometry": {"coordinates":[68.14494999999999,27.69227],"type":"Point"}
}