{
  "type": "Feature",
  "properties": {
    "gn:admin1_code":"4.0",
    "gn:asciiname":"Basti Shaikhan",
    "gn:country_code":"PK",
    "gn:dem":105,
    "gn:feature_class":"P",
    "gn:feature_code":"PPL",
    "gn:name":"Basti Shaikhan",
    "gn:population":0,
    "gn:timezone":"Asia/Karachi",
    "iso:country":"PK",
    "name:und_x_variant":[
        "Basti Sheikh\u0101n"
    ],
    "wof:name":"Basti Shaikhan",
    "wof:placetype":"locality"
},
  "geometry": {"coordinates":[71.16954,29.24604],"type":"Point"}
}