{
  "type": "Feature",
  "properties": {
    "gn:admin1_code":"4.0",
    "gn:asciiname":"Basti Jamisabad",
    "gn:country_code":"PK",
    "gn:dem":135,
    "gn:feature_class":"P",
    "gn:feature_code":"PPL",
    "gn:name":"Basti Jamisabad",
    "gn:population":0,
    "gn:timezone":"Asia/Karachi",
    "iso:country":"PK",
    "name:hin_x_preferred":[
        "\u091c\u0947\u092e\u094d\u0938\u093e\u092c\u093e\u0926"
    ],
    "name:und_x_variant":[
        "James\u0101b\u0101d",
        "Basti Jamisabad"
    ],
    "wof:name":"Basti Jamisabad",
    "wof:placetype":"locality"
},
  "geometry": {"coordinates":[71.85438000000001,30.34368],"type":"Point"}
}