{
  "type": "Feature",
  "properties": {
    "gn:admin1_code":"4.0",
    "gn:asciiname":"Mohra Jaswal",
    "gn:country_code":"PK",
    "gn:dem":553,
    "gn:feature_class":"P",
    "gn:feature_code":"PPL",
    "gn:name":"Mohra Jaswal",
    "gn:population":0,
    "gn:timezone":"Asia/Karachi",
    "iso:country":"PK",
    "wof:name":"Mohra Jaswal",
    "wof:placetype":"locality"
},
  "geometry": {"coordinates":[73.16230999999998,33.21985],"type":"Point"}
}