{
  "type": "Feature",
  "properties": {
    "gn:admin1_code":"3.0",
    "gn:asciiname":"Neldar",
    "gn:country_code":"PK",
    "gn:dem":2589,
    "gn:feature_class":"P",
    "gn:feature_code":"PPL",
    "gn:name":"Neldar",
    "gn:population":0,
    "gn:timezone":"Asia/Karachi",
    "iso:country":"PK",
    "name:eng_x_preferred":[
        "Neldar"
    ],
    "wof:name":"Neldar",
    "wof:placetype":"locality"
},
  "geometry": {"coordinates":[72.38463,35.53281],"type":"Point"}
}