{
  "type": "Feature",
  "properties": {
    "gn:admin1_code":"04",
    "gn:asciiname":"Santpura",
    "gn:cc2":"PK",
    "gn:country_code":"PK",
    "gn:dem":186,
    "gn:feature_class":"P",
    "gn:feature_code":"PPL",
    "gn:name":"Santpura",
    "gn:population":0,
    "gn:timezone":"Asia/Karachi",
    "iso:country":"PK",
    "name:und_x_variant":[
        "Santpur",
        "Santpura"
    ],
    "wof:name":"Santpura",
    "wof:placetype":"neighbourhood"
},
  "geometry": {"coordinates":[73.16667,31.45],"type":"Point"}
}