{
  "type": "Feature",
  "properties": {
    "gn:admin1_code":"6.0",
    "gn:asciiname":"Namb",
    "gn:country_code":"PK",
    "gn:dem":506,
    "gn:feature_class":"P",
    "gn:feature_code":"PPL",
    "gn:name":"Namb",
    "gn:population":0,
    "gn:timezone":"Asia/Karachi",
    "iso:country":"PK",
    "wof:name":"Namb",
    "wof:placetype":"locality"
},
  "geometry": {"coordinates":[73.51798000000002,33.39145],"type":"Point"}
}