{
  "type": "Feature",
  "properties": {
    "gn:admin1_code":"4",
    "gn:asciiname":"Chak Five Hundred Four Gugera Branch",
    "gn:country_code":"PK",
    "gn:dem":164,
    "gn:feature_class":"P",
    "gn:feature_code":"PPL",
    "gn:name":"Chak Five Hundred Four Gugera Branch",
    "gn:population":0,
    "gn:timezone":"Asia/Karachi",
    "iso:country":"PK",
    "name:und_x_variant":[
        "Lakk\u0101nw\u0101la"
    ],
    "wof:name":"Chak Five Hundred Four Gugera Branch",
    "wof:placetype":"locality"
},
  "geometry": {"coordinates":[72.76934,30.77197],"type":"Point"}
}