{
  "type": "Feature",
  "properties": {
    "gn:admin1_code":"5",
    "gn:asciiname":"Goth Asgharabad",
    "gn:country_code":"PK",
    "gn:dem":20,
    "gn:feature_class":"P",
    "gn:feature_code":"PPL",
    "gn:name":"Goth Asgharabad",
    "gn:population":0,
    "gn:timezone":"Asia/Karachi",
    "iso:country":"PK",
    "name:eng_x_preferred":[
        "Asghar\u0101b\u0101d"
    ],
    "wof:name":"Goth Asgharabad",
    "wof:placetype":"locality"
},
  "geometry": {"coordinates":[68.4195,25.13238],"type":"Point"}
}