{
  "type": "Feature",
  "properties": {
    "gn:admin1_code":"4",
    "gn:asciiname":"Thakkarke Jamalwali",
    "gn:country_code":"PK",
    "gn:dem":175,
    "gn:feature_class":"P",
    "gn:feature_code":"PPL",
    "gn:name":"Thakkarke Jam\u0101lw\u0101li",
    "gn:population":0,
    "gn:timezone":"Asia/Karachi",
    "iso:country":"PK",
    "wof:name":"Thakkarke Jamalwali",
    "wof:placetype":"locality"
},
  "geometry": {"coordinates":[73.85556,30.42222000000001],"type":"Point"}
}