{
  "type": "Feature",
  "properties": {
    "gn:admin1_code":"07",
    "gn:asciiname":"Shimrot",
    "gn:country_code":"PK",
    "gn:dem":1738,
    "gn:feature_class":"P",
    "gn:feature_code":"PPL",
    "gn:name":"Shimrot",
    "gn:population":0,
    "gn:timezone":"Asia/Karachi",
    "iso:country":"PK",
    "wof:name":"Shimrot",
    "wof:placetype":"locality"
},
  "geometry": {"coordinates":[74.55521,35.75393],"type":"Point"}
}