{
  "type": "Feature",
  "properties": {
    "gn:admin1_code":"02",
    "gn:asciiname":"Wulgai",
    "gn:country_code":"PK",
    "gn:dem":2437,
    "gn:feature_class":"P",
    "gn:feature_code":"PPL",
    "gn:name":"Wulgai",
    "gn:population":0,
    "gn:timezone":"Asia/Karachi",
    "iso:country":"PK",
    "wof:name":"Wulgai",
    "wof:placetype":"locality"
},
  "geometry": {"coordinates":[67.50935,30.95724],"type":"Point"}
}