{
  "type": "Feature",
  "properties": {
    "gn:admin1_code":"2.0",
    "gn:asciiname":"Dodaki",
    "gn:country_code":"PK",
    "gn:dem":1336,
    "gn:feature_class":"P",
    "gn:feature_code":"PPL",
    "gn:name":"Dodaki",
    "gn:population":0,
    "gn:timezone":"Asia/Karachi",
    "iso:country":"PK",
    "wof:name":"Dodaki",
    "wof:placetype":"locality"
},
  "geometry": {"coordinates":[66.45461,27.26337],"type":"Point"}
}