{
  "type": "Feature",
  "properties": {
    "gn:admin1_code":"4.0",
    "gn:asciiname":"Bhoj Kot",
    "gn:cc2":"PK",
    "gn:country_code":"PK",
    "gn:dem":194,
    "gn:feature_class":"P",
    "gn:feature_code":"PPL",
    "gn:name":"Bhoj Kot",
    "gn:population":0,
    "gn:timezone":"Asia/Karachi",
    "iso:country":"PK",
    "name:und_x_variant":[
        "Bhujikot",
        "Bhoji Kot",
        "Bhoj Kot"
    ],
    "wof:name":"Bhoj Kot",
    "wof:placetype":"locality"
},
  "geometry": {"coordinates":[72.96666999999999,32.46667],"type":"Point"}
}