{
  "type": "Feature",
  "properties": {
    "gn:admin1_code":"2.0",
    "gn:asciiname":"Chatanpati",
    "gn:cc2":"PK",
    "gn:country_code":"PK",
    "gn:dem":57,
    "gn:feature_class":"P",
    "gn:feature_code":"PPL",
    "gn:name":"Chatanpati",
    "gn:population":0,
    "gn:timezone":"Asia/Karachi",
    "iso:country":"PK",
    "name:und_x_variant":[
        "Chhattanpatti",
        "Chatanpati"
    ],
    "wof:name":"Chatanpati",
    "wof:placetype":"locality"
},
  "geometry": {"coordinates":[68.43333,28.43333],"type":"Point"}
}