{
  "type": "Feature",
  "properties": {
    "gn:admin1_code":"3",
    "gn:asciiname":"Shira",
    "gn:country_code":"PK",
    "gn:dem":1713,
    "gn:feature_class":"P",
    "gn:feature_code":"PPL",
    "gn:name":"Shira",
    "gn:population":0,
    "gn:timezone":"Asia/Karachi",
    "iso:country":"PK",
    "name:ara_x_preferred":[
        "\u0634\u064a\u0631\u0627"
    ],
    "name:ben_x_preferred":[
        "\u09b6\u09bf\u09b0\u09be"
    ],
    "name:ceb_x_preferred":[
        "Shira"
    ],
    "name:deu_x_preferred":[
        "Shira"
    ],
    "name:ell_x_preferred":[
        "\u03a3\u03af\u03c1\u03b1"
    ],
    "name:fas_x_preferred":[
        "\u0634\u06cc\u0631\u0627"
    ],
    "name:fra_x_preferred":[
        "Shira"
    ],
    "name:heb_x_preferred":[
        "\u05e9\u05d9\u05e8\u05d4"
    ],
    "name:hin_x_preferred":[
        "\u0936\u0940\u0930\u093e"
    ],
    "name:ind_x_preferred":[
        "Shira"
    ],
    "name:ita_x_preferred":[
        "Shira"
    ],
    "name:jpn_x_preferred":[
        "\u30b7\u30e9"
    ],
    "name:kor_x_preferred":[
        "\uc26c\ub77c"
    ],
    "name:mar_x_preferred":[
        "\u0936\u093f\u0930\u093e"
    ],
    "name:pol_x_preferred":[
        "Shira"
    ],
    "name:por_x_preferred":[
        "Shira"
    ],
    "name:spa_x_preferred":[
        "Shira"
    ],
    "name:swe_x_preferred":[
        "Shira"
    ],
    "name:tur_x_preferred":[
        "Shira"
    ],
    "name:ukr_x_preferred":[
        "\u0428\u0438\u0440\u0430"
    ],
    "name:urd_x_preferred":[
        "\u0634\u06cc\u0631\u0627"
    ],
    "name:vie_x_preferred":[
        "Shira"
    ],
    "name:zho_cn_x_preferred":[
        "\u5e0c\u62c9"
    ],
    "name:zho_tw_x_preferred":[
        "\u5e0c\u62c9"
    ],
    "wof:name":"Shira",
    "wof:placetype":"locality"
},
  "geometry": {"coordinates":[72.9102,34.49244],"type":"Point"}
}