{
  "type": "Feature",
  "properties": {
    "gn:admin1_code":"3",
    "gn:asciiname":"Shira",
    "gn:country_code":"PK",
    "gn:dem":1713,
    "gn:feature_class":"P",
    "gn:feature_code":"PPL",
    "gn:name":"Shira",
    "gn:population":0,
    "gn:timezone":"Asia/Karachi",
    "iso:country":"PK",
    "name:ceb_x_preferred":[
        "Shira"
    ],
    "name:deu_x_preferred":[
        "Shira"
    ],
    "name:mar_x_preferred":[
        "\u0936\u093f\u0930\u093e"
    ],
    "wof:name":"Shira",
    "wof:placetype":"locality"
},
  "geometry": {"coordinates":[72.9102,34.49244],"type":"Point"}
}