{
  "type": "Feature",
  "properties": {
    "gn:admin1_code":"2",
    "gn:asciiname":"Goth Yaru Lashari",
    "gn:country_code":"PK",
    "gn:dem":110,
    "gn:feature_class":"P",
    "gn:feature_code":"PPL",
    "gn:name":"Goth Yaru Lashari",
    "gn:population":0,
    "gn:timezone":"Asia/Karachi",
    "iso:country":"PK",
    "wof:name":"Goth Yaru Lashari",
    "wof:placetype":"locality"
},
  "geometry": {"coordinates":[67.85094000000001,29.27378],"type":"Point"}
}