{
  "type": "Feature",
  "properties": {
    "gn:admin1_code":"3.0",
    "gn:asciiname":"Kamangar",
    "gn:country_code":"PK",
    "gn:dem":712,
    "gn:feature_class":"P",
    "gn:feature_code":"PPL",
    "gn:name":"Kamangar",
    "gn:population":0,
    "gn:timezone":"Asia/Karachi",
    "iso:country":"PK",
    "wof:name":"Kamangar",
    "wof:placetype":"locality"
},
  "geometry": {"coordinates":[71.16065999999999,33.09713],"type":"Point"}
}