{
  "type": "Feature",
  "properties": {
    "gn:admin1_code":"4.0",
    "gn:asciiname":"Aminabad",
    "gn:country_code":"PK",
    "gn:dem":215,
    "gn:feature_class":"P",
    "gn:feature_code":"PPL",
    "gn:name":"Aminabad",
    "gn:population":0,
    "gn:timezone":"Asia/Karachi",
    "iso:country":"PK",
    "name:aze_x_preferred":[
        "Aminabad"
    ],
    "name:ckb_x_preferred":[
        "\u0626\u06d5\u0645\u06cc\u0646\u0627\u0648\u0627"
    ],
    "name:fas_x_preferred":[
        "\u0627\u0645\u06cc\u0646\u200c\u0622\u0628\u0627\u062f"
    ],
    "name:und_x_variant":[
        "Amin\u0101b\u0101d"
    ],
    "wof:name":"Aminabad",
    "wof:placetype":"locality"
},
  "geometry": {"coordinates":[74.39221999999999,31.88833],"type":"Point"}
}