{
  "type": "Feature",
  "properties": {
    "gn:admin1_code":"02",
    "gn:asciiname":"Kach Sandozai",
    "gn:country_code":"PK",
    "gn:dem":990,
    "gn:feature_class":"P",
    "gn:feature_code":"PPL",
    "gn:name":"Kach Sandozai",
    "gn:population":0,
    "gn:timezone":"Asia/Karachi",
    "iso:country":"PK",
    "name:eng_x_preferred":[
        "S\u0101dozai Kili"
    ],
    "name:und_x_variant":[
        "Sadozai",
        "Kach Sandozai"
    ],
    "wof:name":"Kach Sandozai",
    "wof:placetype":"locality"
},
  "geometry": {"coordinates":[68.89664999999999,30.16753],"type":"Point"}
}