{
  "type": "Feature",
  "properties": {
    "gn:admin1_code":"4.0",
    "gn:asciiname":"Basti Farid Bhatti",
    "gn:country_code":"PK",
    "gn:dem":99,
    "gn:feature_class":"P",
    "gn:feature_code":"PPL",
    "gn:name":"Basti Farid Bhatti",
    "gn:population":0,
    "gn:timezone":"Asia/Karachi",
    "iso:country":"PK",
    "name:und_x_variant":[
        "Basti H\u0101ji Ghul\u0101m Far\u012bd Bhatti"
    ],
    "wof:name":"Basti Farid Bhatti",
    "wof:placetype":"locality"
},
  "geometry": {"coordinates":[71.02455,29.20188],"type":"Point"}
}