{
  "type": "Feature",
  "properties": {
    "gn:admin1_code":"4",
    "gn:asciiname":"Janjuawala",
    "gn:country_code":"PK",
    "gn:dem":201,
    "gn:feature_class":"P",
    "gn:feature_code":"PPL",
    "gn:name":"Janjuawala",
    "gn:population":0,
    "gn:timezone":"Asia/Karachi",
    "iso:country":"PK",
    "name:und_x_variant":[
        "Janj\u0101nw\u0101la"
    ],
    "wof:name":"Janjuawala",
    "wof:placetype":"locality"
},
  "geometry": {"coordinates":[71.81301999999999,32.39612],"type":"Point"}
}