{
  "type": "Feature",
  "properties": {
    "gn:admin1_code":"4",
    "gn:asciiname":"Pindi",
    "gn:country_code":"PK",
    "gn:dem":266,
    "gn:feature_class":"P",
    "gn:feature_code":"PPL",
    "gn:name":"Pindi",
    "gn:population":0,
    "gn:timezone":"Asia/Karachi",
    "iso:country":"PK",
    "name:und_x_variant":[
        "Pindi Gujran",
        "Pindi"
    ],
    "wof:name":"Pindi",
    "wof:placetype":"locality"
},
  "geometry": {"coordinates":[74.32222,32.73472],"type":"Point"}
}