{
  "type": "Feature",
  "properties": {
    "gn:admin1_code":"4",
    "gn:asciiname":"Jalloke",
    "gn:country_code":"PK",
    "gn:dem":188,
    "gn:feature_class":"P",
    "gn:feature_code":"PPL",
    "gn:name":"Jalloke",
    "gn:population":0,
    "gn:timezone":"Asia/Karachi",
    "iso:country":"PK",
    "name:und_x_variant":[
        "Jal\u016bke"
    ],
    "wof:name":"Jalloke",
    "wof:placetype":"locality"
},
  "geometry": {"coordinates":[73.17744,31.86216],"type":"Point"}
}