{
  "type": "Feature",
  "properties": {
    "gn:admin1_code":"6",
    "gn:asciiname":"Marnat",
    "gn:country_code":"PK",
    "gn:dem":2368,
    "gn:feature_class":"P",
    "gn:feature_code":"PPL",
    "gn:name":"Marn\u0101t",
    "gn:population":0,
    "gn:timezone":"Asia/Karachi",
    "iso:country":"PK",
    "wof:name":"Marnat",
    "wof:placetype":"locality"
},
  "geometry": {"coordinates":[74.60139000000002,34.78194000000001],"type":"Point"}
}