{
  "type": "Feature",
  "properties": {
    "gn:admin1_code":"3.0",
    "gn:asciiname":"Badami",
    "gn:country_code":"PK",
    "gn:dem":1914,
    "gn:feature_class":"P",
    "gn:feature_code":"PPL",
    "gn:name":"Badami",
    "gn:population":0,
    "gn:timezone":"Asia/Karachi",
    "iso:country":"PK",
    "name:bar_x_preferred":[
        "Badami"
    ],
    "name:ben_x_preferred":[
        "\u09ac\u09be\u09a6\u09be\u09ae\u09c0"
    ],
    "name:bpy_x_preferred":[
        "\u09ac\u09be\u09a6\u09be\u09ae\u09bf"
    ],
    "name:cat_x_preferred":[
        "Badami"
    ],
    "name:ces_x_preferred":[
        "B\u00e1d\u00e1m\u00ed"
    ],
    "name:che_x_preferred":[
        "\u0411\u0430\u0434\u0430\u043c\u0438"
    ],
    "name:deu_x_preferred":[
        "Badami"
    ],
    "name:fra_x_preferred":[
        "Badami"
    ],
    "name:guj_x_preferred":[
        "\u0aac\u0aa6\u0abe\u0aae\u0ac0"
    ],
    "name:hin_x_preferred":[
        "\u092c\u0926\u093e\u092e\u0940"
    ],
    "name:hun_x_preferred":[
        "B\u00e1d\u00e1mi"
    ],
    "name:ita_x_preferred":[
        "Badami"
    ],
    "name:kan_x_preferred":[
        "\u0cac\u0cbe\u0ca6\u0cbe\u0cae\u0cbf"
    ],
    "name:mal_x_preferred":[
        "\u0d2c\u0d3e\u0d26\u0d3e\u0d2e\u0d3f"
    ],
    "name:mar_x_preferred":[
        "\u092c\u093e\u0926\u093e\u092e\u0940"
    ],
    "name:mlg_x_preferred":[
        "Badami"
    ],
    "name:msa_x_preferred":[
        "Badami"
    ],
    "name:new_x_preferred":[
        "\u092c\u093e\u0926\u093e\u092e\u0940"
    ],
    "name:nld_x_preferred":[
        "Badami"
    ],
    "name:pol_x_preferred":[
        "Badami"
    ],
    "name:rus_x_preferred":[
        "\u0411\u0430\u0434\u0430\u043c\u0438"
    ],
    "name:san_x_preferred":[
        "\u092c\u093e\u0926\u093e\u092e\u0940"
    ],
    "name:spa_x_preferred":[
        "Badami"
    ],
    "name:tam_x_preferred":[
        "\u0baa\u0bbe\u0ba4\u0bae\u0bbf"
    ],
    "name:tel_x_preferred":[
        "\u0c2c\u0c3e\u0c26\u0c3e\u0c2e\u0c3f"
    ],
    "name:tur_x_preferred":[
        "Badami"
    ],
    "name:ukr_x_preferred":[
        "\u0411\u0430\u0434\u0430\u043c\u0456"
    ],
    "name:vie_x_preferred":[
        "Badami"
    ],
    "name:zho_x_preferred":[
        "\u5df4\u8fbe\u7c73"
    ],
    "wof:name":"Badami",
    "wof:placetype":"locality"
},
  "geometry": {"coordinates":[72.13611,35.07854],"type":"Point"}
}