{
  "type": "Feature",
  "properties": {
    "gn:admin1_code":"3.0",
    "gn:asciiname":"Badami",
    "gn:country_code":"PK",
    "gn:dem":1914,
    "gn:feature_class":"P",
    "gn:feature_code":"PPL",
    "gn:name":"Badami",
    "gn:population":0,
    "gn:timezone":"Asia/Karachi",
    "iso:country":"PK",
    "wof:name":"Badami",
    "wof:placetype":"locality"
},
  "geometry": {"coordinates":[72.13611,35.07854],"type":"Point"}
}