{
  "type": "Feature",
  "properties": {
    "gn:admin1_code":"3",
    "gn:asciiname":"Ghanaila",
    "gn:country_code":"PK",
    "gn:dem":1817,
    "gn:feature_class":"P",
    "gn:feature_code":"PPL",
    "gn:name":"Ghanaila",
    "gn:population":0,
    "gn:timezone":"Asia/Karachi",
    "iso:country":"PK",
    "name:und_x_variant":[
        "Ghanela"
    ],
    "wof:name":"Ghanaila",
    "wof:placetype":"locality"
},
  "geometry": {"coordinates":[73.35684999999999,34.61956],"type":"Point"}
}