{
  "type": "Feature",
  "properties": {
    "gn:admin1_code":"4.0",
    "gn:asciiname":"Dhok Mian Karam Elahi",
    "gn:country_code":"PK",
    "gn:dem":798,
    "gn:feature_class":"P",
    "gn:feature_code":"PPL",
    "gn:name":"Dhok Mian Karam Elahi",
    "gn:population":0,
    "gn:timezone":"Asia/Karachi",
    "iso:country":"PK",
    "wof:name":"Dhok Mian Karam Elahi",
    "wof:placetype":"locality"
},
  "geometry": {"coordinates":[72.04510000000001,32.53574],"type":"Point"}
}