{
  "type": "Feature",
  "properties": {
    "gn:admin1_code":"5",
    "gn:asciiname":"Sharifani",
    "gn:country_code":"PK",
    "gn:dem":52,
    "gn:feature_class":"P",
    "gn:feature_code":"PPL",
    "gn:name":"Sharifani",
    "gn:population":0,
    "gn:timezone":"Asia/Karachi",
    "iso:country":"PK",
    "name:und_x_variant":[
        "Goth Shar\u012bf\u0101ni"
    ],
    "wof:name":"Sharifani",
    "wof:placetype":"locality"
},
  "geometry": {"coordinates":[68.02673,27.53727],"type":"Point"}
}