{
  "type": "Feature",
  "properties": {
    "gn:admin1_code":"4.0",
    "gn:asciiname":"Bhoia Khurd",
    "gn:country_code":"PK",
    "gn:dem":301,
    "gn:feature_class":"P",
    "gn:feature_code":"PPL",
    "gn:name":"Bhoia Khurd",
    "gn:population":0,
    "gn:timezone":"Asia/Karachi",
    "iso:country":"PK",
    "wof:name":"Bhoia Khurd",
    "wof:placetype":"locality"
},
  "geometry": {"coordinates":[75.02273000000002,32.45262],"type":"Point"}
}