{
  "type": "Feature",
  "properties": {
    "gn:admin1_code":"3.0",
    "gn:asciiname":"Abbas Kalle",
    "gn:country_code":"PK",
    "gn:dem":310,
    "gn:feature_class":"P",
    "gn:feature_code":"PPL",
    "gn:name":"Abbas Kalle",
    "gn:population":0,
    "gn:timezone":"Asia/Karachi",
    "iso:country":"PK",
    "name:eng_x_preferred":[
        "Ab\u0101s Kor\u016bna"
    ],
    "wof:name":"Abbas Kalle",
    "wof:placetype":"locality"
},
  "geometry": {"coordinates":[71.84214,34.15584],"type":"Point"}
}