{
  "type": "Feature",
  "properties": {
    "gn:admin1_code":"04",
    "gn:asciiname":"Chak Seventy-six Gugera Branch",
    "gn:country_code":"PK",
    "gn:dem":184,
    "gn:feature_class":"P",
    "gn:feature_code":"PPL",
    "gn:name":"Chak Seventy-six Gugera Branch",
    "gn:population":0,
    "gn:timezone":"Asia/Karachi",
    "iso:country":"PK",
    "name:und_x_variant":[
        "Santokhgarh",
        "Chak Seventy-Six GB Janubi",
        "Chak Seventy-six Gugera Branch"
    ],
    "wof:name":"Chak Seventy-six Gugera Branch",
    "wof:placetype":"locality"
},
  "geometry": {"coordinates":[73.16656,31.28764],"type":"Point"}
}