{
  "type": "Feature",
  "properties": {
    "gn:admin1_code":"2",
    "gn:asciiname":"Shahr Sardar Kot",
    "gn:country_code":"PK",
    "gn:dem":1735,
    "gn:feature_class":"P",
    "gn:feature_code":"PPL",
    "gn:name":"Shahr Sardar Kot",
    "gn:population":0,
    "gn:timezone":"Asia/Karachi",
    "iso:country":"PK",
    "name:und_x_variant":[
        "Shahr Sard\u0101r"
    ],
    "wof:name":"Shahr Sardar Kot",
    "wof:placetype":"locality"
},
  "geometry": {"coordinates":[66.53612,29.40456],"type":"Point"}
}