{
  "type": "Feature",
  "properties": {
    "gn:admin1_code":"3.0",
    "gn:asciiname":"Fidabad",
    "gn:country_code":"PK",
    "gn:dem":401,
    "gn:feature_class":"P",
    "gn:feature_code":"PPL",
    "gn:name":"Fidabad",
    "gn:population":0,
    "gn:timezone":"Asia/Karachi",
    "iso:country":"PK",
    "wof:name":"Fidabad",
    "wof:placetype":"locality"
},
  "geometry": {"coordinates":[71.61417,33.86954],"type":"Point"}
}