{
  "type": "Feature",
  "properties": {
    "gn:admin1_code":"5.0",
    "gn:asciiname":"Haji Durran",
    "gn:country_code":"PK",
    "gn:dem":47,
    "gn:feature_class":"P",
    "gn:feature_code":"PPL",
    "gn:name":"Haji Durran",
    "gn:population":0,
    "gn:timezone":"Asia/Karachi",
    "iso:country":"PK",
    "name:und_x_variant":[
        "H\u0101ji Durr\u0101ni"
    ],
    "wof:name":"Haji Durran",
    "wof:placetype":"locality"
},
  "geometry": {"coordinates":[67.89248000000001,27.91748],"type":"Point"}
}