{
  "type": "Feature",
  "properties": {
    "gn:admin1_code":"1",
    "gn:asciiname":"Khara Manza",
    "gn:country_code":"PK",
    "gn:dem":2235,
    "gn:feature_class":"P",
    "gn:feature_code":"PPLL",
    "gn:name":"Khara Manza",
    "gn:population":0,
    "gn:timezone":"Asia/Karachi",
    "iso:country":"PK",
    "wof:name":"Khara Manza",
    "wof:placetype":"locality"
},
  "geometry": {"coordinates":[69.78546999999999,32.71857],"type":"Point"}
}