{
  "type": "Feature",
  "properties": {
    "gn:admin1_code":"3",
    "gn:asciiname":"Barthana",
    "gn:country_code":"PK",
    "gn:dem":1415,
    "gn:feature_class":"P",
    "gn:feature_code":"PPL",
    "gn:name":"Barthana",
    "gn:population":0,
    "gn:timezone":"Asia/Karachi",
    "iso:country":"PK",
    "name:und_x_variant":[
        "Bart\u0101na"
    ],
    "wof:name":"Barthana",
    "wof:placetype":"locality"
},
  "geometry": {"coordinates":[72.33073,35.04109],"type":"Point"}
}