{
  "type": "Feature",
  "properties": {
    "gn:admin1_code":"04",
    "gn:asciiname":"Rosha Shahani",
    "gn:country_code":"PK",
    "gn:dem":174,
    "gn:feature_class":"P",
    "gn:feature_code":"PPL",
    "gn:name":"Rosha Shahani",
    "gn:population":0,
    "gn:timezone":"Asia/Karachi",
    "iso:country":"PK",
    "name:und_x_variant":[
        "Roshe Shah\u0101ni",
        "Ahmad Sh\u0101h"
    ],
    "wof:name":"Rosha Shahani",
    "wof:placetype":"locality"
},
  "geometry": {"coordinates":[73.15906,30.83171],"type":"Point"}
}