{
  "type": "Feature",
  "properties": {
    "gn:admin1_code":"2.0",
    "gn:asciiname":"Darzi Chah",
    "gn:country_code":"PK",
    "gn:dem":912,
    "gn:feature_class":"P",
    "gn:feature_code":"PPL",
    "gn:name":"Darzi Chah",
    "gn:population":0,
    "gn:timezone":"Asia/Karachi",
    "iso:country":"PK",
    "name:und_x_variant":[
        "Darzi"
    ],
    "wof:name":"Darzi Chah",
    "wof:placetype":"locality"
},
  "geometry": {"coordinates":[65.63821999999999,29.64248],"type":"Point"}
}