{
  "type": "Feature",
  "properties": {
    "iso:country":"PK",
    "name:ara_x_preferred":[
        "\u0635\u062f\u0631"
    ],
    "name:ceb_x_preferred":[
        "Sadr"
    ],
    "name:deu_x_preferred":[
        "Sadr"
    ],
    "name:eng_x_preferred":[
        "Sadr"
    ],
    "name:fas_x_preferred":[
        "\u0635\u062f\u0631"
    ],
    "name:fra_x_preferred":[
        "Sadr"
    ],
    "name:heb_x_preferred":[
        "\u05e1\u05d0\u05d3\u05e8"
    ],
    "name:jav_x_preferred":[
        "Dhadha"
    ],
    "name:pag_x_preferred":[
        "Pageo"
    ],
    "name:rus_x_preferred":[
        "\u0421\u0430\u0434\u0440"
    ],
    "name:swe_x_preferred":[
        "Sadr"
    ],
    "name:urd_x_preferred":[
        "\u0635\u062f\u0631"
    ],
    "qs:gn_adm0_cc":"PK",
    "qs:gn_local":1174872,
    "qs:gn_nam_loc":"Karachi, Sindh, PK",
    "qs:gn_namadm1":"05",
    "qs:local_max":2851,
    "qs:local_sum":5348,
    "qs:localhoods":21,
    "qs:name":"Sadr",
    "qs:name_adm0":"Pakistan",
    "qs:name_adm1":"Sindh",
    "qs:name_local":"Karachi",
    "qs:photo_max":14,
    "qs:photo_sum":51,
    "qs:placetype":"Suburb",
    "qs:quad_count":8,
    "qs:woe_adm0":23424922,
    "qs:woe_adm1":2346499,
    "qs:woe_adm2":0,
    "qs:woe_lau":0,
    "qs:woe_local":2211096,
    "qs:woe_ver":"7.10.0",
    "wof:lang":[
        "eng"
    ],
    "wof:name":"Sadr",
    "wof:placetype":"neighbourhood"
},
  "geometry": {"coordinates":[67.02641800000001,24.86161],"type":"Point"}
}