{
  "type": "Feature",
  "properties": {
    "gn:admin1_code":"7.0",
    "gn:asciiname":"Paliat",
    "gn:country_code":"PK",
    "gn:dem":2893,
    "gn:feature_class":"P",
    "gn:feature_code":"PPL",
    "gn:name":"Paliat",
    "gn:population":0,
    "gn:timezone":"Asia/Karachi",
    "iso:country":"PK",
    "wof:name":"Paliat",
    "wof:placetype":"locality"
},
  "geometry": {"coordinates":[74.91365,35.39975],"type":"Point"}
}