{
  "type": "Feature",
  "properties": {
    "gn:admin1_code":"4",
    "gn:asciiname":"Burhanwala",
    "gn:country_code":"PK",
    "gn:dem":136,
    "gn:feature_class":"P",
    "gn:feature_code":"PPL",
    "gn:name":"Burhanwala",
    "gn:population":0,
    "gn:timezone":"Asia/Karachi",
    "iso:country":"PK",
    "wof:name":"Burhanwala",
    "wof:placetype":"locality"
},
  "geometry": {"coordinates":[72.34444000000001,30.10972000000001],"type":"Point"}
}