{
  "type": "Feature",
  "properties": {
    "gn:admin1_code":"5.0",
    "gn:asciiname":"Allah Bakhsh Mihri",
    "gn:country_code":"PK",
    "gn:dem":12,
    "gn:feature_class":"P",
    "gn:feature_code":"PPL",
    "gn:name":"Allah Bakhsh Mihri",
    "gn:population":0,
    "gn:timezone":"Asia/Karachi",
    "iso:country":"PK",
    "wof:name":"Allah Bakhsh Mihri",
    "wof:placetype":"locality"
},
  "geometry": {"coordinates":[68.58445,24.84837000000001],"type":"Point"}
}