{
  "type": "Feature",
  "properties": {
    "gn:admin1_code":"2.0",
    "gn:asciiname":"Kili Sanjar Khan",
    "gn:country_code":"PK",
    "gn:dem":1287,
    "gn:feature_class":"P",
    "gn:feature_code":"PPL",
    "gn:name":"Kili Sanjar Khan",
    "gn:population":0,
    "gn:timezone":"Asia/Karachi",
    "iso:country":"PK",
    "wof:name":"Kili Sanjar Khan",
    "wof:placetype":"locality"
},
  "geometry": {"coordinates":[65.37568,27.29147],"type":"Point"}
}