{
  "type": "Feature",
  "properties": {
    "gn:admin1_code":"4.0",
    "gn:asciiname":"Chak Fifteen North Branch",
    "gn:country_code":"PK",
    "gn:dem":193,
    "gn:feature_class":"P",
    "gn:feature_code":"PPL",
    "gn:name":"Chak Fifteen North Branch",
    "gn:population":0,
    "gn:timezone":"Asia/Karachi",
    "iso:country":"PK",
    "name:und_x_variant":[
        "Chak 15 NB"
    ],
    "wof:name":"Chak Fifteen North Branch",
    "wof:placetype":"locality"
},
  "geometry": {"coordinates":[72.81215,32.27109],"type":"Point"}
}