{
  "type": "Feature",
  "properties": {
    "gn:admin1_code":"4.0",
    "gn:asciiname":"Kot Hari Chand",
    "gn:country_code":"PK",
    "gn:dem":216,
    "gn:feature_class":"P",
    "gn:feature_code":"PPL",
    "gn:name":"Kot Hari Chand",
    "gn:population":0,
    "gn:timezone":"Asia/Karachi",
    "iso:country":"PK",
    "wof:name":"Kot Hari Chand",
    "wof:placetype":"neighbourhood"
},
  "geometry": {"coordinates":[74.23876,31.98174],"type":"Point"}
}