{
  "type": "Feature",
  "properties": {
    "gn:admin1_code":"1.0",
    "gn:asciiname":"Tamas Kili",
    "gn:country_code":"PK",
    "gn:dem":553,
    "gn:feature_class":"P",
    "gn:feature_code":"PPL",
    "gn:name":"Tamas Kili",
    "gn:population":0,
    "gn:timezone":"Asia/Karachi",
    "iso:country":"PK",
    "name:und_x_variant":[
        "Az\u0101d Khel",
        "Mult\u0101n Kili"
    ],
    "wof:name":"Tamas Kili",
    "wof:placetype":"locality"
},
  "geometry": {"coordinates":[71.24166,34.22846],"type":"Point"}
}