{
  "type": "Feature",
  "properties": {
    "gn:admin1_code":"3.0",
    "gn:asciiname":"Zankai Banda",
    "gn:country_code":"PK",
    "gn:dem":782,
    "gn:feature_class":"P",
    "gn:feature_code":"PPL",
    "gn:name":"Zankai Banda",
    "gn:population":0,
    "gn:timezone":"Asia/Karachi",
    "iso:country":"PK",
    "name:und_x_variant":[
        "Zanki"
    ],
    "wof:name":"Zankai Banda",
    "wof:placetype":"locality"
},
  "geometry": {"coordinates":[71.10221,33.53402],"type":"Point"}
}