{
  "type": "Feature",
  "properties": {
    "gn:admin1_code":"4.0",
    "gn:asciiname":"Dhok Karmullah",
    "gn:country_code":"PK",
    "gn:dem":381,
    "gn:feature_class":"P",
    "gn:feature_code":"PPL",
    "gn:name":"Dhok Karmullah",
    "gn:population":0,
    "gn:timezone":"Asia/Karachi",
    "iso:country":"PK",
    "name:und_x_variant":[
        "Karmull\u0101hw\u0101li"
    ],
    "wof:name":"Dhok Karmullah",
    "wof:placetype":"locality"
},
  "geometry": {"coordinates":[71.83471,32.85890999999999],"type":"Point"}
}