{
  "type": "Feature",
  "properties": {
    "gn:admin1_code":"2.0",
    "gn:asciiname":"Dandar",
    "gn:country_code":"PK",
    "gn:dem":550,
    "gn:feature_class":"P",
    "gn:feature_code":"PPL",
    "gn:name":"Dandar",
    "gn:population":0,
    "gn:timezone":"Asia/Karachi",
    "iso:country":"PK",
    "wof:name":"Dandar",
    "wof:placetype":"locality"
},
  "geometry": {"coordinates":[64.40595,26.12714],"type":"Point"}
}