{
  "type": "Feature",
  "properties": {
    "gn:admin1_code":"4.0",
    "gn:asciiname":"Churand",
    "gn:country_code":"PK",
    "gn:dem":212,
    "gn:feature_class":"P",
    "gn:feature_code":"PPL",
    "gn:name":"Churand",
    "gn:population":0,
    "gn:timezone":"Asia/Karachi",
    "iso:country":"PK",
    "name:und_x_variant":[
        "Chorand",
        "Churand"
    ],
    "wof:name":"Churand",
    "wof:placetype":"locality"
},
  "geometry": {"coordinates":[73.59097,32.52369],"type":"Point"}
}