{
  "type": "Feature",
  "properties": {
    "gn:admin1_code":"6",
    "gn:asciiname":"Chikar Nakka",
    "gn:country_code":"PK",
    "gn:dem":1648,
    "gn:feature_class":"P",
    "gn:feature_code":"PPL",
    "gn:name":"Chikar Nakka",
    "gn:population":0,
    "gn:timezone":"Asia/Karachi",
    "iso:country":"PK",
    "name:und_x_variant":[
        "Khui"
    ],
    "wof:name":"Chikar Nakka",
    "wof:placetype":"locality"
},
  "geometry": {"coordinates":[73.57514999999999,34.4429],"type":"Point"}
}