{
  "type": "Feature",
  "properties": {
    "gn:admin1_code":"2",
    "gn:asciiname":"Shinkai Shakh",
    "gn:country_code":"PK",
    "gn:dem":1500,
    "gn:feature_class":"P",
    "gn:feature_code":"PPL",
    "gn:name":"Shinkai Shakh",
    "gn:population":0,
    "gn:timezone":"Asia/Karachi",
    "iso:country":"PK",
    "wof:name":"Shinkai Shakh",
    "wof:placetype":"locality"
},
  "geometry": {"coordinates":[69.89624000000001,31.7962],"type":"Point"}
}