{
  "type": "Feature",
  "properties": {
    "gn:admin1_code":"4.0",
    "gn:asciiname":"Chak One Hundred Eighty",
    "gn:country_code":"PK",
    "gn:dem":146,
    "gn:feature_class":"P",
    "gn:feature_code":"PPL",
    "gn:name":"Chak One Hundred Eighty",
    "gn:population":0,
    "gn:timezone":"Asia/Karachi",
    "iso:country":"PK",
    "name:und_x_variant":[
        "Jhok\u0101n"
    ],
    "wof:name":"Chak One Hundred Eighty",
    "wof:placetype":"locality"
},
  "geometry": {"coordinates":[72.82719,29.32257],"type":"Point"}
}