{
  "type": "Feature",
  "properties": {
    "gn:admin1_code":"2.0",
    "gn:asciiname":"Assot Kili",
    "gn:country_code":"PK",
    "gn:dem":1831,
    "gn:feature_class":"P",
    "gn:feature_code":"PPL",
    "gn:name":"Assot Kili",
    "gn:population":0,
    "gn:timezone":"Asia/Karachi",
    "iso:country":"PK",
    "name:und_x_variant":[
        "Isot Kili"
    ],
    "wof:name":"Assot Kili",
    "wof:placetype":"locality"
},
  "geometry": {"coordinates":[69.99767,31.24444],"type":"Point"}
}