{
  "type": "Feature",
  "properties": {
    "gn:admin1_code":"4.0",
    "gn:asciiname":"Colony Chak One Hundred Fifty-three",
    "gn:country_code":"PK",
    "gn:dem":150,
    "gn:feature_class":"P",
    "gn:feature_code":"PPL",
    "gn:name":"Colony Chak One Hundred Fifty-three",
    "gn:population":0,
    "gn:timezone":"Asia/Karachi",
    "iso:country":"PK",
    "wof:name":"Colony Chak One Hundred Fifty-three",
    "wof:placetype":"locality"
},
  "geometry": {"coordinates":[72.67831,29.55954],"type":"Point"}
}