{
  "type": "Feature",
  "properties": {
    "gn:admin1_code":"2.0",
    "gn:asciiname":"Goth Harun",
    "gn:country_code":"PK",
    "gn:dem":45,
    "gn:feature_class":"P",
    "gn:feature_code":"PPL",
    "gn:name":"Goth Harun",
    "gn:population":0,
    "gn:timezone":"Asia/Karachi",
    "iso:country":"PK",
    "name:eng_x_preferred":[
        "Goth Harun"
    ],
    "wof:name":"Goth Harun",
    "wof:placetype":"locality"
},
  "geometry": {"coordinates":[66.77046,25.03655],"type":"Point"}
}