{
  "type": "Feature",
  "properties": {
    "gn:admin1_code":"2",
    "gn:asciiname":"Baibani",
    "gn:country_code":"PK",
    "gn:dem":1135,
    "gn:feature_class":"P",
    "gn:feature_code":"PPL",
    "gn:name":"Baibani",
    "gn:population":0,
    "gn:timezone":"Asia/Karachi",
    "iso:country":"PK",
    "name:und_x_variant":[
        "Bh\u0101b\u0101ni"
    ],
    "wof:name":"Baibani",
    "wof:placetype":"locality"
},
  "geometry": {"coordinates":[69.91735,30.10805],"type":"Point"}
}