{
  "type": "Feature",
  "properties": {
    "gn:admin1_code":"4",
    "gn:asciiname":"Chak One Hundred Twelve ML",
    "gn:country_code":"PK",
    "gn:dem":159,
    "gn:feature_class":"P",
    "gn:feature_code":"PPL",
    "gn:name":"Chak One Hundred Twelve ML",
    "gn:population":0,
    "gn:timezone":"Asia/Karachi",
    "iso:country":"PK",
    "name:und_x_variant":[
        "Chak 112 ML",
        "Chak One Hundred Twelve ML"
    ],
    "wof:name":"Chak One Hundred Twelve ML",
    "wof:placetype":"locality"
},
  "geometry": {"coordinates":[71.15125999999999,31.18794],"type":"Point"}
}