{
  "type": "Feature",
  "properties": {
    "gn:admin1_code":"3",
    "gn:asciiname":"Gamian Seri",
    "gn:country_code":"PK",
    "gn:dem":907,
    "gn:feature_class":"P",
    "gn:feature_code":"PPL",
    "gn:name":"Gamian Seri",
    "gn:population":0,
    "gn:timezone":"Asia/Karachi",
    "iso:country":"PK",
    "wof:name":"Gamian Seri",
    "wof:placetype":"locality"
},
  "geometry": {"coordinates":[72.8952,34.40168],"type":"Point"}
}