{
  "type": "Feature",
  "properties": {
    "gn:admin1_code":"4",
    "gn:asciiname":"Chak Maluk",
    "gn:country_code":"PK",
    "gn:dem":238,
    "gn:feature_class":"P",
    "gn:feature_code":"PPL",
    "gn:name":"Chak Maluk",
    "gn:population":0,
    "gn:timezone":"Asia/Karachi",
    "iso:country":"PK",
    "name:und_x_variant":[
        "Chak Maluke",
        "Chak Maluk"
    ],
    "wof:name":"Chak Maluk",
    "wof:placetype":"locality"
},
  "geometry": {"coordinates":[74.41316999999999,32.53292],"type":"Point"}
}