{
  "type": "Feature",
  "properties": {
    "gn:admin1_code":"4",
    "gn:asciiname":"Awan Tahli",
    "gn:country_code":"PK",
    "gn:dem":186,
    "gn:feature_class":"P",
    "gn:feature_code":"PPL",
    "gn:name":"Aw\u0101n Tahli",
    "gn:population":0,
    "gn:timezone":"Asia/Karachi",
    "iso:country":"PK",
    "wof:name":"Awan Tahli",
    "wof:placetype":"locality"
},
  "geometry": {"coordinates":[73.62639,31.16389],"type":"Point"}
}