{
  "type": "Feature",
  "properties": {
    "gn:admin1_code":"1.0",
    "gn:asciiname":"Sar Khonai",
    "gn:country_code":"PK",
    "gn:dem":1227,
    "gn:feature_class":"P",
    "gn:feature_code":"PPL",
    "gn:name":"Sar Khonai",
    "gn:population":0,
    "gn:timezone":"Asia/Karachi",
    "iso:country":"PK",
    "wof:name":"Sar Khonai",
    "wof:placetype":"locality"
},
  "geometry": {"coordinates":[70.13681,32.66866],"type":"Point"}
}