{
  "type": "Feature",
  "properties": {
    "gn:admin1_code":"4",
    "gn:asciiname":"Lal Khanwala Khu",
    "gn:country_code":"PK",
    "gn:dem":162,
    "gn:feature_class":"P",
    "gn:feature_code":"PPL",
    "gn:name":"Lal Khanwala Khu",
    "gn:population":0,
    "gn:timezone":"Asia/Karachi",
    "iso:country":"PK",
    "name:und_x_variant":[
        "L\u0101lw\u0101la"
    ],
    "wof:name":"Lal Khanwala Khu",
    "wof:placetype":"locality"
},
  "geometry": {"coordinates":[71.19014,31.37927],"type":"Point"}
}