{
  "type": "Feature",
  "properties": {
    "gn:admin1_code":"3.0",
    "gn:asciiname":"Bajno",
    "gn:country_code":"PK",
    "gn:dem":974,
    "gn:feature_class":"P",
    "gn:feature_code":"PPL",
    "gn:name":"Bajno",
    "gn:population":0,
    "gn:timezone":"Asia/Karachi",
    "iso:country":"PK",
    "name:und_x_variant":[
        "Bajnah",
        "Bajna",
        "Bajno"
    ],
    "wof:name":"Bajno",
    "wof:placetype":"locality"
},
  "geometry": {"coordinates":[73.25318,34.45086],"type":"Point"}
}