{
  "type": "Feature",
  "properties": {
    "gn:admin1_code":"4",
    "gn:asciiname":"Jainabad",
    "gn:country_code":"PK",
    "gn:dem":227,
    "gn:feature_class":"P",
    "gn:feature_code":"PPL",
    "gn:name":"Jainabad",
    "gn:population":0,
    "gn:timezone":"Asia/Karachi",
    "iso:country":"PK",
    "name:und_x_variant":[
        "Jain\u0101b\u0101d R\u0101mgarh"
    ],
    "wof:name":"Jainabad",
    "wof:placetype":"locality"
},
  "geometry": {"coordinates":[74.40489000000002,32.15943],"type":"Point"}
}