{
  "type": "Feature",
  "properties": {
    "gn:admin1_code":"3",
    "gn:asciiname":"Sirkh Miane",
    "gn:country_code":"PK",
    "gn:dem":355,
    "gn:feature_class":"P",
    "gn:feature_code":"PPL",
    "gn:name":"Sirkh Miane",
    "gn:population":0,
    "gn:timezone":"Asia/Karachi",
    "iso:country":"PK",
    "name:eng_x_preferred":[
        "Sir\u012bkh Mi\u0101na"
    ],
    "wof:name":"Sirkh Miane",
    "wof:placetype":"locality"
},
  "geometry": {"coordinates":[72.14869,34.32755],"type":"Point"}
}