{
  "type": "Feature",
  "properties": {
    "gn:admin1_code":"3.0",
    "gn:asciiname":"Bhamala",
    "gn:country_code":"PK",
    "gn:dem":624,
    "gn:feature_class":"P",
    "gn:feature_code":"PPL",
    "gn:name":"Bhamala",
    "gn:population":0,
    "gn:timezone":"Asia/Karachi",
    "iso:country":"PK",
    "wof:name":"Bhamala",
    "wof:placetype":"locality"
},
  "geometry": {"coordinates":[72.97556999999998,33.83402],"type":"Point"}
}