{
  "type": "Feature",
  "properties": {
    "gn:admin1_code":"4",
    "gn:asciiname":"Dodo Khan Khosa",
    "gn:country_code":"PK",
    "gn:dem":74,
    "gn:feature_class":"P",
    "gn:feature_code":"PPL",
    "gn:name":"Dodo Khan Khosa",
    "gn:population":0,
    "gn:timezone":"Asia/Karachi",
    "iso:country":"PK",
    "name:und_x_variant":[
        "Dodo Kh\u0101n Khsa"
    ],
    "wof:name":"Dodo Khan Khosa",
    "wof:placetype":"locality"
},
  "geometry": {"coordinates":[69.56453,28.37937],"type":"Point"}
}