{
  "type": "Feature",
  "properties": {
    "gn:admin1_code":"2.0",
    "gn:asciiname":"Saiyid Malik Tobo",
    "gn:country_code":"PK",
    "gn:dem":1032,
    "gn:feature_class":"P",
    "gn:feature_code":"PPL",
    "gn:name":"Saiyid Malik Tobo",
    "gn:population":0,
    "gn:timezone":"Asia/Karachi",
    "iso:country":"PK",
    "wof:name":"Saiyid Malik Tobo",
    "wof:placetype":"locality"
},
  "geometry": {"coordinates":[65.60214000000001,27.11448],"type":"Point"}
}