{
  "type": "Feature",
  "properties": {
    "gn:admin1_code":"3",
    "gn:asciiname":"Damanik Banda",
    "gn:country_code":"PK",
    "gn:dem":2453,
    "gn:feature_class":"P",
    "gn:feature_code":"PPL",
    "gn:name":"Damanik Banda",
    "gn:population":0,
    "gn:timezone":"Asia/Karachi",
    "iso:country":"PK",
    "name:eng_x_preferred":[
        "Daman\u012bk"
    ],
    "wof:name":"Damanik Banda",
    "wof:placetype":"locality"
},
  "geometry": {"coordinates":[71.62594,35.2477],"type":"Point"}
}