{
  "type": "Feature",
  "properties": {
    "gn:admin1_code":"4.0",
    "gn:asciiname":"Chak Thirteen Panjnad",
    "gn:country_code":"PK",
    "gn:dem":88,
    "gn:feature_class":"P",
    "gn:feature_code":"PPL",
    "gn:name":"Chak Thirteen Panjnad",
    "gn:population":0,
    "gn:timezone":"Asia/Karachi",
    "iso:country":"PK",
    "name:und_x_variant":[
        "Chak Thirteen P"
    ],
    "wof:name":"Chak Thirteen Panjnad",
    "wof:placetype":"locality"
},
  "geometry": {"coordinates":[70.74313000000002,28.72333],"type":"Point"}
}