{
  "type": "Feature",
  "properties": {
    "gn:admin1_code":"5",
    "gn:asciiname":"Goth Buhro Sahib Laghari",
    "gn:country_code":"PK",
    "gn:dem":16,
    "gn:feature_class":"P",
    "gn:feature_code":"PPL",
    "gn:name":"Goth Buhro Sahib Laghari",
    "gn:population":0,
    "gn:timezone":"Asia/Karachi",
    "iso:country":"PK",
    "name:und_x_variant":[
        "Buhro S\u0101hib Kh\u0101n Lagh\u0101ri Goth",
        "Buhro S\u0101hib Kh\u0101n Lagh\u0101ri",
        "Goth Buhro Sahib Laghari"
    ],
    "wof:name":"Goth Buhro Sahib Laghari",
    "wof:placetype":"locality"
},
  "geometry": {"coordinates":[68.94371,25.01171],"type":"Point"}
}