{
  "type": "Feature",
  "properties": {
    "gn:admin1_code":"6",
    "gn:asciiname":"Bade na Pai",
    "gn:country_code":"PK",
    "gn:dem":629,
    "gn:feature_class":"P",
    "gn:feature_code":"PPL",
    "gn:name":"Bade na Pai",
    "gn:population":0,
    "gn:timezone":"Asia/Karachi",
    "iso:country":"PK",
    "name:und_x_variant":[
        "Bada na Pail"
    ],
    "wof:name":"Bade na Pai",
    "wof:placetype":"locality"
},
  "geometry": {"coordinates":[74.07117,33.0468],"type":"Point"}
}