{
  "type": "Feature",
  "properties": {
    "gn:admin1_code":"5",
    "gn:asciiname":"Dhani Bakhsh Tunia",
    "gn:country_code":"PK",
    "gn:dem":51,
    "gn:feature_class":"P",
    "gn:feature_code":"PPL",
    "gn:name":"Dhani Bakhsh Tunia",
    "gn:population":0,
    "gn:timezone":"Asia/Karachi",
    "iso:country":"PK",
    "name:und_x_variant":[
        "Ali Sher Tunia"
    ],
    "wof:name":"Dhani Bakhsh Tunia",
    "wof:placetype":"locality"
},
  "geometry": {"coordinates":[68.04666999999999,27.54272000000001],"type":"Point"}
}