{
  "type": "Feature",
  "properties": {
    "gn:admin1_code":"4.0",
    "gn:asciiname":"Bet Waryanwala",
    "gn:cc2":"PK",
    "gn:country_code":"PK",
    "gn:dem":112,
    "gn:feature_class":"P",
    "gn:feature_code":"PPL",
    "gn:name":"Bet W\u0101ry\u0101nw\u0101la",
    "gn:population":0,
    "gn:timezone":"Asia/Karachi",
    "iso:country":"PK",
    "name:und_x_variant":[
        "Bet W\u0101ri\u0101nw\u0101la",
        "Bet W\u0101ry\u0101nw\u0101la"
    ],
    "wof:name":"Bet Waryanwala",
    "wof:placetype":"locality"
},
  "geometry": {"coordinates":[70.88,29.65583],"type":"Point"}
}