{
  "type": "Feature",
  "properties": {
    "gn:admin1_code":"2.0",
    "gn:asciiname":"Kili Sher Muhammad",
    "gn:country_code":"PK",
    "gn:dem":2417,
    "gn:feature_class":"P",
    "gn:feature_code":"PPL",
    "gn:name":"Kili Sher Muhammad",
    "gn:population":0,
    "gn:timezone":"Asia/Karachi",
    "iso:country":"PK",
    "wof:name":"Kili Sher Muhammad",
    "wof:placetype":"locality"
},
  "geometry": {"coordinates":[67.5791,30.62888],"type":"Point"}
}