{
  "type": "Feature",
  "properties": {
    "gn:admin1_code":"4.0",
    "gn:asciiname":"Ch Khushi Muhammad",
    "gn:country_code":"PK",
    "gn:dem":87,
    "gn:feature_class":"P",
    "gn:feature_code":"PPL",
    "gn:name":"Ch Khushi Muhammad",
    "gn:population":0,
    "gn:timezone":"Asia/Karachi",
    "iso:country":"PK",
    "wof:name":"Ch Khushi Muhammad",
    "wof:placetype":"locality"
},
  "geometry": {"coordinates":[70.46738000000001,28.71983],"type":"Point"}
}