{
  "type": "Feature",
  "properties": {
    "gn:admin1_code":"4",
    "gn:asciiname":"Jagga Muhammad Yar",
    "gn:country_code":"PK",
    "gn:dem":175,
    "gn:feature_class":"P",
    "gn:feature_code":"PPL",
    "gn:name":"Jagga Muhammad Y\u0101r",
    "gn:population":0,
    "gn:timezone":"Asia/Karachi",
    "iso:country":"PK",
    "wof:name":"Jagga Muhammad Yar",
    "wof:placetype":"locality"
},
  "geometry": {"coordinates":[73.90555999999999,30.34583],"type":"Point"}
}