{
  "type": "Feature",
  "properties": {
    "gn:admin1_code":"03",
    "gn:asciiname":"Banda Kalle",
    "gn:country_code":"PK",
    "gn:dem":1329,
    "gn:feature_class":"P",
    "gn:feature_code":"PPL",
    "gn:name":"Banda Kalle",
    "gn:population":0,
    "gn:timezone":"Asia/Karachi",
    "iso:country":"PK",
    "name:eng_x_preferred":[
        "B\u0101nda Kili"
    ],
    "wof:name":"Banda Kalle",
    "wof:placetype":"locality"
},
  "geometry": {"coordinates":[71.95062,34.77227],"type":"Point"}
}