{
  "type": "Feature",
  "properties": {
    "gn:admin1_code":"2",
    "gn:asciiname":"Goth Mughe",
    "gn:country_code":"PK",
    "gn:dem":52,
    "gn:feature_class":"P",
    "gn:feature_code":"PPL",
    "gn:name":"Goth Mughe",
    "gn:population":0,
    "gn:timezone":"Asia/Karachi",
    "iso:country":"PK",
    "name:und_x_variant":[
        "Goth M\u016bghal"
    ],
    "wof:name":"Goth Mughe",
    "wof:placetype":"locality"
},
  "geometry": {"coordinates":[67.84995000000001,28.17872],"type":"Point"}
}