{
  "type": "Feature",
  "properties": {
    "gn:admin1_code":"1.0",
    "gn:asciiname":"Mian Khelo Mela",
    "gn:country_code":"PK",
    "gn:dem":1468,
    "gn:feature_class":"P",
    "gn:feature_code":"PPL",
    "gn:name":"Mian Khelo Mela",
    "gn:population":0,
    "gn:timezone":"Asia/Karachi",
    "iso:country":"PK",
    "wof:name":"Mian Khelo Mela",
    "wof:placetype":"locality"
},
  "geometry": {"coordinates":[71.00666,33.68226],"type":"Point"}
}