{
  "type": "Feature",
  "properties": {
    "gn:admin1_code":"1.0",
    "gn:asciiname":"Gulo China",
    "gn:country_code":"PK",
    "gn:dem":1548,
    "gn:feature_class":"P",
    "gn:feature_code":"PPL",
    "gn:name":"Gulo China",
    "gn:population":0,
    "gn:timezone":"Asia/Karachi",
    "iso:country":"PK",
    "wof:name":"Gulo China",
    "wof:placetype":"locality"
},
  "geometry": {"coordinates":[70.77996999999998,33.87434],"type":"Point"}
}