{
  "type": "Feature",
  "properties": {
    "gn:admin1_code":"05",
    "gn:asciiname":"Mian Shoran",
    "gn:country_code":"PK",
    "gn:dem":32,
    "gn:feature_class":"P",
    "gn:feature_code":"PPL",
    "gn:name":"Mian Shoran",
    "gn:population":0,
    "gn:timezone":"Asia/Karachi",
    "iso:country":"PK",
    "name:und_x_variant":[
        "Shoran",
        "Mi\u0101n Chhohra",
        "Mian Shora",
        "M\u012b\u0101n Shoran",
        "Mian Shoran"
    ],
    "wof:name":"Mian Shoran",
    "wof:placetype":"locality"
},
  "geometry": {"coordinates":[68.35614,26.18528],"type":"Point"}
}