{
  "type": "Feature",
  "properties": {
    "gn:admin1_code":"2",
    "gn:asciiname":"Mahi Bohar",
    "gn:country_code":"PK",
    "gn:dem":48,
    "gn:feature_class":"P",
    "gn:feature_code":"PPL",
    "gn:name":"Mahi Bohar",
    "gn:population":0,
    "gn:timezone":"Asia/Karachi",
    "iso:country":"PK",
    "name:und_x_variant":[
        "M\u0101hi Bahar",
        "Mahi Bohar"
    ],
    "wof:name":"Mahi Bohar",
    "wof:placetype":"locality"
},
  "geometry": {"coordinates":[67.98096,28.04986],"type":"Point"}
}