{
  "type": "Feature",
  "properties": {
    "gn:admin1_code":"5.0",
    "gn:asciiname":"Goth Dil Murad Chachar",
    "gn:country_code":"PK",
    "gn:dem":69,
    "gn:feature_class":"P",
    "gn:feature_code":"PPL",
    "gn:name":"Goth Dil Murad Chachar",
    "gn:population":0,
    "gn:timezone":"Asia/Karachi",
    "iso:country":"PK",
    "wof:name":"Goth Dil Murad Chachar",
    "wof:placetype":"locality"
},
  "geometry": {"coordinates":[69.07573000000001,27.96126],"type":"Point"}
}