{
  "type": "Feature",
  "properties": {
    "gn:admin1_code":"4.0",
    "gn:asciiname":"Dera Arabi",
    "gn:country_code":"PK",
    "gn:dem":113,
    "gn:feature_class":"P",
    "gn:feature_code":"PPL",
    "gn:name":"Dera Arabi",
    "gn:population":0,
    "gn:timezone":"Asia/Karachi",
    "iso:country":"PK",
    "name:und_x_variant":[
        "Dera Arbi"
    ],
    "wof:name":"Dera Arabi",
    "wof:placetype":"locality"
},
  "geometry": {"coordinates":[71.37438,29.68781],"type":"Point"}
}