{
  "type": "Feature",
  "properties": {
    "gn:admin1_code":"5.0",
    "gn:asciiname":"Ismail Goth",
    "gn:country_code":"PK",
    "gn:dem":402,
    "gn:feature_class":"P",
    "gn:feature_code":"PPL",
    "gn:name":"Ismail Goth",
    "gn:population":0,
    "gn:timezone":"Asia/Karachi",
    "iso:country":"PK",
    "name:und_x_variant":[
        "Goth Ism\u0101il"
    ],
    "wof:name":"Ismail Goth",
    "wof:placetype":"locality"
},
  "geometry": {"coordinates":[67.51039,25.44717],"type":"Point"}
}