{
  "type": "Feature",
  "properties": {
    "gn:admin1_code":"3.0",
    "gn:asciiname":"Bal Mar",
    "gn:country_code":"PK",
    "gn:dem":1252,
    "gn:feature_class":"P",
    "gn:feature_code":"PPL",
    "gn:name":"Bal Mar",
    "gn:population":0,
    "gn:timezone":"Asia/Karachi",
    "iso:country":"PK",
    "wof:name":"Bal Mar",
    "wof:placetype":"locality"
},
  "geometry": {"coordinates":[73.05840999999999,34.39514],"type":"Point"}
}