{
  "type": "Feature",
  "properties": {
    "gn:admin1_code":"5",
    "gn:asciiname":"Goth Mir Allan Khan",
    "gn:country_code":"PK",
    "gn:dem":14,
    "gn:feature_class":"P",
    "gn:feature_code":"PPL",
    "gn:name":"Goth Mir Allan Khan",
    "gn:population":0,
    "gn:timezone":"Asia/Karachi",
    "iso:country":"PK",
    "name:und_x_variant":[
        "Goth M\u012br Abdull\u0101h Kh\u0101n"
    ],
    "wof:name":"Goth Mir Allan Khan",
    "wof:placetype":"locality"
},
  "geometry": {"coordinates":[69.22678000000001,25.70705],"type":"Point"}
}