{
  "type": "Feature",
  "properties": {
    "gn:admin1_code":"4",
    "gn:asciiname":"Dandka",
    "gn:country_code":"PK",
    "gn:dem":211,
    "gn:feature_class":"P",
    "gn:feature_code":"PPL",
    "gn:name":"Dandka",
    "gn:population":0,
    "gn:timezone":"Asia/Karachi",
    "iso:country":"PK",
    "name:und_x_variant":[
        "Dhundka",
        "Dandl"
    ],
    "wof:name":"Dandka",
    "wof:placetype":"locality"
},
  "geometry": {"coordinates":[73.51119,32.34815],"type":"Point"}
}