{
  "type": "Feature",
  "properties": {
    "gn:admin1_code":"3",
    "gn:asciiname":"Gopalam Baba Ziarat",
    "gn:country_code":"PK",
    "gn:dem":958,
    "gn:feature_class":"P",
    "gn:feature_code":"PPL",
    "gn:name":"Gopalam Baba Ziarat",
    "gn:population":0,
    "gn:timezone":"Asia/Karachi",
    "iso:country":"PK",
    "wof:name":"Gopalam Baba Ziarat",
    "wof:placetype":"locality"
},
  "geometry": {"coordinates":[72.00147,34.90338],"type":"Point"}
}