{
  "type": "Feature",
  "properties": {
    "gn:admin1_code":"03",
    "gn:asciiname":"Churi Khel",
    "gn:country_code":"PK",
    "gn:dem":343,
    "gn:feature_class":"P",
    "gn:feature_code":"PPL",
    "gn:name":"Churi Khel",
    "gn:population":0,
    "gn:timezone":"Asia/Karachi",
    "iso:country":"PK",
    "wof:name":"Churi Khel",
    "wof:placetype":"locality"
},
  "geometry": {"coordinates":[70.50004,32.7206],"type":"Point"}
}