{
  "type": "Feature",
  "properties": {
    "gn:admin1_code":"4.0",
    "gn:asciiname":"Dhok Ghulam Ali",
    "gn:country_code":"PK",
    "gn:dem":486,
    "gn:feature_class":"P",
    "gn:feature_code":"PPL",
    "gn:name":"Dhok Ghulam Ali",
    "gn:population":0,
    "gn:timezone":"Asia/Karachi",
    "iso:country":"PK",
    "wof:name":"Dhok Ghulam Ali",
    "wof:placetype":"locality"
},
  "geometry": {"coordinates":[72.84414,33.46411],"type":"Point"}
}