{
  "type": "Feature",
  "properties": {
    "gn:admin1_code":"5.0",
    "gn:asciiname":"Talibwaro Tar",
    "gn:country_code":"PK",
    "gn:dem":45,
    "gn:feature_class":"P",
    "gn:feature_code":"PPL",
    "gn:name":"Talibwaro Tar",
    "gn:population":0,
    "gn:timezone":"Asia/Karachi",
    "iso:country":"PK",
    "wof:name":"Talibwaro Tar",
    "wof:placetype":"locality"
},
  "geometry": {"coordinates":[69.67293000000001,26.19559],"type":"Point"}
}