{
  "type": "Feature",
  "properties": {
    "gn:admin1_code":"4.0",
    "gn:asciiname":"Bahudipur Quraishian",
    "gn:country_code":"PK",
    "gn:dem":85,
    "gn:feature_class":"P",
    "gn:feature_code":"PPL",
    "gn:name":"Bahudipur Quraishian",
    "gn:population":0,
    "gn:timezone":"Asia/Karachi",
    "iso:country":"PK",
    "name:und_x_variant":[
        "Bahud\u012bpur"
    ],
    "wof:name":"Bahudipur Quraishian",
    "wof:placetype":"locality"
},
  "geometry": {"coordinates":[70.29244,28.61456],"type":"Point"}
}