{
  "type": "Feature",
  "properties": {
    "gn:admin1_code":"4",
    "gn:asciiname":"Haji Ahmad Din",
    "gn:country_code":"PK",
    "gn:dem":94,
    "gn:feature_class":"P",
    "gn:feature_code":"PPL",
    "gn:name":"H\u0101ji Ahmad D\u012bn",
    "gn:population":0,
    "gn:timezone":"Asia/Karachi",
    "iso:country":"PK",
    "wof:name":"Haji Ahmad Din",
    "wof:placetype":"locality"
},
  "geometry": {"coordinates":[70.87639,28.94306],"type":"Point"}
}