{
  "type": "Feature",
  "properties": {
    "gn:admin1_code":"4.0",
    "gn:asciiname":"Dera Shamas",
    "gn:country_code":"PK",
    "gn:dem":87,
    "gn:feature_class":"P",
    "gn:feature_code":"PPL",
    "gn:name":"Dera Shamas",
    "gn:population":0,
    "gn:timezone":"Asia/Karachi",
    "iso:country":"PK",
    "name:und_x_variant":[
        "Dera Shams"
    ],
    "wof:name":"Dera Shamas",
    "wof:placetype":"locality"
},
  "geometry": {"coordinates":[70.28239000000001,28.55797],"type":"Point"}
}