{
  "type": "Feature",
  "properties": {
    "gn:admin1_code":"2.0",
    "gn:asciiname":"Kili Afzal Khan",
    "gn:country_code":"PK",
    "gn:dem":1616,
    "gn:feature_class":"P",
    "gn:feature_code":"PPL",
    "gn:name":"Kili Afzal Khan",
    "gn:population":0,
    "gn:timezone":"Asia/Karachi",
    "iso:country":"PK",
    "wof:name":"Kili Afzal Khan",
    "wof:placetype":"locality"
},
  "geometry": {"coordinates":[66.67891999999999,29.82094],"type":"Point"}
}