{
  "type": "Feature",
  "properties": {
    "gn:admin1_code":"4.0",
    "gn:asciiname":"Jhok Yaranwala",
    "gn:country_code":"PK",
    "gn:dem":164,
    "gn:feature_class":"P",
    "gn:feature_code":"PPL",
    "gn:name":"Jhok Yaranwala",
    "gn:population":0,
    "gn:timezone":"Asia/Karachi",
    "iso:country":"PK",
    "name:und_x_variant":[
        "Jhok Yaran",
        "Jhok Yaranwala",
        "Jhok Y\u0101ranw\u0101li"
    ],
    "wof:name":"Jhok Yaranwala",
    "wof:placetype":"locality"
},
  "geometry": {"coordinates":[70.64671,30.53243],"type":"Point"}
}