{
  "type": "Feature",
  "properties": {
    "gn:admin1_code":"6",
    "gn:asciiname":"Bhabara",
    "gn:country_code":"PK",
    "gn:dem":929,
    "gn:feature_class":"P",
    "gn:feature_code":"PPL",
    "gn:name":"Bhabara",
    "gn:population":0,
    "gn:timezone":"Asia/Karachi",
    "iso:country":"PK",
    "name:und_x_variant":[
        "Bh\u0101bra"
    ],
    "wof:name":"Bhabara",
    "wof:placetype":"locality"
},
  "geometry": {"coordinates":[73.97229,33.60213],"type":"Point"}
}