{
  "type": "Feature",
  "properties": {
    "gn:admin1_code":"3",
    "gn:asciiname":"Kuz Duba",
    "gn:country_code":"PK",
    "gn:dem":1203,
    "gn:feature_class":"P",
    "gn:feature_code":"PPL",
    "gn:name":"Kuz Duba",
    "gn:population":0,
    "gn:timezone":"Asia/Karachi",
    "iso:country":"PK",
    "name:und_x_variant":[
        "Kuz Doba"
    ],
    "wof:name":"Kuz Duba",
    "wof:placetype":"locality"
},
  "geometry": {"coordinates":[72.77126,34.46364000000001],"type":"Point"}
}