{
  "type": "Feature",
  "properties": {
    "gn:admin1_code":"4",
    "gn:asciiname":"Chak One Hundred Twenty-six-Two Fifteen L",
    "gn:country_code":"PK",
    "gn:dem":150,
    "gn:feature_class":"P",
    "gn:feature_code":"PPL",
    "gn:name":"Chak One Hundred Twenty-six-Two Fifteen L",
    "gn:population":0,
    "gn:timezone":"Asia/Karachi",
    "iso:country":"PK",
    "wof:name":"Chak One Hundred Twenty-six-Two Fifteen L",
    "wof:placetype":"locality"
},
  "geometry": {"coordinates":[72.36944,30.425],"type":"Point"}
}