{
  "type": "Feature",
  "properties": {
    "gn:admin1_code":"3.0",
    "gn:asciiname":"Ragha Shah",
    "gn:country_code":"PK",
    "gn:dem":438,
    "gn:feature_class":"P",
    "gn:feature_code":"PPL",
    "gn:name":"Ragha Shah",
    "gn:population":0,
    "gn:timezone":"Asia/Karachi",
    "iso:country":"PK",
    "wof:name":"Ragha Shah",
    "wof:placetype":"locality"
},
  "geometry": {"coordinates":[70.48338000000003,32.95482],"type":"Point"}
}