{
  "type": "Feature",
  "properties": {
    "gn:admin1_code":"04",
    "gn:asciiname":"Sanda Kalan",
    "gn:country_code":"PK",
    "gn:dem":198,
    "gn:feature_class":"P",
    "gn:feature_code":"PPL",
    "gn:name":"Sanda Kalan",
    "gn:population":0,
    "gn:timezone":"Asia/Karachi",
    "iso:country":"PK",
    "name:und_x_variant":[
        "S\u0101nda"
    ],
    "wof:name":"Sanda Kalan",
    "wof:placetype":"locality"
},
  "geometry": {"coordinates":[74.49848,31.04782],"type":"Point"}
}