{
  "type": "Feature",
  "properties": {
    "gn:admin1_code":"1.0",
    "gn:asciiname":"Toi Mela",
    "gn:country_code":"PK",
    "gn:dem":982,
    "gn:feature_class":"P",
    "gn:feature_code":"PPL",
    "gn:name":"Toi Mela",
    "gn:population":0,
    "gn:timezone":"Asia/Karachi",
    "iso:country":"PK",
    "wof:name":"Toi Mela",
    "wof:placetype":"locality"
},
  "geometry": {"coordinates":[71.27813,33.68309],"type":"Point"}
}