{
  "type": "Feature",
  "properties": {
    "gn:admin1_code":"3.0",
    "gn:asciiname":"Gharibabad",
    "gn:country_code":"PK",
    "gn:dem":341,
    "gn:feature_class":"P",
    "gn:feature_code":"PPL",
    "gn:name":"Gharibabad",
    "gn:population":0,
    "gn:timezone":"Asia/Karachi",
    "iso:country":"PK",
    "name:diq_x_preferred":[
        "\u011eeribabad"
    ],
    "wof:name":"Gharibabad",
    "wof:placetype":"locality"
},
  "geometry": {"coordinates":[71.58440999999998,33.98138],"type":"Point"}
}