{
  "type": "Feature",
  "properties": {
    "gn:admin1_code":"6",
    "gn:asciiname":"Ghorenali",
    "gn:country_code":"PK",
    "gn:dem":2791,
    "gn:feature_class":"P",
    "gn:feature_code":"PPL",
    "gn:name":"Ghorenali",
    "gn:population":0,
    "gn:timezone":"Asia/Karachi",
    "iso:country":"PK",
    "name:und_x_variant":[
        "Hor B\u0101ri"
    ],
    "wof:name":"Ghorenali",
    "wof:placetype":"locality"
},
  "geometry": {"coordinates":[73.77163,34.0806],"type":"Point"}
}