{
  "type": "Feature",
  "properties": {
    "gn:admin1_code":"5.0",
    "gn:asciiname":"Goth Ismail",
    "gn:country_code":"PK",
    "gn:dem":7,
    "gn:feature_class":"P",
    "gn:feature_code":"PPL",
    "gn:name":"Goth Ismail",
    "gn:population":0,
    "gn:timezone":"Asia/Karachi",
    "iso:country":"PK",
    "name:eng_x_preferred":[
        "Goth Ism\u0101li"
    ],
    "wof:name":"Goth Ismail",
    "wof:placetype":"locality"
},
  "geometry": {"coordinates":[68.13706999999999,24.56223],"type":"Point"}
}