{
  "type": "Feature",
  "properties": {
    "gn:admin1_code":"4.0",
    "gn:asciiname":"Yari Khel",
    "gn:country_code":"PK",
    "gn:dem":364,
    "gn:feature_class":"P",
    "gn:feature_code":"PPL",
    "gn:name":"Yari Khel",
    "gn:population":0,
    "gn:timezone":"Asia/Karachi",
    "iso:country":"PK",
    "wof:name":"Yari Khel",
    "wof:placetype":"locality"
},
  "geometry": {"coordinates":[71.932,32.82482],"type":"Point"}
}