{
  "type": "Feature",
  "properties": {
    "gn:admin1_code":"6",
    "gn:asciiname":"Kingu",
    "gn:country_code":"PK",
    "gn:dem":1694,
    "gn:feature_class":"P",
    "gn:feature_code":"PPL",
    "gn:name":"Kingu",
    "gn:population":0,
    "gn:timezone":"Asia/Karachi",
    "iso:country":"PK",
    "name:aze_x_preferred":[
        "Kinqu"
    ],
    "name:bel_x_preferred":[
        "\u041a\u0456\u043d\u0433\u0443"
    ],
    "name:deu_x_preferred":[
        "Kingu"
    ],
    "name:eus_x_preferred":[
        "Kingu"
    ],
    "name:fin_x_preferred":[
        "Kingu"
    ],
    "name:fra_x_preferred":[
        "Kingu"
    ],
    "name:hrv_x_preferred":[
        "Kingu"
    ],
    "name:ita_x_preferred":[
        "Kingu"
    ],
    "name:jpn_x_preferred":[
        "\u30ad\u30f3\u30b0\u30fc"
    ],
    "name:lit_x_preferred":[
        "Kingu"
    ],
    "name:nld_x_preferred":[
        "Kingu"
    ],
    "name:por_x_preferred":[
        "Kingu"
    ],
    "name:rus_x_preferred":[
        "\u041a\u0438\u043d\u0433\u0443"
    ],
    "name:slv_x_preferred":[
        "Kingu"
    ],
    "name:spa_x_preferred":[
        "Kingu"
    ],
    "name:tur_x_preferred":[
        "Kingu"
    ],
    "name:ukr_x_preferred":[
        "\u041a\u0456\u043d\u0433\u0443"
    ],
    "wof:name":"Kingu",
    "wof:placetype":"locality"
},
  "geometry": {"coordinates":[74.04949000000001,34.72133],"type":"Point"}
}