{
  "type": "Feature",
  "properties": {
    "gn:admin1_code":"6",
    "gn:asciiname":"Kingu",
    "gn:country_code":"PK",
    "gn:dem":1694,
    "gn:feature_class":"P",
    "gn:feature_code":"PPL",
    "gn:name":"Kingu",
    "gn:population":0,
    "gn:timezone":"Asia/Karachi",
    "iso:country":"PK",
    "wof:name":"Kingu",
    "wof:placetype":"locality"
},
  "geometry": {"coordinates":[74.04949000000001,34.72133],"type":"Point"}
}