{
  "type": "Feature",
  "properties": {
    "gn:admin1_code":"4",
    "gn:asciiname":"Laloki",
    "gn:country_code":"PK",
    "gn:dem":233,
    "gn:feature_class":"P",
    "gn:feature_code":"PPL",
    "gn:name":"Laloki",
    "gn:population":0,
    "gn:timezone":"Asia/Karachi",
    "iso:country":"PK",
    "wof:name":"Laloki",
    "wof:placetype":"locality"
},
  "geometry": {"coordinates":[74.26878000000001,32.60824],"type":"Point"}
}