{
  "type": "Feature",
  "properties": {
    "gn:admin1_code":"6",
    "gn:asciiname":"Saran",
    "gn:country_code":"PK",
    "gn:dem":2362,
    "gn:feature_class":"P",
    "gn:feature_code":"PPL",
    "gn:name":"Saran",
    "gn:population":0,
    "gn:timezone":"Asia/Karachi",
    "iso:country":"PK",
    "name:ara_x_preferred":[
        "\u0633\u0627\u0631\u0627\u0646"
    ],
    "name:cat_x_preferred":[
        "Saran"
    ],
    "name:ceb_x_preferred":[
        "Saran"
    ],
    "name:deu_x_preferred":[
        "Saran"
    ],
    "name:fra_x_preferred":[
        "Saran"
    ],
    "name:ita_x_preferred":[
        "Saran"
    ],
    "name:jpn_x_preferred":[
        "\u30b5\u30e9\u30f3"
    ],
    "name:nld_x_preferred":[
        "Saran"
    ],
    "name:pol_x_preferred":[
        "Saran"
    ],
    "name:por_x_preferred":[
        "Saran"
    ],
    "name:spa_x_preferred":[
        "Saran"
    ],
    "name:swe_x_preferred":[
        "Saran"
    ],
    "wof:name":"Saran",
    "wof:placetype":"locality"
},
  "geometry": {"coordinates":[73.52717,34.38174],"type":"Point"}
}