{
  "type": "Feature",
  "properties": {
    "gn:admin1_code":"5.0",
    "gn:asciiname":"Ahsanabad",
    "gn:country_code":"PK",
    "gn:dem":57,
    "gn:feature_class":"P",
    "gn:feature_code":"PPL",
    "gn:name":"Ahsanabad",
    "gn:population":0,
    "gn:timezone":"Asia/Karachi",
    "iso:country":"PK",
    "name:eng_x_preferred":[
        "Ahsanabad"
    ],
    "wof:name":"Ahsanabad",
    "wof:placetype":"locality"
},
  "geometry": {"coordinates":[67.11374000000001,25.00427],"type":"Point"}
}