{
  "type": "Feature",
  "properties": {
    "gn:admin1_code":"3",
    "gn:asciiname":"Manki",
    "gn:country_code":"PK",
    "gn:dem":2577,
    "gn:feature_class":"P",
    "gn:feature_code":"PPL",
    "gn:name":"Manki",
    "gn:population":0,
    "gn:timezone":"Asia/Karachi",
    "iso:country":"PK",
    "name:und_x_variant":[
        "M\u0101nk\u012b"
    ],
    "wof:name":"Manki",
    "wof:placetype":"locality"
},
  "geometry": {"coordinates":[72.53558000000002,34.72952],"type":"Point"}
}