{
  "type": "Feature",
  "properties": {
    "gn:admin1_code":"7.0",
    "gn:asciiname":"Askole",
    "gn:country_code":"PK",
    "gn:dem":4288,
    "gn:feature_class":"P",
    "gn:feature_code":"PPL",
    "gn:name":"Askole",
    "gn:population":0,
    "gn:timezone":"Asia/Karachi",
    "iso:country":"PK",
    "name:deu_x_preferred":[
        "Askole"
    ],
    "name:ita_x_preferred":[
        "Askole"
    ],
    "wof:name":"Askole",
    "wof:placetype":"locality"
},
  "geometry": {"coordinates":[75.85458,35.69224000000001],"type":"Point"}
}