{
  "type": "Feature",
  "properties": {
    "gn:admin1_code":"2.0",
    "gn:asciiname":"Kamalabad",
    "gn:country_code":"PK",
    "gn:dem":1476,
    "gn:feature_class":"P",
    "gn:feature_code":"PPL",
    "gn:name":"Kamalabad",
    "gn:population":0,
    "gn:timezone":"Asia/Karachi",
    "iso:country":"PK",
    "name:ceb_x_preferred":[
        "Kamalabad"
    ],
    "name:fas_x_preferred":[
        "\u06a9\u0645\u0627\u0644\u200c\u0622\u0628\u0627\u062f"
    ],
    "name:swe_x_preferred":[
        "Kamalabad"
    ],
    "wof:name":"Kamalabad",
    "wof:placetype":"locality"
},
  "geometry": {"coordinates":[66.49024,29.97295],"type":"Point"}
}