{
  "type": "Feature",
  "properties": {
    "gn:admin1_code":"3.0",
    "gn:asciiname":"Sangini Shakkar Khel",
    "gn:country_code":"PK",
    "gn:dem":701,
    "gn:feature_class":"P",
    "gn:feature_code":"PPL",
    "gn:name":"Sangini Shakkar Khel",
    "gn:population":0,
    "gn:timezone":"Asia/Karachi",
    "iso:country":"PK",
    "name:und_x_variant":[
        "Sangini"
    ],
    "wof:name":"Sangini Shakkar Khel",
    "wof:placetype":"locality"
},
  "geometry": {"coordinates":[71.11868,33.35337],"type":"Point"}
}