{
  "type": "Feature",
  "properties": {
    "gn:admin1_code":"5",
    "gn:asciiname":"Shahbaz Khan",
    "gn:country_code":"PK",
    "gn:dem":64,
    "gn:feature_class":"P",
    "gn:feature_code":"PPL",
    "gn:name":"Shahbaz Khan",
    "gn:population":0,
    "gn:timezone":"Asia/Karachi",
    "iso:country":"PK",
    "name:ukr_x_preferred":[
        "\u0425\u0430\u0445\u0431\u0430\u0437 \u0425\u0430\u043d"
    ],
    "wof:name":"Shahbaz Khan",
    "wof:placetype":"locality"
},
  "geometry": {"coordinates":[68.92392,28.27984],"type":"Point"}
}