{
  "type": "Feature",
  "properties": {
    "gn:admin1_code":"4",
    "gn:asciiname":"Chak Twenty-six -Two Right",
    "gn:country_code":"PK",
    "gn:dem":183,
    "gn:feature_class":"P",
    "gn:feature_code":"PPL",
    "gn:name":"Chak Twenty-six -Two Right",
    "gn:population":0,
    "gn:timezone":"Asia/Karachi",
    "iso:country":"PK",
    "name:und_x_variant":[
        "Chak Twenty-six-Two R"
    ],
    "wof:name":"Chak Twenty-six -Two Right",
    "wof:placetype":"locality"
},
  "geometry": {"coordinates":[73.50953,30.85442],"type":"Point"}
}