{
  "type": "Feature",
  "properties": {
    "gn:admin1_code":"2.0",
    "gn:asciiname":"Les",
    "gn:country_code":"PK",
    "gn:dem":1828,
    "gn:feature_class":"P",
    "gn:feature_code":"PPL",
    "gn:name":"Les",
    "gn:population":0,
    "gn:timezone":"Asia/Karachi",
    "iso:country":"PK",
    "name:eng_x_preferred":[
        "Les"
    ],
    "wof:name":"Les",
    "wof:placetype":"locality"
},
  "geometry": {"coordinates":[67.26613,30.06637000000001],"type":"Point"}
}