{
  "type": "Feature",
  "properties": {
    "gn:admin1_code":"5",
    "gn:asciiname":"Gheema Farm",
    "gn:country_code":"PK",
    "gn:dem":15,
    "gn:feature_class":"P",
    "gn:feature_code":"PPL",
    "gn:name":"Gheema Farm",
    "gn:population":0,
    "gn:timezone":"Asia/Karachi",
    "iso:country":"PK",
    "name:und_x_variant":[
        "Goth Muhammad Y\u0101q\u016bb Marri"
    ],
    "wof:name":"Gheema Farm",
    "wof:placetype":"locality"
},
  "geometry": {"coordinates":[69.23705,25.49433],"type":"Point"}
}