{
  "type": "Feature",
  "properties": {
    "gn:admin1_code":"4.0",
    "gn:asciiname":"Basti Sharifabad",
    "gn:country_code":"PK",
    "gn:dem":142,
    "gn:feature_class":"P",
    "gn:feature_code":"PPL",
    "gn:name":"Basti Sharifabad",
    "gn:population":0,
    "gn:timezone":"Asia/Karachi",
    "iso:country":"PK",
    "name:und_x_variant":[
        "Basti Shafiq\u0101b\u0101d"
    ],
    "wof:name":"Basti Sharifabad",
    "wof:placetype":"locality"
},
  "geometry": {"coordinates":[72.01134999999999,30.96253],"type":"Point"}
}