{
  "type": "Feature",
  "properties": {
    "gn:admin1_code":"4.0",
    "gn:asciiname":"Dhok Soni",
    "gn:country_code":"PK",
    "gn:dem":447,
    "gn:feature_class":"P",
    "gn:feature_code":"PPL",
    "gn:name":"Dhok Soni",
    "gn:population":0,
    "gn:timezone":"Asia/Karachi",
    "iso:country":"PK",
    "wof:name":"Dhok Soni",
    "wof:placetype":"locality"
},
  "geometry": {"coordinates":[72.29779000000001,33.36483],"type":"Point"}
}