{
  "type": "Feature",
  "properties": {
    "gn:admin1_code":"4",
    "gn:asciiname":"Mochiwala",
    "gn:country_code":"PK",
    "gn:dem":130,
    "gn:feature_class":"P",
    "gn:feature_code":"PPL",
    "gn:name":"Mochiwala",
    "gn:population":0,
    "gn:timezone":"Asia/Karachi",
    "iso:country":"PK",
    "name:eng_x_preferred":[
        "Mooh\u012bw\u0101la"
    ],
    "name:fas_x_preferred":[
        "\u0645\u0648\u0686\u06cc\u200c\u0648\u0627\u0644\u0627"
    ],
    "name:urd_x_preferred":[
        "\u0645\u0648\u0686\u06cc \u0648\u0627\u0644\u0627"
    ],
    "wof:name":"Mochiwala",
    "wof:placetype":"locality"
},
  "geometry": {"coordinates":[70.65456,30.29606],"type":"Point"}
}