{
  "type": "Feature",
  "properties": {
    "gn:admin1_code":"5.0",
    "gn:asciiname":"Goth Harun Channo",
    "gn:country_code":"PK",
    "gn:dem":17,
    "gn:feature_class":"P",
    "gn:feature_code":"PPL",
    "gn:name":"Goth Harun Channo",
    "gn:population":0,
    "gn:timezone":"Asia/Karachi",
    "iso:country":"PK",
    "name:und_x_variant":[
        "Har\u016bn Chapn\u016b"
    ],
    "wof:name":"Goth Harun Channo",
    "wof:placetype":"locality"
},
  "geometry": {"coordinates":[68.5197,25.1177],"type":"Point"}
}