{
  "type": "Feature",
  "properties": {
    "gn:admin1_code":"02",
    "gn:asciiname":"Makola",
    "gn:country_code":"PK",
    "gn:dem":14,
    "gn:feature_class":"P",
    "gn:feature_code":"PPL",
    "gn:name":"Makola",
    "gn:population":0,
    "gn:timezone":"Asia/Karachi",
    "iso:country":"PK",
    "name:ceb_x_preferred":[
        "Makola"
    ],
    "name:swe_x_preferred":[
        "Makola"
    ],
    "wof:name":"Makola",
    "wof:placetype":"locality"
},
  "geometry": {"coordinates":[64.05723,25.50515],"type":"Point"}
}