{
  "type": "Feature",
  "properties": {
    "gn:admin1_code":"3",
    "gn:asciiname":"Nar Gali",
    "gn:country_code":"PK",
    "gn:dem":2624,
    "gn:feature_class":"P",
    "gn:feature_code":"PPL",
    "gn:name":"Nar Gali",
    "gn:population":0,
    "gn:timezone":"Asia/Karachi",
    "iso:country":"PK",
    "wof:name":"Nar Gali",
    "wof:placetype":"locality"
},
  "geometry": {"coordinates":[73.55849000000001,34.63061],"type":"Point"}
}