{
  "type": "Feature",
  "properties": {
    "gn:admin1_code":"7.0",
    "gn:asciiname":"Sorain",
    "gn:country_code":"PK",
    "gn:dem":2619,
    "gn:feature_class":"P",
    "gn:feature_code":"PPL",
    "gn:name":"Sorain",
    "gn:population":0,
    "gn:timezone":"Asia/Karachi",
    "iso:country":"PK",
    "wof:name":"Sorain",
    "wof:placetype":"locality"
},
  "geometry": {"coordinates":[73.76703000000001,35.30772],"type":"Point"}
}