{
  "type": "Feature",
  "properties": {
    "gn:admin1_code":"5.0",
    "gn:asciiname":"Chakar Khan Shahani",
    "gn:country_code":"PK",
    "gn:dem":31,
    "gn:feature_class":"P",
    "gn:feature_code":"PPL",
    "gn:name":"Chakar Khan Shahani",
    "gn:population":0,
    "gn:timezone":"Asia/Karachi",
    "iso:country":"PK",
    "wof:name":"Chakar Khan Shahani",
    "wof:placetype":"locality"
},
  "geometry": {"coordinates":[68.38544,26.33429000000001],"type":"Point"}
}