{
  "type": "Feature",
  "properties": {
    "gn:admin1_code":"6",
    "gn:asciiname":"Ulari",
    "gn:country_code":"PK",
    "gn:dem":2512,
    "gn:feature_class":"P",
    "gn:feature_code":"PPL",
    "gn:name":"Ulari",
    "gn:population":0,
    "gn:timezone":"Asia/Karachi",
    "iso:country":"PK",
    "wof:name":"Ulari",
    "wof:placetype":"locality"
},
  "geometry": {"coordinates":[73.92553000000002,34.73589],"type":"Point"}
}