{
  "type": "Feature",
  "properties": {
    "gn:admin1_code":"3",
    "gn:asciiname":"Nikka Pani",
    "gn:country_code":"PK",
    "gn:dem":702,
    "gn:feature_class":"P",
    "gn:feature_code":"PPL",
    "gn:name":"Nikka Pani",
    "gn:population":0,
    "gn:timezone":"Asia/Karachi",
    "iso:country":"PK",
    "name:und_x_variant":[
        "Nakka"
    ],
    "wof:name":"Nikka Pani",
    "wof:placetype":"locality"
},
  "geometry": {"coordinates":[72.89261999999999,34.42432],"type":"Point"}
}