{
  "type": "Feature",
  "properties": {
    "gn:admin1_code":"3.0",
    "gn:asciiname":"Pai China",
    "gn:country_code":"PK",
    "gn:dem":728,
    "gn:feature_class":"P",
    "gn:feature_code":"PPL",
    "gn:name":"Pai China",
    "gn:population":0,
    "gn:timezone":"Asia/Karachi",
    "iso:country":"PK",
    "wof:name":"Pai China",
    "wof:placetype":"locality"
},
  "geometry": {"coordinates":[72.39279999999999,34.50673],"type":"Point"}
}