{
  "type": "Feature",
  "properties": {
    "gn:admin1_code":"4.0",
    "gn:asciiname":"Sohniwala",
    "gn:country_code":"PK",
    "gn:dem":85,
    "gn:feature_class":"P",
    "gn:feature_code":"PPL",
    "gn:name":"Sohniwala",
    "gn:population":0,
    "gn:timezone":"Asia/Karachi",
    "iso:country":"PK",
    "name:und_x_variant":[
        "Chak Sohn\u012bw\u0101la"
    ],
    "wof:name":"Sohniwala",
    "wof:placetype":"locality"
},
  "geometry": {"coordinates":[70.29913000000001,28.50164],"type":"Point"}
}