{
  "type": "Feature",
  "properties": {
    "gn:admin1_code":"7.0",
    "gn:asciiname":"Thamrus",
    "gn:country_code":"PK",
    "gn:dem":1786,
    "gn:feature_class":"P",
    "gn:feature_code":"PPL",
    "gn:name":"Thamrus",
    "gn:population":0,
    "gn:timezone":"Asia/Karachi",
    "iso:country":"PK",
    "wof:name":"Thamrus",
    "wof:placetype":"locality"
},
  "geometry": {"coordinates":[74.3098,35.30154],"type":"Point"}
}