{
  "type": "Feature",
  "properties": {
    "gn:admin1_code":"5.0",
    "gn:asciiname":"Goth Dino Makrani",
    "gn:country_code":"PK",
    "gn:dem":26,
    "gn:feature_class":"P",
    "gn:feature_code":"PPL",
    "gn:name":"Goth Dino Makrani",
    "gn:population":0,
    "gn:timezone":"Asia/Karachi",
    "iso:country":"PK",
    "name:und_x_variant":[
        "D\u012bno Makr\u0101ni"
    ],
    "wof:name":"Goth Dino Makrani",
    "wof:placetype":"locality"
},
  "geometry": {"coordinates":[68.63179000000001,25.63719],"type":"Point"}
}