{
  "type": "Feature",
  "properties": {
    "gn:admin1_code":"4.0",
    "gn:asciiname":"Kanwanwali",
    "gn:country_code":"PK",
    "gn:dem":199,
    "gn:feature_class":"P",
    "gn:feature_code":"PPL",
    "gn:name":"Kanwanwali",
    "gn:population":0,
    "gn:timezone":"Asia/Karachi",
    "iso:country":"PK",
    "name:und_x_variant":[
        "K\u0101w\u0101nw\u0101li"
    ],
    "wof:name":"Kanwanwali",
    "wof:placetype":"locality"
},
  "geometry": {"coordinates":[73.46348,31.83624],"type":"Point"}
}