{
  "type": "Feature",
  "properties": {
    "gn:admin1_code":"3",
    "gn:asciiname":"Mir Saindah",
    "gn:country_code":"PK",
    "gn:dem":1625,
    "gn:feature_class":"P",
    "gn:feature_code":"PPL",
    "gn:name":"Mir Saindah",
    "gn:population":0,
    "gn:timezone":"Asia/Karachi",
    "iso:country":"PK",
    "name:eng_x_preferred":[
        "M\u012br\u0101si\u0101ndeh"
    ],
    "wof:name":"Mir Saindah",
    "wof:placetype":"locality"
},
  "geometry": {"coordinates":[71.79666999999998,35.75034],"type":"Point"}
}