{
  "type": "Feature",
  "properties": {
    "gn:admin1_code":"2",
    "gn:asciiname":"Lazad",
    "gn:country_code":"PK",
    "gn:dem":1563,
    "gn:feature_class":"P",
    "gn:feature_code":"PPL",
    "gn:name":"Lazad",
    "gn:population":0,
    "gn:timezone":"Asia/Karachi",
    "iso:country":"PK",
    "wof:name":"Lazad",
    "wof:placetype":"locality"
},
  "geometry": {"coordinates":[68.31193,30.70666],"type":"Point"}
}