{
  "type": "Feature",
  "properties": {
    "gn:admin1_code":"4",
    "gn:asciiname":"Bhuwa",
    "gn:country_code":"PK",
    "gn:dem":259,
    "gn:feature_class":"P",
    "gn:feature_code":"PPL",
    "gn:name":"Bhuwa",
    "gn:population":0,
    "gn:timezone":"Asia/Karachi",
    "iso:country":"PK",
    "name:und_x_variant":[
        "Bhoea"
    ],
    "wof:name":"Bhuwa",
    "wof:placetype":"locality"
},
  "geometry": {"coordinates":[74.19025000000001,32.71617],"type":"Point"}
}