{
  "type": "Feature",
  "properties": {
    "gn:admin1_code":"1.0",
    "gn:asciiname":"Torgai",
    "gn:country_code":"PK",
    "gn:dem":1779,
    "gn:feature_class":"P",
    "gn:feature_code":"PPL",
    "gn:name":"Torgai",
    "gn:population":0,
    "gn:timezone":"Asia/Karachi",
    "iso:country":"PK",
    "wof:name":"Torgai",
    "wof:placetype":"locality"
},
  "geometry": {"coordinates":[70.45648,33.57937],"type":"Point"}
}