{
  "type": "Feature",
  "properties": {
    "gn:admin1_code":"5",
    "gn:asciiname":"Goth Bela Saida Upper",
    "gn:country_code":"PK",
    "gn:dem":53,
    "gn:feature_class":"P",
    "gn:feature_code":"PPL",
    "gn:name":"Goth Bela Saida Upper",
    "gn:population":0,
    "gn:timezone":"Asia/Karachi",
    "iso:country":"PK",
    "name:und_x_variant":[
        "B\u0101la Saidi"
    ],
    "wof:name":"Goth Bela Saida Upper",
    "wof:placetype":"locality"
},
  "geometry": {"coordinates":[68.47572,27.45315],"type":"Point"}
}