{
  "type": "Feature",
  "properties": {
    "gn:admin1_code":"04",
    "gn:asciiname":"Basti Loharanwala",
    "gn:country_code":"PK",
    "gn:dem":156,
    "gn:feature_class":"P",
    "gn:feature_code":"PPL",
    "gn:name":"Basti Loharanwala",
    "gn:population":0,
    "gn:timezone":"Asia/Karachi",
    "iso:country":"PK",
    "name:und_x_variant":[
        "Loh\u0101r\u0101nw\u0101la"
    ],
    "wof:name":"Basti Loharanwala",
    "wof:placetype":"locality"
},
  "geometry": {"coordinates":[72.09575,31.24524000000001],"type":"Point"}
}