{
  "type": "Feature",
  "properties": {
    "iso:country":"PK",
    "name:deu_x_preferred":[
        "Naya"
    ],
    "name:fra_x_preferred":[
        "Naya"
    ],
    "name:ita_x_preferred":[
        "Naya"
    ],
    "name:rus_x_preferred":[
        "\u041d\u0430\u0439\u044f"
    ],
    "qs:gn_country":"PK",
    "qs:gn_fcode":"PPLX",
    "qs:gn_pop":0,
    "qs:name":"Naya",
    "qs:name_adm0":"Pakistan",
    "qs:name_adm1":"Punjab",
    "qs:photos":1,
    "qs:photos_1k":1,
    "qs:photos_9k":1,
    "qs:photos_9r":1,
    "qs:photos_all":1,
    "qs:photos_sr":1,
    "qs:placetype":"Suburb",
    "qs:pop_sr":"0",
    "qs:woe_adm0":23424922,
    "wd:wordcount":60,
    "wof:name":"Naya",
    "wof:placetype":"neighbourhood"
},
  "geometry": {"coordinates":[73.06667,33.61667],"type":"Point"}
}