{
  "type": "Feature",
  "properties": {
    "gn:admin1_code":"5",
    "gn:asciiname":"Goth Mir Gul Husan Talpur",
    "gn:country_code":"PK",
    "gn:dem":14,
    "gn:feature_class":"P",
    "gn:feature_code":"PPL",
    "gn:name":"Goth Mir Gul Husan Talpur",
    "gn:population":0,
    "gn:timezone":"Asia/Karachi",
    "iso:country":"PK",
    "name:und_x_variant":[
        "Goth M\u012br Dost Muhammad",
        "Mir Gul Hassan"
    ],
    "wof:name":"Goth Mir Gul Husan Talpur",
    "wof:placetype":"locality"
},
  "geometry": {"coordinates":[69.16481,25.32946],"type":"Point"}
}