{
  "type": "Feature",
  "properties": {
    "gn:admin1_code":"5.0",
    "gn:asciiname":"Goth Ghalam Hasani Dhudkar",
    "gn:country_code":"PK",
    "gn:dem":189,
    "gn:feature_class":"P",
    "gn:feature_code":"PPL",
    "gn:name":"Goth Ghalam Hasani Dhudkar",
    "gn:population":0,
    "gn:timezone":"Asia/Karachi",
    "iso:country":"PK",
    "wof:name":"Goth Ghalam Hasani Dhudkar",
    "wof:placetype":"locality"
},
  "geometry": {"coordinates":[67.76045999999999,25.72384],"type":"Point"}
}