{
  "type": "Feature",
  "properties": {
    "gn:admin1_code":"6.0",
    "gn:asciiname":"Bharan Gala",
    "gn:country_code":"PK",
    "gn:dem":1392,
    "gn:feature_class":"P",
    "gn:feature_code":"PPL",
    "gn:name":"Bharan Gala",
    "gn:population":0,
    "gn:timezone":"Asia/Karachi",
    "iso:country":"PK",
    "wof:name":"Bharan Gala",
    "wof:placetype":"locality"
},
  "geometry": {"coordinates":[73.6983,33.79651],"type":"Point"}
}