{
  "type": "Feature",
  "properties": {
    "gn:admin1_code":"4",
    "gn:asciiname":"Kahar",
    "gn:country_code":"PK",
    "gn:dem":438,
    "gn:feature_class":"P",
    "gn:feature_code":"PPL",
    "gn:name":"Kahar",
    "gn:population":0,
    "gn:timezone":"Asia/Karachi",
    "iso:country":"PK",
    "name:und_x_variant":[
        "Kanar"
    ],
    "wof:name":"Kahar",
    "wof:placetype":"locality"
},
  "geometry": {"coordinates":[72.10253,32.73387],"type":"Point"}
}