{
  "type": "Feature",
  "properties": {
    "gn:admin1_code":"4.0",
    "gn:asciiname":"Chak Ninety-six Rakh Branch",
    "gn:country_code":"PK",
    "gn:dem":195,
    "gn:feature_class":"P",
    "gn:feature_code":"PPL",
    "gn:name":"Chak Ninety-six Rakh Branch",
    "gn:population":0,
    "gn:timezone":"Asia/Karachi",
    "iso:country":"PK",
    "name:und_x_variant":[
        "Fazalabad",
        "Fazl\u0101b\u0101d",
        "Chak Ninety-six Rakh Branch",
        "M\u0101ri"
    ],
    "wof:name":"Chak Ninety-six Rakh Branch",
    "wof:placetype":"locality"
},
  "geometry": {"coordinates":[73.40875,31.47927],"type":"Point"}
}