{
  "type": "Feature",
  "properties": {
    "gn:admin1_code":"1.0",
    "gn:asciiname":"Ghundakai",
    "gn:country_code":"PK",
    "gn:dem":1620,
    "gn:feature_class":"P",
    "gn:feature_code":"PPL",
    "gn:name":"Ghundakai",
    "gn:population":0,
    "gn:timezone":"Asia/Karachi",
    "iso:country":"PK",
    "wof:name":"Ghundakai",
    "wof:placetype":"locality"
},
  "geometry": {"coordinates":[70.01201999999999,32.68372],"type":"Point"}
}