{
  "type": "Feature",
  "properties": {
    "gn:admin1_code":"3",
    "gn:asciiname":"Kuwidakot",
    "gn:country_code":"PK",
    "gn:dem":1841,
    "gn:feature_class":"P",
    "gn:feature_code":"PPL",
    "gn:name":"Kuwidakot",
    "gn:population":0,
    "gn:timezone":"Asia/Karachi",
    "iso:country":"PK",
    "name:eng_x_preferred":[
        "Kuwidakot"
    ],
    "wof:name":"Kuwidakot",
    "wof:placetype":"locality"
},
  "geometry": {"coordinates":[71.93943,35.20768],"type":"Point"}
}