{
  "type": "Feature",
  "properties": {
    "gn:admin1_code":"5.0",
    "gn:asciiname":"Goth Bandi",
    "gn:country_code":"PK",
    "gn:dem":213,
    "gn:feature_class":"P",
    "gn:feature_code":"PPL",
    "gn:name":"Goth Bandi",
    "gn:population":0,
    "gn:timezone":"Asia/Karachi",
    "iso:country":"PK",
    "name:und_x_variant":[
        "Goth P\u0101ndhi"
    ],
    "wof:name":"Goth Bandi",
    "wof:placetype":"locality"
},
  "geometry": {"coordinates":[67.623,25.20185],"type":"Point"}
}