{
  "type": "Feature",
  "properties": {
    "gn:admin1_code":"3",
    "gn:asciiname":"Kara",
    "gn:country_code":"PK",
    "gn:dem":1724,
    "gn:feature_class":"P",
    "gn:feature_code":"PPL",
    "gn:name":"Kara",
    "gn:population":0,
    "gn:timezone":"Asia/Karachi",
    "iso:country":"PK",
    "wof:name":"Kara",
    "wof:placetype":"locality"
},
  "geometry": {"coordinates":[73.37455,34.54496],"type":"Point"}
}