{
  "type": "Feature",
  "properties": {
    "gn:admin1_code":"2",
    "gn:asciiname":"Shaikh Ahmadi",
    "gn:country_code":"PK",
    "gn:dem":114,
    "gn:feature_class":"P",
    "gn:feature_code":"PPL",
    "gn:name":"Shaikh Ahmadi",
    "gn:population":0,
    "gn:timezone":"Asia/Karachi",
    "iso:country":"PK",
    "name:eng_x_preferred":[
        "Shaikh Ahmadi"
    ],
    "wof:name":"Shaikh Ahmadi",
    "wof:placetype":"locality"
},
  "geometry": {"coordinates":[66.94049,25.15499],"type":"Point"}
}