{
  "type": "Feature",
  "properties": {
    "gn:admin1_code":"6",
    "gn:asciiname":"Nimae",
    "gn:country_code":"PK",
    "gn:dem":1050,
    "gn:feature_class":"P",
    "gn:feature_code":"PPL",
    "gn:name":"Nimae",
    "gn:population":0,
    "gn:timezone":"Asia/Karachi",
    "iso:country":"PK",
    "name:und_x_variant":[
        "Nanderi",
        "Nimae"
    ],
    "wof:name":"Nimae",
    "wof:placetype":"locality"
},
  "geometry": {"coordinates":[74.03055999999999,33.58889],"type":"Point"}
}