{
  "type": "Feature",
  "properties": {
    "gn:admin1_code":"2.0",
    "gn:asciiname":"Latida",
    "gn:country_code":"PK",
    "gn:dem":28,
    "gn:feature_class":"P",
    "gn:feature_code":"PPL",
    "gn:name":"Latida",
    "gn:population":0,
    "gn:timezone":"Asia/Karachi",
    "iso:country":"PK",
    "name:und_x_variant":[
        "L\u0101nti D\u0101n",
        "Latida"
    ],
    "wof:name":"Latida",
    "wof:placetype":"locality"
},
  "geometry": {"coordinates":[62.99871,25.50078],"type":"Point"}
}