{
  "type": "Feature",
  "properties": {
    "gn:admin1_code":"4.0",
    "gn:asciiname":"Ali Khel",
    "gn:country_code":"PK",
    "gn:dem":225,
    "gn:feature_class":"P",
    "gn:feature_code":"PPL",
    "gn:name":"Ali Khel",
    "gn:population":0,
    "gn:timezone":"Asia/Karachi",
    "iso:country":"PK",
    "wof:name":"Ali Khel",
    "wof:placetype":"locality"
},
  "geometry": {"coordinates":[71.71986,32.51976],"type":"Point"}
}