{
  "type": "Feature",
  "properties": {
    "gn:admin1_code":"4.0",
    "gn:asciiname":"Bichhor",
    "gn:country_code":"PK",
    "gn:dem":686,
    "gn:feature_class":"P",
    "gn:feature_code":"PPL",
    "gn:name":"Bichhor",
    "gn:population":0,
    "gn:timezone":"Asia/Karachi",
    "iso:country":"PK",
    "wof:name":"Bichhor",
    "wof:placetype":"locality"
},
  "geometry": {"coordinates":[73.57119,33.83985999999999],"type":"Point"}
}