{
  "type": "Feature",
  "properties": {
    "gn:admin1_code":"4.0",
    "gn:asciiname":"Bichhor",
    "gn:country_code":"PK",
    "gn:dem":686,
    "gn:feature_class":"P",
    "gn:feature_code":"PPL",
    "gn:name":"Bichhor",
    "gn:population":0,
    "gn:timezone":"Asia/Karachi",
    "iso:country":"PK",
    "name:hin_x_preferred":[
        "\u092c\u093f\u091b\u094c\u0930"
    ],
    "name:mal_x_preferred":[
        "\u0d2c\u0d3f\u0d1a\u0d4d\u0d1a\u0d4b\u0d7c"
    ],
    "wof:name":"Bichhor",
    "wof:placetype":"locality"
},
  "geometry": {"coordinates":[73.57119,33.83985999999999],"type":"Point"}
}