{
  "type": "Feature",
  "properties": {
    "gn:admin1_code":"4",
    "gn:asciiname":"Dhok Padi",
    "gn:country_code":"PK",
    "gn:dem":795,
    "gn:feature_class":"P",
    "gn:feature_code":"PPL",
    "gn:name":"Dhok Padi",
    "gn:population":0,
    "gn:timezone":"Asia/Karachi",
    "iso:country":"PK",
    "name:und_x_variant":[
        "Padhi"
    ],
    "wof:name":"Dhok Padi",
    "wof:placetype":"locality"
},
  "geometry": {"coordinates":[72.07458000000003,32.59044],"type":"Point"}
}