{
  "type": "Feature",
  "properties": {
    "gn:admin1_code":"04",
    "gn:asciiname":"Sang",
    "gn:country_code":"PK",
    "gn:dem":305,
    "gn:feature_class":"P",
    "gn:feature_code":"PPL",
    "gn:name":"Sang",
    "gn:population":0,
    "gn:timezone":"Asia/Karachi",
    "iso:country":"PK",
    "name:ceb_x_preferred":[
        "Sang"
    ],
    "name:deu_x_preferred":[
        "Sang"
    ],
    "name:fas_x_preferred":[
        "\u0633\u0646\u06af"
    ],
    "name:fra_x_preferred":[
        "Sang"
    ],
    "name:rus_x_preferred":[
        "\u0421\u0430\u043d\u0433"
    ],
    "name:swe_x_preferred":[
        "Sang"
    ],
    "wof:name":"Sang",
    "wof:placetype":"locality"
},
  "geometry": {"coordinates":[73.98146,32.94447],"type":"Point"}
}