{
  "type": "Feature",
  "properties": {
    "gn:admin1_code":"5.0",
    "gn:asciiname":"Goth Chakar Panhwar",
    "gn:country_code":"PK",
    "gn:dem":6,
    "gn:feature_class":"P",
    "gn:feature_code":"PPL",
    "gn:name":"Goth Chakar Panhwar",
    "gn:population":0,
    "gn:timezone":"Asia/Karachi",
    "iso:country":"PK",
    "name:und_x_variant":[
        "Ch\u0101kar Panhar"
    ],
    "wof:name":"Goth Chakar Panhwar",
    "wof:placetype":"locality"
},
  "geometry": {"coordinates":[69.06124,24.49359],"type":"Point"}
}