{
  "type": "Feature",
  "properties": {
    "gn:admin1_code":"5.0",
    "gn:asciiname":"Haji Muhammad",
    "gn:country_code":"PK",
    "gn:dem":4,
    "gn:feature_class":"P",
    "gn:feature_code":"PPL",
    "gn:name":"Haji Muhammad",
    "gn:population":0,
    "gn:timezone":"Asia/Karachi",
    "iso:country":"PK",
    "name:fas_x_preferred":[
        "\u062d\u0627\u062c\u06cc \u0645\u062d\u0645\u062f"
    ],
    "name:urd_x_preferred":[
        "\u062d\u0627\u062c\u06cc \u0645\u062d\u0645\u062f"
    ],
    "wof:name":"Haji Muhammad",
    "wof:placetype":"locality"
},
  "geometry": {"coordinates":[68.89999,24.36592000000001],"type":"Point"}
}