{
  "type": "Feature",
  "properties": {
    "gn:admin1_code":"4",
    "gn:asciiname":"Ziadewala",
    "gn:country_code":"PK",
    "gn:dem":174,
    "gn:feature_class":"P",
    "gn:feature_code":"PPL",
    "gn:name":"Ziadewala",
    "gn:population":0,
    "gn:timezone":"Asia/Karachi",
    "iso:country":"PK",
    "name:und_x_variant":[
        "Z\u0101diw\u0101la",
        "Z\u0101dew\u0101la",
        "Ziadewala"
    ],
    "wof:name":"Ziadewala",
    "wof:placetype":"locality"
},
  "geometry": {"coordinates":[72.59909,31.7444],"type":"Point"}
}