{
  "type": "Feature",
  "properties": {
    "gn:admin1_code":"1",
    "gn:asciiname":"Shahbozai",
    "gn:country_code":"PK",
    "gn:dem":1850,
    "gn:feature_class":"P",
    "gn:feature_code":"PPL",
    "gn:name":"Shahbozai",
    "gn:population":0,
    "gn:timezone":"Asia/Karachi",
    "iso:country":"PK",
    "wof:name":"Shahbozai",
    "wof:placetype":"locality"
},
  "geometry": {"coordinates":[69.94145,32.65081],"type":"Point"}
}