{
  "type": "Feature",
  "properties": {
    "gn:admin1_code":"3",
    "gn:asciiname":"Ziaranai",
    "gn:country_code":"PK",
    "gn:dem":1746,
    "gn:feature_class":"P",
    "gn:feature_code":"PPL",
    "gn:name":"Ziaranai",
    "gn:population":0,
    "gn:timezone":"Asia/Karachi",
    "iso:country":"PK",
    "name:eng_x_preferred":[
        "Ziaranai"
    ],
    "wof:name":"Ziaranai",
    "wof:placetype":"locality"
},
  "geometry": {"coordinates":[71.70837,35.04492],"type":"Point"}
}