{
  "type": "Feature",
  "properties": {
    "gn:admin1_code":"4.0",
    "gn:asciiname":"Dhok Jhakkawali",
    "gn:country_code":"PK",
    "gn:dem":255,
    "gn:feature_class":"P",
    "gn:feature_code":"PPL",
    "gn:name":"Dhok Jhakkawali",
    "gn:population":0,
    "gn:timezone":"Asia/Karachi",
    "iso:country":"PK",
    "name:und_x_variant":[
        "Jhakkaw\u0101li Dhok"
    ],
    "wof:name":"Dhok Jhakkawali",
    "wof:placetype":"locality"
},
  "geometry": {"coordinates":[71.87829000000001,33.05973],"type":"Point"}
}