{
  "type": "Feature",
  "properties": {
    "gn:admin1_code":"5.0",
    "gn:asciiname":"Punu Sand",
    "gn:country_code":"PK",
    "gn:dem":10,
    "gn:feature_class":"P",
    "gn:feature_code":"PPL",
    "gn:name":"Punu Sand",
    "gn:population":0,
    "gn:timezone":"Asia/Karachi",
    "iso:country":"PK",
    "name:eng_x_preferred":[
        "Punu Sand"
    ],
    "wof:name":"Punu Sand",
    "wof:placetype":"locality"
},
  "geometry": {"coordinates":[68.03997,24.5344],"type":"Point"}
}