{
  "type": "Feature",
  "properties": {
    "gn:admin1_code":"3",
    "gn:asciiname":"Sokar",
    "gn:country_code":"PK",
    "gn:dem":1261,
    "gn:feature_class":"P",
    "gn:feature_code":"PPL",
    "gn:name":"Sokar",
    "gn:population":0,
    "gn:timezone":"Asia/Karachi",
    "iso:country":"PK",
    "name:deu_x_preferred":[
        "Sokar"
    ],
    "name:ita_x_preferred":[
        "Sokar"
    ],
    "wof:name":"Sokar",
    "wof:placetype":"locality"
},
  "geometry": {"coordinates":[72.68623000000002,34.67171],"type":"Point"}
}