{
  "type": "Feature",
  "properties": {
    "gn:admin1_code":"4",
    "gn:asciiname":"Mad Haji Mithauwala",
    "gn:country_code":"PK",
    "gn:dem":95,
    "gn:feature_class":"P",
    "gn:feature_code":"PPL",
    "gn:name":"Mad Haji Mithauwala",
    "gn:population":0,
    "gn:timezone":"Asia/Karachi",
    "iso:country":"PK",
    "wof:name":"Mad Haji Mithauwala",
    "wof:placetype":"locality"
},
  "geometry": {"coordinates":[70.26515000000001,29.17652],"type":"Point"}
}