{
  "type": "Feature",
  "properties": {
    "gn:admin1_code":"5.0",
    "gn:asciiname":"Khairodero",
    "gn:country_code":"PK",
    "gn:dem":59,
    "gn:feature_class":"P",
    "gn:feature_code":"PPL",
    "gn:name":"Khairodero",
    "gn:population":0,
    "gn:timezone":"Asia/Karachi",
    "iso:country":"PK",
    "name:und_x_variant":[
        "Goth Khairo Dero",
        "Khairodero",
        "Goth Khairo Daro"
    ],
    "wof:name":"Khairodero",
    "wof:placetype":"locality"
},
  "geometry": {"coordinates":[68.25018,27.72201],"type":"Point"}
}