{
  "type": "Feature",
  "properties": {
    "gn:admin1_code":"7.0",
    "gn:asciiname":"Ishkil",
    "gn:country_code":"PK",
    "gn:dem":3007,
    "gn:feature_class":"P",
    "gn:feature_code":"PPL",
    "gn:name":"Ishkil",
    "gn:population":0,
    "gn:timezone":"Asia/Karachi",
    "iso:country":"PK",
    "name:und_x_variant":[
        "Ishk\u012bl"
    ],
    "wof:name":"Ishkil",
    "wof:placetype":"locality"
},
  "geometry": {"coordinates":[73.64437,36.32869],"type":"Point"}
}