{
  "type": "Feature",
  "properties": {
    "gn:admin1_code":"04",
    "gn:asciiname":"Saduki",
    "gn:country_code":"PK",
    "gn:dem":230,
    "gn:feature_class":"P",
    "gn:feature_code":"PPL",
    "gn:name":"Saduki",
    "gn:population":0,
    "gn:timezone":"Asia/Karachi",
    "iso:country":"PK",
    "name:und_x_variant":[
        "Sadhokee",
        "S\u0101dh\u016bke",
        "Saduki"
    ],
    "wof:name":"Saduki",
    "wof:placetype":"locality"
},
  "geometry": {"coordinates":[73.93871999999998,32.59869],"type":"Point"}
}