{
  "type": "Feature",
  "properties": {
    "gn:admin1_code":"3.0",
    "gn:asciiname":"Narkun Payin",
    "gn:country_code":"PK",
    "gn:dem":1792,
    "gn:feature_class":"P",
    "gn:feature_code":"PPL",
    "gn:name":"Narkun Payin",
    "gn:population":0,
    "gn:timezone":"Asia/Karachi",
    "iso:country":"PK",
    "name:eng_x_preferred":[
        "Narkun Payin"
    ],
    "wof:name":"Narkun Payin",
    "wof:placetype":"locality"
},
  "geometry": {"coordinates":[72.06003,35.32425999999999],"type":"Point"}
}