{
  "type": "Feature",
  "properties": {
    "gn:admin1_code":"4.0",
    "gn:asciiname":"Fateh Muhammadwala",
    "gn:country_code":"PK",
    "gn:dem":120,
    "gn:feature_class":"P",
    "gn:feature_code":"PPL",
    "gn:name":"Fateh Muhammadwala",
    "gn:population":0,
    "gn:timezone":"Asia/Karachi",
    "iso:country":"PK",
    "name:eng_x_preferred":[
        "Fateh Muhammadwala"
    ],
    "wof:name":"Fateh Muhammadwala",
    "wof:placetype":"locality"
},
  "geometry": {"coordinates":[70.73491999999997,30.09416],"type":"Point"}
}