{
  "type": "Feature",
  "properties": {
    "gn:admin1_code":"4",
    "gn:asciiname":"Khatar",
    "gn:country_code":"PK",
    "gn:dem":714,
    "gn:feature_class":"P",
    "gn:feature_code":"PPL",
    "gn:name":"Khatar",
    "gn:population":0,
    "gn:timezone":"Asia/Karachi",
    "iso:country":"PK",
    "wof:name":"Khatar",
    "wof:placetype":"locality"
},
  "geometry": {"coordinates":[72.01891999999999,32.42423],"type":"Point"}
}