{
  "type": "Feature",
  "properties": {
    "gn:admin1_code":"4.0",
    "gn:asciiname":"Dera Bagri",
    "gn:country_code":"PK",
    "gn:dem":193,
    "gn:feature_class":"P",
    "gn:feature_code":"PPL",
    "gn:name":"Dera Bagri",
    "gn:population":0,
    "gn:timezone":"Asia/Karachi",
    "iso:country":"PK",
    "name:und_x_variant":[
        "Bagri"
    ],
    "wof:name":"Dera Bagri",
    "wof:placetype":"locality"
},
  "geometry": {"coordinates":[73.09711,32.1099],"type":"Point"}
}