{
  "type": "Feature",
  "properties": {
    "gn:admin1_code":"2.0",
    "gn:asciiname":"Kili Haji Dad Muhammad",
    "gn:country_code":"PK",
    "gn:dem":1651,
    "gn:feature_class":"P",
    "gn:feature_code":"PPL",
    "gn:name":"Kili Haji Dad Muhammad",
    "gn:population":0,
    "gn:timezone":"Asia/Karachi",
    "iso:country":"PK",
    "wof:name":"Kili Haji Dad Muhammad",
    "wof:placetype":"locality"
},
  "geometry": {"coordinates":[61.16685,29.55235],"type":"Point"}
}