{
  "type": "Feature",
  "properties": {
    "gn:admin1_code":"3.0",
    "gn:asciiname":"Bharat",
    "gn:country_code":"PK",
    "gn:dem":339,
    "gn:feature_class":"P",
    "gn:feature_code":"PPL",
    "gn:name":"Bharat",
    "gn:population":0,
    "gn:timezone":"Asia/Karachi",
    "iso:country":"PK",
    "name:ben_x_preferred":[
        "\u09ad\u09b0\u09a4"
    ],
    "name:ceb_x_preferred":[
        "Bharat"
    ],
    "name:deu_x_preferred":[
        "Bharata"
    ],
    "name:epo_x_preferred":[
        "Bharata"
    ],
    "name:fra_x_preferred":[
        "Bharata"
    ],
    "name:hin_x_preferred":[
        "\u092d\u0930\u0924"
    ],
    "name:ind_x_preferred":[
        "Bharata"
    ],
    "name:ita_x_preferred":[
        "Bharat"
    ],
    "name:jpn_x_preferred":[
        "\u30d0\u30e9\u30bf"
    ],
    "name:lit_x_preferred":[
        "Bharata"
    ],
    "name:mai_x_preferred":[
        "\u092d\u0930\u0924"
    ],
    "name:mal_x_preferred":[
        "\u0d2d\u0d30\u0d24\u0d7b"
    ],
    "name:mar_x_preferred":[
        "\u092d\u0930\u0924"
    ],
    "name:rus_x_preferred":[
        "\u0411\u0445\u0430\u0440\u0430\u0442\u0430"
    ],
    "name:san_x_preferred":[
        "\u092d\u0930\u0924\u0903"
    ],
    "name:spa_x_preferred":[
        "Bharata"
    ],
    "name:tgk_x_preferred":[
        "\u0411\u04b3\u0430\u0440\u0430\u0442"
    ],
    "name:ukr_x_preferred":[
        "\u0411\u0445\u0430\u0440\u0430\u0442\u0430"
    ],
    "name:und_x_variant":[
        "Bharth",
        "Bhart",
        "Surkamand"
    ],
    "wof:name":"Bharat",
    "wof:placetype":"locality"
},
  "geometry": {"coordinates":[70.63694,32.89028],"type":"Point"}
}