{
  "type": "Feature",
  "properties": {
    "gn:admin1_code":"3.0",
    "gn:asciiname":"Bharat",
    "gn:country_code":"PK",
    "gn:dem":339,
    "gn:feature_class":"P",
    "gn:feature_code":"PPL",
    "gn:name":"Bharat",
    "gn:population":0,
    "gn:timezone":"Asia/Karachi",
    "iso:country":"PK",
    "name:und_x_variant":[
        "Bharth",
        "Bhart",
        "Surkamand"
    ],
    "wof:name":"Bharat",
    "wof:placetype":"locality"
},
  "geometry": {"coordinates":[70.63694,32.89028],"type":"Point"}
}