{
  "type": "Feature",
  "properties": {
    "gn:admin1_code":"7.0",
    "gn:asciiname":"Dalot",
    "gn:country_code":"PK",
    "gn:dem":3438,
    "gn:feature_class":"P",
    "gn:feature_code":"PPL",
    "gn:name":"Dalot",
    "gn:population":0,
    "gn:timezone":"Asia/Karachi",
    "iso:country":"PK",
    "wof:name":"Dalot",
    "wof:placetype":"locality"
},
  "geometry": {"coordinates":[73.64509,35.76117],"type":"Point"}
}