{
  "type": "Feature",
  "properties": {
    "gn:admin1_code":"2.0",
    "gn:asciiname":"Halkai",
    "gn:country_code":"PK",
    "gn:dem":2180,
    "gn:feature_class":"P",
    "gn:feature_code":"PPL",
    "gn:name":"Halkai",
    "gn:population":0,
    "gn:timezone":"Asia/Karachi",
    "iso:country":"PK",
    "name:eng_x_preferred":[
        "Halkai"
    ],
    "wof:name":"Halkai",
    "wof:placetype":"locality"
},
  "geometry": {"coordinates":[67.38696999999999,30.76847],"type":"Point"}
}