{
  "type": "Feature",
  "properties": {
    "gn:admin1_code":"7.0",
    "gn:asciiname":"Jutal",
    "gn:country_code":"PK",
    "gn:dem":1619,
    "gn:feature_class":"P",
    "gn:feature_code":"PPL",
    "gn:name":"Jutal",
    "gn:population":0,
    "gn:timezone":"Asia/Karachi",
    "iso:country":"PK",
    "wof:name":"Jutal",
    "wof:placetype":"locality"
},
  "geometry": {"coordinates":[74.29973000000003,36.04516],"type":"Point"}
}