{
  "type": "Feature",
  "properties": {
    "gn:admin1_code":"4.0",
    "gn:asciiname":"Bhattian de Jhugge",
    "gn:country_code":"PK",
    "gn:dem":175,
    "gn:feature_class":"P",
    "gn:feature_code":"PPL",
    "gn:name":"Bhattian de Jhugge",
    "gn:population":0,
    "gn:timezone":"Asia/Karachi",
    "iso:country":"PK",
    "wof:name":"Bhattian de Jhugge",
    "wof:placetype":"locality"
},
  "geometry": {"coordinates":[72.13786999999998,31.67235],"type":"Point"}
}