{
  "type": "Feature",
  "properties": {
    "gn:admin1_code":"3",
    "gn:asciiname":"Kandaogai",
    "gn:country_code":"PK",
    "gn:dem":2973,
    "gn:feature_class":"P",
    "gn:feature_code":"PPL",
    "gn:name":"Kandaogai",
    "gn:population":0,
    "gn:timezone":"Asia/Karachi",
    "iso:country":"PK",
    "wof:name":"Kandaogai",
    "wof:placetype":"locality"
},
  "geometry": {"coordinates":[72.66070999999999,35.02356],"type":"Point"}
}