{
  "type": "Feature",
  "properties": {
    "gn:admin1_code":"2.0",
    "gn:asciiname":"Shagai",
    "gn:country_code":"PK",
    "gn:dem":861,
    "gn:feature_class":"P",
    "gn:feature_code":"PPL",
    "gn:name":"Shagai",
    "gn:population":0,
    "gn:timezone":"Asia/Karachi",
    "iso:country":"PK",
    "wof:name":"Shagai",
    "wof:placetype":"locality"
},
  "geometry": {"coordinates":[70.18862,31.0652],"type":"Point"}
}