{
  "type": "Feature",
  "properties": {
    "gn:admin1_code":"3.0",
    "gn:asciiname":"Musa Khel",
    "gn:country_code":"PK",
    "gn:dem":340,
    "gn:feature_class":"P",
    "gn:feature_code":"PPL",
    "gn:name":"Musa Khel",
    "gn:population":0,
    "gn:timezone":"Asia/Karachi",
    "iso:country":"PK",
    "wof:name":"Musa Khel",
    "wof:placetype":"locality"
},
  "geometry": {"coordinates":[70.64444,32.93278],"type":"Point"}
}