{
  "type": "Feature",
  "properties": {
    "iso:country":"PK",
    "name:eng_x_preferred":[
        "Sangla Hill Tehsil"
    ],
    "name:fra_x_preferred":[
        "Sangla Hill"
    ],
    "name:jpn_x_preferred":[
        "\u30b5\u30f3\u30b0\u30e9\u30fc\u30fb\u30d2\u30eb"
    ],
    "name:nld_x_preferred":[
        "Sangla Hill Tehsil"
    ],
    "name:pnb_x_preferred":[
        "\u062a\u0635\u06cc\u0644 \u0633\u0627\u0646\u06af\u0644\u0627 \u06c1\u0644"
    ],
    "name:spa_x_preferred":[
        "Sangala"
    ],
    "name:urd_x_preferred":[
        "\u0633\u0627\u0646\u06af\u0644\u06c1 \u06c1\u0644"
    ],
    "qs:gn_country":"PK",
    "qs:gn_fcode":"PPL",
    "qs:gn_pop":57002,
    "qs:name":"Sangla Hill",
    "qs:name_adm0":"Pakistan",
    "qs:name_adm1":"Punjab",
    "qs:photos":7,
    "qs:photos_1k":1,
    "qs:photos_9k":1,
    "qs:photos_9r":1,
    "qs:photos_all":7,
    "qs:photos_sr":1,
    "qs:placetype":"Town",
    "qs:pop_sr":"8",
    "qs:woe_adm0":23424922,
    "wd:wordcount":2019,
    "wof:name":"Sangla Hill",
    "wof:placetype":"locality",
    "wof:population":57002
},
  "geometry": {"coordinates":[73.38333,31.71667],"type":"Point"}
}