{
  "type": "Feature",
  "properties": {
    "gn:admin1_code":"4.0",
    "gn:asciiname":"Adrana",
    "gn:country_code":"PK",
    "gn:dem":333,
    "gn:feature_class":"P",
    "gn:feature_code":"PPL",
    "gn:name":"Adrana",
    "gn:population":0,
    "gn:timezone":"Asia/Karachi",
    "iso:country":"PK",
    "name:und_x_variant":[
        "Adranah",
        "Adrana"
    ],
    "wof:name":"Adrana",
    "wof:placetype":"locality"
},
  "geometry": {"coordinates":[73.42471,32.97541],"type":"Point"}
}