{
  "type": "Feature",
  "properties": {
    "gn:admin1_code":"2.0",
    "gn:asciiname":"Khalq Haji Wahid Bakhsh",
    "gn:country_code":"PK",
    "gn:dem":1717,
    "gn:feature_class":"P",
    "gn:feature_code":"PPL",
    "gn:name":"Khalq Haji Wahid Bakhsh",
    "gn:population":0,
    "gn:timezone":"Asia/Karachi",
    "iso:country":"PK",
    "wof:name":"Khalq Haji Wahid Bakhsh",
    "wof:placetype":"locality"
},
  "geometry": {"coordinates":[66.95766,30.0788],"type":"Point"}
}