{
  "type": "Feature",
  "properties": {
    "gn:admin1_code":"01",
    "gn:asciiname":"Pashat",
    "gn:country_code":"PK",
    "gn:dem":972,
    "gn:feature_class":"P",
    "gn:feature_code":"PPL",
    "gn:name":"Pashat",
    "gn:population":0,
    "gn:timezone":"Asia/Karachi",
    "iso:country":"PK",
    "name:eng_x_preferred":[
        "Pashat"
    ],
    "name:und_x_variant":[
        "Sal\u0101rzai"
    ],
    "wof:name":"Pashat",
    "wof:placetype":"locality"
},
  "geometry": {"coordinates":[71.52664,34.86545],"type":"Point"}
}