{
  "type": "Feature",
  "properties": {
    "gn:admin1_code":"5.0",
    "gn:asciiname":"Pul Twenty-two Mil",
    "gn:country_code":"PK",
    "gn:dem":70,
    "gn:feature_class":"P",
    "gn:feature_code":"PPL",
    "gn:name":"Pul Twenty-two Mil",
    "gn:population":0,
    "gn:timezone":"Asia/Karachi",
    "iso:country":"PK",
    "wof:name":"Pul Twenty-two Mil",
    "wof:placetype":"locality"
},
  "geometry": {"coordinates":[69.22974000000001,28.39301],"type":"Point"}
}