{
  "type": "Feature",
  "properties": {
    "gn:admin1_code":"3",
    "gn:asciiname":"Dambar Kola",
    "gn:country_code":"PK",
    "gn:dem":1649,
    "gn:feature_class":"P",
    "gn:feature_code":"PPL",
    "gn:name":"Dambar Kola",
    "gn:population":0,
    "gn:timezone":"Asia/Karachi",
    "iso:country":"PK",
    "name:eng_x_preferred":[
        "Damharkola"
    ],
    "wof:name":"Dambar Kola",
    "wof:placetype":"locality"
},
  "geometry": {"coordinates":[71.85231999999998,35.16216],"type":"Point"}
}