{
  "type": "Feature",
  "properties": {
    "gn:admin1_code":"3.0",
    "gn:asciiname":"Spin Kanrai",
    "gn:country_code":"PK",
    "gn:dem":304,
    "gn:feature_class":"P",
    "gn:feature_code":"PPL",
    "gn:name":"Spin Kanrai",
    "gn:population":0,
    "gn:timezone":"Asia/Karachi",
    "iso:country":"PK",
    "name:eng_x_preferred":[
        "Sp\u012bnk\u0101ni"
    ],
    "wof:name":"Spin Kanrai",
    "wof:placetype":"locality"
},
  "geometry": {"coordinates":[71.94758,34.13513],"type":"Point"}
}