{
  "type": "Feature",
  "properties": {
    "gn:admin1_code":"3",
    "gn:asciiname":"Rakhan",
    "gn:country_code":"PK",
    "gn:dem":2915,
    "gn:feature_class":"P",
    "gn:feature_code":"PPL",
    "gn:name":"Rakhan",
    "gn:population":0,
    "gn:timezone":"Asia/Karachi",
    "iso:country":"PK",
    "wof:name":"Rakhan",
    "wof:placetype":"locality"
},
  "geometry": {"coordinates":[73.86306999999999,34.94322],"type":"Point"}
}