{
  "type": "Feature",
  "properties": {
    "gn:admin1_code":"4",
    "gn:asciiname":"Balochanwala",
    "gn:country_code":"PK",
    "gn:dem":162,
    "gn:feature_class":"P",
    "gn:feature_code":"PPL",
    "gn:name":"Balochanwala",
    "gn:population":0,
    "gn:timezone":"Asia/Karachi",
    "iso:country":"PK",
    "name:und_x_variant":[
        "Balochw\u0101la"
    ],
    "wof:name":"Balochanwala",
    "wof:placetype":"locality"
},
  "geometry": {"coordinates":[71.0099,31.43377000000001],"type":"Point"}
}