{
  "type": "Feature",
  "properties": {
    "gn:admin1_code":"4.0",
    "gn:asciiname":"Tibba Chak Eighty-three - Five Right",
    "gn:country_code":"PK",
    "gn:dem":160,
    "gn:feature_class":"P",
    "gn:feature_code":"PPL",
    "gn:name":"Tibba Chak Eighty-three - Five Right",
    "gn:population":0,
    "gn:timezone":"Asia/Karachi",
    "iso:country":"PK",
    "wof:name":"Tibba Chak Eighty-three - Five Right",
    "wof:placetype":"locality"
},
  "geometry": {"coordinates":[73.14690999999998,29.57114],"type":"Point"}
}