{
  "type": "Feature",
  "properties": {
    "gn:admin1_code":"7.0",
    "gn:asciiname":"Nolti",
    "gn:country_code":"PK",
    "gn:dem":2573,
    "gn:feature_class":"P",
    "gn:feature_code":"PPL",
    "gn:name":"Nolti",
    "gn:population":0,
    "gn:timezone":"Asia/Karachi",
    "iso:country":"PK",
    "wof:name":"Nolti",
    "wof:placetype":"locality"
},
  "geometry": {"coordinates":[73.27070000000001,36.1613],"type":"Point"}
}