{
  "type": "Feature",
  "properties": {
    "gn:admin1_code":"2.0",
    "gn:asciiname":"Goru",
    "gn:country_code":"PK",
    "gn:dem":1502,
    "gn:feature_class":"P",
    "gn:feature_code":"PPL",
    "gn:name":"Goru",
    "gn:population":0,
    "gn:timezone":"Asia/Karachi",
    "iso:country":"PK",
    "wof:name":"Goru",
    "wof:placetype":"locality"
},
  "geometry": {"coordinates":[66.57523,28.4475],"type":"Point"}
}