{
  "type": "Feature",
  "properties": {
    "gn:admin1_code":"4.0",
    "gn:asciiname":"Shino Ghund",
    "gn:country_code":"PK",
    "gn:dem":581,
    "gn:feature_class":"P",
    "gn:feature_code":"PPL",
    "gn:name":"Shino Ghund",
    "gn:population":0,
    "gn:timezone":"Asia/Karachi",
    "iso:country":"PK",
    "wof:name":"Shino Ghund",
    "wof:placetype":"locality"
},
  "geometry": {"coordinates":[71.56518,33.08637],"type":"Point"}
}