{
  "type": "Feature",
  "properties": {
    "gn:admin1_code":"4.0",
    "gn:asciiname":"Chak Ninety-six Fateh",
    "gn:country_code":"PK",
    "gn:dem":151,
    "gn:feature_class":"P",
    "gn:feature_code":"PPL",
    "gn:name":"Chak Ninety-six Fateh",
    "gn:population":0,
    "gn:timezone":"Asia/Karachi",
    "iso:country":"PK",
    "name:und_x_variant":[
        "Phtanaw\u0101la"
    ],
    "wof:name":"Chak Ninety-six Fateh",
    "wof:placetype":"locality"
},
  "geometry": {"coordinates":[72.798,29.69031],"type":"Point"}
}