{
  "type": "Feature",
  "properties": {
    "gn:admin1_code":"2.0",
    "gn:asciiname":"Makkad Bazar",
    "gn:country_code":"PK",
    "gn:dem":875,
    "gn:feature_class":"P",
    "gn:feature_code":"PPL",
    "gn:name":"Makkad Bazar",
    "gn:population":0,
    "gn:timezone":"Asia/Karachi",
    "iso:country":"PK",
    "name:und_x_variant":[
        "Makkad"
    ],
    "wof:name":"Makkad Bazar",
    "wof:placetype":"locality"
},
  "geometry": {"coordinates":[63.58268,26.63047000000001],"type":"Point"}
}