{
  "type": "Feature",
  "properties": {
    "gn:admin1_code":"3.0",
    "gn:asciiname":"Pir Panjan Shah",
    "gn:country_code":"PK",
    "gn:dem":226,
    "gn:feature_class":"P",
    "gn:feature_code":"PPL",
    "gn:name":"Pir Panjan Shah",
    "gn:population":0,
    "gn:timezone":"Asia/Karachi",
    "iso:country":"PK",
    "wof:name":"Pir Panjan Shah",
    "wof:placetype":"locality"
},
  "geometry": {"coordinates":[70.3977,31.74928],"type":"Point"}
}