{
  "type": "Feature",
  "properties": {
    "gn:admin1_code":"01",
    "gn:asciiname":"Yasin Kor",
    "gn:country_code":"PK",
    "gn:dem":683,
    "gn:feature_class":"P",
    "gn:feature_code":"PPL",
    "gn:name":"Yasin Kor",
    "gn:population":0,
    "gn:timezone":"Asia/Karachi",
    "iso:country":"PK",
    "wof:name":"Yasin Kor",
    "wof:placetype":"locality"
},
  "geometry": {"coordinates":[71.34137,34.46011],"type":"Point"}
}