{
  "type": "Feature",
  "properties": {
    "gn:admin1_code":"4.0",
    "gn:asciiname":"Danna Hardo",
    "gn:cc2":"PK",
    "gn:country_code":"PK",
    "gn:dem":515,
    "gn:feature_class":"P",
    "gn:feature_code":"PPL",
    "gn:name":"Danna Hardo",
    "gn:population":0,
    "gn:timezone":"Asia/Karachi",
    "iso:country":"PK",
    "name:und_x_variant":[
        "Dina Hardo",
        "Dolal Hardo",
        "Danna Hardo"
    ],
    "wof:name":"Danna Hardo",
    "wof:placetype":"locality"
},
  "geometry": {"coordinates":[73.06667,33.65],"type":"Point"}
}