{
  "type": "Feature",
  "properties": {
    "gn:admin1_code":"4",
    "gn:asciiname":"Nawan Jindewala",
    "gn:country_code":"PK",
    "gn:dem":154,
    "gn:feature_class":"P",
    "gn:feature_code":"PPL",
    "gn:name":"Nawan Jindewala",
    "gn:population":0,
    "gn:timezone":"Asia/Karachi",
    "iso:country":"PK",
    "name:und_x_variant":[
        "Naw\u0101n Jind\u0101w\u0101la"
    ],
    "wof:name":"Nawan Jindewala",
    "wof:placetype":"locality"
},
  "geometry": {"coordinates":[71.74103000000002,31.10583],"type":"Point"}
}