{
  "type": "Feature",
  "properties": {
    "gn:admin1_code":"2.0",
    "gn:asciiname":"Dab Khanzai",
    "gn:country_code":"PK",
    "gn:dem":1540,
    "gn:feature_class":"P",
    "gn:feature_code":"PPL",
    "gn:name":"Dab Khanzai",
    "gn:population":0,
    "gn:timezone":"Asia/Karachi",
    "iso:country":"PK",
    "name:eng_x_preferred":[
        "Dab Kh\u0101nzai"
    ],
    "wof:name":"Dab Khanzai",
    "wof:placetype":"locality"
},
  "geometry": {"coordinates":[67.07895000000001,30.72229],"type":"Point"}
}