{
  "type": "Feature",
  "properties": {
    "gn:admin1_code":"6",
    "gn:asciiname":"Nathal",
    "gn:country_code":"PK",
    "gn:dem":2678,
    "gn:feature_class":"P",
    "gn:feature_code":"PPL",
    "gn:name":"Nathal",
    "gn:population":0,
    "gn:timezone":"Asia/Karachi",
    "iso:country":"PK",
    "wof:name":"Nathal",
    "wof:placetype":"locality"
},
  "geometry": {"coordinates":[73.67532,34.28348],"type":"Point"}
}