{
  "type": "Feature",
  "properties": {
    "gn:admin1_code":"5",
    "gn:asciiname":"Goth Khatian",
    "gn:country_code":"PK",
    "gn:dem":57,
    "gn:feature_class":"P",
    "gn:feature_code":"PPL",
    "gn:name":"Goth Khatian",
    "gn:population":0,
    "gn:timezone":"Asia/Karachi",
    "iso:country":"PK",
    "name:und_x_variant":[
        "Chadha"
    ],
    "wof:name":"Goth Khatian",
    "wof:placetype":"locality"
},
  "geometry": {"coordinates":[68.31343000000001,27.75251],"type":"Point"}
}