{
  "type": "Feature",
  "properties": {
    "gn:admin1_code":"1.0",
    "gn:asciiname":"Kund Walai",
    "gn:country_code":"PK",
    "gn:dem":1831,
    "gn:feature_class":"P",
    "gn:feature_code":"PPL",
    "gn:name":"Kund Walai",
    "gn:population":0,
    "gn:timezone":"Asia/Karachi",
    "iso:country":"PK",
    "wof:name":"Kund Walai",
    "wof:placetype":"locality"
},
  "geometry": {"coordinates":[70.86266999999999,33.74144],"type":"Point"}
}