{
  "type": "Feature",
  "properties": {
    "gn:admin1_code":"4.0",
    "gn:asciiname":"Gilmala",
    "gn:country_code":"PK",
    "gn:dem":155,
    "gn:feature_class":"P",
    "gn:feature_code":"PPL",
    "gn:name":"Gilmala",
    "gn:population":0,
    "gn:timezone":"Asia/Karachi",
    "iso:country":"PK",
    "wof:name":"Gilmala",
    "wof:placetype":"locality"
},
  "geometry": {"coordinates":[72.25598000000002,31.08807],"type":"Point"}
}