{
  "type": "Feature",
  "properties": {
    "gn:admin1_code":"4.0",
    "gn:asciiname":"Chak Shaikh Fateh",
    "gn:country_code":"PK",
    "gn:dem":161,
    "gn:feature_class":"P",
    "gn:feature_code":"PPL",
    "gn:name":"Chak Shaikh Fateh",
    "gn:population":0,
    "gn:timezone":"Asia/Karachi",
    "iso:country":"PK",
    "wof:name":"Chak Shaikh Fateh",
    "wof:placetype":"locality"
},
  "geometry": {"coordinates":[73.13696999999998,30.26266],"type":"Point"}
}