{
  "type": "Feature",
  "properties": {
    "gn:admin1_code":"4",
    "gn:asciiname":"Rajor",
    "gn:country_code":"PK",
    "gn:dem":240,
    "gn:feature_class":"P",
    "gn:feature_code":"PPL",
    "gn:name":"Rajor",
    "gn:population":0,
    "gn:timezone":"Asia/Karachi",
    "iso:country":"PK",
    "name:und_x_variant":[
        "R\u0101jar"
    ],
    "wof:name":"Rajor",
    "wof:placetype":"locality"
},
  "geometry": {"coordinates":[73.75904,32.89133],"type":"Point"}
}