{
  "type": "Feature",
  "properties": {
    "gn:admin1_code":"3.0",
    "gn:asciiname":"Afghan Colony",
    "gn:country_code":"PK",
    "gn:dem":410,
    "gn:feature_class":"P",
    "gn:feature_code":"PPL",
    "gn:name":"Afghan Colony",
    "gn:population":0,
    "gn:timezone":"Asia/Karachi",
    "iso:country":"PK",
    "name:eng_x_preferred":[
        "Afghan Colony"
    ],
    "name:urd_x_preferred":[
        "\u0627\u0641\u063a\u0627\u0646 \u06a9\u0627\u0644\u0648\u0646\u06cc"
    ],
    "wof:name":"Afghan Colony",
    "wof:placetype":"locality"
},
  "geometry": {"coordinates":[70.51287000000001,32.97707],"type":"Point"}
}