{
  "type": "Feature",
  "properties": {
    "gn:admin1_code":"4",
    "gn:asciiname":"Libbewala",
    "gn:country_code":"PK",
    "gn:dem":122,
    "gn:feature_class":"P",
    "gn:feature_code":"PPL",
    "gn:name":"Libbewala",
    "gn:population":0,
    "gn:timezone":"Asia/Karachi",
    "iso:country":"PK",
    "name:eng_x_preferred":[
        "Libbewala"
    ],
    "wof:name":"Libbewala",
    "wof:placetype":"locality"
},
  "geometry": {"coordinates":[70.93249,30.09658],"type":"Point"}
}