{
  "type": "Feature",
  "properties": {
    "gn:gn_country":"PK",
    "gn:gn_fcode":"PPL",
    "gn:gn_pop":18170,
    "gn:population":18170,
    "iso:country":"PK",
    "name:eng_x_preferred":[
        "Jand"
    ],
    "name:nld_x_preferred":[
        "Jand"
    ],
    "name:pnb_x_preferred":[
        "\u062c\u0646\u0688"
    ],
    "name:por_x_preferred":[
        "Jand"
    ],
    "name:urd_x_preferred":[
        "\u062c\u0646\u062f\u060c \u0627\u062a\u0648\u06a9\u06a9"
    ],
    "name:urd_x_variant":[
        "\u062c\u0646\u062f"
    ],
    "qs_pg:aaroncc":"PK",
    "qs_pg:gn_country":"PK",
    "qs_pg:gn_fcode":"PPL",
    "qs_pg:gn_pop":18170,
    "qs_pg:name":"Jand",
    "qs_pg:photos_9r":0,
    "qs_pg:photos_sr":0,
    "qs_pg:pop_sr":6,
    "qs_pg:qs_pg_placetype":"locality",
    "wof:name":"Jand",
    "wof:placetype":"locality",
    "wof:population":18170
},
  "geometry": {"coordinates":[72.01927999999999,33.42985],"type":"Point"}
}