{
  "type": "Feature",
  "properties": {
    "gn:admin1_code":"5.0",
    "gn:asciiname":"Imam Bakhsh Baloch",
    "gn:country_code":"PK",
    "gn:dem":6,
    "gn:feature_class":"P",
    "gn:feature_code":"PPL",
    "gn:name":"Im\u0101m Bakhsh Baloch",
    "gn:population":0,
    "gn:timezone":"Asia/Karachi",
    "iso:country":"PK",
    "wof:name":"Imam Bakhsh Baloch",
    "wof:placetype":"locality"
},
  "geometry": {"coordinates":[67.72610999999999,24.64194],"type":"Point"}
}