{
  "type": "Feature",
  "properties": {
    "gn:admin1_code":"2",
    "gn:asciiname":"Gulkhair",
    "gn:country_code":"PK",
    "gn:dem":2450,
    "gn:feature_class":"P",
    "gn:feature_code":"PPL",
    "gn:name":"Gulkhair",
    "gn:population":0,
    "gn:timezone":"Asia/Karachi",
    "iso:country":"PK",
    "name:und_x_variant":[
        "Gul Khair"
    ],
    "wof:name":"Gulkhair",
    "wof:placetype":"locality"
},
  "geometry": {"coordinates":[67.9443,31.11593],"type":"Point"}
}