{
  "type": "Feature",
  "properties": {
    "gn:admin1_code":"3.0",
    "gn:asciiname":"Dang Lakhtai Bala",
    "gn:country_code":"PK",
    "gn:dem":323,
    "gn:feature_class":"P",
    "gn:feature_code":"PPL",
    "gn:name":"Dang Lakhtai Bala",
    "gn:population":0,
    "gn:timezone":"Asia/Karachi",
    "iso:country":"PK",
    "name:eng_x_preferred":[
        "Dang Lakhta B\u0101la"
    ],
    "wof:name":"Dang Lakhtai Bala",
    "wof:placetype":"locality"
},
  "geometry": {"coordinates":[71.52091,34.15105],"type":"Point"}
}