{
  "type": "Feature",
  "properties": {
    "gn:admin1_code":"3",
    "gn:asciiname":"Dabhukan da Nar",
    "gn:country_code":"PK",
    "gn:dem":3202,
    "gn:feature_class":"P",
    "gn:feature_code":"PPL",
    "gn:name":"Dabhukan da Nar",
    "gn:population":0,
    "gn:timezone":"Asia/Karachi",
    "iso:country":"PK",
    "name:und_x_variant":[
        "Dabuk\u0101n da N\u0101r"
    ],
    "wof:name":"Dabhukan da Nar",
    "wof:placetype":"locality"
},
  "geometry": {"coordinates":[73.81565999999999,34.89879000000001],"type":"Point"}
}