{
  "type": "Feature",
  "properties": {
    "gn:admin1_code":"01",
    "gn:asciiname":"Tangai Loe Kalle",
    "gn:country_code":"PK",
    "gn:dem":1008,
    "gn:feature_class":"P",
    "gn:feature_code":"PPL",
    "gn:name":"Tangai Loe Kalle",
    "gn:population":0,
    "gn:timezone":"Asia/Karachi",
    "iso:country":"PK",
    "name:eng_x_preferred":[
        "Tangai"
    ],
    "name:eng_x_variant":[
        "Loe Kili"
    ],
    "name:und_x_variant":[
        "Tangai Charmang"
    ],
    "wof:name":"Tangai Loe Kalle",
    "wof:placetype":"locality"
},
  "geometry": {"coordinates":[71.50549000000002,34.79109],"type":"Point"}
}