{
  "type": "Feature",
  "properties": {
    "gn:admin1_code":"2.0",
    "gn:asciiname":"Alizai",
    "gn:country_code":"PK",
    "gn:dem":1530,
    "gn:feature_class":"P",
    "gn:feature_code":"PPL",
    "gn:name":"Alizai",
    "gn:population":0,
    "gn:timezone":"Asia/Karachi",
    "iso:country":"PK",
    "wof:name":"Alizai",
    "wof:placetype":"locality"
},
  "geometry": {"coordinates":[69.39796,30.71821],"type":"Point"}
}