{
  "type": "Feature",
  "properties": {
    "gn:admin1_code":"7.0",
    "gn:asciiname":"Khali",
    "gn:country_code":"PK",
    "gn:dem":3470,
    "gn:feature_class":"P",
    "gn:feature_code":"PPL",
    "gn:name":"Khali",
    "gn:population":0,
    "gn:timezone":"Asia/Karachi",
    "iso:country":"PK",
    "name:ceb_x_preferred":[
        "Khali"
    ],
    "name:por_x_preferred":[
        "Khali"
    ],
    "wof:name":"Khali",
    "wof:placetype":"locality"
},
  "geometry": {"coordinates":[74.02198,35.19936],"type":"Point"}
}