{
  "type": "Feature",
  "properties": {
    "gn:admin1_code":"3",
    "gn:asciiname":"Nam Shera",
    "gn:country_code":"PK",
    "gn:dem":715,
    "gn:feature_class":"P",
    "gn:feature_code":"PPL",
    "gn:name":"Nam Shera",
    "gn:population":0,
    "gn:timezone":"Asia/Karachi",
    "iso:country":"PK",
    "name:und_x_variant":[
        "Namshahra"
    ],
    "wof:name":"Nam Shera",
    "wof:placetype":"locality"
},
  "geometry": {"coordinates":[72.99082,34.28585],"type":"Point"}
}