{
  "type": "Feature",
  "properties": {
    "gn:admin1_code":"04",
    "gn:asciiname":"Kotla Musa Khan",
    "gn:country_code":"PK",
    "gn:dem":105,
    "gn:feature_class":"P",
    "gn:feature_code":"PPL",
    "gn:name":"Kotla Musa Khan",
    "gn:population":0,
    "gn:timezone":"Asia/Karachi",
    "iso:country":"PK",
    "name:fas_x_preferred":[
        "\u06a9\u0648\u062a\u0644\u0647 \u0645\u0648\u0633\u06cc\u200c\u062e\u0627\u0646"
    ],
    "name:pol_x_preferred":[
        "Kotla Musa Khan"
    ],
    "name:urd_x_preferred":[
        "\u06a9\u0648\u0679\u0644\u06c1 \u0645\u0648\u0633\u06cc\u0670 \u062e\u0627\u0646"
    ],
    "wof:name":"Kotla Musa Khan",
    "wof:placetype":"locality"
},
  "geometry": {"coordinates":[71.22154999999999,29.27425],"type":"Point"}
}