{
  "type": "Feature",
  "properties": {
    "gn:admin1_code":"3.0",
    "gn:asciiname":"Haji Jamal Din",
    "gn:country_code":"PK",
    "gn:dem":345,
    "gn:feature_class":"P",
    "gn:feature_code":"PPL",
    "gn:name":"Haji Jamal Din",
    "gn:population":0,
    "gn:timezone":"Asia/Karachi",
    "iso:country":"PK",
    "name:und_x_variant":[
        "Aslam Kh\u0101n Dheri",
        "Haji Jamal Din"
    ],
    "wof:name":"Haji Jamal Din",
    "wof:placetype":"locality"
},
  "geometry": {"coordinates":[71.70896999999999,34.27985],"type":"Point"}
}