{
  "type": "Feature",
  "properties": {
    "gn:admin1_code":"2.0",
    "gn:asciiname":"Lashtai",
    "gn:country_code":"PK",
    "gn:dem":2168,
    "gn:feature_class":"P",
    "gn:feature_code":"PPL",
    "gn:name":"Lashtai",
    "gn:population":0,
    "gn:timezone":"Asia/Karachi",
    "iso:country":"PK",
    "wof:name":"Lashtai",
    "wof:placetype":"locality"
},
  "geometry": {"coordinates":[66.49840999999999,30.66695],"type":"Point"}
}