{
  "type": "Feature",
  "properties": {
    "gn:admin1_code":"2.0",
    "gn:asciiname":"Rustam Khan Rajwani Jamali",
    "gn:country_code":"PK",
    "gn:dem":64,
    "gn:feature_class":"P",
    "gn:feature_code":"PPL",
    "gn:name":"Rustam Khan Rajwani Jamali",
    "gn:population":0,
    "gn:timezone":"Asia/Karachi",
    "iso:country":"PK",
    "wof:name":"Rustam Khan Rajwani Jamali",
    "wof:placetype":"locality"
},
  "geometry": {"coordinates":[68.19046999999999,28.49199],"type":"Point"}
}