{
  "type": "Feature",
  "properties": {
    "gn:admin1_code":"7.0",
    "gn:asciiname":"Khara Khata",
    "gn:country_code":"PK",
    "gn:dem":3195,
    "gn:feature_class":"P",
    "gn:feature_code":"PPL",
    "gn:name":"Khara Khata",
    "gn:population":0,
    "gn:timezone":"Asia/Karachi",
    "iso:country":"PK",
    "wof:name":"Khara Khata",
    "wof:placetype":"locality"
},
  "geometry": {"coordinates":[74.04363000000002,35.88997],"type":"Point"}
}