{
  "type": "Feature",
  "properties": {
    "gn:admin1_code":"4",
    "gn:asciiname":"Chak Fourteen A South Branch",
    "gn:country_code":"PK",
    "gn:dem":190,
    "gn:feature_class":"P",
    "gn:feature_code":"PPL",
    "gn:name":"Chak Fourteen A South Branch",
    "gn:population":0,
    "gn:timezone":"Asia/Karachi",
    "iso:country":"PK",
    "name:und_x_variant":[
        "Ris\u0101la"
    ],
    "wof:name":"Chak Fourteen A South Branch",
    "wof:placetype":"locality"
},
  "geometry": {"coordinates":[72.81586,32.15176],"type":"Point"}
}