{
  "type": "Feature",
  "properties": {
    "gn:admin1_code":"4",
    "gn:asciiname":"Basti Bakhtawar",
    "gn:country_code":"PK",
    "gn:dem":163,
    "gn:feature_class":"P",
    "gn:feature_code":"PPL",
    "gn:name":"Basti Bakhtawar",
    "gn:population":0,
    "gn:timezone":"Asia/Karachi",
    "iso:country":"PK",
    "name:und_x_variant":[
        "Bakht\u0101war Basti",
        "Basti Bakhtawar"
    ],
    "wof:name":"Basti Bakhtawar",
    "wof:placetype":"locality"
},
  "geometry": {"coordinates":[70.94105999999999,31.46463],"type":"Point"}
}