{
  "type": "Feature",
  "properties": {
    "gn:admin1_code":"3.0",
    "gn:asciiname":"Bachoi",
    "gn:country_code":"PK",
    "gn:dem":2094,
    "gn:feature_class":"P",
    "gn:feature_code":"PPL",
    "gn:name":"Bachoi",
    "gn:population":0,
    "gn:timezone":"Asia/Karachi",
    "iso:country":"PK",
    "wof:name":"Bachoi",
    "wof:placetype":"locality"
},
  "geometry": {"coordinates":[73.62690000000001,35.42993],"type":"Point"}
}