{
  "type": "Feature",
  "properties": {
    "gn:admin1_code":"6.0",
    "gn:asciiname":"Dhan",
    "gn:country_code":"PK",
    "gn:dem":959,
    "gn:feature_class":"P",
    "gn:feature_code":"PPL",
    "gn:name":"Dhan",
    "gn:population":0,
    "gn:timezone":"Asia/Karachi",
    "iso:country":"PK",
    "wof:name":"Dhan",
    "wof:placetype":"locality"
},
  "geometry": {"coordinates":[73.66320999999998,33.7471],"type":"Point"}
}