{
  "type": "Feature",
  "properties": {
    "gn:admin1_code":"4",
    "gn:asciiname":"Chak One Hundred Sixty-one -Ten Right A",
    "gn:country_code":"PK",
    "gn:dem":129,
    "gn:feature_class":"P",
    "gn:feature_code":"PPL",
    "gn:name":"Chak One Hundred Sixty-one -Ten Right A",
    "gn:population":0,
    "gn:timezone":"Asia/Karachi",
    "iso:country":"PK",
    "name:und_x_variant":[
        "Chak One Hundred Sixty-One A-Ten R"
    ],
    "wof:name":"Chak One Hundred Sixty-one -Ten Right A",
    "wof:placetype":"locality"
},
  "geometry": {"coordinates":[71.86926,30.17566],"type":"Point"}
}