{
  "type": "Feature",
  "properties": {
    "gn:admin1_code":"4",
    "gn:asciiname":"Basti Charohanwala",
    "gn:country_code":"PK",
    "gn:dem":151,
    "gn:feature_class":"P",
    "gn:feature_code":"PPL",
    "gn:name":"Basti Charohanwala",
    "gn:population":0,
    "gn:timezone":"Asia/Karachi",
    "iso:country":"PK",
    "name:und_x_variant":[
        "Rogr\u012bw\u0101la",
        "Basti Charoh\u0101nw\u0101li",
        "Basti Charohanwala"
    ],
    "wof:name":"Basti Charohanwala",
    "wof:placetype":"locality"
},
  "geometry": {"coordinates":[70.97261999999998,31.1155],"type":"Point"}
}