{
  "type": "Feature",
  "properties": {
    "gn:admin1_code":"4",
    "gn:asciiname":"Chahran",
    "gn:country_code":"PK",
    "gn:dem":698,
    "gn:feature_class":"P",
    "gn:feature_code":"PPL",
    "gn:name":"Chahran",
    "gn:population":0,
    "gn:timezone":"Asia/Karachi",
    "iso:country":"PK",
    "wof:name":"Chahran",
    "wof:placetype":"locality"
},
  "geometry": {"coordinates":[72.09999999999999,32.44167],"type":"Point"}
}