{
  "type": "Feature",
  "properties": {
    "gn:admin1_code":"2.0",
    "gn:asciiname":"Kando",
    "gn:country_code":"PK",
    "gn:dem":939,
    "gn:feature_class":"P",
    "gn:feature_code":"PPL",
    "gn:name":"Kando",
    "gn:population":0,
    "gn:timezone":"Asia/Karachi",
    "iso:country":"PK",
    "name:ceb_x_preferred":[
        "Kando"
    ],
    "name:deu_x_preferred":[
        "Kando"
    ],
    "name:fra_x_preferred":[
        "Kando"
    ],
    "name:swe_x_preferred":[
        "Kando"
    ],
    "wof:name":"Kando",
    "wof:placetype":"locality"
},
  "geometry": {"coordinates":[63.01653,26.47301],"type":"Point"}
}