{
  "type": "Feature",
  "properties": {
    "gn:admin1_code":"2.0",
    "gn:asciiname":"Shah Muhammad Kili",
    "gn:country_code":"PK",
    "gn:dem":2012,
    "gn:feature_class":"P",
    "gn:feature_code":"PPL",
    "gn:name":"Shah Muhammad Kili",
    "gn:population":0,
    "gn:timezone":"Asia/Karachi",
    "iso:country":"PK",
    "wof:name":"Shah Muhammad Kili",
    "wof:placetype":"locality"
},
  "geometry": {"coordinates":[68.93422,31.12651],"type":"Point"}
}