{
  "type": "Feature",
  "properties": {
    "gn:admin1_code":"5.0",
    "gn:asciiname":"Arbab Khan Unar",
    "gn:country_code":"PK",
    "gn:dem":45,
    "gn:feature_class":"P",
    "gn:feature_code":"PPL",
    "gn:name":"Arbab Khan Unar",
    "gn:population":0,
    "gn:timezone":"Asia/Karachi",
    "iso:country":"PK",
    "wof:name":"Arbab Khan Unar",
    "wof:placetype":"locality"
},
  "geometry": {"coordinates":[68.34039,26.69409000000001],"type":"Point"}
}