{
  "type": "Feature",
  "properties": {
    "gn:admin1_code":"4",
    "gn:asciiname":"Chak Forty-one-Fifteen Left",
    "gn:country_code":"PK",
    "gn:dem":154,
    "gn:feature_class":"P",
    "gn:feature_code":"PPL",
    "gn:name":"Chak Forty-one-Fifteen Left",
    "gn:population":0,
    "gn:timezone":"Asia/Karachi",
    "iso:country":"PK",
    "name:und_x_variant":[
        "Chak Forty-one A-Fifteen"
    ],
    "wof:name":"Chak Forty-one-Fifteen Left",
    "wof:placetype":"locality"
},
  "geometry": {"coordinates":[72.44356999999999,30.52669],"type":"Point"}
}