{
  "type": "Feature",
  "properties": {
    "gn:admin1_code":"4.0",
    "gn:asciiname":"Hawai Adda",
    "gn:country_code":"PK",
    "gn:dem":123,
    "gn:feature_class":"P",
    "gn:feature_code":"PPL",
    "gn:name":"Hawai Adda",
    "gn:population":0,
    "gn:timezone":"Asia/Karachi",
    "iso:country":"PK",
    "name:eng_x_preferred":[
        "Hawai Adda"
    ],
    "wof:name":"Hawai Adda",
    "wof:placetype":"locality"
},
  "geometry": {"coordinates":[71.84121,29.81],"type":"Point"}
}