{
  "type": "Feature",
  "properties": {
    "gn:admin1_code":"6",
    "gn:asciiname":"Kuthian",
    "gn:country_code":"PK",
    "gn:dem":941,
    "gn:feature_class":"P",
    "gn:feature_code":"PPL",
    "gn:name":"Kuthian",
    "gn:population":0,
    "gn:timezone":"Asia/Karachi",
    "iso:country":"PK",
    "name:und_x_variant":[
        "Kothi",
        "Kothi\u0101n"
    ],
    "wof:name":"Kuthian",
    "wof:placetype":"locality"
},
  "geometry": {"coordinates":[73.94811,33.50416],"type":"Point"}
}