{
  "type": "Feature",
  "properties": {
    "gn:admin1_code":"2.0",
    "gn:asciiname":"Rasul Bakhsh Chhutto",
    "gn:country_code":"PK",
    "gn:dem":1418,
    "gn:feature_class":"P",
    "gn:feature_code":"PPL",
    "gn:name":"Rasul Bakhsh Chhutto",
    "gn:population":0,
    "gn:timezone":"Asia/Karachi",
    "iso:country":"PK",
    "wof:name":"Rasul Bakhsh Chhutto",
    "wof:placetype":"locality"
},
  "geometry": {"coordinates":[67.17549,27.44962],"type":"Point"}
}