{
  "type": "Feature",
  "properties": {
    "gn:admin1_code":"5",
    "gn:asciiname":"Goth Atta Hussain",
    "gn:country_code":"PK",
    "gn:dem":19,
    "gn:feature_class":"P",
    "gn:feature_code":"PPL",
    "gn:name":"Goth Atta Hussain",
    "gn:population":0,
    "gn:timezone":"Asia/Karachi",
    "iso:country":"PK",
    "name:und_x_variant":[
        "H\u0101fiz R\u0101jar"
    ],
    "wof:name":"Goth Atta Hussain",
    "wof:placetype":"locality"
},
  "geometry": {"coordinates":[69.09090999999999,25.84012],"type":"Point"}
}