{
  "type": "Feature",
  "properties": {
    "gn:admin1_code":"02",
    "gn:asciiname":"Nathwani",
    "gn:country_code":"PK",
    "gn:dem":1379,
    "gn:feature_class":"P",
    "gn:feature_code":"PPL",
    "gn:name":"Nathwani",
    "gn:population":0,
    "gn:timezone":"Asia/Karachi",
    "iso:country":"PK",
    "name:und_x_variant":[
        "Notani",
        "Nuti\u0101ni",
        "Noti\u0101ni",
        "Nathwani"
    ],
    "wof:name":"Nathwani",
    "wof:placetype":"locality"
},
  "geometry": {"coordinates":[66.54241999999999,27.97796],"type":"Point"}
}