{
  "type": "Feature",
  "properties": {
    "gn:admin1_code":"2.0",
    "gn:asciiname":"Karani Kach",
    "gn:country_code":"PK",
    "gn:dem":1747,
    "gn:feature_class":"P",
    "gn:feature_code":"PPL",
    "gn:name":"Kar\u0101ni Kach",
    "gn:population":0,
    "gn:timezone":"Asia/Karachi",
    "iso:country":"PK",
    "wof:name":"Karani Kach",
    "wof:placetype":"locality"
},
  "geometry": {"coordinates":[67.43569000000001,30.28264],"type":"Point"}
}