{
  "type": "Feature",
  "properties": {
    "gn:admin1_code":"5.0",
    "gn:asciiname":"Faiz Muhammad Khosa",
    "gn:country_code":"PK",
    "gn:dem":64,
    "gn:feature_class":"P",
    "gn:feature_code":"PPL",
    "gn:name":"Faiz Muhammad Khosa",
    "gn:population":0,
    "gn:timezone":"Asia/Karachi",
    "iso:country":"PK",
    "wof:name":"Faiz Muhammad Khosa",
    "wof:placetype":"locality"
},
  "geometry": {"coordinates":[68.85884,28.38373],"type":"Point"}
}