{
  "type": "Feature",
  "properties": {
    "gn:admin1_code":"3.0",
    "gn:asciiname":"Sari Bang Galian",
    "gn:country_code":"PK",
    "gn:dem":1548,
    "gn:feature_class":"P",
    "gn:feature_code":"PPL",
    "gn:name":"Sari Bang Galian",
    "gn:population":0,
    "gn:timezone":"Asia/Karachi",
    "iso:country":"PK",
    "name:eng_x_preferred":[
        "Saribang"
    ],
    "wof:name":"Sari Bang Galian",
    "wof:placetype":"locality"
},
  "geometry": {"coordinates":[73.0938,33.89036],"type":"Point"}
}