{
  "type": "Feature",
  "properties": {
    "gn:admin1_code":"4",
    "gn:asciiname":"Chak Ninety-eight Dara Nawab Branch",
    "gn:country_code":"PK",
    "gn:dem":104,
    "gn:feature_class":"P",
    "gn:feature_code":"PPL",
    "gn:name":"Chak Ninety-eight Dara Nawab Branch",
    "gn:population":0,
    "gn:timezone":"Asia/Karachi",
    "iso:country":"PK",
    "name:und_x_variant":[
        "Chak 98 D N B"
    ],
    "wof:name":"Chak Ninety-eight Dara Nawab Branch",
    "wof:placetype":"locality"
},
  "geometry": {"coordinates":[71.27493,29.02713],"type":"Point"}
}