{
  "type": "Feature",
  "properties": {
    "gn:admin1_code":"2.0",
    "gn:asciiname":"Musa Bazar",
    "gn:country_code":"PK",
    "gn:dem":543,
    "gn:feature_class":"P",
    "gn:feature_code":"PPL",
    "gn:name":"Musa Bazar",
    "gn:population":0,
    "gn:timezone":"Asia/Karachi",
    "iso:country":"PK",
    "wof:name":"Musa Bazar",
    "wof:placetype":"locality"
},
  "geometry": {"coordinates":[64.47269,26.13463],"type":"Point"}
}