{
  "type": "Feature",
  "properties": {
    "gn:admin1_code":"4",
    "gn:asciiname":"Chak Doggar",
    "gn:country_code":"PK",
    "gn:dem":171,
    "gn:feature_class":"P",
    "gn:feature_code":"PPL",
    "gn:name":"Chak Doggar",
    "gn:population":0,
    "gn:timezone":"Asia/Karachi",
    "iso:country":"PK",
    "name:und_x_variant":[
        "Chak Dogar"
    ],
    "wof:name":"Chak Doggar",
    "wof:placetype":"locality"
},
  "geometry": {"coordinates":[73.6395,30.38446],"type":"Point"}
}