{
  "type": "Feature",
  "properties": {
    "gn:admin1_code":"5",
    "gn:asciiname":"Goth Inayat Shah",
    "gn:country_code":"PK",
    "gn:dem":19,
    "gn:feature_class":"P",
    "gn:feature_code":"PPL",
    "gn:name":"Goth Inayat Shah",
    "gn:population":0,
    "gn:timezone":"Asia/Karachi",
    "iso:country":"PK",
    "name:und_x_variant":[
        "Ch\u0101war"
    ],
    "wof:name":"Goth Inayat Shah",
    "wof:placetype":"locality"
},
  "geometry": {"coordinates":[68.9067,25.31183],"type":"Point"}
}