{
  "type": "Feature",
  "properties": {
    "gn:admin1_code":"03",
    "gn:asciiname":"Shamsi Khan",
    "gn:country_code":"PK",
    "gn:dem":867,
    "gn:feature_class":"P",
    "gn:feature_code":"PPL",
    "gn:name":"Shamsi Khan",
    "gn:population":0,
    "gn:timezone":"Asia/Karachi",
    "iso:country":"PK",
    "name:und_x_variant":[
        "Shamsh Khan",
        "Shamsi Khan"
    ],
    "wof:name":"Shamsi Khan",
    "wof:placetype":"locality"
},
  "geometry": {"coordinates":[71.84425999999998,34.73595],"type":"Point"}
}