{
  "type": "Feature",
  "properties": {
    "gn:admin1_code":"2.0",
    "gn:asciiname":"Kam Ziaba",
    "gn:country_code":"PK",
    "gn:dem":2266,
    "gn:feature_class":"P",
    "gn:feature_code":"PPL",
    "gn:name":"Kam Ziaba",
    "gn:population":0,
    "gn:timezone":"Asia/Karachi",
    "iso:country":"PK",
    "wof:name":"Kam Ziaba",
    "wof:placetype":"locality"
},
  "geometry": {"coordinates":[67.86704,31.45052],"type":"Point"}
}