{
  "type": "Feature",
  "properties": {
    "gn:admin1_code":"3",
    "gn:asciiname":"Banda Shahalian",
    "gn:country_code":"PK",
    "gn:dem":1145,
    "gn:feature_class":"P",
    "gn:feature_code":"PPL",
    "gn:name":"Banda Shahalian",
    "gn:population":0,
    "gn:timezone":"Asia/Karachi",
    "iso:country":"PK",
    "name:und_x_variant":[
        "B\u0101nda Shahli\u0101n"
    ],
    "wof:name":"Banda Shahalian",
    "wof:placetype":"locality"
},
  "geometry": {"coordinates":[73.26519,34.11562],"type":"Point"}
}