{
  "type": "Feature",
  "properties": {
    "gn:admin1_code":"5",
    "gn:asciiname":"Nur Kalhoro",
    "gn:country_code":"PK",
    "gn:dem":44,
    "gn:feature_class":"P",
    "gn:feature_code":"PPL",
    "gn:name":"Nur Kalhoro",
    "gn:population":0,
    "gn:timezone":"Asia/Karachi",
    "iso:country":"PK",
    "name:und_x_variant":[
        "Nuh Kalhoro"
    ],
    "wof:name":"Nur Kalhoro",
    "wof:placetype":"locality"
},
  "geometry": {"coordinates":[68.20394,26.82441],"type":"Point"}
}