{
  "type": "Feature",
  "properties": {
    "gn:admin1_code":"01",
    "gn:asciiname":"Sangrai",
    "gn:country_code":"PK",
    "gn:dem":1865,
    "gn:feature_class":"P",
    "gn:feature_code":"PPL",
    "gn:name":"Sangrai",
    "gn:population":0,
    "gn:timezone":"Asia/Karachi",
    "iso:country":"PK",
    "name:und_x_variant":[
        "Sang\u0101rai"
    ],
    "wof:name":"Sangrai",
    "wof:placetype":"locality"
},
  "geometry": {"coordinates":[69.55288,32.97131],"type":"Point"}
}