{
  "type": "Feature",
  "properties": {
    "gn:admin1_code":"5.0",
    "gn:asciiname":"Gadnai",
    "gn:country_code":"PK",
    "gn:dem":27,
    "gn:feature_class":"P",
    "gn:feature_code":"PPL",
    "gn:name":"Gadnai",
    "gn:population":0,
    "gn:timezone":"Asia/Karachi",
    "iso:country":"PK",
    "name:und_x_variant":[
        "Godn\u0101i"
    ],
    "wof:name":"Gadnai",
    "wof:placetype":"locality"
},
  "geometry": {"coordinates":[69.35101999999999,24.30431],"type":"Point"}
}