{
  "type": "Feature",
  "properties": {
    "gn:admin1_code":"01",
    "gn:asciiname":"Alam Khel Kas",
    "gn:country_code":"PK",
    "gn:dem":1884,
    "gn:feature_class":"P",
    "gn:feature_code":"PPL",
    "gn:name":"Alam Khel Kas",
    "gn:population":0,
    "gn:timezone":"Asia/Karachi",
    "iso:country":"PK",
    "name:und_x_variant":[
        "Alam Khel Kats",
        "Alam khel"
    ],
    "wof:name":"Alam Khel Kas",
    "wof:placetype":"locality"
},
  "geometry": {"coordinates":[70.72339000000002,33.78737],"type":"Point"}
}