{
  "type": "Feature",
  "properties": {
    "gn:admin1_code":"4.0",
    "gn:asciiname":"Chak Fifty-nine/Six Muhajir Branch",
    "gn:country_code":"PK",
    "gn:dem":188,
    "gn:feature_class":"P",
    "gn:feature_code":"PPL",
    "gn:name":"Chak Fifty-nine/Six Muhajir Branch",
    "gn:population":0,
    "gn:timezone":"Asia/Karachi",
    "iso:country":"PK",
    "name:und_x_variant":[
        "Chak MB 59/6"
    ],
    "wof:name":"Chak Fifty-nine/Six Muhajir Branch",
    "wof:placetype":"locality"
},
  "geometry": {"coordinates":[72.34260999999999,32.35153],"type":"Point"}
}