{
  "type": "Feature",
  "properties": {
    "gn:admin1_code":"2.0",
    "gn:asciiname":"Malik Baran Kili",
    "gn:country_code":"PK",
    "gn:dem":1570,
    "gn:feature_class":"P",
    "gn:feature_code":"PPL",
    "gn:name":"Malik Baran Kili",
    "gn:population":0,
    "gn:timezone":"Asia/Karachi",
    "iso:country":"PK",
    "name:und_x_variant":[
        "Mulla B\u0101r\u0101n Kahwa"
    ],
    "wof:name":"Malik Baran Kili",
    "wof:placetype":"locality"
},
  "geometry": {"coordinates":[68.25830000000001,30.7616],"type":"Point"}
}