{
  "type": "Feature",
  "properties": {
    "gn:admin1_code":"04",
    "gn:asciiname":"Basti Nurpur",
    "gn:country_code":"PK",
    "gn:dem":135,
    "gn:feature_class":"P",
    "gn:feature_code":"PPL",
    "gn:name":"Basti Nurpur",
    "gn:population":0,
    "gn:timezone":"Asia/Karachi",
    "iso:country":"PK",
    "name:und_x_variant":[
        "Noorpur",
        "N\u016brpur",
        "Basti Nurpur"
    ],
    "wof:name":"Basti Nurpur",
    "wof:placetype":"locality"
},
  "geometry": {"coordinates":[72.3736,29.78376],"type":"Point"}
}