{
  "type": "Feature",
  "properties": {
    "gn:admin1_code":"2.0",
    "gn:asciiname":"Gohrami",
    "gn:country_code":"PK",
    "gn:dem":1133,
    "gn:feature_class":"P",
    "gn:feature_code":"PPL",
    "gn:name":"Gohrami",
    "gn:population":0,
    "gn:timezone":"Asia/Karachi",
    "iso:country":"PK",
    "wof:name":"Gohrami",
    "wof:placetype":"locality"
},
  "geometry": {"coordinates":[64.81931,26.96632],"type":"Point"}
}