{
  "type": "Feature",
  "properties": {
    "gn:admin1_code":"4.0",
    "gn:asciiname":"Chak Eighty Gugera Branch",
    "gn:country_code":"PK",
    "gn:dem":183,
    "gn:feature_class":"P",
    "gn:feature_code":"PPL",
    "gn:name":"Chak Eighty Gugera Branch",
    "gn:population":0,
    "gn:timezone":"Asia/Karachi",
    "iso:country":"PK",
    "name:und_x_variant":[
        "Khush\u012bpur",
        "Chak Eighty GB",
        "Chak Eighty Gugera Branch"
    ],
    "wof:name":"Chak Eighty Gugera Branch",
    "wof:placetype":"locality"
},
  "geometry": {"coordinates":[73.14480999999998,31.26665],"type":"Point"}
}