{
  "type": "Feature",
  "properties": {
    "gn:admin1_code":"2.0",
    "gn:asciiname":"Kili Khadarnai",
    "gn:country_code":"PK",
    "gn:dem":1761,
    "gn:feature_class":"P",
    "gn:feature_code":"PPL",
    "gn:name":"Kili Khadarnai",
    "gn:population":0,
    "gn:timezone":"Asia/Karachi",
    "iso:country":"PK",
    "wof:name":"Kili Khadarnai",
    "wof:placetype":"locality"
},
  "geometry": {"coordinates":[66.47145999999999,29.58832],"type":"Point"}
}