{
  "type": "Feature",
  "properties": {
    "gn:admin1_code":"4.0",
    "gn:asciiname":"Saidabad",
    "gn:country_code":"PK",
    "gn:dem":130,
    "gn:feature_class":"P",
    "gn:feature_code":"PPL",
    "gn:name":"Saidabad",
    "gn:population":0,
    "gn:timezone":"Asia/Karachi",
    "iso:country":"PK",
    "name:eng_x_preferred":[
        "Saidabad"
    ],
    "name:fas_x_preferred":[
        "\u0633\u0639\u06cc\u062f\u0622\u0628\u0627\u062f"
    ],
    "name:urd_x_preferred":[
        "\u0633\u0639\u06cc\u062f \u0622\u0628\u0627\u062f"
    ],
    "wof:name":"Saidabad",
    "wof:placetype":"locality"
},
  "geometry": {"coordinates":[71.92614,29.95831],"type":"Point"}
}