{
  "type": "Feature",
  "properties": {
    "gn:admin1_code":"5",
    "gn:asciiname":"Khan Juneja",
    "gn:country_code":"PK",
    "gn:dem":51,
    "gn:feature_class":"P",
    "gn:feature_code":"PPL",
    "gn:name":"Khan Juneja",
    "gn:population":0,
    "gn:timezone":"Asia/Karachi",
    "iso:country":"PK",
    "name:und_x_variant":[
        "G\u0101he Kh\u0101n Juneja"
    ],
    "wof:name":"Khan Juneja",
    "wof:placetype":"locality"
},
  "geometry": {"coordinates":[68.08869,27.82219000000001],"type":"Point"}
}