{
  "type": "Feature",
  "properties": {
    "gn:admin1_code":"4.0",
    "gn:asciiname":"Tallan",
    "gn:country_code":"PK",
    "gn:dem":284,
    "gn:feature_class":"P",
    "gn:feature_code":"PPL",
    "gn:name":"Tallan",
    "gn:population":0,
    "gn:timezone":"Asia/Karachi",
    "iso:country":"PK",
    "wof:name":"Tallan",
    "wof:placetype":"locality"
},
  "geometry": {"coordinates":[75.0313,32.3674],"type":"Point"}
}