{
  "type": "Feature",
  "properties": {
    "gn:admin1_code":"7.0",
    "gn:asciiname":"Kiore",
    "gn:country_code":"PK",
    "gn:dem":2184,
    "gn:feature_class":"P",
    "gn:feature_code":"PPL",
    "gn:name":"Kiore",
    "gn:population":0,
    "gn:timezone":"Asia/Karachi",
    "iso:country":"PK",
    "wof:name":"Kiore",
    "wof:placetype":"locality"
},
  "geometry": {"coordinates":[75.36176999999998,35.48292],"type":"Point"}
}