{
  "type": "Feature",
  "properties": {
    "gn:admin1_code":"5",
    "gn:asciiname":"Goth Mir Allah Dad Talpur",
    "gn:country_code":"PK",
    "gn:dem":15,
    "gn:feature_class":"P",
    "gn:feature_code":"PPL",
    "gn:name":"Goth Mir Allah Dad Talpur",
    "gn:population":0,
    "gn:timezone":"Asia/Karachi",
    "iso:country":"PK",
    "name:und_x_variant":[
        "Goth M\u012br Im\u0101m Bakhsh T\u0101lpur"
    ],
    "wof:name":"Goth Mir Allah Dad Talpur",
    "wof:placetype":"locality"
},
  "geometry": {"coordinates":[69.14475999999999,25.35589],"type":"Point"}
}