{
  "type": "Feature",
  "properties": {
    "gn:admin1_code":"1",
    "gn:asciiname":"Malal Zhawar",
    "gn:country_code":"PK",
    "gn:dem":2163,
    "gn:feature_class":"P",
    "gn:feature_code":"PPLL",
    "gn:name":"Malal Zhawar",
    "gn:population":0,
    "gn:timezone":"Asia/Karachi",
    "iso:country":"PK",
    "name:und_x_variant":[
        "Malai Zh\u0101war",
        "Malal Zhawar"
    ],
    "wof:name":"Malal Zhawar",
    "wof:placetype":"locality"
},
  "geometry": {"coordinates":[69.86820999999999,32.74861],"type":"Point"}
}