{
  "type": "Feature",
  "properties": {
    "gn:admin1_code":"1.0",
    "gn:asciiname":"Shakli Khel",
    "gn:country_code":"PK",
    "gn:dem":2058,
    "gn:feature_class":"P",
    "gn:feature_code":"PPL",
    "gn:name":"Shakli Khel",
    "gn:population":0,
    "gn:timezone":"Asia/Karachi",
    "iso:country":"PK",
    "name:und_x_variant":[
        "Bada Kh\u0101n"
    ],
    "wof:name":"Shakli Khel",
    "wof:placetype":"locality"
},
  "geometry": {"coordinates":[70.76903,33.74391],"type":"Point"}
}