{
  "type": "Feature",
  "properties": {
    "gn:admin1_code":"4",
    "gn:asciiname":"Shahpur",
    "gn:country_code":"PK",
    "gn:dem":123,
    "gn:feature_class":"P",
    "gn:feature_code":"PPL",
    "gn:name":"Shahpur",
    "gn:population":0,
    "gn:timezone":"Asia/Karachi",
    "iso:country":"PK",
    "name:ben_x_preferred":[
        "\u09b6\u09be\u09b9\u09aa\u09c1\u09b0"
    ],
    "name:cat_x_preferred":[
        "Shapur"
    ],
    "name:eng_x_preferred":[
        "Shahpur"
    ],
    "name:nld_x_preferred":[
        "Shahpur"
    ],
    "name:pol_x_preferred":[
        "Shahpur"
    ],
    "name:por_x_preferred":[
        "Shahpur"
    ],
    "name:urd_x_preferred":[
        "\u0634\u0627\u06c1 \u067e\u0648\u0631"
    ],
    "wof:name":"Shahpur",
    "wof:placetype":"locality"
},
  "geometry": {"coordinates":[71.43838,30.04079],"type":"Point"}
}