{
  "type": "Feature",
  "properties": {
    "gn:admin1_code":"01",
    "gn:asciiname":"Taghuna",
    "gn:country_code":"PK",
    "gn:dem":1961,
    "gn:feature_class":"P",
    "gn:feature_code":"PPL",
    "gn:name":"Taghuna",
    "gn:population":0,
    "gn:timezone":"Asia/Karachi",
    "iso:country":"PK",
    "wof:name":"Taghuna",
    "wof:placetype":"locality"
},
  "geometry": {"coordinates":[70.49424999999999,33.81638],"type":"Point"}
}