{
  "type": "Feature",
  "properties": {
    "gn:admin1_code":"04",
    "gn:asciiname":"Chak Four Hundred Twenty-seven Jhang Branch",
    "gn:country_code":"PK",
    "gn:dem":161,
    "gn:feature_class":"P",
    "gn:feature_code":"PPL",
    "gn:name":"Chak Four Hundred Twenty-seven Jhang Branch",
    "gn:population":0,
    "gn:timezone":"Asia/Karachi",
    "iso:country":"PK",
    "name:und_x_variant":[
        "Musalmanian",
        "Musalm\u0101ni",
        "Chak Number Four Hundred Twenty-Seven",
        "Chak Four Hundred Twenty-seven Jhang Branch"
    ],
    "wof:name":"Chak Four Hundred Twenty-seven Jhang Branch",
    "wof:placetype":"locality"
},
  "geometry": {"coordinates":[72.52461,31.21205],"type":"Point"}
}