{
  "type": "Feature",
  "properties": {
    "gn:admin1_code":"5",
    "gn:asciiname":"Ali Bakhsh Sundrani",
    "gn:country_code":"PK",
    "gn:dem":66,
    "gn:feature_class":"P",
    "gn:feature_code":"PPL",
    "gn:name":"Ali Bakhsh Sundrani",
    "gn:population":0,
    "gn:timezone":"Asia/Karachi",
    "iso:country":"PK",
    "wof:name":"Ali Bakhsh Sundrani",
    "wof:placetype":"locality"
},
  "geometry": {"coordinates":[69.05139,28.10278],"type":"Point"}
}