{
  "type": "Feature",
  "properties": {
    "gn:admin1_code":"3.0",
    "gn:asciiname":"Shagai Kalle",
    "gn:country_code":"PK",
    "gn:dem":355,
    "gn:feature_class":"P",
    "gn:feature_code":"PPL",
    "gn:name":"Shagai Kalle",
    "gn:population":0,
    "gn:timezone":"Asia/Karachi",
    "iso:country":"PK",
    "wof:name":"Shagai Kalle",
    "wof:placetype":"locality"
},
  "geometry": {"coordinates":[71.79971999999999,34.27249],"type":"Point"}
}