{
  "type": "Feature",
  "properties": {
    "gn:admin1_code":"3.0",
    "gn:asciiname":"Baldher",
    "gn:country_code":"PK",
    "gn:dem":741,
    "gn:feature_class":"P",
    "gn:feature_code":"PPL",
    "gn:name":"Baldher",
    "gn:population":0,
    "gn:timezone":"Asia/Karachi",
    "iso:country":"PK",
    "wof:name":"Baldher",
    "wof:placetype":"locality"
},
  "geometry": {"coordinates":[73.09007,34.00519],"type":"Point"}
}