{
  "type": "Feature",
  "properties": {
    "gn:admin1_code":"3.0",
    "gn:asciiname":"Amrait",
    "gn:country_code":"PK",
    "gn:dem":2266,
    "gn:feature_class":"P",
    "gn:feature_code":"PPL",
    "gn:name":"Amrait",
    "gn:population":0,
    "gn:timezone":"Asia/Karachi",
    "iso:country":"PK",
    "wof:name":"Amrait",
    "wof:placetype":"locality"
},
  "geometry": {"coordinates":[72.14108,35.19253],"type":"Point"}
}