{
  "type": "Feature",
  "properties": {
    "gn:admin1_code":"3.0",
    "gn:asciiname":"Kachhi",
    "gn:country_code":"PK",
    "gn:dem":462,
    "gn:feature_class":"P",
    "gn:feature_code":"PPL",
    "gn:name":"Kachhi",
    "gn:population":0,
    "gn:timezone":"Asia/Karachi",
    "iso:country":"PK",
    "name:und_x_variant":[
        "Kachi",
        "Kachhi"
    ],
    "wof:name":"Kachhi",
    "wof:placetype":"locality"
},
  "geometry": {"coordinates":[72.9461,34.13078],"type":"Point"}
}