{
  "type": "Feature",
  "properties": {
    "gn:admin1_code":"3",
    "gn:asciiname":"Tiliala",
    "gn:country_code":"PK",
    "gn:dem":847,
    "gn:feature_class":"P",
    "gn:feature_code":"PPL",
    "gn:name":"Tiliala",
    "gn:population":0,
    "gn:timezone":"Asia/Karachi",
    "iso:country":"PK",
    "name:und_x_variant":[
        "Tilh\u0101la"
    ],
    "wof:name":"Tiliala",
    "wof:placetype":"locality"
},
  "geometry": {"coordinates":[73.05112,34.33327],"type":"Point"}
}