{
  "type": "Feature",
  "properties": {
    "gn:admin1_code":"4.0",
    "gn:asciiname":"Hamid Kot",
    "gn:country_code":"PK",
    "gn:dem":109,
    "gn:feature_class":"P",
    "gn:feature_code":"PPL",
    "gn:name":"Hamid Kot",
    "gn:population":0,
    "gn:timezone":"Asia/Karachi",
    "iso:country":"PK",
    "name:und_x_variant":[
        "Ham\u012bdw\u0101la"
    ],
    "wof:name":"Hamid Kot",
    "wof:placetype":"locality"
},
  "geometry": {"coordinates":[70.60296,29.70132000000001],"type":"Point"}
}