{
  "type": "Feature",
  "properties": {
    "gn:admin1_code":"4",
    "gn:asciiname":"Rahimeke Uttar",
    "gn:country_code":"PK",
    "gn:dem":194,
    "gn:feature_class":"P",
    "gn:feature_code":"PPL",
    "gn:name":"Rahimeke Uttar",
    "gn:population":0,
    "gn:timezone":"Asia/Karachi",
    "iso:country":"PK",
    "wof:name":"Rahimeke Uttar",
    "wof:placetype":"locality"
},
  "geometry": {"coordinates":[74.44444,30.89306],"type":"Point"}
}