{
  "type": "Feature",
  "properties": {
    "gn:admin1_code":"06",
    "gn:asciiname":"Kurhla",
    "gn:country_code":"PK",
    "gn:dem":292,
    "gn:feature_class":"P",
    "gn:feature_code":"PPL",
    "gn:name":"Kurhla",
    "gn:population":0,
    "gn:timezone":"Asia/Karachi",
    "iso:country":"PK",
    "name:und_x_variant":[
        "Korlah",
        "Kurhla"
    ],
    "wof:name":"Kurhla",
    "wof:placetype":"locality"
},
  "geometry": {"coordinates":[73.58622,33.06189000000001],"type":"Point"}
}