{
  "type": "Feature",
  "properties": {
    "gn:admin1_code":"5.0",
    "gn:asciiname":"Purana Khobbar",
    "gn:country_code":"PK",
    "gn:dem":47,
    "gn:feature_class":"P",
    "gn:feature_code":"PPL",
    "gn:name":"Purana Khobbar",
    "gn:population":0,
    "gn:timezone":"Asia/Karachi",
    "iso:country":"PK",
    "name:und_x_variant":[
        "Pur\u0101na Khabbar"
    ],
    "wof:name":"Purana Khobbar",
    "wof:placetype":"locality"
},
  "geometry": {"coordinates":[67.81801,27.72604],"type":"Point"}
}