{
  "type": "Feature",
  "properties": {
    "gn:admin1_code":"2.0",
    "gn:asciiname":"Shaharwa",
    "gn:country_code":"PK",
    "gn:dem":1291,
    "gn:feature_class":"P",
    "gn:feature_code":"PPL",
    "gn:name":"Shaharwa",
    "gn:population":0,
    "gn:timezone":"Asia/Karachi",
    "iso:country":"PK",
    "wof:name":"Shaharwa",
    "wof:placetype":"locality"
},
  "geometry": {"coordinates":[66.68649000000001,28.12521],"type":"Point"}
}