{
  "type": "Feature",
  "properties": {
    "gn:admin1_code":"5.0",
    "gn:asciiname":"Wahidabad",
    "gn:country_code":"PK",
    "gn:dem":66,
    "gn:feature_class":"P",
    "gn:feature_code":"PPL",
    "gn:name":"Wahidabad",
    "gn:population":0,
    "gn:timezone":"Asia/Karachi",
    "iso:country":"PK",
    "name:eng_x_preferred":[
        "Wahidabad"
    ],
    "name:urd_x_preferred":[
        "\u0648\u062d\u06cc\u062f \u0622\u0628\u0627\u062f"
    ],
    "wof:name":"Wahidabad",
    "wof:placetype":"locality"
},
  "geometry": {"coordinates":[68.60453,28.05224],"type":"Point"}
}