{
  "type": "Feature",
  "properties": {
    "gn:admin1_code":"2.0",
    "gn:asciiname":"Jafarabad",
    "gn:country_code":"PK",
    "gn:dem":54,
    "gn:feature_class":"P",
    "gn:feature_code":"PPL",
    "gn:name":"Jafarabad",
    "gn:population":0,
    "gn:timezone":"Asia/Karachi",
    "iso:country":"PK",
    "name:ara_x_preferred":[
        "\u062c\u0639\u0641\u0631 \u0622\u0628\u0627\u062f"
    ],
    "name:azb_x_preferred":[
        "\u062c\u0639\u0641\u0631\u0622\u0628\u0627\u062f"
    ],
    "name:fas_x_preferred":[
        "\u062c\u0639\u0641\u0631\u0622\u0628\u0627\u062f"
    ],
    "name:mzn_x_preferred":[
        "\u062c\u0639\u0641\u0631\u0622\u0628\u0627\u062f"
    ],
    "name:pol_x_preferred":[
        "Jafarabad"
    ],
    "name:rus_x_preferred":[
        "\u0414\u0436\u0430\u0444\u0430\u0440\u0430\u0431\u0430\u0434"
    ],
    "name:und_x_variant":[
        "Qab\u016bla"
    ],
    "wof:name":"Jafarabad",
    "wof:placetype":"locality"
},
  "geometry": {"coordinates":[67.88476999999999,28.15615],"type":"Point"}
}