{
  "type": "Feature",
  "properties": {
    "gn:admin1_code":"2.0",
    "gn:asciiname":"Jafarabad",
    "gn:country_code":"PK",
    "gn:dem":54,
    "gn:feature_class":"P",
    "gn:feature_code":"PPL",
    "gn:name":"Jafarabad",
    "gn:population":0,
    "gn:timezone":"Asia/Karachi",
    "iso:country":"PK",
    "name:und_x_variant":[
        "Qab\u016bla",
        "Jafarabad"
    ],
    "wof:name":"Jafarabad",
    "wof:placetype":"locality"
},
  "geometry": {"coordinates":[67.88476999999999,28.15615],"type":"Point"}
}