{
  "type": "Feature",
  "properties": {
    "gn:admin1_code":"1.0",
    "gn:asciiname":"Sadatabad",
    "gn:country_code":"PK",
    "gn:dem":1497,
    "gn:feature_class":"P",
    "gn:feature_code":"PPL",
    "gn:name":"Sadatabad",
    "gn:population":0,
    "gn:timezone":"Asia/Karachi",
    "iso:country":"PK",
    "name:fas_x_preferred":[
        "\u0633\u0627\u062f\u0627\u062a\u200c\u0622\u0628\u0627\u062f"
    ],
    "name:und_x_variant":[
        "Nara Kili",
        "Nari Kili",
        "Sadatabad"
    ],
    "wof:name":"Sadatabad",
    "wof:placetype":"locality"
},
  "geometry": {"coordinates":[70.03019,33.82921],"type":"Point"}
}