{
  "type": "Feature",
  "properties": {
    "gn:admin1_code":"7.0",
    "gn:asciiname":"Shah Sultan",
    "gn:country_code":"PK",
    "gn:dem":3446,
    "gn:feature_class":"P",
    "gn:feature_code":"PPL",
    "gn:name":"Shah Sultan",
    "gn:population":0,
    "gn:timezone":"Asia/Karachi",
    "iso:country":"PK",
    "wof:name":"Shah Sultan",
    "wof:placetype":"locality"
},
  "geometry": {"coordinates":[76.08587,35.41476],"type":"Point"}
}