{
  "type": "Feature",
  "properties": {
    "gn:admin1_code":"6",
    "gn:asciiname":"Tahi",
    "gn:country_code":"PK",
    "gn:dem":739,
    "gn:feature_class":"P",
    "gn:feature_code":"PPL",
    "gn:name":"Tahi",
    "gn:population":0,
    "gn:timezone":"Asia/Karachi",
    "iso:country":"PK",
    "name:ceb_x_preferred":[
        "Tahi"
    ],
    "name:deu_x_preferred":[
        "Tahi"
    ],
    "name:swe_x_preferred":[
        "Tahi"
    ],
    "wof:name":"Tahi",
    "wof:placetype":"locality"
},
  "geometry": {"coordinates":[73.95520999999999,33.62925],"type":"Point"}
}