{
  "type": "Feature",
  "properties": {
    "gn:admin1_code":"4",
    "gn:asciiname":"Ditta Sandilawala",
    "gn:country_code":"PK",
    "gn:dem":145,
    "gn:feature_class":"P",
    "gn:feature_code":"PPL",
    "gn:name":"Ditta Sandil\u0101w\u0101la",
    "gn:population":0,
    "gn:timezone":"Asia/Karachi",
    "iso:country":"PK",
    "wof:name":"Ditta Sandilawala",
    "wof:placetype":"locality"
},
  "geometry": {"coordinates":[71.60694000000002,30.81111],"type":"Point"}
}