{
  "type": "Feature",
  "properties": {
    "gn:admin1_code":"2.0",
    "gn:asciiname":"Karimdadzai",
    "gn:country_code":"PK",
    "gn:dem":1183,
    "gn:feature_class":"P",
    "gn:feature_code":"PPL",
    "gn:name":"Karimdadzai",
    "gn:population":0,
    "gn:timezone":"Asia/Karachi",
    "iso:country":"PK",
    "wof:name":"Karimdadzai",
    "wof:placetype":"locality"
},
  "geometry": {"coordinates":[66.26738,27.6455],"type":"Point"}
}