{
  "type": "Feature",
  "properties": {
    "gn:admin1_code":"3",
    "gn:asciiname":"Naranjpura",
    "gn:country_code":"PK",
    "gn:dem":1433,
    "gn:feature_class":"P",
    "gn:feature_code":"PPL",
    "gn:name":"Naranjpura",
    "gn:population":0,
    "gn:timezone":"Asia/Karachi",
    "iso:country":"PK",
    "wof:name":"Naranjpura",
    "wof:placetype":"locality"
},
  "geometry": {"coordinates":[72.32876,34.88216],"type":"Point"}
}