{
  "type": "Feature",
  "properties": {
    "gn:admin1_code":"4.0",
    "gn:asciiname":"Dhok Sadr",
    "gn:country_code":"PK",
    "gn:dem":527,
    "gn:feature_class":"P",
    "gn:feature_code":"PPL",
    "gn:name":"Dhok Sadr",
    "gn:population":0,
    "gn:timezone":"Asia/Karachi",
    "iso:country":"PK",
    "name:und_x_variant":[
        "Dhok S\u0101det"
    ],
    "wof:name":"Dhok Sadr",
    "wof:placetype":"locality"
},
  "geometry": {"coordinates":[72.14589000000002,32.78879000000001],"type":"Point"}
}