{
  "type": "Feature",
  "properties": {
    "gn:admin1_code":"4",
    "gn:asciiname":"Chak One Hundred Fifty-eight -Ten Right",
    "gn:country_code":"PK",
    "gn:dem":133,
    "gn:feature_class":"P",
    "gn:feature_code":"PPL",
    "gn:name":"Chak One Hundred Fifty-eight -Ten Right",
    "gn:population":0,
    "gn:timezone":"Asia/Karachi",
    "iso:country":"PK",
    "name:und_x_variant":[
        "Chak One Hundred Fifty-Eight",
        "Kot Haibat Kh\u0101n",
        "Chak One Hundred Fifty-eight -Ten Right"
    ],
    "wof:name":"Chak One Hundred Fifty-eight -Ten Right",
    "wof:placetype":"locality"
},
  "geometry": {"coordinates":[71.84908,30.15867],"type":"Point"}
}