{
  "type": "Feature",
  "properties": {
    "gn:admin1_code":"5",
    "gn:asciiname":"Goth Hamal Kaloi",
    "gn:country_code":"PK",
    "gn:dem":38,
    "gn:feature_class":"P",
    "gn:feature_code":"PPL",
    "gn:name":"Goth Hamal Kaloi",
    "gn:population":0,
    "gn:timezone":"Asia/Karachi",
    "iso:country":"PK",
    "name:und_x_variant":[
        "Hamal Kailoi"
    ],
    "wof:name":"Goth Hamal Kaloi",
    "wof:placetype":"locality"
},
  "geometry": {"coordinates":[68.04791,26.37827],"type":"Point"}
}