{
  "type": "Feature",
  "properties": {
    "gn:admin1_code":"6",
    "gn:asciiname":"Dhuli Upper",
    "gn:country_code":"PK",
    "gn:dem":1702,
    "gn:feature_class":"P",
    "gn:feature_code":"PPL",
    "gn:name":"Dhuli Upper",
    "gn:population":0,
    "gn:timezone":"Asia/Karachi",
    "iso:country":"PK",
    "name:und_x_variant":[
        "Dh\u016bli"
    ],
    "wof:name":"Dhuli Upper",
    "wof:placetype":"locality"
},
  "geometry": {"coordinates":[73.92322,33.9332],"type":"Point"}
}