{
  "type": "Feature",
  "properties": {
    "gn:admin1_code":"4.0",
    "gn:asciiname":"Chak One Hundred Seventy-three",
    "gn:country_code":"PK",
    "gn:dem":160,
    "gn:feature_class":"P",
    "gn:feature_code":"PPL",
    "gn:name":"Chak One Hundred Seventy-three",
    "gn:population":0,
    "gn:timezone":"Asia/Karachi",
    "iso:country":"PK",
    "name:eng_x_preferred":[
        "Chak One Hundred Seventy-three"
    ],
    "name:und_x_variant":[
        "Khairew\u0101li Jhok",
        "Kuriw\u0101li Jhok"
    ],
    "wof:name":"Chak One Hundred Seventy-three",
    "wof:placetype":"locality"
},
  "geometry": {"coordinates":[72.49908000000001,31.35449],"type":"Point"}
}