{
  "type": "Feature",
  "properties": {
    "gn:admin1_code":"4",
    "gn:asciiname":"Basti Ahmed Malik",
    "gn:country_code":"PK",
    "gn:dem":77,
    "gn:feature_class":"P",
    "gn:feature_code":"PPL",
    "gn:name":"Basti Ahmed Malik",
    "gn:population":0,
    "gn:timezone":"Asia/Karachi",
    "iso:country":"PK",
    "name:und_x_variant":[
        "Ahmad Kosh"
    ],
    "wof:name":"Basti Ahmed Malik",
    "wof:placetype":"locality"
},
  "geometry": {"coordinates":[69.83391999999999,28.38383],"type":"Point"}
}