{
  "type": "Feature",
  "properties": {
    "gn:admin1_code":"2",
    "gn:asciiname":"Gambat",
    "gn:country_code":"PK",
    "gn:dem":102,
    "gn:feature_class":"P",
    "gn:feature_code":"PPL",
    "gn:name":"Gambat",
    "gn:population":0,
    "gn:timezone":"Asia/Karachi",
    "iso:country":"PK",
    "name:fas_x_preferred":[
        "\u06af\u0645\u0628\u062a"
    ],
    "name:ita_x_preferred":[
        "Gambat"
    ],
    "name:snd_x_preferred":[
        "\u06af\u0645\u0628\u067d \u062a\u0639\u0644\u0642\u0648"
    ],
    "name:spa_x_preferred":[
        "Gambat"
    ],
    "name:urd_x_preferred":[
        "\u06af\u0645\u0628\u0679"
    ],
    "wof:name":"Gambat",
    "wof:placetype":"locality"
},
  "geometry": {"coordinates":[67.91526999999999,29.13308],"type":"Point"}
}