{
  "type": "Feature",
  "properties": {
    "gn:admin1_code":"5.0",
    "gn:asciiname":"Aulu ji Veri",
    "gn:country_code":"PK",
    "gn:dem":74,
    "gn:feature_class":"P",
    "gn:feature_code":"PPL",
    "gn:name":"Aulu ji Veri",
    "gn:population":0,
    "gn:timezone":"Asia/Karachi",
    "iso:country":"PK",
    "name:und_x_variant":[
        "\u0100lu ji Veri"
    ],
    "wof:name":"Aulu ji Veri",
    "wof:placetype":"locality"
},
  "geometry": {"coordinates":[70.78761,24.77017],"type":"Point"}
}