{
  "type": "Feature",
  "properties": {
    "gn:admin1_code":"1.0",
    "gn:asciiname":"Khanan Garhi",
    "gn:country_code":"PK",
    "gn:dem":1188,
    "gn:feature_class":"P",
    "gn:feature_code":"PPL",
    "gn:name":"Khanan Garhi",
    "gn:population":0,
    "gn:timezone":"Asia/Karachi",
    "iso:country":"PK",
    "wof:name":"Khanan Garhi",
    "wof:placetype":"locality"
},
  "geometry": {"coordinates":[71.08022,33.71072],"type":"Point"}
}