{
  "type": "Feature",
  "properties": {
    "gn:admin1_code":"4",
    "gn:asciiname":"Hataranwala Janubi",
    "gn:country_code":"PK",
    "gn:dem":190,
    "gn:feature_class":"P",
    "gn:feature_code":"PPL",
    "gn:name":"Hataranwala Janubi",
    "gn:population":0,
    "gn:timezone":"Asia/Karachi",
    "iso:country":"PK",
    "name:und_x_variant":[
        "Hat\u0101r\u0101n"
    ],
    "wof:name":"Hataranwala Janubi",
    "wof:placetype":"locality"
},
  "geometry": {"coordinates":[71.28716999999997,32.00963],"type":"Point"}
}