{
  "type": "Feature",
  "properties": {
    "gn:admin1_code":"4.0",
    "gn:asciiname":"Jhanda",
    "gn:country_code":"PK",
    "gn:dem":257,
    "gn:feature_class":"P",
    "gn:feature_code":"PPL",
    "gn:name":"Jhanda",
    "gn:population":0,
    "gn:timezone":"Asia/Karachi",
    "iso:country":"PK",
    "wof:name":"Jhanda",
    "wof:placetype":"locality"
},
  "geometry": {"coordinates":[75.28333000000001,32.21667],"type":"Point"}
}