{
  "type": "Feature",
  "properties": {
    "gn:admin1_code":"4",
    "gn:asciiname":"Kotli Lala",
    "gn:country_code":"PK",
    "gn:dem":262,
    "gn:feature_class":"P",
    "gn:feature_code":"PPL",
    "gn:name":"Kotli Lala",
    "gn:population":0,
    "gn:timezone":"Asia/Karachi",
    "iso:country":"PK",
    "wof:name":"Kotli Lala",
    "wof:placetype":"locality"
},
  "geometry": {"coordinates":[74.7407,32.45391],"type":"Point"}
}