{
  "type": "Feature",
  "properties": {
    "gn:admin1_code":"2.0",
    "gn:asciiname":"Razai Khan Baluch",
    "gn:country_code":"PK",
    "gn:dem":1109,
    "gn:feature_class":"P",
    "gn:feature_code":"PPL",
    "gn:name":"Razai Khan Baluch",
    "gn:population":0,
    "gn:timezone":"Asia/Karachi",
    "iso:country":"PK",
    "wof:name":"Razai Khan Baluch",
    "wof:placetype":"locality"
},
  "geometry": {"coordinates":[68.54643,30.17334],"type":"Point"}
}