{
  "type": "Feature",
  "properties": {
    "gn:admin1_code":"2.0",
    "gn:asciiname":"Goth Ramzan",
    "gn:country_code":"PK",
    "gn:dem":439,
    "gn:feature_class":"P",
    "gn:feature_code":"PPL",
    "gn:name":"Goth Ramzan",
    "gn:population":0,
    "gn:timezone":"Asia/Karachi",
    "iso:country":"PK",
    "wof:name":"Goth Ramzan",
    "wof:placetype":"locality"
},
  "geometry": {"coordinates":[66.89734,25.91743],"type":"Point"}
}