{
  "type": "Feature",
  "properties": {
    "gn:admin1_code":"3.0",
    "gn:asciiname":"Ghurdarra",
    "gn:country_code":"PK",
    "gn:dem":990,
    "gn:feature_class":"P",
    "gn:feature_code":"PPL",
    "gn:name":"Ghurdarra",
    "gn:population":0,
    "gn:timezone":"Asia/Karachi",
    "iso:country":"PK",
    "name:und_x_variant":[
        "Ghor Darra",
        "Ghurdarra"
    ],
    "wof:name":"Ghurdarra",
    "wof:placetype":"locality"
},
  "geometry": {"coordinates":[72.54128,34.60751],"type":"Point"}
}