{
  "type": "Feature",
  "properties": {
    "gn:admin1_code":"5",
    "gn:asciiname":"Goth Khokhara",
    "gn:country_code":"PK",
    "gn:dem":14,
    "gn:feature_class":"P",
    "gn:feature_code":"PPL",
    "gn:name":"Goth Khokhara",
    "gn:population":0,
    "gn:timezone":"Asia/Karachi",
    "iso:country":"PK",
    "name:und_x_variant":[
        "Khokra"
    ],
    "wof:name":"Goth Khokhara",
    "wof:placetype":"locality"
},
  "geometry": {"coordinates":[68.67626,25.05297],"type":"Point"}
}