{
  "type": "Feature",
  "properties": {
    "gn:admin1_code":"1.0",
    "gn:asciiname":"Gher Dand",
    "gn:country_code":"PK",
    "gn:dem":901,
    "gn:feature_class":"P",
    "gn:feature_code":"PPL",
    "gn:name":"Gher Dand",
    "gn:population":0,
    "gn:timezone":"Asia/Karachi",
    "iso:country":"PK",
    "name:und_x_variant":[
        "Ghair Dand"
    ],
    "wof:name":"Gher Dand",
    "wof:placetype":"locality"
},
  "geometry": {"coordinates":[71.14872,34.46875],"type":"Point"}
}