{
  "type": "Feature",
  "properties": {
    "gn:admin1_code":"4",
    "gn:asciiname":"Chak Sixty Southern Branch",
    "gn:country_code":"PK",
    "gn:dem":185,
    "gn:feature_class":"P",
    "gn:feature_code":"PPL",
    "gn:name":"Chak Sixty Southern Branch",
    "gn:population":0,
    "gn:timezone":"Asia/Karachi",
    "iso:country":"PK",
    "name:und_x_variant":[
        "Chak Sixty SB"
    ],
    "wof:name":"Chak Sixty Southern Branch",
    "wof:placetype":"locality"
},
  "geometry": {"coordinates":[72.71585999999998,31.83758],"type":"Point"}
}