{
  "type": "Feature",
  "properties": {
    "gn:admin1_code":"4",
    "gn:asciiname":"Chak Shadman",
    "gn:country_code":"PK",
    "gn:dem":324,
    "gn:feature_class":"P",
    "gn:feature_code":"PPL",
    "gn:name":"Chak Shadman",
    "gn:population":0,
    "gn:timezone":"Asia/Karachi",
    "iso:country":"PK",
    "wof:name":"Chak Shadman",
    "wof:placetype":"locality"
},
  "geometry": {"coordinates":[73.40652,32.69237],"type":"Point"}
}