{
  "type": "Feature",
  "properties": {
    "gn:admin1_code":"7.0",
    "gn:asciiname":"Buro",
    "gn:country_code":"PK",
    "gn:dem":2699,
    "gn:feature_class":"P",
    "gn:feature_code":"PPL",
    "gn:name":"Buro",
    "gn:population":0,
    "gn:timezone":"Asia/Karachi",
    "iso:country":"PK",
    "name:ceb_x_preferred":[
        "Buro"
    ],
    "name:deu_x_preferred":[
        "Buro"
    ],
    "name:ita_x_preferred":[
        "Buro"
    ],
    "name:swe_x_preferred":[
        "Buro"
    ],
    "name:tgl_x_preferred":[
        "Buro"
    ],
    "wof:name":"Buro",
    "wof:placetype":"locality"
},
  "geometry": {"coordinates":[75.90608,35.13197],"type":"Point"}
}