{
  "type": "Feature",
  "properties": {
    "gn:admin1_code":"4.0",
    "gn:asciiname":"Dhok",
    "gn:country_code":"PK",
    "gn:dem":261,
    "gn:feature_class":"P",
    "gn:feature_code":"PPL",
    "gn:name":"Dhok",
    "gn:population":0,
    "gn:timezone":"Asia/Karachi",
    "iso:country":"PK",
    "name:und_x_variant":[
        "Kiri Dhok"
    ],
    "wof:name":"Dhok",
    "wof:placetype":"locality"
},
  "geometry": {"coordinates":[71.98411999999998,33.08846],"type":"Point"}
}