{
  "type": "Feature",
  "properties": {
    "gn:admin1_code":"2.0",
    "gn:asciiname":"Gush Tang",
    "gn:country_code":"PK",
    "gn:dem":139,
    "gn:feature_class":"P",
    "gn:feature_code":"PPL",
    "gn:name":"Gush Tang",
    "gn:population":0,
    "gn:timezone":"Asia/Karachi",
    "iso:country":"PK",
    "name:und_x_variant":[
        "Gishtang"
    ],
    "wof:name":"Gush Tang",
    "wof:placetype":"neighbourhood"
},
  "geometry": {"coordinates":[63.0308,25.9972],"type":"Point"}
}