{
  "type": "Feature",
  "properties": {
    "gn:admin1_code":"4",
    "gn:asciiname":"Sai de Basti",
    "gn:country_code":"PK",
    "gn:dem":137,
    "gn:feature_class":"P",
    "gn:feature_code":"PPL",
    "gn:name":"Sai de Basti",
    "gn:population":0,
    "gn:timezone":"Asia/Karachi",
    "iso:country":"PK",
    "name:und_x_variant":[
        "Sa\u012bdi Basti"
    ],
    "wof:name":"Sai de Basti",
    "wof:placetype":"locality"
},
  "geometry": {"coordinates":[71.92766999999998,30.7608],"type":"Point"}
}