{
  "type": "Feature",
  "properties": {
    "gn:admin1_code":"1.0",
    "gn:asciiname":"Terai",
    "gn:country_code":"PK",
    "gn:dem":1349,
    "gn:feature_class":"P",
    "gn:feature_code":"PPL",
    "gn:name":"Terai",
    "gn:population":0,
    "gn:timezone":"Asia/Karachi",
    "iso:country":"PK",
    "name:ben_x_preferred":[
        "\u09a4\u09b0\u09be\u0987"
    ],
    "name:bih_x_preferred":[
        "\u0924\u0930\u093e\u0908"
    ],
    "name:ces_x_preferred":[
        "Teraje"
    ],
    "name:deu_x_preferred":[
        "Terai"
    ],
    "name:epo_x_preferred":[
        "Terajo"
    ],
    "name:eus_x_preferred":[
        "Terai ordokia"
    ],
    "name:fra_x_preferred":[
        "Terra\u00ef"
    ],
    "name:hin_x_preferred":[
        "\u0924\u0930\u093e\u0908 \u0915\u094d\u0937\u0947\u0924\u094d\u0930"
    ],
    "name:hun_x_preferred":[
        "Terai"
    ],
    "name:ind_x_preferred":[
        "Terai"
    ],
    "name:ita_x_preferred":[
        "Terai"
    ],
    "name:kir_x_preferred":[
        "\u0422\u0435\u0440\u0430\u0438"
    ],
    "name:lit_x_preferred":[
        "Terajai"
    ],
    "name:mai_x_preferred":[
        "\u0924\u0930\u093e\u0908"
    ],
    "name:nep_x_preferred":[
        "\u0924\u0930\u093e\u0908"
    ],
    "name:nno_x_preferred":[
        "Terai"
    ],
    "name:nor_x_preferred":[
        "Tarai"
    ],
    "name:pan_x_preferred":[
        "\u0a24\u0a30\u0a3e\u0a08 \u0a16\u0a47\u0a24\u0a30"
    ],
    "name:pnb_x_preferred":[
        "\u062a\u0631\u0627\u0626\u06cc"
    ],
    "name:pol_x_preferred":[
        "Teraj"
    ],
    "name:por_x_preferred":[
        "Terai"
    ],
    "name:rus_x_preferred":[
        "\u0422\u0435\u0440\u0430\u0438"
    ],
    "name:san_x_preferred":[
        "\u0924\u0930\u093e\u0908"
    ],
    "name:slv_x_preferred":[
        "Tarai"
    ],
    "name:spa_x_preferred":[
        "Terai"
    ],
    "name:swe_x_preferred":[
        "Terai"
    ],
    "name:tam_x_preferred":[
        "\u0ba4\u0bc6\u0bb0\u0bbe\u0baf\u0bcd"
    ],
    "name:ukr_x_preferred":[
        "\u0422\u0435\u0440\u0430\u0457"
    ],
    "name:zho_x_preferred":[
        "\u5fb7\u8d56\u5e73\u539f"
    ],
    "wof:name":"Terai",
    "wof:placetype":"locality"
},
  "geometry": {"coordinates":[70.65971,33.56764],"type":"Point"}
}