{
  "type": "Feature",
  "properties": {
    "gn:admin1_code":"1.0",
    "gn:asciiname":"Terai",
    "gn:country_code":"PK",
    "gn:dem":1349,
    "gn:feature_class":"P",
    "gn:feature_code":"PPL",
    "gn:name":"Terai",
    "gn:population":0,
    "gn:timezone":"Asia/Karachi",
    "iso:country":"PK",
    "wof:name":"Terai",
    "wof:placetype":"locality"
},
  "geometry": {"coordinates":[70.65971,33.56764],"type":"Point"}
}