{
  "type": "Feature",
  "properties": {
    "gn:admin1_code":"1.0",
    "gn:asciiname":"Tura",
    "gn:country_code":"PK",
    "gn:dem":1481,
    "gn:feature_class":"P",
    "gn:feature_code":"PPL",
    "gn:name":"Tura",
    "gn:population":0,
    "gn:timezone":"Asia/Karachi",
    "iso:country":"PK",
    "name:bel_x_preferred":[
        "\u0422\u0443\u0440\u0430"
    ],
    "name:bul_x_preferred":[
        "\u0422\u0443\u0440\u0430"
    ],
    "name:cat_x_preferred":[
        "Tura"
    ],
    "name:ceb_x_preferred":[
        "Tura"
    ],
    "name:ces_x_preferred":[
        "Tura"
    ],
    "name:deu_x_preferred":[
        "Tura"
    ],
    "name:fra_x_preferred":[
        "Tura"
    ],
    "name:ita_x_preferred":[
        "Tura"
    ],
    "name:lit_x_preferred":[
        "Tura"
    ],
    "name:pol_x_preferred":[
        "Tura"
    ],
    "name:por_x_preferred":[
        "Tura"
    ],
    "name:rus_x_preferred":[
        "\u0422\u0443\u0440\u0430"
    ],
    "name:slk_x_preferred":[
        "Tura"
    ],
    "name:spa_x_preferred":[
        "Tura"
    ],
    "name:srp_x_preferred":[
        "\u0422\u0443\u0440\u0430"
    ],
    "name:swe_x_preferred":[
        "Tura"
    ],
    "name:ukr_x_preferred":[
        "\u0422\u0443\u0440\u0430"
    ],
    "name:und_x_variant":[
        "Tora"
    ],
    "name:uzb_x_preferred":[
        "Tura"
    ],
    "wof:name":"Tura",
    "wof:placetype":"locality"
},
  "geometry": {"coordinates":[71.11038000000001,34.67828],"type":"Point"}
}