{
  "type": "Feature",
  "properties": {
    "gn:admin1_code":"3",
    "gn:asciiname":"Damner",
    "gn:country_code":"PK",
    "gn:dem":653,
    "gn:feature_class":"P",
    "gn:feature_code":"PPL",
    "gn:name":"Damner",
    "gn:population":0,
    "gn:timezone":"Asia/Karachi",
    "iso:country":"PK",
    "wof:name":"Damner",
    "wof:placetype":"locality"
},
  "geometry": {"coordinates":[72.61153,34.25768],"type":"Point"}
}