{
  "type": "Feature",
  "properties": {
    "gn:admin1_code":"5",
    "gn:asciiname":"Ali Sher Jaskani",
    "gn:country_code":"PK",
    "gn:dem":72,
    "gn:feature_class":"P",
    "gn:feature_code":"PPL",
    "gn:name":"Ali Sher Jaskani",
    "gn:population":0,
    "gn:timezone":"Asia/Karachi",
    "iso:country":"PK",
    "name:und_x_variant":[
        "Ali Sher Jask\u0101n",
        "Ali Sher Jaskani"
    ],
    "wof:name":"Ali Sher Jaskani",
    "wof:placetype":"locality"
},
  "geometry": {"coordinates":[69.3408,28.04042],"type":"Point"}
}