{
  "type": "Feature",
  "properties": {
    "gn:admin1_code":"4.0",
    "gn:asciiname":"Bagihari",
    "gn:country_code":"PK",
    "gn:dem":199,
    "gn:feature_class":"P",
    "gn:feature_code":"PPL",
    "gn:name":"Bagihari",
    "gn:population":0,
    "gn:timezone":"Asia/Karachi",
    "iso:country":"PK",
    "name:und_x_variant":[
        "Bagih\u0101ra",
        "Baghiari",
        "Bagihari",
        "Mustafa\u0101bad"
    ],
    "wof:name":"Bagihari",
    "wof:placetype":"locality"
},
  "geometry": {"coordinates":[73.81989,31.52117],"type":"Point"}
}