{
  "type": "Feature",
  "properties": {
    "gn:admin1_code":"4",
    "gn:asciiname":"Langar Mochianwala",
    "gn:country_code":"PK",
    "gn:dem":173,
    "gn:feature_class":"P",
    "gn:feature_code":"PPL",
    "gn:name":"Langar Mochianwala",
    "gn:population":0,
    "gn:timezone":"Asia/Karachi",
    "iso:country":"PK",
    "name:und_x_variant":[
        "Langar M\u0101hu\u012bw\u0101la"
    ],
    "wof:name":"Langar Mochianwala",
    "wof:placetype":"locality"
},
  "geometry": {"coordinates":[71.15698,31.71278],"type":"Point"}
}