{
  "type": "Feature",
  "properties": {
    "gn:admin1_code":"4",
    "gn:asciiname":"Chak One Hundred Fourteen Dara Nawab Branch",
    "gn:country_code":"PK",
    "gn:dem":114,
    "gn:feature_class":"P",
    "gn:feature_code":"PPL",
    "gn:name":"Chak One Hundred Fourteen Dara Nawab Branch",
    "gn:population":0,
    "gn:timezone":"Asia/Karachi",
    "iso:country":"PK",
    "name:und_x_variant":[
        "Chak 114 D N B"
    ],
    "wof:name":"Chak One Hundred Fourteen Dara Nawab Branch",
    "wof:placetype":"locality"
},
  "geometry": {"coordinates":[71.48581999999998,29.07666],"type":"Point"}
}