{
  "type": "Feature",
  "properties": {
    "gn:admin1_code":"4",
    "gn:asciiname":"Sohawa Daloana",
    "gn:country_code":"PK",
    "gn:dem":217,
    "gn:feature_class":"P",
    "gn:feature_code":"PPL",
    "gn:name":"Sohawa Daloana",
    "gn:population":0,
    "gn:timezone":"Asia/Karachi",
    "iso:country":"PK",
    "name:und_x_variant":[
        "Sah\u0101wa D\u012blw\u0101na"
    ],
    "wof:name":"Sohawa Daloana",
    "wof:placetype":"locality"
},
  "geometry": {"coordinates":[73.46229,32.54478],"type":"Point"}
}