{
  "type": "Feature",
  "properties": {
    "gn:admin1_code":"2.0",
    "gn:asciiname":"Haji Nawab Qila",
    "gn:country_code":"PK",
    "gn:dem":1658,
    "gn:feature_class":"P",
    "gn:feature_code":"PPL",
    "gn:name":"Haji Nawab Qila",
    "gn:population":0,
    "gn:timezone":"Asia/Karachi",
    "iso:country":"PK",
    "wof:name":"Haji Nawab Qila",
    "wof:placetype":"locality"
},
  "geometry": {"coordinates":[69.80157,31.48769],"type":"Point"}
}