{
  "type": "Feature",
  "properties": {
    "gn:admin1_code":"05",
    "gn:asciiname":"Goth Nodo",
    "gn:country_code":"PK",
    "gn:dem":313,
    "gn:feature_class":"P",
    "gn:feature_code":"PPL",
    "gn:name":"Goth Nodo",
    "gn:population":0,
    "gn:timezone":"Asia/Karachi",
    "iso:country":"PK",
    "name:und_x_variant":[
        "Goth Nando",
        "Goth Nado",
        "Goth Nodo"
    ],
    "wof:name":"Goth Nodo",
    "wof:placetype":"locality"
},
  "geometry": {"coordinates":[67.30719000000001,25.28614],"type":"Point"}
}