{
  "type": "Feature",
  "properties": {
    "gn:admin1_code":"03",
    "gn:asciiname":"Kandro Shah",
    "gn:country_code":"PK",
    "gn:dem":1207,
    "gn:feature_class":"P",
    "gn:feature_code":"PPL",
    "gn:name":"Kandro Shah",
    "gn:population":0,
    "gn:timezone":"Asia/Karachi",
    "iso:country":"PK",
    "wof:name":"Kandro Shah",
    "wof:placetype":"locality"
},
  "geometry": {"coordinates":[71.99724000000001,34.77659],"type":"Point"}
}