{
  "type": "Feature",
  "properties": {
    "gn:admin1_code":"3.0",
    "gn:asciiname":"Ilanai",
    "gn:country_code":"PK",
    "gn:dem":2148,
    "gn:feature_class":"P",
    "gn:feature_code":"PPL",
    "gn:name":"Ilanai",
    "gn:population":0,
    "gn:timezone":"Asia/Karachi",
    "iso:country":"PK",
    "wof:name":"Ilanai",
    "wof:placetype":"locality"
},
  "geometry": {"coordinates":[71.94993000000002,35.27199],"type":"Point"}
}