{
  "type": "Feature",
  "properties": {
    "gn:admin1_code":"4.0",
    "gn:asciiname":"Chak Seven Hundred Fifty-three Gugera Branch",
    "gn:country_code":"PK",
    "gn:dem":143,
    "gn:feature_class":"P",
    "gn:feature_code":"PPL",
    "gn:name":"Chak Seven Hundred Fifty-three Gugera Branch",
    "gn:population":0,
    "gn:timezone":"Asia/Karachi",
    "iso:country":"PK",
    "wof:name":"Chak Seven Hundred Fifty-three Gugera Branch",
    "wof:placetype":"locality"
},
  "geometry": {"coordinates":[72.30379000000001,30.67694],"type":"Point"}
}