{
  "type": "Feature",
  "properties": {
    "gn:admin1_code":"4.0",
    "gn:asciiname":"Gulshan Iqbal",
    "gn:country_code":"PK",
    "gn:dem":252,
    "gn:feature_class":"P",
    "gn:feature_code":"PPL",
    "gn:name":"Gulshan Iqbal",
    "gn:population":0,
    "gn:timezone":"Asia/Karachi",
    "iso:country":"PK",
    "wof:name":"Gulshan Iqbal",
    "wof:placetype":"locality"
},
  "geometry": {"coordinates":[74.55934999999999,32.4789],"type":"Point"}
}