{
  "type": "Feature",
  "properties": {
    "gn:admin1_code":"3",
    "gn:asciiname":"Molai",
    "gn:country_code":"PK",
    "gn:dem":1637,
    "gn:feature_class":"P",
    "gn:feature_code":"PPL",
    "gn:name":"Molai",
    "gn:population":0,
    "gn:timezone":"Asia/Karachi",
    "iso:country":"PK",
    "name:eng_x_preferred":[
        "Malui"
    ],
    "wof:name":"Molai",
    "wof:placetype":"locality"
},
  "geometry": {"coordinates":[71.94726999999997,35.01531],"type":"Point"}
}