{
  "type": "Feature",
  "properties": {
    "gn:admin1_code":"2.0",
    "gn:asciiname":"Band Ka Shahr",
    "gn:country_code":"PK",
    "gn:dem":51,
    "gn:feature_class":"P",
    "gn:feature_code":"PPL",
    "gn:name":"Band Ka Shahr",
    "gn:population":0,
    "gn:timezone":"Asia/Karachi",
    "iso:country":"PK",
    "name:und_x_variant":[
        "Mahm\u016bd Burra",
        "Mahm\u016bd Burro"
    ],
    "wof:name":"Band Ka Shahr",
    "wof:placetype":"locality"
},
  "geometry": {"coordinates":[67.61541,28.04029],"type":"Point"}
}