{
  "type": "Feature",
  "properties": {
    "gn:admin1_code":"02",
    "gn:asciiname":"Phuleji",
    "gn:country_code":"PK",
    "gn:dem":141,
    "gn:elevation":"130.0",
    "gn:feature_class":"P",
    "gn:feature_code":"PPL",
    "gn:name":"Phuleji",
    "gn:population":0,
    "gn:timezone":"Asia/Karachi",
    "iso:country":"PK",
    "name:und_x_variant":[
        "Foliji",
        "Phuleji"
    ],
    "wof:name":"Phuleji",
    "wof:placetype":"locality"
},
  "geometry": {"coordinates":[68.34769,28.9986],"type":"Point"}
}