{
  "type": "Feature",
  "properties": {
    "gn:admin1_code":"03",
    "gn:asciiname":"Tabbi Murad",
    "gn:country_code":"PK",
    "gn:dem":334,
    "gn:feature_class":"P",
    "gn:feature_code":"PPL",
    "gn:name":"Tabbi Murad",
    "gn:population":0,
    "gn:timezone":"Asia/Karachi",
    "iso:country":"PK",
    "name:und_x_variant":[
        "Tabi Murad",
        "Tabbi Murad"
    ],
    "wof:name":"Tabbi Murad",
    "wof:placetype":"locality"
},
  "geometry": {"coordinates":[70.72615,32.45665],"type":"Point"}
}