{
  "type": "Feature",
  "properties": {
    "gn:admin1_code":"4.0",
    "gn:asciiname":"Khamb",
    "gn:country_code":"PK",
    "gn:dem":239,
    "gn:feature_class":"P",
    "gn:feature_code":"PPL",
    "gn:name":"Khamb",
    "gn:population":0,
    "gn:timezone":"Asia/Karachi",
    "iso:country":"PK",
    "name:und_x_variant":[
        "Khainbi",
        "Khambi",
        "Khamb"
    ],
    "wof:name":"Khamb",
    "wof:placetype":"locality"
},
  "geometry": {"coordinates":[73.72291,32.88223],"type":"Point"}
}