{
  "type": "Feature",
  "properties": {
    "gn:admin1_code":"3.0",
    "gn:asciiname":"Sainzo Shah",
    "gn:country_code":"PK",
    "gn:dem":419,
    "gn:feature_class":"P",
    "gn:feature_code":"PPL",
    "gn:name":"Sainzo Shah",
    "gn:population":0,
    "gn:timezone":"Asia/Karachi",
    "iso:country":"PK",
    "name:eng_x_preferred":[
        "Sid-e-zo-Sh\u0101h"
    ],
    "wof:name":"Sainzo Shah",
    "wof:placetype":"locality"
},
  "geometry": {"coordinates":[71.77226,34.4021],"type":"Point"}
}