{
  "type": "Feature",
  "properties": {
    "gn:admin1_code":"01",
    "gn:asciiname":"Ayar",
    "gn:country_code":"PK",
    "gn:dem":2034,
    "gn:feature_class":"P",
    "gn:feature_code":"PPL",
    "gn:name":"Ayar",
    "gn:population":0,
    "gn:timezone":"Asia/Karachi",
    "iso:country":"PK",
    "wof:name":"Ayar",
    "wof:placetype":"locality"
},
  "geometry": {"coordinates":[70.64764,33.73464],"type":"Point"}
}