{
  "type": "Feature",
  "properties": {
    "gn:admin1_code":"1.0",
    "gn:asciiname":"Zukhane",
    "gn:country_code":"PK",
    "gn:dem":1760,
    "gn:feature_class":"P",
    "gn:feature_code":"PPL",
    "gn:name":"Zukhane",
    "gn:population":0,
    "gn:timezone":"Asia/Karachi",
    "iso:country":"PK",
    "name:und_x_variant":[
        "Zukhani"
    ],
    "wof:name":"Zukhane",
    "wof:placetype":"locality"
},
  "geometry": {"coordinates":[70.90295999999999,33.72555],"type":"Point"}
}