{
  "type": "Feature",
  "properties": {
    "gn:admin1_code":"1.0",
    "gn:asciiname":"Chardiwar",
    "gn:country_code":"PK",
    "gn:dem":973,
    "gn:feature_class":"P",
    "gn:feature_code":"PPL",
    "gn:name":"Chardiwar",
    "gn:population":0,
    "gn:timezone":"Asia/Karachi",
    "iso:country":"PK",
    "name:und_x_variant":[
        "Chardewar",
        "Chardiwar"
    ],
    "wof:name":"Chardiwar",
    "wof:placetype":"locality"
},
  "geometry": {"coordinates":[70.35146,33.50995],"type":"Point"}
}