{
  "type": "Feature",
  "properties": {
    "gn:admin1_code":"2.0",
    "gn:asciiname":"Katawal",
    "gn:country_code":"PK",
    "gn:dem":32,
    "gn:feature_class":"P",
    "gn:feature_code":"PPL",
    "gn:name":"Katawal",
    "gn:population":0,
    "gn:timezone":"Asia/Karachi",
    "iso:country":"PK",
    "name:und_x_variant":[
        "Kataw\u0101l"
    ],
    "wof:name":"Katawal",
    "wof:placetype":"locality"
},
  "geometry": {"coordinates":[63.0419,25.47413],"type":"Point"}
}