{
  "type": "Feature",
  "properties": {
    "gn:admin1_code":"4.0",
    "gn:asciiname":"Qadarpur",
    "gn:country_code":"PK",
    "gn:dem":193,
    "gn:feature_class":"P",
    "gn:feature_code":"PPL",
    "gn:name":"Qadarpur",
    "gn:population":0,
    "gn:timezone":"Asia/Karachi",
    "iso:country":"PK",
    "name:und_x_variant":[
        "Q\u0101dirpur"
    ],
    "wof:name":"Qadarpur",
    "wof:placetype":"locality"
},
  "geometry": {"coordinates":[72.74042,32.19661],"type":"Point"}
}