{
  "type": "Feature",
  "properties": {
    "gn:admin1_code":"4",
    "gn:asciiname":"Sath Shahani",
    "gn:country_code":"PK",
    "gn:dem":170,
    "gn:feature_class":"P",
    "gn:feature_code":"PPL",
    "gn:name":"Sath Shahani",
    "gn:population":0,
    "gn:timezone":"Asia/Karachi",
    "iso:country":"PK",
    "name:und_x_variant":[
        "Satah Shah\u0101ni"
    ],
    "wof:name":"Sath Shahani",
    "wof:placetype":"locality"
},
  "geometry": {"coordinates":[72.21024,31.817],"type":"Point"}
}