{
  "type": "Feature",
  "properties": {
    "gn:admin1_code":"2.0",
    "gn:asciiname":"Ali Khan Lashari",
    "gn:country_code":"PK",
    "gn:dem":60,
    "gn:feature_class":"P",
    "gn:feature_code":"PPL",
    "gn:name":"Ali Khan Lashari",
    "gn:population":0,
    "gn:timezone":"Asia/Karachi",
    "iso:country":"PK",
    "wof:name":"Ali Khan Lashari",
    "wof:placetype":"locality"
},
  "geometry": {"coordinates":[68.13915,28.35506],"type":"Point"}
}