{
  "type": "Feature",
  "properties": {
    "gn:admin1_code":"7.0",
    "gn:asciiname":"Ghatum",
    "gn:country_code":"PK",
    "gn:dem":2572,
    "gn:feature_class":"P",
    "gn:feature_code":"PPL",
    "gn:name":"Ghatum",
    "gn:population":0,
    "gn:timezone":"Asia/Karachi",
    "iso:country":"PK",
    "wof:name":"Ghatum",
    "wof:placetype":"locality"
},
  "geometry": {"coordinates":[74.02051,36.06619],"type":"Point"}
}