{
  "type": "Feature",
  "properties": {
    "gn:admin1_code":"2",
    "gn:asciiname":"Kirku Kili",
    "gn:country_code":"PK",
    "gn:dem":1239,
    "gn:feature_class":"P",
    "gn:feature_code":"PPL",
    "gn:name":"Kirku Kili",
    "gn:population":0,
    "gn:timezone":"Asia/Karachi",
    "iso:country":"PK",
    "name:und_x_variant":[
        "Karku"
    ],
    "wof:name":"Kirku Kili",
    "wof:placetype":"locality"
},
  "geometry": {"coordinates":[66.13405,27.71974],"type":"Point"}
}