{
  "type": "Feature",
  "properties": {
    "gn:admin1_code":"3",
    "gn:asciiname":"Ghulam Hussain Kour",
    "gn:country_code":"PK",
    "gn:dem":219,
    "gn:feature_class":"P",
    "gn:feature_code":"PPL",
    "gn:name":"Ghulam Hussain Kour",
    "gn:population":0,
    "gn:timezone":"Asia/Karachi",
    "iso:country":"PK",
    "name:und_x_variant":[
        "Ghul\u0101m Muhammad"
    ],
    "wof:name":"Ghulam Hussain Kour",
    "wof:placetype":"locality"
},
  "geometry": {"coordinates":[70.92364999999999,32.14599],"type":"Point"}
}