{
  "type": "Feature",
  "properties": {
    "gn:admin1_code":"4.0",
    "gn:asciiname":"Dina Nath",
    "gn:country_code":"PK",
    "gn:dem":203,
    "gn:feature_class":"P",
    "gn:feature_code":"PPL",
    "gn:name":"Dina Nath",
    "gn:population":0,
    "gn:timezone":"Asia/Karachi",
    "iso:country":"PK",
    "name:und_x_variant":[
        "D\u012bna N\u0101thw\u0101la"
    ],
    "wof:name":"Dina Nath",
    "wof:placetype":"locality"
},
  "geometry": {"coordinates":[74.00627,31.24569],"type":"Point"}
}