{
  "type": "Feature",
  "properties": {
    "gn:admin1_code":"04",
    "gn:asciiname":"Rashida",
    "gn:country_code":"PK",
    "gn:dem":178,
    "gn:feature_class":"P",
    "gn:feature_code":"PPL",
    "gn:name":"Rashida",
    "gn:population":0,
    "gn:timezone":"Asia/Karachi",
    "iso:country":"PK",
    "wof:name":"Rashida",
    "wof:placetype":"locality"
},
  "geometry": {"coordinates":[72.8931,31.66984],"type":"Point"}
}