{
  "type": "Feature",
  "properties": {
    "gn:admin1_code":"2.0",
    "gn:asciiname":"Shamsabad Karez",
    "gn:country_code":"PK",
    "gn:dem":1689,
    "gn:feature_class":"P",
    "gn:feature_code":"PPL",
    "gn:name":"Shamsabad Karez",
    "gn:population":0,
    "gn:timezone":"Asia/Karachi",
    "iso:country":"PK",
    "wof:name":"Shamsabad Karez",
    "wof:placetype":"locality"
},
  "geometry": {"coordinates":[66.86521,29.81517],"type":"Point"}
}