{
  "type": "Feature",
  "properties": {
    "gn:admin1_code":"2.0",
    "gn:asciiname":"Marsia",
    "gn:country_code":"PK",
    "gn:dem":2444,
    "gn:feature_class":"P",
    "gn:feature_code":"PPL",
    "gn:name":"Marsia",
    "gn:population":0,
    "gn:timezone":"Asia/Karachi",
    "iso:country":"PK",
    "wof:name":"Marsia",
    "wof:placetype":"locality"
},
  "geometry": {"coordinates":[67.59562,31.00405],"type":"Point"}
}