{
  "type": "Feature",
  "properties": {
    "gn:admin1_code":"5.0",
    "gn:asciiname":"Aban jo Tar",
    "gn:country_code":"PK",
    "gn:dem":81,
    "gn:feature_class":"P",
    "gn:feature_code":"PPL",
    "gn:name":"Aban jo Tar",
    "gn:population":0,
    "gn:timezone":"Asia/Karachi",
    "iso:country":"PK",
    "name:und_x_variant":[
        "Abban jo Tar"
    ],
    "wof:name":"Aban jo Tar",
    "wof:placetype":"locality"
},
  "geometry": {"coordinates":[70.36596999999999,24.79262],"type":"Point"}
}