{
  "type": "Feature",
  "properties": {
    "gn:admin1_code":"3",
    "gn:asciiname":"Naryat",
    "gn:country_code":"PK",
    "gn:dem":1125,
    "gn:feature_class":"P",
    "gn:feature_code":"PPL",
    "gn:name":"Naryat",
    "gn:population":0,
    "gn:timezone":"Asia/Karachi",
    "iso:country":"PK",
    "name:und_x_variant":[
        "Nariat"
    ],
    "wof:name":"Naryat",
    "wof:placetype":"locality"
},
  "geometry": {"coordinates":[73.43508,34.27421],"type":"Point"}
}