{
  "type": "Feature",
  "properties": {
    "gn:admin1_code":"5",
    "gn:asciiname":"Goth Nehal Khan Balkani",
    "gn:country_code":"PK",
    "gn:dem":69,
    "gn:feature_class":"P",
    "gn:feature_code":"PPL",
    "gn:name":"Goth Nehal Khan Balkani",
    "gn:population":0,
    "gn:timezone":"Asia/Karachi",
    "iso:country":"PK",
    "name:und_x_variant":[
        "Nehal Kh\u0101n Bhulk\u0101ni"
    ],
    "wof:name":"Goth Nehal Khan Balkani",
    "wof:placetype":"locality"
},
  "geometry": {"coordinates":[69.07937,28.17487],"type":"Point"}
}