{
  "type": "Feature",
  "properties": {
    "gn:admin1_code":"4.0",
    "gn:asciiname":"Mari",
    "gn:country_code":"PK",
    "gn:dem":315,
    "gn:feature_class":"P",
    "gn:feature_code":"PPL",
    "gn:name":"Mari",
    "gn:population":0,
    "gn:timezone":"Asia/Karachi",
    "iso:country":"PK",
    "wof:name":"Mari",
    "wof:placetype":"locality"
},
  "geometry": {"coordinates":[72.45251999999998,33.11325],"type":"Point"}
}