{
  "type": "Feature",
  "properties": {
    "gn:admin1_code":"6",
    "gn:asciiname":"Junganwali Baihk",
    "gn:country_code":"PK",
    "gn:dem":3066,
    "gn:feature_class":"P",
    "gn:feature_code":"PPL",
    "gn:name":"Junganwali Baihk",
    "gn:population":0,
    "gn:timezone":"Asia/Kolkata",
    "iso:country":"PK",
    "name:und_x_variant":[
        "Tung\u0101nw\u0101li Baihk"
    ],
    "wof:name":"Junganwali Baihk",
    "wof:placetype":"locality"
},
  "geometry": {"coordinates":[73.98878000000001,34.27192],"type":"Point"}
}