{
  "type": "Feature",
  "properties": {
    "gn:admin1_code":"2.0",
    "gn:asciiname":"Ibrahimzai",
    "gn:country_code":"PK",
    "gn:dem":1483,
    "gn:feature_class":"P",
    "gn:feature_code":"PPL",
    "gn:name":"Ibrahimzai",
    "gn:population":0,
    "gn:timezone":"Asia/Karachi",
    "iso:country":"PK",
    "name:und_x_variant":[
        "Ibrah\u012bmazi",
        "Ibrahimzai"
    ],
    "wof:name":"Ibrahimzai",
    "wof:placetype":"locality"
},
  "geometry": {"coordinates":[66.67709000000001,30.66398],"type":"Point"}
}