{
  "type": "Feature",
  "properties": {
    "gn:admin1_code":"1.0",
    "gn:asciiname":"Ghulam Jan Kalle",
    "gn:country_code":"PK",
    "gn:dem":1762,
    "gn:feature_class":"P",
    "gn:feature_code":"PPL",
    "gn:name":"Ghulam Jan Kalle",
    "gn:population":0,
    "gn:timezone":"Asia/Karachi",
    "iso:country":"PK",
    "wof:name":"Ghulam Jan Kalle",
    "wof:placetype":"locality"
},
  "geometry": {"coordinates":[70.11521999999999,33.90319],"type":"Point"}
}