{
  "type": "Feature",
  "properties": {
    "gn:admin1_code":"6.0",
    "gn:asciiname":"Chaumukh",
    "gn:country_code":"PK",
    "gn:dem":451,
    "gn:feature_class":"P",
    "gn:feature_code":"PPL",
    "gn:name":"Chaumukh",
    "gn:population":0,
    "gn:timezone":"Asia/Karachi",
    "iso:country":"PK",
    "wof:name":"Chaumukh",
    "wof:placetype":"locality"
},
  "geometry": {"coordinates":[73.52445999999998,33.34256],"type":"Point"}
}