{
  "type": "Feature",
  "properties": {
    "gn:admin1_code":"01",
    "gn:asciiname":"Kuz Targhao",
    "gn:country_code":"PK",
    "gn:dem":930,
    "gn:feature_class":"P",
    "gn:feature_code":"PPL",
    "gn:name":"Kuz Targhao",
    "gn:population":0,
    "gn:timezone":"Asia/Karachi",
    "iso:country":"PK",
    "name:eng_x_preferred":[
        "Targh\u0101o"
    ],
    "name:und_x_variant":[
        "Kuz Targhow"
    ],
    "wof:name":"Kuz Targhao",
    "wof:placetype":"locality"
},
  "geometry": {"coordinates":[71.65991,34.66004],"type":"Point"}
}