{
  "type": "Feature",
  "properties": {
    "gn:admin1_code":"3",
    "gn:asciiname":"Mando",
    "gn:country_code":"PK",
    "gn:dem":835,
    "gn:feature_class":"P",
    "gn:feature_code":"PPL",
    "gn:name":"Mando",
    "gn:population":0,
    "gn:timezone":"Asia/Karachi",
    "iso:country":"PK",
    "name:ceb_x_preferred":[
        "Mando"
    ],
    "name:deu_x_preferred":[
        "Mando"
    ],
    "name:fas_x_preferred":[
        "\u0645\u0627\u0646\u062f\u0648"
    ],
    "name:nld_x_preferred":[
        "Mando"
    ],
    "name:pol_x_preferred":[
        "Mando"
    ],
    "name:por_x_preferred":[
        "Mando"
    ],
    "name:spa_x_preferred":[
        "Mando"
    ],
    "name:swe_x_preferred":[
        "Mando"
    ],
    "wof:name":"Mando",
    "wof:placetype":"locality"
},
  "geometry": {"coordinates":[73.07470000000001,34.33835999999999],"type":"Point"}
}