{
  "type": "Feature",
  "properties": {
    "gn:admin1_code":"3.0",
    "gn:asciiname":"Bans",
    "gn:country_code":"PK",
    "gn:dem":2845,
    "gn:feature_class":"P",
    "gn:feature_code":"PPL",
    "gn:name":"Bans",
    "gn:population":0,
    "gn:timezone":"Asia/Karachi",
    "iso:country":"PK",
    "wof:name":"Bans",
    "wof:placetype":"locality"
},
  "geometry": {"coordinates":[73.82796999999999,34.93197],"type":"Point"}
}