{
  "type": "Feature",
  "properties": {
    "gn:admin1_code":"3.0",
    "gn:asciiname":"Shewa Banda",
    "gn:country_code":"PK",
    "gn:dem":349,
    "gn:feature_class":"P",
    "gn:feature_code":"PPL",
    "gn:name":"Shewa Banda",
    "gn:population":0,
    "gn:timezone":"Asia/Karachi",
    "iso:country":"PK",
    "wof:name":"Shewa Banda",
    "wof:placetype":"locality"
},
  "geometry": {"coordinates":[72.20616,34.29518],"type":"Point"}
}