{
  "type": "Feature",
  "properties": {
    "gn:admin1_code":"04",
    "gn:asciiname":"Rautla",
    "gn:cc2":"PK",
    "gn:country_code":"PK",
    "gn:dem":146,
    "gn:feature_class":"P",
    "gn:feature_code":"PPL",
    "gn:name":"Rautla",
    "gn:population":0,
    "gn:timezone":"Asia/Karachi",
    "iso:country":"PK",
    "name:und_x_variant":[
        "Rotla",
        "Rautla"
    ],
    "wof:name":"Rautla",
    "wof:placetype":"locality"
},
  "geometry": {"coordinates":[72.26666999999998,30.55],"type":"Point"}
}