{
  "type": "Feature",
  "properties": {
    "gn:admin1_code":"4.0",
    "gn:asciiname":"Basti Bahar",
    "gn:country_code":"PK",
    "gn:dem":739,
    "gn:feature_class":"P",
    "gn:feature_code":"PPL",
    "gn:name":"Basti Bahar",
    "gn:population":0,
    "gn:timezone":"Asia/Karachi",
    "iso:country":"PK",
    "wof:name":"Basti Bahar",
    "wof:placetype":"locality"
},
  "geometry": {"coordinates":[70.24576999999999,30.36939000000001],"type":"Point"}
}