{
  "type": "Feature",
  "properties": {
    "gn:admin1_code":"5.0",
    "gn:asciiname":"Plant Steel Town",
    "gn:country_code":"PK",
    "gn:dem":53,
    "gn:feature_class":"P",
    "gn:feature_code":"PPL",
    "gn:name":"Plant Steel Town",
    "gn:population":0,
    "gn:timezone":"Asia/Karachi",
    "iso:country":"PK",
    "wof:name":"Plant Steel Town",
    "wof:placetype":"locality"
},
  "geometry": {"coordinates":[67.36265999999999,24.8625],"type":"Point"}
}