{
  "type": "Feature",
  "properties": {
    "gn:admin1_code":"4",
    "gn:asciiname":"Kalianpur",
    "gn:country_code":"PK",
    "gn:dem":207,
    "gn:feature_class":"P",
    "gn:feature_code":"PPL",
    "gn:name":"Kalianpur",
    "gn:population":0,
    "gn:timezone":"Asia/Karachi",
    "iso:country":"PK",
    "name:und_x_variant":[
        "Kaly\u0101npur"
    ],
    "wof:name":"Kalianpur",
    "wof:placetype":"locality"
},
  "geometry": {"coordinates":[73.11094,32.53217],"type":"Point"}
}