{
  "type": "Feature",
  "properties": {
    "gn:admin1_code":"7.0",
    "gn:asciiname":"Shingai",
    "gn:country_code":"PK",
    "gn:dem":2647,
    "gn:feature_class":"P",
    "gn:feature_code":"PPL",
    "gn:name":"Shingai",
    "gn:population":0,
    "gn:timezone":"Asia/Karachi",
    "iso:country":"PK",
    "wof:name":"Shingai",
    "wof:placetype":"locality"
},
  "geometry": {"coordinates":[74.80461,35.13633],"type":"Point"}
}