{
  "type": "Feature",
  "properties": {
    "gn:admin1_code":"1.0",
    "gn:asciiname":"Nasapai",
    "gn:country_code":"PK",
    "gn:dem":796,
    "gn:feature_class":"P",
    "gn:feature_code":"PPL",
    "gn:name":"Nasapai",
    "gn:population":0,
    "gn:timezone":"Asia/Karachi",
    "iso:country":"PK",
    "wof:name":"Nasapai",
    "wof:placetype":"locality"
},
  "geometry": {"coordinates":[71.4735,34.39277],"type":"Point"}
}